Workbook
Name Icms: 'Anexo 1'!$L$33:$L$35

Sheet Comércio
C1: COMPARAÇÃO LUCRO REAL X LUCRO PRESUMIDO X SIMPLES NACIONAL NO COMÉRCIO
B3: Para simulação: Digite nas células em amarelo | F3: Atacadista > | J3: Ajuda >
C5: LUCRO REAL | F5: LUCRO PRESUMIDO | I5: SIMPLES NACIONAL
C7: Receita Bruta (Mensal) | D7: 500000 | F7: Receita Bruta (Mensal) | G7: =D7 -> R$ 500,000.00 | I7: Receita Bruta Mensal (limite de 200 mil + 20%) | J7: =G7 -> R$ 500,000.00
C8: 0.18 | D8: =(D7*C8) -> R$ 90,000.00 | F8: =C8 -> ICMS sobre Vendas 18% | G8: =D8 -> R$ 90,000.00 | I8: Em 12 meses (anual) | J8: =G7*12 -> R$ 6,000,000.00
C9: 0.07 | D9: =(D13*C9) -> R$ 17,500.00 | F9: =C9 -> ICMS: Crédito sobre Compras 7% | G9: =D9 -> R$ 17,500.00
C10: 0.0065 | D10: =D7*C10 -> R$ 3,250.00 | F10: 0.0065 | G10: =G7*F10 -> R$ 3,250.00 | I10: ICMS - Simples | J10: =IF(I10="Substituição Tributária",G8-G9,0) -> R$ 0.00
C11: 0.03 | D11: =D7*C11 -> R$ 15,000.00 | F11: 0.03 | G11: =G7*F11 -> R$ 15,000.00
B12: = | C12: Receita Líquida | D12: =D7-D8+D9-D10-D11 -> R$ 409,250.00 | F12: Receita Líquida | G12: =G7-G8+G9-G10-G11 -> R$ 409,250.00
B13: - | C13: 0.5 | D13: =D7*C13 -> R$ 250,000.00 | F13: =C13 -> Custo da Mercadoria Vendida = 50.0% | G13: =G7*F13 -> R$ 250,000.00 | I13: =C13 -> Custo da Mercadoria Vendida = 50.0% | J13: =J7*I13 -> R$ 250,000.00
B14: = | C14: Margem Bruta | D14: =D12-D13 -> R$ 159,250.00 | F14: =C14 -> Margem Bruta | G14: =G12-G13 -> R$ 159,250.00
B15: - | C15: 0.1 | D15: =D7*C15 -> R$ 50,000.00 | F15: =C15 -> Folha pagamento s/ Receita Bruta = 10.0% | G15: =G7*F15 -> R$ 50,000.00 | I15: =C15 -> Folha pagamento s/ Receita Bruta = 10.0% | J15: =J7*I15 -> R$ 50,000.00
B16: - | C16: 0.275 | D16: =D15*C16 -> R$ 13,750.00 | F16: =C16 -> Encargos sociais sobre folha = 27.5% | G16: =D16 -> R$ 13,750.00
B17: - | C17: 0.02 | D17: =D7*C17 -> R$ 10,000.00 | F17: =C17 -> Despesas diversas s/ Receita Bruta = 2.0% | G17: =D17 -> R$ 10,000.00 | I17: =C17 -> Despesas diversas s/ Receita Bruta = 2.0% | J17: =J7*I17 -> R$ 10,000.00
B18: = | C18: Lucro Líquido | D18: =D14-D15-D16-D17 -> R$ 85,500.00 | F18: Lucro Líquido | G18: =D18 -> R$ 85,500.00
C19: 0.09 | D19: =D18*C19 -> R$ 7,695.00 | F19: Base de cálculo do Lucro Presumido CSLL
C20: LALUR | F20: 0.12 | G20: =G7*F20 -> R$ 60,000.00
C21: 0.15 | D21: =D18*C21 -> R$ 12,825.00 | F21: 0.09 | G21: =G20*F21 -> R$ 5,400.00
F22: Base de cálculo do Lucro Presumido IR | I22: Encargos Fiscais (anexo I do Simples)
D23: =D18-D19-D21 -> R$ 64,980.00 | F23: 0.08 | G23: =G7*F23 -> R$ 40,000.00 | I23: =VLOOKUP(I10,'Anexo 1'!L33:M34,2) -> Alíquota de 11.61% | J23: =J7*I23 -> R$ 58,050.00
C24: 0.1 | D24: =IF(D23>20000,(D23-20000)*C24,0) -> R$ 4,498.00 | F24: =C21 -> Alíquota do IR de 15% | G24: =G23*F24 -> R$ 6,000.00
F25: 0.1 | G25: =IF(G23>20000,(G23-20000)*F25,0) -> R$ 2,000.00
C26: Lucro Real | D26: =D23-D24 -> R$ 60,482.00 | F26: Lucro Presumido | G26: =G18-G21-G24-G25 -> R$ 72,100.00 | I26: Lucro: Simples | J26: =J7-J10-J13-J15-J17-J23 -> R$ 131,950.00
C29: =D8-D9+D10+D11+D16+D19+D21+D24 -> Carga Tributária: Lucro Real R$ 129,518.00 | F29: =C30 -> Carga Tributária: Lucro Presumido R$ 135,400.00 | I29: =F31 -> Carga Tributária: Simples R$ 58,050.00
C30: =G8+G10+G11+G16+G21+G24+G25 -> Carga Tributária: Lucro Presumido R$ 135,400.00 | F30: =C29 -> Carga Tributária: Lucro Real R$ 129,518.00 | I30: =C29 -> Carga Tributária: Lucro Real R$ 129,518.00
C31: =J10+J23 -> Carga Tributária: Simples R$ 58,050.00 | F31: =C31 -> Carga Tributária: Simples R$ 58,050.00 | I31: =C30 -> Carga Tributária: Lucro Presumido R$ 135,400.00
C33: =G26 -> Lucro: no Lucro Presumido R$ 72,100.00 | F33: =D26 -> Lucro: no Lucro Real R$ 60,482.00 | I33: =C33 -> Lucro: no Lucro Presumido R$ 72,100.00
C34: =J26 -> Lucro: no Simples R$ 131,950.00 | F34: =C34 -> Lucro: no Simples R$ 131,950.00 | I34: =F33 -> Lucro: no Lucro Real R$ 60,482.00

Sheet Anexo 1
A1: Anexo I - Partilha do Simples Nacional – Comércio
A3: Receita Anual | C3: Total | D3: IRPJ | E3: CSLL | F3: COFINS | G3: PIS/PASEP | H3: CPP | I3: ICMS | K3: TOTAL (*)
A4: 0 | B4: =120000 -> R$ 120,000.00 | C4: 0.04 | D4: 0.00% | E4: 0.00% | F4: 0.00% | G4: 0.00% | H4: 2.75% | I4: 1.25% | K4: =SUM(D4:J4)-I4 -> -1.25%
A5: =B4+0.01 -> R$ 120,000.01 | B5: =240000 -> R$ 240,000.00 | C5: 0.0547 | D5: 0.00% | E5: 0.00% | F5: 0.86% | G5: 0.00% | H5: 2.75% | I5: 1.86% | K5: =SUM(D5:J5)-I5 -> -1.86%
A6: =B5+0.01 -> R$ 240,000.01 | B6: =360000 -> R$ 360,000.00 | C6: 0.0684 | D6: 0.27% | E6: 0.31% | F6: 0.95% | G6: 0.23% | H6: 2.75% | I6: 2.33% | K6: =SUM(D6:J6)-I6 -> -2.33%
A7: =B6+0.01 -> R$ 360,000.01 | B7: =480000 -> R$ 480,000.00 | C7: 0.0754 | D7: 0.35% | E7: 0.35% | F7: 1.04% | G7: 0.25% | H7: 2.99% | I7: 2.56% | K7: =SUM(D7:J7)-I7 -> -2.56%
A8: =B7+0.01 -> R$ 480,000.01 | B8: =600000 -> R$ 600,000.00 | C8: 0.076 | D8: 0.35% | E8: 0.35% | F8: 1.05% | G8: 0.25% | H8: 3.02% | I8: 2.58% | K8: =SUM(D8:J8)-I8 -> -2.58%
A9: =B8+0.01 -> R$ 600,000.01 | B9: =720000 -> R$ 720,000.00 | C9: 0.0828 | D9: 0.38% | E9: 0.38% | F9: 1.15% | G9: 0.27% | H9: 3.28% | I9: 2.82% | K9: =SUM(D9:J9)-I9 -> -2.82%
A10: =B9+0.01 -> R$ 720,000.01 | B10: =840000 -> R$ 840,000.00 | C10: 0.0836 | D10: 0.39% | E10: 0.39% | F10: 1.16% | G10: 0.28% | H10: 3.30% | I10: 2.84% | K10: =SUM(D10:J10)-I10 -> -2.84%
A11: =B10+0.01 -> R$ 840,000.01 | B11: =960000 -> R$ 960,000.00 | C11: 0.0845 | D11: 0.39% | E11: 0.39% | F11: 1.17% | G11: 0.28% | H11: 3.35% | I11: 2.87% | K11: =SUM(D11:J11)-I11 -> -2.87%
A12: =B11+0.01 -> R$ 960,000.01 | B12: =1080000 -> R$ 1,080,000.00 | C12: 0.0903 | D12: 0.42% | E12: 0.42% | F12: 1.25% | G12: 0.30% | H12: 3.57% | I12: 3.07% | K12: =SUM(D12:J12)-I12 -> -3.07%
A13: =B12+0.01 -> R$ 1,080,000.01 | B13: =1200000 -> R$ 1,200,000.00 | C13: 0.0912 | D13: 0.43% | E13: 0.43% | F13: 1.26% | G13: 0.30% | H13: 3.60% | I13: 3.10% | K13: =SUM(D13:J13)-I13 -> -3.10%
A14: =B13+0.01 -> R$ 1,200,000.01 | B14: =1320000 -> R$ 1,320,000.00 | C14: 0.0995 | D14: 0.46% | E14: 0.46% | F14: 1.38% | G14: 0.33% | H14: 3.94% | I14: 3.38% | K14: =SUM(D14:J14)-I14 -> -3.38%
A15: =B14+0.01 -> R$ 1,320,000.01 | B15: =1440000/1 -> R$ 1,440,000.00 | C15: 0.1004 | D15: 0.46% | E15: 0.46% | F15: 1.39% | G15: 0.33% | H15: 3.99% | I15: 3.41% | K15: =SUM(D15:J15)-I15 -> -3.41%
A16: =B15+0.01 -> R$ 1,440,000.01 | B16: =1560000 -> R$ 1,560,000.00 | C16: 0.1013 | D16: 0.47% | E16: 0.47% | F16: 1.40% | G16: 0.33% | H16: 4.01% | I16: 3.45% | K16: =SUM(D16:J16)-I16 -> -3.45%
A17: =B16+0.01 -> R$ 1,560,000.01 | B17: =1680000 -> R$ 1,680,000.00 | C17: 0.1023 | D17: 0.47% | E17: 0.47% | F17: 1.42% | G17: 0.34% | H17: 4.05% | I17: 3.48% | K17: =SUM(D17:J17)-I17 -> -3.48%
A18: =B17+0.01 -> R$ 1,680,000.01 | B18: =1800000 -> R$ 1,800,000.00 | C18: 0.1032 | D18: 0.48% | E18: 0.48% | F18: 1.43% | G18: 0.34% | H18: 4.08% | I18: 3.51% | K18: =SUM(D18:J18)-I18 -> -3.51%
A19: =B18+0.01 -> R$ 1,800,000.01 | B19: =1920000 -> R$ 1,920,000.00 | C19: 0.1123 | D19: 0.52% | E19: 0.52% | F19: 1.56% | G19: 0.37% | H19: 4.44% | I19: 3.82% | K19: =SUM(D19:J19)-I19 -> -3.82%
A20: =B19+0.01 -> R$ 1,920,000.01 | B20: =2040000 -> R$ 2,040,000.00 | C20: 0.1132 | D20: 0.52% | E20: 0.52% | F20: 1.57% | G20: 0.37% | H20: 4.49% | I20: 3.85% | K20: =SUM(D20:J20)-I20 -> -3.85%
A21: =B20+0.01 -> R$ 2,040,000.01 | B21: =2160000 -> R$ 2,160,000.00 | C21: 0.1142 | D21: 0.53% | E21: 0.53% | F21: 1.58% | G21: 0.38% | H21: 4.52% | I21: 3.88% | K21: =SUM(D21:J21)-I21 -> -3.88%
A22: =B21+0.01 -> R$ 2,160,000.01 | B22: =2280000 -> R$ 2,280,000.00 | C22: 0.1151 | D22: 0.53% | E22: 0.53% | F22: 1.60% | G22: 0.38% | H22: 4.56% | I22: 3.91% | K22: =SUM(D22:J22)-I22 -> -3.91%
A23: =2280000.01 -> R$ 2,280,000.01 | B23: 2400000 | C23: 0.1161 | D23: 0.54% | E23: 0.54% | F23: 1.60% | G23: 0.38% | H23: 4.60% | I23: 3.95% | K23: =SUM(D23:J23)-I23 -> -3.95%
A24: =2400000*1.2 -> R$ 2,880,000.00 | C24: 0.1161 | K24: =SUM(D23:J23)-I23 -> -3.95%
J25: (*) sem ICMS
L33: ICMS - Simples | M33: =VLOOKUP('Comércio'!J8,A4:C24,3) -> 11.61%
L34: Isenção | M34: =VLOOKUP('Comércio'!J8,A4:K24,11) -> -3.95%
L35: Substituição Tributária | M35: =VLOOKUP('Comércio'!J8,A4:K24,11) -> -3.95%

Sheet Serviços (III)
C2: COMPARAÇÃO LUCRO REAL X LUCRO PRESUMIDO X SIMPLES NACIONAL - Serviços e Locação (Anexo III)
B5: Digite nas células em amarelo | G5: Atividades > | J5: Ajuda >
C7: LUCRO REAL | F7: LUCRO PRESUMIDO | I7: SIMPLES NACIONAL
C9: Receita Bruta | D9: 300000 | F9: Receita Bruta | G9: =D9 -> R$ 300,000.00 | I9: Receita Bruta Mensal (limite de 200 mil + 20%) | J9: =G9 -> R$ 300,000.00
C10: 0.05 | D10: =(D9*C10) -> R$ 15,000.00 | F10: =C10 -> ISS de 5% | G10: =D10 -> R$ 15,000.00 | I10: Em 12 meses | J10: =G9*12 -> R$ 3,600,000.00
C11: 0.0065 | D11: =D9*C11 -> R$ 1,950.00 | F11: 0.0065 | G11: =G9*F11 -> R$ 1,950.00
C12: 0.03 | D12: =D9*C12 -> R$ 9,000.00 | F12: 0.03 | G12: =G9*F12 -> R$ 9,000.00
B13: = | C13: Receita Líquida | D13: =D9-D10-D11-D12 -> R$ 274,050.00 | F13: Receita Líquida | G13: =G9-G10-G11-G12 -> R$ 274,050.00
B14: - | C14: 0.58 | D14: =D9*C14 -> R$ 174,000.00 | F14: =C14 -> Custo do Serviço = 58.0% | G14: =G9*F14 -> R$ 174,000.00 | I14: =C14 -> Custo do Serviço = 58.0% | J14: =J9*I14 -> R$ 174,000.00
B15: = | C15: Margem Bruta | D15: =D13-D14 -> R$ 100,050.00 | F15: Resultado operacional | G15: =G13-G14 -> R$ 100,050.00
B16: - | C16: 0.03 | D16: =D9*C16 -> R$ 9,000.00 | F16: =C16 -> folha salarial = 3.0% | G16: =G9*F16 -> R$ 9,000.00 | I16: =C16 -> folha salarial = 3.0% | J16: =J9*I16 -> R$ 9,000.00
B17: - | C17: 0.2 | D17: =D16*C17 -> R$ 1,800.00 | F17: =C17 -> encargos sociais = 20.0% | G17: =D17 -> R$ 1,800.00
B18: - | C18: 0 | D18: =D9*C18 -> R$ 0.00 | F18: =C18 -> despesas diversas = 0.0% | G18: =D18 -> R$ 0.00 | I18: =C18 -> despesas diversas = 0.0% | J18: =J9*I18 -> R$ 0.00
B19: = | C19: Lucro Líquido | D19: =D15-D16-D17-D18 -> R$ 89,250.00 | F19: Lucro Líquido | G19: =D19 -> R$ 89,250.00
C20: 0.09 | D20: =D19*C20 -> R$ 8,032.50 | F20: Base de cálculo do Lucro Presumido CSLL
C21: LALUR | F21: 0.12 | G21: =G9*F21 -> R$ 36,000.00
C22: 0.15 | D22: =D19*C22 -> R$ 13,387.50 | F22: 0.09 | G22: =G21*F22 -> R$ 3,240.00
F23: Base de cálculo do Lucro Presumido IR | I23: Encargos Fiscais (Anexo III)
D24: =D19-D20-D22 -> R$ 67,830.00 | F24: 0.32 | G24: =G9*F24 -> R$ 96,000.00 | I24: =VLOOKUP(J10,'Anexo III'!A4:C24,3) -> Alíquota de 17.42% | J24: =J9*I24 -> R$ 52,260.00
C25: 0.1 | D25: =IF(D24>20000,(D24-20000)*C25,0) -> R$ 4,783.00 | F25: =C22 -> Alíquota do IR de 15% | G25: =G24*F25 -> R$ 14,400.00
F26: 0.1 | G26: =IF(G24>20000,(G24-20000)*F26,0) -> R$ 7,600.00
C28: Lucro Real | D28: =D24-D25 -> R$ 63,047.00 | F28: Lucro Presumido | G28: =G19-G22-G25 -> R$ 71,610.00 | I28: Lucro - Simples | J28: =J9-J11-J14-J16-J18-J24 -> R$ 64,740.00
C31: =D10+D11+D12+D17+D20+D22+D25 -> Carga Tributária - Lucro Real R$ 53,953.00 | F31: =C31 -> Carga Tributária - Lucro Real R$ 53,953.00 | I31: =C31 -> Carga Tributária - Lucro Real R$ 53,953.00
C32: =G10+G11+G12+G17+G22+G25+G26 -> Carga Tributária - Lucro Presumido R$ 52,990.00 | F32: =C32 -> Carga Tributária - Lucro Presumido R$ 52,990.00 | I32: =C32 -> Carga Tributária - Lucro Presumido R$ 52,990.00
C33: =J16+J24 -> Carga Tributária- Simples R$ 61,260.00 | F33: =C33 -> Carga Tributária- Simples R$ 61,260.00 | I33: =C33 -> Carga Tributária- Simples R$ 61,260.00
C35: =G28 -> Lucro Presumido R$ 71,610.00 | F35: =D28 -> Lucro Real R$ 63,047.00 | I35: =G28 -> Lucro Presumido R$ 71,610.00
C36: =J28 -> Lucro no Simples R$ 64,740.00 | F36: =J28 -> Lucro no Simples R$ 64,740.00 | I36: =D28 -> Lucro Real R$ 63,047.00

Sheet Anexo III
A1: Anexo III - Partilha do Simples Nacional – Serviços e Locação de Bens Móveis
A3: Receita Mensal | C3: TOTAL | D3: IRPJ | E3: CSLL | F3: COFINS | G3: PIS/PASEP | H3: CPP | I3: ISS | J3: TOTAL
A4: 0 | B4: 120000 | C4: 0.06 | D4: 0 | E4: 0 | F4: 0 | G4: 0 | H4: 0.04 | I4: 0.02 | J4: =SUM(D4:I4) -> 6.00%
A5: =B4+0.01 -> R$ 120,000.01 | B5: =240000 -> R$ 240,000.00 | C5: 0.0821 | D5: 0 | E5: 0 | F5: 0.0142 | G5: 0 | H5: 0.04 | I5: 0.0279 | J5: =SUM(D5:I5) -> 8.21%
A6: =B5+0.01 -> R$ 240,000.01 | B6: =360000 -> R$ 360,000.00 | C6: 0.1026 | D6: 0.0048 | E6: 0.0043 | F6: 0.0143 | G6: 0.0035 | H6: 0.0407 | I6: 0.035 | J6: =SUM(D6:I6) -> 10.26%
A7: =B6+0.01 -> R$ 360,000.01 | B7: =480000 -> R$ 480,000.00 | C7: 0.1131 | D7: 0.0053 | E7: 0.0053 | F7: 0.0156 | G7: 0.0038 | H7: 0.0447 | I7: 0.0384 | J7: =SUM(D7:I7) -> 11.31%
A8: =B7+0.01 -> R$ 480,000.01 | B8: =600000 -> R$ 600,000.00 | C8: 0.114 | D8: 0.0053 | E8: 0.0052 | F8: 0.0158 | G8: 0.0038 | H8: 0.0452 | I8: 0.0387 | J8: =SUM(D8:I8) -> 11.40%
A9: =B8+0.01 -> R$ 600,000.01 | B9: =720000 -> R$ 720,000.00 | C9: 0.1242 | D9: 0.0057 | E9: 0.0057 | F9: 0.0173 | G9: 0.004 | H9: 0.0492 | I9: 0.0423 | J9: =SUM(D9:I9) -> 12.42%
A10: =B9+0.01 -> R$ 720,000.01 | B10: =840000 -> R$ 840,000.00 | C10: 0.1254 | D10: 0.0059 | E10: 0.0056 | F10: 0.0174 | G10: 0.0042 | H10: 0.0497 | I10: 0.0426 | J10: =SUM(D10:I10) -> 12.54%
A11: =B10+0.01 -> R$ 840,000.01 | B11: =960000 -> R$ 960,000.00 | C11: 0.1268 | D11: 0.0059 | E11: 0.0057 | F11: 0.0176 | G11: 0.0042 | H11: 0.0503 | I11: 0.0431 | J11: =SUM(D11:I11) -> 12.68%
A12: =B11+0.01 -> R$ 960,000.01 | B12: =1080000 -> R$ 1,080,000.00 | C12: 0.1355 | D12: 0.0063 | E12: 0.0061 | F12: 0.0188 | G12: 0.0045 | H12: 0.0537 | I12: 0.0461 | J12: =SUM(D12:I12) -> 13.55%
A13: =B12+0.01 -> R$ 1,080,000.01 | B13: =1200000 -> R$ 1,200,000.00 | C13: 0.1368 | D13: 0.0063 | E13: 0.0064 | F13: 0.0189 | G13: 0.0045 | H13: 0.0542 | I13: 0.0465 | J13: =SUM(D13:I13) -> 13.68%
A14: =B13+0.01 -> R$ 1,200,000.01 | B14: =1320000 -> R$ 1,320,000.00 | C14: 0.1493 | D14: 0.0069 | E14: 0.0069 | F14: 0.0207 | G14: 0.005 | H14: 0.0598 | I14: 0.05 | J14: =SUM(D14:I14) -> 14.93%
A15: =B14+0.01 -> R$ 1,320,000.01 | B15: =1440000 -> R$ 1,440,000.00 | C15: 0.1506 | D15: 0.0069 | E15: 0.0069 | F15: 0.0209 | G15: 0.005 | H15: 0.0609 | I15: 0.05 | J15: =SUM(D15:I15) -> 15.06%
A16: =B15+0.01 -> R$ 1,440,000.01 | B16: =1560000 -> R$ 1,560,000.00 | C16: 0.152 | D16: 0.0071 | E16: 0.007 | F16: 0.021 | G16: 0.005 | H16: 0.0619 | I16: 0.05 | J16: =SUM(D16:I16) -> 15.20%
A17: =B16+0.01 -> R$ 1,560,000.01 | B17: =1680000 -> R$ 1,680,000.00 | C17: 0.1535 | D17: 0.0071 | E17: 0.007 | F17: 0.0213 | G17: 0.0051 | H17: 0.063 | I17: 0.05 | J17: =SUM(D17:I17) -> 15.35%
A18: =B17+0.01 -> R$ 1,680,000.01 | B18: =1800000 -> R$ 1,800,000.00 | C18: 0.1548 | D18: 0.0072 | E18: 0.007 | F18: 0.0215 | G18: 0.0051 | H18: 0.064 | I18: 0.05 | J18: =SUM(D18:I18) -> 15.48%
A19: =B18+0.01 -> R$ 1,800,000.01 | B19: =1920000 -> R$ 1,920,000.00 | C19: 0.1685 | D19: 0.0078 | E19: 0.0076 | F19: 0.0234 | G19: 0.0056 | H19: 0.0741 | I19: 0.05 | J19: =SUM(D19:I19) -> 16.85%
A20: =B19+0.01 -> R$ 1,920,000.01 | B20: =2040000 -> R$ 2,040,000.00 | C20: 0.1698 | D20: 0.0078 | E20: 0.0078 | F20: 0.0236 | G20: 0.0056 | H20: 0.075 | I20: 0.05 | J20: =SUM(D20:I20) -> 16.98%
A21: =B20+0.01 -> R$ 2,040,000.01 | B21: =2160000 -> R$ 2,160,000.00 | C21: 0.1713 | D21: 0.008 | E21: 0.0079 | F21: 0.0237 | G21: 0.0057 | H21: 0.076 | I21: 0.05 | J21: =SUM(D21:I21) -> 17.13%
A22: =B21+0.01 -> R$ 2,160,000.01 | B22: =2280000 -> R$ 2,280,000.00 | C22: 0.1727 | D22: 0.008 | E22: 0.0079 | F22: 0.024 | G22: 0.0057 | H22: 0.0771 | I22: 0.05 | J22: =SUM(D22:I22) -> 17.27%
A23: =2280000.01 -> R$ 2,280,000.01 | B23: 2400000 | C23: 0.1742 | D23: 0.0081 | E23: 0.0079 | F23: 0.0242 | G23: 0.0057 | H23: 0.0783 | I23: 0.05 | J23: =SUM(D23:I23) -> 17.42%
A24: =2400000*1.2 -> R$ 2,880,000.00 | C24: 0.1742

Sheet Serviços IV
C2: COMPARAÇÃO LUCRO REAL X LUCRO PRESUMIDO X SIMPLES NACIONAL - Serviços (Anexo IV)
B5: Digite nas células em amarelo | G5: Atividades > | J5: Ajuda >
C7: LUCRO REAL | F7: LUCRO PRESUMIDO | I7: SIMPLES NACIONAL
C9: Receita Bruta | D9: 300000 | F9: Receita Bruta | G9: =D9 -> R$ 300,000.00 | I9: Receita Bruta Mensal (limite de 200 mil + 20%) | J9: =G9 -> R$ 300,000.00
C10: 0.05 | D10: =(D9*C10) -> R$ 15,000.00 | F10: =C10 -> ISS de 5% | G10: =D10 -> R$ 15,000.00 | I10: Em 12 meses | J10: =G9*12 -> R$ 3,600,000.00
C11: 0.0065 | D11: =D9*C11 -> R$ 1,950.00 | F11: 0.0065 | G11: =G9*F11 -> R$ 1,950.00
C12: 0.03 | D12: =D9*C12 -> R$ 9,000.00 | F12: 0.03 | G12: =G9*F12 -> R$ 9,000.00
B13: = | C13: Receita Líquida | D13: =D9-D10-D11-D12 -> R$ 274,050.00 | F13: Receita Líquida | G13: =G9-G10-G11-G12 -> R$ 274,050.00
B14: - | C14: 0.58 | D14: =D9*C14 -> R$ 174,000.00 | F14: =C14 -> Custo do Serviço = 58.0% | G14: =G9*F14 -> R$ 174,000.00 | I14: =C14 -> Custo do Serviço = 58.0% | J14: =J9*I14 -> R$ 174,000.00
B15: = | C15: Margem Bruta | D15: =D13-D14 -> R$ 100,050.00 | F15: Resultado operacional | G15: =G13-G14 -> R$ 100,050.00
B16: - | C16: 0.1 | D16: =D9*C16 -> R$ 30,000.00 | F16: =C16 -> folha salarial = 10.0% | G16: =G9*F16 -> R$ 30,000.00 | I16: =C16 -> folha salarial = 10.0% | J16: =J9*I16 -> R$ 30,000.00
B17: - | C17: 0.275 | D17: =D16*C17 -> R$ 8,250.00 | F17: =C17 -> encargos sociais = 27.5% | G17: =D17 -> R$ 8,250.00
B18: - | C18: 0.02 | D18: =D9*C18 -> R$ 6,000.00 | F18: =C18 -> despesas diversas = 2.0% | G18: =D18 -> R$ 6,000.00 | I18: =F17 -> encargos sociais = 27.5% | J18: =G17 -> R$ 8,250.00
B19: = | C19: Lucro Líquido | D19: =D15-D16-D17-D18 -> R$ 55,800.00 | F19: Lucro Líquido | G19: =D19 -> R$ 55,800.00
C20: 0.09 | D20: =D19*C20 -> R$ 5,022.00 | F20: Base de cálculo do Lucro Presumido CSLL | I20: =C18 -> despesas diversas = 2.0% | J20: =J9*I20 -> R$ 6,000.00
C21: LALUR | F21: 0.12 | G21: =G9*F21 -> R$ 36,000.00
C22: 0.15 | D22: =D19*C22 -> R$ 8,370.00 | F22: 0.09 | G22: =G21*F22 -> R$ 3,240.00
F23: Base de cálculo do Lucro Presumido IR | I23: Encargos Fiscais (Anexo IV)
D24: =D19-D20-D22 -> R$ 42,408.00 | F24: 0.32 | G24: =G9*F24 -> R$ 96,000.00 | I24: =VLOOKUP(J10,'Anexo IV'!A4:D24,3) -> Alíquota de 16.85% | J24: =J9*I24 -> R$ 50,550.00
C25: 0.1 | D25: =IF(D24>20000,(D24-20000)*C25,0) -> R$ 2,240.80 | F25: =C22 -> Alíquota do IR de 15% | G25: =G24*F25 -> R$ 14,400.00
F26: 0.1 | G26: =IF(G24>20000,(G24-20000)*F26,0) -> R$ 7,600.00
C28: Lucro Real | D28: =D24-D25 -> R$ 40,167.20 | F28: Lucro Presumido | G28: =G19-G22-G25 -> R$ 38,160.00 | I28: Lucro - Simples | J28: =J9-J14-J16-J18-J20-J24 -> R$ 31,200.00
C31: =D10+D11+D12+D17+D20+D22+D25 -> Carga Tributária - Lucro Real R$ 49,832.80 | F31: =C31 -> Carga Tributária - Lucro Real R$ 49,832.80 | I31: =C31 -> Carga Tributária - Lucro Real R$ 49,832.80
C32: =G10+G11+G12+G17+G22+G25+G26 -> Carga Tributária - Lucro Presumido R$ 59,440.00 | F32: =C32 -> Carga Tributária - Lucro Presumido R$ 59,440.00 | I32: =C32 -> Carga Tributária - Lucro Presumido R$ 59,440.00
C33: =J16+J24 -> Carga Tributária- Simples R$ 80,550.00 | F33: =C33 -> Carga Tributária- Simples R$ 80,550.00 | I33: =C33 -> Carga Tributária- Simples R$ 80,550.00
C35: =G28 -> Lucro Presumido R$ 38,160.00 | F35: =D28 -> Lucro Real R$ 40,167.20 | I35: =G28 -> Lucro Presumido R$ 38,160.00
C36: =J28 -> Lucro no Simples R$ 31,200.00 | F36: =J28 -> Lucro no Simples R$ 31,200.00 | I36: =D28 -> Lucro Real R$ 40,167.20

Sheet Anexo IV
A1: Anexo IV - Serviços
A3: Receita Mensal | C3: TOTAL | D3: IRPJ | E3: CSLL | F3: COFINS | G3: PIS/PASEP | H3: ISS
A4: 0 | B4: 120000 | C4: 0.045 | D4: 0 | E4: 0.0122 | F4: 0.0128 | G4: 0 | H4: 0.02
A5: =B4+0.01 -> R$ 120,000.01 | B5: =240000 -> R$ 240,000.00 | C5: 0.0654 | D5: 0 | E5: 0.0184 | F5: 0.0191 | G5: 0 | H5: 0.0279
A6: =B5+0.01 -> R$ 240,000.01 | B6: =360000 -> R$ 360,000.00 | C6: 0.077 | D6: 0.0016 | E6: 0.0185 | F6: 0.0195 | G6: 0.0024 | H6: 0.035
A7: =B6+0.01 -> R$ 360,000.01 | B7: =480000 -> R$ 480,000.00 | C7: 0.0849 | D7: 0.0052 | E7: 0.0187 | F7: 0.0199 | G7: 0.0027 | H7: 0.0384
A8: =B7+0.01 -> R$ 480,000.01 | B8: =600000 -> R$ 600,000.00 | C8: 0.0897 | D8: 0.0089 | E8: 0.0189 | F8: 0.0203 | G8: 0.0029 | H8: 0.0387
A9: =B8+0.01 -> R$ 600,000.01 | B9: =720000 -> R$ 720,000.00 | C9: 0.0978 | D9: 0.0125 | E9: 0.0191 | F9: 0.0207 | G9: 0.0032 | H9: 0.0423
A10: =B9+0.01 -> R$ 720,000.01 | B10: =840000 -> R$ 840,000.00 | C10: 0.1026 | D10: 0.0162 | E10: 0.0193 | F10: 0.0211 | G10: 0.0034 | H10: 0.0426
A11: =B10+0.01 -> R$ 840,000.01 | B11: =960000 -> R$ 960,000.00 | C11: 0.1076 | D11: 0.02 | E11: 0.0195 | F11: 0.0215 | G11: 0.0035 | H11: 0.0431
A12: =B11+0.01 -> R$ 960,000.01 | B12: =1080000 -> R$ 1,080,000.00 | C12: 0.1151 | D12: 0.0237 | E12: 0.0197 | F12: 0.0219 | G12: 0.0037 | H12: 0.0461
A13: =B12+0.01 -> R$ 1,080,000.01 | B13: =1200000 -> R$ 1,200,000.00 | C13: 0.12 | D13: 0.0274 | E13: 0.02 | F13: 0.0223 | G13: 0.0038 | H13: 0.0465
A14: =B13+0.01 -> R$ 1,200,000.01 | B14: =1320000 -> R$ 1,320,000.00 | C14: 0.128 | D14: 0.0312 | E14: 0.0201 | F14: 0.0227 | G14: 0.004 | H14: 0.05
A15: =B14+0.01 -> R$ 1,320,000.01 | B15: =1440000 -> R$ 1,440,000.00 | C15: 0.1325 | D15: 0.0349 | E15: 0.0203 | F15: 0.0231 | G15: 0.0042 | H15: 0.05
A16: =B15+0.01 -> R$ 1,440,000.01 | B16: =1560000 -> R$ 1,560,000.00 | C16: 0.137 | D16: 0.0386 | E16: 0.0205 | F16: 0.0235 | G16: 0.0044 | H16: 0.05
A17: =B16+0.01 -> R$ 1,560,000.01 | B17: =1680000 -> R$ 1,680,000.00 | C17: 0.1415 | D17: 0.0423 | E17: 0.0207 | F17: 0.0239 | G17: 0.0046 | H17: 0.05
A18: =B17+0.01 -> R$ 1,680,000.01 | B18: =1800000 -> R$ 1,800,000.00 | C18: 0.146 | D18: 0.046 | E18: 0.021 | F18: 0.0243 | G18: 0.0047 | H18: 0.05
A19: =B18+0.01 -> R$ 1,800,000.01 | B19: =1920000 -> R$ 1,920,000.00 | C19: 0.1505 | D19: 0.049 | E19: 0.0219 | F19: 0.0247 | G19: 0.0049 | H19: 0.05
A20: =B19+0.01 -> R$ 1,920,000.01 | B20: =2040000 -> R$ 2,040,000.00 | C20: 0.155 | D20: 0.0521 | E20: 0.0227 | F20: 0.0251 | G20: 0.0051 | H20: 0.05
A21: =B20+0.01 -> R$ 2,040,000.01 | B21: =2160000 -> R$ 2,160,000.00 | C21: 0.1595 | D21: 0.0551 | E21: 0.0236 | F21: 0.0255 | G21: 0.0053 | H21: 0.05
A22: =B21+0.01 -> R$ 2,160,000.01 | B22: =2280000 -> R$ 2,280,000.00 | C22: 0.164 | D22: 0.0581 | E22: 0.0245 | F22: 0.0259 | G22: 0.0055 | H22: 0.05
A23: =2280000.01 -> R$ 2,280,000.01 | B23: 2400000 | C23: 0.1685 | D23: 0.0612 | E23: 0.0253 | F23: 0.0263 | G23: 0.0057 | H23: 0.05
A24: =2400000*1.2 -> R$ 2,880,000.00 | C24: 0.1685
