Workbook

Sheet Jan
B2: Fluxo de Caixa de Janeiro de 2015
B4: ÍTEM / DESCRIÇÃO | D4: Realizado | E4: PREVISTO | F4: PREVISTO | G4: Realizado | H4: Realizado | I4: Realizado | J4: Realizado | K4: Realizado | L4: PREVISTO | M4: PREVISTO | N4: Realizado | O4: Realizado | P4: Realizado | Q4: Realizado | R4: Realizado | S4: PREVISTO | T4: PREVISTO | U4: Realizado | V4: Realizado | W4: Realizado | X4: Realizado | Y4: Realizado | Z4: PREVISTO | AA4: PREVISTO | AB4: Realizado | AC4: Realizado | AD4: Realizado | AE4: Realizado | AF4: Realizado | AG4: PREVISTO
D5: 42006 | E5: =D5+1 -> 42007 | F5: =E5+1 -> 42008 | G5: =F5+1 -> 42009 | H5: =G5+1 -> 42010 | I5: =H5+1 -> 42011 | J5: =I5+1 -> 42012 | K5: =J5+1 -> 42013 | L5: =K5+1 -> 42014 | ... AG5: =AF5+1 -> 42035 | AH5: ACUMULADO
C6: SALDO ANTERIOR DA CONTA CORRENTE | D6: 145330.03 | E6: =D77 -> 213824.71 | F6: =E77 -> 213824.71 | G6: =F77 -> 213824.71 | H6: =G77 -> 231337.3 | I6: =H77 -> 256642.48 | J6: =I77 -> 292558.13 | K6: =J77 -> 309064.94 | L6: =K77 -> 228324.42 | ... AG6: =AF77 -> 68629.55 | AH6: =D6 -> 145330.03
B7: ENTRADAS | C7: Adiantamento de Clientes | G7: =3000+342+2660 -> 6002 | H7: =421.05 -> 421.05 | I7: =391.35 -> 391.35 | J7: =280.4 -> 280.4 | P7: =2301.6+500 -> 2801.6 | R7: =440 -> 440 | U7: =952.35+254.1 -> 1206.45 | W7: =636.3 -> 636.3 | X7: =1263+2935+825 -> 5023 | Y7: =2216.55+368.55+1986.6 -> 4571.7 | AB7: =2939.05+23100+1898.4 -> 27937.45 | AC7: =13812.45 -> 13812.45 | AD7: =1458+1052 -> 2510 | AH7: =SUM(D7:AG7) -> 66033.75
C8: Depósito RDS | K8: =1179.5+8+262.14+445.15+663.1+1032.15+1077.54+1147.6+2224 -> 8039.18 | R8: =1079.7+1152.75+900.6+720.17+476.35+33.09+121.84+2829.4+1890.33 -> 9204.23 | V8: =2728.35+660.45+849.25+1273.5 -> 5511.55 | AB8: =160.14+648.79+848.05+850.15+5296.3 -> 7803.43 | AF8: =35.09+340.45+1399.4+1443.84 -> 3218.78 | AH8: =SUM(D8:AG8) -> 33777.17
C9: Crédito Não Identificado | AH9: =SUM(D9:AG9) -> 0
C10: Fundo de Reserva | V10: 15000 | AH10: =SUM(D10:AG10) -> 15000
C11: Faturas | D11: =8893.55+288.75+254.1 -> 9436.4 | G11: =6700+254.1 -> 6954.1 | H11: =15125.52 -> 15125.52 | I11: =27254.22+1934.7 -> 29188.92 | J11: =5366.3+4382.52+424.9 -> 10173.72 | K11: =4145.35+241.4+2098+3055.5+6111 -> 15651.25 | N11: =1235+1727.25+1330+613.8+1869.56+5631.56 -> 12407.17 | O11: =16257.5+1884.23+618.02+1142.97+651.42+696.09 -> 21250.23 | P11: =2280.6 -> 2280.6 | Q11: =1530.75+1234.31 -> 2765.06 | R11: =4388.85+6382.5+283.36+222.33+271.81 -> 11548.85 | U11: =66218.67+241.4+556.72+1948.1+2066.81+271.81 -> 71303.51 | V11: =67043.57+11004+1713.71+619+505.55 -> 80885.83 | W11: =7654.19+2385.41+587.51 -> 10627.11 | X11: =83837.17+2274.81 -> 86111.98 | Y11: =6840.56+482.8+254.1+1619.34+667.59 -> 9864.39 | AB11: =22666.73+557.55+288.75+6456.21+2657.08+842.11+1122.82+2363.82+2453+2355.65+2122.48+1806.11+3872.4+2310.97+3107.29+3221.67 -> 58204.64 | AC11: =103520+6285.3+9333.45 -> 119138.75 | AD11: =76295.24+3638.95+2007.78 -> 81941.97 | AE11: =29760.76+2422.49+2441.78+2076.95 -> 36701.98 | AF11: =8551.23+735 -> 9286.23 | AH11: =SUM(D11:AG11) -> 700848.21
C12: Receitas Diversas | D12: 3.59 | G12: 3.89 | H12: 4.31 | I12: =23383.92+4.94 -> 23388.86 | J12: 5.12 | K12: =0.01+3.84 -> 3.85 | N12: 4.8 | O12: 5.27 | P12: 4.87 | Q12: =62305.99+4.06 -> 62310.05 | R12: 4.83 | U12: 6.61 | V12: 0.35 | W12: 0.18 | X12: 2.02 | Y12: 2.05 | AB12: 2.67 | AC12: =180+5.2 -> 185.2 | AD12: =180.95+2.72 -> 183.67 | AE12: 3.67 | AF12: =375+1.23 -> 376.23 | AH12: =SUM(D12:AG12) -> 86502.09
C13: Amex | D13: 6872.51 | G13: =6432.15 -> 6432.15 | H13: 4726.84 | I13: 3663.36 | J13: 2636.83 | K13: 1135.58 | N13: 3047.72 | O13: 683.06 | P13: 891.56 | Q13: 743.43 | R13: 656.39 | U13: 11218.06 | V13: 358.58 | Y13: 360.8 | AD13: 557.86 | AH13: =SUM(D13:AG13) -> 43984.73
C14: Visa Electron | D14: 3962.37 | G14: 2651.31 | H14: 586.06 | I14: 1961.41 | J14: 871.75 | K14: 1688.06 | N14: 3913.57 | O14: 1016.28 | P14: 90.12 | Q14: 678.89 | R14: 2025.99 | U14: 5426.83 | V14: 2978.83 | W14: 234.65 | X14: 165.91 | Y14: 1244.8 | AB14: 2657.85 | AC14: 1432.25 | AD14: 709.52 | AE14: 2575.32 | AF14: 740.61 | AH14: =SUM(D14:AG14) -> 37612.38
C15: Master Débito | D15: 12719.38 | G15: =556.98+458.61 -> 1015.59 | H15: 5455.06 | J15: 36.6 | K15: =3195.82+2642.86 -> 5838.68 | N15: =5131.47+74.08 -> 5205.55 | O15: =323.75+543.19 -> 866.94 | P15: =50.63+137.86 -> 188.49 | Q15: 3103.34 | R15: 419.95 | U15: =4977.5+614.96 -> 5592.46 | V15: 851.15 | W15: 114.16 | X15: 463.17 | Y15: 16.68 | AB15: 2274.59 | AC15: 2343.89 | AD15: =1188.37+12.76 -> 1201.13 | AE15: 2709.05 | AF15: 876.5 | AH15: =SUM(D15:AG15) -> 51292.36
C16: Visa Crédito | D16: 27262.61 | G16: 23040.58 | H16: 8343.95 | I16: 22416.38 | J16: 5728.06 | K16: 16816.67 | N16: 29947.47 | O16: 15031.09 | P16: 21099.34 | Q16: 868.99 | R16: 12599.17 | U16: 23976.14 | V16: 1347.06 | W16: 2753.93 | X16: 10546.28 | Y16: 1803.71 | AB16: 15595.73 | AC16: 1168.94 | AD16: 11465.86 | AE16: 8485.29 | AF16: 13114.01 | AH16: =SUM(D16:AG16) -> 273411.26
C17: Master Crédito | D17: =17658.28+822.94 -> 18481.22 | G17: 6060.69 | H17: 1328.64 | I17: 5764.28 | J17: 522.71 | K17: 1093.45 | N17: 5303.14 | O17: 3260.07 | P17: 2449.29 | Q17: 3687.63 | R17: 11082.73 | U17: 8221.43 | V17: 3004.22 | W17: 4352.27 | X17: 3304.9 | Y17: 2302.6 | AB17: 4874.44 | AC17: 5286.58 | AD17: 9006.42 | AE17: 3580.61 | AF17: 992.43 | AH17: =SUM(D17:AG17) -> 103959.75
C18: TOTAL DAS ENTRADAS | D18: =SUM(D7:D17) -> 78738.08 | E18: =SUM(E7:E17) -> 0 | F18: =SUM(F7:F17) -> 0 | G18: =SUM(G7:G17) -> 52160.31 | H18: =SUM(H7:H17) -> 35991.43 | I18: =SUM(I7:I17) -> 86774.56 | J18: =SUM(J7:J17) -> 20255.19 | K18: =SUM(K7:K17) -> 50266.72 | ... AH18: =SUM(AH7:AH17) -> 1412421.7
C19: Repasse Salários e Encargos | I19: 45378.91 | AF19: 65000 | AH19: =SUM(D19:AG19) -> 110378.91
B20: SAIDAS | C20: Repasse Aluguel de Salas e Equipamentos | G20: =6820.81+945.47 -> 7766.28 | AH20: =SUM(D20:AG20) -> 7766.28
C21: Repasse A&B | Q21: 60343.29 | AF21: =(1280+40393.29+45061+833.25)-5921.3 -> 81646.24 | AH21: =SUM(D21:AG21) -> 141989.53
C22: Repasse Telefonia | AH22: =SUM(D22:AG22) -> 0
C23: Repasse Internet | G23: =1261.93 -> 1261.93 | AH23: =SUM(D23:AG23) -> 1261.93
C24: Repasse Diversos | G24: =693.35+1060.57+1272.93 -> 3026.85 | P24: =714.92 -> 714.92 | AH24: =SUM(D24:AG24) -> 3741.77
C25: Repasse ao Condomínio | D25: =-SUM(D19:D24) -> 0 | E25: =-SUM(E19:E24) -> 0 | F25: =-SUM(F19:F24) -> 0 | G25: =-SUM(G19:G24) -> -12055.06 | H25: =-SUM(H19:H24) -> 0 | I25: =-SUM(I19:I24) -> -45378.91 | J25: =-SUM(J19:J24) -> 0 | K25: =-SUM(K19:K24) -> 0 | ... AH25: =-SUM(AH19:AH24) -> -265138.42
C26: Impostos Lei 10.833 | AH26: =SUM(D26:AG26) -> 0
C27: IRRF | U27: =10.8+141.93+56.25+613.6+42.67 -> 865.25 | AH27: =SUM(D27:AG27) -> 865.25
C28: ISS a Recolher | K28: =55786.8 -> 55786.8 | AH28: =SUM(D28:AG28) -> 55786.8
C29: ISS Retido a Recolher | AH29: =SUM(D29:AG29) -> 0
C30: INSS Retido a Recolher | AH30: =SUM(D30:AG30) -> 0
C31: IPTU a Pagar | AH31: =SUM(D31:AG31) -> 0
C32: PIS a Recolher | Y32: =6816.16-3626.68 -> 3189.48 | AH32: =SUM(D32:AG32) -> 3189.48
C33: COFINS a Recolher | Y33: =31459.14-15964.25 -> 15494.89 | AH33: =SUM(D33:AG33) -> 15494.89
C34: IRPJ a Recolher | AD34: =(86863.53+88794.35+60425.77)-80399.88 -> 155683.77 | AH34: =SUM(D34:AG34) -> 155683.77
C35: CSLL a Recolher | AD35: =(39885.97+30393.28+38470.87)-16599.87 -> 92150.25 | AH35: =SUM(D35:AG35) -> 92150.25
C36: Total de Impostos | D36: =-SUM(D26:D35) -> 0 | E36: =-SUM(E26:E35) -> 0 | F36: =-SUM(F26:F35) -> 0 | G36: =-SUM(G26:G35) -> 0 | H36: =-SUM(H26:H35) -> 0 | I36: =-SUM(I26:I35) -> 0 | J36: =-SUM(J26:J35) -> 0 | K36: =-SUM(K26:K35) -> -55786.8 | ... AH36: =-SUM(AH26:AH35) -> -323170.44
C37: Água e Esgoto | AH37: =SUM(D37:AG37) -> 0
C38: Energia Elétrica | K38: 11.06 | O38: 17506.77 | AH38: =SUM(D38:AG38) -> 17517.83
C39: Telefone | AH39: =SUM(D39:AG39) -> 0
C40: Total de Contas de Consumo | D40: =-SUM(D37:D39) -> 0 | E40: =-SUM(E37:E39) -> 0 | F40: =-SUM(F37:F39) -> 0 | G40: =-SUM(G37:G39) -> 0 | H40: =-SUM(H37:H39) -> 0 | I40: =-SUM(I37:I39) -> 0 | J40: =-SUM(J37:J39) -> 0 | K40: =-SUM(K37:K39) -> -11.06 | ... AH40: =-SUM(AH37:AH39) -> -17517.83
C41: Adiantamento Dividendos | V41: =44367.37+55696.44+48097.69+95299.9+127253.96+60476.44 -> 431191.8 | W41: =2397.95+2860.53+3028.9 -> 8287.38 | AH41: =SUM(D41:AG41) -> 439479.18
C42: Fundo de Reserva | AB42: =15000+18975.27 -> 33975.27 | AH42: =SUM(D42:AG42) -> 33975.27
C43: Adiantamento a Fornecedor | G43: =1820.47+1200+162+631.28+66+19.72+10300.9+7.35 -> 14207.72 | H43: =8061.5+1100+(7.35*2) -> 9176.2 | K43: 4512.5 | Q43: 62305.99 | AH43: =SUM(D43:AG43) -> 90202.41
C44: Gastos Gerais do Proprietário | AH44: =SUM(D44:AG44) -> 0
C45: Taxa de Condomínio | K45: =40676.09 -> 40676.09 | P45: 14976.24 | U45: 10000 | W45: 17372.58 | AB45: 43612.05 | AH45: =SUM(D45:AG45) -> 126636.96
C46: Taxa de Processamento / Administração / Reservas | K46: =17229.75 -> 17229.75 | P46: =7919.79 -> 7919.79 | V46: 51293.71 | AH46: =SUM(D46:AG46) -> 76443.25
C47: Despesa Comissão Agências de Viagens | D47: =712.1+40.3 -> 752.4 | G47: =315+468 -> 783 | H47: =1440 -> 1440 | K47: =467.64+1515.71+35+290.4+60.48 -> 2369.23 | P47: =70+259+120.9 -> 449.9 | U47: =7181.45+154.6+35+70+341.5 -> 7782.55 | W47: =1882.19+70+38.33+80.6+161.2+268.32 -> 2500.64 | AB47: =1187.14+88.34+80.6 -> 1356.08 | AF47: =56+168+137.4+305.2 -> 666.6 | AH47: =SUM(D47:AG47) -> 18100.4
C48: Serviço Prestado Gerente Geral | AF48: 7464.97 | AH48: =SUM(D48:AG48) -> 7464.97
C49: Repasse Salário GRV | K49: 7103.1 | AH49: =SUM(D49:AG49) -> 7103.1
C50: Custo Livros/Jornais/Revistas | AB50: =122.5+153.9 -> 276.4 | AH50: =SUM(D50:AG50) -> 276.4
C51: Custo com Hospedes | G51: =2194.77 -> 2194.77 | K51: =338.97+232.24 -> 571.21 | W51: =199.9+10.07 -> 209.97 | AB51: =338.01+44.6 -> 382.61 | AH51: =SUM(D51:AG51) -> 3358.56
C52: Repasse Restaurante | AH52: =SUM(D52:AG52) -> 0
C53: Serviço Lavanderia | P53: =15623.32 -> 15623.32 | AF53: =10909.11 -> 10909.11 | AH53: =SUM(D53:AG53) -> 26532.43
C54: Assessoria Jurídica/Contábil e Auditoria | P54: =853.98+3180 -> 4033.98 | AF54: =3180 -> 3180 | AH54: =SUM(D54:AG54) -> 7213.98
C55: Serviços Postais e de Entrega Rápida | K55: =224.55 -> 224.55 | AF55: 187.95 | AH55: =SUM(D55:AG55) -> 412.5
C56: Aluguel de Equipamentos | AH56: =SUM(D56:AG56) -> 0
C57: Cópias e Autenticações | AH57: =SUM(D57:AG57) -> 0
C58: Ornamentação | AH58: =SUM(D58:AG58) -> 0
C59: Serviços Contratados PJ | D59: =7500 -> 7500 | G59: =2350 -> 2350 | J59: 3693.75 | K59: =709.2 -> 709.2 | P59: =1590+1444+307+5845.16 -> 9186.16 | Q59: 842.27 | AD59: 456 | AF59: =180 -> 180 | AH59: =SUM(D59:AG59) -> 24917.38
C60: Outros Serviços Contratados | AH60: =SUM(D60:AG60) -> 0
C61: Material de Manutenção / Pintura | D61: =190 -> 190 | U61: 550 | AB61: =180 -> 180 | AH61: =SUM(D61:AG61) -> 920
C62: Custo Ar Condicionado | D62: =544 -> 544 | AB62: 4212 | AH62: =SUM(D62:AG62) -> 4756
C63: Material de Limpeza | D63: =488+718.45 -> 1206.45 | G63: =773.5 -> 773.5 | U63: =628 -> 628 | AH63: =SUM(D63:AG63) -> 2607.95
C64: Material de Apartamento | K64: =1133.99 -> 1133.99 | AH64: =SUM(D64:AG64) -> 1133.99
C65: Material de Escritório/Serviços Gráficos | AH65: =SUM(D65:AG65) -> 0
C66: Seguro Responsabilidade Civil | AH66: =SUM(D66:AG66) -> 0
C67: Despesa Viagens e Estadias | G67: =1977.65 -> 1977.65 | U67: =1279.5 -> 1279.5 | AH67: =SUM(D67:AG67) -> 3257.15
C68: Reembolso KM | K68: =263.94+195.18 -> 459.12 | U68: 149.38 | AD68: 168.49 | AH68: =SUM(D68:AG68) -> 776.99
C69: Promoção de Vendas | I69: 5480 | AH69: =SUM(D69:AG69) -> 5480
C70: Associação de Classe | G70: 190 | K70: =198.59 -> 198.59 | AH70: =SUM(D70:AG70) -> 388.59
C71: Gastos Diversos | AH71: =SUM(D71:AG71) -> 0
C72: Despesas Bancárias | D72: =(7.35*3)+28.5 -> 50.55 | G72: =(7.35*1)+16.17+28.5+64 -> 116.02 | H72: =7.35+62.7 -> 70.05 | J72: =7.35+41.58+5.7 -> 54.63 | K72: =7.35*3 -> 22.05 | N72: =32.34 -> 32.34 | O72: 96.9 | P72: =66.99+11.4+(7.35*2) -> 93.09 | Q72: =(7.35*3)+45+11.4 -> 78.45 | U72: =57.75+7.35 -> 65.1 | V72: =617.4+85.47+51.3 -> 754.17 | W72: =(7.35*5)+17.1 -> 53.85 | X72: 27.72 | Y72: =16.17 -> 16.17 | AB72: =7.35*2 -> 14.7 | AC72: 39.9 | AD72: =5.7+7.35 -> 13.05 | AE72: =122.43+28.5 -> 150.93 | AF72: =(7.35*5)+71.61 -> 108.36 | AH72: =SUM(D72:AG72) -> 1858.03
C73: Cheques Não Compesados | AH73: =SUM(D73:AG73) -> 0
C74: Total de Serviços Contratados e Terceirizados | D74: =-SUM(D41:D73) -> -10243.4 | E74: =-SUM(E41:E73) -> 0 | F74: =-SUM(F41:F73) -> 0 | G74: =-SUM(G41:G73) -> -22592.66 | H74: =-SUM(H41:H73) -> -10686.25 | I74: =-SUM(I41:I73) -> -5480 | J74: =-SUM(J41:J73) -> -3748.38 | K74: =-SUM(K41:K73) -> -75209.38 | ... AH74: =-SUM(AH41:AH73) -> -883295.49
C75: TOTAL DAS SAÍDAS | D75: =D25+D36+D40+D74 -> -10243.4 | E75: =E25+E36+E40+E74 -> 0 | F75: =F25+F36+F40+F74 -> 0 | G75: =G25+G36+G40+G74 -> -34647.72 | H75: =H25+H36+H40+H74 -> -10686.25 | I75: =I25+I36+I40+I74 -> -50858.91 | J75: =J25+J36+J40+J74 -> -3748.38 | K75: =K25+K36+K40+K74 -> -131007.24 | ... AH75: =AH25+AH36+AH40+AH74 -> -1489122.2
C77: SALDO DA CONTA CORRENTE | D77: =D6+D18+D75 -> 213824.71 | E77: =E6+E18+E75 -> 213824.71 | F77: =F6+F18+F75 -> 213824.71 | G77: =G6+G18+G75 -> 231337.3 | H77: =H6+H18+H75 -> 256642.48 | I77: =I6+I18+I75 -> 292558.13 | J77: =J6+J18+J75 -> 309064.94 | K77: =K6+K18+K75 -> 228324.42 | ... AH77: =AH6+AH18+AH75 -> 68629.55
B78: APLICAÇÕES
C79: APLICAÇÕES | D79: 527087.44 | E79: =D83 -> 527422.83 | F79: =E83 -> 527422.83 | G79: =F83 -> 527422.83 | H79: =G83 -> 527596.89 | I79: =H83 -> 527768.09 | J79: =I83 -> 527942.14 | K79: =J83 -> 528100.57 | L79: =K83 -> 528267.75 | ... AG79: =AF83 -> 549903.35
C80: Fundo Reserva | AB80: 18975.27 | AH80: =SUM(D80:AF80) -> 18975.27
C81: Dividendos a Pagar | V81: -15000 | AB81: 15000 | AH81: =SUM(D81:AF81) -> 0
C82: Rendimentos de Aplicações | D82: 335.39 | G82: 174.06 | H82: 171.2 | I82: 174.05 | J82: 158.43 | K82: 167.18 | N82: 160.68 | O82: 161.57 | P82: 164.28 | Q82: 163.75 | R82: 178.91 | U82: 166.82 | V82: 165.47 | W82: 164.26 | X82: 237.22 | Y82: 192.99 | AB82: 178.8 | AC82: 177.6 | AD82: 179.16 | AE82: 170.77 | AF82: 198.05 | AH82: =SUM(D82:AF82) -> 3840.64
C83: SALDO DAS APLICAÇÕES | D83: =SUM(D80:D82)+D79 -> 527422.83 | E83: =SUM(E80:E82)+D83 -> 527422.83 | F83: =SUM(F80:F82)+E83 -> 527422.83 | G83: =SUM(G80:G82)+F83 -> 527596.89 | H83: =SUM(H80:H82)+G83 -> 527768.09 | I83: =SUM(I80:I82)+H83 -> 527942.14 | J83: =SUM(J80:J82)+I83 -> 528100.57 | K83: =SUM(K80:K82)+J83 -> 528267.75 | L83: =SUM(L80:L82)+K83 -> 528267.75 | ... AG83: =SUM(AG80:AG82)+AF83 -> 549903.35 | AH83: =SUM(AH80:AH82) -> 22815.91
C85: SALDO TOTAL | D85: =D77+D83 -> 741247.54 | E85: =E77+E83 -> 741247.54 | F85: =F77+F83 -> 741247.54 | G85: =G77+G83 -> 758934.19 | H85: =H77+H83 -> 784410.57 | I85: =I77+I83 -> 820500.27 | J85: =J77+J83 -> 837165.51 | K85: =K77+K83 -> 756592.17 | ... AH85: =AH77+AH83 -> 91445.46
C87: RESUMO DO DIA
C88: DATA ATUAL: | D88: =AF5 -> 42034
C89: SALDO INICIAL: | D89: =AF6 -> 209367.99
C90: ENTRADA PREVISTA: | D90: =AF18 -> 28604.79
C91: SAÍDA PREVISTA: | D91: =AF75 -> -169343.23
C92: SALDO PREVISTO C/C: | D92: =SUM(D89:D91) -> 68629.55 | O92: Financeiro | U92: G. Financeiro | Y92: Gerente Geral
C93: ADIANTAMENTO CLIENTES | D93: 11855.36
C94: ADIANTAMENTO DIVIDENDOS | D94: 100637.35
C95: FUNDO REPOSIÇÃO ATIVOS: | D95: 437212.59
C96: SALDO FINAL PREVISTO: | D96: =SUM(D92:D95) -> 618334.85

Sheet Fev
B2: Fluxo de Caixa de Fevereiro de 2015
B4: ÍTEM / DESCRIÇÃO | D4: Realizado | E4: Realizado | F4: Realizado | G4: Realizado | H4: Realizado | I4: PREVISTO | J4: PREVISTO | K4: Realizado | L4: Realizado | M4: Realizado | N4: Realizado | O4: Realizado | P4: PREVISTO | Q4: PREVISTO | R4: PREVISTO | S4: PREVISTO | T4: Realizado | U4: Realizado | V4: Realizado | W4: PREVISTO | X4: PREVISTO | Y4: Realizado | Z4: Realizado | AA4: Realizado | AB4: Realizado | AC4: Realizado | AD4: PREVISTO | AE4: PREVISTO | AF4: PREVISTO | AG4: PREVISTO
D5: 41672 | E5: =D5+1 -> 41673 | F5: =E5+1 -> 41674 | G5: =F5+1 -> 41675 | H5: =G5+1 -> 41676 | I5: =H5+1 -> 41677 | J5: =I5+1 -> 41678 | K5: =J5+1 -> 41679 | L5: =K5+1 -> 41680 | ... AG5: =AF5+1 -> 41701 | AH5: ACUMULADO
C6: SALDO ANTERIOR DA CONTA CORRENTE | D6: =Jan!AG77 -> 68629.55 | E6: =D77 -> 71718.21 | F6: =E77 -> 154558 | G6: =F77 -> 170153.95 | H6: =G77 -> 218453.82 | I6: =H77 -> 229506.8 | J6: =I77 -> 229506.8 | K6: =J77 -> 229506.8 | L6: =K77 -> 226678.59 | ... AG6: =AF77 -> -211532.21 | AH6: =D6 -> 68629.55
B7: ENTRADAS | C7: Adiantamento de Clientes | D7: =54 -> 54 | E7: =289+346.5+318+40 -> 993.5 | F7: =500+263 -> 763 | G7: =1630+160 -> 1790 | H7: =1993 -> 1993 | K7: =3234 -> 3234 | M7: =822.15+793 -> 1615.15 | N7: =60+378 -> 438 | T7: =218.92 -> 218.92 | U7: =1512+410+263.02 -> 2185.02 | V7: =277.2 -> 277.2 | Y7: =419.47+302.4 -> 721.87 | AC7: =328.77+126.45 -> 455.22 | AE7: 105 | AG7: =1122 -> 1122 | AH7: =SUM(D7:AC7) -> 14738.88
C8: Depósito RDS | O8: =298.3+852.9+285.9+476.8+113.58+617.4+302.6+984.95+1885.25+534.75+1011.99+124.95+463.8+128.16 -> 8081.33 | V8: =2412.8+1486.9+1308.86+992.17+1628.82+918.64+3375.54 -> 12123.73 | AC8: =112+153.69+180+241.75+316.5+1786.85+1809.16 -> 4599.95 | AD8: =60.5+261.92+445.46+522.3+976.54+1005.6+1034.88+1067.2+1525.61+1951+2957.06+2993.25+695.1 -> 15496.42 | AH8: =SUM(D8:AC8) -> 24805.01
C9: Crédito Não Identificado | V9: =15608.42+14391.58 -> 30000 | AE9: 330.3 | AF9: =720+1155 -> 1875 | AH9: =SUM(D9:AC9) -> 30000
C10: Fundo de Reserva | V10: 104000 | AH10: =SUM(D10:AC10) -> 104000
C11: Faturas | D11: =1794.66+3971.75+4508.7 -> 10275.11 | E11: =66160.24+2053.32+1352.45+830.18+415.09+415.09 -> 71226.37 | F11: =55550.14+466.2 -> 56016.34 | G11: =32898.79+346.5+382.85+1455.3+1997.1 -> 37080.54 | H11: =3226.36 -> 3226.36 | K11: =24448.23+781.2 -> 25229.43 | L11: =30338.71+280.7+6172.89+5580.98+5993.85+3139.44+2807.05+1122.82+1250.7+561.41 -> 57248.55 | M11: =4929.65+1997.1 -> 6926.75 | N11: =2865.45+330.75+374.16 -> 3570.36 | O11: =10629.72+1621.93+1102.5 -> 13354.15 | T11: =6000.37 -> 6000.37 | U11: =59909.21+1102.5+1102.5+724.5 -> 62838.71 | V11: =6040.3 -> 6040.3 | Y11: =2810.42+437.85+7017.11 -> 10265.38 | Z11: =29219.49 -> 29219.49 | AA11: =3445.2+4632.47+5402.44+4750.2+288.75 -> 18519.06 | AB11: =61132.6+3253.08+2034.64 -> 66420.32 | AC11: =12142.11 -> 12142.11 | AD11: =367.5+280.7+431.55 -> 1079.75 | AE11: =16199.5+280.7+2807.02+431.55+667.8+38762.15 -> 59148.72 | AF11: =11953.14+438.9+5099.44+347.7 -> 17839.18 | AG11: =3155.25+1150.3+1213.9+1964.93+367.5+3182.55 -> 11034.43 | AH11: =SUM(D11:AC11) -> 495599.7
C12: Receitas Diversas | D12: 1.23 | E12: 2.63 | F12: 2.96 | G12: 3.8 | H12: =214.78+4.04 -> 218.82 | K12: 3.99 | L12: 5.47 | M12: 5.14 | N12: 5.21 | O12: 2.05 | T12: 4.36 | U12: 4.89 | V12: 1.6 | Y12: 0.21 | Z12: 0.68 | AA12: 0.3 | AB12: 1.87 | AC12: 0.16 | AH12: =SUM(D12:AC12) -> 265.37
C13: Amex | D13: 741.64 | E13: 0 | F13: 3975.61 | G13: 1572.35 | H13: 339.79 | K13: 7246.21 | L13: 0 | N13: 220.09 | O13: 1955.81 | T13: 17594.44 | U13: 402.96 | V13: 2034.64 | Y13: 3075.6 | Z13: 202.86 | AA13: 2076.75 | AB13: 3438.18 | AC13: 3524.01 | AD13: 62.31 | AE13: 6210.32 | AF13: 386.4 | AG13: 1763.58 | AH13: =SUM(D13:AC13) -> 48400.94
C14: Visa Electron | D14: 3904.38 | E14: 381.88 | F14: 1159.69 | G14: 736.35 | H14: 1110.38 | K14: 3289.26 | L14: 1356.62 | M14: 616.39 | N14: 2638.46 | O14: 885.87 | T14: 4522.17 | U14: 2255.59 | V14: 1111.9 | Y14: 3629.83 | Z14: 1838.47 | AA14: 1364.75 | AB14: 1228.36 | AC14: 2015.44 | AD14: 339 | AE14: 1384.02 | AF14: 1043.01 | AG14: 932.33 | AH14: =SUM(D14:AC14) -> 34045.79
C15: Master Débito | D15: =2561.81+678.68 -> 3240.49 | E15: =98.76+22.67 -> 121.43 | F15: 292.89 | G15: 497.65 | H15: =400.57+380.26 -> 780.83 | K15: =1117.21+710.53 -> 1827.74 | L15: 26.44 | M15: 13.74 | N15: 73.98 | O15: 3379.99 | T15: =9163.06+726.33 -> 9889.39 | U15: =813.07+415.73 -> 1228.8 | V15: 509.59 | Y15: =623.26+972.4 -> 1595.66 | Z15: 1298.13 | AA15: 680.59 | AB15: 794.37 | AC15: =98.9+100.47 -> 199.37 | AD15: 579.5 | AE15: 591.98 | AF15: 908.79 | AG15: 722.36 | AH15: =SUM(D15:AC15) -> 26451.08
C16: Visa Crédito | D16: 12834.6 | E16: 7694.22 | F16: 3517.95 | G16: 5767.61 | H16: 4797.8 | K16: 33579.27 | L16: 19601.14 | M16: 13555.31 | N16: 8110.71 | O16: 7402.6 | T16: =66920.52 -> 66920.52 | U16: 5090.94 | V16: 11608.59 | Y16: 19712.47 | Z16: 1431.71 | AA16: 5550.9 | AB16: 10763.38 | AC16: =411.47+33020.09 -> 33431.56 | AD16: 2469.31 | AE16: 8498.82 | AF16: 5130.87 | AG16: 3605.2 | AH16: =SUM(D16:AC16) -> 271371.28
C17: Master Crédito | D17: =12060.7+878.08 -> 12938.78 | E17: 2519.96 | F17: 3951.51 | G17: 950.9 | H17: 931.85 | K17: =17811.59+962.97 -> 18774.56 | L17: 7324.5 | M17: 1875.43 | N17: 4977.75 | O17: =6840.87+21.3987 -> 6862.2687 | T17: =26595.04+359.74 -> 26954.78 | U17: 2833.09 | V17: 3517.75 | Y17: 31550.34 | Z17: 922.12 | AA17: 2432.75 | AB17: 6749.24 | AC17: 3021.44 | AD17: 2920.6 | AE17: =1595.03 -> 1595.03 | AF17: 6574.5 | AG17: =340.34+310.06 -> 650.4 | AH17: =SUM(D17:AC17) -> 139089.02
C18: TOTAL DAS ENTRADAS | D18: =SUM(D7:D17) -> 43990.23 | E18: =SUM(E7:E17) -> 82939.99 | F18: =SUM(F7:F17) -> 69679.95 | G18: =SUM(G7:G17) -> 48399.2 | H18: =SUM(H7:H17) -> 13398.83 | I18: =SUM(I7:I17) -> 0 | J18: =SUM(J7:J17) -> 0 | K18: =SUM(K7:K17) -> 93184.46 | ... AH18: =SUM(AH7:AH17) -> 1188767.1
C19: Repasse Salários e Encargos | D19: =875.6+20145.35 -> 21020.95 | AC19: 30000 | AH19: =SUM(E19:AC19) -> 30000
B20: SAIDAS | C20: Repasse Aluguel de Salas e Equipamentos | D20: =6440.17+2784.67 -> 9224.84 | AH20: =SUM(E20:AC20) -> 0
C21: Repasse A&B | O21: =71641.47+190+51999+866.8 -> 124697.27 | AC21: =52159.27+40320+506-4 -> 92981.27 | AG21: =45546.8+28000+470.4+266.2 -> 74283.4 | AH21: =SUM(E21:AC21) -> 217678.54
C22: Repasse Telefonia | AH22: =SUM(E22:AC22) -> 0
C23: Repasse Internet | D23: =989.55 -> 989.55 | AH23: =SUM(E23:AC23) -> 0
C24: Repasse Diversos | D24: =1222.08+492.43 -> 1714.51 | O24: =3078.2+342.07 -> 3420.27 | AH24: =SUM(E24:AC24) -> 3420.27
C25: Repasse ao Condomínio | D25: =-SUM(D19:D24) -> -32949.85 | E25: =-SUM(E19:E24) -> 0 | F25: =-SUM(F19:F24) -> 0 | G25: =-SUM(G19:G24) -> 0 | H25: =-SUM(H19:H24) -> 0 | I25: =-SUM(I19:I24) -> 0 | J25: =-SUM(J19:J24) -> 0 | K25: =-SUM(K19:K24) -> 0 | ... AH25: =-SUM(AH19:AH24) -> -251098.81
C26: Impostos Lei 10.833 | AH26: =SUM(D26:AC26) -> 0
C27: IRRF | U27: =10.8+13.03+28.66+13+56.25+109.36 -> 231.1 | AH27: =SUM(D27:AC27) -> 231.1
C28: ISS a Recolher | H28: =587.15 -> 587.15 | K28: 58733.01 | AH28: =SUM(D28:AC28) -> 59320.16
C29: ISS Retido a Recolher | AH29: =SUM(D29:AC29) -> 0
C30: INSS Retido a Recolher | AH30: =SUM(D30:AC30) -> 0
C31: IPTU a Pagar | N31: 14678.84 | O31: =75+75 -> 150 | AH31: =SUM(D31:AC31) -> 14828.84
C32: PIS a Recolher | AA32: =8438.11-3431.24 -> 5006.87 | AH32: =SUM(D32:AC32) -> 5006.87
C33: COFINS a Recolher | AA33: =38945.12-15751.01 -> 23194.11 | AH33: =SUM(D33:AC33) -> 23194.11
C34: IRPJ a Recolher | AE34: =55072.82+95830.65+81485.32+802.49 -> 233191.28 | AH34: =SUM(D34:AC34) -> 0
C35: CSLL a Recolher | AE35: =37604.18+28466.22+42419.03+288.89 -> 108778.32 | AH35: =SUM(D35:AC35) -> 0
C36: Total de Impostos | D36: =-SUM(D26:D35) -> 0 | E36: =-SUM(E26:E35) -> 0 | F36: =-SUM(F26:F35) -> 0 | G36: =-SUM(G26:G35) -> 0 | H36: =-SUM(H26:H35) -> -587.15 | I36: =-SUM(I26:I35) -> 0 | J36: =-SUM(J26:J35) -> 0 | K36: =-SUM(K26:K35) -> -58733.01 | ... AH36: =-SUM(AH26:AH35) -> -102581.08
C37: Água e Esgoto | AH37: =SUM(D37:AC37) -> 0
C38: Energia Elétrica | M38: =3028.92+2225.55+2885.16+2109.63+1764.16+2554.1+2193.97+1135.45+4451.01 -> 22347.95 | AH38: =SUM(D38:AC38) -> 22347.95
C39: Telefone | AH39: =SUM(D39:AC39) -> 0
C40: Total de Contas de Consumo | D40: =-SUM(D37:D39) -> 0 | E40: =-SUM(E37:E39) -> 0 | F40: =-SUM(F37:F39) -> 0 | G40: =-SUM(G37:G39) -> 0 | H40: =-SUM(H37:H39) -> 0 | I40: =-SUM(I37:I39) -> 0 | J40: =-SUM(J37:J39) -> 0 | K40: =-SUM(K37:K39) -> 0 | ... AH40: =-SUM(AH37:AH39) -> -22347.95
C41: Adiantamento Dividendos | V41: =60476.04+35496.22+42759.96+59920.25+66029.31+43674.66 -> 308356.44 | Y41: =7824.8+13894.25+10833.89+16711.68+14866.6+17836.66+7971.03+41183.46 -> 131122.37 | Z41: =2860.53*3 -> 8581.59 | AH41: =SUM(D41:AC41) -> 448060.4
C42: Fundo de Reserva | F42: 50000 | AH42: =SUM(D42:AC42) -> 50000
C43: Adiantamento a Fornecedor | AH43: =SUM(D43:AC43) -> 0
C44: Gastos Gerais do Proprietário | AH44: =SUM(D44:AC44) -> 0
C45: Taxa de Condomínio | M45: 14976.24 | O45: 43631.85 | U45: 40676.09 | Y45: 14391.58 | AA45: 13676.39 | AC45: =1932.03+27352.78 -> 29284.81 | AH45: =SUM(D45:AC45) -> 156636.96
C46: Taxa de Processamento / Administração / Reservas | K46: =7919.79+22847.31 -> 30767.1 | V46: 51827.7 | AH46: =SUM(D46:AC46) -> 82594.8
C47: Despesa Comissão Agências de Viagens | F47: =80.6 -> 80.6 | H47: =241.92+35+198+92.68 -> 567.6 | K47: =800 -> 800 | M47: =1490.21+115.6+130.2+210 -> 1946.01 | O47: =523.97+25398.9 -> 25922.87 | U47: =35+35+685.8 -> 755.8 | Y47: =2126.96+80.6 -> 2207.56 | AA47: =3714.19+150.8 -> 3864.99 | AE47: =2510.5+54.6+59.2+29.6+184+65.8+349.8 -> 3253.5 | AG47: 102.48 | AH47: =SUM(D47:AC47) -> 36145.43
C48: Serviço Prestado Gerente Geral | AH48: =SUM(D48:AB48) -> 0
C49: Repasse Salário GRV | AH49: =SUM(D49:AB49) -> 0
C50: Custo Livros/Jornais/Revistas | O50: =122.5 -> 122.5 | AA50: =153.9 -> 153.9 | AH50: =SUM(D50:AC50) -> 276.4
C51: Custo com Hospedes | H51: =53.65+224 -> 277.65 | M51: =46.4 -> 46.4 | O51: =36.8+141.3+336 -> 514.1 | Y51: =1503.12 -> 1503.12 | AH51: =SUM(D51:AC51) -> 2341.27
C52: Repasse Restaurante | AH52: =SUM(D52:AC52) -> 0
C53: Serviço Lavanderia | O53: =21020.03 -> 21020.03 | AE53: 6960.78 | AH53: =SUM(D53:AB53) -> 21020.03
C54: Assessoria Jurídica/Contábil e Auditoria | F54: =853.98 -> 853.98 | M54: =400 -> 400 | AC54: 3180 | AH54: =SUM(D54:AC54) -> 4433.98
C55: Serviços Postais e de Entrega Rápida | M55: =293.45 -> 293.45 | AH55: =SUM(D55:AB55) -> 293.45
C56: Aluguel de Equipamentos | AH56: =SUM(D56:AC56) -> 0
C57: Cópias e Autenticações | K57: =79.46 -> 79.46 | AH57: =SUM(D57:AC57) -> 79.46
C58: Ornamentação | AH58: =SUM(D58:AC58) -> 0
C59: Serviços Contratados PJ | D59: 7500 | F59: =307+2350 -> 2657 | H59: =390 -> 390 | K59: =709.2+3693.75 -> 4402.95 | O59: =1590+1444+614 -> 3648 | AA59: =24.82 -> 24.82 | AG59: =6258.9+12494.35+9154.1 -> 27907.35 | AH59: =SUM(D59:AC59) -> 18622.77
C60: Outros Serviços Contratados | AH60: =SUM(D60:AC60) -> 0
C61: Material de Manutenção / Pintura | U61: =345.6 -> 345.6 | AH61: =SUM(D61:AC61) -> 345.6
C62: Custo Ar Condicionado | AA62: 4212 | AH62: =SUM(D62:AC62) -> 4212
C63: Material de Limpeza | M63: =1169.75+892.45 -> 2062.2 | AA63: =1344 -> 1344 | AE63: =795+1981.12 -> 2776.12 | AH63: =SUM(D63:AC63) -> 3406.2
C64: Material de Apartamento | M64: =1134+137.94 -> 1271.94 | AH64: =SUM(D64:AC64) -> 1271.94
C65: Material de Escritório/Serviços Gráficos | D65: =424 -> 424 | H65: =147 -> 147 | AA65: =440 -> 440 | AH65: =SUM(D65:AC65) -> 1011
C66: Seguro Responsabilidade Civil | AH66: =SUM(D66:AC66) -> 0
C67: Despesa Viagens e Estadias | F67: =266.97 -> 266.97 | K67: 1160.01 | M67: =429.56 -> 429.56 | U67: 2500 | AH67: =SUM(D67:AC67) -> 4356.54
C68: Reembolso KM | M68: =86.23+129.46 -> 215.69 | U68: 381.35 | AH68: =SUM(D68:AC68) -> 597.04
C69: Promoção de Vendas | O69: =71.61 -> 71.61 | AC69: =1250 -> 1250 | AH69: =SUM(D69:AC69) -> 1321.61
C70: Associação de Classe | F70: 201 | H70: =361.75 -> 361.75 | AH70: =SUM(D70:AC70) -> 562.75
C71: Gastos Diversos | AH71: =SUM(D71:AC71) -> 0
C72: Despesas Bancárias | D72: =27.72 -> 27.72 | E72: =34.2+66 -> 100.2 | F72: =7.35+17.1 -> 24.45 | G72: 99.33 | H72: =7.35*2 -> 14.7 | K72: =(7.35*2)+55.44 -> 70.14 | L72: =64.68+68.4 -> 133.08 | M72: =(7.35*3)+20.79+11.4 -> 54.24 | N72: =34.2 -> 34.2 | O72: =(7.35*2)+64.68+45 -> 124.38 | U72: =67+7.35+51.3 -> 125.65 | V72: =(7.35*80) -> 588 | Y72: =(7.35*7)+103.95 -> 155.4 | Z72: =39.9+7.35 -> 47.25 | AA72: =(7.35*2) -> 14.7 | AB72: =46.2+22.8 -> 69 | AC72: =25.41+7.35 -> 32.76 | AD72: 198.38 | AE72: =34.6+7.35 -> 41.95 | AF72: 14.81 | AG72: =37.5+7.35 -> 44.85 | AH72: =SUM(D72:AC72) -> 1715.2
C73: Cheques Não Compesados | AH73: =SUM(D73:AC73) -> 0
C74: Total de Serviços Contratados e Terceirizados | D74: =-SUM(D41:D73) -> -7951.72 | E74: =-SUM(E41:E73) -> -100.2 | F74: =-SUM(F41:F73) -> -54084 | G74: =-SUM(G41:G73) -> -99.33 | H74: =-SUM(H41:H73) -> -1758.7 | I74: =-SUM(I41:I73) -> 0 | J74: =-SUM(J41:J73) -> 0 | K74: =-SUM(K41:K73) -> -37279.66 | ... AH74: =-SUM(AH41:AH73) -> -839304.83
C75: TOTAL DAS SAÍDAS | D75: =D25+D36+D40+D74 -> -40901.57 | E75: =E25+E36+E40+E74 -> -100.2 | F75: =F25+F36+F40+F74 -> -54084 | G75: =G25+G36+G40+G74 -> -99.33 | H75: =H25+H36+H40+H74 -> -2345.85 | I75: =I25+I36+I40+I74 -> 0 | J75: =J25+J36+J40+J74 -> 0 | K75: =K25+K36+K40+K74 -> -96012.67 | ... AH75: =AH25+AH36+AH40+AH74 -> -1215332.7
C77: SALDO DA CONTA CORRENTE | D77: =D6+D18+D75 -> 71718.21 | E77: =E6+E18+E75 -> 154558 | F77: =F6+F18+F75 -> 170153.95 | G77: =G6+G18+G75 -> 218453.82 | H77: =H6+H18+H75 -> 229506.8 | I77: =I6+I18+I75 -> 229506.8 | J77: =J6+J18+J75 -> 229506.8 | K77: =K6+K18+K75 -> 226678.59 | ... AH77: =AH6+AH18+AH75 -> 42063.949
B78: APLICAÇÕES
C79: APLICAÇÕES | D79: =Jan!AG83 -> 549903.35 | E79: =D83 -> 550140.35 | F79: =E79 -> 550140.35 | G79: =F79 -> 550140.35 | H79: =G79 -> 550140.35 | I79: =H79 -> 550140.35 | J79: =I79 -> 550140.35 | K79: =J79 -> 550140.35 | L79: =K79 -> 550140.35 | M79: =L79 -> 550140.35 | ... AG79: =AF79 -> 550140.35
C80: Fundo Reserva | AH80: =SUM(D80:AC80) -> 0
C81: Dividendos a Pagar | F81: 50000 | V81: -104000 | AH81: =SUM(D81:AC81) -> -54000
C82: Rendimentos de Aplicações | D82: 237 | E82: 173.93 | F82: 175.87 | G82: 176.77 | H82: 187.99 | K82: 181.53 | L82: 184.89 | M82: 184.8 | N82: 186.34 | O82: 224.21 | T82: 192.77 | U82: 197.43 | V82: 180.7 | Y82: 165.83 | Z82: 167.03 | AA82: 166.81 | AB82: 165.88 | AC82: 182.42 | AD82: =19.77+58.6+26.69 -> 105.06 | AE82: =21.36+58.63+26.81 -> 106.8 | AF82: =23.85+58.65+27.05 -> 109.55 | AH82: =SUM(D82:AC82) -> 3332.2
C83: SALDO DAS APLICAÇÕES | D83: =SUM(D80:D82)+D79 -> 550140.35 | E83: =SUM(E80:E82)+D83 -> 550314.28 | F83: =SUM(F80:F82)+E83 -> 600490.15 | G83: =SUM(G80:G82)+F83 -> 600666.92 | H83: =SUM(H80:H82)+G83 -> 600854.91 | I83: =SUM(I80:I82)+H83 -> 600854.91 | J83: =SUM(J80:J82)+I83 -> 600854.91 | K83: =SUM(K80:K82)+J83 -> 601036.44 | L83: =SUM(L80:L82)+K83 -> 601221.33 | ... AG83: =SUM(AG80:AG82)+AF83 -> 499556.96 | AH83: =SUM(AH80:AH82) -> -50667.8
C85: SALDO TOTAL | D85: =D77+D83 -> 621858.56 | E85: =E77+E83 -> 704872.28 | F85: =F77+F83 -> 770644.1 | G85: =G77+G83 -> 819120.74 | H85: =H77+H83 -> 830361.71 | I85: =I77+I83 -> 830361.71 | J85: =J77+J83 -> 830361.71 | K85: =K77+K83 -> 827715.03 | ... AH85: =AH77+AH83 -> -8603.8513
C87: RESUMO DO DIA
C88: DATA ATUAL: | D88: =AC5 -> 41697
C89: SALDO INICIAL: | D89: =AC6 -> 106453.68
C90: ENTRADA PREVISTA: | D90: =AC18 -> 59389.26
C91: SAÍDA PREVISTA: | D91: =AC75 -> -156728.84
C92: SALDO PREVISTO C/C: | D92: =SUM(D89:D91) -> 9114.0987 | L92: Financeiro | S92: G. Financeiro | Y92: Gerente Geral
C93: ADIANTAMENTO CLIENTES | D93: 11907.42
C94: ADIANTAMENTO DIVIDENDOS | D94: 47201.73
C95: FUNDO REPOSIÇÃO ATIVOS: | D95: 439943.98
C96: SALDO FINAL PREVISTO: | D96: =SUM(D92:D95) -> 508167.23

Sheet Março
B2: Fluxo de Caixa de Março de 2015
B4: ÍTEM / DESCRIÇÃO | D4: Realizado | E4: Realizado | F4: Realizado | G4: Realizado | H4: Realizado | I4: PREVISTO | J4: PREVISTO | K4: Realizado | L4: Realizado | M4: Realizado | N4: Realizado | O4: Realizado | P4: PREVISTO | Q4: PREVISTO | R4: Realizado | S4: Realizado | T4: Realizado | U4: Realizado | V4: Realizado | W4: PREVISTO | X4: PREVISTO | Y4: Realizado | Z4: Realizado | AA4: Realizado | AB4: Realizado | AC4: Realizado | AD4: PREVISTO | AE4: PREVISTO | AF4: Realizado | AG4: Realizado | AH4: PREVISTO
D5: 42065 | E5: =D5+1 -> 42066 | F5: =E5+1 -> 42067 | G5: =F5+1 -> 42068 | H5: =G5+1 -> 42069 | I5: =H5+1 -> 42070 | J5: =I5+1 -> 42071 | K5: =J5+1 -> 42072 | L5: =K5+1 -> 42073 | ... AH5: =AG5+1 -> 42095 | AI5: ACUMULADO
C6: SALDO ANTERIOR DA CONTA CORRENTE | D6: =Fev!AC77 -> 9114.0987 | E6: =D77 -> 80963.659 | F6: =E77 -> 115898.69 | G6: =F77 -> 81249.329 | H6: =G77 -> 126891.73 | I6: =H77 -> 132739.16 | J6: =I77 -> 132739.16 | K6: =J77 -> 132739.16 | L6: =K77 -> 222786.49 | ... AH6: =AG77 -> 141151.21 | AI6: =D6 -> 9114.0987
B7: ENTRADAS | C7: Adiantamento de Clientes | D7: =372+370+279.09 -> 1021.09 | E7: =1053+35.2+318.15+80 -> 1486.35 | F7: =280+409 -> 689 | G7: =11105+320 -> 11425 | K7: =443+426.3 -> 869.3 | N7: =219 -> 219 | R7: =351+699.3 -> 1050.3 | T7: =280+420 -> 700 | U7: =280+438 -> 718 | V7: =491+4604+12165+1500+280+289.8 -> 19329.8 | Y7: =346.5 -> 346.5 | AC7: =230+1480.5 -> 1710.5 | AF7: =2722.65+1008 -> 3730.65 | AI7: =SUM(D7:AG7) -> 43295.49
C8: Depósito RDS | O8: =2235.34+1121.83+312.54+468.79+77.3+147.26+199.6+204.26+274.42+288.6+664.9+1495.15+2035.88 -> 9525.87 | AG8: =2871.78+70.4+214.82+258.17+261.63+414.49+604.75+659.59+668.35+950.7+1032.46+1403.55+1444.51+1478.66+1684+2858.4+2907.43+3050.28+3253.94-1302.2 -> 24785.71 | AI8: =SUM(D8:AG8) -> 34311.58
C9: Crédito Não Identificado | AI9: =SUM(D9:AG9) -> 0
C10: Fundo de Reserva | AI10: =SUM(D10:AG10) -> 0
C11: Faturas | D11: =37553.29+3379.53+19759.95 -> 60692.77 | E11: =13421.55+403.6+489.72 -> 14314.87 | F11: =1771.02+2192.4+25000 -> 28963.42 | G11: =9212+365.4+665.7+1638.51 -> 11881.61 | H11: =1627.5+3236.89+416.35 -> 5280.74 | K11: =166959.54+1076.46+1208.9+2179.1+1671.9 -> 173095.9 | L11: =33959.7+16707.04 -> 50666.74 | M11: =1499.2 -> 1499.2 | N11: =15054.25+775.05 -> 15829.3 | O11: =10658.41+932.4 -> 11590.81 | R11: =15096.04+5082+3954 -> 24132.04 | S11: =95977.88+708.74+14559.3 -> 111245.92 | T11: =320.25 -> 320.25 | U11: =396.1 -> 396.1 | V11: =17855.61+330.75+3645.86 -> 21832.22 | Y11: =10743.92+4794.6+3929.87+20000 -> 39468.39 | Z11: =23793.21+274.31+744.59 -> 24812.11 | AA11: =6428.06 -> 6428.06 | AB11: =9455.06+553.63 -> 10008.69 | AC11: =7013.71 -> 7013.71 | AF11: =8044.05+8400+843.92+579.6 -> 17867.57 | AG11: =68285.97+5910.49+5508.21+3222.68+1875.9+3273.27+579.6 -> 88656.12 | AI11: =SUM(D11:AG11) -> 725996.54
C12: Receitas Diversas | D12: 1.36 | E12: 2.01 | F12: 1.43 | G12: 2.28 | H12: 2.35 | K12: 4.05 | L12: 4.45 | M12: 4.23 | N12: =358.56+5.15 -> 363.71 | O12: 4.5 | R12: 7.16 | S12: 9.41 | T12: 8.31 | U12: 8.81 | V12: 0.79 | Y12: 2.13 | Z12: 2.79 | AA12: 2.41 | AB12: =366.3+2.78 -> 369.08 | AC12: =445.5+75+564.71+2.71 -> 1087.92 | AF12: =187.5+0.27 -> 187.77 | AG12: =26.24+520.82+2.57 -> 549.63 | AI12: =SUM(D12:AG12) -> 2626.58
C13: Amex | D13: 4042.67 | E13: 1779.38 | F13: 3884.19 | G13: 5967.15 | H13: 817.91 | K13: 2696 | L13: 2653.02 | M13: 5838.32 | N13: 15116.94 | O13: 4161.98 | R13: 15329.67 | T13: 418.19 | U13: 5189.74 | V13: 177.91 | Y13: =749.57 -> 749.57 | Z13: 1764.88 | AA13: 6298.27 | AB13: 630.95 | AC13: 3502.51 | AF13: 7533.97 | AG13: 14.44 | AI13: =SUM(D13:AG13) -> 88567.66
C14: Visa Electron | D14: 2292.23 | E14: 1932.17 | F14: 280.13 | G14: 33.36 | H14: 2080.54 | K14: =2438.14 -> 2438.14 | L14: 154.83 | M14: 173.43 | N14: 252.16 | O14: 1173.08 | R14: 2284.33 | S14: 1395.07 | T14: 235.69 | U14: 764.03 | Y14: 3419.3 | Z14: =1825.77 -> 1825.77 | AA14: 389.43 | AB14: 609.08 | AC14: 1954.35 | AF14: 8407.48 | AG14: 725.81 | AI14: =SUM(D14:AG14) -> 32820.41
C15: Master Débito | D15: =1106.29+553.74 -> 1660.03 | E15: =26.29+555.58 -> 581.87 | F15: 1661.12 | G15: =81.73+74.57 -> 156.3 | H15: 161.13 | K15: =1990.08+123.38 -> 2113.46 | M15: 762.88 | N15: 88.55 | O15: 356.77 | R15: =4338.57+3.92 -> 4342.49 | S15: 212.28 | T15: 202.67 | U15: =1214.09+17.66 -> 1231.75 | Y15: =845+923.51 -> 1768.51 | Z15: =643.67 -> 643.67 | AA15: =319.18 -> 319.18 | AB15: 99.83 | AC15: =535.01+103.03 -> 638.04 | AF15: =4265.26+154.54 -> 4419.8 | AG15: =630.97+459.64 -> 1090.61 | AI15: =SUM(D15:AG15) -> 22510.94
C16: Visa Crédito | D16: =42876.1 -> 42876.1 | E16: 9151.35 | F16: 8631.59 | G16: 15369.36 | H16: 5816.61 | K16: 54732 | L16: =8870.34 -> 8870.34 | M16: 24269.26 | N16: 36640.16 | O16: =3909.78 -> 3909.78 | R16: 63219.3 | S16: 2632.25 | T16: 8798.18 | U16: 20872.13 | V16: 3898.07 | Y16: 40781.77 | Z16: 9543.85 | AA16: 15791.05 | AB16: 5841.73 | AC16: 8492.97 | AF16: 20832.87 | AG16: 8497.98 | AI16: =SUM(D16:AG16) -> 419468.7
C17: Master Crédito | D17: =14352.02+25.09 -> 14377.11 | E17: 5924.46 | F17: 3674.99 | G17: 885.28 | H17: 458.29 | K17: =15300.4+408.41 -> 15708.81 | L17: =120.86+763.58 -> 884.44 | M17: 2644.6 | N17: 5161.54 | O17: 29504.88 | R17: =48763.14+677.57 -> 49440.71 | S17: =5781.26+2767.45 -> 8548.71 | T17: 1522.68 | U17: 1880.42 | V17: 8011.83 | Y17: 9389.2 | Z17: 414.88 | AA17: 6996.33 | AB17: 2560.95 | AC17: 2117.77 | AF17: 7020.29 | AG17: 2759.94 | AI17: =SUM(D17:AG17) -> 179888.11
C18: TOTAL DAS ENTRADAS | D18: =SUM(D7:D17) -> 126963.36 | E18: =SUM(E7:E17) -> 35172.46 | F18: =SUM(F7:F17) -> 47785.87 | G18: =SUM(G7:G17) -> 45720.34 | H18: =SUM(H7:H17) -> 14617.57 | I18: =SUM(I7:I17) -> 0 | J18: =SUM(J7:J17) -> 0 | K18: =SUM(K7:K17) -> 251657.66 | ... AH18: =SUM(AH7:AH17) -> 0 | AI18: =SUM(D18:AG18) -> 1549486
C19: Repasse Salários e Encargos | F19: =49213.04+875.6 -> 50088.64 | AA19: 16000 | AC19: 25000 | AF19: 50000 | AI19: =SUM(D19:AF19) -> 141088.64
B20: SAIDAS | C20: Repasse Aluguel de Salas e Equipamentos | F20: =6992.84+2756.88 -> 9749.72 | AI20: =SUM(D20:AG20) -> 9749.72
C21: Repasse A&B | O21: =34224.45+862.4+39829 -> 74915.85 | AF21: =35727.09+2158.2+38621+1073.73-355.3 -> 77224.72 | AI21: =SUM(D21:AG21) -> 152140.57
C22: Repasse Telefonia | F22: =1.98 -> 1.98 | AI22: =SUM(D22:AG22) -> 1.98
C23: Repasse Internet | F23: =2207.11 -> 2207.11 | AI23: =SUM(D23:AG23) -> 2207.11
C24: Repasse Diversos | F24: =450.36+1073.73 -> 1524.09 | O24: =108.49 -> 108.49 | AI24: =SUM(D24:AG24) -> 1632.58
C25: Repasse ao Condomínio | D25: =-SUM(D19:D24) -> 0 | E25: =-SUM(E19:E24) -> 0 | F25: =-SUM(F19:F24) -> -63571.54 | G25: =-SUM(G19:G24) -> 0 | H25: =-SUM(H19:H24) -> 0 | I25: =-SUM(I19:I24) -> 0 | J25: =-SUM(J19:J24) -> 0 | K25: =-SUM(K19:K24) -> 0 | ... AI25: =-SUM(AI19:AI24) -> -306820.6
C26: Impostos Lei 10.833 | AI26: =SUM(D26:AG26) -> 0
C27: IRRF | T27: =56.25+386.79+10.8+32.39+22.69 -> 508.92 | AI27: =SUM(D27:AG27) -> 508.92
C28: ISS a Recolher | K28: 59891.9 | AI28: =SUM(D28:AG28) -> 59891.9
C29: ISS Retido a Recolher | AI29: =SUM(D29:AG29) -> 0
C30: INSS Retido a Recolher | AI30: =SUM(D30:AG30) -> 0
C31: IPTU a Pagar | L31: 13381.47 | AI31: =SUM(D31:AG31) -> 13381.47
C32: PIS a Recolher | AA32: =5776.57 -> 5776.57 | AI32: =SUM(D32:AG32) -> 5776.57
C33: COFINS a Recolher | AA33: 26663.2 | AI33: =SUM(D33:AG33) -> 26663.2
C34: IRPJ a Recolher | AI34: =SUM(D34:AG34) -> 0
C35: CSLL a Recolher | AI35: =SUM(D35:AG35) -> 0
C36: Total de Impostos | D36: =-SUM(D26:D35) -> 0 | E36: =-SUM(E26:E35) -> 0 | F36: =-SUM(F26:F35) -> 0 | G36: =-SUM(G26:G35) -> 0 | H36: =-SUM(H26:H35) -> 0 | I36: =-SUM(I26:I35) -> 0 | J36: =-SUM(J26:J35) -> 0 | K36: =-SUM(K26:K35) -> -59891.9 | ... AI36: =-SUM(AI26:AI35) -> -106222.06
C37: Água e Esgoto | AI37: =SUM(D37:AG37) -> 0
C38: Energia Elétrica | M38: 12.32 | N38: =22488.21 -> 22488.21 | AI38: =SUM(D38:AG38) -> 22500.53
C39: Telefone | AI39: =SUM(D39:AG39) -> 0
C40: Total de Contas de Consumo | D40: =-SUM(D37:D39) -> 0 | E40: =-SUM(E37:E39) -> 0 | F40: =-SUM(F37:F39) -> 0 | G40: =-SUM(G37:G39) -> 0 | H40: =-SUM(H37:H39) -> 0 | I40: =-SUM(I37:I39) -> 0 | J40: =-SUM(J37:J39) -> 0 | K40: =-SUM(K37:K39) -> 0 | ... AI40: =-SUM(AI37:AI39) -> -22500.53
C41: Adiantamento Dividendos | V41: =36631.69+35718.18+102256.65+39740.4+42032.32+46797.33+59243.27+79919.5 -> 442339.34 | AI41: =SUM(D41:AG41) -> 442339.34
C42: Fundo de Reserva | D42: 25960.91 | K42: =16877.2+50000 -> 66877.2 | AF42: =6135.55+50000 -> 56135.55 | AI42: =SUM(D42:AF42) -> 148973.66
C43: Adiantamento a Fornecedor | AI43: =SUM(D43:AG43) -> 0
C44: Gastos Gerais do Proprietário | AI44: =SUM(D44:AG44) -> 0
C45: Taxa de Condomínio | K45: 27352.78 | M45: 40676.09 | O45: =14976.24 -> 14976.24 | T45: =43631.85 -> 43631.85 | AI45: =SUM(D45:AG45) -> 126636.96
C46: Taxa de Processamento / Administração / Reservas | L46: =21128.59+7919.79 -> 29048.38 | V46: 51556.96 | AC46: =112.41 -> 112.41 | AI46: =SUM(D46:AG46) -> 80717.75
C47: Despesa Comissão Agências de Viagens | D47: =88.4+35 -> 123.4 | F47: =123.7 -> 123.7 | K47: =800+95.04+35+95.4+72.6+123.6+35+227+500 -> 1983.64 | M47: =1095+90 -> 1185 | R47: 316.2 | T47: =28804.25+2219.89 -> 31024.14 | V47: 75 | Y47: =(18629.19+1079.49+162.11+648.46)+425.1+30.3+772.09+151.45 -> 21898.19 | Z47: 121.63 | AA47: =4751.7+210+50+33+74.89 -> 5119.59 | AC47: =1065.87+2797.79 -> 3863.66 | AF47: =75.8+63+132.7+33 -> 304.5 | AI47: =SUM(D47:AG47) -> 66138.65
C48: Serviço Prestado Gerente Geral | D48: 7464.98 | AI48: =SUM(D48:AF48) -> 7464.98
C49: Repasse Salário Vendas | D49: =461.69+7103.1 -> 7564.79 | H49: 5927.26 | AI49: =SUM(D49:AG49) -> 13492.05
C50: Custo Livros/Jornais/Revistas | O50: =122.5 -> 122.5 | AC50: =153.9 -> 153.9 | AI50: =SUM(D50:AG50) -> 276.4
C51: Custo com Hospedes | D51: 250 | H51: 1659 | O51: =464.6 -> 464.6 | AG51: 224.71 | AI51: =SUM(D51:AG51) -> 2598.31
C52: Repasse Restaurante | AI52: =SUM(D52:AG52) -> 0
C53: Serviço Lavanderia | F53: 18531.64 | R53: 13169.7 | AF53: 13904.04 | AI53: =SUM(D53:AF53) -> 45605.38
C54: Assessoria Jurídica/Contábil e Auditoria | K54: =866.98 -> 866.98 | AF54: =3180 -> 3180 | AI54: =SUM(D54:AG54) -> 4046.98
C55: Serviços Postais e de Entrega Rápida | D55: 319.5 | M55: 222.35 | AF55: =225.85 -> 225.85 | AI55: =SUM(D55:AG55) -> 767.7
C56: Aluguel de Equipamentos | AI56: =SUM(D56:AG56) -> 0
C57: Cópias e Autenticações | AI57: =SUM(D57:AG57) -> 0
C58: Ornamentação | AI58: =SUM(D58:AG58) -> 0
C59: Serviços Contratados PJ | D59: =3500+7950 -> 11450 | K59: 3693.75 | M59: 1590 | O59: =359.2+614+1444 -> 2417.2 | AF59: =1683 -> 1683 | AI59: =SUM(D59:AG59) -> 20833.95
C60: Outros Serviços Contratados | AI60: =SUM(D60:AG60) -> 0
C61: Material de Manutenção / Pintura | AI61: =SUM(D61:AG61) -> 0
C62: Custo Ar Condicionado | AA62: 4212 | AI62: =SUM(D62:AG62) -> 4212
C63: Material de Limpeza | M63: =1238.95 -> 1238.95 | AF63: =829 -> 829 | AI63: =SUM(D63:AG63) -> 2067.95
C64: Material de Apartamento | D64: =1965.52 -> 1965.52 | M64: =358.56+640 -> 998.56 | O64: 358.56 | AI64: =SUM(D64:AG64) -> 3322.64
C65: Material de Escritório/Serviços Gráficos | O65: =510.86 -> 510.86 | Y65: =1099+1215 -> 2314 | AA65: =342 -> 342 | AF65: =300 -> 300 | AI65: =SUM(D65:AG65) -> 3466.86
C66: Seguro Responsabilidade Civil | AI66: =SUM(D66:AG66) -> 0
C67: Despesa Viagens e Estadias | H67: =1183.88 -> 1183.88 | M67: 1500 | AA67: 269.51 | AI67: =SUM(D67:AG67) -> 2953.39
C68: Reembolso KM | AI68: =SUM(D68:AG68) -> 0
C69: Promoção de Vendas | K69: 709.2 | O69: 816 | R69: =394+487.97 -> 881.97 | T69: =252 -> 252 | AF69: 1012 | AI69: =SUM(D69:AG69) -> 3671.17
C70: Associação de Classe | F70: 201 | K70: =162.43 -> 162.43 | AI70: =SUM(D70:AG70) -> 363.43
C71: Gastos Diversos | AI71: =SUM(D71:AG71) -> 0
C72: Despesas Bancárias | D72: =7.35*2 -> 14.7 | E72: =99.33+74.1+64 -> 237.43 | F72: 7.35 | G72: =32.34+45.6 -> 77.94 | K72: =(7.35*2)+57.75 -> 72.45 | L72: =125.4 -> 125.4 | M72: =(7.35*4)+57.75+5.7 -> 92.85 | N72: =34.2 -> 34.2 | O72: =50.82+45+(7.35*3) -> 117.87 | S72: =92.4+28.5 -> 120.9 | U72: =23.1+17.1 -> 40.2 | V72: =639.45+55.44 -> 694.89 | Y72: =34.65+7.35 -> 42 | Z72: =17.1 -> 17.1 | AA72: =(7.35*2)+55.44+5.7 -> 75.84 | AC72: =55.44 -> 55.44 | AF72: =7.35*6 -> 44.1 | AG72: 85.5 | AI72: =SUM(D72:AG72) -> 1956.16
C73: Cheques Não Compesados | AI73: =SUM(D73:AG73) -> 0
C74: Total de Serviços Contratados e Terceirizados | D74: =-SUM(D41:D73) -> -55113.8 | E74: =-SUM(E41:E73) -> -237.43 | F74: =-SUM(F41:F73) -> -18863.69 | G74: =-SUM(G41:G73) -> -77.94 | H74: =-SUM(H41:H73) -> -8770.14 | I74: =-SUM(I41:I73) -> 0 | J74: =-SUM(J41:J73) -> 0 | K74: =-SUM(K41:K73) -> -101718.43 | ... AI74: =-SUM(AI41:AI73) -> -981905.71
C75: TOTAL DAS SAÍDAS | D75: =D25+D36+D40+D74 -> -55113.8 | E75: =E25+E36+E40+E74 -> -237.43 | F75: =F25+F36+F40+F74 -> -82435.23 | G75: =G25+G36+G40+G74 -> -77.94 | H75: =H25+H36+H40+H74 -> -8770.14 | I75: =I25+I36+I40+I74 -> 0 | J75: =J25+J36+J40+J74 -> 0 | K75: =K25+K36+K40+K74 -> -161610.33 | ... AI75: =AI25+AI36+AI40+AI74 -> -1417448.9
C77: SALDO DA CONTA CORRENTE | D77: =D6+D18+D75 -> 80963.659 | E77: =E6+E18+E75 -> 115898.69 | F77: =F6+F18+F75 -> 81249.329 | G77: =G6+G18+G75 -> 126891.73 | H77: =H6+H18+H75 -> 132739.16 | I77: =I6+I18+I75 -> 132739.16 | J77: =J6+J18+J75 -> 132739.16 | K77: =K6+K18+K75 -> 222786.49 | ... AI77: =AI6+AI18+AI75 -> 141151.21
B78: APLICAÇÕES
C79: APLICAÇÕES | D79: =Fev!AC83 -> 499235.55 | E79: =D83 -> 525365.4 | F79: =E83 -> 525538.26 | G79: =F83 -> 525710.23 | H79: =G83 -> 525890.26 | I79: =H83 -> 526065.29 | J79: =I83 -> 526065.29 | K79: =J83 -> 526065.29 | L79: =K83 -> 593116.85 | ... AH79: =AG83 -> 652721.88
C80: Fundo Reserva | D80: 25960.91 | K80: 16877.2 | AF80: 6135.35 | AI80: =SUM(D80:AG80) -> 48973.46
C81: Dividendos a Pagar | K81: 50000 | AF81: 50000 | AI81: =SUM(D81:AG81) -> 100000
C82: Rendimentos de Aplicações | D82: 168.94 | E82: 172.86 | F82: 171.97 | G82: 180.03 | H82: 175.03 | K82: 174.36 | L82: 176.17 | M82: 178.4 | N82: 180.42 | O82: 194.02 | R82: 185.3 | S82: 188.01 | T82: 190.5 | U82: 190.89 | V82: 214.84 | Y82: 498.98 | Z82: 202.28 | AA82: 201.75 | AB82: 204.95 | AC82: 237.43 | AF82: 212.87 | AG82: 212.87 | AI82: =SUM(D82:AG82) -> 4512.87
C83: SALDO DAS APLICAÇÕES | D83: =SUM(D80:D82)+D79 -> 525365.4 | E83: =SUM(E80:E82)+D83 -> 525538.26 | F83: =SUM(F80:F82)+E83 -> 525710.23 | G83: =SUM(G80:G82)+F83 -> 525890.26 | H83: =SUM(H80:H82)+G83 -> 526065.29 | I83: =SUM(I80:I82)+H83 -> 526065.29 | J83: =SUM(J80:J82)+I83 -> 526065.29 | K83: =SUM(K80:K82)+J83 -> 593116.85 | L83: =SUM(L80:L82)+K83 -> 593293.02 | ... AH83: =SUM(AH80:AH82)+AG83 -> 652721.88 | AI83: =AH83 -> 652721.88
C85: SALDO TOTAL | D85: =D77+D83 -> 606329.06 | E85: =E77+E83 -> 641436.95 | F85: =F77+F83 -> 606959.56 | G85: =G77+G83 -> 652781.99 | H85: =H77+H83 -> 658804.45 | I85: =I77+I83 -> 658804.45 | J85: =J77+J83 -> 658804.45 | K85: =K77+K83 -> 815903.34 | ... AI85: =AI77+AI83 -> 793873.09
C87: RESUMO DO DIA
C88: DATA ATUAL: | D88: =AF5 -> 42093
C89: SALDO INICIAL: | D89: =AF6 -> 149223.54
C90: ENTRADA PREVISTA: | D90: =AF18 -> 70000.4
C91: SAÍDA PREVISTA: | D91: =AF75 -> -204842.76
C92: SALDO PREVISTO C/C: | D92: =SUM(D89:D91) -> 14381.179 | L92: Financeiro | S92: G. Financeiro | Y92: Gerente Geral
C93: ADIANTAMENTO CLIENTES | D93: 11972
C94: ADIANTAMENTO DIVIDENDOS | D94: 97714.88
C95: FUNDO REPOSIÇÃO ATIVOS: | D95: 486473.91
C96: SALDO FINAL PREVISTO: | D96: =SUM(D92:D95) -> 610541.97

Sheet Abril
B2: Fluxo de Caixa de Abril de 2015
B4: ÍTEM / DESCRIÇÃO | D4: Realizado | E4: Realizado | F4: PREVISTO | G4: PREVISTO | H4: PREVISTO | I4: Realizado | J4: Realizado | K4: Realizado | L4: Realizado | M4: Realizado | N4: PREVISTO | O4: PREVISTO | P4: Realizado | Q4: Realizado | R4: Realizado | S4: Realizado | T4: Realizado | U4: PREVISTO | V4: PREVISTO | W4: Realizado | X4: PREVISTO | Y4: Realizado | Z4: Realizado | AA4: Realizado | AB4: PREVISTO | AC4: PREVISTO | AD4: Realizado | AE4: Realizado | AF4: Realizado | AG4: Realizado | AH4: PREVISTO
D5: 42095 | E5: =D5+1 -> 42096 | F5: =E5+1 -> 42097 | G5: =F5+1 -> 42098 | H5: =G5+1 -> 42099 | I5: =H5+1 -> 42100 | J5: =I5+1 -> 42101 | K5: =J5+1 -> 42102 | L5: =K5+1 -> 42103 | ... AH5: =AG5+1 -> 42125 | AI5: ACUMULADO
C6: SALDO ANTERIOR DA CONTA CORRENTE | D6: =Março!AG77 -> 141151.21 | E6: =D77 -> 176160.08 | F6: =E77 -> 230701.58 | G6: =F77 -> 230701.58 | H6: =G77 -> 230701.58 | I6: =H77 -> 230701.58 | J6: =I77 -> 222645.17 | K6: =J77 -> 286827.07 | L6: =K77 -> 313495.48 | ... AH6: =AG77 -> 26437.649 | AI6: =D6 -> 141151.21
B7: ENTRADAS | C7: Adiantamento de Clientes | D7: =419 -> 419 | E7: =1052.1+636 -> 1688.1 | I7: =433.12+456.23+886 -> 1775.35 | J7: =55+1500 -> 1555 | K7: =490.87+758.1+491 -> 1739.97 | L7: =439.45+431.03 -> 870.48 | M7: =11000 -> 11000 | P7: =263.03+213.05 -> 476.08 | Q7: =897 -> 897 | R7: =11000+622 -> 11622 | S7: =525+1000+239.4 -> 1764.4 | T7: =332+183 -> 515 | W7: =497.7+157.5 -> 655.2 | Y7: =771.75+1732.5 -> 2504.25 | Z7: =478 -> 478 | AD7: =650.1 -> 650.1 | AE7: =250+465.15+335 -> 1050.15 | AF7: =913.5+673.05 -> 1586.55 | AG7: =1037.31 -> 1037.31 | AI7: =SUM(D7:AG7) -> 42283.94
C8: Depósito RDS | W8: =397+1146.8+4545.1+9.72+63.4+66.2+126.94+137.05+228.09+245.45+273.98+542.9+577.2+685.14+790.9+995.29+1046.06+1080.83+1150.47+1216.57+1448.04 -> 16773.13 | AG8: =1089.9+20+37+73.1+105.6+652.11+753.42+1383.3+1514.25+4417.7 -> 10046.38 | AI8: =SUM(D8:AG8) -> 26819.51
C9: Crédito Não Identificado | AI9: =SUM(D9:AG9) -> 0
C10: Fundo de Reserva | W10: 20000 | AF10: 125000 | AI10: =SUM(D10:AG10) -> 145000
C11: Faturas | D11: =5491.95+693+2192.46+2103.17 -> 10480.58 | E11: =19311.59+1904.24+3383.54+886.71 -> 25486.08 | I11: =4710.94+397.95+2325.17+2125.2+466.2 -> 10025.46 | J11: =34173.61+3087.75+2192.36+1964.93+561.41 -> 41980.06 | K11: =18648+2146.26+3196.24+2181.99 -> 26172.49 | L11: =15680.95+1087.8+3087.75 -> 19856.5 | M11: =9972.66+2075.48 -> 12048.14 | P11: =24360.52+4771.98+3395.42+14236.95 -> 46764.87 | Q11: =58287.07+516.71+1363.8+19935.7 -> 80103.28 | R11: =15980.9+291.9+693 -> 16965.8 | S11: =430.1+8608.95+280.7+4771.98+6476.95+6335+1080.15+1161.16 -> 29144.99 | T11: =5133.14+2713 -> 7846.14 | W11: =12650.1+5557.72+397.95+1646.4+1631.3+658.35 -> 22541.82 | Y11: =26856.02+245+505.12 -> 27606.14 | Z11: =10975.92 -> 10975.92 | AA11: =7478.09+444 -> 7922.09 | AD11: =21183.48 -> 21183.48 | AE11: =44730.64+661.5 -> 45392.14 | AF11: =12183.95 -> 12183.95 | AG11: =5597.95+8309.95+280.7+280.7+10359.77+9852.4+992.25+726.5 -> 36400.22 | AI11: =SUM(D11:AG11) -> 511080.15
C12: Receitas Diversas | D12: =111.25+3.2 -> 114.45 | E12: 4.18 | I12: =168.51+4.08 -> 172.59 | J12: 5.19 | K12: 5.72 | L12: 6.43 | M12: 4.81 | P12: =720+6.74 -> 726.74 | Q12: 8.32 | R12: 5.65 | S12: 6.42 | T12: 6.44 | W12: 0.45 | Y12: =2574.48+2585.49+1.06 -> 5161.03 | Z12: 1.58 | AA12: 1.12 | AD12: =2574.48+2585.49+2.34 -> 5162.31 | AE12: =2574.48+2585.49+3.38 -> 5163.35 | AF12: 0.02 | AG12: 0.48 | AI12: =SUM(D12:AG12) -> 16557.28
C13: Amex | D13: 16010.24 | E13: 3480.27 | I13: 7912.18 | J13: 8789.94 | K13: 1019.37 | L13: 6083.43 | M13: 1869.75 | P13: 15622.97 | Q13: 2667.75 | R13: 144.61 | S13: 2897.11 | T13: 6327.23 | W13: 10950.96 | Y13: 3690.57 | Z13: =774.93 -> 774.93 | AA13: 823.46 | AD13: 12090.26 | AE13: 68.49 | AF13: 801.59 | AG13: 1269.42 | AI13: =SUM(D13:AG13) -> 103294.53
C14: Visa Electron | D14: 996.72 | E14: 884.48 | I14: 6631.59 | J14: 137.35 | K14: 66.33 | L14: 2605.56 | M14: 373.35 | P14: 6130.71 | Q14: 80.95 | R14: 1718.77 | S14: 512.94 | T14: 1265.01 | W14: 3587.31 | Y14: 1129.26 | Z14: 0 | AA14: 2765.77 | AD14: 5645.78 | AE14: 163.37 | AF14: 63.93 | AG14: 232.7 | AI14: =SUM(D14:AG14) -> 34991.88
C15: Master Débito | D15: 909.19 | E15: =877.02+1527.5 -> 2404.52 | I15: =3175.71+45.33 -> 3221.04 | J15: =245.59+69.05 -> 314.64 | L15: =1047.92+22.57 -> 1070.49 | M15: =1228.73+182.7 -> 1411.43 | P15: =1589.54+40.42 -> 1629.96 | Q15: 141.78 | R15: 3234.78 | S15: 747.34 | T15: 428.79 | W15: =1857.62+1236.37 -> 3093.99 | Y15: 517.73 | Z15: 0 | AD15: =1536.65+9.81 -> 1546.46 | AE15: =919.85+51.51 -> 971.36 | AF15: 218.81 | AG15: 52.3 | AI15: =SUM(D15:AG15) -> 21914.61
C16: Visa Crédito | D16: 11550.2 | E16: 7272.47 | I16: 28930.7 | J16: 6741.7 | K16: =3199.65+287.93 -> 3487.58 | L16: 8229.27 | M16: 3490.71 | P16: 37197.02 | Q16: 9549.19 | R16: =1984.86+4460.64 -> 6445.5 | S16: 2189.95 | T16: 5202.67 | W16: =561.56+27428.91 -> 27990.47 | Y16: =21375.47 -> 21375.47 | Z16: =11034.69 -> 11034.69 | AD16: 26849.35 | AE16: 2836.4 | AF16: 10281.51 | AG16: 9386.94 | AI16: =SUM(D16:AG16) -> 240041.79
C17: Master Crédito | D17: 2906.26 | E17: 13417.22 | I17: 12591.14 | J17: =4133.53+571.77 -> 4705.3 | K17: 587 | L17: 2877.38 | M17: =287.93+3165.49 -> 3453.42 | P17: =324.68+24715.23+1820.92 -> 26860.83 | Q17: 5952.98 | R17: =1323.25+143.33 -> 1466.58 | S17: =605.46+6096.86 -> 6702.32 | T17: 1778.17 | W17: =1162.94+9710.56+14.59 -> 10888.09 | Y17: =3668.47 -> 3668.47 | Z17: =4921.21 -> 4921.21 | AA17: =661.62+4201.81 -> 4863.43 | AD17: 11489.71 | AE17: 8023.14 | AF17: 3980.32 | AG17: 6860.8 | AI17: =SUM(D17:AG17) -> 137993.77
C18: TOTAL DAS ENTRADAS | D18: =SUM(D7:D17) -> 43386.64 | E18: =SUM(E7:E17) -> 54637.32 | F18: =SUM(F7:F17) -> 0 | G18: =SUM(G7:G17) -> 0 | H18: =SUM(H7:H17) -> 0 | I18: =SUM(I7:I17) -> 71260.05 | J18: =SUM(J7:J17) -> 64229.18 | K18: =SUM(K7:K17) -> 33078.46 | ... AH18: =SUM(AH7:AH17) -> 0 | AI18: =SUM(D18:AG18) -> 1279977.5
C19: Repasse Salários e Encargos | I19: =6246.47+1573.47 -> 7819.94 | AI19: =SUM(D19:AF19) -> 7819.94
B20: SAIDAS | C20: Repasse Aluguel de Salas e Equipamentos | I20: =4457.56 -> 4457.56 | AI20: =SUM(D20:AG20) -> 4457.56
C21: Repasse A&B | R21: =62029.4+1482.2+891+594+41927.6 -> 106924.2 | AI21: =SUM(D21:AG21) -> 106924.2
C22: Repasse Telefonia | I22: =651.92 -> 651.92 | AI22: =SUM(D22:AG22) -> 651.92
C23: Repasse Internet | I23: =1256.61 -> 1256.61 | AI23: =SUM(D23:AG23) -> 1256.61
C24: Repasse Diversos | I24: =630.32+603.69 -> 1234.01 | P24: =100.27 -> 100.27 | AI24: =SUM(D24:AG24) -> 1334.28
C25: Repasse ao Condomínio | D25: =-SUM(D19:D24) -> 0 | E25: =-SUM(E19:E24) -> 0 | F25: =-SUM(F19:F24) -> 0 | G25: =-SUM(G19:G24) -> 0 | H25: =-SUM(H19:H24) -> 0 | I25: =-SUM(I19:I24) -> -15420.04 | J25: =-SUM(J19:J24) -> 0 | K25: =-SUM(K19:K24) -> 0 | ... AI25: =-SUM(AI19:AI24) -> -122444.51
C26: Impostos Lei 10.833 | AI26: =SUM(D26:AG26) -> 0
C27: IRRF | T27: =42.61+33.81+11.76+16.23+18.65+439.53+10.8+56.25+29.36 -> 659 | AI27: =SUM(D27:AG27) -> 659
C28: ISS a Recolher | AI28: =SUM(D28:AG28) -> 0
C29: ISS Retido a Recolher | M29: 54224.86 | AI29: =SUM(D29:AG29) -> 54224.86
C30: INSS Retido a Recolher | AI30: =SUM(D30:AG30) -> 0
C31: IPTU a Pagar | M31: 13381.47 | AI31: =SUM(D31:AG31) -> 13381.47
C32: PIS a Recolher | Y32: =7389.88-2699.34 -> 4690.54 | AI32: =SUM(D32:AG32) -> 4690.54
C33: COFINS a Recolher | Y33: =34107.12-12523.47 -> 21583.65 | AI33: =SUM(D33:AG33) -> 21583.65
C34: IRPJ a Recolher | AF34: =(85319.98+90317+102167.39)-58877.14 -> 218927.23 | AI34: =SUM(D34:AG34) -> 218927.23
C35: CSLL a Recolher | AF35: =(37500.26+33954.12+32875.19)-12182.02 -> 92147.55 | AI35: =SUM(D35:AG35) -> 92147.55
C36: Total de Impostos | D36: =-SUM(D26:D35) -> 0 | E36: =-SUM(E26:E35) -> 0 | F36: =-SUM(F26:F35) -> 0 | G36: =-SUM(G26:G35) -> 0 | H36: =-SUM(H26:H35) -> 0 | I36: =-SUM(I26:I35) -> 0 | J36: =-SUM(J26:J35) -> 0 | K36: =-SUM(K26:K35) -> 0 | ... AI36: =-SUM(AI26:AI35) -> -405614.3
C37: Água e Esgoto | AI37: =SUM(D37:AG37) -> 0
C38: Energia Elétrica | P38: 20933.14 | AI38: =SUM(D38:AG38) -> 20933.14
C39: Telefone | AI39: =SUM(D39:AG39) -> 0
C40: Total de Contas de Consumo | D40: =-SUM(D37:D39) -> 0 | E40: =-SUM(E37:E39) -> 0 | F40: =-SUM(F37:F39) -> 0 | G40: =-SUM(G37:G39) -> 0 | H40: =-SUM(H37:H39) -> 0 | I40: =-SUM(I37:I39) -> 0 | J40: =-SUM(J37:J39) -> 0 | K40: =-SUM(K37:K39) -> 0 | ... AI40: =-SUM(AI37:AI39) -> -20933.14
C41: Adiantamento Dividendos | W41: =(2520*159)-2574.18 -> 398105.82 | AD41: =2574.48+2585.49 -> 5159.97 | AE41: =2574.48+2585.49 -> 5159.97 | AI41: =SUM(D41:AG41) -> 408425.76
C42: Fundo de Reserva | AI42: =SUM(D42:AF42) -> 0
C43: Adiantamento a Fornecedor | K43: 111.25 | Q43: 11000 | T43: 6000 | AA43: 40000 | AD43: 7000 | AF43: 12000 | AG43: 40000 | AI43: =SUM(D43:AG43) -> 116111.25
C44: Gastos Gerais do Proprietário | AI44: =SUM(D44:AG44) -> 0
C45: Taxa de Condomínio | I45: 40676.09 | M45: 27352.78 | R45: 43631.85 | T45: 13391.13 | AI45: =SUM(D45:AG45) -> 125051.85
C46: Taxa de Processamento / Administração / Reservas | M46: =7919.79+20675.39 -> 28595.18 | W46: 46575.56 | AI46: =SUM(D46:AG46) -> 75170.74
C47: Despesa Comissão Agências de Viagens | D47: =144.8+210+156.8 -> 511.6 | I47: =3613.1+792+4965.31 -> 9370.41 | K47: =1961.7+1224.34 -> 3186.04 | P47: =1928.43+66+86.2 -> 2080.63 | R47: =207.45+18828.53+49.4 -> 19085.38 | T47: =66+2473.22 -> 2539.22 | Y47: 262.5 | AD47: =3919.41 -> 3919.41 | AF47: =1749.96+3903.79+811.52+33+141.8+55 -> 6695.07 | AI47: =SUM(D47:AG47) -> 47650.26
C48: Serviço Prestado Gerente Geral | D48: 7464.98 | AI48: =SUM(D48:AF48) -> 7464.98
C49: Repasse Salário Vendas | AI49: =SUM(D49:AG49) -> 0
C50: Custo Livros/Jornais/Revistas | R50: =122.5 -> 122.5 | AD50: =153.9 -> 153.9 | AI50: =SUM(D50:AG50) -> 276.4
C51: Custo com Hospedes | K51: 930.3 | R51: =223.7 -> 223.7 | W51: 69.9 | AF51: =622+337.6 -> 959.6 | AI51: =SUM(D51:AG51) -> 2183.5
C52: Repasse Restaurante | AI52: =SUM(D52:AG52) -> 0
C53: Serviço Lavanderia | R53: =14977.99 -> 14977.99 | AI53: =SUM(D53:AE53) -> 14977.99
C54: Assessoria Jurídica/Contábil e Auditoria | K54: =900.36 -> 900.36 | AF54: 3180 | AI54: =SUM(D54:AF54) -> 4080.36
C55: Serviços Postais e de Entrega Rápida | K55: =585.9 -> 585.9 | AF55: 425.65 | AI55: =SUM(D55:AG55) -> 1011.55
C56: Aluguel de Equipamentos | AI56: =SUM(D56:AG56) -> 0
C57: Cópias e Autenticações | AI57: =SUM(D57:AG57) -> 0
C58: Ornamentação | AI58: =SUM(D58:AG58) -> 0
C59: Serviços Contratados PJ | I59: =7950+3500 -> 11450 | M59: =720 -> 720 | P59: =3693.75+1590 -> 5283.75 | R59: =1444+614+359.2+720 -> 3137.2 | W59: 816 | AI59: =SUM(F59:AG59) -> 21406.95
C60: Outros Serviços Contratados | AI60: =SUM(D60:AG60) -> 0
C61: Material de Manutenção / Pintura | AI61: =SUM(D61:AG61) -> 0
C62: Custo Ar Condicionado | Y62: 4212 | AI62: =SUM(D62:AG62) -> 4212
C63: Material de Limpeza | AI63: =SUM(D63:AG63) -> 0
C64: Material de Apartamento | D64: 300 | I64: =1161.72 -> 1161.72 | M64: =301 -> 301 | T64: =190.87 -> 190.87 | AF64: =2863.6 -> 2863.6 | AI64: =SUM(D64:AG64) -> 4817.19
C65: Material de Escritório/Serviços Gráficos | K65: =164.7+164.7 -> 329.4 | T65: 170.2 | AD65: =918 -> 918 | AI65: =SUM(D65:AG65) -> 1417.6
C66: Seguro Responsabilidade Civil | AI66: =SUM(D66:AG66) -> 0
C67: Despesa Viagens e Estadias | I67: =397.43 -> 397.43 | M67: 364.08 | R67: =411.31+401.66 -> 812.97 | AI67: =SUM(D67:AG67) -> 1574.48
C68: Reembolso KM | P68: 192.44 | Y68: 241.64 | AD68: 145.07 | AI68: =SUM(D68:AG68) -> 579.15
C69: Promoção de Vendas | I69: =278.95 -> 278.95 | K69: =358.9 -> 358.9 | M69: =793 -> 793 | R69: =894.4 -> 894.4 | AA69: 1750 | AD69: =500+300 -> 800 | AF69: =300+1620 -> 1920 | AI69: =SUM(D69:AG69) -> 6795.25
C70: Associação de Classe | I70: =270.73+201 -> 471.73 | AI70: =SUM(D70:AG70) -> 471.73
C71: Gastos Diversos | AI71: =SUM(D71:AG71) -> 0
C72: Despesas Bancárias | D72: =66.99+34.2 -> 101.19 | E72: =11.82+84 -> 95.82 | I72: =90.09 -> 90.09 | J72: =47.28 -> 47.28 | K72: 7.9 | L72: =92.4+11.82 -> 104.22 | M72: =7.9*3 -> 23.7 | P72: =(7.9*2) -> 15.8 | Q72: 29.55 | R72: =131.67+11.82+45+(7.9*3) -> 212.19 | S72: =2.31+3.21 -> 5.52 | T72: =64.68+7.9 -> 72.58 | W72: =687.3 -> 687.3 | Y72: =(7.9*2)+80.85+47.28 -> 143.93 | Z72: =18.48+23.64 -> 42.12 | AD72: =(7.9*2)+30.03 -> 45.83 | AE72: =(7.9*2)+94.56 -> 110.36 | AF72: =(7.9*3)+92.4+17.73 -> 133.83 | AG72: =2.31+3.21+29.55+7.9+7.9 -> 50.87 | AI72: =SUM(D72:AG72) -> 2020.08
C73: Cheques Não Compesados | AI73: =SUM(D73:AG73) -> 0
C74: Total de Serviços Contratados e Terceirizados | D74: =-SUM(D41:D73) -> -8377.77 | E74: =-SUM(E41:E73) -> -95.82 | F74: =-SUM(F41:F73) -> 0 | G74: =-SUM(G41:G73) -> 0 | H74: =-SUM(H41:H73) -> 0 | I74: =-SUM(I41:I73) -> -63896.42 | J74: =-SUM(J41:J73) -> -47.28 | K74: =-SUM(K41:K73) -> -6410.05 | ... AI74: =-SUM(AI41:AI73) -> -845699.07
C75: TOTAL DAS SAÍDAS | D75: =D25+D36+D40+D74 -> -8377.77 | E75: =E25+E36+E40+E74 -> -95.82 | F75: =F25+F36+F40+F74 -> 0 | G75: =G25+G36+G40+G74 -> 0 | H75: =H25+H36+H40+H74 -> 0 | I75: =I25+I36+I40+I74 -> -79316.46 | J75: =J25+J36+J40+J74 -> -47.28 | K75: =K25+K36+K40+K74 -> -6410.05 | ... AI75: =AI25+AI36+AI40+AI74 -> -1394691
C77: SALDO DA CONTA CORRENTE | D77: =D6+D18+D75 -> 176160.08 | E77: =E6+E18+E75 -> 230701.58 | F77: =F6+F18+F75 -> 230701.58 | G77: =G6+G18+G75 -> 230701.58 | H77: =H6+H18+H75 -> 230701.58 | I77: =I6+I18+I75 -> 222645.17 | J77: =J6+J18+J75 -> 286827.07 | K77: =K6+K18+K75 -> 313495.48 | ... AI77: =AI6+AI18+AI75 -> 26437.649
B78: APLICAÇÕES
C79: APLICAÇÕES | D79: =Março!AG83 -> 652721.88 | E79: =D83 -> 652932.07 | F79: =E83 -> 653194.69 | G79: =F83 -> 653194.69 | H79: =G83 -> 653194.69 | I79: =H83 -> 653194.69 | J79: =I83 -> 653413.71 | K79: =J83 -> 653634.98 | L79: =K83 -> 653846.44 | ... AH79: =AG83 -> 512460.56
C80: Fundo Reserva | AI80: =SUM(D80:AG80) -> 0
C81: Dividendos a Pagar | W81: -20000 | AF81: -125000 | AI81: =SUM(D81:AG81) -> -145000
C82: Rendimentos de Aplicações | D82: 210.19 | E82: 262.62 | I82: 219.02 | J82: 221.27 | K82: 211.46 | L82: 211.49 | M82: 223.37 | P82: 214.94 | Q82: 217.93 | R82: 217.33 | S82: 218.45 | T82: 236.41 | W82: 425.91 | Y82: 218.54 | Z82: 377.15 | AA82: 243.04 | AD82: 223.88 | AE82: 225.14 | AF82: 177 | AG82: 183.54 | AI82: =SUM(D82:AG82) -> 4738.68
C83: SALDO DAS APLICAÇÕES | D83: =SUM(D80:D82)+D79 -> 652932.07 | E83: =SUM(E80:E82)+D83 -> 653194.69 | F83: =SUM(F80:F82)+E83 -> 653194.69 | G83: =SUM(G80:G82)+F83 -> 653194.69 | H83: =SUM(H80:H82)+G83 -> 653194.69 | I83: =SUM(I80:I82)+H83 -> 653413.71 | J83: =SUM(J80:J82)+I83 -> 653634.98 | K83: =SUM(K80:K82)+J83 -> 653846.44 | L83: =SUM(L80:L82)+K83 -> 654057.93 | ... AH83: =SUM(AH80:AH82)+AG83 -> 512460.56 | AI83: =AH83 -> 512460.56
C85: SALDO TOTAL | D85: =D77+D83 -> 829092.15 | E85: =E77+E83 -> 883896.27 | F85: =F77+F83 -> 883896.27 | G85: =G77+G83 -> 883896.27 | H85: =H77+H83 -> 883896.27 | I85: =I77+I83 -> 876058.88 | J85: =J77+J83 -> 940462.05 | K85: =K77+K83 -> 967341.92 | ... AI85: =AI77+AI83 -> 538898.21
C87: RESUMO DO DIA
C88: DATA ATUAL: | D88: =AG5 -> 42124
C89: SALDO INICIAL: | D89: =AG6 -> 1201.9687
C90: ENTRADA PREVISTA: | D90: =AG18 -> 65286.55
C91: SAÍDA PREVISTA: | D91: =AG75 -> -40050.87
C92: SALDO PREVISTO C/C: | D92: =SUM(D89:D91) -> 26437.649 | L92: Financeiro | S92: G. Financeiro | Y92: Gerente Geral
C93: ADIANTAMENTO CLIENTES | D93: 12036.9
C94: ADIANTAMENTO DIVIDENDOS | D94: 3659.38
C95: FUNDO REPOSIÇÃO ATIVOS: | D95: 496580.74
C96: SALDO FINAL PREVISTO: | D96: =SUM(D92:D95) -> 538714.67

Sheet Maio
B2: Fluxo de Caixa de Maio de 2015
B4: ÍTEM / DESCRIÇÃO | D4: PREVISTO | E4: PREVISTO | F4: PREVISTO | G4: Realizado | H4: Realizado | I4: Realizado | J4: Realizado | K4: Realizado | L4: PREVISTO | M4: PREVISTO | N4: Realizado | O4: Realizado | P4: Realizado | Q4: Realizado | R4: Realizado | S4: PREVISTO | T4: PREVISTO | U4: Realizado | V4: Realizado | W4: Realizado | X4: Realizado | Y4: Realizado | Z4: PREVISTO | AA4: PREVISTO | AB4: Realizado | AC4: Realizado | AD4: Realizado | AE4: Realizado | AF4: Realizado | AG4: PREVISTO | AH4: PREVISTO
D5: 42125 | E5: =D5+1 -> 42126 | F5: =E5+1 -> 42127 | G5: =F5+1 -> 42128 | H5: =G5+1 -> 42129 | I5: =H5+1 -> 42130 | J5: =I5+1 -> 42131 | K5: =J5+1 -> 42132 | L5: =K5+1 -> 42133 | ... AH5: =AG5+1 -> 42155 | AI5: ACUMULADO
C6: SALDO ANTERIOR DA CONTA CORRENTE | D6: =Abril!AG77 -> 26437.649 | E6: =D77 -> 26437.649 | F6: =E77 -> 26437.649 | G6: =F77 -> 26437.649 | H6: =G77 -> 37345.819 | I6: =H77 -> 115064.37 | J6: =I77 -> 48953.569 | K6: =J77 -> 131426.74 | L6: =K77 -> 80839.179 | ... AH6: =AG77 -> 32489.369 | AI6: =D6 -> 26437.649
B7: ENTRADAS | C7: Adiantamento de Clientes | G7: =157+1774.85+456 -> 2387.85 | H7: =199.5+157+902.75+684+160+434+187 -> 2724.25 | I7: =1421+157+1500 -> 3078 | N7: =1144.5+2047.5+346+270 -> 3808 | O7: =157 -> 157 | P7: =1966.1+46.3 -> 2012.4 | Q7: 5670 | R7: =2000 -> 2000 | U7: =443.62+172 -> 615.62 | V7: =302.4+3201.45+157+500 -> 4160.85 | X7: =610 -> 610 | Y7: =2000+530 -> 2530 | AB7: =500+30.5+250 -> 780.5 | AC7: =10840+735 -> 11575 | AE7: =1310.4+4830 -> 6140.4 | AF7: =1620+1753.11+490+887.25 -> 4750.36 | AI7: =SUM(D7:AG7) -> 53000.23
C8: Depósito RDS | N8: =274.5+425.3+448.72+470+540.9+664.45+701.7+1023.77+1121.38+1649.05+1842.9 -> 9162.67 | W8: =2638.45+446+496.17+522.92+674.35+1251.55+1562.7+1611.2+1856.55+2423.45 -> 13483.34 | AE8: =761.28+882.85+51+343.78+425.75+855.33+1200.1+2176 -> 6696.09 | AI8: =SUM(D8:AG8) -> 29342.1
C9: Crédito Não Identificado | AI9: =SUM(D9:AG9) -> 0
C10: Fundo de Reserva | W10: =13248.56+9805.58+12258.24+11231.77+6455.85 -> 53000 | AI10: =SUM(D10:AG10) -> 53000
C11: Faturas | G11: =50030.45+1734.03+330.75+1323+9081.45 -> 62499.68 | H11: =6628.75+57027.68+760.2 -> 64416.63 | I11: =423.15+1584.64+15594.6+11578.7 -> 29181.09 | J11: =9234.59+22747.78+9478.72+4040.41+4491.28+6002.01+1162.67+415.8 -> 57573.26 | K11: 5510.01 | N11: =20481.33 -> 20481.33 | O11: =48143.7 -> 48143.7 | P11: =5416.55+16258.24 -> 21674.79 | Q11: =1+16233.08 -> 16234.08 | R11: =9860.4+2079 -> 11939.4 | U11: =10022.95+422.25+215.6 -> 10660.8 | V11: =5793.18+41612.12+351.75+728.7+578.45+330.75 -> 49394.95 | W11: =606.33+5750.64+280.7 -> 6637.67 | X11: =622+1362.9 -> 1984.9 | Y11: =496.29+3735.92+397.95+8460.9+900.9+532 -> 14523.96 | AB11: =2574.35+634.2+351.75+1268.4 -> 4828.7 | AC11: =5566.85+30672.65+598.98+588 -> 37426.48 | AD11: =1066.08+588+693+4192.93+798 -> 7338.01 | AE11: =2381.48+1318.98+220.5+1493.12+207.9+294+693 -> 6608.98 | AF11: =1157.3+1375.84+294+882+3391.5+1206.4+215.96+611.8+588 -> 9722.8 | AI11: =SUM(D11:AG11) -> 486781.22
C12: Receitas Diversas | G12: 0.71 | H12: 2.14 | I12: 0.93 | J12: 2.49 | K12: 1.54 | N12: 1.94 | O12: 3.25 | P12: 3.57 | Q12: 4.29 | R12: 4.44 | U12: 3.47 | V12: 4.57 | W12: 0.14 | X12: 0.62 | Y12: 0.78 | AB12: =70.2+0.58 -> 70.78 | AC12: 1.81 | AD12: 1.79 | AE12: 2.62 | AF12: 0.62 | AI12: =SUM(D12:AG12) -> 112.5
C13: Amex | G13: 2164.77 | H13: 1308.59 | I13: 1531.59 | J13: 9840.72 | K13: 1227.83 | N13: 5289.62 | O13: 9945.46 | P13: 5654.72 | Q13: 2185.81 | R13: 461.45 | U13: 4394.14 | V13: 339.79 | X13: 969.75 | Y13: 2953.65 | AB13: 4160.17 | AC13: 1745.85 | AD13: 956.73 | AE13: 1809.94 | AF13: 2224.36 | AI13: =SUM(D13:AG13) -> 59164.94
C14: Visa Electron | G14: 3004.29 | H14: 2359.29 | I14: 211.9 | J14: 193.18 | K14: 1746.33 | N14: 2484.04 | O14: 396.7 | P14: 2255.84 | Q14: 1033.1 | R14: 255.51 | U14: 4920.11 | V14: 1125.58 | W14: 3259.75 | X14: 1740.57 | Y14: 1631.83 | AB14: 1148.48 | AC14: 1458.53 | AD14: 1214.2 | AE14: 532.29 | AF14: 1510.75 | AI14: =SUM(D14:AG14) -> 32482.27
C15: Master Débito | G15: =1829.23+13.74 -> 1842.97 | H15: 1204 | I15: =3.92+1302.25 -> 1306.17 | J15: 161.7 | K15: 59.81 | N15: =1324.47+43.71 -> 1368.18 | O15: =865.42+254.48 -> 1119.9 | P15: =2143.91+283.47 -> 2427.38 | Q15: =134.81+21.58 -> 156.39 | R15: =380.6+164.15 -> 544.75 | U15: =2405.35+68 -> 2473.35 | V15: =88.75 -> 88.75 | W15: =177.52+115.88 -> 293.4 | X15: 761.85 | Y15: =869.73+14.72 -> 884.45 | AB15: 1791.75 | AC15: =96.85+91.84 -> 188.69 | AD15: =1136.33+288.47 -> 1424.8 | AE15: 261.25 | AF15: =2184.63+14.72 -> 2199.35 | AI15: =SUM(D15:AG15) -> 20558.89
C16: Visa Crédito | G16: 22041.56 | H16: 4408.06 | I16: 11964.4 | J16: 12833.73 | K16: 10062 | N16: 22737.17 | O16: 5779.84 | P16: 24281.66 | Q16: 10387.02 | R16: 4196.41 | U16: 18690.15 | V16: 5568.64 | W16: 8453.17 | X16: 12711.99 | Y16: 10640.24 | AB16: 30823.76 | AC16: 7509.77 | AD16: 8623.24 | AE16: 12855.86 | AF16: 15150.51 | AI16: =SUM(D16:AG16) -> 259719.18
C17: Master Crédito | G17: 20137.5 | H17: 1497.01 | I17: 991.6 | J17: 1994.82 | K17: 4124.68 | N17: 12910.68 | O17: 1168.93 | P17: 3719.08 | Q17: 1940.71 | R17: 1625.12 | U17: 20084.56 | V17: 2035.25 | W17: 3256.96 | X17: 6053.53 | Y17: 3195.16 | AB17: 11506.09 | AC17: 3780.13 | AD17: 2750.92 | AE17: 7712.84 | AF17: 514.31 | AI17: =SUM(D17:AG17) -> 110999.88
C18: TOTAL DAS ENTRADAS | D18: =SUM(D7:D17) -> 0 | E18: =SUM(E7:E17) -> 0 | F18: =SUM(F7:F17) -> 0 | G18: =SUM(G7:G17) -> 114079.33 | H18: =SUM(H7:H17) -> 77919.97 | I18: =SUM(I7:I17) -> 48265.68 | J18: =SUM(J7:J17) -> 82599.9 | K18: =SUM(K7:K17) -> 22732.2 | ... AH18: =SUM(AH7:AH17) -> 0 | AI18: =SUM(D18:AG18) -> 1105161.2
C19: Repasse Salários e Encargos | I19: 6606.47 | K19: 1621.6 | AI19: =SUM(D19:AF19) -> 8228.07
B20: SAIDAS | C20: Repasse Aluguel de Salas e Equipamentos | AI20: =SUM(D20:AG20) -> 0
C21: Repasse A&B | G21: =47073.66+2090+15000 -> 64163.66 | I21: 18637 | U21: =415.2+910.8+1942.45+33930+42395.09 -> 79593.54 | AF21: =(33539+514.8+36444.14)-4555.68 -> 65942.26 | AI21: =SUM(D21:AG21) -> 228336.46
C22: Repasse Telefonia | AI22: =SUM(D22:AG22) -> 0
C23: Repasse Internet | AI23: =SUM(D23:AG23) -> 0
C24: Repasse Diversos | K24: =968.31+261.21 -> 1229.52 | AI24: =SUM(D24:AG24) -> 1229.52
C25: Repasse ao Condomínio | D25: =-SUM(D19:D24) -> 0 | E25: =-SUM(E19:E24) -> 0 | F25: =-SUM(F19:F24) -> 0 | G25: =-SUM(G19:G24) -> -64163.66 | H25: =-SUM(H19:H24) -> 0 | I25: =-SUM(I19:I24) -> -25243.47 | J25: =-SUM(J19:J24) -> 0 | K25: =-SUM(K19:K24) -> -2851.12 | ... AI25: =-SUM(AI19:AI24) -> -237794.05
C26: Impostos Lei 10.833 | AI26: =SUM(D26:AG26) -> 0
C27: IRRF | U27: =59.69+12.36+59.45+26.7+56.25+286.73+55.02+29.87 -> 586.07 | AI27: =SUM(D27:AG27) -> 586.07
C28: ISS a Recolher | K28: 55810.06 | AI28: =SUM(D28:AG28) -> 55810.06
C29: ISS Retido a Recolher | AI29: =SUM(D29:AG29) -> 0
C30: INSS Retido a Recolher | AI30: =SUM(D30:AG30) -> 0
C31: IPTU a Pagar | K31: 13381.47 | AB31: =70.46 -> 70.46 | AF31: 11466.76 | AI31: =SUM(D31:AG31) -> 24918.69
C32: PIS a Recolher | AB32: 4548.29 | AI32: =SUM(D32:AG32) -> 4548.29
C33: COFINS a Recolher | AB33: 21158.47 | AI33: =SUM(D33:AG33) -> 21158.47
C34: IRPJ a Recolher | AI34: =SUM(D34:AG34) -> 0
C35: CSLL a Recolher | AI35: =SUM(D35:AG35) -> 0
C36: Total de Impostos | D36: =-SUM(D26:D35) -> 0 | E36: =-SUM(E26:E35) -> 0 | F36: =-SUM(F26:F35) -> 0 | G36: =-SUM(G26:G35) -> 0 | H36: =-SUM(H26:H35) -> 0 | I36: =-SUM(I26:I35) -> 0 | J36: =-SUM(J26:J35) -> 0 | K36: =-SUM(K26:K35) -> -69191.53 | ... AI36: =-SUM(AI26:AI35) -> -107021.58
C37: Água e Esgoto | AI37: =SUM(D37:AG37) -> 0
C38: Energia Elétrica | I38: =22294.37 -> 22294.37 | K38: 12.92 | P38: 106.06 | AI38: =SUM(D38:AG38) -> 22413.35
C39: Telefone | AI39: =SUM(D39:AG39) -> 0
C40: Total de Contas de Consumo | D40: =-SUM(D37:D39) -> 0 | E40: =-SUM(E37:E39) -> 0 | F40: =-SUM(F37:F39) -> 0 | G40: =-SUM(G37:G39) -> 0 | H40: =-SUM(H37:H39) -> 0 | I40: =-SUM(I37:I39) -> -22294.37 | J40: =-SUM(J37:J39) -> 0 | K40: =-SUM(K37:K39) -> -12.92 | ... AI40: =-SUM(AI37:AI39) -> -22413.35
C41: Adiantamento Dividendos | G41: =2574.48+2585.49 -> 5159.97 | W41: =270300.17-1736.75 -> 268563.42 | AI41: =SUM(D41:AG41) -> 273723.39
C42: Fundo de Reserva | Y42: 19173.37 | AF42: 20000 | AI42: =SUM(D42:AF42) -> 39173.37
C43: Adiantamento a Fornecedor | U43: 5000 | W43: 24500 | AB43: 25500 | AD43: 18000 | AF43: 42000 | AI43: =SUM(D43:AG43) -> 115000
C44: Gastos Gerais do Proprietário | AI44: =SUM(D44:AG44) -> 0
C45: Taxa de Condomínio | G45: 5000 | I45: 40676.09 | N45: 27352.78 | P45: 43631.85 | U45: 9976.24 | AI45: =SUM(D45:AG45) -> 126636.96
C46: Taxa de Processamento / Administração / Reservas | N46: =7919.79+16621.51 -> 24541.3 | W46: =31842.07 -> 31842.07 | AB46: =1790 -> 1790 | AI46: =SUM(D46:AG46) -> 58173.37
C47: Despesa Comissão Agências de Viagens | G47: =198+40.3+33+166.88 -> 438.18 | I47: =37.5+(153.13+612.52+14155.72) -> 14958.87 | J47: 120.82 | K47: =82.69+53.79 -> 136.48 | P47: 563 | R47: =34.2 -> 34.2 | U47: =898.74+14183.19 -> 15081.93 | Y47: =70.2+3578.06 -> 3648.26 | AB47: =72.4 -> 72.4 | AD47: =865.5+70.2 -> 935.7 | AF47: =70.87+96.6 -> 167.47 | AI47: =SUM(D47:AG47) -> 36157.31
C48: Serviço Prestado Gerente Geral | I48: =7464.97 -> 7464.97 | AB48: =8062.17 -> 8062.17 | AI48: =SUM(E48:AF48) -> 15527.14
C49: Repasse Salário Vendas | AI49: =SUM(D49:AG49) -> 0
C50: Custo Livros/Jornais/Revistas | R50: 122.5 | AB50: =153.9 -> 153.9 | AI50: =SUM(D50:AG50) -> 276.4
C51: Custo com Hospedes | Y51: =409.5+410 -> 819.5 | AE51: 349.85 | AI51: =SUM(D51:AG51) -> 1169.35
C52: Repasse Restaurante | AI52: =SUM(D52:AG52) -> 0
C53: Serviço Lavanderia | G53: 11552.45 | R53: 9971.51 | AI53: =SUM(D53:AF53) -> 21523.96
C54: Assessoria Jurídica/Contábil e Auditoria | K54: =900.36 -> 900.36 | AI54: =SUM(D54:AF54) -> 900.36
C55: Serviços Postais e de Entrega Rápida | K55: 219.45 | AF55: =1724.9 -> 1724.9 | AI55: =SUM(D55:AG55) -> 1944.35
C56: Aluguel de Equipamentos | AI56: =SUM(D56:AG56) -> 0
C57: Cópias e Autenticações | R57: 23.7 | AI57: =SUM(D57:AG57) -> 23.7
C58: Ornamentação | AI58: =SUM(D58:AG58) -> 0
C59: Serviços Contratados PJ | G59: =3500+7950 -> 11450 | I59: =3693.75 -> 3693.75 | N59: =720+350.42+1590 -> 2660.42 | Y59: =180 -> 180 | AB59: =681.5 -> 681.5 | AI59: =SUM(F59:AG59) -> 18665.67
C60: Outros Serviços Contratados | AI60: =SUM(D60:AG60) -> 0
C61: Material de Manutenção / Pintura | AI61: =SUM(D61:AG61) -> 0
C62: Custo Ar Condicionado | AB62: 4212 | AI62: =SUM(D62:AG62) -> 4212
C63: Material de Limpeza | G63: =1372.5+1003 -> 2375.5 | AB63: =505.1+157.5 -> 662.6 | AF63: =549 -> 549 | AI63: =SUM(D63:AG63) -> 3587.1
C64: Material de Apartamento | G64: =1161.72+1161.37 -> 2323.09 | P64: 137.65 | AD64: =1512+285 -> 1797 | AI64: =SUM(D64:AG64) -> 4257.74
C65: Material de Escritório/Serviços Gráficos | U65: =217.05 -> 217.05 | AB65: 2286.15 | AI65: =SUM(D65:AG65) -> 2503.2
C66: Seguro Responsabilidade Civil | AI66: =SUM(D66:AG66) -> 0
C67: Despesa Viagens e Estadias | U67: =526.38+1000+866.83 -> 2393.21 | AI67: =SUM(D67:AG67) -> 2393.21
C68: Reembolso KM | U68: 18.67 | AI68: =SUM(D68:AG68) -> 18.67
C69: Promoção de Vendas | G69: =457.83 -> 457.83 | R69: =1444+359.2+614 -> 2417.2 | U69: 816 | AI69: =SUM(D69:AG69) -> 3691.03
C70: Associação de Classe | G70: 201 | P70: 383.18 | AI70: =SUM(D70:AG70) -> 584.18
C71: Gastos Diversos | AI71: =SUM(D71:AG71) -> 0
C72: Despesas Bancárias | G72: =41.58+7.9 -> 49.48 | H72: =4.62+6.42+106.38+84 -> 201.42 | I72: 44.96 | J72: =5.91 -> 5.91 | K72: =7.9 -> 7.9 | O72: 29.55 | P72: =11.82+7.9 -> 19.72 | Q72: =2.31+3.21+29.55 -> 35.07 | R72: 45 | U72: =(7.9*4)+13.86+19.26 -> 64.72 | V72: =11.55+16.05+23.64 -> 51.24 | W72: =710.18 -> 710.18 | Y72: =(7.9*4)+4.62+6.42 -> 42.64 | AB72: =(7.9*2)+11.55+16.05 -> 43.4 | AC72: =18.48+25.68+11.82 -> 55.98 | AD72: =11.82+6.42+4.62 -> 22.86 | AE72: =6.93+9.63+11.82 -> 28.38 | AF72: =(7.9*2)+4.62+6.42 -> 26.84 | AI72: =SUM(D72:AG72) -> 1485.25
C73: Cheques Não Compesados | W73: 252.8 | AI73: =SUM(D73:AG73) -> 252.8
C74: Total de Serviços Contratados e Terceirizados | D74: =-SUM(D41:D73) -> 0 | E74: =-SUM(E41:E73) -> 0 | F74: =-SUM(F41:F73) -> 0 | G74: =-SUM(G41:G73) -> -39007.5 | H74: =-SUM(H41:H73) -> -201.42 | I74: =-SUM(I41:I73) -> -66838.64 | J74: =-SUM(J41:J73) -> -126.73 | K74: =-SUM(K41:K73) -> -1264.19 | ... AI74: =-SUM(AI41:AI73) -> -731880.51
C75: TOTAL DAS SAÍDAS | D75: =D25+D36+D40+D74 -> 0 | E75: =E25+E36+E40+E74 -> 0 | F75: =F25+F36+F40+F74 -> 0 | G75: =G25+G36+G40+G74 -> -103171.16 | H75: =H25+H36+H40+H74 -> -201.42 | I75: =I25+I36+I40+I74 -> -114376.48 | J75: =J25+J36+J40+J74 -> -126.73 | K75: =K25+K36+K40+K74 -> -73319.76 | ... AI75: =AI25+AI36+AI40+AI74 -> -1099109.5
C77: SALDO DA CONTA CORRENTE | D77: =D6+D18+D75 -> 26437.649 | E77: =E6+E18+E75 -> 26437.649 | F77: =F6+F18+F75 -> 26437.649 | G77: =G6+G18+G75 -> 37345.819 | H77: =H6+H18+H75 -> 115064.37 | I77: =I6+I18+I75 -> 48953.569 | J77: =J6+J18+J75 -> 131426.74 | K77: =K6+K18+K75 -> 80839.179 | ... AI77: =AI6+AI18+AI75 -> 32489.369
B78: APLICAÇÕES
C79: APLICAÇÕES | D79: =Abril!AG83 -> 512460.56 | E79: =D83 -> 512460.56 | F79: =E83 -> 512460.56 | G79: =F83 -> 512460.56 | H79: =G83 -> 512759.4 | I79: =H83 -> 512943.75 | J79: =I83 -> 513128.11 | K79: =J83 -> 513312.61 | L79: =K83 -> 513497.18 | ... AH79: =AG83 -> 502504.81
C80: Fundo Reserva | W80: -53000 | Y80: =Y42 -> 19173.37 | AF80: =AF42 -> 20000 | AI80: =SUM(G80:AF80) -> -13826.63
C81: Dividendos a Pagar | AI81: =SUM(G81:AF81) -> 0
C82: Rendimentos de Aplicações | G82: 298.84 | H82: 184.35 | I82: 184.36 | J82: 184.5 | K82: 184.57 | N82: 184.64 | O82: 184.71 | P82: 184.79 | Q82: 184.89 | R82: 184.92 | U82: 185.08 | V82: 185.11 | W82: 163.78 | X82: 163.87 | Y82: 164.55 | AB82: 355.21 | AC82: 166.35 | AD82: 166.79 | AE82: 188.68 | AF82: 170.89 | AI82: =SUM(G82:AF82) -> 3870.88
C83: SALDO DAS APLICAÇÕES | D83: =SUM(D80:D82)+D79 -> 512460.56 | E83: =SUM(E80:E82)+D83 -> 512460.56 | F83: =SUM(F80:F82)+E83 -> 512460.56 | G83: =SUM(G80:G82)+F83 -> 512759.4 | H83: =SUM(H80:H82)+G83 -> 512943.75 | I83: =SUM(I80:I82)+H83 -> 513128.11 | J83: =SUM(J80:J82)+I83 -> 513312.61 | K83: =SUM(K80:K82)+J83 -> 513497.18 | L83: =SUM(L80:L82)+K83 -> 513497.18 | ... AH83: =SUM(AH80:AH82)+AG83 -> 502504.81 | AI83: =AH83 -> 502504.81
C85: SALDO TOTAL | D85: =D77+D83 -> 538898.21 | E85: =E77+E83 -> 538898.21 | F85: =F77+F83 -> 538898.21 | G85: =G77+G83 -> 550105.22 | H85: =H77+H83 -> 628008.12 | I85: =I77+I83 -> 562081.68 | J85: =J77+J83 -> 644739.35 | K85: =K77+K83 -> 594336.36 | ... AI85: =AI77+AI83 -> 534994.18
C87: RESUMO DO DIA
C88: DATA ATUAL: | G88: =AF5 -> 42153
C89: SALDO INICIAL: | G89: =AF6 -> 138293.54
C90: ENTRADA PREVISTA: | G90: =AF18 -> 36073.06
C91: SAÍDA PREVISTA: | G91: =AF75 -> -141877.23
C92: SALDO PREVISTO C/C: | G92: =SUM(G89:G91) -> 32489.369 | O92: Financeiro | U92: Gerente Financeiro | Y92: Gerente Geral
C93: ADIANTAMENTO CLIENTES | G93: =12123.72 -> 12123.72
C94: ADIANTAMENTO DIVIDENDOS | G94: 3682.84
C95: FUNDO REPOSIÇÃO ATIVOS: | G95: 466527.36
C96: SALDO FINAL PREVISTO: | G96: =SUM(G92:G95) -> 514823.29

Sheet Junho
B2: Fluxo de Caixa de Junho de 2015
B4: ÍTEM / DESCRIÇÃO | D4: Realizado | E4: Realizado | F4: Realizado | G4: PREVISTO | H4: Realizado | I4: PREVISTO | J4: PREVISTO | K4: Realizado | L4: Realizado | M4: Realizado | N4: Realizado | O4: Realizado | P4: PREVISTO | Q4: PREVISTO | R4: Realizado | S4: Realizado | T4: Realizado | U4: Realizado | V4: Realizado | W4: PREVISTO | X4: PREVISTO | Y4: Realizado | Z4: Realizado | AA4: Realizado | AB4: Realizado | AC4: Realizado | AD4: PREVISTO | AE4: PREVISTO | AF4: Realizado | AG4: Realizado | AH4: PREVISTO
D5: 42156 | E5: =D5+1 -> 42157 | F5: =E5+1 -> 42158 | G5: =F5+1 -> 42159 | H5: =G5+1 -> 42160 | I5: =H5+1 -> 42161 | J5: =I5+1 -> 42162 | K5: =J5+1 -> 42163 | L5: =K5+1 -> 42164 | ... AH5: =AG5+1 -> 42186 | AI5: ACUMULADO
C6: SALDO ANTERIOR DA CONTA CORRENTE | D6: =Maio!AF77 -> 32489.369 | E6: =D77 -> 66941.619 | F6: =E77 -> 107903.77 | G6: =F77 -> 116423.69 | H6: =G77 -> 116423.69 | I6: =H77 -> 121304.9 | J6: =I77 -> 121304.9 | K6: =J77 -> 121304.9 | L6: =K77 -> 197642 | ... AH6: =AG77 -> 118497.17 | AI6: =D6 -> 32489.369
B7: ENTRADAS | C7: Adiantamento de Clientes | D7: =514+300+246 -> 1060 | E7: =945+450 -> 1395 | F7: =218.92 -> 218.92 | H7: =156.95+294 -> 450.95 | K7: =1549.8+945+157 -> 2651.8 | L7: =700+187 -> 887 | M7: =129.15+443.62 -> 572.77 | N7: =200+490.75 -> 690.75 | O7: =645.75+600+6350.4+237 -> 7833.15 | R7: =6350.4 -> 6350.4 | S7: =271.67+710 -> 981.67 | T7: =564.9+346+280+532 -> 1722.9 | U7: =2750 -> 2750 | V7: 171.92 | Y7: 9667.5 | Z7: =630 -> 630 | AB7: =165+275+907.2 -> 1347.2 | AC7: =302.4 -> 302.4 | AF7: =840+2429.2 -> 3269.2 | AG7: 262.5 | AI7: =SUM(D7:AG7) -> 43216.03
C8: Depósito RDS | O8: =1465.25+293.24+395.2+440.2+476.33+592+746.2+927.4+1039.56+1228.64+1319.2+1621+1855+2765.75+5048.2 -> 20213.17 | V8: =1086+157+2578.2+309.9+421.35+478.51+775.2+1752.6+250 -> 7808.76 | AG8: =10+22+519.7+815+816.4+857.95+1242.7+1299.2+1696.98+2346.91+3879.07 -> 13505.91 | AI8: =SUM(D8:AG8) -> 41527.84
C9: Crédito Não Identificado | AI9: =SUM(D9:AG9) -> 0
C10: Fundo de Reserva | U10: 33052.61 | AI10: =SUM(D10:AG10) -> 33052.61
C11: Faturas | D11: =3356.48+2391.56+317.1+317.1+294+588+588+1814.41+872+872+872+6234.9+1796.97+6888.36 -> 27202.88 | E11: =17719.31+247.94+3197.25+3762.22+495.88+1461.46+2266.88 -> 29150.94 | F11: =5090.03+338.1+294+507.16+206+798 -> 7233.29 | H11: =14751.68+574.35+1350+1471.47+215.6+431.2 -> 18794.3 | K11: =10910.69+290.66+3371.18+2325.33+581.33+581.33+1268.4+4065.6+1323+247.94+431.2+2593.92 -> 27990.58 | L11: =6904.63+1080.15+1212+4410+951.3+338.1+3476.95 -> 18373.13 | M11: =4318.42+1011.15+1064+1176 -> 7569.57 | N11: =9979.53+385.35+2509.5+7949.6+294 -> 21117.98 | O11: =4027.69+1412.01+2929.5+2262.75+470.93 -> 11102.88 | R11: =6107.81+221.55+2156+1078+659.12+951.3 -> 11173.78 | S11: =22355.91+47560.37+294+598.5+1541.4+1356.08+929.5+703.5 -> 75339.26 | T11: =6225.2+581.33+588+1753.5+267.75+3197.32+3197.32+1162.66+3197.32+1130+270.27 -> 21570.67 | U11: =426.46+994.35+2833.8 -> 4254.61 | V11: =5998.06+294 -> 6292.06 | Y11: =9768.45+872+636.02+751.8+389.03+753+266+423.06+26.99 -> 13886.35 | Z11: =50693.44+613.75+564.9+595.35+362.25+2142+1667.83+4727.8 -> 61367.32 | AB11: =4035.01+4558.15+389.7+294+1034.1+1335.61+882+1170.75+1170.75+294 -> 15164.07 | AC11: =16598.81+20212.5+294+1129.8+7700.7+1080 -> 47015.81 | AF11: =26190.01+1336.05+8327.3+1239.7 -> 37093.06 | AG11: =24981.84+284.29+882+1704.3 -> 27852.43 | AI11: =SUM(D11:AG11) -> 489544.97
C12: Receitas Diversas | D12: 0.61 | E12: 2.6 | F12: =4555.68+2.19 -> 4557.87 | H12: 2.36 | K12: 3.88 | L12: 4.06 | M12: 2.52 | N12: 3.48 | O12: 4.22 | R12: 2.29 | S12: 4.16 | T12: 3.28 | U12: 4.26 | V12: 1 | Y12: 1.06 | Z12: 2.9 | AB12: 1.14 | AF12: 5.29 | AG12: 2.35 | AI12: =SUM(D12:AG12) -> 4609.33
C13: Amex | D13: 1690.49 | E13: 324.14 | F13: 2863.41 | H13: 7158.93 | K13: 13039.77 | L13: 1673.59 | M13: 1780.14 | N13: 2316.71 | O13: 646.44 | R13: 7197.48 | T13: 3094.08 | U13: 3619.18 | V13: 1493.43 | Y13: 957.54 | Z13: 641.14 | AB13: =3208.56+11851.96 -> 15060.52 | AC13: 1047.68 | AF13: 2703.67 | AG13: 1685.81 | AI13: =SUM(D13:AG13) -> 68994.15
C14: Visa Electron | D14: 7064.51 | E14: 389.39 | F14: 579.16 | H14: 3870.73 | K14: 3184.52 | L14: 917.17 | M14: 665.59 | N14: 283.66 | O14: 3169.53 | R14: 4931.71 | S14: 685.66 | T14: 1432.41 | U14: 725.5 | V14: 2255.1 | Y14: 4826.79 | Z14: 91.25 | AB14: =485.35+1048.1 -> 1533.45 | AC14: 2235.01 | AF14: 3195.84 | AG14: 2173.12 | AI14: =SUM(D14:AG14) -> 44210.1
C15: Master Débito | D15: =4356.33+324.08 -> 4680.41 | F15: 1115.19 | H15: 1493.84 | K15: =2043.2+384.92 -> 2428.12 | L15: =296.28+24.09 -> 320.37 | M15: =1047.72+288.47 -> 1336.19 | N15: 1391.49 | O15: 1505.65 | R15: =1542.6+151.21 -> 1693.81 | T15: 920.28 | U15: 310.89 | V15: 1399.62 | Y15: =1767+593 -> 2360 | Z15: =28.45+849.96+1962.4 -> 2840.81 | AB15: =1161+219.89 -> 1380.89 | AC15: =615.35 -> 615.35 | AF15: =1972.71+1544.63 -> 3517.34 | AG15: 42 | AI15: =SUM(D15:AG15) -> 29352.25
C16: Visa Crédito | D16: 27164.25 | E16: 3809.75 | F16: =14898.44 -> 14898.44 | H16: =9178.07+746.7 -> 9924.77 | K16: 18930.56 | L16: 4549.43 | M16: 14944.56 | N16: 19969.45 | O16: 6576.3 | R16: 26726.32 | S16: 11408.9 | T16: 10986.2 | U16: 10663.76 | V16: 4945.96 | Y16: 27794.27 | Z16: 3529.66 | AB16: =6934.14+4435.42 -> 11369.56 | AC16: =21827.42 -> 21827.42 | AF16: 32674.07 | AG16: =8148.62 -> 8148.62 | AI16: =SUM(D16:AG16) -> 290842.25
C17: Master Crédito | D17: 16261.83 | E17: 6076.03 | F17: 1962.07 | H17: 10825.28 | K17: =15203.87+66.61 -> 15270.48 | L17: 1292.08 | M17: 142.85 | N17: 4944.83 | O17: 995.98 | R17: 11617.24 | S17: 7311.84 | T17: 1043.69 | U17: 1390.19 | V17: 5584.74 | Y17: 7099.52 | Z17: 1719.62 | AB17: =124.61+1520.73+979.16+4813.57 -> 7438.07 | AC17: 5548.02 | AF17: 21412.4 | AG17: =121.77+2785.82 -> 2907.59 | AI17: =SUM(D17:AG17) -> 130844.35
C18: TOTAL DAS ENTRADAS | D18: =SUM(D7:D17) -> 85124.98 | E18: =SUM(E7:E17) -> 41147.85 | F18: =SUM(F7:F17) -> 33428.35 | G18: =SUM(G7:G17) -> 0 | H18: =SUM(H7:H17) -> 52521.16 | I18: =SUM(I7:I17) -> 0 | J18: =SUM(J7:J17) -> 0 | K18: =SUM(K7:K17) -> 83499.71 | ... AH18: =SUM(AH7:AH17) -> 0 | AI18: =SUM(D18:AG18) -> 1176193.9
C19: Repasse Salários e Encargos | H19: =6306.47 -> 6306.47 | AI19: =SUM(D19:AF19) -> 6306.47
B20: SAIDAS | C20: Repasse Aluguel de Salas e Equipamentos | AI20: =SUM(D20:AG20) -> 0
C21: Repasse A&B | F21: =4555.68 -> 4555.68 | R21: =(354.8+48985.77+43530+591.8+947.76)-192.05 -> 94218.08 | Y21: 22087.8 | AF21: =39525.7+565.95+1738 -> 41829.65 | AG21: 70857.87 | AI21: =SUM(D21:AG21) -> 233549.08
C22: Repasse Telefonia | AI22: =SUM(D22:AG22) -> 0
C23: Repasse Internet | AI23: =SUM(D23:AG23) -> 0
C24: Repasse Diversos | AI24: =SUM(D24:AG24) -> 0
C25: Repasse ao Condomínio | D25: =-SUM(D19:D24) -> 0 | E25: =-SUM(E19:E24) -> 0 | F25: =-SUM(F19:F24) -> -4555.68 | G25: =-SUM(G19:G24) -> 0 | H25: =-SUM(H19:H24) -> -6306.47 | I25: =-SUM(I19:I24) -> 0 | J25: =-SUM(J19:J24) -> 0 | K25: =-SUM(K19:K24) -> 0 | ... AI25: =-SUM(AI19:AI24) -> -239855.55
C26: Impostos Lei 10.833 | AI26: =SUM(D26:AG26) -> 0
C27: IRRF | T27: =17.27+54.49+13.18+56.25+215.99 -> 357.18 | AI27: =SUM(D27:AG27) -> 357.18
C28: ISS a Recolher | M28: =44726.78 -> 44726.78 | AI28: =SUM(D28:AG28) -> 44726.78
C29: ISS Retido a Recolher | AI29: =SUM(D29:AG29) -> 0
C30: INSS Retido a Recolher | AI30: =SUM(D30:AG30) -> 0
C31: IPTU a Pagar | L31: 10954.19 | M31: =76.84+13381.47 -> 13458.31 | AI31: =SUM(D31:AG31) -> 24412.5
C32: PIS a Recolher | AB32: 4709.7 | AI32: =SUM(D32:AG32) -> 4709.7
C33: COFINS a Recolher | AB33: 21737.2 | AI33: =SUM(D33:AG33) -> 21737.2
C34: IRPJ a Recolher | AI34: =SUM(D34:AG34) -> 0
C35: CSLL a Recolher | AI35: =SUM(D35:AG35) -> 0
C36: Total de Impostos | D36: =-SUM(D26:D35) -> 0 | E36: =-SUM(E26:E35) -> 0 | F36: =-SUM(F26:F35) -> 0 | G36: =-SUM(G26:G35) -> 0 | H36: =-SUM(H26:H35) -> 0 | I36: =-SUM(I26:I35) -> 0 | J36: =-SUM(J26:J35) -> 0 | K36: =-SUM(K26:K35) -> 0 | ... AI36: =-SUM(AI26:AI35) -> -95943.36
C37: Água e Esgoto | AI37: =SUM(D37:AG37) -> 0
C38: Energia Elétrica | H38: 23107.33 | K38: 14.62 | AI38: =SUM(D38:AG38) -> 23121.95
C39: Telefone | AI39: =SUM(D39:AG39) -> 0
C40: Total de Contas de Consumo | D40: =-SUM(D37:D39) -> 0 | E40: =-SUM(E37:E39) -> 0 | F40: =-SUM(F37:F39) -> 0 | G40: =-SUM(G37:G39) -> 0 | H40: =-SUM(H37:H39) -> -23107.33 | I40: =-SUM(I37:I39) -> 0 | J40: =-SUM(J37:J39) -> 0 | K40: =-SUM(K37:K39) -> -14.62 | ... AI40: =-SUM(AI37:AI39) -> -23121.95
C41: Adiantamento Dividendos | V41: =214905.18-14377.38 -> 200527.8 | Y41: =22062.62+14377.38 -> 36440 | AI41: =SUM(D41:AG41) -> 236967.8
C42: Fundo de Reserva | AI42: =SUM(D42:AF42) -> 0
C43: Adiantamento a Fornecedor | T43: 43000 | Y43: 16000 | AB43: 31000 | AF43: 50000 | AI43: =SUM(D43:AG43) -> 140000
C44: Gastos Gerais do Proprietário | AI44: =SUM(D44:AG44) -> 0
C45: Taxa de Condomínio | D45: 28000 | F45: 15631.85 | H45: 14976.24 | M45: 27352.78 | R45: 40676.09 | AI45: =SUM(D45:AG45) -> 126636.96
C46: Taxa de Processamento / Administração / Reservas | M46: =7919.79+16743.63 -> 24663.42 | V46: 28357.64 | AI46: =SUM(D46:AG46) -> 53021.06
C47: Despesa Comissão Agências de Viagens | D47: =301.2 -> 301.2 | H47: 62.4 | K47: 360.64 | M47: =96.6+1034.64+73.5+73.5+84.52+1134.06 -> 2496.82 | O47: =35 -> 35 | R47: =21.8 -> 21.8 | T47: =(155.41+621.64+17525.01)+246.96+2757.81+42+14515.55+112+152.6 -> 36128.98 | U47: 121.98 | Y47: =32.2+2875.33+153.9 -> 3061.43 | AI47: =SUM(D47:AG47) -> 42590.25
C48: Serviço Prestado Gerente Geral | AI48: =SUM(E48:AF48) -> 0
C49: Repasse Salário Vendas | AI49: =SUM(D49:AG49) -> 0
C50: Custo Livros/Jornais/Revistas | R50: =122.5 -> 122.5 | AI50: =SUM(D50:AG50) -> 122.5
C51: Custo com Hospedes | K51: =132.3+147 -> 279.3 | R51: 6350.4 | T51: =89.8+193.05 -> 282.85 | AI51: =SUM(D51:AG51) -> 6912.55
C52: Repasse Restaurante | AI52: =SUM(D52:AG52) -> 0
C53: Serviço Lavanderia | D53: 9400.31 | R53: 10928.43 | AF53: 10760.79 | AI53: =SUM(D53:AF53) -> 31089.53
C54: Assessoria Jurídica/Contábil e Auditoria | D54: =3180 -> 3180 | R54: =900.36+1109.51 -> 2009.87 | AF54: 3180 | AI54: =SUM(D54:AF54) -> 8369.87
C55: Serviços Postais e de Entrega Rápida | M55: 260.75 | AF55: 262 | AI55: =SUM(D55:AG55) -> 522.75
C56: Aluguel de Equipamentos | AI56: =SUM(D56:AG56) -> 0
C57: Cópias e Autenticações | AI57: =SUM(D57:AG57) -> 0
C58: Ornamentação | AI58: =SUM(D58:AG58) -> 0
C59: Serviços Contratados PJ | D59: 7950 | F59: 3500 | K59: 3693.75 | M59: =720 -> 720 | O59: =1590+120 -> 1710 | R59: =1444+614+359.2 -> 2417.2 | T59: =816 -> 816 | AB59: 4930.41 | AI59: =SUM(F59:AG59) -> 17787.36
C60: Outros Serviços Contratados | AI60: =SUM(D60:AG60) -> 0
C61: Material de Manutenção / Pintura | AI61: =SUM(D61:AG61) -> 0
C62: Custo Ar Condicionado | AB62: 4212 | AI62: =SUM(D62:AG62) -> 4212
C63: Material de Limpeza | M63: 330 | AI63: =SUM(D63:AG63) -> 330
C64: Material de Apartamento | D64: 1161.37 | F64: =1161.37 -> 1161.37 | H64: =1891.63 -> 1891.63 | O64: =420 -> 420 | R64: =14119.71 -> 14119.71 | T64: =5650.8 -> 5650.8 | AB64: =1511+1920 -> 3431 | AF64: =1161.37 -> 1161.37 | AI64: =SUM(D64:AF64) -> 28997.25
C65: Material de Escritório/Serviços Gráficos | D65: 646.73 | K65: 190 | O65: =2286.15 -> 2286.15 | AF65: 255.49 | AI65: =SUM(D65:AG65) -> 3378.37
C66: Seguro Responsabilidade Civil | AI66: =SUM(D66:AG66) -> 0
C67: Despesa Viagens e Estadias | K67: =2500+20.18 -> 2520.18 | O67: =1370.76+2500 -> 3870.76 | R67: =3832.34 -> 3832.34 | U67: 1000 | AI67: =SUM(D67:AG67) -> 11223.28
C68: Reembolso KM | H68: =1058.6 -> 1058.6 | AI68: =SUM(D68:AG68) -> 1058.6
C69: Promoção de Vendas | AI69: =SUM(E69:AG69) -> 0
C70: Associação de Classe | H70: =201 -> 201 | T70: 120.88 | AI70: =SUM(D70:AG70) -> 321.88
C71: Gastos Diversos | V71: =244+80 -> 324 | Y71: 6933.1 | AI71: =SUM(D71:AG71) -> 7257.1
C72: Despesas Bancárias | D72: =13.86+19.26 -> 33.12 | E72: =27.72+38.52+35.46+84 -> 185.7 | F72: =9.24+12.84+29.55+7.9 -> 59.53 | H72: =6.93+9.63+11.82+7.9 -> 36.28 | K72: =36.96+51.36+(7.9*2) -> 104.12 | L72: =32.34+44.94+41.37 -> 118.65 | M72: =18.48+25.68+11.82+(7.9*2) -> 71.78 | N72: =30.03+41.74 -> 71.77 | O72: =(7.9*3)+9.24+12.84 -> 45.78 | R72: =23.1+32.1+7.9+45 -> 108.1 | S72: =39.27+54.57+41.37 -> 135.21 | T72: =(7.9*3)+11.55+16.05+17.73 -> 69.03 | U72: =4.62+6.42+5.91+7.9 -> 24.85 | V72: 731.72 | Y72: 112.12 | Z72: =66.99+93.09+29.55 -> 189.63 | AB72: =6.93+9.63+11.55+16.05+17.73+7.9 -> 69.79 | AC72: =41.73+30.03 -> 71.76 | AF72: =32.34+44.94+7.9+7.9 -> 93.08 | AG72: =41.58+57.78+76.83+7.9 -> 184.09 | AI72: =SUM(D72:AG72) -> 2516.11
C73: Cheques Não Compesados | AI73: =SUM(D73:AG73) -> 0
C74: Total de Serviços Contratados e Terceirizados | D74: =-SUM(D41:D73) -> -50672.73 | E74: =-SUM(E41:E73) -> -185.7 | F74: =-SUM(F41:F73) -> -20352.75 | G74: =-SUM(G41:G73) -> 0 | H74: =-SUM(H41:H73) -> -18226.15 | I74: =-SUM(I41:I73) -> 0 | J74: =-SUM(J41:J73) -> 0 | K74: =-SUM(K41:K73) -> -7147.99 | ... AI74: =-SUM(AI41:AI73) -> -723315.22
C75: TOTAL DAS SAÍDAS | D75: =D25+D36+D40+D74 -> -50672.73 | E75: =E25+E36+E40+E74 -> -185.7 | F75: =F25+F36+F40+F74 -> -24908.43 | G75: =G25+G36+G40+G74 -> 0 | H75: =H25+H36+H40+H74 -> -47639.95 | I75: =I25+I36+I40+I74 -> 0 | J75: =J25+J36+J40+J74 -> 0 | K75: =K25+K36+K40+K74 -> -7162.61 | ... AI75: =AI25+AI36+AI40+AI74 -> -1082236.1
C77: SALDO DA CONTA CORRENTE | D77: =D6+D18+D75 -> 66941.619 | E77: =E6+E18+E75 -> 107903.77 | F77: =F6+F18+F75 -> 116423.69 | G77: =G6+G18+G75 -> 116423.69 | H77: =H6+H18+H75 -> 121304.9 | I77: =I6+I18+I75 -> 121304.9 | J77: =J6+J18+J75 -> 121304.9 | K77: =K6+K18+K75 -> 197642 | ... AI77: =AI6+AI18+AI75 -> 126447.17
B78: APLICAÇÕES
C79: APLICAÇÕES | D79: =Maio!AF83 -> 502504.81 | E79: =D83 -> 502674.51 | F79: =E83 -> 502844.91 | G79: =F83 -> 503019.24 | H79: =G83 -> 503019.24 | I79: =H83 -> 503531.42 | J79: =I83 -> 503531.42 | K79: =J83 -> 503531.42 | L79: =K83 -> 503820.8 | ... AH79: =AG83 -> 474047.87
C80: Fundo Reserva | U80: -33052.61 | AI80: =SUM(G80:AF80) -> -33052.61
C81: Dividendos a Pagar | AI81: =SUM(G81:AF81) -> 0
C82: Rendimentos de Aplicações | D82: 169.7 | E82: 170.4 | F82: 174.33 | H82: 512.18 | K82: 289.38 | L82: 185.26 | M82: 185.88 | N82: 186.33 | O82: 197.8 | R82: 189.77 | S82: 190.53 | T82: 190.66 | U82: 179.25 | V82: 189.2 | Y82: 343 | Z82: 179.8 | AB82: 189.11 | AC82: 182.44 | AF82: 436.45 | AG82: 254.2 | AI82: =SUM(G82:AF82) -> 3827.04
C83: SALDO DAS APLICAÇÕES | D83: =SUM(D80:D82)+D79 -> 502674.51 | E83: =SUM(E80:E82)+D83 -> 502844.91 | F83: =SUM(F80:F82)+E83 -> 503019.24 | G83: =SUM(G80:G82)+F83 -> 503019.24 | H83: =SUM(H80:H82)+G83 -> 503531.42 | I83: =SUM(I80:I82)+H83 -> 503531.42 | J83: =SUM(J80:J82)+I83 -> 503531.42 | K83: =SUM(K80:K82)+J83 -> 503820.8 | L83: =SUM(L80:L82)+K83 -> 504006.06 | ... AH83: =SUM(AH80:AH82)+AG83 -> 474047.87 | AI83: =AH83 -> 474047.87
C85: SALDO TOTAL | D85: =D77+D83 -> 569616.13 | E85: =E77+E83 -> 610748.68 | F85: =F77+F83 -> 619442.93 | G85: =G77+G83 -> 619442.93 | H85: =H77+H83 -> 624836.32 | I85: =I77+I83 -> 624836.32 | J85: =J77+J83 -> 624836.32 | K85: =K77+K83 -> 701462.8 | ... AI85: =AI77+AI83 -> 600495.04
C87: RESUMO DO DIA
C88: DATA ATUAL: | D88: =AG5 -> 42185
C89: SALDO INICIAL: | D89: =AG6 -> 132958.8
C90: ENTRADA PREVISTA: | D90: =AG18 -> 56580.33
C91: SAÍDA PREVISTA: | D91: =AG75 -> -71041.96
C92: SALDO PREVISTO C/C: | D92: =SUM(D89:D91) -> 118497.17 | L92: Financeiro | S92: Gerente Financeiro | Z92: Gerente Geral
C93: ADIANTAMENTO CLIENTES | D93: 12201.32
C94: ADIANTAMENTO DIVIDENDOS | D94: 3709.66
C95: FUNDO REPOSIÇÃO ATIVOS: | D95: 458136.89
C96: SALDO FINAL PREVISTO: | D96: =SUM(D92:D95) -> 592545.04

Sheet Julho
B2: Fluxo de Caixa de Julho de 2015
B4: ÍTEM / DESCRIÇÃO | D4: Realizado | E4: Realizado | F4: Realizado | G4: PREVISTO | H4: PREVISTO | I4: Realizado | J4: Realizado | K4: Realizado | L4: Realizado | M4: Realizado | N4: PREVISTO | O4: PREVISTO | P4: Realizado | Q4: Realizado | R4: Realizado | S4: Realizado | T4: Realizado | U4: PREVISTO | V4: PREVISTO | W4: Realizado | X4: Realizado | Y4: Realizado | Z4: Realizado | AA4: Realizado | AB4: PREVISTO | AC4: PREVISTO | AD4: Realizado | AE4: Realizado | AF4: Realizado | AG4: Realizado | AH4: Realizado
D5: 42186 | E5: =D5+1 -> 42187 | F5: =E5+1 -> 42188 | G5: =F5+1 -> 42189 | H5: =G5+1 -> 42190 | I5: =H5+1 -> 42191 | J5: =I5+1 -> 42192 | K5: =J5+1 -> 42193 | L5: =K5+1 -> 42194 | ... AH5: =AG5+1 -> 42216 | AI5: ACUMULADO
C6: SALDO ANTERIOR DA CONTA CORRENTE | D6: =Junho!AG77 -> 118497.17 | E6: =D77 -> 154858.27 | F6: =E77 -> 163119.87 | G6: =F77 -> 171165.14 | H6: =G77 -> 171165.14 | I6: =H77 -> 171165.14 | J6: =I77 -> 200277.03 | K6: =J77 -> 237625.77 | L6: =K77 -> 310121.76 | ... AH6: =AG77 -> 86930.679 | AI6: =D6 -> 118497.17
B7: ENTRADAS | C7: Adiantamento de Clientes | D7: =404.7+441 -> 845.7 | F7: 294 | I7: =271.76+1980 -> 2251.76 | J7: 172 | K7: =299.25+1120+460 -> 1879.25 | L7: =58.65+850.5 -> 909.15 | M7: =56+263 -> 319 | P7: =1006.95 -> 1006.95 | Q7: =266+588 -> 854 | R7: =588+2500+315 -> 3403 | T7: =12848+507 -> 13355 | W7: =4215.98+220.5 -> 4436.48 | AA7: =873.6+35+882 -> 1790.6 | AD7: =250 -> 250 | AE7: =588 -> 588 | AF7: =23.1 -> 23.1 | AG7: =1500+346+487.3 -> 2333.3 | AH7: =262.5+960+262.5 -> 1485 | AI7: =SUM(D7:AH7) -> 36196.29
C8: Depósito RDS | M8: =152.95+249.96+403+460.85+634.93+1063.3+2219.05 -> 5184.04 | AD8: =102.3+133.85+137.36+203.61+244.13+383.15+418.2+432.2+785.4+985.7+993.74+1066.17+1126+1144.85+2314.5 -> 10471.16 | AH8: =495.39+649.39+743+873.69+966.23+1065.8+2091.85+2763.1 -> 9648.45 | AI8: =SUM(D8:AH8) -> 25303.65
C9: Crédito Não Identificado | AI9: =SUM(D9:AH9) -> 0
C10: Fundo de Reserva | AI10: =SUM(D10:AH10) -> 0
C11: Faturas | D11: =23428.95+309.75+288.75 -> 24027.45 | E11: =3881.85+1470+299.25+1164.98+668.34+2199.12+6762 -> 16445.54 | F11: =13573.55+267.75+798+1307.54 -> 15946.84 | I11: =294+273+927.08+294+4319.38+306.95 -> 6414.41 | J11: =18381.93+1681.59+220.5 -> 20284.02 | K11: =3411.31+7818.85+588+1249.6+799.7+3929.87+3105.77+1030+1424+11396.99+900.88+220.5+676.2+4678.68+2090 -> 43320.35 | L11: 16338.98 | M11: =2118+4267.2+1764+876.75+2380.12+4899.77+2791.75+267.75+162.52 -> 19527.86 | P11: =36315.15+294+522.5+532+743.6+1431.72 -> 39838.97 | Q11: =39652.86+120+985.6+307.65+532+1239+2461.8 -> 45298.91 | R11: =15954.02+1321.5+531.05 -> 17806.57 | T11: =2728.32+3140.7+882+3897.6+2662.8+1500+9032.24+1533.95+4359.98+713+288.75 -> 30739.34 | W11: =2491.5 -> 2491.5 | X11: =44925.98+294+294+474.04 -> 45988.02 | Y11: =2951.98+7879.2+234.68 -> 11065.86 | Z11: =2156.4+299.25+474.9+1606.5+525+546+1575+220.5+1420.02 -> 8823.57 | AA11: =6910.6+3483.9+1220.1 -> 11614.6 | AD11: =7195.6+1293.5+588+294+535.5+7029.48+646.8 -> 17582.88 | AE11: =20104.35+882+1640.15+263+2047.5+769.5+940.5 -> 26647 | AF11: =3911.95+532+1327.2+3675+2000+1254+211.68+646.8+211.68+862.4+679.14 -> 15311.85 | AG11: =4887+194.25+3034.5+661.5+1675.82 -> 10453.07 | AH11: =18646.25+294+588+3209.85+2583+1764+819+770.7+1050+1478.88 -> 31203.68 | AI11: =SUM(D11:AH11) -> 477171.27
C12: Receitas Diversas | D12: 3.03 | E12: 3.86 | F12: 3.38 | I12: 3.9 | J12: 4.66 | K12: 5.97 | M12: 13.11 | P12: 7.36 | Q12: 8.66 | R12: 14.19 | T12: 7.94 | W12: 2.34 | X12: 3.4 | Y12: 4.1 | Z12: 3.35 | AA12: 3.67 | AD12: 5.19 | AE12: 5.85 | AF12: 1.08 | AG12: 1.65 | AH12: 0.21 | AI12: =SUM(D12:AH12) -> 106.9
C13: Amex | D13: 883.74 | E13: 2082.69 | F13: 277.24 | I13: 5372.65 | J13: 1724.6 | K13: 3367 | M13: 4703.83 | P13: 3558.87 | Q13: 6490.5 | R13: 2368.38 | T13: =1870.08+2333.18 -> 4203.26 | W13: 5033.72 | X13: 1704.02 | Y13: 5152.64 | Z13: 1331.34 | AA13: 866.21 | AD13: 4173.32 | AE13: 1670.92 | AF13: 7763.46 | AG13: 1689.98 | AH13: =343.99+2747.59 -> 3091.58 | AI13: =SUM(D13:AH13) -> 67509.95
C14: Visa Electron | D14: 852.17 | E14: 24.73 | F14: 2543.65 | I14: 4198.08 | J14: 2991.24 | K14: 1683.84 | L14: 205.37 | M14: 734.42 | P14: 2480.23 | Q14: 1931.54 | R14: 872.48 | T14: =769.55+844.91 -> 1614.46 | W14: 7106.81 | X14: 1817.23 | Y14: 316.33 | Z14: 1112.44 | AA14: 525.73 | AD14: 4330.49 | AE14: 1394.58 | AF14: 428.35 | AG14: 1558.34 | AH14: =170.82 -> 170.82 | AI14: =SUM(D14:AH14) -> 38893.33
C15: Master Débito | D15: 370.11 | E15: 104.1 | F15: 195.06 | I15: =296.71+2578.09+714.71 -> 3589.51 | J15: =458.02+245.8 -> 703.82 | K15: 3466.1 | L15: 1466.41 | M15: 367.46 | P15: =4576.37+183.78 -> 4760.15 | Q15: 448.9 | R15: 687.77 | T15: =58.77+701.1 -> 759.87 | W15: =1080+172.89 -> 1252.89 | X15: 633.95 | Y15: 147.19 | Z15: 292.01 | AA15: =1447.47+13.74 -> 1461.21 | AD15: =4601.23+217.34 -> 4818.57 | AE15: =1208.64+400.58 -> 1609.22 | AF15: 1135.24 | AG15: 285.14 | AH15: =908.6+430.67 -> 1339.27 | AI15: =SUM(D15:AH15) -> 29893.95
C16: Visa Crédito | D16: 14584.89 | E16: 5592.81 | F16: 16056.89 | I16: 42035.83 | J16: 10157.99 | K16: 16108.86 | L16: 8281.59 | M16: 11506.61 | P16: 32562.39 | Q16: =3671 -> 3671 | R16: 12248.18 | T16: =9284.31+9861.15 -> 19145.46 | W16: 20515.64 | X16: 3769.6 | Y16: 15580.14 | Z16: 5189.79 | AA16: 3072.15 | AD16: 30734.53 | AE16: 5430.75 | AF16: 14061.16 | AG16: 11540.52 | AH16: 11163.04 | AI16: =SUM(D16:AH16) -> 313009.82
C17: Master Crédito | D17: 3781.44 | E17: 3415.27 | F17: =266.84+1281.3 -> 1548.14 | I17: 17949.76 | J17: 1434.19 | K17: 4005.4 | L17: 7122.8 | M17: 2047.23 | P17: =11902.91+119.61 -> 12022.52 | Q17: 3629.22 | R17: 2563.1 | T17: =2488.13+3519.94 -> 6008.07 | W17: =11651+457.56 -> 12108.56 | X17: 1144.06 | Y17: 1820.24 | Z17: 1722.6 | AA17: 3039.41 | AD17: 20377.01 | AE17: 1031.14 | AF17: 844.84 | AG17: 4606.07 | AH17: =3444.97 -> 3444.97 | AI17: =SUM(D17:AH17) -> 115666.04
C18: TOTAL DAS ENTRADAS | D18: =SUM(D7:D17) -> 45348.53 | E18: =SUM(E7:E17) -> 27669 | F18: =SUM(F7:F17) -> 36865.2 | G18: =SUM(G7:G17) -> 0 | H18: =SUM(H7:H17) -> 0 | I18: =SUM(I7:I17) -> 81815.9 | J18: =SUM(J7:J17) -> 37472.52 | K18: =SUM(K7:K17) -> 73836.77 | ... AH18: =SUM(AH7:AH17) -> 61547.02 | AI18: =SUM(D18:AH18) -> 1103751.2
C19: Repasse Salários e Encargos | W19: =4750+42000 -> 46750 | Z19: 20000 | AD19: 16500 | AF19: 25500 | AH19: 13100 | AI19: =SUM(D19:AH19) -> 121850
B20: SAIDAS | C20: Repasse Aluguel de Salas e Equipamentos | AI20: =SUM(D20:AH20) -> 0
C21: Repasse A&B | R21: =(35042.5+1435.36+79.2)-(830.5+130+237.5) -> 35359.06 | W21: 47812.29 | AH21: =(60901.96+39254)-391.8 -> 99764.16 | AI21: =SUM(D21:AH21) -> 182935.51
C22: Repasse Telefonia | AI22: =SUM(D22:AH22) -> 0
C23: Repasse Internet | AI23: =SUM(D23:AH23) -> 0
C24: Repasse Diversos | AI24: =SUM(D24:AH24) -> 0
C25: Repasse ao Condomínio | D25: =-SUM(D19:D24) -> 0 | E25: =-SUM(E19:E24) -> 0 | F25: =-SUM(F19:F24) -> 0 | G25: =-SUM(G19:G24) -> 0 | H25: =-SUM(H19:H24) -> 0 | I25: =-SUM(I19:I24) -> 0 | J25: =-SUM(J19:J24) -> 0 | K25: =-SUM(K19:K24) -> 0 | ... AI25: =-SUM(AI19:AI24) -> -304785.51
C26: Impostos Lei 10.833 | AI26: =SUM(D26:AH26) -> 0
C27: IRRF | T27: =25.8+78.8+56.25+221.05 -> 381.9 | AI27: =SUM(D27:AH27) -> 381.9
C28: ISS a Recolher | AI28: =SUM(D28:AH28) -> 0
C29: ISS Retido a Recolher | M29: 37530.84 | AI29: =SUM(D29:AH29) -> 37530.84
C30: INSS Retido a Recolher | AI30: =SUM(D30:AH30) -> 0
C31: IPTU a Pagar | M31: =13445.45+10481.58 -> 23927.03 | AI31: =SUM(D31:AH31) -> 23927.03
C32: PIS a Recolher | Z32: 5717.52 | AI32: =SUM(D32:AH32) -> 5717.52
C33: COFINS a Recolher | Z33: 26424.54 | AI33: =SUM(D33:AH33) -> 26424.54
C34: IRPJ a Recolher | AF34: 171979.91 | AI34: =SUM(D34:AH34) -> 171979.91
C35: CSLL a Recolher | AF35: 76650.27 | AI35: =SUM(D35:AH35) -> 76650.27
C36: Total de Impostos | D36: =-SUM(D26:D35) -> 0 | E36: =-SUM(E26:E35) -> 0 | F36: =-SUM(F26:F35) -> 0 | G36: =-SUM(G26:G35) -> 0 | H36: =-SUM(H26:H35) -> 0 | I36: =-SUM(I26:I35) -> 0 | J36: =-SUM(J26:J35) -> 0 | K36: =-SUM(K26:K35) -> 0 | ... AI36: =-SUM(AI26:AI35) -> -342612.01
C37: Água e Esgoto | AI37: =SUM(D37:AH37) -> 0
C38: Energia Elétrica | E38: 19304.6 | M38: 46.55 | AH38: 16112.16 | AI38: =SUM(D38:AH38) -> 35463.31
C39: Telefone | AI39: =SUM(D39:AH39) -> 0
C40: Total de Contas de Consumo | D40: =-SUM(D37:D39) -> 0 | E40: =-SUM(E37:E39) -> -19304.6 | F40: =-SUM(F37:F39) -> 0 | G40: =-SUM(G37:G39) -> 0 | H40: =-SUM(H37:H39) -> 0 | I40: =-SUM(I37:I39) -> 0 | J40: =-SUM(J37:J39) -> 0 | K40: =-SUM(K37:K39) -> 0 | ... AI40: =-SUM(AI37:AI39) -> -35463.31
C41: Adiantamento Dividendos | W41: =222684.6-1436.38 -> 221248.22 | Z41: 1436.38 | AI41: =SUM(D41:AH41) -> 222684.6
C42: Fundo de Reserva | AI42: =SUM(D42:AH42) -> 0
C43: Adiantamento a Fornecedor | D43: 88 | AI43: =SUM(D43:AH43) -> 88
C44: Gastos Gerais do Proprietário | AI44: =SUM(D44:AH44) -> 0
C45: Taxa de Condomínio | F45: 27352.78 | I45: 40676.09 | R45: =14976.24+43631.85 -> 58608.09 | AI45: =SUM(D45:AH45) -> 126636.96
C46: Taxa de Processamento / Administração / Reservas | P46: =7919.79+16276.95 -> 24196.74 | W46: =91.18+26539.11 -> 26630.29 | AI46: =SUM(D46:AH46) -> 50827.03
C47: Despesa Comissão Agências de Viagens | D47: =60.4+84+37.5+56 -> 237.9 | F47: =604.8+196 -> 800.8 | M47: =231.3+1693.95 -> 1925.25 | R47: =104+919.01+992.4 -> 2015.41 | T47: =67.2+2854.83+294+291.37+73.5+73.5+97+15810.63+56 -> 19618.03 | Z47: =60.8+1275.25+199.5+35+80.6 -> 1651.15 | AD47: =28 -> 28 | AF47: =501 -> 501 | AH47: =56+6335.16 -> 6391.16 | AI47: =SUM(D47:AH47) -> 33168.7
C48: Serviço Prestado Gerente Geral | I48: 8062.17 | AI48: =SUM(D48:AH48) -> 8062.17
C49: Repasse Salário Vendas | AI49: =SUM(D49:AH49) -> 0
C50: Custo Livros/Jornais/Revistas | R50: =122.5 -> 122.5 | Z50: 153.9 | AI50: =SUM(D50:AH50) -> 276.4
C51: Custo com Hospedes | M51: 294 | AH51: =588+1254 -> 1842 | AI51: =SUM(D51:AH51) -> 2136
C52: Repasse Restaurante | AI52: =SUM(D52:AH52) -> 0
C53: Serviço Lavanderia | R53: =9652.91 -> 9652.91 | AF53: 11654.22 | AI53: =SUM(D53:AH53) -> 21307.13
C54: Assessoria Jurídica/Contábil e Auditoria | K54: 900.36 | R54: =1109.51 -> 1109.51 | AF54: =3180 -> 3180 | AI54: =SUM(D54:AH54) -> 5189.87
C55: Serviços Postais e de Entrega Rápida | R55: =237.9 -> 237.9 | AI55: =SUM(D55:AH55) -> 237.9
C56: Aluguel de Equipamentos | AI56: =SUM(D56:AH56) -> 0
C57: Cópias e Autenticações | R57: =32.87 -> 32.87 | AI57: =SUM(D57:AH57) -> 32.87
C58: Ornamentação | AI58: =SUM(D58:AH58) -> 0
C59: Serviços Contratados PJ | D59: 7950 | I59: =3693.75+201 -> 3894.75 | P59: 720 | R59: =1590+816+614+1444+3500 -> 7964 | Z59: =359.2 -> 359.2 | AI59: =SUM(D59:AH59) -> 20887.95
C60: Outros Serviços Contratados | AI60: =SUM(D60:AH60) -> 0
C61: Material de Manutenção / Pintura | D61: 583.77 | W61: 389 | AI61: =SUM(D61:AH61) -> 972.77
C62: Custo Ar Condicionado | AI62: =SUM(D62:AH62) -> 0
C63: Material de Limpeza | P63: =863 -> 863 | AI63: =SUM(D63:AH63) -> 863
C64: Material de Apartamento | P64: =1962.91+14118 -> 16080.91 | R64: =2258.4 -> 2258.4 | T64: =5650 -> 5650 | AD64: =664.2+1511 -> 2175.2 | AI64: =SUM(D64:AH64) -> 26164.51
C65: Material de Escritório/Serviços Gráficos | M65: 1781.75 | R65: =230 -> 230 | Z65: 416.13 | AI65: =SUM(D65:AH65) -> 2427.88
C66: Seguro Responsabilidade Civil | AI66: =SUM(D66:AH66) -> 0
C67: Despesa Viagens e Estadias | AI67: =SUM(D67:AH67) -> 0
C68: Reembolso KM | AI68: =SUM(D68:AH68) -> 0
C69: Promoção de Vendas | W69: =408+1289.19+600 -> 2297.19 | AF69: =155.84 -> 155.84 | AH69: =1000 -> 1000 | AI69: =SUM(D69:AH69) -> 3453.03
C70: Associação de Classe | M70: 287.6 | AI70: =SUM(D70:AH70) -> 287.6
C71: Gastos Diversos | F71: 595.35 | K71: =212.5+189.65 -> 402.15 | P71: 10 | AI71: =SUM(D71:AH71) -> 1007.5
C72: Despesas Bancárias | D72: 127.76 | E72: 102.8 | F72: =23.1+32.1+7.9+7.9 -> 71 | I72: 71 | J72: =36.96+51.36+35.46 -> 123.78 | K72: =6.93+9.63+5.91+7.9+7.9 -> 38.27 | L72: =18.48+25.68+5.91 -> 50.07 | M72: =4.62+6.42+7.9 -> 18.94 | P72: =41.58+57.78+7.9 -> 107.26 | Q72: =43.89+60.99+70.92 -> 175.8 | R72: =13.86+19.26+5.91+52.7+(7.9*4) -> 123.33 | T72: =6.93+9.63+11.55+16.05 -> 44.16 | W72: 735.46 | X72: =62.37+86.67+17.73 -> 166.77 | Y72: =4.62+6.42 -> 11.04 | Z72: =(7.9*2)+9.24+12.84 -> 37.88 | AA72: =20.79+28.89 -> 49.68 | AD72: =25.41+35.31 -> 60.72 | AE72: =43.89+60.99+23.64 -> 128.52 | AF72: =16.05+94.71+7.9 -> 118.66 | AG72: =16.17+22.47+5.91 -> 44.55 | AH72: =7.9+7.9+50.82+70.62 -> 137.24 | AI72: =SUM(D72:AH72) -> 2544.69
C73: Cheques Não Compesados | AI73: =SUM(D73:AH73) -> 0
C74: Total de Serviços Contratados e Terceirizados | D74: =-SUM(D41:D73) -> -8987.43 | E74: =-SUM(E41:E73) -> -102.8 | F74: =-SUM(F41:F73) -> -28819.93 | G74: =-SUM(G41:G73) -> 0 | H74: =-SUM(H41:H73) -> 0 | I74: =-SUM(I41:I73) -> -52704.01 | J74: =-SUM(J41:J73) -> -123.78 | K74: =-SUM(K41:K73) -> -1340.78 | ... AI74: =-SUM(AI41:AI73) -> -529256.56
C75: TOTAL DAS SAÍDAS | D75: =D25+D36+D40+D74 -> -8987.43 | E75: =E25+E36+E40+E74 -> -19407.4 | F75: =F25+F36+F40+F74 -> -28819.93 | G75: =G25+G36+G40+G74 -> 0 | H75: =H25+H36+H40+H74 -> 0 | I75: =I25+I36+I40+I74 -> -52704.01 | J75: =J25+J36+J40+J74 -> -123.78 | K75: =K25+K36+K40+K74 -> -1340.78 | ... AI75: =AI25+AI36+AI40+AI74 -> -1212117.4
C77: SALDO DA CONTA CORRENTE | D77: =D6+D18+D75 -> 154858.27 | E77: =E6+E18+E75 -> 163119.87 | F77: =F6+F18+F75 -> 171165.14 | G77: =G6+G18+G75 -> 171165.14 | H77: =H6+H18+H75 -> 171165.14 | I77: =I6+I18+I75 -> 200277.03 | J77: =J6+J18+J75 -> 237625.77 | K77: =K6+K18+K75 -> 310121.76 | ... AI77: =AI6+AI18+AI75 -> 10130.979
B78: APLICAÇÕES
C79: APLICAÇÕES | D79: =Junho!AG83 -> 474047.87 | E79: =D83 -> 474309.37 | F79: =E83 -> 474571.11 | G79: =F83 -> 474833.87 | H79: =G83 -> 474833.87 | I79: =H83 -> 474833.87 | J79: =I83 -> 474833.87 | K79: =J83 -> 474833.87 | L79: =K83 -> 474833.87 | ... AH79: =AG83 -> 478226.21
C80: Fundo Reserva | AI80: =SUM(G80:AF80) -> 0
C81: Dividendos a Pagar | AI81: =SUM(G81:AF81) -> 0
C82: Rendimentos de Aplicações | D82: 261.5 | E82: 261.74 | F82: 262.76 | M82: 633.76 | P82: 177.85 | Q82: 177.94 | R82: 356.07 | T82: 178.19 | W82: 178.22 | X82: 178.36 | Y82: 178.4 | Z82: 178.53 | AA82: 201.85 | AD82: 243.75 | AE82: 179.54 | AF82: 179.62 | AG82: 350.26 | AH82: 186.71 | AI82: =SUM(G82:AF82) -> 3042.08
C83: SALDO DAS APLICAÇÕES | D83: =SUM(D80:D82)+D79 -> 474309.37 | E83: =SUM(E80:E82)+D83 -> 474571.11 | F83: =SUM(F80:F82)+E83 -> 474833.87 | G83: =SUM(G80:G82)+F83 -> 474833.87 | H83: =SUM(H80:H82)+G83 -> 474833.87 | I83: =SUM(I80:I82)+H83 -> 474833.87 | J83: =SUM(J80:J82)+I83 -> 474833.87 | K83: =SUM(K80:K82)+J83 -> 474833.87 | L83: =SUM(L80:L82)+K83 -> 474833.87 | ... AH83: =SUM(AH80:AH82)+AG83 -> 478412.92 | AI83: =AH83 -> 478412.92
C85: SALDO TOTAL | D85: =D77+D83 -> 629167.64 | E85: =E77+E83 -> 637690.98 | F85: =F77+F83 -> 645999.01 | G85: =G77+G83 -> 645999.01 | H85: =H77+H83 -> 645999.01 | I85: =I77+I83 -> 675110.9 | J85: =J77+J83 -> 712459.64 | K85: =K77+K83 -> 784955.63 | ... AI85: =AI77+AI83 -> 488543.9
C87: RESUMO DO DIA
C88: DATA ATUAL: | D88: =AH5 -> 42216
C89: SALDO INICIAL: | D89: =AH6 -> 86930.679
C90: ENTRADA PREVISTA: | D90: =AH18 -> 61547.02
C91: SAÍDA PREVISTA: | D91: =AH75 -> -138346.72
C92: SALDO PREVISTO C/C: | D92: =SUM(D89:D91) -> 10130.979 | L92: Financeiro | S92: Gerente Financeiro | Z92: Gerente Geral
C93: ADIANTAMENTO CLIENTES | D93: 12280.42
C94: ADIANTAMENTO DIVIDENDOS | D94: 3736.94
C95: FUNDO REPOSIÇÃO ATIVOS: | D95: 462208.85
C96: SALDO FINAL PREVISTO: | D96: =SUM(D92:D95) -> 488357.19

Sheet Agosto
B2: Fluxo de Caixa de Agosto de 2015
B4: ÍTEM / DESCRIÇÃO | D4: Realizado | E4: Realizado | F4: Realizado | G4: Realizado | H4: Realizado | I4: Realizado | J4: Realizado | K4: Previsto | L4: Previsto | M4: Realizado | N4: Realizado | O4: Realizado | P4: Realizado | Q4: Realizado | R4: Previsto | S4: Previsto | T4: Realizado | U4: Realizado | V4: Realizado | W4: Realizado | X4: Realizado | Y4: Previsto | Z4: Previsto | AA4: Realizado | AB4: Realizado | AC4: Realizado | AD4: Realizado | AE4: Realizado | AF4: Previsto | AG4: Previsto | AH4: Realizado
D5: 42217 | E5: =D5+1 -> 42218 | F5: =E5+1 -> 42219 | G5: =F5+1 -> 42220 | H5: =G5+1 -> 42221 | I5: =H5+1 -> 42222 | J5: =I5+1 -> 42223 | K5: =J5+1 -> 42224 | L5: =K5+1 -> 42225 | ... AH5: =AG5+1 -> 42247 | AI5: ACUMULADO
C6: SALDO ANTERIOR DA CONTA CORRENTE | D6: =Julho!AH77 -> 10130.979 | E6: =D77 -> 10130.979 | F6: =E77 -> 10130.979 | G6: =F77 -> 50850.249 | H6: =G77 -> 102551.21 | I6: =H77 -> 91679.959 | J6: =I77 -> 121076.75 | K6: =J77 -> 141336.18 | L6: =K77 -> 141336.18 | ... AH6: =AG77 -> 136066.72 | AI6: =D6 -> 10130.979
B7: ENTRADAS | C7: Adiantamento de Clientes | F7: =490.88 -> 490.88 | G7: =444 -> 444 | H7: =793.8+1324+434.7+90.09 -> 2642.59 | I7: =77.65 -> 77.65 | M7: =298+341.25+286.65 -> 925.9 | N7: =497.7+2080+1456.04 -> 4033.74 | O7: =409.5+262.5+360 -> 1032 | P7: =409.5+724.5 -> 1134 | Q7: =419.48+3000+3180+537.75 -> 7137.23 | T7: =218.25+491+262.5+456 -> 1427.75 | U7: =280+2240+912.44 -> 3432.44 | V7: =199.5+2531+1050+792 -> 4572.5 | W7: =1000 -> 1000 | X7: =3683.51+1090 -> 4773.51 | AA7: =745.5+1648.5 -> 2394 | AC7: =30000+456.22 -> 30456.22 | AE7: =991.2 -> 991.2 | AH7: =462 -> 462 | AI7: =SUM(D7:AH7) -> 67427.61
C8: Depósito RDS | P8: =520.41+2199.69+116.5+159.81+184.2+209.3+416+440.3+448.6+486.15+652.15+815.16 -> 6648.27 | W8: =33.3+163.5+210.26+235.5+402.2+964.18+1242.3+1399.97 -> 4651.21 | AA8: =385.2+848.75+1118.7+1623.6+2633.89 -> 6610.14 | AH8: =719.51+169.05+188.53+551.05+626.4+1283.87+2375.47 -> 5913.88 | AI8: =SUM(D8:AH8) -> 23823.5
C9: Crédito Não Identificado | AI9: =SUM(D9:AH9) -> 0
C10: Fundo de Reserva | AI10: =SUM(D10:AH10) -> 0
C11: Faturas | F11: =4148.66+1178.96+2317.7+646.8+1732.5 -> 10024.62 | G11: =35447.89 -> 35447.89 | H11: =4229.95+1000+4902.46+215.6 -> 10348.01 | I11: =7161.01+622.12 -> 7783.13 | J11: =5608.65+668.32+2604+1283.1 -> 10164.07 | M11: =11635.02+472.5+294+294+231+2275.32 -> 15201.84 | N11: =13781.52+33219.8+934.5+606+852.86+7200.5 -> 56595.18 | O11: =2498+509.6+273.95+320.85 -> 3602.4 | P11: =238.35+1092.45+420.8 -> 1751.6 | Q11: =991.2+3590.95+594.3+284.55+661.5 -> 6122.5 | T11: =1772+2420+659.2+882+474+646.8+2340.03+215.6+862.4 -> 10272.03 | U11: =10704.9+22152.55+206+431.2+5974.98+3995.53 -> 43465.16 | V11: =1732.3+4513.3+1145.04+1622.88+6009.55 -> 15023.07 | W11: =2099.87+1965.15+997.5+219.71+1628.03+832.8 -> 7743.06 | X11: =566.2+12132+4301.6+431.2+294 -> 17725 | AA11: =1245.3+7074+4349.2+561.4+1886.6 -> 15116.5 | AB11: =2406.34+33385.29+31390+431.2 -> 67612.83 | AC11: =2519.3+840+1858.5+569.1+3452.4+3672.9+199.24+495.6 -> 13607.04 | AD11: =237.5+4571.98+569.1+1291.5+1564.5+588+1606.28 -> 10428.86 | AE11: =7169.58+1171.8+211.75 -> 8553.13 | AH11: =9302.22+606 -> 9908.22 | AI11: =SUM(D11:AH11) -> 376496.14
C12: Receitas Diversas | F12: 1.01 | G12: 2.09 | I12: 4.31 | J12: 2.88 | M12: =10+1.59 -> 11.59 | N12: 3.21 | O12: 3.73 | P12: 4.26 | Q12: =22227.96+2.56 -> 22230.52 | T12: 2.96 | U12: 4.19 | V12: 3.71 | W12: 0.36 | X12: 0.23 | AA12: =298+0.85 -> 298.85 | AB12: 1.65 | AC12: 1.95 | AD12: 3.16 | AE12: 2.76 | AH12: 0.77 | AI12: =SUM(D12:AH12) -> 22584.19
C13: Amex | F13: 3177.89 | H13: =6189.4 -> 6189.4 | I13: 675.7 | J13: 1465.52 | M13: 10371.31 | N13: 3570.33 | O13: 507.15 | P13: 3727.67 | Q13: 3174.76 | T13: 3679.87 | V13: 1786.47 | W13: 3737.3 | X13: 2871.65 | AA13: 7635.04 | AB13: 1334.67 | AC13: 4975.43 | AD13: 2825.98 | AE13: 5795.95 | AH13: =6607.69 -> 6607.69 | AI13: =SUM(D13:AH13) -> 74109.78
C14: Visa Electron | F14: 3067.2 | G14: 1901.7 | H14: 565.82 | I14: 376.58 | J14: 1226.99 | M14: 3349.57 | N14: 2837.13 | O14: 247.06 | P14: 397.39 | Q14: 330.76 | T14: 2045.55 | U14: 1410.33 | V14: 1712.52 | W14: 270.7 | X14: 205.43 | AA14: =1785.23+1883.97+3737.01 -> 7406.21 | AB14: 551.13 | AC14: 42.97 | AD14: 1612.13 | AE14: 250.49 | AH14: =50.83+195.02+2108.3 -> 2354.15 | AI14: =SUM(D14:AH14) -> 32161.81
C15: Master Débito | F15: =2072.2+981.2 -> 3053.4 | G15: 171.91 | I15: =2929.96+155.47 -> 3085.43 | J15: =328.76+679.97 -> 1008.73 | M15: =1840.66+352.4 -> 2193.06 | N15: =12.95+1251.72 -> 1264.67 | O15: 46.61 | P15: 114.61 | Q15: =599.18+80.06 -> 679.24 | T15: 2132.3 | U15: 45.13 | V15: =705.21+188.39 -> 893.6 | W15: =778.36+345.28 -> 1123.64 | X15: 1976.33 | AA15: =39.2+382.25+1134.21 -> 1555.66 | AB15: 1146.63 | AC15: 935.13 | AD15: 373.35 | AE15: =832.94 -> 832.94 | AH15: =135.85+161.89+320.8 -> 618.54 | AI15: =SUM(D15:AH15) -> 23250.91
C16: Visa Crédito | F16: 32997.67 | G16: 11146.07 | H16: 26483.63 | I16: =11172.52 -> 11172.52 | J16: 13438.2 | M16: 23629.54 | N16: 8635.28 | O16: 33419.58 | P16: 8192.52 | Q16: 8906.42 | T16: 32548.11 | U16: 7205.72 | V16: 11003.06 | W16: 7619.26 | X16: 10763.18 | AA16: 27837.42 | AB16: 1851.79 | AC16: 6045.23 | AD16: 10494.46 | AE16: 10412.81 | AH16: 27065.04 | AI16: =SUM(D16:AH16) -> 330867.51
C17: Master Crédito | F17: 13053.92 | G17: 2886.47 | H17: 1180.17 | I17: 6260.11 | J17: 1615.48 | M17: =8997.65+1003.31 -> 10000.96 | N17: =3273.44+2282.42 -> 5555.86 | O17: 2832.68 | P17: 5840.14 | Q17: 3728.58 | T17: =11730.75+171.05 -> 11901.8 | U17: 5647.17 | V17: 2979.57 | W17: 3890.96 | X17: 1885.38 | AA17: 7310.33 | AB17: 5191.26 | AC17: 2660.88 | AD17: 3854.11 | AE17: =1277.89+67.29 -> 1345.18 | AH17: 7220.71 | AI17: =SUM(D17:AH17) -> 106841.72
C18: TOTAL DAS ENTRADAS | D18: =SUM(D7:D17) -> 0 | E18: =SUM(E7:E17) -> 0 | F18: =SUM(F7:F17) -> 65866.59 | G18: =SUM(G7:G17) -> 52000.13 | H18: =SUM(H7:H17) -> 47409.62 | I18: =SUM(I7:I17) -> 29435.43 | J18: =SUM(J7:J17) -> 28921.87 | K18: =SUM(K7:K17) -> 0 | ... AH18: =SUM(AH7:AH17) -> 60151 | AI18: =SUM(D18:AH18) -> 1057563.2
C19: Repasse Salários e Encargos | AI19: =SUM(D19:AH19) -> 0
B20: SAIDAS | C20: Repasse Aluguel de Salas e Equipamentos | AI20: =SUM(D20:AH20) -> 0
C21: Repasse A&B | Q21: =(59742.57+1680.8+1113.2+112.2+768.9+79.2+618.75+128.7+37836+540.54+288.27)-291 -> 102618.13 | AH21: =72445.58-5897.3 -> 66548.28 | AI21: =SUM(D21:AH21) -> 169166.41
C22: Repasse Telefonia | AI22: =SUM(D22:AH22) -> 0
C23: Repasse Internet | AI23: =SUM(D23:AH23) -> 0
C24: Repasse Diversos | AC24: 420 | AI24: =SUM(D24:AH24) -> 420
C25: Repasse ao Condomínio | D25: =-SUM(D19:D24) -> 0 | E25: =-SUM(E19:E24) -> 0 | F25: =-SUM(F19:F24) -> 0 | G25: =-SUM(G19:G24) -> 0 | H25: =-SUM(H19:H24) -> 0 | I25: =-SUM(I19:I24) -> 0 | J25: =-SUM(J19:J24) -> 0 | K25: =-SUM(K19:K24) -> 0 | ... AI25: =-SUM(AI19:AI24) -> -169586.41
C26: Impostos Lei 10.833 | AE26: =391.38+174.38 -> 565.76 | AI26: =SUM(D26:AH26) -> 565.76
C27: IRRF | V27: =101.25+240.77+31.91+56.25+21.66 -> 451.84 | AI27: =SUM(D27:AH27) -> 451.84
C28: ISS a Recolher | M28: =587.15+51069.28 -> 51656.43 | AI28: =SUM(D28:AH28) -> 51656.43
C29: ISS Retido a Recolher | AI29: =SUM(D29:AH29) -> 0
C30: INSS Retido a Recolher | AI30: =SUM(D30:AH30) -> 0
C31: IPTU a Pagar | M31: 24040.8 | AI31: =SUM(D31:AH31) -> 24040.8
C32: PIS a Recolher | AB32: 6194.6 | AI32: =SUM(D32:AH32) -> 6194.6
C33: COFINS a Recolher | AB33: 28590.43 | AI33: =SUM(D33:AH33) -> 28590.43
C34: IRPJ a Recolher | AI34: =SUM(D34:AH34) -> 0
C35: CSLL a Recolher | AI35: =SUM(D35:AH35) -> 0
C36: Total de Impostos | D36: =-SUM(D26:D35) -> 0 | E36: =-SUM(E26:E35) -> 0 | F36: =-SUM(F26:F35) -> 0 | G36: =-SUM(G26:G35) -> 0 | H36: =-SUM(H26:H35) -> 0 | I36: =-SUM(I26:I35) -> 0 | J36: =-SUM(J26:J35) -> 0 | K36: =-SUM(K26:K35) -> 0 | ... AI36: =-SUM(AI26:AI35) -> -111499.86
C37: Água e Esgoto | AI37: =SUM(D37:AH37) -> 0
C38: Energia Elétrica | H38: =14.37+14.6 -> 28.97 | AI38: =SUM(D38:AH38) -> 28.97
C39: Telefone | AI39: =SUM(D39:AH39) -> 0
C40: Total de Contas de Consumo | D40: =-SUM(D37:D39) -> 0 | E40: =-SUM(E37:E39) -> 0 | F40: =-SUM(F37:F39) -> 0 | G40: =-SUM(G37:G39) -> 0 | H40: =-SUM(H37:H39) -> -28.97 | I40: =-SUM(I37:I39) -> 0 | J40: =-SUM(J37:J39) -> 0 | K40: =-SUM(K37:K39) -> 0 | ... AI40: =-SUM(AI37:AI39) -> -28.97
C41: Adiantamento Dividendos | W41: =(1400*159+0.42)-(1430.27+1514.45+6947.14+8355.85+5974.5+8918.34+20591.8+1458.81) -> 167409.26 | X41: =20591.8+6947.14+8918.34+8355.85 -> 44813.13 | AA41: =1430.27+1356.28+1356.28+1831.67+1458.81 -> 7433.31 | AI41: =SUM(D41:AH41) -> 219655.7
C42: Fundo de Reserva | AH42: 31125.84 | AI42: =SUM(D42:AH42) -> 31125.84
C43: Adiantamento a Fornecedor | Q43: =30000-Q45 -> 18397.07 | V43: 42000 | AA43: 31000 | AB43: 5500 | AC43: 4600 | AE43: 46000 | AH43: 5500 | AI43: =SUM(D43:AH43) -> 152997.07
C44: Gastos Gerais do Proprietário | AI44: =SUM(D44:AH44) -> 0
C45: Taxa de Condomínio | F45: 13000 | H45: 46250 | J45: 7000 | M45: 20000 | Q45: 11602.93 | AI45: =SUM(D45:AH45) -> 97852.93
C46: Taxa de Processamento / Administração / Reservas | M46: =16658.89+7919.79 -> 24578.68 | W46: 27702.69 | AI46: =SUM(D46:AH46) -> 52281.37
C47: Despesa Comissão Agências de Viagens | H47: =75+112 -> 187 | M47: =2095.63+28+1096.12 -> 3219.75 | O47: =1130.2+666.6+52+852.4+136.4+112+57.2+29.9+140+89.4 -> 3266.1 | Q47: =318.9+959.01 -> 1277.91 | T47: =41.8+78.4 -> 120.2 | V47: =17546.11+1299.54+1334.25+28 -> 20207.9 | X47: 151.2 | AA47: =1007.3 -> 1007.3 | AB47: =29.8+1007.6 -> 1037.4 | AC47: =7899.02+28+121.7 -> 8048.72 | AE47: =1004.72+151.1 -> 1155.82 | AH47: =58.7 -> 58.7 | AI47: =SUM(D47:AH47) -> 39738
C48: Serviço Prestado Gerente Geral | H48: =8062.17 -> 8062.17 | AI48: =SUM(D48:AH48) -> 8062.17
C49: Repasse Salário Vendas | AI49: =SUM(D49:AH49) -> 0
C50: Custo Livros/Jornais/Revistas | T50: =122.5 -> 122.5 | AB50: 153.9 | AI50: =SUM(D50:AH50) -> 276.4
C51: Custo com Hospedes | J51: 793.8 | P51: 391.43 | Q51: =170.5 -> 170.5 | T51: 22227.96 | X51: 298 | AA51: 360 | AB51: 298 | AH51: =(31390-7.9)+459.9 -> 31842 | AI51: =SUM(D51:AH51) -> 56381.69
C52: Repasse Restaurante | AI52: =SUM(D52:AH52) -> 0
C53: Serviço Lavanderia | T53: =10517.23 -> 10517.23 | AH53: 9326.6 | AI53: =SUM(D53:AH53) -> 19843.83
C54: Assessoria Jurídica/Contábil e Auditoria | M54: =900.36 -> 900.36 | Q54: =1109.51 -> 1109.51 | AH54: 3180 | AI54: =SUM(D54:AH54) -> 5189.87
C55: Serviços Postais e de Entrega Rápida | J55: =318.8+503.3 -> 822.1 | AE55: =368.55 -> 368.55 | AI55: =SUM(D55:AH55) -> 1190.65
C56: Aluguel de Equipamentos | AI56: =SUM(D56:AH56) -> 0
C57: Cópias e Autenticações | M57: =155.6 -> 155.6 | AI57: =SUM(D57:AH57) -> 155.6
C58: Ornamentação | AI58: =SUM(D58:AH58) -> 0
C59: Serviços Contratados PJ | F59: =3500+7950 -> 11450 | H59: =3519.37 -> 3519.37 | M59: =720 -> 720 | O59: =1590 -> 1590 | Q59: =816 -> 816 | T59: =174.44+1355.19+585.45+342.5 -> 2457.58 | AA59: =300+180 -> 480 | AH59: 7950 | AI59: =SUM(D59:AH59) -> 28982.95
C60: Outros Serviços Contratados | AI60: =SUM(D60:AH60) -> 0
C61: Material de Manutenção / Pintura | AI61: =SUM(D61:AH61) -> 0
C62: Custo Ar Condicionado | AI62: =SUM(D62:AH62) -> 0
C63: Material de Limpeza | M63: =945+760.24 -> 1705.24 | T63: =540 -> 540 | AI63: =SUM(D63:AH63) -> 2245.24
C64: Material de Apartamento | F64: =664.2 -> 664.2 | M64: =664.2 -> 664.2 | O64: =14118 -> 14118 | T64: =5650 -> 5650 | AA64: =618.33 -> 618.33 | AB64: =1511 -> 1511 | AH64: 618.33 | AI64: =SUM(D64:AH64) -> 23844.06
C65: Material de Escritório/Serviços Gráficos | Q65: =854.9 -> 854.9 | V65: =520 -> 520 | AC65: 354.09 | AH65: 1794.02 | AI65: =SUM(D65:AH65) -> 3523.01
C66: Seguro Responsabilidade Civil | AI66: =SUM(D66:AH66) -> 0
C67: Despesa Viagens e Estadias | AI67: =SUM(D67:AH67) -> 0
C68: Reembolso KM | X68: =103.1+375.73+98.21 -> 577.04 | AI68: =SUM(D68:AH68) -> 577.04
C69: Promoção de Vendas | M69: 1000 | T69: =625 -> 625 | AH69: 625 | AI69: =SUM(D69:AH69) -> 2250
C70: Associação de Classe | H70: =201 -> 201 | V70: =479.32 -> 479.32 | AI70: =SUM(D70:AH70) -> 680.32
C71: Gastos Diversos | AI71: =SUM(D71:AH71) -> 0
C72: Despesas Bancárias | F72: =13.86+19.26 -> 33.12 | G72: =57.78+159.39+82 -> 299.17 | H72: =6.93+9.63+7.9+7.9 -> 32.36 | I72: =16.17+22.47 -> 38.64 | J72: =16.17+22.47+7.9 -> 46.54 | M72: =51.36+129.36+7.9 -> 188.62 | N72: =41.73+103.95 -> 145.68 | O72: =4.62+6.42+7.9+7.9 -> 26.84 | P72: =2.31+3.21 -> 5.52 | Q72: =3.21+48.51+52.7+7.9+7.9 -> 120.22 | T72: =3.21+34.65+7.9 -> 45.76 | U72: =18.48+25.68 -> 44.16 | W72: =4.62+6.42+655.7 -> 666.74 | X72: =(7.9*4)+3.21+90.09 -> 124.9 | AA72: =(7.9*3)+4.62+6.42 -> 34.74 | AB72: =9.24+12.84+7.9 -> 29.98 | AC72: =7.9*2 -> 15.8 | AD72: =3.21+166.32 -> 169.53 | AE72: 7.9 | AH72: =7.9*2 -> 15.8 | AI72: =SUM(D72:AH72) -> 2092.02
C73: Cheques Não Compesados | AI73: =SUM(D73:AH73) -> 0
C74: Total de Serviços Contratados e Terceirizados | D74: =-SUM(D41:D73) -> 0 | E74: =-SUM(E41:E73) -> 0 | F74: =-SUM(F41:F73) -> -25147.32 | G74: =-SUM(G41:G73) -> -299.17 | H74: =-SUM(H41:H73) -> -58251.9 | I74: =-SUM(I41:I73) -> -38.64 | J74: =-SUM(J41:J73) -> -8662.44 | K74: =-SUM(K41:K73) -> 0 | ... AI74: =-SUM(AI41:AI73) -> -748945.76
C75: TOTAL DAS SAÍDAS | D75: =D25+D36+D40+D74 -> 0 | E75: =E25+E36+E40+E74 -> 0 | F75: =F25+F36+F40+F74 -> -25147.32 | G75: =G25+G36+G40+G74 -> -299.17 | H75: =H25+H36+H40+H74 -> -58280.87 | I75: =I25+I36+I40+I74 -> -38.64 | J75: =J25+J36+J40+J74 -> -8662.44 | K75: =K25+K36+K40+K74 -> 0 | ... AI75: =AI25+AI36+AI40+AI74 -> -1030061
C77: SALDO DA CONTA CORRENTE | D77: =D6+D18+D75 -> 10130.979 | E77: =E6+E18+E75 -> 10130.979 | F77: =F6+F18+F75 -> 50850.249 | G77: =G6+G18+G75 -> 102551.21 | H77: =H6+H18+H75 -> 91679.959 | I77: =I6+I18+I75 -> 121076.75 | J77: =J6+J18+J75 -> 141336.18 | K77: =K6+K18+K75 -> 141336.18 | ... AI77: =AI6+AI18+AI75 -> 37633.149
B78: APLICAÇÕES
C79: APLICAÇÕES | D79: =Julho!AH83 -> 478412.92 | E79: =D83 -> 478412.92 | F79: =E83 -> 478412.92 | G79: =F83 -> 478599.74 | H79: =G83 -> 478786.57 | I79: =H83 -> 478786.57 | J79: =I83 -> 478786.57 | K79: =J83 -> 479347.73 | L79: =K83 -> 479347.73 | ... AH79: =AG83 -> 482199.19
C80: Fundo Reserva | AH80: 31125.84 | AI80: =SUM(G80:AF80) -> 0
C81: Dividendos a Pagar | AI81: =SUM(G81:AF81) -> 0
C82: Rendimentos de Aplicações | F82: 186.82 | G82: 186.83 | J82: 561.16 | M82: 187.23 | N82: 187.36 | O82: 187.39 | P82: 187.51 | Q82: 187.5 | T82: 187.72 | U82: 187.78 | V82: 187.93 | W82: 187.95 | X82: 187.35 | AA82: 188.89 | AB82: 188.21 | AC82: 188.35 | AD82: 188.37 | AE82: 221.92 | AH82: 282.17 | AI82: =SUM(G82:AF82) -> 3599.45
C83: SALDO DAS APLICAÇÕES | D83: =SUM(D80:D82)+D79 -> 478412.92 | E83: =SUM(E80:E82)+D83 -> 478412.92 | F83: =SUM(F80:F82)+E83 -> 478599.74 | G83: =SUM(G80:G82)+F83 -> 478786.57 | H83: =SUM(H80:H82)+G83 -> 478786.57 | I83: =SUM(I80:I82)+H83 -> 478786.57 | J83: =SUM(J80:J82)+I83 -> 479347.73 | K83: =SUM(K80:K82)+J83 -> 479347.73 | L83: =SUM(L80:L82)+K83 -> 479347.73 | ... AH83: =SUM(AH80:AH82)+AG83 -> 513607.2 | AI83: =AH83 -> 513607.2
C85: SALDO TOTAL | D85: =D77+D83 -> 488543.9 | E85: =E77+E83 -> 488543.9 | F85: =F77+F83 -> 529449.99 | G85: =G77+G83 -> 581337.78 | H85: =H77+H83 -> 570466.53 | I85: =I77+I83 -> 599863.32 | J85: =J77+J83 -> 620683.91 | K85: =K77+K83 -> 620683.91 | ... AI85: =AI77+AI83 -> 551240.35
C87: RESUMO DO DIA
C88: DATA ATUAL: | D88: =AH5 -> 42247
C89: SALDO INICIAL: | D89: =AH6 -> 136066.72
C90: ENTRADA PREVISTA: | D90: =AH18 -> 60151
C91: SAÍDA PREVISTA: | D91: =AH75 -> -158584.57
C92: SALDO PREVISTO C/C: | D92: =SUM(D89:D91) -> 37633.149 | L92: Financeiro | S92: Gerente Financeiro | Z92: Gerente Geral
C93: ADIANTAMENTO CLIENTES | D93: 12360.1
C94: ADIANTAMENTO DIVIDENDOS | D94: 3764.08
C95: FUNDO REPOSIÇÃO ATIVOS: | D95: 466075.01
C96: SALDO FINAL PREVISTO: | D96: =SUM(D92:D95) -> 519832.34

Sheet Setembro
B2: Fluxo de Caixa de Setembro de 2015
B4: ÍTEM / DESCRIÇÃO | D4: Realizado | E4: Realizado | F4: Realizado | G4: Realizado | H4: Previsto | I4: Previsto | J4: Previsto | K4: Realizado | L4: Realizado | M4: Realizado | N4: Realizado | O4: Previsto | P4: Previsto | Q4: Realizado | R4: Realizado | S4: Realizado | T4: Realizado | U4: Realizado | V4: Previsto | W4: Previsto | X4: Realizado | Y4: Realizado | Z4: Realizado | AA4: Realizado | AB4: Realizado | AC4: Previsto | AD4: Previsto | AE4: Realizado | AF4: Realizado | AG4: Realizado | AH4: Previsto
D5: 42248 | E5: =D5+1 -> 42249 | F5: =E5+1 -> 42250 | G5: =F5+1 -> 42251 | H5: =G5+1 -> 42252 | I5: =H5+1 -> 42253 | J5: =I5+1 -> 42254 | K5: =J5+1 -> 42255 | L5: =K5+1 -> 42256 | ... AH5: =AG5+1 -> 42278 | AI5: ACUMULADO
C6: SALDO ANTERIOR DA CONTA CORRENTE | D6: =Agosto!AH77 -> 37633.149 | E6: =D77 -> 77802.199 | F6: =E77 -> 34669.959 | G6: =F77 -> 53412.769 | H6: =G77 -> 92413.069 | I6: =H77 -> 92413.069 | J6: =I77 -> 92413.069 | K6: =J77 -> 92413.069 | L6: =K77 -> 143460.55 | ... AH6: =AG77 -> 123402.72 | AI6: =D6 -> 37633.149
B7: ENTRADAS | C7: Adiantamento de Clientes | D7: =1006.95+882 -> 1888.95 | E7: =288.75+231 -> 519.75 | F7: =1138.5+859.95+250+187 -> 2435.45 | G7: =192.68+220.5+8662.5+1026.81+290 -> 10392.49 | K7: =2881+273 -> 3154 | L7: =560+420+157+192.68 -> 1329.68 | M7: =10000+887.25+21.55+500 -> 11408.8 | N7: =520+420+509.55 -> 1449.55 | Q7: =210+157 -> 367 | R7: =31.05+21860+630+276.15 -> 22797.2 | S7: =35 -> 35 | T7: =443.62+239.4+1955.1 -> 2638.12 | U7: =1381+1822.1 -> 3203.1 | X7: =262.5+429.95+63+196.98+294 -> 1246.43 | Y7: =260 -> 260 | Z7: =4187.5+525 -> 4712.5 | AA7: =28 -> 28 | AB7: =186.95 -> 186.95 | AE7: =156.98 -> 156.98 | AG7: =302.4+157+156.95 -> 616.35 | AI7: =SUM(D7:AH7) -> 68826.3
C8: Depósito RDS | L8: =662.43+166.1+278.4+432.8+497.06+579.15+971.17+1136.4 -> 4723.51 | U8: =2039.5+0.6+321.32+674.69+790.31+1180.7+1294.16+1547.48+2164.86+2282.65+2741.5 -> 15037.77 | Y8: =2228.65+2509.19+8700.77+20285.4 -> 33724.01 | AG8: =2215.4+840.29+899.77+1069.1+1628.75+2079.15+2734.1 -> 11466.56 | AI8: =SUM(D8:AH8) -> 64951.85
C9: Crédito Não Identificado | AI9: =SUM(D9:AH9) -> 0
C10: Fundo de Reserva | AI10: =SUM(D10:AH10) -> 0
C11: Faturas | D11: =27758.08+49.5+568.57+202.86 -> 28579.01 | E11: =2447.73+1403.52 -> 3851.25 | F11: =1614.9+4530.44+294+816.2+1012.55 -> 8268.09 | G11: =6900.62+4446.75+211.75 -> 11559.12 | K11: =9834.65+21212.1 -> 31046.75 | L11: =45241.86+19986+7368.5+428.89+5313.7 -> 78338.95 | M11: =10545.43+797.05+433.12 -> 11775.6 | N11: =15509.89+561.75+431.2+3897.98 -> 20400.82 | Q11: =18644.82+1575+2044.35+10601.85 -> 32866.02 | R11: =24384.65 -> 24384.65 | S11: =18958.33 -> 18958.33 | T11: =4432.19+262.5+2840.04+1659 -> 9193.73 | U11: =2525.18+866.25+577.5 -> 3968.93 | X11: =2301.95+90.09+842.11+561.41+561.41+786.74+647.43+6090+2352+211.75+1242.78+1767.92+4451.37 -> 21906.96 | Y11: =21000.96+609.45+1953 -> 23563.41 | Z11: =13843.25+1513 -> 15356.25 | AA11: =13633.98+20547.25+5852.63+420 -> 40453.86 | AB11: =5714.27+561.41+4654.65 -> 10930.33 | AE11: =6131.44+3078 -> 9209.44 | AF11: =41912.13+3087.75 -> 44999.88 | AG11: =441+2515.16+2421.25 -> 5377.41 | AI11: =SUM(D11:AH11) -> 454988.79
C12: Receitas Diversas | D12: 1.58 | E12: 0.7 | F12: 1.06 | G12: 1.87 | K12: 2.9 | L12: 4.88 | M12: 3.6 | N12: 4.14 | Q12: 4.23 | R12: 2.67 | S12: 3.3 | T12: 3.79 | U12: 3.74 | X12: 0.91 | Y12: 2.11 | Z12: 2.02 | AA12: 3.14 | AB12: 3.04 | AE12: 3.76 | AF12: 4.92 | AG12: =817.6+2.5 -> 820.1 | AI12: =SUM(D12:AH12) -> 878.46
C13: Amex | D13: 1660.41 | E13: 4868.65 | F13: 704.7 | G13: 1260.63 | K13: =1782.77 -> 1782.77 | L13: 1907.9 | M13: 4794.84 | N13: 1594.42 | Q13: =5617.1 -> 5617.1 | R13: 2488.08 | S13: 3054.05 | T13: 3424.97 | U13: 10954.6 | X13: =3350.96 -> 3350.96 | Y13: 2660.51 | Z13: 1429.15 | AA13: 5380.85 | AB13: 4814.17 | AE13: 1947.43 | AF13: 253.57 | AG13: 3975.56 | AI13: =SUM(D13:AH13) -> 67925.32
C14: Visa Electron | D14: =345.88 -> 345.88 | E14: 76.93 | F14: 577.77 | G14: 995.62 | K14: =29.44+525.63+698.66+2145.09 -> 3398.82 | L14: 746.6 | M14: 540.22 | N14: 2061.1 | Q14: =760.23+1166.55+2205.19 -> 4131.97 | R14: =1583.75 -> 1583.75 | S14: 1348.96 | T14: 1253.72 | U14: 2654.98 | X14: =1127.07+4250.44+5509.51 -> 10887.02 | Y14: 3741.35 | Z14: 626.02 | AA14: 903.5 | AB14: 2940.77 | AE14: =747.3+1209.08+2599.7 -> 4556.08 | AF14: 4417.66 | AG14: 321.3 | AI14: =SUM(D14:AH14) -> 48110.02
C15: Master Débito | D15: =124.37+1133.29 -> 1257.66 | E15: 691.65 | F15: 290.15 | G15: 2618.86 | K15: =313.01+544.27+917.42+1342.51+31.59+103.03+257.56+1983.25 -> 5492.64 | L15: 1366.48 | M15: 317.68 | N15: =327.6 -> 327.6 | Q15: =178.59+402.29+1040.1+257.56+803.66 -> 2682.2 | R15: =1162.82+137.49 -> 1300.31 | S15: =51.51+29.27 -> 80.78 | T15: =771.32+19.62 -> 790.94 | U15: =1403.16+169.99 -> 1573.15 | X15: =929.94+1084.03+3539.26+252.56+257.56 -> 6063.35 | Y15: 629.24 | Z15: =447.65+32.38 -> 480.03 | AA15: 1069.5 | AB15: 1116.58 | AE15: =826.13+1597.18+1898.37+247.26 -> 4568.94 | AF15: 1543.38 | AG15: 32.67 | AI15: =SUM(D15:AH15) -> 34293.79
C16: Visa Crédito | D16: 3766.81 | E16: 12296.41 | F16: 5679.82 | G16: 6150.15 | K16: =28462.76 -> 28462.76 | L16: 14100.36 | M16: =6053.7 -> 6053.7 | N16: 6074.92 | Q16: 23859.1 | R16: =7426.14 -> 7426.14 | S16: 10341.79 | T16: 8262.65 | U16: 5238.34 | X16: 19707.35 | Y16: 6023.53 | Z16: 3735.84 | AA16: 4679.04 | AB16: 5126.3 | AE16: 18934.76 | AF16: 4844.85 | AG16: 5293.02 | AI16: =SUM(D16:AH16) -> 206057.64
C17: Master Crédito | D17: 2807.35 | E17: 3387.28 | F17: 791.29 | G17: 10994.39 | K17: =8072.69 -> 8072.69 | L17: 1265.15 | M17: =4965.2+250.15 -> 5215.35 | N17: 901.53 | Q17: =5205.46 -> 5205.46 | R17: 4818.2 | S17: 11496.88 | T17: =1086.94 -> 1086.94 | U17: 595.58 | X17: =6707.17+121.55 -> 6828.72 | Y17: 1489 | Z17: 436.32 | AA17: 3344.41 | AB17: 2632.98 | AE17: 9502 | AF17: 998.64 | AG17: 1196.09 | AI17: =SUM(D17:AH17) -> 83066.25
C18: TOTAL DAS ENTRADAS | D18: =SUM(D7:D17) -> 40307.65 | E18: =SUM(E7:E17) -> 25692.62 | F18: =SUM(F7:F17) -> 18748.33 | G18: =SUM(G7:G17) -> 43973.13 | H18: =SUM(H7:H17) -> 0 | I18: =SUM(I7:I17) -> 0 | J18: =SUM(J7:J17) -> 0 | K18: =SUM(K7:K17) -> 81413.33 | ... AG18: =SUM(AG7:AG17) -> 29099.06 | AI18: =SUM(D18:AH18) -> 1029098.4
C19: Repasse Salários e Encargos | AI19: =SUM(D19:AH19) -> 0
B20: SAIDAS | C20: Repasse Aluguel de Salas e Equipamentos | AI20: =SUM(D20:AH20) -> 0
C21: Repasse A&B | R21: =594+387.2+84983.42+36264+326.7+454.65 -> 123009.97 | AG21: 81130.14 | AI21: =SUM(D21:AH21) -> 204140.11
C22: Repasse Telefonia | AI22: =SUM(D22:AH22) -> 0
C23: Repasse Internet | AI23: =SUM(D23:AH23) -> 0
C24: Repasse Diversos | Q24: 574 | AI24: =SUM(D24:AH24) -> 574
C25: Repasse ao Condomínio | D25: =-SUM(D19:D24) -> 0 | E25: =-SUM(E19:E24) -> 0 | F25: =-SUM(F19:F24) -> 0 | G25: =-SUM(G19:G24) -> 0 | H25: =-SUM(H19:H24) -> 0 | I25: =-SUM(I19:I24) -> 0 | J25: =-SUM(J19:J24) -> 0 | K25: =-SUM(K19:K24) -> 0 | ... AI25: =-SUM(AI19:AI24) -> -204714.11
C26: Impostos Lei 10.833 | U26: =16.7+28.55+67.15+313.89 -> 426.29 | Z26: 174.38 | AE26: 48.95 | AI26: =SUM(D26:AH26) -> 649.62
C27: IRRF | U27: =21.66+56.25+19.79+51.94+126.25+267.2 -> 543.09 | AI27: =SUM(D27:AH27) -> 543.09
C28: ISS a Recolher | M28: 40487.35 | AI28: =SUM(D28:AH28) -> 40487.35
C29: ISS Retido a Recolher | AI29: =SUM(D29:AH29) -> 0
C30: INSS Retido a Recolher | AI30: =SUM(D30:AH30) -> 0
C31: IPTU a Pagar | M31: =10499.41+13458.32 -> 23957.73 | AI31: =SUM(D31:AH31) -> 23957.73
C32: PIS a Recolher | AB32: 5245.79 | AI32: =SUM(D32:AH32) -> 5245.79
C33: COFINS a Recolher | AB33: 24211.33 | AI33: =SUM(D33:AH33) -> 24211.33
C34: IRPJ a Recolher | AI34: =SUM(D34:AH34) -> 0
C35: CSLL a Recolher | AI35: =SUM(D35:AH35) -> 0
C36: Total de Impostos | D36: =-SUM(D26:D35) -> 0 | E36: =-SUM(E26:E35) -> 0 | F36: =-SUM(F26:F35) -> 0 | G36: =-SUM(G26:G35) -> 0 | H36: =-SUM(H26:H35) -> 0 | I36: =-SUM(I26:I35) -> 0 | J36: =-SUM(J26:J35) -> 0 | K36: =-SUM(K26:K35) -> 0 | ... AI36: =-SUM(AI26:AI35) -> -95094.91
C37: Água e Esgoto | AI37: =SUM(D37:AH37) -> 0
C38: Energia Elétrica | L38: 6704.19 | M38: =8577.33+19.55 -> 8596.88 | AB38: 122.98 | AG38: =135.36+18.46 -> 153.82 | AI38: =SUM(D38:AH38) -> 15577.87
C39: Telefone | AI39: =SUM(D39:AH39) -> 0
C40: Total de Contas de Consumo | D40: =-SUM(D37:D39) -> 0 | E40: =-SUM(E37:E39) -> 0 | F40: =-SUM(F37:F39) -> 0 | G40: =-SUM(G37:G39) -> 0 | H40: =-SUM(H37:H39) -> 0 | I40: =-SUM(I37:I39) -> 0 | J40: =-SUM(J37:J39) -> 0 | K40: =-SUM(K37:K39) -> 0 | ... AI40: =-SUM(AI37:AI39) -> -15577.87
C41: Adiantamento Dividendos | X41: =14149.5+13761.75+21619.99+30644.27+15445.85+11447.68+9710.14+12746.02+9299.67+35421.66+12957.78+2369.49 -> 189573.8 | AI41: =SUM(D41:AH41) -> 189573.8
C42: Fundo de Reserva | AI42: =SUM(D42:AH42) -> 0
C43: Adiantamento a Fornecedor | U43: =21860+16000 -> 37860 | Y43: 13000 | Z43: 28000 | AE43: 10200 | AG43: 46000 | AI43: =SUM(D43:AH43) -> 135060
C44: Gastos Gerais do Proprietário | AI44: =SUM(D44:AH44) -> 0
C45: Taxa de Condomínio | E45: =43631.85 -> 43631.85 | K45: 27352.78 | Q45: 55652.33 | AI45: =SUM(D45:AH45) -> 126636.96
C46: Taxa de Processamento / Administração / Reservas | M46: =14014.82+7919.79 -> 21934.61 | X46: 17822.78 | AI46: =SUM(D46:AH46) -> 39757.39
C47: Despesa Comissão Agências de Viagens | E47: =28+28+199.2+12329.06 -> 12584.26 | G47: =615.3 -> 615.3 | K47: =166+56 -> 222 | M47: =3410.81+2944.24+1049.92 -> 7404.97 | N47: =1532.5+228.78+56+53.1 -> 1870.38 | Q47: =879.02 -> 879.02 | R47: 87.4 | S47: =8528.33+180.2 -> 8708.53 | U47: =1876.47+6546.08 -> 8422.55 | Z47: =89.4+84 -> 173.4 | AB47: =137.5 -> 137.5 | AE47: =855.08+197.2+2032.4+112+52 -> 3248.68 | AG47: 154 | AI47: =SUM(D47:AH47) -> 44507.99
C48: Serviço Prestado Gerente Geral | E48: 8062.17 | AI48: =SUM(D48:AH48) -> 8062.17
C49: Repasse Salário Vendas | AI49: =SUM(D49:AH49) -> 0
C50: Custo Livros/Jornais/Revistas | AB50: =153.9 -> 153.9 | AI50: =SUM(D50:AH50) -> 153.9
C51: Custo com Hospedes | E51: =100.28 -> 100.28 | N51: 139.7 | U51: =175.3 -> 175.3 | Z51: 187.3 | AB51: 270.8 | AG51: 202.7 | AI51: =SUM(D51:AH51) -> 1076.08
C52: Repasse Restaurante | AI52: =SUM(D52:AH52) -> 0
C53: Serviço Lavanderia | R53: 10210.52 | AG53: 8228.8 | AI53: =SUM(D53:AH53) -> 18439.32
C54: Assessoria Jurídica/Contábil e Auditoria | M54: 900.36 | AI54: =SUM(D54:AH54) -> 900.36
C55: Serviços Postais e de Entrega Rápida | M55: =674.6 -> 674.6 | AG55: 329.35 | AI55: =SUM(D55:AH55) -> 1003.95
C56: Aluguel de Equipamentos | AI56: =SUM(D56:AH56) -> 0
C57: Cópias e Autenticações | AI57: =SUM(D57:AH57) -> 0
C58: Ornamentação | AI58: =SUM(D58:AH58) -> 0
C59: Serviços Contratados PJ | E59: =3500+460 -> 3960 | G59: 3519.37 | N59: =1003.68 -> 1003.68 | R59: =1590+1355.19+342.5+585.45+720 -> 4593.14 | Z59: =1023 -> 1023 | AB59: =391.2 -> 391.2 | AG59: =3180+7950 -> 11130 | AI59: =SUM(D59:AH59) -> 25620.39
C60: Outros Serviços Contratados | AI60: =SUM(D60:AH60) -> 0
C61: Material de Manutenção / Pintura | AI61: =SUM(D61:AH61) -> 0
C62: Custo Ar Condicionado | AI62: =SUM(D62:AH62) -> 0
C63: Material de Limpeza | Q63: =920 -> 920 | U63: 439.99 | AI63: =SUM(D63:AH63) -> 1359.99
C64: Material de Apartamento | G64: =788.68 -> 788.68 | K64: 618.33 | N64: 788.68 | Q64: 14118 | S64: 5650 | U64: =788.68+481.5 -> 1270.18 | Z64: 2015 | AI64: =SUM(D64:AH64) -> 25248.87
C65: Material de Escritório/Serviços Gráficos | K65: 711 | AG65: =412.3 -> 412.3 | AI65: =SUM(D65:AH65) -> 1123.3
C66: Seguro Responsabilidade Civil | AI66: =SUM(D66:AH66) -> 0
C67: Despesa Viagens e Estadias | K67: 1260.74 | R67: 1800 | Z67: =333.29 -> 333.29 | AI67: =SUM(D67:AH67) -> 3394.03
C68: Reembolso KM | E68: =154.62+196.98 -> 351.6 | R68: =241.4+332.94+127.45+169.54+198.4+134.32+150.62 -> 1354.67 | AI68: =SUM(D68:AH68) -> 1706.27
C69: Promoção de Vendas | AB69: =2159 -> 2159 | AI69: =SUM(D69:AH69) -> 2159
C70: Associação de Classe | K70: 201 | N70: =242 -> 242 | AI70: =SUM(D70:AH70) -> 443
C71: Gastos Diversos | AI71: =SUM(D71:AH71) -> 0
C72: Despesas Bancárias | D72: 138.6 | E72: =23.1+80+(7.9*4) -> 134.7 | F72: =2.31+3.21 -> 5.52 | G72: =41.58+7.9 -> 49.48 | L72: =101.64 -> 101.64 | M72: =7.9*2 -> 15.8 | N72: =7.9*2 -> 15.8 | R72: =(7.9*3)+52.7 -> 76.4 | S72: =7.9+133.98 -> 141.88 | X72: 687.3 | Y72: =154.77 -> 154.77 | Z72: 7.9 | AB72: =55.44+7.9 -> 63.34 | AE72: =34.65 -> 34.65 | AF72: 71.61 | AG72: =7.9*2 -> 15.8 | AI72: =SUM(D72:AH72) -> 1715.19
C73: Cheques Não Compesados | AI73: =SUM(D73:AH73) -> 0
C74: Total de Serviços Contratados e Terceirizados | D74: =-SUM(D41:D73) -> -138.6 | E74: =-SUM(E41:E73) -> -68824.86 | F74: =-SUM(F41:F73) -> -5.52 | G74: =-SUM(G41:G73) -> -4972.83 | H74: =-SUM(H41:H73) -> 0 | I74: =-SUM(I41:I73) -> 0 | J74: =-SUM(J41:J73) -> 0 | K74: =-SUM(K41:K73) -> -30365.85 | ... AI74: =-SUM(AI41:AI73) -> -627941.96
C75: TOTAL DAS SAÍDAS | D75: =D25+D36+D40+D74 -> -138.6 | E75: =E25+E36+E40+E74 -> -68824.86 | F75: =F25+F36+F40+F74 -> -5.52 | G75: =G25+G36+G40+G74 -> -4972.83 | H75: =H25+H36+H40+H74 -> 0 | I75: =I25+I36+I40+I74 -> 0 | J75: =J25+J36+J40+J74 -> 0 | K75: =K25+K36+K40+K74 -> -30365.85 | ... AI75: =AI25+AI36+AI40+AI74 -> -943328.85
C77: SALDO DA CONTA CORRENTE | D77: =D6+D18+D75 -> 77802.199 | E77: =E6+E18+E75 -> 34669.959 | F77: =F6+F18+F75 -> 53412.769 | G77: =G6+G18+G75 -> 92413.069 | H77: =H6+H18+H75 -> 92413.069 | I77: =I6+I18+I75 -> 92413.069 | J77: =J6+J18+J75 -> 92413.069 | K77: =K6+K18+K75 -> 143460.55 | ... AI77: =AI6+AI18+AI75 -> 123402.72
B78: APLICAÇÕES
C79: APLICAÇÕES | D79: =Agosto!AH83 -> 513607.2 | E79: =D83 -> 513797.98 | F79: =E83 -> 513989.48 | G79: =F83 -> 514182.05 | H79: =G83 -> 514402.16 | I79: =H83 -> 514402.16 | J79: =I83 -> 514402.16 | K79: =J83 -> 514402.16 | L79: =K83 -> 514657.77 | ... AH79: =AG83 -> 517966.18
C80: Fundo Reserva | AH80: 31125.84 | AI80: =SUM(G80:AF80) -> 0
C81: Dividendos a Pagar | AI81: =SUM(G81:AF81) -> 0
C82: Rendimentos de Aplicações | D82: 190.78 | E82: 191.5 | F82: 192.57 | G82: 220.11 | K82: 255.61 | M82: =106.94+286.91 -> 393.85 | N82: 204.13 | Q82: 199.09 | R82: 200.94 | S82: 200.59 | T82: 201.33 | U82: 212 | X82: 204.96 | Y82: 204.19 | Z82: 204.97 | AA82: 207.49 | AB82: 232.96 | AE82: 230.17 | AF82: 208.87 | AG82: 202.87 | AI82: =SUM(G82:AF82) -> 3581.26
C83: SALDO DAS APLICAÇÕES | D83: =SUM(D80:D82)+D79 -> 513797.98 | E83: =SUM(E80:E82)+D83 -> 513989.48 | F83: =SUM(F80:F82)+E83 -> 514182.05 | G83: =SUM(G80:G82)+F83 -> 514402.16 | H83: =SUM(H80:H82)+G83 -> 514402.16 | I83: =SUM(I80:I82)+H83 -> 514402.16 | J83: =SUM(J80:J82)+I83 -> 514402.16 | K83: =SUM(K80:K82)+J83 -> 514657.77 | L83: =SUM(L80:L82)+K83 -> 514657.77 | ... AH83: =SUM(AH80:AH82)+AG83 -> 549092.02 | AI83: =AH83 -> 549092.02
C85: SALDO TOTAL | D85: =D77+D83 -> 591600.18 | E85: =E77+E83 -> 548659.44 | F85: =F77+F83 -> 567594.82 | G85: =G77+G83 -> 606815.23 | H85: =H77+H83 -> 606815.23 | I85: =I77+I83 -> 606815.23 | J85: =J77+J83 -> 606815.23 | K85: =K77+K83 -> 658118.32 | ... AI85: =AI77+AI83 -> 672494.74
C87: RESUMO DO DIA
C88: DATA ATUAL: | D88: =AG5 -> 42277
C89: SALDO INICIAL: | D89: =AG6 -> 242060.57
C90: ENTRADA PREVISTA: | D90: =AG18 -> 29099.06
C91: SAÍDA PREVISTA: | D91: =AG75 -> -147756.91
C92: SALDO PREVISTO C/C: | D92: =SUM(D89:D91) -> 123402.72 | L92: Financeiro | S92: Gerente Financeiro | Z92: Gerente Geral
C93: ADIANTAMENTO CLIENTES | D93: 12440.21
C94: ADIANTAMENTO DIVIDENDOS | D94: 3796.47
C95: FUNDO REPOSIÇÃO ATIVOS: | D95: 501526.63
C96: SALDO FINAL PREVISTO: | D96: =SUM(D92:D95) -> 641166.03

Sheet Outubro
B2: Fluxo de Caixa de Outubro de 2015
B4: ÍTEM / DESCRIÇÃO | D4: Realizado | E4: Previsto | F4: Previsto | G4: Previsto | H4: Previsto | I4: Previsto | J4: Previsto | K4: Previsto | L4: Previsto | M4: Previsto | N4: Previsto | O4: Previsto | P4: Previsto | Q4: Previsto | R4: Previsto | S4: Previsto | T4: Previsto | U4: Previsto | V4: Previsto | W4: Previsto | X4: Previsto | Y4: Previsto | Z4: Previsto | AA4: Previsto | AB4: Previsto | AC4: Previsto | AD4: Previsto | AE4: Previsto | AF4: Previsto | AG4: Previsto | AH4: Previsto
D5: 42278 | E5: =D5+1 -> 42279 | F5: =E5+1 -> 42280 | G5: =F5+1 -> 42281 | H5: =G5+1 -> 42282 | I5: =H5+1 -> 42283 | J5: =I5+1 -> 42284 | K5: =J5+1 -> 42285 | L5: =K5+1 -> 42286 | ... AH5: =AG5+1 -> 42308 | AI5: ACUMULADO
C6: SALDO ANTERIOR DA CONTA CORRENTE | D6: =Setembro!AG77 -> 123402.72 | E6: =D77 -> 129808.6 | F6: =E77 -> 144610.66 | G6: =F77 -> 145610.66 | H6: =G77 -> 146610.66 | I6: =H77 -> 158306.93 | J6: =I77 -> 167430.16 | K6: =J77 -> 176868.42 | L6: =K77 -> 189470.28 | ... AH6: =AG77 -> 376662 | AI6: =D6 -> 123402.72
B7: ENTRADAS | C7: Adiantamento de Clientes | D7: =434.5+525+270 -> 1229.5 | K7: =2881+273 -> 3154 | L7: =560+420+157+192.68 -> 1329.68 | O7: =10000+887.25+21.55+500 -> 11408.8 | P7: =520+420+509.55 -> 1449.55 | Q7: =210+157 -> 367 | R7: =31.05+21860+630+276.15 -> 22797.2 | S7: =35 -> 35 | V7: =443.62+239.4+1955.1 -> 2638.12 | W7: =1381+1822.1 -> 3203.1 | X7: =262.5+429.95+63+196.98+294 -> 1246.43 | Y7: =260 -> 260 | Z7: =4187.5+525 -> 4712.5 | AC7: =28 -> 28 | AD7: =186.95 -> 186.95 | AE7: =156.98 -> 156.98 | AI7: =SUM(D7:AH7) -> 54202.81
C8: Depósito RDS | L8: =662.43+166.1+278.4+432.8+497.06+579.15+971.17+1136.4 -> 4723.51 | W8: =2039.5+0.6+321.32+674.69+790.31+1180.7+1294.16+1547.48+2164.86+2282.65+2741.5 -> 15037.77 | Y8: =2228.65+2509.19+8700.77+20285.4 -> 33724.01 | AG8: 11728.51 | AI8: =SUM(D8:AH8) -> 65213.8
C9: Crédito Não Identificado | AI9: =SUM(D9:AH9) -> 0
C10: Fundo de Reserva | AI10: =SUM(D10:AH10) -> 0
C11: Faturas | D11: =9589.8+284.29 -> 9874.09 | E11: =7167.03 -> 7167.03 | K11: =9834.65+21212.1 -> 31046.75 | L11: =45241.86+19986+7368.5+428.89+5313.7 -> 78338.95 | O11: =10545.43+797.05+433.12 -> 11775.6 | P11: =15509.89+561.75+431.2+3897.98 -> 20400.82 | Q11: =18644.82+1575+2044.35+10601.85 -> 32866.02 | R11: =24384.65 -> 24384.65 | S11: =18958.33 -> 18958.33 | V11: =4432.19+262.5+2840.04+1659 -> 9193.73 | W11: =2525.18+866.25+577.5 -> 3968.93 | X11: =2301.95+90.09+842.11+561.41+561.41+786.74+647.43+6090+2352+211.75+1242.78+1767.92+4451.37 -> 21906.96 | Y11: =21000.96+609.45+1953 -> 23563.41 | Z11: =13843.25+1513 -> 15356.25 | AC11: =13633.98+20547.25+5852.63+420 -> 40453.86 | AD11: =5714.27+561.41+4654.65 -> 10930.33 | AE11: =6131.44+3078 -> 9209.44 | AF11: =41912.13+3087.75 -> 44999.88 | AG11: =441 -> 441 | AI11: =SUM(D11:AH11) -> 414836.03
C12: Receitas Diversas | D12: 2.63 | AI12: =SUM(D12:AH12) -> 2.63
C13: Amex | D13: 1924.03 | E13: 4578.36 | H13: 1976.54 | I13: 355 | J13: 2004.45 | K13: 1485.03 | L13: 2672.32 | P13: 3713.48 | Q13: 2561.11 | R13: 6681.91 | S13: 4645.63 | V13: 4842.35 | W13: 1937.15 | X13: 2433.3 | Y13: 2137.48 | Z13: 1243.51 | AC13: 8925.49 | AD13: 1001.15 | AE13: 2199.19 | AF13: 634.28 | AG13: 859.5 | AI13: =SUM(D13:AH13) -> 58811.26
C14: Visa Electron | D14: 1701.29 | E14: 156.3 | F14: 500 | G14: 500 | H14: 500 | I14: 500 | J14: 500 | K14: 500 | L14: 500 | M14: 500 | N14: 500 | O14: 500 | P14: 500 | Q14: 500 | R14: 500 | S14: 500 | T14: 500 | U14: 500 | V14: 500 | W14: 500 | X14: 500 | Y14: 500 | Z14: 500 | AA14: 500 | AB14: 500 | AC14: 500 | AD14: 500 | AE14: 500 | AF14: 500 | AG14: 500 | AI14: =SUM(D14:AH14) -> 15857.59
C15: Master Débito | D15: 398.27 | E15: 777.78 | F15: 500 | G15: 500 | H15: 500 | I15: 500 | J15: 500 | K15: 500 | L15: 500 | M15: 500 | N15: 500 | O15: 500 | P15: 500 | Q15: 500 | R15: 500 | S15: 500 | T15: 500 | U15: 500 | V15: 500 | W15: 500 | X15: 500 | Y15: 500 | Z15: 500 | AA15: 500 | AB15: 500 | AC15: 500 | AD15: 500 | AE15: 500 | AF15: 500 | AG15: 500 | AI15: =SUM(D15:AH15) -> 15176.05
C16: Visa Crédito | D16: 7513.18 | E16: 6942.5 | H16: 24664.46 | I16: 5299.16 | J16: 5637.13 | K16: 4677.87 | L16: 7311.33 | P16: 16800.11 | Q16: 10608.42 | R16: 10734.04 | S16: 6190.82 | V16: 14819.87 | W16: 3381.47 | X16: 6710.58 | Y16: 6078.15 | Z16: 8554.69 | AC16: 19977.28 | AD16: 4337.37 | AE16: 7818.55 | AF16: 10077.19 | AG16: 3604.6 | AI16: =SUM(D16:AH16) -> 191738.77
C17: Master Crédito | D17: 583.84 | E17: 3756.96 | H17: 8978.62 | I17: 2469.07 | J17: 796.68 | K17: 1604.06 | L17: 1750.66 | P17: 10693.73 | Q17: 1891.14 | R17: 2106.52 | S17: 3675.91 | V17: =123.14+10518.33 -> 10641.47 | W17: 1659.43 | X17: 3712.28 | Y17: 2478.78 | Z17: 1173.16 | AC17: 12994.29 | AD17: 1704.79 | AE17: 3178.52 | AF17: 4792.74 | AG17: 3424.14 | AI17: =SUM(D17:AH17) -> 84066.79
C18: TOTAL DAS ENTRADAS | D18: =SUM(D7:D17) -> 23226.83 | E18: =SUM(E7:E17) -> 23378.93 | F18: =SUM(F7:F17) -> 1000 | G18: =SUM(G7:G17) -> 1000 | H18: =SUM(H7:H17) -> 36619.62 | I18: =SUM(I7:I17) -> 9123.23 | J18: =SUM(J7:J17) -> 9438.26 | K18: =SUM(K7:K17) -> 42967.71 | L18: =SUM(L7:L17) -> 97126.45 | M18: =SUM(O7:O17) -> 24184.4 | N18: =SUM(P7:P17) -> 54057.69 | O18: =SUM(Q7:Q17) -> 49293.69 | P18: =SUM(R7:R17) -> 67704.32 | Q18: =SUM(S7:S17) -> 34505.69 | R18: =SUM(V7:V17) -> 43135.54 | S18: =SUM(S7:S17) -> 34505.69 | T18: =SUM(V7:V17) -> 43135.54 | U18: =SUM(W7:W17) -> 30187.85 | V18: =SUM(X7:X17) -> 37009.55 | W18: =SUM(Y7:Y17) -> 69241.83 | X18: =SUM(Z7:Z17) -> 32040.11 | Y18: =SUM(Y7:Y17) -> 69241.83 | Z18: =SUM(Z7:Z17) -> 32040.11 | AA18: =SUM(AC7:AC17) -> 83378.92 | AB18: =SUM(AD7:AD17) -> 19160.59 | AC18: =SUM(AE7:AE17) -> 23562.68 | AD18: =SUM(AF7:AF17) -> 61504.09 | AE18: =SUM(AG7:AG17) -> 21057.75 | AF18: =SUM(AF7:AF17) -> 61504.09 | AG18: =SUM(AG7:AG17) -> 21057.75 | AI18: =SUM(D18:AH18) -> 1155390.7
C19: Repasse Salários e Encargos | AI19: =SUM(D19:AH19) -> 0
B20: SAIDAS | C20: Repasse Aluguel de Salas e Equipamentos | AI20: =SUM(D20:AH20) -> 0
C21: Repasse A&B | R21: =594+387.2+84983.42+36264+326.7+454.65 -> 123009.97 | AG21: 81130.14 | AI21: =SUM(D21:AH21) -> 204140.11
C22: Repasse Telefonia | AI22: =SUM(D22:AH22) -> 0
C23: Repasse Internet | AI23: =SUM(D23:AH23) -> 0
C24: Repasse Diversos | Q24: 574 | AI24: =SUM(D24:AH24) -> 574
C25: Repasse ao Condomínio | D25: =-SUM(D19:D24) -> 0 | E25: =-SUM(E19:E24) -> 0 | F25: =-SUM(F19:F24) -> 0 | G25: =-SUM(G19:G24) -> 0 | H25: =-SUM(H19:H24) -> 0 | I25: =-SUM(I19:I24) -> 0 | J25: =-SUM(J19:J24) -> 0 | K25: =-SUM(K19:K24) -> 0 | ... AI25: =-SUM(AI19:AI24) -> -204714.11
C26: Impostos Lei 10.833 | E26: =16.7+67.15+28.55 -> 112.4 | V26: =16.7+28.55+67.15+313.89 -> 426.29 | Z26: 174.38 | AE26: 48.95 | AI26: =SUM(D26:AH26) -> 762.02
C27: IRRF | V27: =21.66+56.25+19.79+51.94+126.25+267.2 -> 543.09 | AI27: =SUM(D27:AH27) -> 543.09
C28: ISS a Recolher | L28: 40487.35 | AI28: =SUM(D28:AH28) -> 40487.35
C29: ISS Retido a Recolher | AI29: =SUM(D29:AH29) -> 0
C30: INSS Retido a Recolher | AI30: =SUM(D30:AH30) -> 0
C31: IPTU a Pagar | L31: =10499.41+13458.32 -> 23957.73 | AI31: =SUM(D31:AH31) -> 23957.73
C32: PIS a Recolher | Z32: 5245.79 | AI32: =SUM(D32:AH32) -> 5245.79
C33: COFINS a Recolher | Z33: 24211.33 | AI33: =SUM(D33:AH33) -> 24211.33
C34: IRPJ a Recolher | AI34: =SUM(D34:AH34) -> 0
C35: CSLL a Recolher | AI35: =SUM(D35:AH35) -> 0
C36: Total de Impostos | D36: =-SUM(D26:D35) -> 0 | E36: =-SUM(E26:E35) -> -112.4 | F36: =-SUM(F26:F35) -> 0 | G36: =-SUM(G26:G35) -> 0 | H36: =-SUM(H26:H35) -> 0 | I36: =-SUM(I26:I35) -> 0 | J36: =-SUM(J26:J35) -> 0 | K36: =-SUM(K26:K35) -> 0 | ... AI36: =-SUM(AI26:AI35) -> -95207.31
C37: Água e Esgoto | AI37: =SUM(D37:AH37) -> 0
C38: Energia Elétrica | D38: 16774.75 | AG38: =135.36+18.46 -> 153.82 | AI38: =SUM(D38:AH38) -> 16928.57
C39: Telefone | AI39: =SUM(D39:AH39) -> 0
C40: Total de Contas de Consumo | D40: =-SUM(D37:D39) -> -16774.75 | E40: =-SUM(E37:E39) -> 0 | F40: =-SUM(F37:F39) -> 0 | G40: =-SUM(G37:G39) -> 0 | H40: =-SUM(H37:H39) -> 0 | I40: =-SUM(I37:I39) -> 0 | J40: =-SUM(J37:J39) -> 0 | K40: =-SUM(K37:K39) -> 0 | ... AI40: =-SUM(AI37:AI39) -> -16928.57
C41: Adiantamento Dividendos | X41: =14149.5+13761.75+21619.99+30644.27+15445.85+11447.68+9710.14+12746.02+9299.67+35421.66+12957.78+2369.49 -> 189573.8 | AI41: =SUM(D41:AH41) -> 189573.8
C42: Fundo de Reserva | H42: 20000 | AG42: 11000 | AI42: =SUM(D42:AH42) -> 31000
C43: Adiantamento a Fornecedor | S43: =21860+16000 -> 37860 | Y43: 13000 | Z43: 28000 | AE43: 10200 | AG43: 46000 | AI43: =SUM(D43:AH43) -> 135060
C44: Gastos Gerais do Proprietário | AI44: =SUM(D44:AH44) -> 0
C45: Taxa de Condomínio | K45: 27352.78 | Q45: 55652.33 | AI45: =SUM(D45:AH45) -> 83005.11
C46: Taxa de Processamento / Administração / Reservas | L46: =14014.82+7919.79 -> 21934.61 | X46: 17822.78 | AI46: =SUM(D46:AH46) -> 39757.39
C47: Despesa Comissão Agências de Viagens | E47: =140+140 -> 280 | H47: =615.3 -> 615.3 | K47: =166+56 -> 222 | L47: =3410.81+2944.24+1049.92 -> 7404.97 | Q47: =879.02 -> 879.02 | R47: 87.4 | S47: =8528.33+180.2 -> 8708.53 | Z47: =89.4+84 -> 173.4 | AC47: =137.5 -> 137.5 | AE47: =855.08+197.2+2032.4+112+52 -> 3248.68 | AG47: 154 | AI47: =SUM(D47:AH47) -> 21910.8
C48: Serviço Prestado Gerente Geral | E48: 8062.17 | AI48: =SUM(D48:AH48) -> 8062.17
C49: Repasse Salário Vendas | AI49: =SUM(D49:AH49) -> 0
C50: Custo Livros/Jornais/Revistas | AC50: =153.9 -> 153.9 | AI50: =SUM(D50:AH50) -> 153.9
C51: Custo com Hospedes | L51: 139.7 | S51: =175.3 -> 175.3 | Z51: 187.3 | AC51: 270.8 | AI51: =SUM(D51:AH51) -> 773.1
C52: Repasse Restaurante | AI52: =SUM(D52:AH52) -> 0
C53: Serviço Lavanderia | R53: 10210.52 | AG53: 8228.8 | AI53: =SUM(D53:AH53) -> 18439.32
C54: Assessoria Jurídica/Contábil e Auditoria | L54: 900.36 | AI54: =SUM(D54:AH54) -> 900.36
C55: Serviços Postais e de Entrega Rápida | L55: =674.6 -> 674.6 | AG55: 329.35 | AI55: =SUM(D55:AH55) -> 1003.95
C56: Aluguel de Equipamentos | AI56: =SUM(D56:AH56) -> 0
C57: Cópias e Autenticações | AI57: =SUM(D57:AH57) -> 0
C58: Ornamentação | AI58: =SUM(D58:AH58) -> 0
C59: Serviços Contratados PJ | H59: 3519.37 | L59: =1003.68 -> 1003.68 | R59: =1590+1355.19+342.5+585.45+720 -> 4593.14 | Z59: =1023 -> 1023 | AC59: =391.2 -> 391.2 | AG59: =3180+7950 -> 11130 | AI59: =SUM(D59:AH59) -> 21660.39
C60: Outros Serviços Contratados | AI60: =SUM(D60:AH60) -> 0
C61: Material de Manutenção / Pintura | AI61: =SUM(D61:AH61) -> 0
C62: Custo Ar Condicionado | AI62: =SUM(D62:AH62) -> 0
C63: Material de Limpeza | Q63: =920 -> 920 | S63: 439.99 | AI63: =SUM(D63:AH63) -> 1359.99
C64: Material de Apartamento | H64: =788.68 -> 788.68 | K64: 618.33 | L64: 788.68 | Q64: 14118 | S64: 5650 | Z64: 2015 | AI64: =SUM(D64:AH64) -> 23978.69
C65: Material de Escritório/Serviços Gráficos | K65: 711 | AG65: =412.3 -> 412.3 | AI65: =SUM(D65:AH65) -> 1123.3
C66: Seguro Responsabilidade Civil | AI66: =SUM(D66:AH66) -> 0
C67: Despesa Viagens e Estadias | K67: 1260.74 | R67: 1800 | Z67: =333.29 -> 333.29 | AI67: =SUM(D67:AH67) -> 3394.03
C68: Reembolso KM | R68: =241.4+332.94+127.45+169.54+198.4+134.32+150.62 -> 1354.67 | AI68: =SUM(D68:AH68) -> 1354.67
C69: Promoção de Vendas | E69: 122.3 | AC69: =2159 -> 2159 | AI69: =SUM(D69:AH69) -> 2281.3
C70: Associação de Classe | K70: 201 | L70: =242 -> 242 | AI70: =SUM(D70:AH70) -> 443
C71: Gastos Diversos | AI71: =SUM(D71:AH71) -> 0
C72: Despesas Bancárias | D72: =46.2 -> 46.2 | AI72: =SUM(D72:AH72) -> 46.2
C73: Cheques Não Compesados | AI73: =SUM(D73:AH73) -> 0
C74: Total de Serviços Contratados e Terceirizados | D74: =-SUM(D41:D73) -> -46.2 | E74: =-SUM(E41:E73) -> -8464.47 | F74: =-SUM(F41:F73) -> 0 | G74: =-SUM(G41:G73) -> 0 | H74: =-SUM(H41:H73) -> -24923.35 | I74: =-SUM(I41:I73) -> 0 | J74: =-SUM(J41:J73) -> 0 | K74: =-SUM(K41:K73) -> -30365.85 | ... AI74: =-SUM(AI41:AI73) -> -585281.47
C75: TOTAL DAS SAÍDAS | D75: =D25+D36+D40+D74 -> -16820.95 | E75: =E25+E36+E40+E74 -> -8576.87 | F75: =F25+F36+F40+F74 -> 0 | G75: =G25+G36+G40+G74 -> 0 | H75: =H25+H36+H40+H74 -> -24923.35 | I75: =I25+I36+I40+I74 -> 0 | J75: =J25+J36+J40+J74 -> 0 | K75: =K25+K36+K40+K74 -> -30365.85 | ... AI75: =AI25+AI36+AI40+AI74 -> -902131.46
C77: SALDO DA CONTA CORRENTE | D77: =D6+D18+D75 -> 129808.6 | E77: =E6+E18+E75 -> 144610.66 | F77: =F6+F18+F75 -> 145610.66 | G77: =G6+G18+G75 -> 146610.66 | H77: =H6+H18+H75 -> 158306.93 | I77: =I6+I18+I75 -> 167430.16 | J77: =J6+J18+J75 -> 176868.42 | K77: =K6+K18+K75 -> 189470.28 | ... AI77: =AI6+AI18+AI75 -> 376662
B78: APLICAÇÕES
C79: APLICAÇÕES | D79: =Setembro!AG83 -> 517966.18 | E79: =D83 -> 518169.16 | F79: =E83 -> 518169.16 | G79: =F83 -> 518169.16 | H79: =G83 -> 518169.16 | I79: =H83 -> 518169.16 | J79: =I83 -> 518169.16 | K79: =J83 -> 518169.16 | L79: =K83 -> 518169.16 | ... AH79: =AG83 -> 518169.16
C80: Fundo Reserva | AH80: 31125.84 | AI80: =SUM(G80:AF80) -> 0
C81: Dividendos a Pagar | AI81: =SUM(G81:AF81) -> 0
C82: Rendimentos de Aplicações | D82: 202.98 | AI82: =SUM(G82:AF82) -> 0
C83: SALDO DAS APLICAÇÕES | D83: =SUM(D80:D82)+D79 -> 518169.16 | E83: =SUM(E80:E82)+D83 -> 518169.16 | F83: =SUM(F80:F82)+E83 -> 518169.16 | G83: =SUM(G80:G82)+F83 -> 518169.16 | H83: =SUM(H80:H82)+G83 -> 518169.16 | I83: =SUM(I80:I82)+H83 -> 518169.16 | J83: =SUM(J80:J82)+I83 -> 518169.16 | K83: =SUM(K80:K82)+J83 -> 518169.16 | L83: =SUM(L80:L82)+K83 -> 518169.16 | ... AH83: =SUM(AH80:AH82)+AG83 -> 549295 | AI83: =AH83 -> 549295
C85: SALDO TOTAL | D85: =D77+D83 -> 647977.76 | E85: =E77+E83 -> 662779.82 | F85: =F77+F83 -> 663779.82 | G85: =G77+G83 -> 664779.82 | H85: =H77+H83 -> 676476.09 | I85: =I77+I83 -> 685599.32 | J85: =J77+J83 -> 695037.58 | K85: =K77+K83 -> 707639.44 | ... AI85: =AI77+AI83 -> 925957
C87: RESUMO DO DIA
C88: DATA ATUAL: | D88: =E5 -> 42279
C89: SALDO INICIAL: | D89: =E6 -> 129808.6
C90: ENTRADA PREVISTA: | D90: =E18 -> 23378.93
C91: SAÍDA PREVISTA: | D91: =E75 -> -8576.87
C92: SALDO PREVISTO C/C: | D92: =SUM(D89:D91) -> 144610.66 | L92: Financeiro | S92: Gerente Financeiro | Z92: Gerente Geral
C93: ADIANTAMENTO CLIENTES | D93: 12447.78
C94: ADIANTAMENTO DIVIDENDOS | D94: 3799.18
C95: FUNDO REPOSIÇÃO ATIVOS: | D95: 501922.2
C96: SALDO FINAL PREVISTO: | D96: =SUM(D92:D95) -> 662779.82
