Workbook

Sheet Anexos
A1: ANEXO 01 | B1: PROVIMENTO 04/2000
A2: ANEXO 02 | B2: RESUMO GERAL
A3: ANEXO 03 | B3: DIFERENÇAS SALARIAIS NOS PARÂMETROS DO DETERMINADO EM SENTENÇA
A4: ANEXO 04 | B4: HORAS EXTRAS + REFLEXOS DEFERIDOS
A5: ANEXO 05 | B5: TIQUETE REFEIÇÃO
A6: ANEXO 06 | B6: APURAÇÃO DA CONTRIBUIÇÃO PREVIDENCIÁRIA
A7: ANEXO 06.1 | B7: APURAÇÃO DA CONTRIBUIÇÃO PREVIDENCIÁRIA (PLANILHA AUXILIAR)
A8: ANEXO 07 | B8: APURAÇÃO DO IMPOSTO DE RENDA RETIDO NA FONTE
A9: ANEXO 07.1 | B9: PLANILHA AUXILIAR DE APURAÇÃO DO IRRF
A10: ANEXO 08 | B10: TABELA ÚNICA PARA ATUALIZAÇÃO DE DÉBITOS TRABALHISTAS DISPONIBILIZADA PELO TRT MG - TABELA ATÉ 30/11/2013

Sheet Anexo 1 PROV
A1: PROCESSO:
A2: VARA: VARA DO TRABALHO DE BELO HORIZONTE - MG
A3: RECLAMANTE:
A4: RECLAMADA:
A6: ANEXO 1 - PROVIMENTO 04/2000
A8: Total Líquido devido ao reclamante, corrigido até 30/11/2013 | B8: R$ | C8: ='Anexo 2 RESUMO'!F39 -> 46023.161
A10: F.G.T.S (p/ depósito em conta vinculada) | B10: R$ | C10: 0
A12: INSS - cota reclamante | B12: R$ | C12: ='Anexo 2 RESUMO'!F35 -> 4067.95
A14: INSS - cota reclamada | B14: R$ | C14: ='Anexo 2 RESUMO'!F43 -> 6729
A16: IRRF | B16: R$ | C16: ='Anexo 2 RESUMO'!F37 -> 0
A18: Pensão Alimentícia | B18: R$ | C18: 0
A20: Honorários advocatícios ou sindical ( %) | B20: R$ | C20: 0
A22: Honorários Periciais a arbitrar | B22: R$ | C22: 0
A24: Custas processuais = R$ 400,00 (arbitradas em 01/04/2013) x 1,001415532 = | B24: R$ | C24: =400*E25 -> 400.56621
E25: ='Anexo 8 Tabela TRT'!L58 -> 1.0014155
A26: Despesas com Imprensa Oficial | B26: R$ | C26: 0
A28: TOTAL GERAL DA EXECUÇÃO ATÉ 30/11/2013 | B28: R$ | C28: =SUM(C8:C27) -> 57220.677

Sheet Anexo 2 RESUMO
A1: PROCESSO:
A2: VARA:
A3: RECLAMANTE:
A4: RECLAMADA:
A6: ANEXO 2 - RESUMO GERAL
A7: ANEXO 03
A8: DIFERENÇAS SALARIAIS NOS PARÂMETROS DO DETERMINADO EM SENTENÇA
A9: Valor Devido Corrigido | C9: R$ | D9: ='Anexo 3 Dif Sal'!H37 -> 1057.3982
A10: VALOR APURADO CORRIGIDO ATÉ 30/11/2013 | E10: R$ | F10: =SUM(D9:D9) -> 1057.3982
A12: ANEXO 04
A13: HORAS EXTRAS + REFLEXOS DEFERIDOS
A14: Valor Devido Corrigido | C14: R$ | D14: ='Anexo 4 HE'!U81 -> 23429.349
A15: F.G.T.S CORRIGIDO | C15: R$ | D15: ='Anexo 4 HE'!V81 -> 2628.5801
A16: VALOR APURADO CORRIGIDO ATÉ 30/11/2013 | E16: R$ | F16: =SUM(D14:D15) -> 26057.929
A18: ANEXO 05
A19: TIQUETE REFEIÇÃO
A20: Valor Devido Corrigido | C20: R$ | D20: ='Anexo 5 Tiquete'!F35 -> 3234.5333
A21: VALOR APURADO CORRIGIDO ATÉ 30/11/2013 | E21: R$ | F21: =SUM(D20:D20) -> 3234.5333
A23: Outras Verbas Deferidas:
A24: Danos Morais | C24: R$ | D24: =Outros!M5 -> 10014.155
A25: Multa Normativa | C25: R$ | D25: =Outros!G5 -> 2230.4658
A26: VALOR APURADO CORRIGIDO ATÉ 30/11/2013 | E26: R$ | F26: =SUM(D24:D25) -> 12244.621
A28: SOMA DOS VALORES APURADOS E CORRIGIDOS ATÉ 30/11/2013 | E28: R$ | F28: =SUM(F10:F26) -> 42594.482
A30: JUROS MORATÓRIOS | D30: ='Anexo 7 IRRF'!O22 -> 0.176 | E30: R$ | F30: =F28*D30 -> 7496.6288
A31: Juros do ajuizamento da ação (12/06/2012) até 30/11/2013
A33: VALOR BRUTO DEVIDO ATÉ 30/11/2013 | E33: R$ | F33: =F28+F30 -> 50091.111
A35: DEDUÇÃO INSS COTA RECLAMANTE | E35: R$ | F35: 4067.95
A37: DEDUÇÃO IRRF | E37: R$ | F37: 0
A39: VALOR LÍQUIDO DEVIDO ATÉ 30/11/2013 | E39: R$ | F39: =F33-F35-F37 -> 46023.161
A41: CONTRIBUIÇÃO PREVIDENCIÁRIA A RECOLHER
A42: Cota Reclamante | E42: =E37 -> R$ | F42: =F35 -> 4067.95
A43: Cota Reclamada ( sem a contribuição de terceiros) | D43: 0.21 | E43: =E42 -> R$ | F43: 6729
A45: SOMA CONTRIBUIÇÃO PREVIDENCIÁRIA A SER RECOLHIDA | E45: =E43 -> R$ | F45: =SUM(F42:F43) -> 10796.95
A47: IMPOSTO DE RENDA RETIDO A SER RECOLHIDO
A49: BASE DE CÁLCULO DO IR | E49: =E42 -> R$ | F49: ='Plan Aux IR'!G20 -> 20998.095
A51: IR A SER RECOLHIDO | E51: =E45 -> R$ | F51: =F37 -> 0

Sheet Anexo 3 Dif Sal
A1: PROCESSO:
A2: VARA:
A3: RECLAMANTE:
A4: RECLAMADA:
A6: ANEXO 3
A7: DIFERENÇAS SALARIAIS NOS PARÂMETROS DO DETERMINADO EM SENTENÇA
A9: Mês / Ano | B9: Salário Base | C9: Indices de Reajustes previstos nas CCTs acostadas aos autos | D9: Percentual de reajuste | E9: Salário Recomposto | F9: Diferenças Apuradas | G9: Correção Monetária - Tabela TRT para 30/11/2013
G10: Indices | H10: Valor
A12: Col. 1 | B12: Col. 2 | C12: Col. 3 | D12: Col. 4 | E12: Col. 5 | F12: Col. 6 | G12: Col. 7 | H12: Col. 8
A13: 40330 | B13: 1298.53 | E13: =B13 -> 1298.53 | F13: =E13-B13 -> 0 | G13: ='Anexo 8 Tabela TRT'!I60 -> 1.0215159 | H13: =F13*G13 -> 0
A14: 40360 | B14: 1298.53 | C14: Cláusula 2ª, CCT 2011/2012, fl. 45 (sobre o salário de jun/2010) | D14: 0.06 | E14: =(E13*D14)+E13 -> 1376.4418 | F14: =E14-B14 -> 77.9118 | G14: ='Anexo 8 Tabela TRT'!I61 -> 1.0203415 | H14: =F14*G14 -> 79.496639
A15: 40391 | B15: 1298.53 | E15: =E14 -> 1376.4418 | F15: =E15-B15 -> 77.9118 | G15: ='Anexo 8 Tabela TRT'!I62 -> 1.0194148 | H15: =F15*G15 -> 79.424442
A16: 40422 | B16: 1298.53 | E16: =E15 -> 1376.4418 | F16: =E16-B16 -> 77.9118 | G16: ='Anexo 8 Tabela TRT'!I63 -> 1.0186997 | H16: =F16*G16 -> 79.368725 | J16: O advogado não pediu reflexos em 13°salário, férias + 1/3 e FGTS
A17: 40452 | B17: 1298.53 | E17: =E16 -> 1376.4418 | F17: =E17-B17 -> 77.9118 | G17: ='Anexo 8 Tabela TRT'!I64 -> 1.0182191 | H17: =F17*G17 -> 79.331281
A18: 40483 | B18: 1367.35 | E18: =E17 -> 1376.4418 | F18: =E18-B18 -> 9.0918 | G18: ='Anexo 8 Tabela TRT'!I65 -> 1.0178771 | H18: =F18*G18 -> 9.2543347
A19: 40513 | B19: 1367.35 | E19: =E18 -> 1376.4418 | F19: =E19-B19 -> 9.0918 | G19: ='Anexo 8 Tabela TRT'!J54 -> 1.0164479 | H19: =F19*G19 -> 9.2413414
A20: 40544 | B20: 1367.35 | E20: =E19 -> 1376.4418 | F20: =E20-B20 -> 9.0918 | G20: ='Anexo 8 Tabela TRT'!J55 -> 1.0157217 | H20: =F20*G20 -> 9.2347386
A21: 40575 | B21: 1367.35 | E21: =E20 -> 1376.4418 | F21: =E21-B21 -> 9.0918 | G21: ='Anexo 8 Tabela TRT'!J56 -> 1.0151897 | H21: =F21*G21 -> 9.2299021
A22: 40603 | B22: 1367.35 | E22: =E21 -> 1376.4418 | F22: =E22-B22 -> 9.0918 | G22: ='Anexo 8 Tabela TRT'!J57 -> 1.0139608 | H22: =F22*G22 -> 9.218729
A23: 40634 | B23: 1367.35 | E23: =E22 -> 1376.4418 | F23: =E23-B23 -> 9.0918 | G23: ='Anexo 8 Tabela TRT'!J58 -> 1.0135868 | H23: =F23*G23 -> 9.2153285
A24: 40664 | B24: 1367.35 | E24: =E23 -> 1376.4418 | F24: =E24-B24 -> 9.0918 | G24: ='Anexo 8 Tabela TRT'!J59 -> 1.011998 | H24: =F24*G24 -> 9.2008832
A25: 40695 | B25: 1367.35 | E25: =E24 -> 1376.4418 | F25: =E25-B25 -> 9.0918 | G25: ='Anexo 8 Tabela TRT'!J60 -> 1.0108719 | H25: =F25*G25 -> 9.1906448
A26: 40725 | B26: 1367.35 | C26: Cláusula 2ª, CCT 2010/2011, fl. 63 (sobre o salário de jun/2011) | D26: 0.07 | E26: =(E25*D26)+E25 -> 1472.7927 | F26: =E26-B26 -> 105.44273 | G26: ='Anexo 8 Tabela TRT'!J61 -> 1.009631 | H26: =F26*G26 -> 106.45825
A27: 40756 | B27: 1367.35 | E27: =E26 -> 1472.7927 | F27: =E27-B27 -> 105.44273 | G27: ='Anexo 8 Tabela TRT'!J62 -> 1.0075394 | H27: =F27*G27 -> 106.2377
A28: 40787 | B28: 1367.35 | E28: =E27 -> 1472.7927 | F28: =E28-B28 -> 105.44273 | G28: ='Anexo 8 Tabela TRT'!J63 -> 1.0065298 | H28: =F28*G28 -> 106.13125
A29: 40817 | B29: 1435.72 | E29: =E28 -> 1472.7927 | F29: =E29-B29 -> 37.072726 | G29: ='Anexo 8 Tabela TRT'!J64 -> 1.0059062 | H29: =F29*G29 -> 37.291683
A30: 40848 | B30: 1435.72 | E30: =E29 -> 1472.7927 | F30: =E30-B30 -> 37.072726 | G30: ='Anexo 8 Tabela TRT'!J65 -> 1.0052578 | H30: =F30*G30 -> 37.267646
A31: 40878 | B31: 1435.72 | E31: =E30 -> 1472.7927 | F31: =E31-B31 -> 37.072726 | G31: ='Anexo 8 Tabela TRT'!K54 -> 1.0043167 | H31: =F31*G31 -> 37.232759
A32: 40909 | B32: 1435.72 | E32: =E31 -> 1472.7927 | F32: =E32-B32 -> 37.072726 | G32: ='Anexo 8 Tabela TRT'!K55 -> 1.0034497 | H32: =F32*G32 -> 37.200617
A33: 40940 | B33: 1435.72 | E33: =E32 -> 1472.7927 | F33: =E33-B33 -> 37.072726 | G33: ='Anexo 8 Tabela TRT'!K56 -> 1.0034497 | H33: =F33*G33 -> 37.200617
A34: 40969 | B34: 1435.72 | E34: =E33 -> 1472.7927 | F34: =E34-B34 -> 37.072726 | G34: ='Anexo 8 Tabela TRT'!K57 -> 1.0023792 | H34: =F34*G34 -> 37.16093
A35: 41024 | B35: =1435.72/30*25 -> 1196.4333 | E35: =E34/30*25 -> 1227.3273 | F35: =E35-B35 -> 30.893938 | G35: ='Anexo 8 Tabela TRT'!K58 -> 1.0021517 | H35: =F35*G35 -> 30.960413
A36: Reflexo no seguro desemprego (5 parcelas) | F36: 92.65 | G36: =G35 -> 1.0021517 | H36: =F36*G36 -> 92.849356
A37: TOTAL | H37: =SUM(H13:H36) -> 1057.3982

Sheet Anexo 4 HE
A1: PROCESSO:
A2: VARA:
A3: RECLAMANTE:
A4: RECLAMADA:
A6: ANEXO 4
A7: HORAS EXTRAS + REFLEXOS DEFERIDOS
A9: Mês / Ano | B9: Salário Base para as Horas Extras (incluindo o salário recomposto) | C9: Divisor conf. Senten-ça | D9: Valor de uma Hora de Trab. | E9: Valor de uma Hora Extra (60%) | F9: Valor de uma Hora Extra (90%) | G9: Quant. de Horas extras a pagar (60%) | I9: Quant. de Horas extras a pagar (90%) | K9: Horas de Intervalo Intrajornada | M9: Soma das Horas Extras Apuradas | N9: Horas Extras pagas nos recibos de salário | O9: Diferenças Apuradas em Horas Extras | P9: RSR sobre as Horas Extras | S9: Valores Devidos Horas Extras + RSR | T9: Correção Monetária - Tabela TRT para 30/11/2013 | V9: FGTS Atualizado (8% + 40%)
G10: Quant. de Horas em centesimais | H10: Valor apurado | I10: Quant. de Horas em centesimais | J10: Valor apurado | K10: Quant. de Horas em centesimais | L10: Valor apurado | P10: Dias Uteis | Q10: Dias de Repou-so | R10: Valor Apurado | T10: Indices | U10: Valor
A12: Col. 1 | B12: Col. 2 | C12: Col. 3 | D12: Col. 4 | E12: Col. 5 | F12: Col. 6 | G12: Col. 7 | H12: Col. 8 | I12: Col. 9 | J12: Col. 10 | K12: Col. 11 | L12: Col. 12 | M12: Col. 13 | N12: Col. 14 | O12: Col. 15 | P12: Col. 16 | Q12: Col. 17 | R12: Col. 18 | S12: Col. 19 | T12: Col. 20 | U12: Col. 21 | V12: Col. 22
A13: 39234 | B13: 850.9 | C13: 220 | D13: =B13/C13 -> 3.8677273 | E13: =D13*1.6 -> 6.1883636 | F13: =D13*1.9 -> 7.3486818 | G13: 17.55 | H13: =E13*G13 -> 108.60578 | I13: 0 | J13: =F13*I13 -> 0 | K13: 14 | L13: =E13*K13 -> 86.637091 | M13: =H13+J13+L13 -> 195.24287 | N13: 77.28 | O13: =M13-N13 -> 117.96287 | P13: 25 | Q13: 5 | R13: =O13/P13*Q13 -> 23.592575 | S13: =O13+R13 -> 141.55545 | T13: ='Anexo 8 Tabela TRT'!F60 -> 1.053497 | U13: =S13*T13 -> 149.12824 | V13: =U13*11.2% -> 16.702362
A14: 39264 | B14: 850.9 | C14: 220 | D14: =B14/C14 -> 3.8677273 | E14: =D14*1.6 -> 6.1883636 | F14: =D14*1.9 -> 7.3486818 | G14: 30.816667 | H14: =E14*G14 -> 190.70474 | I14: 2.3833333 | J14: =F14*I14 -> 17.514358 | K14: 22 | L14: =E14*K14 -> 136.144 | M14: =H14+J14+L14 -> 344.3631 | N14: 0 | O14: =M14-N14 -> 344.3631 | P14: 26 | Q14: 5 | R14: =O14/P14*Q14 -> 66.223673 | S14: =O14+R14 -> 410.58677 | T14: ='Anexo 8 Tabela TRT'!F61 -> 1.0519517 | U14: =S14*T14 -> 431.91744 | V14: =U14*11.2% -> 48.374753
A15: 39295 | B15: 893.37 | C15: 220 | D15: =B15/C15 -> 4.0607727 | E15: =D15*1.6 -> 6.4972364 | F15: =D15*1.9 -> 7.7154682 | G15: 31.716667 | H15: =E15*G15 -> 206.07068 | I15: 0.5 | J15: =F15*I15 -> 3.8577341 | K15: 22 | L15: =E15*K15 -> 142.9392 | M15: =H15+J15+L15 -> 352.86761 | N15: 0 | O15: =M15-N15 -> 352.86761 | P15: 26 | Q15: 5 | R15: =O15/P15*Q15 -> 67.859157 | S15: =O15+R15 -> 420.72677 | T15: ='Anexo 8 Tabela TRT'!F62 -> 1.0504118 | U15: =S15*T15 -> 441.93635 | V15: =U15*11.2% -> 49.496871
A16: 39326 | B16: 893.37 | C16: 220 | D16: =B16/C16 -> 4.0607727 | E16: =D16*1.6 -> 6.4972364 | F16: =D16*1.9 -> 7.7154682 | G16: 30.1 | H16: =E16*G16 -> 195.56681 | I16: 2.9333333 | J16: =F16*I16 -> 22.63204 | K16: 19 | L16: =E16*K16 -> 123.44749 | M16: =H16+J16+L16 -> 341.64635 | N16: 14.01 | O16: =M16-N16 -> 327.63635 | P16: 24 | Q16: 6 | R16: =O16/P16*Q16 -> 81.909086 | S16: =O16+R16 -> 409.54543 | T16: ='Anexo 8 Tabela TRT'!F63 -> 1.0500421 | U16: =S16*T16 -> 430.03996 | V16: =U16*11.2% -> 48.164476
A17: 39356 | B17: 893.37 | C17: 220 | D17: =B17/C17 -> 4.0607727 | E17: =D17*1.6 -> 6.4972364 | F17: =D17*1.9 -> 7.7154682 | G17: 35.416667 | H17: =E17*G17 -> 230.11045 | I17: 2.1666667 | J17: =F17*I17 -> 16.716848 | K17: 22 | L17: =E17*K17 -> 142.9392 | M17: =H17+J17+L17 -> 389.7665 | N17: 26.8 | O17: =M17-N17 -> 362.9665 | P17: 26 | Q17: 5 | R17: =O17/P17*Q17 -> 69.80125 | S17: =O17+R17 -> 432.76775 | T17: ='Anexo 8 Tabela TRT'!F64 -> 1.0488444 | U17: =S17*T17 -> 453.90602 | V17: =U17*11.2% -> 50.837474
A18: 39387 | B18: 893.37 | C18: 220 | D18: =B18/C18 -> 4.0607727 | E18: =D18*1.6 -> 6.4972364 | F18: =D18*1.9 -> 7.7154682 | G18: 30.166667 | H18: =E18*G18 -> 195.99996 | I18: 0.15 | J18: =F18*I18 -> 1.1573202 | K18: 20 | L18: =E18*K18 -> 129.94473 | M18: =H18+J18+L18 -> 327.10201 | N18: 216.02 | O18: =M18-N18 -> 111.08201 | P18: 24 | Q18: 6 | R18: =O18/P18*Q18 -> 27.770503 | S18: =O18+R18 -> 138.85251 | T18: ='Anexo 8 Tabela TRT'!F65 -> 1.0482259 | U18: =S18*T18 -> 145.5488 | V18: =U18*11.2% -> 16.301466
A19: 39417 | B19: 893.37 | C19: 220 | D19: =B19/C19 -> 4.0607727 | E19: =D19*1.6 -> 6.4972364 | F19: =D19*1.9 -> 7.7154682 | G19: 12.833333 | H19: =E19*G19 -> 83.3812 | I19: 0 | J19: =F19*I19 -> 0 | K19: 10 | L19: =E19*K19 -> 64.972364 | M19: =H19+J19+L19 -> 148.35356 | N19: 0 | O19: =M19-N19 -> 148.35356 | P19: 24 | Q19: 7 | R19: =O19/P19*Q19 -> 43.269789 | S19: =O19+R19 -> 191.62335 | T19: ='Anexo 8 Tabela TRT'!G54 -> 1.0475555 | U19: =S19*T19 -> 200.73609 | V19: =U19*11.2% -> 22.482442
A20: 13º Salário 2007 (Média) | B20: 893.37 | C20: 220 | D20: =B20/C20 -> 4.0607727 | E20: =D20*1.6 -> 6.4972364 | F20: =D20*1.9 -> 7.7154682 | G20: =AVERAGE(G13:G19)*7/12 -> 15.716667 | H20: =E20*G20 -> 102.1149 | I20: =AVERAGE(I13:I19)*7/12 -> 0.67777778 | J20: =F20*I20 -> 5.2293729 | K20: =AVERAGE(K13:K19)*7/12 -> 10.75 | L20: =E20*K20 -> 69.845291 | M20: =H20+J20+L20 -> 177.18956 | N20: 0 | O20: =M20-N20 -> 177.18956 | S20: =O20+R20 -> 177.18956 | T20: =T18 -> 1.0482259 | U20: =S20*T20 -> 185.73469 | V20: =U20*11.2% -> 20.802285
A21: 39448 | B21: 893.37 | C21: 220 | D21: =B21/C21 -> 4.0607727 | E21: =D21*1.6 -> 6.4972364 | F21: =D21*1.9 -> 7.7154682 | G21: 26.266667 | H21: =E21*G21 -> 170.66074 | I21: 2.5666667 | J21: =F21*I21 -> 19.803035 | K21: 18 | L21: =E21*K21 -> 116.95025 | M21: =H21+J21+L21 -> 307.41403 | N21: 25.88 | O21: =M21-N21 -> 281.53403 | P21: 26 | Q21: 5 | R21: =O21/P21*Q21 -> 54.14116 | S21: =O21+R21 -> 335.67519 | T21: ='Anexo 8 Tabela TRT'!G55 -> 1.0464985 | U21: =S21*T21 -> 351.28359 | V21: =U21*11.2% -> 39.343762
A22: 39479 | B22: 893.37 | C22: 220 | D22: =B22/C22 -> 4.0607727 | E22: =D22*1.6 -> 6.4972364 | F22: =D22*1.9 -> 7.7154682 | G22: 18 | H22: =E22*G22 -> 116.95025 | I22: 2 | J22: =F22*I22 -> 15.430936 | K22: 19 | L22: =E22*K22 -> 123.44749 | M22: =H22+J22+L22 -> 255.82868 | N22: 0 | O22: =M22-N22 -> 255.82868 | P22: 24 | Q22: 5 | R22: =O22/P22*Q22 -> 53.297642 | S22: =O22+R22 -> 309.12632 | T22: ='Anexo 8 Tabela TRT'!G56 -> 1.0462443 | U22: =S22*T22 -> 323.42165 | V22: =U22*11.2% -> 36.223224
A23: 39508 | B23: 893.37 | C23: 220 | D23: =B23/C23 -> 4.0607727 | E23: =D23*1.6 -> 6.4972364 | F23: =D23*1.9 -> 7.7154682 | G23: 13.5 | H23: =E23*G23 -> 87.712691 | I23: 0 | J23: =F23*I23 -> 0 | K23: 15 | L23: =E23*K23 -> 97.458545 | M23: =H23+J23+L23 -> 185.17124 | N23: 12.18 | O23: =M23-N23 -> 172.99124 | P23: 25 | Q23: 6 | R23: =O23/P23*Q23 -> 41.517897 | S23: =O23+R23 -> 214.50913 | T23: ='Anexo 8 Tabela TRT'!G57 -> 1.0458165 | U23: =S23*T23 -> 224.3372 | V23: =U23*11.2% -> 25.125766
A24: 39539 | B24: 955.91 | C24: 220 | D24: =B24/C24 -> 4.3450455 | E24: =D24*1.6 -> 6.9520727 | F24: =D24*1.9 -> 8.2555864 | G24: 23.166667 | H24: =E24*G24 -> 161.05635 | I24: 0 | J24: =F24*I24 -> 0 | K24: 21 | L24: =E24*K24 -> 145.99353 | M24: =H24+J24+L24 -> 307.04988 | N24: 8.22 | O24: =M24-N24 -> 298.82988 | P24: 25 | Q24: 5 | R24: =O24/P24*Q24 -> 59.765976 | S24: =O24+R24 -> 358.59585 | T24: ='Anexo 8 Tabela TRT'!G58 -> 1.0448187 | U24: =S24*T24 -> 374.66767 | V24: =U24*11.2% -> 41.962779
A25: 39569 | B25: 955.91 | C25: 220 | D25: =B25/C25 -> 4.3450455 | E25: =D25*1.6 -> 6.9520727 | F25: =D25*1.9 -> 8.2555864 | G25: 15.583333 | H25: =E25*G25 -> 108.33647 | I25: 0.016666667 | J25: =F25*I25 -> 0.13759311 | K25: 20 | L25: =E25*K25 -> 139.04145 | M25: =H25+J25+L25 -> 247.51551 | N25: 0 | O25: =M25-N25 -> 247.51551 | P25: 25 | Q25: 6 | R25: =O25/P25*Q25 -> 59.403723 | S25: =O25+R25 -> 306.91924 | T25: ='Anexo 8 Tabela TRT'!G59 -> 1.0440503 | U25: =S25*T25 -> 320.43913 | V25: =U25*11.2% -> 35.889182
A26: Férias + 1/3 (média) período aquisitivo 03/05/07 a 02/05/08 | G26: =(SUM(G13:G19)+SUM(G21:G25))/12 -> 23.759722 | H26: =E26*G26 -> 0 | I26: =(SUM(I13:I19)+SUM(I21:I25))/12 -> 1.0597222 | J26: =F26*I26 -> 0 | K26: =(SUM(K13:K19)+SUM(K21:K25))/12 -> 18.5 | L26: =E26*K26 -> 0 | M26: =H26+J26+L26 -> 0 | N26: 0 | O26: =M26-N26 -> 0 | S26: =O26+R26 -> 0 | T26: =T25 -> 1.0440503 | U26: =S26*T26 -> 0 | V26: =U26*11.2% -> 0
A27: 39600 | B27: 955.91 | C27: 220 | D27: =B27/C27 -> 4.3450455 | E27: =D27*1.6 -> 6.9520727 | F27: =D27*1.9 -> 8.2555864 | G27: 1.1166667 | H27: =E27*G27 -> 7.7631479 | I27: 0 | J27: =F27*I27 -> 0 | K27: 1 | L27: =E27*K27 -> 6.9520727 | M27: =H27+J27+L27 -> 14.715221 | N27: 44.27 | O27: =M27-N27 -> -29.554779 | P27: 25 | Q27: 5 | R27: 0 | S27: =O27+R27 -> -29.554779 | T27: ='Anexo 8 Tabela TRT'!G60 -> 1.0428552 | U27: =S27*T27 -> -30.821355 | V27: 0
A28: 39630 | B28: 955.91 | C28: 220 | D28: =B28/C28 -> 4.3450455 | E28: =D28*1.6 -> 6.9520727 | F28: =D28*1.9 -> 8.2555864 | G28: 19.45 | H28: =E28*G28 -> 135.21781 | I28: 0 | J28: =F28*I28 -> 0 | K28: 17 | L28: =E28*K28 -> 118.18524 | M28: =H28+J28+L28 -> 253.40305 | N28: 0 | O28: =M28-N28 -> 253.40305 | P28: 27 | Q28: 4 | R28: =O28/P28*Q28 -> 37.541193 | S28: =O28+R28 -> 290.94424 | T28: ='Anexo 8 Tabela TRT'!G61 -> 1.040863 | U28: =S28*T28 -> 302.8331 | V28: =U28*11.2% -> 33.917307
A29: 39661 | B29: 955.91 | C29: 220 | D29: =B29/C29 -> 4.3450455 | E29: =D29*1.6 -> 6.9520727 | F29: =D29*1.9 -> 8.2555864 | G29: 23.996667 | H29: =E29*G29 -> 166.82657 | I29: 0.85 | J29: =F29*I29 -> 7.0172484 | K29: 22 | L29: =E29*K29 -> 152.9456 | M29: =H29+J29+L29 -> 326.78942 | N29: 23.1 | O29: =M29-N29 -> 303.68942 | P29: 25 | Q29: 6 | R29: =O29/P29*Q29 -> 72.885461 | S29: =O29+R29 -> 376.57488 | T29: ='Anexo 8 Tabela TRT'!G62 -> 1.0392272 | U29: =S29*T29 -> 391.34688 | V29: =U29*11.2% -> 43.83085
A30: 39692 | B30: 955.91 | C30: 220 | D30: =B30/C30 -> 4.3450455 | E30: =D30*1.6 -> 6.9520727 | F30: =D30*1.9 -> 8.2555864 | G30: 18.433333 | H30: =E30*G30 -> 128.14987 | I30: 0 | J30: =F30*I30 -> 0 | K30: 21 | L30: =E30*K30 -> 145.99353 | M30: =H30+J30+L30 -> 274.1434 | N30: 53.96 | O30: =M30-N30 -> 220.1834 | P30: 26 | Q30: 4 | R30: =O30/P30*Q30 -> 33.874369 | S30: =O30+R30 -> 254.05777 | T30: ='Anexo 8 Tabela TRT'!G63 -> 1.037184 | U30: =S30*T30 -> 263.50465 | V30: =U30*11.2% -> 29.512521
A31: 39722 | B31: 955.91 | C31: 220 | D31: =B31/C31 -> 4.3450455 | E31: =D31*1.6 -> 6.9520727 | F31: =D31*1.9 -> 8.2555864 | G31: 17.05 | H31: =E31*G31 -> 118.53284 | I31: 0 | J31: =F31*I31 -> 0 | K31: 22 | L31: =E31*K31 -> 152.9456 | M31: =H31+J31+L31 -> 271.47844 | N31: 0 | O31: =M31-N31 -> 271.47844 | P31: 27 | Q31: 4 | R31: =O31/P31*Q31 -> 40.219028 | S31: =O31+R31 -> 311.69747 | T31: ='Anexo 8 Tabela TRT'!G64 -> 1.0345913 | U31: =S31*T31 -> 322.47949 | V31: =U31*11.2% -> 36.117703
A32: 39753 | B32: 955.91 | C32: 220 | D32: =B32/C32 -> 4.3450455 | E32: =D32*1.6 -> 6.9520727 | F32: =D32*1.9 -> 8.2555864 | G32: 17.833333 | H32: =E32*G32 -> 123.97863 | I32: 0 | J32: =F32*I32 -> 0 | K32: 22 | L32: =E32*K32 -> 152.9456 | M32: =H32+J32+L32 -> 276.92423 | N32: 2.68 | O32: =M32-N32 -> 274.24423 | P32: 24 | Q32: 6 | R32: =O32/P32*Q32 -> 68.561058 | S32: =O32+R32 -> 342.80529 | T32: ='Anexo 8 Tabela TRT'!G65 -> 1.03292 | U32: =S32*T32 -> 354.09045 | V32: =U32*11.2% -> 39.658131
A33: 39783 | B33: 955.91 | C33: 220 | D33: =B33/C33 -> 4.3450455 | E33: =D33*1.6 -> 6.9520727 | F33: =D33*1.9 -> 8.2555864 | G33: 18.266667 | H33: =E33*G33 -> 126.9912 | I33: 0 | J33: =F33*I33 -> 0 | K33: 20 | L33: =E33*K33 -> 139.04145 | M33: =H33+J33+L33 -> 266.03265 | N33: 21.53 | O33: =M33-N33 -> 244.50265 | P33: 25 | Q33: 6 | R33: =O33/P33*Q33 -> 58.680636 | S33: =O33+R33 -> 303.18329 | T33: ='Anexo 8 Tabela TRT'!H54 -> 1.0307051 | U33: =S33*T33 -> 312.49255 | V33: =U33*11.2% -> 34.999165
A34: 13º Salário 2008 (Média) | B34: 955.91 | C34: 220 | D34: =B34/C34 -> 4.3450455 | E34: =D34*1.6 -> 6.9520727 | F34: =D34*1.9 -> 8.2555864 | G34: =(SUM(G21:G25)+SUM(G27:G33))/12 -> 17.721944 | H34: =E34*G34 -> 123.20425 | I34: =(SUM(I21:I25)+SUM(I27:I33))/12 -> 0.45277778 | J34: =F34*I34 -> 3.737946 | K34: =(SUM(K21:K25)+SUM(K27:K33))/12 -> 18.166667 | L34: =E34*K34 -> 126.29599 | M34: =H34+J34+L34 -> 253.23818 | N34: 0 | O34: =M34-N34 -> 253.23818 | S34: =O34+R34 -> 253.23818 | T34: =T32 -> 1.03292 | U34: =S34*T34 -> 261.57479 | V34: =U34*11.2% -> 29.296377
A35: 39814 | B35: 955.91 | C35: 220 | D35: =B35/C35 -> 4.3450455 | E35: =D35*1.6 -> 6.9520727 | F35: =D35*1.9 -> 8.2555864 | G35: 20.95 | H35: =E35*G35 -> 145.64592 | I35: 2.8666667 | J35: =F35*I35 -> 23.666014 | K35: 16 | L35: =E35*K35 -> 111.23316 | M35: =H35+J35+L35 -> 280.5451 | N35: 0 | O35: =M35-N35 -> 280.5451 | P35: 26 | Q35: 5 | R35: =O35/P35*Q35 -> 53.950981 | S35: =O35+R35 -> 334.49608 | T35: ='Anexo 8 Tabela TRT'!H55 -> 1.028812 | U35: =S35*T35 -> 344.1336 | V35: =U35*11.2% -> 38.542963
A36: 39845 | B36: 955.91 | C36: 220 | D36: =B36/C36 -> 4.3450455 | E36: =D36*1.6 -> 6.9520727 | F36: =D36*1.9 -> 8.2555864 | G36: 27.633333 | H36: =E36*G36 -> 192.10894 | I36: 1.25 | J36: =F36*I36 -> 10.319483 | K36: 21 | L36: =E36*K36 -> 145.99353 | M36: =H36+J36+L36 -> 348.42195 | N36: 0 | O36: =M36-N36 -> 348.42195 | P36: 23 | Q36: 5 | R36: =O36/P36*Q36 -> 75.743903 | S36: =O36+R36 -> 424.16586 | T36: ='Anexo 8 Tabela TRT'!H56 -> 1.0283483 | U36: =S36*T36 -> 436.19022 | V36: =U36*11.2% -> 48.853305
A37: 39873 | B37: 955.91 | C37: 220 | D37: =B37/C37 -> 4.3450455 | E37: =D37*1.6 -> 6.9520727 | F37: =D37*1.9 -> 8.2555864 | G37: 19.75 | H37: =E37*G37 -> 137.30344 | I37: 0 | J37: =F37*I37 -> 0 | K37: 18 | L37: =E37*K37 -> 125.13731 | M37: =H37+J37+L37 -> 262.44075 | N37: 0 | O37: =M37-N37 -> 262.44075 | P37: 26 | Q37: 5 | R37: =O37/P37*Q37 -> 50.469374 | S37: =O37+R37 -> 312.91012 | T37: ='Anexo 8 Tabela TRT'!H57 -> 1.0268716 | U37: =S37*T37 -> 321.31852 | V37: =U37*11.2% -> 35.987674
A38: 39904 | B38: 1012.5 | C38: 220 | D38: =B38/C38 -> 4.6022727 | E38: =D38*1.6 -> 7.3636364 | F38: =D38*1.9 -> 8.7443182 | G38: 18.533333 | H38: =E38*G38 -> 136.47273 | I38: 1.65 | J38: =F38*I38 -> 14.428125 | K38: 21 | L38: =E38*K38 -> 154.63636 | M38: =H38+J38+L38 -> 305.53722 | N38: 0 | O38: =M38-N38 -> 305.53722 | P38: 24 | Q38: 6 | R38: =O38/P38*Q38 -> 76.384304 | S38: =O38+R38 -> 381.92152 | T38: ='Anexo 8 Tabela TRT'!H58 -> 1.0264056 | U38: =S38*T38 -> 392.0064 | V38: =U38*11.2% -> 43.904717
A39: 39934 | B39: 1012.5 | C39: 220 | D39: =B39/C39 -> 4.6022727 | E39: =D39*1.6 -> 7.3636364 | F39: =D39*1.9 -> 8.7443182 | G39: 14.2 | H39: =E39*G39 -> 104.56364 | I39: 1.4166667 | J39: =F39*I39 -> 12.387784 | K39: 20 | L39: =E39*K39 -> 147.27273 | M39: =H39+J39+L39 -> 264.22415 | N39: 0 | O39: =M39-N39 -> 264.22415 | P39: 25 | Q39: 6 | R39: =O39/P39*Q39 -> 63.413795 | S39: =O39+R39 -> 327.63794 | T39: ='Anexo 8 Tabela TRT'!H59 -> 1.025945 | U39: =S39*T39 -> 336.1385 | V39: =U39*11.2% -> 37.647512
A40: 39965 | B40: 1012.5 | C40: 220 | D40: =B40/C40 -> 4.6022727 | E40: =D40*1.6 -> 7.3636364 | F40: =D40*1.9 -> 8.7443182 | G40: 18.316667 | H40: =E40*G40 -> 134.87727 | I40: 0 | J40: =F40*I40 -> 0 | K40: 20 | L40: =E40*K40 -> 147.27273 | M40: =H40+J40+L40 -> 282.15 | N40: 0 | O40: =M40-N40 -> 282.15 | P40: 25 | Q40: 5 | R40: =O40/P40*Q40 -> 56.43 | S40: =O40+R40 -> 338.58 | T40: ='Anexo 8 Tabela TRT'!H60 -> 1.0252724 | U40: =S40*T40 -> 347.13673 | V40: =U40*11.2% -> 38.879314
A41: 39995 | B41: 1012.5 | C41: 220 | D41: =B41/C41 -> 4.6022727 | E41: =D41*1.6 -> 7.3636364 | F41: =D41*1.9 -> 8.7443182 | G41: 19.95 | H41: =E41*G41 -> 146.90455 | I41: 2.25 | J41: =F41*I41 -> 19.674716 | K41: 20 | L41: =E41*K41 -> 147.27273 | M41: =H41+J41+L41 -> 313.85199 | N41: 0 | O41: =M41-N41 -> 313.85199 | P41: 27 | Q41: 4 | R41: =O41/P41*Q41 -> 46.496591 | S41: =O41+R41 -> 360.34858 | T41: ='Anexo 8 Tabela TRT'!H61 -> 1.024196 | U41: =S41*T41 -> 369.06756 | V41: =U41*11.2% -> 41.335567
A42: 40026 | B42: 1012.5 | C42: 220 | D42: =B42/C42 -> 4.6022727 | E42: =D42*1.6 -> 7.3636364 | F42: =D42*1.9 -> 8.7443182 | G42: 16.416667 | H42: =E42*G42 -> 120.88636 | I42: 2.4833333 | J42: =F42*I42 -> 21.715057 | K42: 17 | L42: =E42*K42 -> 125.18182 | M42: =H42+J42+L42 -> 267.78324 | N42: 28.45 | O42: =M42-N42 -> 239.33324 | P42: 25 | Q42: 6 | R42: =O42/P42*Q42 -> 57.439977 | S42: =O42+R42 -> 296.77322 | T42: ='Anexo 8 Tabela TRT'!H62 -> 1.0239942 | U42: =S42*T42 -> 303.89406 | V42: =U42*11.2% -> 34.036135
A43: Férias + 1/3 (média) período aquisitivo 03/05/08 a 02/05/09 | G43: =(SUM(G25,G27:G33,G35:G38)/12) -> 18.216389 | H43: =E43*G43 -> 0 | I43: =(SUM(I25,I27:I33,I35:I38)/12) -> 0.55277778 | J43: =F43*I43 -> 0 | K43: =(SUM(K25,K27:K33,K35:K38)/12) -> 18.416667 | L43: =E43*K43 -> 0 | M43: =H43+J43+L43 -> 0 | N43: 0 | O43: =M43-N43 -> 0 | S43: =O43+R43 -> 0 | T43: =T42 -> 1.0239942 | U43: =S43*T43 -> 0 | V43: =U43*11.2% -> 0
A44: 40057 | B44: 1012.5 | C44: 220 | D44: =B44/C44 -> 4.6022727 | E44: =D44*1.6 -> 7.3636364 | F44: =D44*1.9 -> 8.7443182 | G44: 2.8 | H44: =E44*G44 -> 20.618182 | I44: 0 | J44: =F44*I44 -> 0 | K44: 5 | L44: =E44*K44 -> 36.818182 | M44: =H44+J44+L44 -> 57.436364 | N44: 2.81 | O44: =M44-N44 -> 54.626364 | P44: 25 | Q44: 5 | R44: =O44/P44*Q44 -> 10.925273 | S44: =O44+R44 -> 65.551636 | T44: ='Anexo 8 Tabela TRT'!H63 -> 1.0239942 | U44: =S44*T44 -> 67.124498 | V44: =U44*11.2% -> 7.5179438
A45: 40087 | B45: 1012.5 | C45: 220 | D45: =B45/C45 -> 4.6022727 | E45: =D45*1.6 -> 7.3636364 | F45: =D45*1.9 -> 8.7443182 | G45: 18.283333 | H45: =E45*G45 -> 134.63182 | I45: 0.96666667 | J45: =F45*I45 -> 8.4528409 | K45: 21 | L45: =E45*K45 -> 154.63636 | M45: =H45+J45+L45 -> 297.72102 | N45: 0 | O45: =M45-N45 -> 297.72102 | P45: 26 | Q45: 5 | R45: =O45/P45*Q45 -> 57.254043 | S45: =O45+R45 -> 354.97507 | T45: ='Anexo 8 Tabela TRT'!H64 -> 1.0239942 | U45: =S45*T45 -> 363.49242 | V45: =U45*11.2% -> 40.711151
A46: 40118 | B46: 1012.5 | C46: 220 | D46: =B46/C46 -> 4.6022727 | E46: =D46*1.6 -> 7.3636364 | F46: =D46*1.9 -> 8.7443182 | G46: 11.133333 | H46: =E46*G46 -> 81.981818 | I46: 1.85 | J46: =F46*I46 -> 16.176989 | K46: 20 | L46: =E46*K46 -> 147.27273 | M46: =H46+J46+L46 -> 245.43153 | N46: 0 | O46: =M46-N46 -> 245.43153 | P46: 24 | Q46: 6 | R46: =O46/P46*Q46 -> 61.357884 | S46: =O46+R46 -> 306.78942 | T46: ='Anexo 8 Tabela TRT'!H65 -> 1.0239942 | U46: =S46*T46 -> 314.1506 | V46: =U46*11.2% -> 35.184867
A47: 40148 | B47: 1012.5 | C47: 220 | D47: =B47/C47 -> 4.6022727 | E47: =D47*1.6 -> 7.3636364 | F47: =D47*1.9 -> 8.7443182 | G47: 17.183333 | H47: =E47*G47 -> 126.53182 | I47: 0.48333333 | J47: =F47*I47 -> 4.2264205 | K47: 21 | L47: =E47*K47 -> 154.63636 | M47: =H47+J47+L47 -> 285.3946 | N47: 0.35 | O47: =M47-N47 -> 285.0446 | P47: 25 | Q47: 6 | R47: =O47/P47*Q47 -> 68.410705 | S47: =O47+R47 -> 353.45531 | T47: ='Anexo 8 Tabela TRT'!I54 -> 1.0234487 | U47: =S47*T47 -> 361.74339 | V47: =U47*11.2% -> 40.51526
A48: 13º Salário 2009 (Média) | B48: 1012.5 | C48: 220 | D48: =B48/C48 -> 4.6022727 | E48: =D48*1.6 -> 7.3636364 | F48: =D48*1.9 -> 8.7443182 | G48: =(SUM(G35:G42)+SUM(G44:G47))/12 -> 17.095833 | H48: =E48*G48 -> 125.8875 | I48: =(SUM(I35:I42)+SUM(I44:I47))/12 -> 1.2680556 | J48: =F48*I48 -> 11.088281 | K48: =(SUM(K35:K42)+SUM(K44:K47))/12 -> 18.333333 | L48: =E48*K48 -> 135 | M48: =H48+J48+L48 -> 271.97578 | N48: 0 | O48: =M48-N48 -> 271.97578 | S48: =O48+R48 -> 271.97578 | T48: =T46 -> 1.0239942 | U48: =S48*T48 -> 278.50163 | V48: =U48*11.2% -> 31.192183
A49: 40179 | B49: 1012.5 | C49: 220 | D49: =B49/C49 -> 4.6022727 | E49: =D49*1.6 -> 7.3636364 | F49: =D49*1.9 -> 8.7443182 | G49: 17.333333 | H49: =E49*G49 -> 127.63636 | I49: 0 | J49: =F49*I49 -> 0 | K49: 20 | L49: =E49*K49 -> 147.27273 | M49: =H49+J49+L49 -> 274.90909 | N49: 0 | O49: =M49-N49 -> 274.90909 | P49: 25 | Q49: 6 | R49: =O49/P49*Q49 -> 65.978182 | S49: =O49+R49 -> 340.88727 | T49: ='Anexo 8 Tabela TRT'!I55 -> 1.0234487 | U49: =S49*T49 -> 348.88065 | V49: =U49*11.2% -> 39.074633
A50: 40210 | B50: 1012.5 | C50: 220 | D50: =B50/C50 -> 4.6022727 | E50: =D50*1.6 -> 7.3636364 | F50: =D50*1.9 -> 8.7443182 | G50: 17.716667 | H50: =E50*G50 -> 130.45909 | I50: 0.93333333 | J50: =F50*I50 -> 8.1613636 | K50: 20 | L50: =E50*K50 -> 147.27273 | M50: =H50+J50+L50 -> 285.89318 | N50: 0 | O50: =M50-N50 -> 285.89318 | P50: 23 | Q50: 5 | R50: =O50/P50*Q50 -> 62.150692 | S50: =O50+R50 -> 348.04387 | T50: ='Anexo 8 Tabela TRT'!I56 -> 1.0234487 | U50: =S50*T50 -> 356.20507 | V50: =U50*11.2% -> 39.894967
A51: 40238 | B51: 1012.5 | C51: 220 | D51: =B51/C51 -> 4.6022727 | E51: =D51*1.6 -> 7.3636364 | F51: =D51*1.9 -> 8.7443182 | G51: 16.75 | H51: =E51*G51 -> 123.34091 | I51: 1.3333333 | J51: =F51*I51 -> 11.659091 | K51: 15 | L51: =E51*K51 -> 110.45455 | M51: =H51+J51+L51 -> 245.45455 | N51: 0 | O51: =M51-N51 -> 245.45455 | P51: 27 | Q51: 4 | R51: =O51/P51*Q51 -> 36.363636 | S51: =O51+R51 -> 281.81818 | T51: ='Anexo 8 Tabela TRT'!I57 -> 1.0226388 | U51: =S51*T51 -> 288.19821 | V51: =U51*11.2% -> 32.2782
A52: 40269 | B52: 1298.53 | C52: 220 | D52: =B52/C52 -> 5.9024091 | E52: =D52*1.6 -> 9.4438545 | F52: =D52*1.9 -> 11.214577 | G52: 24.45 | H52: =E52*G52 -> 230.90224 | I52: 1.7833333 | J52: =F52*I52 -> 19.999329 | K52: 22 | L52: =E52*K52 -> 207.7648 | M52: =H52+J52+L52 -> 458.66637 | N52: 0 | O52: =M52-N52 -> 458.66637 | P52: 24 | Q52: 6 | R52: =O52/P52*Q52 -> 114.66659 | S52: =O52+R52 -> 573.33297 | T52: ='Anexo 8 Tabela TRT'!I58 -> 1.0226388 | U52: =S52*T52 -> 586.31255 | V52: =U52*11.2% -> 65.667005
A53: 40299 | B53: 1298.53 | C53: 220 | D53: =B53/C53 -> 5.9024091 | E53: =D53*1.6 -> 9.4438545 | F53: =D53*1.9 -> 11.214577 | G53: 16.433333 | H53: =E53*G53 -> 155.19401 | I53: 2.0666667 | J53: =F53*I53 -> 23.176793 | K53: 20 | L53: =E53*K53 -> 188.87709 | M53: =H53+J53+L53 -> 367.24789 | N53: 0 | O53: =M53-N53 -> 367.24789 | P53: 25 | Q53: 6 | R53: =O53/P53*Q53 -> 88.139494 | S53: =O53+R53 -> 455.38739 | T53: ='Anexo 8 Tabela TRT'!I59 -> 1.0221175 | U53: =S53*T53 -> 465.45944 | V53: =U53*11.2% -> 52.131457
A54: 40330 | B54: ='Anexo 3 Dif Sal'!E13 -> 1298.53 | C54: 220 | D54: =B54/C54 -> 5.9024091 | E54: =D54*1.6 -> 9.4438545 | F54: =D54*1.9 -> 11.214577 | G54: 11.016667 | H54: =E54*G54 -> 104.0398 | I54: 0 | J54: =F54*I54 -> 0 | K54: 13 | L54: =E54*K54 -> 122.77011 | M54: =H54+J54+L54 -> 226.80991 | N54: 0 | O54: =M54-N54 -> 226.80991 | P54: 25 | Q54: 5 | R54: =O54/P54*Q54 -> 45.361981 | S54: =O54+R54 -> 272.17189 | T54: ='Anexo 8 Tabela TRT'!I60 -> 1.0215159 | U54: =S54*T54 -> 278.0279 | V54: =U54*11.2% -> 31.139125
A55: Férias + 1/3 (média) período aquisitivo 03/05/09 a 02/05/10 | G55: =(SUM(G39:G42,G44:G47,G49:G52)/12) -> 16.211111 | H55: =E55*G55 -> 0 | I55: =(SUM(I39:I42,I44:I47,I49:I52)/12) -> 1.125 | J55: =F55*I55 -> 0 | K55: =(SUM(K39:K42,K44:K47,K49:K52)/12) -> 18.416667 | L55: =E55*K55 -> 0 | M55: =H55+J55+L55 -> 0 | N55: 0 | O55: =M55-N55 -> 0 | S55: =O55+R55 -> 0 | T55: =T54 -> 1.0215159 | U55: =S55*T55 -> 0 | V55: =U55*11.2% -> 0
A56: 40360 | B56: ='Anexo 3 Dif Sal'!E14 -> 1376.4418 | C56: 220 | D56: =B56/C56 -> 6.2565536 | E56: =D56*1.6 -> 10.010486 | F56: =D56*1.9 -> 11.887452 | G56: 15.75 | H56: =E56*G56 -> 157.66515 | I56: 4.7 | J56: =F56*I56 -> 55.871024 | K56: 7 | L56: =E56*K56 -> 70.073401 | M56: =H56+J56+L56 -> 283.60958 | N56: 0 | O56: =M56-N56 -> 283.60958 | P56: 27 | Q56: 4 | R56: =O56/P56*Q56 -> 42.016234 | S56: =O56+R56 -> 325.62581 | T56: ='Anexo 8 Tabela TRT'!I61 -> 1.0203415 | U56: =S56*T56 -> 332.24951 | V56: =U56*11.2% -> 37.211945
A57: 40391 | B57: ='Anexo 3 Dif Sal'!E15 -> 1376.4418 | C57: 220 | D57: =B57/C57 -> 6.2565536 | E57: =D57*1.6 -> 10.010486 | F57: =D57*1.9 -> 11.887452 | G57: 23.216667 | H57: =E57*G57 -> 232.41011 | I57: 1.55 | J57: =F57*I57 -> 18.42555 | K57: 21 | L57: =E57*K57 -> 210.2202 | M57: =H57+J57+L57 -> 461.05587 | N57: 20.27 | O57: =M57-N57 -> 440.78587 | P57: 26 | Q57: 5 | R57: =O57/P57*Q57 -> 84.766513 | S57: =O57+R57 -> 525.55238 | T57: ='Anexo 8 Tabela TRT'!I62 -> 1.0194148 | U57: =S57*T57 -> 535.75587 | V57: =U57*11.2% -> 60.004658
A58: 40422 | B58: ='Anexo 3 Dif Sal'!E16 -> 1376.4418 | C58: 220 | D58: =B58/C58 -> 6.2565536 | E58: =D58*1.6 -> 10.010486 | F58: =D58*1.9 -> 11.887452 | G58: 17.083333 | H58: =E58*G58 -> 171.01247 | I58: 2.3666667 | J58: =F58*I58 -> 28.133636 | K58: 21 | L58: =E58*K58 -> 210.2202 | M58: =H58+J58+L58 -> 409.3663 | N58: 0 | O58: =M58-N58 -> 409.3663 | P58: 25 | Q58: 5 | R58: =O58/P58*Q58 -> 81.873261 | S58: =O58+R58 -> 491.23957 | T58: ='Anexo 8 Tabela TRT'!I63 -> 1.0186997 | U58: =S58*T58 -> 500.42559 | V58: =U58*11.2% -> 56.047666
A59: 40452 | B59: ='Anexo 3 Dif Sal'!E17 -> 1376.4418 | C59: 220 | D59: =B59/C59 -> 6.2565536 | E59: =D59*1.6 -> 10.010486 | F59: =D59*1.9 -> 11.887452 | G59: 17.766667 | H59: =E59*G59 -> 177.85296 | I59: 0 | J59: =F59*I59 -> 0 | K59: 19 | L59: =E59*K59 -> 190.19923 | M59: =H59+J59+L59 -> 368.0522 | N59: 0 | O59: =M59-N59 -> 368.0522 | P59: 25 | Q59: 6 | R59: =O59/P59*Q59 -> 88.332527 | S59: =O59+R59 -> 456.38472 | T59: ='Anexo 8 Tabela TRT'!I64 -> 1.0182191 | U59: =S59*T59 -> 464.69963 | V59: =U59*11.2% -> 52.046359
A60: 40483 | B60: ='Anexo 3 Dif Sal'!E18 -> 1376.4418 | C60: 220 | D60: =B60/C60 -> 6.2565536 | E60: =D60*1.6 -> 10.010486 | F60: =D60*1.9 -> 11.887452 | G60: 17.45 | H60: =E60*G60 -> 174.68298 | I60: 2.5166667 | J60: =F60*I60 -> 29.916754 | K60: 19 | L60: =E60*K60 -> 190.19923 | M60: =H60+J60+L60 -> 394.79896 | N60: 0 | O60: =M60-N60 -> 394.79896 | P60: 24 | Q60: 6 | R60: =O60/P60*Q60 -> 98.699741 | S60: =O60+R60 -> 493.4987 | T60: ='Anexo 8 Tabela TRT'!I65 -> 1.0178771 | U60: =S60*T60 -> 502.32101 | V60: =U60*11.2% -> 56.259953
A61: 40513 | B61: ='Anexo 3 Dif Sal'!E19 -> 1376.4418 | C61: 220 | D61: =B61/C61 -> 6.2565536 | E61: =D61*1.6 -> 10.010486 | F61: =D61*1.9 -> 11.887452 | G61: 16.616667 | H61: =E61*G61 -> 166.34091 | I61: 8.3166667 | J61: =F61*I61 -> 98.863975 | K61: 17 | L61: =E61*K61 -> 170.17826 | M61: =H61+J61+L61 -> 435.38314 | N61: 12.22 | O61: =M61-N61 -> 423.16314 | P61: 25 | Q61: 6 | R61: =O61/P61*Q61 -> 101.55915 | S61: =O61+R61 -> 524.72229 | T61: ='Anexo 8 Tabela TRT'!J54 -> 1.0164479 | U61: =S61*T61 -> 533.3529 | V61: =U61*11.2% -> 59.735524
A62: 13º Salário 2010 (Média) | B62: =B61 -> 1376.4418 | C62: 220 | D62: =B62/C62 -> 6.2565536 | E62: =D62*1.6 -> 10.010486 | F62: =D62*1.9 -> 11.887452 | G62: =SUM(G49:G54,G56:G61)/12 -> 17.631944 | H62: =E62*G62 -> 176.50433 | I62: =SUM(I49:I54,I56:I61)/12 -> 2.1305556 | J62: =F62*I62 -> 25.326877 | K62: =SUM(K49:K54,K56:K61)/12 -> 17.833333 | L62: =E62*K62 -> 178.52033 | M62: =H62+J62+L62 -> 380.35154 | N62: 0 | O62: =M62-N62 -> 380.35154 | S62: =O62+R62 -> 380.35154 | T62: =T60 -> 1.0178771 | U62: =S62*T62 -> 387.15111 | V62: =U62*11.2% -> 43.360924
A63: 40544 | B63: ='Anexo 3 Dif Sal'!E20 -> 1376.4418 | C63: 220 | D63: =B63/C63 -> 6.2565536 | E63: =D63*1.6 -> 10.010486 | F63: =D63*1.9 -> 11.887452 | G63: 21.766667 | H63: =E63*G63 -> 217.89491 | I63: 1.6666667 | J63: =F63*I63 -> 19.81242 | K63: 15 | L63: =E63*K63 -> 150.15729 | M63: =H63+J63+L63 -> 387.86462 | N63: 0 | O63: =M63-N63 -> 387.86462 | P63: 25 | Q63: 6 | R63: =O63/P63*Q63 -> 93.087508 | S63: =O63+R63 -> 480.95212 | T63: ='Anexo 8 Tabela TRT'!J55 -> 1.0157217 | U63: =S63*T63 -> 488.51351 | V63: =U63*11.2% -> 54.713513
A64: 40575 | B64: ='Anexo 3 Dif Sal'!E21 -> 1376.4418 | C64: 220 | D64: =B64/C64 -> 6.2565536 | E64: =D64*1.6 -> 10.010486 | F64: =D64*1.9 -> 11.887452 | G64: 20.9 | H64: =E64*G64 -> 209.21915 | I64: 0 | J64: =F64*I64 -> 0 | K64: 21 | L64: =E64*K64 -> 210.2202 | M64: =H64+J64+L64 -> 419.43936 | N64: 30.6 | O64: =M64-N64 -> 388.83936 | P64: 24 | Q64: 4 | R64: =O64/P64*Q64 -> 64.806559 | S64: =O64+R64 -> 453.64592 | T64: ='Anexo 8 Tabela TRT'!J56 -> 1.0151897 | U64: =S64*T64 -> 460.53668 | V64: =U64*11.2% -> 51.580108
A65: 40603 | B65: ='Anexo 3 Dif Sal'!E22 -> 1376.4418 | C65: 220 | D65: =B65/C65 -> 6.2565536 | E65: =D65*1.6 -> 10.010486 | F65: =D65*1.9 -> 11.887452 | G65: 25.416667 | H65: =E65*G65 -> 254.43318 | I65: 0 | J65: =F65*I65 -> 0 | K65: 18 | L65: =E65*K65 -> 180.18874 | M65: =H65+J65+L65 -> 434.62193 | N65: 0 | O65: =M65-N65 -> 434.62193 | P65: 26 | Q65: 5 | R65: =O65/P65*Q65 -> 83.58114 | S65: =O65+R65 -> 518.20307 | T65: ='Anexo 8 Tabela TRT'!J57 -> 1.0139608 | U65: =S65*T65 -> 525.43761 | V65: =U65*11.2% -> 58.849012
A66: 40634 | B66: ='Anexo 3 Dif Sal'!E23 -> 1376.4418 | C66: 220 | D66: =B66/C66 -> 6.2565536 | E66: =D66*1.6 -> 10.010486 | F66: =D66*1.9 -> 11.887452 | G66: 27.433333 | H66: =E66*G66 -> 274.62099 | I66: 2.1666667 | J66: =F66*I66 -> 25.756146 | K66: 23 | L66: =E66*K66 -> 230.24117 | M66: =H66+J66+L66 -> 530.61831 | N66: 77.63 | O66: =M66-N66 -> 452.98831 | P66: 24 | Q66: 6 | R66: =O66/P66*Q66 -> 113.24708 | S66: =O66+R66 -> 566.23539 | T66: ='Anexo 8 Tabela TRT'!J58 -> 1.0135868 | U66: =S66*T66 -> 573.92872 | V66: =U66*11.2% -> 64.280017
A67: 40664 | B67: ='Anexo 3 Dif Sal'!E24 -> 1376.4418 | C67: 220 | D67: =B67/C67 -> 6.2565536 | E67: =D67*1.6 -> 10.010486 | F67: =D67*1.9 -> 11.887452 | G67: 15.8 | H67: =E67*G67 -> 158.16568 | I67: 0 | J67: =F67*I67 -> 0 | K67: 18 | L67: =E67*K67 -> 180.18874 | M67: =H67+J67+L67 -> 338.35442 | N67: 88.45 | O67: =M67-N67 -> 249.90442 | P67: 26 | Q67: 5 | R67: =O67/P67*Q67 -> 48.058542 | S67: =O67+R67 -> 297.96296 | T67: ='Anexo 8 Tabela TRT'!J59 -> 1.011998 | U67: =S67*T67 -> 301.53791 | V67: =U67*11.2% -> 33.772246
A68: 40695 | B68: ='Anexo 3 Dif Sal'!E25 -> 1376.4418 | C68: 220 | D68: =B68/C68 -> 6.2565536 | E68: =D68*1.6 -> 10.010486 | F68: =D68*1.9 -> 11.887452 | G68: 22.083333 | H68: =E68*G68 -> 221.0649 | I68: 1.2833333 | J68: =F68*I68 -> 15.255563 | K68: 23 | L68: =E68*K68 -> 230.24117 | M68: =H68+J68+L68 -> 466.56163 | N68: 28.92 | O68: =M68-N68 -> 437.64163 | P68: 25 | Q68: 5 | R68: =O68/P68*Q68 -> 87.528326 | S68: =O68+R68 -> 525.16996 | T68: ='Anexo 8 Tabela TRT'!J60 -> 1.0108719 | U68: =S68*T68 -> 530.87953 | V68: =U68*11.2% -> 59.458508
A69: 40725 | B69: ='Anexo 3 Dif Sal'!E26 -> 1472.7927 | C69: 220 | D69: =B69/C69 -> 6.6945124 | E69: =D69*1.6 -> 10.71122 | F69: =D69*1.9 -> 12.719574 | G69: 20.583333 | H69: =E69*G69 -> 220.47261 | I69: 0.26666667 | J69: =F69*I69 -> 3.3918863 | K69: 21 | L69: =E69*K69 -> 224.93562 | M69: =H69+J69+L69 -> 448.80011 | N69: 21.27 | O69: =M69-N69 -> 427.53011 | P69: 26 | Q69: 5 | R69: =O69/P69*Q69 -> 82.217329 | S69: =O69+R69 -> 509.74744 | T69: ='Anexo 8 Tabela TRT'!J61 -> 1.009631 | U69: =S69*T69 -> 514.65683 | V69: =U69*11.2% -> 57.641565
A70: 40756 | B70: ='Anexo 3 Dif Sal'!E27 -> 1472.7927 | C70: 220 | D70: =B70/C70 -> 6.6945124 | E70: =D70*1.6 -> 10.71122 | F70: =D70*1.9 -> 12.719574 | G70: 17.366667 | H70: =E70*G70 -> 186.01818 | I70: 4.2666667 | J70: =F70*I70 -> 54.27018 | K70: 21 | L70: =E70*K70 -> 224.93562 | M70: =H70+J70+L70 -> 465.22398 | N70: 37.79 | O70: =M70-N70 -> 427.43398 | P70: 26 | Q70: 5 | R70: =O70/P70*Q70 -> 82.198843 | S70: =O70+R70 -> 509.63282 | T70: ='Anexo 8 Tabela TRT'!J62 -> 1.0075394 | U70: =S70*T70 -> 513.47514 | V70: =U70*11.2% -> 57.509215
A71: 40787 | B71: ='Anexo 3 Dif Sal'!E28 -> 1472.7927 | C71: 220 | D71: =B71/C71 -> 6.6945124 | E71: =D71*1.6 -> 10.71122 | F71: =D71*1.9 -> 12.719574 | G71: 19.433333 | H71: =E71*G71 -> 208.15471 | I71: 0 | J71: =F71*I71 -> 0 | K71: 22 | L71: =E71*K71 -> 235.64684 | M71: =H71+J71+L71 -> 443.80154 | N71: 33.21 | O71: =M71-N71 -> 410.59154 | P71: 25 | Q71: 5 | R71: =O71/P71*Q71 -> 82.118308 | S71: =O71+R71 -> 492.70985 | T71: ='Anexo 8 Tabela TRT'!J63 -> 1.0065298 | U71: =S71*T71 -> 495.92716 | V71: =U71*11.2% -> 55.543842
A72: Férias + 1/3 (média) período aquisitivo 03/05/09 a 02/05/10 | G72: =SUM(G39:G42,G44:G47,G49:G52)/12 -> 16.211111 | H72: =E72*G72 -> 0 | I72: =SUM(I39:I42,I44:I47,I49:I52)/12 -> 1.125 | J72: =F72*I72 -> 0 | K72: =SUM(K39:K42,K44:K47,K49:K52)/12 -> 18.416667 | L72: =E72*K72 -> 0 | M72: =H72+J72+L72 -> 0 | N72: 0 | O72: =M72-N72 -> 0 | S72: =O72+R72 -> 0 | T72: =T71 -> 1.0065298 | U72: =S72*T72 -> 0 | V72: =U72*11.2% -> 0
A73: 40817 | B73: ='Anexo 3 Dif Sal'!E29 -> 1472.7927 | C73: 220 | D73: =B73/C73 -> 6.6945124 | E73: =D73*1.6 -> 10.71122 | F73: =D73*1.9 -> 12.719574 | G73: 0.35 | H73: =E73*G73 -> 3.7489269 | I73: 0 | J73: =F73*I73 -> 0 | K73: 1 | L73: =E73*K73 -> 10.71122 | M73: =H73+J73+L73 -> 14.460147 | N73: 23.7 | O73: =M73-N73 -> -9.2398532 | P73: 25 | Q73: 6 | R73: 0 | S73: =O73+R73 -> -9.2398532 | T73: ='Anexo 8 Tabela TRT'!J64 -> 1.0059062 | U73: =S73*T73 -> -9.2944253 | V73: 0
A74: 40848 | B74: ='Anexo 3 Dif Sal'!E30 -> 1472.7927 | C74: 220 | D74: =B74/C74 -> 6.6945124 | E74: =D74*1.6 -> 10.71122 | F74: =D74*1.9 -> 12.719574 | G74: 12.366667 | H74: =E74*G74 -> 132.46209 | I74: 0 | J74: =F74*I74 -> 0 | K74: 14 | L74: =E74*K74 -> 149.95708 | M74: =H74+J74+L74 -> 282.41916 | N74: 15.38 | O74: =M74-N74 -> 267.03916 | P74: 24 | Q74: 6 | R74: =O74/P74*Q74 -> 66.759791 | S74: =O74+R74 -> 333.79895 | T74: ='Anexo 8 Tabela TRT'!J65 -> 1.0052578 | U74: =S74*T74 -> 335.55399 | V74: =U74*11.2% -> 37.582047
A75: 40878 | B75: ='Anexo 3 Dif Sal'!E31 -> 1472.7927 | C75: 220 | D75: =B75/C75 -> 6.6945124 | E75: =D75*1.6 -> 10.71122 | F75: =D75*1.9 -> 12.719574 | G75: 15.233333 | H75: =E75*G75 -> 163.16758 | I75: 0 | J75: =F75*I75 -> 0 | K75: 19 | L75: =E75*K75 -> 203.51318 | M75: =H75+J75+L75 -> 366.68076 | N75: 42.8 | O75: =M75-N75 -> 323.88076 | P75: 26 | Q75: 5 | R75: =O75/P75*Q75 -> 62.284761 | S75: =O75+R75 -> 386.16552 | T75: ='Anexo 8 Tabela TRT'!K54 -> 1.0043167 | U75: =S75*T75 -> 387.83249 | V75: =U75*11.2% -> 43.437239
A76: 13º Salário 2011 (Média) | B76: =B75 -> 1472.7927 | C76: 220 | D76: =B76/C76 -> 6.6945124 | E76: =D76*1.6 -> 10.71122 | F76: =D76*1.9 -> 12.719574 | G76: =SUM(G63:G71,G73:G75)/12 -> 18.227778 | H76: =E76*G76 -> 195.24173 | I76: =SUM(I63:I71,I73:I75)/12 -> 0.80416667 | J76: =F76*I76 -> 10.228657 | K76: =SUM(K63:K71,K73:K75)/12 -> 18 | L76: =E76*K76 -> 192.80196 | M76: =H76+J76+L76 -> 398.27235 | N76: 0 | O76: =M76-N76 -> 398.27235 | S76: =O76+R76 -> 398.27235 | T76: =T74 -> 1.0052578 | U76: =S76*T76 -> 400.36637 | V76: =U76*11.2% -> 44.841034
A77: 40909 | B77: ='Anexo 3 Dif Sal'!E32 -> 1472.7927 | C77: 220 | D77: =B77/C77 -> 6.6945124 | E77: =D77*1.6 -> 10.71122 | F77: =D77*1.9 -> 12.719574 | G77: 16.366667 | H77: =E77*G77 -> 175.30696 | I77: 0 | J77: =F77*I77 -> 0 | K77: 21 | L77: =E77*K77 -> 224.93562 | M77: =H77+J77+L77 -> 400.24258 | N77: 20.08 | O77: =M77-N77 -> 380.16258 | P77: 26 | Q77: 5 | R77: =O77/P77*Q77 -> 73.108189 | S77: =O77+R77 -> 453.27077 | T77: ='Anexo 8 Tabela TRT'!K55 -> 1.0034497 | U77: =S77*T77 -> 454.83444 | V77: =U77*11.2% -> 50.941457
A78: 40940 | B78: ='Anexo 3 Dif Sal'!E33 -> 1472.7927 | C78: 220 | D78: =B78/C78 -> 6.6945124 | E78: =D78*1.6 -> 10.71122 | F78: =D78*1.9 -> 12.719574 | G78: 24.383333 | H78: =E78*G78 -> 261.17524 | I78: 0 | J78: =F78*I78 -> 0 | K78: 23 | L78: =E78*K78 -> 246.35806 | M78: =H78+J78+L78 -> 507.5333 | N78: 71.8 | O78: =M78-N78 -> 435.7333 | P78: 24 | Q78: 5 | R78: =O78/P78*Q78 -> 90.777771 | S78: =O78+R78 -> 526.51107 | T78: ='Anexo 8 Tabela TRT'!K56 -> 1.0034497 | U78: =S78*T78 -> 528.3274 | V78: =U78*11.2% -> 59.172669
A79: 40969 | B79: ='Anexo 3 Dif Sal'!E34 -> 1472.7927 | C79: 220 | D79: =B79/C79 -> 6.6945124 | E79: =D79*1.6 -> 10.71122 | F79: =D79*1.9 -> 12.719574 | G79: 14.483333 | H79: =E79*G79 -> 155.13417 | I79: 0 | J79: =F79*I79 -> 0 | K79: 18 | L79: =E79*K79 -> 192.80196 | M79: =H79+J79+L79 -> 347.93612 | N79: 53.87 | O79: =M79-N79 -> 294.06612 | P79: 27 | Q79: 4 | R79: =O79/P79*Q79 -> 43.565352 | S79: =O79+R79 -> 337.63148 | T79: ='Anexo 8 Tabela TRT'!K57 -> 1.0023792 | U79: =S79*T79 -> 338.43477 | V79: =U79*11.2% -> 37.904694
A80: 41024 | B80: =B79 -> 1472.7927 | C80: 220 | D80: =B80/C80 -> 6.6945124 | E80: =D80*1.6 -> 10.71122 | F80: =D80*1.9 -> 12.719574 | G80: 22.75 | H80: =E80*G80 -> 243.68025 | I80: 0.66666667 | J80: =F80*I80 -> 8.4797157 | K80: 25 | L80: =E80*K80 -> 267.7805 | M80: =H80+J80+L80 -> 519.94046 | N80: 47.31 | O80: =M80-N80 -> 472.63046 | P80: 21 | Q80: 4 | R80: =O80/P80*Q80 -> 90.02485 | S80: =O80+R80 -> 562.65531 | T80: ='Anexo 8 Tabela TRT'!K58 -> 1.0021517 | U80: =S80*T80 -> 563.86599 | V80: =U80*11.2% -> 63.15299
A81: TOTAL | U81: =SUM(U13:U80) -> 23429.349 | V81: =SUM(V13:V80) -> 2628.5801

Sheet Anexo 5 Tiquete
A1: PROCESSO:
A2: VARA:
A3: RECLAMANTE:
A4: RECLAMADA:
A6: ANEXO 5
A7: TIQUETE REFEIÇÃO
A9: Mês / Ano | B9: Valor Unitário do Tiquete conforme CCT's acostadas aos autos | C9: Dias efetivamente trabalhados | D9: Valores Devidos | E9: Correção Monetária - Tabela TRT para 30/11/2013
E10: Indices | F10: Valor
A12: Col. 1 | B12: Col. 2 | C12: Col. 3 | D12: Col. 4 | E12: Col. 5 | F12: Col. 6
A13: 40360 | B13: 7 | C13: 22 | D13: =B13*C13 -> 154 | E13: ='Anexo 8 Tabela TRT'!I61 -> 1.0203415 | F13: =D13*E13 -> 157.13258
A14: 40391 | B14: 7 | C14: 21 | D14: =B14*C14 -> 147 | E14: ='Anexo 8 Tabela TRT'!I62 -> 1.0194148 | F14: =D14*E14 -> 149.85398
A15: 40422 | B15: 7 | C15: 21 | D15: =B15*C15 -> 147 | E15: ='Anexo 8 Tabela TRT'!I63 -> 1.0186997 | F15: =D15*E15 -> 149.74885
A16: 40452 | B16: 7 | C16: 20 | D16: =B16*C16 -> 140 | E16: ='Anexo 8 Tabela TRT'!I64 -> 1.0182191 | F16: =D16*E16 -> 142.55067
A17: 40483 | B17: 7 | C17: 20 | D17: =B17*C17 -> 140 | E17: ='Anexo 8 Tabela TRT'!I65 -> 1.0178771 | F17: =D17*E17 -> 142.50279
A18: 40513 | B18: 7 | C18: 22 | D18: =B18*C18 -> 154 | E18: ='Anexo 8 Tabela TRT'!J54 -> 1.0164479 | F18: =D18*E18 -> 156.53298
A19: 40544 | B19: 7 | C19: 21 | D19: =B19*C19 -> 147 | E19: ='Anexo 8 Tabela TRT'!J55 -> 1.0157217 | F19: =D19*E19 -> 149.31109
A20: 40575 | B20: 7 | C20: 20 | D20: =B20*C20 -> 140 | E20: ='Anexo 8 Tabela TRT'!J56 -> 1.0151897 | F20: =D20*E20 -> 142.12656
A21: 40603 | B21: 7 | C21: 22 | D21: =B21*C21 -> 154 | E21: ='Anexo 8 Tabela TRT'!J57 -> 1.0139608 | F21: =D21*E21 -> 156.14997
A22: 40634 | B22: 7 | C22: 19 | D22: =B22*C22 -> 133 | E22: ='Anexo 8 Tabela TRT'!J58 -> 1.0135868 | F22: =D22*E22 -> 134.80705
A23: 40664 | B23: 7 | C23: 22 | D23: =B23*C23 -> 154 | E23: ='Anexo 8 Tabela TRT'!J59 -> 1.011998 | F23: =D23*E23 -> 155.84769
A24: 40695 | B24: 7 | C24: 21 | D24: =B24*C24 -> 147 | E24: ='Anexo 8 Tabela TRT'!J60 -> 1.0108719 | F24: =D24*E24 -> 148.59816
A25: 40725 | B25: 7 | C25: 21 | D25: =B25*C25 -> 147 | E25: ='Anexo 8 Tabela TRT'!J61 -> 1.009631 | F25: =D25*E25 -> 148.41576
A26: 40756 | B26: 7 | C26: 22 | D26: =B26*C26 -> 154 | E26: ='Anexo 8 Tabela TRT'!J62 -> 1.0075394 | F26: =D26*E26 -> 155.16106
A27: 40787 | B27: 7 | C27: 21 | D27: =B27*C27 -> 147 | E27: ='Anexo 8 Tabela TRT'!J63 -> 1.0065298 | F27: =D27*E27 -> 147.95988
A28: 40817 | B28: 7 | C28: 20 | D28: =B28*C28 -> 140 | E28: ='Anexo 8 Tabela TRT'!J64 -> 1.0059062 | F28: =D28*E28 -> 140.82686
A29: 40848 | B29: 7 | C29: 20 | D29: =B29*C29 -> 140 | E29: ='Anexo 8 Tabela TRT'!J65 -> 1.0052578 | F29: =D29*E29 -> 140.73609
A30: 40878 | B30: 7 | C30: 21 | D30: =B30*C30 -> 147 | E30: ='Anexo 8 Tabela TRT'!K54 -> 1.0043167 | F30: =D30*E30 -> 147.63456
A31: 40909 | B31: 7 | C31: 22 | D31: =B31*C31 -> 154 | E31: ='Anexo 8 Tabela TRT'!K55 -> 1.0034497 | F31: =D31*E31 -> 154.53126
A32: 40940 | B32: 7 | C32: 20 | D32: =B32*C32 -> 140 | E32: ='Anexo 8 Tabela TRT'!K56 -> 1.0034497 | F32: =D32*E32 -> 140.48296
A33: 40969 | B33: 7 | C33: 22 | D33: =B33*C33 -> 154 | E33: ='Anexo 8 Tabela TRT'!K57 -> 1.0023792 | F33: =D33*E33 -> 154.3664
A34: 41024 | B34: 7 | C34: 17 | D34: =B34*C34 -> 119 | E34: ='Anexo 8 Tabela TRT'!K58 -> 1.0021517 | F34: =D34*E34 -> 119.25605
A35: TOTAL | F35: =SUM(F13:F34) -> 3234.5333

Sheet Anexo 6 INSS
A1: PROCESSO:
A2: VARA:
A3: RECLAMANTE:
A4: RECLAMADA:
A6: ANEXO 6
A7: APURAÇÃO DA CONTRIBUIÇÃO PREVIDENCIÁRIA
A9: Mês / Ano | B9: Base de Cálculo à época | C9: Valores conquistados nesta ação que são base de cálculo para o INSS (Tabela de Incidências do Manual de Cálculos Judiciais TRT 3ª Região) | F9: Nova Base de Cálculo | G9: Alíquota devida à época | H9: Cota parte do Reclamante | I9: Valor já recolhido à época | J9: Diferença da Cota parte do Reclamante | K9: Correção Monetária Tabela TRT para 30/11/2013 | M9: Base de Cálculo INSS parte da Reclamada | N9: Cota Parte do Reclamante | T9: Cota Parte da Reclamada
N10: Juros | Q10: Multa | T10: Juros | X10: Multa
C11: Anexo 3 | D11: Anexo 4 | E11: Soma | K11: Indices | L11: Valor Atualizado | N11: Base Cálc. Principal | O11: % | P11: Total | Q11: Base Cálc. Principal | R11: % | S11: Total | T11: Base Cálc. | U11: Cota (21%) Principal | V11: % | W11: Total | X11: Cota (21%) Principal | Y11: % | Z11: Total
A12: Col. 1 | B12: Col. 2 | C12: Col. 3 | D12: Col. 4 | E12: Col. 5 | F12: Col. 6 | G12: Col. 7 | H12: Col. 8 | I12: Col. 9 | J12: Col. 10 | K12: Col. 11 | L12: Col. 12 | M12: Col. 13 | N12: Col. 14 | O12: Col. 15 | P12: Col. 16 | Q12: Col. 17 | R12: Col. 18 | S12: Col. 19 | T12: Col. 20 | U12: Col. 21 | V12: Col. 22 | W12: Col. 23 | X12: Col. 24 | Y12: Col. 25 | Z12: Col. 26
A13: 39234 | B13: 955.52 | D13: ='Anexo 4 HE'!S13 -> 141.55545 | E13: =SUM(C13:D13) -> 141.55545 | F13: =B13+E13 -> 1097.0754 | G13: 0.0865 | H13: =F13*G13 -> 94.897026 | I13: 82.65 | J13: =H13-I13 -> 12.247026 | K13: ='Anexo 4 HE'!T13 -> 1.053497 | L13: =J13*K13 -> 12.902205 | M13: =E13*K13 -> 149.12824
A14: 39264 | B14: 897.33 | D14: ='Anexo 4 HE'!S14 -> 410.58677 | E14: =SUM(C14:D14) -> 410.58677 | F14: =B14+E14 -> 1307.9168 | G14: 0.09 | H14: =F14*G14 -> 117.71251 | I14: 77.62 | J14: =H14-I14 -> 40.092509 | K14: ='Anexo 4 HE'!T14 -> 1.0519517 | L14: =J14*K14 -> 42.175382 | M14: =E14*K14 -> 431.91744
A15: 39295 | B15: 932.54 | D15: ='Anexo 4 HE'!S15 -> 420.72677 | E15: =SUM(C15:D15) -> 420.72677 | F15: =B15+E15 -> 1353.2668 | G15: 0.09 | H15: =F15*G15 -> 121.79401 | I15: 80.66 | J15: =H15-I15 -> 41.134009 | K15: ='Anexo 4 HE'!T15 -> 1.0504118 | L15: =J15*K15 -> 43.207647 | M15: =E15*K15 -> 441.93635
A16: 39326 | B16: 910.07 | D16: ='Anexo 4 HE'!S16 -> 409.54543 | E16: =SUM(C16:D16) -> 409.54543 | F16: =B16+E16 -> 1319.6154 | G16: 0.09 | H16: =F16*G16 -> 118.76539 | I16: 78.72 | J16: =H16-I16 -> 40.045389 | K16: ='Anexo 4 HE'!T16 -> 1.0500421 | L16: =J16*K16 -> 42.049346 | M16: =E16*K16 -> 430.03996
A17: 39356 | B17: 926.87 | D17: ='Anexo 4 HE'!S17 -> 432.76775 | E17: =SUM(C17:D17) -> 432.76775 | F17: =B17+E17 -> 1359.6378 | G17: 0.09 | H17: =F17*G17 -> 122.3674 | I17: 80.17 | J17: =H17-I17 -> 42.197398 | K17: ='Anexo 4 HE'!T17 -> 1.0488444 | L17: =J17*K17 -> 44.258503 | M17: =E17*K17 -> 453.90602
A18: 39387 | B18: 1150.93 | D18: ='Anexo 4 HE'!S18 -> 138.85251 | E18: =SUM(C18:D18) -> 138.85251 | F18: =B18+E18 -> 1289.7825 | G18: 0.09 | H18: =F18*G18 -> 116.08043 | I18: 103.58 | J18: =H18-I18 -> 12.500426 | K18: ='Anexo 4 HE'!T18 -> 1.0482259 | L18: =J18*K18 -> 13.103271 | M18: =E18*K18 -> 145.5488
A19: 39417 | B19: 893.37 | D19: ='Anexo 4 HE'!S19 -> 191.62335 | E19: =SUM(C19:D19) -> 191.62335 | F19: =B19+E19 -> 1084.9934 | G19: 0.0865 | H19: =F19*G19 -> 93.851925 | I19: 77.28 | J19: =H19-I19 -> 16.571925 | K19: ='Anexo 4 HE'!T19 -> 1.0475555 | L19: =J19*K19 -> 17.360011 | M19: =E19*K19 -> 200.73609
A20: 13º Salário 2007 (Média) | B20: 647.39 | D20: ='Anexo 4 HE'!S20 -> 177.18956 | E20: =SUM(C20:D20) -> 177.18956 | F20: =B20+E20 -> 824.57956 | G20: 0.0765 | H20: =F20*G20 -> 63.080336 | I20: 49.53 | J20: =H20-I20 -> 13.550336 | K20: ='Anexo 4 HE'!T20 -> 1.0482259 | L20: =J20*K20 -> 14.203814 | M20: =E20*K20 -> 185.73469
A21: 39448 | B21: 925.46 | D21: ='Anexo 4 HE'!S21 -> 335.67519 | E21: =SUM(C21:D21) -> 335.67519 | F21: =B21+E21 -> 1261.1352 | G21: 0.09 | H21: =F21*G21 -> 113.50217 | I21: 83.29 | J21: =H21-I21 -> 30.212167 | K21: ='Anexo 4 HE'!T21 -> 1.0464985 | L21: =J21*K21 -> 31.616988 | M21: =E21*K21 -> 351.28359
A22: 39479 | B22: 893.37 | D22: ='Anexo 4 HE'!S22 -> 309.12632 | E22: =SUM(C22:D22) -> 309.12632 | F22: =B22+E22 -> 1202.4963 | G22: 0.09 | H22: =F22*G22 -> 108.22467 | I22: 80.4 | J22: =H22-I22 -> 27.824669 | K22: ='Anexo 4 HE'!T22 -> 1.0462443 | L22: =J22*K22 -> 29.111401 | M22: =E22*K22 -> 323.42165
A23: 39508 | B23: 908.09 | D23: ='Anexo 4 HE'!S23 -> 214.50913 | E23: =SUM(C23:D23) -> 214.50913 | F23: =B23+E23 -> 1122.5991 | G23: 0.09 | H23: =F23*G23 -> 101.03392 | I23: 72.65 | J23: =H23-I23 -> 28.383922 | K23: ='Anexo 4 HE'!T23 -> 1.0458165 | L23: =J23*K23 -> 29.684375 | M23: =E23*K23 -> 224.3372
A24: 39539 | B24: 903.56 | D24: ='Anexo 4 HE'!S24 -> 358.59585 | E24: =SUM(C24:D24) -> 358.59585 | F24: =B24+E24 -> 1262.1559 | G24: 0.09 | H24: =F24*G24 -> 113.59403 | I24: 72.28 | J24: =H24-I24 -> 41.314027 | K24: ='Anexo 4 HE'!T24 -> 1.0448187 | L24: =J24*K24 -> 43.165669 | M24: =E24*K24 -> 374.66767
A25: 39569 | B25: 506.24 | D25: ='Anexo 4 HE'!S25 -> 306.91924 | E25: =SUM(C25:D25) -> 306.91924 | F25: =B25+E25 -> 813.15924 | G25: 0.08 | H25: =F25*G25 -> 65.052739 | I25: 80.68 | J25: 0 | K25: ='Anexo 4 HE'!T25 -> 1.0440503 | L25: =J25*K25 -> 0 | M25: =E25*K25 -> 320.43913
A26: Férias + 1/3 | B26: 1249.37 | D26: ='Anexo 4 HE'!S26 -> 0 | E26: =SUM(C26:D26) -> 0 | F26: =B26+E26 -> 1249.37 | G26: 0.11 | H26: =F26*G26 -> 137.4307 | I26: 112.44 | J26: =H26-I26 -> 24.9907 | K26: ='Anexo 4 HE'!T26 -> 1.0440503 | L26: =J26*K26 -> 26.091548 | M26: =E26*K26 -> 0
A27: 39600 | B27: 442.02 | D27: 0 | E27: =SUM(C27:D27) -> 0 | F27: =B27+E27 -> 442.02 | G27: 0.08 | H27: =F27*G27 -> 35.3616 | I27: 35.36 | J27: =H27-I27 -> 0.0016 | K27: ='Anexo 4 HE'!T27 -> 1.0428552 | L27: =J27*K27 -> 0.0016685683 | M27: =E27*K27 -> 0
A28: 39630 | B28: 893.37 | D28: ='Anexo 4 HE'!S28 -> 290.94424 | E28: =SUM(C28:D28) -> 290.94424 | F28: =B28+E28 -> 1184.3142 | G28: 0.09 | H28: =F28*G28 -> 106.58828 | I28: 71.47 | J28: =H28-I28 -> 35.118282 | K28: ='Anexo 4 HE'!T28 -> 1.040863 | L28: =J28*K28 -> 36.55332 | M28: =E28*K28 -> 302.8331
A29: 39661 | B29: 1122.25 | D29: ='Anexo 4 HE'!S29 -> 376.57488 | E29: =SUM(C29:D29) -> 376.57488 | F29: =B29+E29 -> 1498.8249 | G29: 0.09 | H29: =F29*G29 -> 134.89424 | I29: 101 | J29: =H29-I29 -> 33.894239 | K29: ='Anexo 4 HE'!T29 -> 1.0392272 | L29: =J29*K29 -> 35.223817 | M29: =E29*K29 -> 391.34688
A30: 39692 | B30: 1162.64 | D30: ='Anexo 4 HE'!S30 -> 254.05777 | E30: =SUM(C30:D30) -> 254.05777 | F30: =B30+E30 -> 1416.6978 | G30: 0.09 | H30: =F30*G30 -> 127.5028 | I30: 104.64 | J30: =H30-I30 -> 22.862799 | K30: ='Anexo 4 HE'!T30 -> 1.037184 | L30: =J30*K30 -> 23.71293 | M30: =E30*K30 -> 263.50465
A31: 39722 | B31: 955.91 | D31: ='Anexo 4 HE'!S31 -> 311.69747 | E31: =SUM(C31:D31) -> 311.69747 | F31: =B31+E31 -> 1267.6075 | G31: 0.09 | H31: =F31*G31 -> 114.08467 | I31: 86.03 | J31: =H31-I31 -> 28.054672 | K31: ='Anexo 4 HE'!T31 -> 1.0345913 | L31: =J31*K31 -> 29.02512 | M31: =E31*K31 -> 322.47949
A32: 39753 | B32: 958.99 | D32: ='Anexo 4 HE'!S32 -> 342.80529 | E32: =SUM(C32:D32) -> 342.80529 | F32: =B32+E32 -> 1301.7953 | G32: 0.09 | H32: =F32*G32 -> 117.16158 | I32: 86.31 | J32: =H32-I32 -> 30.851576 | K32: ='Anexo 4 HE'!T32 -> 1.03292 | L32: =J32*K32 -> 31.867211 | M32: =E32*K32 -> 354.09045
A33: 39783 | B33: 982.82 | D33: ='Anexo 4 HE'!S33 -> 303.18329 | E33: =SUM(C33:D33) -> 303.18329 | F33: =B33+E33 -> 1286.0033 | G33: 0.09 | H33: =F33*G33 -> 115.7403 | I33: 88.45 | J33: =H33-I33 -> 27.290296 | K33: ='Anexo 4 HE'!T33 -> 1.0307051 | L33: =J33*K33 -> 28.128246 | M33: =E33*K33 -> 312.49255
A34: 13º Salário 2008 (Média) | B34: 981.69 | D34: ='Anexo 4 HE'!S34 -> 253.23818 | E34: =SUM(C34:D34) -> 253.23818 | F34: =B34+E34 -> 1234.9282 | G34: 0.09 | H34: =F34*G34 -> 111.14354 | I34: 88.35 | J34: =H34-I34 -> 22.793536 | K34: ='Anexo 4 HE'!T34 -> 1.03292 | L34: =J34*K34 -> 23.5439 | M34: =E34*K34 -> 261.57479
A35: 39814 | B35: 955.91 | D35: ='Anexo 4 HE'!S35 -> 334.49608 | E35: =SUM(C35:D35) -> 334.49608 | F35: =B35+E35 -> 1290.4061 | G35: 0.09 | H35: =F35*G35 -> 116.13655 | I35: 86.03 | J35: =H35-I35 -> 30.106547 | K35: ='Anexo 4 HE'!T35 -> 1.028812 | L35: =J35*K35 -> 30.973979 | M35: =E35*K35 -> 344.1336
A36: 39845 | B36: 955.91 | D36: ='Anexo 4 HE'!S36 -> 424.16586 | E36: =SUM(C36:D36) -> 424.16586 | F36: =B36+E36 -> 1380.0759 | G36: 0.09 | H36: =F36*G36 -> 124.20683 | I36: 76.47 | J36: =H36-I36 -> 47.736827 | K36: ='Anexo 4 HE'!T36 -> 1.0283483 | L36: =J36*K36 -> 49.090083 | M36: =E36*K36 -> 436.19022
A37: 39873 | B37: 955.91 | D37: ='Anexo 4 HE'!S37 -> 312.91012 | E37: =SUM(C37:D37) -> 312.91012 | F37: =B37+E37 -> 1268.8201 | G37: 0.09 | H37: =F37*G37 -> 114.19381 | I37: 76.47 | J37: =H37-I37 -> 37.723811 | N37: =J37 -> 37.723811 | O37: ='Multa INSS'!O62 -> 41.77 | P37: =N37*(O37%) -> 15.757236 | Q37: =N37 -> 37.723811 | R37: 0.2 | S37: =Q37*R37 -> 7.5447622 | T37: =E37 -> 312.91012 | U37: =T37*21% -> 65.711125 | V37: =O37 -> 41.77 | W37: =U37*(V37%) -> 27.447537 | X37: =U37 -> 65.711125 | Y37: =R37 -> 0.2 | Z37: =X37*Y37 -> 13.142225
A38: 39904 | B38: 955.91 | D38: ='Anexo 4 HE'!S38 -> 381.92152 | E38: =SUM(C38:D38) -> 381.92152 | F38: =B38+E38 -> 1337.8315 | G38: 0.09 | H38: =F38*G38 -> 120.40484 | I38: 76.47 | J38: =H38-I38 -> 43.934837 | N38: =J38 -> 43.934837 | O38: ='Multa INSS'!O63 -> 41 | P38: =N38*(O38%) -> 18.013283 | Q38: =N38 -> 43.934837 | R38: 0.2 | S38: =Q38*R38 -> 8.7869674 | T38: =E38 -> 381.92152 | U38: =T38*21% -> 80.203519 | V38: =O38 -> 41 | W38: =U38*(V38%) -> 32.883443 | X38: =U38 -> 80.203519 | Y38: =R38 -> 0.2 | Z38: =X38*Y38 -> 16.040704
A39: 39934 | B39: 955.91 | D39: ='Anexo 4 HE'!S39 -> 327.63794 | E39: =SUM(C39:D39) -> 327.63794 | F39: =B39+E39 -> 1283.5479 | G39: 0.09 | H39: =F39*G39 -> 115.51931 | I39: 76.47 | J39: =H39-I39 -> 39.049315 | N39: =J39 -> 39.049315 | O39: ='Multa INSS'!O64 -> 40.24 | P39: =N39*(O39%) -> 15.713444 | Q39: =N39 -> 39.049315 | R39: 0.2 | S39: =Q39*R39 -> 7.809863 | T39: =E39 -> 327.63794 | U39: =T39*21% -> 68.803968 | V39: =O39 -> 40.24 | W39: =U39*(V39%) -> 27.686717 | X39: =U39 -> 68.803968 | Y39: =R39 -> 0.2 | Z39: =X39*Y39 -> 13.760794
A40: 39965 | B40: 951.08 | D40: ='Anexo 4 HE'!S40 -> 338.58 | E40: =SUM(C40:D40) -> 338.58 | F40: =B40+E40 -> 1289.66 | G40: 0.09 | H40: =F40*G40 -> 116.0694 | I40: 76.09 | J40: =H40-I40 -> 39.9794 | N40: =J40 -> 39.9794 | O40: ='Multa INSS'!O65 -> 39.45 | P40: =N40*(O40%) -> 15.771873 | Q40: =N40 -> 39.9794 | R40: 0.2 | S40: =Q40*R40 -> 7.99588 | T40: =E40 -> 338.58 | U40: =T40*21% -> 71.1018 | V40: =O40 -> 39.45 | W40: =U40*(V40%) -> 28.04966 | X40: =U40 -> 71.1018 | Y40: =R40 -> 0.2 | Z40: =X40*Y40 -> 14.22036
A41: 39995 | B41: 955.91 | D41: ='Anexo 4 HE'!S41 -> 360.34858 | E41: =SUM(C41:D41) -> 360.34858 | F41: =B41+E41 -> 1316.2586 | G41: 0.09 | H41: =F41*G41 -> 118.46327 | I41: 76.47 | J41: =H41-I41 -> 41.993272 | N41: =J41 -> 41.993272 | O41: ='Multa INSS'!O66 -> 38.76 | P41: =N41*(O41%) -> 16.276592 | Q41: =N41 -> 41.993272 | R41: 0.2 | S41: =Q41*R41 -> 8.3986544 | T41: =E41 -> 360.34858 | U41: =T41*21% -> 75.673202 | V41: =O41 -> 38.76 | W41: =U41*(V41%) -> 29.330933 | X41: =U41 -> 75.673202 | Y41: =R41 -> 0.2 | Z41: =X41*Y41 -> 15.13464
A42: 40026 | B42: 287.57 | D42: ='Anexo 4 HE'!S42 -> 296.77322 | E42: =SUM(C42:D42) -> 296.77322 | F42: =B42+E42 -> 584.34322 | G42: 0.08 | H42: =F42*G42 -> 46.747457 | I42: 76.47 | J42: 0 | N42: =J42 -> 0 | O42: ='Multa INSS'!O67 -> 38.07 | P42: =N42*(O42%) -> 0 | Q42: =N42 -> 0 | R42: 0.2 | S42: =Q42*R42 -> 0 | T42: =E42 -> 296.77322 | U42: =T42*21% -> 62.322375 | V42: =O42 -> 38.07 | W42: =U42*(V42%) -> 23.726128 | X42: =U42 -> 62.322375 | Y42: =R42 -> 0.2 | Z42: =X42*Y42 -> 12.464475
A43: Férias + 1/3 | B43: 1288.24 | D43: ='Anexo 4 HE'!S43 -> 0 | E43: =SUM(C43:D43) -> 0 | F43: =B43+E43 -> 1288.24 | G43: 0.11 | H43: =F43*G43 -> 141.7064 | I43: 65.35 | J43: =H43-I43 -> 76.3564 | N43: =J43 -> 76.3564 | O43: =O42 -> 38.07 | P43: =N43*(O43%) -> 29.068881 | Q43: =N43 -> 76.3564 | R43: 0.2 | S43: =Q43*R43 -> 15.27128 | T43: =E43 -> 0 | U43: =T43*21% -> 0 | V43: =O43 -> 38.07 | W43: =U43*(V43%) -> 0 | X43: =U43 -> 0 | Y43: =R43 -> 0.2 | Z43: =X43*Y43 -> 0
A44: 40057 | B44: 704.35 | D44: ='Anexo 4 HE'!S44 -> 65.551636 | E44: =SUM(C44:D44) -> 65.551636 | F44: =B44+E44 -> 769.90164 | G44: 0.08 | H44: =F44*G44 -> 61.592131 | I44: 56.35 | J44: =H44-I44 -> 5.2421309 | N44: =J44 -> 5.2421309 | O44: ='Multa INSS'!O68 -> 37.38 | P44: =N44*(O44%) -> 1.9595085 | Q44: =N44 -> 5.2421309 | R44: 0.2 | S44: =Q44*R44 -> 1.0484262 | T44: =E44 -> 65.551636 | U44: =T44*21% -> 13.765844 | V44: =O44 -> 37.38 | W44: =U44*(V44%) -> 5.1456724 | X44: =U44 -> 13.765844 | Y44: =R44 -> 0.2 | Z44: =X44*Y44 -> 2.7531687
A45: 40087 | B45: 955.91 | D45: ='Anexo 4 HE'!S45 -> 354.97507 | E45: =SUM(C45:D45) -> 354.97507 | F45: =B45+E45 -> 1310.8851 | G45: 0.09 | H45: =F45*G45 -> 117.97966 | I45: 76.47 | J45: =H45-I45 -> 41.509656 | N45: =J45 -> 41.509656 | O45: ='Multa INSS'!O69 -> 36.72 | P45: =N45*(O45%) -> 15.242346 | Q45: =N45 -> 41.509656 | R45: 0.2 | S45: =Q45*R45 -> 8.3019312 | T45: =E45 -> 354.97507 | U45: =T45*21% -> 74.544764 | V45: =O45 -> 36.72 | W45: =U45*(V45%) -> 27.372837 | X45: =U45 -> 74.544764 | Y45: =R45 -> 0.2 | Z45: =X45*Y45 -> 14.908953
A46: 40118 | B46: 958.99 | D46: ='Anexo 4 HE'!S46 -> 306.78942 | E46: =SUM(C46:D46) -> 306.78942 | F46: =B46+E46 -> 1265.7794 | G46: 0.09 | H46: =F46*G46 -> 113.92015 | I46: 76.47 | J46: =H46-I46 -> 37.450148 | N46: =J46 -> 37.450148 | O46: ='Multa INSS'!O70 -> 35.99 | P46: =N46*(O46%) -> 13.478308 | Q46: =N46 -> 37.450148 | R46: 0.2 | S46: =Q46*R46 -> 7.4900295 | T46: =E46 -> 306.78942 | U46: =T46*21% -> 64.425778 | V46: =O46 -> 35.99 | W46: =U46*(V46%) -> 23.186837 | X46: =U46 -> 64.425778 | Y46: =R46 -> 0.2 | Z46: =X46*Y46 -> 12.885156
A47: 40148 | B47: 1250.18 | D47: ='Anexo 4 HE'!S47 -> 353.45531 | E47: =SUM(C47:D47) -> 353.45531 | F47: =B47+E47 -> 1603.6353 | G47: 0.09 | H47: =F47*G47 -> 144.32718 | I47: 112.52 | J47: =H47-I47 -> 31.807178 | N47: =J47 -> 31.807178 | O47: ='Multa INSS'!O71 -> 35.33 | P47: =N47*(O47%) -> 11.237476 | Q47: =N47 -> 31.807178 | R47: 0.2 | S47: =Q47*R47 -> 6.3614355 | T47: =E47 -> 353.45531 | U47: =T47*21% -> 74.225614 | V47: =O47 -> 35.33 | W47: =U47*(V47%) -> 26.22391 | X47: =U47 -> 74.225614 | Y47: =R47 -> 0.2 | Z47: =X47*Y47 -> 14.845123
A48: 13º Salário 2009 (Média) | B48: 1018.81 | D48: ='Anexo 4 HE'!S48 -> 271.97578 | E48: =SUM(C48:D48) -> 271.97578 | F48: =B48+E48 -> 1290.7858 | G48: 0.09 | H48: =F48*G48 -> 116.17072 | I48: 91.69 | J48: =H48-I48 -> 24.48072 | N48: =J48 -> 24.48072 | O48: =O47 -> 35.33 | P48: =N48*(O48%) -> 8.6490385 | Q48: =N48 -> 24.48072 | R48: 0.2 | S48: =Q48*R48 -> 4.8961441 | T48: =E48 -> 271.97578 | U48: =T48*21% -> 57.114914 | V48: =O48 -> 35.33 | W48: =U48*(V48%) -> 20.178699 | X48: =U48 -> 57.114914 | Y48: =R48 -> 0.2 | Z48: =X48*Y48 -> 11.422983
A49: 40179 | B49: 1249.74 | D49: ='Anexo 4 HE'!S49 -> 340.88727 | E49: =SUM(C49:D49) -> 340.88727 | F49: =B49+E49 -> 1590.6273 | G49: 0.09 | H49: =F49*G49 -> 143.15645 | I49: 112.48 | J49: =H49-I49 -> 30.676455 | N49: =J49 -> 30.676455 | O49: ='Multa INSS'!Q12 -> 34.74 | P49: =N49*(O49%) -> 10.657 | Q49: =N49 -> 30.676455 | R49: 0.2 | S49: =Q49*R49 -> 6.1352909 | T49: =E49 -> 340.88727 | U49: =T49*21% -> 71.586327 | V49: =O49 -> 34.74 | W49: =U49*(V49%) -> 24.86909 | X49: =U49 -> 71.586327 | Y49: =R49 -> 0.2 | Z49: =X49*Y49 -> 14.317265
A50: 40210 | B50: 1012.5 | D50: ='Anexo 4 HE'!S50 -> 348.04387 | E50: =SUM(C50:D50) -> 348.04387 | F50: =B50+E50 -> 1360.5439 | G50: 0.09 | H50: =F50*G50 -> 122.44895 | I50: 81 | J50: =H50-I50 -> 41.448949 | N50: =J50 -> 41.448949 | O50: ='Multa INSS'!Q13 -> 33.98 | P50: =N50*(O50%) -> 14.084353 | Q50: =N50 -> 41.448949 | R50: 0.2 | S50: =Q50*R50 -> 8.2897897 | T50: =E50 -> 348.04387 | U50: =T50*21% -> 73.089213 | V50: =O50 -> 33.98 | W50: =U50*(V50%) -> 24.835715 | X50: =U50 -> 73.089213 | Y50: =R50 -> 0.2 | Z50: =X50*Y50 -> 14.617843
A51: 40238 | B51: 1012.5 | D51: ='Anexo 4 HE'!S51 -> 281.81818 | E51: =SUM(C51:D51) -> 281.81818 | F51: =B51+E51 -> 1294.3182 | G51: 0.09 | H51: =F51*G51 -> 116.48864 | I51: 80.85 | J51: =H51-I51 -> 35.638636 | N51: =J51 -> 35.638636 | O51: ='Multa INSS'!Q14 -> 33.31 | P51: =N51*(O51%) -> 11.87123 | Q51: =N51 -> 35.638636 | R51: 0.2 | S51: =Q51*R51 -> 7.1277273 | T51: =E51 -> 281.81818 | U51: =T51*21% -> 59.181818 | V51: =O51 -> 33.31 | W51: =U51*(V51%) -> 19.713464 | X51: =U51 -> 59.181818 | Y51: =R51 -> 0.2 | Z51: =X51*Y51 -> 11.836364
A52: 40269 | B52: 1012.5 | D52: ='Anexo 4 HE'!S52 -> 573.33297 | E52: =SUM(C52:D52) -> 573.33297 | F52: =B52+E52 -> 1585.833 | G52: 0.09 | H52: =F52*G52 -> 142.72497 | I52: 81 | J52: =H52-I52 -> 61.724967 | N52: =J52 -> 61.724967 | O52: ='Multa INSS'!Q15 -> 32.56 | P52: =N52*(O52%) -> 20.097649 | Q52: =N52 -> 61.724967 | R52: 0.2 | S52: =Q52*R52 -> 12.344993 | T52: =E52 -> 573.33297 | U52: =T52*21% -> 120.39992 | V52: =O52 -> 32.56 | W52: =U52*(V52%) -> 39.202215 | X52: =U52 -> 120.39992 | Y52: =R52 -> 0.2 | Z52: =X52*Y52 -> 24.079985
A53: 40299 | B53: 1012.5 | D53: ='Anexo 4 HE'!S53 -> 455.38739 | E53: =SUM(C53:D53) -> 455.38739 | F53: =B53+E53 -> 1467.8874 | G53: 0.09 | H53: =F53*G53 -> 132.10986 | I53: 81 | J53: =H53-I53 -> 51.109865 | N53: =J53 -> 51.109865 | O53: ='Multa INSS'!Q16 -> 31.77 | P53: =N53*(O53%) -> 16.237604 | Q53: =N53 -> 51.109865 | R53: 0.2 | S53: =Q53*R53 -> 10.221973 | T53: =E53 -> 455.38739 | U53: =T53*21% -> 95.631352 | V53: =O53 -> 31.77 | W53: =U53*(V53%) -> 30.38208 | X53: =U53 -> 95.631352 | Y53: =R53 -> 0.2 | Z53: =X53*Y53 -> 19.12627
A54: 40330 | B54: 565.64 | C54: ='Anexo 3 Dif Sal'!F13 -> 0 | D54: ='Anexo 4 HE'!S54 -> 272.17189 | E54: =SUM(C54:D54) -> 272.17189 | F54: =B54+E54 -> 837.81189 | G54: 0.08 | H54: =F54*G54 -> 67.024951 | I54: 89.3 | J54: 0 | N54: =J54 -> 0 | O54: ='Multa INSS'!Q17 -> 30.91 | P54: =N54*(O54%) -> 0 | Q54: =N54 -> 0 | R54: 0.2 | S54: =Q54*R54 -> 0 | T54: =E54 -> 272.17189 | U54: =T54*21% -> 57.156096 | V54: =O54 -> 30.91 | W54: =U54*(V54%) -> 17.666949 | X54: =U54 -> 57.156096 | Y54: =R54 -> 0.2 | Z54: =X54*Y54 -> 11.431219
A55: Férias + 1/3 | B55: 1354.21 | C55: 0 | D55: ='Anexo 4 HE'!S55 -> 0 | E55: =SUM(C55:D55) -> 0 | F55: =B55+E55 -> 1354.21 | G55: 0.11 | H55: =F55*G55 -> 148.9631 | I55: 121.88 | J55: =H55-I55 -> 27.0831 | N55: =J55 -> 27.0831 | O55: =O54 -> 30.91 | P55: =N55*(O55%) -> 8.3713862 | Q55: =N55 -> 27.0831 | R55: 0.2 | S55: =Q55*R55 -> 5.41662 | T55: =E55 -> 0 | U55: =T55*21% -> 0 | V55: =O55 -> 30.91 | W55: =U55*(V55%) -> 0 | X55: =U55 -> 0 | Y55: =R55 -> 0.2 | Z55: =X55*Y55 -> 0
A56: 40360 | B56: 1038.82 | C56: ='Anexo 3 Dif Sal'!F14 -> 77.9118 | D56: ='Anexo 4 HE'!S56 -> 325.62581 | E56: =SUM(C56:D56) -> 403.53761 | F56: =B56+E56 -> 1442.3576 | G56: 0.09 | H56: =F56*G56 -> 129.81218 | I56: 83.11 | J56: =H56-I56 -> 46.702185 | N56: =J56 -> 46.702185 | O56: ='Multa INSS'!Q18 -> 30.02 | P56: =N56*(O56%) -> 14.019996 | Q56: =N56 -> 46.702185 | R56: 0.2 | S56: =Q56*R56 -> 9.340437 | T56: =E56 -> 403.53761 | U56: =T56*21% -> 84.742898 | V56: =O56 -> 30.02 | W56: =U56*(V56%) -> 25.439818 | X56: =U56 -> 84.742898 | Y56: =R56 -> 0.2 | Z56: =X56*Y56 -> 16.94858
A57: 40391 | B57: 1321.8 | C57: ='Anexo 3 Dif Sal'!F15 -> 77.9118 | D57: ='Anexo 4 HE'!S57 -> 525.55238 | E57: =SUM(C57:D57) -> 603.46418 | F57: =B57+E57 -> 1925.2642 | G57: 0.11 | H57: =F57*G57 -> 211.77906 | I57: 118.96 | J57: =H57-I57 -> 92.81906 | N57: =J57 -> 92.81906 | O57: ='Multa INSS'!Q19 -> 29.17 | P57: =N57*(O57%) -> 27.07532 | Q57: =N57 -> 92.81906 | R57: 0.2 | S57: =Q57*R57 -> 18.563812 | T57: =E57 -> 603.46418 | U57: =T57*21% -> 126.72748 | V57: =O57 -> 29.17 | W57: =U57*(V57%) -> 36.966405 | X57: =U57 -> 126.72748 | Y57: =R57 -> 0.2 | Z57: =X57*Y57 -> 25.345495
A58: 40422 | B58: 1525.77 | C58: ='Anexo 3 Dif Sal'!F16 -> 77.9118 | D58: ='Anexo 4 HE'!S58 -> 491.23957 | E58: =SUM(C58:D58) -> 569.15137 | F58: =B58+E58 -> 2094.9214 | G58: 0.11 | H58: =F58*G58 -> 230.44135 | I58: 137.32 | J58: =H58-I58 -> 93.12135 | N58: =J58 -> 93.12135 | O58: ='Multa INSS'!Q20 -> 28.36 | P58: =N58*(O58%) -> 26.409215 | Q58: =N58 -> 93.12135 | R58: 0.2 | S58: =Q58*R58 -> 18.62427 | T58: =E58 -> 569.15137 | U58: =T58*21% -> 119.52179 | V58: =O58 -> 28.36 | W58: =U58*(V58%) -> 33.896379 | X58: =U58 -> 119.52179 | Y58: =R58 -> 0.2 | Z58: =X58*Y58 -> 23.904357
A59: 40452 | B59: 1298.53 | C59: ='Anexo 3 Dif Sal'!F17 -> 77.9118 | D59: ='Anexo 4 HE'!S59 -> 456.38472 | E59: =SUM(C59:D59) -> 534.29652 | F59: =B59+E59 -> 1832.8265 | G59: 0.11 | H59: =F59*G59 -> 201.61092 | I59: 116.87 | J59: =H59-I59 -> 84.740917 | N59: =J59 -> 84.740917 | O59: ='Multa INSS'!Q21 -> 27.55 | P59: =N59*(O59%) -> 23.346123 | Q59: =N59 -> 84.740917 | R59: 0.2 | S59: =Q59*R59 -> 16.948183 | T59: =E59 -> 534.29652 | U59: =T59*21% -> 112.20227 | V59: =O59 -> 27.55 | W59: =U59*(V59%) -> 30.911725 | X59: =U59 -> 112.20227 | Y59: =R59 -> 0.2 | Z59: =X59*Y59 -> 22.440454
A60: 40483 | B60: 1544.67 | C60: ='Anexo 3 Dif Sal'!F18 -> 9.0918 | D60: ='Anexo 4 HE'!S60 -> 493.4987 | E60: =SUM(C60:D60) -> 502.5905 | F60: =B60+E60 -> 2047.2605 | G60: 0.11 | H60: =F60*G60 -> 225.19866 | I60: 139.02 | J60: =H60-I60 -> 86.178655 | N60: =J60 -> 86.178655 | O60: ='Multa INSS'!Q22 -> 26.62 | P60: =N60*(O60%) -> 22.940758 | Q60: =N60 -> 86.178655 | R60: 0.2 | S60: =Q60*R60 -> 17.235731 | T60: =E60 -> 502.5905 | U60: =T60*21% -> 105.54401 | V60: =O60 -> 26.62 | W60: =U60*(V60%) -> 28.095814 | X60: =U60 -> 105.54401 | Y60: =R60 -> 0.2 | Z60: =X60*Y60 -> 21.108801
A61: 40513 | B61: 1714.12 | C61: ='Anexo 3 Dif Sal'!F19 -> 9.0918 | D61: ='Anexo 4 HE'!S61 -> 524.72229 | E61: =SUM(C61:D61) -> 533.81409 | F61: =B61+E61 -> 2247.9341 | G61: 0.11 | H61: =F61*G61 -> 247.27275 | I61: 154.27 | J61: =H61-I61 -> 93.00275 | N61: =J61 -> 93.00275 | O61: ='Multa INSS'!Q23 -> 25.76 | P61: =N61*(O61%) -> 23.957508 | Q61: =N61 -> 93.00275 | R61: 0.2 | S61: =Q61*R61 -> 18.60055 | T61: =E61 -> 533.81409 | U61: =T61*21% -> 112.10096 | V61: =O61 -> 25.76 | W61: =U61*(V61%) -> 28.877207 | X61: =U61 -> 112.10096 | Y61: =R61 -> 0.2 | Z61: =X61*Y61 -> 22.420192
A62: 13º Salário 2010 (Média) | B62: 1409.27 | C62: 0 | D62: ='Anexo 4 HE'!S62 -> 380.35154 | E62: =SUM(C62:D62) -> 380.35154 | F62: =B62+E62 -> 1789.6215 | G62: 0.11 | H62: =F62*G62 -> 196.85837 | I62: 126.83 | J62: =H62-I62 -> 70.028369 | N62: =J62 -> 70.028369 | O62: =O61 -> 25.76 | P62: =N62*(O62%) -> 18.039308 | Q62: =N62 -> 70.028369 | R62: 0.2 | S62: =Q62*R62 -> 14.005674 | T62: =E62 -> 380.35154 | U62: =T62*21% -> 79.873823 | V62: =O62 -> 25.76 | W62: =U62*(V62%) -> 20.575497 | X62: =U62 -> 79.873823 | Y62: =R62 -> 0.2 | Z62: =X62*Y62 -> 15.974765
A63: 40544 | B63: 1367.35 | C63: ='Anexo 3 Dif Sal'!F20 -> 9.0918 | D63: ='Anexo 4 HE'!S63 -> 480.95212 | E63: =SUM(C63:D63) -> 490.04392 | F63: =B63+E63 -> 1857.3939 | G63: 0.11 | H63: =F63*G63 -> 204.31333 | I63: 123.06 | J63: =H63-I63 -> 81.253331 | N63: =J63 -> 81.253331 | O63: ='Multa INSS'!Q24 -> 24.92 | P63: =N63*(O63%) -> 20.24833 | Q63: =N63 -> 81.253331 | R63: 0.2 | S63: =Q63*R63 -> 16.250666 | T63: =E63 -> 490.04392 | U63: =T63*21% -> 102.90922 | V63: =O63 -> 24.92 | W63: =U63*(V63%) -> 25.644979 | X63: =U63 -> 102.90922 | Y63: =R63 -> 0.2 | Z63: =X63*Y63 -> 20.581845
A64: 40575 | B64: 1405.29 | C64: ='Anexo 3 Dif Sal'!F21 -> 9.0918 | D64: ='Anexo 4 HE'!S64 -> 453.64592 | E64: =SUM(C64:D64) -> 462.73772 | F64: =B64+E64 -> 1868.0277 | G64: 0.11 | H64: =F64*G64 -> 205.48305 | I64: 126.48 | J64: =H64-I64 -> 79.003049 | N64: =J64 -> 79.003049 | O64: ='Multa INSS'!Q25 -> 24 | P64: =N64*(O64%) -> 18.960732 | Q64: =N64 -> 79.003049 | R64: 0.2 | S64: =Q64*R64 -> 15.80061 | T64: =E64 -> 462.73772 | U64: =T64*21% -> 97.17492 | V64: =O64 -> 24 | W64: =U64*(V64%) -> 23.321981 | X64: =U64 -> 97.17492 | Y64: =R64 -> 0.2 | Z64: =X64*Y64 -> 19.434984
A65: 40603 | B65: 1367.35 | C65: ='Anexo 3 Dif Sal'!F22 -> 9.0918 | D65: ='Anexo 4 HE'!S65 -> 518.20307 | E65: =SUM(C65:D65) -> 527.29487 | F65: =B65+E65 -> 1894.6449 | G65: 0.11 | H65: =F65*G65 -> 208.41094 | I65: 123.06 | J65: =H65-I65 -> 85.350935 | N65: =J65 -> 85.350935 | O65: ='Multa INSS'!Q26 -> 23.16 | P65: =N65*(O65%) -> 19.767277 | Q65: =N65 -> 85.350935 | R65: 0.2 | S65: =Q65*R65 -> 17.070187 | T65: =E65 -> 527.29487 | U65: =T65*21% -> 110.73192 | V65: =O65 -> 23.16 | W65: =U65*(V65%) -> 25.645513 | X65: =U65 -> 110.73192 | Y65: =R65 -> 0.2 | Z65: =X65*Y65 -> 22.146384
A66: 40634 | B66: 1459.91 | C66: ='Anexo 3 Dif Sal'!F23 -> 9.0918 | D66: ='Anexo 4 HE'!S66 -> 566.23539 | E66: =SUM(C66:D66) -> 575.32719 | F66: =B66+E66 -> 2035.2372 | G66: 0.11 | H66: =F66*G66 -> 223.87609 | I66: 131.39 | J66: =H66-I66 -> 92.486091 | N66: =J66 -> 92.486091 | O66: ='Multa INSS'!Q27 -> 22.17 | P66: =N66*(O66%) -> 20.504166 | Q66: =N66 -> 92.486091 | R66: 0.2 | S66: =Q66*R66 -> 18.497218 | T66: =E66 -> 575.32719 | U66: =T66*21% -> 120.81871 | V66: =O66 -> 22.17 | W66: =U66*(V66%) -> 26.785508 | X66: =U66 -> 120.81871 | Y66: =R66 -> 0.2 | Z66: =X66*Y66 -> 24.163742
A67: 40664 | B67: 1477.91 | C67: ='Anexo 3 Dif Sal'!F24 -> 9.0918 | D67: ='Anexo 4 HE'!S67 -> 297.96296 | E67: =SUM(C67:D67) -> 307.05476 | F67: =B67+E67 -> 1784.9648 | G67: 0.09 | H67: =F67*G67 -> 160.64683 | I67: 133.01 | J67: =H67-I67 -> 27.636829 | N67: =J67 -> 27.636829 | O67: ='Multa INSS'!Q28 -> 21.21 | P67: =N67*(O67%) -> 5.8617714 | Q67: =N67 -> 27.636829 | R67: 0.2 | S67: =Q67*R67 -> 5.5273657 | T67: =E67 -> 307.05476 | U67: =T67*21% -> 64.4815 | V67: =O67 -> 21.21 | W67: =U67*(V67%) -> 13.676526 | X67: =U67 -> 64.4815 | Y67: =R67 -> 0.2 | Z67: =X67*Y67 -> 12.8963
A68: 40695 | B68: 1491.83 | C68: ='Anexo 3 Dif Sal'!F25 -> 9.0918 | D68: ='Anexo 4 HE'!S68 -> 525.16996 | E68: =SUM(C68:D68) -> 534.26176 | F68: =B68+E68 -> 2026.0918 | G68: 0.11 | H68: =F68*G68 -> 222.87009 | I68: 126.16 | J68: =H68-I68 -> 96.710093 | N68: =J68 -> 96.710093 | O68: ='Multa INSS'!Q29 -> 20.24 | P68: =N68*(O68%) -> 19.574123 | Q68: =N68 -> 96.710093 | R68: 0.2 | S68: =Q68*R68 -> 19.342019 | T68: =E68 -> 534.26176 | U68: =T68*21% -> 112.19497 | V68: =O68 -> 20.24 | W68: =U68*(V68%) -> 22.708262 | X68: =U68 -> 112.19497 | Y68: =R68 -> 0.2 | Z68: =X68*Y68 -> 22.438994
A69: 40725 | B69: 1392.87 | C69: ='Anexo 3 Dif Sal'!F26 -> 105.44273 | D69: ='Anexo 4 HE'!S69 -> 509.74744 | E69: =SUM(C69:D69) -> 615.19017 | F69: =B69+E69 -> 2008.0602 | G69: 0.11 | H69: =F69*G69 -> 220.88662 | I69: 125.36 | J69: =H69-I69 -> 95.526618 | N69: =J69 -> 95.526618 | O69: ='Multa INSS'!Q30 -> 19.17 | P69: =N69*(O69%) -> 18.312453 | Q69: =N69 -> 95.526618 | R69: 0.2 | S69: =Q69*R69 -> 19.105324 | T69: =E69 -> 615.19017 | U69: =T69*21% -> 129.18993 | V69: =O69 -> 19.17 | W69: =U69*(V69%) -> 24.76571 | X69: =U69 -> 129.18993 | Y69: =R69 -> 0.2 | Z69: =X69*Y69 -> 25.837987
A70: 40756 | B70: 1501.97 | C70: ='Anexo 3 Dif Sal'!F27 -> 105.44273 | D70: ='Anexo 4 HE'!S70 -> 509.63282 | E70: =SUM(C70:D70) -> 615.07555 | F70: =B70+E70 -> 2117.0455 | G70: 0.11 | H70: =F70*G70 -> 232.87501 | I70: 135.18 | J70: =H70-I70 -> 97.69501 | N70: =J70 -> 97.69501 | O70: ='Multa INSS'!Q31 -> 18.23 | P70: =N70*(O70%) -> 17.8098 | Q70: =N70 -> 97.69501 | R70: 0.2 | S70: =Q70*R70 -> 19.539002 | T70: =E70 -> 615.07555 | U70: =T70*21% -> 129.16587 | V70: =O70 -> 18.23 | W70: =U70*(V70%) -> 23.546937 | X70: =U70 -> 129.16587 | Y70: =R70 -> 0.2 | Z70: =X70*Y70 -> 25.833173
A71: 40787 | B71: 1432 | C71: ='Anexo 3 Dif Sal'!F28 -> 105.44273 | D71: ='Anexo 4 HE'!S71 -> 492.70985 | E71: =SUM(C71:D71) -> 598.15258 | F71: =B71+E71 -> 2030.1526 | G71: 0.11 | H71: =F71*G71 -> 223.31678 | I71: 171.86 | J71: =H71-I71 -> 51.456783 | N71: =J71 -> 51.456783 | O71: ='Multa INSS'!Q32 -> 17.35 | P71: =N71*(O71%) -> 8.9277519 | Q71: =N71 -> 51.456783 | R71: 0.2 | S71: =Q71*R71 -> 10.291357 | T71: =E71 -> 598.15258 | U71: =T71*21% -> 125.61204 | V71: =O71 -> 17.35 | W71: =U71*(V71%) -> 21.793689 | X71: =U71 -> 125.61204 | Y71: =R71 -> 0.2 | Z71: =X71*Y71 -> 25.122408
A72: Férias + 1/3 | B72: 477.88 | C72: 0 | D72: ='Anexo 4 HE'!S72 -> 0 | E72: =SUM(C72:D72) -> 0 | F72: =B72+E72 -> 477.88 | G72: 0.08 | H72: =F72*G72 -> 38.2304 | I72: 38.23 | J72: =H72-I72 -> 0.0004 | N72: =J72 -> 0.0004 | O72: =O71 -> 17.35 | P72: =N72*(O72%) -> 6.94e-05 | Q72: =N72 -> 0.0004 | R72: 0.2 | S72: =Q72*R72 -> 8e-05 | T72: =E72 -> 0 | U72: =T72*21% -> 0 | V72: =O72 -> 17.35 | W72: =U72*(V72%) -> 0 | X72: =U72 -> 0 | Y72: =R72 -> 0.2 | Z72: =X72*Y72 -> 0
A73: 40817 | B73: 1526.66 | C73: ='Anexo 3 Dif Sal'!F29 -> 37.072726 | D73: 0 | E73: =SUM(C73:D73) -> 37.072726 | F73: =B73+E73 -> 1563.7327 | G73: 0.09 | H73: =F73*G73 -> 140.73595 | I73: 137.4 | J73: =H73-I73 -> 3.3359453 | N73: =J73 -> 3.3359453 | O73: ='Multa INSS'!Q33 -> 16.49 | P73: =N73*(O73%) -> 0.55009739 | Q73: =N73 -> 3.3359453 | R73: 0.2 | S73: =Q73*R73 -> 0.66718907 | T73: =E73 -> 37.072726 | U73: =T73*21% -> 7.7852725 | V73: =O73 -> 16.49 | W73: =U73*(V73%) -> 1.2837914 | X73: =U73 -> 7.7852725 | Y73: =R73 -> 0.2 | Z73: =X73*Y73 -> 1.5570545
A74: 40848 | B74: 1452.64 | C74: ='Anexo 3 Dif Sal'!F30 -> 37.072726 | D74: ='Anexo 4 HE'!S74 -> 333.79895 | E74: =SUM(C74:D74) -> 370.87168 | F74: =B74+E74 -> 1823.5117 | G74: 0.09 | H74: =F74*G74 -> 164.11605 | I74: 130.74 | J74: =H74-I74 -> 33.376051 | N74: =J74 -> 33.376051 | O74: ='Multa INSS'!Q34 -> 15.58 | P74: =N74*(O74%) -> 5.1999888 | Q74: =N74 -> 33.376051 | R74: 0.2 | S74: =Q74*R74 -> 6.6752102 | T74: =E74 -> 370.87168 | U74: =T74*21% -> 77.883053 | V74: =O74 -> 15.58 | W74: =U74*(V74%) -> 12.13418 | X74: =U74 -> 77.883053 | Y74: =R74 -> 0.2 | Z74: =X74*Y74 -> 15.576611
A75: 40878 | B75: 1488.31 | C75: ='Anexo 3 Dif Sal'!F31 -> 37.072726 | D75: ='Anexo 4 HE'!S75 -> 386.16552 | E75: =SUM(C75:D75) -> 423.23825 | F75: =B75+E75 -> 1911.5482 | G75: 0.11 | H75: =F75*G75 -> 210.27031 | I75: 133.95 | J75: =H75-I75 -> 76.320307 | N75: =J75 -> 76.320307 | O75: ='Multa INSS'!Q35 -> 14.69 | P75: =N75*(O75%) -> 11.211453 | Q75: =N75 -> 76.320307 | R75: 0.2 | S75: =Q75*R75 -> 15.264061 | T75: =E75 -> 423.23825 | U75: =T75*21% -> 88.880032 | V75: =O75 -> 14.69 | W75: =U75*(V75%) -> 13.056477 | X75: =U75 -> 88.880032 | Y75: =R75 -> 0.2 | Z75: =X75*Y75 -> 17.776006
A76: 13º Salário 2011 (Média) | B76: 1490.14 | C76: 0 | D76: ='Anexo 4 HE'!S76 -> 398.27235 | E76: =SUM(C76:D76) -> 398.27235 | F76: =B76+E76 -> 1888.4123 | G76: 0.09 | H76: =F76*G76 -> 169.95711 | I76: 134.11 | J76: =H76-I76 -> 35.847111 | N76: =J76 -> 35.847111 | O76: =O75 -> 14.69 | P76: =N76*(O76%) -> 5.2659407 | Q76: =N76 -> 35.847111 | R76: 0.2 | S76: =Q76*R76 -> 7.1694223 | T76: =E76 -> 398.27235 | U76: =T76*21% -> 83.637193 | V76: =O76 -> 14.69 | W76: =U76*(V76%) -> 12.286304 | X76: =U76 -> 83.637193 | Y76: =R76 -> 0.2 | Z76: =X76*Y76 -> 16.727439
A77: 40909 | B77: 1451.17 | C77: ='Anexo 3 Dif Sal'!F32 -> 37.072726 | D77: ='Anexo 4 HE'!S77 -> 453.27077 | E77: =SUM(C77:D77) -> 490.3435 | F77: =B77+E77 -> 1941.5135 | G77: 0.09 | H77: =F77*G77 -> 174.73621 | I77: 130.61 | J77: =H77-I77 -> 44.126215 | N77: =J77 -> 44.126215 | O77: ='Multa INSS'!Q36 -> 13.94 | P77: =N77*(O77%) -> 6.1511943 | Q77: =N77 -> 44.126215 | R77: 0.2 | S77: =Q77*R77 -> 8.8252429 | T77: =E77 -> 490.3435 | U77: =T77*21% -> 102.97213 | V77: =O77 -> 13.94 | W77: =U77*(V77%) -> 14.354315 | X77: =U77 -> 102.97213 | Y77: =R77 -> 0.2 | Z77: =X77*Y77 -> 20.594427
A78: 40940 | B78: 1518.06 | C78: ='Anexo 3 Dif Sal'!F33 -> 37.072726 | D78: ='Anexo 4 HE'!S78 -> 526.51107 | E78: =SUM(C78:D78) -> 563.5838 | F78: =B78+E78 -> 2081.6438 | G78: 0.11 | H78: =F78*G78 -> 228.98082 | I78: 136.63 | J78: =H78-I78 -> 92.350818 | N78: =J78 -> 92.350818 | O78: ='Multa INSS'!Q37 -> 13.12 | P78: =N78*(O78%) -> 12.116427 | Q78: =N78 -> 92.350818 | R78: 0.2 | S78: =Q78*R78 -> 18.470164 | T78: =E78 -> 563.5838 | U78: =T78*21% -> 118.3526 | V78: =O78 -> 13.12 | W78: =U78*(V78%) -> 15.527861 | X78: =U78 -> 118.3526 | Y78: =R78 -> 0.2 | Z78: =X78*Y78 -> 23.670519
A79: 40969 | B79: 1440.93 | C79: ='Anexo 3 Dif Sal'!F34 -> 37.072726 | D79: ='Anexo 4 HE'!S79 -> 337.63148 | E79: =SUM(C79:D79) -> 374.7042 | F79: =B79+E79 -> 1815.6342 | G79: 0.09 | H79: =F79*G79 -> 163.40708 | I79: 129.68 | J79: =H79-I79 -> 33.727078 | N79: =J79 -> 33.727078 | O79: ='Multa INSS'!Q38 -> 12.41 | P79: =N79*(O79%) -> 4.1855304 | Q79: =N79 -> 33.727078 | R79: 0.2 | S79: =Q79*R79 -> 6.7454156 | T79: =E79 -> 374.7042 | U79: =T79*21% -> 78.687882 | V79: =O79 -> 12.41 | W79: =U79*(V79%) -> 9.7651662 | X79: =U79 -> 78.687882 | Y79: =R79 -> 0.2 | Z79: =X79*Y79 -> 15.737576
A80: 41024 | B80: 3194.93 | C80: ='Anexo 3 Dif Sal'!F35 -> 30.893938 | D80: ='Anexo 4 HE'!S80 -> 562.65531 | E80: =SUM(C80:D80) -> 593.54925 | F80: =B80+E80 -> 3788.4793 | G80: 0.11 | H80: =F80*G80 -> 416.73272 | I80: 351.44 | J80: =H80-I80 -> 65.292718 | N80: =J80 -> 65.292718 | O80: ='Multa INSS'!Q39 -> 11.67 | P80: =N80*(O80%) -> 7.6196601 | Q80: =N80 -> 65.292718 | R80: 0.2 | S80: =Q80*R80 -> 13.058544 | T80: =E80 -> 593.54925 | U80: =T80*21% -> 124.64534 | V80: =O80 -> 11.67 | W80: =U80*(V80%) -> 14.546111 | X80: =U80 -> 124.64534 | Y80: =R80 -> 0.2 | Z80: =X80*Y80 -> 24.929069
A81: INSS COTA PARTE DA RECLAMANTE | L81: =SUM(L13:L80) -> 677.05043 | N81: =SUM(N13:N80) -> 2325.2975 | P81: =SUM(P13:P80) -> 600.5422 | S81: =SUM(S13:S80) -> 465.0595 | U81: =SUM(U13:U80) -> 3600.7734 | W81: =SUM(W13:W80) -> 933.50804 | Z81: =SUM(Z13:Z80) -> 720.15469
A82: BASE DE CÁLCULO DA COTA PARTE DA RECLAMADA | M82: =SUM(M13:M80) -> 7021.7425
J85: INSS PARTE DA RECLAMADA - MEMÓRIA DE CÁLCULO | O85: Total Reclamada | U85: Total Reclamante
J86: FPAS EMPRESA | M86: 0.2 | P86: Principal (até 02/2009) | S86: =M91 -> 1474.5659 | U86: Col. 12 | V86: Principal (até 02/2009) | Y86: =L81 -> 677.05043
J87: R.A.T. | M87: 0.01 | O87: Col. 21 | P87: Principal (a partir de 03/2009) | S87: =U81 -> 3600.7734 | U87: Col. 14 | V87: Principal (a partir de 03/2009) | Y87: =N81 -> 2325.2975
J88: TOTAL | M88: =SUM(M86:M87) -> 0.21 | O88: Col. 23 | P88: Juros | S88: =W81 -> 933.50804 | U88: Col. 16 | V88: Juros | Y88: =P81 -> 600.5422
J89: Base de Cálculo sobre os Valores Apurados Nesta Ação | M89: =M82 -> 7021.7425 | O89: Col. 26 | P89: Multa | S89: =Z81 -> 720.15469 | U89: Col. 19 | V89: Multa | Y89: =S81 -> 465.0595
J90: % Parte da Reclamada | M90: =M88 -> 0.21 | O90: Total | S90: =SUM(S86:S89) -> 6729.0021 | U90: Total | Y90: =SUM(Y86:Y89) -> 4067.9496
J91: TOTAL | M91: =M89*M90 -> 1474.5659

Sheet Multa INSS
A1: PROCESSO:
A2: VARA:
A3: RECLAMANTE:
A4: RECLAMADA:
A6: ANEXO 6.1 (PLANILHA AUXILIAR)
A7: APURAÇÃO DA CONTRIBUIÇÃO PREVIDENCIÁRIA
A9: Tabela Prática a ser aplicada nas contribuições em atraso - vigência 11/2013
A11: Compet | B11: Coefic. Ufir | C11: Juros% | D11: Compet | E11: Coefic. Ufir | F11: Juros% | G11: Compet | H11: Coefic. Ufir | I11: Juros% | J11: Compet | K11: Juros% | L11: Compet | M11: Juros% | N11: Compet | O11: Juros% | P11: Compet | Q11: Juros%
A12: 29221 | B12: 0.00194635 | C12: 784.48 | D12: 31048 | E12: 4.322e-05 | F12: 724.48 | G12: 32874 | H12: 0.01084363 | I12: 664.48 | J12: 34700 | K12: 318.51 | L12: 36526 | M12: 185.1 | N12: 38353 | O12: 99.18 | P12: 40179 | Q12: 34.74
A13: 29252 | B13: 0.00194635 | C13: 783.48 | D13: 31079 | E13: 3.835e-05 | F13: 723.48 | G13: 32905 | H13: 0.00635213 | I13: 663.48 | J13: 34731 | K13: 315.91 | L13: 36557 | M13: 183.65 | N13: 38384 | O13: 97.65 | P13: 40210 | Q13: 33.98
A14: 29281 | B14: 0.00177425 | C14: 782.48 | D14: 31107 | E14: 3.429e-05 | F14: 722.48 | G14: 32933 | H14: 0.00509111 | I14: 662.48 | J14: 34759 | K14: 311.65 | L14: 36586 | M14: 182.35 | N14: 38412 | O14: 96.24 | P14: 40238 | Q14: 33.31
A15: 29312 | B15: 0.00177425 | C15: 781.48 | D15: 31138 | E15: 3.117e-05 | F15: 721.48 | G15: 32964 | H15: 0.00509111 | I15: 661.48 | J15: 34790 | K15: 307.4 | L15: 36617 | M15: 180.86 | N15: 38443 | O15: 94.74 | P15: 40269 | Q15: 32.56
A16: 29342 | B16: 0.00177425 | C16: 780.48 | D16: 31168 | E16: 2.855e-05 | F16: 720.48 | G16: 32994 | H16: 0.00483117 | I16: 660.48 | J16: 34820 | K16: 303.36 | L16: 36647 | M16: 179.47 | N16: 38473 | O16: 93.15 | P16: 40299 | Q16: 31.77
A17: 29373 | B17: 0.00177425 | C17: 779.48 | D17: 31199 | E17: 2.653e-05 | F17: 719.48 | G17: 33025 | H17: 0.0044076 | I17: 659.48 | J17: 34851 | K17: 299.34 | L17: 36678 | M17: 178.16 | N17: 38504 | O17: 91.64 | P17: 40330 | Q17: 30.91
A18: 29403 | B18: 0.00177425 | C18: 778.48 | D18: 31229 | E18: 2.452e-05 | F18: 718.48 | G18: 33055 | H18: 0.00397833 | I18: 658.48 | J18: 34881 | K18: 295.5 | L18: 36708 | M18: 176.75 | N18: 38534 | O18: 89.98 | P18: 40360 | Q18: 30.02
A19: 29434 | B19: 0.00177425 | C19: 777.48 | D19: 31260 | E19: 2.247e-05 | F19: 717.48 | G19: 33086 | H19: 0.0035978 | I19: 657.48 | J19: 34912 | K19: 292.18 | L19: 36739 | M19: 175.53 | N19: 38565 | O19: 88.48 | P19: 40391 | Q19: 29.17
A20: 29465 | B20: 0.00177425 | C20: 776.48 | D20: 31291 | E20: 2.062e-05 | F20: 716.48 | G20: 33117 | H20: 0.00318812 | I20: 656.48 | J20: 34943 | K20: 289.09 | L20: 36770 | M20: 174.24 | N20: 38596 | O20: 87.07 | P20: 40422 | Q20: 28.36
A21: 29495 | B21: 0.00177425 | C21: 775.48 | D21: 31321 | E21: 1.856e-05 | F21: 715.48 | G21: 33147 | H21: 0.00280374 | I21: 655.48 | J21: 34973 | K21: 286.21 | L21: 36800 | M21: 173.02 | N21: 38626 | O21: 85.69 | P21: 40452 | Q21: 27.55
A22: 29526 | B22: 0.00177425 | C22: 774.48 | D22: 31352 | E22: 1.637e-05 | F22: 714.48 | G22: 33178 | H22: 0.00240361 | I22: 654.48 | J22: 35004 | K22: 283.43 | L22: 36831 | M22: 171.82 | N22: 38657 | O22: 84.22 | P22: 40483 | Q22: 26.62
A23: 29556 | B23: 0.00168975 | C23: 773.48 | D23: 31382 | E23: 1.408e-05 | F23: 713.48 | G23: 33208 | H23: 0.00201337 | I23: 653.48 | J23: 35034 | K23: 280.85 | L23: 36861 | M23: 170.55 | N23: 38687 | O23: 82.79 | P23: 40513 | Q23: 25.76
... A58: 30621 | B58: 0.00017364 | C58: 738.48 | D58: 32448 | E58: 0.00021233 | F58: 678.48 | G58: 34274 | H58: 0.00727961 | I58: 294.96 | J58: 36100 | K58: 211.03 | L58: 37926 | M58: 116.92 | N58: 39753 | O58: 46.49 | P58: 41579 | Q58: 0
A59: 30651 | B59: 0.00015814 | C59: 737.48 | D59: 32478 | E59: 0.00021233 | F59: 677.48 | G59: 34304 | H59: 0.00532566 | I59: 293.96 | J59: 36130 | K59: 208.85 | L59: 37956 | M59: 115.65 | N59: 39783 | O59: 44.44
A60: 30682 | B60: 0.00014082 | C60: 736.48 | D60: 32509 | E60: 0.21232724 | F60: 676.48 | G60: 34335 | H60: 0.00382673 | I60: 292.96 | J60: 36161 | K60: 206.47 | L60: 37987 | M60: 114.57 | N60: 39814 | O60: 43.58
A61: 30713 | B61: 0.00012802 | C61: 735.48 | D61: 32540 | E61: 0.20498241 | F61: 675.48 | G61: 34366 | H61: 0.00273928 | I61: 291.96 | J61: 36192 | K61: 203.14 | L61: 38018 | M61: 113.19 | N61: 39845 | O61: 42.61
A62: 30742 | B62: 0.00011756 | C62: 734.48 | D62: 32568 | E62: 0.19318896 | F62: 674.48 | G62: 34394 | H62: 0.00190716 | I62: 290.96 | J62: 36220 | K62: 200.79 | L62: 38047 | M62: 112.01 | N62: 39873 | O62: 41.77
A63: 30773 | B63: 0.00010795 | C63: 733.48 | D63: 32599 | E63: 0.18004271 | F63: 673.48 | G63: 34425 | H63: 0.0013502 | I63: 289.96 | J63: 36251 | K63: 198.77 | L63: 38078 | M63: 110.78 | N63: 39904 | O63: 41
A64: 30803 | B64: 9.885e-05 | C64: 732.48 | D64: 32629 | E64: 0.16376126 | F64: 672.48 | G64: 34455 | H64: 0.00093628 | I64: 288.96 | J64: 36281 | K64: 197.1 | L64: 38108 | M64: 109.55 | N64: 39934 | O64: 40.24
A65: 30834 | B65: 8.962e-05 | C65: 731.48 | D65: 32660 | E65: 0.13118799 | F65: 671.48 | G65: 34486 | H65: 0.00064727 | I65: 287.96 | J65: 36312 | K65: 195.44 | L65: 38139 | M65: 108.26 | N65: 39965 | O65: 39.45
A66: 30864 | B66: 8.103e-05 | C66: 730.48 | D66: 32690 | E66: 0.10187871 | F66: 670.48 | G66: 34516 | H66: 1.6917611 | I66: 286.96 | J66: 36342 | K66: 193.87 | L66: 38169 | M66: 106.97 | N66: 39995 | O66: 38.76
A67: 30895 | B67: 7.334e-05 | C67: 729.48 | D67: 32721 | E67: 0.07877165 | F67: 669.48 | G67: 34547 | H67: 1.6110843 | I67: 285.96 | J67: 36373 | K67: 192.38 | L67: 38200 | M67: 105.72 | N67: 40026 | O67: 38.07
A68: 30926 | B68: 6.513e-05 | C68: 728.48 | D68: 32752 | E68: 0.05466369 | F68: 668.48 | G68: 34578 | H68: 1.5852885 | I68: 284.96 | J68: 36404 | K68: 191 | L68: 38231 | M68: 104.51 | N68: 40057 | O68: 37.38
A69: 30956 | B69: 5.926e-05 | C69: 727.48 | D69: 32782 | E69: 0.03951094 | F69: 667.48 | G69: 34608 | H69: 1.5556938 | I69: 283.96 | J69: 36434 | K69: 189.61 | L69: 38261 | M69: 103.26 | N69: 40087 | O69: 36.72
A70: 30987 | B70: 5.363e-05 | C70: 726.48 | D70: 32813 | E70: 0.02726627 | F70: 666.48 | G70: 34639 | H70: 1.5110305 | I70: 282.96 | J70: 36465 | K70: 188.01 | L70: 38292 | M70: 101.78 | N70: 40118 | O70: 35.99
A71: 31017 | B71: 4.763e-05 | C71: 725.48 | D71: 32843 | E71: 0.01797005 | F71: 665.48 | G71: 34669 | H71: 1.4777597 | I71: 281.96 | J71: 36495 | K71: 186.55 | L71: 38322 | M71: 100.4 | N71: 40148 | O71: 35.33
A73: Fonte: http://www2.dataprev.gov.br/pls/sal/pr_sal2_emite_planilha

Sheet Anexo 7 IRRF
A1: PROCESSO:
A2: VARA:
A3: RECLAMANTE:
A4: RECLAMADA:
A6: ANEXO 7
A7: APURAÇÃO DO IMPOSTO DE RENDA RETIDO NA FONTE
A9: Mês / Ano | B9: Valores conquistados nesta ação que são base de incidência do IRRF (Tabela de Incidências do Manual de Cálculos Judiciais TRT 3ª Região) (Valores transferidos já corrigidos) | E9: Juros do ajuizamento da ação (12/06/2012) até 30/11/2013 (1%am) | G9: Total Bruto (Valor Corrigido + Juros) | H9: INSS cota parte do Reclamante | I9: Base IR com juros e líquida de INSS (RRA)
B10: Anexo 3 | C10: Anexo 4 | D10: Soma | E10: % | F10: Valor
A12: Col. 1 | B12: Col. 2 | C12: Col. 3 | D12: Col. 4 | E12: Col. 5 | F12: Col. 6 | G12: Col. 7 | H12: Col. 8 | I12: Col. 9
A13: 39234 | C13: ='Anexo 4 HE'!U13 -> 149.12824 | D13: =SUM(B13:C13) -> 149.12824 | E13: Não foi incluído conforme determinação do Exmo Juiz na r. sentença. | G13: =D13 -> 149.12824 | H13: ='Anexo 6 INSS'!L13 -> 12.902205 | I13: =G13-H13 -> 136.22603
A14: 39264 | C14: ='Anexo 4 HE'!U14 -> 431.91744 | D14: =SUM(B14:C14) -> 431.91744 | G14: =D14 -> 431.91744 | H14: ='Anexo 6 INSS'!L14 -> 42.175382 | I14: =G14-H14 -> 389.74205
A15: 39295 | C15: ='Anexo 4 HE'!U15 -> 441.93635 | D15: =SUM(B15:C15) -> 441.93635 | G15: =D15 -> 441.93635 | H15: ='Anexo 6 INSS'!L15 -> 43.207647 | I15: =G15-H15 -> 398.7287
A16: 39326 | C16: ='Anexo 4 HE'!U16 -> 430.03996 | D16: =SUM(B16:C16) -> 430.03996 | G16: =D16 -> 430.03996 | H16: ='Anexo 6 INSS'!L16 -> 42.049346 | I16: =G16-H16 -> 387.99062
A17: 39356 | C17: ='Anexo 4 HE'!U17 -> 453.90602 | D17: =SUM(B17:C17) -> 453.90602 | G17: =D17 -> 453.90602 | H17: ='Anexo 6 INSS'!L17 -> 44.258503 | I17: =G17-H17 -> 409.64752
A18: 39387 | C18: ='Anexo 4 HE'!U18 -> 145.5488 | D18: =SUM(B18:C18) -> 145.5488 | G18: =D18 -> 145.5488 | H18: ='Anexo 6 INSS'!L18 -> 13.103271 | I18: =G18-H18 -> 132.44553
A19: 39417 | C19: ='Anexo 4 HE'!U19 -> 200.73609 | D19: =SUM(B19:C19) -> 200.73609 | G19: =D19 -> 200.73609 | H19: ='Anexo 6 INSS'!L19 -> 17.360011 | I19: =G19-H19 -> 183.37608 | L19: Ajuizamento da ação | N19: 41072 | O19: 0.006 | P19: 18 dias | Q19: =1/30*18 -> 0.6
A20: 13º Salário 2007 (Média) | C20: ='Anexo 4 HE'!U20 -> 185.73469 | D20: =SUM(B20:C20) -> 185.73469 | G20: =D20 -> 185.73469 | H20: ='Anexo 6 INSS'!L20 -> 14.203814 | I20: =G20-H20 -> 171.53088 | L20: 2012 | N20: 6 m | O20: 0.06
A21: 39448 | C21: ='Anexo 4 HE'!U21 -> 351.28359 | D21: =SUM(B21:C21) -> 351.28359 | G21: =D21 -> 351.28359 | H21: ='Anexo 6 INSS'!L21 -> 31.616988 | I21: =G21-H21 -> 319.6666 | L21: 41608 | N21: 11 m | O21: 0.11
A22: 39479 | C22: ='Anexo 4 HE'!U22 -> 323.42165 | D22: =SUM(B22:C22) -> 323.42165 | G22: =D22 -> 323.42165 | H22: ='Anexo 6 INSS'!L22 -> 29.111401 | I22: =G22-H22 -> 294.31025 | N22: Total | O22: =SUM(O19:O21) -> 0.176
A23: 39508 | C23: ='Anexo 4 HE'!U23 -> 224.3372 | D23: =SUM(B23:C23) -> 224.3372 | G23: =D23 -> 224.3372 | H23: ='Anexo 6 INSS'!L23 -> 29.684375 | I23: =G23-H23 -> 194.65282
A24: 39539 | C24: ='Anexo 4 HE'!U24 -> 374.66767 | D24: =SUM(B24:C24) -> 374.66767 | G24: =D24 -> 374.66767 | H24: ='Anexo 6 INSS'!L24 -> 43.165669 | I24: =G24-H24 -> 331.502
A25: 39569 | C25: ='Anexo 4 HE'!U25 -> 320.43913 | D25: =SUM(B25:C25) -> 320.43913 | G25: =D25 -> 320.43913 | H25: ='Anexo 6 INSS'!L25 -> 0 | I25: =G25-H25 -> 320.43913
A26: Férias + 1/3 | C26: ='Anexo 4 HE'!U26 -> 0 | D26: =SUM(B26:C26) -> 0 | G26: =D26 -> 0 | H26: ='Anexo 6 INSS'!L26 -> 26.091548 | I26: 0
A27: 39600 | C27: 0 | D27: =SUM(B27:C27) -> 0 | G27: =D27 -> 0 | H27: ='Anexo 6 INSS'!L27 -> 0.0016685683 | I27: =G27-H27 -> -0.0016685683
A28: 39630 | C28: ='Anexo 4 HE'!U28 -> 302.8331 | D28: =SUM(B28:C28) -> 302.8331 | G28: =D28 -> 302.8331 | H28: ='Anexo 6 INSS'!L28 -> 36.55332 | I28: =G28-H28 -> 266.27978
A29: 39661 | C29: ='Anexo 4 HE'!U29 -> 391.34688 | D29: =SUM(B29:C29) -> 391.34688 | G29: =D29 -> 391.34688 | H29: ='Anexo 6 INSS'!L29 -> 35.223817 | I29: =G29-H29 -> 356.12306
A30: 39692 | C30: ='Anexo 4 HE'!U30 -> 263.50465 | D30: =SUM(B30:C30) -> 263.50465 | G30: =D30 -> 263.50465 | H30: ='Anexo 6 INSS'!L30 -> 23.71293 | I30: =G30-H30 -> 239.79172
A31: 39722 | C31: ='Anexo 4 HE'!U31 -> 322.47949 | D31: =SUM(B31:C31) -> 322.47949 | G31: =D31 -> 322.47949 | H31: ='Anexo 6 INSS'!L31 -> 29.02512 | I31: =G31-H31 -> 293.45437
A32: 39753 | C32: ='Anexo 4 HE'!U32 -> 354.09045 | D32: =SUM(B32:C32) -> 354.09045 | G32: =D32 -> 354.09045 | H32: ='Anexo 6 INSS'!L32 -> 31.867211 | I32: =G32-H32 -> 322.22324
A33: 39783 | C33: ='Anexo 4 HE'!U33 -> 312.49255 | D33: =SUM(B33:C33) -> 312.49255 | G33: =D33 -> 312.49255 | H33: ='Anexo 6 INSS'!L33 -> 28.128246 | I33: =G33-H33 -> 284.3643
A34: 13º Salário 2008 (Média) | C34: ='Anexo 4 HE'!U34 -> 261.57479 | D34: =SUM(B34:C34) -> 261.57479 | G34: =D34 -> 261.57479 | H34: ='Anexo 6 INSS'!L34 -> 23.5439 | I34: =G34-H34 -> 238.03089
A35: 39814 | C35: ='Anexo 4 HE'!U35 -> 344.1336 | D35: =SUM(B35:C35) -> 344.1336 | G35: =D35 -> 344.1336 | H35: ='Anexo 6 INSS'!L35 -> 30.973979 | I35: =G35-H35 -> 313.15962
A36: 39845 | C36: ='Anexo 4 HE'!U36 -> 436.19022 | D36: =SUM(B36:C36) -> 436.19022 | G36: =D36 -> 436.19022 | H36: ='Anexo 6 INSS'!L36 -> 49.090083 | I36: =G36-H36 -> 387.10014
A37: 39873 | C37: ='Anexo 4 HE'!U37 -> 321.31852 | D37: =SUM(B37:C37) -> 321.31852 | G37: =D37 -> 321.31852 | H37: ='Anexo 6 INSS'!N37+'Anexo 6 INSS'!P37 -> 53.481047 | I37: =G37-H37 -> 267.83747
A38: 39904 | C38: ='Anexo 4 HE'!U38 -> 392.0064 | D38: =SUM(B38:C38) -> 392.0064 | G38: =D38 -> 392.0064 | H38: ='Anexo 6 INSS'!N38+'Anexo 6 INSS'!P38 -> 61.94812 | I38: =G38-H38 -> 330.05828
A39: 39934 | C39: ='Anexo 4 HE'!U39 -> 336.1385 | D39: =SUM(B39:C39) -> 336.1385 | G39: =D39 -> 336.1385 | H39: ='Anexo 6 INSS'!N39+'Anexo 6 INSS'!P39 -> 54.762759 | I39: =G39-H39 -> 281.37574
A40: 39965 | C40: ='Anexo 4 HE'!U40 -> 347.13673 | D40: =SUM(B40:C40) -> 347.13673 | G40: =D40 -> 347.13673 | H40: ='Anexo 6 INSS'!N40+'Anexo 6 INSS'!P40 -> 55.751273 | I40: =G40-H40 -> 291.38546
A41: 39995 | C41: ='Anexo 4 HE'!U41 -> 369.06756 | D41: =SUM(B41:C41) -> 369.06756 | G41: =D41 -> 369.06756 | H41: ='Anexo 6 INSS'!N41+'Anexo 6 INSS'!P41 -> 58.269864 | I41: =G41-H41 -> 310.7977
A42: 40026 | C42: ='Anexo 4 HE'!U42 -> 303.89406 | D42: =SUM(B42:C42) -> 303.89406 | G42: =D42 -> 303.89406 | H42: ='Anexo 6 INSS'!N42+'Anexo 6 INSS'!P42 -> 0 | I42: =G42-H42 -> 303.89406
A43: Férias + 1/3 | C43: ='Anexo 4 HE'!U43 -> 0 | D43: =SUM(B43:C43) -> 0 | G43: =D43 -> 0 | H43: ='Anexo 6 INSS'!N43+'Anexo 6 INSS'!P43 -> 105.42528 | I43: 0
A44: 40057 | C44: ='Anexo 4 HE'!U44 -> 67.124498 | D44: =SUM(B44:C44) -> 67.124498 | G44: =D44 -> 67.124498 | H44: ='Anexo 6 INSS'!N44+'Anexo 6 INSS'!P44 -> 7.2016394 | I44: =G44-H44 -> 59.922859
A45: 40087 | C45: ='Anexo 4 HE'!U45 -> 363.49242 | D45: =SUM(B45:C45) -> 363.49242 | G45: =D45 -> 363.49242 | H45: ='Anexo 6 INSS'!N45+'Anexo 6 INSS'!P45 -> 56.752002 | I45: =G45-H45 -> 306.74042
A46: 40118 | C46: ='Anexo 4 HE'!U46 -> 314.1506 | D46: =SUM(B46:C46) -> 314.1506 | G46: =D46 -> 314.1506 | H46: ='Anexo 6 INSS'!N46+'Anexo 6 INSS'!P46 -> 50.928456 | I46: =G46-H46 -> 263.22214
A47: 40148 | C47: ='Anexo 4 HE'!U47 -> 361.74339 | D47: =SUM(B47:C47) -> 361.74339 | G47: =D47 -> 361.74339 | H47: ='Anexo 6 INSS'!N47+'Anexo 6 INSS'!P47 -> 43.044653 | I47: =G47-H47 -> 318.69874
A48: 13º Salário 2009 (Média) | C48: ='Anexo 4 HE'!U48 -> 278.50163 | D48: =SUM(B48:C48) -> 278.50163 | G48: =D48 -> 278.50163 | H48: ='Anexo 6 INSS'!N48+'Anexo 6 INSS'!P48 -> 33.129759 | I48: =G48-H48 -> 245.37188
A49: 40179 | C49: ='Anexo 4 HE'!U49 -> 348.88065 | D49: =SUM(B49:C49) -> 348.88065 | G49: =D49 -> 348.88065 | H49: ='Anexo 6 INSS'!N49+'Anexo 6 INSS'!P49 -> 41.333455 | I49: =G49-H49 -> 307.5472
A50: 40210 | C50: ='Anexo 4 HE'!U50 -> 356.20507 | D50: =SUM(B50:C50) -> 356.20507 | G50: =D50 -> 356.20507 | H50: ='Anexo 6 INSS'!N50+'Anexo 6 INSS'!P50 -> 55.533301 | I50: =G50-H50 -> 300.67176
A51: 40238 | C51: ='Anexo 4 HE'!U51 -> 288.19821 | D51: =SUM(B51:C51) -> 288.19821 | G51: =D51 -> 288.19821 | H51: ='Anexo 6 INSS'!N51+'Anexo 6 INSS'!P51 -> 47.509866 | I51: =G51-H51 -> 240.68835
A52: 40269 | C52: ='Anexo 4 HE'!U52 -> 586.31255 | D52: =SUM(B52:C52) -> 586.31255 | G52: =D52 -> 586.31255 | H52: ='Anexo 6 INSS'!N52+'Anexo 6 INSS'!P52 -> 81.822616 | I52: =G52-H52 -> 504.48993
A53: 40299 | C53: ='Anexo 4 HE'!U53 -> 465.45944 | D53: =SUM(B53:C53) -> 465.45944 | G53: =D53 -> 465.45944 | H53: ='Anexo 6 INSS'!N53+'Anexo 6 INSS'!P53 -> 67.347469 | I53: =G53-H53 -> 398.11197
A54: 40330 | B54: ='Anexo 3 Dif Sal'!H13 -> 0 | C54: ='Anexo 4 HE'!U54 -> 278.0279 | D54: =SUM(B54:C54) -> 278.0279 | G54: =D54 -> 278.0279 | H54: ='Anexo 6 INSS'!N54+'Anexo 6 INSS'!P54 -> 0 | I54: =G54-H54 -> 278.0279
A55: Férias + 1/3 | B55: 0 | C55: ='Anexo 4 HE'!U55 -> 0 | D55: =SUM(B55:C55) -> 0 | G55: =D55 -> 0 | H55: ='Anexo 6 INSS'!N55+'Anexo 6 INSS'!P55 -> 35.454486 | I55: 0
A56: 40360 | B56: ='Anexo 3 Dif Sal'!H14 -> 79.496639 | C56: ='Anexo 4 HE'!U56 -> 332.24951 | D56: =SUM(B56:C56) -> 411.74615 | G56: =D56 -> 411.74615 | H56: ='Anexo 6 INSS'!N56+'Anexo 6 INSS'!P56 -> 60.722181 | I56: =G56-H56 -> 351.02397
A57: 40391 | B57: ='Anexo 3 Dif Sal'!H15 -> 79.424442 | C57: ='Anexo 4 HE'!U57 -> 535.75587 | D57: =SUM(B57:C57) -> 615.18032 | G57: =D57 -> 615.18032 | H57: ='Anexo 6 INSS'!N57+'Anexo 6 INSS'!P57 -> 119.89438 | I57: =G57-H57 -> 495.28594
A58: 40422 | B58: ='Anexo 3 Dif Sal'!H16 -> 79.368725 | C58: ='Anexo 4 HE'!U58 -> 500.42559 | D58: =SUM(B58:C58) -> 579.79431 | G58: =D58 -> 579.79431 | H58: ='Anexo 6 INSS'!N58+'Anexo 6 INSS'!P58 -> 119.53057 | I58: =G58-H58 -> 460.26375
A59: 40452 | B59: ='Anexo 3 Dif Sal'!H17 -> 79.331281 | C59: ='Anexo 4 HE'!U59 -> 464.69963 | D59: =SUM(B59:C59) -> 544.03091 | G59: =D59 -> 544.03091 | H59: ='Anexo 6 INSS'!N59+'Anexo 6 INSS'!P59 -> 108.08704 | I59: =G59-H59 -> 435.94387
A60: 40483 | B60: ='Anexo 3 Dif Sal'!H18 -> 9.2543347 | C60: ='Anexo 4 HE'!U60 -> 502.32101 | D60: =SUM(B60:C60) -> 511.57535 | G60: =D60 -> 511.57535 | H60: ='Anexo 6 INSS'!N60+'Anexo 6 INSS'!P60 -> 109.11941 | I60: =G60-H60 -> 402.45593
A61: 40513 | B61: ='Anexo 3 Dif Sal'!H19 -> 9.2413414 | C61: ='Anexo 4 HE'!U61 -> 533.3529 | D61: =SUM(B61:C61) -> 542.59424 | G61: =D61 -> 542.59424 | H61: ='Anexo 6 INSS'!N61+'Anexo 6 INSS'!P61 -> 116.96026 | I61: =G61-H61 -> 425.63398
A62: 13º Salário 2010 (Média) | B62: 0 | C62: ='Anexo 4 HE'!U62 -> 387.15111 | D62: =SUM(B62:C62) -> 387.15111 | G62: =D62 -> 387.15111 | H62: ='Anexo 6 INSS'!N62+'Anexo 6 INSS'!P62 -> 88.067677 | I62: =G62-H62 -> 299.08343
A63: 40544 | B63: ='Anexo 3 Dif Sal'!H20 -> 9.2347386 | C63: ='Anexo 4 HE'!U63 -> 488.51351 | D63: =SUM(B63:C63) -> 497.74825 | G63: =D63 -> 497.74825 | H63: ='Anexo 6 INSS'!N63+'Anexo 6 INSS'!P63 -> 101.50166 | I63: =G63-H63 -> 396.24659
A64: 40575 | B64: ='Anexo 3 Dif Sal'!H21 -> 9.2299021 | C64: ='Anexo 4 HE'!U64 -> 460.53668 | D64: =SUM(B64:C64) -> 469.76658 | G64: =D64 -> 469.76658 | H64: ='Anexo 6 INSS'!N64+'Anexo 6 INSS'!P64 -> 97.96378 | I64: =G64-H64 -> 371.8028
A65: 40603 | B65: ='Anexo 3 Dif Sal'!H22 -> 9.218729 | C65: ='Anexo 4 HE'!U65 -> 525.43761 | D65: =SUM(B65:C65) -> 534.65634 | G65: =D65 -> 534.65634 | H65: ='Anexo 6 INSS'!N65+'Anexo 6 INSS'!P65 -> 105.11821 | I65: =G65-H65 -> 429.53812
A66: 40634 | B66: ='Anexo 3 Dif Sal'!H23 -> 9.2153285 | C66: ='Anexo 4 HE'!U66 -> 573.92872 | D66: =SUM(B66:C66) -> 583.14405 | G66: =D66 -> 583.14405 | H66: ='Anexo 6 INSS'!N66+'Anexo 6 INSS'!P66 -> 112.99026 | I66: =G66-H66 -> 470.1538
A67: 40664 | B67: ='Anexo 3 Dif Sal'!H24 -> 9.2008832 | C67: ='Anexo 4 HE'!U67 -> 301.53791 | D67: =SUM(B67:C67) -> 310.7388 | G67: =D67 -> 310.7388 | H67: ='Anexo 6 INSS'!N67+'Anexo 6 INSS'!P67 -> 33.4986 | I67: =G67-H67 -> 277.2402
A68: 40695 | B68: ='Anexo 3 Dif Sal'!H25 -> 9.1906448 | C68: ='Anexo 4 HE'!U68 -> 530.87953 | D68: =SUM(B68:C68) -> 540.07018 | G68: =D68 -> 540.07018 | H68: ='Anexo 6 INSS'!N68+'Anexo 6 INSS'!P68 -> 116.28422 | I68: =G68-H68 -> 423.78596
A69: 40725 | B69: ='Anexo 3 Dif Sal'!H26 -> 106.45825 | C69: ='Anexo 4 HE'!U69 -> 514.65683 | D69: =SUM(B69:C69) -> 621.11508 | G69: =D69 -> 621.11508 | H69: ='Anexo 6 INSS'!N69+'Anexo 6 INSS'!P69 -> 113.83907 | I69: =G69-H69 -> 507.27601
A70: 40756 | B70: ='Anexo 3 Dif Sal'!H27 -> 106.2377 | C70: ='Anexo 4 HE'!U70 -> 513.47514 | D70: =SUM(B70:C70) -> 619.71283 | G70: =D70 -> 619.71283 | H70: ='Anexo 6 INSS'!N70+'Anexo 6 INSS'!P70 -> 115.50481 | I70: =G70-H70 -> 504.20802
A71: 40787 | B71: ='Anexo 3 Dif Sal'!H28 -> 106.13125 | C71: ='Anexo 4 HE'!U71 -> 495.92716 | D71: =SUM(B71:C71) -> 602.05841 | G71: =D71 -> 602.05841 | H71: ='Anexo 6 INSS'!N71+'Anexo 6 INSS'!P71 -> 60.384535 | I71: =G71-H71 -> 541.67387
A72: Férias + 1/3 | B72: 0 | C72: ='Anexo 4 HE'!U72 -> 0 | D72: =SUM(B72:C72) -> 0 | G72: =D72 -> 0 | H72: ='Anexo 6 INSS'!N72+'Anexo 6 INSS'!P72 -> 0.0004694 | I72: =G72-H72 -> -0.0004694
A73: 40817 | B73: ='Anexo 3 Dif Sal'!H29 -> 37.291683 | C73: 0 | D73: =SUM(B73:C73) -> 37.291683 | G73: =D73 -> 37.291683 | H73: ='Anexo 6 INSS'!N73+'Anexo 6 INSS'!P73 -> 3.8860427 | I73: =G73-H73 -> 33.405641
A74: 40848 | B74: ='Anexo 3 Dif Sal'!H30 -> 37.267646 | C74: ='Anexo 4 HE'!U74 -> 335.55399 | D74: =SUM(B74:C74) -> 372.82164 | G74: =D74 -> 372.82164 | H74: ='Anexo 6 INSS'!N74+'Anexo 6 INSS'!P74 -> 38.57604 | I74: =G74-H74 -> 334.2456
A75: 40878 | B75: ='Anexo 3 Dif Sal'!H31 -> 37.232759 | C75: ='Anexo 4 HE'!U75 -> 387.83249 | D75: =SUM(B75:C75) -> 425.06525 | G75: =D75 -> 425.06525 | H75: ='Anexo 6 INSS'!N75+'Anexo 6 INSS'!P75 -> 87.53176 | I75: =G75-H75 -> 337.53349
A76: 13º Salário 2011 (Média) | B76: 0 | C76: ='Anexo 4 HE'!U76 -> 400.36637 | D76: =SUM(B76:C76) -> 400.36637 | G76: =D76 -> 400.36637 | H76: ='Anexo 6 INSS'!N76+'Anexo 6 INSS'!P76 -> 41.113052 | I76: =G76-H76 -> 359.25332
A77: 40909 | B77: ='Anexo 3 Dif Sal'!H32 -> 37.200617 | C77: ='Anexo 4 HE'!U77 -> 454.83444 | D77: =SUM(B77:C77) -> 492.03506 | G77: =D77 -> 492.03506 | H77: ='Anexo 6 INSS'!N77+'Anexo 6 INSS'!P77 -> 50.277409 | I77: =G77-H77 -> 441.75765
A78: 40940 | B78: ='Anexo 3 Dif Sal'!H33 -> 37.200617 | C78: ='Anexo 4 HE'!U78 -> 528.3274 | D78: =SUM(B78:C78) -> 565.52802 | G78: =D78 -> 565.52802 | H78: ='Anexo 6 INSS'!N78+'Anexo 6 INSS'!P78 -> 104.46724 | I78: =G78-H78 -> 461.06077
A79: 40969 | B79: ='Anexo 3 Dif Sal'!H34 -> 37.16093 | C79: ='Anexo 4 HE'!U79 -> 338.43477 | D79: =SUM(B79:C79) -> 375.5957 | G79: =D79 -> 375.5957 | H79: ='Anexo 6 INSS'!N79+'Anexo 6 INSS'!P79 -> 37.912609 | I79: =G79-H79 -> 337.68309
A80: 41024 | B80: ='Anexo 3 Dif Sal'!H35 -> 30.960413 | C80: ='Anexo 4 HE'!U80 -> 563.86599 | D80: =SUM(B80:C80) -> 594.8264 | G80: =D80 -> 594.8264 | H80: ='Anexo 6 INSS'!N80+'Anexo 6 INSS'!P80 -> 72.912378 | I80: =G80-H80 -> 521.91402
A81: Total | I81: =SUM(I13:I80) -> 20998.095

Sheet Plan Aux IR
A1: PROCESSO:
A2: VARA:
A3: RECLAMANTE:
A4: RECLAMADA:
A7: PLANILHA AUXILIAR DO CÁLCULO DO IMPOSTO DE RENDA
A10: Base de Cálculo em R$ (de acordo com a IN 1.145 / 2011 (ano calendário 2013)) | B10: Base de Cálculo em R$ | D10: Base de Cálculo em R$ (recomposta) | G10: Alíquota (%) | H10: Parcela a Deduzir do Imposto (R$) (de acordo com a IN 1.145 / 2011 (ano calendário 2013)) | I10: Parcela a deduzir | J10: Parcela a deduzir (recomposta)
D11: nº de meses incluido os 13º sal. | E11: De | F11: Até | J11: nº de meses incluido os 13º sal. | K11: Valor
A12: Até (1.710,78 x NM) | B12: 0 | C12: 1710.78 | D12: 64 | E12: =B12*D12 -> 0 | F12: =C12*D12 -> 109489.92 | G12: - | H12: - | I12: 0 | J12: =D12 -> 64 | K12: =I12*J12 -> 0
A13: Acima de (1.710,78 x NM) até (2.563,91 x NM) | B13: =C12+0.01 -> 1710.79 | C13: 2563.91 | D13: =D12 -> 64 | E13: =B13*D13 -> 109490.56 | F13: =C13*D13 -> 164090.24 | G13: 0.075 | H13: 128,3085 x NM | I13: 128.3085 | J13: =J12 -> 64 | K13: =I13*J13 -> 8211.744
A14: Acima de (2.563,91 x NM) até (3.418,59 x NM) | B14: =C13+0.01 -> 2563.92 | C14: 3418.59 | D14: =D13 -> 64 | E14: =B14*D14 -> 164090.88 | F14: =C14*D14 -> 218789.76 | G14: 0.15 | H14: 320,60175 x NM | I14: 320.60175 | J14: =J13 -> 64 | K14: =I14*J14 -> 20518.512
A15: Acima de (3.418,59 x NM) até (4.271,59 x NM) | B15: =C14+0.01 -> 3418.6 | C15: 4271.59 | D15: =D14 -> 64 | E15: =B15*D15 -> 218790.4 | F15: =C15*D15 -> 273381.76 | G15: 0.225 | H15: 576,996 x NM | I15: 576.996 | J15: =J14 -> 64 | K15: =I15*J15 -> 36927.744
A16: Acima de (4.271,59 x NM) | B16: =C15+0.01 -> 4271.6 | C16: acima | D16: =D15 -> 64 | E16: =B16*D16 -> 273382.4 | F16: acima | G16: 0.275 | H16: 790,5755 x NM | I16: 790.5755 | J16: =J15 -> 64 | K16: =I16*J16 -> 50596.832
A19: Cálculo do Imposto de Renda de acordo com a tabela recomposta acima
A20: Valor transferido do Anexo 7 - IRRF | G20: ='Anexo 7 IRRF'!I81 -> 20998.095
A21: Aliquota (%) | G21: 0
A22: Valor Bruto | G22: =G20*G21 -> 0
A23: Parcela a deduzir | G23: 0
A24: Valor a recolher na fonte a título de IR categoria RRA | G24: =G22-G23 -> 0

Sheet Anexo 8 Tabela TRT
A1: PROCESSO:
A2: VARA:
A3: RECLAMANTE:
A4: RECLAMADA:
A6: ANEXO 8
A8: PODER JUDICIÁRIO FEDERAL - JUSTIÇA DO TRABALHO
A10: TABELA ÚNICA PARA ATUALIZAÇÃO DE DÉBITOS TRABALHISTAS
A11: ATÉ 30 DE NOVEMBRO DE 2013 - PARA 1º DE DEZEMBRO DE 2013*
A12: *TR prefixada de 1º novembro/2013 a 1ºdezembro/2013 (Banco Central) = 0,02070%
B14: 1970 | C14: 1971 | D14: 1972 | E14: 1973 | F14: 1974 | G14: 1975 | H14: 1976 | I14: 1977 | J14: 1978 | K14: 1979 | L14: 1980
A15: JAN | B15: 0.48796219 | C15: 0.40915389 | D15: 0.33593328 | E15: 0.29163922 | F15: 0.25635667 | G15: 0.19354942 | H15: 0.15494015 | I15: 0.11248049 | J15: 0.08668491 | K15: 0.063213721 | L15: 0.042345523
A16: FEV | B16: 0.48796219 | C16: 0.40915389 | D16: 0.33593328 | E16: 0.29163922 | F16: 0.25635667 | G16: 0.19354942 | H16: 0.15494015 | I16: 0.11248049 | J16: 0.08668491 | K16: 0.063213721 | L16: 0.042345523
A17: MAR | B17: 0.48796219 | C17: 0.40915389 | D17: 0.33593328 | E17: 0.29163922 | F17: 0.25635667 | G17: 0.19354942 | H17: 0.15494015 | I17: 0.11248049 | J17: 0.08668491 | K17: 0.063213721 | L17: 0.042345523
A18: ABR | B18: 0.46263936 | C18: 0.39260131 | D18: 0.32390043 | E18: 0.28239092 | F18: 0.24683364 | G18: 0.18407772 | H18: 0.1452341 | I18: 0.1060248 | J18: 0.080882022 | K18: 0.058941498 | L18: 0.037790468
A19: MAI | B19: 0.46263936 | C19: 0.39260131 | D19: 0.32390043 | E19: 0.28239092 | F19: 0.24683364 | G19: 0.18407772 | H19: 0.1452341 | I19: 0.1060248 | J19: 0.080882022 | K19: 0.058941498 | L19: 0.037790468
A20: JUN | B20: 0.46263936 | C20: 0.39260131 | D20: 0.32390043 | E20: 0.28239092 | F20: 0.24683364 | G20: 0.18407772 | H20: 0.1452341 | I20: 0.1060248 | J20: 0.080882022 | K20: 0.058941498 | L20: 0.037790468
A21: JUL | B21: 0.44730927 | C21: 0.37519884 | D21: 0.30880912 | E21: 0.27265277 | F21: 0.23012294 | G21: 0.17322367 | H21: 0.13362286 | I21: 0.096624271 | J21: 0.074032913 | K21: 0.052957272 | L21: 0.034150988
A22: AGO | B22: 0.44730927 | C22: 0.37519884 | D22: 0.30880912 | E22: 0.27265277 | F22: 0.23012294 | G22: 0.17322367 | H22: 0.13362286 | I22: 0.096624271 | J22: 0.074032913 | K22: 0.052957272 | L22: 0.034150988
A23: SET | B23: 0.44730927 | C23: 0.37519884 | D23: 0.30880912 | E23: 0.27265277 | F23: 0.23012294 | G23: 0.17322367 | H23: 0.13362286 | I23: 0.096624271 | J23: 0.074032913 | K23: 0.052957272 | L23: 0.034150988
A24: OUT | B24: 0.43406911 | C24: 0.35258974 | D24: 0.29976101 | E24: 0.2653955 | F24: 0.20278432 | G24: 0.16435881 | H24: 0.12272582 | I24: 0.090947697 | J24: 0.068114003 | K24: 0.048175119 | L24: 0.031131974
A25: NOV | B25: 0.43406911 | C25: 0.35258974 | D25: 0.29976101 | E25: 0.2653955 | F25: 0.20278432 | G25: 0.16435881 | H25: 0.12272582 | I25: 0.090947697 | J25: 0.068114003 | K25: 0.048175119 | L25: 0.031131974
A26: DEZ | B26: 0.43406911 | C26: 0.35258974 | D26: 0.29976101 | E26: 0.2653955 | F26: 0.20278432 | G26: 0.16435881 | H26: 0.12272582 | I26: 0.090947697 | J26: 0.068114003 | K26: 0.048175119 | L26: 0.031131974
B27: 1981 | C27: 1982 | D27: 1983 | E27: 1984 | F27: 1985 | G27: 1986 | H27: 1987 | I27: 1988 | J27: 1989 | K27: 1990 | L27: 1991
A28: JAN | B28: 0.02797248 | C28: 0.014207953 | D28: 0.0070965912 | E28: 0.0027375719 | F28: 0.0008455144 | G28: 0.0002580606 | H28: 0.15895206 | I28: 0.034611663 | J28: 0.0033485837 | K28: 0.18731993 | L28: 0.014899996
A29: FEV | B29: 0.02797248 | C29: 0.014207953 | D29: 0.0070965912 | E29: 0.0027375719 | F29: 0.0008455144 | G29: 0.00022202541 | H29: 0.13607744 | I29: 0.029707032 | J29: 2.7366655 | K29: 0.11999227 | L29: 0.012394579
A30: MAR | B30: 0.02797248 | C30: 0.014207953 | D30: 0.0070965912 | E30: 0.0027375719 | F30: 0.0008455144 | G30: 0.19414621 | H30: 0.11375811 | I30: 0.025183988 | J30: 2.3123494 | K30: 0.069448009 | L30: 0.011583719
A31: ABR | B31: 0.023531998 | C31: 0.012273363 | D31: 0.0057564276 | E31: 0.0020183229 | F31: 0.00060461232 | G31: 0.19436 | H31: 0.09934338 | I31: 0.021708463 | J31: 1.9300137 | K31: 0.037677957 | L31: 0.010676239
A32: MAI | B32: 0.023531998 | C32: 0.012273363 | D32: 0.0057564276 | E32: 0.0020183229 | F32: 0.00060461232 | G32: 0.19285573 | H32: 0.082129117 | I32: 0.018199583 | J32: 1.7393779 | K32: 0.037677957 | L32: 0.0098010086
A33: JUN | B33: 0.023531998 | C33: 0.012273363 | D33: 0.0057564276 | E33: 0.0020183229 | F33: 0.00060461232 | G33: 0.19019302 | H33: 0.066533633 | I33: 0.015452185 | J33: 1.5821156 | K33: 0.035754371 | L33: 0.008992576
A34: JUL | B34: 0.01975792 | C34: 0.010452164 | D34: 0.0045361146 | E34: 0.0015585199 | F34: 0.00045001222 | G34: 0.18780786 | H34: 0.05637488 | I34: 0.012927453 | J34: 1.2674162 | K34: 0.032619625 | L34: 0.008219905
A35: AGO | B35: 0.01975792 | C35: 0.010452164 | D35: 0.0045361146 | E35: 0.0015585199 | F35: 0.00045001222 | G35: 0.18559923 | H35: 0.054706337 | I35: 0.010422003 | J35: 0.98432445 | K35: 0.029442752 | L35: 0.0074692458
A36: SET | B36: 0.01975792 | C36: 0.010452164 | D36: 0.0045361146 | E36: 0.0015585199 | F36: 0.00045001222 | G36: 0.18253268 | H36: 0.051435067 | I36: 0.008637497 | J36: 0.76103638 | K36: 0.026625748 | L36: 0.006671948
A37: OUT | B37: 0.016667662 | C37: 0.0086125711 | D37: 0.0035027864 | E37: 0.0011561638 | F37: 0.0003543235 | G37: 0.17944621 | H37: 0.048670578 | I37: 0.0069651615 | J37: 0.55979137 | K37: 0.023593929 | L37: 0.0057132625
A38: NOV | B38: 0.016667662 | C38: 0.0086125711 | D38: 0.0035027864 | E38: 0.0011561638 | F38: 0.0003543235 | G38: 0.17611759 | H38: 0.044578291 | I38: 0.0054736047 | J38: 0.406766 | K38: 0.020749212 | L38: 0.004770195
A39: DEZ | B39: 0.016667662 | C39: 0.0086125711 | D39: 0.0035027864 | E39: 0.0011561638 | F39: 0.0003543235 | G39: 0.17050788 | H39: 0.039505752 | I39: 0.0043126411 | J39: 0.28762976 | K39: 0.017789105 | L39: 0.0036547617
B40: 1992 | C40: 1993 | D40: 1994 | E40: 1995 | F40: 1996 | G40: 1997 | H40: 1998 | I40: 1999 | J40: 2000 | K40: 2001 | L40: 2002
A41: JAN | B41: 0.0028459443 | C41: 0.00022654762 | D41: 0.0087988569 | E41: 2.3020082 | F41: 1.7489455 | G41: 1.5959703 | H41: 1.4537236 | I41: 1.3486145 | J41: 1.2755321 | K41: 1.249342 | L41: 1.2214292
A42: FEV | B42: 0.0022680462 | C42: 0.0001787217 | D42: 0.0062209113 | E42: 2.2546316 | F42: 1.7273092 | G42: 1.584184 | H42: 1.4372541 | I42: 1.3416874 | J42: 1.2727968 | K42: 1.247634 | L42: 1.2182727
A43: MAR | B43: 0.0018056255 | C43: 0.00014139375 | D43: 0.004447956 | E43: 2.2136112 | F43: 1.7108424 | G43: 1.5737719 | H43: 1.430871 | I43: 1.3306457 | J43: 1.2698406 | K43: 1.247175 | L43: 1.2168477
A44: ABR | B44: 0.0014529858 | C44: 0.00011238673 | D44: 0.0031356757 | E44: 2.163847 | F44: 1.6970302 | G44: 1.5638943 | H44: 1.418115 | I44: 1.315369 | J44: 1.267 | K44: 1.2450286 | L44: 1.2147123
A45: MAI | B45: 0.0012000213 | C45: 8.7651483e-05 | D45: 0.0021481645 | E45: 2.0913463 | F45: 1.6859083 | G45: 1.5542409 | H45: 1.411453 | I45: 1.3074043 | J45: 1.2653538 | K45: 1.2431067 | L45: 1.2118559
A46: JUN | B46: 0.0010016036 | C46: 6.8115856e-05 | D46: 0.0014669247 | E46: 2.0255739 | F46: 1.6760398 | G46: 1.5444276 | H46: 1.4050698 | I46: 1.2999155 | J46: 1.2622084 | K46: 1.2408397 | L46: 1.2093139
A47: JUL | B47: 0.00082742969 | C47: 5.2364588e-05 | D47: 2.7465758 | E47: 1.9687499 | F47: 1.6658796 | G47: 1.5344003 | H47: 1.3982004 | I47: 1.2958878 | J47: 1.259513 | K47: 1.2390332 | L47: 1.2074038
A48: AGO | B48: 0.0006689544 | C48: 0.040166133 | D48: 2.6151351 | E48: 1.911584 | F48: 1.6561892 | G48: 1.52437 | H48: 1.3905482 | I48: 1.2920981 | J48: 1.2575675 | K48: 1.2360161 | L48: 1.2042055
A49: SET | B49: 0.00054289433 | C49: 0.030123094 | D49: 2.5605644 | E49: 1.8630605 | F49: 1.6458614 | G49: 1.5148717 | H49: 1.3853545 | I49: 1.2883041 | J49: 1.2550261 | K49: 1.2317837 | L49: 1.2012252
A50: OUT | B50: 0.00043299915 | C50: 0.022376388 | D50: 2.4995967 | E50: 1.8276176 | F50: 1.6350375 | G50: 1.5051275 | H50: 1.3791319 | I50: 1.2848158 | J50: 1.2537248 | K50: 1.2297828 | L50: 1.1988814
A51: NOV | B51: 0.00034620544 | C51: 0.016389356 | D51: 2.4373207 | E51: 1.7978806 | F51: 1.6229965 | G51: 1.4953287 | H51: 1.3669767 | I51: 1.2819123 | J51: 1.252077 | K51: 1.2262109 | L51: 1.1955721
A52: DEZ | B52: 0.00028080578 | C52: 0.012036836 | D52: 2.3681472 | E52: 1.7723814 | F52: 1.6098824 | G52: 1.4727456 | H52: 1.3586401 | I52: 1.2793561 | J52: 1.2505801 | K52: 1.2238513 | L52: 1.1924193
B53: 2003 | C53: 2004 | D53: 2005 | E53: 2006 | F53: 2007 | G53: 2008 | H53: 2009 | I53: 2010 | J53: 2011 | K53: 2012 | L53: 2013
A54: JAN | B54: 1.1881313 | C54: 1.1353529 | D54: 1.1150762 | E54: 1.0843508 | F54: 1.0626959 | G54: 1.0475555 | H54: 1.0307051 | I54: 1.0234487 | J54: 1.0164479 | K54: 1.0043167 | L54: 1.0014155
A55: FEV | B55: 1.1823638 | C55: 1.1339015 | D55: 1.1129838 | E55: 1.0818345 | F55: 1.0603747 | G55: 1.0464985 | H55: 1.028812 | I55: 1.0234487 | J55: 1.0157217 | K55: 1.0034497 | L55: 1.0014155
A56: MAR | B56: 1.1775171 | C56: 1.1333824 | D56: 1.1119141 | E56: 1.0810507 | F56: 1.0596108 | G56: 1.0462443 | H56: 1.0283483 | I56: 1.0234487 | J56: 1.0151897 | K56: 1.0034497 | L56: 1.0014155
A57: ABR | B57: 1.1730805 | C57: 1.1313709 | D57: 1.1089919 | E57: 1.0788143 | F57: 1.0576267 | G57: 1.0458165 | H57: 1.0268716 | I57: 1.0226388 | J57: 1.0139608 | K57: 1.0023792 | L57: 1.0014155
A58: MAI | B58: 1.1681928 | C58: 1.1303829 | D58: 1.106775 | E58: 1.0778927 | F58: 1.0562831 | G58: 1.0448187 | H58: 1.0264056 | I58: 1.0226388 | J58: 1.0135868 | K58: 1.0021517 | L58: 1.0014155
A59: JUN | B59: 1.1627858 | C59: 1.128638 | D59: 1.1039853 | E59: 1.0758615 | F59: 1.054502 | G59: 1.0440503 | H59: 1.025945 | I59: 1.0221175 | J59: 1.011998 | K59: 1.0016829 | L59: 1.0014155
A60: JUL | B60: 1.1579618 | C60: 1.126654 | D60: 1.1006909 | E60: 1.0737816 | F60: 1.053497 | G60: 1.0428552 | H60: 1.0252724 | I60: 1.0215159 | J60: 1.0108719 | K60: 1.0016829 | L60: 1.0014155
A61: AGO | B61: 1.1516679 | C61: 1.1244591 | D61: 1.0978639 | E61: 1.0719047 | F61: 1.0519517 | G61: 1.040863 | H61: 1.024196 | I61: 1.0203415 | J61: 1.009631 | K61: 1.0015387 | L61: 1.0012063
A62: SET | B62: 1.1470362 | C62: 1.122209 | D62: 1.0940719 | E62: 1.0692999 | F62: 1.0504118 | G62: 1.0392272 | H62: 1.0239942 | I62: 1.0194148 | J62: 1.0075394 | K62: 1.0014155 | L62: 1.0012063
A63: OUT | B63: 1.1431905 | C63: 1.1202732 | D63: 1.0911944 | E63: 1.0676759 | F63: 1.0500421 | G63: 1.037184 | H63: 1.0239942 | I63: 1.0186997 | J63: 1.0065298 | K63: 1.0014155 | L63: 1.0011272
A64: NOV | B64: 1.1395292 | C64: 1.1190333 | D64: 1.0889077 | E64: 1.0656778 | F64: 1.0488444 | G64: 1.0345913 | H64: 1.0239942 | I64: 1.0182191 | J64: 1.0059062 | K64: 1.0014155 | L64: 1.000207
A65: DEZ | B65: 1.137509 | C65: 1.1177524 | D65: 1.0868112 | E65: 1.0643133 | F65: 1.0482259 | G65: 1.03292 | H65: 1.0239942 | I65: 1.0178771 | J65: 1.0052578 | K65: 1.0014155 | L65: 1

Sheet Outros
A2: Data base da categoria | B2: Valor de cada Multa Normativa | D2: Quant. | E2: Valor devido | F2: Correção Monetária Tabela TRT para 30/11/2013 | J2: Data do arbitramento | K2: Valor Arbitrado | L2: Correção Monetária Tabela TRT para 30/11/2013
B3: Salário Mensal recomposto | C3: 50% do salário mensal | F3: Indices (Súmula 381) | G3: Valor Atualizado | L3: Indices (Súmula 381) | M3: Valor Atualizado
A4: 40725 | B4: ='Anexo 3 Dif Sal'!E26 -> 1472.7927 | C4: =B4/2 -> 736.39636 | D4: 3 | E4: =C4*D4 -> 2209.1891 | F4: ='Anexo 8 Tabela TRT'!J61 -> 1.009631 | G4: =E4*F4 -> 2230.4658 | J4: 41365 | K4: 10000 | L4: ='Anexo 8 Tabela TRT'!L58 -> 1.0014155 | M4: =K4*L4 -> 10014.155
A5: Total | G5: =SUM(G4:G4) -> 2230.4658 | J5: Total | M5: =M4 -> 10014.155
A9: Não imprimir - Foram utilizados os parâmetros determinados na sentença.
