Workbook

Sheet Início
A1: MAPA DE ANÁLISE FINANCEIRA - INÍCIO

Sheet Direitos
A1: MAPA DE ANÁLISE FINANCEIRA - DIREITOS
C3: DIREITOS: | F3: =SUM(F7:F40) -> 0
B4: NOME | C4: PORCENTAGEM | D4: PRAZO | E4: VALOR
E5: FINANÇA DISPONÍVEL | H5: 30 DIAS | I5: =D6 -> 0 | J5: =E6 -> 0 | L5: =B6 -> BANCO | M5: =C6 -> #DIV/0!
B6: BANCO | C6: =E6/F8 -> #DIV/0! | H6: 60 DIAS | I6: =D7 -> 0 | J6: =E7 -> 0 | L6: =B7 -> CAIXA | M6: =C7 -> #DIV/0!
B7: CAIXA | C7: =E7/F8 -> #DIV/0! | H7: 90 DIAS | I7: =D8 -> 0 | J7: =E8 -> 0 | L7: =B8 -> 0 | M7: =C8 -> 0
F8: =E7+E6 -> 0 | H8: MAIS DE 90 DIAS | I8: =D9 -> 0 | J8: =E9 -> 0 | L8: =B9 -> 0 | M8: =C9 -> 0
I9: =D11 -> 0 | J9: =E11 -> 0 | L9: =B10 -> 0 | M9: =C10 -> 0
E10: APLICAÇÕES | I10: =D12 -> 0 | J10: =E12 -> 0 | L10: =B11 -> APLICAÇÃO 1 | M10: =C11 -> #DIV/0!
B11: APLICAÇÃO 1 | C11: =E11/F15 -> #DIV/0! | I11: =D13 -> 0 | J11: =E13 -> 0 | L11: =B12 -> APLICAÇÃO 2 | M11: =C12 -> #DIV/0!
B12: APLICAÇÃO 2 | C12: =E12/F15 -> #DIV/0! | I12: =D14 -> 0 | J12: =E14 -> 0 | L12: =B13 -> APLICAÇÃO 3 | M12: =C13 -> #DIV/0!
B13: APLICAÇÃO 3 | C13: =E13/F15 -> #DIV/0! | I13: =D15 -> 0 | J13: =E15 -> 0 | L13: =B14 -> APLICAÇÃO 4 | M13: =C14 -> #DIV/0!
B14: APLICAÇÃO 4 | C14: =E14/F15 -> #DIV/0! | I14: =D16 -> 0 | J14: =E16 -> 0 | L14: =B15 -> 0 | M14: =C15 -> 0
F15: =SUM(E11:E14) -> 0 | I15: =D18 -> 0 | J15: =E18 -> 0 | L15: =B16 -> 0 | M15: =C16 -> 0
I16: =D19 -> 0 | J16: =E19 -> 0 | L16: =B17 -> 0 | M16: =C17 -> 0
E17: FATURAS A RECEBER | I17: =D20 -> 0 | J17: =E20 -> 0 | L17: =B18 -> FATURA 1 | M17: =C18 -> #DIV/0!
B18: FATURA 1 | C18: =E18/F24 -> #DIV/0! | I18: =D21 -> 0 | J18: =E21 -> 0 | L18: =B19 -> FATURA 2 | M18: =C19 -> #DIV/0!
B19: FATURA 2 | C19: =E19/F24 -> #DIV/0! | I19: =D22 -> 0 | J19: =E22 -> 0 | L19: =B20 -> FATURA 3 | M19: =C20 -> #DIV/0!
B20: FATURA 3 | C20: =E20/F24 -> #DIV/0! | I20: =D23 -> 0 | J20: =E23 -> 0 | L20: =B21 -> FATURA 4 | M20: =C21 -> #DIV/0!
B21: FATURA 4 | C21: =E21/F24 -> #DIV/0! | I21: =D24 -> 0 | J21: =E24 -> 0 | L21: =B22 -> FATURA 5 | M21: =C22 -> #DIV/0!
B22: FATURA 5 | C22: =E22/F24 -> #DIV/0! | I22: =D25 -> 0 | J22: =E25 -> 0 | L22: =B23 -> FATURA 6 | M22: =C23 -> #DIV/0!
B23: FATURA 6 | C23: =E23/F24 -> #DIV/0! | I23: =D27 -> 0 | J23: =E27 -> 0 | L23: =B24 -> 0 | M23: =C24 -> 0
F24: =SUM(E18:E23) -> 0 | I24: =D28 -> 0 | J24: =E28 -> 0 | L24: =B25 -> 0 | M24: =C25 -> 0
I25: =D29 -> 0 | J25: =E29 -> 0 | L25: =B26 -> 0 | M25: =C26 -> 0
E26: ESTOQUE | I26: =D30 -> 0 | J26: =E30 -> 0 | L26: =B27 -> MATÉRIA 1 | M26: =C27 -> #DIV/0!
B27: MATÉRIA 1 | C27: =E27/F31 -> #DIV/0! | I27: =D31 -> 0 | J27: =E31 -> 0 | L27: =B28 -> MATÉRIA 2 | M27: =C28 -> #DIV/0!
B28: MATÉRIA 2 | C28: =E28/F31 -> #DIV/0! | I28: =D32 -> 0 | J28: =E32 -> 0 | L28: =B29 -> PRODUTO 1 | M28: =C29 -> #DIV/0!
B29: PRODUTO 1 | C29: =E29/F31 -> #DIV/0! | I29: =D34 -> 0 | J29: =E34 -> 0 | L29: =B30 -> PRODUTO 2 | M29: =C30 -> #DIV/0!
B30: PRODUTO 2 | C30: =E30/F31 -> #DIV/0! | I30: =D35 -> 0 | J30: =E35 -> 0 | L30: =B31 -> 0 | M30: =C31 -> 0
F31: =SUM(E27:E30) -> 0 | I31: =D36 -> 0 | J31: =E36 -> 0 | L31: =B32 -> 0 | M31: =C32 -> 0
I32: =D37 -> 0 | J32: =E37 -> 0 | L32: =B33 -> 0 | M32: =C33 -> 0
E33: BENS IMOBILIZADOS | I33: =D38 -> 0 | J33: =E38 -> 0 | L33: =B34 -> EQUIPAMENTO 1 | M33: =C34 -> #DIV/0!
B34: EQUIPAMENTO 1 | C34: =E34/F40 -> #DIV/0! | I34: =D39 -> 0 | J34: =E39 -> 0 | L34: =B35 -> EQUIPAMENTO 2 | M34: =C35 -> #DIV/0!
B35: EQUIPAMENTO 2 | C35: =E35/F40 -> #DIV/0! | L35: =B36 -> EQUIPAMENTO 3 | M35: =C36 -> #DIV/0!
B36: EQUIPAMENTO 3 | C36: =E36/F40 -> #DIV/0! | L36: =B37 -> EQUIPAMENTO 4 | M36: =C37 -> #DIV/0!
B37: EQUIPAMENTO 4 | C37: =E37/F40 -> #DIV/0! | L37: =B38 -> EQUIPAMENTO 5 | M37: =C38 -> #DIV/0!
B38: EQUIPAMENTO 5 | C38: =E38/F40 -> #DIV/0! | L38: =B39 -> EQUIPAMENTO 4 | M38: =C39 -> #DIV/0!
B39: EQUIPAMENTO 4 | C39: =E39/F40 -> #DIV/0! | L39: =B40 -> 0 | M39: =C40 -> 0
F40: =SUM(E34:E39) -> 0

Sheet Obrigações
A1: MAPA DE ANÁLISE FINANCEIRA - OBRIGAÇÕES
C3: OBRIGAÇÕES | F3: =SUM(F8:F32) -> 0 | H3: 30 DIAS
H4: 60 DIAS
B5: EMPRÉSTIMOS | H5: 90 DIAS
B6: EMPRÉSTIMO 1 | C6: =E6/F9 -> #DIV/0! | H6: MAIS DE 90 DIAS | I6: =D6 -> 0 | J6: =E6 -> 0 | L6: =B6 -> EMPRÉSTIMO 1 | M6: =C6 -> #DIV/0!
B7: EMPRESTIMO 2 | C7: =E7/F9 -> #DIV/0! | I7: =D7 -> 0 | J7: =E7 -> 0 | L7: =B7 -> EMPRESTIMO 2 | M7: =C7 -> #DIV/0!
B8: EMPRESTIMO 3 | C8: =E8/F9 -> #DIV/0! | I8: =D8 -> 0 | J8: =E8 -> 0 | L8: =B8 -> EMPRESTIMO 3 | M8: =C8 -> #DIV/0!
F9: =SUM(E6:E8) -> 0 | I9: =D12 -> 0 | J9: =E12 -> 0 | L9: =B9 -> 0 | M9: =C9 -> 0
I10: =D13 -> 0 | J10: =E13 -> 0 | L10: =B10 -> 0 | M10: =C10 -> 0
B11: SALÁRIOS E ENCARGOS | I11: =D14 -> 0 | J11: =E14 -> 0 | L11: =B11 -> SALÁRIOS E ENCARGOS | M11: =C11 -> 0
B12: SALÁRIO 1 | C12: =E12/F16 -> #DIV/0! | I12: =D15 -> 0 | J12: =E15 -> 0 | L12: =B12 -> SALÁRIO 1 | M12: =C12 -> #DIV/0!
B13: SALÁRIO 2 | C13: =E13/F16 -> #DIV/0! | I13: =D19 -> 0 | J13: =E19 -> 0 | L13: =B13 -> SALÁRIO 2 | M13: =C13 -> #DIV/0!
B14: SALÁRIO 3 | C14: =E14/F16 -> #DIV/0! | I14: =D20 -> 0 | J14: =E20 -> 0 | L14: =B14 -> SALÁRIO 3 | M14: =C14 -> #DIV/0!
B15: SALÁRIO 4 | C15: =E15/F16 -> #DIV/0! | I15: =D21 -> 0 | J15: =E21 -> 0 | L15: =B15 -> SALÁRIO 4 | M15: =C15 -> #DIV/0!
F16: =SUM(E12:E15) -> 0 | I16: =D22 -> 0 | J16: =E22 -> 0 | L16: =B16 -> 0 | M16: =C16 -> 0
I17: =D23 -> 0 | J17: =E23 -> 0 | L17: =B17 -> 0 | M17: =C17 -> 0
B18: FATURAS A PAGAR | I18: =D24 -> 0 | J18: =E24 -> 0 | L18: =B18 -> FATURAS A PAGAR | M18: =C18 -> 0
B19: FATURA 1 | C19: =E19/F25 -> #DIV/0! | I19: =D25 -> 0 | J19: =E25 -> 0 | L19: =B19 -> FATURA 1 | M19: =C19 -> #DIV/0!
B20: FATURA 2 | C20: =E20/F25 -> #DIV/0! | I20: =D26 -> 0 | J20: =E26 -> 0 | L20: =B20 -> FATURA 2 | M20: =C20 -> #DIV/0!
B21: FATURA 3 | C21: =E21/F25 -> #DIV/0! | I21: =D28 -> 0 | J21: =E28 -> 0 | L21: =B21 -> FATURA 3 | M21: =C21 -> #DIV/0!
B22: FATURA 4 | C22: =E22/F25 -> #DIV/0! | I22: =D29 -> 0 | J22: =E29 -> 0 | L22: =B22 -> FATURA 4 | M22: =C22 -> #DIV/0!
B23: FATURA 5 | C23: =E23/F25 -> #DIV/0! | I23: =D30 -> 0 | J23: =E30 -> 0 | L23: =B23 -> FATURA 5 | M23: =C23 -> #DIV/0!
B24: FATURA 6 | C24: =E24/F25 -> #DIV/0! | L24: =B24 -> FATURA 6 | M24: =C24 -> #DIV/0!
F25: =SUM(E19:E24) -> 0 | L25: =B25 -> 0 | M25: =C25 -> 0
L26: =B26 -> 0 | M26: =C26 -> 0
B27: IMPOSTOS | L27: =B27 -> IMPOSTOS | M27: =C27 -> 0
B28: IMPOSTOS 1 | C28: =E28/F31 -> #DIV/0! | L28: =B28 -> IMPOSTOS 1 | M28: =C28 -> #DIV/0!
B29: IMPOSTOS 2 | C29: =E29/F31 -> #DIV/0! | L29: =B29 -> IMPOSTOS 2 | M29: =C29 -> #DIV/0!
B30: IMPOSTOS 3 | C30: =E30/F31 -> #DIV/0! | L30: =B30 -> IMPOSTOS 3 | M30: =C30 -> #DIV/0!
F31: =SUM(E28:E30) -> 0 | L31: =B31 -> 0 | M31: =C31 -> 0
L32: =B32 -> 0 | M32: =C32 -> 0

Sheet Relatório
A1: MAPA DE ANÁLISE FINANCEIRA - RELATÓRIO
C3: ANÁLISE FINANCEIRA - PREVISÃO DE CAIXA
C5: Previsão de Entradas | D5: Previsão de Saídas | E5: Previsão de Saldo
B6: 30 DIAS | C6: =SUMIF(Direitos!$I$5:$J$30,Relatório!$B6,Direitos!$J$5:$J$34) -> 0 | D6: =SUMIF(Obrigações!$I$6:$J$23,Relatório!$B6,Obrigações!$J$6:$J$23) -> 0 | E6: =C6-D6 -> 0
B7: 60 DIAS | C7: =SUMIF(Direitos!$I$5:$J$30,Relatório!$B7,Direitos!$J$5:$J$34) -> 0 | D7: =SUMIF(Obrigações!$I$6:$J$23,Relatório!$B7,Obrigações!$J$6:$J$23) -> 0 | E7: =C7-D7 -> 0
B8: 90 DIAS | C8: =SUMIF(Direitos!$I$5:$J$30,Relatório!$B8,Direitos!$J$5:$J$34) -> 0 | D8: =SUMIF(Obrigações!$I$6:$J$23,Relatório!$B8,Obrigações!$J$6:$J$23) -> 0 | E8: =C8-D8 -> 0
B9: MAIS DE 90 DIAS | C9: =SUMIF(Direitos!$I$5:$J$30,Relatório!$B9,Direitos!$J$5:$J$34) -> 0 | D9: =SUMIF(Obrigações!$I$6:$J$23,Relatório!$B9,Obrigações!$J$6:$J$23) -> 0 | E9: =C9-D9 -> 0
B10: Total | C10: =SUM(C6:C9) -> 0 | D10: =SUM(D6:D9) -> 0 | E10: =C10-D10 -> 0
B12: ANÁLISE FINANCEIRA - PREVISÃO DE CAIXA | C12: BALANÇO PATRIMONIAL | D12: BALANÇO PATRIMONIAL
D14: ATIVO | E14: PASSIVO
C15: CIRCULANTE | D15: =SUM(C6:C8) -> 0 | E15: =SUM(D6:D8) -> 0
C16: NÃO CIRCULANTE | D16: =C9 -> 0 | E16: =D9 -> 0
B18: ANÁLISE FINANCEIRA - PREVISÃO DE CAIXA | E18: INDICADORES
E20: GRAU
D21: ENDIVIDAMENTO | E21: =SUM(D6:D8)/(C10) -> #DIV/0!
D22: LIQUIDEZ | E22: =C10/D10 -> #DIV/0!
D23: CAPITAL DE GIRO (em 30 dias) | E23: =C6-D6 -> 0

Sheet Panorama
A1: MAPA DE ANÁLISE FINANCEIRA - PANORAMA
B3: DIREITOS
B20: OBRIGAÇÕES
