Workbook

Sheet Início
A1: NECESSIDADE DE CAPITAL DE GIRO - INÍCIO

Sheet Análise
A1: NECESSIDADE DE CAPITAL DE GIRO - ANÁLISE
C4: NECESSIDADE DE CAPITAL DE GIRO | E4: =(E8+F45-K45) -> 0 | F4: =IF(E4<0,"A empresa deve analisar fontes para levantar fundos e financiar suas operações de curto prazo, sendo que existe uma necessidade de Capital de Giro.","A empresa não necessita de Capital de Giro, pois ela consegue sanar as obrigações de curto prazo, dados os valores inseridos. Caso isso se repita rotineiramente, uma alternativa a manter o dinheiro em caixa, seria investir esse valor em outras fontes") -> A empresa não necessita de Capital de Giro, pois ela consegue sanar as obrigações de curto prazo, dados os valores inseridos. Caso isso se repita rotineiramente, uma alternativa a manter o dinheiro em caixa, seria investir esse valor em outras fontes
C8: SALDO DISPONÍVEL:
C11: FATURAS A RECEBER | H11: FATURAS A PAGAR
C12: NOME DA FATURA | D12: Nº PARCELAS | E12: INÍCIO DAS PARCELAS | F12: VALOR TOTAL | H12: NOME DA FATURA | I12: Nº PARCELAS | J12: INÍCIO DAS PARCELAS | K12: VALOR TOTAL
G13: =F13/$F$45 -> #DIV/0! | L13: =K13/$K$45 -> #DIV/0!
G14: =F14/$F$45 -> #DIV/0! | L14: =K14/$K$45 -> #DIV/0!
G15: =F15/$F$45 -> #DIV/0! | L15: =K15/$K$45 -> #DIV/0!
G16: =F16/$F$45 -> #DIV/0! | L16: =K16/$K$45 -> #DIV/0!
G17: =F17/$F$45 -> #DIV/0! | L17: =K17/$K$45 -> #DIV/0!
G18: =F18/$F$45 -> #DIV/0! | L18: =K18/$K$45 -> #DIV/0!
G19: =F19/$F$45 -> #DIV/0! | L19: =K19/$K$45 -> #DIV/0!
G20: =F20/$F$45 -> #DIV/0! | L20: =K20/$K$45 -> #DIV/0!
G21: =F21/$F$45 -> #DIV/0! | L21: =K21/$K$45 -> #DIV/0!
G22: =F22/$F$45 -> #DIV/0! | L22: =K22/$K$45 -> #DIV/0!
G23: =F23/$F$45 -> #DIV/0! | L23: =K23/$K$45 -> #DIV/0!
G24: =F24/$F$45 -> #DIV/0! | L24: =K24/$K$45 -> #DIV/0!
... G44: =F44/$F$45 -> #DIV/0! | L44: =K44/$K$45 -> #DIV/0!
E45: TOTAL: | F45: =SUM(F13:F44) -> 0 | J45: TOTAL: | K45: =SUM(K13:K44) -> 0

Sheet Panorama
A1: NECESSIDADE DE CAPITAL DE GIRO - PANORAMA
F5: Auxiliar | G5: Valores
E6: =Análise!H11 -> FATURAS A PAGAR | F6: 0 | G6: =Análise!K45 -> 0
E7: =Análise!C11 -> FATURAS A RECEBER | F7: =F8+G8 -> 0 | G7: =Análise!F45 -> 0
E8: =Análise!C8 -> SALDO DISPONÍVEL: | F8: =F9+G9 -> 0 | G8: =Análise!E8 -> 0
E9: =Análise!C4 -> NECESSIDADE DE CAPITAL DE GIRO | F9: 0 | G9: =IF((Análise!E4)<0,ABS(Análise!E4),0) -> 0
