Workbook

Sheet INSTRUÇOES
Q26: =HYPERLINK("mailto:contato@softensistemas.com.br","contato@softensistemas.com.br") -> contato@softensistemas.com.br
Q27: =HYPERLINK("http://www.softensistemas.com.br/","www.softensistemas.com.br") -> www.softensistemas.com.br

Sheet CALCULO PERC. CUSTO INDIRETO
A1: DESPESAS MENSAIS FIXAS | G1: RECEITAS MENSAIS
A5: CUSTO FIXO INDIRETO | B5: MÊS 1 | C5: MÊS 2 | D5: MÊS 3 | E5: MEDIA | G5: Faturamento Médio | H5: MÊS 1 | I5: MÊS 2 | J5: MÊS 3 | K5: MEDIA | L5: TAXA MEDIA CARTAO
A6: Aluguel | B6: 1000 | C6: 1000 | D6: 1000 | E6: =AVERAGE(B6:D6) -> 1000 | G6: Dinheiro | H6: 8000 | I6: 2000 | J6: 5000 | K6: =AVERAGE(H6:J6) -> 5000
A7: Água | B7: 50 | C7: 65 | D7: 50 | E7: =AVERAGE(B7:D7) -> 55 | G7: Cartão Debito | H7: 1000 | I7: 6000 | J7: 10000 | K7: =AVERAGE(H7:J7) -> 5666.6667 | L7: =H12*K7 -> 153
A8: Energia | B8: 180 | C8: 220 | D8: 250 | E8: =AVERAGE(B8:D8) -> 216.66667 | G8: Cart. Credito | H8: 6000 | I8: 6000 | J8: 3000 | K8: =AVERAGE(H8:J8) -> 5000 | L8: =H13*K8 -> 158.85
A9: Internet | B9: 100 | C9: 100 | D9: 100 | E9: =AVERAGE(B9:D9) -> 100 | G9: Outras Receitas | H9: 0 | I9: 0 | J9: 0 | K9: =AVERAGE(H9:J9) -> 0
A10: Fornecedores a Pagar | B10: 5000 | C10: 2500 | D10: 2800 | E10: =AVERAGE(B10:D10) -> 3433.3333 | G10: Total Receitas Bruta | H10: =SUM(H6:H9) -> 15000 | I10: =SUM(I6:I9) -> 14000 | J10: =SUM(J6:J9) -> 18000 | K10: =AVERAGE(H10:J10) -> 15666.667 | L10: =SUM(L7:L8) -> 311.85
A11: Financiamento | B11: 100 | C11: 100 | D11: 100 | E11: =AVERAGE(B11:D11) -> 100
A12: Salário + Encargos (Roberto) | B12: 1600 | C12: 1600 | D12: 1600 | E12: =AVERAGE(B12:D12) -> 1600 | G12: TAXA C. DÉBITO | H12: 0.027 | I12: % TAXA APROX
A13: Salário + Encargos (Vanessa) | B13: 1800 | C13: 1800 | D13: 1800 | E13: =AVERAGE(B13:D13) -> 1800 | G13: TAXA C. CRÉDITO | H13: 0.03177 | I13: =L10/(K7+K8) -> 0.029235937
B14: 0 | C14: 0 | D14: 0 | E14: =AVERAGE(B14:D14) -> 0
B15: 0 | C15: 0 | D15: 0 | E15: =AVERAGE(B15:D15) -> 0
B16: 0 | C16: 0 | D16: 0 | E16: =AVERAGE(B16:D16) -> 0
B17: 0 | C17: 0 | D17: 0 | E17: =AVERAGE(B17:D17) -> 0 | I17: PERCENTUAL DO CUSTO FIXO MEDIO
B18: 0 | C18: 0 | D18: 0 | E18: =AVERAGE(B18:D18) -> 0 | I18: =E29/K10 -> 0.53010638
B19: 0 | C19: 0 | D19: 0 | E19: =AVERAGE(B19:D19) -> 0
B20: 0 | C20: 0 | D20: 0 | E20: =AVERAGE(B20:D20) -> 0
B21: 0 | C21: 0 | D21: 0 | E21: =AVERAGE(B21:D21) -> 0 | I21: Este percentual representa o PESO dos seus gastos fixos sobre sua receita BRUTA. Valor a ser considerado na hora de formar o preço de venda, pois o percentual aqui demonstrado representa o quanto deve-se resguardar do produto e destinar ao pagamento de suas contas fixas.
B22: 0 | C22: 0 | D22: 0 | E22: =AVERAGE(B22:D22) -> 0
B23: 0 | C23: 0 | D23: 0 | E23: =AVERAGE(B23:D23) -> 0
B24: 0 | C24: 0 | D24: 0 | E24: =AVERAGE(B24:D24) -> 0
B25: 0 | C25: 0 | D25: 0 | E25: =AVERAGE(B25:D25) -> 0
B26: 0 | C26: 0 | D26: 0 | E26: =AVERAGE(B26:D26) -> 0
B27: 0 | C27: 0 | D27: 0 | E27: =AVERAGE(B27:D27) -> 0
B28: 0 | C28: 0 | D28: 0 | E28: =AVERAGE(B28:D28) -> 0
A29: TOTAL | B29: =SUM(B6:B28) -> 9830 | C29: =SUM(C6:C28) -> 7385 | D29: =SUM(D6:D28) -> 7700 | E29: =AVERAGE(B29:D29) -> 8305

Sheet CALC. FORMAÇAO DE PREÇO
L3: ='CALCULO PERC. CUSTO INDIRETO'!I18*$C$46 -> 814.77351
A10: CUSTOS DIRETOS | D10: PERC. DE LUCRO LIVRE DESEJADO
A11: FRETE | B11: 100 | D11: 0.2
A12: OUTRAS DESPESAS | B12: 0
A14: MERCADORIA | B14: QUANT. | C14: CUSTO MERC. UNIT. | D14: IPI % | E14: FRETE RATEADO | F14: OUTRAS DEPESAS | G14: VALOR IPI | H14: CUSTO UNIT. ANT INDIRETO | I14: C. INDIRETOS RATEADO | J14: CUSTO. ANT. IND. VARIAVEL. | K14: CUSTO FINAL | L14: LUCRO LIVRE OBTIDO | M14: PREÇO FINAL VENDA
A15: PRODUTO EXEMPLO 1 | B15: 30 | C15: 20 | D15: 0.05 | E15: =IF(B15=0,0,'CALC. FORMAÇAO DE PREÇO'!$B$11/$B$46) -> 1.0752688 | F15: =IF(B15=0,0,'CALC. FORMAÇAO DE PREÇO'!$B$12/$B$46) -> 0 | G15: =C15*D15 -> 1 | H15: =IF(B15=0,0,SUM(C15,E15,F15,G15)) -> 22.075269 | I15: =IF(B15=0,0,($L$3/$B$46)) -> 8.7610055 | J15: =H15+I15 -> 30.836274 | K15: =('CALCULO PERC. CUSTO INDIRETO'!$I$13*J15)+J15 -> 31.737802 | L15: =J15*$D$11 -> 6.1672549 | M15: =K15+L15 -> 37.905057
A16: PRODUTO EXEMPLO 2 | B16: 20 | C16: 7 | D16: 0.02 | E16: =IF(B16=0,0,'CALC. FORMAÇAO DE PREÇO'!$B$11/$B$46) -> 1.0752688 | F16: =IF(B16=0,0,'CALC. FORMAÇAO DE PREÇO'!$B$12/$B$46) -> 0 | G16: =C16*D16 -> 0.14 | H16: =IF(B16=0,0,SUM(C16,E16,F16,G16)) -> 8.2152688 | I16: =IF(B16=0,0,($L$3/$B$46)) -> 8.7610055 | J16: =H16+I16 -> 16.976274 | K16: =('CALCULO PERC. CUSTO INDIRETO'!$I$13*J16)+J16 -> 17.472592 | L16: =J16*$D$11 -> 3.3952549 | M16: =K16+L16 -> 20.867846
A17: PRODUTO EXEMPLO 3 | B17: 20 | C17: 10 | D17: 0 | E17: =IF(B17=0,0,'CALC. FORMAÇAO DE PREÇO'!$B$11/$B$46) -> 1.0752688 | F17: =IF(B17=0,0,'CALC. FORMAÇAO DE PREÇO'!$B$12/$B$46) -> 0 | G17: =C17*D17 -> 0 | H17: =IF(B17=0,0,SUM(C17,E17,F17,G17)) -> 11.075269 | I17: =IF(B17=0,0,($L$3/$B$46)) -> 8.7610055 | J17: =H17+I17 -> 19.836274 | K17: =('CALCULO PERC. CUSTO INDIRETO'!$I$13*J17)+J17 -> 20.416206 | L17: =J17*$D$11 -> 3.9672549 | M17: =K17+L17 -> 24.383461
A18: PRODUTO EXEMPLO 4 | B18: 20 | C18: 500 | D18: 0 | E18: =IF(B18=0,0,'CALC. FORMAÇAO DE PREÇO'!$B$11/$B$46) -> 1.0752688 | F18: =IF(B18=0,0,'CALC. FORMAÇAO DE PREÇO'!$B$12/$B$46) -> 0 | G18: =C18*D18 -> 0 | H18: =IF(B18=0,0,SUM(C18,E18,F18,G18)) -> 501.07527 | I18: =IF(B18=0,0,($L$3/$B$46)) -> 8.7610055 | J18: =H18+I18 -> 509.83627 | K18: =('CALCULO PERC. CUSTO INDIRETO'!$I$13*J18)+J18 -> 524.74182 | L18: =J18*$D$11 -> 101.96725 | M18: =K18+L18 -> 626.70907
A19: PRODUTO EXEMPLO 5 | B19: 1 | C19: 300 | D19: 0 | E19: =IF(B19=0,0,'CALC. FORMAÇAO DE PREÇO'!$B$11/$B$46) -> 1.0752688 | F19: =IF(B19=0,0,'CALC. FORMAÇAO DE PREÇO'!$B$12/$B$46) -> 0 | G19: =C19*D19 -> 0 | H19: =IF(B19=0,0,SUM(C19,E19,F19,G19)) -> 301.07527 | I19: =IF(B19=0,0,($L$3/$B$46)) -> 8.7610055 | J19: =H19+I19 -> 309.83627 | K19: =('CALCULO PERC. CUSTO INDIRETO'!$I$13*J19)+J19 -> 318.89463 | L19: =J19*$D$11 -> 61.967255 | M19: =K19+L19 -> 380.86188
A20: PRODUTO EXEMPLO 6 | B20: 1 | C20: 400 | D20: 0 | E20: =IF(B20=0,0,'CALC. FORMAÇAO DE PREÇO'!$B$11/$B$46) -> 1.0752688 | F20: =IF(B20=0,0,'CALC. FORMAÇAO DE PREÇO'!$B$12/$B$46) -> 0 | G20: =C20*D20 -> 0 | H20: =IF(B20=0,0,SUM(C20,E20,F20,G20)) -> 401.07527 | I20: =IF(B20=0,0,($L$3/$B$46)) -> 8.7610055 | J20: =H20+I20 -> 409.83627 | K20: =('CALCULO PERC. CUSTO INDIRETO'!$I$13*J20)+J20 -> 421.81822 | L20: =J20*$D$11 -> 81.967255 | M20: =K20+L20 -> 503.78548
A21: PRODUTO EXEMPLO 7 | B21: 1 | C21: 300 | D21: 0 | E21: =IF(B21=0,0,'CALC. FORMAÇAO DE PREÇO'!$B$11/$B$46) -> 1.0752688 | F21: =IF(B21=0,0,'CALC. FORMAÇAO DE PREÇO'!$B$12/$B$46) -> 0 | G21: =C21*D21 -> 0 | H21: =IF(B21=0,0,SUM(C21,E21,F21,G21)) -> 301.07527 | I21: =IF(B21=0,0,($L$3/$B$46)) -> 8.7610055 | J21: =H21+I21 -> 309.83627 | K21: =('CALCULO PERC. CUSTO INDIRETO'!$I$13*J21)+J21 -> 318.89463 | L21: =J21*$D$11 -> 61.967255 | M21: =K21+L21 -> 380.86188
B22: 0 | C22: 0 | D22: 0 | E22: =IF(B22=0,0,'CALC. FORMAÇAO DE PREÇO'!$B$11/$B$46) -> 0 | F22: =IF(B22=0,0,'CALC. FORMAÇAO DE PREÇO'!$B$12/$B$46) -> 0 | G22: =C22*D22 -> 0 | H22: =IF(B22=0,0,SUM(C22,E22,F22,G22)) -> 0 | I22: =IF(B22=0,0,($L$3/$B$46)) -> 0 | J22: =H22+I22 -> 0 | K22: =('CALCULO PERC. CUSTO INDIRETO'!$I$13*J22)+J22 -> 0 | L22: =J22*$D$11 -> 0 | M22: =K22+L22 -> 0
B23: 0 | C23: 0 | D23: 0 | E23: =IF(B23=0,0,'CALC. FORMAÇAO DE PREÇO'!$B$11/$B$46) -> 0 | F23: =IF(B23=0,0,'CALC. FORMAÇAO DE PREÇO'!$B$12/$B$46) -> 0 | G23: =C23*D23 -> 0 | H23: =IF(B23=0,0,SUM(C23,E23,F23,G23)) -> 0 | I23: =IF(B23=0,0,($L$3/$B$46)) -> 0 | J23: =H23+I23 -> 0 | K23: =('CALCULO PERC. CUSTO INDIRETO'!$I$13*J23)+J23 -> 0 | L23: =J23*$D$11 -> 0 | M23: =K23+L23 -> 0
B24: 0 | C24: 0 | D24: 0 | E24: =IF(B24=0,0,'CALC. FORMAÇAO DE PREÇO'!$B$11/$B$46) -> 0 | F24: =IF(B24=0,0,'CALC. FORMAÇAO DE PREÇO'!$B$12/$B$46) -> 0 | G24: =C24*D24 -> 0 | H24: =IF(B24=0,0,SUM(C24,E24,F24,G24)) -> 0 | I24: =IF(B24=0,0,($L$3/$B$46)) -> 0 | J24: =H24+I24 -> 0 | K24: =('CALCULO PERC. CUSTO INDIRETO'!$I$13*J24)+J24 -> 0 | L24: =J24*$D$11 -> 0 | M24: =K24+L24 -> 0
B25: 0 | C25: 0 | D25: 0 | E25: =IF(B25=0,0,'CALC. FORMAÇAO DE PREÇO'!$B$11/$B$46) -> 0 | F25: =IF(B25=0,0,'CALC. FORMAÇAO DE PREÇO'!$B$12/$B$46) -> 0 | G25: =C25*D25 -> 0 | H25: =IF(B25=0,0,SUM(C25,E25,F25,G25)) -> 0 | I25: =IF(B25=0,0,($L$3/$B$46)) -> 0 | J25: =H25+I25 -> 0 | K25: =('CALCULO PERC. CUSTO INDIRETO'!$I$13*J25)+J25 -> 0 | L25: =J25*$D$11 -> 0 | M25: =K25+L25 -> 0
B26: 0 | C26: 0 | D26: 0 | E26: =IF(B26=0,0,'CALC. FORMAÇAO DE PREÇO'!$B$11/$B$46) -> 0 | F26: =IF(B26=0,0,'CALC. FORMAÇAO DE PREÇO'!$B$12/$B$46) -> 0 | G26: =C26*D26 -> 0 | H26: =IF(B26=0,0,SUM(C26,E26,F26,G26)) -> 0 | I26: =IF(B26=0,0,($L$3/$B$46)) -> 0 | J26: =H26+I26 -> 0 | K26: =('CALCULO PERC. CUSTO INDIRETO'!$I$13*J26)+J26 -> 0 | L26: =J26*$D$11 -> 0 | M26: =K26+L26 -> 0
B27: 0 | C27: 0 | D27: 0 | E27: =IF(B27=0,0,'CALC. FORMAÇAO DE PREÇO'!$B$11/$B$46) -> 0 | F27: =IF(B27=0,0,'CALC. FORMAÇAO DE PREÇO'!$B$12/$B$46) -> 0 | G27: =C27*D27 -> 0 | H27: =IF(B27=0,0,SUM(C27,E27,F27,G27)) -> 0 | I27: =IF(B27=0,0,($L$3/$B$46)) -> 0 | J27: =H27+I27 -> 0 | K27: =('CALCULO PERC. CUSTO INDIRETO'!$I$13*J27)+J27 -> 0 | L27: =J27*$D$11 -> 0 | M27: =K27+L27 -> 0
B28: 0 | C28: 0 | D28: 0 | E28: =IF(B28=0,0,'CALC. FORMAÇAO DE PREÇO'!$B$11/$B$46) -> 0 | F28: =IF(B28=0,0,'CALC. FORMAÇAO DE PREÇO'!$B$12/$B$46) -> 0 | G28: =C28*D28 -> 0 | H28: =IF(B28=0,0,SUM(C28,E28,F28,G28)) -> 0 | I28: =IF(B28=0,0,($L$3/$B$46)) -> 0 | J28: =H28+I28 -> 0 | K28: =('CALCULO PERC. CUSTO INDIRETO'!$I$13*J28)+J28 -> 0 | L28: =J28*$D$11 -> 0 | M28: =K28+L28 -> 0
B29: 0 | C29: 0 | D29: 0 | E29: =IF(B29=0,0,'CALC. FORMAÇAO DE PREÇO'!$B$11/$B$46) -> 0 | F29: =IF(B29=0,0,'CALC. FORMAÇAO DE PREÇO'!$B$12/$B$46) -> 0 | G29: =C29*D29 -> 0 | H29: =IF(B29=0,0,SUM(C29,E29,F29,G29)) -> 0 | I29: =IF(B29=0,0,($L$3/$B$46)) -> 0 | J29: =H29+I29 -> 0 | K29: =('CALCULO PERC. CUSTO INDIRETO'!$I$13*J29)+J29 -> 0 | L29: =J29*$D$11 -> 0 | M29: =K29+L29 -> 0
B30: 0 | C30: 0 | D30: 0 | E30: =IF(B30=0,0,'CALC. FORMAÇAO DE PREÇO'!$B$11/$B$46) -> 0 | F30: =IF(B30=0,0,'CALC. FORMAÇAO DE PREÇO'!$B$12/$B$46) -> 0 | G30: =C30*D30 -> 0 | H30: =IF(B30=0,0,SUM(C30,E30,F30,G30)) -> 0 | I30: =IF(B30=0,0,($L$3/$B$46)) -> 0 | J30: =H30+I30 -> 0 | K30: =('CALCULO PERC. CUSTO INDIRETO'!$I$13*J30)+J30 -> 0 | L30: =J30*$D$11 -> 0 | M30: =K30+L30 -> 0
B31: 0 | C31: 0 | D31: 0 | E31: =IF(B31=0,0,'CALC. FORMAÇAO DE PREÇO'!$B$11/$B$46) -> 0 | F31: =IF(B31=0,0,'CALC. FORMAÇAO DE PREÇO'!$B$12/$B$46) -> 0 | G31: =C31*D31 -> 0 | H31: =IF(B31=0,0,SUM(C31,E31,F31,G31)) -> 0 | I31: =IF(B31=0,0,($L$3/$B$46)) -> 0 | J31: =H31+I31 -> 0 | K31: =('CALCULO PERC. CUSTO INDIRETO'!$I$13*J31)+J31 -> 0 | L31: =J31*$D$11 -> 0 | M31: =K31+L31 -> 0
B32: 0 | C32: 0 | D32: 0 | E32: =IF(B32=0,0,'CALC. FORMAÇAO DE PREÇO'!$B$11/$B$46) -> 0 | F32: =IF(B32=0,0,'CALC. FORMAÇAO DE PREÇO'!$B$12/$B$46) -> 0 | G32: =C32*D32 -> 0 | H32: =IF(B32=0,0,SUM(C32,E32,F32,G32)) -> 0 | I32: =IF(B32=0,0,($L$3/$B$46)) -> 0 | J32: =H32+I32 -> 0 | K32: =('CALCULO PERC. CUSTO INDIRETO'!$I$13*J32)+J32 -> 0 | L32: =J32*$D$11 -> 0 | M32: =K32+L32 -> 0
B33: 0 | C33: 0 | D33: 0 | E33: =IF(B33=0,0,'CALC. FORMAÇAO DE PREÇO'!$B$11/$B$46) -> 0 | F33: =IF(B33=0,0,'CALC. FORMAÇAO DE PREÇO'!$B$12/$B$46) -> 0 | G33: =C33*D33 -> 0 | H33: =IF(B33=0,0,SUM(C33,E33,F33,G33)) -> 0 | I33: =IF(B33=0,0,($L$3/$B$46)) -> 0 | J33: =H33+I33 -> 0 | K33: =('CALCULO PERC. CUSTO INDIRETO'!$I$13*J33)+J33 -> 0 | L33: =J33*$D$11 -> 0 | M33: =K33+L33 -> 0
... B45: 0 | C45: 0 | D45: 0 | E45: =IF(B45=0,0,'CALC. FORMAÇAO DE PREÇO'!$B$11/$B$46) -> 0 | F45: =IF(B45=0,0,'CALC. FORMAÇAO DE PREÇO'!$B$12/$B$46) -> 0 | G45: =C45*D45 -> 0 | H45: =IF(B45=0,0,SUM(C45,E45,F45,G45)) -> 0 | I45: =IF(B45=0,0,($L$3/$B$46)) -> 0 | J45: =H45+I45 -> 0 | K45: =('CALCULO PERC. CUSTO INDIRETO'!$I$13*J45)+J45 -> 0 | L45: =J45*$D$11 -> 0 | M45: =K45+L45 -> 0
A46: TOTAL | B46: =SUM(B15:B45) -> 93 | C46: =SUM(C15:C45) -> 1537
