Workbook

Sheet REGRAS GERAIS
A1: PERT - SIMPLES NACIONAL
A3: debitos até | B3: 43040
A4: entrada de | B4: 0.05
A5: entrada parcelada em até | B5: 5
A6: parcela mínima | B6: 300
D7: www.enebe.com.br
A8: Descontos
B9: Multa | C9: Juros | D9: Encargos legais
A10: à vista: | B10: 0.7 | C10: 0.9 | D10: 1
A11: até 145 parcelas | B11: 0.5 | C11: 0.8 | D11: 1
A12: até 175 parcelas | B12: 0.25 | C12: 0.5 | D12: 1
A16: LEI COMPLEMENTAR Nº 162, DE 6 DE JANEIRO DE 2018
A17: http://www.normaslegais.com.br/legislacao/lei-complementar-162-2018.htm

Sheet DEBITOS rfb
B2: Período de Apuração | C2: Data de Vencimento | D2: Débito Declarado (R$) | E2: Saldo Devedor | I2: Nº Parcelamento
E3: Principal (R$) | F3: Multa (R$) | G3: Juros (R$) | H3: Total (R$) | I3: (exigibilidade suspensa)
B4: 41334 | C4: 41386 | D4: 2637.84 | E4: 213.41 | F4: 42.68 | G4: 115.07 | H4: 371.16
B5: 41395 | C5: 41445 | D5: 4463.09 | E5: 898.41 | F5: 179.68 | G5: 473.55 | H5: 1551.64
B6: 41426 | C6: 41477 | D6: 1265.23 | E6: 236.15 | F6: 47.23 | G6: 122.77 | H6: 406.15
B7: 41456 | C7: 41506 | D7: 4459.55 | E7: 952.6 | F7: 190.52 | G7: 488.49 | H7: 1631.61
B8: 42095 | C8: 42144 | D8: 20670.25 | E8: 12383.25 | F8: 2476.65 | G8: 4100.09 | H8: 18959.99
B9: 42248 | C9: 42297 | D9: 11018.56 | E9: 11018.56 | F9: 2203.71 | G9: 3033.41 | H9: 16255.68
B10: 42278 | C10: 42328 | D10: 14299.19 | E10: 14299.19 | F10: 2859.84 | G10: 3785 | H10: 20944.03
B11: 42309 | C11: 42359 | D11: 8865.57 | E11: 8865.57 | F11: 1773.11 | G11: 2243.88 | H11: 12882.56
B12: 42491 | C12: 42541 | D12: 9613.47 | E12: 9613.47 | F12: 1922.69 | G12: 1803.49 | H12: 13339.65
B13: 42522 | C13: 42571 | D13: 9925.99 | E13: 9925.99 | F13: 1985.2 | G13: 1751.94 | H13: 13663.13
B14: 42552 | C14: 42604 | D14: 5941.1 | E14: 5941.1 | F14: 1188.22 | G14: 976.12 | H14: 8105.44
B15: 42583 | C15: 42634 | D15: 11931.59 | E15: 11931.59 | F15: 2386.32 | G15: 1827.92 | H15: 16145.83
... B24: 43040 | C24: 43089 | D24: 1912.6 | E24: 1912.6 | F24: 382.52 | G24: 49.35 | H24: 2344.47
A26: Gerar DAS
E27: =SUM(E4:E26) -> 117847 | F27: =SUM(F4:F26) -> 23569.41 | G27: =SUM(G4:G26) -> 23964.72 | H27: =SUM(H4:H26) -> 165381.13
A30: NÃO PARCELAVEIS
B32: 43070 | C32: 43122 | D32: 3078.45 | E32: 3078.45 | F32: 615.69 | G32: 61.57 | H32: 3755.71

Sheet resumo geral
A3: SIMULAÇÃO PARCELAMENTO
A4: Programa Especial de Regularização Tributária - PERT - SIMPLES NACIONAL
A6: RECEITA FEDERAL
A7: Débitos até 11/2017 | B7: Original | C7: Multa | E7: Juros | F7: Encargos Legais | G7: Total
A8: Sem Desconto | B8: ='DEBITOS rfb'!E27 -> 117847 | C8: ='DEBITOS rfb'!F27 -> 23569.41 | E8: ='DEBITOS rfb'!G27 -> 23964.72 | F8: 0 | G8: =SUM(B8:F8) -> 165381.13
B9: =B8/G8 -> 0.71257827 | C9: =C8/G8 -> 0.14251572 | E9: =E8/G8 -> 0.14490601 | F9: =F8/G8 -> 0 | G9: =SUM(B9:F9) -> 1
A11: ENTRADA | B11: ='REGRAS GERAIS'!B4 -> 0.05 | C11: =IF(G8*B11<G11,G11,G8*B11) -> 8269.0565 | F11: ---------- PARCELA MINIMA --------> | G11: ='REGRAS GERAIS'!B6 -> 300
A12: Desmembramento: | B12: =C11*B9 -> 5892.35 | C12: =C11*C9 -> 1178.4705 | E12: =C11*E9 -> 1198.236 | F12: =C11*F9 -> 0 | G12: =C11*G9 -> 8269.0565
A14: Parcelas da Entrada: até | B14: ='REGRAS GERAIS'!B5 -> 5 | C14: =C11/B14 -> 1653.8113 | F14: ---------- PARCELA MINIMA --------> | G14: =G11 -> 300
A17: SALDO À PARCELAR | B17: =B8-B12 -> 111954.65 | C17: =C8-C12 -> 22390.94 | D17: =D8-D12 -> 0 | E17: =E8-E12 -> 22766.484 | F17: =F8-F12 -> 0 | G17: =G8-G12 -> 157112.07
A18: (após entrada)
A20: SIMULAÇÕES PARCELAS APÓS ENTRADA:
A22: Débitos administrados pela RFB
A23: OPÇÃO | B23: Original | C23: Multa | E23: Juros | F23: Encargos Legais | G23: Total
A24: ='REGRAS GERAIS'!A10 -> à vista: | B24: Descontos -> | C24: ='REGRAS GERAIS'!B10 -> 0.7 | E24: ='REGRAS GERAIS'!C10 -> 0.9 | F24: ='REGRAS GERAIS'!D10 -> 1 | G24: Economia --> | H24: =100%-((G25+C11)/G8) -> 0.21866457
A25: (após entrada) | B25: =B17 -> 111954.65 | C25: =C17-(C17*C24) -> 6717.2819 | D25: 0.5 | E25: =E17-(E17*E24) -> 2276.6484 | F25: =F17-(F17*F24) -> 0 | G25: =SUM(B25:F25) -> 120949.08
A27: OPÇÃO | B27: Original | C27: Multa | E27: Juros | F27: Encargos Legais | G27: Total
A28: ='REGRAS GERAIS'!A11 -> até 145 parcelas | B28: Descontos -> | C28: ='REGRAS GERAIS'!B11 -> 0.5 | E28: ='REGRAS GERAIS'!C11 -> 0.8 | F28: ='REGRAS GERAIS'!D11 -> 1 | G28: Economia --> | H28: =100%-((G29+C11)/G8) -> 0.17782051
B29: =B17 -> 111954.65 | C29: =C17-(C17*C28) -> 11195.47 | D29: 0.5 | E29: =E17-(E17*E28) -> 4553.2968 | F29: =F17-(F17*F28) -> 0 | G29: =SUM(B29:F29) -> 127703.92
A30: Parcelas ---> | B30: =ROUNDDOWN(IF(G29/G30>145,145,G29/G30),0) -> 145 | C30: =G29/B30 -> 880.71667 | F30: ---------- PARCELA MINIMA --------> | G30: =G11 -> 300
A32: OPÇÃO | B32: Original | C32: Multa | E32: Juros | F32: Encargos Legais | G32: Total
A33: ='REGRAS GERAIS'!A12 -> até 175 parcelas | B33: Descontos -> | C33: ='REGRAS GERAIS'!B12 -> 0.25 | E33: ='REGRAS GERAIS'!C12 -> 0.5 | F33: ='REGRAS GERAIS'!D12 -> 1 | G33: Economia --> | H33: =100%-((G34+C11)/G8) -> 0.10267481
B34: =B17 -> 111954.65 | C34: =C17-(C17*C33) -> 16793.205 | D34: 0.5 | E34: =E17-(E17*E33) -> 11383.242 | F34: =F17-(F17*F33) -> 0 | G34: =SUM(B34:F34) -> 140131.6
A35: Parcelas ---> | B35: =ROUNDDOWN(IF(G34/G35>175,175,G34/G35),0) -> 175 | C35: =G34/B35 -> 800.75198 | F35: ---------- PARCELA MINIMA --------> | G35: =G11 -> 300
