Workbook
Name Anos: Cálculos!$I$6
Name AnoSelecionado: 'Relatório Financeiro'!$K$2
Name Anoslst: OFFSET('Entrada de Dados Financeiros'!$B$5:$I$5,0,1,1,COUNTA('Entrada de Dados Financeiros'!$B$5:$I$5)-1)
Name Métricaslst: OFFSET('Entrada de Dados Financeiros'!$B$6:$B$30,0,0,COUNTA('Entrada de Dados Financeiros'!$B$6:$B$30))

Sheet Relatório Financeiro
B2: RELATÓRIO FINANCEIRO ANUAL | K2: 2014 | N2: Selecione o ano do relatório na Célula L2
B3: NOME DA EMPRESA | N3: Para editar dados, selecione a planilha de Entrada de Dados Financeiros
B5: MÉTRICAS-CHAVE | D5: Clique para alterar o relatório de métricas-chave
B7: =Cálculos!B8 -> RECEITAS | D7: =Cálculos!B9 -> LUCRO LÍQUIDO | F7: =Cálculos!B10 -> JUROS | H7: =Cálculos!B11 -> DEPRECIAÇÃO | J7: =Cálculos!B12 -> LUCRO OPERACIONAL
B8: =IFERROR(Cálculos!G8,"") -> 180583.88 | D8: =IFERROR(Cálculos!G9,"") -> 67474.85 | F8: =IFERROR(Cálculos!G10,"") -> 3789.47 | H8: =IFERROR(Cálculos!G11,"") -> 5546.88 | J8: =IFERROR(Cálculos!G12,"") -> 73425.99
B9: =Cálculos!H8 -> 0.0030953754 | D9: =Cálculos!H9 -> 0.018148663 | F9: =Cálculos!H10 -> 0.13514963 | H9: =Cálculos!H11 -> 0.094400227 | J9: =Cálculos!H12 -> -0.050335608
B13: TODAS AS MÉTRICAS | D13: Não modifique as informações abaixo. Clique para inserir Dados Financeiros
B15: MÉTRICA | D15: ="ANO DO RELATÓRIO ("&AnoSelecionado&")" -> ANO DO RELATÓRIO (2014) | F15: ="ANO ANTERIOR ("&AnoSelecionado-1&")" -> ANO ANTERIOR (2013) | H15: % DE ALTERAÇÃO | I15: =CONCATENATE("TENDÊNCIA DE ",Anos," ANOS") -> TENDÊNCIA DE 5 ANOS
B16: =Cálculos!B15 -> RECEITAS | D16: =IF($B16="","",Cálculos!G15) -> 180583.88 | F16: =IF($B16="","",Cálculos!F15) -> 180026.63 | H16: =IFERROR(D16/F16-1,"") -> 0.0030953754
B17: =Cálculos!B16 -> DESPESAS OPERACIONAIS | D17: =IF($B17="","",Cálculos!G16) -> 94419.45 | F17: =IF($B17="","",Cálculos!F16) -> 80883.33 | H17: =IFERROR(D17/F17-1,"") -> 0.16735364
B18: =Cálculos!B17 -> LUCRO OPERACIONAL | D18: =IF($B18="","",Cálculos!G17) -> 73425.99 | F18: =IF($B18="","",Cálculos!F17) -> 77317.83 | H18: =IFERROR(D18/F18-1,"") -> -0.050335608
B19: =Cálculos!B18 -> DEPRECIAÇÃO | D19: =IF($B19="","",Cálculos!G18) -> 5546.88 | F19: =IF($B19="","",Cálculos!F18) -> 5068.42 | H19: =IFERROR(D19/F19-1,"") -> 0.094400227
B20: =Cálculos!B19 -> JUROS | D20: =IF($B20="","",Cálculos!G19) -> 3789.47 | F20: =IF($B20="","",Cálculos!F19) -> 3338.3 | H20: =IFERROR(D20/F20-1,"") -> 0.13514963
B21: =Cálculos!B20 -> LUCRO LÍQUIDO | D21: =IF($B21="","",Cálculos!G20) -> 67474.85 | F21: =IF($B21="","",Cálculos!F20) -> 66272.1 | H21: =IFERROR(D21/F21-1,"") -> 0.018148663
B22: =Cálculos!B21 -> IMPOSTOS | D22: =IF($B22="","",Cálculos!G21) -> 31408.25 | F22: =IF($B22="","",Cálculos!F21) -> 29424.53 | H22: =IFERROR(D22/F22-1,"") -> 0.06741722
B23: =Cálculos!B22 -> LUCRO APÓS DEDUÇÃO DE IMPOSTOS | D23: =IF($B23="","",Cálculos!G22) -> 50247.68 | F23: =IF($B23="","",Cálculos!F22) -> 42438.2 | H23: =IFERROR(D23/F23-1,"") -> 0.18402006
B24: =Cálculos!B23 -> MÉTRICA 1 | D24: =IF($B24="","",Cálculos!G23) -> 19.96 | F24: =IF($B24="","",Cálculos!F23) -> 16.78 | H24: =IFERROR(D24/F24-1,"") -> 0.18951132
B25: =Cálculos!B24 -> MÉTRICA 2 | D25: =IF($B25="","",Cálculos!G24) -> 26.01 | F25: =IF($B25="","",Cálculos!F24) -> 21.84 | H25: =IFERROR(D25/F25-1,"") -> 0.19093407
B26: =Cálculos!B25 -> MÉTRICA 3 | D26: =IF($B26="","",Cálculos!G25) -> 31.08 | F26: =IF($B26="","",Cálculos!F25) -> 26.39 | H26: =IFERROR(D26/F26-1,"") -> 0.17771883
B27: =Cálculos!B26 -> MÉTRICA 4 | D27: =IF($B27="","",Cálculos!G26) -> 14.92 | F27: =IF($B27="","",Cálculos!F26) -> 14.59 | H27: =IFERROR(D27/F27-1,"") -> 0.022618232
... B40: =Cálculos!B39 | D40: =IF($B40="","",Cálculos!G39) | F40: =IF($B40="","",Cálculos!F39) | H40: =IFERROR(D40/F40-1,"")

Sheet Entrada de Dados Financeiros
B2: INSIRA SEUS DADOS FINANCEIROS
B3: VOCÊ PODE DEFINIR ATÉ 25 MÉTRICAS-CHAVE PARA 7 ANOS
B4: Clique para ver o Relatório Financeiro
B5: NOME DA MÉTRICA | C5: 2008 | D5: 2009 | E5: 2010 | F5: 2011 | G5: 2012 | H5: 2013 | I5: 2014
B6: RECEITAS | C6: 125000 | D6: 134137.45 | E6: 142728.38 | F6: 150687.46 | G6: 165044.56 | H6: 180026.63 | I6: 180583.88
B7: DESPESAS OPERACIONAIS | C7: 65000 | D7: 70962.31 | E7: 75924.86 | F7: 78901.27 | G7: 81674.37 | H7: 80883.33 | I7: 94419.45
B8: LUCRO OPERACIONAL | C8: 60000 | D8: 64207.3 | E8: 68857.69 | F8: 75643.25 | G8: 76755.26 | H8: 77317.83 | I8: 73425.99
B9: DEPRECIAÇÃO | C9: 4500 | D9: 4517.77 | E9: 4656.92 | F9: 4974.21 | G9: 5024.11 | H9: 5068.42 | I9: 5546.88
B10: JUROS | C10: 2500 | D10: 2745.82 | E10: 2893.11 | F10: 3136.12 | G10: 3148.53 | H10: 3338.3 | I10: 3789.47
B11: LUCRO LÍQUIDO | C11: 54000 | D11: 54761.075 | E11: 55860.81 | F11: 59747.95 | G11: 61483.59 | H11: 66272.1 | I11: 67474.85
B12: IMPOSTOS | C12: 22000 | D12: 23920.54 | E12: 25576.74 | F12: 27498.86 | G12: 28335.67 | H12: 29424.53 | I12: 31408.25
B13: LUCRO APÓS DEDUÇÃO DE IMPOSTOS | C13: 32000 | D13: 34943.49 | E13: 38418.53 | F13: 39895.05 | G13: 40607.73 | H13: 42438.2 | I13: 50247.68
B14: MÉTRICA 1 | C14: 12.8 | D14: 12.81 | E14: 13.78 | F14: 14.29 | G14: 15.57 | H14: 16.78 | I14: 19.96
B15: MÉTRICA 2 | C15: 18.2 | D15: 18.59 | E15: 19.22 | F15: 20.17 | G15: 20.48 | H15: 21.84 | I15: 26.01
B16: MÉTRICA 3 | C16: 19.1 | D16: 20.55 | E16: 21.87 | F16: 23.19 | G16: 24.67 | H16: 26.39 | I16: 31.08
... B19: MÉTRICA 6 | C19: 0.23 | D19: 0.25 | E19: 0.27 | F19: 0.28 | G19: 0.29 | H19: 0.3 | I19: 0.34

Sheet Configurações de Métricas-chave
B2: DEFINIR MÉTRICAS-CHAVE AQUI
B3: SELECIONE ATÉ 5 MÉTRICAS-CHAVE PARA MOSTRAR NA PARTE SUPERIOR DO RELATÓRIO
B4: Clique para ver o Relatório Financeiro
B5: 1 | C5: RECEITAS | D5: =IF(ISBLANK(C5),"← Selecione um valor no menu suspenso",IF(COUNTIF($C$5:C5,C5)>1,"Você selecionou "&C5&" duas vezes.",""))
B6: 2 | C6: LUCRO LÍQUIDO | D6: =IF(ISBLANK(C6),"← Selecione um valor no menu suspenso",IF(COUNTIF($C$5:C6,C6)>1,"Você selecionou "&C6&" duas vezes.",""))
B7: 3 | C7: JUROS | D7: =IF(ISBLANK(C7),"← Selecione um valor no menu suspenso",IF(COUNTIF($C$5:C7,C7)>1,"Você selecionou "&C7&" duas vezes.",""))
B8: 4 | C8: DEPRECIAÇÃO | D8: =IF(ISBLANK(C8),"← Selecione um valor no menu suspenso",IF(COUNTIF($C$5:C8,C8)>1,"Você selecionou "&C8&" duas vezes.",""))
B9: 5 | C9: LUCRO OPERACIONAL | D9: =IF(ISBLANK(C9),"← Selecione um valor no menu suspenso",IF(COUNTIF($C$5:C9,C9)>1,"Você selecionou "&C9&" duas vezes.",""))

Sheet Cálculos
A1: Esta planilha é usada para cálculos de Relatório Financeiro e deve permanecer oculta.
D2: Posição
B3: Este ano | C3: =AnoSelecionado -> 2014 | D3: =MATCH(C3,Anoslst,0)+1 -> 8
B4: Ano anterior | C4: =C3-1 -> 2013 | D4: =MATCH(C4,Anoslst,0)+1 -> 7
B6: Posição | C6: =MATCH(C7,Anoslst,0)+1 -> 4 | D6: =MATCH(D7,Anoslst,0)+1 -> 5 | E6: =MATCH(E7,Anoslst,0)+1 -> 6 | F6: =MATCH(F7,Anoslst,0)+1 -> 7 | G6: =MATCH(G7,Anoslst,0)+1 -> 8 | I6: =COUNT(C6:G6) -> 5
B7: Métricas-chave | C7: =D7-1 -> 2010 | D7: =E7-1 -> 2011 | E7: =F7-1 -> 2012 | F7: =G7-1 -> 2013 | G7: =C3 -> 2014
A8: =MATCH(B8,'Entrada de Dados Financeiros'!$B$6:$B$30,0) -> 1 | B8: =IF('Configurações de Métricas-chave'!C5="","",'Configurações de Métricas-chave'!C5) -> RECEITAS | C8: =IFERROR(INDEX('Entrada de Dados Financeiros'!$B$6:$I$30,$A8,C$6),NA()) -> 142728.38 | D8: =IFERROR(INDEX('Entrada de Dados Financeiros'!$B$6:$I$30,$A8,D$6),NA()) -> 150687.46 | E8: =IFERROR(INDEX('Entrada de Dados Financeiros'!$B$6:$I$30,$A8,E$6),NA()) -> 165044.56 | F8: =IFERROR(INDEX('Entrada de Dados Financeiros'!$B$6:$I$30,$A8,F$6),NA()) -> 180026.63 | G8: =IFERROR(INDEX('Entrada de Dados Financeiros'!$B$6:$I$30,$A8,G$6),NA()) -> 180583.88 | H8: =IFERROR(G8/F8-1,"") -> 0.0030953754
A9: =MATCH(B9,'Entrada de Dados Financeiros'!$B$6:$B$30,0) -> 6 | B9: =IF('Configurações de Métricas-chave'!C6="","",'Configurações de Métricas-chave'!C6) -> LUCRO LÍQUIDO | C9: =IFERROR(INDEX('Entrada de Dados Financeiros'!$B$6:$I$30,$A9,C$6),NA()) -> 55860.81 | D9: =IFERROR(INDEX('Entrada de Dados Financeiros'!$B$6:$I$30,$A9,D$6),NA()) -> 59747.95 | E9: =IFERROR(INDEX('Entrada de Dados Financeiros'!$B$6:$I$30,$A9,E$6),NA()) -> 61483.59 | F9: =IFERROR(INDEX('Entrada de Dados Financeiros'!$B$6:$I$30,$A9,F$6),NA()) -> 66272.1 | G9: =IFERROR(INDEX('Entrada de Dados Financeiros'!$B$6:$I$30,$A9,G$6),NA()) -> 67474.85 | H9: =IFERROR(G9/F9-1,"") -> 0.018148663
A10: =MATCH(B10,'Entrada de Dados Financeiros'!$B$6:$B$30,0) -> 5 | B10: =IF('Configurações de Métricas-chave'!C7="","",'Configurações de Métricas-chave'!C7) -> JUROS | C10: =IFERROR(INDEX('Entrada de Dados Financeiros'!$B$6:$I$30,$A10,C$6),NA()) -> 2893.11 | D10: =IFERROR(INDEX('Entrada de Dados Financeiros'!$B$6:$I$30,$A10,D$6),NA()) -> 3136.12 | E10: =IFERROR(INDEX('Entrada de Dados Financeiros'!$B$6:$I$30,$A10,E$6),NA()) -> 3148.53 | F10: =IFERROR(INDEX('Entrada de Dados Financeiros'!$B$6:$I$30,$A10,F$6),NA()) -> 3338.3 | G10: =IFERROR(INDEX('Entrada de Dados Financeiros'!$B$6:$I$30,$A10,G$6),NA()) -> 3789.47 | H10: =IFERROR(G10/F10-1,"") -> 0.13514963
A11: =MATCH(B11,'Entrada de Dados Financeiros'!$B$6:$B$30,0) -> 4 | B11: =IF('Configurações de Métricas-chave'!C8="","",'Configurações de Métricas-chave'!C8) -> DEPRECIAÇÃO | C11: =IFERROR(INDEX('Entrada de Dados Financeiros'!$B$6:$I$30,$A11,C$6),NA()) -> 4656.92 | D11: =IFERROR(INDEX('Entrada de Dados Financeiros'!$B$6:$I$30,$A11,D$6),NA()) -> 4974.21 | E11: =IFERROR(INDEX('Entrada de Dados Financeiros'!$B$6:$I$30,$A11,E$6),NA()) -> 5024.11 | F11: =IFERROR(INDEX('Entrada de Dados Financeiros'!$B$6:$I$30,$A11,F$6),NA()) -> 5068.42 | G11: =IFERROR(INDEX('Entrada de Dados Financeiros'!$B$6:$I$30,$A11,G$6),NA()) -> 5546.88 | H11: =IFERROR(G11/F11-1,"") -> 0.094400227
A12: =MATCH(B12,'Entrada de Dados Financeiros'!$B$6:$B$30,0) -> 3 | B12: =IF('Configurações de Métricas-chave'!C9="","",'Configurações de Métricas-chave'!C9) -> LUCRO OPERACIONAL | C12: =IFERROR(INDEX('Entrada de Dados Financeiros'!$B$6:$I$30,$A12,C$6),NA()) -> 68857.69 | D12: =IFERROR(INDEX('Entrada de Dados Financeiros'!$B$6:$I$30,$A12,D$6),NA()) -> 75643.25 | E12: =IFERROR(INDEX('Entrada de Dados Financeiros'!$B$6:$I$30,$A12,E$6),NA()) -> 76755.26 | F12: =IFERROR(INDEX('Entrada de Dados Financeiros'!$B$6:$I$30,$A12,F$6),NA()) -> 77317.83 | G12: =IFERROR(INDEX('Entrada de Dados Financeiros'!$B$6:$I$30,$A12,G$6),NA()) -> 73425.99 | H12: =IFERROR(G12/F12-1,"") -> -0.050335608
B14: Todas as Métricas (funciona em até 25 métricas)
A15: =ROWS($B$15:B15) -> 1 | B15: =IF('Entrada de Dados Financeiros'!B6=0,"",'Entrada de Dados Financeiros'!B6) -> RECEITAS | C15: =IF(B15="",NA(),IFERROR(INDEX('Entrada de Dados Financeiros'!$B$6:$I$30,$A15,C$6),NA())) -> 142728.38 | D15: =IF(B15="",NA(),IFERROR(INDEX('Entrada de Dados Financeiros'!$B$6:$I$30,$A15,D$6),NA())) -> 150687.46 | E15: =IF(B15="",NA(),IFERROR(INDEX('Entrada de Dados Financeiros'!$B$6:$I$30,$A15,E$6),NA())) -> 165044.56 | F15: =IF(B15="",NA(),IFERROR(INDEX('Entrada de Dados Financeiros'!$B$6:$I$30,$A15,F$6),NA())) -> 180026.63 | G15: =IF(B15="",NA(),IFERROR(INDEX('Entrada de Dados Financeiros'!$B$6:$I$30,$A15,G$6),NA())) -> 180583.88
A16: =ROWS($B$15:B16) -> 2 | B16: =IF('Entrada de Dados Financeiros'!B7=0,"",'Entrada de Dados Financeiros'!B7) -> DESPESAS OPERACIONAIS | C16: =IF(B16="",NA(),IFERROR(INDEX('Entrada de Dados Financeiros'!$B$6:$I$30,$A16,C$6),NA())) -> 75924.86 | D16: =IF(B16="",NA(),IFERROR(INDEX('Entrada de Dados Financeiros'!$B$6:$I$30,$A16,D$6),NA())) -> 78901.27 | E16: =IF(B16="",NA(),IFERROR(INDEX('Entrada de Dados Financeiros'!$B$6:$I$30,$A16,E$6),NA())) -> 81674.37 | F16: =IF(B16="",NA(),IFERROR(INDEX('Entrada de Dados Financeiros'!$B$6:$I$30,$A16,F$6),NA())) -> 80883.33 | G16: =IF(B16="",NA(),IFERROR(INDEX('Entrada de Dados Financeiros'!$B$6:$I$30,$A16,G$6),NA())) -> 94419.45
A17: =ROWS($B$15:B17) -> 3 | B17: =IF('Entrada de Dados Financeiros'!B8=0,"",'Entrada de Dados Financeiros'!B8) -> LUCRO OPERACIONAL | C17: =IF(B17="",NA(),IFERROR(INDEX('Entrada de Dados Financeiros'!$B$6:$I$30,$A17,C$6),NA())) -> 68857.69 | D17: =IF(B17="",NA(),IFERROR(INDEX('Entrada de Dados Financeiros'!$B$6:$I$30,$A17,D$6),NA())) -> 75643.25 | E17: =IF(B17="",NA(),IFERROR(INDEX('Entrada de Dados Financeiros'!$B$6:$I$30,$A17,E$6),NA())) -> 76755.26 | F17: =IF(B17="",NA(),IFERROR(INDEX('Entrada de Dados Financeiros'!$B$6:$I$30,$A17,F$6),NA())) -> 77317.83 | G17: =IF(B17="",NA(),IFERROR(INDEX('Entrada de Dados Financeiros'!$B$6:$I$30,$A17,G$6),NA())) -> 73425.99
A18: =ROWS($B$15:B18) -> 4 | B18: =IF('Entrada de Dados Financeiros'!B9=0,"",'Entrada de Dados Financeiros'!B9) -> DEPRECIAÇÃO | C18: =IF(B18="",NA(),IFERROR(INDEX('Entrada de Dados Financeiros'!$B$6:$I$30,$A18,C$6),NA())) -> 4656.92 | D18: =IF(B18="",NA(),IFERROR(INDEX('Entrada de Dados Financeiros'!$B$6:$I$30,$A18,D$6),NA())) -> 4974.21 | E18: =IF(B18="",NA(),IFERROR(INDEX('Entrada de Dados Financeiros'!$B$6:$I$30,$A18,E$6),NA())) -> 5024.11 | F18: =IF(B18="",NA(),IFERROR(INDEX('Entrada de Dados Financeiros'!$B$6:$I$30,$A18,F$6),NA())) -> 5068.42 | G18: =IF(B18="",NA(),IFERROR(INDEX('Entrada de Dados Financeiros'!$B$6:$I$30,$A18,G$6),NA())) -> 5546.88
A19: =ROWS($B$15:B19) -> 5 | B19: =IF('Entrada de Dados Financeiros'!B10=0,"",'Entrada de Dados Financeiros'!B10) -> JUROS | C19: =IF(B19="",NA(),IFERROR(INDEX('Entrada de Dados Financeiros'!$B$6:$I$30,$A19,C$6),NA())) -> 2893.11 | D19: =IF(B19="",NA(),IFERROR(INDEX('Entrada de Dados Financeiros'!$B$6:$I$30,$A19,D$6),NA())) -> 3136.12 | E19: =IF(B19="",NA(),IFERROR(INDEX('Entrada de Dados Financeiros'!$B$6:$I$30,$A19,E$6),NA())) -> 3148.53 | F19: =IF(B19="",NA(),IFERROR(INDEX('Entrada de Dados Financeiros'!$B$6:$I$30,$A19,F$6),NA())) -> 3338.3 | G19: =IF(B19="",NA(),IFERROR(INDEX('Entrada de Dados Financeiros'!$B$6:$I$30,$A19,G$6),NA())) -> 3789.47
A20: =ROWS($B$15:B20) -> 6 | B20: =IF('Entrada de Dados Financeiros'!B11=0,"",'Entrada de Dados Financeiros'!B11) -> LUCRO LÍQUIDO | C20: =IF(B20="",NA(),IFERROR(INDEX('Entrada de Dados Financeiros'!$B$6:$I$30,$A20,C$6),NA())) -> 55860.81 | D20: =IF(B20="",NA(),IFERROR(INDEX('Entrada de Dados Financeiros'!$B$6:$I$30,$A20,D$6),NA())) -> 59747.95 | E20: =IF(B20="",NA(),IFERROR(INDEX('Entrada de Dados Financeiros'!$B$6:$I$30,$A20,E$6),NA())) -> 61483.59 | F20: =IF(B20="",NA(),IFERROR(INDEX('Entrada de Dados Financeiros'!$B$6:$I$30,$A20,F$6),NA())) -> 66272.1 | G20: =IF(B20="",NA(),IFERROR(INDEX('Entrada de Dados Financeiros'!$B$6:$I$30,$A20,G$6),NA())) -> 67474.85
A21: =ROWS($B$15:B21) -> 7 | B21: =IF('Entrada de Dados Financeiros'!B12=0,"",'Entrada de Dados Financeiros'!B12) -> IMPOSTOS | C21: =IF(B21="",NA(),IFERROR(INDEX('Entrada de Dados Financeiros'!$B$6:$I$30,$A21,C$6),NA())) -> 25576.74 | D21: =IF(B21="",NA(),IFERROR(INDEX('Entrada de Dados Financeiros'!$B$6:$I$30,$A21,D$6),NA())) -> 27498.86 | E21: =IF(B21="",NA(),IFERROR(INDEX('Entrada de Dados Financeiros'!$B$6:$I$30,$A21,E$6),NA())) -> 28335.67 | F21: =IF(B21="",NA(),IFERROR(INDEX('Entrada de Dados Financeiros'!$B$6:$I$30,$A21,F$6),NA())) -> 29424.53 | G21: =IF(B21="",NA(),IFERROR(INDEX('Entrada de Dados Financeiros'!$B$6:$I$30,$A21,G$6),NA())) -> 31408.25
A22: =ROWS($B$15:B22) -> 8 | B22: =IF('Entrada de Dados Financeiros'!B13=0,"",'Entrada de Dados Financeiros'!B13) -> LUCRO APÓS DEDUÇÃO DE IMPOSTOS | C22: =IF(B22="",NA(),IFERROR(INDEX('Entrada de Dados Financeiros'!$B$6:$I$30,$A22,C$6),NA())) -> 38418.53 | D22: =IF(B22="",NA(),IFERROR(INDEX('Entrada de Dados Financeiros'!$B$6:$I$30,$A22,D$6),NA())) -> 39895.05 | E22: =IF(B22="",NA(),IFERROR(INDEX('Entrada de Dados Financeiros'!$B$6:$I$30,$A22,E$6),NA())) -> 40607.73 | F22: =IF(B22="",NA(),IFERROR(INDEX('Entrada de Dados Financeiros'!$B$6:$I$30,$A22,F$6),NA())) -> 42438.2 | G22: =IF(B22="",NA(),IFERROR(INDEX('Entrada de Dados Financeiros'!$B$6:$I$30,$A22,G$6),NA())) -> 50247.68
A23: =ROWS($B$15:B23) -> 9 | B23: =IF('Entrada de Dados Financeiros'!B14=0,"",'Entrada de Dados Financeiros'!B14) -> MÉTRICA 1 | C23: =IF(B23="",NA(),IFERROR(INDEX('Entrada de Dados Financeiros'!$B$6:$I$30,$A23,C$6),NA())) -> 13.78 | D23: =IF(B23="",NA(),IFERROR(INDEX('Entrada de Dados Financeiros'!$B$6:$I$30,$A23,D$6),NA())) -> 14.29 | E23: =IF(B23="",NA(),IFERROR(INDEX('Entrada de Dados Financeiros'!$B$6:$I$30,$A23,E$6),NA())) -> 15.57 | F23: =IF(B23="",NA(),IFERROR(INDEX('Entrada de Dados Financeiros'!$B$6:$I$30,$A23,F$6),NA())) -> 16.78 | G23: =IF(B23="",NA(),IFERROR(INDEX('Entrada de Dados Financeiros'!$B$6:$I$30,$A23,G$6),NA())) -> 19.96
A24: =ROWS($B$15:B24) -> 10 | B24: =IF('Entrada de Dados Financeiros'!B15=0,"",'Entrada de Dados Financeiros'!B15) -> MÉTRICA 2 | C24: =IF(B24="",NA(),IFERROR(INDEX('Entrada de Dados Financeiros'!$B$6:$I$30,$A24,C$6),NA())) -> 19.22 | D24: =IF(B24="",NA(),IFERROR(INDEX('Entrada de Dados Financeiros'!$B$6:$I$30,$A24,D$6),NA())) -> 20.17 | E24: =IF(B24="",NA(),IFERROR(INDEX('Entrada de Dados Financeiros'!$B$6:$I$30,$A24,E$6),NA())) -> 20.48 | F24: =IF(B24="",NA(),IFERROR(INDEX('Entrada de Dados Financeiros'!$B$6:$I$30,$A24,F$6),NA())) -> 21.84 | G24: =IF(B24="",NA(),IFERROR(INDEX('Entrada de Dados Financeiros'!$B$6:$I$30,$A24,G$6),NA())) -> 26.01
A25: =ROWS($B$15:B25) -> 11 | B25: =IF('Entrada de Dados Financeiros'!B16=0,"",'Entrada de Dados Financeiros'!B16) -> MÉTRICA 3 | C25: =IF(B25="",NA(),IFERROR(INDEX('Entrada de Dados Financeiros'!$B$6:$I$30,$A25,C$6),NA())) -> 21.87 | D25: =IF(B25="",NA(),IFERROR(INDEX('Entrada de Dados Financeiros'!$B$6:$I$30,$A25,D$6),NA())) -> 23.19 | E25: =IF(B25="",NA(),IFERROR(INDEX('Entrada de Dados Financeiros'!$B$6:$I$30,$A25,E$6),NA())) -> 24.67 | F25: =IF(B25="",NA(),IFERROR(INDEX('Entrada de Dados Financeiros'!$B$6:$I$30,$A25,F$6),NA())) -> 26.39 | G25: =IF(B25="",NA(),IFERROR(INDEX('Entrada de Dados Financeiros'!$B$6:$I$30,$A25,G$6),NA())) -> 31.08
A26: =ROWS($B$15:B26) -> 12 | B26: =IF('Entrada de Dados Financeiros'!B17=0,"",'Entrada de Dados Financeiros'!B17) -> MÉTRICA 4 | C26: =IF(B26="",NA(),IFERROR(INDEX('Entrada de Dados Financeiros'!$B$6:$I$30,$A26,C$6),NA())) -> 12.59 | D26: =IF(B26="",NA(),IFERROR(INDEX('Entrada de Dados Financeiros'!$B$6:$I$30,$A26,D$6),NA())) -> 13.7 | E26: =IF(B26="",NA(),IFERROR(INDEX('Entrada de Dados Financeiros'!$B$6:$I$30,$A26,E$6),NA())) -> 13.76 | F26: =IF(B26="",NA(),IFERROR(INDEX('Entrada de Dados Financeiros'!$B$6:$I$30,$A26,F$6),NA())) -> 14.59 | G26: =IF(B26="",NA(),IFERROR(INDEX('Entrada de Dados Financeiros'!$B$6:$I$30,$A26,G$6),NA())) -> 14.92
... A39: =ROWS($B$15:B39) -> 25 | B39: =IF('Entrada de Dados Financeiros'!B30=0,"",'Entrada de Dados Financeiros'!B30) | C39: =IF(B39="",NA(),IFERROR(INDEX('Entrada de Dados Financeiros'!$B$6:$I$30,$A39,C$6),NA())) -> #N/A | D39: =IF(B39="",NA(),IFERROR(INDEX('Entrada de Dados Financeiros'!$B$6:$I$30,$A39,D$6),NA())) -> #N/A | E39: =IF(B39="",NA(),IFERROR(INDEX('Entrada de Dados Financeiros'!$B$6:$I$30,$A39,E$6),NA())) -> #N/A | F39: =IF(B39="",NA(),IFERROR(INDEX('Entrada de Dados Financeiros'!$B$6:$I$30,$A39,F$6),NA())) -> #N/A | G39: =IF(B39="",NA(),IFERROR(INDEX('Entrada de Dados Financeiros'!$B$6:$I$30,$A39,G$6),NA())) -> #N/A
