Workbook

Sheet CÁLCULO TÍTULOS EXTRAJUDICIAIS
A1: DEMONSTRATIVO DE CÁLCULO *
A2: Devedor
A3: Credor
A4: Data da atualização da dívida (dia/mês/ano) | E4: 40374 | F4: Data da correção monetária (mês/ano) | I4: 40374
A6: n° | B6: Descrição | C6: Data Inicial (dia/mês/ano) | D6: Valor Inicial (R$) | E6: Correção Monetária | G6: Juros Moratórios (a.m.) | H6: Valor Corrigido e Atualizado (R$) | I6: Soma Total em Reais (R$)
E7: Fator Inicial | F7: Fator Final
D8: =SUMIF(D9:D23,">0",D9:D23) -> 125570.88 | G8: 0.01
A9: 1 | B9: Cheque 290238 | C9: 40280 | D9: 40691.22 | E9: =HLOOKUP(YEAR(C9),'Indices TJ'!$A$1:$AZ$13,MONTH(C9)+1) -> 42.45296 | F9: =HLOOKUP(YEAR($I$4),'Indices TJ'!$A$1:$AZ$13,MONTH($I$4)+1) -> 42.899504 | G9: =IF(($E$4-C9)>30,ROUND(($E$4-C9)/30,0)*$G$8,ROUND(($E$4-C9)/30,2)*$G$8) -> 0.03 | H9: =IF(AND(E9<>0,F9<>0),(((D9/E9)*F9))+(((D9/E9)*F9))*G9,D9*(1+G9)) -> 42352.81 | I9: =H9 -> 42352.81
A10: 2 | B10: Cheque 290239 | C10: 40281 | D10: 40000 | E10: =HLOOKUP(YEAR(C10),'Indices TJ'!$A$1:$AZ$13,MONTH(C10)+1) -> 42.45296 | F10: =HLOOKUP(YEAR($I$4),'Indices TJ'!$A$1:$AZ$13,MONTH($I$4)+1) -> 42.899504 | G10: =IF(($E$4-C10)>30,ROUND(($E$4-C10)/30,0)*$G$8,ROUND(($E$4-C10)/30,2)*$G$8) -> 0.03 | H10: =IF(AND(E10<>0,F10<>0),(((D10/E10)*F10))+(((D10/E10)*F10))*G10,D10*(1+G10)) -> 41633.365 | I10: =I9+H10 -> 83986.175 | J10: =((D9/E9)*F9)-D9 -> 428.01303
A11: 3 | B11: DMI - 0-000003036/0183042-1 | C11: 40295 | D11: 43513.58 | E11: =HLOOKUP(YEAR(C11),'Indices TJ'!$A$1:$AZ$13,MONTH(C11)+1) -> 42.45296 | F11: =HLOOKUP(YEAR($I$4),'Indices TJ'!$A$1:$AZ$13,MONTH($I$4)+1) -> 42.899504 | G11: =IF(($E$4-C11)>30,ROUND(($E$4-C11)/30,0)*$G$8,ROUND(($E$4-C11)/30,2)*$G$8) -> 0.03 | H11: =IF(AND(E11<>0,F11<>0),(((D11/E11)*F11))+(((D11/E11)*F11))*G11,D11*(1+G11)) -> 45290.419 | I11: =I10+H11 -> 129276.59 | J11: =((D10/E10)*F10)-D10 -> 420.74239
A12: 4 | B12: Custas Judiciais | C12: 40351 | D12: 1366.08 | E12: =HLOOKUP(YEAR(C12),'Indices TJ'!$A$1:$AZ$13,MONTH(C12)+1) -> 42.946746 | F12: =HLOOKUP(YEAR($I$4),'Indices TJ'!$A$1:$AZ$13,MONTH($I$4)+1) -> 42.899504 | G12: =IF(($E$4-C12)>30,ROUND(($E$4-C12)/30,0)*$G$8,ROUND(($E$4-C12)/30,2)*$G$8) -> 0.0077 | H12: =IF(AND(E12<>0,F12<>0),(((D12/E12)*F12))+(((D12/E12)*F12))*G12,D12*(1+G12)) -> 1375.0845 | I12: =I11+H12 -> 130651.68 | J12: =((D11/E11)*F11)-D11 -> 457.70019
A13: 5 | E13: =HLOOKUP(YEAR(C13),'Indices TJ'!$A$1:$AZ$13,MONTH(C13)+1) -> #N/A | F13: =HLOOKUP(YEAR($I$4),'Indices TJ'!$A$1:$AZ$13,MONTH($I$4)+1) -> 42.899504 | G13: =IF(($E$4-C13)>30,ROUND(($E$4-C13)/30,0)*$G$8,ROUND(($E$4-C13)/30,2)*$G$8) -> 13.46 | H13: =IF(AND(E13<>0,F13<>0),(((D13/E13)*F13))+(((D13/E13)*F13))*G13,D13*(1+G13)) -> #N/A | I13: =I12+H13 -> #N/A | J13: =((D12/E12)*F12)-D12 -> -1.5027064
A14: 6 | E14: =HLOOKUP(YEAR(C14),'Indices TJ'!$A$1:$AZ$13,MONTH(C14)+1) -> #N/A | F14: =HLOOKUP(YEAR($I$4),'Indices TJ'!$A$1:$AZ$13,MONTH($I$4)+1) -> 42.899504 | G14: =IF(($E$4-C14)>30,ROUND(($E$4-C14)/30,0)*$G$8,ROUND(($E$4-C14)/30,2)*$G$8) -> 13.46 | H14: =IF(AND(E14<>0,F14<>0),(((D14/E14)*F14))+(((D14/E14)*F14))*G14,D14*(1+G14)) -> #N/A | I14: =I13+H14 -> #N/A | J14: =((D13/E13)*F13)-D13 -> #N/A
A15: 7 | E15: =HLOOKUP(YEAR(C15),'Indices TJ'!$A$1:$AZ$13,MONTH(C15)+1) -> #N/A | F15: =HLOOKUP(YEAR($I$4),'Indices TJ'!$A$1:$AZ$13,MONTH($I$4)+1) -> 42.899504 | G15: =IF(($E$4-C15)>30,ROUND(($E$4-C15)/30,0)*$G$8,ROUND(($E$4-C15)/30,2)*$G$8) -> 13.46 | H15: =IF(AND(E15<>0,F15<>0),(((D15/E15)*F15))+(((D15/E15)*F15))*G15,D15*(1+G15)) -> #N/A | I15: =I14+H15 -> #N/A | J15: =((D14/E14)*F14)-D14 -> #N/A
A16: 8 | E16: =HLOOKUP(YEAR(C16),'Indices TJ'!$A$1:$AZ$13,MONTH(C16)+1) -> #N/A | F16: =HLOOKUP(YEAR($I$4),'Indices TJ'!$A$1:$AZ$13,MONTH($I$4)+1) -> 42.899504 | G16: =IF(($E$4-C16)>30,ROUND(($E$4-C16)/30,0)*$G$8,ROUND(($E$4-C16)/30,2)*$G$8) -> 13.46 | H16: =IF(AND(E16<>0,F16<>0),(((D16/E16)*F16))+(((D16/E16)*F16))*G16,D16*(1+G16)) -> #N/A | I16: =I15+H16 -> #N/A | J16: =((D15/E15)*F15)-D15 -> #N/A
A17: 9 | E17: =HLOOKUP(YEAR(C17),'Indices TJ'!$A$1:$AZ$13,MONTH(C17)+1) -> #N/A | F17: =HLOOKUP(YEAR($I$4),'Indices TJ'!$A$1:$AZ$13,MONTH($I$4)+1) -> 42.899504 | G17: =IF(($E$4-C17)>30,ROUND(($E$4-C17)/30,0)*$G$8,ROUND(($E$4-C17)/30,2)*$G$8) -> 13.46 | H17: =IF(AND(E17<>0,F17<>0),(((D17/E17)*F17))+(((D17/E17)*F17))*G17,D17*(1+G17)) -> #N/A | I17: =I16+H17 -> #N/A | J17: =((D16/E16)*F16)-D16 -> #N/A
A18: 10 | E18: =HLOOKUP(YEAR(C18),'Indices TJ'!$A$1:$AZ$13,MONTH(C18)+1) -> #N/A | F18: =HLOOKUP(YEAR($I$4),'Indices TJ'!$A$1:$AZ$13,MONTH($I$4)+1) -> 42.899504 | G18: =IF(($E$4-C18)>30,ROUND(($E$4-C18)/30,0)*$G$8,ROUND(($E$4-C18)/30,2)*$G$8) -> 13.46 | H18: =IF(AND(E18<>0,F18<>0),(((D18/E18)*F18))+(((D18/E18)*F18))*G18,D18*(1+G18)) -> #N/A | I18: =I17+H18 -> #N/A | J18: =((D17/E17)*F17)-D17 -> #N/A
A19: 11 | E19: =HLOOKUP(YEAR(C19),'Indices TJ'!$A$1:$AZ$13,MONTH(C19)+1) -> #N/A | F19: =HLOOKUP(YEAR($I$4),'Indices TJ'!$A$1:$AZ$13,MONTH($I$4)+1) -> 42.899504 | G19: =IF(($E$4-C19)>30,ROUND(($E$4-C19)/30,0)*$G$8,ROUND(($E$4-C19)/30,2)*$G$8) -> 13.46 | H19: =IF(AND(E19<>0,F19<>0),(((D19/E19)*F19))+(((D19/E19)*F19))*G19,D19*(1+G19)) -> #N/A | I19: =I18+H19 -> #N/A | J19: =((D18/E18)*F18)-D18 -> #N/A
A20: 12 | E20: =HLOOKUP(YEAR(C20),'Indices TJ'!$A$1:$AZ$13,MONTH(C20)+1) -> #N/A | F20: =HLOOKUP(YEAR($I$4),'Indices TJ'!$A$1:$AZ$13,MONTH($I$4)+1) -> 42.899504 | G20: =IF(($E$4-C20)>30,ROUND(($E$4-C20)/30,0)*$G$8,ROUND(($E$4-C20)/30,2)*$G$8) -> 13.46 | H20: =IF(AND(E20<>0,F20<>0),(((D20/E20)*F20))+(((D20/E20)*F20))*G20,D20*(1+G20)) -> #N/A | I20: =I19+H20 -> #N/A | J20: =((D19/E19)*F19)-D19 -> #N/A
A21: 13 | E21: =HLOOKUP(YEAR(C21),'Indices TJ'!$A$1:$AZ$13,MONTH(C21)+1) -> #N/A | F21: =HLOOKUP(YEAR($I$4),'Indices TJ'!$A$1:$AZ$13,MONTH($I$4)+1) -> 42.899504 | G21: =IF(($E$4-C21)>30,ROUND(($E$4-C21)/30,0)*$G$8,ROUND(($E$4-C21)/30,2)*$G$8) -> 13.46 | H21: =IF(AND(E21<>0,F21<>0),(((D21/E21)*F21))+(((D21/E21)*F21))*G21,D21*(1+G21)) -> #N/A | I21: =I20+H21 -> #N/A | J21: =((D20/E20)*F20)-D20 -> #N/A
A22: 14 | E22: =HLOOKUP(YEAR(C22),'Indices TJ'!$A$1:$AZ$13,MONTH(C22)+1) -> #N/A | F22: =HLOOKUP(YEAR($I$4),'Indices TJ'!$A$1:$AZ$13,MONTH($I$4)+1) -> 42.899504 | G22: =IF(($E$4-C22)>30,ROUND(($E$4-C22)/30,0)*$G$8,ROUND(($E$4-C22)/30,2)*$G$8) -> 13.46 | H22: =IF(AND(E22<>0,F22<>0),(((D22/E22)*F22))+(((D22/E22)*F22))*G22,D22*(1+G22)) -> #N/A | I22: =I21+H22 -> #N/A | J22: =((D21/E21)*F21)-D21 -> #N/A
A23: 15 | E23: =HLOOKUP(YEAR(C23),'Indices TJ'!$A$1:$AZ$13,MONTH(C23)+1) -> #N/A | F23: =HLOOKUP(YEAR($I$4),'Indices TJ'!$A$1:$AZ$13,MONTH($I$4)+1) -> 42.899504 | G23: =IF(($E$4-C23)>30,ROUND(($E$4-C23)/30,0)*$G$8,ROUND(($E$4-C23)/30,2)*$G$8) -> 13.46 | H23: =IF(AND(E23<>0,F23<>0),(((D23/E23)*F23))+(((D23/E23)*F23))*G23,D23*(1+G23)) -> #N/A | I23: =I22+H23 -> #N/A | J23: =((D22/E22)*F22)-D22 -> #N/A
A24: Totais em Reais (R$) | D24: Atualização(R$) | E24: =(SUMIF($J$10:$J$24,">0",$J$10:$J$24)) -> 1306.4556 | F24: Juros (R$) | G24: =(H24-D8)-E24 -> 3774.3422 | H24: =SUMIF(H9:H23,">0",H9:H23) -> 130651.68 | J24: =((D23/E23)*F23)-D23 -> #N/A
A25: Multa moratória | G25: 0 | H25: =G25*H24 -> 0 | I25: =H24+H25 -> 130651.68
A26: DESCONTO | G26: 0 | H26: =G26*H24 -> 0 | I26: =I25-H26 -> 130651.68
A27: Honorários advocatícios | G27: 0.05 | H27: =G27*I26 -> 6532.5839 | I27: =I26+H27 -> 137184.26
A28: Despesas extras com a cobrança em Reais (R$) | I28: =I27+H28 -> 137184.26
A29: VALOR DA DÍVIDA EM: | G29: =E4 -> 40374 | H29: =I28 -> 137184.26
A30: * Correção monetária seguindo tabela praticada pelo Tribunal de Justiça do Estado de São Paulo. - www.tj.sp.gov.br
A32: PARCELAMENTO DA DÍVIDA
A33: Valor a ser parcelado | C33: Abatimento / desconto ( - ) | D33: Valor deduzido abatimento/desconto | F33: Número de Parcelas | G33: Juros Mensais | H33: Valor da parcela mensal (fixa)
A34: 136865.95 | C34: 0 | D34: =A34-C34 -> 136865.95 | F34: 10 | G34: 0.005 | H34: =((D34*(F34*G34)+D34))/(((G34*(F34-1)/2)+1)*F34) -> 14054.694
A35: VALOR TOTAL PARCELADO | H35: =F34*H34 -> 140546.94
A37: Observação: Para atualizar o valor, basta dividir o valor a atualizar (observar o padrão monetário vigente à época) pelo fator do mês do termo inicial e multiplicar pelo fator do mês do termo final, obtendo-se o resultado na moeda vigente na data do termo final, não sendo necessário efetuar qualquer conversão. Os juros morátorios são aplicados sobre o valor atualizado.

Sheet CÁLCULO TÍTULOS JUDICIAIS
A1: DEMONSTRATIVO DE CÁLCULO * | I1: DEMONSTRATIVO DE CÁLCULO * | Q1: DEMONSTRATIVO DE CÁLCULO * | Y1: DEMONSTRATIVO DE CÁLCULO * | AG1: DEMONSTRATIVO DE CÁLCULO * | AO1: DEMONSTRATIVO DE CÁLCULO * | AW1: DEMONSTRATIVO DE CÁLCULO * | BE1: DEMONSTRATIVO DE CÁLCULO * | BM1: DEMONSTRATIVO DE CÁLCULO * | BU1: DEMONSTRATIVO DE CÁLCULO * | CC1: DEMONSTRATIVO DE CÁLCULO * | CK1: DEMONSTRATIVO DE CÁLCULO * | CS1: DEMONSTRATIVO DE CÁLCULO * | DA1: DEMONSTRATIVO DE CÁLCULO * | DI1: DEMONSTRATIVO DE CÁLCULO * | DQ1: DEMONSTRATIVO DE CÁLCULO * | DY1: DEMONSTRATIVO DE CÁLCULO * | EG1: DEMONSTRATIVO DE CÁLCULO * | EO1: DEMONSTRATIVO DE CÁLCULO * | EW1: DEMONSTRATIVO DE CÁLCULO * | FE1: DEMONSTRATIVO DE CÁLCULO * | FM1: DEMONSTRATIVO DE CÁLCULO * | FU1: DEMONSTRATIVO DE CÁLCULO * | GC1: DEMONSTRATIVO DE CÁLCULO * | GK1: DEMONSTRATIVO DE CÁLCULO * | GS1: DEMONSTRATIVO DE CÁLCULO * | HA1: DEMONSTRATIVO DE CÁLCULO * | HI1: DEMONSTRATIVO DE CÁLCULO * | HQ1: DEMONSTRATIVO DE CÁLCULO * | HY1: DEMONSTRATIVO DE CÁLCULO * | IG1: DEMONSTRATIVO DE CÁLCULO * | IO1: DEMONSTRATIVO DE CÁLCULO *
A2: Data da atualização da dívida (mês/ano) | E2: 40374 | I2: * Correção monetária seguindo tabela praticada pelo Tribunal de Justiça do Estado de São Paulo.
A3: n° | B3: Data Inicial | C3: Valor Inicial | D3: Correção Monetária | F3: Juros Moratórios (a.m.) | G3: Valor Corrigido e Atualizado (R$) | H3: Soma Total em Reais (R$)
D4: Fator Inicial | E4: Fator Final | I4: Para calcular basta dividir o valor a atualizar (observar o padrão monetário vigente à época) pelo fator do mês do termo inicial e multiplicar pelo fator do mês do termo final, obtendo-se o resultado na moeda vigente na data do termo final, não sendo necessário efetuar qualquer conversão.
C5: =SUMIF(C6:C104,"<>0",C6:C104) -> 9000 | F5: 0.01
A6: 1 | B6: 39979 | C6: 3000 | D6: =HLOOKUP(YEAR(B6),'Indices TJ'!$A$1:$AZ$13,MONTH(B6)+1) -> 40.780757 | E6: =HLOOKUP(YEAR($E$2),'Indices TJ'!$A$1:$AZ$13,MONTH($E$2)+1) -> 42.899504 | F6: =IF(($E$2-B6)>30,ROUND(($E$2-B6)/30,0)*$F$5,0) -> 0.13 | G6: =(((C6/D6)*E6))+(((C6/D6)*E6))*F6 -> 3566.126 | H6: =G6 -> 3566.126
A7: 2 | B7: 40009 | C7: 3000 | D7: =HLOOKUP(YEAR(B7),'Indices TJ'!$A$1:$AZ$13,MONTH(B7)+1) -> 40.952036 | E7: =HLOOKUP(YEAR($E$2),'Indices TJ'!$A$1:$AZ$13,MONTH($E$2)+1) -> 42.899504 | F7: =IF(($E$2-B7)>30,ROUND(($E$2-B7)/30,0)*$F$5,0) -> 0.12 | G7: =(((C7/D7)*E7))+(((C7/D7)*E7))*F7 -> 3519.7843 | H7: =H6+G7 -> 7085.9103
A8: 3 | B8: 39949 | C8: 3000 | D8: =HLOOKUP(YEAR(B8),'Indices TJ'!$A$1:$AZ$13,MONTH(B8)+1) -> 40.537532 | E8: =HLOOKUP(YEAR($E$2),'Indices TJ'!$A$1:$AZ$13,MONTH($E$2)+1) -> 42.899504 | F8: =IF(($E$2-B8)>30,ROUND(($E$2-B8)/30,0)*$F$5,0) -> 0.14 | G8: =(((C8/D8)*E8))+(((C8/D8)*E8))*F8 -> 3619.2707 | H8: =H7+G8 -> 10705.181
A9: 4 | D9: =HLOOKUP(YEAR(B9),'Indices TJ'!$A$1:$AZ$13,MONTH(B9)+1) -> #N/A | E9: =HLOOKUP(YEAR($E$2),'Indices TJ'!$A$1:$AZ$13,MONTH($E$2)+1) -> 42.899504 | F9: =IF(($E$2-B9)>30,ROUND(($E$2-B9)/30,0)*$F$5,0) -> 13.46 | G9: =(((C9/D9)*E9))+(((C9/D9)*E9))*F9 -> #N/A | H9: =H8+G9 -> #N/A
A10: 5 | D10: =HLOOKUP(YEAR(B10),'Indices TJ'!$A$1:$AZ$13,MONTH(B10)+1) -> #N/A | E10: =HLOOKUP(YEAR($E$2),'Indices TJ'!$A$1:$AZ$13,MONTH($E$2)+1) -> 42.899504 | F10: =IF(($E$2-B10)>30,ROUND(($E$2-B10)/30,0)*$F$5,0) -> 13.46 | G10: =(((C10/D10)*E10))+(((C10/D10)*E10))*F10 -> #N/A | H10: =H9+G10 -> #N/A | I10: =AND(E6>0,C6>0) -> TRUE
A11: 6 | D11: =HLOOKUP(YEAR(B11),'Indices TJ'!$A$1:$AZ$13,MONTH(B11)+1) -> #N/A | E11: =HLOOKUP(YEAR($E$2),'Indices TJ'!$A$1:$AZ$13,MONTH($E$2)+1) -> 42.899504 | F11: =IF(($E$2-B11)>30,ROUND(($E$2-B11)/30,0)*$F$5,0) -> 13.46 | G11: =(((C11/D11)*E11))+(((C11/D11)*E11))*F11 -> #N/A | H11: =H10+G11 -> #N/A
A12: 7 | D12: =HLOOKUP(YEAR(B12),'Indices TJ'!$A$1:$AZ$13,MONTH(B12)+1) -> #N/A | E12: =HLOOKUP(YEAR($E$2),'Indices TJ'!$A$1:$AZ$13,MONTH($E$2)+1) -> 42.899504 | F12: =IF(($E$2-B12)>30,ROUND(($E$2-B12)/30,0)*$F$5,0) -> 13.46 | G12: =(((C12/D12)*E12))+(((C12/D12)*E12))*F12 -> #N/A | H12: =H11+G12 -> #N/A
A13: 8 | D13: =HLOOKUP(YEAR(B13),'Indices TJ'!$A$1:$AZ$13,MONTH(B13)+1) -> #N/A | E13: =HLOOKUP(YEAR($E$2),'Indices TJ'!$A$1:$AZ$13,MONTH($E$2)+1) -> 42.899504 | F13: =IF(($E$2-B13)>30,ROUND(($E$2-B13)/30,0)*$F$5,0) -> 13.46 | G13: =(((C13/D13)*E13))+(((C13/D13)*E13))*F13 -> #N/A | H13: =H12+G13 -> #N/A
A14: 9 | D14: =HLOOKUP(YEAR(B14),'Indices TJ'!$A$1:$AZ$13,MONTH(B14)+1) -> #N/A | E14: =HLOOKUP(YEAR($E$2),'Indices TJ'!$A$1:$AZ$13,MONTH($E$2)+1) -> 42.899504 | F14: =IF(($E$2-B14)>30,ROUND(($E$2-B14)/30,0)*$F$5,0) -> 13.46 | G14: =(((C14/D14)*E14))+(((C14/D14)*E14))*F14 -> #N/A | H14: =H13+G14 -> #N/A
A15: 10 | D15: =HLOOKUP(YEAR(B15),'Indices TJ'!$A$1:$AZ$13,MONTH(B15)+1) -> #N/A | E15: =HLOOKUP(YEAR($E$2),'Indices TJ'!$A$1:$AZ$13,MONTH($E$2)+1) -> 42.899504 | F15: =IF(($E$2-B15)>30,ROUND(($E$2-B15)/30,0)*$F$5,0) -> 13.46 | G15: =(((C15/D15)*E15))+(((C15/D15)*E15))*F15 -> #N/A | H15: =H14+G15 -> #N/A
A16: 11 | D16: =HLOOKUP(YEAR(B16),'Indices TJ'!$A$1:$AZ$13,MONTH(B16)+1) -> #N/A | E16: =HLOOKUP(YEAR($E$2),'Indices TJ'!$A$1:$AZ$13,MONTH($E$2)+1) -> 42.899504 | F16: =IF(($E$2-B16)>30,ROUND(($E$2-B16)/30,0)*$F$5,0) -> 13.46 | G16: =(((C16/D16)*E16))+(((C16/D16)*E16))*F16 -> #N/A | H16: =H15+G16 -> #N/A
A17: 12 | D17: =HLOOKUP(YEAR(B17),'Indices TJ'!$A$1:$AZ$13,MONTH(B17)+1) -> #N/A | E17: =HLOOKUP(YEAR($E$2),'Indices TJ'!$A$1:$AZ$13,MONTH($E$2)+1) -> 42.899504 | F17: =IF(($E$2-B17)>30,ROUND(($E$2-B17)/30,0)*$F$5,0) -> 13.46 | G17: =(((C17/D17)*E17))+(((C17/D17)*E17))*F17 -> #N/A | H17: =H16+G17 -> #N/A
A18: 13 | D18: =HLOOKUP(YEAR(B18),'Indices TJ'!$A$1:$AZ$13,MONTH(B18)+1) -> #N/A | E18: =HLOOKUP(YEAR($E$2),'Indices TJ'!$A$1:$AZ$13,MONTH($E$2)+1) -> 42.899504 | F18: =IF(($E$2-B18)>30,ROUND(($E$2-B18)/30,0)*$F$5,0) -> 13.46 | G18: =(((C18/D18)*E18))+(((C18/D18)*E18))*F18 -> #N/A | H18: =H17+G18 -> #N/A
A19: 14 | D19: =HLOOKUP(YEAR(B19),'Indices TJ'!$A$1:$AZ$13,MONTH(B19)+1) -> #N/A | E19: =HLOOKUP(YEAR($E$2),'Indices TJ'!$A$1:$AZ$13,MONTH($E$2)+1) -> 42.899504 | F19: =IF(($E$2-B19)>30,ROUND(($E$2-B19)/30,0)*$F$5,0) -> 13.46 | G19: =(((C19/D19)*E19))+(((C19/D19)*E19))*F19 -> #N/A | H19: =H18+G19 -> #N/A
A20: 15 | D20: =HLOOKUP(YEAR(B20),'Indices TJ'!$A$1:$AZ$13,MONTH(B20)+1) -> #N/A | E20: =HLOOKUP(YEAR($E$2),'Indices TJ'!$A$1:$AZ$13,MONTH($E$2)+1) -> 42.899504 | F20: =IF(($E$2-B20)>30,ROUND(($E$2-B20)/30,0)*$F$5,0) -> 13.46 | G20: =(((C20/D20)*E20))+(((C20/D20)*E20))*F20 -> #N/A | H20: =H19+G20 -> #N/A
A21: 16 | D21: =HLOOKUP(YEAR(B21),'Indices TJ'!$A$1:$AZ$13,MONTH(B21)+1) -> #N/A | E21: =HLOOKUP(YEAR($E$2),'Indices TJ'!$A$1:$AZ$13,MONTH($E$2)+1) -> 42.899504 | F21: =IF(($E$2-B21)>30,ROUND(($E$2-B21)/30,0)*$F$5,0) -> 13.46 | G21: =(((C21/D21)*E21))+(((C21/D21)*E21))*F21 -> #N/A | H21: =H20+G21 -> #N/A
A22: 17 | D22: =HLOOKUP(YEAR(B22),'Indices TJ'!$A$1:$AZ$13,MONTH(B22)+1) -> #N/A | E22: =HLOOKUP(YEAR($E$2),'Indices TJ'!$A$1:$AZ$13,MONTH($E$2)+1) -> 42.899504 | F22: =IF(($E$2-B22)>30,ROUND(($E$2-B22)/30,0)*$F$5,0) -> 13.46 | G22: =(((C22/D22)*E22))+(((C22/D22)*E22))*F22 -> #N/A | H22: =H21+G22 -> #N/A
... A29: 24 | D29: =HLOOKUP(YEAR(B29),'Indices TJ'!$A$1:$AZ$13,MONTH(B29)+1) -> #N/A | E29: =HLOOKUP(YEAR($E$2),'Indices TJ'!$A$1:$AZ$13,MONTH($E$2)+1) -> 42.899504 | F29: =IF(($E$2-B29)>30,ROUND(($E$2-B29)/30,0)*$F$5,0) -> 13.46 | G29: =(((C29/D29)*E29))+(((C29/D29)*E29))*F29 -> #N/A | H29: =H28+G29 -> #N/A
A30: 25 | D30: =HLOOKUP(YEAR(B30),'Indices TJ'!$A$1:$AZ$13,MONTH(B30)+1) -> #N/A | E30: =HLOOKUP(YEAR($E$2),'Indices TJ'!$A$1:$AZ$13,MONTH($E$2)+1) -> 42.899504 | F30: =IF(($E$2-B35)>30,ROUND(($E$2-B35)/30,0)*$F$5,0) -> 13.46 | G30: =(((C30/D30)*E30))+(((C30/D30)*E30))*F30 -> #N/A | H30: =H29+G30 -> #N/A
A31: 26 | D31: =HLOOKUP(YEAR(B31),'Indices TJ'!$A$1:$AZ$13,MONTH(B31)+1) -> #N/A | E31: =HLOOKUP(YEAR($E$2),'Indices TJ'!$A$1:$AZ$13,MONTH($E$2)+1) -> 42.899504 | F31: =IF(($E$2-B36)>30,ROUND(($E$2-B36)/30,0)*$F$5,0) -> 13.46 | G31: =(((C31/D31)*E31))+(((C31/D31)*E31))*F31 -> #N/A | H31: =H30+G31 -> #N/A
A32: 27 | D32: =HLOOKUP(YEAR(B32),'Indices TJ'!$A$1:$AZ$13,MONTH(B32)+1) -> #N/A | E32: =HLOOKUP(YEAR($E$2),'Indices TJ'!$A$1:$AZ$13,MONTH($E$2)+1) -> 42.899504 | F32: =IF(($E$2-B32)>30,ROUND(($E$2-B32)/30,0)*$F$5,0) -> 13.46 | G32: =(((C32/D32)*E32))+(((C32/D32)*E32))*F32 -> #N/A | H32: =H31+G32 -> #N/A
A33: 28 | D33: =HLOOKUP(YEAR(B33),'Indices TJ'!$A$1:$AZ$13,MONTH(B33)+1) -> #N/A | E33: =HLOOKUP(YEAR($E$2),'Indices TJ'!$A$1:$AZ$13,MONTH($E$2)+1) -> 42.899504 | F33: =IF(($E$2-B33)>30,ROUND(($E$2-B33)/30,0)*$F$5,0) -> 13.46 | G33: =(((C33/D33)*E33))+(((C33/D33)*E33))*F33 -> #N/A | H33: =H32+G33 -> #N/A
A34: 29 | D34: =HLOOKUP(YEAR(B34),'Indices TJ'!$A$1:$AZ$13,MONTH(B34)+1) -> #N/A | E34: =HLOOKUP(YEAR($E$2),'Indices TJ'!$A$1:$AZ$13,MONTH($E$2)+1) -> 42.899504 | F34: =IF(($E$2-B34)>30,ROUND(($E$2-B34)/30,0)*$F$5,0) -> 13.46 | G34: =(((C34/D34)*E34))+(((C34/D34)*E34))*F34 -> #N/A | H34: =H33+G34 -> #N/A
A35: 30 | D35: =HLOOKUP(YEAR(B35),'Indices TJ'!$A$1:$AZ$13,MONTH(B35)+1) -> #N/A | E35: =HLOOKUP(YEAR($E$2),'Indices TJ'!$A$1:$AZ$13,MONTH($E$2)+1) -> 42.899504 | F35: =IF(($E$2-B35)>30,ROUND(($E$2-B35)/30,0)*$F$5,0) -> 13.46 | G35: =(((C35/D35)*E35))+(((C35/D35)*E35))*F35 -> #N/A | H35: =H34+G35 -> #N/A
A36: 31 | D36: =HLOOKUP(YEAR(B36),'Indices TJ'!$A$1:$AZ$13,MONTH(B36)+1) -> #N/A | E36: =HLOOKUP(YEAR($E$2),'Indices TJ'!$A$1:$AZ$13,MONTH($E$2)+1) -> 42.899504 | F36: =IF(($E$2-B36)>30,ROUND(($E$2-B36)/30,0)*$F$5,0) -> 13.46 | G36: =(((C36/D36)*E36))+(((C36/D36)*E36))*F36 -> #N/A | H36: =H35+G36 -> #N/A
A37: 32 | D37: =HLOOKUP(YEAR(B37),'Indices TJ'!$A$1:$AZ$13,MONTH(B37)+1) -> #N/A | E37: =HLOOKUP(YEAR($E$2),'Indices TJ'!$A$1:$AZ$13,MONTH($E$2)+1) -> 42.899504 | F37: =IF(($E$2-B37)>30,ROUND(($E$2-B37)/30,0)*$F$5,0) -> 13.46 | G37: =(((C37/D37)*E37))+(((C37/D37)*E37))*F37 -> #N/A | H37: =H36+G37 -> #N/A
A38: 33 | D38: =HLOOKUP(YEAR(B38),'Indices TJ'!$A$1:$AZ$13,MONTH(B38)+1) -> #N/A | E38: =HLOOKUP(YEAR($E$2),'Indices TJ'!$A$1:$AZ$13,MONTH($E$2)+1) -> 42.899504 | F38: =IF(($E$2-B38)>30,ROUND(($E$2-B38)/30,0)*$F$5,0) -> 13.46 | G38: =(((C38/D38)*E38))+(((C38/D38)*E38))*F38 -> #N/A | H38: =H37+G38 -> #N/A
A39: 34 | D39: =HLOOKUP(YEAR(B39),'Indices TJ'!$A$1:$AZ$13,MONTH(B39)+1) -> #N/A | E39: =HLOOKUP(YEAR($E$2),'Indices TJ'!$A$1:$AZ$13,MONTH($E$2)+1) -> 42.899504 | F39: =IF(($E$2-B39)>30,ROUND(($E$2-B39)/30,0)*$F$5,0) -> 13.46 | G39: =(((C39/D39)*E39))+(((C39/D39)*E39))*F39 -> #N/A | H39: =H38+G39 -> #N/A
A40: 35 | D40: =HLOOKUP(YEAR(B40),'Indices TJ'!$A$1:$AZ$13,MONTH(B40)+1) -> #N/A | E40: =HLOOKUP(YEAR($E$2),'Indices TJ'!$A$1:$AZ$13,MONTH($E$2)+1) -> 42.899504 | F40: =IF(($E$2-B40)>30,ROUND(($E$2-B40)/30,0)*$F$5,0) -> 13.46 | G40: =(((C40/D40)*E40))+(((C40/D40)*E40))*F40 -> #N/A | H40: =H39+G40 -> #N/A
A41: 36 | D41: =HLOOKUP(YEAR(B41),'Indices TJ'!$A$1:$AZ$13,MONTH(B41)+1) -> #N/A | E41: =HLOOKUP(YEAR($E$2),'Indices TJ'!$A$1:$AZ$13,MONTH($E$2)+1) -> 42.899504 | F41: =IF(($E$2-B41)>30,ROUND(($E$2-B41)/30,0)*$F$5,0) -> 13.46 | G41: =(((C41/D41)*E41))+(((C41/D41)*E41))*F41 -> #N/A | H41: =H40+G41 -> #N/A
A42: 37 | D42: =HLOOKUP(YEAR(B42),'Indices TJ'!$A$1:$AZ$13,MONTH(B42)+1) -> #N/A | E42: =HLOOKUP(YEAR($E$2),'Indices TJ'!$A$1:$AZ$13,MONTH($E$2)+1) -> 42.899504 | F42: =IF(($E$2-B42)>30,ROUND(($E$2-B42)/30,0)*$F$5,0) -> 13.46 | G42: =(((C42/D42)*E42))+(((C42/D42)*E42))*F42 -> #N/A | H42: =H41+G42 -> #N/A
A43: 38 | D43: =HLOOKUP(YEAR(B43),'Indices TJ'!$A$1:$AZ$13,MONTH(B43)+1) -> #N/A | E43: =HLOOKUP(YEAR($E$2),'Indices TJ'!$A$1:$AZ$13,MONTH($E$2)+1) -> 42.899504 | F43: =IF(($E$2-B43)>30,ROUND(($E$2-B43)/30,0)*$F$5,0) -> 13.46 | G43: =(((C43/D43)*E43))+(((C43/D43)*E43))*F43 -> #N/A | H43: =H42+G43 -> #N/A
... A104: 99 | D104: =HLOOKUP(YEAR(B104),'Indices TJ'!$A$1:$AZ$13,MONTH(B104)+1) -> #N/A | E104: =HLOOKUP(YEAR($E$2),'Indices TJ'!$A$1:$AZ$13,MONTH($E$2)+1) -> 42.899504 | F104: =IF(($E$2-B104)>30,ROUND(($E$2-B104)/30,0)*$F$5,0) -> 13.46 | G104: =(((C104/D104)*E104))+(((C104/D104)*E104))*F104 -> #N/A | H104: =H103+G104 -> #N/A

Sheet CALC. TÍT.JUDIC. # DATA JUROS M
A1: DEMONSTRATIVO DE CÁLCULO * | J1: * Correção monetária seguindo tabela praticada pelo Tribunal de Justiça do Estado de São Paulo.
A2: Data da atualização da dívida (mês/ano) | E2: 40374
A3: n° | B3: Data Inicial (mês/ano) (correção monetária) | C3: Valor Inicial | D3: Correção Monetária | F3: Juros Moratórios (a.m.) | H3: Valor Corrigido e Atualizado (R$) | I3: Soma Total em Reais (R$) | J3: Para calcular basta dividir o valor a atualizar (observar o padrão monetário vigente à época) pelo fator do mês do termo inicial e multiplicar pelo fator do mês do termo final, obtendo-se o resultado na moeda vigente na data do termo final, não sendo nec
D4: Fator Inicial | E4: Fator Final | F4: Data Inicial (mês/ano) (juros moratórios) | G4: 0.01
C5: =SUMIF(C6:C104,"<>0",C6:C104) -> 9946.54
A6: 1 | B6: 40026 | C6: 10500 | D6: =HLOOKUP(YEAR(B6),'Indices TJ'!$A$1:$AZ$13,MONTH(B6)+1) -> 41.046225 | E6: =HLOOKUP(YEAR($E$2),'Indices TJ'!$A$1:$AZ$13,MONTH($E$2)+1) -> 42.899504 | F6: 40118 | G6: =IF(($E$2-F6)>30,ROUND(($E$2-F6)/30,0)*$G$4,ROUND(($E$2-F6)/30,2)*$G$4) -> 0.09 | H6: =(((C6/D6)*E6))+(((C6/D6)*E6))*G6 -> 11961.753 | I6: =H6 -> 11961.753
A7: 2 | B7: 40330 | C7: -553.46 | D7: =HLOOKUP(YEAR(B7),'Indices TJ'!$A$1:$AZ$13,MONTH(B7)+1) -> 42.946746 | E7: =HLOOKUP(YEAR($E$2),'Indices TJ'!$A$1:$AZ$13,MONTH($E$2)+1) -> 42.899504 | F7: 40344 | G7: =IF(($E$2-F7)>30,ROUND(($E$2-F7)/30,0)*$G$4,ROUND(($E$2-F7)/30,2)*$G$4) -> 0.01 | H7: =(((C7/D7)*E7))+(((C7/D7)*E7))*G7 -> -558.3797 | I7: =I6+H7 -> 11403.374
A8: 3 | D8: =HLOOKUP(YEAR(B8),'Indices TJ'!$A$1:$AZ$13,MONTH(B8)+1) -> #N/A | E8: =HLOOKUP(YEAR($E$2),'Indices TJ'!$A$1:$AZ$13,MONTH($E$2)+1) -> 42.899504 | G8: =IF(($E$2-F8)>30,ROUND(($E$2-F8)/30,0)*$G$4,ROUND(($E$2-F8)/30,2)*$G$4) -> 13.46 | H8: =(((C8/D8)*E8))+(((C8/D8)*E8))*G8 -> #N/A | I8: =I7+H8 -> #N/A
A9: 4 | D9: =HLOOKUP(YEAR(B9),'Indices TJ'!$A$1:$AZ$13,MONTH(B9)+1) -> #N/A | E9: =HLOOKUP(YEAR($E$2),'Indices TJ'!$A$1:$AZ$13,MONTH($E$2)+1) -> 42.899504 | G9: =IF(($E$2-F9)>30,ROUND(($E$2-F9)/30,0)*$G$4,ROUND(($E$2-F9)/30,2)*$G$4) -> 13.46 | H9: =(((C9/D9)*E9))+(((C9/D9)*E9))*G9 -> #N/A | I9: =I8+H9 -> #N/A | J9: =AND(E6>0,C6>0) -> TRUE
A10: 5 | D10: =HLOOKUP(YEAR(B10),'Indices TJ'!$A$1:$AZ$13,MONTH(B10)+1) -> #N/A | E10: =HLOOKUP(YEAR($E$2),'Indices TJ'!$A$1:$AZ$13,MONTH($E$2)+1) -> 42.899504 | G10: =IF(($E$2-F10)>30,ROUND(($E$2-F10)/30,0)*$G$4,ROUND(($E$2-F10)/30,2)*$G$4) -> 13.46 | H10: =(((C10/D10)*E10))+(((C10/D10)*E10))*G10 -> #N/A | I10: =I9+H10 -> #N/A
A11: 6 | D11: =HLOOKUP(YEAR(B11),'Indices TJ'!$A$1:$AZ$13,MONTH(B11)+1) -> #N/A | E11: =HLOOKUP(YEAR($E$2),'Indices TJ'!$A$1:$AZ$13,MONTH($E$2)+1) -> 42.899504 | G11: =IF(($E$2-F11)>30,ROUND(($E$2-F11)/30,0)*$G$4,ROUND(($E$2-F11)/30,2)*$G$4) -> 13.46 | H11: =(((C11/D11)*E11))+(((C11/D11)*E11))*G11 -> #N/A | I11: =I10+H11 -> #N/A
A12: 7 | D12: =HLOOKUP(YEAR(B12),'Indices TJ'!$A$1:$AZ$13,MONTH(B12)+1) -> #N/A | E12: =HLOOKUP(YEAR($E$2),'Indices TJ'!$A$1:$AZ$13,MONTH($E$2)+1) -> 42.899504 | G12: =IF(($E$2-F12)>30,ROUND(($E$2-F12)/30,0)*$G$4,ROUND(($E$2-F12)/30,2)*$G$4) -> 13.46 | H12: =(((C12/D12)*E12))+(((C12/D12)*E12))*G12 -> #N/A | I12: =I11+H12 -> #N/A
A13: 8 | D13: =HLOOKUP(YEAR(B13),'Indices TJ'!$A$1:$AZ$13,MONTH(B13)+1) -> #N/A | E13: =HLOOKUP(YEAR($E$2),'Indices TJ'!$A$1:$AZ$13,MONTH($E$2)+1) -> 42.899504 | G13: =IF(($E$2-F13)>30,ROUND(($E$2-F13)/30,0)*$G$4,ROUND(($E$2-F13)/30,2)*$G$4) -> 13.46 | H13: =(((C13/D13)*E13))+(((C13/D13)*E13))*G13 -> #N/A | I13: =I12+H13 -> #N/A
A14: 9 | D14: =HLOOKUP(YEAR(B14),'Indices TJ'!$A$1:$AZ$13,MONTH(B14)+1) -> #N/A | E14: =HLOOKUP(YEAR($E$2),'Indices TJ'!$A$1:$AZ$13,MONTH($E$2)+1) -> 42.899504 | G14: =IF(($E$2-F14)>30,ROUND(($E$2-F14)/30,0)*$G$4,ROUND(($E$2-F14)/30,2)*$G$4) -> 13.46 | H14: =(((C14/D14)*E14))+(((C14/D14)*E14))*G14 -> #N/A | I14: =I13+H14 -> #N/A
A15: 10 | D15: =HLOOKUP(YEAR(B15),'Indices TJ'!$A$1:$AZ$13,MONTH(B15)+1) -> #N/A | E15: =HLOOKUP(YEAR($E$2),'Indices TJ'!$A$1:$AZ$13,MONTH($E$2)+1) -> 42.899504 | G15: =IF(($E$2-F15)>30,ROUND(($E$2-F15)/30,0)*$G$4,ROUND(($E$2-F15)/30,2)*$G$4) -> 13.46 | H15: =(((C15/D15)*E15))+(((C15/D15)*E15))*G15 -> #N/A | I15: =I14+H15 -> #N/A
A16: 11 | D16: =HLOOKUP(YEAR(B16),'Indices TJ'!$A$1:$AZ$13,MONTH(B16)+1) -> #N/A | E16: =HLOOKUP(YEAR($E$2),'Indices TJ'!$A$1:$AZ$13,MONTH($E$2)+1) -> 42.899504 | G16: =IF(($E$2-F16)>30,ROUND(($E$2-F16)/30,0)*$G$4,ROUND(($E$2-F16)/30,2)*$G$4) -> 13.46 | H16: =(((C16/D16)*E16))+(((C16/D16)*E16))*G16 -> #N/A | I16: =I15+H16 -> #N/A
A17: 12 | D17: =HLOOKUP(YEAR(B17),'Indices TJ'!$A$1:$AZ$13,MONTH(B17)+1) -> #N/A | E17: =HLOOKUP(YEAR($E$2),'Indices TJ'!$A$1:$AZ$13,MONTH($E$2)+1) -> 42.899504 | G17: =IF(($E$2-F17)>30,ROUND(($E$2-F17)/30,0)*$G$4,ROUND(($E$2-F17)/30,2)*$G$4) -> 13.46 | H17: =(((C17/D17)*E17))+(((C17/D17)*E17))*G17 -> #N/A | I17: =I16+H17 -> #N/A
A18: 13 | D18: =HLOOKUP(YEAR(B18),'Indices TJ'!$A$1:$AZ$13,MONTH(B18)+1) -> #N/A | E18: =HLOOKUP(YEAR($E$2),'Indices TJ'!$A$1:$AZ$13,MONTH($E$2)+1) -> 42.899504 | G18: =IF(($E$2-F18)>30,ROUND(($E$2-F18)/30,0)*$G$4,ROUND(($E$2-F18)/30,2)*$G$4) -> 13.46 | H18: =(((C18/D18)*E18))+(((C18/D18)*E18))*G18 -> #N/A | I18: =I17+H18 -> #N/A
A19: 14 | D19: =HLOOKUP(YEAR(B19),'Indices TJ'!$A$1:$AZ$13,MONTH(B19)+1) -> #N/A | E19: =HLOOKUP(YEAR($E$2),'Indices TJ'!$A$1:$AZ$13,MONTH($E$2)+1) -> 42.899504 | G19: =IF(($E$2-F19)>30,ROUND(($E$2-F19)/30,0)*$G$4,ROUND(($E$2-F19)/30,2)*$G$4) -> 13.46 | H19: =(((C19/D19)*E19))+(((C19/D19)*E19))*G19 -> #N/A | I19: =I18+H19 -> #N/A
A20: 15 | D20: =HLOOKUP(YEAR(B20),'Indices TJ'!$A$1:$AZ$13,MONTH(B20)+1) -> #N/A | E20: =HLOOKUP(YEAR($E$2),'Indices TJ'!$A$1:$AZ$13,MONTH($E$2)+1) -> 42.899504 | G20: =IF(($E$2-F20)>30,ROUND(($E$2-F20)/30,0)*$G$4,ROUND(($E$2-F20)/30,2)*$G$4) -> 13.46 | H20: =(((C20/D20)*E20))+(((C20/D20)*E20))*G20 -> #N/A | I20: =I19+H20 -> #N/A
A21: 16 | D21: =HLOOKUP(YEAR(B21),'Indices TJ'!$A$1:$AZ$13,MONTH(B21)+1) -> #N/A | E21: =HLOOKUP(YEAR($E$2),'Indices TJ'!$A$1:$AZ$13,MONTH($E$2)+1) -> 42.899504 | G21: =IF(($E$2-F21)>30,ROUND(($E$2-F21)/30,0)*$G$4,ROUND(($E$2-F21)/30,2)*$G$4) -> 13.46 | H21: =(((C21/D21)*E21))+(((C21/D21)*E21))*G21 -> #N/A | I21: =I20+H21 -> #N/A
... A104: 99 | D104: =HLOOKUP(YEAR(B104),'Indices TJ'!$A$1:$AZ$13,MONTH(B104)+1) -> #N/A | E104: =HLOOKUP(YEAR($E$2),'Indices TJ'!$A$1:$AZ$13,MONTH($E$2)+1) -> 42.899504 | G104: =IF(($E$2-F104)>30,ROUND(($E$2-F104)/30,0)*$G$4,ROUND(($E$2-F104)/30,2)*$G$4) -> 13.46 | H104: =(((C104/D104)*E104))+(((C104/D104)*E104))*G104 -> #N/A | I104: =I103+H104 -> #N/A

Sheet Indices TJ
B1: 1964 | C1: 1965 | D1: 1966 | E1: 1967 | F1: 1968 | G1: 1969 | H1: 1970 | I1: 1971 | J1: 1972 | K1: 1973 | L1: 1974 | M1: 1975 | N1: 1976 | O1: 1977 | P1: 1978 | Q1: 1979 | R1: 1980 | S1: 1981 | T1: 1982 | U1: 1983 | V1: 1984 | W1: 1985 | X1: 1986 | Y1: 1987 | Z1: 1988 | AA1: 1989 | AB1: 1990 | AC1: 1991 | AD1: 1992 | AE1: 1993 | AF1: 1994 | AG1: 1995 | AH1: 1996 | AI1: 1997 | AJ1: 1998 | AK1: 1999 | AL1: 2000 | AM1: 2001 | AN1: 2002 | AO1: 2003 | AP1: 2004 | AQ1: 2005 | AR1: 2006 | AS1: 2007 | AT1: 2008 | AU1: 2009 | AV1: 2010 | AW1: 2011 | AX1: 2012 | AY1: 2013 | AZ1: 2014
A2: JAN | B2: ----- | C2: 11300 | D2: 16600 | E2: 23230 | F2: 28.48 | G2: 35.62 | H2: 42.35 | I2: 50.51 | J2: 61.52 | K2: 70.87 | L2: 80.62 | M2: 106.76 | N2: 133.34 | O2: 183.65 | P2: 238.32 | Q2: 326.82 | R2: 487.83 | S2: 738.5 | T2: 1453.96 | U2: 2910.93 | V2: 7545.98 | W2: 24432.06 | X2: 80047.66 | Y2: 129.98 | Z2: 596.94 | AA2: 6,170000 | AB2: 102.52731 | AC2: 1942.7263 | AD2: 11230.66 | AE2: 140277.06 | AF2: 3631.9291 | AG2: 13.851199 | AH2: 16.819757 | AI2: 18.353215 | AJ2: 19.149765 | AK2: 19.626072 | AL2: 21.280595 | AM2: 22.402504 | AN2: 24.51769 | AO2: 28.131595 | AP2: 31.052744 | AQ2: 32.957268 | AR2: 34.620735 | AS2: 35.594754 | AT2: 37.429911 | AU2: 39.855905 | AV2: 41.495485
A3: FEV | B3: ----- | C3: 11300 | D3: 17050 | E3: 23.78 | F3: 28.98 | G3: 36.27 | H3: 43.3 | I3: 51.44 | J3: 62.26 | K3: 71.57 | L3: 81.47 | M3: 108.38 | N3: 135.9 | O3: 186.83 | P3: 243.35 | Q3: 334.2 | R3: 508.33 | S3: 775.43 | T3: 1526.66 | U3: 3085.59 | V3: 8285.49 | W3: 27510.5 | X3: 93039.4 | Y3: 151.85 | Z3: 695.5 | AA3: 8,805824 | AB3: 160.05538 | AC3: 2329.5232 | AD3: 14141.647 | AE3: 180634.78 | AF3: 5132.6422 | AG3: 14.082514 | AH3: 17.065325 | AI3: 18.501876 | AJ3: 19.312538 | AK3: 19.753641 | AL3: 21.410406 | AM3: 22.575003 | AN3: 24.780029 | AO3: 28.826445 | AP3: 31.310481 | AQ3: 33.145124 | AR3: 34.752293 | AS3: 35.769168 | AT3: 37.688177 | AU3: 40.110982 | AV3: 41.860645
A4: MAR | B4: ----- | C4: 11300 | D4: 17300 | E4: 24.28 | F4: 29.4 | G4: 36.91 | H4: 44.17 | I4: 52.12 | J4: 63.09 | K4: 72.32 | L4: 82.69 | M4: 110.18 | N4: 138.94 | O4: 190.51 | P4: 248.99 | Q4: 341.97 | R4: 527.14 | S4: 825.83 | T4: 1602.99 | U4: 3292.32 | V4: 9304.61 | W4: 30316.57 | X4: 106.4 | Y4: 181.61 | Z4: 820.42 | AA4: 9.698734 | AB4: 276.54368 | AC4: 2838.9899 | AD4: 17603.522 | AE4: 225414.14 | AF4: 7214.9551 | AG4: 14.22193 | AH4: 17.186488 | AI4: 18.585134 | AJ4: 19.416825 | AK4: 20.008462 | AL4: 21.421111 | AM4: 22.68562 | AN4: 24.856847 | AO4: 29.247311 | AP4: 31.432591 | AQ4: 33.290962 | AR4: 34.832223 | AS4: 35.919398 | AT4: 37.86908 | AU4: 40.235326 | AV4: 42.153669
A5: ABR | B5: ----- | C5: 13400 | D5: 17600 | E5: 24.64 | F5: 29.83 | G5: 37.43 | H5: 44.67 | I5: 52.64 | J5: 63.81 | K5: 73.19 | L5: 83.73 | M5: 112.25 | N5: 142.24 | O5: 194.83 | P5: 255.41 | Q5: 350.51 | R5: 546.64 | S5: 877.86 | T5: 1683.14 | U5: 3588.63 | V5: 10235.07 | W5: 34166.77 | X5: 106.28 | Y5: 207.97 | Z5: 951.77 | AA5: 10.289386 | AB5: 509.72531 | AC5: 3173.7068 | AD5: 21409.403 | AE5: 287583.35 | AF5: 10323.158 | AG5: 14.422459 | AH5: 17.236328 | AI5: 18.711512 | AJ5: 19.511967 | AK5: 20.26457 | AL5: 21.448958 | AM5: 22.79451 | AN5: 25.010959 | AO5: 29.647999 | AP5: 31.611756 | AQ5: 33.533986 | AR5: 34.92627 | AS5: 36.077443 | AT5: 38.062212 | AU5: 40.315796 | AV5: 42.45296
A6: MAI | B6: ----- | C6: 13400 | D6: 18280 | E6: 25.01 | F6: 30.39 | G6: 38.01 | H6: 45.08 | I6: 53.25 | J6: 64.66 | K6: 74.03 | L6: 85.1 | M6: 114.49 | N6: 145.83 | O6: 200.45 | P6: 262.87 | Q6: 363.64 | R6: 566.86 | S6: 930.53 | T6: 1775.71 | U6: 3911.61 | V6: 11145.99 | W6: 38208.46 | X6: 107.12 | Y6: 251.56 | Z6: 1135.27 | AA6: 11.04154 | AB6: 738.08225 | AC6: 3332.7095 | AD6: 25871.123 | AE6: 369170.75 | AF6: 14747.663 | AG6: 14.69937 | AH6: 17.396625 | AI6: 18.823781 | AJ6: 19.59977 | AK6: 20.359813 | AL6: 21.468262 | AM6: 22.985983 | AN6: 25.181033 | AO6: 30.057141 | AP6: 31.741364 | AQ6: 33.839145 | AR6: 34.968181 | AS6: 36.171244 | AT6: 38.30581 | AU6: 40.537532 | AV6: 42.762866
A7: JUN | B7: ----- | C7: 13400 | D7: 19090 | E7: 25.46 | F7: 31.2 | G7: 38.48 | H7: 45.5 | I7: 54.01 | J7: 65.75 | K7: 74.97 | L7: 86.91 | M7: 117.13 | N7: 150.17 | O7: 206.9 | P7: 270.88 | Q7: 377.54 | R7: 586.13 | S7: 986.36 | T7: 1873.37 | U7: 4224.54 | V7: 12137.98 | W7: 42031.56 | X7: 108.61 | Y7: 310.53 | Z7: 1337.12 | AA7: 12.139069 | AB7: 796.16932 | AC7: 3555.3345 | AD7: 32209.548 | AE7: 468034.68 | AF7: 21049.34 | AG7: 15.077143 | AH7: 17.619301 | AI7: 18.844487 | AJ7: 19.740888 | AK7: 20.369992 | AL7: 21.457527 | AM7: 23.117003 | AN7: 25.203695 | AO7: 30.354706 | AP7: 31.868329 | AQ7: 34.076019 | AR7: 35.013639 | AS7: 36.265289 | AT7: 38.673545 | AU7: 40.780757 | AV7: 42.946746
A8: JUL | B8: ----- | C8: 15200 | D8: 19870 | E8: 26.18 | F8: 32.09 | G8: 39 | H8: 46.2 | I8: 55.08 | J8: 66.93 | K8: 75.8 | L8: 89.8 | M8: 119.27 | N8: 154.6 | O8: 213.8 | P8: 279.04 | Q8: 390.1 | R8: 604.89 | S8: 1045.54 | T8: 1976.41 | U8: 4554.05 | V8: 13254.67 | W8: 45901.91 | X8: 109.99 | Y8: 366.49 | Z8: 1598.26 | AA8: 15.153199 | AB8: 872.20349 | AC8: 3940.3772 | AD8: 38925.239 | AE8: 610176.81 | AF8: 11.346741 | AG8: 15.351547 | AH8: 17.853637 | AI8: 18.910442 | AJ8: 19.770499 | AK8: 20.38425 | AL8: 21.521899 | AM8: 23.255705 | AN8: 25.357437 | AO8: 30.336493 | AP8: 32.02767 | AQ8: 34.038535 | AR8: 34.989129 | AS8: 36.377711 | AT8: 39.025474 | AU8: 40.952036 | AV8: 42.899504
A9: AGO | B9: ----- | C9: 15200 | D9: 20430 | E9: 26.84 | F9: 32.81 | G9: 39.27 | H9: 46.61 | I9: 56.18 | J9: 67.89 | K9: 76.48 | L9: 93.75 | M9: 121.31 | N9: 158.55 | O9: 219.51 | P9: 287.58 | Q9: 400.71 | R9: 624.25 | S9: 1108.27 | T9: 2094.99 | U9: 4963.91 | V9: 14619.9 | W9: 49396.88 | X9: 111.31 | Y9: 377.67 | Z9: 1982.48 | AA9: 19.511259 | AB9: 984.89218 | AC9: 4418.739 | AD9: 47519.932 | AE9: 799.39264 | AF9: 12.036622 | AG9: 15.729195 | AH9: 18.06788 | AI9: 18.94448 | AJ9: 19.715141 | AK9: 20.535093 | AL9: 21.821053 | AM9: 23.513843 | AN9: 25.649047 | AO9: 30.348627 | AP9: 32.261471 | AQ9: 34.048746 | AR9: 35.027617 | AS9: 36.494119 | AT9: 39.251821 | AU9: 41.046225
A10: SET | B10: ----- | C10: 15700 | D10: 21010 | E10: 27.25 | F10: 33.41 | G10: 39.56 | H10: 47.05 | I10: 57.36 | J10: 68.46 | K10: 77.12 | L10: 98.22 | M10: 123.2 | N10: 162.97 | O10: 224.01 | P10: 295.57 | Q10: 412.24 | R10: 644.23 | S10: 1172.55 | T10: 2241.64 | U10: 5385.84 | V10: 16169.61 | W10: 53437.4 | X10: 113.18 | Y10: 401.69 | Z10: 2392.06 | AA10: 25.235862 | AB10: 1103.3747 | AC10: 5108.946 | AD10: 58154.893 | AE10: 1065.9101 | AF10: 12.693821 | AG10: 15.889632 | AH10: 18.158219 | AI10: 18.938796 | AJ10: 19.618536 | AK10: 20.648036 | AL10: 22.085087 | AM10: 23.699602 | AN10: 25.869628 | AO10: 30.403254 | AP10: 32.422778 | AQ10: 34.048746 | AR10: 35.020611 | AS10: 36.709434 | AT10: 39.334249 | AU10: 41.079061
A11: OUT | B11: 10000 | C11: 15900 | D11: 21610 | E11: 27.38 | F11: 33.88 | G11: 39.92 | H11: 47.61 | I11: 58.61 | J11: 68.95 | K11: 77.87 | L11: 101.9 | M11: 125.7 | N11: 168.33 | O11: 227.15 | P11: 303.29 | Q11: 428.8 | R11: 663.56 | S11: 1239.39 | T11: 2398.55 | U11: 5897.49 | V11: 17867.42 | W11: 58300.2 | X11: 115.13 | Y11: 424.51 | Z11: 2966.39 | AA11: 34.308154 | AB11: 1244.1653 | AC11: 5906.9634 | AD11: 72100.436 | AE11: 1445.6939 | AF11: 12.885497 | AG11: 16.07554 | AH11: 18.16185 | AI11: 18.957734 | AJ11: 19.557718 | AK11: 20.728563 | AL11: 22.180052 | AM11: 23.80388 | AN11: 26.084345 | AO11: 30.65256 | AP11: 32.477896 | AQ11: 34.099819 | AR11: 35.076643 | AS11: 36.801207 | AT11: 39.39325 | AU11: 41.144787
A12: NOV | B12: 10000 | C12: 16050 | D12: 22180 | E12: 27.57 | F12: 34.39 | G12: 40.57 | H12: 48.51 | I12: 59.79 | J12: 69.61 | K12: 78.4 | L12: 104.1 | M12: 128.43 | N12: 174.4 | O12: 230.3 | P12: 310.49 | Q12: 448.47 | R12: 684.79 | S12: 1310.04 | T12: 2566.45 | U12: 6469.55 | V12: 20118.71 | W12: 63547.22 | X12: 117.32 | Y12: 463.48 | Z12: 3774.73 | AA12: 47.214881 | AB12: 1420.8368 | AC12: 7152.1513 | AD12: 90897.02 | AE12: 1938.9647 | AF12: 13.125167 | AG12: 16.300597 | AH12: 18.230865 | AI12: 19.012711 | AJ12: 19.579231 | AK12: 20.927557 | AL12: 22.21554 | AM12: 24.027636 | AN12: 26.493869 | AO12: 30.772104 | AP12: 32.533108 | AQ12: 34.297597 | AR12: 35.227442 | AS12: 36.91161 | AT12: 39.590216 | AU12: 41.243534
A13: DEZ | B13: 10000 | C13: 16300 | D13: 22690 | E13: 27.96 | F13: 34.95 | G13: 41.42 | H13: 49.54 | I13: 60.77 | J13: 70.07 | K13: 79.07 | L13: 105.41 | M13: 130.93 | N13: 179.68 | O13: 233.74 | P13: 318.44 | Q13: 468.71 | R13: 706.7 | S13: 1382.09 | T13: 2733.27 | U13: 7012.99 | V13: 22110.46 | W13: 70613.67 | X13: 121.17 | Y13: 522.99 | Z13: 4790.89 | AA13: 66.771284 | AB13: 1642.2032 | AC13: 9046.041 | AD13: 111703.35 | AE13: 2636.992 | AF13: 13.554359 | AG13: 16.546736 | AH13: 18.292849 | AI13: 19.04123 | AJ13: 19.543988 | AK13: 21.124276 | AL13: 22.279965 | AM13: 24.337592 | AN13: 27.392011 | AO13: 30.88596 | AP13: 32.676253 | AQ13: 34.482804 | AR13: 35.375427 | AS13: 37.070329 | AT13: 39.740658 | AU13: 41.396135
A15: Observação I: Dividir o valor a atualizar (observar o padrão monetário vigente à época) pelo fator do mês do termo inicial e multiplicar pelo fator do mês do termo final, obtendo-se o resultado na moeda vigente na data do termo final, não sendo necessário efetuar qualquer conversão. Esclarecendo que, nesta tabela, não estão incluídos os juros moratórios, apenas a correção monetária.
