Workbook

Sheet Ini
C2: PLANILHA DE
C3: PLANILHA DE AVALIAÇÃO ECONÔMICO-FINANCEIRA DE EMPRESA
C4: BALANÇO
C5: Seja bem-vindo(a). Com esta planilha você terá o controle das finanças da empresa e poderá tomar decisões importantes com base em números
C6: Instruções sobre como você deve começar
C8: 1 | E8: Balanço Patrimonial
E9: Os valores devem ser registrados aqui. Você irá relacionar isso de acordo com e a uma categoria das contas do Ativo (circulante e não circulante) e do Passivo (circulante, não circulante e Patrimôni Líquido.
C12: 2 | E12: Demonstração de Resultado de Exercício (DRE)
E13: A Demonstração do Resultado do Exercício tem como objetivo principal apresentarr esumida o resultado apurado em relação ao conjunto de operações realizadas num determinado período, normalmente, de doze meses.
C16: 3 | E16: Veja os resultados através de gráficos
E17: Aqui você verá os gráficos a partir de todos os dados que você cadastrou em “Balanço Patromônial” e “DRE” . É uma forma rápida e agradável para visualizar seus resultados de forma prática.
C20: 4 | E20: Faça uma Análise de Balanço
E21: Identifique os fatores positivos ou negativos sobre a saúde financeira e administrativa das empresas nos números divulgados em seus balanços patrimoniais
C24: 5 | E24: Imprima um relatório financeiro completo
E25: Já separamos uma aba exclusiva com suas principais informações financeiras prontas para impressão. Basta entrar no relatório e imprimir!

Sheet Bal
C1: 1. BALANÇO PATRIMÔNIAL
C6: 1000 | D6: Ativo Circulante (Bens e Direitos) | E6: =IF(ISERROR($E$7+$E$17+$E$27+$E$37+$E$47+$E$57+$E$67+$E$77+$E$87),"",$E$7+$E$17+$E$27+$E$37+$E$47+$E$57+$E$67+$E$77+$E$87) -> 153280 | H6: 1000 | I6: Contas do Ativo Circulante - Resultado
C7: 1110 | D7: Disponibilidades | E7: =IF(ISERROR(SUM(E8:E16)),"",SUM(E8:E16)) -> 57560 | H7: 1110 | I7: Disponibilidades | J7: 57560 | K7: 0.37552192 | L7: =IF(ISERROR(SUM($J$7:$J$15)),"",SUM($J$7:$J$15)) -> 153280
C8: 1111 | D8: Caixa | E8: 5850 | F8: =IF(ISERROR(E8/$E$7),"",E8/$E$7) -> 0.10163308 | H8: 1120 | I8: Aplicações em Instrumentos Financeiros | J8: 0 | K8: 0
C9: 1112 | D9: Recurso de Caixa Pequena | F9: =IF(ISERROR(E9/$E$7),"",E9/$E$7) -> 0 | H9: 1130 | I9: Estoque | J9: 46320 | K9: 0.30219207
C10: 1113 | D10: Bancos - Conta movimento no País | E10: 51710 | F10: =IF(ISERROR(E10/$E$7),"",E10/$E$7) -> 0.89836692 | H10: 1140 | I10: Créditos Tributários | J10: 0 | K10: 0
C11: 1114 | D11: Bancos no Exterior | F11: =IF(ISERROR(E11/$E$7),"",E11/$E$7) -> 0 | H11: 1150 | I11: Clientes Créditos a Receber | J11: 49400 | K11: 0.32228601
C12: 1115 | D12: Bancos Contas Vinculadas | F12: =IF(ISERROR(E12/$E$7),"",E12/$E$7) -> 0 | H12: 1160 | I12: Clientes Vencidos a Liquidar | J12: 0 | K12: 0
C13: 1116 | D13: Depósitos em Garantias e Cauções em Dinheiro | F13: =IF(ISERROR(E13/$E$7),"",E13/$E$7) -> 0 | H13: 1170 | I13: Outros Créditos | J13: 0 | K13: 0
C14: 1117 | D14: Disponibilidades em Moedas Estrangeiras | F14: =IF(ISERROR(E14/$E$7),"",E14/$E$7) -> 0 | H14: 1180 | I14: Outros Valores e Bens | J14: 0 | K14: 0
C15: 1118 | D15: Aplicações em Ouro | F15: =IF(ISERROR(E15/$E$7),"",E15/$E$7) -> 0 | H15: 1190 | I15: Despesas Antecipadas | J15: 0 | K15: 0
C16: 1119 | D16: Outras Disponibilidades - Valores Mobiliários | F16: =IF(ISERROR(E16/$E$7),"",E16/$E$7) -> 0
C17: 1120 | D17: Aplicações em Instrumentos Financeiros | E17: =IF(ISERROR(SUM(E18:E26)),"",SUM(E18:E26)) -> 0 | H17: Direitos Realizáveis a Curto Prazo
C18: 1121 | D18: Aplicações Compromissadas por Revenda | F18: =IF(ISERROR(E18/$E$17),"",E18/$E$17) | H18: 1120 | I18: Aplicações em Instrumentos Financeiros | J18: 0 | K18: 0
C19: 1122 | D19: Aplicações de Renda Fixa | F19: =IF(ISERROR(E19/$E$17),"",E19/$E$17) | H19: 1150 | I19: Clientes Créditos a Receber | J19: 49400 | K19: 1
C20: 1123 | D20: Aplicações de Renda Variável | F20: =IF(ISERROR(E20/$E$17),"",E20/$E$17) | H20: 1160 | I20: Clientes Vencidos a Liquidar | J20: 0 | K20: 0
C21: 1124 | D21: Títulos e Aplicações Vinculados | F21: =IF(ISERROR(E21/$E$17),"",E21/$E$17) | H21: Resultado | J21: 49400
C22: 1125 | D22: Devedores por Empréstimos de Títulos e Valores Mobiliários | F22: =IF(ISERROR(E22/$E$17),"",E22/$E$17)
C23: 1126 | D23: Box de Aplicação | F23: =IF(ISERROR(E23/$E$17),"",E23/$E$17) | H23: Valor Total do Ativo Circulante
C24: 1127 | D24: Valores Mobiliários em Moedas Estrangeiras | F24: =IF(ISERROR(E24/$E$17),"",E24/$E$17) | H24: Resultado | J24: 153280
C25: 1128 | D25: Valores Mobiliários Sujeitas a Restrições | F25: =IF(ISERROR(E25/$E$17),"",E25/$E$17)
C26: 1129 | D26: Outros Títulos e Valores Mobiliários a Receber | F26: =IF(ISERROR(E26/$E$17),"",E26/$E$17)
C27: 1130 | D27: Estoque | E27: =IF(ISERROR(SUM(E28:E36)),"",SUM(E28:E36)) -> 46320
C28: 1131 | D28: Estoque de Matéria Prima (insumos) | F28: =IF(ISERROR(E28/$E$27),"",E28/$E$27) -> 0
C29: 1132 | D29: Estoque de Produção em Elaboração | F29: =IF(ISERROR(E29/$E$27),"",E29/$E$27) -> 0
C30: 1133 | D30: Estoque de Produtos Acabados | F30: =IF(ISERROR(E30/$E$27),"",E30/$E$27) -> 0
C31: 1134 | D31: Estoque de Mercadorias para Revenda | E31: 46320 | F31: =IF(ISERROR(E31/$E$27),"",E31/$E$27) -> 1
C32: 1135 | D32: Mercadoria de Reposição na Prestação de Serviços | F32: =IF(ISERROR(E32/$E$27),"",E32/$E$27) -> 0
C33: 1136 | D33: Devedores por Estoques Remetidos para a Industrialização | F33: =IF(ISERROR(E33/$E$27),"",E33/$E$27) -> 0
C34: 1137 | D34: Devedores por Mercadorias Remetidas em Consignação ou Comodato | F34: =IF(ISERROR(E34/$E$27),"",E34/$E$27) -> 0
C35: 1138 | D35: Mercadorias Recebidas em Consignação ou Comodato | F35: =IF(ISERROR(E35/$E$27),"",E35/$E$27) -> 0
C36: 1139 | D36: Outros Estoques | F36: =IF(ISERROR(E36/$E$27),"",E36/$E$27) -> 0
C37: 1140 | D37: Créditos Tributários | E37: =IF(ISERROR(SUM(E38:E46)),"",SUM(E38:E46)) -> 0
C38: 1141 | D38: IRPJ - Imposto de Renda de Pessoa Jurídica | F38: =IF(ISERROR(E38/$E$37),"",E38/$E$37)
C39: 1142 | D39: CSLL - Contribuição Social sobre o Lucro Líquido | F39: =IF(ISERROR(E39/$E$37),"",E39/$E$37)
C40: 1143 | D40: ICMS - Imposto sobre Circulação de Mercadorias e Serviços e Outros Tributos Estaduais | F40: =IF(ISERROR(E40/$E$37),"",E40/$E$37)
C41: 1144 | D41: IPI - Imposto sobre Produtos Industrializados | F41: =IF(ISERROR(E41/$E$37),"",E41/$E$37)
C42: 1145 | D42: ISS - Imposto sobre Serviços e outros Tributos Municipais a Recuperar | F42: =IF(ISERROR(E42/$E$37),"",E42/$E$37)
C43: 1146 | D43: Contribuições Sociais - PIS e COFINS a Recuperar | F43: =IF(ISERROR(E43/$E$37),"",E43/$E$37)
C44: 1147 | D44: Crédito Fiscal do ICMS sobre o Imobilizado de Uso | F44: =IF(ISERROR(E44/$E$37),"",E44/$E$37)
C45: 1148 | D45: Crédito Fiscal do ICMS sobre Arrendamento Mercantil - Leasing | F45: =IF(ISERROR(E45/$E$37),"",E45/$E$37)
C46: 1149 | D46: Outros Impostos e Contribuições a Recuperar | F46: =IF(ISERROR(E46/$E$37),"",E46/$E$37)
C47: 1150 | D47: Clientes - Créditos a Receber | E47: =IF(ISERROR(SUM(E48:E56)),"",SUM(E48:E56)) -> 49400
C48: 1151 | D48: Duplicatas a Receber | E48: 49400 | F48: =IF(ISERROR(E48/$E$47),"",E48/$E$47) -> 1
C49: 1152 | D49: Notas Promissórias a Receber | F49: =IF(ISERROR(E49/$E$47),"",E49/$E$47) -> 0
C50: 1153 | D50: Carnês a Receber | F50: =IF(ISERROR(E50/$E$47),"",E50/$E$47) -> 0
C51: 1154 | D51: Cheques e Ordens a Receber | F51: =IF(ISERROR(E51/$E$47),"",E51/$E$47) -> 0
C52: 1155 | D52: Cartões de Créditos a Receber | F52: =IF(ISERROR(E52/$E$47),"",E52/$E$47) -> 0
C53: 1156 | F53: =IF(ISERROR(E53/$E$47),"",E53/$E$47) -> 0
C54: 1157 | F54: =IF(ISERROR(E54/$E$47),"",E54/$E$47) -> 0
C55: 1158 | F55: =IF(ISERROR(E55/$E$47),"",E55/$E$47) -> 0
C56: 1159 | D56: Outros Créditos com Clientes a Receber | F56: =IF(ISERROR(E56/$E$47),"",E56/$E$47) -> 0
C57: 1160 | D57: Clientes Vencidos a Liquidar | E57: =IF(ISERROR(SUM(E58:E66)),"",SUM(E58:E66)) -> 0
C58: 1161 | D58: Duplicatas a Vencidas Receber | F58: =IF(ISERROR(E58/$E$57),"",E58/$E$57)
C59: 1162 | D59: Notas Promissórias Vencidas a Receber | F59: =IF(ISERROR(E59/$E$57),"",E59/$E$57)
C60: 1163 | D60: Carnês Vencidos a Receber | F60: =IF(ISERROR(E60/$E$57),"",E60/$E$57)
C61: 1164 | D61: Cheques e Ordens Vencidos a Receber | F61: =IF(ISERROR(E61/$E$57),"",E61/$E$57)
C62: 1165 | D62: Cartões de Créditos Vencidos a Receber | F62: =IF(ISERROR(E62/$E$57),"",E62/$E$57)
C63: 1166 | D63: Créditos em Empresas em Regima Especial | F63: =IF(ISERROR(E63/$E$57),"",E63/$E$57)
C64: 1167 | D64: Créditos em Instituições Financeiras em Regime Especial | F64: =IF(ISERROR(E64/$E$57),"",E64/$E$57)
C65: 1168 | F65: =IF(ISERROR(E65/$E$57),"",E65/$E$57)
C66: 1169 | D66: Outros Créditos Vencidos a Receber | F66: =IF(ISERROR(E66/$E$57),"",E66/$E$57)
C67: 1170 | D67: Outros Créditos | E67: =IF(ISERROR(SUM(E68:E76)),"",SUM(E68:E76)) -> 0
C68: 1171 | D68: Comissões e Corretagem a Receber | F68: =IF(ISERROR(E68/$E$67),"",E68/$E$67)
C69: 1172 | D69: Dividendos / Bonificações em Dinheiro a Receber | F69: =IF(ISERROR(E69/$E$67),"",E69/$E$67)
C70: 1173 | D70: Rendas a Receber de Títulos e Valores Mobiliários | F70: =IF(ISERROR(E70/$E$67),"",E70/$E$67)
C71: 1174 | D71: Outras Rendas a Receber | F71: =IF(ISERROR(E71/$E$67),"",E71/$E$67)
C72: 1175 | D72: Valores a Receber pela Venda de Bens | F72: =IF(ISERROR(E72/$E$67),"",E72/$E$67)
C73: 1176 | D73: Devedores por Intermediação Financeira | F73: =IF(ISERROR(E73/$E$67),"",E73/$E$67)
C74: 1177 | D74: Adiantamento a Fornecedores | F74: =IF(ISERROR(E74/$E$67),"",E74/$E$67)
C75: 1178 | F75: =IF(ISERROR(E75/$E$67),"",E75/$E$67)
C76: 1179 | D76: Outras Contas a Receber | F76: =IF(ISERROR(E76/$E$67),"",E76/$E$67)
C77: 1180 | D77: Outros Valores e Bens | E77: =IF(ISERROR(SUM(E78:E86)),"",SUM(E78:E86)) -> 0
C78: 1181 | D78: Adiantamento e Antecipações Salariais | F78: =IF(ISERROR(E78/$E$77),"",E78/$E$77)
C79: 1182 | D79: Adiantamento de Férias | F79: =IF(ISERROR(E79/$E$77),"",E79/$E$77)
C80: 1183 | D80: Adiantamento para Pagamento de Nossa Conta | F80: =IF(ISERROR(E80/$E$77),"",E80/$E$77)
C81: 1184 | D81: Adiantamento do 13º Salário | F81: =IF(ISERROR(E81/$E$77),"",E81/$E$77)
C82: 1185 | D82: Importações em Andamento | F82: =IF(ISERROR(E82/$E$77),"",E82/$E$77)
C83: 1186 | D83: Devedores Diversos - País | F83: =IF(ISERROR(E83/$E$77),"",E83/$E$77)
C84: 1187 | D84: Devedores Diversos - Exterior | F84: =IF(ISERROR(E84/$E$77),"",E84/$E$77)
C85: 1188 | F85: =IF(ISERROR(E85/$E$77),"",E85/$E$77)
C86: 1189 | D86: Outros Ativos Circulantes | F86: =IF(ISERROR(E86/$E$77),"",E86/$E$77)
C87: 1190 | D87: Despesas Antecipadas | E87: =IF(ISERROR(SUM(E88:E96)),"",SUM(E88:E96)) -> 0
C88: 1191 | D88: Estoque de Materiais de Escritório | F88: =IF(ISERROR(E88/$E$87),"",E88/$E$87)
C89: 1192 | D89: Seguros a Apropriar | F89: =IF(ISERROR(E89/$E$87),"",E89/$E$87)
C90: 1193 | D90: Juros Pagos Antecipadamente | F90: =IF(ISERROR(E90/$E$87),"",E90/$E$87)
C91: 1194 | D91: Adiantamento para Despesas | F91: =IF(ISERROR(E91/$E$87),"",E91/$E$87)
C92: 1195 | D92: Antecipação do 13º Salário | F92: =IF(ISERROR(E92/$E$87),"",E92/$E$87)
C93: 1196 | D93: Estoques de Sucatas | F93: =IF(ISERROR(E93/$E$87),"",E93/$E$87)
C94: 1197 | D94: Estoques de Produtos de Limpeza e Conservação | F94: =IF(ISERROR(E94/$E$87),"",E94/$E$87)
C95: 1198 | D95: Estoques de Peças de Reposição do Imobilizado | F95: =IF(ISERROR(E95/$E$87),"",E95/$E$87)
C96: 1199 | D96: Outros Despesas Antecipadas | F96: =IF(ISERROR(E96/$E$87),"",E96/$E$87)

Sheet Atin
C1: 1. BALANÇO PATRIMÔNIAL
C6: 2000 | D6: Ativo Não Circulante (Bens e Direitos) | E6: =IF(ISERROR($E$7+$E$17+$E$27+$E$37+$E$47+$E$57+$E$67+$E$77+$E$87+$E$97+$E$107+$E$117+$E$127+$E$137+$E$147),"",$E$7+$E$17+$E$27+$E$37+$E$47+$E$57+$E$67+$E$77+$E$87+$E$97+$E$107+$E$117+$E$127+$E$137+$E$147) -> 141500 | H6: 2000 | I6: Contas do Ativo Não Circulante - Resultado
C7: 2200 | D7: Valores e Bens | E7: =IF(ISERROR(SUM(E8:E16)),"",SUM(E8:E16)) -> 65000 | H7: 2200 | I7: Valores e Bens | J7: =IF(ISERROR($E$7),"",$E$7) -> 65000 | K7: =IF(ISERROR(J7/$L$7),"",J7/$L$7) -> 0.45936396 | L7: =IF(ISERROR(SUM($J$7:$J$21)),"",SUM($J$7:$J$21)) -> 141500
C8: 2211 | D8: Adiantamentos por Conta de Imobilizações | F8: =IF(ISERROR(E8/$E$7),"",E8/$E$7) -> 0 | H8: 2220 | I8: Garantias e Cauções | J8: =IF(ISERROR($E$17),"",$E$17) -> 0 | K8: =IF(ISERROR(J8/$L$7),"",J8/$L$7) -> 0
C9: 2212 | D9: Clientes - Devedores de Longo Prazo | E9: 65000 | F9: =IF(ISERROR(E9/$E$7),"",E9/$E$7) -> 1 | H9: 2230 | I9: Aplicações em Instrumentos Financeiros a Longo Prazo | J9: =IF(ISERROR($E$27),"",$E$27) -> 0 | K9: =IF(ISERROR(J9/$L$7),"",J9/$L$7) -> 0
C10: 2213 | D10: Imóveis em Construção | F10: =IF(ISERROR(E10/$E$7),"",E10/$E$7) -> 0 | H10: 2240 | I10: Depósitos Judiciais | J10: =IF(ISERROR($E$37),"",$E$37) -> 0 | K10: =IF(ISERROR(J10/$L$7),"",J10/$L$7) -> 0
C11: 2214 | D11: Estoque de Reposição Permanente | F11: =IF(ISERROR(E11/$E$7),"",E11/$E$7) -> 0 | H11: 2250 | I11: Imóveis para Locação ou Venda | J11: =IF(ISERROR($E$47),"",$E$47) -> 0 | K11: =IF(ISERROR(J11/$L$7),"",J11/$L$7) -> 0
C12: 2215 | D12: Antecipação de Valores Residuais de Arrendamento Mercantil | F12: =IF(ISERROR(E12/$E$7),"",E12/$E$7) -> 0 | H12: 2290 | I12: Outras Contas do Realizável | J12: =IF(ISERROR($E$57),"",$E$57) -> 0 | K12: =IF(ISERROR(J12/$L$7),"",J12/$L$7) -> 0
C13: 2216 | F13: =IF(ISERROR(E13/$E$7),"",E13/$E$7) -> 0 | H13: 2310 | I13: Investimentos | J13: =IF(ISERROR($E$67),"",$E$67) -> 0 | K13: =IF(ISERROR(J13/$L$7),"",J13/$L$7) -> 0
C14: 2217 | D14: Créditos Fiscais e Tributários de Longo Prazo | F14: =IF(ISERROR(E14/$E$7),"",E14/$E$7) -> 0 | H14: 2320 | I14: Imobilizado de Uso | J14: =IF(ISERROR($E$77),"",$E$77) -> 50000 | K14: =IF(ISERROR(J14/$L$7),"",J14/$L$7) -> 0.35335689
C15: 2218 | F15: =IF(ISERROR(E15/$E$7),"",E15/$E$7) -> 0 | H15: 2330 | I15: Ativo Diferido | J15: =IF(ISERROR($E$87),"",$E$87) -> 18500 | K15: =IF(ISERROR(J15/$L$7),"",J15/$L$7) -> 0.13074205
C16: 2219 | D16: Outros Valores e Bens a Longo Prazo | F16: =IF(ISERROR(E16/$E$7),"",E16/$E$7) -> 0 | H16: 2340 | I16: Intangível | J16: =IF(ISERROR($E$97),"",$E$97) -> 20000 | K16: =IF(ISERROR(J16/$L$7),"",J16/$L$7) -> 0.14134276
C17: 2220 | D17: Garantias e Cauções | E17: =IF(ISERROR(SUM(E18:E26)),"",SUM(E18:E26)) -> 0 | H17: 2350 | I17: Imobilizado de Arrendamento (Leaseback) | J17: =IF(ISERROR($E$107),"",$E$107) -> 0 | K17: =IF(ISERROR(J17/$L$7),"",J17/$L$7) -> 0
C18: 2221 | D18: Garantias e Cauções em Títulos | F18: =IF(ISERROR(E18/$E$17),"",E18/$E$17) | H18: 2360 | I18: Imobilizado Para Locação | J18: =IF(ISERROR($E$117),"",$E$117) -> 0 | K18: =IF(ISERROR(J18/$L$7),"",J18/$L$7) -> 0
C19: 2222 | D19: Garantias e Cauções em Bens Móveis | F19: =IF(ISERROR(E19/$E$17),"",E19/$E$17) | H19: 2370 | I19: Ativo Biológico e Produto Agrícola | J19: =IF(ISERROR($E$127),"",$E$127) -> 0 | K19: =IF(ISERROR(J19/$L$7),"",J19/$L$7) -> 0
C20: 2223 | D20: Garantias e Cauções em Imóveis | F20: =IF(ISERROR(E20/$E$17),"",E20/$E$17) | H20: 2380 | I20: Imobilzado Recebido em Comodato | J20: =IF(ISERROR($E$137),"",$E$137) -> 0 | K20: =IF(ISERROR(J20/$L$7),"",J20/$L$7) -> 0
C21: 2224 | D21: Garantias e Cauções em Dinheiro | F21: =IF(ISERROR(E21/$E$17),"",E21/$E$17) | H21: 2390 | I21: Outros | J21: =IF(ISERROR($E$147),"",$E$147) -> -12000 | K21: =IF(ISERROR(J21/$L$7),"",J21/$L$7) -> -0.084805654
C22: 2225 | F22: =IF(ISERROR(E22/$E$17),"",E22/$E$17)
C23: 2226 | F23: =IF(ISERROR(E23/$E$17),"",E23/$E$17) | H23: 2200 | I23: Direitos Realizáveis a Longo Prazo
C24: 2227 | F24: =IF(ISERROR(E24/$E$17),"",E24/$E$17) | H24: 2210 | I24: Valores e Bens | J24: =IF(ISERROR($E$7),"",$E$7) -> 65000 | K24: =IF(ISERROR(J24/$J$30),"",J24/$J$30) -> 1
C25: 2228 | F25: =IF(ISERROR(E25/$E$17),"",E25/$E$17) | H25: 2220 | I25: Garantias e Cauções | J25: =IF(ISERROR($E$17),"",$E$17) -> 0 | K25: =IF(ISERROR(J25/$J$30),"",J25/$J$30) -> 0
C26: 2229 | D26: Outras Garantias e Cauções | F26: =IF(ISERROR(E26/$E$17),"",E26/$E$17) | H26: 2230 | I26: Aplicações em Instrumentos Financeiros a Longo Prazo | J26: =IF(ISERROR($E$27),"",$E$27) -> 0 | K26: =IF(ISERROR(J26/$J$30),"",J26/$J$30) -> 0
C27: 2230 | D27: Aplicações em Instrumentos Financeiros a Longo Prazo | E27: =IF(ISERROR(SUM(E28:E36)),"",SUM(E28:E36)) -> 0 | H27: 2240 | I27: Depósitos Judiciais | J27: =IF(ISERROR($E$37),"",$E$37) -> 0 | K27: =IF(ISERROR(J27/$J$30),"",J27/$J$30) -> 0
C28: 2231 | D28: TVM de Sociedades em Regime Especial | F28: =IF(ISERROR(E28/$E$27),"",E28/$E$27) | H28: 2250 | I28: Imóveis para Locação ou Venda | J28: =IF(ISERROR($E$47),"",$E$47) -> 0 | K28: =IF(ISERROR(J28/$J$30),"",J28/$J$30) -> 0
C29: 2232 | D29: Participações em Sociedades em Regime Especial | F29: =IF(ISERROR(E29/$E$27),"",E29/$E$27) | H29: 2290 | I29: Outras Contas do Realizável | J29: =IF(ISERROR($E$57),"",$E$57) -> 0 | K29: =IF(ISERROR(J29/$J$30),"",J29/$J$30) -> 0
C30: 2233 | D30: Opções por Incentivos Fiscais | F30: =IF(ISERROR(E30/$E$27),"",E30/$E$27) | H30: Resultado | J30: =IF(ISERROR(SUM($J$24:$J$29)),"",SUM($J$24:$J$29)) -> 65000
C31: 2234 | F31: =IF(ISERROR(E31/$E$27),"",E31/$E$27)
C32: 2235 | F32: =IF(ISERROR(E32/$E$27),"",E32/$E$27) | H32: 2300 | I32: Ativo Permanente
C33: 2236 | F33: =IF(ISERROR(E33/$E$27),"",E33/$E$27) | H33: 2310 | I33: Investimentos | J33: =IF(ISERROR($E$67),"",$E$67) -> 0 | K33: =IF(ISERROR(J33/$J$42),"",J33/$J$42) -> 0
C34: 2237 | F34: =IF(ISERROR(E34/$E$27),"",E34/$E$27) | H34: 2320 | I34: Imobilizado de Uso | J34: =IF(ISERROR($E$77),"",$E$77) -> 50000 | K34: =IF(ISERROR(J34/$J$42),"",J34/$J$42) -> 0.65359477
C35: 2238 | F35: =IF(ISERROR(E35/$E$27),"",E35/$E$27) | H35: 2330 | I35: Ativo Diferido | J35: =IF(ISERROR($E$87),"",$E$87) -> 18500 | K35: =IF(ISERROR(J35/$J$42),"",J35/$J$42) -> 0.24183007
C36: 2239 | D36: Outros Títulos e Valores Mobiliários de Longo Prazo | F36: =IF(ISERROR(E36/$E$27),"",E36/$E$27) | H36: 2340 | I36: Intangível | J36: =IF(ISERROR($E$97),"",$E$97) -> 20000 | K36: =IF(ISERROR(J36/$J$42),"",J36/$J$42) -> 0.26143791
C37: 2240 | D37: Depósitos Judiciais | E37: =IF(ISERROR(SUM(E38:E46)),"",SUM(E38:E46)) -> 0 | H37: 2350 | I37: Imobilizado de Arrendamento (Leaseback) | J37: =IF(ISERROR($E$107),"",$E$107) -> 0 | K37: =IF(ISERROR(J37/$J$42),"",J37/$J$42) -> 0
C38: 2241 | D38: Depósitos Judiciais - Trabalhistas | F38: =IF(ISERROR(E38/$E$37),"",E38/$E$37) | H38: 2360 | I38: Imobilizado Para Locação | J38: =IF(ISERROR($E$117),"",$E$117) -> 0 | K38: =IF(ISERROR(J38/$J$42),"",J38/$J$42) -> 0
C39: 2242 | D39: Depósitos Judiciais - Fiscais e Tributários | F39: =IF(ISERROR(E39/$E$37),"",E39/$E$37) | H39: 2370 | I39: Ativo Biológico e Produto Agrícola | J39: =IF(ISERROR($E$127),"",$E$127) -> 0 | K39: =IF(ISERROR(J39/$J$42),"",J39/$J$42) -> 0
C40: 2243 | F40: =IF(ISERROR(E40/$E$37),"",E40/$E$37) | H40: 2380 | I40: Imobilzado Recebido em Comodato | J40: =IF(ISERROR($E$137),"",$E$137) -> 0 | K40: =IF(ISERROR(J40/$J$42),"",J40/$J$42) -> 0
C41: 2244 | F41: =IF(ISERROR(E41/$E$37),"",E41/$E$37) | H41: 2390 | I41: Outros | J41: =IF(ISERROR($E$147),"",$E$147) -> -12000 | K41: =IF(ISERROR(J41/$J$42),"",J41/$J$42) -> -0.15686275
C42: 2245 | F42: =IF(ISERROR(E42/$E$37),"",E42/$E$37) | H42: Resultado | J42: =IF(ISERROR(SUM($J$33:$J$41)),"",SUM($J$33:$J$41)) -> 76500
C43: 2246 | F43: =IF(ISERROR(E43/$E$37),"",E43/$E$37)
C44: 2247 | F44: =IF(ISERROR(E44/$E$37),"",E44/$E$37) | H44: Valor Total do Ativo Circulante
C45: 2248 | F45: =IF(ISERROR(E45/$E$37),"",E45/$E$37) | H45: Resultado | J45: =IF(ISERROR(SUM($J$7:$J$21)),"",SUM($J$7:$J$21)) -> 141500
C46: 2249 | D46: Outros Depósitos Judiciais | F46: =IF(ISERROR(E46/$E$37),"",E46/$E$37)
C47: 2250 | D47: Imóveis para Locação ou Venda | E47: =IF(ISERROR(SUM(E48:E56)),"",SUM(E48:E56)) -> 0
C48: 2251 | D48: Imóveis para Locação ou Venda - Terrenos | F48: =IF(ISERROR(E48/$E$47),"",E48/$E$47)
C49: 2252 | D49: Imóveis para Locação ou Venda - Escritórios | F49: =IF(ISERROR(E49/$E$47),"",E49/$E$47)
C50: 2253 | D50: Imóveis para Locação ou Venda - Galpões | F50: =IF(ISERROR(E50/$E$47),"",E50/$E$47)
C51: 2254 | D51: Imóveis para Locação ou Venda - Salas | F51: =IF(ISERROR(E51/$E$47),"",E51/$E$47)
C52: 2255 | D52: Imóveis para Locação ou Venda - Lojas | F52: =IF(ISERROR(E52/$E$47),"",E52/$E$47)
C53: 2256 | F53: =IF(ISERROR(E53/$E$47),"",E53/$E$47)
C54: 2257 | F54: =IF(ISERROR(E54/$E$47),"",E54/$E$47)
C55: 2258 | F55: =IF(ISERROR(E55/$E$47),"",E55/$E$47)
C56: 2259 | D56: Outros Imóveis para Locação ou Venda | F56: =IF(ISERROR(E56/$E$47),"",E56/$E$47)
C57: 2290 | D57: Outras Contas do Realizável | E57: =IF(ISERROR(SUM(E58:E66)),"",SUM(E58:E66)) -> 0
C58: 2291 | D58: Créditos com Pessoas Ligadas | F58: =IF(ISERROR(E58/$E$57),"",E58/$E$57)
C59: 2292 | D59: Créditos com Empresas Ligadas | F59: =IF(ISERROR(E59/$E$57),"",E59/$E$57)
C60: 2293 | D60: Adiantamentos por Conta de Imobilizações | F60: =IF(ISERROR(E60/$E$57),"",E60/$E$57)
C61: 2294 | D61: Créditos em Sociedade em Regime Especial | F61: =IF(ISERROR(E61/$E$57),"",E61/$E$57)
C62: 2295 | D62: Emprestimos e Depósitos Compulsórios | F62: =IF(ISERROR(E62/$E$57),"",E62/$E$57)
C63: 2296 | F63: =IF(ISERROR(E63/$E$57),"",E63/$E$57)
C64: 2297 | F64: =IF(ISERROR(E64/$E$57),"",E64/$E$57)
C65: 2298 | F65: =IF(ISERROR(E65/$E$57),"",E65/$E$57)
C66: 2299 | D66: Outras Contas do Realizável a Longo Prazo | F66: =IF(ISERROR(E66/$E$57),"",E66/$E$57)
C67: 2310 | D67: Investimentos | E67: =IF(ISERROR(SUM(E68:E76)),"",SUM(E68:E76)) -> 0
C68: 2311 | D68: Investimentos em Controladas | F68: =IF(ISERROR(E68/$E$67),"",E68/$E$67)
C69: 2312 | D69: Investimentos em Coligadas | F69: =IF(ISERROR(E69/$E$67),"",E69/$E$67)
C70: 2313 | D70: Investimentos por Incentivos Fiscais | F70: =IF(ISERROR(E70/$E$67),"",E70/$E$67)
C71: 2314 | D71: Títulos Patrimôniais | F71: =IF(ISERROR(E71/$E$67),"",E71/$E$67)
C72: 2315 | F72: =IF(ISERROR(E72/$E$67),"",E72/$E$67)
C73: 2316 | F73: =IF(ISERROR(E73/$E$67),"",E73/$E$67)
C74: 2317 | D74: Participações em Outras Empresas | F74: =IF(ISERROR(E74/$E$67),"",E74/$E$67)
C75: 2318 | D75: Obras de Arte e Antiguidades | F75: =IF(ISERROR(E75/$E$67),"",E75/$E$67)
C76: 2319 | D76: Outros Investimentos | F76: =IF(ISERROR(E76/$E$67),"",E76/$E$67)
C77: 2320 | D77: Imobilizado de Uso | E77: =IF(ISERROR(SUM(E78:E86)),"",SUM(E78:E86)) -> 50000
C78: 2321 | D78: Terrenos | F78: =IF(ISERROR(E78/E77),"",E78/$E$77) -> 0
C79: 2322 | D79: Edifícios e Construções | F79: =IF(ISERROR(E79/E78),"",E79/$E$77)
C80: 2323 | D80: Equipamentos, Máquinas e Instalações Industriais | F80: =IF(ISERROR(E80/E79),"",E80/$E$77)
C81: 2324 | D81: Móveis, Utensílios e Instalações Não Industriais | E81: 50000 | F81: =IF(ISERROR(E81/E80),"",E81/$E$77)
C82: 2325 | D82: Bens Oriundos de Arrendamento Mercantil | F82: =IF(ISERROR(E82/E81),"",E82/$E$77) -> 0
C83: 2326 | D83: Recursos Minerais, Recursos Florestais e Direitos de Exploração | F83: =IF(ISERROR(E83/E82),"",E83/$E$77)
C84: 2327 | D84: Veículos | F84: =IF(ISERROR(E84/E83),"",E84/$E$77)
C85: 2328 | D85: Sistemas de Comunicação e de Processamento de Dados | F85: =IF(ISERROR(E85/E84),"",E85/$E$77)
C86: 2329 | D86: Outras Imobilizações | F86: =IF(ISERROR(E86/E85),"",E86/$E$77)
C87: 2330 | D87: Ativo Diferido | E87: =IF(ISERROR(SUM(E88:E96)),"",SUM(E88:E96)) -> 18500
C88: 2331 | D88: Despesas Pré-Operacionais | F88: =IF(ISERROR(E88/$E$87),"",E88/$E$87) -> 0
C89: 2332 | D89: Despesas com Produções Científicas e Tecnológicas | E89: 18500 | F89: =IF(ISERROR(E89/$E$87),"",E89/$E$87) -> 1
C90: 2333 | D90: Demais Aplicações em Despesas Amortizáveis | F90: =IF(ISERROR(E90/$E$87),"",E90/$E$87) -> 0
C91: 2334 | D91: Benfeitorias em Imóveis de Teceiros | F91: =IF(ISERROR(E91/$E$87),"",E91/$E$87) -> 0
C92: 2335 | D92: Ágio em Participações Societárias | F92: =IF(ISERROR(E92/$E$87),"",E92/$E$87) -> 0
C93: 2336 | D93: Exploração de Recursos Florestais | F93: =IF(ISERROR(E93/$E$87),"",E93/$E$87) -> 0
C94: 2337 | D94: Prospecção e Lavra de Recursos Minerais | F94: =IF(ISERROR(E94/$E$87),"",E94/$E$87) -> 0
C95: 2338 | F95: =IF(ISERROR(E95/$E$87),"",E95/$E$87) -> 0
C96: 2339 | D96: Outras Contas do Diferido | F96: =IF(ISERROR(E96/$E$87),"",E96/$E$87) -> 0
C97: 2340 | D97: Intangível | E97: =IF(ISERROR(SUM(E98:E106)),"",SUM(E98:E106)) -> 20000
C98: 2341 | D98: Fundo de Comércio Adquirido | F98: =IF(ISERROR(E98/$E$97),"",E98/$E$97) -> 0
C99: 2342 | D99: Franquias Adquiridas e Desenvolvidas | F99: =IF(ISERROR(E99/$E$97),"",E99/$E$97) -> 0
C100: 2343 | D100: Direitos Autorais Adquiridos e Desenvolvidos | F100: =IF(ISERROR(E100/$E$97),"",E100/$E$97) -> 0
C101: 2344 | D101: Macas e Patentes Adquiridas e Desenvolvidas | E101: 20000 | F101: =IF(ISERROR(E101/$E$97),"",E101/$E$97) -> 1
C102: 2345 | D102: Investimentos em Projetos Científicos e Tecnológicos | F102: =IF(ISERROR(E102/$E$97),"",E102/$E$97) -> 0
C103: 2346 | D103: Benfeitorias em Imóveis de Teceiros | F103: =IF(ISERROR(E103/$E$97),"",E103/$E$97) -> 0
C104: 2347 | F104: =IF(ISERROR(E104/$E$97),"",E104/$E$97) -> 0
...

Sheet Pas
C1: 1. BALANÇO PATRIMÔNIAL
C6: 3400 | D6: Passivo Circulante (Deveres e Obrigações) | E6: =IF(ISERROR($E$7+$E$17+$E$27+$E$37+$E$47+$E$57+$E$67+$E$77+$E$87),"",$E$7+$E$17+$E$27+$E$37+$E$47+$E$57+$E$67+$E$77+$E$87) -> 58958 | H6: 3400 | I6: Contas do Passivo Circulante - Resultado
C7: 3410 | D7: Fornecedores | E7: =IF(ISERROR(SUM(E8:E16)),"",SUM(E8:E16)) -> 31840 | H7: 3410 | I7: Fornecedores | J7: =IF(ISERROR($E$7),"",$E$7) -> 31840 | K7: =IF(ISERROR(J7/$L$7),"",J7/$L$7) -> 0.54004546 | L7: =IF(ISERROR(SUM($J$7:$J$15)),"",SUM($J$7:$J$15)) -> 58958
C8: 3411 | D8: Fornecedores de Mercadorias para Revenda | E8: 31840 | F8: =IF(ISERROR(E8/$E$7),"",E8/$E$7) -> 1 | H8: 3410 | I8: Obrigações Financeiras a Curto Prazo | J8: =IF(ISERROR($E$17),"",$E$17) -> 0 | K8: =IF(ISERROR(J8/$L$7),"",J8/$L$7) -> 0
C9: 3412 | D9: Fornecedores de Bens para o Permanente | F9: =IF(ISERROR(E9/$E$7),"",E9/$E$7) -> 0 | H9: 3410 | I9: Obrigações Fiscais e Tributárias | J9: =IF(ISERROR($E$27),"",$E$27) -> 0 | K9: =IF(ISERROR(J9/$L$7),"",J9/$L$7) -> 0
C10: 3413 | D10: Fornecedores de Matérias Primas para a Industrialização | F10: =IF(ISERROR(E10/$E$7),"",E10/$E$7) -> 0 | H10: 3410 | I10: Obrigações Trabalhistas e Previdenciárias | J10: =IF(ISERROR($E$37),"",$E$37) -> 12750 | K10: =IF(ISERROR(J10/$L$7),"",J10/$L$7) -> 0.21625564
C11: 3414 | D11: Fornecedores de Peças de Reposição | F11: =IF(ISERROR(E11/$E$7),"",E11/$E$7) -> 0 | H11: 3410 | I11: Obrigações Sociais e Estatutárias | J11: =IF(ISERROR($E$47),"",$E$47) -> 8874 | K11: =IF(ISERROR(J11/$L$7),"",J11/$L$7) -> 0.15051393
C12: 3415 | D12: Fornecedores de Bens em Consignação ou Comodato | F12: =IF(ISERROR(E12/$E$7),"",E12/$E$7) -> 0 | H12: 3410 | I12: Obrigações Administrativas e Operacionais | J12: =IF(ISERROR($E$57),"",$E$57) -> 5494 | K12: =IF(ISERROR(J12/$L$7),"",J12/$L$7) -> 0.093184979
C13: 3416 | D13: Forncedores de Material de Expediente | F13: =IF(ISERROR(E13/$E$7),"",E13/$E$7) -> 0 | H13: 3410 | I13: Provisões para Contingências | J13: =IF(ISERROR($E$67),"",$E$67) -> 0 | K13: =IF(ISERROR(J13/$L$7),"",J13/$L$7) -> 0
C14: 3417 | F14: =IF(ISERROR(E14/$E$7),"",E14/$E$7) -> 0 | H14: 3410 | I14: Relações Interfinanceiras | J14: =IF(ISERROR($E$77),"",$E$77) -> 0 | K14: =IF(ISERROR(J14/$L$7),"",J14/$L$7) -> 0
C15: 3418 | D15: Fornecedores no Exterior | F15: =IF(ISERROR(E15/$E$7),"",E15/$E$7) -> 0 | H15: 3410 | I15: Outras Obrigações | J15: =IF(ISERROR($E$87),"",$E$87) -> 0 | K15: =IF(ISERROR(J15/$L$7),"",J15/$L$7) -> 0
C16: 3419 | D16: Outros Fornecedores | F16: =IF(ISERROR(E16/$E$7),"",E16/$E$7) -> 0
C17: 3420 | D17: Obrigações Financeiras de Curto Prazo | E17: =IF(ISERROR(SUM(E18:E26)),"",SUM(E18:E26)) -> 0 | H17: 3400 | I17: Obrigações Realizáveis a Curto Prazo
C18: 3421 | D18: Bancos Oficiais Federais | F18: =IF(ISERROR(E18/$E$17),"",E18/$E$17) | H18: 3410 | I18: Fornecedores | J18: =IF(ISERROR($E$7),"",$E$7) -> 31840 | K18: =IF(ISERROR(J18/$J$21),"",J18/$J$21) -> 2.4972549
C19: 3422 | D19: Bancos Oficiais Estaduais | F19: =IF(ISERROR(E19/$E$17),"",E19/$E$17) | H19: 3410 | I19: Obrigações Financeiras a Curto Prazo | J19: =IF(ISERROR($E$17),"",$E$17) -> 0 | K19: =IF(ISERROR(J19/$J$21),"",J19/$J$21) -> 0
C20: 3423 | D20: Bancos Privados no Brasil | F20: =IF(ISERROR(E20/$E$17),"",E20/$E$17) | H20: 3410 | I20: Obrigações Fiscais e Tributárias | J20: =IF(ISERROR($E$27),"",$E$27) -> 0 | K20: =IF(ISERROR(J20/$J$21),"",J20/$J$21) -> 0
C21: 3424 | D21: Bancos Oficiais no Exterior | F21: =IF(ISERROR(E21/$E$17),"",E21/$E$17) | H21: 3410 | I21: Obrigações Trabalhistas e Previdenciárias | J21: =IF(ISERROR($E$37),"",$E$37) -> 12750 | K21: =IF(ISERROR(J21/$J$21),"",J21/$J$21) -> 1
C22: 3425 | D22: Outros Bancos no Exterior | F22: =IF(ISERROR(E22/$E$17),"",E22/$E$17) | H22: 3410 | I22: Obrigações Sociais e Estatutárias | J22: =IF(ISERROR($E$47),"",$E$47) -> 8874 | K22: =IF(ISERROR(J22/$J$21),"",J22/$J$21) -> 0.696
C23: 3426 | D23: Empresas de Factoring / Forfaiting | F23: =IF(ISERROR(E23/$E$17),"",E23/$E$17) | H23: 3410 | I23: Provisões para Contingências | J23: =IF(ISERROR($E$67),"",$E$67) -> 0 | K23: =IF(ISERROR(J23/$J$21),"",J23/$J$21) -> 0
C24: 3427 | F24: =IF(ISERROR(E24/$E$17),"",E24/$E$17) | H24: Resultado | J24: =IF(ISERROR(SUM($J$18:$J$23)),"",SUM($J$18:$J$23)) -> 53464
C25: 3428 | D25: Box de Captação | F25: =IF(ISERROR(E25/$E$17),"",E25/$E$17)
C26: 3429 | D26: Outros Financiamentos de Curto Prazo | F26: =IF(ISERROR(E26/$E$17),"",E26/$E$17) | H26: Valor Total do Passivo Circulante
C27: 3430 | D27: Obrigações Fiscais e Tributárias | E27: =IF(ISERROR(SUM(E28:E36)),"",SUM(E28:E36)) -> 0 | H27: Resultado | J27: =IF(ISERROR(SUM($J$7:$J$15)),"",SUM($J$7:$J$15)) -> 58958
C28: 3431 | D28: Imposto de Renda Retido na Fonte | F28: =IF(ISERROR(E28/$E$27),"",E28/$E$27)
C29: 3432 | D29: Imposto de Renda e Contribuição Social a Pagar | F29: =IF(ISERROR(E29/$E$27),"",E29/$E$27)
C30: 3433 | D30: Outros Impostos Federais | F30: =IF(ISERROR(E30/$E$27),"",E30/$E$27)
C31: 3434 | D31: Impostos Estaduais | F31: =IF(ISERROR(E31/$E$27),"",E31/$E$27)
C32: 3435 | D32: Impostos Municipais | F32: =IF(ISERROR(E32/$E$27),"",E32/$E$27)
C33: 3436 | F33: =IF(ISERROR(E33/$E$27),"",E33/$E$27)
C34: 3437 | F34: =IF(ISERROR(E34/$E$27),"",E34/$E$27)
C35: 3438 | F35: =IF(ISERROR(E35/$E$27),"",E35/$E$27)
C36: 3439 | D36: Outras Obrigações Fiscais e Tributárias | F36: =IF(ISERROR(E36/$E$27),"",E36/$E$27)
C37: 3440 | D37: Obrigações Trabalhistas e Previdenciárias | E37: =IF(ISERROR(SUM(E38:E46)),"",SUM(E38:E46)) -> 12750
C38: 3441 | D38: Ordenados e Salários a Pagar | E38: 12750 | F38: =IF(ISERROR(E38/$E$37),"",E38/$E$37) -> 1
C39: 3442 | D39: Autonômos - Pessoas Físicas | F39: =IF(ISERROR(E39/$E$37),"",E39/$E$37) -> 0
C40: 3443 | D40: Terceirizados - Pessoas Jurídicas | F40: =IF(ISERROR(E40/$E$37),"",E40/$E$37) -> 0
C41: 3444 | D41: Contribuição ao INSS | F41: =IF(ISERROR(E41/$E$37),"",E41/$E$37) -> 0
C42: 3445 | D42: FGTS | F42: =IF(ISERROR(E42/$E$37),"",E42/$E$37) -> 0
C43: 3446 | D43: Contribuição Sindical | F43: =IF(ISERROR(E43/$E$37),"",E43/$E$37) -> 0
C44: 3447 | D44: Indenizações Trabalhistas a Pagar | F44: =IF(ISERROR(E44/$E$37),"",E44/$E$37) -> 0
C45: 3448 | D45: Débitos Previdenciários a Pagar | F45: =IF(ISERROR(E45/$E$37),"",E45/$E$37) -> 0
C46: 3449 | D46: Outras Obrigações Trabalhistas e Previdenciárias | F46: =IF(ISERROR(E46/$E$37),"",E46/$E$37) -> 0
C47: 3450 | D47: Obrigações Sociais e Estatutárias | E47: =IF(ISERROR(SUM(E48:E56)),"",SUM(E48:E56)) -> 8874
C48: 3451 | D48: Antecipação de Lucros e Dividendos a Pagar | F48: =IF(ISERROR(E48/$E$47),"",E48/$E$47) -> 0
C49: 3452 | D49: Lucros e Divendendos a Distribuir | E49: 8874 | F49: =IF(ISERROR(E49/$E$47),"",E49/$E$47) -> 1
C50: 3453 | D50: Participação nos Lucros a Pagar | F50: =IF(ISERROR(E50/$E$47),"",E50/$E$47) -> 0
C51: 3454 | D51: Juros sobre Capital a Pagar | F51: =IF(ISERROR(E51/$E$47),"",E51/$E$47) -> 0
C52: 3455 | D52: Juros de Debêntures a Pagar | F52: =IF(ISERROR(E52/$E$47),"",E52/$E$47) -> 0
C53: 3456 | D53: Debêntures a Resgatar | F53: =IF(ISERROR(E53/$E$47),"",E53/$E$47) -> 0
C54: 3457 | D54: Ações Preferenciais Resgatáveis a Liquidar | F54: =IF(ISERROR(E54/$E$47),"",E54/$E$47) -> 0
C55: 3458 | D55: Outros Valores Mobiliários a Pagar | F55: =IF(ISERROR(E55/$E$47),"",E55/$E$47) -> 0
C56: 3459 | D56: Outros Divedendos e Lucros a Pagar | F56: =IF(ISERROR(E56/$E$47),"",E56/$E$47) -> 0
C57: 3460 | D57: Obrigações Administrativas e Operacionais | E57: =IF(ISERROR(SUM(E58:E66)),"",SUM(E58:E66)) -> 5494
C58: 3461 | D58: Provisão para Pagamento a Efetuar (Agua, Luz, Gás, Telefone) | F58: =IF(ISERROR(E58/$E$57),"",E58/$E$57) -> 0
C59: 3462 | D59: IPVA, Multas de Trânsito e Despesas Correspondentes | F59: =IF(ISERROR(E59/$E$57),"",E59/$E$57) -> 0
C60: 3463 | D60: Alugueis e Condomínios a Pagar | E60: 5494 | F60: =IF(ISERROR(E60/$E$57),"",E60/$E$57) -> 1
C61: 3464 | D61: Arrendamento Mercantil a Pagar | F61: =IF(ISERROR(E61/$E$57),"",E61/$E$57) -> 0
C62: 3465 | F62: =IF(ISERROR(E62/$E$57),"",E62/$E$57) -> 0
C63: 3466 | F63: =IF(ISERROR(E63/$E$57),"",E63/$E$57) -> 0
C64: 3467 | F64: =IF(ISERROR(E64/$E$57),"",E64/$E$57) -> 0
C65: 3468 | F65: =IF(ISERROR(E65/$E$57),"",E65/$E$57) -> 0
C66: 3469 | D66: Outras Obrigações Administrativas e Operacionais | F66: =IF(ISERROR(E66/$E$57),"",E66/$E$57) -> 0
C67: 3470 | D67: Provisões para Contingências | E67: =IF(ISERROR(SUM(E68:E76)),"",SUM(E68:E76)) -> 0
C68: 3471 | D68: Provisão para Pagamento de Contingências Trabalhistas | F68: =IF(ISERROR(E68/$E$67),"",E68/$E$67)
C69: 3472 | D69: Provisão para Pagamento de Contingências Tributárias | F69: =IF(ISERROR(E69/$E$67),"",E69/$E$67)
C70: 3473 | D70: Provisão para Pagamento de Contingências Previdenciárias | F70: =IF(ISERROR(E70/$E$67),"",E70/$E$67)
C71: 3474 | D71: Provisão para Pagamento de Contingências Civis e Comerciais | F71: =IF(ISERROR(E71/$E$67),"",E71/$E$67)
C72: 3475 | D72: Provisão para Pagamento de Contingências Societárias | F72: =IF(ISERROR(E72/$E$67),"",E72/$E$67)
C73: 3476 | F73: =IF(ISERROR(E73/$E$67),"",E73/$E$67)
C74: 3477 | F74: =IF(ISERROR(E74/$E$67),"",E74/$E$67)
C75: 3478 | F75: =IF(ISERROR(E75/$E$67),"",E75/$E$67)
C76: 3479 | D76: Outras Provisão para Pagamento de Contingências e Calculáveis | F76: =IF(ISERROR(E76/$E$67),"",E76/$E$67)
C77: 3480 | D77: Relações Interfinanceiras | E77: =IF(ISERROR(SUM(E78:E86)),"",SUM(E78:E86)) -> 0
C78: 3481 | D78: Relações entre Matriz e Filiais | F78: =IF(ISERROR(E78/$E$77),"",E78/$E$77)
C79: 3482 | D79: Relações entre Controladora e Controladas | F79: =IF(ISERROR(E79/$E$77),"",E79/$E$77)
C80: 3483 | D80: Relações com Coligadas | F80: =IF(ISERROR(E80/$E$77),"",E80/$E$77)
C81: 3484 | D81: Relações com Representantes | F81: =IF(ISERROR(E81/$E$77),"",E81/$E$77)
C82: 3485 | D82: Relações com Sócios ou Acionistas | F82: =IF(ISERROR(E82/$E$77),"",E82/$E$77)
C83: 3486 | F83: =IF(ISERROR(E83/$E$77),"",E83/$E$77)
C84: 3487 | D84: Relações com Correspondentes | F84: =IF(ISERROR(E84/$E$77),"",E84/$E$77)
C85: 3488 | F85: =IF(ISERROR(E85/$E$77),"",E85/$E$77)
C86: 3489 | D86: Outras Relações Interfinanceiras | F86: =IF(ISERROR(E86/$E$77),"",E86/$E$77)
C87: 3490 | D87: Outras Obrigações | E87: =IF(ISERROR(SUM(E88:E96)),"",SUM(E88:E96)) -> 0
C88: 3491 | D88: Credores por Intermediação Financeira | F88: =IF(ISERROR(E88/$E$87),"",E88/$E$87)
C89: 3492 | F89: =IF(ISERROR(E89/$E$87),"",E89/$E$87)
C90: 3493 | F90: =IF(ISERROR(E90/$E$87),"",E90/$E$87)
C91: 3494 | F91: =IF(ISERROR(E91/$E$87),"",E91/$E$87)
C92: 3495 | F92: =IF(ISERROR(E92/$E$87),"",E92/$E$87)
C93: 3496 | F93: =IF(ISERROR(E93/$E$87),"",E93/$E$87)
C94: 3497 | F94: =IF(ISERROR(E94/$E$87),"",E94/$E$87)
C95: 3498 | F95: =IF(ISERROR(E95/$E$87),"",E95/$E$87)
C96: 3499 | D96: Diversos Outros Credores por Obrigações a Pagar | F96: =IF(ISERROR(E96/$E$87),"",E96/$E$87)

Sheet Pasn
C1: 1. BALANÇO PATRIMÔNIAL
C6: 4000 | D6: Passivo Não Circulante (Deveres e Obrigações) | E6: =IF(ISERROR($E$7+$E$17+$E$27+$E$37+$E$47+$E$57+$E$67+$E$77+$E$87+$E$97+$E$107+$E$117+$E$127+$E$137+$E$147+$E$157+$E$167+$E$177+$E$187+$E$197),"",$E$7+$E$17+$E$27+$E$37+$E$47+$E$57+$E$67+$E$77+$E$87+$E$97+$E$107+$E$117+$E$127+$E$137+$E$147+$E$157+$E$167+$E$177+$E$187+$E$197) -> 235822 | H6: 4000 | I6: Contas do Passivo Não Circulante - Resultado
C7: 4510 | D7: Fornecedores | E7: =IF(ISERROR(SUM(E8:E16)),"",SUM(E8:E16)) -> 50000 | H7: 4510 | I7: Fornecedores | J7: =IF(ISERROR($E$7),"",$E$7) -> 50000 | K7: =IF(ISERROR(J7/$L$7),"",J7/$L$7) -> 0.21202432 | L7: =IF(ISERROR(SUM($J$7:$J$26)),"",SUM($J$7:$J$26)) -> 235822
C8: 4511 | D8: Fornecedores de Bens do Ativo Permanente | E8: 50000 | F8: =IF(ISERROR(E8/$E$7),"",E8/$E$7) -> 1 | H8: 4520 | I8: Obrigações Financeiras a Longo Prazo | J8: =IF(ISERROR($E$17),"",$E$17) -> 0 | K8: =IF(ISERROR(J8/$L$7),"",J8/$L$7) -> 0
C9: 4512 | F9: =IF(ISERROR(E9/$E$7),"",E9/$E$7) -> 0 | H9: 4530 | I9: Obrigações Fiscais e Tributárias | J9: =IF(ISERROR($E$27),"",$E$27) -> 0 | K9: =IF(ISERROR(J9/$L$7),"",J9/$L$7) -> 0
C10: 4513 | F10: =IF(ISERROR(E10/$E$7),"",E10/$E$7) -> 0 | H10: 4540 | I10: Obrigações Trabalhistas e Previdenciárias | J10: =IF(ISERROR($E$37),"",$E$37) -> 0 | K10: =IF(ISERROR(J10/$L$7),"",J10/$L$7) -> 0
C11: 4514 | F11: =IF(ISERROR(E11/$E$7),"",E11/$E$7) -> 0 | H11: 4550 | I11: Obrigações Sociais e Estatutárias | J11: =IF(ISERROR($E$47),"",$E$47) -> 0 | K11: =IF(ISERROR(J11/$L$7),"",J11/$L$7) -> 0
C12: 4515 | F12: =IF(ISERROR(E12/$E$7),"",E12/$E$7) -> 0 | H12: 4560 | I12: Créditos de Coligadas e Controladas | J12: =IF(ISERROR($E$57),"",$E$57) -> 0 | K12: =IF(ISERROR(J12/$L$7),"",J12/$L$7) -> 0
C13: 4516 | F13: =IF(ISERROR(E13/$E$7),"",E13/$E$7) -> 0 | H13: 4570 | I13: Provisões para Contingências | J13: =IF(ISERROR($E$67),"",$E$67) -> 0 | K13: =IF(ISERROR(J13/$L$7),"",J13/$L$7) -> 0
C14: 4517 | F14: =IF(ISERROR(E14/$E$7),"",E14/$E$7) -> 0 | H14: 4580 | I14: Receitas Diferidas | J14: =IF(ISERROR($E$77),"",$E$77) -> 0 | K14: =IF(ISERROR(J14/$L$7),"",J14/$L$7) -> 0
C15: 4518 | F15: =IF(ISERROR(E15/$E$7),"",E15/$E$7) -> 0 | H15: 4590 | I15: Outras Obrigações | J15: =IF(ISERROR($E$87),"",$E$87) -> 0 | K15: =IF(ISERROR(J15/$L$7),"",J15/$L$7) -> 0
C16: 4519 | D16: Outros Fornecedores do Longo Prazo | F16: =IF(ISERROR(E16/$E$7),"",E16/$E$7) -> 0 | H16: 4610 | I16: Resultados de Exercícios Futuros - Receitas Diferidas | J16: =IF(ISERROR($E$97),"",$E$97) -> 0 | K16: =IF(ISERROR(J16/$L$7),"",J16/$L$7) -> 0
C17: 4520 | D17: Obrigações Financeiras de Longo Prazo | E17: =IF(ISERROR(SUM(E18:E26)),"",SUM(E18:E26)) -> 0 | H17: 4620 | I17: Custos e Despesas de Exercícios Futuros | J17: =IF(ISERROR($E$107),"",$E$107) -> 0 | K17: =IF(ISERROR(J17/$L$7),"",J17/$L$7) -> 0
C18: 4521 | D18: Bancos Oficiais Federais | F18: =IF(ISERROR(E18/$E$17),"",E18/$E$17) | H18: 5710 | I18: Capital / Capital Social / Patrimônio Social | J18: =IF(ISERROR($E$117),"",$E$117) -> 120000 | K18: =IF(ISERROR(J18/$L$7),"",J18/$L$7) -> 0.50885838
C19: 4522 | D19: Bancos Oficiais Estaduais | F19: =IF(ISERROR(E19/$E$17),"",E19/$E$17) | H19: 5720 | I19: Reserva de Capital | J19: =IF(ISERROR($E$127),"",$E$127) -> 1556 | K19: =IF(ISERROR(J19/$L$7),"",J19/$L$7) -> 0.0065981969
C20: 4523 | D20: Bancos Privados no Brasil | F20: =IF(ISERROR(E20/$E$17),"",E20/$E$17) | H20: 5730 | I20: Ações em Tesouraria | J20: =IF(ISERROR($E$137),"",$E$137) -> 0 | K20: =IF(ISERROR(J20/$L$7),"",J20/$L$7) -> 0
C21: 4524 | D21: Bancos Privados no Exterior | F21: =IF(ISERROR(E21/$E$17),"",E21/$E$17) | H21: 5740 | I21: Ajustes de Avaliação Patrimônial | J21: =IF(ISERROR($E$147),"",$E$147) -> 0 | K21: =IF(ISERROR(J21/$L$7),"",J21/$L$7) -> 0
C22: 4525 | D22: Outros Bancos no Exterior | F22: =IF(ISERROR(E22/$E$17),"",E22/$E$17) | H22: 5750 | I22: Reservas de Lucros | J22: =IF(ISERROR($E$157),"",$E$157) -> 64266 | K22: =IF(ISERROR(J22/$L$7),"",J22/$L$7) -> 0.2725191
C23: 4526 | D23: Empresas de Factoring / Forfaiting | F23: =IF(ISERROR(E23/$E$17),"",E23/$E$17) | H23: 5760 | I23: Reservas de Reavaliação | J23: =IF(ISERROR($E$167),"",$E$167) -> 0 | K23: =IF(ISERROR(J23/$L$7),"",J23/$L$7) -> 0
C24: 4527 | D24: Box de Captção | F24: =IF(ISERROR(E24/$E$17),"",E24/$E$17) | H24: 5770 | I24: Outras Reservas | J24: =IF(ISERROR($E$177),"",$E$177) -> 0 | K24: =IF(ISERROR(J24/$L$7),"",J24/$L$7) -> 0
C25: 4528 | F25: =IF(ISERROR(E25/$E$17),"",E25/$E$17) | H25: 5780 | I25: Lucros Acumulados / Sobras / Superávits | J25: =IF(ISERROR($E$187),"",$E$187) -> 0 | K25: =IF(ISERROR(J25/$L$7),"",J25/$L$7) -> 0
C26: 4529 | D26: Outros Financiamentos de Longo Prazo | F26: =IF(ISERROR(E26/$E$17),"",E26/$E$17) | H26: 5790 | I26: Prejuízos, Perdas e Déficits Acumulados | J26: =IF(ISERROR($E$197),"",$E$197) -> 0 | K26: =IF(ISERROR(J26/$L$7),"",J26/$L$7) -> 0
C27: 4530 | D27: Obrigações Fiscais e Tributárias | E27: =IF(ISERROR(SUM(E28:E36)),"",SUM(E28:E36)) -> 0
C28: 4531 | D28: Imposto de Renda Diferido | F28: =IF(ISERROR(E28/$E$27),"",E28/$E$27) | H28: 4500 | I28: Obrigações Realizáveis a Longo Prazo
C29: 4532 | D29: Parcelamentos de Débitos Tributários e Federais | F29: =IF(ISERROR(E29/$E$27),"",E29/$E$27) | H29: 4510 | I29: Fornecedores | J29: =IF(ISERROR($E$7),"",$E$7) -> 50000 | K29: =IF(ISERROR(J29/$J$38),"",J29/$J$38) -> 1
C30: 4533 | D30: Parcelamentos de Débitos Tributários e Estaduais | F30: =IF(ISERROR(E30/$E$27),"",E30/$E$27) | H30: 4520 | I30: Obrigações Financeiras a Longo Prazo | J30: =IF(ISERROR($E$17),"",$E$17) -> 0 | K30: =IF(ISERROR(J30/$J$38),"",J30/$J$38) -> 0
C31: 4534 | D31: Parcelamentos de Débitos Tributários e Municipais | F31: =IF(ISERROR(E31/$E$27),"",E31/$E$27) | H31: 4530 | I31: Obrigações Fiscais e Tributárias | J31: =IF(ISERROR($E$27),"",$E$27) -> 0 | K31: =IF(ISERROR(J31/$J$38),"",J31/$J$38) -> 0
C32: 4535 | D32: Contribuição Social Diferida | F32: =IF(ISERROR(E32/$E$27),"",E32/$E$27) | H32: 4540 | I32: Obrigações Trabalhistas e Previdenciárias | J32: =IF(ISERROR($E$37),"",$E$37) -> 0 | K32: =IF(ISERROR(J32/$J$38),"",J32/$J$38) -> 0
C33: 4536 | D33: Outras Provisões para Impostos Diferidos | F33: =IF(ISERROR(E33/$E$27),"",E33/$E$27) | H33: 4550 | I33: Obrigações Sociais e Estatutárias | J33: =IF(ISERROR($E$47),"",$E$47) -> 0 | K33: =IF(ISERROR(J33/$J$38),"",J33/$J$38) -> 0
C34: 4537 | F34: =IF(ISERROR(E34/$E$27),"",E34/$E$27) | H34: 4560 | I34: Créditos de Coligadas e Controladas | J34: =IF(ISERROR($E$57),"",$E$57) -> 0 | K34: =IF(ISERROR(J34/$J$38),"",J34/$J$38) -> 0
C35: 4538 | F35: =IF(ISERROR(E35/$E$27),"",E35/$E$27) | H35: 4570 | I35: Provisões para Contingências | J35: =IF(ISERROR($E$67),"",$E$67) -> 0 | K35: =IF(ISERROR(J35/$J$38),"",J35/$J$38) -> 0
C36: 4539 | D36: Outras Obrigações Fiscais e Tributárias | F36: =IF(ISERROR(E36/$E$27),"",E36/$E$27) | H36: 4580 | I36: Receitas Diferidas | J36: =IF(ISERROR($E$77),"",$E$77) -> 0 | K36: =IF(ISERROR(J36/$J$38),"",J36/$J$38) -> 0
C37: 4540 | D37: Obrigações Trabalhistas e Previdenciárias | E37: =IF(ISERROR(SUM(E38:E46)),"",SUM(E38:E46)) -> 0 | H37: 4590 | I37: Outras Obrigações | J37: =IF(ISERROR($E$87),"",$E$87) -> 0 | K37: =IF(ISERROR(J37/$J$38),"",J37/$J$38) -> 0
C38: 4541 | D38: Ações Judiciais Trabalhistas | F38: =IF(ISERROR(E38/$E$37),"",E38/$E$37) | H38: Resultado | J38: =IF(ISERROR(SUM($J$29:$J$37)),"",SUM($J$29:$J$37)) -> 50000
C39: 4542 | D39: Ações Judiciais Previdenciárias | F39: =IF(ISERROR(E39/$E$37),"",E39/$E$37)
C40: 4543 | D40: Parcelamento de Débitos Trabalhistas | F40: =IF(ISERROR(E40/$E$37),"",E40/$E$37) | H40: 4600 | I40: Resultado de Exercícios Futuros
C41: 4544 | D41: Parcelamento de Débitos Previdenciários | F41: =IF(ISERROR(E41/$E$37),"",E41/$E$37) | H41: 4610 | I41: Resultados de Exercícios Futuros - Receitas Diferidas | J41: =IF(ISERROR($E$97),"",$E$97) -> 0 | K41: =IF(ISERROR(J41/$J$43),"",J41/$J$43)
C42: 4545 | F42: =IF(ISERROR(E42/$E$37),"",E42/$E$37) | H42: 4620 | I42: Custos e Despesas de Exercícios Futuros | J42: =IF(ISERROR($E$107),"",$E$107) -> 0 | K42: =IF(ISERROR(J42/$J$43),"",J42/$J$43)
C43: 4546 | F43: =IF(ISERROR(E43/$E$37),"",E43/$E$37) | H43: Resultado | J43: =IF(ISERROR(SUM($J$41:$J$42)),"",SUM($J$41:$J$42)) -> 0
C44: 4547 | F44: =IF(ISERROR(E44/$E$37),"",E44/$E$37)
C45: 4548 | F45: =IF(ISERROR(E45/$E$37),"",E45/$E$37) | H45: 5700 | I45: Patrimônio Liquido
C46: 4549 | D46: Outras Obrigações Trabalhistas e Previdenciárias | F46: =IF(ISERROR(E46/$E$37),"",E46/$E$37) | H46: 5710 | I46: Capital / Capital Social / Patrimônio Social | J46: =IF(ISERROR($E$117),"",$E$117) -> 120000 | K46: =IF(ISERROR(J46/$J$55),"",J46/$J$55) -> 0.64577929
C47: 4550 | D47: Obrigações Sociais e Estatutárias de Longo Prazo | E47: =IF(ISERROR(SUM(E48:E56)),"",SUM(E48:E56)) -> 0 | H47: 5720 | I47: Reserva de Capital | J47: =IF(ISERROR($E$127),"",$E$127) -> 1556 | K47: =IF(ISERROR(J47/$J$51),"",J47/$J$51)
C48: 4552 | D48: Antecipações de Dividendos a Pagar de Longo Prazo | F48: =IF(ISERROR(E48/$E$47),"",E48/$E$47) | H48: 5730 | I48: Ações em Tesouraria | J48: =IF(ISERROR($E$137),"",$E$137) -> 0 | K48: =IF(ISERROR(J48/$J$51),"",J48/$J$51)
C49: 4553 | D49: Dividendos a Distribuir a Longo Prazo | F49: =IF(ISERROR(E49/$E$47),"",E49/$E$47) | H49: 5740 | I49: Ajustes de Avaliação Patrimônial | J49: =IF(ISERROR($E$147),"",$E$147) -> 0 | K49: =IF(ISERROR(J49/$J$51),"",J49/$J$51)
C50: 4554 | D50: Participação nos Lucros a Pagar de Longo Prazo | F50: =IF(ISERROR(E50/$E$47),"",E50/$E$47) | H50: 5750 | I50: Reservas de Lucros | J50: =IF(ISERROR($E$157),"",$E$157) -> 64266 | K50: =IF(ISERROR(J50/$J$51),"",J50/$J$51)
C51: 4555 | D51: Juros sobre Capital a Pagar de Longo Prazo | F51: =IF(ISERROR(E51/$E$47),"",E51/$E$47) | H51: 5760 | I51: Reservas de Reavaliação | J51: =IF(ISERROR($E$167),"",$E$167) -> 0 | K51: =IF(ISERROR(J51/$J$51),"",J51/$J$51)
C52: 4556 | F52: =IF(ISERROR(E52/$E$47),"",E52/$E$47) | H52: 5770 | I52: Outras Reservas | J52: =IF(ISERROR($E$177),"",$E$177) -> 0 | K52: =IF(ISERROR(J52/$J$51),"",J52/$J$51)
C53: 4557 | F53: =IF(ISERROR(E53/$E$47),"",E53/$E$47) | H53: 5780 | I53: Lucros Acumulados / Sobras / Superávits | J53: =IF(ISERROR($E$187),"",$E$187) -> 0 | K53: =IF(ISERROR(J53/$J$51),"",J53/$J$51)
C54: 4558 | F54: =IF(ISERROR(E54/$E$47),"",E54/$E$47) | H54: 5790 | I54: Prejuízos, Perdas e Déficits Acumulados | J54: =IF(ISERROR($E$197),"",$E$197) -> 0 | K54: =IF(ISERROR(J54/$J$51),"",J54/$J$51)
C55: 4559 | F55: =IF(ISERROR(E55/$E$47),"",E55/$E$47) | H55: Resultado | J55: =IF(ISERROR(SUM($J$46:$J$54)),"",SUM($J$46:$J$54)) -> 185822
C56: 4551 | D56: Outras Obrigações Sociais e Estatutárias de Longo Prazo | F56: =IF(ISERROR(E56/$E$47),"",E56/$E$47)
C57: 4560 | D57: Créditos de Coligadas e Controladas | E57: =IF(ISERROR(SUM(E58:E66)),"",SUM(E58:E66)) -> 0 | H57: Valor Total do Passivo Não Circulante
C58: 4561 | D58: Empresas Controladas | F58: =IF(ISERROR(E58/$E$57),"",E58/$E$57) | H58: Resultado | J58: =IF(ISERROR(SUM($J$7:$J$26)),"",SUM($J$7:$J$26)) -> 235822
C59: 4562 | D59: Empresas Coligadas | F59: =IF(ISERROR(E59/$E$57),"",E59/$E$57)
C60: 4563 | D60: Administradores | F60: =IF(ISERROR(E60/$E$57),"",E60/$E$57)
C61: 4564 | D61: Controladores | F61: =IF(ISERROR(E61/$E$57),"",E61/$E$57)
C62: 4565 | D62: Acionistas Minoritários | F62: =IF(ISERROR(E62/$E$57),"",E62/$E$57)
C63: 4566 | F63: =IF(ISERROR(E63/$E$57),"",E63/$E$57)
C64: 4567 | F64: =IF(ISERROR(E64/$E$57),"",E64/$E$57)
C65: 4568 | F65: =IF(ISERROR(E65/$E$57),"",E65/$E$57)
C66: 4569 | D66: Outros Créditos com Ligadas | F66: =IF(ISERROR(E66/$E$57),"",E66/$E$57)
C67: 4570 | D67: Provisões para Contingências de Longo Prazo | E67: =IF(ISERROR(SUM(E68:E76)),"",SUM(E68:E76)) -> 0
C68: 4571 | D68: Provisões para Contingências Trabalhistas de Longo Prazo | F68: =IF(ISERROR(E68/$E$67),"",E68/$E$67)
C69: 4572 | D69: Provisões para Contingências Tributárias de Longo Prazo | F69: =IF(ISERROR(E69/$E$67),"",E69/$E$67)
C70: 4573 | D70: Provisões para Contingências Previdenciárias de Longo Prazo | F70: =IF(ISERROR(E70/$E$67),"",E70/$E$67)
C71: 4574 | D71: Provisões para Contingências Civis e Comerciais de Longo Prazo | F71: =IF(ISERROR(E71/$E$67),"",E71/$E$67)
C72: 4575 | D72: Provisões para Contingências Societárias de Longo Prazo | F72: =IF(ISERROR(E72/$E$67),"",E72/$E$67)
C73: 4576 | F73: =IF(ISERROR(E73/$E$67),"",E73/$E$67)
C74: 4577 | F74: =IF(ISERROR(E74/$E$67),"",E74/$E$67)
C75: 4578 | F75: =IF(ISERROR(E75/$E$67),"",E75/$E$67)
C76: 4579 | D76: Outras Provisões para Contingências de Longo Prazo | F76: =IF(ISERROR(E76/$E$67),"",E76/$E$67)
C77: 4580 | D77: Receitas Diferidas | E77: =IF(ISERROR(SUM(E78:E86)),"",SUM(E78:E86)) -> 0
C78: 4581 | D78: Receitas Diferidas | F78: =IF(ISERROR(E78/$E$77),"",E78/$E$77)
C79: 4582 | D79: Custos e Despesas Corresnpondentes às Receitas Diferidas | F79: =IF(ISERROR(E79/$E$77),"",E79/$E$77)
C80: 4583 | F80: =IF(ISERROR(E80/$E$77),"",E80/$E$77)
C81: 4584 | F81: =IF(ISERROR(E81/$E$77),"",E81/$E$77)
C82: 4585 | F82: =IF(ISERROR(E82/$E$77),"",E82/$E$77)
C83: 4586 | F83: =IF(ISERROR(E83/$E$77),"",E83/$E$77)
C84: 4587 | F84: =IF(ISERROR(E84/$E$77),"",E84/$E$77)
C85: 4588 | F85: =IF(ISERROR(E85/$E$77),"",E85/$E$77)
C86: 4589 | F86: =IF(ISERROR(E86/$E$77),"",E86/$E$77)
C87: 4590 | D87: Outras Obrigações a Longo Prazo | E87: =IF(ISERROR(SUM(E88:E96)),"",SUM(E88:E96)) -> 0
C88: 4591 | F88: =IF(ISERROR(E88/$E$87),"",E88/$E$87)
C89: 4592 | F89: =IF(ISERROR(E89/$E$87),"",E89/$E$87)
C90: 4593 | F90: =IF(ISERROR(E90/$E$87),"",E90/$E$87)
C91: 4594 | F91: =IF(ISERROR(E91/$E$87),"",E91/$E$87)
C92: 4595 | F92: =IF(ISERROR(E92/$E$87),"",E92/$E$87)
C93: 4596 | F93: =IF(ISERROR(E93/$E$87),"",E93/$E$87)
C94: 4597 | F94: =IF(ISERROR(E94/$E$87),"",E94/$E$87)
C95: 4598 | F95: =IF(ISERROR(E95/$E$87),"",E95/$E$87)
C96: 4599 | D96: Diversas Outras Contas do Exigível | F96: =IF(ISERROR(E96/$E$87),"",E96/$E$87)
C97: 4610 | D97: Resultados de Exercícios Futuros - Receitas Diferidas | E97: =IF(ISERROR(SUM(E98:E106)),"",SUM(E98:E106)) -> 0
C98: 4611 | D98: Receitas do Exercício Seguinte | F98: =IF(ISERROR(E98/$E$97),"",E98/$E$97)
C99: 4612 | D99: Receitas dos Demais Exercícios Futuros | F99: =IF(ISERROR(E99/$E$97),"",E99/$E$97)
C100: 4613 | D100: Deságios na Aquisição de Participações Societárias | F100: =IF(ISERROR(E100/$E$97),"",E100/$E$97)
C101: 4614 | D101: Deságios na Incorporação, Fusão e Cisão | F101: =IF(ISERROR(E101/$E$97),"",E101/$E$97)
C102: 4615 | D102: Deságios na Aquisição de Emprezas Privatizadas | F102: =IF(ISERROR(E102/$E$97),"",E102/$E$97)
C103: 4616 | F103: =IF(ISERROR(E103/$E$97),"",E103/$E$97)
C104: 4617 | F104: =IF(ISERROR(E104/$E$97),"",E104/$E$97)
...

Sheet Res Bp
C1: 1. BALANÇO PATRIMÔNIAL
C6: 1000 | D6: Contas do Ativo Circulante - Resultado | H6: 3400 | I6: Contas do Passivo Circulante - Resultado
C7: 1110 | D7: Disponibilidades | E7: =IF(ISERROR(Bal!J7),"",Bal!J7) -> 57560 | F7: =IF(ISERROR(Bal!K7),"",Bal!K7) -> 0.37552192 | H7: 3410 | I7: Fornecedores | J7: =IF(ISERROR(Pas!J7),"",Pas!J7) -> 31840 | K7: =IF(ISERROR(Pas!K7),"",Pas!K7) -> 0.54004546 | L7: =IF(ISERROR(SUM($E$7:$E$15)),"",SUM($E$7:$E$15)) -> 153280
C8: 1120 | D8: Aplicações em Instrumentos Financeiros | E8: =IF(ISERROR(Bal!J8),"",Bal!J8) -> 0 | F8: =IF(ISERROR(Bal!K8),"",Bal!K8) -> 0 | H8: 3410 | I8: Obrigações Financeiras a Curto Prazo | J8: =IF(ISERROR(Pas!J8),"",Pas!J8) -> 0 | K8: =IF(ISERROR(Pas!K8),"",Pas!K8) -> 0
C9: 1130 | D9: Estoque | E9: =IF(ISERROR(Bal!J9),"",Bal!J9) -> 46320 | F9: =IF(ISERROR(Bal!K9),"",Bal!K9) -> 0.30219207 | H9: 3410 | I9: Obrigações Fiscais e Tributárias | J9: =IF(ISERROR(Pas!J9),"",Pas!J9) -> 0 | K9: =IF(ISERROR(Pas!K9),"",Pas!K9) -> 0
C10: 1140 | D10: Créditos Tributários | E10: =IF(ISERROR(Bal!J10),"",Bal!J10) -> 0 | F10: =IF(ISERROR(Bal!K10),"",Bal!K10) -> 0 | H10: 3410 | I10: Obrigações Trabalhistas e Previdenciárias | J10: =IF(ISERROR(Pas!J10),"",Pas!J10) -> 12750 | K10: =IF(ISERROR(Pas!K10),"",Pas!K10) -> 0.21625564
C11: 1150 | D11: Clientes Créditos a Receber | E11: =IF(ISERROR(Bal!J11),"",Bal!J11) -> 49400 | F11: =IF(ISERROR(Bal!K11),"",Bal!K11) -> 0.32228601 | H11: 3410 | I11: Obrigações Sociais e Estatutárias | J11: =IF(ISERROR(Pas!J11),"",Pas!J11) -> 8874 | K11: =IF(ISERROR(Pas!K11),"",Pas!K11) -> 0.15051393
C12: 1160 | D12: Clientes Vencidos a Liquidar | E12: =IF(ISERROR(Bal!J12),"",Bal!J12) -> 0 | F12: =IF(ISERROR(Bal!K12),"",Bal!K12) -> 0 | H12: 3410 | I12: Obrigações Administrativas e Operacionais | J12: =IF(ISERROR(Pas!J12),"",Pas!J12) -> 5494 | K12: =IF(ISERROR(Pas!K12),"",Pas!K12) -> 0.093184979
C13: 1170 | D13: Outros Créditos | E13: =IF(ISERROR(Bal!J13),"",Bal!J13) -> 0 | F13: =IF(ISERROR(Bal!K13),"",Bal!K13) -> 0 | H13: 3410 | I13: Provisões para Contingências | J13: =IF(ISERROR(Pas!J13),"",Pas!J13) -> 0 | K13: =IF(ISERROR(Pas!K13),"",Pas!K13) -> 0
C14: 1180 | D14: Outros Valores e Bens | E14: =IF(ISERROR(Bal!J14),"",Bal!J14) -> 0 | F14: =IF(ISERROR(Bal!K14),"",Bal!K14) -> 0 | H14: 3410 | I14: Relações Interfinanceiras | J14: =IF(ISERROR(Pas!J14),"",Pas!J14) -> 0 | K14: =IF(ISERROR(Pas!K14),"",Pas!K14) -> 0
C15: 1190 | D15: Despesas Antecipadas | E15: =IF(ISERROR(Bal!J15),"",Bal!J15) -> 0 | F15: =IF(ISERROR(Bal!K15),"",Bal!K15) -> 0 | H15: 3410 | I15: Outras Obrigações | J15: =IF(ISERROR(Pas!J15),"",Pas!J15) -> 0 | K15: =IF(ISERROR(Pas!K15),"",Pas!K15) -> 0
C16: Resultado | E16: =IF(ISERROR(SUM(E7:E15)),"",SUM(E7:E15)) -> 153280 | H16: Resultado | J16: =IF(ISERROR(SUM(J7:J15)),"",SUM(J7:J15)) -> 58958
C18: 2000 | D18: Contas do Ativo Não Circulante - Resultado | H18: 4000 | I18: Contas do Passivo Não Circulante - Resultado
C19: 2200 | D19: Valores e Bens | E19: =IF(ISERROR(Atin!J7),"",Atin!J7) -> 65000 | F19: =IF(ISERROR(Atin!K7),"",Atin!K7) -> 0.45936396 | H19: 4510 | I19: Fornecedores | J19: =IF(ISERROR(Pasn!J7),"",Pasn!J7) -> 50000 | K19: =IF(ISERROR(Pasn!K7),"",Pasn!K7) -> 0.21202432
C20: 2220 | D20: Garantias e Cauções | E20: =IF(ISERROR(Atin!J8),"",Atin!J8) -> 0 | F20: =IF(ISERROR(Atin!K8),"",Atin!K8) -> 0 | H20: 4520 | I20: Obrigações Financeiras a Longo Prazo | J20: =IF(ISERROR(Pasn!J8),"",Pasn!J8) -> 0 | K20: =IF(ISERROR(Pasn!K8),"",Pasn!K8) -> 0
C21: 2230 | D21: Aplicações em Instrumentos Financeiros a Longo Prazo | E21: =IF(ISERROR(Atin!J9),"",Atin!J9) -> 0 | F21: =IF(ISERROR(Atin!K9),"",Atin!K9) -> 0 | H21: 4530 | I21: Obrigações Fiscais e Tributárias | J21: =IF(ISERROR(Pasn!J9),"",Pasn!J9) -> 0 | K21: =IF(ISERROR(Pasn!K9),"",Pasn!K9) -> 0
C22: 2240 | D22: Depósitos Judiciais | E22: =IF(ISERROR(Atin!J10),"",Atin!J10) -> 0 | F22: =IF(ISERROR(Atin!K10),"",Atin!K10) -> 0 | H22: 4540 | I22: Obrigações Trabalhistas e Previdenciárias | J22: =IF(ISERROR(Pasn!J10),"",Pasn!J10) -> 0 | K22: =IF(ISERROR(Pasn!K10),"",Pasn!K10) -> 0
C23: 2250 | D23: Imóveis para Locação ou Venda | E23: =IF(ISERROR(Atin!J11),"",Atin!J11) -> 0 | F23: =IF(ISERROR(Atin!K11),"",Atin!K11) -> 0 | H23: 4550 | I23: Obrigações Sociais e Estatutárias | J23: =IF(ISERROR(Pasn!J11),"",Pasn!J11) -> 0 | K23: =IF(ISERROR(Pasn!K11),"",Pasn!K11) -> 0
C24: 2290 | D24: Outras Contas do Realizável | E24: =IF(ISERROR(Atin!J12),"",Atin!J12) -> 0 | F24: =IF(ISERROR(Atin!K12),"",Atin!K12) -> 0 | H24: 4560 | I24: Créditos de Coligadas e Controladas | J24: =IF(ISERROR(Pasn!J12),"",Pasn!J12) -> 0 | K24: =IF(ISERROR(Pasn!K12),"",Pasn!K12) -> 0
C25: 2310 | D25: Investimentos | E25: =IF(ISERROR(Atin!J13),"",Atin!J13) -> 0 | F25: =IF(ISERROR(Atin!K13),"",Atin!K13) -> 0 | H25: 4570 | I25: Provisões para Contingências | J25: =IF(ISERROR(Pasn!J13),"",Pasn!J13) -> 0 | K25: =IF(ISERROR(Pasn!K13),"",Pasn!K13) -> 0
C26: 2320 | D26: Imobilizado de Uso | E26: =IF(ISERROR(Atin!J14),"",Atin!J14) -> 50000 | F26: =IF(ISERROR(Atin!K14),"",Atin!K14) -> 0.35335689 | H26: 4580 | I26: Receitas Diferidas | J26: =IF(ISERROR(Pasn!J14),"",Pasn!J14) -> 0 | K26: =IF(ISERROR(Pasn!K14),"",Pasn!K14) -> 0
C27: 2330 | D27: Ativo Diferido | E27: =IF(ISERROR(Atin!J15),"",Atin!J15) -> 18500 | F27: =IF(ISERROR(Atin!K15),"",Atin!K15) -> 0.13074205 | H27: 4590 | I27: Outras Obrigações | J27: =IF(ISERROR(Pasn!J15),"",Pasn!J15) -> 0 | K27: =IF(ISERROR(Pasn!K15),"",Pasn!K15) -> 0
C28: 2340 | D28: Intangível | E28: =IF(ISERROR(Atin!J16),"",Atin!J16) -> 20000 | F28: =IF(ISERROR(Atin!K16),"",Atin!K16) -> 0.14134276 | H28: 4610 | I28: Resultados de Exercícios Futuros - Receitas Diferidas | J28: =IF(ISERROR(Pasn!J16),"",Pasn!J16) -> 0 | K28: =IF(ISERROR(Pasn!K16),"",Pasn!K16) -> 0
C29: 2350 | D29: Imobilizado de Arrendamento (Leaseback) | E29: =IF(ISERROR(Atin!J17),"",Atin!J17) -> 0 | F29: =IF(ISERROR(Atin!K17),"",Atin!K17) -> 0 | H29: 4620 | I29: Custos e Despesas de Exercícios Futuros | J29: =IF(ISERROR(Pasn!J17),"",Pasn!J17) -> 0 | K29: =IF(ISERROR(Pasn!K17),"",Pasn!K17) -> 0
C30: 2360 | D30: Imobilizado Para Locação | E30: =IF(ISERROR(Atin!J18),"",Atin!J18) -> 0 | F30: =IF(ISERROR(Atin!K18),"",Atin!K18) -> 0 | H30: 5710 | I30: Capital / Capital Social / Patrimônio Social | J30: =IF(ISERROR(Pasn!J18),"",Pasn!J18) -> 120000 | K30: =IF(ISERROR(Pasn!K18),"",Pasn!K18) -> 0.50885838
... C33: 2390 | D33: Outros | E33: =IF(ISERROR(Atin!J21),"",Atin!J21) -> -12000 | F33: =IF(ISERROR(Atin!K21),"",Atin!K21) -> -0.084805654 | H33: 5740 | I33: Ajustes de Avaliação Patrimônial | J33: =IF(ISERROR(Pasn!J21),"",Pasn!J21) -> 0 | K33: =IF(ISERROR(Pasn!K21),"",Pasn!K21) -> 0
C34: Resultado | E34: =IF(ISERROR(SUM(E19:E33)),"",SUM(E19:E33)) -> 141500 | H34: 5750 | I34: Reservas de Lucros | J34: =IF(ISERROR(Pasn!J22),"",Pasn!J22) -> 64266 | K34: =IF(ISERROR(Pasn!K22),"",Pasn!K22) -> 0.2725191
H35: 5760 | I35: Reservas de Reavaliação | J35: =IF(ISERROR(Pasn!J23),"",Pasn!J23) -> 0 | K35: =IF(ISERROR(Pasn!K23),"",Pasn!K23) -> 0
C36: Resultado Total | H36: 5770 | I36: Outras Reservas | J36: =IF(ISERROR(Pasn!J24),"",Pasn!J24) -> 0 | K36: =IF(ISERROR(Pasn!K24),"",Pasn!K24) -> 0
C37: Ativo | E37: =IF(ISERROR(E34+E16),"",E34+E16) -> 294780 | H37: 5780 | I37: Lucros Acumulados / Sobras / Superávits | J37: =IF(ISERROR(Pasn!J25),"",Pasn!J25) -> 0 | K37: =IF(ISERROR(Pasn!K25),"",Pasn!K25) -> 0
C38: Passivo | E38: =IF(ISERROR(J16+J39),"",J16+J39) -> 294780 | H38: 5790 | I38: Prejuízos, Perdas e Déficits Acumulados | J38: =IF(ISERROR(Pasn!J26),"",Pasn!J26) -> 0 | K38: =IF(ISERROR(Pasn!K26),"",Pasn!K26) -> 0
C39: Resultado | E39: =IF(ISERROR(E37-E38),"",E37-E38) -> 0 | H39: Resultado | J39: =IF(ISERROR(SUM(J19:J38)),"",SUM(J19:J38)) -> 235822

Sheet Dre
C1: 2. DRE
C6: 6800 | D6: Contas de Resultado Credora (Receitas) | E6: =IF(ISERROR($E$7+$E$17+$E$27+$E$37+$E$47+$E$57+$E$67+$E$77+$E$87),"",$E$7+$E$17+$E$27+$E$37+$E$47+$E$57+$E$67+$E$77+$E$87) -> 408670 | H6: 6800 | I6: Contas de Resultado Credora (Receitas) - Resultado
C7: 6810 | D7: Receitas de Exportação | E7: =IF(ISERROR(SUM(E8:E16)),"",SUM(E8:E16)) -> 0 | H7: 6810 | I7: Receitas de Exportação | J7: =IF(ISERROR($E$7),"",$E$7) -> 0 | K7: =IF(ISERROR(J7/$L$7),"",J7/$L$7) -> 0 | L7: =IF(ISERROR(SUM($J$7:$J$15)),"",SUM($J$7:$J$15)) -> 408670
C8: 6811 | D8: Receita Bruta de Exportação | F8: =IF(ISERROR(E8/$E$7),"",E8/$E$7) | H8: 6820 | I8: Receita da Venda de Produtos | J8: =IF(ISERROR($E$17),"",$E$17) -> 408670 | K8: =IF(ISERROR(J8/$L$7),"",J8/$L$7) -> 1
C9: 6812 | D9: Deduções da Receita Bruta | F9: =IF(ISERROR(E9/$E$7),"",E9/$E$7) | H9: 6830 | I9: Receitas da Revenda de Mercadorias | J9: =IF(ISERROR($E$27),"",$E$27) -> 0 | K9: =IF(ISERROR(J9/$L$7),"",J9/$L$7) -> 0
C10: 6813 | F10: =IF(ISERROR(E10/$E$7),"",E10/$E$7) | H10: 6840 | I10: Receitas da Prestação de Serviços | J10: =IF(ISERROR($E$37),"",$E$37) -> 0 | K10: =IF(ISERROR(J10/$L$7),"",J10/$L$7) -> 0
C11: 6814 | F11: =IF(ISERROR(E11/$E$7),"",E11/$E$7) | H11: 6850 | I11: Receitas da Atividade Rural | J11: =IF(ISERROR($E$47),"",$E$47) -> 0 | K11: =IF(ISERROR(J11/$L$7),"",J11/$L$7) -> 0
C12: 6815 | D12: Outras Receitas Operacionais | F12: =IF(ISERROR(E12/$E$7),"",E12/$E$7) | H12: 6860 | I12: Receitas das Atividades de Educação e Saúde | J12: =IF(ISERROR($E$57),"",$E$57) -> 0 | K12: =IF(ISERROR(J12/$L$7),"",J12/$L$7) -> 0
C13: 6816 | D13: Receitas Não Operacionais | F13: =IF(ISERROR(E13/$E$7),"",E13/$E$7) | H13: 6870 | I13: Receitas das Atividades de Assistência Social | J13: =IF(ISERROR($E$67),"",$E$67) -> 0 | K13: =IF(ISERROR(J13/$L$7),"",J13/$L$7) -> 0
C14: 6817 | F14: =IF(ISERROR(E14/$E$7),"",E14/$E$7) | H14: 6880 | I14: Receitas das Atividades Imobiliárias | J14: =IF(ISERROR($E$77),"",$E$77) -> 0 | K14: =IF(ISERROR(J14/$L$7),"",J14/$L$7) -> 0
C15: 6818 | F15: =IF(ISERROR(E15/$E$7),"",E15/$E$7) | H15: 6890 | I15: Receitas das Atividades em Geral | J15: =IF(ISERROR($E$87),"",$E$87) -> 0 | K15: =IF(ISERROR(J15/$L$7),"",J15/$L$7) -> 0
C16: 6819 | F16: =IF(ISERROR(E16/$E$7),"",E16/$E$7)
C17: 6820 | D17: Receita da Venda de Produtos | E17: =IF(ISERROR(SUM(E18:E26)),"",SUM(E18:E26)) -> 408670 | H17: Valor Total das Contas de Resultado Credora (Receitas)
C18: 6821 | D18: Receita Bruta da Venda de Produtos | E18: 420120 | F18: =IF(ISERROR(E18/$E$17),"",E18/$E$17) -> 1.0280177 | H18: Resultado | J18: =IF(ISERROR(SUM($J$7:$J$15)),"",SUM($J$7:$J$15)) -> 408670
C19: 6822 | D19: Deduções da Receita Bruta | F19: =IF(ISERROR(E19/$E$17),"",E19/$E$17) -> 0
C20: 6823 | D20: (-) Abatimentos | E20: -6580 | F20: =IF(ISERROR(E20/$E$17),"",E20/$E$17) -> -0.016101011
C21: 6824 | D21: (-) Devolução de Vendas | E21: -4870 | F21: =IF(ISERROR(E21/$E$17),"",E21/$E$17) -> -0.011916705
C22: 6825 | F22: =IF(ISERROR(E22/$E$17),"",E22/$E$17) -> 0
C23: 6826 | F23: =IF(ISERROR(E23/$E$17),"",E23/$E$17) -> 0
C24: 6827 | F24: =IF(ISERROR(E24/$E$17),"",E24/$E$17) -> 0
C25: 6828 | D25: Outras Receitas Operacionais | F25: =IF(ISERROR(E25/$E$17),"",E25/$E$17) -> 0
C26: 6829 | D26: Receitas Não Operacionais | F26: =IF(ISERROR(E26/$E$17),"",E26/$E$17) -> 0
C27: 6830 | D27: Receitas da Revenda de Mercadorias | E27: =IF(ISERROR(SUM(E28:E36)),"",SUM(E28:E36)) -> 0
C28: 6831 | D28: Receita Bruta da Venda de Mercadorias | F28: =IF(ISERROR(E28/$E$27),"",E28/$E$27)
C29: 6832 | F29: =IF(ISERROR(E29/$E$27),"",E29/$E$27)
C30: 6833 | D30: Deduções da Receita Bruta | F30: =IF(ISERROR(E30/$E$27),"",E30/$E$27)
C31: 6834 | F31: =IF(ISERROR(E31/$E$27),"",E31/$E$27)
C32: 6835 | F32: =IF(ISERROR(E32/$E$27),"",E32/$E$27)
C33: 6836 | D33: Outras Receitas Operacionais | F33: =IF(ISERROR(E33/$E$27),"",E33/$E$27)
C34: 6837 | F34: =IF(ISERROR(E34/$E$27),"",E34/$E$27)
C35: 6838 | F35: =IF(ISERROR(E35/$E$27),"",E35/$E$27)
C36: 6839 | D36: Receitas Não Operacionais | F36: =IF(ISERROR(E36/$E$27),"",E36/$E$27)
C37: 6840 | D37: Receitas da Prestação de Serviços | E37: =IF(ISERROR(SUM(E38:E46)),"",SUM(E38:E46)) -> 0
C38: 6841 | D38: Receita Bruta de Serviços Prestados | F38: =IF(ISERROR(E38/$E$37),"",E38/$E$37)
C39: 6842 | F39: =IF(ISERROR(E39/$E$37),"",E39/$E$37)
C40: 6843 | F40: =IF(ISERROR(E40/$E$37),"",E40/$E$37)
C41: 6844 | F41: =IF(ISERROR(E41/$E$37),"",E41/$E$37)
C42: 6845 | F42: =IF(ISERROR(E42/$E$37),"",E42/$E$37)
C43: 6846 | F43: =IF(ISERROR(E43/$E$37),"",E43/$E$37)
C44: 6847 | D44: Deduções da Receita Bruta | F44: =IF(ISERROR(E44/$E$37),"",E44/$E$37)
C45: 6848 | D45: Outras Receitas Operacionais | F45: =IF(ISERROR(E45/$E$37),"",E45/$E$37)
C46: 6849 | D46: Receitas Não Operacionais | F46: =IF(ISERROR(E46/$E$37),"",E46/$E$37)
C47: 6850 | D47: Receitas da Atividade Rural | E47: =IF(ISERROR(SUM(E48:E56)),"",SUM(E48:E56)) -> 0
C48: 6851 | D48: Receita Bruta da Atividade Rural | F48: =IF(ISERROR(E48/$E$47),"",E48/$E$47)
C49: 6852 | D49: Outras Receitas da Atividade Rural | F49: =IF(ISERROR(E49/$E$47),"",E49/$E$47)
C50: 6853 | F50: =IF(ISERROR(E50/$E$47),"",E50/$E$47)
C51: 6854 | F51: =IF(ISERROR(E51/$E$47),"",E51/$E$47)
C52: 6855 | F52: =IF(ISERROR(E52/$E$47),"",E52/$E$47)
C53: 6856 | F53: =IF(ISERROR(E53/$E$47),"",E53/$E$47)
C54: 6857 | D54: Deduções da Receita Bruta | F54: =IF(ISERROR(E54/$E$47),"",E54/$E$47)
C55: 6858 | D55: Outras Receitas Operacionais | F55: =IF(ISERROR(E55/$E$47),"",E55/$E$47)
C56: 6859 | D56: Receitas Não Operacionais | F56: =IF(ISERROR(E56/$E$47),"",E56/$E$47)
C57: 6860 | D57: Receitas das Atividades de Educação e Saúde | E57: =IF(ISERROR(SUM(E58:E66)),"",SUM(E58:E66)) -> 0
C58: 6861 | D58: Receita da Venda de Produtos | F58: =IF(ISERROR(E58/$E$57),"",E58/$E$57)
C59: 6862 | D59: Receita da Prestação de Serviços de Educação | F59: =IF(ISERROR(E59/$E$57),"",E59/$E$57)
C60: 6863 | D60: Receita de Prestação de Serviços de Saúde | F60: =IF(ISERROR(E60/$E$57),"",E60/$E$57)
C61: 6864 | F61: =IF(ISERROR(E61/$E$57),"",E61/$E$57)
C62: 6865 | F62: =IF(ISERROR(E62/$E$57),"",E62/$E$57)
C63: 6866 | F63: =IF(ISERROR(E63/$E$57),"",E63/$E$57)
C64: 6867 | D64: Deduções da Receita Bruta | F64: =IF(ISERROR(E64/$E$57),"",E64/$E$57)
C65: 6868 | D65: Outras Receitas Operacionais | F65: =IF(ISERROR(E65/$E$57),"",E65/$E$57)
C66: 6869 | D66: Receitas Não Operacionais | F66: =IF(ISERROR(E66/$E$57),"",E66/$E$57)
C67: 6870 | D67: Receitas de Atividades de Assistência Social | E67: =IF(ISERROR(SUM(E68:E76)),"",SUM(E68:E76)) -> 0
C68: 6871 | D68: Receita da Venda de Produtos | F68: =IF(ISERROR(E68/$E$67),"",E68/$E$67)
C69: 6872 | D69: Receita da Prestação de Serviços de Assistência Social | F69: =IF(ISERROR(E69/$E$67),"",E69/$E$67)
C70: 6873 | D70: Receita de Outras Atividades | F70: =IF(ISERROR(E70/$E$67),"",E70/$E$67)
C71: 6874 | F71: =IF(ISERROR(E71/$E$67),"",E71/$E$67)
C72: 6875 | F72: =IF(ISERROR(E72/$E$67),"",E72/$E$67)
C73: 6876 | F73: =IF(ISERROR(E73/$E$67),"",E73/$E$67)
C74: 6877 | D74: Deduções da Receita Bruta | F74: =IF(ISERROR(E74/$E$67),"",E74/$E$67)
C75: 6878 | D75: Outras Receitas Operacionais | F75: =IF(ISERROR(E75/$E$67),"",E75/$E$67)
C76: 6879 | D76: Receitas Não Operacionais | F76: =IF(ISERROR(E76/$E$67),"",E76/$E$67)
C77: 6880 | D77: Receitas das Atividades Imobiliárias | E77: =IF(ISERROR(SUM(E78:E86)),"",SUM(E78:E86)) -> 0
C78: 6881 | D78: Receita de Unidades Imobiliárias | F78: =IF(ISERROR(E78/$E$77),"",E78/$E$77)
C79: 6882 | D79: Deduções da Receita Bruta | F79: =IF(ISERROR(E79/$E$77),"",E79/$E$77)
C80: 6883 | F80: =IF(ISERROR(E80/$E$77),"",E80/$E$77)
C81: 6884 | F81: =IF(ISERROR(E81/$E$77),"",E81/$E$77)
C82: 6885 | F82: =IF(ISERROR(E82/$E$77),"",E82/$E$77)
C83: 6886 | F83: =IF(ISERROR(E83/$E$77),"",E83/$E$77)
C84: 6887 | F84: =IF(ISERROR(E84/$E$77),"",E84/$E$77)
C85: 6888 | D85: Outras Receitas Operacionais | F85: =IF(ISERROR(E85/$E$77),"",E85/$E$77)
C86: 6889 | D86: Receitas Não Operacionais | F86: =IF(ISERROR(E86/$E$77),"",E86/$E$77)
C87: 6890 | D87: Receitas das Atividades em Geral | E87: =IF(ISERROR(SUM(E88:E96)),"",SUM(E88:E96)) -> 0
C88: 6891 | D88: Receita Bruta das Atividades em Geral | F88: =IF(ISERROR(E88/$E$87),"",E88/$E$87)
C89: 6892 | D89: Deduções da Receita Bruta | F89: =IF(ISERROR(E89/$E$87),"",E89/$E$87)
C90: 6893 | F90: =IF(ISERROR(E90/$E$87),"",E90/$E$87)
C91: 6894 | F91: =IF(ISERROR(E91/$E$87),"",E91/$E$87)
C92: 6895 | F92: =IF(ISERROR(E92/$E$87),"",E92/$E$87)
C93: 6896 | F93: =IF(ISERROR(E93/$E$87),"",E93/$E$87)
C94: 6897 | F94: =IF(ISERROR(E94/$E$87),"",E94/$E$87)
C95: 6898 | D95: Outras Receitas Operacionais | F95: =IF(ISERROR(E95/$E$87),"",E95/$E$87)
C96: 6899 | D96: Receitas Não Operacionais | F96: =IF(ISERROR(E96/$E$87),"",E96/$E$87)

Sheet Des
C1: 2. DRE
C6: 6900 | D6: Contas de Resultado Devedoras (Custos e Despesas) | E6: =IF(ISERROR($E$7+$E$17+$E$27+$E$37+$E$47+$E$57+$E$67+$E$77+$E$87),"",$E$7+$E$17+$E$27+$E$37+$E$47+$E$57+$E$67+$E$77+$E$87) -> 377534 | H6: 6900 | I6: Contas de Resultado Devedoras (Custos e Despesas) - Resultado
C7: 6910 | D7: Custos | E7: =IF(ISERROR(SUM(E8:E16)),"",SUM(E8:E16)) -> 350640 | H7: 6910 | I7: Custo | J7: =IF(ISERROR($E$7),"",$E$7) -> 350640 | K7: =IF(ISERROR(J7/$L$7),"",J7/$L$7) -> 0.92876403 | L7: =IF(ISERROR(SUM($J$7:$J$15)),"",SUM($J$7:$J$15)) -> 377534
C8: 6191 | D8: Custos dos Produtos de Fabricação Própria (Produzidos e Vendidos) | E8: 350640 | F8: =IF(ISERROR(E8/$E$7),"",E8/$E$7) -> 1 | H8: 6920 | I8: Despesa da Venda de Produtos | J8: =IF(ISERROR($E$17),"",$E$17) -> 10500 | K8: =IF(ISERROR(J8/$L$7),"",J8/$L$7) -> 0.027812065
C9: 6912 | F9: =IF(ISERROR(E9/$E$7),"",E9/$E$7) -> 0 | H9: 6930 | I9: Despesas da Revenda de Mercadorias | J9: =IF(ISERROR($E$27),"",$E$27) -> 0 | K9: =IF(ISERROR(J9/$L$7),"",J9/$L$7) -> 0
C10: 6913 | D10: Custo de Mercadorias Revendidades | F10: =IF(ISERROR(E10/$E$7),"",E10/$E$7) -> 0 | H10: 6940 | I10: Despesas da Prestação de Serviços | J10: =IF(ISERROR($E$37),"",$E$37) -> 0 | K10: =IF(ISERROR(J10/$L$7),"",J10/$L$7) -> 0
C11: 6914 | D11: Custo dos Serviços Prestados | F11: =IF(ISERROR(E11/$E$7),"",E11/$E$7) -> 0 | H11: 6950 | I11: Despesas da Atividade Rural | J11: =IF(ISERROR($E$47),"",$E$47) -> 0 | K11: =IF(ISERROR(J11/$L$7),"",J11/$L$7) -> 0
C12: 6915 | D12: Custa da Atividade Rural | F12: =IF(ISERROR(E12/$E$7),"",E12/$E$7) -> 0 | H12: 6960 | I12: Despesas das Atividades Ligadas à Educação e Saúde | J12: =IF(ISERROR($E$57),"",$E$57) -> 0 | K12: =IF(ISERROR(J12/$L$7),"",J12/$L$7) -> 0
C13: 6916 | D13: Custo dos Bens e Serviços para Educação e Saúde | F13: =IF(ISERROR(E13/$E$7),"",E13/$E$7) -> 0 | H13: 6970 | I13: Despesas de Atividades de Assistência Social | J13: =IF(ISERROR($E$67),"",$E$67) -> 0 | K13: =IF(ISERROR(J13/$L$7),"",J13/$L$7) -> 0
C14: 6917 | D14: Custo dos Bens e Serviços para Assisntência Social | F14: =IF(ISERROR(E14/$E$7),"",E14/$E$7) -> 0 | H14: 6980 | I14: Despesas das Atividades Imobiliárias | J14: =IF(ISERROR($E$77),"",$E$77) -> 0 | K14: =IF(ISERROR(J14/$L$7),"",J14/$L$7) -> 0
C15: 6918 | D15: Custo das Unidades Imobiliárias Vendidas | F15: =IF(ISERROR(E15/$E$7),"",E15/$E$7) -> 0 | H15: 6990 | I15: Despesas das Atividades em Geral | J15: =IF(ISERROR($E$87),"",$E$87) -> 16394 | K15: =IF(ISERROR(J15/$L$7),"",J15/$L$7) -> 0.043423904
C16: 6919 | D16: Custo dos Bens e Serviços para Demais Atividades | F16: =IF(ISERROR(E16/$E$7),"",E16/$E$7) -> 0
C17: 6920 | D17: Despesa da Venda de Produtos | E17: =IF(ISERROR(SUM(E18:E26)),"",SUM(E18:E26)) -> 10500 | H17: Contas de Resultado Devedoras (Custos e Despesas)
C18: 6921 | D18: Despesas Operacionais | E18: 10500 | F18: =IF(ISERROR(E18/$E$17),"",E18/$E$17) -> 1 | H18: Resultado | J18: =IF(ISERROR(SUM($J$7:$J$15)),"",SUM($J$7:$J$15)) -> 377534
C19: 6922 | F19: =IF(ISERROR(E19/$E$17),"",E19/$E$17) -> 0
C20: 6923 | F20: =IF(ISERROR(E20/$E$17),"",E20/$E$17) -> 0
C21: 6924 | D21: Outras Despesas Operacionais | F21: =IF(ISERROR(E21/$E$17),"",E21/$E$17) -> 0
C22: 6925 | D22: Despesas Não Operacionais | F22: =IF(ISERROR(E22/$E$17),"",E22/$E$17) -> 0
C23: 6926 | D23: Participações de Empregados | F23: =IF(ISERROR(E23/$E$17),"",E23/$E$17) -> 0
C24: 6927 | D24: Outras Participações | F24: =IF(ISERROR(E24/$E$17),"",E24/$E$17) -> 0
C25: 6928 | F25: =IF(ISERROR(E25/$E$17),"",E25/$E$17) -> 0
C26: 6929 | D26: Provisão para CSLL e IRPJ | F26: =IF(ISERROR(E26/$E$17),"",E26/$E$17) -> 0
C27: 6930 | D27: Despesas da Revenda de Mercadorias | E27: =IF(ISERROR(SUM(E28:E36)),"",SUM(E28:E36)) -> 0
C28: 6931 | D28: Despesas Operacionais | F28: =IF(ISERROR(E28/$E$27),"",E28/$E$27)
C29: 6932 | F29: =IF(ISERROR(E29/$E$27),"",E29/$E$27)
C30: 6933 | D30: Outras Despesas Operacionais | F30: =IF(ISERROR(E30/$E$27),"",E30/$E$27)
C31: 6934 | D31: Despesas Não Operacionais | F31: =IF(ISERROR(E31/$E$27),"",E31/$E$27)
C32: 6935 | F32: =IF(ISERROR(E32/$E$27),"",E32/$E$27)
C33: 6936 | D33: Participações de Empregados | F33: =IF(ISERROR(E33/$E$27),"",E33/$E$27)
C34: 6937 | D34: Outras Participações | F34: =IF(ISERROR(E34/$E$27),"",E34/$E$27)
C35: 6938 | F35: =IF(ISERROR(E35/$E$27),"",E35/$E$27)
C36: 6939 | D36: Provisão para CSLL e IRPJ | F36: =IF(ISERROR(E36/$E$27),"",E36/$E$27)
C37: 6940 | D37: Despesas da Prestação de Serviços | E37: =IF(ISERROR(SUM(E38:E46)),"",SUM(E38:E46)) -> 0
C38: 6941 | D38: Despesas Operacionais | F38: =IF(ISERROR(E38/$E$37),"",E38/$E$37)
C39: 6942 | F39: =IF(ISERROR(E39/$E$37),"",E39/$E$37)
C40: 6943 | D40: Outras Despesas Operacionais | F40: =IF(ISERROR(E40/$E$37),"",E40/$E$37)
C41: 6944 | F41: =IF(ISERROR(E41/$E$37),"",E41/$E$37)
C42: 6945 | D42: Despesas Não Operacionais | F42: =IF(ISERROR(E42/$E$37),"",E42/$E$37)
C43: 6946 | D43: Participações de Empregados | F43: =IF(ISERROR(E43/$E$37),"",E43/$E$37)
C44: 6947 | D44: Outras Participações | F44: =IF(ISERROR(E44/$E$37),"",E44/$E$37)
C45: 6948 | F45: =IF(ISERROR(E45/$E$37),"",E45/$E$37)
C46: 6949 | D46: Provisão para CSLL e IRPJ | F46: =IF(ISERROR(E46/$E$37),"",E46/$E$37)
C47: 6950 | D47: Despesas da Atividade Rural | E47: =IF(ISERROR(SUM(E48:E56)),"",SUM(E48:E56)) -> 0
C48: 6951 | D48: Despesas Operacionais | F48: =IF(ISERROR(E48/$E$47),"",E48/$E$47)
C49: 6952 | F49: =IF(ISERROR(E49/$E$47),"",E49/$E$47)
C50: 6953 | F50: =IF(ISERROR(E50/$E$47),"",E50/$E$47)
C51: 6954 | D51: Outras Despesas Operacionais | F51: =IF(ISERROR(E51/$E$47),"",E51/$E$47)
C52: 6955 | D52: Despesas Não Operacionais | F52: =IF(ISERROR(E52/$E$47),"",E52/$E$47)
C53: 6956 | D53: Participações de Empregados | F53: =IF(ISERROR(E53/$E$47),"",E53/$E$47)
C54: 6957 | D54: Outras Participações | F54: =IF(ISERROR(E54/$E$47),"",E54/$E$47)
C55: 6958 | F55: =IF(ISERROR(E55/$E$47),"",E55/$E$47)
C56: 6959 | D56: Provisão para CSLL e IRPJ | F56: =IF(ISERROR(E56/$E$47),"",E56/$E$47)
C57: 6960 | D57: Despesas das Atividades Ligadas à Educação e Saúde | E57: =IF(ISERROR(SUM(E58:E66)),"",SUM(E58:E66)) -> 0
C58: 6961 | D58: Despesas Operacionais | F58: =IF(ISERROR(E58/$E$57),"",E58/$E$57)
C59: 6962 | F59: =IF(ISERROR(E59/$E$57),"",E59/$E$57)
C60: 6963 | F60: =IF(ISERROR(E60/$E$57),"",E60/$E$57)
C61: 6964 | D61: Outras Despesas Operacionais | F61: =IF(ISERROR(E61/$E$57),"",E61/$E$57)
C62: 6965 | D62: Despesas Não Operacionais | F62: =IF(ISERROR(E62/$E$57),"",E62/$E$57)
C63: 6966 | D63: Participações de Empregados | F63: =IF(ISERROR(E63/$E$57),"",E63/$E$57)
C64: 6967 | D64: Outras Participações | F64: =IF(ISERROR(E64/$E$57),"",E64/$E$57)
C65: 6968 | F65: =IF(ISERROR(E65/$E$57),"",E65/$E$57)
C66: 6969 | D66: Provisão para CSLL e IRPJ | F66: =IF(ISERROR(E66/$E$57),"",E66/$E$57)
C67: 6970 | D67: Despesas de Atividades de Assistência Social | E67: =IF(ISERROR(SUM(E68:E76)),"",SUM(E68:E76)) -> 0
C68: 6971 | D68: Despesas Operacionais | F68: =IF(ISERROR(E68/$E$67),"",E68/$E$67)
C69: 6972 | F69: =IF(ISERROR(E69/$E$67),"",E69/$E$67)
C70: 6973 | F70: =IF(ISERROR(E70/$E$67),"",E70/$E$67)
C71: 6974 | D71: Outras Despesas Operacionais | F71: =IF(ISERROR(E71/$E$67),"",E71/$E$67)
C72: 6975 | D72: Despesas Não Operacionais | F72: =IF(ISERROR(E72/$E$67),"",E72/$E$67)
C73: 6976 | D73: Participações de Empregados | F73: =IF(ISERROR(E73/$E$67),"",E73/$E$67)
C74: 6977 | F74: =IF(ISERROR(E74/$E$67),"",E74/$E$67)
C75: 6978 | F75: =IF(ISERROR(E75/$E$67),"",E75/$E$67)
C76: 6979 | D76: Provisão para CSLL e IRPJ | F76: =IF(ISERROR(E76/$E$67),"",E76/$E$67)
C77: 6980 | D77: Despesas das Atividades Imobiliárias | E77: =IF(ISERROR(SUM(E78:E86)),"",SUM(E78:E86)) -> 0
C78: 6981 | D78: Despesas Operacionais | F78: =IF(ISERROR(E78/$E$77),"",E78/$E$77)
C79: 6982 | F79: =IF(ISERROR(E79/$E$77),"",E79/$E$77)
C80: 6983 | D80: Outras Despesas Operacionais | F80: =IF(ISERROR(E80/$E$77),"",E80/$E$77)
C81: 6984 | D81: Despesas Não Operacionais | F81: =IF(ISERROR(E81/$E$77),"",E81/$E$77)
C82: 6985 | F82: =IF(ISERROR(E82/$E$77),"",E82/$E$77)
C83: 6986 | D83: Participações de Empregados | F83: =IF(ISERROR(E83/$E$77),"",E83/$E$77)
C84: 6987 | D84: Outras Participações | F84: =IF(ISERROR(E84/$E$77),"",E84/$E$77)
C85: 6988 | F85: =IF(ISERROR(E85/$E$77),"",E85/$E$77)
C86: 6989 | D86: Provisão para CSLL e IRPJ | F86: =IF(ISERROR(E86/$E$77),"",E86/$E$77)
C87: 6990 | D87: Despesas das Atividades em Geral | E87: =IF(ISERROR(SUM(E88:E96)),"",SUM(E88:E96)) -> 16394
C88: 6991 | D88: Despesas Operacionais | F88: =IF(ISERROR(E88/$E$87),"",E88/$E$87) -> 0
C89: 6992 | D89: Outras Despesas Operacionais | F89: =IF(ISERROR(E89/$E$87),"",E89/$E$87) -> 0
C90: 6993 | D90: Administrativas | E90: 4800 | F90: =IF(ISERROR(E90/$E$87),"",E90/$E$87) -> 0.29279005
C91: 6894 | D91: Financeiras | E91: 6100 | F91: =IF(ISERROR(E91/$E$87),"",E91/$E$87) -> 0.37208735
C92: 6895 | D92: Despesas Não Operacionais | F92: =IF(ISERROR(E92/$E$87),"",E92/$E$87) -> 0
C93: 6896 | D93: Participações de Empregados | F93: =IF(ISERROR(E93/$E$87),"",E93/$E$87) -> 0
C94: 6897 | D94: Outras Participações | F94: =IF(ISERROR(E94/$E$87),"",E94/$E$87) -> 0
C95: 6898 | F95: =IF(ISERROR(E95/$E$87),"",E95/$E$87) -> 0
C96: 6899 | D96: Provisão para CSLL e IRPJ | E96: 5494 | F96: =IF(ISERROR(E96/$E$87),"",E96/$E$87) -> 0.33512261

Sheet Res
C1: 2. DRE
C6: 6800 | D6: Contas de Resultado Credora (Receitas) - Resultado | H6: 6900 | I6: Contas de Resultado Devedoras (Custos e Despesas) - Resultado
C7: 6810 | D7: Receitas de Exportação | E7: =IF(ISERROR(Dre!J7),"",Dre!J7) -> 0 | F7: =IF(ISERROR(E7/$E$16),"",E7/$E$16) -> 0 | H7: 6910 | I7: Custo | J7: =IF(ISERROR(Des!J7),"",Des!J7) -> 350640 | K7: =IF(ISERROR(J7/$J$16),"",J7/$J$16) -> 0.92876403
C8: 6820 | D8: Receita da Venda de Produtos | E8: =IF(ISERROR(Dre!J8),"",Dre!J8) -> 408670 | F8: =IF(ISERROR(E8/$E$16),"",E8/$E$16) -> 1 | H8: 6920 | I8: Despesa da Venda de Produtos | J8: =IF(ISERROR(Des!J8),"",Des!J8) -> 10500 | K8: =IF(ISERROR(J8/$J$16),"",J8/$J$16) -> 0.027812065
C9: 6830 | D9: Receitas da Revenda de Mercadorias | E9: =IF(ISERROR(Dre!J9),"",Dre!J9) -> 0 | F9: =IF(ISERROR(E9/$E$16),"",E9/$E$16) -> 0 | H9: 6930 | I9: Despesas da Revenda de Mercadorias | J9: =IF(ISERROR(Des!J9),"",Des!J9) -> 0 | K9: =IF(ISERROR(J9/$J$16),"",J9/$J$16) -> 0
C10: 6840 | D10: Receitas da Prestação de Serviços | E10: =IF(ISERROR(Dre!J10),"",Dre!J10) -> 0 | F10: =IF(ISERROR(E10/$E$16),"",E10/$E$16) -> 0 | H10: 6940 | I10: Despesas da Prestação de Serviços | J10: =IF(ISERROR(Des!J10),"",Des!J10) -> 0 | K10: =IF(ISERROR(J10/$J$16),"",J10/$J$16) -> 0
C11: 6850 | D11: Receitas da Atividade Rural | E11: =IF(ISERROR(Dre!J11),"",Dre!J11) -> 0 | F11: =IF(ISERROR(E11/$E$16),"",E11/$E$16) -> 0 | H11: 6950 | I11: Despesas da Atividade Rural | J11: =IF(ISERROR(Des!J11),"",Des!J11) -> 0 | K11: =IF(ISERROR(J11/$J$16),"",J11/$J$16) -> 0
C12: 6860 | D12: Receitas das Atividades de Educação e Saúde | E12: =IF(ISERROR(Dre!J12),"",Dre!J12) -> 0 | F12: =IF(ISERROR(E12/$E$16),"",E12/$E$16) -> 0 | H12: 6960 | I12: Despesas das Atividades Ligadas à Educação e Saúde | J12: =IF(ISERROR(Des!J12),"",Des!J12) -> 0 | K12: =IF(ISERROR(J12/$J$16),"",J12/$J$16) -> 0
C13: 6870 | D13: Receitas das Atividades de Assistência Social | E13: =IF(ISERROR(Dre!J13),"",Dre!J13) -> 0 | F13: =IF(ISERROR(E13/$E$16),"",E13/$E$16) -> 0 | H13: 6970 | I13: Despesas de Atividades de Assistência Social | J13: =IF(ISERROR(Des!J13),"",Des!J13) -> 0 | K13: =IF(ISERROR(J13/$J$16),"",J13/$J$16) -> 0
C14: 6880 | D14: Receitas das Atividades Imobiliárias | E14: =IF(ISERROR(Dre!J14),"",Dre!J14) -> 0 | F14: =IF(ISERROR(E14/$E$16),"",E14/$E$16) -> 0 | H14: 6980 | I14: Despesas das Atividades Imobiliárias | J14: =IF(ISERROR(Des!J14),"",Des!J14) -> 0 | K14: =IF(ISERROR(J14/$J$16),"",J14/$J$16) -> 0
C15: 6890 | D15: Receitas das Atividades em Geral | E15: =IF(ISERROR(Dre!J15),"",Dre!J15) -> 0 | F15: =IF(ISERROR(E15/$E$16),"",E15/$E$16) -> 0 | H15: 6990 | I15: Despesas das Atividades em Geral | J15: =IF(ISERROR(Des!J15),"",Des!J15) -> 16394 | K15: =IF(ISERROR(J15/$J$16),"",J15/$J$16) -> 0.043423904
C16: Contas de Resultado Credora (Receitas) - Resultado | E16: =IF(ISERROR(SUM(E7:E15)),"",SUM(E7:E15)) -> 408670 | H16: Contas de Resultado Devedoras (Custos e Despesas) - Resultado | J16: =IF(ISERROR(SUM(J7:J15)),"",SUM(J7:J15)) -> 377534
C18: Demonstração do Resultado do Exercício (DRE)
C19: Contas de Resultado Credora (Receitas) | E19: =IF(ISERROR($E$16),"",$E$16) -> 408670 | F19: =IF(ISERROR($E$19/$G$19),"",$E$19/$G$19) -> 0.51980148 | G19: =IF(ISERROR(SUM(E19:E20)),"",SUM(E19:E20)) -> 786204
C20: Contas de Resultado Devedoras (Custos e Despesas) | E20: =IF(ISERROR($J$16),"",$J$16) -> 377534 | F20: =IF(ISERROR($E$19/$G$19),"",$E$19/$G$19) -> 0.51980148
C21: Resultado do Exercício | E21: =IF(ISERROR(E19-E20),"",E19-E20) -> 31136

Sheet Gra
C1: 4. GRÁFICOS
C6: 1 - ATIVO CIRCULANTE
C16: 1.1 - ATIVO NÃO CIRCULANTE
C26: 1.2 - PASSIVO CIRCULANTE
C36: 1.3 - PASSIVO NÃO CIRCULANTE
L37: Balanço Patrimônial
L38: =IF(ISERROR(Bal!$D$6),"",Bal!$D$6) -> Ativo Circulante (Bens e Direitos) | M38: =IF(ISERROR(Bal!$E$6),"",Bal!$E$6) -> 153280 | N38: =IF(ISERROR($M$38/$M$42),"",$M$38/$M$42) -> 0.2599905
L39: =IF(ISERROR(Atin!$D$6),"",Atin!$D$6) -> Ativo Não Circulante (Bens e Direitos) | M39: =IF(ISERROR(Atin!$E$6),"",Atin!$E$6) -> 141500 | N39: =IF(ISERROR($M$39/$M$42),"",$M$39/$M$42) -> 0.2400095
L40: =IF(ISERROR(Pas!$D$6),"",Pas!$D$6) -> Passivo Circulante (Deveres e Obrigações) | M40: =IF(ISERROR(Pas!$E$6),"",Pas!$E$6) -> 58958 | N40: =IF(ISERROR($M$40/$M$42),"",$M$40/$M$42) -> 0.10000339
L41: =IF(ISERROR(Pasn!$D$6),"",Pasn!$D$6) -> Passivo Não Circulante (Deveres e Obrigações) | M41: =IF(ISERROR(Pasn!$E$6),"",Pasn!$E$6) -> 235822 | N41: =IF(ISERROR($M$41/$M$42),"",$M$41/$M$42) -> 0.39999661
M42: =IF(ISERROR(SUM($M$38:$M$41)),"",SUM($M$38:$M$41)) -> 589560
C46: 1.4 - BALANÇO PATRIMÔNIAL
C56: 2 - RECEITAS - DRE
C66: 2.1 - DESPESAS (DRE)
C76: 2.2 - DEMONSTRAÇÃO DE RESULTADO DE EXERCÍCIO (DRE)

Sheet Ana
C1: 4. ALERTAS E DICAS
C6: Endividamento Geral ou Nível de Alavancagem | F6: =IF(ISERROR(SUM(F7:F9)),"",SUM(F7:F9)) -> 294780 | G6: Interpretação do índice | V6: =IF(ISERROR(SUM(V7:V8)),"",SUM(V7:V8)) -> 244780
C7: Passivo Circulante | D7: =IF(ISERROR(Pas!$E$6),"",Pas!$E$6) -> 58958 | E7: =IF(ISERROR($D$7/$F$6),"",$D$7/$F$6) -> 0.20000678 | F7: =IF(ISERROR(D7),"",D7) -> 58958 | G7: =IF($D$10<=1,"O PATRIMÔNIO LÍQUIDO será suficiente para a liquidação do Passivo","O PATRIMÔNIO LÍQUIDO não será suficiente para pagamento ou liquidação do Passivo") -> O PATRIMÔNIO LÍQUIDO será suficiente para a liquidação do Passivo | V7: =IF(ISERROR(D19),"",D19) -> 58958
C8: Exigível a Longo Prazo | D8: =IF(ISERROR(Pasn!$J$38),"",Pasn!$J$38) -> 50000 | E8: =IF(ISERROR($D$8/$F$6),"",$D$8/$F$6) -> 0.16961802 | F8: =IF(ISERROR(D8),"",D8) -> 50000 | V8: =IF(ISERROR(D20),"",D20) -> 185822
C9: Patrimônio Liquido | D9: =IF(ISERROR(Pasn!$J$55),"",Pasn!$J$55) -> 185822 | E9: =IF(ISERROR($D$9/$F$6),"",$D$9/$F$6) -> 0.6303752 | F9: =IF(ISERROR(D9),"",D9) -> 185822
C10: Resultado | D10: =IF(ISERROR(ROUND($F$10/$F$9,2)),"",ROUND($F$10/$F$9,2)) -> 0.59 | F10: =IF(ISERROR(SUM(F7:F8)),"",SUM(F7:F8)) -> 108958
C12: Endividamento Financeiro Versus Total | F12: =IF(ISERROR(SUM(F13:F15)),"",SUM(F13:F15)) -> 217916 | G12: Interpretação do índice
C13: Obrigações Financeiras | D13: =IF(ISERROR(Pas!$E$6+Pasn!$J$38),"",Pas!$E$6+Pasn!$J$38) -> 108958 | E13: =IF(ISERROR(D13/$F$12),"",D13/$F$12) -> 0.5 | F13: =IF(ISERROR($D$13),"",$D$13) -> 108958 | G13: =IF(ISERROR("Seu percentual de Passivo referente a dívidadas com estabelecimentos bancários no país e no exterior é de " & ($D$16)),"","Seu percentual de Passivo referente a dívidadas com estabelecimentos bancários no país e no exterior é de " & ($D$16)) -> Seu percentual de Passivo referente a dívidadas com estabelecimentos bancários no país e no exterior é de 1%
C14: Passivo Circulante | D14: =IF(ISERROR(Pas!$E$6),"",Pas!$E$6) -> 58958 | E14: =IF(ISERROR(D14/$F$12),"",D14/$F$12) -> 0.27055379 | F14: =IF(ISERROR($D$14),"",$D$14) -> 58958
C15: Exigível a Longo Prazo | D15: =IF(ISERROR(Pasn!$J$38),"",Pasn!$J$38) -> 50000 | E15: =IF(ISERROR(D15/$F$12),"",D15/$F$12) -> 0.22944621 | F15: =IF(ISERROR($D$15),"",$D$15) -> 50000
C16: Resultado | D16: =IF(ISERROR(ROUND($F$13/$F$16,2)&"%"),"",ROUND($F$13/$F$16,2)&"%") -> 1% | F16: =IF(ISERROR(SUM($F$14:$F$15)),"",SUM($F$14:$F$15)) -> 108958
C18: Endividamento de Curto Prazo | G18: Interpretação do índice
C19: Passivo Circulante | D19: =IF(ISERROR(Pas!$E$6),"",Pas!$E$6) -> 58958 | E19: =IF(ISERROR($D$19/$V$6),"",$D$19/$V$6) -> 0.24086118 | F19: =IF(ISERROR($D$19),"",$D$19) -> 58958 | G19: =IF($D$21<=1,"O PATRIMÔNIO LÍQUIDO será suficiente para a liquidação do Passivo Circulante; mediante o índice de ENDIVIDAMENTO GERAL poderá será apurada como ficará o nível de endividamento se houver saldo a pagar no grupamento EXIGÍVEL DE LONGO PRAZO","O PATRIMÔNIO LÍQUIDO será suficiente para pagamento ou liquidação do Passivo Circulante, ficando parte dele a descoberto; o eventual EXIGÍVEL DE LONGO PRAZO existente também ficará sem pagamento") -> O PATRIMÔNIO LÍQUIDO será suficiente para a liquidação do Passivo Circulante; mediante o índice de ENDIVIDAMENTO GERAL poderá será apurada como ficará o nível de endividamento se houver saldo a pagar no grupamento EXIGÍVEL DE LONGO PRAZO
C20: Patrimônio Líquido | D20: =IF(ISERROR(Pasn!$J$55),"",Pasn!$J$55) -> 185822 | E20: =IF(ISERROR($D$20/$V$6),"",$D$20/$V$6) -> 0.75913882 | F20: =IF(ISERROR($D$20),"",$D$20) -> 185822
C21: Resultado | D21: =IF(ISERROR(ROUND($F$19/$F$20,2)),"",ROUND($F$19/$F$20,2)) -> 0.32
C23: Endividamento Financeiro Versus Capital Próprio | F23: =IF(ISERROR(SUM(F24:F25)),"",SUM(F24:F25)) -> 294780 | G23: Interpretação do índice
C24: Obrigações Financeiras | D24: =IF(ISERROR(Pas!$E$6+Pasn!$J$38),"",Pas!$E$6+Pasn!$J$38) -> 108958 | E24: =IF(ISERROR($D$24/$F$23),"",$D$24/$F$23) -> 0.3696248 | F24: =IF(ISERROR($D$24),"",$D$24) -> 108958 | G24: =IF($D$26<=1,"O PATRIMÔNIO LÍQUIDO será suficiente para pagamento ou liquidação das Obrigações Financeiras","O PATRIMÔNIO LÍQUIDO (capital próprio) não será suficiente para pagamento ou liquidação das Obrigações Financeiras") -> O PATRIMÔNIO LÍQUIDO será suficiente para pagamento ou liquidação das Obrigações Financeiras
C25: Patrimônio Líquido | D25: =IF(ISERROR(Pasn!$J$55),"",Pasn!$J$55) -> 185822 | E25: =IF(ISERROR($D$25/$F$23),"",$D$25/$F$23) -> 0.6303752 | F25: =IF(ISERROR($D$25),"",$D$25) -> 185822
C26: Resultado | D26: =IF(ISERROR(ROUND($F$24/$F$25,2)),"",ROUND($F$24/$F$25,2)) -> 0.59
C28: Endividamento Financeiro de Curto Prazo Versus Ativo Circulante | F28: =IF(ISERROR(SUM(F29:F30)),"",SUM(F29:F30)) -> 212238 | G28: Interpretação do índice
C29: Obrigações Financeiras (Passivo Circulante) | D29: =IF(ISERROR(Pas!$E$6),"",Pas!$E$6) -> 58958 | E29: =IF(ISERROR($D$29/$F$28),"",$D$29/$F$28) -> 0.27779191 | F29: =IF(ISERROR($D$29),"",$D$29) -> 58958 | G29: =IF($D$31<=1,"O ATIVO CIRCULANTE será suficiente para pagamento ou liquidação das Obrigações Financeiras","O ATIVO CIRCULANTE (recebíveis de curto prazo) não será suficiente para pagamento ou liquidação das Obrigações Financeiras") -> O ATIVO CIRCULANTE será suficiente para pagamento ou liquidação das Obrigações Financeiras
C30: Ativo Circulante | D30: =IF(ISERROR(Bal!$E$6),"",Bal!$E$6) -> 153280 | E30: =IF(ISERROR($D$30/$F$28),"",$D$30/$F$28) -> 0.72220809 | F30: =IF(ISERROR($D$30),"",$D$30) -> 153280
C31: Resultado | D31: =IF(ISERROR(ROUND($F$29/$F$30,2)),"",ROUND($F$29/$F$30,2)) -> 0.38
C33: Nível de Desconto de Duplicatas | F33: =IF(ISERROR(SUM(F34:F35)),"",SUM(F34:F35)) -> 81240 | G33: Interpretação do índice
C34: Duplicatas Descontadas | D34: =IF(ISERROR(Pas!$J$7),"",(Pas!$J$7)) -> 31840 | E34: =IF(ISERROR(D34/$F$33),"",D34/$F$33) -> 0.39192516 | F34: =IF(ISERROR(D34),"",D34) -> 31840 | G34: =IF($D$31<=1,"O ATIVO CIRCULANTE será suficiente para pagamento ou liquidação das Obrigações Financeiras","O ATIVO CIRCULANTE (recebíveis de curto prazo) não será suficiente para pagamento ou liquidação das Obrigações Financeiras") -> O ATIVO CIRCULANTE será suficiente para pagamento ou liquidação das Obrigações Financeiras
C35: Duplicatas a Receber | D35: =IF(ISERROR(Bal!J11),"",Bal!J11) -> 49400 | E35: =IF(ISERROR(D35/$F$33),"",D35/$F$33) -> 0.60807484 | F35: =IF(ISERROR(D35),"",D35) -> 49400
C36: Resultado | D36: =IF(ISERROR(ROUND(F34/F35,2)),"",ROUND(F34/F35,2)) -> 0.64
C38: Imobilização do Patrimônio Líquido | F38: =IF(ISERROR(SUM($F$39:$F$40)),"",SUM($F$39:$F$40)) -> 262322 | G38: Interpretação do índice
C39: Ativo Permanente | D39: =IF(ISERROR(Atin!$J$42),"",Atin!$J$42) -> 76500 | E39: =IF(ISERROR($D$39/$F$38),"",$D$39/$F$38) -> 0.29162632 | F39: =IF(ISERROR($D$39),"",$D$39) -> 76500 | G39: =IF(ISERROR("O percentual do Patrimônio Líquido que se encontra aplicado no Ativo Permanente é de " & ($D$41)),"","O percentual do Patrimônio Líquido que se encontra aplicado no Ativo Permanente é de " & ($D$41)) -> O percentual do Patrimônio Líquido que se encontra aplicado no Ativo Permanente é de 0,41%
C40: Patrimônio Líquido | D40: =IF(ISERROR(Pasn!$J$55),"",Pasn!$J$55) -> 185822 | E40: =IF(ISERROR($D$40/$F$38),"",$D$40/$F$38) -> 0.70837368 | F40: =IF(ISERROR($D$40),"",$D$40) -> 185822
C41: Resultado | D41: =IF(ISERROR(ROUND($F$39/$F$40,2) &"%"),"",ROUND($F$39/$F$40,2) &"%") -> 0,41%

Sheet Cpd
C1: 4. ALERTAS E DICAS
C6: Liquidez Corrente | F6: =IF(ISERROR(SUM(F7:F8)),"",SUM(F7:F8)) -> 212238 | G6: Interpretação do índice
C7: Ativo Circulante | D7: =IF(ISERROR(Bal!$J$24),"",Bal!$J$24) -> 153280 | E7: =IF(ISERROR(F7/$F$6),"",F7/$F$6) -> 0.72220809 | F7: =IF(ISERROR(D7),"",D7) -> 153280 | G7: =IF($D$9>=1,"Significa que a entidade tem ou terá recursos financeiros suficientes para honrar seus compromissos de curto prazo (até um ano)","Significa que a entidade não tem ou não terá recursos financeiros para honrar seus compromissos de curto prazo (até um ano)") -> Significa que a entidade tem ou terá recursos financeiros suficientes para honrar seus compromissos de curto prazo (até um ano)
C8: Passivo Circulante | D8: =IF(ISERROR(Pas!$J$27),"",Pas!$J$27) -> 58958 | E8: =IF(ISERROR(F8/$F$6),"",F8/$F$6) -> 0.27779191 | F8: =IF(ISERROR(D8),"",D8) -> 58958
C9: Total de Liquidez Corrente | D9: =IF(ISERROR(ROUND(F7/F8,2)),"",ROUND(F7/F8,2)) -> 2.6
C11: Liquidez Imediata | F11: =IF(ISERROR(SUM(F12:F13)),"",SUM(F12:F13)) -> 116518 | G11: Interpretação do índice
C12: Disponibilidades | D12: =IF(ISERROR(Bal!$J$7),"",Bal!$J$7) -> 57560 | E12: =IF(ISERROR(D12/$F$11),"",D12/$F$11) -> 0.49400093 | F12: =IF(ISERROR(D12),"",D12) -> 57560 | G12: =IF($D$14>=1,"A empresa terá condições de pagar seu Passivo Circulante no dia seguinte ao da apuração","A empresa terá condições de pagar parte do seu Passivo Circulante no dia seguinte ao da apuração") -> A empresa terá condições de pagar parte do seu Passivo Circulante no dia seguinte ao da apuração
C13: Passivo Circulante | D13: =IF(ISERROR(Pas!$J$27),"",Pas!$J$27) -> 58958 | E13: =IF(ISERROR(D13/$F$11),"",D13/$F$11) -> 0.50599907 | F13: =IF(ISERROR(D13),"",D13) -> 58958
C14: Total de Liquidez Imediata | D14: =IF(ISERROR(ROUND(F12/F13,2)),"",ROUND(F12/F13,2)) -> 0.98
C16: Liquidez Seca | F16: =IF(ISERROR(SUM(F17:F19)),"",SUM(F17:F19)) -> 258558 | G16: Interpretação do índice
C17: Ativo Circulante | D17: =IF(ISERROR(Bal!$J$24),"",Bal!$J$24) -> 153280 | E17: =IF(ISERROR(D17/$F$16),"",D17/$F$16) -> 0.59282637 | F17: =IF(ISERROR(D17),"",D17) -> 153280 | G17: =IF($D$20>=1,"Significa que a entidade tem ou terá recursos financeiros em curto prazo para honrar seus compromissos de curto prazo (até um ano), independente de conseguir vender seus estoques","Significa que a entidade tem ou terá em curto prazo somente uma parte dos recursos financeiros necessários a liquidação do Passivo Circulante") -> Significa que a entidade tem ou terá recursos financeiros em curto prazo para honrar seus compromissos de curto prazo (até um ano), independente de conseguir vender seus estoques
C18: Estoque | D18: =IF(ISERROR(Bal!$J$9),"",Bal!$J$9) -> 46320 | E18: =IF(ISERROR(D18/$F$16),"",D18/$F$16) -> 0.17914743 | F18: =IF(ISERROR(D18),"",D18) -> 46320
C19: Passivo Circulante | D19: =IF(ISERROR(Pas!$J$27),"",Pas!$J$27) -> 58958 | E19: =IF(ISERROR(D19/$F$16),"",D19/$F$16) -> 0.22802621 | F19: =IF(ISERROR(D19),"",D19) -> 58958
C20: Total de Liquidez Seca | D20: =IF(ISERROR(ROUND(F20/F19,2)),"",ROUND(F20/F19,2)) -> 1.81 | F20: =IF(ISERROR(F17-F18),"",F17-F18) -> 106960
C22: Liquidez Geral | F22: =IF(ISERROR(SUM($F$23:$F$26)),"",SUM($F$23:$F$26)) -> 513060 | G22: Interpretação do índice
C23: Ativo Circulante | D23: =IF(ISERROR(Bal!$J$24),"",Bal!$J$24) -> 153280 | E23: =IF(ISERROR(F23/$F$22),"",F23/$F$22) -> 0.29875648 | F23: =IF(ISERROR($D$23),"",$D$23) -> 153280 | G23: =IF($D$27>=1,"Significa que a entidade terá recursos financeiros suficientes para honrar seus compromissos","Significa que a entidade não terá recursos financeiros para honrar seus compromissos") -> Significa que a entidade não terá recursos financeiros para honrar seus compromissos
C24: Ativo Realizável a Longo Prazo | D24: =IF(ISERROR(Atin!$J$30),"",Atin!$J$30) -> 65000 | E24: =IF(ISERROR(F24/$F$22),"",F24/$F$22) -> 0.12669084 | F24: =IF(ISERROR($D$24),"",$D$24) -> 65000
C25: Passivo Circulante | D25: =IF(ISERROR(Pas!$J$27),"",Pas!$J$27) -> 58958 | E25: =IF(ISERROR(F25/$F$22),"",F25/$F$22) -> 0.11491443 | F25: =IF(ISERROR($D$25),"",$D$25) -> 58958
C26: Passivo Não Circulante | D26: =IF(ISERROR(Pasn!$J$58),"",Pasn!$J$58) -> 235822 | E26: =IF(ISERROR(F26/$F$22),"",F26/$F$22) -> 0.45963825 | F26: =IF(ISERROR($D$26),"",$D$26) -> 235822
C27: Total de Liquidez Corrente | D27: =IF(ISERROR(ROUND($D$28/$E$28,2)),"",ROUND($D$28/$E$28,2)) -> 0.74
D28: =IF(ISERROR($F$23+$F$24),"",$F$23+$F$24) -> 218280 | E28: =IF(ISERROR($F$25+$F$26),"",$F$25+$F$26) -> 294780

Sheet Ato
C1: 4. ALERTAS E DICAS
C6: Prazo Médio de Recebimento de Vendas | F6: =IF(ISERROR(SUM(F7:F8)),"",SUM(F7:F8)) -> 458070 | G6: Interpretação do índice
C7: Duplicatas a Receber | D7: =IF(ISERROR(Bal!$J$11),"",Bal!$J$11) -> 49400 | E7: =IF(ISERROR(D7/$F$6),"",D7/$F$6) -> 0.10784378 | F7: =IF(ISERROR(D7),"",D7) -> 49400 | G7: =IF(ISERROR("O prazo médio de recebimento do valor das vendas praticas ao longo do ano é de " &ROUND($D$9,2) & " dias"),"","O prazo médio de recebimento do valor das vendas praticas ao longo do ano é de " &ROUND($D$9,2) & " dias") -> O prazo médio de recebimento do valor das vendas praticas ao longo do ano é de 44,12 dias
C8: Receitas de Vendas | D8: =IF(ISERROR(Dre!$J$8),"",Dre!$J$8) -> 408670 | E8: =IF(ISERROR(D8/$F$6),"",D8/$F$6) -> 0.89215622 | F8: =IF(ISERROR(D8),"",D8) -> 408670
C9: Resultado | D9: =IF(ISERROR(ROUND(F9/F8,2)),"",ROUND(F9/F8,2)) -> 44.12 | F9: =IF(ISERROR(F7*365),"",F7*365) -> 18031000
C11: Prazo Médio de Renovação dos Estoques | F11: =IF(ISERROR(SUM(F12:F13)),"",SUM(F12:F13)) -> 56820 | G11: Interpretação do índice
C12: Estoques | D12: =IF(ISERROR(Bal!$J$9),"",Bal!$J$9) -> 46320 | E12: =IF(ISERROR(D12/F11),"",D12/F11) -> 0.81520591 | F12: =IF(ISERROR(D12),"",D12) -> 46320 | G12: =IF(ISERROR("O prazo médio da rotatividade da estoque ao longo do ano é de " & ROUND($D$14,2) & " dias"),"","O prazo médio da rotatividade da estoque ao longo do ano é de " & ROUND($D$14,2) & " dias") -> O prazo médio da rotatividade da estoque ao longo do ano é de 1610,17 dias
C13: Custo de Produtos Vendidos | D13: =IF(ISERROR(Des!$J$8),"",Des!$J$8) -> 10500 | E13: =IF(ISERROR(D13/F11),"",D13/F11) -> 0.18479409 | F13: =IF(ISERROR(D13),"",D13) -> 10500
C14: Resultado | D14: =IF(ISERROR(ROUND(F14/F13,2)),"",ROUND(F14/F13,2)) -> 1610.17 | F14: =IF(ISERROR(F12*365),"",F12*365) -> 16906800
C16: Prazo Médio de Pagamento de Compras | F16: =IF(ISERROR(SUM(F17:F18)),"",SUM(F17:F18)) -> 382480 | G16: Interpretação do índice
C17: Fornecedores | D17: =IF(ISERROR(Pas!$J$7),"",Pas!$J$7) -> 31840 | E17: =IF(ISERROR(D17/$F$16),"",D17/$F$16) -> 0.083246183 | F17: =IF(ISERROR(D17),"",D17) -> 31840 | G17: =IF(ISERROR("O prazo médio de pagamento das compras efutuadas junto aos fornecedores ao longo do ano é de " & ROUND($D$19,2) & " dias"),"","O prazo médio de pagamento das compras efutuadas junto aos fornecedores ao longo do ano é de " & ROUND($D$19,2) & " dias") -> O prazo médio de pagamento das compras efutuadas junto aos fornecedores ao longo do ano é de 33,14 dias
C18: Compras (CMV) | D18: =IF(ISERROR(Res!$J$7),"",Res!$J$7) -> 350640 | E18: =IF(ISERROR(D18/$F$16),"",D18/$F$16) -> 0.91675382 | F18: =IF(ISERROR(D18),"",D18) -> 350640
C19: Resultado | D19: =IF(ISERROR(ROUND(F19/F18,2)),"",ROUND(F19/F18,2)) -> 33.14 | F19: =IF(ISERROR(F17*365),"",F17*365) -> 11621600
C21: Ciclo Financeiro | F21: =IF(ISERROR(SUM(F22:F24)),"",SUM(F22:F24)) -> 1687.43 | G21: Interpretação do índice
C22: Prazo Médio de Recebimento de Vendas | D22: =IF(ISERROR($D$9),"",$D$9) -> 44.12 | E22: =IF(ISERROR(D22/$F$21),"",D22/$F$21) -> 0.02614627 | F22: =IF(ISERROR(D22),"",D22) -> 44.12 | G22: =IF(ISERROR("A quantidade de faturamento estável que a empresa necessita para atender seues compromissos operacionais é de " & ROUND($D$25,2) & " dias"),"","A quantidade de faturamento estável que a empresa necessita para atender seues compromissos operacionais é de " & ROUND($D$25,2) & " dias") -> A quantidade de faturamento estável que a empresa necessita para atender seues compromissos operacionais é de 1621,15 dias
C23: Prazo Médio Renovação dos Estoques | D23: =IF(ISERROR($D$14),"",$D$14) -> 1610.17 | E23: =IF(ISERROR(D23/$F$21),"",D23/$F$21) -> 0.9542144 | F23: =IF(ISERROR(D23),"",D23) -> 1610.17
C24: Prazo Médio de Pagamento de Compras | D24: =IF(ISERROR($D$19),"",$D$19) -> 33.14 | E24: =IF(ISERROR(D24/$F$21),"",D24/$F$21) -> 0.019639333 | F24: =IF(ISERROR(D24),"",D24) -> 33.14
C25: Resultado | D25: =IF(ISERROR(F22+F23-F24),"",F22+F23-F24) -> 1621.15

Sheet Ren
C1: 4. ALERTAS E DICAS
C6: Rentabilidade Patrimonial | F6: =IF(ISERROR(SUM(F7:F8)),"",SUM(F7:F8)) -> 216958 | G6: Interpretação do índice
C7: Resultado Líquido do Exercício | D7: =IF(ISERROR(Res!$E$21),"",Res!$E$21) -> 31136 | E7: =IF(ISERROR(F7/$F$6),"",F7/$F$6) -> 0.14351165 | F7: =IF(ISERROR(D7),"",D7) -> 31136 | G7: =IF(ISERROR("Seu retorno de Capital Próprio Investido é de R$ " & $D$9),"","Seu retorno de Capital Próprio Investido é de R$ " & $D$9) -> Seu retorno de Capital Próprio Investido é de R$ 16,76%
C8: Patrimônio Líquido | D8: =IF(ISERROR(Pasn!$J$55),"",Pasn!$J$55) -> 185822 | E8: =IF(ISERROR(F8/$F$6),"",F8/$F$6) -> 0.85648835 | F8: =IF(ISERROR(D8),"",D8) -> 185822
C9: Resultado | D9: =IF(ISERROR(ROUND($F$9/$F$8,2)&"%"),"",ROUND($F$9/$F$8,2)&"%") -> 16,76% | F9: =IF(ISERROR(F7*100),"",F7*100) -> 3113600
C11: Rentabilidade do Ativo | F11: =IF(ISERROR(SUM(D12:D13)),"",SUM(D12:D13)) -> 325916 | G11: Interpretação do índice
C12: Resultado Líquido do Exercício | D12: =IF(ISERROR(Res!$E$21),"",Res!$E$21) -> 31136 | E12: =IF(ISERROR(F12/$F$11),"",F12/$F$11) -> 0.095533819 | F12: =IF(ISERROR(D12),"",D12) -> 31136 | G12: =IF(ISERROR("Sua rentabilidade total de recursos administrados pela empresa é de " & ($D$14)),"","Sua rentabilidade total de recursos administrados pela empresa é de " & ($D$14)) -> Sua rentabilidade total de recursos administrados pela empresa é de 10,56%
C13: Ativo Total | D13: =IF(ISERROR(Bal!$J$24+Atin!$J$45),"",Bal!$J$24+Atin!$J$45) -> 294780 | E13: =IF(ISERROR(F13/$F$11),"",F13/$F$11) -> 0.90446618 | F13: =IF(ISERROR(D13),"",D13) -> 294780
C14: Resultado | D14: =IF(ISERROR((ROUND(F14/F13,2))&"%"),"",((ROUND(F14/F13,2)&"%"))) -> 10,56% | F14: =IF(ISERROR(F12*100),"",F12*100) -> 3113600
C16: Giro do Ativo | F16: =IF(ISERROR(SUM(F17:F18)),"",SUM(F17:F18)) -> 692950 | G16: Interpretação do índice
C17: Receita Líquida de Vendas | D17: =IF(ISERROR(Res!$E$8-Res!$J$8),"",Res!$E$8-Res!$J$8) -> 398170 | E17: =IF(ISERROR(F17/$F$16),"",F17/$F$16) -> 0.57460134 | F17: =IF(ISERROR(D17),"",D17) -> 398170 | G17: =IF(ISERROR("A cada R$ 1,00 de Ativo foi produzido de receita R$ "&ROUND($D$19,2)),"","A cada R$ 1,00 de Ativo foi produzido de receita R$ "&ROUND($D$19,2)) -> A cada R$ 1,00 de Ativo foi produzido de receita R$ 1,35
C18: Ativo Total | D18: =IF(ISERROR(Bal!$J$24+Atin!$J$45),"",Bal!$J$24+Atin!$J$45) -> 294780 | E18: =IF(ISERROR(F18/$F$16),"",F18/$F$16) -> 0.42539866 | F18: =IF(ISERROR(D18),"",D18) -> 294780
C19: Resultado | D19: =IF(ISERROR(F17/F18),"",F17/F18) -> 1.3507361
C21: Margem Líquida | F21: =IF(ISERROR(SUM(F22:F23)),"",SUM(F22:F23)) -> 439806 | G21: Interpretação do índice
C22: Resultado Líquido do Exercício | D22: =IF(ISERROR(Res!$E$21),"",Res!$E$21) -> 31136 | E22: =IF(ISERROR(F22/$F$21),"",F22/$F$21) -> 0.07079485 | F22: =IF(ISERROR(D22),"",D22) -> 31136 | G22: =IF(ISERROR("A capacidade da Empresa em gerar lucro comparativamente à Receita Líquida é de " & ($D$24)),"","A capacidade da Empresa em gerar lucro comparativamente à Receita Líquida é de R$ " & ($D$24)) -> A capacidade da Empresa em gerar lucro comparativamente à Receita Líquida é de R$ 7,62%
C23: Receita Líquida | D23: =IF(ISERROR(Dre!$J$18),"",Dre!$J$18) -> 408670 | E23: =IF(ISERROR(F23/$F$21),"",F23/$F$21) -> 0.92920515 | F23: =IF(ISERROR(D23),"",D23) -> 408670
C24: Resultado | D24: =IF(ISERROR(ROUND(F24/F23,2)&"%"),"",ROUND(F24/F23,2)&"%") -> 7,62% | F24: =IF(ISERROR(F22*100),"",F22*100) -> 3113600
F30: =F27-1 -> -1

Sheet Gcg
C1: 4. ALERTAS E DICAS
C6: GIR - Geração Interna de Recursos / Faturamento Líquido | F6: =IF(ISERROR(SUM(F7:F8)),"",SUM(F7:F8)) -> 700 | G6: Interpretação do índice
C7: Geração Interna de Recurso | D7: 300 | E7: =IF(ISERROR(D3/$F$6),"",F7/$F$6) -> 0.42857143 | F7: =IF(ISERROR(D7),"",D7) -> 300 | G7: =IF(ISERROR("Sua capacidade em gerar caixa comparativamente à Receita Líquida de Vendas é de " & ($D$9)),"","Sua capacidade em gerar caixa comparativamente à Receita Líquida de Vendas é de " & ($D$9)) -> Sua capacidade em gerar caixa comparativamente à Receita Líquida de Vendas é de 75%
C8: Receita Líquida de Vendas | D8: 400 | E8: =IF(ISERROR(D4/$F$6),"",F8/$F$6) -> 0.57142857 | F8: =IF(ISERROR(D8),"",D8) -> 400
C9: Resultado | D9: =IF(ISERROR(ROUND(F9/F8,2)&"%"),"",ROUND(F9/F8,2)&"%") -> 75% | F9: =IF(ISERROR(F7*100),"",F7*100) -> 30000
C11: Margem “EBTDA” | F11: =IF(ISERROR(SUM(F12:F13)),"",SUM(F12:F13)) -> 800 | G11: Interpretação do índice
C12: EBTIDA | D12: 500 | E12: =IF(ISERROR(F12/$F$11),"",F12/$F$11) -> 0.625 | F12: =IF(ISERROR(D12),"",D12) -> 500 | G12: =IF(ISERROR("Sua capacidade de pagar o custo dos recursoso onerosos é de "&($D$14)),"","Sua capacidade de pagar o custo dos recursoso onerosos é de "&($D$14)) -> Sua capacidade de pagar o custo dos recursoso onerosos é de 166,67%
C13: Receita Líquida de Vendas | D13: 300 | E13: =IF(ISERROR(F13/$F$11),"",F13/$F$11) -> 0.375 | F13: =IF(ISERROR(D13),"",D13) -> 300
C14: Resultado | D14: =IF(ISERROR(ROUND(F14/F13,2)&"%"),"",ROUND(F14/F13,2)&"%") -> 166,67% | F14: =IF(ISERROR(F12*100),"",F12*100) -> 50000
C16: Cobertura de Dívidas (em meses) | F16: =IF(ISERROR(SUM(F17:F18)),"",SUM(F17:F18)) -> 600 | G16: Interpretação do índice
C17: Capital de Terceiros | D17: 200 | E17: =IF(ISERROR(F17/$F$16),"",F17/$F$16) -> 0.33333333 | F17: =IF(ISERROR(D17),"",D17) -> 200 | G17: =IF(ISERROR("Sua capacidade de pagar suas dívidads totais com a geração de lucro da atividade é de "&ROUND($D$19,2) & " meses"),"","Sua capacidade de pagar suas dívidads totais com a geração de lucro da atividade é de "&ROUND($D$19,2) & " meses") -> Sua capacidade de pagar suas dívidads totais com a geração de lucro da atividade é de 6 meses
C18: EBTIDA | D18: 400 | E18: =IF(ISERROR(F18/$F$16),"",F18/$F$16) -> 0.66666667 | F18: =IF(ISERROR(D18),"",D18) -> 400
C19: Resultado | D19: =IF(ISERROR(F17/F19),"",F17/F19) -> 6 | F19: =IF(ISERROR(F18/12),"",F18/12) -> 33.333333
C21: Despesas Financeiras / EBTIDA | F21: =IF(ISERROR(SUM(F22:F23)),"",SUM(F22:F23)) -> 500 | G21: Interpretação do índice
C22: Despesas Financeiras | D22: 200 | E22: =IF(ISERROR(F22/$F$21),"",F22/$F$21) -> 0.4 | F22: =IF(ISERROR(D22),"",D22) -> 200 | G22: =IF(ISERROR("Suas despesas financeiras absorvidas do EBTIDA são de " & ($D$24)),"","Suas despesas financeiras absorvidas do EBTIDA são de " & ($D$24)) -> Suas despesas financeiras absorvidas do EBTIDA são de 66,67%
C23: EBTIDA | D23: 300 | E23: =IF(ISERROR($F$23/$F$21),"",$F$23/$F$21) -> 0.6 | F23: =IF(ISERROR(D23),"",D23) -> 300
C24: Resultado | D24: =IF(ISERROR(ROUND($F$24/$F$23,2) &"%"),"",ROUND($F$24/$F$23,2) &"%") -> 66,67% | F24: =IF(ISERROR(F22*100),"",F22*100) -> 20000
C26: Dívida Bancária em dias de Faturamento | F26: =IF(ISERROR(SUM(F27:F28)),"",SUM(F27:F28)) -> 220 | G26: Interpretação do índice
C27: Recursos Onerosos (do Passivo Circulante) | D27: 20 | E27: =IF(ISERROR(F27/$F$26),"",F27/$F$26) -> 0.090909091 | F27: =IF(ISERROR(D27),"",D27) -> 20 | G27: =IF(ISERROR("A quantidade de dias de faturamento necessários para amortizar os recursoso onerosos da empresas é de " &ROUND($D$29,2) & " dias"),"","A quantidade de dias de faturamento necessários para amortizar os recursoso onerosos da empresas é de " &ROUND($D$29,2) & " dias") -> A quantidade de dias de faturamento necessários para amortizar os recursoso onerosos da empresas é de 36,5 dias
C28: Receita Líquida de Vendas | D28: 200 | E28: =IF(ISERROR(F28/$F$26),"",F28/$F$26) -> 0.90909091 | F28: =IF(ISERROR(D28),"",D28) -> 200
C29: Resultado | D29: =IF(ISERROR(F29/F28),"",F29/F28) -> 36.5 | F29: =IF(ISERROR(F27*365),"",F27*365) -> 7300
C31: PMR - Prazo Médio de Recebimento | F31: =IF(ISERROR(SUM(F32:F33)),"",SUM(F32:F33)) -> 700 | G31: Interpretação do índice
C32: Ativos Operacionais | D32: 300 | E32: =IF(ISERROR(F32/$F$31),"",F32/$F$31) -> 0.42857143 | F32: =IF(ISERROR(D32),"",D32) -> 300 | G32: =IF(ISERROR("O prazo médio que os Ativos Opreracionais demorarão para serem transformados em caixa são de " &ROUND($D$34,2) & " dias"),"","O prazo médio que os Ativos Opreracionais demorarão para serem transformados em caixa são de " &ROUND($D$34,2) & " dias") -> O prazo médio que os Ativos Opreracionais demorarão para serem transformados em caixa são de 273,75 dias
C33: Receita Líquida de Vendas | D33: 400 | E33: =IF(ISERROR(F33/$F$31),"",F33/$F$31) -> 0.57142857 | F33: =IF(ISERROR(D33),"",D33) -> 400
C34: Resultado | D34: =IF(ISERROR(F34/F33),"",F34/F33) -> 273.75 | F34: =IF(ISERROR(F32*365),"",F32*365) -> 109500
C36: PMP - Prazo Médio de Pagamentos | F36: =IF(ISERROR(SUM(F37:F38)),"",SUM(F37:F38)) -> 700 | G36: Interpretação do índice
C37: Passivos Operacionais | D37: 300 | E37: =IF(ISERROR(F37/$F$36),"",F37/$F$36) -> 0.42857143 | F37: =IF(ISERROR(D37),"",D37) -> 300 | G37: =IF(ISERROR("O prazo de médio de vencimento dos Passivos Operacionais em dias são de " &ROUND($D$39,2) & " dias"),"","O prazo de médio de vencimento dos Passivos Operacionais em dias são de " &ROUND($D$39,2) & " dias") -> O prazo de médio de vencimento dos Passivos Operacionais em dias são de 273,75 dias
C38: Receita Líquida de Vendas | D38: 400 | E38: =IF(ISERROR(F38/$F$36),"",F38/$F$36) -> 0.57142857 | F38: =IF(ISERROR(D38),"",D38) -> 400
C39: Resultado | D39: =IF(ISERROR(F39/F38),"",F39/F38) -> 273.75 | F39: =IF(ISERROR(F37*365),"",F37*365) -> 109500
C41: CF - Ciclo Financeiro | F41: =IF(ISERROR(SUM(F42:F43)),"",SUM(F42:F43)) -> 850 | G41: Interpretação do índice
C42: Prazo Médio de Recebimento | D42: 500 | E42: =IF(ISERROR(F42/$F$41),"",F42/$F$41) -> 0.58823529 | F42: =IF(ISERROR(D42),"",D42) -> 500 | G42: =IF(ISERROR("A quantidade de dias que a empresa necessita de financiamento de capital de giro são de " &ROUND($D$44,2) & " dias"),"","A quantidade de dias que a empresa necessita de financiamento de capital de giro são de " &ROUND($D$44,2) & " dias") -> A quantidade de dias que a empresa necessita de financiamento de capital de giro são de 150 dias
C43: Prazo Médio de Pagamento | D43: 350 | E43: =IF(ISERROR(F43/$F$41),"",F43/$F$41) -> 0.41176471 | F43: =IF(ISERROR(D43),"",D43) -> 350
C44: Resultado | D44: =IF(ISERROR(F42-F43),"",F42-F43) -> 150

Sheet Rel
C1: 5. RELATÓRIOS DE IMPRESSÃO
C5: RELATÓRIO DE IMPRESSÃO:
C6: BALANÇO PATRIMÔNIAL E ANÁLISE DE BALANÇO
C9: 1 - Ativo Circulante
C10: 1.1 - Ativo Não Circulante
C11: 1.2 - Passivo Circulante
C12: 1.3 - Passivo Não Circulante
C13: 1.4 - Balanço Patromônial
C14: 2 - Receitas
C15: 2.1 - Despesas
C16: 2.2 - DRE
C17: 3 - Gráficos
C19: 1 - ATIVO CIRCULANTE
C20: 1000 | D20: Contas do Ativo Circulante - Resultado
C21: 1110 | D21: Disponibilidades | E21: =IF(ISERROR(Bal!J7),"",Bal!J7) -> 57560 | F21: =IF(ISERROR(Bal!K7),"",Bal!K7) -> 0.37552192 | G21: 1160 | H21: Clientes Vencidos a Liquidar | I21: =IF(ISERROR(Bal!J12),"",Bal!J12) -> 0 | J21: =IF(ISERROR(Bal!K12),"",Bal!K12) -> 0
C22: 1120 | D22: Aplicações em Instrumentos Financeiros | E22: =IF(ISERROR(Bal!J8),"",Bal!J8) -> 0 | F22: =IF(ISERROR(Bal!K8),"",Bal!K8) -> 0 | G22: 1170 | H22: Outros Créditos | I22: =IF(ISERROR(Bal!J13),"",Bal!J13) -> 0 | J22: =IF(ISERROR(Bal!K13),"",Bal!K13) -> 0
C23: 1130 | D23: Estoque | E23: =IF(ISERROR(Bal!J9),"",Bal!J9) -> 46320 | F23: =IF(ISERROR(Bal!K9),"",Bal!K9) -> 0.30219207 | G23: 1180 | H23: Outros Valores e Bens | I23: =IF(ISERROR(Bal!J14),"",Bal!J14) -> 0 | J23: =IF(ISERROR(Bal!K14),"",Bal!K14) -> 0
C24: 1140 | D24: Créditos Tributários | E24: =IF(ISERROR(Bal!J10),"",Bal!J10) -> 0 | F24: =IF(ISERROR(Bal!K10),"",Bal!K10) -> 0 | G24: 1190 | H24: Despesas Antecipadas | I24: =IF(ISERROR(Bal!J15),"",Bal!J15) -> 0 | J24: =IF(ISERROR(Bal!K15),"",Bal!K15) -> 0
C25: 1150 | D25: Clientes Créditos a Receber | E25: =IF(ISERROR(Bal!J11),"",Bal!J11) -> 49400 | F25: =IF(ISERROR(Bal!K11),"",Bal!K11) -> 0.32228601 | G25: Resultado | I25: =IF(ISERROR(Bal!J24),"",Bal!J24) -> 153280
C27: 1.1 - ATIVO NÃO CIRCULANTE
C28: 2000 | D28: Contas do Ativo Não Circulante - Resultado
C29: 2200 | D29: Valores e Bens | E29: =IF(ISERROR(Atin!J7),"",Atin!J7) -> 65000 | F29: =IF(ISERROR(Atin!K7),"",Atin!K7) -> 0.45936396 | G29: 2330 | H29: Ativo Diferido | I29: =IF(ISERROR(Atin!J15),"",Atin!J15) -> 18500 | J29: =IF(ISERROR(Atin!K15),"",Atin!K15) -> 0.13074205
C30: 2220 | D30: Garantias e Cauções | E30: =IF(ISERROR(Atin!J8),"",Atin!J8) -> 0 | F30: =IF(ISERROR(Atin!K8),"",Atin!K8) -> 0 | G30: 2340 | H30: Intangível | I30: =IF(ISERROR(Atin!J16),"",Atin!J16) -> 20000 | J30: =IF(ISERROR(Atin!K16),"",Atin!K16) -> 0.14134276
C31: 2230 | D31: Aplicações em Instrumentos Financeiros a Longo Prazo | E31: =IF(ISERROR(Atin!J9),"",Atin!J9) -> 0 | F31: =IF(ISERROR(Atin!K9),"",Atin!K9) -> 0 | G31: 2350 | H31: Imobilizado de Arrendamento (Leaseback) | I31: =IF(ISERROR(Atin!J17),"",Atin!J17) -> 0 | J31: =IF(ISERROR(Atin!K17),"",Atin!K17) -> 0
C32: 2240 | D32: Depósitos Judiciais | E32: =IF(ISERROR(Atin!J10),"",Atin!J10) -> 0 | F32: =IF(ISERROR(Atin!K10),"",Atin!K10) -> 0 | G32: 2360 | H32: Imobilizado Para Locação | I32: =IF(ISERROR(Atin!J18),"",Atin!J18) -> 0 | J32: =IF(ISERROR(Atin!K18),"",Atin!K18) -> 0
C33: 2250 | D33: Imóveis para Locação ou Venda | E33: =IF(ISERROR(Atin!J11),"",Atin!J11) -> 0 | F33: =IF(ISERROR(Atin!K11),"",Atin!K11) -> 0 | G33: 2370 | H33: Ativo Biológico e Produto Agrícola | I33: =IF(ISERROR(Atin!J19),"",Atin!J19) -> 0 | J33: =IF(ISERROR(Atin!K19),"",Atin!K19) -> 0
C34: 2290 | D34: Outras Contas do Realizável | E34: =IF(ISERROR(Atin!J12),"",Atin!J12) -> 0 | F34: =IF(ISERROR(Atin!K12),"",Atin!K12) -> 0 | G34: 2380 | H34: Imobilzado Recebido em Comodato | I34: =IF(ISERROR(Atin!J20),"",Atin!J20) -> 0 | J34: =IF(ISERROR(Atin!K20),"",Atin!K20) -> 0
C35: 2310 | D35: Investimentos | E35: =IF(ISERROR(Atin!J13),"",Atin!J13) -> 0 | F35: =IF(ISERROR(Atin!K13),"",Atin!K13) -> 0 | G35: 2390 | H35: Outros | I35: =IF(ISERROR(Atin!J21),"",Atin!J21) -> -12000 | J35: =IF(ISERROR(Atin!K21),"",Atin!K21) -> -0.084805654
C36: 2320 | D36: Imobilizado de Uso | E36: =IF(ISERROR(Atin!J14),"",Atin!J14) -> 50000 | F36: =IF(ISERROR(Atin!K14),"",Atin!K14) -> 0.35335689 | G36: Resultado | I36: =IF(ISERROR(Atin!J45),"",Atin!J45) -> 141500
C38: 1.2 - PASSIVO CIRCULANTE
C39: 3400 | D39: Contas do Passivo Circulante - Resultado
C40: 3410 | D40: Fornecedores | E40: =IF(ISERROR(Pas!J7),"",Pas!J7) -> 31840 | F40: =IF(ISERROR(Pas!K7),"",Pas!K7) -> 0.54004546 | G40: 3410 | H40: Obrigações Administrativas e Operacionais | I40: =IF(ISERROR(Pas!J12),"",Pas!J12) -> 5494 | J40: =IF(ISERROR(Pas!K12),"",Pas!K12) -> 0.093184979
C41: 3410 | D41: Obrigações Financeiras a Curto Prazo | E41: =IF(ISERROR(Pas!J8),"",Pas!J8) -> 0 | F41: =IF(ISERROR(Pas!K8),"",Pas!K8) -> 0 | G41: 3410 | H41: Provisões para Contingências | I41: =IF(ISERROR(Pas!J13),"",Pas!J13) -> 0 | J41: =IF(ISERROR(Pas!K13),"",Pas!K13) -> 0
C42: 3410 | D42: Obrigações Fiscais e Tributárias | E42: =IF(ISERROR(Pas!J9),"",Pas!J9) -> 0 | F42: =IF(ISERROR(Pas!K9),"",Pas!K9) -> 0 | G42: 3410 | H42: Relações Interfinanceiras | I42: =IF(ISERROR(Pas!J14),"",Pas!J14) -> 0 | J42: =IF(ISERROR(Pas!K14),"",Pas!K14) -> 0
C43: 3410 | D43: Obrigações Trabalhistas e Previdenciárias | E43: =IF(ISERROR(Pas!J10),"",Pas!J10) -> 12750 | F43: =IF(ISERROR(Pas!K10),"",Pas!K10) -> 0.21625564 | G43: 3410 | H43: Outras Obrigações | I43: =IF(ISERROR(Pas!J15),"",Pas!J15) -> 0 | J43: =IF(ISERROR(Pas!K15),"",Pas!K15) -> 0
C44: 3410 | D44: Obrigações Sociais e Estatutárias | E44: =IF(ISERROR(Pas!J11),"",Pas!J11) -> 8874 | F44: =IF(ISERROR(Pas!K11),"",Pas!K11) -> 0.15051393 | G44: Resultado | I44: =IF(ISERROR(Pas!J27),"",Pas!J27) -> 58958
C46: 1.3 - PASSIVO NÃO CIRCULANTE
C47: 4000 | D47: Contas do Passivo Não Circulante - Resultado
C48: 4510 | D48: Fornecedores | E48: =IF(ISERROR(Pasn!J7),"",Pasn!J7) -> 50000 | F48: =IF(ISERROR(Pasn!K7),"",Pasn!K7) -> 0.21202432 | G48: 5710 | H48: Capital / Capital Social / Patrimônio Social | I48: =IF(ISERROR(Pasn!J18),"",Pasn!J18) -> 120000 | J48: =IF(ISERROR(Pasn!K18),"",Pasn!K18) -> 0.50885838
C49: 4520 | D49: Obrigações Financeiras a Longo Prazo | E49: =IF(ISERROR(Pasn!J8),"",Pasn!J8) -> 0 | F49: =IF(ISERROR(Pasn!K8),"",Pasn!K8) -> 0 | G49: 5720 | H49: Reserva de Capital | I49: =IF(ISERROR(Pasn!J19),"",Pasn!J19) -> 1556 | J49: =IF(ISERROR(Pasn!K19),"",Pasn!K19) -> 0.0065981969
C50: 4530 | D50: Obrigações Fiscais e Tributárias | E50: =IF(ISERROR(Pasn!J9),"",Pasn!J9) -> 0 | F50: =IF(ISERROR(Pasn!K9),"",Pasn!K9) -> 0 | G50: 5730 | H50: Ações em Tesouraria | I50: =IF(ISERROR(Pasn!J20),"",Pasn!J20) -> 0 | J50: =IF(ISERROR(Pasn!K20),"",Pasn!K20) -> 0
C51: 4540 | D51: Obrigações Trabalhistas e Previdenciárias | E51: =IF(ISERROR(Pasn!J10),"",Pasn!J10) -> 0 | F51: =IF(ISERROR(Pasn!K10),"",Pasn!K10) -> 0 | G51: 5740 | H51: Ajustes de Avaliação Patrimônial | I51: =IF(ISERROR(Pasn!J21),"",Pasn!J21) -> 0 | J51: =IF(ISERROR(Pasn!K21),"",Pasn!K21) -> 0
C52: 4550 | D52: Obrigações Sociais e Estatutárias | E52: =IF(ISERROR(Pasn!J11),"",Pasn!J11) -> 0 | F52: =IF(ISERROR(Pasn!K11),"",Pasn!K11) -> 0 | G52: 5750 | H52: Reservas de Lucros | I52: =IF(ISERROR(Pasn!J22),"",Pasn!J22) -> 64266 | J52: =IF(ISERROR(Pasn!K22),"",Pasn!K22) -> 0.2725191
C53: 4560 | D53: Créditos de Coligadas e Controladas | E53: =IF(ISERROR(Pasn!J12),"",Pasn!J12) -> 0 | F53: =IF(ISERROR(Pasn!K12),"",Pasn!K12) -> 0 | G53: 5760 | H53: Reservas de Reavaliação | I53: =IF(ISERROR(Pasn!J23),"",Pasn!J23) -> 0 | J53: =IF(ISERROR(Pasn!K23),"",Pasn!K23) -> 0
C54: 4570 | D54: Provisões para Contingências | E54: =IF(ISERROR(Pasn!J13),"",Pasn!J13) -> 0 | F54: =IF(ISERROR(Pasn!K13),"",Pasn!K13) -> 0 | G54: 5770 | H54: Outras Reservas | I54: =IF(ISERROR(Pasn!J24),"",Pasn!J24) -> 0 | J54: =IF(ISERROR(Pasn!K24),"",Pasn!K24) -> 0
C55: 4580 | D55: Receitas Diferidas | E55: =IF(ISERROR(Pasn!J14),"",Pasn!J14) -> 0 | F55: =IF(ISERROR(Pasn!K14),"",Pasn!K14) -> 0 | G55: 5780 | H55: Lucros Acumulados / Sobras / Superávits | I55: =IF(ISERROR(Pasn!J25),"",Pasn!J25) -> 0 | J55: =IF(ISERROR(Pasn!K25),"",Pasn!K25) -> 0
C56: 4590 | D56: Outras Obrigações | E56: =IF(ISERROR(Pasn!J15),"",Pasn!J15) -> 0 | F56: =IF(ISERROR(Pasn!K15),"",Pasn!K15) -> 0 | G56: 5790 | H56: Prejuízos, Perdas e Déficits Acumulados | I56: =IF(ISERROR(Pasn!J26),"",Pasn!J26) -> 0 | J56: =IF(ISERROR(Pasn!K26),"",Pasn!K26) -> 0
C57: 4610 | D57: Resultados de Exercícios Futuros - Receitas Diferidas | E57: =IF(ISERROR(Pasn!J16),"",Pasn!J16) -> 0 | F57: =IF(ISERROR(Pasn!K16),"",Pasn!K16) -> 0 | G57: Resultado | I57: =IF(ISERROR(Pasn!J58),"",Pasn!J58) -> 235822
C58: 4620 | D58: Custos e Despesas de Exercícios Futuros | E58: =IF(ISERROR(Pasn!J17),"",Pasn!J17) -> 0 | F58: =IF(ISERROR(Pasn!K17),"",Pasn!K17) -> 0
C60: 1.4 - BALANÇO PATRIMÔNIAL
C61: Resultado Total
C62: Ativo | E62: ='Res Bp'!E37:F37 -> 294780
C63: Passivo | E63: ='Res Bp'!E38:F38 -> 294780
C64: Resultado | E64: ='Res Bp'!E39:F39 -> 0
C66: 2 - RECEITAS - DRE
C67: 6800 | D67: Contas de Resultado Credora (Receitas) - Resultado
C68: 6810 | D68: Receitas de Exportação | E68: =IF(ISERROR(Dre!J7),"",Dre!J7) -> 0 | F68: =IF(ISERROR(Dre!K7),"",Dre!K7) -> 0 | G68: 6860 | H68: Receitas das Atividades de Educação e Saúde | I68: =IF(ISERROR(Dre!J12),"",Dre!J12) -> 0 | J68: =IF(ISERROR(Dre!K12),"",Dre!K12) -> 0
C69: 6820 | D69: Receita da Venda de Produtos | E69: =IF(ISERROR(Dre!J8),"",Dre!J8) -> 408670 | F69: =IF(ISERROR(Dre!K8),"",Dre!K8) -> 1 | G69: 6870 | H69: Receitas das Atividades de Assistência Social | I69: =IF(ISERROR(Dre!J13),"",Dre!J13) -> 0 | J69: =IF(ISERROR(Dre!K13),"",Dre!K13) -> 0
C70: 6830 | D70: Receitas da Revenda de Mercadorias | E70: =IF(ISERROR(Dre!J9),"",Dre!J9) -> 0 | F70: =IF(ISERROR(Dre!K9),"",Dre!K9) -> 0 | G70: 6880 | H70: Receitas das Atividades Imobiliárias | I70: =IF(ISERROR(Dre!J14),"",Dre!J14) -> 0 | J70: =IF(ISERROR(Dre!K14),"",Dre!K14) -> 0
C71: 6840 | D71: Receitas da Prestação de Serviços | E71: =IF(ISERROR(Dre!J10),"",Dre!J10) -> 0 | F71: =IF(ISERROR(Dre!K10),"",Dre!K10) -> 0 | G71: 6890 | H71: Receitas das Atividades em Geral | I71: =IF(ISERROR(Dre!J15),"",Dre!J15) -> 0 | J71: =IF(ISERROR(Dre!K15),"",Dre!K15) -> 0
C72: 6850 | D72: Receitas da Atividade Rural | E72: =IF(ISERROR(Dre!J11),"",Dre!J11) -> 0 | F72: =IF(ISERROR(Dre!K11),"",Dre!K11) -> 0 | G72: Resultado | I72: =IF(ISERROR(Dre!J18),"",Dre!J18) -> 408670
C74: 2.1 - DESPESAS (DRE)
C75: 6900 | D75: Contas de Resultado Devedoras (Custos e Despesas) - Resultado
C76: 6910 | D76: Custo | E76: =IF(ISERROR(Des!J7),"",Des!J7) -> 350640 | F76: =IF(ISERROR(Des!K7),"",Des!K7) -> 0.92876403 | G76: 6960 | H76: Despesas das Atividades Ligadas à Educação e Saúde | I76: =IF(ISERROR(Des!J12),"",Des!J12) -> 0 | J76: =IF(ISERROR(Des!K12),"",Des!K12) -> 0
C77: 6920 | D77: Despesa da Venda de Produtos | E77: =IF(ISERROR(Des!J8),"",Des!J8) -> 10500 | F77: =IF(ISERROR(Des!K8),"",Des!K8) -> 0.027812065 | G77: 6970 | H77: Despesas de Atividades de Assistência Social | I77: =IF(ISERROR(Des!J13),"",Des!J13) -> 0 | J77: =IF(ISERROR(Des!K13),"",Des!K13) -> 0
C78: 6930 | D78: Despesas da Revenda de Mercadorias | E78: =IF(ISERROR(Des!J9),"",Des!J9) -> 0 | F78: =IF(ISERROR(Des!K9),"",Des!K9) -> 0 | G78: 6980 | H78: Despesas das Atividades Imobiliárias | I78: =IF(ISERROR(Des!J14),"",Des!J14) -> 0 | J78: =IF(ISERROR(Des!K14),"",Des!K14) -> 0
C79: 6940 | D79: Despesas da Prestação de Serviços | E79: =IF(ISERROR(Des!J10),"",Des!J10) -> 0 | F79: =IF(ISERROR(Des!K10),"",Des!K10) -> 0 | G79: 6990 | H79: Despesas das Atividades em Geral | I79: =IF(ISERROR(Des!J15),"",Des!J15) -> 16394 | J79: =IF(ISERROR(Des!K15),"",Des!K15) -> 0.043423904
C80: 6950 | D80: Despesas da Atividade Rural | E80: =IF(ISERROR(Des!J11),"",Des!J11) -> 0 | F80: =IF(ISERROR(Des!K11),"",Des!K11) -> 0 | G80: Resultado | I80: =IF(ISERROR(Des!J18),"",Des!J18) -> 377534
C82: 2.2 - DEMONSTRAÇÃO DE RESULTADO DE EXERCÍCIO (DRE)
C83: Demonstração do Resultado do Exercício (DRE)
C84: Contas de Resultado Credora (Receitas) | E84: =IF(ISERROR(Res!E19),"",Res!E19) -> 408670 | F84: =IF(ISERROR(Res!F19),"",Res!F19) -> 0.51980148
C85: Contas de Resultado Devedoras (Custos e Despesas) | E85: =IF(ISERROR(Res!E20),"",Res!E20) -> 377534 | F85: =IF(ISERROR(Res!F20),"",Res!F20) -> 0.51980148
C86: Resultado do Exercício | E86: =IF(ISERROR(Res!E21),"",Res!E21) -> 31136
C88: 3 - GRÁFICOS
C89: Ativo Circulante
C102: Ativo Não Circulante
C115: Passivo Cirulante
C128: Passivo Não Circulante
C141: Balanço Patrimônial
C151: Balanço Patrimônial
C160: Receita
C173: Despesas
C186: DRE
C195: DRE

Sheet Dúvidas
C1: DÚVIDAS FREQUENTES
C5: Clique abaixo para selecionar sua dúvida:
C6: 1. Posso adicionar mais linhas e colunas na planilha?
C7: Veja a resposta abaixo:
C8: =IFERROR(VLOOKUP(C6,C60:J74,8,FALSE),"") -> Nós recomendamos fortemente que você utilize a estrutura pronta apresentada, pois existem diversas fórmulas que podem ser afetadas pela adição de linhas e colunas. Além disso, para facilitar o preenchimento mantemos a planilha desbloqueada apenas nos locais para preenchimento.
C60: =IF(E60="","",D60&". "&E60) -> 1. Posso adicionar mais linhas e colunas na planilha? | D60: 1 | E60: Posso adicionar mais linhas e colunas na planilha? | J60: Nós recomendamos fortemente que você utilize a estrutura pronta apresentada, pois existem diversas fórmulas que podem ser afetadas pela adição de linhas e colunas. Além disso, para facilitar o preenchimento mantemos a planilha desbloqueada apenas nos locais para preenchimento.
C61: =IF(E61="","",D61&". "&E61) -> 2. Posso remover linhas? | D61: 2 | E61: Posso remover linhas? | J61: Nós recomendamos fortemente que você utilize a estrutura pronta apresentada, pois existem diversas fórmulas que podem ser afetadas pela adição de linhas e colunas. Além disso, para facilitar o preenchimento mantemos a planilha desbloqueada apenas nos locais para preenchimento.
C62: =IF(E62="","",D62&". "&E62) -> 3. Para que servem os alertas? | D62: 3 | E62: Para que servem os alertas? | J62: Eles são avisos sobre como a sua projeção está. A partir deles, você pode refinar suas projeções e pensar em medidas mais agressivas para tornar seu projeto mais agressivo.
C63: =IF(E63="","",D63&". "&E63) -> 4. Essa planilha pode ser apresentada para instituições financeiras? | D63: 4 | E63: Essa planilha pode ser apresentada para instituições financeiras? | J63: Sim. Porém esses dados não garantem aprovações ou reprovações por parte dessas instituições. Sendo usados como dados complementares.
C64: =IF(E64="","",D64&". "&E64) -> 5. Como desbloquear a planilha? | D64: 5 | E64: Como desbloquear a planilha? | J64: Basta entrar no menu superior "Revisão" e escolher o item desproteger planilha no grupo Alterações. As planilhas não possuem senhas, apenas estão bloqueadas para melhorar a usabilidade delas.
C65: =IF(E65="","",D65&". "&E65) -> 6. Como redimensiono uma coluna ou linha da planilha? | D65: 6 | E65: Como redimensiono uma coluna ou linha da planilha? | J65: Com a planilha desbloqueada(ver pergunta 5), clique sobre o número da linha com o botão diretiro e escolha a opção altura da linha no caso das linhas ou na letra da coluna com o botão direito e escolha a opção largura da coluna no caso de colunas.
C66: =IF(E66="","",D66&". "&E66) -> 7. Como faço para imprimir uma planilha? | D66: 7 | E66: Como faço para imprimir uma planilha? | J66: Escolha Opção Arquivo e vá ao item imprimir no seu menu superior.
C67: =IF(E67="","",D67&". "&E67) -> 8. Como mudo a moeda da planilha? | D67: 8 | E67: Como mudo a moeda da planilha? | J67: Selecione os campos que deseja mudar a moeda. Clique com o botão direito escolha a opção formatar células. Altere o símbolo para o formato que desejar na guia Número.
C68: =IF(E68="","",D68&". "&E68) -> 9. O que é Balanço Patrmônial? | D68: 9 | E68: O que é Balanço Patrmônial? | J68: Balanço Patrimonial é a demonstração contábil destinada a evidenciar, qualitativa e quantitativamente, numa determinada data, a posição patrimonial e financeira da Entidade.
C69: =IF(E69="","",D69&". "&E69) -> 10. O que é Ativo Circulante? | D69: 10 | E69: O que é Ativo Circulante? | J69: O denominado "Ativo Circulante" constitui-se no grupo de contas contábil que registra as disponibilidades (caixa, bancos conta movimento e aplicações financeiras), os título negociáveis (como duplicatas a receber), os estoques e outros créditos de realização a curto prazo, como adiantamento a fornecedores e empregados.
C70: =IF(E70="","",D70&". "&E70) -> 11. O que é Ativo Não Circulante? | D70: 11 | E70: O que é Ativo Não Circulante? | J70: No grupo de contas contábeis denominado Ativo Não Circulante são registrados todos os bens de permanência duradoura, destinados ao funcionamento normal da entidade e do seu empreendimento, assim como os direitos exercidos com essa finalidade.
C71: =IF(E71="","",D71&". "&E71) -> 12. O que é Passivo Circulante? | D71: 12 | E71: O que é Passivo Circulante? | J71: No grupo denominado "Passivo Circulante" são escrituradas as obrigações da entidade, inclusive financiamentos para aquisição de direitos do ativo não-circulante, quando se vencerem no exercício seguinte (prazo de 12 meses seguintes ao do balanço).
... C74: =IF(E74="","",D74&". "&E74) -> 15. O que é Análise de Balanço? | D74: 15 | E74: O que é Análise de Balanço? | J74: Denomina-se análise de balanço a atividade que busca identificar fatores positivos ou negativos sobre a saúde financeira e administrativa das empresas nos números divulgados em seus balanços patrimoniais.

Sheet Sugestões
C1: SUGESTÕES PARA VOCÊ
C6: Veja as 7 ferramentas mais indicadas para você
C8: 1 | D8: Pacote de Planilhas de Finanças Empresariais | G8: 6 | H8: Pacote de Planilhas para Departamento Pessoal
D9: Você encontrará as ferramentas certas para controlar as entradas e saídas de suas contas, acompanhar o fluxo de caixa mensal durante a sua operação, calcular a lucratividade e mais outras funções. | H9: Adquira 7 planilhas de Departamento Pessoal que te ajudarão a administrar a sua empresa
C12: 2 | D12: Pacote de Planilhas com Apostila: Controle Financeiro | G12: 7 | H12: Apresentação de Resultados Financeiros
D13: Nesse pacote você encontrará o passo a passo para não se perder ao longo do processo e ter a certeza de que está montando a melhor estrutura financeira possível para sua empresa | H13: Economize tempo na hora de apresentar os Resultados Financeiros da sua empresa abordando pontos cruciais de maneira eficiente e um design elegante
C16: 3 | D16: Planilha de Formação de Preços para Serviços
D17: Com ela é possível descobrir qual é o preço ideal que você deve praticar no seu mercado levando em consideração todos os fatores importantes para a sua empresa
C20: 4 | D20: Planilha de Estudo de Viabilidade Econômica 3.0
D21: Descubra a viabilidade do seu investimento com apenas uma planilha
C24: 5 | D24: Planilha de Folha de Pagamento
D25: Ganhe tempo controlando com uma só ferramenta a sua folha de pagamento
X34: http://luz.vc/ferramentas/planilhas-integradas/planilha-de-fluxo-de-caixa-com-controle-orcamentario/?utm_source=referral&utm_medium=produtos&utm_campaign=eve3

Sheet Sobre a LUZ
C1: SOBRE A VALOR
