Workbook

Sheet Ini
C1: PLANILHA DE CÁLCULO DE
C2: HORAS EXTRAS 3.5
C3: Seja bem-vindo(a). Com esta planilha você poderá analisar toda a folha de ponto do se funcionário. Invista suas energias em idéias que você sabe que serão viáveis!
C4: IMPORTANTE: LEIA OS PASSOS E ENTENDA A PLANILHA
C6: Passo 1 | E6: PREMISSAS GERAIS
C7: Este é o começo de tudo. É a parte de definição de todas as premissas de decadastro e perfis do funcionário.Contribui com todas bases de cálculo usadas adiante.
C9: Passo 2 | E9: LANÇAMENTOS
C10: Os Lançamentos são os locais onde você vai preencher o dia a dia do seu funcionário durante o mês.
C12: Passo 3 | E12: RESULTADOS CONSOLIDADOS
C13: A hora de retirar um relátório conciso e direto sobre os dados lançados. Nos resultados consolidados você têm um panorama de todo o mês. Uma indispensável ferramenta para tomada de decisões.
C15: Passo 4 | E15: GRÁFICOS
C16: Os gráficos são importantes para que sejam feitas avaliações sobre a situação do seu funcionário de uma forma simples e mais visual. Você poderá ver os gráficos de cada tipo de hora extra de maneira separada. Além de outras análises.
C18: Passo 5 | E18: ALERTAS E DICAS
C19: Esta planilha avaliará todos os dados preenchidos por você e retornará com dicas importantes para o seu segmento. Avaliando seu dia a dia, será mais fácil identificar se está fluindo da maneira correta, isso servirá para alertá-lo sobre possíveis problemas.
C21: Passo 6 | E21: RELATÓRIO PARA IMPRESSÃO
C22: Imprima somente o que importa. Esta parte gera um relatório formatado para impressão em páginas tamanho A4 com seu relatório e o panorama geral. Acompanha gráficos e as dicas importantes que a planilha fornece.
C24: Passo 7 | E24: FOLHA DE PONTO
C25: Imprima a folha de ponto mensal dos seus funcionários de maneira prática e econômica com apenas um clique. É rápido, é simples e é tudo que você precisava para adiantar seu dia a dia.

Sheet P Gerais
C1: 1. PREMISSAS GERAIS
C5: Configuração do período da planilha
C6: Ano corrente | I6: Mês corrente
C8: Salário mínimo vigente para esta categoria de funcionários
C9: Modelo de pagamento das horas extras
C10: Essas horas extras estão sendo pagas ou fará banco de horas?
C12: Acréscimo por cada hora extra (%)
C13: Dia de Semana | E13: Sábado | F13: Domingo | H13: DSR | I13: Feriados | K13: Periculosidade | L13: Insalubridade
C14: 0.5 | E14: 0.5 | F14: 1 | H14: 1 | I14: 1 | K14: 0.3 | L14: 1
C16: Interjornada (Iniciada antes das 11 horas de descanso) | I16: Intrajornada (Trabalho na hora de descanso/almoço)
C17: 1 | I17: 0.5
C19: Descrição dos funcionários

Sheet Departamentos
A1: 3.0.1 | C1: 1. PREMISSAS GERAIS
C5: Cadastro de departamentos

Sheet Funcionários
A1: 3.0.1 | C1: 1. PREMISSAS GERAIS
C5: Cadastro de funcionários | L5: Menu
C6: Funcionário | D6: Área | E6: Salário | F6: insalubridade | G6: periculosidade | L6: =IF(Departamentos!C6=0,"",Departamentos!C6)
F7: =IF(ISERROR(VLOOKUP($C7,Jornada!$C$8:$E$37,2,FALSE)),"",VLOOKUP($C7,Jornada!$C$8:$E$37,2,FALSE)) | G7: =IF(ISERROR(VLOOKUP($C7,Jornada!$C$8:$E$37,3,FALSE)),"",VLOOKUP($C7,Jornada!$C$8:$E$37,3,FALSE)) | H7: =IF(F7="Sim",E7*'P Gerais'!$L$14,0)+IF(G7="Sim",E7*'P Gerais'!$K$14,0) -> 0 | I7: =E7+H7 -> 0 | L7: =IF(Departamentos!C7=0,"",Departamentos!C7)
F8: =IF(ISERROR(VLOOKUP($C8,Jornada!$C$8:$E$37,2,FALSE)),"",VLOOKUP($C8,Jornada!$C$8:$E$37,2,FALSE)) | G8: =IF(ISERROR(VLOOKUP($C8,Jornada!$C$8:$E$37,3,FALSE)),"",VLOOKUP($C8,Jornada!$C$8:$E$37,3,FALSE)) | H8: =IF(F8="Sim",E8*'P Gerais'!$L$14,0)+IF(G8="Sim",E8*'P Gerais'!$K$14,0) -> 0 | I8: =E8+H8 -> 0 | L8: =IF(Departamentos!C8=0,"",Departamentos!C8)
F9: =IF(ISERROR(VLOOKUP($C9,Jornada!$C$8:$E$37,2,FALSE)),"",VLOOKUP($C9,Jornada!$C$8:$E$37,2,FALSE)) | G9: =IF(ISERROR(VLOOKUP($C9,Jornada!$C$8:$E$37,3,FALSE)),"",VLOOKUP($C9,Jornada!$C$8:$E$37,3,FALSE)) | H9: =IF(F9="Sim",E9*'P Gerais'!$L$14,0)+IF(G9="Sim",E9*'P Gerais'!$K$14,0) -> 0 | I9: =E9+H9 -> 0 | L9: =IF(Departamentos!C9=0,"",Departamentos!C9)
F10: =IF(ISERROR(VLOOKUP($C10,Jornada!$C$8:$E$37,2,FALSE)),"",VLOOKUP($C10,Jornada!$C$8:$E$37,2,FALSE)) | G10: =IF(ISERROR(VLOOKUP($C10,Jornada!$C$8:$E$37,3,FALSE)),"",VLOOKUP($C10,Jornada!$C$8:$E$37,3,FALSE)) | H10: =IF(F10="Sim",E10*'P Gerais'!$L$14,0)+IF(G10="Sim",E10*'P Gerais'!$K$14,0) -> 0 | I10: =E10+H10 -> 0 | L10: =IF(Departamentos!C10=0,"",Departamentos!C10)
F11: =IF(ISERROR(VLOOKUP($C11,Jornada!$C$8:$E$37,2,FALSE)),"",VLOOKUP($C11,Jornada!$C$8:$E$37,2,FALSE)) | G11: =IF(ISERROR(VLOOKUP($C11,Jornada!$C$8:$E$37,3,FALSE)),"",VLOOKUP($C11,Jornada!$C$8:$E$37,3,FALSE)) | H11: =IF(F11="Sim",E11*'P Gerais'!$L$14,0)+IF(G11="Sim",E11*'P Gerais'!$K$14,0) -> 0 | I11: =E11+H11 -> 0 | L11: =IF(Departamentos!C11=0,"",Departamentos!C11)
F12: =IF(ISERROR(VLOOKUP($C12,Jornada!$C$8:$E$37,2,FALSE)),"",VLOOKUP($C12,Jornada!$C$8:$E$37,2,FALSE)) | H12: =IF(F12="Sim",E12*'P Gerais'!$L$14,0)+IF(L13="Sim",E12*'P Gerais'!$K$14,0) -> 0 | I12: =E12+H12 -> 0 | L12: =IF(Departamentos!C12=0,"",Departamentos!C12)
F13: =IF(ISERROR(VLOOKUP($C13,Jornada!$C$8:$E$37,2,FALSE)),"",VLOOKUP($C13,Jornada!$C$8:$E$37,2,FALSE)) | H13: =IF(F13="Sim",E13*'P Gerais'!$L$14,0)+IF(L14="Sim",E13*'P Gerais'!$K$14,0) -> 0 | I13: =E13+H13 -> 0 | L13: =IF(Departamentos!C13=0,"",Departamentos!C13)
F14: =IF(ISERROR(VLOOKUP($C14,Jornada!$C$8:$E$37,2,FALSE)),"",VLOOKUP($C14,Jornada!$C$8:$E$37,2,FALSE)) | H14: =IF(F14="Sim",E14*'P Gerais'!$L$14,0)+IF(L15="Sim",E14*'P Gerais'!$K$14,0) -> 0 | I14: =E14+H14 -> 0 | L14: =IF(Departamentos!C14=0,"",Departamentos!C14)
F15: =IF(ISERROR(VLOOKUP($C15,Jornada!$C$8:$E$37,2,FALSE)),"",VLOOKUP($C15,Jornada!$C$8:$E$37,2,FALSE)) | H15: =IF(F15="Sim",E15*'P Gerais'!$L$14,0)+IF(L16="Sim",E15*'P Gerais'!$K$14,0) -> 0 | I15: =E15+H15 -> 0
F16: =IF(ISERROR(VLOOKUP($C16,Jornada!$C$8:$E$37,2,FALSE)),"",VLOOKUP($C16,Jornada!$C$8:$E$37,2,FALSE)) | H16: =IF(F16="Sim",E16*'P Gerais'!$L$14,0)+IF(L17="Sim",E16*'P Gerais'!$K$14,0) -> 0 | I16: =E16+H16 -> 0
F17: =IF(ISERROR(VLOOKUP($C17,Jornada!$C$8:$E$37,2,FALSE)),"",VLOOKUP($C17,Jornada!$C$8:$E$37,2,FALSE)) | H17: =IF(F17="Sim",E17*'P Gerais'!$L$14,0)+IF(L18="Sim",E17*'P Gerais'!$K$14,0) -> 0 | I17: =E17+H17 -> 0
F18: =IF(ISERROR(VLOOKUP($C18,Jornada!$C$8:$E$37,2,FALSE)),"",VLOOKUP($C18,Jornada!$C$8:$E$37,2,FALSE)) | H18: =IF(F18="Sim",E18*'P Gerais'!$L$14,0)+IF(L19="Sim",E18*'P Gerais'!$K$14,0) -> 0 | I18: =E18+H18 -> 0
F19: =IF(ISERROR(VLOOKUP($C19,Jornada!$C$8:$E$37,2,FALSE)),"",VLOOKUP($C19,Jornada!$C$8:$E$37,2,FALSE)) | H19: =IF(F19="Sim",E19*'P Gerais'!$L$14,0)+IF(L20="Sim",E19*'P Gerais'!$K$14,0) -> 0 | I19: =E19+H19 -> 0
F20: =IF(ISERROR(VLOOKUP($C20,Jornada!$C$8:$E$37,2,FALSE)),"",VLOOKUP($C20,Jornada!$C$8:$E$37,2,FALSE)) | H20: =IF(F20="Sim",E20*'P Gerais'!$L$14,0)+IF(L21="Sim",E20*'P Gerais'!$K$14,0) -> 0 | I20: =E20+H20 -> 0
F21: =IF(ISERROR(VLOOKUP($C21,Jornada!$C$8:$E$37,2,FALSE)),"",VLOOKUP($C21,Jornada!$C$8:$E$37,2,FALSE)) | H21: =IF(F21="Sim",E21*'P Gerais'!$L$14,0)+IF(L22="Sim",E21*'P Gerais'!$K$14,0) -> 0 | I21: =E21+H21 -> 0
F22: =IF(ISERROR(VLOOKUP($C22,Jornada!$C$8:$E$37,2,FALSE)),"",VLOOKUP($C22,Jornada!$C$8:$E$37,2,FALSE)) | H22: =IF(F22="Sim",E22*'P Gerais'!$L$14,0)+IF(L23="Sim",E22*'P Gerais'!$K$14,0) -> 0 | I22: =E22+H22 -> 0
F23: =IF(ISERROR(VLOOKUP($C23,Jornada!$C$8:$E$37,2,FALSE)),"",VLOOKUP($C23,Jornada!$C$8:$E$37,2,FALSE)) | H23: =IF(F23="Sim",E23*'P Gerais'!$L$14,0)+IF(L24="Sim",E23*'P Gerais'!$K$14,0) -> 0 | I23: =E23+H23 -> 0
F24: =IF(ISERROR(VLOOKUP($C24,Jornada!$C$8:$E$37,2,FALSE)),"",VLOOKUP($C24,Jornada!$C$8:$E$37,2,FALSE)) | H24: =IF(F24="Sim",E24*'P Gerais'!$L$14,0)+IF(L25="Sim",E24*'P Gerais'!$K$14,0) -> 0 | I24: =E24+H24 -> 0
F25: =IF(ISERROR(VLOOKUP($C25,Jornada!$C$8:$E$37,2,FALSE)),"",VLOOKUP($C25,Jornada!$C$8:$E$37,2,FALSE)) | H25: =IF(F25="Sim",E25*'P Gerais'!$L$14,0)+IF(L26="Sim",E25*'P Gerais'!$K$14,0) -> 0 | I25: =E25+H25 -> 0
F26: =IF(ISERROR(VLOOKUP($C26,Jornada!$C$8:$E$37,2,FALSE)),"",VLOOKUP($C26,Jornada!$C$8:$E$37,2,FALSE)) | H26: =IF(F26="Sim",E26*'P Gerais'!$L$14,0)+IF(L27="Sim",E26*'P Gerais'!$K$14,0) -> 0 | I26: =E26+H26 -> 0
... F36: =IF(ISERROR(VLOOKUP($C36,Jornada!$C$8:$E$37,2,FALSE)),"",VLOOKUP($C36,Jornada!$C$8:$E$37,2,FALSE)) | H36: =IF(F36="Sim",E36*'P Gerais'!$L$14,0)+IF(L37="Sim",E36*'P Gerais'!$K$14,0) -> 0 | I36: =E36+H36 -> 0

Sheet Jornada
C1: 1. PREMISSAS GERAIS
J4: Seg | L4: Ter | N4: Qua | P4: Qui | R4: Sex | T4: Sáb | V4: Dom
I5: Seg | K5: Ter | M5: Qua | O5: Qui | Q5: Sex | S5: Sáb | U5: Dom
I6: Segunda | K6: Terça | M6: Quarta | O6: Quinta | Q6: Sexta | S6: Sábado | U6: Domingo | X6: 0.25 | Z6: Jornada de trabalho | AN6: JORNADA
C7: Funcionário | D7: Insalubridade | E7: Periculosidade | F7: Horas acumuladas no banco de horas | G7: Extras ou Devidas | H7: Tempo de intervalo diário | I7: Início | J7: Fim | K7: Início | L7: Fim | M7: Início | N7: Fim | O7: Início | P7: Fim | Q7: Início | R7: Fim | S7: Início | T7: Fim | U7: Início | V7: Fim | X7: Seg | Y7: Ter | Z7: Qua | AA7: Qui | AB7: Sex | AC7: Sáb | AD7: Dom | AE7: Semanal | AF7: Mensal | AJ7: 0.25 | AK7: 0.625 | AN7: Seg | AO7: Ter | AP7: Qua | AQ7: Qui | AR7: Sex | AS7: Sáb | AT7: Dom
C8: =IF(Funcionários!C7=0,"",Funcionários!C7) | W8: 2 | X8: =IF(I8-J8=0,0,IF(I8>J8,"-",J8-I8-$H8)) -> 0 | Y8: =IF(K8-L8=0,0,IF(K8>L8,"-",L8-K8-$H8)) -> 0 | Z8: =IF(M8-N8=0,0,IF(M8>N8,"-",N8-M8-$H8)) -> 0 | AA8: =IF(O8-P8=0,0,IF(O8>P8,"-",P8-O8-$H8)) -> 0 | AB8: =IF(Q8-R8=0,0,IF(Q8>R8,"-",R8-Q8-$H8)) -> 0 | AC8: =IF(S8-T8=0,0,IF(S8>T8,"-",T8-S8-$H8)) -> 0 | AD8: =IF(U8-V8=0,0,IF(U8>V8,"-",V8-U8-$H8)) -> 0 | AE8: =ROUNDUP(24*(SUM(X8:AD8)),0) -> 0 | AF8: =AE8*5 -> 0 | AG8: =IF(C8="","",VLOOKUP(C8,Funcionários!$C$7:$D$36,2,0)) | AJ8: 0.29166667 | AK8: 0.66666667 | AN8: =IF(I8-J8=0,"",IF(I8>J8,"Erro","Ok")) | AO8: =IF(K8-L8=0,"",IF(K8>L8,"Erro","Ok")) | AP8: =IF(M8-N8=0,"",IF(M8>N8,"Erro","Ok")) | AQ8: =IF(O8-P8=0,"",IF(O8>P8,"Erro","Ok")) | AR8: =IF(Q8-R8=0,"",IF(Q8>R8,"Erro","Ok")) | AS8: =IF(S8-T8=0,"",IF(S8>T8,"Erro","Ok")) | AT8: =IF(U8-V8=0,"",IF(U8>V8,"Erro","Ok"))
C9: =IF(Funcionários!C8=0,"",Funcionários!C8) | W9: 3 | X9: =IF(I9-J9=0,0,IF(I9>J9,"-",J9-I9-$H9)) -> 0 | Y9: =IF(K9-L9=0,0,IF(K9>L9,"-",L9-K9-$H9)) -> 0 | Z9: =IF(M9-N9=0,0,IF(M9>N9,"-",N9-M9-$H9)) -> 0 | AA9: =IF(O9-P9=0,0,IF(O9>P9,"-",P9-O9-$H9)) -> 0 | AB9: =IF(Q9-R9=0,0,IF(Q9>R9,"-",R9-Q9-$H9)) -> 0 | AC9: =IF(S9-T9=0,0,IF(S9>T9,"-",T9-S9-$H9)) -> 0 | AD9: =IF(U9-V9=0,0,IF(U9>V9,"-",V9-U9-$H9)) -> 0 | AE9: =ROUNDUP(24*(SUM(X9:AD9)),0) -> 0 | AF9: =AE9*5 -> 0 | AG9: =IF(C9="","",VLOOKUP(C9,Funcionários!$C$7:$D$36,2,0)) | AJ9: 0.33333333 | AK9: 0.70833333 | AN9: =IF(I9-J9=0,"",IF(I9>J9,"Erro","Ok")) | AO9: =IF(K9-L9=0,"",IF(K9>L9,"Erro","Ok")) | AP9: =IF(M9-N9=0,"",IF(M9>N9,"Erro","Ok")) | AQ9: =IF(O9-P9=0,"",IF(O9>P9,"Erro","Ok")) | AR9: =IF(Q9-R9=0,"",IF(Q9>R9,"Erro","Ok")) | AS9: =IF(S9-T9=0,"",IF(S9>T9,"Erro","Ok")) | AT9: =IF(U9-V9=0,"",IF(U9>V9,"Erro","Ok"))
C10: =IF(Funcionários!C9=0,"",Funcionários!C9) | W10: 4 | X10: =IF(I10-J10=0,0,IF(I10>J10,"-",J10-I10-$H10)) -> 0 | Y10: =IF(K10-L10=0,0,IF(K10>L10,"-",L10-K10-$H10)) -> 0 | Z10: =IF(M10-N10=0,0,IF(M10>N10,"-",N10-M10-$H10)) -> 0 | AA10: =IF(O10-P10=0,0,IF(O10>P10,"-",P10-O10-$H10)) -> 0 | AB10: =IF(Q10-R10=0,0,IF(Q10>R10,"-",R10-Q10-$H10)) -> 0 | AC10: =IF(S10-T10=0,0,IF(S10>T10,"-",T10-S10-$H10)) -> 0 | AD10: =IF(U10-V10=0,0,IF(U10>V10,"-",V10-U10-$H10)) -> 0 | AE10: =ROUNDUP(24*(SUM(X10:AD10)),0) -> 0 | AF10: =AE10*5 -> 0 | AG10: =IF(C10="","",VLOOKUP(C10,Funcionários!$C$7:$D$36,2,0)) | AJ10: 0.375 | AK10: 0.75 | AN10: =IF(I10-J10=0,"",IF(I10>J10,"Erro","Ok")) | AO10: =IF(K10-L10=0,"",IF(K10>L10,"Erro","Ok")) | AP10: =IF(M10-N10=0,"",IF(M10>N10,"Erro","Ok")) | AQ10: =IF(O10-P10=0,"",IF(O10>P10,"Erro","Ok")) | AR10: =IF(Q10-R10=0,"",IF(Q10>R10,"Erro","Ok")) | AS10: =IF(S10-T10=0,"",IF(S10>T10,"Erro","Ok")) | AT10: =IF(U10-V10=0,"",IF(U10>V10,"Erro","Ok"))
C11: =IF(Funcionários!C10=0,"",Funcionários!C10) | W11: 5 | X11: =IF(I11-J11=0,0,IF(I11>J11,"-",J11-I11-$H11)) -> 0 | Y11: =IF(K11-L11=0,0,IF(K11>L11,"-",L11-K11-$H11)) -> 0 | Z11: =IF(M11-N11=0,0,IF(M11>N11,"-",N11-M11-$H11)) -> 0 | AA11: =IF(O11-P11=0,0,IF(O11>P11,"-",P11-O11-$H11)) -> 0 | AB11: =IF(Q11-R11=0,0,IF(Q11>R11,"-",R11-Q11-$H11)) -> 0 | AC11: =IF(S11-T11=0,0,IF(S11>T11,"-",T11-S11-$H11)) -> 0 | AD11: =IF(U11-V11=0,0,IF(U11>V11,"-",V11-U11-$H11)) -> 0 | AE11: =ROUNDUP(24*(SUM(X11:AD11)),0) -> 0 | AF11: =AE11*5 -> 0 | AG11: =IF(C11="","",VLOOKUP(C11,Funcionários!$C$7:$D$36,2,0)) | AJ11: 0.41666667 | AN11: =IF(I11-J11=0,"",IF(I11>J11,"Erro","Ok")) | AO11: =IF(K11-L11=0,"",IF(K11>L11,"Erro","Ok")) | AP11: =IF(M11-N11=0,"",IF(M11>N11,"Erro","Ok")) | AQ11: =IF(O11-P11=0,"",IF(O11>P11,"Erro","Ok")) | AR11: =IF(Q11-R11=0,"",IF(Q11>R11,"Erro","Ok")) | AS11: =IF(S11-T11=0,"",IF(S11>T11,"Erro","Ok")) | AT11: =IF(U11-V11=0,"",IF(U11>V11,"Erro","Ok"))
C12: =IF(Funcionários!C11=0,"",Funcionários!C11) | W12: 6 | X12: =IF(I12-J12=0,0,IF(I12>J12,"-",J12-I12-$H12)) -> 0 | Y12: =IF(K12-L12=0,0,IF(K12>L12,"-",L12-K12-$H12)) -> 0 | Z12: =IF(M12-N12=0,0,IF(M12>N12,"-",N12-M12-$H12)) -> 0 | AA12: =IF(O12-P12=0,0,IF(O12>P12,"-",P12-O12-$H12)) -> 0 | AB12: =IF(Q12-R12=0,0,IF(Q12>R12,"-",R12-Q12-$H12)) -> 0 | AC12: =IF(S12-T12=0,0,IF(S12>T12,"-",T12-S12-$H12)) -> 0 | AD12: =IF(U12-V12=0,0,IF(U12>V12,"-",V12-U12-$H12)) -> 0 | AE12: =ROUNDUP(24*(SUM(X12:AD12)),0) -> 0 | AF12: =AE12*5 -> 0 | AG12: =IF(C12="","",VLOOKUP(C12,Funcionários!$C$7:$D$36,2,0)) | AJ12: 0.45833333 | AN12: =IF(I12-J12=0,"",IF(I12>J12,"Erro","Ok")) | AO12: =IF(K12-L12=0,"",IF(K12>L12,"Erro","Ok")) | AP12: =IF(M12-N12=0,"",IF(M12>N12,"Erro","Ok")) | AQ12: =IF(O12-P12=0,"",IF(O12>P12,"Erro","Ok")) | AR12: =IF(Q12-R12=0,"",IF(Q12>R12,"Erro","Ok")) | AS12: =IF(S12-T12=0,"",IF(S12>T12,"Erro","Ok")) | AT12: =IF(U12-V12=0,"",IF(U12>V12,"Erro","Ok"))
C13: =IF(Funcionários!C12=0,"",Funcionários!C12) | W13: 7 | X13: =IF(I13-J13=0,0,IF(I13>J13,"-",J13-I13-$H13)) -> 0 | Y13: =IF(K13-L13=0,0,IF(K13>L13,"-",L13-K13-$H13)) -> 0 | Z13: =IF(M13-N13=0,0,IF(M13>N13,"-",N13-M13-$H13)) -> 0 | AA13: =IF(O13-P13=0,0,IF(O13>P13,"-",P13-O13-$H13)) -> 0 | AB13: =IF(Q13-R13=0,0,IF(Q13>R13,"-",R13-Q13-$H13)) -> 0 | AC13: =IF(S13-T13=0,0,IF(S13>T13,"-",T13-S13-$H13)) -> 0 | AD13: =IF(U13-V13=0,0,IF(U13>V13,"-",V13-U13-$H13)) -> 0 | AE13: =ROUNDUP(24*(SUM(X13:AD13)),0) -> 0 | AF13: =AE13*5 -> 0 | AG13: =IF(C13="","",VLOOKUP(C13,Funcionários!$C$7:$D$36,2,0)) | AJ13: 0.5 | AN13: =IF(I13-J13=0,"",IF(I13>J13,"Erro","Ok")) | AO13: =IF(K13-L13=0,"",IF(K13>L13,"Erro","Ok")) | AP13: =IF(M13-N13=0,"",IF(M13>N13,"Erro","Ok")) | AQ13: =IF(O13-P13=0,"",IF(O13>P13,"Erro","Ok")) | AR13: =IF(Q13-R13=0,"",IF(Q13>R13,"Erro","Ok")) | AS13: =IF(S13-T13=0,"",IF(S13>T13,"Erro","Ok")) | AT13: =IF(U13-V13=0,"",IF(U13>V13,"Erro","Ok"))
C14: =IF(Funcionários!C13=0,"",Funcionários!C13) | W14: 8 | X14: =IF(I14-J14=0,0,IF(I14>J14,"-",J14-I14-$H14)) -> 0 | Y14: =IF(K14-L14=0,0,IF(K14>L14,"-",L14-K14-$H14)) -> 0 | Z14: =IF(M14-N14=0,0,IF(M14>N14,"-",N14-M14-$H14)) -> 0 | AA14: =IF(O14-P14=0,0,IF(O14>P14,"-",P14-O14-$H14)) -> 0 | AB14: =IF(Q14-R14=0,0,IF(Q14>R14,"-",R14-Q14-$H14)) -> 0 | AC14: =IF(S14-T14=0,0,IF(S14>T14,"-",T14-S14-$H14)) -> 0 | AD14: =IF(U14-V14=0,0,IF(U14>V14,"-",V14-U14-$H14)) -> 0 | AE14: =ROUNDUP(24*(SUM(X14:AD14)),0) -> 0 | AF14: =AE14*5 -> 0 | AG14: =IF(C14="","",VLOOKUP(C14,Funcionários!$C$7:$D$36,2,0)) | AN14: =IF(I14-J14=0,"",IF(I14>J14,"Erro","Ok")) | AO14: =IF(K14-L14=0,"",IF(K14>L14,"Erro","Ok")) | AP14: =IF(M14-N14=0,"",IF(M14>N14,"Erro","Ok")) | AQ14: =IF(O14-P14=0,"",IF(O14>P14,"Erro","Ok")) | AR14: =IF(Q14-R14=0,"",IF(Q14>R14,"Erro","Ok")) | AS14: =IF(S14-T14=0,"",IF(S14>T14,"Erro","Ok")) | AT14: =IF(U14-V14=0,"",IF(U14>V14,"Erro","Ok"))
C15: =IF(Funcionários!C14=0,"",Funcionários!C14) | W15: 9 | X15: =IF(I15-J15=0,0,IF(I15>J15,"-",J15-I15-$H15)) -> 0 | Y15: =IF(K15-L15=0,0,IF(K15>L15,"-",L15-K15-$H15)) -> 0 | Z15: =IF(M15-N15=0,0,IF(M15>N15,"-",N15-M15-$H15)) -> 0 | AA15: =IF(O15-P15=0,0,IF(O15>P15,"-",P15-O15-$H15)) -> 0 | AB15: =IF(Q15-R15=0,0,IF(Q15>R15,"-",R15-Q15-$H15)) -> 0 | AC15: =IF(S15-T15=0,0,IF(S15>T15,"-",T15-S15-$H15)) -> 0 | AD15: =IF(U15-V15=0,0,IF(U15>V15,"-",V15-U15-$H15)) -> 0 | AE15: =ROUNDUP(24*(SUM(X15:AD15)),0) -> 0 | AF15: =AE15*5 -> 0 | AG15: =IF(C15="","",VLOOKUP(C15,Funcionários!$C$7:$D$36,2,0)) | AN15: =IF(I15-J15=0,"",IF(I15>J15,"Erro","Ok")) | AO15: =IF(K15-L15=0,"",IF(K15>L15,"Erro","Ok")) | AP15: =IF(M15-N15=0,"",IF(M15>N15,"Erro","Ok")) | AQ15: =IF(O15-P15=0,"",IF(O15>P15,"Erro","Ok")) | AR15: =IF(Q15-R15=0,"",IF(Q15>R15,"Erro","Ok")) | AS15: =IF(S15-T15=0,"",IF(S15>T15,"Erro","Ok")) | AT15: =IF(U15-V15=0,"",IF(U15>V15,"Erro","Ok"))
C16: =IF(Funcionários!C15=0,"",Funcionários!C15) | W16: 10 | X16: =IF(I16-J16=0,0,IF(I16>J16,"-",J16-I16-$H16)) -> 0 | Y16: =IF(K16-L16=0,0,IF(K16>L16,"-",L16-K16-$H16)) -> 0 | Z16: =IF(M16-N16=0,0,IF(M16>N16,"-",N16-M16-$H16)) -> 0 | AA16: =IF(O16-P16=0,0,IF(O16>P16,"-",P16-O16-$H16)) -> 0 | AB16: =IF(Q16-R16=0,0,IF(Q16>R16,"-",R16-Q16-$H16)) -> 0 | AC16: =IF(S16-T16=0,0,IF(S16>T16,"-",T16-S16-$H16)) -> 0 | AD16: =IF(U16-V16=0,0,IF(U16>V16,"-",V16-U16-$H16)) -> 0 | AE16: =ROUNDUP(24*(SUM(X16:AD16)),0) -> 0 | AF16: =AE16*5 -> 0 | AG16: =IF(C16="","",VLOOKUP(C16,Funcionários!$C$7:$D$36,2,0)) | AN16: =IF(I16-J16=0,"",IF(I16>J16,"Erro","Ok")) | AO16: =IF(K16-L16=0,"",IF(K16>L16,"Erro","Ok")) | AP16: =IF(M16-N16=0,"",IF(M16>N16,"Erro","Ok")) | AQ16: =IF(O16-P16=0,"",IF(O16>P16,"Erro","Ok")) | AR16: =IF(Q16-R16=0,"",IF(Q16>R16,"Erro","Ok")) | AS16: =IF(S16-T16=0,"",IF(S16>T16,"Erro","Ok")) | AT16: =IF(U16-V16=0,"",IF(U16>V16,"Erro","Ok"))
C17: =IF(Funcionários!C16=0,"",Funcionários!C16) | W17: 11 | X17: =IF(I17-J17=0,0,IF(I17>J17,"-",J17-I17-$H17)) -> 0 | Y17: =IF(K17-L17=0,0,IF(K17>L17,"-",L17-K17-$H17)) -> 0 | Z17: =IF(M17-N17=0,0,IF(M17>N17,"-",N17-M17-$H17)) -> 0 | AA17: =IF(O17-P17=0,0,IF(O17>P17,"-",P17-O17-$H17)) -> 0 | AB17: =IF(Q17-R17=0,0,IF(Q17>R17,"-",R17-Q17-$H17)) -> 0 | AC17: =IF(S17-T17=0,0,IF(S17>T17,"-",T17-S17-$H17)) -> 0 | AD17: =IF(U17-V17=0,0,IF(U17>V17,"-",V17-U17-$H17)) -> 0 | AE17: =ROUNDUP(24*(SUM(X17:AD17)),0) -> 0 | AF17: =AE17*5 -> 0 | AG17: =IF(C17="","",VLOOKUP(C17,Funcionários!$C$7:$D$36,2,0)) | AN17: =IF(I17-J17=0,"",IF(I17>J17,"Erro","Ok")) | AO17: =IF(K17-L17=0,"",IF(K17>L17,"Erro","Ok")) | AP17: =IF(M17-N17=0,"",IF(M17>N17,"Erro","Ok")) | AQ17: =IF(O17-P17=0,"",IF(O17>P17,"Erro","Ok")) | AR17: =IF(Q17-R17=0,"",IF(Q17>R17,"Erro","Ok")) | AS17: =IF(S17-T17=0,"",IF(S17>T17,"Erro","Ok")) | AT17: =IF(U17-V17=0,"",IF(U17>V17,"Erro","Ok"))
C18: =IF(Funcionários!C17=0,"",Funcionários!C17) | W18: 12 | X18: =IF(I18-J18=0,0,IF(I18>J18,"-",J18-I18-$H18)) -> 0 | Y18: =IF(K18-L18=0,0,IF(K18>L18,"-",L18-K18-$H18)) -> 0 | Z18: =IF(M18-N18=0,0,IF(M18>N18,"-",N18-M18-$H18)) -> 0 | AA18: =IF(O18-P18=0,0,IF(O18>P18,"-",P18-O18-$H18)) -> 0 | AB18: =IF(Q18-R18=0,0,IF(Q18>R18,"-",R18-Q18-$H18)) -> 0 | AC18: =IF(S18-T18=0,0,IF(S18>T18,"-",T18-S18-$H18)) -> 0 | AD18: =IF(U18-V18=0,0,IF(U18>V18,"-",V18-U18-$H18)) -> 0 | AE18: =ROUNDUP(24*(SUM(X18:AD18)),0) -> 0 | AF18: =AE18*5 -> 0 | AG18: =IF(C18="","",VLOOKUP(C18,Funcionários!$C$7:$D$36,2,0)) | AN18: =IF(I18-J18=0,"",IF(I18>J18,"Erro","Ok")) | AO18: =IF(K18-L18=0,"",IF(K18>L18,"Erro","Ok")) | AP18: =IF(M18-N18=0,"",IF(M18>N18,"Erro","Ok")) | AQ18: =IF(O18-P18=0,"",IF(O18>P18,"Erro","Ok")) | AR18: =IF(Q18-R18=0,"",IF(Q18>R18,"Erro","Ok")) | AS18: =IF(S18-T18=0,"",IF(S18>T18,"Erro","Ok")) | AT18: =IF(U18-V18=0,"",IF(U18>V18,"Erro","Ok"))
C19: =IF(Funcionários!C18=0,"",Funcionários!C18) | W19: 13 | X19: =IF(I19-J19=0,0,IF(I19>J19,"-",J19-I19-$H19)) -> 0 | Y19: =IF(K19-L19=0,0,IF(K19>L19,"-",L19-K19-$H19)) -> 0 | Z19: =IF(M19-N19=0,0,IF(M19>N19,"-",N19-M19-$H19)) -> 0 | AA19: =IF(O19-P19=0,0,IF(O19>P19,"-",P19-O19-$H19)) -> 0 | AB19: =IF(Q19-R19=0,0,IF(Q19>R19,"-",R19-Q19-$H19)) -> 0 | AC19: =IF(S19-T19=0,0,IF(S19>T19,"-",T19-S19-$H19)) -> 0 | AD19: =IF(U19-V19=0,0,IF(U19>V19,"-",V19-U19-$H19)) -> 0 | AE19: =ROUNDUP(24*(SUM(X19:AD19)),0) -> 0 | AF19: =AE19*5 -> 0 | AG19: =IF(C19="","",VLOOKUP(C19,Funcionários!$C$7:$D$36,2,0)) | AN19: =IF(I19-J19=0,"",IF(I19>J19,"Erro","Ok")) | AO19: =IF(K19-L19=0,"",IF(K19>L19,"Erro","Ok")) | AP19: =IF(M19-N19=0,"",IF(M19>N19,"Erro","Ok")) | AQ19: =IF(O19-P19=0,"",IF(O19>P19,"Erro","Ok")) | AR19: =IF(Q19-R19=0,"",IF(Q19>R19,"Erro","Ok")) | AS19: =IF(S19-T19=0,"",IF(S19>T19,"Erro","Ok")) | AT19: =IF(U19-V19=0,"",IF(U19>V19,"Erro","Ok"))
C20: =IF(Funcionários!C19=0,"",Funcionários!C19) | W20: 14 | X20: =IF(I20-J20=0,0,IF(I20>J20,"-",J20-I20-$H20)) -> 0 | Y20: =IF(K20-L20=0,0,IF(K20>L20,"-",L20-K20-$H20)) -> 0 | Z20: =IF(M20-N20=0,0,IF(M20>N20,"-",N20-M20-$H20)) -> 0 | AA20: =IF(O20-P20=0,0,IF(O20>P20,"-",P20-O20-$H20)) -> 0 | AB20: =IF(Q20-R20=0,0,IF(Q20>R20,"-",R20-Q20-$H20)) -> 0 | AC20: =IF(S20-T20=0,0,IF(S20>T20,"-",T20-S20-$H20)) -> 0 | AD20: =IF(U20-V20=0,0,IF(U20>V20,"-",V20-U20-$H20)) -> 0 | AE20: =ROUNDUP(24*(SUM(X20:AD20)),0) -> 0 | AF20: =AE20*5 -> 0 | AG20: =IF(C20="","",VLOOKUP(C20,Funcionários!$C$7:$D$36,2,0)) | AN20: =IF(I20-J20=0,"",IF(I20>J20,"Erro","Ok")) | AO20: =IF(K20-L20=0,"",IF(K20>L20,"Erro","Ok")) | AP20: =IF(M20-N20=0,"",IF(M20>N20,"Erro","Ok")) | AQ20: =IF(O20-P20=0,"",IF(O20>P20,"Erro","Ok")) | AR20: =IF(Q20-R20=0,"",IF(Q20>R20,"Erro","Ok")) | AS20: =IF(S20-T20=0,"",IF(S20>T20,"Erro","Ok")) | AT20: =IF(U20-V20=0,"",IF(U20>V20,"Erro","Ok"))
C21: =IF(Funcionários!C20=0,"",Funcionários!C20) | W21: 15 | X21: =IF(I21-J21=0,0,IF(I21>J21,"-",J21-I21-$H21)) -> 0 | Y21: =IF(K21-L21=0,0,IF(K21>L21,"-",L21-K21-$H21)) -> 0 | Z21: =IF(M21-N21=0,0,IF(M21>N21,"-",N21-M21-$H21)) -> 0 | AA21: =IF(O21-P21=0,0,IF(O21>P21,"-",P21-O21-$H21)) -> 0 | AB21: =IF(Q21-R21=0,0,IF(Q21>R21,"-",R21-Q21-$H21)) -> 0 | AC21: =IF(S21-T21=0,0,IF(S21>T21,"-",T21-S21-$H21)) -> 0 | AD21: =IF(U21-V21=0,0,IF(U21>V21,"-",V21-U21-$H21)) -> 0 | AE21: =ROUNDUP(24*(SUM(X21:AD21)),0) -> 0 | AF21: =AE21*5 -> 0 | AG21: =IF(C21="","",VLOOKUP(C21,Funcionários!$C$7:$D$36,2,0)) | AN21: =IF(I21-J21=0,"",IF(I21>J21,"Erro","Ok")) | AO21: =IF(K21-L21=0,"",IF(K21>L21,"Erro","Ok")) | AP21: =IF(M21-N21=0,"",IF(M21>N21,"Erro","Ok")) | AQ21: =IF(O21-P21=0,"",IF(O21>P21,"Erro","Ok")) | AR21: =IF(Q21-R21=0,"",IF(Q21>R21,"Erro","Ok")) | AS21: =IF(S21-T21=0,"",IF(S21>T21,"Erro","Ok")) | AT21: =IF(U21-V21=0,"",IF(U21>V21,"Erro","Ok"))
C22: =IF(Funcionários!C21=0,"",Funcionários!C21) | W22: 16 | X22: =IF(I22-J22=0,0,IF(I22>J22,"-",J22-I22-$H22)) -> 0 | Y22: =IF(K22-L22=0,0,IF(K22>L22,"-",L22-K22-$H22)) -> 0 | Z22: =IF(M22-N22=0,0,IF(M22>N22,"-",N22-M22-$H22)) -> 0 | AA22: =IF(O22-P22=0,0,IF(O22>P22,"-",P22-O22-$H22)) -> 0 | AB22: =IF(Q22-R22=0,0,IF(Q22>R22,"-",R22-Q22-$H22)) -> 0 | AC22: =IF(S22-T22=0,0,IF(S22>T22,"-",T22-S22-$H22)) -> 0 | AD22: =IF(U22-V22=0,0,IF(U22>V22,"-",V22-U22-$H22)) -> 0 | AE22: =ROUNDUP(24*(SUM(X22:AD22)),0) -> 0 | AF22: =AE22*5 -> 0 | AG22: =IF(C22="","",VLOOKUP(C22,Funcionários!$C$7:$D$36,2,0)) | AN22: =IF(I22-J22=0,"",IF(I22>J22,"Erro","Ok")) | AO22: =IF(K22-L22=0,"",IF(K22>L22,"Erro","Ok")) | AP22: =IF(M22-N22=0,"",IF(M22>N22,"Erro","Ok")) | AQ22: =IF(O22-P22=0,"",IF(O22>P22,"Erro","Ok")) | AR22: =IF(Q22-R22=0,"",IF(Q22>R22,"Erro","Ok")) | AS22: =IF(S22-T22=0,"",IF(S22>T22,"Erro","Ok")) | AT22: =IF(U22-V22=0,"",IF(U22>V22,"Erro","Ok"))
C23: =IF(Funcionários!C22=0,"",Funcionários!C22) | W23: 17 | X23: =IF(I23-J23=0,0,IF(I23>J23,"-",J23-I23-$H23)) -> 0 | Y23: =IF(K23-L23=0,0,IF(K23>L23,"-",L23-K23-$H23)) -> 0 | Z23: =IF(M23-N23=0,0,IF(M23>N23,"-",N23-M23-$H23)) -> 0 | AA23: =IF(O23-P23=0,0,IF(O23>P23,"-",P23-O23-$H23)) -> 0 | AB23: =IF(Q23-R23=0,0,IF(Q23>R23,"-",R23-Q23-$H23)) -> 0 | AC23: =IF(S23-T23=0,0,IF(S23>T23,"-",T23-S23-$H23)) -> 0 | AD23: =IF(U23-V23=0,0,IF(U23>V23,"-",V23-U23-$H23)) -> 0 | AE23: =ROUNDUP(24*(SUM(X23:AD23)),0) -> 0 | AF23: =AE23*5 -> 0 | AG23: =IF(C23="","",VLOOKUP(C23,Funcionários!$C$7:$D$36,2,0)) | AN23: =IF(I23-J23=0,"",IF(I23>J23,"Erro","Ok")) | AO23: =IF(K23-L23=0,"",IF(K23>L23,"Erro","Ok")) | AP23: =IF(M23-N23=0,"",IF(M23>N23,"Erro","Ok")) | AQ23: =IF(O23-P23=0,"",IF(O23>P23,"Erro","Ok")) | AR23: =IF(Q23-R23=0,"",IF(Q23>R23,"Erro","Ok")) | AS23: =IF(S23-T23=0,"",IF(S23>T23,"Erro","Ok")) | AT23: =IF(U23-V23=0,"",IF(U23>V23,"Erro","Ok"))
C24: =IF(Funcionários!C23=0,"",Funcionários!C23) | W24: 18 | X24: =IF(I24-J24=0,0,IF(I24>J24,"-",J24-I24-$H24)) -> 0 | Y24: =IF(K24-L24=0,0,IF(K24>L24,"-",L24-K24-$H24)) -> 0 | Z24: =IF(M24-N24=0,0,IF(M24>N24,"-",N24-M24-$H24)) -> 0 | AA24: =IF(O24-P24=0,0,IF(O24>P24,"-",P24-O24-$H24)) -> 0 | AB24: =IF(Q24-R24=0,0,IF(Q24>R24,"-",R24-Q24-$H24)) -> 0 | AC24: =IF(S24-T24=0,0,IF(S24>T24,"-",T24-S24-$H24)) -> 0 | AD24: =IF(U24-V24=0,0,IF(U24>V24,"-",V24-U24-$H24)) -> 0 | AE24: =ROUNDUP(24*(SUM(X24:AD24)),0) -> 0 | AF24: =AE24*5 -> 0 | AG24: =IF(C24="","",VLOOKUP(C24,Funcionários!$C$7:$D$36,2,0)) | AN24: =IF(I24-J24=0,"",IF(I24>J24,"Erro","Ok")) | AO24: =IF(K24-L24=0,"",IF(K24>L24,"Erro","Ok")) | AP24: =IF(M24-N24=0,"",IF(M24>N24,"Erro","Ok")) | AQ24: =IF(O24-P24=0,"",IF(O24>P24,"Erro","Ok")) | AR24: =IF(Q24-R24=0,"",IF(Q24>R24,"Erro","Ok")) | AS24: =IF(S24-T24=0,"",IF(S24>T24,"Erro","Ok")) | AT24: =IF(U24-V24=0,"",IF(U24>V24,"Erro","Ok"))
C25: =IF(Funcionários!C24=0,"",Funcionários!C24) | W25: 19 | X25: =IF(I25-J25=0,0,IF(I25>J25,"-",J25-I25-$H25)) -> 0 | Y25: =IF(K25-L25=0,0,IF(K25>L25,"-",L25-K25-$H25)) -> 0 | Z25: =IF(M25-N25=0,0,IF(M25>N25,"-",N25-M25-$H25)) -> 0 | AA25: =IF(O25-P25=0,0,IF(O25>P25,"-",P25-O25-$H25)) -> 0 | AB25: =IF(Q25-R25=0,0,IF(Q25>R25,"-",R25-Q25-$H25)) -> 0 | AC25: =IF(S25-T25=0,0,IF(S25>T25,"-",T25-S25-$H25)) -> 0 | AD25: =IF(U25-V25=0,0,IF(U25>V25,"-",V25-U25-$H25)) -> 0 | AE25: =ROUNDUP(24*(SUM(X25:AD25)),0) -> 0 | AF25: =AE25*5 -> 0 | AG25: =IF(C25="","",VLOOKUP(C25,Funcionários!$C$7:$D$36,2,0)) | AN25: =IF(I25-J25=0,"",IF(I25>J25,"Erro","Ok")) | AO25: =IF(K25-L25=0,"",IF(K25>L25,"Erro","Ok")) | AP25: =IF(M25-N25=0,"",IF(M25>N25,"Erro","Ok")) | AQ25: =IF(O25-P25=0,"",IF(O25>P25,"Erro","Ok")) | AR25: =IF(Q25-R25=0,"",IF(Q25>R25,"Erro","Ok")) | AS25: =IF(S25-T25=0,"",IF(S25>T25,"Erro","Ok")) | AT25: =IF(U25-V25=0,"",IF(U25>V25,"Erro","Ok"))
... C37: =IF(Funcionários!C36=0,"",Funcionários!C36) | W37: 31 | X37: =IF(I37-J37=0,0,IF(I37>J37,"-",J37-I37-$H37)) -> 0 | Y37: =IF(K37-L37=0,0,IF(K37>L37,"-",L37-K37-$H37)) -> 0 | Z37: =IF(M37-N37=0,0,IF(M37>N37,"-",N37-M37-$H37)) -> 0 | AA37: =IF(O37-P37=0,0,IF(O37>P37,"-",P37-O37-$H37)) -> 0 | AB37: =IF(Q37-R37=0,0,IF(Q37>R37,"-",R37-Q37-$H37)) -> 0 | AC37: =IF(S37-T37=0,0,IF(S37>T37,"-",T37-S37-$H37)) -> 0 | AD37: =IF(U37-V37=0,0,IF(U37>V37,"-",V37-U37-$H37)) -> 0 | AE37: =ROUNDUP(24*(SUM(X37:AD37)),0) -> 0 | AF37: =AE37*5 -> 0 | AG37: =IF(C37="","",VLOOKUP(C37,Funcionários!$C$7:$D$36,2,0)) | AN37: =IF(I37-J37=0,"",IF(I37>J37,"Erro","Ok")) | AO37: =IF(K37-L37=0,"",IF(K37>L37,"Erro","Ok")) | AP37: =IF(M37-N37=0,"",IF(M37>N37,"Erro","Ok")) | AQ37: =IF(O37-P37=0,"",IF(O37>P37,"Erro","Ok")) | AR37: =IF(Q37-R37=0,"",IF(Q37>R37,"Erro","Ok")) | AS37: =IF(S37-T37=0,"",IF(S37>T37,"Erro","Ok")) | AT37: =IF(U37-V37=0,"",IF(U37>V37,"Erro","Ok"))
I38: a | J38: a | K38: a | L38: a | M38: a | N38: a | O38: a | P38: a | Q38: a | R38: a | S38: a | T38: a | U38: a | V38: a | W38: a

Sheet Lanç
C1: 2. LANÇAMENTOS MENSAIS
C5: Lanç!$C$8 | K5: =IF(ISERROR(VLOOKUP(INDIRECT($C$5),Jornada!$C$8:$F$37,4,0)),0,VLOOKUP(INDIRECT($C$5),Jornada!$C$8:$F$37,4,0)) -> 0 | M5: =IF(ISERROR(VLOOKUP(INDIRECT($C$5),Jornada!$C$8:$G$37,5,0)),0,VLOOKUP(INDIRECT($C$5),Jornada!$C$8:$G$37,5,0)) -> 0 | AK5: 0.25 | AL5: 0.91666667 | AM5: 0.20833333 | AN5: 1 | AO5: 0.70833333
M6: 1
C7: Lista de funcionários | E7: =IF('P Gerais'!J6=0,"Janeiro",'P Gerais'!J6) -> Janeiro | G7: Classificação | H7: Início | I7: Intervalo | K7: Término | M7: Horas Dia | O7: Horas Devidas | Q7: Horas Extras | R7: 0.083333333 | S7: Resumo do Mês | W7: Janeiro | X7: 1 | AB7: =VLOOKUP($E$7,$W$7:$X$18,2,0) -> 1 | AG7: intervalo real | AH7: intervalo devido | AI7: 0 | AJ7: 1 | AK7: 0.45833333 | AL7: Início | AM7: Fim | AN7: Hora Extra Noturna Início
C8: =IF(Funcionários!C7=0,"",Funcionários!C7) | D8: =WEEKDAY(DATE('P Gerais'!$D$6,VLOOKUP(Lanç!$E$7,$W$7:$X$18,2,FALSE),E8)) -> 1 | E8: 1 | F8: =VLOOKUP(D8,$AE$8:$AF$14,2,FALSE) -> Dom | M8: =IF(AND(H8=K8,H8<>0),$M$6-IF(J8<I8,$AJ$7+J8-I8,J8-I8),IF(H8>K8,(K8+1-H8)-IF(J8<I8,$AJ$7+J8-I8,J8-I8),(K8-H8)-IF(J8<I8,$AJ$7+J8-I8,J8-I8))) -> 0 | O8: =IF(OR(G8=0,G8="Férias",G8="Falta Justificada",G8="Feriado",G8="Folga (DSR)"),0,IF(G8="Falta Injustificada",HLOOKUP($F8,Jornada!$X$7:$AD$37,VLOOKUP(INDIRECT($C$5),Jornada!$C$8:$W$37,21,0),0),IF(HLOOKUP($F8,Jornada!$X$7:$AD$37,VLOOKUP(INDIRECT($C$5),Jornada!$C$8:$W$37,21,0),0)-M8>0,HLOOKUP($F8,Jornada!$X$7:$AD$37,VLOOKUP(INDIRECT($C$5),Jornada!$C$8:$W$37,21,0),0)-M8,0))) -> 0 | P8: =IF(HLOOKUP($F8,Jornada!$X$7:$AD$37,VLOOKUP(INDIRECT($C$5),Jornada!$C$8:$W$37,21,0),0)-M8<0,ABS(HLOOKUP($F8,Jornada!$X$7:$AD$37,VLOOKUP(INDIRECT($C$5),Jornada!$C$8:$W$37,21,0),0)-M8),0) -> 0 | Q8: =IF(G8="Normal",P8,IF(G8=0,0,IF(OR(G8="Feriado",G8="Férias"),IF(H8>K8,(K8+1-H8)-IF(J8<I8,$AJ$7+J8-I8,J8-I8),(K8-H8)-IF(J8<I8,$AJ$7+J8-I8,J8-I8)),IF(G8="Folga (DSR)",IF(H8>K8,(K8+1-H8)-IF(J8<I8,$AJ$7+J8-I8,J8-I8),(K8-H8)-IF(J8<I8,$AJ$7+J8-I8,J8-I8)),IF(G8="Falta Justificada",IF(H8>K8,(K8+1-H8)-IF(J8<I8,$AJ$7+J8-I8,J8-I8),(K8-H8)-IF(J8<I8,$AJ$7+J8-I8,J8-I8)),0))))) -> 0 | R8: =IF(Q8>$R$7,1,0) -> 0 | S8: Horas trabalhadas no mês | U8: =SUM(M8:M38) -> 0 | W8: Fevereiro | X8: 2 | AB8: =DATE('P Gerais'!$D$6,AB7,1) -> 1 | AC8: =WEEKDAY(AB8) -> 1 | AE8: 1 | AF8: Dom | AG8: =IF(J8<I8,$AJ$7+J8-I8,J8-I8) -> 0 | AH8: =IF(HLOOKUP($F8,Jornada!$X$7:$AD$37,VLOOKUP(INDIRECT($C$5),Jornada!$C$8:$W$37,21,0),0)=0,0,VLOOKUP(INDIRECT($C$5),Jornada!$C$8:$H$37,4,0)) -> 0 | AI8: =IF(AND(I8=0,J8=0,OR(H8<>0,K8<>0),HLOOKUP($F8,Jornada!$X$7:$AD$37,VLOOKUP(INDIRECT($C$5),Jornada!$C$8:$W$37,21,0),0)>$AK$5,M8>$AK$5),VLOOKUP(INDIRECT($C$5),Jornada!$C$8:$H$37,6,0),IF(AG8>VLOOKUP(INDIRECT($C$5),Jornada!$C$8:$H$37,6,0),IF(VLOOKUP(INDIRECT($C$5),Jornada!$C$8:$H$37,6,0)<AG8,0,ABS(VLOOKUP(INDIRECT($C$5),Jornada!$C$8:$H$37,6,0))-AG8),0)) -> 0 | AJ8: =($AJ$7-K8)+H8 -> 1 | AK8: =IF(AJ8<$AK$7,$AK$7-AJ8,$AI$7) -> 0 | AL8: =HLOOKUP($F8,Jornada!$I$5:$V$37,VLOOKUP(INDIRECT($C$5),Jornada!$C$8:$W$37,21,0)+2,0) -> 0 | AM8: =HLOOKUP($F8,Jornada!$I$4:$V$37,VLOOKUP(INDIRECT($C$5),Jornada!$C$8:$W$37,21,0)+3,0) -> 0 | AN8: =IF(AND(AL8>=$AL$5,AL8<$AN$5,H8>=$AL$5,H8<AL8),AL8-H8,IF(AND(AL8>$AI$7,AL8<=$AM$5,H8>=$AL$5,H8<=$AN$5),$AN$5-H8+AL8,IF(AND(AL8>=$AI$7,AL8<=$AM$5,H8>=$AI$7,H8<=$AM$5,H8<AL8),H8-AL8,0))) -> 0 | AO8: =IF(AP8>Q8,0,AP8) -> 0 | AP8: =IF(Q8=0,0,IF(AND(AM8>=$AL$5,AM8<$AN$5,K8>=$AL$5,K8<$AM$5,K8>AM8),K8-AM8,IF(AND(AM8>=$AL$5,AM8<$AN$5,K8<$AN$5,K8>AM8),K8-$AL$5,IF(AND(AM8>=$AI$7,AM8<$AM$5,K8<$AM$5),K8-AM8,IF(AND(AM8<>AI7,AM8>=$AI$7,AM8<=$AM$5,K8>$AM$5,K8>AM8),$AM$5-AM8,IF(AND(K8>$AL$5,K8<$AN$5),K8-$AL$5,IF(AND(K8>$AI$7,K8<$AM$5),$AN$5-$AL$5+K8,IF(AND(OR(K8>$AL$5,H8>$AO$5),AM8>=$AI$7,AM8<$AM$5,K8>$AM$5),(1+$AM$5-$AL$5)-AG8,0)))))))) -> 0
C9: =IF(Funcionários!C8=0,"",Funcionários!C8) | D9: =IF(D8=7,1,D8+1) -> 2 | E9: =IF(DAY(DATE('P Gerais'!$D$6,VLOOKUP($E$7,$W$7:$X$18,2,0),E8+1))>DAY(EOMONTH(DATE('P Gerais'!$D$6,VLOOKUP($E$7,$W$7:$X$18,2,0),E8),0)),DAY(DATE('P Gerais'!$D$6,VLOOKUP($E$7,$W$7:$X$18,2,0)+1,1)),DAY(DATE('P Gerais'!$D$6,VLOOKUP($E$7,$W$7:$X$18,2,0),E8+1))) -> 2 | F9: =VLOOKUP(D9,$AE$8:$AF$14,2,FALSE) -> Seg | M9: =IF(AND(H9=K9,H9<>0),$M$6-IF(J9<I9,$AJ$7+J9-I9,J9-I9),IF(H9>K9,(K9+1-H9)-IF(J9<I9,$AJ$7+J9-I9,J9-I9),(K9-H9)-IF(J9<I9,$AJ$7+J9-I9,J9-I9))) -> 0 | O9: =IF(OR(G9=0,G9="Férias",G9="Falta Justificada",G9="Feriado",G9="Folga (DSR)"),0,IF(G9="Falta Injustificada",HLOOKUP($F9,Jornada!$X$7:$AD$37,VLOOKUP(INDIRECT($C$5),Jornada!$C$8:$W$37,21,0),0),IF(HLOOKUP($F9,Jornada!$X$7:$AD$37,VLOOKUP(INDIRECT($C$5),Jornada!$C$8:$W$37,21,0),0)-M9>0,HLOOKUP($F9,Jornada!$X$7:$AD$37,VLOOKUP(INDIRECT($C$5),Jornada!$C$8:$W$37,21,0),0)-M9,0))) -> 0 | P9: =IF(HLOOKUP($F9,Jornada!$X$7:$AD$37,VLOOKUP(INDIRECT($C$5),Jornada!$C$8:$W$37,21,0),0)-M9<0,ABS(HLOOKUP($F9,Jornada!$X$7:$AD$37,VLOOKUP(INDIRECT($C$5),Jornada!$C$8:$W$37,21,0),0)-M9),0) -> 0 | Q9: =IF(G9="Normal",P9,IF(G9=0,0,IF(OR(G9="Feriado",G9="Férias"),IF(H9>K9,(K9+1-H9)-IF(J9<I9,$AJ$7+J9-I9,J9-I9),(K9-H9)-IF(J9<I9,$AJ$7+J9-I9,J9-I9)),IF(G9="Folga (DSR)",IF(H9>K9,(K9+1-H9)-IF(J9<I9,$AJ$7+J9-I9,J9-I9),(K9-H9)-IF(J9<I9,$AJ$7+J9-I9,J9-I9)),IF(G9="Falta Justificada",IF(H9>K9,(K9+1-H9)-IF(J9<I9,$AJ$7+J9-I9,J9-I9),(K9-H9)-IF(J9<I9,$AJ$7+J9-I9,J9-I9)),0))))) -> 0 | R9: =IF(Q9>$R$7,1,0) -> 0 | W9: Março | X9: 3 | AB9: =AB8+1 -> 2 | AC9: =WEEKDAY(AB9) -> 2 | AE9: 2 | AF9: Seg | AG9: =IF(J9<I9,$AJ$7+J9-I9,J9-I9) -> 0 | AH9: =IF(HLOOKUP($F9,Jornada!$X$7:$AD$37,VLOOKUP(INDIRECT($C$5),Jornada!$C$8:$W$37,21,0),0)=0,0,VLOOKUP(INDIRECT($C$5),Jornada!$C$8:$H$37,4,0)) -> 0 | AI9: =IF(AND(I9=0,J9=0,OR(H9<>0,K9<>0),HLOOKUP($F9,Jornada!$X$7:$AD$37,VLOOKUP(INDIRECT($C$5),Jornada!$C$8:$W$37,21,0),0)>$AK$5,M9>$AK$5),VLOOKUP(INDIRECT($C$5),Jornada!$C$8:$H$37,6,0),IF(AG9>VLOOKUP(INDIRECT($C$5),Jornada!$C$8:$H$37,6,0),IF(VLOOKUP(INDIRECT($C$5),Jornada!$C$8:$H$37,6,0)<AG9,0,ABS(VLOOKUP(INDIRECT($C$5),Jornada!$C$8:$H$37,6,0))-AG9),0)) -> 0 | AJ9: =($AJ$7-K9)+H9 -> 1 | AK9: =IF(AJ9<$AK$7,$AK$7-AJ9,$AI$7) -> 0 | AL9: =HLOOKUP($F9,Jornada!$I$5:$V$37,VLOOKUP(INDIRECT($C$5),Jornada!$C$8:$W$37,21,0)+2,0) -> 0 | AM9: =HLOOKUP($F9,Jornada!$I$4:$V$37,VLOOKUP(INDIRECT($C$5),Jornada!$C$8:$W$37,21,0)+3,0) -> 0 | AN9: =IF(AND(AL9>=$AL$5,AL9<$AN$5,H9>=$AL$5,H9<AL9),AL9-H9,IF(AND(AL9>$AI$7,AL9<=$AM$5,H9>=$AL$5,H9<=$AN$5),$AN$5-H9+AL9,IF(AND(AL9>=$AI$7,AL9<=$AM$5,H9>=$AI$7,H9<=$AM$5,H9<AL9),H9-AL9,0))) -> 0 | AO9: =IF(AP9>Q9,0,AP9) -> 0 | AP9: =IF(Q9=0,0,IF(AND(AM9>=$AL$5,AM9<$AN$5,K9>=$AL$5,K9<$AM$5,K9>AM9),K9-AM9,IF(AND(AM9>=$AL$5,AM9<$AN$5,K9<$AN$5,K9>AM9),K9-$AL$5,IF(AND(AM9>=$AI$7,AM9<$AM$5,K9<$AM$5),K9-AM9,IF(AND(AM9<>AI8,AM9>=$AI$7,AM9<=$AM$5,K9>$AM$5,K9>AM9),$AM$5-AM9,IF(AND(K9>$AL$5,K9<$AN$5),K9-$AL$5,IF(AND(K9>$AI$7,K9<$AM$5),$AN$5-$AL$5+K9,IF(AND(OR(K9>$AL$5,H9>$AO$5),AM9>=$AI$7,AM9<$AM$5,K9>$AM$5),(1+$AM$5-$AL$5)-AG9,0)))))))) -> 0
C10: =IF(Funcionários!C9=0,"",Funcionários!C9) | D10: =IF(D9=7,1,D9+1) -> 3 | E10: =IF(DAY(DATE('P Gerais'!$D$6,VLOOKUP($E$7,$W$7:$X$18,2,0),E9+1))>DAY(EOMONTH(DATE('P Gerais'!$D$6,VLOOKUP($E$7,$W$7:$X$18,2,0),E9),0)),DAY(DATE('P Gerais'!$D$6,VLOOKUP($E$7,$W$7:$X$18,2,0)+1,1)),DAY(DATE('P Gerais'!$D$6,VLOOKUP($E$7,$W$7:$X$18,2,0),E9+1))) -> 3 | F10: =VLOOKUP(D10,$AE$8:$AF$14,2,FALSE) -> Ter | M10: =IF(AND(H10=K10,H10<>0),$M$6-IF(J10<I10,$AJ$7+J10-I10,J10-I10),IF(H10>K10,(K10+1-H10)-IF(J10<I10,$AJ$7+J10-I10,J10-I10),(K10-H10)-IF(J10<I10,$AJ$7+J10-I10,J10-I10))) -> 0 | O10: =IF(OR(G10=0,G10="Férias",G10="Falta Justificada",G10="Feriado",G10="Folga (DSR)"),0,IF(G10="Falta Injustificada",HLOOKUP($F10,Jornada!$X$7:$AD$37,VLOOKUP(INDIRECT($C$5),Jornada!$C$8:$W$37,21,0),0),IF(HLOOKUP($F10,Jornada!$X$7:$AD$37,VLOOKUP(INDIRECT($C$5),Jornada!$C$8:$W$37,21,0),0)-M10>0,HLOOKUP($F10,Jornada!$X$7:$AD$37,VLOOKUP(INDIRECT($C$5),Jornada!$C$8:$W$37,21,0),0)-M10,0))) -> 0 | P10: =IF(HLOOKUP($F10,Jornada!$X$7:$AD$37,VLOOKUP(INDIRECT($C$5),Jornada!$C$8:$W$37,21,0),0)-M10<0,ABS(HLOOKUP($F10,Jornada!$X$7:$AD$37,VLOOKUP(INDIRECT($C$5),Jornada!$C$8:$W$37,21,0),0)-M10),0) -> 0 | Q10: =IF(G10="Normal",P10,IF(G10=0,0,IF(OR(G10="Feriado",G10="Férias"),IF(H10>K10,(K10+1-H10)-IF(J10<I10,$AJ$7+J10-I10,J10-I10),(K10-H10)-IF(J10<I10,$AJ$7+J10-I10,J10-I10)),IF(G10="Folga (DSR)",IF(H10>K10,(K10+1-H10)-IF(J10<I10,$AJ$7+J10-I10,J10-I10),(K10-H10)-IF(J10<I10,$AJ$7+J10-I10,J10-I10)),IF(G10="Falta Justificada",IF(H10>K10,(K10+1-H10)-IF(J10<I10,$AJ$7+J10-I10,J10-I10),(K10-H10)-IF(J10<I10,$AJ$7+J10-I10,J10-I10)),0))))) -> 0 | R10: =IF(Q10>$R$7,1,0) -> 0 | S10: Acumulado no banco de horas | U10: =IF(M5="Horas devidas",ABS(-K5+F58-U14),ABS(K5+F58-U14)) -> 0 | W10: Abril | X10: 4 | AB10: =AB9+1 -> 3 | AC10: =WEEKDAY(AB10) -> 3 | AE10: 3 | AF10: Ter | AG10: =IF(J10<I10,$AJ$7+J10-I10,J10-I10) -> 0 | AH10: =IF(HLOOKUP($F10,Jornada!$X$7:$AD$37,VLOOKUP(INDIRECT($C$5),Jornada!$C$8:$W$37,21,0),0)=0,0,VLOOKUP(INDIRECT($C$5),Jornada!$C$8:$H$37,4,0)) -> 0 | AI10: =IF(AND(I10=0,J10=0,OR(H10<>0,K10<>0),HLOOKUP($F10,Jornada!$X$7:$AD$37,VLOOKUP(INDIRECT($C$5),Jornada!$C$8:$W$37,21,0),0)>$AK$5,M10>$AK$5),VLOOKUP(INDIRECT($C$5),Jornada!$C$8:$H$37,6,0),IF(AG10>VLOOKUP(INDIRECT($C$5),Jornada!$C$8:$H$37,6,0),IF(VLOOKUP(INDIRECT($C$5),Jornada!$C$8:$H$37,6,0)<AG10,0,ABS(VLOOKUP(INDIRECT($C$5),Jornada!$C$8:$H$37,6,0))-AG10),0)) -> 0 | AJ10: =($AJ$7-K10)+H10 -> 1 | AK10: =IF(AJ10<$AK$7,$AK$7-AJ10,$AI$7) -> 0 | AL10: =HLOOKUP($F10,Jornada!$I$5:$V$37,VLOOKUP(INDIRECT($C$5),Jornada!$C$8:$W$37,21,0)+2,0) -> 0 | AM10: =HLOOKUP($F10,Jornada!$I$4:$V$37,VLOOKUP(INDIRECT($C$5),Jornada!$C$8:$W$37,21,0)+3,0) -> 0 | AN10: =IF(AND(AL10>=$AL$5,AL10<$AN$5,H10>=$AL$5,H10<AL10),AL10-H10,IF(AND(AL10>$AI$7,AL10<=$AM$5,H10>=$AL$5,H10<=$AN$5),$AN$5-H10+AL10,IF(AND(AL10>=$AI$7,AL10<=$AM$5,H10>=$AI$7,H10<=$AM$5,H10<AL10),H10-AL10,0))) -> 0 | AO10: =IF(AP10>Q10,0,AP10) -> 0 | AP10: =IF(Q10=0,0,IF(AND(AM10>=$AL$5,AM10<$AN$5,K10>=$AL$5,K10<$AM$5,K10>AM10),K10-AM10,IF(AND(AM10>=$AL$5,AM10<$AN$5,K10<$AN$5,K10>AM10),K10-$AL$5,IF(AND(AM10>=$AI$7,AM10<$AM$5,K10<$AM$5),K10-AM10,IF(AND(AM10<>AI9,AM10>=$AI$7,AM10<=$AM$5,K10>$AM$5,K10>AM10),$AM$5-AM10,IF(AND(K10>$AL$5,K10<$AN$5),K10-$AL$5,IF(AND(K10>$AI$7,K10<$AM$5),$AN$5-$AL$5+K10,IF(AND(OR(K10>$AL$5,H10>$AO$5),AM10>=$AI$7,AM10<$AM$5,K10>$AM$5),(1+$AM$5-$AL$5)-AG10,0)))))))) -> 0
C11: =IF(Funcionários!C10=0,"",Funcionários!C10) | D11: =IF(D10=7,1,D10+1) -> 4 | E11: =IF(DAY(DATE('P Gerais'!$D$6,VLOOKUP($E$7,$W$7:$X$18,2,0),E10+1))>DAY(EOMONTH(DATE('P Gerais'!$D$6,VLOOKUP($E$7,$W$7:$X$18,2,0),E10),0)),DAY(DATE('P Gerais'!$D$6,VLOOKUP($E$7,$W$7:$X$18,2,0)+1,1)),DAY(DATE('P Gerais'!$D$6,VLOOKUP($E$7,$W$7:$X$18,2,0),E10+1))) -> 4 | F11: =VLOOKUP(D11,$AE$8:$AF$14,2,FALSE) -> Qua | M11: =IF(AND(H11=K11,H11<>0),$M$6-IF(J11<I11,$AJ$7+J11-I11,J11-I11),IF(H11>K11,(K11+1-H11)-IF(J11<I11,$AJ$7+J11-I11,J11-I11),(K11-H11)-IF(J11<I11,$AJ$7+J11-I11,J11-I11))) -> 0 | O11: =IF(OR(G11=0,G11="Férias",G11="Falta Justificada",G11="Feriado",G11="Folga (DSR)"),0,IF(G11="Falta Injustificada",HLOOKUP($F11,Jornada!$X$7:$AD$37,VLOOKUP(INDIRECT($C$5),Jornada!$C$8:$W$37,21,0),0),IF(HLOOKUP($F11,Jornada!$X$7:$AD$37,VLOOKUP(INDIRECT($C$5),Jornada!$C$8:$W$37,21,0),0)-M11>0,HLOOKUP($F11,Jornada!$X$7:$AD$37,VLOOKUP(INDIRECT($C$5),Jornada!$C$8:$W$37,21,0),0)-M11,0))) -> 0 | P11: =IF(HLOOKUP($F11,Jornada!$X$7:$AD$37,VLOOKUP(INDIRECT($C$5),Jornada!$C$8:$W$37,21,0),0)-M11<0,ABS(HLOOKUP($F11,Jornada!$X$7:$AD$37,VLOOKUP(INDIRECT($C$5),Jornada!$C$8:$W$37,21,0),0)-M11),0) -> 0 | Q11: =IF(G11="Normal",P11,IF(G11=0,0,IF(OR(G11="Feriado",G11="Férias"),IF(H11>K11,(K11+1-H11)-IF(J11<I11,$AJ$7+J11-I11,J11-I11),(K11-H11)-IF(J11<I11,$AJ$7+J11-I11,J11-I11)),IF(G11="Folga (DSR)",IF(H11>K11,(K11+1-H11)-IF(J11<I11,$AJ$7+J11-I11,J11-I11),(K11-H11)-IF(J11<I11,$AJ$7+J11-I11,J11-I11)),IF(G11="Falta Justificada",IF(H11>K11,(K11+1-H11)-IF(J11<I11,$AJ$7+J11-I11,J11-I11),(K11-H11)-IF(J11<I11,$AJ$7+J11-I11,J11-I11)),0))))) -> 0 | R11: =IF(Q11>$R$7,1,0) -> 0 | V11: =IF(AND(K5>U12,M5="Horas devidas"),"Negativo",IF(AND(U12>K5,U14>F58),"Negativo",0)) -> 0 | W11: Maio | X11: 5 | Z11: =IF(AND(M5="horas extras",Z13="positivo"),"positivo",IF(AND(M5="horas devidas",Z13="Negativo"),"Negativo",IF(AND(Z13="positivo",M5="horas devidas",U12>K5),"Positivo","Negativo"))) -> Negativo | AB11: =AB10+1 -> 4 | AC11: =WEEKDAY(AB11) -> 4 | AE11: 4 | AF11: Qua | AG11: =IF(J11<I11,$AJ$7+J11-I11,J11-I11) -> 0 | AH11: =IF(HLOOKUP($F11,Jornada!$X$7:$AD$37,VLOOKUP(INDIRECT($C$5),Jornada!$C$8:$W$37,21,0),0)=0,0,VLOOKUP(INDIRECT($C$5),Jornada!$C$8:$H$37,4,0)) -> 0 | AI11: =IF(AND(I11=0,J11=0,OR(H11<>0,K11<>0),HLOOKUP($F11,Jornada!$X$7:$AD$37,VLOOKUP(INDIRECT($C$5),Jornada!$C$8:$W$37,21,0),0)>$AK$5,M11>$AK$5),VLOOKUP(INDIRECT($C$5),Jornada!$C$8:$H$37,6,0),IF(AG11>VLOOKUP(INDIRECT($C$5),Jornada!$C$8:$H$37,6,0),IF(VLOOKUP(INDIRECT($C$5),Jornada!$C$8:$H$37,6,0)<AG11,0,ABS(VLOOKUP(INDIRECT($C$5),Jornada!$C$8:$H$37,6,0))-AG11),0)) -> 0 | AJ11: =($AJ$7-K11)+H11 -> 1 | AK11: =IF(AJ11<$AK$7,$AK$7-AJ11,$AI$7) -> 0 | AL11: =HLOOKUP($F11,Jornada!$I$5:$V$37,VLOOKUP(INDIRECT($C$5),Jornada!$C$8:$W$37,21,0)+2,0) -> 0 | AM11: =HLOOKUP($F11,Jornada!$I$4:$V$37,VLOOKUP(INDIRECT($C$5),Jornada!$C$8:$W$37,21,0)+3,0) -> 0 | AN11: =IF(AND(AL11>=$AL$5,AL11<$AN$5,H11>=$AL$5,H11<AL11),AL11-H11,IF(AND(AL11>$AI$7,AL11<=$AM$5,H11>=$AL$5,H11<=$AN$5),$AN$5-H11+AL11,IF(AND(AL11>=$AI$7,AL11<=$AM$5,H11>=$AI$7,H11<=$AM$5,H11<AL11),H11-AL11,0))) -> 0 | AO11: =IF(AP11>Q11,0,AP11) -> 0 | AP11: =IF(Q11=0,0,IF(AND(AM11>=$AL$5,AM11<$AN$5,K11>=$AL$5,K11<$AM$5,K11>AM11),K11-AM11,IF(AND(AM11>=$AL$5,AM11<$AN$5,K11<$AN$5,K11>AM11),K11-$AL$5,IF(AND(AM11>=$AI$7,AM11<$AM$5,K11<$AM$5),K11-AM11,IF(AND(AM11<>AI10,AM11>=$AI$7,AM11<=$AM$5,K11>$AM$5,K11>AM11),$AM$5-AM11,IF(AND(K11>$AL$5,K11<$AN$5),K11-$AL$5,IF(AND(K11>$AI$7,K11<$AM$5),$AN$5-$AL$5+K11,IF(AND(OR(K11>$AL$5,H11>$AO$5),AM11>=$AI$7,AM11<$AM$5,K11>$AM$5),(1+$AM$5-$AL$5)-AG11,0)))))))) -> 0
C12: =IF(Funcionários!C11=0,"",Funcionários!C11) | D12: =IF(D11=7,1,D11+1) -> 5 | E12: =IF(DAY(DATE('P Gerais'!$D$6,VLOOKUP($E$7,$W$7:$X$18,2,0),E11+1))>DAY(EOMONTH(DATE('P Gerais'!$D$6,VLOOKUP($E$7,$W$7:$X$18,2,0),E11),0)),DAY(DATE('P Gerais'!$D$6,VLOOKUP($E$7,$W$7:$X$18,2,0)+1,1)),DAY(DATE('P Gerais'!$D$6,VLOOKUP($E$7,$W$7:$X$18,2,0),E11+1))) -> 5 | F12: =VLOOKUP(D12,$AE$8:$AF$14,2,FALSE) -> Qui | M12: =IF(AND(H12=K12,H12<>0),$M$6-IF(J12<I12,$AJ$7+J12-I12,J12-I12),IF(H12>K12,(K12+1-H12)-IF(J12<I12,$AJ$7+J12-I12,J12-I12),(K12-H12)-IF(J12<I12,$AJ$7+J12-I12,J12-I12))) -> 0 | O12: =IF(OR(G12=0,G12="Férias",G12="Falta Justificada",G12="Feriado",G12="Folga (DSR)"),0,IF(G12="Falta Injustificada",HLOOKUP($F12,Jornada!$X$7:$AD$37,VLOOKUP(INDIRECT($C$5),Jornada!$C$8:$W$37,21,0),0),IF(HLOOKUP($F12,Jornada!$X$7:$AD$37,VLOOKUP(INDIRECT($C$5),Jornada!$C$8:$W$37,21,0),0)-M12>0,HLOOKUP($F12,Jornada!$X$7:$AD$37,VLOOKUP(INDIRECT($C$5),Jornada!$C$8:$W$37,21,0),0)-M12,0))) -> 0 | P12: =IF(HLOOKUP($F12,Jornada!$X$7:$AD$37,VLOOKUP(INDIRECT($C$5),Jornada!$C$8:$W$37,21,0),0)-M12<0,ABS(HLOOKUP($F12,Jornada!$X$7:$AD$37,VLOOKUP(INDIRECT($C$5),Jornada!$C$8:$W$37,21,0),0)-M12),0) -> 0 | Q12: =IF(G12="Normal",P12,IF(G12=0,0,IF(OR(G12="Feriado",G12="Férias"),IF(H12>K12,(K12+1-H12)-IF(J12<I12,$AJ$7+J12-I12,J12-I12),(K12-H12)-IF(J12<I12,$AJ$7+J12-I12,J12-I12)),IF(G12="Folga (DSR)",IF(H12>K12,(K12+1-H12)-IF(J12<I12,$AJ$7+J12-I12,J12-I12),(K12-H12)-IF(J12<I12,$AJ$7+J12-I12,J12-I12)),IF(G12="Falta Justificada",IF(H12>K12,(K12+1-H12)-IF(J12<I12,$AJ$7+J12-I12,J12-I12),(K12-H12)-IF(J12<I12,$AJ$7+J12-I12,J12-I12)),0))))) -> 0 | R12: =IF(Q12>$R$7,1,0) -> 0 | S12: Horas somados / subtraídas ao banco | U12: =IF(U14>=F58,(U14)-F58,(F58-U14)) -> 0 | W12: Junho | X12: 6 | AB12: =AB11+1 -> 5 | AC12: =WEEKDAY(AB12) -> 5 | AE12: 5 | AF12: Qui | AG12: =IF(J12<I12,$AJ$7+J12-I12,J12-I12) -> 0 | AH12: =IF(HLOOKUP($F12,Jornada!$X$7:$AD$37,VLOOKUP(INDIRECT($C$5),Jornada!$C$8:$W$37,21,0),0)=0,0,VLOOKUP(INDIRECT($C$5),Jornada!$C$8:$H$37,4,0)) -> 0 | AI12: =IF(AND(I12=0,J12=0,OR(H12<>0,K12<>0),HLOOKUP($F12,Jornada!$X$7:$AD$37,VLOOKUP(INDIRECT($C$5),Jornada!$C$8:$W$37,21,0),0)>$AK$5,M12>$AK$5),VLOOKUP(INDIRECT($C$5),Jornada!$C$8:$H$37,6,0),IF(AG12>VLOOKUP(INDIRECT($C$5),Jornada!$C$8:$H$37,6,0),IF(VLOOKUP(INDIRECT($C$5),Jornada!$C$8:$H$37,6,0)<AG12,0,ABS(VLOOKUP(INDIRECT($C$5),Jornada!$C$8:$H$37,6,0))-AG12),0)) -> 0 | AJ12: =($AJ$7-K12)+H12 -> 1 | AK12: =IF(AJ12<$AK$7,$AK$7-AJ12,$AI$7) -> 0 | AL12: =HLOOKUP($F12,Jornada!$I$5:$V$37,VLOOKUP(INDIRECT($C$5),Jornada!$C$8:$W$37,21,0)+2,0) -> 0 | AM12: =HLOOKUP($F12,Jornada!$I$4:$V$37,VLOOKUP(INDIRECT($C$5),Jornada!$C$8:$W$37,21,0)+3,0) -> 0 | AN12: =IF(AND(AL12>=$AL$5,AL12<$AN$5,H12>=$AL$5,H12<AL12),AL12-H12,IF(AND(AL12>$AI$7,AL12<=$AM$5,H12>=$AL$5,H12<=$AN$5),$AN$5-H12+AL12,IF(AND(AL12>=$AI$7,AL12<=$AM$5,H12>=$AI$7,H12<=$AM$5,H12<AL12),H12-AL12,0))) -> 0 | AO12: =IF(AP12>Q12,0,AP12) -> 0 | AP12: =IF(Q12=0,0,IF(AND(AM12>=$AL$5,AM12<$AN$5,K12>=$AL$5,K12<$AM$5,K12>AM12),K12-AM12,IF(AND(AM12>=$AL$5,AM12<$AN$5,K12<$AN$5,K12>AM12),K12-$AL$5,IF(AND(AM12>=$AI$7,AM12<$AM$5,K12<$AM$5),K12-AM12,IF(AND(AM12<>AI11,AM12>=$AI$7,AM12<=$AM$5,K12>$AM$5,K12>AM12),$AM$5-AM12,IF(AND(K12>$AL$5,K12<$AN$5),K12-$AL$5,IF(AND(K12>$AI$7,K12<$AM$5),$AN$5-$AL$5+K12,IF(AND(OR(K12>$AL$5,H12>$AO$5),AM12>=$AI$7,AM12<$AM$5,K12>$AM$5),(1+$AM$5-$AL$5)-AG12,0)))))))) -> 0
C13: =IF(Funcionários!C12=0,"",Funcionários!C12) | D13: =IF(D12=7,1,D12+1) -> 6 | E13: =IF(DAY(DATE('P Gerais'!$D$6,VLOOKUP($E$7,$W$7:$X$18,2,0),E12+1))>DAY(EOMONTH(DATE('P Gerais'!$D$6,VLOOKUP($E$7,$W$7:$X$18,2,0),E12),0)),DAY(DATE('P Gerais'!$D$6,VLOOKUP($E$7,$W$7:$X$18,2,0)+1,1)),DAY(DATE('P Gerais'!$D$6,VLOOKUP($E$7,$W$7:$X$18,2,0),E12+1))) -> 6 | F13: =VLOOKUP(D13,$AE$8:$AF$14,2,FALSE) -> Sex | M13: =IF(AND(H13=K13,H13<>0),$M$6-IF(J13<I13,$AJ$7+J13-I13,J13-I13),IF(H13>K13,(K13+1-H13)-IF(J13<I13,$AJ$7+J13-I13,J13-I13),(K13-H13)-IF(J13<I13,$AJ$7+J13-I13,J13-I13))) -> 0 | O13: =IF(OR(G13=0,G13="Férias",G13="Falta Justificada",G13="Feriado",G13="Folga (DSR)"),0,IF(G13="Falta Injustificada",HLOOKUP($F13,Jornada!$X$7:$AD$37,VLOOKUP(INDIRECT($C$5),Jornada!$C$8:$W$37,21,0),0),IF(HLOOKUP($F13,Jornada!$X$7:$AD$37,VLOOKUP(INDIRECT($C$5),Jornada!$C$8:$W$37,21,0),0)-M13>0,HLOOKUP($F13,Jornada!$X$7:$AD$37,VLOOKUP(INDIRECT($C$5),Jornada!$C$8:$W$37,21,0),0)-M13,0))) -> 0 | P13: =IF(HLOOKUP($F13,Jornada!$X$7:$AD$37,VLOOKUP(INDIRECT($C$5),Jornada!$C$8:$W$37,21,0),0)-M13<0,ABS(HLOOKUP($F13,Jornada!$X$7:$AD$37,VLOOKUP(INDIRECT($C$5),Jornada!$C$8:$W$37,21,0),0)-M13),0) -> 0 | Q13: =IF(G13="Normal",P13,IF(G13=0,0,IF(OR(G13="Feriado",G13="Férias"),IF(H13>K13,(K13+1-H13)-IF(J13<I13,$AJ$7+J13-I13,J13-I13),(K13-H13)-IF(J13<I13,$AJ$7+J13-I13,J13-I13)),IF(G13="Folga (DSR)",IF(H13>K13,(K13+1-H13)-IF(J13<I13,$AJ$7+J13-I13,J13-I13),(K13-H13)-IF(J13<I13,$AJ$7+J13-I13,J13-I13)),IF(G13="Falta Justificada",IF(H13>K13,(K13+1-H13)-IF(J13<I13,$AJ$7+J13-I13,J13-I13),(K13-H13)-IF(J13<I13,$AJ$7+J13-I13,J13-I13)),0))))) -> 0 | R13: =IF(Q13>$R$7,1,0) -> 0 | W13: Julho | X13: 7 | Z13: =IF(U14>F58,"Negativo","Positivo") -> Positivo | AB13: =AB12+1 -> 6 | AC13: =WEEKDAY(AB13) -> 6 | AE13: 6 | AF13: Sex | AG13: =IF(J13<I13,$AJ$7+J13-I13,J13-I13) -> 0 | AH13: =IF(HLOOKUP($F13,Jornada!$X$7:$AD$37,VLOOKUP(INDIRECT($C$5),Jornada!$C$8:$W$37,21,0),0)=0,0,VLOOKUP(INDIRECT($C$5),Jornada!$C$8:$H$37,4,0)) -> 0 | AI13: =IF(AND(I13=0,J13=0,OR(H13<>0,K13<>0),HLOOKUP($F13,Jornada!$X$7:$AD$37,VLOOKUP(INDIRECT($C$5),Jornada!$C$8:$W$37,21,0),0)>$AK$5,M13>$AK$5),VLOOKUP(INDIRECT($C$5),Jornada!$C$8:$H$37,6,0),IF(AG13>VLOOKUP(INDIRECT($C$5),Jornada!$C$8:$H$37,6,0),IF(VLOOKUP(INDIRECT($C$5),Jornada!$C$8:$H$37,6,0)<AG13,0,ABS(VLOOKUP(INDIRECT($C$5),Jornada!$C$8:$H$37,6,0))-AG13),0)) -> 0 | AJ13: =($AJ$7-K13)+H13 -> 1 | AK13: =IF(AJ13<$AK$7,$AK$7-AJ13,$AI$7) -> 0 | AL13: =HLOOKUP($F13,Jornada!$I$5:$V$37,VLOOKUP(INDIRECT($C$5),Jornada!$C$8:$W$37,21,0)+2,0) -> 0 | AM13: =HLOOKUP($F13,Jornada!$I$4:$V$37,VLOOKUP(INDIRECT($C$5),Jornada!$C$8:$W$37,21,0)+3,0) -> 0 | AN13: =IF(AND(AL13>=$AL$5,AL13<$AN$5,H13>=$AL$5,H13<AL13),AL13-H13,IF(AND(AL13>$AI$7,AL13<=$AM$5,H13>=$AL$5,H13<=$AN$5),$AN$5-H13+AL13,IF(AND(AL13>=$AI$7,AL13<=$AM$5,H13>=$AI$7,H13<=$AM$5,H13<AL13),H13-AL13,0))) -> 0 | AO13: =IF(AP13>Q13,0,AP13) -> 0 | AP13: =IF(Q13=0,0,IF(AND(AM13>=$AL$5,AM13<$AN$5,K13>=$AL$5,K13<$AM$5,K13>AM13),K13-AM13,IF(AND(AM13>=$AL$5,AM13<$AN$5,K13<$AN$5,K13>AM13),K13-$AL$5,IF(AND(AM13>=$AI$7,AM13<$AM$5,K13<$AM$5),K13-AM13,IF(AND(AM13<>AI12,AM13>=$AI$7,AM13<=$AM$5,K13>$AM$5,K13>AM13),$AM$5-AM13,IF(AND(K13>$AL$5,K13<$AN$5),K13-$AL$5,IF(AND(K13>$AI$7,K13<$AM$5),$AN$5-$AL$5+K13,IF(AND(OR(K13>$AL$5,H13>$AO$5),AM13>=$AI$7,AM13<$AM$5,K13>$AM$5),(1+$AM$5-$AL$5)-AG13,0)))))))) -> 0
C14: =IF(Funcionários!C13=0,"",Funcionários!C13) | D14: =IF(D13=7,1,D13+1) -> 7 | E14: =IF(DAY(DATE('P Gerais'!$D$6,VLOOKUP($E$7,$W$7:$X$18,2,0),E13+1))>DAY(EOMONTH(DATE('P Gerais'!$D$6,VLOOKUP($E$7,$W$7:$X$18,2,0),E13),0)),DAY(DATE('P Gerais'!$D$6,VLOOKUP($E$7,$W$7:$X$18,2,0)+1,1)),DAY(DATE('P Gerais'!$D$6,VLOOKUP($E$7,$W$7:$X$18,2,0),E13+1))) -> 7 | F14: =VLOOKUP(D14,$AE$8:$AF$14,2,FALSE) -> Sáb | M14: =IF(AND(H14=K14,H14<>0),$M$6-IF(J14<I14,$AJ$7+J14-I14,J14-I14),IF(H14>K14,(K14+1-H14)-IF(J14<I14,$AJ$7+J14-I14,J14-I14),(K14-H14)-IF(J14<I14,$AJ$7+J14-I14,J14-I14))) -> 0 | O14: =IF(OR(G14=0,G14="Férias",G14="Falta Justificada",G14="Feriado",G14="Folga (DSR)"),0,IF(G14="Falta Injustificada",HLOOKUP($F14,Jornada!$X$7:$AD$37,VLOOKUP(INDIRECT($C$5),Jornada!$C$8:$W$37,21,0),0),IF(HLOOKUP($F14,Jornada!$X$7:$AD$37,VLOOKUP(INDIRECT($C$5),Jornada!$C$8:$W$37,21,0),0)-M14>0,HLOOKUP($F14,Jornada!$X$7:$AD$37,VLOOKUP(INDIRECT($C$5),Jornada!$C$8:$W$37,21,0),0)-M14,0))) -> 0 | P14: =IF(HLOOKUP($F14,Jornada!$X$7:$AD$37,VLOOKUP(INDIRECT($C$5),Jornada!$C$8:$W$37,21,0),0)-M14<0,ABS(HLOOKUP($F14,Jornada!$X$7:$AD$37,VLOOKUP(INDIRECT($C$5),Jornada!$C$8:$W$37,21,0),0)-M14),0) -> 0 | Q14: =IF(G14="Normal",P14,IF(G14=0,0,IF(OR(G14="Feriado",G14="Férias"),IF(H14>K14,(K14+1-H14)-IF(J14<I14,$AJ$7+J14-I14,J14-I14),(K14-H14)-IF(J14<I14,$AJ$7+J14-I14,J14-I14)),IF(G14="Folga (DSR)",IF(H14>K14,(K14+1-H14)-IF(J14<I14,$AJ$7+J14-I14,J14-I14),(K14-H14)-IF(J14<I14,$AJ$7+J14-I14,J14-I14)),IF(G14="Falta Justificada",IF(H14>K14,(K14+1-H14)-IF(J14<I14,$AJ$7+J14-I14,J14-I14),(K14-H14)-IF(J14<I14,$AJ$7+J14-I14,J14-I14)),0))))) -> 0 | R14: =IF(Q14>$R$7,1,0) -> 0 | S14: Total de horas devidas | U14: =SUM(O8:O38) -> 0 | W14: Agosto | X14: 8 | AB14: =AB13+1 -> 7 | AC14: =WEEKDAY(AB14) -> 7 | AE14: 7 | AF14: Sáb | AG14: =IF(J14<I14,$AJ$7+J14-I14,J14-I14) -> 0 | AH14: =IF(HLOOKUP($F14,Jornada!$X$7:$AD$37,VLOOKUP(INDIRECT($C$5),Jornada!$C$8:$W$37,21,0),0)=0,0,VLOOKUP(INDIRECT($C$5),Jornada!$C$8:$H$37,4,0)) -> 0 | AI14: =IF(AND(I14=0,J14=0,OR(H14<>0,K14<>0),HLOOKUP($F14,Jornada!$X$7:$AD$37,VLOOKUP(INDIRECT($C$5),Jornada!$C$8:$W$37,21,0),0)>$AK$5,M14>$AK$5),VLOOKUP(INDIRECT($C$5),Jornada!$C$8:$H$37,6,0),IF(AG14>VLOOKUP(INDIRECT($C$5),Jornada!$C$8:$H$37,6,0),IF(VLOOKUP(INDIRECT($C$5),Jornada!$C$8:$H$37,6,0)<AG14,0,ABS(VLOOKUP(INDIRECT($C$5),Jornada!$C$8:$H$37,6,0))-AG14),0)) -> 0 | AJ14: =($AJ$7-K14)+H14 -> 1 | AK14: =IF(AJ14<$AK$7,$AK$7-AJ14,$AI$7) -> 0 | AL14: =HLOOKUP($F14,Jornada!$I$5:$V$37,VLOOKUP(INDIRECT($C$5),Jornada!$C$8:$W$37,21,0)+2,0) -> 0 | AM14: =HLOOKUP($F14,Jornada!$I$4:$V$37,VLOOKUP(INDIRECT($C$5),Jornada!$C$8:$W$37,21,0)+3,0) -> 0 | AN14: =IF(AND(AL14>=$AL$5,AL14<$AN$5,H14>=$AL$5,H14<AL14),AL14-H14,IF(AND(AL14>$AI$7,AL14<=$AM$5,H14>=$AL$5,H14<=$AN$5),$AN$5-H14+AL14,IF(AND(AL14>=$AI$7,AL14<=$AM$5,H14>=$AI$7,H14<=$AM$5,H14<AL14),H14-AL14,0))) -> 0 | AO14: =IF(AP14>Q14,0,AP14) -> 0 | AP14: =IF(Q14=0,0,IF(AND(AM14>=$AL$5,AM14<$AN$5,K14>=$AL$5,K14<$AM$5,K14>AM14),K14-AM14,IF(AND(AM14>=$AL$5,AM14<$AN$5,K14<$AN$5,K14>AM14),K14-$AL$5,IF(AND(AM14>=$AI$7,AM14<$AM$5,K14<$AM$5),K14-AM14,IF(AND(AM14<>AI13,AM14>=$AI$7,AM14<=$AM$5,K14>$AM$5,K14>AM14),$AM$5-AM14,IF(AND(K14>$AL$5,K14<$AN$5),K14-$AL$5,IF(AND(K14>$AI$7,K14<$AM$5),$AN$5-$AL$5+K14,IF(AND(OR(K14>$AL$5,H14>$AO$5),AM14>=$AI$7,AM14<$AM$5,K14>$AM$5),(1+$AM$5-$AL$5)-AG14,0)))))))) -> 0
C15: =IF(Funcionários!C14=0,"",Funcionários!C14) | D15: =IF(D14=7,1,D14+1) -> 1 | E15: =IF(DAY(DATE('P Gerais'!$D$6,VLOOKUP($E$7,$W$7:$X$18,2,0),E14+1))>DAY(EOMONTH(DATE('P Gerais'!$D$6,VLOOKUP($E$7,$W$7:$X$18,2,0),E14),0)),DAY(DATE('P Gerais'!$D$6,VLOOKUP($E$7,$W$7:$X$18,2,0)+1,1)),DAY(DATE('P Gerais'!$D$6,VLOOKUP($E$7,$W$7:$X$18,2,0),E14+1))) -> 8 | F15: =VLOOKUP(D15,$AE$8:$AF$14,2,FALSE) -> Dom | M15: =IF(AND(H15=K15,H15<>0),$M$6-IF(J15<I15,$AJ$7+J15-I15,J15-I15),IF(H15>K15,(K15+1-H15)-IF(J15<I15,$AJ$7+J15-I15,J15-I15),(K15-H15)-IF(J15<I15,$AJ$7+J15-I15,J15-I15))) -> 0 | O15: =IF(OR(G15=0,G15="Férias",G15="Falta Justificada",G15="Feriado",G15="Folga (DSR)"),0,IF(G15="Falta Injustificada",HLOOKUP($F15,Jornada!$X$7:$AD$37,VLOOKUP(INDIRECT($C$5),Jornada!$C$8:$W$37,21,0),0),IF(HLOOKUP($F15,Jornada!$X$7:$AD$37,VLOOKUP(INDIRECT($C$5),Jornada!$C$8:$W$37,21,0),0)-M15>0,HLOOKUP($F15,Jornada!$X$7:$AD$37,VLOOKUP(INDIRECT($C$5),Jornada!$C$8:$W$37,21,0),0)-M15,0))) -> 0 | P15: =IF(HLOOKUP($F15,Jornada!$X$7:$AD$37,VLOOKUP(INDIRECT($C$5),Jornada!$C$8:$W$37,21,0),0)-M15<0,ABS(HLOOKUP($F15,Jornada!$X$7:$AD$37,VLOOKUP(INDIRECT($C$5),Jornada!$C$8:$W$37,21,0),0)-M15),0) -> 0 | Q15: =IF(G15="Normal",P15,IF(G15=0,0,IF(OR(G15="Feriado",G15="Férias"),IF(H15>K15,(K15+1-H15)-IF(J15<I15,$AJ$7+J15-I15,J15-I15),(K15-H15)-IF(J15<I15,$AJ$7+J15-I15,J15-I15)),IF(G15="Folga (DSR)",IF(H15>K15,(K15+1-H15)-IF(J15<I15,$AJ$7+J15-I15,J15-I15),(K15-H15)-IF(J15<I15,$AJ$7+J15-I15,J15-I15)),IF(G15="Falta Justificada",IF(H15>K15,(K15+1-H15)-IF(J15<I15,$AJ$7+J15-I15,J15-I15),(K15-H15)-IF(J15<I15,$AJ$7+J15-I15,J15-I15)),0))))) -> 0 | R15: =IF(Q15>$R$7,1,0) -> 0 | W15: Setembro | X15: 9 | AB15: =AB14+1 -> 8 | AC15: =WEEKDAY(AB15) -> 1 | AG15: =IF(J15<I15,$AJ$7+J15-I15,J15-I15) -> 0 | AH15: =IF(HLOOKUP($F15,Jornada!$X$7:$AD$37,VLOOKUP(INDIRECT($C$5),Jornada!$C$8:$W$37,21,0),0)=0,0,VLOOKUP(INDIRECT($C$5),Jornada!$C$8:$H$37,4,0)) -> 0 | AI15: =IF(AND(I15=0,J15=0,OR(H15<>0,K15<>0),HLOOKUP($F15,Jornada!$X$7:$AD$37,VLOOKUP(INDIRECT($C$5),Jornada!$C$8:$W$37,21,0),0)>$AK$5,M15>$AK$5),VLOOKUP(INDIRECT($C$5),Jornada!$C$8:$H$37,6,0),IF(AG15>VLOOKUP(INDIRECT($C$5),Jornada!$C$8:$H$37,6,0),IF(VLOOKUP(INDIRECT($C$5),Jornada!$C$8:$H$37,6,0)<AG15,0,ABS(VLOOKUP(INDIRECT($C$5),Jornada!$C$8:$H$37,6,0))-AG15),0)) -> 0 | AJ15: =($AJ$7-K15)+H15 -> 1 | AK15: =IF(AJ15<$AK$7,$AK$7-AJ15,$AI$7) -> 0 | AL15: =HLOOKUP($F15,Jornada!$I$5:$V$37,VLOOKUP(INDIRECT($C$5),Jornada!$C$8:$W$37,21,0)+2,0) -> 0 | AM15: =HLOOKUP($F15,Jornada!$I$4:$V$37,VLOOKUP(INDIRECT($C$5),Jornada!$C$8:$W$37,21,0)+3,0) -> 0 | AN15: =IF(AND(AL15>=$AL$5,AL15<$AN$5,H15>=$AL$5,H15<AL15),AL15-H15,IF(AND(AL15>$AI$7,AL15<=$AM$5,H15>=$AL$5,H15<=$AN$5),$AN$5-H15+AL15,IF(AND(AL15>=$AI$7,AL15<=$AM$5,H15>=$AI$7,H15<=$AM$5,H15<AL15),H15-AL15,0))) -> 0 | AO15: =IF(AP15>Q15,0,AP15) -> 0 | AP15: =IF(Q15=0,0,IF(AND(AM15>=$AL$5,AM15<$AN$5,K15>=$AL$5,K15<$AM$5,K15>AM15),K15-AM15,IF(AND(AM15>=$AL$5,AM15<$AN$5,K15<$AN$5,K15>AM15),K15-$AL$5,IF(AND(AM15>=$AI$7,AM15<$AM$5,K15<$AM$5),K15-AM15,IF(AND(AM15<>AI14,AM15>=$AI$7,AM15<=$AM$5,K15>$AM$5,K15>AM15),$AM$5-AM15,IF(AND(K15>$AL$5,K15<$AN$5),K15-$AL$5,IF(AND(K15>$AI$7,K15<$AM$5),$AN$5-$AL$5+K15,IF(AND(OR(K15>$AL$5,H15>$AO$5),AM15>=$AI$7,AM15<$AM$5,K15>$AM$5),(1+$AM$5-$AL$5)-AG15,0)))))))) -> 0
C16: =IF(Funcionários!C15=0,"",Funcionários!C15) | D16: =IF(D15=7,1,D15+1) -> 2 | E16: =IF(DAY(DATE('P Gerais'!$D$6,VLOOKUP($E$7,$W$7:$X$18,2,0),E15+1))>DAY(EOMONTH(DATE('P Gerais'!$D$6,VLOOKUP($E$7,$W$7:$X$18,2,0),E15),0)),DAY(DATE('P Gerais'!$D$6,VLOOKUP($E$7,$W$7:$X$18,2,0)+1,1)),DAY(DATE('P Gerais'!$D$6,VLOOKUP($E$7,$W$7:$X$18,2,0),E15+1))) -> 9 | F16: =VLOOKUP(D16,$AE$8:$AF$14,2,FALSE) -> Seg | M16: =IF(AND(H16=K16,H16<>0),$M$6-IF(J16<I16,$AJ$7+J16-I16,J16-I16),IF(H16>K16,(K16+1-H16)-IF(J16<I16,$AJ$7+J16-I16,J16-I16),(K16-H16)-IF(J16<I16,$AJ$7+J16-I16,J16-I16))) -> 0 | O16: =IF(OR(G16=0,G16="Férias",G16="Falta Justificada",G16="Feriado",G16="Folga (DSR)"),0,IF(G16="Falta Injustificada",HLOOKUP($F16,Jornada!$X$7:$AD$37,VLOOKUP(INDIRECT($C$5),Jornada!$C$8:$W$37,21,0),0),IF(HLOOKUP($F16,Jornada!$X$7:$AD$37,VLOOKUP(INDIRECT($C$5),Jornada!$C$8:$W$37,21,0),0)-M16>0,HLOOKUP($F16,Jornada!$X$7:$AD$37,VLOOKUP(INDIRECT($C$5),Jornada!$C$8:$W$37,21,0),0)-M16,0))) -> 0 | P16: =IF(HLOOKUP($F16,Jornada!$X$7:$AD$37,VLOOKUP(INDIRECT($C$5),Jornada!$C$8:$W$37,21,0),0)-M16<0,ABS(HLOOKUP($F16,Jornada!$X$7:$AD$37,VLOOKUP(INDIRECT($C$5),Jornada!$C$8:$W$37,21,0),0)-M16),0) -> 0 | Q16: =IF(G16="Normal",P16,IF(G16=0,0,IF(OR(G16="Feriado",G16="Férias"),IF(H16>K16,(K16+1-H16)-IF(J16<I16,$AJ$7+J16-I16,J16-I16),(K16-H16)-IF(J16<I16,$AJ$7+J16-I16,J16-I16)),IF(G16="Folga (DSR)",IF(H16>K16,(K16+1-H16)-IF(J16<I16,$AJ$7+J16-I16,J16-I16),(K16-H16)-IF(J16<I16,$AJ$7+J16-I16,J16-I16)),IF(G16="Falta Justificada",IF(H16>K16,(K16+1-H16)-IF(J16<I16,$AJ$7+J16-I16,J16-I16),(K16-H16)-IF(J16<I16,$AJ$7+J16-I16,J16-I16)),0))))) -> 0 | R16: =IF(Q16>$R$7,1,0) -> 0 | S16: Total de horas extras | U16: =SUM(Q8:Q38) -> 0 | W16: Outubro | X16: 10 | AB16: =AB15+1 -> 9 | AC16: =WEEKDAY(AB16) -> 2 | AG16: =IF(J16<I16,$AJ$7+J16-I16,J16-I16) -> 0 | AH16: =IF(HLOOKUP($F16,Jornada!$X$7:$AD$37,VLOOKUP(INDIRECT($C$5),Jornada!$C$8:$W$37,21,0),0)=0,0,VLOOKUP(INDIRECT($C$5),Jornada!$C$8:$H$37,4,0)) -> 0 | AI16: =IF(AND(I16=0,J16=0,OR(H16<>0,K16<>0),HLOOKUP($F16,Jornada!$X$7:$AD$37,VLOOKUP(INDIRECT($C$5),Jornada!$C$8:$W$37,21,0),0)>$AK$5,M16>$AK$5),VLOOKUP(INDIRECT($C$5),Jornada!$C$8:$H$37,6,0),IF(AG16>VLOOKUP(INDIRECT($C$5),Jornada!$C$8:$H$37,6,0),IF(VLOOKUP(INDIRECT($C$5),Jornada!$C$8:$H$37,6,0)<AG16,0,ABS(VLOOKUP(INDIRECT($C$5),Jornada!$C$8:$H$37,6,0))-AG16),0)) -> 0 | AJ16: =($AJ$7-K16)+H16 -> 1 | AK16: =IF(AJ16<$AK$7,$AK$7-AJ16,$AI$7) -> 0 | AL16: =HLOOKUP($F16,Jornada!$I$5:$V$37,VLOOKUP(INDIRECT($C$5),Jornada!$C$8:$W$37,21,0)+2,0) -> 0 | AM16: =HLOOKUP($F16,Jornada!$I$4:$V$37,VLOOKUP(INDIRECT($C$5),Jornada!$C$8:$W$37,21,0)+3,0) -> 0 | AN16: =IF(AND(AL16>=$AL$5,AL16<$AN$5,H16>=$AL$5,H16<AL16),AL16-H16,IF(AND(AL16>$AI$7,AL16<=$AM$5,H16>=$AL$5,H16<=$AN$5),$AN$5-H16+AL16,IF(AND(AL16>=$AI$7,AL16<=$AM$5,H16>=$AI$7,H16<=$AM$5,H16<AL16),H16-AL16,0))) -> 0 | AO16: =IF(AP16>Q16,0,AP16) -> 0 | AP16: =IF(Q16=0,0,IF(AND(AM16>=$AL$5,AM16<$AN$5,K16>=$AL$5,K16<$AM$5,K16>AM16),K16-AM16,IF(AND(AM16>=$AL$5,AM16<$AN$5,K16<$AN$5,K16>AM16),K16-$AL$5,IF(AND(AM16>=$AI$7,AM16<$AM$5,K16<$AM$5),K16-AM16,IF(AND(AM16<>AI15,AM16>=$AI$7,AM16<=$AM$5,K16>$AM$5,K16>AM16),$AM$5-AM16,IF(AND(K16>$AL$5,K16<$AN$5),K16-$AL$5,IF(AND(K16>$AI$7,K16<$AM$5),$AN$5-$AL$5+K16,IF(AND(OR(K16>$AL$5,H16>$AO$5),AM16>=$AI$7,AM16<$AM$5,K16>$AM$5),(1+$AM$5-$AL$5)-AG16,0)))))))) -> 0
C17: =IF(Funcionários!C16=0,"",Funcionários!C16) | D17: =IF(D16=7,1,D16+1) -> 3 | E17: =IF(DAY(DATE('P Gerais'!$D$6,VLOOKUP($E$7,$W$7:$X$18,2,0),E16+1))>DAY(EOMONTH(DATE('P Gerais'!$D$6,VLOOKUP($E$7,$W$7:$X$18,2,0),E16),0)),DAY(DATE('P Gerais'!$D$6,VLOOKUP($E$7,$W$7:$X$18,2,0)+1,1)),DAY(DATE('P Gerais'!$D$6,VLOOKUP($E$7,$W$7:$X$18,2,0),E16+1))) -> 10 | F17: =VLOOKUP(D17,$AE$8:$AF$14,2,FALSE) -> Ter | M17: =IF(AND(H17=K17,H17<>0),$M$6-IF(J17<I17,$AJ$7+J17-I17,J17-I17),IF(H17>K17,(K17+1-H17)-IF(J17<I17,$AJ$7+J17-I17,J17-I17),(K17-H17)-IF(J17<I17,$AJ$7+J17-I17,J17-I17))) -> 0 | O17: =IF(OR(G17=0,G17="Férias",G17="Falta Justificada",G17="Feriado",G17="Folga (DSR)"),0,IF(G17="Falta Injustificada",HLOOKUP($F17,Jornada!$X$7:$AD$37,VLOOKUP(INDIRECT($C$5),Jornada!$C$8:$W$37,21,0),0),IF(HLOOKUP($F17,Jornada!$X$7:$AD$37,VLOOKUP(INDIRECT($C$5),Jornada!$C$8:$W$37,21,0),0)-M17>0,HLOOKUP($F17,Jornada!$X$7:$AD$37,VLOOKUP(INDIRECT($C$5),Jornada!$C$8:$W$37,21,0),0)-M17,0))) -> 0 | P17: =IF(HLOOKUP($F17,Jornada!$X$7:$AD$37,VLOOKUP(INDIRECT($C$5),Jornada!$C$8:$W$37,21,0),0)-M17<0,ABS(HLOOKUP($F17,Jornada!$X$7:$AD$37,VLOOKUP(INDIRECT($C$5),Jornada!$C$8:$W$37,21,0),0)-M17),0) -> 0 | Q17: =IF(G17="Normal",P17,IF(G17=0,0,IF(OR(G17="Feriado",G17="Férias"),IF(H17>K17,(K17+1-H17)-IF(J17<I17,$AJ$7+J17-I17,J17-I17),(K17-H17)-IF(J17<I17,$AJ$7+J17-I17,J17-I17)),IF(G17="Folga (DSR)",IF(H17>K17,(K17+1-H17)-IF(J17<I17,$AJ$7+J17-I17,J17-I17),(K17-H17)-IF(J17<I17,$AJ$7+J17-I17,J17-I17)),IF(G17="Falta Justificada",IF(H17>K17,(K17+1-H17)-IF(J17<I17,$AJ$7+J17-I17,J17-I17),(K17-H17)-IF(J17<I17,$AJ$7+J17-I17,J17-I17)),0))))) -> 0 | R17: =IF(Q17>$R$7,1,0) -> 0 | W17: Novembro | X17: 11 | AB17: =AB16+1 -> 10 | AC17: =WEEKDAY(AB17) -> 3 | AG17: =IF(J17<I17,$AJ$7+J17-I17,J17-I17) -> 0 | AH17: =IF(HLOOKUP($F17,Jornada!$X$7:$AD$37,VLOOKUP(INDIRECT($C$5),Jornada!$C$8:$W$37,21,0),0)=0,0,VLOOKUP(INDIRECT($C$5),Jornada!$C$8:$H$37,4,0)) -> 0 | AI17: =IF(AND(I17=0,J17=0,OR(H17<>0,K17<>0),HLOOKUP($F17,Jornada!$X$7:$AD$37,VLOOKUP(INDIRECT($C$5),Jornada!$C$8:$W$37,21,0),0)>$AK$5,M17>$AK$5),VLOOKUP(INDIRECT($C$5),Jornada!$C$8:$H$37,6,0),IF(AG17>VLOOKUP(INDIRECT($C$5),Jornada!$C$8:$H$37,6,0),IF(VLOOKUP(INDIRECT($C$5),Jornada!$C$8:$H$37,6,0)<AG17,0,ABS(VLOOKUP(INDIRECT($C$5),Jornada!$C$8:$H$37,6,0))-AG17),0)) -> 0 | AJ17: =($AJ$7-K17)+H17 -> 1 | AK17: =IF(AJ17<$AK$7,$AK$7-AJ17,$AI$7) -> 0 | AL17: =HLOOKUP($F17,Jornada!$I$5:$V$37,VLOOKUP(INDIRECT($C$5),Jornada!$C$8:$W$37,21,0)+2,0) -> 0 | AM17: =HLOOKUP($F17,Jornada!$I$4:$V$37,VLOOKUP(INDIRECT($C$5),Jornada!$C$8:$W$37,21,0)+3,0) -> 0 | AN17: =IF(AND(AL17>=$AL$5,AL17<$AN$5,H17>=$AL$5,H17<AL17),AL17-H17,IF(AND(AL17>$AI$7,AL17<=$AM$5,H17>=$AL$5,H17<=$AN$5),$AN$5-H17+AL17,IF(AND(AL17>=$AI$7,AL17<=$AM$5,H17>=$AI$7,H17<=$AM$5,H17<AL17),H17-AL17,0))) -> 0 | AO17: =IF(AP17>Q17,0,AP17) -> 0 | AP17: =IF(Q17=0,0,IF(AND(AM17>=$AL$5,AM17<$AN$5,K17>=$AL$5,K17<$AM$5,K17>AM17),K17-AM17,IF(AND(AM17>=$AL$5,AM17<$AN$5,K17<$AN$5,K17>AM17),K17-$AL$5,IF(AND(AM17>=$AI$7,AM17<$AM$5,K17<$AM$5),K17-AM17,IF(AND(AM17<>AI16,AM17>=$AI$7,AM17<=$AM$5,K17>$AM$5,K17>AM17),$AM$5-AM17,IF(AND(K17>$AL$5,K17<$AN$5),K17-$AL$5,IF(AND(K17>$AI$7,K17<$AM$5),$AN$5-$AL$5+K17,IF(AND(OR(K17>$AL$5,H17>$AO$5),AM17>=$AI$7,AM17<$AM$5,K17>$AM$5),(1+$AM$5-$AL$5)-AG17,0)))))))) -> 0
C18: =IF(Funcionários!C17=0,"",Funcionários!C17) | D18: =IF(D17=7,1,D17+1) -> 4 | E18: =IF(DAY(DATE('P Gerais'!$D$6,VLOOKUP($E$7,$W$7:$X$18,2,0),E17+1))>DAY(EOMONTH(DATE('P Gerais'!$D$6,VLOOKUP($E$7,$W$7:$X$18,2,0),E17),0)),DAY(DATE('P Gerais'!$D$6,VLOOKUP($E$7,$W$7:$X$18,2,0)+1,1)),DAY(DATE('P Gerais'!$D$6,VLOOKUP($E$7,$W$7:$X$18,2,0),E17+1))) -> 11 | F18: =VLOOKUP(D18,$AE$8:$AF$14,2,FALSE) -> Qua | M18: =IF(AND(H18=K18,H18<>0),$M$6-IF(J18<I18,$AJ$7+J18-I18,J18-I18),IF(H18>K18,(K18+1-H18)-IF(J18<I18,$AJ$7+J18-I18,J18-I18),(K18-H18)-IF(J18<I18,$AJ$7+J18-I18,J18-I18))) -> 0 | O18: =IF(OR(G18=0,G18="Férias",G18="Falta Justificada",G18="Feriado",G18="Folga (DSR)"),0,IF(G18="Falta Injustificada",HLOOKUP($F18,Jornada!$X$7:$AD$37,VLOOKUP(INDIRECT($C$5),Jornada!$C$8:$W$37,21,0),0),IF(HLOOKUP($F18,Jornada!$X$7:$AD$37,VLOOKUP(INDIRECT($C$5),Jornada!$C$8:$W$37,21,0),0)-M18>0,HLOOKUP($F18,Jornada!$X$7:$AD$37,VLOOKUP(INDIRECT($C$5),Jornada!$C$8:$W$37,21,0),0)-M18,0))) -> 0 | P18: =IF(HLOOKUP($F18,Jornada!$X$7:$AD$37,VLOOKUP(INDIRECT($C$5),Jornada!$C$8:$W$37,21,0),0)-M18<0,ABS(HLOOKUP($F18,Jornada!$X$7:$AD$37,VLOOKUP(INDIRECT($C$5),Jornada!$C$8:$W$37,21,0),0)-M18),0) -> 0 | Q18: =IF(G18="Normal",P18,IF(G18=0,0,IF(OR(G18="Feriado",G18="Férias"),IF(H18>K18,(K18+1-H18)-IF(J18<I18,$AJ$7+J18-I18,J18-I18),(K18-H18)-IF(J18<I18,$AJ$7+J18-I18,J18-I18)),IF(G18="Folga (DSR)",IF(H18>K18,(K18+1-H18)-IF(J18<I18,$AJ$7+J18-I18,J18-I18),(K18-H18)-IF(J18<I18,$AJ$7+J18-I18,J18-I18)),IF(G18="Falta Justificada",IF(H18>K18,(K18+1-H18)-IF(J18<I18,$AJ$7+J18-I18,J18-I18),(K18-H18)-IF(J18<I18,$AJ$7+J18-I18,J18-I18)),0))))) -> 0 | R18: =IF(Q18>$R$7,1,0) -> 0 | S18: Total de hora extra a pagar | U18: =F54 -> 0 | W18: Dezembro | X18: 12 | AB18: =AB17+1 -> 11 | AC18: =WEEKDAY(AB18) -> 4 | AG18: =IF(J18<I18,$AJ$7+J18-I18,J18-I18) -> 0 | AH18: =IF(HLOOKUP($F18,Jornada!$X$7:$AD$37,VLOOKUP(INDIRECT($C$5),Jornada!$C$8:$W$37,21,0),0)=0,0,VLOOKUP(INDIRECT($C$5),Jornada!$C$8:$H$37,4,0)) -> 0 | AI18: =IF(AND(I18=0,J18=0,OR(H18<>0,K18<>0),HLOOKUP($F18,Jornada!$X$7:$AD$37,VLOOKUP(INDIRECT($C$5),Jornada!$C$8:$W$37,21,0),0)>$AK$5,M18>$AK$5),VLOOKUP(INDIRECT($C$5),Jornada!$C$8:$H$37,6,0),IF(AG18>VLOOKUP(INDIRECT($C$5),Jornada!$C$8:$H$37,6,0),IF(VLOOKUP(INDIRECT($C$5),Jornada!$C$8:$H$37,6,0)<AG18,0,ABS(VLOOKUP(INDIRECT($C$5),Jornada!$C$8:$H$37,6,0))-AG18),0)) -> 0 | AJ18: =($AJ$7-K18)+H18 -> 1 | AK18: =IF(AJ18<$AK$7,$AK$7-AJ18,$AI$7) -> 0 | AL18: =HLOOKUP($F18,Jornada!$I$5:$V$37,VLOOKUP(INDIRECT($C$5),Jornada!$C$8:$W$37,21,0)+2,0) -> 0 | AM18: =HLOOKUP($F18,Jornada!$I$4:$V$37,VLOOKUP(INDIRECT($C$5),Jornada!$C$8:$W$37,21,0)+3,0) -> 0 | AN18: =IF(AND(AL18>=$AL$5,AL18<$AN$5,H18>=$AL$5,H18<AL18),AL18-H18,IF(AND(AL18>$AI$7,AL18<=$AM$5,H18>=$AL$5,H18<=$AN$5),$AN$5-H18+AL18,IF(AND(AL18>=$AI$7,AL18<=$AM$5,H18>=$AI$7,H18<=$AM$5,H18<AL18),H18-AL18,0))) -> 0 | AO18: =IF(AP18>Q18,0,AP18) -> 0 | AP18: =IF(Q18=0,0,IF(AND(AM18>=$AL$5,AM18<$AN$5,K18>=$AL$5,K18<$AM$5,K18>AM18),K18-AM18,IF(AND(AM18>=$AL$5,AM18<$AN$5,K18<$AN$5,K18>AM18),K18-$AL$5,IF(AND(AM18>=$AI$7,AM18<$AM$5,K18<$AM$5),K18-AM18,IF(AND(AM18<>AI17,AM18>=$AI$7,AM18<=$AM$5,K18>$AM$5,K18>AM18),$AM$5-AM18,IF(AND(K18>$AL$5,K18<$AN$5),K18-$AL$5,IF(AND(K18>$AI$7,K18<$AM$5),$AN$5-$AL$5+K18,IF(AND(OR(K18>$AL$5,H18>$AO$5),AM18>=$AI$7,AM18<$AM$5,K18>$AM$5),(1+$AM$5-$AL$5)-AG18,0)))))))) -> 0
C19: =IF(Funcionários!C18=0,"",Funcionários!C18) | D19: =IF(D18=7,1,D18+1) -> 5 | E19: =IF(DAY(DATE('P Gerais'!$D$6,VLOOKUP($E$7,$W$7:$X$18,2,0),E18+1))>DAY(EOMONTH(DATE('P Gerais'!$D$6,VLOOKUP($E$7,$W$7:$X$18,2,0),E18),0)),DAY(DATE('P Gerais'!$D$6,VLOOKUP($E$7,$W$7:$X$18,2,0)+1,1)),DAY(DATE('P Gerais'!$D$6,VLOOKUP($E$7,$W$7:$X$18,2,0),E18+1))) -> 12 | F19: =VLOOKUP(D19,$AE$8:$AF$14,2,FALSE) -> Qui | M19: =IF(AND(H19=K19,H19<>0),$M$6-IF(J19<I19,$AJ$7+J19-I19,J19-I19),IF(H19>K19,(K19+1-H19)-IF(J19<I19,$AJ$7+J19-I19,J19-I19),(K19-H19)-IF(J19<I19,$AJ$7+J19-I19,J19-I19))) -> 0 | O19: =IF(OR(G19=0,G19="Férias",G19="Falta Justificada",G19="Feriado",G19="Folga (DSR)"),0,IF(G19="Falta Injustificada",HLOOKUP($F19,Jornada!$X$7:$AD$37,VLOOKUP(INDIRECT($C$5),Jornada!$C$8:$W$37,21,0),0),IF(HLOOKUP($F19,Jornada!$X$7:$AD$37,VLOOKUP(INDIRECT($C$5),Jornada!$C$8:$W$37,21,0),0)-M19>0,HLOOKUP($F19,Jornada!$X$7:$AD$37,VLOOKUP(INDIRECT($C$5),Jornada!$C$8:$W$37,21,0),0)-M19,0))) -> 0 | P19: =IF(HLOOKUP($F19,Jornada!$X$7:$AD$37,VLOOKUP(INDIRECT($C$5),Jornada!$C$8:$W$37,21,0),0)-M19<0,ABS(HLOOKUP($F19,Jornada!$X$7:$AD$37,VLOOKUP(INDIRECT($C$5),Jornada!$C$8:$W$37,21,0),0)-M19),0) -> 0 | Q19: =IF(G19="Normal",P19,IF(G19=0,0,IF(OR(G19="Feriado",G19="Férias"),IF(H19>K19,(K19+1-H19)-IF(J19<I19,$AJ$7+J19-I19,J19-I19),(K19-H19)-IF(J19<I19,$AJ$7+J19-I19,J19-I19)),IF(G19="Folga (DSR)",IF(H19>K19,(K19+1-H19)-IF(J19<I19,$AJ$7+J19-I19,J19-I19),(K19-H19)-IF(J19<I19,$AJ$7+J19-I19,J19-I19)),IF(G19="Falta Justificada",IF(H19>K19,(K19+1-H19)-IF(J19<I19,$AJ$7+J19-I19,J19-I19),(K19-H19)-IF(J19<I19,$AJ$7+J19-I19,J19-I19)),0))))) -> 0 | R19: =IF(Q19>$R$7,1,0) -> 0 | AB19: =AB18+1 -> 12 | AC19: =WEEKDAY(AB19) -> 5 | AG19: =IF(J19<I19,$AJ$7+J19-I19,J19-I19) -> 0 | AH19: =IF(HLOOKUP($F19,Jornada!$X$7:$AD$37,VLOOKUP(INDIRECT($C$5),Jornada!$C$8:$W$37,21,0),0)=0,0,VLOOKUP(INDIRECT($C$5),Jornada!$C$8:$H$37,4,0)) -> 0 | AI19: =IF(AND(I19=0,J19=0,OR(H19<>0,K19<>0),HLOOKUP($F19,Jornada!$X$7:$AD$37,VLOOKUP(INDIRECT($C$5),Jornada!$C$8:$W$37,21,0),0)>$AK$5,M19>$AK$5),VLOOKUP(INDIRECT($C$5),Jornada!$C$8:$H$37,6,0),IF(AG19>VLOOKUP(INDIRECT($C$5),Jornada!$C$8:$H$37,6,0),IF(VLOOKUP(INDIRECT($C$5),Jornada!$C$8:$H$37,6,0)<AG19,0,ABS(VLOOKUP(INDIRECT($C$5),Jornada!$C$8:$H$37,6,0))-AG19),0)) -> 0 | AJ19: =($AJ$7-K19)+H19 -> 1 | AK19: =IF(AJ19<$AK$7,$AK$7-AJ19,$AI$7) -> 0 | AL19: =HLOOKUP($F19,Jornada!$I$5:$V$37,VLOOKUP(INDIRECT($C$5),Jornada!$C$8:$W$37,21,0)+2,0) -> 0 | AM19: =HLOOKUP($F19,Jornada!$I$4:$V$37,VLOOKUP(INDIRECT($C$5),Jornada!$C$8:$W$37,21,0)+3,0) -> 0 | AN19: =IF(AND(AL19>=$AL$5,AL19<$AN$5,H19>=$AL$5,H19<AL19),AL19-H19,IF(AND(AL19>$AI$7,AL19<=$AM$5,H19>=$AL$5,H19<=$AN$5),$AN$5-H19+AL19,IF(AND(AL19>=$AI$7,AL19<=$AM$5,H19>=$AI$7,H19<=$AM$5,H19<AL19),H19-AL19,0))) -> 0 | AO19: =IF(AP19>Q19,0,AP19) -> 0 | AP19: =IF(Q19=0,0,IF(AND(AM19>=$AL$5,AM19<$AN$5,K19>=$AL$5,K19<$AM$5,K19>AM19),K19-AM19,IF(AND(AM19>=$AL$5,AM19<$AN$5,K19<$AN$5,K19>AM19),K19-$AL$5,IF(AND(AM19>=$AI$7,AM19<$AM$5,K19<$AM$5),K19-AM19,IF(AND(AM19<>AI18,AM19>=$AI$7,AM19<=$AM$5,K19>$AM$5,K19>AM19),$AM$5-AM19,IF(AND(K19>$AL$5,K19<$AN$5),K19-$AL$5,IF(AND(K19>$AI$7,K19<$AM$5),$AN$5-$AL$5+K19,IF(AND(OR(K19>$AL$5,H19>$AO$5),AM19>=$AI$7,AM19<$AM$5,K19>$AM$5),(1+$AM$5-$AL$5)-AG19,0)))))))) -> 0
C20: =IF(Funcionários!C19=0,"",Funcionários!C19) | D20: =IF(D19=7,1,D19+1) -> 6 | E20: =IF(DAY(DATE('P Gerais'!$D$6,VLOOKUP($E$7,$W$7:$X$18,2,0),E19+1))>DAY(EOMONTH(DATE('P Gerais'!$D$6,VLOOKUP($E$7,$W$7:$X$18,2,0),E19),0)),DAY(DATE('P Gerais'!$D$6,VLOOKUP($E$7,$W$7:$X$18,2,0)+1,1)),DAY(DATE('P Gerais'!$D$6,VLOOKUP($E$7,$W$7:$X$18,2,0),E19+1))) -> 13 | F20: =VLOOKUP(D20,$AE$8:$AF$14,2,FALSE) -> Sex | M20: =IF(AND(H20=K20,H20<>0),$M$6-IF(J20<I20,$AJ$7+J20-I20,J20-I20),IF(H20>K20,(K20+1-H20)-IF(J20<I20,$AJ$7+J20-I20,J20-I20),(K20-H20)-IF(J20<I20,$AJ$7+J20-I20,J20-I20))) -> 0 | O20: =IF(OR(G20=0,G20="Férias",G20="Falta Justificada",G20="Feriado",G20="Folga (DSR)"),0,IF(G20="Falta Injustificada",HLOOKUP($F20,Jornada!$X$7:$AD$37,VLOOKUP(INDIRECT($C$5),Jornada!$C$8:$W$37,21,0),0),IF(HLOOKUP($F20,Jornada!$X$7:$AD$37,VLOOKUP(INDIRECT($C$5),Jornada!$C$8:$W$37,21,0),0)-M20>0,HLOOKUP($F20,Jornada!$X$7:$AD$37,VLOOKUP(INDIRECT($C$5),Jornada!$C$8:$W$37,21,0),0)-M20,0))) -> 0 | P20: =IF(HLOOKUP($F20,Jornada!$X$7:$AD$37,VLOOKUP(INDIRECT($C$5),Jornada!$C$8:$W$37,21,0),0)-M20<0,ABS(HLOOKUP($F20,Jornada!$X$7:$AD$37,VLOOKUP(INDIRECT($C$5),Jornada!$C$8:$W$37,21,0),0)-M20),0) -> 0 | Q20: =IF(G20="Normal",P20,IF(G20=0,0,IF(OR(G20="Feriado",G20="Férias"),IF(H20>K20,(K20+1-H20)-IF(J20<I20,$AJ$7+J20-I20,J20-I20),(K20-H20)-IF(J20<I20,$AJ$7+J20-I20,J20-I20)),IF(G20="Folga (DSR)",IF(H20>K20,(K20+1-H20)-IF(J20<I20,$AJ$7+J20-I20,J20-I20),(K20-H20)-IF(J20<I20,$AJ$7+J20-I20,J20-I20)),IF(G20="Falta Justificada",IF(H20>K20,(K20+1-H20)-IF(J20<I20,$AJ$7+J20-I20,J20-I20),(K20-H20)-IF(J20<I20,$AJ$7+J20-I20,J20-I20)),0))))) -> 0 | R20: =IF(Q20>$R$7,1,0) -> 0 | AB20: =AB19+1 -> 13 | AC20: =WEEKDAY(AB20) -> 6 | AG20: =IF(J20<I20,$AJ$7+J20-I20,J20-I20) -> 0 | AH20: =IF(HLOOKUP($F20,Jornada!$X$7:$AD$37,VLOOKUP(INDIRECT($C$5),Jornada!$C$8:$W$37,21,0),0)=0,0,VLOOKUP(INDIRECT($C$5),Jornada!$C$8:$H$37,4,0)) -> 0 | AI20: =IF(AND(I20=0,J20=0,OR(H20<>0,K20<>0),HLOOKUP($F20,Jornada!$X$7:$AD$37,VLOOKUP(INDIRECT($C$5),Jornada!$C$8:$W$37,21,0),0)>$AK$5,M20>$AK$5),VLOOKUP(INDIRECT($C$5),Jornada!$C$8:$H$37,6,0),IF(AG20>VLOOKUP(INDIRECT($C$5),Jornada!$C$8:$H$37,6,0),IF(VLOOKUP(INDIRECT($C$5),Jornada!$C$8:$H$37,6,0)<AG20,0,ABS(VLOOKUP(INDIRECT($C$5),Jornada!$C$8:$H$37,6,0))-AG20),0)) -> 0 | AJ20: =($AJ$7-K20)+H20 -> 1 | AK20: =IF(AJ20<$AK$7,$AK$7-AJ20,$AI$7) -> 0 | AL20: =HLOOKUP($F20,Jornada!$I$5:$V$37,VLOOKUP(INDIRECT($C$5),Jornada!$C$8:$W$37,21,0)+2,0) -> 0 | AM20: =HLOOKUP($F20,Jornada!$I$4:$V$37,VLOOKUP(INDIRECT($C$5),Jornada!$C$8:$W$37,21,0)+3,0) -> 0 | AN20: =IF(AND(AL20>=$AL$5,AL20<$AN$5,H20>=$AL$5,H20<AL20),AL20-H20,IF(AND(AL20>$AI$7,AL20<=$AM$5,H20>=$AL$5,H20<=$AN$5),$AN$5-H20+AL20,IF(AND(AL20>=$AI$7,AL20<=$AM$5,H20>=$AI$7,H20<=$AM$5,H20<AL20),H20-AL20,0))) -> 0 | AO20: =IF(AP20>Q20,0,AP20) -> 0 | AP20: =IF(Q20=0,0,IF(AND(AM20>=$AL$5,AM20<$AN$5,K20>=$AL$5,K20<$AM$5,K20>AM20),K20-AM20,IF(AND(AM20>=$AL$5,AM20<$AN$5,K20<$AN$5,K20>AM20),K20-$AL$5,IF(AND(AM20>=$AI$7,AM20<$AM$5,K20<$AM$5),K20-AM20,IF(AND(AM20<>AI19,AM20>=$AI$7,AM20<=$AM$5,K20>$AM$5,K20>AM20),$AM$5-AM20,IF(AND(K20>$AL$5,K20<$AN$5),K20-$AL$5,IF(AND(K20>$AI$7,K20<$AM$5),$AN$5-$AL$5+K20,IF(AND(OR(K20>$AL$5,H20>$AO$5),AM20>=$AI$7,AM20<$AM$5,K20>$AM$5),(1+$AM$5-$AL$5)-AG20,0)))))))) -> 0
C21: =IF(Funcionários!C20=0,"",Funcionários!C20) | D21: =IF(D20=7,1,D20+1) -> 7 | E21: =IF(DAY(DATE('P Gerais'!$D$6,VLOOKUP($E$7,$W$7:$X$18,2,0),E20+1))>DAY(EOMONTH(DATE('P Gerais'!$D$6,VLOOKUP($E$7,$W$7:$X$18,2,0),E20),0)),DAY(DATE('P Gerais'!$D$6,VLOOKUP($E$7,$W$7:$X$18,2,0)+1,1)),DAY(DATE('P Gerais'!$D$6,VLOOKUP($E$7,$W$7:$X$18,2,0),E20+1))) -> 14 | F21: =VLOOKUP(D21,$AE$8:$AF$14,2,FALSE) -> Sáb | M21: =IF(AND(H21=K21,H21<>0),$M$6-IF(J21<I21,$AJ$7+J21-I21,J21-I21),IF(H21>K21,(K21+1-H21)-IF(J21<I21,$AJ$7+J21-I21,J21-I21),(K21-H21)-IF(J21<I21,$AJ$7+J21-I21,J21-I21))) -> 0 | O21: =IF(OR(G21=0,G21="Férias",G21="Falta Justificada",G21="Feriado",G21="Folga (DSR)"),0,IF(G21="Falta Injustificada",HLOOKUP($F21,Jornada!$X$7:$AD$37,VLOOKUP(INDIRECT($C$5),Jornada!$C$8:$W$37,21,0),0),IF(HLOOKUP($F21,Jornada!$X$7:$AD$37,VLOOKUP(INDIRECT($C$5),Jornada!$C$8:$W$37,21,0),0)-M21>0,HLOOKUP($F21,Jornada!$X$7:$AD$37,VLOOKUP(INDIRECT($C$5),Jornada!$C$8:$W$37,21,0),0)-M21,0))) -> 0 | P21: =IF(HLOOKUP($F21,Jornada!$X$7:$AD$37,VLOOKUP(INDIRECT($C$5),Jornada!$C$8:$W$37,21,0),0)-M21<0,ABS(HLOOKUP($F21,Jornada!$X$7:$AD$37,VLOOKUP(INDIRECT($C$5),Jornada!$C$8:$W$37,21,0),0)-M21),0) -> 0 | Q21: =IF(G21="Normal",P21,IF(G21=0,0,IF(OR(G21="Feriado",G21="Férias"),IF(H21>K21,(K21+1-H21)-IF(J21<I21,$AJ$7+J21-I21,J21-I21),(K21-H21)-IF(J21<I21,$AJ$7+J21-I21,J21-I21)),IF(G21="Folga (DSR)",IF(H21>K21,(K21+1-H21)-IF(J21<I21,$AJ$7+J21-I21,J21-I21),(K21-H21)-IF(J21<I21,$AJ$7+J21-I21,J21-I21)),IF(G21="Falta Justificada",IF(H21>K21,(K21+1-H21)-IF(J21<I21,$AJ$7+J21-I21,J21-I21),(K21-H21)-IF(J21<I21,$AJ$7+J21-I21,J21-I21)),0))))) -> 0 | R21: =IF(Q21>$R$7,1,0) -> 0 | AB21: =AB20+1 -> 14 | AC21: =WEEKDAY(AB21) -> 7 | AG21: =IF(J21<I21,$AJ$7+J21-I21,J21-I21) -> 0 | AH21: =IF(HLOOKUP($F21,Jornada!$X$7:$AD$37,VLOOKUP(INDIRECT($C$5),Jornada!$C$8:$W$37,21,0),0)=0,0,VLOOKUP(INDIRECT($C$5),Jornada!$C$8:$H$37,4,0)) -> 0 | AI21: =IF(AND(I21=0,J21=0,OR(H21<>0,K21<>0),HLOOKUP($F21,Jornada!$X$7:$AD$37,VLOOKUP(INDIRECT($C$5),Jornada!$C$8:$W$37,21,0),0)>$AK$5,M21>$AK$5),VLOOKUP(INDIRECT($C$5),Jornada!$C$8:$H$37,6,0),IF(AG21>VLOOKUP(INDIRECT($C$5),Jornada!$C$8:$H$37,6,0),IF(VLOOKUP(INDIRECT($C$5),Jornada!$C$8:$H$37,6,0)<AG21,0,ABS(VLOOKUP(INDIRECT($C$5),Jornada!$C$8:$H$37,6,0))-AG21),0)) -> 0 | AJ21: =($AJ$7-K21)+H21 -> 1 | AK21: =IF(AJ21<$AK$7,$AK$7-AJ21,$AI$7) -> 0 | AL21: =HLOOKUP($F21,Jornada!$I$5:$V$37,VLOOKUP(INDIRECT($C$5),Jornada!$C$8:$W$37,21,0)+2,0) -> 0 | AM21: =HLOOKUP($F21,Jornada!$I$4:$V$37,VLOOKUP(INDIRECT($C$5),Jornada!$C$8:$W$37,21,0)+3,0) -> 0 | AN21: =IF(AND(AL21>=$AL$5,AL21<$AN$5,H21>=$AL$5,H21<AL21),AL21-H21,IF(AND(AL21>$AI$7,AL21<=$AM$5,H21>=$AL$5,H21<=$AN$5),$AN$5-H21+AL21,IF(AND(AL21>=$AI$7,AL21<=$AM$5,H21>=$AI$7,H21<=$AM$5,H21<AL21),H21-AL21,0))) -> 0 | AO21: =IF(AP21>Q21,0,AP21) -> 0 | AP21: =IF(Q21=0,0,IF(AND(AM21>=$AL$5,AM21<$AN$5,K21>=$AL$5,K21<$AM$5,K21>AM21),K21-AM21,IF(AND(AM21>=$AL$5,AM21<$AN$5,K21<$AN$5,K21>AM21),K21-$AL$5,IF(AND(AM21>=$AI$7,AM21<$AM$5,K21<$AM$5),K21-AM21,IF(AND(AM21<>AI20,AM21>=$AI$7,AM21<=$AM$5,K21>$AM$5,K21>AM21),$AM$5-AM21,IF(AND(K21>$AL$5,K21<$AN$5),K21-$AL$5,IF(AND(K21>$AI$7,K21<$AM$5),$AN$5-$AL$5+K21,IF(AND(OR(K21>$AL$5,H21>$AO$5),AM21>=$AI$7,AM21<$AM$5,K21>$AM$5),(1+$AM$5-$AL$5)-AG21,0)))))))) -> 0
C22: =IF(Funcionários!C21=0,"",Funcionários!C21) | D22: =IF(D21=7,1,D21+1) -> 1 | E22: =IF(DAY(DATE('P Gerais'!$D$6,VLOOKUP($E$7,$W$7:$X$18,2,0),E21+1))>DAY(EOMONTH(DATE('P Gerais'!$D$6,VLOOKUP($E$7,$W$7:$X$18,2,0),E21),0)),DAY(DATE('P Gerais'!$D$6,VLOOKUP($E$7,$W$7:$X$18,2,0)+1,1)),DAY(DATE('P Gerais'!$D$6,VLOOKUP($E$7,$W$7:$X$18,2,0),E21+1))) -> 15 | F22: =VLOOKUP(D22,$AE$8:$AF$14,2,FALSE) -> Dom | M22: =IF(AND(H22=K22,H22<>0),$M$6-IF(J22<I22,$AJ$7+J22-I22,J22-I22),IF(H22>K22,(K22+1-H22)-IF(J22<I22,$AJ$7+J22-I22,J22-I22),(K22-H22)-IF(J22<I22,$AJ$7+J22-I22,J22-I22))) -> 0 | O22: =IF(OR(G22=0,G22="Férias",G22="Falta Justificada",G22="Feriado",G22="Folga (DSR)"),0,IF(G22="Falta Injustificada",HLOOKUP($F22,Jornada!$X$7:$AD$37,VLOOKUP(INDIRECT($C$5),Jornada!$C$8:$W$37,21,0),0),IF(HLOOKUP($F22,Jornada!$X$7:$AD$37,VLOOKUP(INDIRECT($C$5),Jornada!$C$8:$W$37,21,0),0)-M22>0,HLOOKUP($F22,Jornada!$X$7:$AD$37,VLOOKUP(INDIRECT($C$5),Jornada!$C$8:$W$37,21,0),0)-M22,0))) -> 0 | P22: =IF(HLOOKUP($F22,Jornada!$X$7:$AD$37,VLOOKUP(INDIRECT($C$5),Jornada!$C$8:$W$37,21,0),0)-M22<0,ABS(HLOOKUP($F22,Jornada!$X$7:$AD$37,VLOOKUP(INDIRECT($C$5),Jornada!$C$8:$W$37,21,0),0)-M22),0) -> 0 | Q22: =IF(G22="Normal",P22,IF(G22=0,0,IF(OR(G22="Feriado",G22="Férias"),IF(H22>K22,(K22+1-H22)-IF(J22<I22,$AJ$7+J22-I22,J22-I22),(K22-H22)-IF(J22<I22,$AJ$7+J22-I22,J22-I22)),IF(G22="Folga (DSR)",IF(H22>K22,(K22+1-H22)-IF(J22<I22,$AJ$7+J22-I22,J22-I22),(K22-H22)-IF(J22<I22,$AJ$7+J22-I22,J22-I22)),IF(G22="Falta Justificada",IF(H22>K22,(K22+1-H22)-IF(J22<I22,$AJ$7+J22-I22,J22-I22),(K22-H22)-IF(J22<I22,$AJ$7+J22-I22,J22-I22)),0))))) -> 0 | R22: =IF(Q22>$R$7,1,0) -> 0 | S22: Horas Extras | AB22: =AB21+1 -> 15 | AC22: =WEEKDAY(AB22) -> 1 | AG22: =IF(J22<I22,$AJ$7+J22-I22,J22-I22) -> 0 | AH22: =IF(HLOOKUP($F22,Jornada!$X$7:$AD$37,VLOOKUP(INDIRECT($C$5),Jornada!$C$8:$W$37,21,0),0)=0,0,VLOOKUP(INDIRECT($C$5),Jornada!$C$8:$H$37,4,0)) -> 0 | AI22: =IF(AND(I22=0,J22=0,OR(H22<>0,K22<>0),HLOOKUP($F22,Jornada!$X$7:$AD$37,VLOOKUP(INDIRECT($C$5),Jornada!$C$8:$W$37,21,0),0)>$AK$5,M22>$AK$5),VLOOKUP(INDIRECT($C$5),Jornada!$C$8:$H$37,6,0),IF(AG22>VLOOKUP(INDIRECT($C$5),Jornada!$C$8:$H$37,6,0),IF(VLOOKUP(INDIRECT($C$5),Jornada!$C$8:$H$37,6,0)<AG22,0,ABS(VLOOKUP(INDIRECT($C$5),Jornada!$C$8:$H$37,6,0))-AG22),0)) -> 0 | AJ22: =($AJ$7-K22)+H22 -> 1 | AK22: =IF(AJ22<$AK$7,$AK$7-AJ22,$AI$7) -> 0 | AL22: =HLOOKUP($F22,Jornada!$I$5:$V$37,VLOOKUP(INDIRECT($C$5),Jornada!$C$8:$W$37,21,0)+2,0) -> 0 | AM22: =HLOOKUP($F22,Jornada!$I$4:$V$37,VLOOKUP(INDIRECT($C$5),Jornada!$C$8:$W$37,21,0)+3,0) -> 0 | AN22: =IF(AND(AL22>=$AL$5,AL22<$AN$5,H22>=$AL$5,H22<AL22),AL22-H22,IF(AND(AL22>$AI$7,AL22<=$AM$5,H22>=$AL$5,H22<=$AN$5),$AN$5-H22+AL22,IF(AND(AL22>=$AI$7,AL22<=$AM$5,H22>=$AI$7,H22<=$AM$5,H22<AL22),H22-AL22,0))) -> 0 | AO22: =IF(AP22>Q22,0,AP22) -> 0 | AP22: =IF(Q22=0,0,IF(AND(AM22>=$AL$5,AM22<$AN$5,K22>=$AL$5,K22<$AM$5,K22>AM22),K22-AM22,IF(AND(AM22>=$AL$5,AM22<$AN$5,K22<$AN$5,K22>AM22),K22-$AL$5,IF(AND(AM22>=$AI$7,AM22<$AM$5,K22<$AM$5),K22-AM22,IF(AND(AM22<>AI21,AM22>=$AI$7,AM22<=$AM$5,K22>$AM$5,K22>AM22),$AM$5-AM22,IF(AND(K22>$AL$5,K22<$AN$5),K22-$AL$5,IF(AND(K22>$AI$7,K22<$AM$5),$AN$5-$AL$5+K22,IF(AND(OR(K22>$AL$5,H22>$AO$5),AM22>=$AI$7,AM22<$AM$5,K22>$AM$5),(1+$AM$5-$AL$5)-AG22,0)))))))) -> 0
C23: =IF(Funcionários!C22=0,"",Funcionários!C22) | D23: =IF(D22=7,1,D22+1) -> 2 | E23: =IF(DAY(DATE('P Gerais'!$D$6,VLOOKUP($E$7,$W$7:$X$18,2,0),E22+1))>DAY(EOMONTH(DATE('P Gerais'!$D$6,VLOOKUP($E$7,$W$7:$X$18,2,0),E22),0)),DAY(DATE('P Gerais'!$D$6,VLOOKUP($E$7,$W$7:$X$18,2,0)+1,1)),DAY(DATE('P Gerais'!$D$6,VLOOKUP($E$7,$W$7:$X$18,2,0),E22+1))) -> 16 | F23: =VLOOKUP(D23,$AE$8:$AF$14,2,FALSE) -> Seg | M23: =IF(AND(H23=K23,H23<>0),$M$6-IF(J23<I23,$AJ$7+J23-I23,J23-I23),IF(H23>K23,(K23+1-H23)-IF(J23<I23,$AJ$7+J23-I23,J23-I23),(K23-H23)-IF(J23<I23,$AJ$7+J23-I23,J23-I23))) -> 0 | O23: =IF(OR(G23=0,G23="Férias",G23="Falta Justificada",G23="Feriado",G23="Folga (DSR)"),0,IF(G23="Falta Injustificada",HLOOKUP($F23,Jornada!$X$7:$AD$37,VLOOKUP(INDIRECT($C$5),Jornada!$C$8:$W$37,21,0),0),IF(HLOOKUP($F23,Jornada!$X$7:$AD$37,VLOOKUP(INDIRECT($C$5),Jornada!$C$8:$W$37,21,0),0)-M23>0,HLOOKUP($F23,Jornada!$X$7:$AD$37,VLOOKUP(INDIRECT($C$5),Jornada!$C$8:$W$37,21,0),0)-M23,0))) -> 0 | P23: =IF(HLOOKUP($F23,Jornada!$X$7:$AD$37,VLOOKUP(INDIRECT($C$5),Jornada!$C$8:$W$37,21,0),0)-M23<0,ABS(HLOOKUP($F23,Jornada!$X$7:$AD$37,VLOOKUP(INDIRECT($C$5),Jornada!$C$8:$W$37,21,0),0)-M23),0) -> 0 | Q23: =IF(G23="Normal",P23,IF(G23=0,0,IF(OR(G23="Feriado",G23="Férias"),IF(H23>K23,(K23+1-H23)-IF(J23<I23,$AJ$7+J23-I23,J23-I23),(K23-H23)-IF(J23<I23,$AJ$7+J23-I23,J23-I23)),IF(G23="Folga (DSR)",IF(H23>K23,(K23+1-H23)-IF(J23<I23,$AJ$7+J23-I23,J23-I23),(K23-H23)-IF(J23<I23,$AJ$7+J23-I23,J23-I23)),IF(G23="Falta Justificada",IF(H23>K23,(K23+1-H23)-IF(J23<I23,$AJ$7+J23-I23,J23-I23),(K23-H23)-IF(J23<I23,$AJ$7+J23-I23,J23-I23)),0))))) -> 0 | R23: =IF(Q23>$R$7,1,0) -> 0 | S23: =IF(SUM(R8:R38)>0,"Segundo o art 59 da CLT, o máximo de horas extras permitidas por dia são 2 horas. Reveja as horas lançadas se deseja estar de acordo com as leis trabalhistas em vigor no Brasil.","Parabéns!! Todas os dias estão dentro do limite de duas horas extras estipuladas pela CLT.") -> Parabéns!! Todas os dias estão dentro do limite de duas horas extras estipuladas pela CLT. | AB23: =AB22+1 -> 16 | AC23: =WEEKDAY(AB23) -> 2 | AG23: =IF(J23<I23,$AJ$7+J23-I23,J23-I23) -> 0 | AH23: =IF(HLOOKUP($F23,Jornada!$X$7:$AD$37,VLOOKUP(INDIRECT($C$5),Jornada!$C$8:$W$37,21,0),0)=0,0,VLOOKUP(INDIRECT($C$5),Jornada!$C$8:$H$37,4,0)) -> 0 | AI23: =IF(AND(I23=0,J23=0,OR(H23<>0,K23<>0),HLOOKUP($F23,Jornada!$X$7:$AD$37,VLOOKUP(INDIRECT($C$5),Jornada!$C$8:$W$37,21,0),0)>$AK$5,M23>$AK$5),VLOOKUP(INDIRECT($C$5),Jornada!$C$8:$H$37,6,0),IF(AG23>VLOOKUP(INDIRECT($C$5),Jornada!$C$8:$H$37,6,0),IF(VLOOKUP(INDIRECT($C$5),Jornada!$C$8:$H$37,6,0)<AG23,0,ABS(VLOOKUP(INDIRECT($C$5),Jornada!$C$8:$H$37,6,0))-AG23),0)) -> 0 | AJ23: =($AJ$7-K23)+H23 -> 1 | AK23: =IF(AJ23<$AK$7,$AK$7-AJ23,$AI$7) -> 0 | AL23: =HLOOKUP($F23,Jornada!$I$5:$V$37,VLOOKUP(INDIRECT($C$5),Jornada!$C$8:$W$37,21,0)+2,0) -> 0 | AM23: =HLOOKUP($F23,Jornada!$I$4:$V$37,VLOOKUP(INDIRECT($C$5),Jornada!$C$8:$W$37,21,0)+3,0) -> 0 | AN23: =IF(AND(AL23>=$AL$5,AL23<$AN$5,H23>=$AL$5,H23<AL23),AL23-H23,IF(AND(AL23>$AI$7,AL23<=$AM$5,H23>=$AL$5,H23<=$AN$5),$AN$5-H23+AL23,IF(AND(AL23>=$AI$7,AL23<=$AM$5,H23>=$AI$7,H23<=$AM$5,H23<AL23),H23-AL23,0))) -> 0 | AO23: =IF(AP23>Q23,0,AP23) -> 0 | AP23: =IF(Q23=0,0,IF(AND(AM23>=$AL$5,AM23<$AN$5,K23>=$AL$5,K23<$AM$5,K23>AM23),K23-AM23,IF(AND(AM23>=$AL$5,AM23<$AN$5,K23<$AN$5,K23>AM23),K23-$AL$5,IF(AND(AM23>=$AI$7,AM23<$AM$5,K23<$AM$5),K23-AM23,IF(AND(AM23<>AI22,AM23>=$AI$7,AM23<=$AM$5,K23>$AM$5,K23>AM23),$AM$5-AM23,IF(AND(K23>$AL$5,K23<$AN$5),K23-$AL$5,IF(AND(K23>$AI$7,K23<$AM$5),$AN$5-$AL$5+K23,IF(AND(OR(K23>$AL$5,H23>$AO$5),AM23>=$AI$7,AM23<$AM$5,K23>$AM$5),(1+$AM$5-$AL$5)-AG23,0)))))))) -> 0
C24: =IF(Funcionários!C23=0,"",Funcionários!C23) | D24: =IF(D23=7,1,D23+1) -> 3 | E24: =IF(DAY(DATE('P Gerais'!$D$6,VLOOKUP($E$7,$W$7:$X$18,2,0),E23+1))>DAY(EOMONTH(DATE('P Gerais'!$D$6,VLOOKUP($E$7,$W$7:$X$18,2,0),E23),0)),DAY(DATE('P Gerais'!$D$6,VLOOKUP($E$7,$W$7:$X$18,2,0)+1,1)),DAY(DATE('P Gerais'!$D$6,VLOOKUP($E$7,$W$7:$X$18,2,0),E23+1))) -> 17 | F24: =VLOOKUP(D24,$AE$8:$AF$14,2,FALSE) -> Ter | M24: =IF(AND(H24=K24,H24<>0),$M$6-IF(J24<I24,$AJ$7+J24-I24,J24-I24),IF(H24>K24,(K24+1-H24)-IF(J24<I24,$AJ$7+J24-I24,J24-I24),(K24-H24)-IF(J24<I24,$AJ$7+J24-I24,J24-I24))) -> 0 | O24: =IF(OR(G24=0,G24="Férias",G24="Falta Justificada",G24="Feriado",G24="Folga (DSR)"),0,IF(G24="Falta Injustificada",HLOOKUP($F24,Jornada!$X$7:$AD$37,VLOOKUP(INDIRECT($C$5),Jornada!$C$8:$W$37,21,0),0),IF(HLOOKUP($F24,Jornada!$X$7:$AD$37,VLOOKUP(INDIRECT($C$5),Jornada!$C$8:$W$37,21,0),0)-M24>0,HLOOKUP($F24,Jornada!$X$7:$AD$37,VLOOKUP(INDIRECT($C$5),Jornada!$C$8:$W$37,21,0),0)-M24,0))) -> 0 | P24: =IF(HLOOKUP($F24,Jornada!$X$7:$AD$37,VLOOKUP(INDIRECT($C$5),Jornada!$C$8:$W$37,21,0),0)-M24<0,ABS(HLOOKUP($F24,Jornada!$X$7:$AD$37,VLOOKUP(INDIRECT($C$5),Jornada!$C$8:$W$37,21,0),0)-M24),0) -> 0 | Q24: =IF(G24="Normal",P24,IF(G24=0,0,IF(OR(G24="Feriado",G24="Férias"),IF(H24>K24,(K24+1-H24)-IF(J24<I24,$AJ$7+J24-I24,J24-I24),(K24-H24)-IF(J24<I24,$AJ$7+J24-I24,J24-I24)),IF(G24="Folga (DSR)",IF(H24>K24,(K24+1-H24)-IF(J24<I24,$AJ$7+J24-I24,J24-I24),(K24-H24)-IF(J24<I24,$AJ$7+J24-I24,J24-I24)),IF(G24="Falta Justificada",IF(H24>K24,(K24+1-H24)-IF(J24<I24,$AJ$7+J24-I24,J24-I24),(K24-H24)-IF(J24<I24,$AJ$7+J24-I24,J24-I24)),0))))) -> 0 | R24: =IF(Q24>$R$7,1,0) -> 0 | AB24: =AB23+1 -> 17 | AC24: =WEEKDAY(AB24) -> 3 | AG24: =IF(J24<I24,$AJ$7+J24-I24,J24-I24) -> 0 | AH24: =IF(HLOOKUP($F24,Jornada!$X$7:$AD$37,VLOOKUP(INDIRECT($C$5),Jornada!$C$8:$W$37,21,0),0)=0,0,VLOOKUP(INDIRECT($C$5),Jornada!$C$8:$H$37,4,0)) -> 0 | AI24: =IF(AND(I24=0,J24=0,OR(H24<>0,K24<>0),HLOOKUP($F24,Jornada!$X$7:$AD$37,VLOOKUP(INDIRECT($C$5),Jornada!$C$8:$W$37,21,0),0)>$AK$5,M24>$AK$5),VLOOKUP(INDIRECT($C$5),Jornada!$C$8:$H$37,6,0),IF(AG24>VLOOKUP(INDIRECT($C$5),Jornada!$C$8:$H$37,6,0),IF(VLOOKUP(INDIRECT($C$5),Jornada!$C$8:$H$37,6,0)<AG24,0,ABS(VLOOKUP(INDIRECT($C$5),Jornada!$C$8:$H$37,6,0))-AG24),0)) -> 0 | AJ24: =($AJ$7-K24)+H24 -> 1 | AK24: =IF(AJ24<$AK$7,$AK$7-AJ24,$AI$7) -> 0 | AL24: =HLOOKUP($F24,Jornada!$I$5:$V$37,VLOOKUP(INDIRECT($C$5),Jornada!$C$8:$W$37,21,0)+2,0) -> 0 | AM24: =HLOOKUP($F24,Jornada!$I$4:$V$37,VLOOKUP(INDIRECT($C$5),Jornada!$C$8:$W$37,21,0)+3,0) -> 0 | AN24: =IF(AND(AL24>=$AL$5,AL24<$AN$5,H24>=$AL$5,H24<AL24),AL24-H24,IF(AND(AL24>$AI$7,AL24<=$AM$5,H24>=$AL$5,H24<=$AN$5),$AN$5-H24+AL24,IF(AND(AL24>=$AI$7,AL24<=$AM$5,H24>=$AI$7,H24<=$AM$5,H24<AL24),H24-AL24,0))) -> 0 | AO24: =IF(AP24>Q24,0,AP24) -> 0 | AP24: =IF(Q24=0,0,IF(AND(AM24>=$AL$5,AM24<$AN$5,K24>=$AL$5,K24<$AM$5,K24>AM24),K24-AM24,IF(AND(AM24>=$AL$5,AM24<$AN$5,K24<$AN$5,K24>AM24),K24-$AL$5,IF(AND(AM24>=$AI$7,AM24<$AM$5,K24<$AM$5),K24-AM24,IF(AND(AM24<>AI23,AM24>=$AI$7,AM24<=$AM$5,K24>$AM$5,K24>AM24),$AM$5-AM24,IF(AND(K24>$AL$5,K24<$AN$5),K24-$AL$5,IF(AND(K24>$AI$7,K24<$AM$5),$AN$5-$AL$5+K24,IF(AND(OR(K24>$AL$5,H24>$AO$5),AM24>=$AI$7,AM24<$AM$5,K24>$AM$5),(1+$AM$5-$AL$5)-AG24,0)))))))) -> 0
C25: =IF(Funcionários!C24=0,"",Funcionários!C24) | D25: =IF(D24=7,1,D24+1) -> 4 | E25: =IF(DAY(DATE('P Gerais'!$D$6,VLOOKUP($E$7,$W$7:$X$18,2,0),E24+1))>DAY(EOMONTH(DATE('P Gerais'!$D$6,VLOOKUP($E$7,$W$7:$X$18,2,0),E24),0)),DAY(DATE('P Gerais'!$D$6,VLOOKUP($E$7,$W$7:$X$18,2,0)+1,1)),DAY(DATE('P Gerais'!$D$6,VLOOKUP($E$7,$W$7:$X$18,2,0),E24+1))) -> 18 | F25: =VLOOKUP(D25,$AE$8:$AF$14,2,FALSE) -> Qua | M25: =IF(AND(H25=K25,H25<>0),$M$6-IF(J25<I25,$AJ$7+J25-I25,J25-I25),IF(H25>K25,(K25+1-H25)-IF(J25<I25,$AJ$7+J25-I25,J25-I25),(K25-H25)-IF(J25<I25,$AJ$7+J25-I25,J25-I25))) -> 0 | O25: =IF(OR(G25=0,G25="Férias",G25="Falta Justificada",G25="Feriado",G25="Folga (DSR)"),0,IF(G25="Falta Injustificada",HLOOKUP($F25,Jornada!$X$7:$AD$37,VLOOKUP(INDIRECT($C$5),Jornada!$C$8:$W$37,21,0),0),IF(HLOOKUP($F25,Jornada!$X$7:$AD$37,VLOOKUP(INDIRECT($C$5),Jornada!$C$8:$W$37,21,0),0)-M25>0,HLOOKUP($F25,Jornada!$X$7:$AD$37,VLOOKUP(INDIRECT($C$5),Jornada!$C$8:$W$37,21,0),0)-M25,0))) -> 0 | P25: =IF(HLOOKUP($F25,Jornada!$X$7:$AD$37,VLOOKUP(INDIRECT($C$5),Jornada!$C$8:$W$37,21,0),0)-M25<0,ABS(HLOOKUP($F25,Jornada!$X$7:$AD$37,VLOOKUP(INDIRECT($C$5),Jornada!$C$8:$W$37,21,0),0)-M25),0) -> 0 | Q25: =IF(G25="Normal",P25,IF(G25=0,0,IF(OR(G25="Feriado",G25="Férias"),IF(H25>K25,(K25+1-H25)-IF(J25<I25,$AJ$7+J25-I25,J25-I25),(K25-H25)-IF(J25<I25,$AJ$7+J25-I25,J25-I25)),IF(G25="Folga (DSR)",IF(H25>K25,(K25+1-H25)-IF(J25<I25,$AJ$7+J25-I25,J25-I25),(K25-H25)-IF(J25<I25,$AJ$7+J25-I25,J25-I25)),IF(G25="Falta Justificada",IF(H25>K25,(K25+1-H25)-IF(J25<I25,$AJ$7+J25-I25,J25-I25),(K25-H25)-IF(J25<I25,$AJ$7+J25-I25,J25-I25)),0))))) -> 0 | R25: =IF(Q25>$R$7,1,0) -> 0 | Z25: =IF(SUM(R8:R38)>0,1,0) -> 0 | AB25: =AB24+1 -> 18 | AC25: =WEEKDAY(AB25) -> 4 | AG25: =IF(J25<I25,$AJ$7+J25-I25,J25-I25) -> 0 | AH25: =IF(HLOOKUP($F25,Jornada!$X$7:$AD$37,VLOOKUP(INDIRECT($C$5),Jornada!$C$8:$W$37,21,0),0)=0,0,VLOOKUP(INDIRECT($C$5),Jornada!$C$8:$H$37,4,0)) -> 0 | AI25: =IF(AND(I25=0,J25=0,OR(H25<>0,K25<>0),HLOOKUP($F25,Jornada!$X$7:$AD$37,VLOOKUP(INDIRECT($C$5),Jornada!$C$8:$W$37,21,0),0)>$AK$5,M25>$AK$5),VLOOKUP(INDIRECT($C$5),Jornada!$C$8:$H$37,6,0),IF(AG25>VLOOKUP(INDIRECT($C$5),Jornada!$C$8:$H$37,6,0),IF(VLOOKUP(INDIRECT($C$5),Jornada!$C$8:$H$37,6,0)<AG25,0,ABS(VLOOKUP(INDIRECT($C$5),Jornada!$C$8:$H$37,6,0))-AG25),0)) -> 0 | AJ25: =($AJ$7-K25)+H25 -> 1 | AK25: =IF(AJ25<$AK$7,$AK$7-AJ25,$AI$7) -> 0 | AL25: =HLOOKUP($F25,Jornada!$I$5:$V$37,VLOOKUP(INDIRECT($C$5),Jornada!$C$8:$W$37,21,0)+2,0) -> 0 | AM25: =HLOOKUP($F25,Jornada!$I$4:$V$37,VLOOKUP(INDIRECT($C$5),Jornada!$C$8:$W$37,21,0)+3,0) -> 0 | AN25: =IF(AND(AL25>=$AL$5,AL25<$AN$5,H25>=$AL$5,H25<AL25),AL25-H25,IF(AND(AL25>$AI$7,AL25<=$AM$5,H25>=$AL$5,H25<=$AN$5),$AN$5-H25+AL25,IF(AND(AL25>=$AI$7,AL25<=$AM$5,H25>=$AI$7,H25<=$AM$5,H25<AL25),H25-AL25,0))) -> 0 | AO25: =IF(AP25>Q25,0,AP25) -> 0 | AP25: =IF(Q25=0,0,IF(AND(AM25>=$AL$5,AM25<$AN$5,K25>=$AL$5,K25<$AM$5,K25>AM25),K25-AM25,IF(AND(AM25>=$AL$5,AM25<$AN$5,K25<$AN$5,K25>AM25),K25-$AL$5,IF(AND(AM25>=$AI$7,AM25<$AM$5,K25<$AM$5),K25-AM25,IF(AND(AM25<>AI24,AM25>=$AI$7,AM25<=$AM$5,K25>$AM$5,K25>AM25),$AM$5-AM25,IF(AND(K25>$AL$5,K25<$AN$5),K25-$AL$5,IF(AND(K25>$AI$7,K25<$AM$5),$AN$5-$AL$5+K25,IF(AND(OR(K25>$AL$5,H25>$AO$5),AM25>=$AI$7,AM25<$AM$5,K25>$AM$5),(1+$AM$5-$AL$5)-AG25,0)))))))) -> 0
C26: =IF(Funcionários!C25=0,"",Funcionários!C25) | D26: =IF(D25=7,1,D25+1) -> 5 | E26: =IF(DAY(DATE('P Gerais'!$D$6,VLOOKUP($E$7,$W$7:$X$18,2,0),E25+1))>DAY(EOMONTH(DATE('P Gerais'!$D$6,VLOOKUP($E$7,$W$7:$X$18,2,0),E25),0)),DAY(DATE('P Gerais'!$D$6,VLOOKUP($E$7,$W$7:$X$18,2,0)+1,1)),DAY(DATE('P Gerais'!$D$6,VLOOKUP($E$7,$W$7:$X$18,2,0),E25+1))) -> 19 | F26: =VLOOKUP(D26,$AE$8:$AF$14,2,FALSE) -> Qui | M26: =IF(AND(H26=K26,H26<>0),$M$6-IF(J26<I26,$AJ$7+J26-I26,J26-I26),IF(H26>K26,(K26+1-H26)-IF(J26<I26,$AJ$7+J26-I26,J26-I26),(K26-H26)-IF(J26<I26,$AJ$7+J26-I26,J26-I26))) -> 0 | O26: =IF(OR(G26=0,G26="Férias",G26="Falta Justificada",G26="Feriado",G26="Folga (DSR)"),0,IF(G26="Falta Injustificada",HLOOKUP($F26,Jornada!$X$7:$AD$37,VLOOKUP(INDIRECT($C$5),Jornada!$C$8:$W$37,21,0),0),IF(HLOOKUP($F26,Jornada!$X$7:$AD$37,VLOOKUP(INDIRECT($C$5),Jornada!$C$8:$W$37,21,0),0)-M26>0,HLOOKUP($F26,Jornada!$X$7:$AD$37,VLOOKUP(INDIRECT($C$5),Jornada!$C$8:$W$37,21,0),0)-M26,0))) -> 0 | P26: =IF(HLOOKUP($F26,Jornada!$X$7:$AD$37,VLOOKUP(INDIRECT($C$5),Jornada!$C$8:$W$37,21,0),0)-M26<0,ABS(HLOOKUP($F26,Jornada!$X$7:$AD$37,VLOOKUP(INDIRECT($C$5),Jornada!$C$8:$W$37,21,0),0)-M26),0) -> 0 | Q26: =IF(G26="Normal",P26,IF(G26=0,0,IF(OR(G26="Feriado",G26="Férias"),IF(H26>K26,(K26+1-H26)-IF(J26<I26,$AJ$7+J26-I26,J26-I26),(K26-H26)-IF(J26<I26,$AJ$7+J26-I26,J26-I26)),IF(G26="Folga (DSR)",IF(H26>K26,(K26+1-H26)-IF(J26<I26,$AJ$7+J26-I26,J26-I26),(K26-H26)-IF(J26<I26,$AJ$7+J26-I26,J26-I26)),IF(G26="Falta Justificada",IF(H26>K26,(K26+1-H26)-IF(J26<I26,$AJ$7+J26-I26,J26-I26),(K26-H26)-IF(J26<I26,$AJ$7+J26-I26,J26-I26)),0))))) -> 0 | R26: =IF(Q26>$R$7,1,0) -> 0 | S26: =IF(COUNTIF(G8:G38,"Folga (DSR)")<DAY(E39)/8,"O mês não está contemplando um DSR (Descanso Semanal Remunerado) por semana. Isso pode configurar uma irregularidade segundo as leis trabalhistas.","Parabéns!! Sua folha de pagamento contempla uma DSR por semana conforme a lei trabalhista.") -> O mês não está contemplando um DSR (Descanso Semanal Remunerado) por semana. Isso pode configurar uma irregularidade segundo as leis trabalhistas. | AB26: =AB25+1 -> 19 | AC26: =WEEKDAY(AB26) -> 5 | AG26: =IF(J26<I26,$AJ$7+J26-I26,J26-I26) -> 0 | AH26: =IF(HLOOKUP($F26,Jornada!$X$7:$AD$37,VLOOKUP(INDIRECT($C$5),Jornada!$C$8:$W$37,21,0),0)=0,0,VLOOKUP(INDIRECT($C$5),Jornada!$C$8:$H$37,4,0)) -> 0 | AI26: =IF(AND(I26=0,J26=0,OR(H26<>0,K26<>0),HLOOKUP($F26,Jornada!$X$7:$AD$37,VLOOKUP(INDIRECT($C$5),Jornada!$C$8:$W$37,21,0),0)>$AK$5,M26>$AK$5),VLOOKUP(INDIRECT($C$5),Jornada!$C$8:$H$37,6,0),IF(AG26>VLOOKUP(INDIRECT($C$5),Jornada!$C$8:$H$37,6,0),IF(VLOOKUP(INDIRECT($C$5),Jornada!$C$8:$H$37,6,0)<AG26,0,ABS(VLOOKUP(INDIRECT($C$5),Jornada!$C$8:$H$37,6,0))-AG26),0)) -> 0 | AJ26: =($AJ$7-K26)+H26 -> 1 | AK26: =IF(AJ26<$AK$7,$AK$7-AJ26,$AI$7) -> 0 | AL26: =HLOOKUP($F26,Jornada!$I$5:$V$37,VLOOKUP(INDIRECT($C$5),Jornada!$C$8:$W$37,21,0)+2,0) -> 0 | AM26: =HLOOKUP($F26,Jornada!$I$4:$V$37,VLOOKUP(INDIRECT($C$5),Jornada!$C$8:$W$37,21,0)+3,0) -> 0 | AN26: =IF(AND(AL26>=$AL$5,AL26<$AN$5,H26>=$AL$5,H26<AL26),AL26-H26,IF(AND(AL26>$AI$7,AL26<=$AM$5,H26>=$AL$5,H26<=$AN$5),$AN$5-H26+AL26,IF(AND(AL26>=$AI$7,AL26<=$AM$5,H26>=$AI$7,H26<=$AM$5,H26<AL26),H26-AL26,0))) -> 0 | AO26: =IF(AP26>Q26,0,AP26) -> 0 | AP26: =IF(Q26=0,0,IF(AND(AM26>=$AL$5,AM26<$AN$5,K26>=$AL$5,K26<$AM$5,K26>AM26),K26-AM26,IF(AND(AM26>=$AL$5,AM26<$AN$5,K26<$AN$5,K26>AM26),K26-$AL$5,IF(AND(AM26>=$AI$7,AM26<$AM$5,K26<$AM$5),K26-AM26,IF(AND(AM26<>AI25,AM26>=$AI$7,AM26<=$AM$5,K26>$AM$5,K26>AM26),$AM$5-AM26,IF(AND(K26>$AL$5,K26<$AN$5),K26-$AL$5,IF(AND(K26>$AI$7,K26<$AM$5),$AN$5-$AL$5+K26,IF(AND(OR(K26>$AL$5,H26>$AO$5),AM26>=$AI$7,AM26<$AM$5,K26>$AM$5),(1+$AM$5-$AL$5)-AG26,0)))))))) -> 0
C27: =IF(Funcionários!C26=0,"",Funcionários!C26) | D27: =IF(D26=7,1,D26+1) -> 6 | E27: =IF(DAY(DATE('P Gerais'!$D$6,VLOOKUP($E$7,$W$7:$X$18,2,0),E26+1))>DAY(EOMONTH(DATE('P Gerais'!$D$6,VLOOKUP($E$7,$W$7:$X$18,2,0),E26),0)),DAY(DATE('P Gerais'!$D$6,VLOOKUP($E$7,$W$7:$X$18,2,0)+1,1)),DAY(DATE('P Gerais'!$D$6,VLOOKUP($E$7,$W$7:$X$18,2,0),E26+1))) -> 20 | F27: =VLOOKUP(D27,$AE$8:$AF$14,2,FALSE) -> Sex | M27: =IF(AND(H27=K27,H27<>0),$M$6-IF(J27<I27,$AJ$7+J27-I27,J27-I27),IF(H27>K27,(K27+1-H27)-IF(J27<I27,$AJ$7+J27-I27,J27-I27),(K27-H27)-IF(J27<I27,$AJ$7+J27-I27,J27-I27))) -> 0 | O27: =IF(OR(G27=0,G27="Férias",G27="Falta Justificada",G27="Feriado",G27="Folga (DSR)"),0,IF(G27="Falta Injustificada",HLOOKUP($F27,Jornada!$X$7:$AD$37,VLOOKUP(INDIRECT($C$5),Jornada!$C$8:$W$37,21,0),0),IF(HLOOKUP($F27,Jornada!$X$7:$AD$37,VLOOKUP(INDIRECT($C$5),Jornada!$C$8:$W$37,21,0),0)-M27>0,HLOOKUP($F27,Jornada!$X$7:$AD$37,VLOOKUP(INDIRECT($C$5),Jornada!$C$8:$W$37,21,0),0)-M27,0))) -> 0 | P27: =IF(HLOOKUP($F27,Jornada!$X$7:$AD$37,VLOOKUP(INDIRECT($C$5),Jornada!$C$8:$W$37,21,0),0)-M27<0,ABS(HLOOKUP($F27,Jornada!$X$7:$AD$37,VLOOKUP(INDIRECT($C$5),Jornada!$C$8:$W$37,21,0),0)-M27),0) -> 0 | Q27: =IF(G27="Normal",P27,IF(G27=0,0,IF(OR(G27="Feriado",G27="Férias"),IF(H27>K27,(K27+1-H27)-IF(J27<I27,$AJ$7+J27-I27,J27-I27),(K27-H27)-IF(J27<I27,$AJ$7+J27-I27,J27-I27)),IF(G27="Folga (DSR)",IF(H27>K27,(K27+1-H27)-IF(J27<I27,$AJ$7+J27-I27,J27-I27),(K27-H27)-IF(J27<I27,$AJ$7+J27-I27,J27-I27)),IF(G27="Falta Justificada",IF(H27>K27,(K27+1-H27)-IF(J27<I27,$AJ$7+J27-I27,J27-I27),(K27-H27)-IF(J27<I27,$AJ$7+J27-I27,J27-I27)),0))))) -> 0 | R27: =IF(Q27>$R$7,1,0) -> 0 | AB27: =AB26+1 -> 20 | AC27: =WEEKDAY(AB27) -> 6 | AG27: =IF(J27<I27,$AJ$7+J27-I27,J27-I27) -> 0 | AH27: =IF(HLOOKUP($F27,Jornada!$X$7:$AD$37,VLOOKUP(INDIRECT($C$5),Jornada!$C$8:$W$37,21,0),0)=0,0,VLOOKUP(INDIRECT($C$5),Jornada!$C$8:$H$37,4,0)) -> 0 | AI27: =IF(AND(I27=0,J27=0,OR(H27<>0,K27<>0),HLOOKUP($F27,Jornada!$X$7:$AD$37,VLOOKUP(INDIRECT($C$5),Jornada!$C$8:$W$37,21,0),0)>$AK$5,M27>$AK$5),VLOOKUP(INDIRECT($C$5),Jornada!$C$8:$H$37,6,0),IF(AG27>VLOOKUP(INDIRECT($C$5),Jornada!$C$8:$H$37,6,0),IF(VLOOKUP(INDIRECT($C$5),Jornada!$C$8:$H$37,6,0)<AG27,0,ABS(VLOOKUP(INDIRECT($C$5),Jornada!$C$8:$H$37,6,0))-AG27),0)) -> 0 | AJ27: =($AJ$7-K27)+H27 -> 1 | AK27: =IF(AJ27<$AK$7,$AK$7-AJ27,$AI$7) -> 0 | AL27: =HLOOKUP($F27,Jornada!$I$5:$V$37,VLOOKUP(INDIRECT($C$5),Jornada!$C$8:$W$37,21,0)+2,0) -> 0 | AM27: =HLOOKUP($F27,Jornada!$I$4:$V$37,VLOOKUP(INDIRECT($C$5),Jornada!$C$8:$W$37,21,0)+3,0) -> 0 | AN27: =IF(AND(AL27>=$AL$5,AL27<$AN$5,H27>=$AL$5,H27<AL27),AL27-H27,IF(AND(AL27>$AI$7,AL27<=$AM$5,H27>=$AL$5,H27<=$AN$5),$AN$5-H27+AL27,IF(AND(AL27>=$AI$7,AL27<=$AM$5,H27>=$AI$7,H27<=$AM$5,H27<AL27),H27-AL27,0))) -> 0 | AO27: =IF(AP27>Q27,0,AP27) -> 0 | AP27: =IF(Q27=0,0,IF(AND(AM27>=$AL$5,AM27<$AN$5,K27>=$AL$5,K27<$AM$5,K27>AM27),K27-AM27,IF(AND(AM27>=$AL$5,AM27<$AN$5,K27<$AN$5,K27>AM27),K27-$AL$5,IF(AND(AM27>=$AI$7,AM27<$AM$5,K27<$AM$5),K27-AM27,IF(AND(AM27<>AI26,AM27>=$AI$7,AM27<=$AM$5,K27>$AM$5,K27>AM27),$AM$5-AM27,IF(AND(K27>$AL$5,K27<$AN$5),K27-$AL$5,IF(AND(K27>$AI$7,K27<$AM$5),$AN$5-$AL$5+K27,IF(AND(OR(K27>$AL$5,H27>$AO$5),AM27>=$AI$7,AM27<$AM$5,K27>$AM$5),(1+$AM$5-$AL$5)-AG27,0)))))))) -> 0
C28: =IF(Funcionários!C27=0,"",Funcionários!C27) | D28: =IF(D27=7,1,D27+1) -> 7 | E28: =IF(DAY(DATE('P Gerais'!$D$6,VLOOKUP($E$7,$W$7:$X$18,2,0),E27+1))>DAY(EOMONTH(DATE('P Gerais'!$D$6,VLOOKUP($E$7,$W$7:$X$18,2,0),E27),0)),DAY(DATE('P Gerais'!$D$6,VLOOKUP($E$7,$W$7:$X$18,2,0)+1,1)),DAY(DATE('P Gerais'!$D$6,VLOOKUP($E$7,$W$7:$X$18,2,0),E27+1))) -> 21 | F28: =VLOOKUP(D28,$AE$8:$AF$14,2,FALSE) -> Sáb | M28: =IF(AND(H28=K28,H28<>0),$M$6-IF(J28<I28,$AJ$7+J28-I28,J28-I28),IF(H28>K28,(K28+1-H28)-IF(J28<I28,$AJ$7+J28-I28,J28-I28),(K28-H28)-IF(J28<I28,$AJ$7+J28-I28,J28-I28))) -> 0 | O28: =IF(OR(G28=0,G28="Férias",G28="Falta Justificada",G28="Feriado",G28="Folga (DSR)"),0,IF(G28="Falta Injustificada",HLOOKUP($F28,Jornada!$X$7:$AD$37,VLOOKUP(INDIRECT($C$5),Jornada!$C$8:$W$37,21,0),0),IF(HLOOKUP($F28,Jornada!$X$7:$AD$37,VLOOKUP(INDIRECT($C$5),Jornada!$C$8:$W$37,21,0),0)-M28>0,HLOOKUP($F28,Jornada!$X$7:$AD$37,VLOOKUP(INDIRECT($C$5),Jornada!$C$8:$W$37,21,0),0)-M28,0))) -> 0 | P28: =IF(HLOOKUP($F28,Jornada!$X$7:$AD$37,VLOOKUP(INDIRECT($C$5),Jornada!$C$8:$W$37,21,0),0)-M28<0,ABS(HLOOKUP($F28,Jornada!$X$7:$AD$37,VLOOKUP(INDIRECT($C$5),Jornada!$C$8:$W$37,21,0),0)-M28),0) -> 0 | Q28: =IF(G28="Normal",P28,IF(G28=0,0,IF(OR(G28="Feriado",G28="Férias"),IF(H28>K28,(K28+1-H28)-IF(J28<I28,$AJ$7+J28-I28,J28-I28),(K28-H28)-IF(J28<I28,$AJ$7+J28-I28,J28-I28)),IF(G28="Folga (DSR)",IF(H28>K28,(K28+1-H28)-IF(J28<I28,$AJ$7+J28-I28,J28-I28),(K28-H28)-IF(J28<I28,$AJ$7+J28-I28,J28-I28)),IF(G28="Falta Justificada",IF(H28>K28,(K28+1-H28)-IF(J28<I28,$AJ$7+J28-I28,J28-I28),(K28-H28)-IF(J28<I28,$AJ$7+J28-I28,J28-I28)),0))))) -> 0 | R28: =IF(Q28>$R$7,1,0) -> 0 | AB28: =AB27+1 -> 21 | AC28: =WEEKDAY(AB28) -> 7 | AG28: =IF(J28<I28,$AJ$7+J28-I28,J28-I28) -> 0 | AH28: =IF(HLOOKUP($F28,Jornada!$X$7:$AD$37,VLOOKUP(INDIRECT($C$5),Jornada!$C$8:$W$37,21,0),0)=0,0,VLOOKUP(INDIRECT($C$5),Jornada!$C$8:$H$37,4,0)) -> 0 | AI28: =IF(AND(I28=0,J28=0,OR(H28<>0,K28<>0),HLOOKUP($F28,Jornada!$X$7:$AD$37,VLOOKUP(INDIRECT($C$5),Jornada!$C$8:$W$37,21,0),0)>$AK$5,M28>$AK$5),VLOOKUP(INDIRECT($C$5),Jornada!$C$8:$H$37,6,0),IF(AG28>VLOOKUP(INDIRECT($C$5),Jornada!$C$8:$H$37,6,0),IF(VLOOKUP(INDIRECT($C$5),Jornada!$C$8:$H$37,6,0)<AG28,0,ABS(VLOOKUP(INDIRECT($C$5),Jornada!$C$8:$H$37,6,0))-AG28),0)) -> 0 | AJ28: =($AJ$7-K28)+H28 -> 1 | AK28: =IF(AJ28<$AK$7,$AK$7-AJ28,$AI$7) -> 0 | AL28: =HLOOKUP($F28,Jornada!$I$5:$V$37,VLOOKUP(INDIRECT($C$5),Jornada!$C$8:$W$37,21,0)+2,0) -> 0 | AM28: =HLOOKUP($F28,Jornada!$I$4:$V$37,VLOOKUP(INDIRECT($C$5),Jornada!$C$8:$W$37,21,0)+3,0) -> 0 | AN28: =IF(AND(AL28>=$AL$5,AL28<$AN$5,H28>=$AL$5,H28<AL28),AL28-H28,IF(AND(AL28>$AI$7,AL28<=$AM$5,H28>=$AL$5,H28<=$AN$5),$AN$5-H28+AL28,IF(AND(AL28>=$AI$7,AL28<=$AM$5,H28>=$AI$7,H28<=$AM$5,H28<AL28),H28-AL28,0))) -> 0 | AO28: =IF(AP28>Q28,0,AP28) -> 0 | AP28: =IF(Q28=0,0,IF(AND(AM28>=$AL$5,AM28<$AN$5,K28>=$AL$5,K28<$AM$5,K28>AM28),K28-AM28,IF(AND(AM28>=$AL$5,AM28<$AN$5,K28<$AN$5,K28>AM28),K28-$AL$5,IF(AND(AM28>=$AI$7,AM28<$AM$5,K28<$AM$5),K28-AM28,IF(AND(AM28<>AI27,AM28>=$AI$7,AM28<=$AM$5,K28>$AM$5,K28>AM28),$AM$5-AM28,IF(AND(K28>$AL$5,K28<$AN$5),K28-$AL$5,IF(AND(K28>$AI$7,K28<$AM$5),$AN$5-$AL$5+K28,IF(AND(OR(K28>$AL$5,H28>$AO$5),AM28>=$AI$7,AM28<$AM$5,K28>$AM$5),(1+$AM$5-$AL$5)-AG28,0)))))))) -> 0
C29: =IF(Funcionários!C28=0,"",Funcionários!C28) | D29: =IF(D28=7,1,D28+1) -> 1 | E29: =IF(DAY(DATE('P Gerais'!$D$6,VLOOKUP($E$7,$W$7:$X$18,2,0),E28+1))>DAY(EOMONTH(DATE('P Gerais'!$D$6,VLOOKUP($E$7,$W$7:$X$18,2,0),E28),0)),DAY(DATE('P Gerais'!$D$6,VLOOKUP($E$7,$W$7:$X$18,2,0)+1,1)),DAY(DATE('P Gerais'!$D$6,VLOOKUP($E$7,$W$7:$X$18,2,0),E28+1))) -> 22 | F29: =VLOOKUP(D29,$AE$8:$AF$14,2,FALSE) -> Dom | M29: =IF(AND(H29=K29,H29<>0),$M$6-IF(J29<I29,$AJ$7+J29-I29,J29-I29),IF(H29>K29,(K29+1-H29)-IF(J29<I29,$AJ$7+J29-I29,J29-I29),(K29-H29)-IF(J29<I29,$AJ$7+J29-I29,J29-I29))) -> 0 | O29: =IF(OR(G29=0,G29="Férias",G29="Falta Justificada",G29="Feriado",G29="Folga (DSR)"),0,IF(G29="Falta Injustificada",HLOOKUP($F29,Jornada!$X$7:$AD$37,VLOOKUP(INDIRECT($C$5),Jornada!$C$8:$W$37,21,0),0),IF(HLOOKUP($F29,Jornada!$X$7:$AD$37,VLOOKUP(INDIRECT($C$5),Jornada!$C$8:$W$37,21,0),0)-M29>0,HLOOKUP($F29,Jornada!$X$7:$AD$37,VLOOKUP(INDIRECT($C$5),Jornada!$C$8:$W$37,21,0),0)-M29,0))) -> 0 | P29: =IF(HLOOKUP($F29,Jornada!$X$7:$AD$37,VLOOKUP(INDIRECT($C$5),Jornada!$C$8:$W$37,21,0),0)-M29<0,ABS(HLOOKUP($F29,Jornada!$X$7:$AD$37,VLOOKUP(INDIRECT($C$5),Jornada!$C$8:$W$37,21,0),0)-M29),0) -> 0 | Q29: =IF(G29="Normal",P29,IF(G29=0,0,IF(OR(G29="Feriado",G29="Férias"),IF(H29>K29,(K29+1-H29)-IF(J29<I29,$AJ$7+J29-I29,J29-I29),(K29-H29)-IF(J29<I29,$AJ$7+J29-I29,J29-I29)),IF(G29="Folga (DSR)",IF(H29>K29,(K29+1-H29)-IF(J29<I29,$AJ$7+J29-I29,J29-I29),(K29-H29)-IF(J29<I29,$AJ$7+J29-I29,J29-I29)),IF(G29="Falta Justificada",IF(H29>K29,(K29+1-H29)-IF(J29<I29,$AJ$7+J29-I29,J29-I29),(K29-H29)-IF(J29<I29,$AJ$7+J29-I29,J29-I29)),0))))) -> 0 | R29: =IF(Q29>$R$7,1,0) -> 0 | AB29: =AB28+1 -> 22 | AC29: =WEEKDAY(AB29) -> 1 | AG29: =IF(J29<I29,$AJ$7+J29-I29,J29-I29) -> 0 | AH29: =IF(HLOOKUP($F29,Jornada!$X$7:$AD$37,VLOOKUP(INDIRECT($C$5),Jornada!$C$8:$W$37,21,0),0)=0,0,VLOOKUP(INDIRECT($C$5),Jornada!$C$8:$H$37,4,0)) -> 0 | AI29: =IF(AND(I29=0,J29=0,OR(H29<>0,K29<>0),HLOOKUP($F29,Jornada!$X$7:$AD$37,VLOOKUP(INDIRECT($C$5),Jornada!$C$8:$W$37,21,0),0)>$AK$5,M29>$AK$5),VLOOKUP(INDIRECT($C$5),Jornada!$C$8:$H$37,6,0),IF(AG29>VLOOKUP(INDIRECT($C$5),Jornada!$C$8:$H$37,6,0),IF(VLOOKUP(INDIRECT($C$5),Jornada!$C$8:$H$37,6,0)<AG29,0,ABS(VLOOKUP(INDIRECT($C$5),Jornada!$C$8:$H$37,6,0))-AG29),0)) -> 0 | AJ29: =($AJ$7-K29)+H29 -> 1 | AK29: =IF(AJ29<$AK$7,$AK$7-AJ29,$AI$7) -> 0 | AL29: =HLOOKUP($F29,Jornada!$I$5:$V$37,VLOOKUP(INDIRECT($C$5),Jornada!$C$8:$W$37,21,0)+2,0) -> 0 | AM29: =HLOOKUP($F29,Jornada!$I$4:$V$37,VLOOKUP(INDIRECT($C$5),Jornada!$C$8:$W$37,21,0)+3,0) -> 0 | AN29: =IF(AND(AL29>=$AL$5,AL29<$AN$5,H29>=$AL$5,H29<AL29),AL29-H29,IF(AND(AL29>$AI$7,AL29<=$AM$5,H29>=$AL$5,H29<=$AN$5),$AN$5-H29+AL29,IF(AND(AL29>=$AI$7,AL29<=$AM$5,H29>=$AI$7,H29<=$AM$5,H29<AL29),H29-AL29,0))) -> 0 | AO29: =IF(AP29>Q29,0,AP29) -> 0 | AP29: =IF(Q29=0,0,IF(AND(AM29>=$AL$5,AM29<$AN$5,K29>=$AL$5,K29<$AM$5,K29>AM29),K29-AM29,IF(AND(AM29>=$AL$5,AM29<$AN$5,K29<$AN$5,K29>AM29),K29-$AL$5,IF(AND(AM29>=$AI$7,AM29<$AM$5,K29<$AM$5),K29-AM29,IF(AND(AM29<>AI28,AM29>=$AI$7,AM29<=$AM$5,K29>$AM$5,K29>AM29),$AM$5-AM29,IF(AND(K29>$AL$5,K29<$AN$5),K29-$AL$5,IF(AND(K29>$AI$7,K29<$AM$5),$AN$5-$AL$5+K29,IF(AND(OR(K29>$AL$5,H29>$AO$5),AM29>=$AI$7,AM29<$AM$5,K29>$AM$5),(1+$AM$5-$AL$5)-AG29,0)))))))) -> 0
C30: =IF(Funcionários!C29=0,"",Funcionários!C29) | D30: =IF(D29=7,1,D29+1) -> 2 | E30: =IF(DAY(DATE('P Gerais'!$D$6,VLOOKUP($E$7,$W$7:$X$18,2,0),E29+1))>DAY(EOMONTH(DATE('P Gerais'!$D$6,VLOOKUP($E$7,$W$7:$X$18,2,0),E29),0)),DAY(DATE('P Gerais'!$D$6,VLOOKUP($E$7,$W$7:$X$18,2,0)+1,1)),DAY(DATE('P Gerais'!$D$6,VLOOKUP($E$7,$W$7:$X$18,2,0),E29+1))) -> 23 | F30: =VLOOKUP(D30,$AE$8:$AF$14,2,FALSE) -> Seg | M30: =IF(AND(H30=K30,H30<>0),$M$6-IF(J30<I30,$AJ$7+J30-I30,J30-I30),IF(H30>K30,(K30+1-H30)-IF(J30<I30,$AJ$7+J30-I30,J30-I30),(K30-H30)-IF(J30<I30,$AJ$7+J30-I30,J30-I30))) -> 0 | O30: =IF(OR(G30=0,G30="Férias",G30="Falta Justificada",G30="Feriado",G30="Folga (DSR)"),0,IF(G30="Falta Injustificada",HLOOKUP($F30,Jornada!$X$7:$AD$37,VLOOKUP(INDIRECT($C$5),Jornada!$C$8:$W$37,21,0),0),IF(HLOOKUP($F30,Jornada!$X$7:$AD$37,VLOOKUP(INDIRECT($C$5),Jornada!$C$8:$W$37,21,0),0)-M30>0,HLOOKUP($F30,Jornada!$X$7:$AD$37,VLOOKUP(INDIRECT($C$5),Jornada!$C$8:$W$37,21,0),0)-M30,0))) -> 0 | P30: =IF(HLOOKUP($F30,Jornada!$X$7:$AD$37,VLOOKUP(INDIRECT($C$5),Jornada!$C$8:$W$37,21,0),0)-M30<0,ABS(HLOOKUP($F30,Jornada!$X$7:$AD$37,VLOOKUP(INDIRECT($C$5),Jornada!$C$8:$W$37,21,0),0)-M30),0) -> 0 | Q30: =IF(G30="Normal",P30,IF(G30=0,0,IF(OR(G30="Feriado",G30="Férias"),IF(H30>K30,(K30+1-H30)-IF(J30<I30,$AJ$7+J30-I30,J30-I30),(K30-H30)-IF(J30<I30,$AJ$7+J30-I30,J30-I30)),IF(G30="Folga (DSR)",IF(H30>K30,(K30+1-H30)-IF(J30<I30,$AJ$7+J30-I30,J30-I30),(K30-H30)-IF(J30<I30,$AJ$7+J30-I30,J30-I30)),IF(G30="Falta Justificada",IF(H30>K30,(K30+1-H30)-IF(J30<I30,$AJ$7+J30-I30,J30-I30),(K30-H30)-IF(J30<I30,$AJ$7+J30-I30,J30-I30)),0))))) -> 0 | R30: =IF(Q30>$R$7,1,0) -> 0 | AB30: =AB29+1 -> 23 | AC30: =WEEKDAY(AB30) -> 2 | AG30: =IF(J30<I30,$AJ$7+J30-I30,J30-I30) -> 0 | AH30: =IF(HLOOKUP($F30,Jornada!$X$7:$AD$37,VLOOKUP(INDIRECT($C$5),Jornada!$C$8:$W$37,21,0),0)=0,0,VLOOKUP(INDIRECT($C$5),Jornada!$C$8:$H$37,4,0)) -> 0 | AI30: =IF(AND(I30=0,J30=0,OR(H30<>0,K30<>0),HLOOKUP($F30,Jornada!$X$7:$AD$37,VLOOKUP(INDIRECT($C$5),Jornada!$C$8:$W$37,21,0),0)>$AK$5,M30>$AK$5),VLOOKUP(INDIRECT($C$5),Jornada!$C$8:$H$37,6,0),IF(AG30>VLOOKUP(INDIRECT($C$5),Jornada!$C$8:$H$37,6,0),IF(VLOOKUP(INDIRECT($C$5),Jornada!$C$8:$H$37,6,0)<AG30,0,ABS(VLOOKUP(INDIRECT($C$5),Jornada!$C$8:$H$37,6,0))-AG30),0)) -> 0 | AJ30: =($AJ$7-K30)+H30 -> 1 | AK30: =IF(AJ30<$AK$7,$AK$7-AJ30,$AI$7) -> 0 | AL30: =HLOOKUP($F30,Jornada!$I$5:$V$37,VLOOKUP(INDIRECT($C$5),Jornada!$C$8:$W$37,21,0)+2,0) -> 0 | AM30: =HLOOKUP($F30,Jornada!$I$4:$V$37,VLOOKUP(INDIRECT($C$5),Jornada!$C$8:$W$37,21,0)+3,0) -> 0 | AN30: =IF(AND(AL30>=$AL$5,AL30<$AN$5,H30>=$AL$5,H30<AL30),AL30-H30,IF(AND(AL30>$AI$7,AL30<=$AM$5,H30>=$AL$5,H30<=$AN$5),$AN$5-H30+AL30,IF(AND(AL30>=$AI$7,AL30<=$AM$5,H30>=$AI$7,H30<=$AM$5,H30<AL30),H30-AL30,0))) -> 0 | AO30: =IF(AP30>Q30,0,AP30) -> 0 | AP30: =IF(Q30=0,0,IF(AND(AM30>=$AL$5,AM30<$AN$5,K30>=$AL$5,K30<$AM$5,K30>AM30),K30-AM30,IF(AND(AM30>=$AL$5,AM30<$AN$5,K30<$AN$5,K30>AM30),K30-$AL$5,IF(AND(AM30>=$AI$7,AM30<$AM$5,K30<$AM$5),K30-AM30,IF(AND(AM30<>AI29,AM30>=$AI$7,AM30<=$AM$5,K30>$AM$5,K30>AM30),$AM$5-AM30,IF(AND(K30>$AL$5,K30<$AN$5),K30-$AL$5,IF(AND(K30>$AI$7,K30<$AM$5),$AN$5-$AL$5+K30,IF(AND(OR(K30>$AL$5,H30>$AO$5),AM30>=$AI$7,AM30<$AM$5,K30>$AM$5),(1+$AM$5-$AL$5)-AG30,0)))))))) -> 0
C31: =IF(Funcionários!C30=0,"",Funcionários!C30) | D31: =IF(D30=7,1,D30+1) -> 3 | E31: =IF(DAY(DATE('P Gerais'!$D$6,VLOOKUP($E$7,$W$7:$X$18,2,0),E30+1))>DAY(EOMONTH(DATE('P Gerais'!$D$6,VLOOKUP($E$7,$W$7:$X$18,2,0),E30),0)),DAY(DATE('P Gerais'!$D$6,VLOOKUP($E$7,$W$7:$X$18,2,0)+1,1)),DAY(DATE('P Gerais'!$D$6,VLOOKUP($E$7,$W$7:$X$18,2,0),E30+1))) -> 24 | F31: =VLOOKUP(D31,$AE$8:$AF$14,2,FALSE) -> Ter | M31: =IF(AND(H31=K31,H31<>0),$M$6-IF(J31<I31,$AJ$7+J31-I31,J31-I31),IF(H31>K31,(K31+1-H31)-IF(J31<I31,$AJ$7+J31-I31,J31-I31),(K31-H31)-IF(J31<I31,$AJ$7+J31-I31,J31-I31))) -> 0 | O31: =IF(OR(G31=0,G31="Férias",G31="Falta Justificada",G31="Feriado",G31="Folga (DSR)"),0,IF(G31="Falta Injustificada",HLOOKUP($F31,Jornada!$X$7:$AD$37,VLOOKUP(INDIRECT($C$5),Jornada!$C$8:$W$37,21,0),0),IF(HLOOKUP($F31,Jornada!$X$7:$AD$37,VLOOKUP(INDIRECT($C$5),Jornada!$C$8:$W$37,21,0),0)-M31>0,HLOOKUP($F31,Jornada!$X$7:$AD$37,VLOOKUP(INDIRECT($C$5),Jornada!$C$8:$W$37,21,0),0)-M31,0))) -> 0 | P31: =IF(HLOOKUP($F31,Jornada!$X$7:$AD$37,VLOOKUP(INDIRECT($C$5),Jornada!$C$8:$W$37,21,0),0)-M31<0,ABS(HLOOKUP($F31,Jornada!$X$7:$AD$37,VLOOKUP(INDIRECT($C$5),Jornada!$C$8:$W$37,21,0),0)-M31),0) -> 0 | Q31: =IF(G31="Normal",P31,IF(G31=0,0,IF(OR(G31="Feriado",G31="Férias"),IF(H31>K31,(K31+1-H31)-IF(J31<I31,$AJ$7+J31-I31,J31-I31),(K31-H31)-IF(J31<I31,$AJ$7+J31-I31,J31-I31)),IF(G31="Folga (DSR)",IF(H31>K31,(K31+1-H31)-IF(J31<I31,$AJ$7+J31-I31,J31-I31),(K31-H31)-IF(J31<I31,$AJ$7+J31-I31,J31-I31)),IF(G31="Falta Justificada",IF(H31>K31,(K31+1-H31)-IF(J31<I31,$AJ$7+J31-I31,J31-I31),(K31-H31)-IF(J31<I31,$AJ$7+J31-I31,J31-I31)),0))))) -> 0 | R31: =IF(Q31>$R$7,1,0) -> 0 | AB31: =AB30+1 -> 24 | AC31: =WEEKDAY(AB31) -> 3 | AG31: =IF(J31<I31,$AJ$7+J31-I31,J31-I31) -> 0 | AH31: =IF(HLOOKUP($F31,Jornada!$X$7:$AD$37,VLOOKUP(INDIRECT($C$5),Jornada!$C$8:$W$37,21,0),0)=0,0,VLOOKUP(INDIRECT($C$5),Jornada!$C$8:$H$37,4,0)) -> 0 | AI31: =IF(AND(I31=0,J31=0,OR(H31<>0,K31<>0),HLOOKUP($F31,Jornada!$X$7:$AD$37,VLOOKUP(INDIRECT($C$5),Jornada!$C$8:$W$37,21,0),0)>$AK$5,M31>$AK$5),VLOOKUP(INDIRECT($C$5),Jornada!$C$8:$H$37,6,0),IF(AG31>VLOOKUP(INDIRECT($C$5),Jornada!$C$8:$H$37,6,0),IF(VLOOKUP(INDIRECT($C$5),Jornada!$C$8:$H$37,6,0)<AG31,0,ABS(VLOOKUP(INDIRECT($C$5),Jornada!$C$8:$H$37,6,0))-AG31),0)) -> 0 | AJ31: =($AJ$7-K31)+H31 -> 1 | AK31: =IF(AJ31<$AK$7,$AK$7-AJ31,$AI$7) -> 0 | AL31: =HLOOKUP($F31,Jornada!$I$5:$V$37,VLOOKUP(INDIRECT($C$5),Jornada!$C$8:$W$37,21,0)+2,0) -> 0 | AM31: =HLOOKUP($F31,Jornada!$I$4:$V$37,VLOOKUP(INDIRECT($C$5),Jornada!$C$8:$W$37,21,0)+3,0) -> 0 | AN31: =IF(AND(AL31>=$AL$5,AL31<$AN$5,H31>=$AL$5,H31<AL31),AL31-H31,IF(AND(AL31>$AI$7,AL31<=$AM$5,H31>=$AL$5,H31<=$AN$5),$AN$5-H31+AL31,IF(AND(AL31>=$AI$7,AL31<=$AM$5,H31>=$AI$7,H31<=$AM$5,H31<AL31),H31-AL31,0))) -> 0 | AO31: =IF(AP31>Q31,0,AP31) -> 0 | AP31: =IF(Q31=0,0,IF(AND(AM31>=$AL$5,AM31<$AN$5,K31>=$AL$5,K31<$AM$5,K31>AM31),K31-AM31,IF(AND(AM31>=$AL$5,AM31<$AN$5,K31<$AN$5,K31>AM31),K31-$AL$5,IF(AND(AM31>=$AI$7,AM31<$AM$5,K31<$AM$5),K31-AM31,IF(AND(AM31<>AI30,AM31>=$AI$7,AM31<=$AM$5,K31>$AM$5,K31>AM31),$AM$5-AM31,IF(AND(K31>$AL$5,K31<$AN$5),K31-$AL$5,IF(AND(K31>$AI$7,K31<$AM$5),$AN$5-$AL$5+K31,IF(AND(OR(K31>$AL$5,H31>$AO$5),AM31>=$AI$7,AM31<$AM$5,K31>$AM$5),(1+$AM$5-$AL$5)-AG31,0)))))))) -> 0
C32: =IF(Funcionários!C31=0,"",Funcionários!C31) | D32: =IF(D31=7,1,D31+1) -> 4 | E32: =IF(DAY(DATE('P Gerais'!$D$6,VLOOKUP($E$7,$W$7:$X$18,2,0),E31+1))>DAY(EOMONTH(DATE('P Gerais'!$D$6,VLOOKUP($E$7,$W$7:$X$18,2,0),E31),0)),DAY(DATE('P Gerais'!$D$6,VLOOKUP($E$7,$W$7:$X$18,2,0)+1,1)),DAY(DATE('P Gerais'!$D$6,VLOOKUP($E$7,$W$7:$X$18,2,0),E31+1))) -> 25 | F32: =VLOOKUP(D32,$AE$8:$AF$14,2,FALSE) -> Qua | M32: =IF(AND(H32=K32,H32<>0),$M$6-IF(J32<I32,$AJ$7+J32-I32,J32-I32),IF(H32>K32,(K32+1-H32)-IF(J32<I32,$AJ$7+J32-I32,J32-I32),(K32-H32)-IF(J32<I32,$AJ$7+J32-I32,J32-I32))) -> 0 | O32: =IF(OR(G32=0,G32="Férias",G32="Falta Justificada",G32="Feriado",G32="Folga (DSR)"),0,IF(G32="Falta Injustificada",HLOOKUP($F32,Jornada!$X$7:$AD$37,VLOOKUP(INDIRECT($C$5),Jornada!$C$8:$W$37,21,0),0),IF(HLOOKUP($F32,Jornada!$X$7:$AD$37,VLOOKUP(INDIRECT($C$5),Jornada!$C$8:$W$37,21,0),0)-M32>0,HLOOKUP($F32,Jornada!$X$7:$AD$37,VLOOKUP(INDIRECT($C$5),Jornada!$C$8:$W$37,21,0),0)-M32,0))) -> 0 | P32: =IF(HLOOKUP($F32,Jornada!$X$7:$AD$37,VLOOKUP(INDIRECT($C$5),Jornada!$C$8:$W$37,21,0),0)-M32<0,ABS(HLOOKUP($F32,Jornada!$X$7:$AD$37,VLOOKUP(INDIRECT($C$5),Jornada!$C$8:$W$37,21,0),0)-M32),0) -> 0 | Q32: =IF(G32="Normal",P32,IF(G32=0,0,IF(OR(G32="Feriado",G32="Férias"),IF(H32>K32,(K32+1-H32)-IF(J32<I32,$AJ$7+J32-I32,J32-I32),(K32-H32)-IF(J32<I32,$AJ$7+J32-I32,J32-I32)),IF(G32="Folga (DSR)",IF(H32>K32,(K32+1-H32)-IF(J32<I32,$AJ$7+J32-I32,J32-I32),(K32-H32)-IF(J32<I32,$AJ$7+J32-I32,J32-I32)),IF(G32="Falta Justificada",IF(H32>K32,(K32+1-H32)-IF(J32<I32,$AJ$7+J32-I32,J32-I32),(K32-H32)-IF(J32<I32,$AJ$7+J32-I32,J32-I32)),0))))) -> 0 | R32: =IF(Q32>$R$7,1,0) -> 0 | AB32: =AB31+1 -> 25 | AC32: =WEEKDAY(AB32) -> 4 | AG32: =IF(J32<I32,$AJ$7+J32-I32,J32-I32) -> 0 | AH32: =IF(HLOOKUP($F32,Jornada!$X$7:$AD$37,VLOOKUP(INDIRECT($C$5),Jornada!$C$8:$W$37,21,0),0)=0,0,VLOOKUP(INDIRECT($C$5),Jornada!$C$8:$H$37,4,0)) -> 0 | AI32: =IF(AND(I32=0,J32=0,OR(H32<>0,K32<>0),HLOOKUP($F32,Jornada!$X$7:$AD$37,VLOOKUP(INDIRECT($C$5),Jornada!$C$8:$W$37,21,0),0)>$AK$5,M32>$AK$5),VLOOKUP(INDIRECT($C$5),Jornada!$C$8:$H$37,6,0),IF(AG32>VLOOKUP(INDIRECT($C$5),Jornada!$C$8:$H$37,6,0),IF(VLOOKUP(INDIRECT($C$5),Jornada!$C$8:$H$37,6,0)<AG32,0,ABS(VLOOKUP(INDIRECT($C$5),Jornada!$C$8:$H$37,6,0))-AG32),0)) -> 0 | AJ32: =($AJ$7-K32)+H32 -> 1 | AK32: =IF(AJ32<$AK$7,$AK$7-AJ32,$AI$7) -> 0 | AL32: =HLOOKUP($F32,Jornada!$I$5:$V$37,VLOOKUP(INDIRECT($C$5),Jornada!$C$8:$W$37,21,0)+2,0) -> 0 | AM32: =HLOOKUP($F32,Jornada!$I$4:$V$37,VLOOKUP(INDIRECT($C$5),Jornada!$C$8:$W$37,21,0)+3,0) -> 0 | AN32: =IF(AND(AL32>=$AL$5,AL32<$AN$5,H32>=$AL$5,H32<AL32),AL32-H32,IF(AND(AL32>$AI$7,AL32<=$AM$5,H32>=$AL$5,H32<=$AN$5),$AN$5-H32+AL32,IF(AND(AL32>=$AI$7,AL32<=$AM$5,H32>=$AI$7,H32<=$AM$5,H32<AL32),H32-AL32,0))) -> 0 | AO32: =IF(AP32>Q32,0,AP32) -> 0 | AP32: =IF(Q32=0,0,IF(AND(AM32>=$AL$5,AM32<$AN$5,K32>=$AL$5,K32<$AM$5,K32>AM32),K32-AM32,IF(AND(AM32>=$AL$5,AM32<$AN$5,K32<$AN$5,K32>AM32),K32-$AL$5,IF(AND(AM32>=$AI$7,AM32<$AM$5,K32<$AM$5),K32-AM32,IF(AND(AM32<>AI31,AM32>=$AI$7,AM32<=$AM$5,K32>$AM$5,K32>AM32),$AM$5-AM32,IF(AND(K32>$AL$5,K32<$AN$5),K32-$AL$5,IF(AND(K32>$AI$7,K32<$AM$5),$AN$5-$AL$5+K32,IF(AND(OR(K32>$AL$5,H32>$AO$5),AM32>=$AI$7,AM32<$AM$5,K32>$AM$5),(1+$AM$5-$AL$5)-AG32,0)))))))) -> 0
C33: =IF(Funcionários!C32=0,"",Funcionários!C32) | D33: =IF(D32=7,1,D32+1) -> 5 | E33: =IF(DAY(DATE('P Gerais'!$D$6,VLOOKUP($E$7,$W$7:$X$18,2,0),E32+1))>DAY(EOMONTH(DATE('P Gerais'!$D$6,VLOOKUP($E$7,$W$7:$X$18,2,0),E32),0)),DAY(DATE('P Gerais'!$D$6,VLOOKUP($E$7,$W$7:$X$18,2,0)+1,1)),DAY(DATE('P Gerais'!$D$6,VLOOKUP($E$7,$W$7:$X$18,2,0),E32+1))) -> 26 | F33: =VLOOKUP(D33,$AE$8:$AF$14,2,FALSE) -> Qui | M33: =IF(AND(H33=K33,H33<>0),$M$6-IF(J33<I33,$AJ$7+J33-I33,J33-I33),IF(H33>K33,(K33+1-H33)-IF(J33<I33,$AJ$7+J33-I33,J33-I33),(K33-H33)-IF(J33<I33,$AJ$7+J33-I33,J33-I33))) -> 0 | O33: =IF(OR(G33=0,G33="Férias",G33="Falta Justificada",G33="Feriado",G33="Folga (DSR)"),0,IF(G33="Falta Injustificada",HLOOKUP($F33,Jornada!$X$7:$AD$37,VLOOKUP(INDIRECT($C$5),Jornada!$C$8:$W$37,21,0),0),IF(HLOOKUP($F33,Jornada!$X$7:$AD$37,VLOOKUP(INDIRECT($C$5),Jornada!$C$8:$W$37,21,0),0)-M33>0,HLOOKUP($F33,Jornada!$X$7:$AD$37,VLOOKUP(INDIRECT($C$5),Jornada!$C$8:$W$37,21,0),0)-M33,0))) -> 0 | P33: =IF(HLOOKUP($F33,Jornada!$X$7:$AD$37,VLOOKUP(INDIRECT($C$5),Jornada!$C$8:$W$37,21,0),0)-M33<0,ABS(HLOOKUP($F33,Jornada!$X$7:$AD$37,VLOOKUP(INDIRECT($C$5),Jornada!$C$8:$W$37,21,0),0)-M33),0) -> 0 | Q33: =IF(G33="Normal",P33,IF(G33=0,0,IF(OR(G33="Feriado",G33="Férias"),IF(H33>K33,(K33+1-H33)-IF(J33<I33,$AJ$7+J33-I33,J33-I33),(K33-H33)-IF(J33<I33,$AJ$7+J33-I33,J33-I33)),IF(G33="Folga (DSR)",IF(H33>K33,(K33+1-H33)-IF(J33<I33,$AJ$7+J33-I33,J33-I33),(K33-H33)-IF(J33<I33,$AJ$7+J33-I33,J33-I33)),IF(G33="Falta Justificada",IF(H33>K33,(K33+1-H33)-IF(J33<I33,$AJ$7+J33-I33,J33-I33),(K33-H33)-IF(J33<I33,$AJ$7+J33-I33,J33-I33)),0))))) -> 0 | R33: =IF(Q33>$R$7,1,0) -> 0 | AB33: =AB32+1 -> 26 | AC33: =WEEKDAY(AB33) -> 5 | AG33: =IF(J33<I33,$AJ$7+J33-I33,J33-I33) -> 0 | AH33: =IF(HLOOKUP($F33,Jornada!$X$7:$AD$37,VLOOKUP(INDIRECT($C$5),Jornada!$C$8:$W$37,21,0),0)=0,0,VLOOKUP(INDIRECT($C$5),Jornada!$C$8:$H$37,4,0)) -> 0 | AI33: =IF(AND(I33=0,J33=0,OR(H33<>0,K33<>0),HLOOKUP($F33,Jornada!$X$7:$AD$37,VLOOKUP(INDIRECT($C$5),Jornada!$C$8:$W$37,21,0),0)>$AK$5,M33>$AK$5),VLOOKUP(INDIRECT($C$5),Jornada!$C$8:$H$37,6,0),IF(AG33>VLOOKUP(INDIRECT($C$5),Jornada!$C$8:$H$37,6,0),IF(VLOOKUP(INDIRECT($C$5),Jornada!$C$8:$H$37,6,0)<AG33,0,ABS(VLOOKUP(INDIRECT($C$5),Jornada!$C$8:$H$37,6,0))-AG33),0)) -> 0 | AJ33: =($AJ$7-K33)+H33 -> 1 | AK33: =IF(AJ33<$AK$7,$AK$7-AJ33,$AI$7) -> 0 | AL33: =HLOOKUP($F33,Jornada!$I$5:$V$37,VLOOKUP(INDIRECT($C$5),Jornada!$C$8:$W$37,21,0)+2,0) -> 0 | AM33: =HLOOKUP($F33,Jornada!$I$4:$V$37,VLOOKUP(INDIRECT($C$5),Jornada!$C$8:$W$37,21,0)+3,0) -> 0 | AN33: =IF(AND(AL33>=$AL$5,AL33<$AN$5,H33>=$AL$5,H33<AL33),AL33-H33,IF(AND(AL33>$AI$7,AL33<=$AM$5,H33>=$AL$5,H33<=$AN$5),$AN$5-H33+AL33,IF(AND(AL33>=$AI$7,AL33<=$AM$5,H33>=$AI$7,H33<=$AM$5,H33<AL33),H33-AL33,0))) -> 0 | AO33: =IF(AP33>Q33,0,AP33) -> 0 | AP33: =IF(Q33=0,0,IF(AND(AM33>=$AL$5,AM33<$AN$5,K33>=$AL$5,K33<$AM$5,K33>AM33),K33-AM33,IF(AND(AM33>=$AL$5,AM33<$AN$5,K33<$AN$5,K33>AM33),K33-$AL$5,IF(AND(AM33>=$AI$7,AM33<$AM$5,K33<$AM$5),K33-AM33,IF(AND(AM33<>AI32,AM33>=$AI$7,AM33<=$AM$5,K33>$AM$5,K33>AM33),$AM$5-AM33,IF(AND(K33>$AL$5,K33<$AN$5),K33-$AL$5,IF(AND(K33>$AI$7,K33<$AM$5),$AN$5-$AL$5+K33,IF(AND(OR(K33>$AL$5,H33>$AO$5),AM33>=$AI$7,AM33<$AM$5,K33>$AM$5),(1+$AM$5-$AL$5)-AG33,0)))))))) -> 0
C34: =IF(Funcionários!C33=0,"",Funcionários!C33) | D34: =IF(D33=7,1,D33+1) -> 6 | E34: =IF(DAY(DATE('P Gerais'!$D$6,VLOOKUP($E$7,$W$7:$X$18,2,0),E33+1))>DAY(EOMONTH(DATE('P Gerais'!$D$6,VLOOKUP($E$7,$W$7:$X$18,2,0),E33),0)),DAY(DATE('P Gerais'!$D$6,VLOOKUP($E$7,$W$7:$X$18,2,0)+1,1)),DAY(DATE('P Gerais'!$D$6,VLOOKUP($E$7,$W$7:$X$18,2,0),E33+1))) -> 27 | F34: =VLOOKUP(D34,$AE$8:$AF$14,2,FALSE) -> Sex | M34: =IF(AND(H34=K34,H34<>0),$M$6-IF(J34<I34,$AJ$7+J34-I34,J34-I34),IF(H34>K34,(K34+1-H34)-IF(J34<I34,$AJ$7+J34-I34,J34-I34),(K34-H34)-IF(J34<I34,$AJ$7+J34-I34,J34-I34))) -> 0 | O34: =IF(OR(G34=0,G34="Férias",G34="Falta Justificada",G34="Feriado",G34="Folga (DSR)"),0,IF(G34="Falta Injustificada",HLOOKUP($F34,Jornada!$X$7:$AD$37,VLOOKUP(INDIRECT($C$5),Jornada!$C$8:$W$37,21,0),0),IF(HLOOKUP($F34,Jornada!$X$7:$AD$37,VLOOKUP(INDIRECT($C$5),Jornada!$C$8:$W$37,21,0),0)-M34>0,HLOOKUP($F34,Jornada!$X$7:$AD$37,VLOOKUP(INDIRECT($C$5),Jornada!$C$8:$W$37,21,0),0)-M34,0))) -> 0 | P34: =IF(HLOOKUP($F34,Jornada!$X$7:$AD$37,VLOOKUP(INDIRECT($C$5),Jornada!$C$8:$W$37,21,0),0)-M34<0,ABS(HLOOKUP($F34,Jornada!$X$7:$AD$37,VLOOKUP(INDIRECT($C$5),Jornada!$C$8:$W$37,21,0),0)-M34),0) -> 0 | Q34: =IF(G34="Normal",P34,IF(G34=0,0,IF(OR(G34="Feriado",G34="Férias"),IF(H34>K34,(K34+1-H34)-IF(J34<I34,$AJ$7+J34-I34,J34-I34),(K34-H34)-IF(J34<I34,$AJ$7+J34-I34,J34-I34)),IF(G34="Folga (DSR)",IF(H34>K34,(K34+1-H34)-IF(J34<I34,$AJ$7+J34-I34,J34-I34),(K34-H34)-IF(J34<I34,$AJ$7+J34-I34,J34-I34)),IF(G34="Falta Justificada",IF(H34>K34,(K34+1-H34)-IF(J34<I34,$AJ$7+J34-I34,J34-I34),(K34-H34)-IF(J34<I34,$AJ$7+J34-I34,J34-I34)),0))))) -> 0 | R34: =IF(Q34>$R$7,1,0) -> 0 | AB34: =AB33+1 -> 27 | AC34: =WEEKDAY(AB34) -> 6 | AG34: =IF(J34<I34,$AJ$7+J34-I34,J34-I34) -> 0 | AH34: =IF(HLOOKUP($F34,Jornada!$X$7:$AD$37,VLOOKUP(INDIRECT($C$5),Jornada!$C$8:$W$37,21,0),0)=0,0,VLOOKUP(INDIRECT($C$5),Jornada!$C$8:$H$37,4,0)) -> 0 | AI34: =IF(AND(I34=0,J34=0,OR(H34<>0,K34<>0),HLOOKUP($F34,Jornada!$X$7:$AD$37,VLOOKUP(INDIRECT($C$5),Jornada!$C$8:$W$37,21,0),0)>$AK$5,M34>$AK$5),VLOOKUP(INDIRECT($C$5),Jornada!$C$8:$H$37,6,0),IF(AG34>VLOOKUP(INDIRECT($C$5),Jornada!$C$8:$H$37,6,0),IF(VLOOKUP(INDIRECT($C$5),Jornada!$C$8:$H$37,6,0)<AG34,0,ABS(VLOOKUP(INDIRECT($C$5),Jornada!$C$8:$H$37,6,0))-AG34),0)) -> 0 | AJ34: =($AJ$7-K34)+H34 -> 1 | AK34: =IF(AJ34<$AK$7,$AK$7-AJ34,$AI$7) -> 0 | AL34: =HLOOKUP($F34,Jornada!$I$5:$V$37,VLOOKUP(INDIRECT($C$5),Jornada!$C$8:$W$37,21,0)+2,0) -> 0 | AM34: =HLOOKUP($F34,Jornada!$I$4:$V$37,VLOOKUP(INDIRECT($C$5),Jornada!$C$8:$W$37,21,0)+3,0) -> 0 | AN34: =IF(AND(AL34>=$AL$5,AL34<$AN$5,H34>=$AL$5,H34<AL34),AL34-H34,IF(AND(AL34>$AI$7,AL34<=$AM$5,H34>=$AL$5,H34<=$AN$5),$AN$5-H34+AL34,IF(AND(AL34>=$AI$7,AL34<=$AM$5,H34>=$AI$7,H34<=$AM$5,H34<AL34),H34-AL34,0))) -> 0 | AO34: =IF(AP34>Q34,0,AP34) -> 0 | AP34: =IF(Q34=0,0,IF(AND(AM34>=$AL$5,AM34<$AN$5,K34>=$AL$5,K34<$AM$5,K34>AM34),K34-AM34,IF(AND(AM34>=$AL$5,AM34<$AN$5,K34<$AN$5,K34>AM34),K34-$AL$5,IF(AND(AM34>=$AI$7,AM34<$AM$5,K34<$AM$5),K34-AM34,IF(AND(AM34<>AI33,AM34>=$AI$7,AM34<=$AM$5,K34>$AM$5,K34>AM34),$AM$5-AM34,IF(AND(K34>$AL$5,K34<$AN$5),K34-$AL$5,IF(AND(K34>$AI$7,K34<$AM$5),$AN$5-$AL$5+K34,IF(AND(OR(K34>$AL$5,H34>$AO$5),AM34>=$AI$7,AM34<$AM$5,K34>$AM$5),(1+$AM$5-$AL$5)-AG34,0)))))))) -> 0
C35: =IF(Funcionários!C34=0,"",Funcionários!C34) | D35: =IF(D34=7,1,D34+1) -> 7 | E35: =IF(DAY(DATE('P Gerais'!$D$6,VLOOKUP($E$7,$W$7:$X$18,2,0),E34+1))>DAY(EOMONTH(DATE('P Gerais'!$D$6,VLOOKUP($E$7,$W$7:$X$18,2,0),E34),0)),DAY(DATE('P Gerais'!$D$6,VLOOKUP($E$7,$W$7:$X$18,2,0)+1,1)),DAY(DATE('P Gerais'!$D$6,VLOOKUP($E$7,$W$7:$X$18,2,0),E34+1))) -> 28 | F35: =VLOOKUP(D35,$AE$8:$AF$14,2,FALSE) -> Sáb | M35: =IF(AND(H35=K35,H35<>0),$M$6-IF(J35<I35,$AJ$7+J35-I35,J35-I35),IF(H35>K35,(K35+1-H35)-IF(J35<I35,$AJ$7+J35-I35,J35-I35),(K35-H35)-IF(J35<I35,$AJ$7+J35-I35,J35-I35))) -> 0 | O35: =IF(OR(G35=0,G35="Férias",G35="Falta Justificada",G35="Feriado",G35="Folga (DSR)"),0,IF(G35="Falta Injustificada",HLOOKUP($F35,Jornada!$X$7:$AD$37,VLOOKUP(INDIRECT($C$5),Jornada!$C$8:$W$37,21,0),0),IF(HLOOKUP($F35,Jornada!$X$7:$AD$37,VLOOKUP(INDIRECT($C$5),Jornada!$C$8:$W$37,21,0),0)-M35>0,HLOOKUP($F35,Jornada!$X$7:$AD$37,VLOOKUP(INDIRECT($C$5),Jornada!$C$8:$W$37,21,0),0)-M35,0))) -> 0 | P35: =IF(HLOOKUP($F35,Jornada!$X$7:$AD$37,VLOOKUP(INDIRECT($C$5),Jornada!$C$8:$W$37,21,0),0)-M35<0,ABS(HLOOKUP($F35,Jornada!$X$7:$AD$37,VLOOKUP(INDIRECT($C$5),Jornada!$C$8:$W$37,21,0),0)-M35),0) -> 0 | Q35: =IF(G35="Normal",P35,IF(G35=0,0,IF(OR(G35="Feriado",G35="Férias"),IF(H35>K35,(K35+1-H35)-IF(J35<I35,$AJ$7+J35-I35,J35-I35),(K35-H35)-IF(J35<I35,$AJ$7+J35-I35,J35-I35)),IF(G35="Folga (DSR)",IF(H35>K35,(K35+1-H35)-IF(J35<I35,$AJ$7+J35-I35,J35-I35),(K35-H35)-IF(J35<I35,$AJ$7+J35-I35,J35-I35)),IF(G35="Falta Justificada",IF(H35>K35,(K35+1-H35)-IF(J35<I35,$AJ$7+J35-I35,J35-I35),(K35-H35)-IF(J35<I35,$AJ$7+J35-I35,J35-I35)),0))))) -> 0 | R35: =IF(Q35>$R$7,1,0) -> 0 | AB35: =IF(MONTH(AB34+1)<>MONTH(AB34),"",AB34+1) -> 28 | AC35: =WEEKDAY(AB35) -> 7 | AG35: =IF(J35<I35,$AJ$7+J35-I35,J35-I35) -> 0 | AH35: =IF(HLOOKUP($F35,Jornada!$X$7:$AD$37,VLOOKUP(INDIRECT($C$5),Jornada!$C$8:$W$37,21,0),0)=0,0,VLOOKUP(INDIRECT($C$5),Jornada!$C$8:$H$37,4,0)) -> 0 | AI35: =IF(AND(I35=0,J35=0,OR(H35<>0,K35<>0),HLOOKUP($F35,Jornada!$X$7:$AD$37,VLOOKUP(INDIRECT($C$5),Jornada!$C$8:$W$37,21,0),0)>$AK$5,M35>$AK$5),VLOOKUP(INDIRECT($C$5),Jornada!$C$8:$H$37,6,0),IF(AG35>VLOOKUP(INDIRECT($C$5),Jornada!$C$8:$H$37,6,0),IF(VLOOKUP(INDIRECT($C$5),Jornada!$C$8:$H$37,6,0)<AG35,0,ABS(VLOOKUP(INDIRECT($C$5),Jornada!$C$8:$H$37,6,0))-AG35),0)) -> 0 | AJ35: =($AJ$7-K35)+H35 -> 1 | AK35: =IF(AJ35<$AK$7,$AK$7-AJ35,$AI$7) -> 0 | AL35: =HLOOKUP($F35,Jornada!$I$5:$V$37,VLOOKUP(INDIRECT($C$5),Jornada!$C$8:$W$37,21,0)+2,0) -> 0 | AM35: =HLOOKUP($F35,Jornada!$I$4:$V$37,VLOOKUP(INDIRECT($C$5),Jornada!$C$8:$W$37,21,0)+3,0) -> 0 | AN35: =IF(AND(AL35>=$AL$5,AL35<$AN$5,H35>=$AL$5,H35<AL35),AL35-H35,IF(AND(AL35>$AI$7,AL35<=$AM$5,H35>=$AL$5,H35<=$AN$5),$AN$5-H35+AL35,IF(AND(AL35>=$AI$7,AL35<=$AM$5,H35>=$AI$7,H35<=$AM$5,H35<AL35),H35-AL35,0))) -> 0 | AO35: =IF(AP35>Q35,0,AP35) -> 0 | AP35: =IF(Q35=0,0,IF(AND(AM35>=$AL$5,AM35<$AN$5,K35>=$AL$5,K35<$AM$5,K35>AM35),K35-AM35,IF(AND(AM35>=$AL$5,AM35<$AN$5,K35<$AN$5,K35>AM35),K35-$AL$5,IF(AND(AM35>=$AI$7,AM35<$AM$5,K35<$AM$5),K35-AM35,IF(AND(AM35<>AI34,AM35>=$AI$7,AM35<=$AM$5,K35>$AM$5,K35>AM35),$AM$5-AM35,IF(AND(K35>$AL$5,K35<$AN$5),K35-$AL$5,IF(AND(K35>$AI$7,K35<$AM$5),$AN$5-$AL$5+K35,IF(AND(OR(K35>$AL$5,H35>$AO$5),AM35>=$AI$7,AM35<$AM$5,K35>$AM$5),(1+$AM$5-$AL$5)-AG35,0)))))))) -> 0
C36: =IF(Funcionários!C35=0,"",Funcionários!C35) | D36: =IF(D35=7,1,D35+1) -> 1 | E36: =IF(DAY(DATE('P Gerais'!$D$6,VLOOKUP($E$7,$W$7:$X$18,2,0),E35+1))>DAY(EOMONTH(DATE('P Gerais'!$D$6,VLOOKUP($E$7,$W$7:$X$18,2,0),E35),0)),DAY(DATE('P Gerais'!$D$6,VLOOKUP($E$7,$W$7:$X$18,2,0)+1,1)),DAY(DATE('P Gerais'!$D$6,VLOOKUP($E$7,$W$7:$X$18,2,0),E35+1))) -> 29 | F36: =VLOOKUP(D36,$AE$8:$AF$14,2,FALSE) -> Dom | M36: =IF(AND(H36=K36,H36<>0),$M$6-IF(J36<I36,$AJ$7+J36-I36,J36-I36),IF(H36>K36,(K36+1-H36)-IF(J36<I36,$AJ$7+J36-I36,J36-I36),(K36-H36)-IF(J36<I36,$AJ$7+J36-I36,J36-I36))) -> 0 | O36: =IF(OR(G36=0,G36="Férias",G36="Falta Justificada",G36="Feriado",G36="Folga (DSR)"),0,IF(G36="Falta Injustificada",HLOOKUP($F36,Jornada!$X$7:$AD$37,VLOOKUP(INDIRECT($C$5),Jornada!$C$8:$W$37,21,0),0),IF(HLOOKUP($F36,Jornada!$X$7:$AD$37,VLOOKUP(INDIRECT($C$5),Jornada!$C$8:$W$37,21,0),0)-M36>0,HLOOKUP($F36,Jornada!$X$7:$AD$37,VLOOKUP(INDIRECT($C$5),Jornada!$C$8:$W$37,21,0),0)-M36,0))) -> 0 | P36: =IF(HLOOKUP($F36,Jornada!$X$7:$AD$37,VLOOKUP(INDIRECT($C$5),Jornada!$C$8:$W$37,21,0),0)-M36<0,ABS(HLOOKUP($F36,Jornada!$X$7:$AD$37,VLOOKUP(INDIRECT($C$5),Jornada!$C$8:$W$37,21,0),0)-M36),0) -> 0 | Q36: =IF(G36="Normal",P36,IF(G36=0,0,IF(OR(G36="Feriado",G36="Férias"),IF(H36>K36,(K36+1-H36)-IF(J36<I36,$AJ$7+J36-I36,J36-I36),(K36-H36)-IF(J36<I36,$AJ$7+J36-I36,J36-I36)),IF(G36="Folga (DSR)",IF(H36>K36,(K36+1-H36)-IF(J36<I36,$AJ$7+J36-I36,J36-I36),(K36-H36)-IF(J36<I36,$AJ$7+J36-I36,J36-I36)),IF(G36="Falta Justificada",IF(H36>K36,(K36+1-H36)-IF(J36<I36,$AJ$7+J36-I36,J36-I36),(K36-H36)-IF(J36<I36,$AJ$7+J36-I36,J36-I36)),0))))) -> 0 | R36: =IF(Q36>$R$7,1,0) -> 0 | AB36: =IF(MONTH(AB35+1)<>MONTH(AB35),"",IF(AB35="","",AB35+1)) -> 29 | AC36: =IF(ISERROR(WEEKDAY(AB36)),"",WEEKDAY(AB36)) -> 1 | AG36: =IF(J36<I36,$AJ$7+J36-I36,J36-I36) -> 0 | AH36: =IF(HLOOKUP($F36,Jornada!$X$7:$AD$37,VLOOKUP(INDIRECT($C$5),Jornada!$C$8:$W$37,21,0),0)=0,0,VLOOKUP(INDIRECT($C$5),Jornada!$C$8:$H$37,4,0)) -> 0 | AI36: =IF(AND(I36=0,J36=0,OR(H36<>0,K36<>0),HLOOKUP($F36,Jornada!$X$7:$AD$37,VLOOKUP(INDIRECT($C$5),Jornada!$C$8:$W$37,21,0),0)>$AK$5,M36>$AK$5),VLOOKUP(INDIRECT($C$5),Jornada!$C$8:$H$37,6,0),IF(AG36>VLOOKUP(INDIRECT($C$5),Jornada!$C$8:$H$37,6,0),IF(VLOOKUP(INDIRECT($C$5),Jornada!$C$8:$H$37,6,0)<AG36,0,ABS(VLOOKUP(INDIRECT($C$5),Jornada!$C$8:$H$37,6,0))-AG36),0)) -> 0 | AJ36: =($AJ$7-K36)+H36 -> 1 | AK36: =IF(AJ36<$AK$7,$AK$7-AJ36,$AI$7) -> 0 | AL36: =HLOOKUP($F36,Jornada!$I$5:$V$37,VLOOKUP(INDIRECT($C$5),Jornada!$C$8:$W$37,21,0)+2,0) -> 0 | AM36: =HLOOKUP($F36,Jornada!$I$4:$V$37,VLOOKUP(INDIRECT($C$5),Jornada!$C$8:$W$37,21,0)+3,0) -> 0 | AN36: =IF(AND(AL36>=$AL$5,AL36<$AN$5,H36>=$AL$5,H36<AL36),AL36-H36,IF(AND(AL36>$AI$7,AL36<=$AM$5,H36>=$AL$5,H36<=$AN$5),$AN$5-H36+AL36,IF(AND(AL36>=$AI$7,AL36<=$AM$5,H36>=$AI$7,H36<=$AM$5,H36<AL36),H36-AL36,0))) -> 0 | AO36: =IF(AP36>Q36,0,AP36) -> 0 | AP36: =IF(Q36=0,0,IF(AND(AM36>=$AL$5,AM36<$AN$5,K36>=$AL$5,K36<$AM$5,K36>AM36),K36-AM36,IF(AND(AM36>=$AL$5,AM36<$AN$5,K36<$AN$5,K36>AM36),K36-$AL$5,IF(AND(AM36>=$AI$7,AM36<$AM$5,K36<$AM$5),K36-AM36,IF(AND(AM36<>AI35,AM36>=$AI$7,AM36<=$AM$5,K36>$AM$5,K36>AM36),$AM$5-AM36,IF(AND(K36>$AL$5,K36<$AN$5),K36-$AL$5,IF(AND(K36>$AI$7,K36<$AM$5),$AN$5-$AL$5+K36,IF(AND(OR(K36>$AL$5,H36>$AO$5),AM36>=$AI$7,AM36<$AM$5,K36>$AM$5),(1+$AM$5-$AL$5)-AG36,0)))))))) -> 0
C37: =IF(Funcionários!C36=0,"",Funcionários!C36) | D37: =IF(D36=7,1,D36+1) -> 2 | E37: =IF(DAY(DATE('P Gerais'!$D$6,VLOOKUP($E$7,$W$7:$X$18,2,0),E36+1))>DAY(EOMONTH(DATE('P Gerais'!$D$6,VLOOKUP($E$7,$W$7:$X$18,2,0),E36),0)),DAY(DATE('P Gerais'!$D$6,VLOOKUP($E$7,$W$7:$X$18,2,0)+1,1)),DAY(DATE('P Gerais'!$D$6,VLOOKUP($E$7,$W$7:$X$18,2,0),E36+1))) -> 30 | F37: =VLOOKUP(D37,$AE$8:$AF$14,2,FALSE) -> Seg | M37: =IF(AND(H37=K37,H37<>0),$M$6-IF(J37<I37,$AJ$7+J37-I37,J37-I37),IF(H37>K37,(K37+1-H37)-IF(J37<I37,$AJ$7+J37-I37,J37-I37),(K37-H37)-IF(J37<I37,$AJ$7+J37-I37,J37-I37))) -> 0 | O37: =IF(OR(G37=0,G37="Férias",G37="Falta Justificada",G37="Feriado",G37="Folga (DSR)"),0,IF(G37="Falta Injustificada",HLOOKUP($F37,Jornada!$X$7:$AD$37,VLOOKUP(INDIRECT($C$5),Jornada!$C$8:$W$37,21,0),0),IF(HLOOKUP($F37,Jornada!$X$7:$AD$37,VLOOKUP(INDIRECT($C$5),Jornada!$C$8:$W$37,21,0),0)-M37>0,HLOOKUP($F37,Jornada!$X$7:$AD$37,VLOOKUP(INDIRECT($C$5),Jornada!$C$8:$W$37,21,0),0)-M37,0))) -> 0 | P37: =IF(HLOOKUP($F37,Jornada!$X$7:$AD$37,VLOOKUP(INDIRECT($C$5),Jornada!$C$8:$W$37,21,0),0)-M37<0,ABS(HLOOKUP($F37,Jornada!$X$7:$AD$37,VLOOKUP(INDIRECT($C$5),Jornada!$C$8:$W$37,21,0),0)-M37),0) -> 0 | Q37: =IF(G37="Normal",P37,IF(G37=0,0,IF(OR(G37="Feriado",G37="Férias"),IF(H37>K37,(K37+1-H37)-IF(J37<I37,$AJ$7+J37-I37,J37-I37),(K37-H37)-IF(J37<I37,$AJ$7+J37-I37,J37-I37)),IF(G37="Folga (DSR)",IF(H37>K37,(K37+1-H37)-IF(J37<I37,$AJ$7+J37-I37,J37-I37),(K37-H37)-IF(J37<I37,$AJ$7+J37-I37,J37-I37)),IF(G37="Falta Justificada",IF(H37>K37,(K37+1-H37)-IF(J37<I37,$AJ$7+J37-I37,J37-I37),(K37-H37)-IF(J37<I37,$AJ$7+J37-I37,J37-I37)),0))))) -> 0 | R37: =IF(Q37>$R$7,1,0) -> 0 | AB37: =IF(AB36="","",IF(MONTH(AB36+1)<>MONTH(AB36),"",AB36+1)) -> 30 | AC37: =IF(ISERROR(WEEKDAY(AB37)),"",WEEKDAY(AB37)) -> 2 | AG37: =IF(J37<I37,$AJ$7+J37-I37,J37-I37) -> 0 | AH37: =IF(HLOOKUP($F37,Jornada!$X$7:$AD$37,VLOOKUP(INDIRECT($C$5),Jornada!$C$8:$W$37,21,0),0)=0,0,VLOOKUP(INDIRECT($C$5),Jornada!$C$8:$H$37,4,0)) -> 0 | AI37: =IF(AND(I37=0,J37=0,OR(H37<>0,K37<>0),HLOOKUP($F37,Jornada!$X$7:$AD$37,VLOOKUP(INDIRECT($C$5),Jornada!$C$8:$W$37,21,0),0)>$AK$5,M37>$AK$5),VLOOKUP(INDIRECT($C$5),Jornada!$C$8:$H$37,6,0),IF(AG37>VLOOKUP(INDIRECT($C$5),Jornada!$C$8:$H$37,6,0),IF(VLOOKUP(INDIRECT($C$5),Jornada!$C$8:$H$37,6,0)<AG37,0,ABS(VLOOKUP(INDIRECT($C$5),Jornada!$C$8:$H$37,6,0))-AG37),0)) -> 0 | AJ37: =($AJ$7-K37)+H37 -> 1 | AK37: =IF(AJ37<$AK$7,$AK$7-AJ37,$AI$7) -> 0 | AL37: =HLOOKUP($F37,Jornada!$I$5:$V$37,VLOOKUP(INDIRECT($C$5),Jornada!$C$8:$W$37,21,0)+2,0) -> 0 | AM37: =HLOOKUP($F37,Jornada!$I$4:$V$37,VLOOKUP(INDIRECT($C$5),Jornada!$C$8:$W$37,21,0)+3,0) -> 0 | AN37: =IF(AND(AL37>=$AL$5,AL37<$AN$5,H37>=$AL$5,H37<AL37),AL37-H37,IF(AND(AL37>$AI$7,AL37<=$AM$5,H37>=$AL$5,H37<=$AN$5),$AN$5-H37+AL37,IF(AND(AL37>=$AI$7,AL37<=$AM$5,H37>=$AI$7,H37<=$AM$5,H37<AL37),H37-AL37,0))) -> 0 | AO37: =IF(AP37>Q37,0,AP37) -> 0 | AP37: =IF(Q37=0,0,IF(AND(AM37>=$AL$5,AM37<$AN$5,K37>=$AL$5,K37<$AM$5,K37>AM37),K37-AM37,IF(AND(AM37>=$AL$5,AM37<$AN$5,K37<$AN$5,K37>AM37),K37-$AL$5,IF(AND(AM37>=$AI$7,AM37<$AM$5,K37<$AM$5),K37-AM37,IF(AND(AM37<>AI36,AM37>=$AI$7,AM37<=$AM$5,K37>$AM$5,K37>AM37),$AM$5-AM37,IF(AND(K37>$AL$5,K37<$AN$5),K37-$AL$5,IF(AND(K37>$AI$7,K37<$AM$5),$AN$5-$AL$5+K37,IF(AND(OR(K37>$AL$5,H37>$AO$5),AM37>=$AI$7,AM37<$AM$5,K37>$AM$5),(1+$AM$5-$AL$5)-AG37,0)))))))) -> 0
D38: =IF(D37=7,1,D37+1) -> 3 | E38: =IF(DAY(DATE('P Gerais'!$D$6,VLOOKUP($E$7,$W$7:$X$18,2,0),E37+1))>DAY(EOMONTH(DATE('P Gerais'!$D$6,VLOOKUP($E$7,$W$7:$X$18,2,0),E37),0)),DAY(DATE('P Gerais'!$D$6,VLOOKUP($E$7,$W$7:$X$18,2,0)+1,1)),DAY(DATE('P Gerais'!$D$6,VLOOKUP($E$7,$W$7:$X$18,2,0),E37+1))) -> 31 | F38: =VLOOKUP(D38,$AE$8:$AF$14,2,FALSE) -> Ter | M38: =IF(AND(H38=K38,H38<>0),$M$6-IF(J38<I38,$AJ$7+J38-I38,J38-I38),IF(H38>K38,(K38+1-H38)-IF(J38<I38,$AJ$7+J38-I38,J38-I38),(K38-H38)-IF(J38<I38,$AJ$7+J38-I38,J38-I38))) -> 0 | O38: =IF(OR(G38=0,G38="Férias",G38="Falta Justificada",G38="Feriado",G38="Folga (DSR)"),0,IF(G38="Falta Injustificada",HLOOKUP($F38,Jornada!$X$7:$AD$37,VLOOKUP(INDIRECT($C$5),Jornada!$C$8:$W$37,21,0),0),IF(HLOOKUP($F38,Jornada!$X$7:$AD$37,VLOOKUP(INDIRECT($C$5),Jornada!$C$8:$W$37,21,0),0)-M38>0,HLOOKUP($F38,Jornada!$X$7:$AD$37,VLOOKUP(INDIRECT($C$5),Jornada!$C$8:$W$37,21,0),0)-M38,0))) -> 0 | P38: =IF(HLOOKUP($F38,Jornada!$X$7:$AD$37,VLOOKUP(INDIRECT($C$5),Jornada!$C$8:$W$37,21,0),0)-M38<0,ABS(HLOOKUP($F38,Jornada!$X$7:$AD$37,VLOOKUP(INDIRECT($C$5),Jornada!$C$8:$W$37,21,0),0)-M38),0) -> 0 | Q38: =IF(G38="Normal",P38,IF(G38=0,0,IF(OR(G38="Feriado",G38="Férias"),IF(H38>K38,(K38+1-H38)-IF(J38<I38,$AJ$7+J38-I38,J38-I38),(K38-H38)-IF(J38<I38,$AJ$7+J38-I38,J38-I38)),IF(G38="Folga (DSR)",IF(H38>K38,(K38+1-H38)-IF(J38<I38,$AJ$7+J38-I38,J38-I38),(K38-H38)-IF(J38<I38,$AJ$7+J38-I38,J38-I38)),IF(G38="Falta Justificada",IF(H38>K38,(K38+1-H38)-IF(J38<I38,$AJ$7+J38-I38,J38-I38),(K38-H38)-IF(J38<I38,$AJ$7+J38-I38,J38-I38)),0))))) -> 0 | R38: =IF(Q38>$R$7,1,0) -> 0 | AB38: =IF(AB37="","",IF(MONTH(AB37+1)<>MONTH(AB37),"",AB37+1)) -> 31 | AC38: =IF(ISERROR(WEEKDAY(AB38)),"",WEEKDAY(AB38)) -> 3 | AG38: =IF(J38<I38,$AJ$7+J38-I38,J38-I38) -> 0 | AH38: =IF(HLOOKUP($F38,Jornada!$X$7:$AD$37,VLOOKUP(INDIRECT($C$5),Jornada!$C$8:$W$37,21,0),0)=0,0,VLOOKUP(INDIRECT($C$5),Jornada!$C$8:$H$37,4,0)) -> 0 | AI38: =IF(AND(I38=0,J38=0,OR(H38<>0,K38<>0),HLOOKUP($F38,Jornada!$X$7:$AD$37,VLOOKUP(INDIRECT($C$5),Jornada!$C$8:$W$37,21,0),0)>$AK$5,M38>$AK$5),VLOOKUP(INDIRECT($C$5),Jornada!$C$8:$H$37,6,0),IF(AG38>VLOOKUP(INDIRECT($C$5),Jornada!$C$8:$H$37,6,0),IF(VLOOKUP(INDIRECT($C$5),Jornada!$C$8:$H$37,6,0)<AG38,0,ABS(VLOOKUP(INDIRECT($C$5),Jornada!$C$8:$H$37,6,0))-AG38),0)) -> 0 | AJ38: =($AJ$7-K38)+H38 -> 1 | AK38: =IF(AJ38<$AK$7,$AK$7-AJ38,$AI$7) -> 0 | AL38: =HLOOKUP($F38,Jornada!$I$5:$V$37,VLOOKUP(INDIRECT($C$5),Jornada!$C$8:$W$37,21,0)+2,0) -> 0 | AM38: =HLOOKUP($F38,Jornada!$I$4:$V$37,VLOOKUP(INDIRECT($C$5),Jornada!$C$8:$W$37,21,0)+3,0) -> 0 | AN38: =IF(AND(AL38>=$AL$5,AL38<$AN$5,H38>=$AL$5,H38<AL38),AL38-H38,IF(AND(AL38>$AI$7,AL38<=$AM$5,H38>=$AL$5,H38<=$AN$5),$AN$5-H38+AL38,IF(AND(AL38>=$AI$7,AL38<=$AM$5,H38>=$AI$7,H38<=$AM$5,H38<AL38),H38-AL38,0))) -> 0 | AO38: =IF(AP38>Q38,0,AP38) -> 0 | AP38: =IF(Q38=0,0,IF(AND(AM38>=$AL$5,AM38<$AN$5,K38>=$AL$5,K38<$AM$5,K38>AM38),K38-AM38,IF(AND(AM38>=$AL$5,AM38<$AN$5,K38<$AN$5,K38>AM38),K38-$AL$5,IF(AND(AM38>=$AI$7,AM38<$AM$5,K38<$AM$5),K38-AM38,IF(AND(AM38<>AI37,AM38>=$AI$7,AM38<=$AM$5,K38>$AM$5,K38>AM38),$AM$5-AM38,IF(AND(K38>$AL$5,K38<$AN$5),K38-$AL$5,IF(AND(K38>$AI$7,K38<$AM$5),$AN$5-$AL$5+K38,IF(AND(OR(K38>$AL$5,H38>$AO$5),AM38>=$AI$7,AM38<$AM$5,K38>$AM$5),(1+$AM$5-$AL$5)-AG38,0)))))))) -> 0
E39: =EOMONTH(AB8,0) -> 31 | F39: =DAY(E39) -> 31 | G39: =COUNTIF(F8:F38,"Dom")+COUNTIF(G8:G38,"Feriado") -> 5 | H39: =(SUM(Q8:Q38)/(F39-G39))*G39 -> 0
H40: =IF(INDIRECT($C$5)="",0,VLOOKUP(INDIRECT($C$5),Funcionários!$C$7:$E$36,3,0)+IF(VLOOKUP(INDIRECT($C$5),Jornada!$C$8:$E$37,2,0)="Sim",IF('P Gerais'!$I$8<>0,VLOOKUP(INDIRECT($C$5),Funcionários!$C$7:$E$36,3,0)*'P Gerais'!$L$14,'P Gerais'!$I$8*'P Gerais'!$L$14),0)+IF(VLOOKUP(INDIRECT($C$5),Jornada!$C$8:$E$37,3,0)="Sim",VLOOKUP(INDIRECT($C$5),Funcionários!$C$7:$E$36,3,0)*'P Gerais'!$K$14,0)) -> 0 | I40: =VLOOKUP(INDIRECT($C$5),Jornada!$C$8:$AF$37,30,0) -> 0 | J40: valor p/ hora | K40: =IF(I40=0,0,H40/I40) -> 0
B41: Seg | C41: Horas Extras às Segundas | F41: =SUMIFS($Q$8:$Q$38,$F$8:$F$38,$B41,$G$8:$G$38,"Normal") -> 0 | G41: =IF($M$41="Sistema de banco de horas",0,'P Gerais'!$C$14) -> 0.5 | H41: =IF($M$41="Sistema de banco de horas",0,$K$40*(1+G41)*(F41*24)) -> 0 | I41: =IF(SUMIF($F$8:$F$38,$B41,$Q$8:$Q$38)-SUMIFS($M$8:$M$38,$F$8:$F$38,$B41,$G$8:$G$38,"Feriado")-SUMIFS($M$8:$M$38,$F$8:$F$38,$B41,$G$8:$G$38,"Folga (DSR)")-SUMIFS($M$8:$M$38,$F$8:$F$38,$B41,$G$8:$G$38,"Férias")-SUMIF($F$8:$F$38,$B41,$AN$8:$AN$38)-SUMIF($F$8:$F$38,$B41,$AO$8:$AO$38)<0,0,SUMIF($F$8:$F$38,$B41,$Q$8:$Q$38)-SUMIFS($M$8:$M$38,$F$8:$F$38,$B41,$G$8:$G$38,"Feriado")-SUMIFS($M$8:$M$38,$F$8:$F$38,$B41,$G$8:$G$38,"Folga (DSR)")-SUMIFS($M$8:$M$38,$F$8:$F$38,$B41,$G$8:$G$38,"Férias")-SUMIF($F$8:$F$38,$B41,$AN$8:$AN$38)-SUMIF($F$8:$F$38,$B41,$AO$8:$AO$38)) -> 0 | J41: =H41 -> 0 | M41: ='P Gerais'!I10 -> 0
B42: Ter | C42: Horas Extras às Terças | F42: =SUMIFS($Q$8:$Q$38,$F$8:$F$38,$B42,$G$8:$G$38,"Normal") -> 0 | G42: =IF($M$41="Sistema de banco de horas",0,'P Gerais'!$C$14) -> 0.5 | H42: =IF($M$41="Sistema de banco de horas",0,$K$40*(1+G42)*(F42*24)) -> 0 | I42: =IF(SUMIF($F$8:$F$38,$B42,$Q$8:$Q$38)-SUMIFS($M$8:$M$38,$F$8:$F$38,$B42,$G$8:$G$38,"Feriado")-SUMIFS($M$8:$M$38,$F$8:$F$38,$B42,$G$8:$G$38,"Folga (DSR)")-SUMIFS($M$8:$M$38,$F$8:$F$38,$B42,$G$8:$G$38,"Férias")-SUMIF($F$8:$F$38,$B42,$AN$8:$AN$38)-SUMIF($F$8:$F$38,$B42,$AO$8:$AO$38)<0,0,SUMIF($F$8:$F$38,$B42,$Q$8:$Q$38)-SUMIFS($M$8:$M$38,$F$8:$F$38,$B42,$G$8:$G$38,"Feriado")-SUMIFS($M$8:$M$38,$F$8:$F$38,$B42,$G$8:$G$38,"Folga (DSR)")-SUMIFS($M$8:$M$38,$F$8:$F$38,$B42,$G$8:$G$38,"Férias")-SUMIF($F$8:$F$38,$B42,$AN$8:$AN$38)-SUMIF($F$8:$F$38,$B42,$AO$8:$AO$38)) -> 0 | J42: =H42 -> 0
B43: Qua | C43: Horas Extras às Quartas | F43: =SUMIFS($Q$8:$Q$38,$F$8:$F$38,$B43,$G$8:$G$38,"Normal") -> 0 | G43: =IF($M$41="Sistema de banco de horas",0,'P Gerais'!$C$14) -> 0.5 | H43: =IF($M$41="Sistema de banco de horas",0,$K$40*(1+G43)*(F43*24)) -> 0 | I43: =IF(SUMIF($F$8:$F$38,$B43,$Q$8:$Q$38)-SUMIFS($M$8:$M$38,$F$8:$F$38,$B43,$G$8:$G$38,"Feriado")-SUMIFS($M$8:$M$38,$F$8:$F$38,$B43,$G$8:$G$38,"Folga (DSR)")-SUMIFS($M$8:$M$38,$F$8:$F$38,$B43,$G$8:$G$38,"Férias")-SUMIF($F$8:$F$38,$B43,$AN$8:$AN$38)-SUMIF($F$8:$F$38,$B43,$AO$8:$AO$38)<0,0,SUMIF($F$8:$F$38,$B43,$Q$8:$Q$38)-SUMIFS($M$8:$M$38,$F$8:$F$38,$B43,$G$8:$G$38,"Feriado")-SUMIFS($M$8:$M$38,$F$8:$F$38,$B43,$G$8:$G$38,"Folga (DSR)")-SUMIFS($M$8:$M$38,$F$8:$F$38,$B43,$G$8:$G$38,"Férias")-SUMIF($F$8:$F$38,$B43,$AN$8:$AN$38)-SUMIF($F$8:$F$38,$B43,$AO$8:$AO$38)) -> 0 | J43: =H43 -> 0
B44: Qui | C44: Horas Extras às Quintas | F44: =SUMIFS($Q$8:$Q$38,$F$8:$F$38,$B44,$G$8:$G$38,"Normal") -> 0 | G44: =IF($M$41="Sistema de banco de horas",0,'P Gerais'!$C$14) -> 0.5 | H44: =IF($M$41="Sistema de banco de horas",0,$K$40*(1+G44)*(F44*24)) -> 0 | I44: =IF(SUMIF($F$8:$F$38,$B44,$Q$8:$Q$38)-SUMIFS($M$8:$M$38,$F$8:$F$38,$B44,$G$8:$G$38,"Feriado")-SUMIFS($M$8:$M$38,$F$8:$F$38,$B44,$G$8:$G$38,"Folga (DSR)")-SUMIFS($M$8:$M$38,$F$8:$F$38,$B44,$G$8:$G$38,"Férias")-SUMIF($F$8:$F$38,$B44,$AN$8:$AN$38)-SUMIF($F$8:$F$38,$B44,$AO$8:$AO$38)<0,0,SUMIF($F$8:$F$38,$B44,$Q$8:$Q$38)-SUMIFS($M$8:$M$38,$F$8:$F$38,$B44,$G$8:$G$38,"Feriado")-SUMIFS($M$8:$M$38,$F$8:$F$38,$B44,$G$8:$G$38,"Folga (DSR)")-SUMIFS($M$8:$M$38,$F$8:$F$38,$B44,$G$8:$G$38,"Férias")-SUMIF($F$8:$F$38,$B44,$AN$8:$AN$38)-SUMIF($F$8:$F$38,$B44,$AO$8:$AO$38)) -> 0 | J44: =H44 -> 0
B45: Sex | C45: Horas Extras às Sextas | F45: =SUMIFS($Q$8:$Q$38,$F$8:$F$38,$B45,$G$8:$G$38,"Normal") -> 0 | G45: =IF($M$41="Sistema de banco de horas",0,'P Gerais'!$C$14) -> 0.5 | H45: =IF($M$41="Sistema de banco de horas",0,$K$40*(1+G45)*(F45*24)) -> 0 | I45: =IF(SUMIF($F$8:$F$38,$B45,$Q$8:$Q$38)-SUMIFS($M$8:$M$38,$F$8:$F$38,$B45,$G$8:$G$38,"Feriado")-SUMIFS($M$8:$M$38,$F$8:$F$38,$B45,$G$8:$G$38,"Folga (DSR)")-SUMIFS($M$8:$M$38,$F$8:$F$38,$B45,$G$8:$G$38,"Férias")-SUMIF($F$8:$F$38,$B45,$AN$8:$AN$38)-SUMIF($F$8:$F$38,$B45,$AO$8:$AO$38)<0,0,SUMIF($F$8:$F$38,$B45,$Q$8:$Q$38)-SUMIFS($M$8:$M$38,$F$8:$F$38,$B45,$G$8:$G$38,"Feriado")-SUMIFS($M$8:$M$38,$F$8:$F$38,$B45,$G$8:$G$38,"Folga (DSR)")-SUMIFS($M$8:$M$38,$F$8:$F$38,$B45,$G$8:$G$38,"Férias")-SUMIF($F$8:$F$38,$B45,$AN$8:$AN$38)-SUMIF($F$8:$F$38,$B45,$AO$8:$AO$38)) -> 0 | J45: =H45 -> 0
B46: Sáb | C46: Horas Extras aos Sábados | F46: =SUMIFS($Q$8:$Q$38,$F$8:$F$38,$B46,$G$8:$G$38,"Normal") -> 0 | G46: =IF($M$41="Sistema de banco de horas",0,'P Gerais'!$E$14) -> 0.5 | H46: =IF($M$41="Sistema de banco de horas",0,$K$40*(1+G46)*(F46*24)) -> 0 | I46: =IF(SUMIF($F$8:$F$38,$B46,$Q$8:$Q$38)-SUMIFS($M$8:$M$38,$F$8:$F$38,$B46,$G$8:$G$38,"Feriado")-SUMIFS($M$8:$M$38,$F$8:$F$38,$B46,$G$8:$G$38,"Folga (DSR)")-SUMIFS($M$8:$M$38,$F$8:$F$38,$B46,$G$8:$G$38,"Férias")-SUMIF($F$8:$F$38,$B46,$AN$8:$AN$38)-SUMIF($F$8:$F$38,$B46,$AO$8:$AO$38)<0,0,SUMIF($F$8:$F$38,$B46,$Q$8:$Q$38)-SUMIFS($M$8:$M$38,$F$8:$F$38,$B46,$G$8:$G$38,"Feriado")-SUMIFS($M$8:$M$38,$F$8:$F$38,$B46,$G$8:$G$38,"Folga (DSR)")-SUMIFS($M$8:$M$38,$F$8:$F$38,$B46,$G$8:$G$38,"Férias")-SUMIF($F$8:$F$38,$B46,$AN$8:$AN$38)-SUMIF($F$8:$F$38,$B46,$AO$8:$AO$38)) -> 0 | J46: =H46 -> 0
B47: Dom | C47: Horas Extras aos Domingos | F47: =SUMIFS($Q$8:$Q$38,$F$8:$F$38,$B47,$G$8:$G$38,"Normal") -> 0 | G47: =IF($M$41="Sistema de banco de horas",0,'P Gerais'!$F$14) -> 1 | H47: =IF($M$41="Sistema de banco de horas",0,$K$40*(1+G47)*(F47*24)) -> 0 | I47: =IF(SUMIF($F$8:$F$38,$B47,$Q$8:$Q$38)-SUMIFS($M$8:$M$38,$F$8:$F$38,$B47,$G$8:$G$38,"Feriado")-SUMIFS($M$8:$M$38,$F$8:$F$38,$B47,$G$8:$G$38,"Folga (DSR)")-SUMIFS($M$8:$M$38,$F$8:$F$38,$B47,$G$8:$G$38,"Férias")-SUMIF($F$8:$F$38,$B47,$AN$8:$AN$38)-SUMIF($F$8:$F$38,$B47,$AO$8:$AO$38)<0,0,SUMIF($F$8:$F$38,$B47,$Q$8:$Q$38)-SUMIFS($M$8:$M$38,$F$8:$F$38,$B47,$G$8:$G$38,"Feriado")-SUMIFS($M$8:$M$38,$F$8:$F$38,$B47,$G$8:$G$38,"Folga (DSR)")-SUMIFS($M$8:$M$38,$F$8:$F$38,$B47,$G$8:$G$38,"Férias")-SUMIF($F$8:$F$38,$B47,$AN$8:$AN$38)-SUMIF($F$8:$F$38,$B47,$AO$8:$AO$38)) -> 0 | J47: =H47 -> 0
C48: Horas Extras nos Feriados | F48: =SUMIFS($Q$8:$Q$38,$G$8:$G$38,"Feriado") -> 0 | G48: =IF($M$41="Sistema de banco de horas",0,'P Gerais'!$I$14) -> 1 | H48: =IF($M$41="Sistema de banco de horas",0,$K$40*(1+G48)*(F48*24)) -> 0 | J48: =H48 -> 0
C49: Horas Extras no DSR (Descanso Semanal Remunerado) | F49: =SUMIFS($Q$8:$Q$38,$G$8:$G$38,"Folga (DSR)") -> 0 | G49: =IF($M$41="Sistema de banco de horas",0,'P Gerais'!H14) -> 1 | H49: =((F53/(F39-G39))*G39) -> 0 | J49: =H49 -> 0
C50: Horas Extras na Intrajornada | F50: =IF($M$41="Sistema de banco de horas",(SUM(AI$8:AI$38)*(1+G50)),SUM(AI$8:AI$38)) -> 0 | G50: =IF($M$41="Sistema de banco de horas",0,'P Gerais'!$I$17) -> 0.5 | H50: =IF($M$41="Sistema de banco de horas",0,$K$40*(1+G50)*(F50*24)) -> 0 | I50: =IF(SUM($AN$8:$AO$38)>SUM(AI$8:AI$38),0,SUM(AI$8:AI$38)-SUM($AN$8:$AO$38)) -> 0 | J50: =H50 -> 0
C51: Horas Extras às Interjornada | F51: =IF($M$41="Sistema de banco de horas",(SUM(AK$8:AK$38)*(1+G51)),SUM(AK$8:AK$38)) -> 0 | G51: =IF($M$41="Sistema de banco de horas",0,'P Gerais'!$C$17) -> 1 | H51: =IF($M$41="Sistema de banco de horas",0,$K$40*(1+G51)*(F51*24)) -> 0 | J51: =H51 -> 0
C52: Debitadas do Banco de Horas | F52: =U12 -> 0
C53: Total de Horas Extras | F53: =SUM(H48)+J50+H51+SUM(J41:J47) -> 0
C54: Total de Horas Extras a Pagar | F54: =F53+(H49*(1+G49)) -> 0
C55: Salário Base com Horas Extras | F55: =H40+F54 -> 0
C56: Horas Extras em Férias | F56: =IF($M$41="Sistema de banco de horas",(SUMIF($G$8:$G$38,"Férias",Q8:Q38))*(1+G48),SUMIF($G$8:$G$38,"Férias",Q8:Q38)) -> 0
F57: =U14 -> 0
F58: =SUM(F41:F51) -> 0

Sheet Lanç (2)
A1: 1 | C1: 2. LANÇAMENTOS MENSAIS
C5: 'Lanç (2)'!$C$9 | K5: =IF(ISERROR(VLOOKUP(INDIRECT($C$5),Jornada!$C$8:$F$37,4,0)),0,VLOOKUP(INDIRECT($C$5),Jornada!$C$8:$F$37,4,0)) -> 0 | M5: =IF(ISERROR(VLOOKUP(INDIRECT($C$5),Jornada!$C$8:$G$37,5,0)),0,VLOOKUP(INDIRECT($C$5),Jornada!$C$8:$G$37,5,0)) -> 0 | AK5: 0.25 | AL5: 0.91666667 | AM5: 0.20833333 | AN5: 1 | AO5: 0.70833333
M6: 1
C7: Lista de funcionários | E7: =Lanç!E7 -> Janeiro | G7: Classificação | H7: Início | I7: Intervalo | K7: Término | M7: Horas Dia | O7: Horas Devidas | Q7: Horas Extras | R7: 0.083333333 | S7: Resumo do Mês | W7: Janeiro | X7: 1 | AB7: =VLOOKUP($E$7,$W$7:$X$18,2,0) -> 1 | AG7: intervalo real | AH7: intervalo devido | AI7: 0 | AJ7: 1 | AK7: 0.45833333 | AL7: Início | AM7: Fim | AN7: Hora Extra Noturna Início
C8: =IF(Funcionários!C7=0,"",Funcionários!C7) | E8: =Lanç!E8 -> 1 | F8: =Lanç!F8 -> Dom | M8: =IF(AND(H8=K8,H8<>0),$M$6-IF(J8<I8,$AJ$7+J8-I8,J8-I8),IF(H8>K8,(K8+1-H8)-IF(J8<I8,$AJ$7+J8-I8,J8-I8),(K8-H8)-IF(J8<I8,$AJ$7+J8-I8,J8-I8))) -> 0 | O8: =IF(OR(G8=0,G8="Férias",G8="Falta Justificada",G8="Feriado",G8="Folga (DSR)"),0,IF(G8="Falta Injustificada",HLOOKUP($F8,Jornada!$X$7:$AD$37,VLOOKUP(INDIRECT($C$5),Jornada!$C$8:$W$37,21,0),0),IF(HLOOKUP($F8,Jornada!$X$7:$AD$37,VLOOKUP(INDIRECT($C$5),Jornada!$C$8:$W$37,21,0),0)-M8>0,HLOOKUP($F8,Jornada!$X$7:$AD$37,VLOOKUP(INDIRECT($C$5),Jornada!$C$8:$W$37,21,0),0)-M8,0))) -> 0 | P8: =IF(HLOOKUP($F8,Jornada!$X$7:$AD$37,VLOOKUP(INDIRECT($C$5),Jornada!$C$8:$W$37,21,0),0)-M8<0,ABS(HLOOKUP($F8,Jornada!$X$7:$AD$37,VLOOKUP(INDIRECT($C$5),Jornada!$C$8:$W$37,21,0),0)-M8),0) -> 0 | Q8: =IF(G8="Normal",P8,IF(G8=0,0,IF(OR(G8="Feriado",G8="Férias"),IF(H8>K8,(K8+1-H8)-IF(J8<I8,$AJ$7+J8-I8,J8-I8),(K8-H8)-IF(J8<I8,$AJ$7+J8-I8,J8-I8)),IF(G8="Folga (DSR)",IF(H8>K8,(K8+1-H8)-IF(J8<I8,$AJ$7+J8-I8,J8-I8),(K8-H8)-IF(J8<I8,$AJ$7+J8-I8,J8-I8)),IF(G8="Falta Justificada",IF(H8>K8,(K8+1-H8)-IF(J8<I8,$AJ$7+J8-I8,J8-I8),(K8-H8)-IF(J8<I8,$AJ$7+J8-I8,J8-I8)),0))))) -> 0 | R8: =IF(Q8>$R$7,1,0) -> 0 | S8: Horas trabalhadas no mês | U8: =SUM(M8:M38) -> 0 | W8: Fevereiro | X8: 2 | AB8: =DATE('P Gerais'!$D$6,AB7,1) -> 1 | AC8: =WEEKDAY(AB8) -> 1 | AE8: 1 | AF8: Dom | AG8: =IF(J8<I8,$AJ$7+J8-I8,J8-I8) -> 0 | AH8: =IF(HLOOKUP($F8,Jornada!$X$7:$AD$37,VLOOKUP(INDIRECT($C$5),Jornada!$C$8:$W$37,21,0),0)=0,0,VLOOKUP(INDIRECT($C$5),Jornada!$C$8:$H$37,4,0)) -> 0 | AI8: =IF(AND(I8=0,J8=0,OR(H8<>0,K8<>0),HLOOKUP($F8,Jornada!$X$7:$AD$37,VLOOKUP(INDIRECT($C$5),Jornada!$C$8:$W$37,21,0),0)>$AK$5,M8>$AK$5),VLOOKUP(INDIRECT($C$5),Jornada!$C$8:$H$37,6,0),IF(AG8>VLOOKUP(INDIRECT($C$5),Jornada!$C$8:$H$37,6,0),IF(VLOOKUP(INDIRECT($C$5),Jornada!$C$8:$H$37,6,0)<AG8,0,ABS(VLOOKUP(INDIRECT($C$5),Jornada!$C$8:$H$37,6,0))-AG8),0)) -> 0 | AJ8: =($AJ$7-K8)+H8 -> 1 | AK8: =IF(AJ8<$AK$7,$AK$7-AJ8,$AI$7) -> 0 | AL8: =HLOOKUP($F8,Jornada!$I$5:$V$37,VLOOKUP(INDIRECT($C$5),Jornada!$C$8:$W$37,21,0)+2,0) -> 0 | AM8: =HLOOKUP($F8,Jornada!$I$4:$V$37,VLOOKUP(INDIRECT($C$5),Jornada!$C$8:$W$37,21,0)+3,0) -> 0 | AN8: =IF(AND(AL8>=$AL$5,AL8<$AN$5,H8>=$AL$5,H8<AL8),AL8-H8,IF(AND(AL8>$AI$7,AL8<=$AM$5,H8>=$AL$5,H8<=$AN$5),$AN$5-H8+AL8,IF(AND(AL8>=$AI$7,AL8<=$AM$5,H8>=$AI$7,H8<=$AM$5,H8<AL8),H8-AL8,0))) -> 0 | AO8: =IF(AP8>Q8,0,AP8) -> 0 | AP8: =IF(Q8=0,0,IF(AND(AM8>=$AL$5,AM8<$AN$5,K8>=$AL$5,K8<$AM$5,K8>AM8),K8-AM8,IF(AND(AM8>=$AL$5,AM8<$AN$5,K8<$AN$5,K8>AM8),K8-$AL$5,IF(AND(AM8>=$AI$7,AM8<$AM$5,K8<$AM$5),K8-AM8,IF(AND(AM8<>AI7,AM8>=$AI$7,AM8<=$AM$5,K8>$AM$5,K8>AM8),$AM$5-AM8,IF(AND(K8>$AL$5,K8<$AN$5),K8-$AL$5,IF(AND(K8>$AI$7,K8<$AM$5),$AN$5-$AL$5+K8,IF(AND(OR(K8>$AL$5,H8>$AO$5),AM8>=$AI$7,AM8<$AM$5,K8>$AM$5),(1+$AM$5-$AL$5)-AG8,0)))))))) -> 0
C9: =IF(Funcionários!C8=0,"",Funcionários!C8) | E9: =Lanç!E9 -> 2 | F9: =Lanç!F9 -> Seg | M9: =IF(AND(H9=K9,H9<>0),$M$6-IF(J9<I9,$AJ$7+J9-I9,J9-I9),IF(H9>K9,(K9+1-H9)-IF(J9<I9,$AJ$7+J9-I9,J9-I9),(K9-H9)-IF(J9<I9,$AJ$7+J9-I9,J9-I9))) -> 0 | O9: =IF(OR(G9=0,G9="Férias",G9="Falta Justificada",G9="Feriado",G9="Folga (DSR)"),0,IF(G9="Falta Injustificada",HLOOKUP($F9,Jornada!$X$7:$AD$37,VLOOKUP(INDIRECT($C$5),Jornada!$C$8:$W$37,21,0),0),IF(HLOOKUP($F9,Jornada!$X$7:$AD$37,VLOOKUP(INDIRECT($C$5),Jornada!$C$8:$W$37,21,0),0)-M9>0,HLOOKUP($F9,Jornada!$X$7:$AD$37,VLOOKUP(INDIRECT($C$5),Jornada!$C$8:$W$37,21,0),0)-M9,0))) -> 0 | P9: =IF(HLOOKUP($F9,Jornada!$X$7:$AD$37,VLOOKUP(INDIRECT($C$5),Jornada!$C$8:$W$37,21,0),0)-M9<0,ABS(HLOOKUP($F9,Jornada!$X$7:$AD$37,VLOOKUP(INDIRECT($C$5),Jornada!$C$8:$W$37,21,0),0)-M9),0) -> 0 | Q9: =IF(G9="Normal",P9,IF(G9=0,0,IF(OR(G9="Feriado",G9="Férias"),IF(H9>K9,(K9+1-H9)-IF(J9<I9,$AJ$7+J9-I9,J9-I9),(K9-H9)-IF(J9<I9,$AJ$7+J9-I9,J9-I9)),IF(G9="Folga (DSR)",IF(H9>K9,(K9+1-H9)-IF(J9<I9,$AJ$7+J9-I9,J9-I9),(K9-H9)-IF(J9<I9,$AJ$7+J9-I9,J9-I9)),IF(G9="Falta Justificada",IF(H9>K9,(K9+1-H9)-IF(J9<I9,$AJ$7+J9-I9,J9-I9),(K9-H9)-IF(J9<I9,$AJ$7+J9-I9,J9-I9)),0))))) -> 0 | R9: =IF(Q9>$R$7,1,0) -> 0 | W9: Março | X9: 3 | AB9: =AB8+1 -> 2 | AC9: =WEEKDAY(AB9) -> 2 | AE9: 2 | AF9: Seg | AG9: =IF(J9<I9,$AJ$7+J9-I9,J9-I9) -> 0 | AH9: =IF(HLOOKUP($F9,Jornada!$X$7:$AD$37,VLOOKUP(INDIRECT($C$5),Jornada!$C$8:$W$37,21,0),0)=0,0,VLOOKUP(INDIRECT($C$5),Jornada!$C$8:$H$37,4,0)) -> 0 | AI9: =IF(AND(I9=0,J9=0,OR(H9<>0,K9<>0),HLOOKUP($F9,Jornada!$X$7:$AD$37,VLOOKUP(INDIRECT($C$5),Jornada!$C$8:$W$37,21,0),0)>$AK$5,M9>$AK$5),VLOOKUP(INDIRECT($C$5),Jornada!$C$8:$H$37,6,0),IF(AG9>VLOOKUP(INDIRECT($C$5),Jornada!$C$8:$H$37,6,0),IF(VLOOKUP(INDIRECT($C$5),Jornada!$C$8:$H$37,6,0)<AG9,0,ABS(VLOOKUP(INDIRECT($C$5),Jornada!$C$8:$H$37,6,0))-AG9),0)) -> 0 | AJ9: =($AJ$7-K9)+H9 -> 1 | AK9: =IF(AJ9<$AK$7,$AK$7-AJ9,$AI$7) -> 0 | AL9: =HLOOKUP($F9,Jornada!$I$5:$V$37,VLOOKUP(INDIRECT($C$5),Jornada!$C$8:$W$37,21,0)+2,0) -> 0 | AM9: =HLOOKUP($F9,Jornada!$I$4:$V$37,VLOOKUP(INDIRECT($C$5),Jornada!$C$8:$W$37,21,0)+3,0) -> 0 | AN9: =IF(AND(AL9>=$AL$5,AL9<$AN$5,H9>=$AL$5,H9<AL9),AL9-H9,IF(AND(AL9>$AI$7,AL9<=$AM$5,H9>=$AL$5,H9<=$AN$5),$AN$5-H9+AL9,IF(AND(AL9>=$AI$7,AL9<=$AM$5,H9>=$AI$7,H9<=$AM$5,H9<AL9),H9-AL9,0))) -> 0 | AO9: =IF(AP9>Q9,0,AP9) -> 0 | AP9: =IF(Q9=0,0,IF(AND(AM9>=$AL$5,AM9<$AN$5,K9>=$AL$5,K9<$AM$5,K9>AM9),K9-AM9,IF(AND(AM9>=$AL$5,AM9<$AN$5,K9<$AN$5,K9>AM9),K9-$AL$5,IF(AND(AM9>=$AI$7,AM9<$AM$5,K9<$AM$5),K9-AM9,IF(AND(AM9<>AI8,AM9>=$AI$7,AM9<=$AM$5,K9>$AM$5,K9>AM9),$AM$5-AM9,IF(AND(K9>$AL$5,K9<$AN$5),K9-$AL$5,IF(AND(K9>$AI$7,K9<$AM$5),$AN$5-$AL$5+K9,IF(AND(OR(K9>$AL$5,H9>$AO$5),AM9>=$AI$7,AM9<$AM$5,K9>$AM$5),(1+$AM$5-$AL$5)-AG9,0)))))))) -> 0
C10: =IF(Funcionários!C9=0,"",Funcionários!C9) | E10: =Lanç!E10 -> 3 | F10: =Lanç!F10 -> Ter | M10: =IF(AND(H10=K10,H10<>0),$M$6-IF(J10<I10,$AJ$7+J10-I10,J10-I10),IF(H10>K10,(K10+1-H10)-IF(J10<I10,$AJ$7+J10-I10,J10-I10),(K10-H10)-IF(J10<I10,$AJ$7+J10-I10,J10-I10))) -> 0 | O10: =IF(OR(G10=0,G10="Férias",G10="Falta Justificada",G10="Feriado",G10="Folga (DSR)"),0,IF(G10="Falta Injustificada",HLOOKUP($F10,Jornada!$X$7:$AD$37,VLOOKUP(INDIRECT($C$5),Jornada!$C$8:$W$37,21,0),0),IF(HLOOKUP($F10,Jornada!$X$7:$AD$37,VLOOKUP(INDIRECT($C$5),Jornada!$C$8:$W$37,21,0),0)-M10>0,HLOOKUP($F10,Jornada!$X$7:$AD$37,VLOOKUP(INDIRECT($C$5),Jornada!$C$8:$W$37,21,0),0)-M10,0))) -> 0 | P10: =IF(HLOOKUP($F10,Jornada!$X$7:$AD$37,VLOOKUP(INDIRECT($C$5),Jornada!$C$8:$W$37,21,0),0)-M10<0,ABS(HLOOKUP($F10,Jornada!$X$7:$AD$37,VLOOKUP(INDIRECT($C$5),Jornada!$C$8:$W$37,21,0),0)-M10),0) -> 0 | Q10: =IF(G10="Normal",P10,IF(G10=0,0,IF(OR(G10="Feriado",G10="Férias"),IF(H10>K10,(K10+1-H10)-IF(J10<I10,$AJ$7+J10-I10,J10-I10),(K10-H10)-IF(J10<I10,$AJ$7+J10-I10,J10-I10)),IF(G10="Folga (DSR)",IF(H10>K10,(K10+1-H10)-IF(J10<I10,$AJ$7+J10-I10,J10-I10),(K10-H10)-IF(J10<I10,$AJ$7+J10-I10,J10-I10)),IF(G10="Falta Justificada",IF(H10>K10,(K10+1-H10)-IF(J10<I10,$AJ$7+J10-I10,J10-I10),(K10-H10)-IF(J10<I10,$AJ$7+J10-I10,J10-I10)),0))))) -> 0 | R10: =IF(Q10>$R$7,1,0) -> 0 | S10: Acumulado no banco de horas | U10: =IF(M5="Horas devidas",ABS(-K5+F58-U14),ABS(K5+F58-U14)) -> 0 | W10: Abril | X10: 4 | AB10: =AB9+1 -> 3 | AC10: =WEEKDAY(AB10) -> 3 | AE10: 3 | AF10: Ter | AG10: =IF(J10<I10,$AJ$7+J10-I10,J10-I10) -> 0 | AH10: =IF(HLOOKUP($F10,Jornada!$X$7:$AD$37,VLOOKUP(INDIRECT($C$5),Jornada!$C$8:$W$37,21,0),0)=0,0,VLOOKUP(INDIRECT($C$5),Jornada!$C$8:$H$37,4,0)) -> 0 | AI10: =IF(AND(I10=0,J10=0,OR(H10<>0,K10<>0),HLOOKUP($F10,Jornada!$X$7:$AD$37,VLOOKUP(INDIRECT($C$5),Jornada!$C$8:$W$37,21,0),0)>$AK$5,M10>$AK$5),VLOOKUP(INDIRECT($C$5),Jornada!$C$8:$H$37,6,0),IF(AG10>VLOOKUP(INDIRECT($C$5),Jornada!$C$8:$H$37,6,0),IF(VLOOKUP(INDIRECT($C$5),Jornada!$C$8:$H$37,6,0)<AG10,0,ABS(VLOOKUP(INDIRECT($C$5),Jornada!$C$8:$H$37,6,0))-AG10),0)) -> 0 | AJ10: =($AJ$7-K10)+H10 -> 1 | AK10: =IF(AJ10<$AK$7,$AK$7-AJ10,$AI$7) -> 0 | AL10: =HLOOKUP($F10,Jornada!$I$5:$V$37,VLOOKUP(INDIRECT($C$5),Jornada!$C$8:$W$37,21,0)+2,0) -> 0 | AM10: =HLOOKUP($F10,Jornada!$I$4:$V$37,VLOOKUP(INDIRECT($C$5),Jornada!$C$8:$W$37,21,0)+3,0) -> 0 | AN10: =IF(AND(AL10>=$AL$5,AL10<$AN$5,H10>=$AL$5,H10<AL10),AL10-H10,IF(AND(AL10>$AI$7,AL10<=$AM$5,H10>=$AL$5,H10<=$AN$5),$AN$5-H10+AL10,IF(AND(AL10>=$AI$7,AL10<=$AM$5,H10>=$AI$7,H10<=$AM$5,H10<AL10),H10-AL10,0))) -> 0 | AO10: =IF(AP10>Q10,0,AP10) -> 0 | AP10: =IF(Q10=0,0,IF(AND(AM10>=$AL$5,AM10<$AN$5,K10>=$AL$5,K10<$AM$5,K10>AM10),K10-AM10,IF(AND(AM10>=$AL$5,AM10<$AN$5,K10<$AN$5,K10>AM10),K10-$AL$5,IF(AND(AM10>=$AI$7,AM10<$AM$5,K10<$AM$5),K10-AM10,IF(AND(AM10<>AI9,AM10>=$AI$7,AM10<=$AM$5,K10>$AM$5,K10>AM10),$AM$5-AM10,IF(AND(K10>$AL$5,K10<$AN$5),K10-$AL$5,IF(AND(K10>$AI$7,K10<$AM$5),$AN$5-$AL$5+K10,IF(AND(OR(K10>$AL$5,H10>$AO$5),AM10>=$AI$7,AM10<$AM$5,K10>$AM$5),(1+$AM$5-$AL$5)-AG10,0)))))))) -> 0
C11: =IF(Funcionários!C10=0,"",Funcionários!C10) | E11: =Lanç!E11 -> 4 | F11: =Lanç!F11 -> Qua | M11: =IF(AND(H11=K11,H11<>0),$M$6-IF(J11<I11,$AJ$7+J11-I11,J11-I11),IF(H11>K11,(K11+1-H11)-IF(J11<I11,$AJ$7+J11-I11,J11-I11),(K11-H11)-IF(J11<I11,$AJ$7+J11-I11,J11-I11))) -> 0 | O11: =IF(OR(G11=0,G11="Férias",G11="Falta Justificada",G11="Feriado",G11="Folga (DSR)"),0,IF(G11="Falta Injustificada",HLOOKUP($F11,Jornada!$X$7:$AD$37,VLOOKUP(INDIRECT($C$5),Jornada!$C$8:$W$37,21,0),0),IF(HLOOKUP($F11,Jornada!$X$7:$AD$37,VLOOKUP(INDIRECT($C$5),Jornada!$C$8:$W$37,21,0),0)-M11>0,HLOOKUP($F11,Jornada!$X$7:$AD$37,VLOOKUP(INDIRECT($C$5),Jornada!$C$8:$W$37,21,0),0)-M11,0))) -> 0 | P11: =IF(HLOOKUP($F11,Jornada!$X$7:$AD$37,VLOOKUP(INDIRECT($C$5),Jornada!$C$8:$W$37,21,0),0)-M11<0,ABS(HLOOKUP($F11,Jornada!$X$7:$AD$37,VLOOKUP(INDIRECT($C$5),Jornada!$C$8:$W$37,21,0),0)-M11),0) -> 0 | Q11: =IF(G11="Normal",P11,IF(G11=0,0,IF(OR(G11="Feriado",G11="Férias"),IF(H11>K11,(K11+1-H11)-IF(J11<I11,$AJ$7+J11-I11,J11-I11),(K11-H11)-IF(J11<I11,$AJ$7+J11-I11,J11-I11)),IF(G11="Folga (DSR)",IF(H11>K11,(K11+1-H11)-IF(J11<I11,$AJ$7+J11-I11,J11-I11),(K11-H11)-IF(J11<I11,$AJ$7+J11-I11,J11-I11)),IF(G11="Falta Justificada",IF(H11>K11,(K11+1-H11)-IF(J11<I11,$AJ$7+J11-I11,J11-I11),(K11-H11)-IF(J11<I11,$AJ$7+J11-I11,J11-I11)),0))))) -> 0 | R11: =IF(Q11>$R$7,1,0) -> 0 | V11: =IF(AND(K5>U12,M5="Horas devidas"),"Negativo",IF(AND(U12>K5,U14>F58),"Negativo",0)) -> 0 | W11: Maio | X11: 5 | Z11: =IF(AND(M5="horas extras",Z13="positivo"),"positivo",IF(AND(M5="horas devidas",Z13="Negativo"),"Negativo",IF(AND(Z13="positivo",M5="horas devidas",U12>K5),"Positivo","Negativo"))) -> Negativo | AB11: =AB10+1 -> 4 | AC11: =WEEKDAY(AB11) -> 4 | AE11: 4 | AF11: Qua | AG11: =IF(J11<I11,$AJ$7+J11-I11,J11-I11) -> 0 | AH11: =IF(HLOOKUP($F11,Jornada!$X$7:$AD$37,VLOOKUP(INDIRECT($C$5),Jornada!$C$8:$W$37,21,0),0)=0,0,VLOOKUP(INDIRECT($C$5),Jornada!$C$8:$H$37,4,0)) -> 0 | AI11: =IF(AND(I11=0,J11=0,OR(H11<>0,K11<>0),HLOOKUP($F11,Jornada!$X$7:$AD$37,VLOOKUP(INDIRECT($C$5),Jornada!$C$8:$W$37,21,0),0)>$AK$5,M11>$AK$5),VLOOKUP(INDIRECT($C$5),Jornada!$C$8:$H$37,6,0),IF(AG11>VLOOKUP(INDIRECT($C$5),Jornada!$C$8:$H$37,6,0),IF(VLOOKUP(INDIRECT($C$5),Jornada!$C$8:$H$37,6,0)<AG11,0,ABS(VLOOKUP(INDIRECT($C$5),Jornada!$C$8:$H$37,6,0))-AG11),0)) -> 0 | AJ11: =($AJ$7-K11)+H11 -> 1 | AK11: =IF(AJ11<$AK$7,$AK$7-AJ11,$AI$7) -> 0 | AL11: =HLOOKUP($F11,Jornada!$I$5:$V$37,VLOOKUP(INDIRECT($C$5),Jornada!$C$8:$W$37,21,0)+2,0) -> 0 | AM11: =HLOOKUP($F11,Jornada!$I$4:$V$37,VLOOKUP(INDIRECT($C$5),Jornada!$C$8:$W$37,21,0)+3,0) -> 0 | AN11: =IF(AND(AL11>=$AL$5,AL11<$AN$5,H11>=$AL$5,H11<AL11),AL11-H11,IF(AND(AL11>$AI$7,AL11<=$AM$5,H11>=$AL$5,H11<=$AN$5),$AN$5-H11+AL11,IF(AND(AL11>=$AI$7,AL11<=$AM$5,H11>=$AI$7,H11<=$AM$5,H11<AL11),H11-AL11,0))) -> 0 | AO11: =IF(AP11>Q11,0,AP11) -> 0 | AP11: =IF(Q11=0,0,IF(AND(AM11>=$AL$5,AM11<$AN$5,K11>=$AL$5,K11<$AM$5,K11>AM11),K11-AM11,IF(AND(AM11>=$AL$5,AM11<$AN$5,K11<$AN$5,K11>AM11),K11-$AL$5,IF(AND(AM11>=$AI$7,AM11<$AM$5,K11<$AM$5),K11-AM11,IF(AND(AM11<>AI10,AM11>=$AI$7,AM11<=$AM$5,K11>$AM$5,K11>AM11),$AM$5-AM11,IF(AND(K11>$AL$5,K11<$AN$5),K11-$AL$5,IF(AND(K11>$AI$7,K11<$AM$5),$AN$5-$AL$5+K11,IF(AND(OR(K11>$AL$5,H11>$AO$5),AM11>=$AI$7,AM11<$AM$5,K11>$AM$5),(1+$AM$5-$AL$5)-AG11,0)))))))) -> 0
C12: =IF(Funcionários!C11=0,"",Funcionários!C11) | E12: =Lanç!E12 -> 5 | F12: =Lanç!F12 -> Qui | M12: =IF(AND(H12=K12,H12<>0),$M$6-IF(J12<I12,$AJ$7+J12-I12,J12-I12),IF(H12>K12,(K12+1-H12)-IF(J12<I12,$AJ$7+J12-I12,J12-I12),(K12-H12)-IF(J12<I12,$AJ$7+J12-I12,J12-I12))) -> 0 | O12: =IF(OR(G12=0,G12="Férias",G12="Falta Justificada",G12="Feriado",G12="Folga (DSR)"),0,IF(G12="Falta Injustificada",HLOOKUP($F12,Jornada!$X$7:$AD$37,VLOOKUP(INDIRECT($C$5),Jornada!$C$8:$W$37,21,0),0),IF(HLOOKUP($F12,Jornada!$X$7:$AD$37,VLOOKUP(INDIRECT($C$5),Jornada!$C$8:$W$37,21,0),0)-M12>0,HLOOKUP($F12,Jornada!$X$7:$AD$37,VLOOKUP(INDIRECT($C$5),Jornada!$C$8:$W$37,21,0),0)-M12,0))) -> 0 | P12: =IF(HLOOKUP($F12,Jornada!$X$7:$AD$37,VLOOKUP(INDIRECT($C$5),Jornada!$C$8:$W$37,21,0),0)-M12<0,ABS(HLOOKUP($F12,Jornada!$X$7:$AD$37,VLOOKUP(INDIRECT($C$5),Jornada!$C$8:$W$37,21,0),0)-M12),0) -> 0 | Q12: =IF(G12="Normal",P12,IF(G12=0,0,IF(OR(G12="Feriado",G12="Férias"),IF(H12>K12,(K12+1-H12)-IF(J12<I12,$AJ$7+J12-I12,J12-I12),(K12-H12)-IF(J12<I12,$AJ$7+J12-I12,J12-I12)),IF(G12="Folga (DSR)",IF(H12>K12,(K12+1-H12)-IF(J12<I12,$AJ$7+J12-I12,J12-I12),(K12-H12)-IF(J12<I12,$AJ$7+J12-I12,J12-I12)),IF(G12="Falta Justificada",IF(H12>K12,(K12+1-H12)-IF(J12<I12,$AJ$7+J12-I12,J12-I12),(K12-H12)-IF(J12<I12,$AJ$7+J12-I12,J12-I12)),0))))) -> 0 | R12: =IF(Q12>$R$7,1,0) -> 0 | S12: Horas somados / subtraídas ao banco | U12: =IF(U14>=F58,(U14)-F58,(F58-U14)) -> 0 | W12: Junho | X12: 6 | AB12: =AB11+1 -> 5 | AC12: =WEEKDAY(AB12) -> 5 | AE12: 5 | AF12: Qui | AG12: =IF(J12<I12,$AJ$7+J12-I12,J12-I12) -> 0 | AH12: =IF(HLOOKUP($F12,Jornada!$X$7:$AD$37,VLOOKUP(INDIRECT($C$5),Jornada!$C$8:$W$37,21,0),0)=0,0,VLOOKUP(INDIRECT($C$5),Jornada!$C$8:$H$37,4,0)) -> 0 | AI12: =IF(AND(I12=0,J12=0,OR(H12<>0,K12<>0),HLOOKUP($F12,Jornada!$X$7:$AD$37,VLOOKUP(INDIRECT($C$5),Jornada!$C$8:$W$37,21,0),0)>$AK$5,M12>$AK$5),VLOOKUP(INDIRECT($C$5),Jornada!$C$8:$H$37,6,0),IF(AG12>VLOOKUP(INDIRECT($C$5),Jornada!$C$8:$H$37,6,0),IF(VLOOKUP(INDIRECT($C$5),Jornada!$C$8:$H$37,6,0)<AG12,0,ABS(VLOOKUP(INDIRECT($C$5),Jornada!$C$8:$H$37,6,0))-AG12),0)) -> 0 | AJ12: =($AJ$7-K12)+H12 -> 1 | AK12: =IF(AJ12<$AK$7,$AK$7-AJ12,$AI$7) -> 0 | AL12: =HLOOKUP($F12,Jornada!$I$5:$V$37,VLOOKUP(INDIRECT($C$5),Jornada!$C$8:$W$37,21,0)+2,0) -> 0 | AM12: =HLOOKUP($F12,Jornada!$I$4:$V$37,VLOOKUP(INDIRECT($C$5),Jornada!$C$8:$W$37,21,0)+3,0) -> 0 | AN12: =IF(AND(AL12>=$AL$5,AL12<$AN$5,H12>=$AL$5,H12<AL12),AL12-H12,IF(AND(AL12>$AI$7,AL12<=$AM$5,H12>=$AL$5,H12<=$AN$5),$AN$5-H12+AL12,IF(AND(AL12>=$AI$7,AL12<=$AM$5,H12>=$AI$7,H12<=$AM$5,H12<AL12),H12-AL12,0))) -> 0 | AO12: =IF(AP12>Q12,0,AP12) -> 0 | AP12: =IF(Q12=0,0,IF(AND(AM12>=$AL$5,AM12<$AN$5,K12>=$AL$5,K12<$AM$5,K12>AM12),K12-AM12,IF(AND(AM12>=$AL$5,AM12<$AN$5,K12<$AN$5,K12>AM12),K12-$AL$5,IF(AND(AM12>=$AI$7,AM12<$AM$5,K12<$AM$5),K12-AM12,IF(AND(AM12<>AI11,AM12>=$AI$7,AM12<=$AM$5,K12>$AM$5,K12>AM12),$AM$5-AM12,IF(AND(K12>$AL$5,K12<$AN$5),K12-$AL$5,IF(AND(K12>$AI$7,K12<$AM$5),$AN$5-$AL$5+K12,IF(AND(OR(K12>$AL$5,H12>$AO$5),AM12>=$AI$7,AM12<$AM$5,K12>$AM$5),(1+$AM$5-$AL$5)-AG12,0)))))))) -> 0
C13: =IF(Funcionários!C12=0,"",Funcionários!C12) | E13: =Lanç!E13 -> 6 | F13: =Lanç!F13 -> Sex | M13: =IF(AND(H13=K13,H13<>0),$M$6-IF(J13<I13,$AJ$7+J13-I13,J13-I13),IF(H13>K13,(K13+1-H13)-IF(J13<I13,$AJ$7+J13-I13,J13-I13),(K13-H13)-IF(J13<I13,$AJ$7+J13-I13,J13-I13))) -> 0 | O13: =IF(OR(G13=0,G13="Férias",G13="Falta Justificada",G13="Feriado",G13="Folga (DSR)"),0,IF(G13="Falta Injustificada",HLOOKUP($F13,Jornada!$X$7:$AD$37,VLOOKUP(INDIRECT($C$5),Jornada!$C$8:$W$37,21,0),0),IF(HLOOKUP($F13,Jornada!$X$7:$AD$37,VLOOKUP(INDIRECT($C$5),Jornada!$C$8:$W$37,21,0),0)-M13>0,HLOOKUP($F13,Jornada!$X$7:$AD$37,VLOOKUP(INDIRECT($C$5),Jornada!$C$8:$W$37,21,0),0)-M13,0))) -> 0 | P13: =IF(HLOOKUP($F13,Jornada!$X$7:$AD$37,VLOOKUP(INDIRECT($C$5),Jornada!$C$8:$W$37,21,0),0)-M13<0,ABS(HLOOKUP($F13,Jornada!$X$7:$AD$37,VLOOKUP(INDIRECT($C$5),Jornada!$C$8:$W$37,21,0),0)-M13),0) -> 0 | Q13: =IF(G13="Normal",P13,IF(G13=0,0,IF(OR(G13="Feriado",G13="Férias"),IF(H13>K13,(K13+1-H13)-IF(J13<I13,$AJ$7+J13-I13,J13-I13),(K13-H13)-IF(J13<I13,$AJ$7+J13-I13,J13-I13)),IF(G13="Folga (DSR)",IF(H13>K13,(K13+1-H13)-IF(J13<I13,$AJ$7+J13-I13,J13-I13),(K13-H13)-IF(J13<I13,$AJ$7+J13-I13,J13-I13)),IF(G13="Falta Justificada",IF(H13>K13,(K13+1-H13)-IF(J13<I13,$AJ$7+J13-I13,J13-I13),(K13-H13)-IF(J13<I13,$AJ$7+J13-I13,J13-I13)),0))))) -> 0 | R13: =IF(Q13>$R$7,1,0) -> 0 | W13: Julho | X13: 7 | Z13: =IF(U14>F58,"Negativo","Positivo") -> Positivo | AB13: =AB12+1 -> 6 | AC13: =WEEKDAY(AB13) -> 6 | AE13: 6 | AF13: Sex | AG13: =IF(J13<I13,$AJ$7+J13-I13,J13-I13) -> 0 | AH13: =IF(HLOOKUP($F13,Jornada!$X$7:$AD$37,VLOOKUP(INDIRECT($C$5),Jornada!$C$8:$W$37,21,0),0)=0,0,VLOOKUP(INDIRECT($C$5),Jornada!$C$8:$H$37,4,0)) -> 0 | AI13: =IF(AND(I13=0,J13=0,OR(H13<>0,K13<>0),HLOOKUP($F13,Jornada!$X$7:$AD$37,VLOOKUP(INDIRECT($C$5),Jornada!$C$8:$W$37,21,0),0)>$AK$5,M13>$AK$5),VLOOKUP(INDIRECT($C$5),Jornada!$C$8:$H$37,6,0),IF(AG13>VLOOKUP(INDIRECT($C$5),Jornada!$C$8:$H$37,6,0),IF(VLOOKUP(INDIRECT($C$5),Jornada!$C$8:$H$37,6,0)<AG13,0,ABS(VLOOKUP(INDIRECT($C$5),Jornada!$C$8:$H$37,6,0))-AG13),0)) -> 0 | AJ13: =($AJ$7-K13)+H13 -> 1 | AK13: =IF(AJ13<$AK$7,$AK$7-AJ13,$AI$7) -> 0 | AL13: =HLOOKUP($F13,Jornada!$I$5:$V$37,VLOOKUP(INDIRECT($C$5),Jornada!$C$8:$W$37,21,0)+2,0) -> 0 | AM13: =HLOOKUP($F13,Jornada!$I$4:$V$37,VLOOKUP(INDIRECT($C$5),Jornada!$C$8:$W$37,21,0)+3,0) -> 0 | AN13: =IF(AND(AL13>=$AL$5,AL13<$AN$5,H13>=$AL$5,H13<AL13),AL13-H13,IF(AND(AL13>$AI$7,AL13<=$AM$5,H13>=$AL$5,H13<=$AN$5),$AN$5-H13+AL13,IF(AND(AL13>=$AI$7,AL13<=$AM$5,H13>=$AI$7,H13<=$AM$5,H13<AL13),H13-AL13,0))) -> 0 | AO13: =IF(AP13>Q13,0,AP13) -> 0 | AP13: =IF(Q13=0,0,IF(AND(AM13>=$AL$5,AM13<$AN$5,K13>=$AL$5,K13<$AM$5,K13>AM13),K13-AM13,IF(AND(AM13>=$AL$5,AM13<$AN$5,K13<$AN$5,K13>AM13),K13-$AL$5,IF(AND(AM13>=$AI$7,AM13<$AM$5,K13<$AM$5),K13-AM13,IF(AND(AM13<>AI12,AM13>=$AI$7,AM13<=$AM$5,K13>$AM$5,K13>AM13),$AM$5-AM13,IF(AND(K13>$AL$5,K13<$AN$5),K13-$AL$5,IF(AND(K13>$AI$7,K13<$AM$5),$AN$5-$AL$5+K13,IF(AND(OR(K13>$AL$5,H13>$AO$5),AM13>=$AI$7,AM13<$AM$5,K13>$AM$5),(1+$AM$5-$AL$5)-AG13,0)))))))) -> 0
C14: =IF(Funcionários!C13=0,"",Funcionários!C13) | E14: =Lanç!E14 -> 7 | F14: =Lanç!F14 -> Sáb | M14: =IF(AND(H14=K14,H14<>0),$M$6-IF(J14<I14,$AJ$7+J14-I14,J14-I14),IF(H14>K14,(K14+1-H14)-IF(J14<I14,$AJ$7+J14-I14,J14-I14),(K14-H14)-IF(J14<I14,$AJ$7+J14-I14,J14-I14))) -> 0 | O14: =IF(OR(G14=0,G14="Férias",G14="Falta Justificada",G14="Feriado",G14="Folga (DSR)"),0,IF(G14="Falta Injustificada",HLOOKUP($F14,Jornada!$X$7:$AD$37,VLOOKUP(INDIRECT($C$5),Jornada!$C$8:$W$37,21,0),0),IF(HLOOKUP($F14,Jornada!$X$7:$AD$37,VLOOKUP(INDIRECT($C$5),Jornada!$C$8:$W$37,21,0),0)-M14>0,HLOOKUP($F14,Jornada!$X$7:$AD$37,VLOOKUP(INDIRECT($C$5),Jornada!$C$8:$W$37,21,0),0)-M14,0))) -> 0 | P14: =IF(HLOOKUP($F14,Jornada!$X$7:$AD$37,VLOOKUP(INDIRECT($C$5),Jornada!$C$8:$W$37,21,0),0)-M14<0,ABS(HLOOKUP($F14,Jornada!$X$7:$AD$37,VLOOKUP(INDIRECT($C$5),Jornada!$C$8:$W$37,21,0),0)-M14),0) -> 0 | Q14: =IF(G14="Normal",P14,IF(G14=0,0,IF(OR(G14="Feriado",G14="Férias"),IF(H14>K14,(K14+1-H14)-IF(J14<I14,$AJ$7+J14-I14,J14-I14),(K14-H14)-IF(J14<I14,$AJ$7+J14-I14,J14-I14)),IF(G14="Folga (DSR)",IF(H14>K14,(K14+1-H14)-IF(J14<I14,$AJ$7+J14-I14,J14-I14),(K14-H14)-IF(J14<I14,$AJ$7+J14-I14,J14-I14)),IF(G14="Falta Justificada",IF(H14>K14,(K14+1-H14)-IF(J14<I14,$AJ$7+J14-I14,J14-I14),(K14-H14)-IF(J14<I14,$AJ$7+J14-I14,J14-I14)),0))))) -> 0 | R14: =IF(Q14>$R$7,1,0) -> 0 | S14: Total de horas devidas | U14: =SUM(O8:O38) -> 0 | W14: Agosto | X14: 8 | AB14: =AB13+1 -> 7 | AC14: =WEEKDAY(AB14) -> 7 | AE14: 7 | AF14: Sáb | AG14: =IF(J14<I14,$AJ$7+J14-I14,J14-I14) -> 0 | AH14: =IF(HLOOKUP($F14,Jornada!$X$7:$AD$37,VLOOKUP(INDIRECT($C$5),Jornada!$C$8:$W$37,21,0),0)=0,0,VLOOKUP(INDIRECT($C$5),Jornada!$C$8:$H$37,4,0)) -> 0 | AI14: =IF(AND(I14=0,J14=0,OR(H14<>0,K14<>0),HLOOKUP($F14,Jornada!$X$7:$AD$37,VLOOKUP(INDIRECT($C$5),Jornada!$C$8:$W$37,21,0),0)>$AK$5,M14>$AK$5),VLOOKUP(INDIRECT($C$5),Jornada!$C$8:$H$37,6,0),IF(AG14>VLOOKUP(INDIRECT($C$5),Jornada!$C$8:$H$37,6,0),IF(VLOOKUP(INDIRECT($C$5),Jornada!$C$8:$H$37,6,0)<AG14,0,ABS(VLOOKUP(INDIRECT($C$5),Jornada!$C$8:$H$37,6,0))-AG14),0)) -> 0 | AJ14: =($AJ$7-K14)+H14 -> 1 | AK14: =IF(AJ14<$AK$7,$AK$7-AJ14,$AI$7) -> 0 | AL14: =HLOOKUP($F14,Jornada!$I$5:$V$37,VLOOKUP(INDIRECT($C$5),Jornada!$C$8:$W$37,21,0)+2,0) -> 0 | AM14: =HLOOKUP($F14,Jornada!$I$4:$V$37,VLOOKUP(INDIRECT($C$5),Jornada!$C$8:$W$37,21,0)+3,0) -> 0 | AN14: =IF(AND(AL14>=$AL$5,AL14<$AN$5,H14>=$AL$5,H14<AL14),AL14-H14,IF(AND(AL14>$AI$7,AL14<=$AM$5,H14>=$AL$5,H14<=$AN$5),$AN$5-H14+AL14,IF(AND(AL14>=$AI$7,AL14<=$AM$5,H14>=$AI$7,H14<=$AM$5,H14<AL14),H14-AL14,0))) -> 0 | AO14: =IF(AP14>Q14,0,AP14) -> 0 | AP14: =IF(Q14=0,0,IF(AND(AM14>=$AL$5,AM14<$AN$5,K14>=$AL$5,K14<$AM$5,K14>AM14),K14-AM14,IF(AND(AM14>=$AL$5,AM14<$AN$5,K14<$AN$5,K14>AM14),K14-$AL$5,IF(AND(AM14>=$AI$7,AM14<$AM$5,K14<$AM$5),K14-AM14,IF(AND(AM14<>AI13,AM14>=$AI$7,AM14<=$AM$5,K14>$AM$5,K14>AM14),$AM$5-AM14,IF(AND(K14>$AL$5,K14<$AN$5),K14-$AL$5,IF(AND(K14>$AI$7,K14<$AM$5),$AN$5-$AL$5+K14,IF(AND(OR(K14>$AL$5,H14>$AO$5),AM14>=$AI$7,AM14<$AM$5,K14>$AM$5),(1+$AM$5-$AL$5)-AG14,0)))))))) -> 0
C15: =IF(Funcionários!C14=0,"",Funcionários!C14) | E15: =Lanç!E15 -> 8 | F15: =Lanç!F15 -> Dom | M15: =IF(AND(H15=K15,H15<>0),$M$6-IF(J15<I15,$AJ$7+J15-I15,J15-I15),IF(H15>K15,(K15+1-H15)-IF(J15<I15,$AJ$7+J15-I15,J15-I15),(K15-H15)-IF(J15<I15,$AJ$7+J15-I15,J15-I15))) -> 0 | O15: =IF(OR(G15=0,G15="Férias",G15="Falta Justificada",G15="Feriado",G15="Folga (DSR)"),0,IF(G15="Falta Injustificada",HLOOKUP($F15,Jornada!$X$7:$AD$37,VLOOKUP(INDIRECT($C$5),Jornada!$C$8:$W$37,21,0),0),IF(HLOOKUP($F15,Jornada!$X$7:$AD$37,VLOOKUP(INDIRECT($C$5),Jornada!$C$8:$W$37,21,0),0)-M15>0,HLOOKUP($F15,Jornada!$X$7:$AD$37,VLOOKUP(INDIRECT($C$5),Jornada!$C$8:$W$37,21,0),0)-M15,0))) -> 0 | P15: =IF(HLOOKUP($F15,Jornada!$X$7:$AD$37,VLOOKUP(INDIRECT($C$5),Jornada!$C$8:$W$37,21,0),0)-M15<0,ABS(HLOOKUP($F15,Jornada!$X$7:$AD$37,VLOOKUP(INDIRECT($C$5),Jornada!$C$8:$W$37,21,0),0)-M15),0) -> 0 | Q15: =IF(G15="Normal",P15,IF(G15=0,0,IF(OR(G15="Feriado",G15="Férias"),IF(H15>K15,(K15+1-H15)-IF(J15<I15,$AJ$7+J15-I15,J15-I15),(K15-H15)-IF(J15<I15,$AJ$7+J15-I15,J15-I15)),IF(G15="Folga (DSR)",IF(H15>K15,(K15+1-H15)-IF(J15<I15,$AJ$7+J15-I15,J15-I15),(K15-H15)-IF(J15<I15,$AJ$7+J15-I15,J15-I15)),IF(G15="Falta Justificada",IF(H15>K15,(K15+1-H15)-IF(J15<I15,$AJ$7+J15-I15,J15-I15),(K15-H15)-IF(J15<I15,$AJ$7+J15-I15,J15-I15)),0))))) -> 0 | R15: =IF(Q15>$R$7,1,0) -> 0 | W15: Setembro | X15: 9 | AB15: =AB14+1 -> 8 | AC15: =WEEKDAY(AB15) -> 1 | AG15: =IF(J15<I15,$AJ$7+J15-I15,J15-I15) -> 0 | AH15: =IF(HLOOKUP($F15,Jornada!$X$7:$AD$37,VLOOKUP(INDIRECT($C$5),Jornada!$C$8:$W$37,21,0),0)=0,0,VLOOKUP(INDIRECT($C$5),Jornada!$C$8:$H$37,4,0)) -> 0 | AI15: =IF(AND(I15=0,J15=0,OR(H15<>0,K15<>0),HLOOKUP($F15,Jornada!$X$7:$AD$37,VLOOKUP(INDIRECT($C$5),Jornada!$C$8:$W$37,21,0),0)>$AK$5,M15>$AK$5),VLOOKUP(INDIRECT($C$5),Jornada!$C$8:$H$37,6,0),IF(AG15>VLOOKUP(INDIRECT($C$5),Jornada!$C$8:$H$37,6,0),IF(VLOOKUP(INDIRECT($C$5),Jornada!$C$8:$H$37,6,0)<AG15,0,ABS(VLOOKUP(INDIRECT($C$5),Jornada!$C$8:$H$37,6,0))-AG15),0)) -> 0 | AJ15: =($AJ$7-K15)+H15 -> 1 | AK15: =IF(AJ15<$AK$7,$AK$7-AJ15,$AI$7) -> 0 | AL15: =HLOOKUP($F15,Jornada!$I$5:$V$37,VLOOKUP(INDIRECT($C$5),Jornada!$C$8:$W$37,21,0)+2,0) -> 0 | AM15: =HLOOKUP($F15,Jornada!$I$4:$V$37,VLOOKUP(INDIRECT($C$5),Jornada!$C$8:$W$37,21,0)+3,0) -> 0 | AN15: =IF(AND(AL15>=$AL$5,AL15<$AN$5,H15>=$AL$5,H15<AL15),AL15-H15,IF(AND(AL15>$AI$7,AL15<=$AM$5,H15>=$AL$5,H15<=$AN$5),$AN$5-H15+AL15,IF(AND(AL15>=$AI$7,AL15<=$AM$5,H15>=$AI$7,H15<=$AM$5,H15<AL15),H15-AL15,0))) -> 0 | AO15: =IF(AP15>Q15,0,AP15) -> 0 | AP15: =IF(Q15=0,0,IF(AND(AM15>=$AL$5,AM15<$AN$5,K15>=$AL$5,K15<$AM$5,K15>AM15),K15-AM15,IF(AND(AM15>=$AL$5,AM15<$AN$5,K15<$AN$5,K15>AM15),K15-$AL$5,IF(AND(AM15>=$AI$7,AM15<$AM$5,K15<$AM$5),K15-AM15,IF(AND(AM15<>AI14,AM15>=$AI$7,AM15<=$AM$5,K15>$AM$5,K15>AM15),$AM$5-AM15,IF(AND(K15>$AL$5,K15<$AN$5),K15-$AL$5,IF(AND(K15>$AI$7,K15<$AM$5),$AN$5-$AL$5+K15,IF(AND(OR(K15>$AL$5,H15>$AO$5),AM15>=$AI$7,AM15<$AM$5,K15>$AM$5),(1+$AM$5-$AL$5)-AG15,0)))))))) -> 0
C16: =IF(Funcionários!C15=0,"",Funcionários!C15) | E16: =Lanç!E16 -> 9 | F16: =Lanç!F16 -> Seg | M16: =IF(AND(H16=K16,H16<>0),$M$6-IF(J16<I16,$AJ$7+J16-I16,J16-I16),IF(H16>K16,(K16+1-H16)-IF(J16<I16,$AJ$7+J16-I16,J16-I16),(K16-H16)-IF(J16<I16,$AJ$7+J16-I16,J16-I16))) -> 0 | O16: =IF(OR(G16=0,G16="Férias",G16="Falta Justificada",G16="Feriado",G16="Folga (DSR)"),0,IF(G16="Falta Injustificada",HLOOKUP($F16,Jornada!$X$7:$AD$37,VLOOKUP(INDIRECT($C$5),Jornada!$C$8:$W$37,21,0),0),IF(HLOOKUP($F16,Jornada!$X$7:$AD$37,VLOOKUP(INDIRECT($C$5),Jornada!$C$8:$W$37,21,0),0)-M16>0,HLOOKUP($F16,Jornada!$X$7:$AD$37,VLOOKUP(INDIRECT($C$5),Jornada!$C$8:$W$37,21,0),0)-M16,0))) -> 0 | P16: =IF(HLOOKUP($F16,Jornada!$X$7:$AD$37,VLOOKUP(INDIRECT($C$5),Jornada!$C$8:$W$37,21,0),0)-M16<0,ABS(HLOOKUP($F16,Jornada!$X$7:$AD$37,VLOOKUP(INDIRECT($C$5),Jornada!$C$8:$W$37,21,0),0)-M16),0) -> 0 | Q16: =IF(G16="Normal",P16,IF(G16=0,0,IF(OR(G16="Feriado",G16="Férias"),IF(H16>K16,(K16+1-H16)-IF(J16<I16,$AJ$7+J16-I16,J16-I16),(K16-H16)-IF(J16<I16,$AJ$7+J16-I16,J16-I16)),IF(G16="Folga (DSR)",IF(H16>K16,(K16+1-H16)-IF(J16<I16,$AJ$7+J16-I16,J16-I16),(K16-H16)-IF(J16<I16,$AJ$7+J16-I16,J16-I16)),IF(G16="Falta Justificada",IF(H16>K16,(K16+1-H16)-IF(J16<I16,$AJ$7+J16-I16,J16-I16),(K16-H16)-IF(J16<I16,$AJ$7+J16-I16,J16-I16)),0))))) -> 0 | R16: =IF(Q16>$R$7,1,0) -> 0 | S16: Total de horas extras | U16: =SUM(Q8:Q38) -> 0 | W16: Outubro | X16: 10 | AB16: =AB15+1 -> 9 | AC16: =WEEKDAY(AB16) -> 2 | AG16: =IF(J16<I16,$AJ$7+J16-I16,J16-I16) -> 0 | AH16: =IF(HLOOKUP($F16,Jornada!$X$7:$AD$37,VLOOKUP(INDIRECT($C$5),Jornada!$C$8:$W$37,21,0),0)=0,0,VLOOKUP(INDIRECT($C$5),Jornada!$C$8:$H$37,4,0)) -> 0 | AI16: =IF(AND(I16=0,J16=0,OR(H16<>0,K16<>0),HLOOKUP($F16,Jornada!$X$7:$AD$37,VLOOKUP(INDIRECT($C$5),Jornada!$C$8:$W$37,21,0),0)>$AK$5,M16>$AK$5),VLOOKUP(INDIRECT($C$5),Jornada!$C$8:$H$37,6,0),IF(AG16>VLOOKUP(INDIRECT($C$5),Jornada!$C$8:$H$37,6,0),IF(VLOOKUP(INDIRECT($C$5),Jornada!$C$8:$H$37,6,0)<AG16,0,ABS(VLOOKUP(INDIRECT($C$5),Jornada!$C$8:$H$37,6,0))-AG16),0)) -> 0 | AJ16: =($AJ$7-K16)+H16 -> 1 | AK16: =IF(AJ16<$AK$7,$AK$7-AJ16,$AI$7) -> 0 | AL16: =HLOOKUP($F16,Jornada!$I$5:$V$37,VLOOKUP(INDIRECT($C$5),Jornada!$C$8:$W$37,21,0)+2,0) -> 0 | AM16: =HLOOKUP($F16,Jornada!$I$4:$V$37,VLOOKUP(INDIRECT($C$5),Jornada!$C$8:$W$37,21,0)+3,0) -> 0 | AN16: =IF(AND(AL16>=$AL$5,AL16<$AN$5,H16>=$AL$5,H16<AL16),AL16-H16,IF(AND(AL16>$AI$7,AL16<=$AM$5,H16>=$AL$5,H16<=$AN$5),$AN$5-H16+AL16,IF(AND(AL16>=$AI$7,AL16<=$AM$5,H16>=$AI$7,H16<=$AM$5,H16<AL16),H16-AL16,0))) -> 0 | AO16: =IF(AP16>Q16,0,AP16) -> 0 | AP16: =IF(Q16=0,0,IF(AND(AM16>=$AL$5,AM16<$AN$5,K16>=$AL$5,K16<$AM$5,K16>AM16),K16-AM16,IF(AND(AM16>=$AL$5,AM16<$AN$5,K16<$AN$5,K16>AM16),K16-$AL$5,IF(AND(AM16>=$AI$7,AM16<$AM$5,K16<$AM$5),K16-AM16,IF(AND(AM16<>AI15,AM16>=$AI$7,AM16<=$AM$5,K16>$AM$5,K16>AM16),$AM$5-AM16,IF(AND(K16>$AL$5,K16<$AN$5),K16-$AL$5,IF(AND(K16>$AI$7,K16<$AM$5),$AN$5-$AL$5+K16,IF(AND(OR(K16>$AL$5,H16>$AO$5),AM16>=$AI$7,AM16<$AM$5,K16>$AM$5),(1+$AM$5-$AL$5)-AG16,0)))))))) -> 0
C17: =IF(Funcionários!C16=0,"",Funcionários!C16) | E17: =Lanç!E17 -> 10 | F17: =Lanç!F17 -> Ter | M17: =IF(AND(H17=K17,H17<>0),$M$6-IF(J17<I17,$AJ$7+J17-I17,J17-I17),IF(H17>K17,(K17+1-H17)-IF(J17<I17,$AJ$7+J17-I17,J17-I17),(K17-H17)-IF(J17<I17,$AJ$7+J17-I17,J17-I17))) -> 0 | O17: =IF(OR(G17=0,G17="Férias",G17="Falta Justificada",G17="Feriado",G17="Folga (DSR)"),0,IF(G17="Falta Injustificada",HLOOKUP($F17,Jornada!$X$7:$AD$37,VLOOKUP(INDIRECT($C$5),Jornada!$C$8:$W$37,21,0),0),IF(HLOOKUP($F17,Jornada!$X$7:$AD$37,VLOOKUP(INDIRECT($C$5),Jornada!$C$8:$W$37,21,0),0)-M17>0,HLOOKUP($F17,Jornada!$X$7:$AD$37,VLOOKUP(INDIRECT($C$5),Jornada!$C$8:$W$37,21,0),0)-M17,0))) -> 0 | P17: =IF(HLOOKUP($F17,Jornada!$X$7:$AD$37,VLOOKUP(INDIRECT($C$5),Jornada!$C$8:$W$37,21,0),0)-M17<0,ABS(HLOOKUP($F17,Jornada!$X$7:$AD$37,VLOOKUP(INDIRECT($C$5),Jornada!$C$8:$W$37,21,0),0)-M17),0) -> 0 | Q17: =IF(G17="Normal",P17,IF(G17=0,0,IF(OR(G17="Feriado",G17="Férias"),IF(H17>K17,(K17+1-H17)-IF(J17<I17,$AJ$7+J17-I17,J17-I17),(K17-H17)-IF(J17<I17,$AJ$7+J17-I17,J17-I17)),IF(G17="Folga (DSR)",IF(H17>K17,(K17+1-H17)-IF(J17<I17,$AJ$7+J17-I17,J17-I17),(K17-H17)-IF(J17<I17,$AJ$7+J17-I17,J17-I17)),IF(G17="Falta Justificada",IF(H17>K17,(K17+1-H17)-IF(J17<I17,$AJ$7+J17-I17,J17-I17),(K17-H17)-IF(J17<I17,$AJ$7+J17-I17,J17-I17)),0))))) -> 0 | R17: =IF(Q17>$R$7,1,0) -> 0 | W17: Novembro | X17: 11 | AB17: =AB16+1 -> 10 | AC17: =WEEKDAY(AB17) -> 3 | AG17: =IF(J17<I17,$AJ$7+J17-I17,J17-I17) -> 0 | AH17: =IF(HLOOKUP($F17,Jornada!$X$7:$AD$37,VLOOKUP(INDIRECT($C$5),Jornada!$C$8:$W$37,21,0),0)=0,0,VLOOKUP(INDIRECT($C$5),Jornada!$C$8:$H$37,4,0)) -> 0 | AI17: =IF(AND(I17=0,J17=0,OR(H17<>0,K17<>0),HLOOKUP($F17,Jornada!$X$7:$AD$37,VLOOKUP(INDIRECT($C$5),Jornada!$C$8:$W$37,21,0),0)>$AK$5,M17>$AK$5),VLOOKUP(INDIRECT($C$5),Jornada!$C$8:$H$37,6,0),IF(AG17>VLOOKUP(INDIRECT($C$5),Jornada!$C$8:$H$37,6,0),IF(VLOOKUP(INDIRECT($C$5),Jornada!$C$8:$H$37,6,0)<AG17,0,ABS(VLOOKUP(INDIRECT($C$5),Jornada!$C$8:$H$37,6,0))-AG17),0)) -> 0 | AJ17: =($AJ$7-K17)+H17 -> 1 | AK17: =IF(AJ17<$AK$7,$AK$7-AJ17,$AI$7) -> 0 | AL17: =HLOOKUP($F17,Jornada!$I$5:$V$37,VLOOKUP(INDIRECT($C$5),Jornada!$C$8:$W$37,21,0)+2,0) -> 0 | AM17: =HLOOKUP($F17,Jornada!$I$4:$V$37,VLOOKUP(INDIRECT($C$5),Jornada!$C$8:$W$37,21,0)+3,0) -> 0 | AN17: =IF(AND(AL17>=$AL$5,AL17<$AN$5,H17>=$AL$5,H17<AL17),AL17-H17,IF(AND(AL17>$AI$7,AL17<=$AM$5,H17>=$AL$5,H17<=$AN$5),$AN$5-H17+AL17,IF(AND(AL17>=$AI$7,AL17<=$AM$5,H17>=$AI$7,H17<=$AM$5,H17<AL17),H17-AL17,0))) -> 0 | AO17: =IF(AP17>Q17,0,AP17) -> 0 | AP17: =IF(Q17=0,0,IF(AND(AM17>=$AL$5,AM17<$AN$5,K17>=$AL$5,K17<$AM$5,K17>AM17),K17-AM17,IF(AND(AM17>=$AL$5,AM17<$AN$5,K17<$AN$5,K17>AM17),K17-$AL$5,IF(AND(AM17>=$AI$7,AM17<$AM$5,K17<$AM$5),K17-AM17,IF(AND(AM17<>AI16,AM17>=$AI$7,AM17<=$AM$5,K17>$AM$5,K17>AM17),$AM$5-AM17,IF(AND(K17>$AL$5,K17<$AN$5),K17-$AL$5,IF(AND(K17>$AI$7,K17<$AM$5),$AN$5-$AL$5+K17,IF(AND(OR(K17>$AL$5,H17>$AO$5),AM17>=$AI$7,AM17<$AM$5,K17>$AM$5),(1+$AM$5-$AL$5)-AG17,0)))))))) -> 0
C18: =IF(Funcionários!C17=0,"",Funcionários!C17) | E18: =Lanç!E18 -> 11 | F18: =Lanç!F18 -> Qua | M18: =IF(AND(H18=K18,H18<>0),$M$6-IF(J18<I18,$AJ$7+J18-I18,J18-I18),IF(H18>K18,(K18+1-H18)-IF(J18<I18,$AJ$7+J18-I18,J18-I18),(K18-H18)-IF(J18<I18,$AJ$7+J18-I18,J18-I18))) -> 0 | O18: =IF(OR(G18=0,G18="Férias",G18="Falta Justificada",G18="Feriado",G18="Folga (DSR)"),0,IF(G18="Falta Injustificada",HLOOKUP($F18,Jornada!$X$7:$AD$37,VLOOKUP(INDIRECT($C$5),Jornada!$C$8:$W$37,21,0),0),IF(HLOOKUP($F18,Jornada!$X$7:$AD$37,VLOOKUP(INDIRECT($C$5),Jornada!$C$8:$W$37,21,0),0)-M18>0,HLOOKUP($F18,Jornada!$X$7:$AD$37,VLOOKUP(INDIRECT($C$5),Jornada!$C$8:$W$37,21,0),0)-M18,0))) -> 0 | P18: =IF(HLOOKUP($F18,Jornada!$X$7:$AD$37,VLOOKUP(INDIRECT($C$5),Jornada!$C$8:$W$37,21,0),0)-M18<0,ABS(HLOOKUP($F18,Jornada!$X$7:$AD$37,VLOOKUP(INDIRECT($C$5),Jornada!$C$8:$W$37,21,0),0)-M18),0) -> 0 | Q18: =IF(G18="Normal",P18,IF(G18=0,0,IF(OR(G18="Feriado",G18="Férias"),IF(H18>K18,(K18+1-H18)-IF(J18<I18,$AJ$7+J18-I18,J18-I18),(K18-H18)-IF(J18<I18,$AJ$7+J18-I18,J18-I18)),IF(G18="Folga (DSR)",IF(H18>K18,(K18+1-H18)-IF(J18<I18,$AJ$7+J18-I18,J18-I18),(K18-H18)-IF(J18<I18,$AJ$7+J18-I18,J18-I18)),IF(G18="Falta Justificada",IF(H18>K18,(K18+1-H18)-IF(J18<I18,$AJ$7+J18-I18,J18-I18),(K18-H18)-IF(J18<I18,$AJ$7+J18-I18,J18-I18)),0))))) -> 0 | R18: =IF(Q18>$R$7,1,0) -> 0 | S18: Total de hora extra a pagar | U18: =F54 -> 0 | W18: Dezembro | X18: 12 | AB18: =AB17+1 -> 11 | AC18: =WEEKDAY(AB18) -> 4 | AG18: =IF(J18<I18,$AJ$7+J18-I18,J18-I18) -> 0 | AH18: =IF(HLOOKUP($F18,Jornada!$X$7:$AD$37,VLOOKUP(INDIRECT($C$5),Jornada!$C$8:$W$37,21,0),0)=0,0,VLOOKUP(INDIRECT($C$5),Jornada!$C$8:$H$37,4,0)) -> 0 | AI18: =IF(AND(I18=0,J18=0,OR(H18<>0,K18<>0),HLOOKUP($F18,Jornada!$X$7:$AD$37,VLOOKUP(INDIRECT($C$5),Jornada!$C$8:$W$37,21,0),0)>$AK$5,M18>$AK$5),VLOOKUP(INDIRECT($C$5),Jornada!$C$8:$H$37,6,0),IF(AG18>VLOOKUP(INDIRECT($C$5),Jornada!$C$8:$H$37,6,0),IF(VLOOKUP(INDIRECT($C$5),Jornada!$C$8:$H$37,6,0)<AG18,0,ABS(VLOOKUP(INDIRECT($C$5),Jornada!$C$8:$H$37,6,0))-AG18),0)) -> 0 | AJ18: =($AJ$7-K18)+H18 -> 1 | AK18: =IF(AJ18<$AK$7,$AK$7-AJ18,$AI$7) -> 0 | AL18: =HLOOKUP($F18,Jornada!$I$5:$V$37,VLOOKUP(INDIRECT($C$5),Jornada!$C$8:$W$37,21,0)+2,0) -> 0 | AM18: =HLOOKUP($F18,Jornada!$I$4:$V$37,VLOOKUP(INDIRECT($C$5),Jornada!$C$8:$W$37,21,0)+3,0) -> 0 | AN18: =IF(AND(AL18>=$AL$5,AL18<$AN$5,H18>=$AL$5,H18<AL18),AL18-H18,IF(AND(AL18>$AI$7,AL18<=$AM$5,H18>=$AL$5,H18<=$AN$5),$AN$5-H18+AL18,IF(AND(AL18>=$AI$7,AL18<=$AM$5,H18>=$AI$7,H18<=$AM$5,H18<AL18),H18-AL18,0))) -> 0 | AO18: =IF(AP18>Q18,0,AP18) -> 0 | AP18: =IF(Q18=0,0,IF(AND(AM18>=$AL$5,AM18<$AN$5,K18>=$AL$5,K18<$AM$5,K18>AM18),K18-AM18,IF(AND(AM18>=$AL$5,AM18<$AN$5,K18<$AN$5,K18>AM18),K18-$AL$5,IF(AND(AM18>=$AI$7,AM18<$AM$5,K18<$AM$5),K18-AM18,IF(AND(AM18<>AI17,AM18>=$AI$7,AM18<=$AM$5,K18>$AM$5,K18>AM18),$AM$5-AM18,IF(AND(K18>$AL$5,K18<$AN$5),K18-$AL$5,IF(AND(K18>$AI$7,K18<$AM$5),$AN$5-$AL$5+K18,IF(AND(OR(K18>$AL$5,H18>$AO$5),AM18>=$AI$7,AM18<$AM$5,K18>$AM$5),(1+$AM$5-$AL$5)-AG18,0)))))))) -> 0
C19: =IF(Funcionários!C18=0,"",Funcionários!C18) | E19: =Lanç!E19 -> 12 | F19: =Lanç!F19 -> Qui | M19: =IF(AND(H19=K19,H19<>0),$M$6-IF(J19<I19,$AJ$7+J19-I19,J19-I19),IF(H19>K19,(K19+1-H19)-IF(J19<I19,$AJ$7+J19-I19,J19-I19),(K19-H19)-IF(J19<I19,$AJ$7+J19-I19,J19-I19))) -> 0 | O19: =IF(OR(G19=0,G19="Férias",G19="Falta Justificada",G19="Feriado",G19="Folga (DSR)"),0,IF(G19="Falta Injustificada",HLOOKUP($F19,Jornada!$X$7:$AD$37,VLOOKUP(INDIRECT($C$5),Jornada!$C$8:$W$37,21,0),0),IF(HLOOKUP($F19,Jornada!$X$7:$AD$37,VLOOKUP(INDIRECT($C$5),Jornada!$C$8:$W$37,21,0),0)-M19>0,HLOOKUP($F19,Jornada!$X$7:$AD$37,VLOOKUP(INDIRECT($C$5),Jornada!$C$8:$W$37,21,0),0)-M19,0))) -> 0 | P19: =IF(HLOOKUP($F19,Jornada!$X$7:$AD$37,VLOOKUP(INDIRECT($C$5),Jornada!$C$8:$W$37,21,0),0)-M19<0,ABS(HLOOKUP($F19,Jornada!$X$7:$AD$37,VLOOKUP(INDIRECT($C$5),Jornada!$C$8:$W$37,21,0),0)-M19),0) -> 0 | Q19: =IF(G19="Normal",P19,IF(G19=0,0,IF(OR(G19="Feriado",G19="Férias"),IF(H19>K19,(K19+1-H19)-IF(J19<I19,$AJ$7+J19-I19,J19-I19),(K19-H19)-IF(J19<I19,$AJ$7+J19-I19,J19-I19)),IF(G19="Folga (DSR)",IF(H19>K19,(K19+1-H19)-IF(J19<I19,$AJ$7+J19-I19,J19-I19),(K19-H19)-IF(J19<I19,$AJ$7+J19-I19,J19-I19)),IF(G19="Falta Justificada",IF(H19>K19,(K19+1-H19)-IF(J19<I19,$AJ$7+J19-I19,J19-I19),(K19-H19)-IF(J19<I19,$AJ$7+J19-I19,J19-I19)),0))))) -> 0 | R19: =IF(Q19>$R$7,1,0) -> 0 | AB19: =AB18+1 -> 12 | AC19: =WEEKDAY(AB19) -> 5 | AG19: =IF(J19<I19,$AJ$7+J19-I19,J19-I19) -> 0 | AH19: =IF(HLOOKUP($F19,Jornada!$X$7:$AD$37,VLOOKUP(INDIRECT($C$5),Jornada!$C$8:$W$37,21,0),0)=0,0,VLOOKUP(INDIRECT($C$5),Jornada!$C$8:$H$37,4,0)) -> 0 | AI19: =IF(AND(I19=0,J19=0,OR(H19<>0,K19<>0),HLOOKUP($F19,Jornada!$X$7:$AD$37,VLOOKUP(INDIRECT($C$5),Jornada!$C$8:$W$37,21,0),0)>$AK$5,M19>$AK$5),VLOOKUP(INDIRECT($C$5),Jornada!$C$8:$H$37,6,0),IF(AG19>VLOOKUP(INDIRECT($C$5),Jornada!$C$8:$H$37,6,0),IF(VLOOKUP(INDIRECT($C$5),Jornada!$C$8:$H$37,6,0)<AG19,0,ABS(VLOOKUP(INDIRECT($C$5),Jornada!$C$8:$H$37,6,0))-AG19),0)) -> 0 | AJ19: =($AJ$7-K19)+H19 -> 1 | AK19: =IF(AJ19<$AK$7,$AK$7-AJ19,$AI$7) -> 0 | AL19: =HLOOKUP($F19,Jornada!$I$5:$V$37,VLOOKUP(INDIRECT($C$5),Jornada!$C$8:$W$37,21,0)+2,0) -> 0 | AM19: =HLOOKUP($F19,Jornada!$I$4:$V$37,VLOOKUP(INDIRECT($C$5),Jornada!$C$8:$W$37,21,0)+3,0) -> 0 | AN19: =IF(AND(AL19>=$AL$5,AL19<$AN$5,H19>=$AL$5,H19<AL19),AL19-H19,IF(AND(AL19>$AI$7,AL19<=$AM$5,H19>=$AL$5,H19<=$AN$5),$AN$5-H19+AL19,IF(AND(AL19>=$AI$7,AL19<=$AM$5,H19>=$AI$7,H19<=$AM$5,H19<AL19),H19-AL19,0))) -> 0 | AO19: =IF(AP19>Q19,0,AP19) -> 0 | AP19: =IF(Q19=0,0,IF(AND(AM19>=$AL$5,AM19<$AN$5,K19>=$AL$5,K19<$AM$5,K19>AM19),K19-AM19,IF(AND(AM19>=$AL$5,AM19<$AN$5,K19<$AN$5,K19>AM19),K19-$AL$5,IF(AND(AM19>=$AI$7,AM19<$AM$5,K19<$AM$5),K19-AM19,IF(AND(AM19<>AI18,AM19>=$AI$7,AM19<=$AM$5,K19>$AM$5,K19>AM19),$AM$5-AM19,IF(AND(K19>$AL$5,K19<$AN$5),K19-$AL$5,IF(AND(K19>$AI$7,K19<$AM$5),$AN$5-$AL$5+K19,IF(AND(OR(K19>$AL$5,H19>$AO$5),AM19>=$AI$7,AM19<$AM$5,K19>$AM$5),(1+$AM$5-$AL$5)-AG19,0)))))))) -> 0
C20: =IF(Funcionários!C19=0,"",Funcionários!C19) | E20: =Lanç!E20 -> 13 | F20: =Lanç!F20 -> Sex | M20: =IF(AND(H20=K20,H20<>0),$M$6-IF(J20<I20,$AJ$7+J20-I20,J20-I20),IF(H20>K20,(K20+1-H20)-IF(J20<I20,$AJ$7+J20-I20,J20-I20),(K20-H20)-IF(J20<I20,$AJ$7+J20-I20,J20-I20))) -> 0 | O20: =IF(OR(G20=0,G20="Férias",G20="Falta Justificada",G20="Feriado",G20="Folga (DSR)"),0,IF(G20="Falta Injustificada",HLOOKUP($F20,Jornada!$X$7:$AD$37,VLOOKUP(INDIRECT($C$5),Jornada!$C$8:$W$37,21,0),0),IF(HLOOKUP($F20,Jornada!$X$7:$AD$37,VLOOKUP(INDIRECT($C$5),Jornada!$C$8:$W$37,21,0),0)-M20>0,HLOOKUP($F20,Jornada!$X$7:$AD$37,VLOOKUP(INDIRECT($C$5),Jornada!$C$8:$W$37,21,0),0)-M20,0))) -> 0 | P20: =IF(HLOOKUP($F20,Jornada!$X$7:$AD$37,VLOOKUP(INDIRECT($C$5),Jornada!$C$8:$W$37,21,0),0)-M20<0,ABS(HLOOKUP($F20,Jornada!$X$7:$AD$37,VLOOKUP(INDIRECT($C$5),Jornada!$C$8:$W$37,21,0),0)-M20),0) -> 0 | Q20: =IF(G20="Normal",P20,IF(G20=0,0,IF(OR(G20="Feriado",G20="Férias"),IF(H20>K20,(K20+1-H20)-IF(J20<I20,$AJ$7+J20-I20,J20-I20),(K20-H20)-IF(J20<I20,$AJ$7+J20-I20,J20-I20)),IF(G20="Folga (DSR)",IF(H20>K20,(K20+1-H20)-IF(J20<I20,$AJ$7+J20-I20,J20-I20),(K20-H20)-IF(J20<I20,$AJ$7+J20-I20,J20-I20)),IF(G20="Falta Justificada",IF(H20>K20,(K20+1-H20)-IF(J20<I20,$AJ$7+J20-I20,J20-I20),(K20-H20)-IF(J20<I20,$AJ$7+J20-I20,J20-I20)),0))))) -> 0 | R20: =IF(Q20>$R$7,1,0) -> 0 | AB20: =AB19+1 -> 13 | AC20: =WEEKDAY(AB20) -> 6 | AG20: =IF(J20<I20,$AJ$7+J20-I20,J20-I20) -> 0 | AH20: =IF(HLOOKUP($F20,Jornada!$X$7:$AD$37,VLOOKUP(INDIRECT($C$5),Jornada!$C$8:$W$37,21,0),0)=0,0,VLOOKUP(INDIRECT($C$5),Jornada!$C$8:$H$37,4,0)) -> 0 | AI20: =IF(AND(I20=0,J20=0,OR(H20<>0,K20<>0),HLOOKUP($F20,Jornada!$X$7:$AD$37,VLOOKUP(INDIRECT($C$5),Jornada!$C$8:$W$37,21,0),0)>$AK$5,M20>$AK$5),VLOOKUP(INDIRECT($C$5),Jornada!$C$8:$H$37,6,0),IF(AG20>VLOOKUP(INDIRECT($C$5),Jornada!$C$8:$H$37,6,0),IF(VLOOKUP(INDIRECT($C$5),Jornada!$C$8:$H$37,6,0)<AG20,0,ABS(VLOOKUP(INDIRECT($C$5),Jornada!$C$8:$H$37,6,0))-AG20),0)) -> 0 | AJ20: =($AJ$7-K20)+H20 -> 1 | AK20: =IF(AJ20<$AK$7,$AK$7-AJ20,$AI$7) -> 0 | AL20: =HLOOKUP($F20,Jornada!$I$5:$V$37,VLOOKUP(INDIRECT($C$5),Jornada!$C$8:$W$37,21,0)+2,0) -> 0 | AM20: =HLOOKUP($F20,Jornada!$I$4:$V$37,VLOOKUP(INDIRECT($C$5),Jornada!$C$8:$W$37,21,0)+3,0) -> 0 | AN20: =IF(AND(AL20>=$AL$5,AL20<$AN$5,H20>=$AL$5,H20<AL20),AL20-H20,IF(AND(AL20>$AI$7,AL20<=$AM$5,H20>=$AL$5,H20<=$AN$5),$AN$5-H20+AL20,IF(AND(AL20>=$AI$7,AL20<=$AM$5,H20>=$AI$7,H20<=$AM$5,H20<AL20),H20-AL20,0))) -> 0 | AO20: =IF(AP20>Q20,0,AP20) -> 0 | AP20: =IF(Q20=0,0,IF(AND(AM20>=$AL$5,AM20<$AN$5,K20>=$AL$5,K20<$AM$5,K20>AM20),K20-AM20,IF(AND(AM20>=$AL$5,AM20<$AN$5,K20<$AN$5,K20>AM20),K20-$AL$5,IF(AND(AM20>=$AI$7,AM20<$AM$5,K20<$AM$5),K20-AM20,IF(AND(AM20<>AI19,AM20>=$AI$7,AM20<=$AM$5,K20>$AM$5,K20>AM20),$AM$5-AM20,IF(AND(K20>$AL$5,K20<$AN$5),K20-$AL$5,IF(AND(K20>$AI$7,K20<$AM$5),$AN$5-$AL$5+K20,IF(AND(OR(K20>$AL$5,H20>$AO$5),AM20>=$AI$7,AM20<$AM$5,K20>$AM$5),(1+$AM$5-$AL$5)-AG20,0)))))))) -> 0
C21: =IF(Funcionários!C20=0,"",Funcionários!C20) | E21: =Lanç!E21 -> 14 | F21: =Lanç!F21 -> Sáb | M21: =IF(AND(H21=K21,H21<>0),$M$6-IF(J21<I21,$AJ$7+J21-I21,J21-I21),IF(H21>K21,(K21+1-H21)-IF(J21<I21,$AJ$7+J21-I21,J21-I21),(K21-H21)-IF(J21<I21,$AJ$7+J21-I21,J21-I21))) -> 0 | O21: =IF(OR(G21=0,G21="Férias",G21="Falta Justificada",G21="Feriado",G21="Folga (DSR)"),0,IF(G21="Falta Injustificada",HLOOKUP($F21,Jornada!$X$7:$AD$37,VLOOKUP(INDIRECT($C$5),Jornada!$C$8:$W$37,21,0),0),IF(HLOOKUP($F21,Jornada!$X$7:$AD$37,VLOOKUP(INDIRECT($C$5),Jornada!$C$8:$W$37,21,0),0)-M21>0,HLOOKUP($F21,Jornada!$X$7:$AD$37,VLOOKUP(INDIRECT($C$5),Jornada!$C$8:$W$37,21,0),0)-M21,0))) -> 0 | P21: =IF(HLOOKUP($F21,Jornada!$X$7:$AD$37,VLOOKUP(INDIRECT($C$5),Jornada!$C$8:$W$37,21,0),0)-M21<0,ABS(HLOOKUP($F21,Jornada!$X$7:$AD$37,VLOOKUP(INDIRECT($C$5),Jornada!$C$8:$W$37,21,0),0)-M21),0) -> 0 | Q21: =IF(G21="Normal",P21,IF(G21=0,0,IF(OR(G21="Feriado",G21="Férias"),IF(H21>K21,(K21+1-H21)-IF(J21<I21,$AJ$7+J21-I21,J21-I21),(K21-H21)-IF(J21<I21,$AJ$7+J21-I21,J21-I21)),IF(G21="Folga (DSR)",IF(H21>K21,(K21+1-H21)-IF(J21<I21,$AJ$7+J21-I21,J21-I21),(K21-H21)-IF(J21<I21,$AJ$7+J21-I21,J21-I21)),IF(G21="Falta Justificada",IF(H21>K21,(K21+1-H21)-IF(J21<I21,$AJ$7+J21-I21,J21-I21),(K21-H21)-IF(J21<I21,$AJ$7+J21-I21,J21-I21)),0))))) -> 0 | R21: =IF(Q21>$R$7,1,0) -> 0 | AB21: =AB20+1 -> 14 | AC21: =WEEKDAY(AB21) -> 7 | AG21: =IF(J21<I21,$AJ$7+J21-I21,J21-I21) -> 0 | AH21: =IF(HLOOKUP($F21,Jornada!$X$7:$AD$37,VLOOKUP(INDIRECT($C$5),Jornada!$C$8:$W$37,21,0),0)=0,0,VLOOKUP(INDIRECT($C$5),Jornada!$C$8:$H$37,4,0)) -> 0 | AI21: =IF(AND(I21=0,J21=0,OR(H21<>0,K21<>0),HLOOKUP($F21,Jornada!$X$7:$AD$37,VLOOKUP(INDIRECT($C$5),Jornada!$C$8:$W$37,21,0),0)>$AK$5,M21>$AK$5),VLOOKUP(INDIRECT($C$5),Jornada!$C$8:$H$37,6,0),IF(AG21>VLOOKUP(INDIRECT($C$5),Jornada!$C$8:$H$37,6,0),IF(VLOOKUP(INDIRECT($C$5),Jornada!$C$8:$H$37,6,0)<AG21,0,ABS(VLOOKUP(INDIRECT($C$5),Jornada!$C$8:$H$37,6,0))-AG21),0)) -> 0 | AJ21: =($AJ$7-K21)+H21 -> 1 | AK21: =IF(AJ21<$AK$7,$AK$7-AJ21,$AI$7) -> 0 | AL21: =HLOOKUP($F21,Jornada!$I$5:$V$37,VLOOKUP(INDIRECT($C$5),Jornada!$C$8:$W$37,21,0)+2,0) -> 0 | AM21: =HLOOKUP($F21,Jornada!$I$4:$V$37,VLOOKUP(INDIRECT($C$5),Jornada!$C$8:$W$37,21,0)+3,0) -> 0 | AN21: =IF(AND(AL21>=$AL$5,AL21<$AN$5,H21>=$AL$5,H21<AL21),AL21-H21,IF(AND(AL21>$AI$7,AL21<=$AM$5,H21>=$AL$5,H21<=$AN$5),$AN$5-H21+AL21,IF(AND(AL21>=$AI$7,AL21<=$AM$5,H21>=$AI$7,H21<=$AM$5,H21<AL21),H21-AL21,0))) -> 0 | AO21: =IF(AP21>Q21,0,AP21) -> 0 | AP21: =IF(Q21=0,0,IF(AND(AM21>=$AL$5,AM21<$AN$5,K21>=$AL$5,K21<$AM$5,K21>AM21),K21-AM21,IF(AND(AM21>=$AL$5,AM21<$AN$5,K21<$AN$5,K21>AM21),K21-$AL$5,IF(AND(AM21>=$AI$7,AM21<$AM$5,K21<$AM$5),K21-AM21,IF(AND(AM21<>AI20,AM21>=$AI$7,AM21<=$AM$5,K21>$AM$5,K21>AM21),$AM$5-AM21,IF(AND(K21>$AL$5,K21<$AN$5),K21-$AL$5,IF(AND(K21>$AI$7,K21<$AM$5),$AN$5-$AL$5+K21,IF(AND(OR(K21>$AL$5,H21>$AO$5),AM21>=$AI$7,AM21<$AM$5,K21>$AM$5),(1+$AM$5-$AL$5)-AG21,0)))))))) -> 0
C22: =IF(Funcionários!C21=0,"",Funcionários!C21) | E22: =Lanç!E22 -> 15 | F22: =Lanç!F22 -> Dom | M22: =IF(AND(H22=K22,H22<>0),$M$6-IF(J22<I22,$AJ$7+J22-I22,J22-I22),IF(H22>K22,(K22+1-H22)-IF(J22<I22,$AJ$7+J22-I22,J22-I22),(K22-H22)-IF(J22<I22,$AJ$7+J22-I22,J22-I22))) -> 0 | O22: =IF(OR(G22=0,G22="Férias",G22="Falta Justificada",G22="Feriado",G22="Folga (DSR)"),0,IF(G22="Falta Injustificada",HLOOKUP($F22,Jornada!$X$7:$AD$37,VLOOKUP(INDIRECT($C$5),Jornada!$C$8:$W$37,21,0),0),IF(HLOOKUP($F22,Jornada!$X$7:$AD$37,VLOOKUP(INDIRECT($C$5),Jornada!$C$8:$W$37,21,0),0)-M22>0,HLOOKUP($F22,Jornada!$X$7:$AD$37,VLOOKUP(INDIRECT($C$5),Jornada!$C$8:$W$37,21,0),0)-M22,0))) -> 0 | P22: =IF(HLOOKUP($F22,Jornada!$X$7:$AD$37,VLOOKUP(INDIRECT($C$5),Jornada!$C$8:$W$37,21,0),0)-M22<0,ABS(HLOOKUP($F22,Jornada!$X$7:$AD$37,VLOOKUP(INDIRECT($C$5),Jornada!$C$8:$W$37,21,0),0)-M22),0) -> 0 | Q22: =IF(G22="Normal",P22,IF(G22=0,0,IF(OR(G22="Feriado",G22="Férias"),IF(H22>K22,(K22+1-H22)-IF(J22<I22,$AJ$7+J22-I22,J22-I22),(K22-H22)-IF(J22<I22,$AJ$7+J22-I22,J22-I22)),IF(G22="Folga (DSR)",IF(H22>K22,(K22+1-H22)-IF(J22<I22,$AJ$7+J22-I22,J22-I22),(K22-H22)-IF(J22<I22,$AJ$7+J22-I22,J22-I22)),IF(G22="Falta Justificada",IF(H22>K22,(K22+1-H22)-IF(J22<I22,$AJ$7+J22-I22,J22-I22),(K22-H22)-IF(J22<I22,$AJ$7+J22-I22,J22-I22)),0))))) -> 0 | R22: =IF(Q22>$R$7,1,0) -> 0 | S22: Horas Extras | AB22: =AB21+1 -> 15 | AC22: =WEEKDAY(AB22) -> 1 | AG22: =IF(J22<I22,$AJ$7+J22-I22,J22-I22) -> 0 | AH22: =IF(HLOOKUP($F22,Jornada!$X$7:$AD$37,VLOOKUP(INDIRECT($C$5),Jornada!$C$8:$W$37,21,0),0)=0,0,VLOOKUP(INDIRECT($C$5),Jornada!$C$8:$H$37,4,0)) -> 0 | AI22: =IF(AND(I22=0,J22=0,OR(H22<>0,K22<>0),HLOOKUP($F22,Jornada!$X$7:$AD$37,VLOOKUP(INDIRECT($C$5),Jornada!$C$8:$W$37,21,0),0)>$AK$5,M22>$AK$5),VLOOKUP(INDIRECT($C$5),Jornada!$C$8:$H$37,6,0),IF(AG22>VLOOKUP(INDIRECT($C$5),Jornada!$C$8:$H$37,6,0),IF(VLOOKUP(INDIRECT($C$5),Jornada!$C$8:$H$37,6,0)<AG22,0,ABS(VLOOKUP(INDIRECT($C$5),Jornada!$C$8:$H$37,6,0))-AG22),0)) -> 0 | AJ22: =($AJ$7-K22)+H22 -> 1 | AK22: =IF(AJ22<$AK$7,$AK$7-AJ22,$AI$7) -> 0 | AL22: =HLOOKUP($F22,Jornada!$I$5:$V$37,VLOOKUP(INDIRECT($C$5),Jornada!$C$8:$W$37,21,0)+2,0) -> 0 | AM22: =HLOOKUP($F22,Jornada!$I$4:$V$37,VLOOKUP(INDIRECT($C$5),Jornada!$C$8:$W$37,21,0)+3,0) -> 0 | AN22: =IF(AND(AL22>=$AL$5,AL22<$AN$5,H22>=$AL$5,H22<AL22),AL22-H22,IF(AND(AL22>$AI$7,AL22<=$AM$5,H22>=$AL$5,H22<=$AN$5),$AN$5-H22+AL22,IF(AND(AL22>=$AI$7,AL22<=$AM$5,H22>=$AI$7,H22<=$AM$5,H22<AL22),H22-AL22,0))) -> 0 | AO22: =IF(AP22>Q22,0,AP22) -> 0 | AP22: =IF(Q22=0,0,IF(AND(AM22>=$AL$5,AM22<$AN$5,K22>=$AL$5,K22<$AM$5,K22>AM22),K22-AM22,IF(AND(AM22>=$AL$5,AM22<$AN$5,K22<$AN$5,K22>AM22),K22-$AL$5,IF(AND(AM22>=$AI$7,AM22<$AM$5,K22<$AM$5),K22-AM22,IF(AND(AM22<>AI21,AM22>=$AI$7,AM22<=$AM$5,K22>$AM$5,K22>AM22),$AM$5-AM22,IF(AND(K22>$AL$5,K22<$AN$5),K22-$AL$5,IF(AND(K22>$AI$7,K22<$AM$5),$AN$5-$AL$5+K22,IF(AND(OR(K22>$AL$5,H22>$AO$5),AM22>=$AI$7,AM22<$AM$5,K22>$AM$5),(1+$AM$5-$AL$5)-AG22,0)))))))) -> 0
C23: =IF(Funcionários!C22=0,"",Funcionários!C22) | E23: =Lanç!E23 -> 16 | F23: =Lanç!F23 -> Seg | M23: =IF(AND(H23=K23,H23<>0),$M$6-IF(J23<I23,$AJ$7+J23-I23,J23-I23),IF(H23>K23,(K23+1-H23)-IF(J23<I23,$AJ$7+J23-I23,J23-I23),(K23-H23)-IF(J23<I23,$AJ$7+J23-I23,J23-I23))) -> 0 | O23: =IF(OR(G23=0,G23="Férias",G23="Falta Justificada",G23="Feriado",G23="Folga (DSR)"),0,IF(G23="Falta Injustificada",HLOOKUP($F23,Jornada!$X$7:$AD$37,VLOOKUP(INDIRECT($C$5),Jornada!$C$8:$W$37,21,0),0),IF(HLOOKUP($F23,Jornada!$X$7:$AD$37,VLOOKUP(INDIRECT($C$5),Jornada!$C$8:$W$37,21,0),0)-M23>0,HLOOKUP($F23,Jornada!$X$7:$AD$37,VLOOKUP(INDIRECT($C$5),Jornada!$C$8:$W$37,21,0),0)-M23,0))) -> 0 | P23: =IF(HLOOKUP($F23,Jornada!$X$7:$AD$37,VLOOKUP(INDIRECT($C$5),Jornada!$C$8:$W$37,21,0),0)-M23<0,ABS(HLOOKUP($F23,Jornada!$X$7:$AD$37,VLOOKUP(INDIRECT($C$5),Jornada!$C$8:$W$37,21,0),0)-M23),0) -> 0 | Q23: =IF(G23="Normal",P23,IF(G23=0,0,IF(OR(G23="Feriado",G23="Férias"),IF(H23>K23,(K23+1-H23)-IF(J23<I23,$AJ$7+J23-I23,J23-I23),(K23-H23)-IF(J23<I23,$AJ$7+J23-I23,J23-I23)),IF(G23="Folga (DSR)",IF(H23>K23,(K23+1-H23)-IF(J23<I23,$AJ$7+J23-I23,J23-I23),(K23-H23)-IF(J23<I23,$AJ$7+J23-I23,J23-I23)),IF(G23="Falta Justificada",IF(H23>K23,(K23+1-H23)-IF(J23<I23,$AJ$7+J23-I23,J23-I23),(K23-H23)-IF(J23<I23,$AJ$7+J23-I23,J23-I23)),0))))) -> 0 | R23: =IF(Q23>$R$7,1,0) -> 0 | S23: =IF(SUM(R8:R38)>0,"Segundo o art 59 da CLT, o máximo de horas extras permitidas por dia são 2 horas. Reveja as horas lançadas se deseja estar de acordo com as leis trabalhistas em vigor no Brasil.","Parabéns!! Todas os dias estão dentro do limite de duas horas extras estipuladas pela CLT.") -> Parabéns!! Todas os dias estão dentro do limite de duas horas extras estipuladas pela CLT. | AB23: =AB22+1 -> 16 | AC23: =WEEKDAY(AB23) -> 2 | AG23: =IF(J23<I23,$AJ$7+J23-I23,J23-I23) -> 0 | AH23: =IF(HLOOKUP($F23,Jornada!$X$7:$AD$37,VLOOKUP(INDIRECT($C$5),Jornada!$C$8:$W$37,21,0),0)=0,0,VLOOKUP(INDIRECT($C$5),Jornada!$C$8:$H$37,4,0)) -> 0 | AI23: =IF(AND(I23=0,J23=0,OR(H23<>0,K23<>0),HLOOKUP($F23,Jornada!$X$7:$AD$37,VLOOKUP(INDIRECT($C$5),Jornada!$C$8:$W$37,21,0),0)>$AK$5,M23>$AK$5),VLOOKUP(INDIRECT($C$5),Jornada!$C$8:$H$37,6,0),IF(AG23>VLOOKUP(INDIRECT($C$5),Jornada!$C$8:$H$37,6,0),IF(VLOOKUP(INDIRECT($C$5),Jornada!$C$8:$H$37,6,0)<AG23,0,ABS(VLOOKUP(INDIRECT($C$5),Jornada!$C$8:$H$37,6,0))-AG23),0)) -> 0 | AJ23: =($AJ$7-K23)+H23 -> 1 | AK23: =IF(AJ23<$AK$7,$AK$7-AJ23,$AI$7) -> 0 | AL23: =HLOOKUP($F23,Jornada!$I$5:$V$37,VLOOKUP(INDIRECT($C$5),Jornada!$C$8:$W$37,21,0)+2,0) -> 0 | AM23: =HLOOKUP($F23,Jornada!$I$4:$V$37,VLOOKUP(INDIRECT($C$5),Jornada!$C$8:$W$37,21,0)+3,0) -> 0 | AN23: =IF(AND(AL23>=$AL$5,AL23<$AN$5,H23>=$AL$5,H23<AL23),AL23-H23,IF(AND(AL23>$AI$7,AL23<=$AM$5,H23>=$AL$5,H23<=$AN$5),$AN$5-H23+AL23,IF(AND(AL23>=$AI$7,AL23<=$AM$5,H23>=$AI$7,H23<=$AM$5,H23<AL23),H23-AL23,0))) -> 0 | AO23: =IF(AP23>Q23,0,AP23) -> 0 | AP23: =IF(Q23=0,0,IF(AND(AM23>=$AL$5,AM23<$AN$5,K23>=$AL$5,K23<$AM$5,K23>AM23),K23-AM23,IF(AND(AM23>=$AL$5,AM23<$AN$5,K23<$AN$5,K23>AM23),K23-$AL$5,IF(AND(AM23>=$AI$7,AM23<$AM$5,K23<$AM$5),K23-AM23,IF(AND(AM23<>AI22,AM23>=$AI$7,AM23<=$AM$5,K23>$AM$5,K23>AM23),$AM$5-AM23,IF(AND(K23>$AL$5,K23<$AN$5),K23-$AL$5,IF(AND(K23>$AI$7,K23<$AM$5),$AN$5-$AL$5+K23,IF(AND(OR(K23>$AL$5,H23>$AO$5),AM23>=$AI$7,AM23<$AM$5,K23>$AM$5),(1+$AM$5-$AL$5)-AG23,0)))))))) -> 0
C24: =IF(Funcionários!C23=0,"",Funcionários!C23) | E24: =Lanç!E24 -> 17 | F24: =Lanç!F24 -> Ter | M24: =IF(AND(H24=K24,H24<>0),$M$6-IF(J24<I24,$AJ$7+J24-I24,J24-I24),IF(H24>K24,(K24+1-H24)-IF(J24<I24,$AJ$7+J24-I24,J24-I24),(K24-H24)-IF(J24<I24,$AJ$7+J24-I24,J24-I24))) -> 0 | O24: =IF(OR(G24=0,G24="Férias",G24="Falta Justificada",G24="Feriado",G24="Folga (DSR)"),0,IF(G24="Falta Injustificada",HLOOKUP($F24,Jornada!$X$7:$AD$37,VLOOKUP(INDIRECT($C$5),Jornada!$C$8:$W$37,21,0),0),IF(HLOOKUP($F24,Jornada!$X$7:$AD$37,VLOOKUP(INDIRECT($C$5),Jornada!$C$8:$W$37,21,0),0)-M24>0,HLOOKUP($F24,Jornada!$X$7:$AD$37,VLOOKUP(INDIRECT($C$5),Jornada!$C$8:$W$37,21,0),0)-M24,0))) -> 0 | P24: =IF(HLOOKUP($F24,Jornada!$X$7:$AD$37,VLOOKUP(INDIRECT($C$5),Jornada!$C$8:$W$37,21,0),0)-M24<0,ABS(HLOOKUP($F24,Jornada!$X$7:$AD$37,VLOOKUP(INDIRECT($C$5),Jornada!$C$8:$W$37,21,0),0)-M24),0) -> 0 | Q24: =IF(G24="Normal",P24,IF(G24=0,0,IF(OR(G24="Feriado",G24="Férias"),IF(H24>K24,(K24+1-H24)-IF(J24<I24,$AJ$7+J24-I24,J24-I24),(K24-H24)-IF(J24<I24,$AJ$7+J24-I24,J24-I24)),IF(G24="Folga (DSR)",IF(H24>K24,(K24+1-H24)-IF(J24<I24,$AJ$7+J24-I24,J24-I24),(K24-H24)-IF(J24<I24,$AJ$7+J24-I24,J24-I24)),IF(G24="Falta Justificada",IF(H24>K24,(K24+1-H24)-IF(J24<I24,$AJ$7+J24-I24,J24-I24),(K24-H24)-IF(J24<I24,$AJ$7+J24-I24,J24-I24)),0))))) -> 0 | R24: =IF(Q24>$R$7,1,0) -> 0 | AB24: =AB23+1 -> 17 | AC24: =WEEKDAY(AB24) -> 3 | AG24: =IF(J24<I24,$AJ$7+J24-I24,J24-I24) -> 0 | AH24: =IF(HLOOKUP($F24,Jornada!$X$7:$AD$37,VLOOKUP(INDIRECT($C$5),Jornada!$C$8:$W$37,21,0),0)=0,0,VLOOKUP(INDIRECT($C$5),Jornada!$C$8:$H$37,4,0)) -> 0 | AI24: =IF(AND(I24=0,J24=0,OR(H24<>0,K24<>0),HLOOKUP($F24,Jornada!$X$7:$AD$37,VLOOKUP(INDIRECT($C$5),Jornada!$C$8:$W$37,21,0),0)>$AK$5,M24>$AK$5),VLOOKUP(INDIRECT($C$5),Jornada!$C$8:$H$37,6,0),IF(AG24>VLOOKUP(INDIRECT($C$5),Jornada!$C$8:$H$37,6,0),IF(VLOOKUP(INDIRECT($C$5),Jornada!$C$8:$H$37,6,0)<AG24,0,ABS(VLOOKUP(INDIRECT($C$5),Jornada!$C$8:$H$37,6,0))-AG24),0)) -> 0 | AJ24: =($AJ$7-K24)+H24 -> 1 | AK24: =IF(AJ24<$AK$7,$AK$7-AJ24,$AI$7) -> 0 | AL24: =HLOOKUP($F24,Jornada!$I$5:$V$37,VLOOKUP(INDIRECT($C$5),Jornada!$C$8:$W$37,21,0)+2,0) -> 0 | AM24: =HLOOKUP($F24,Jornada!$I$4:$V$37,VLOOKUP(INDIRECT($C$5),Jornada!$C$8:$W$37,21,0)+3,0) -> 0 | AN24: =IF(AND(AL24>=$AL$5,AL24<$AN$5,H24>=$AL$5,H24<AL24),AL24-H24,IF(AND(AL24>$AI$7,AL24<=$AM$5,H24>=$AL$5,H24<=$AN$5),$AN$5-H24+AL24,IF(AND(AL24>=$AI$7,AL24<=$AM$5,H24>=$AI$7,H24<=$AM$5,H24<AL24),H24-AL24,0))) -> 0 | AO24: =IF(AP24>Q24,0,AP24) -> 0 | AP24: =IF(Q24=0,0,IF(AND(AM24>=$AL$5,AM24<$AN$5,K24>=$AL$5,K24<$AM$5,K24>AM24),K24-AM24,IF(AND(AM24>=$AL$5,AM24<$AN$5,K24<$AN$5,K24>AM24),K24-$AL$5,IF(AND(AM24>=$AI$7,AM24<$AM$5,K24<$AM$5),K24-AM24,IF(AND(AM24<>AI23,AM24>=$AI$7,AM24<=$AM$5,K24>$AM$5,K24>AM24),$AM$5-AM24,IF(AND(K24>$AL$5,K24<$AN$5),K24-$AL$5,IF(AND(K24>$AI$7,K24<$AM$5),$AN$5-$AL$5+K24,IF(AND(OR(K24>$AL$5,H24>$AO$5),AM24>=$AI$7,AM24<$AM$5,K24>$AM$5),(1+$AM$5-$AL$5)-AG24,0)))))))) -> 0
C25: =IF(Funcionários!C24=0,"",Funcionários!C24) | E25: =Lanç!E25 -> 18 | F25: =Lanç!F25 -> Qua | M25: =IF(AND(H25=K25,H25<>0),$M$6-IF(J25<I25,$AJ$7+J25-I25,J25-I25),IF(H25>K25,(K25+1-H25)-IF(J25<I25,$AJ$7+J25-I25,J25-I25),(K25-H25)-IF(J25<I25,$AJ$7+J25-I25,J25-I25))) -> 0 | O25: =IF(OR(G25=0,G25="Férias",G25="Falta Justificada",G25="Feriado",G25="Folga (DSR)"),0,IF(G25="Falta Injustificada",HLOOKUP($F25,Jornada!$X$7:$AD$37,VLOOKUP(INDIRECT($C$5),Jornada!$C$8:$W$37,21,0),0),IF(HLOOKUP($F25,Jornada!$X$7:$AD$37,VLOOKUP(INDIRECT($C$5),Jornada!$C$8:$W$37,21,0),0)-M25>0,HLOOKUP($F25,Jornada!$X$7:$AD$37,VLOOKUP(INDIRECT($C$5),Jornada!$C$8:$W$37,21,0),0)-M25,0))) -> 0 | P25: =IF(HLOOKUP($F25,Jornada!$X$7:$AD$37,VLOOKUP(INDIRECT($C$5),Jornada!$C$8:$W$37,21,0),0)-M25<0,ABS(HLOOKUP($F25,Jornada!$X$7:$AD$37,VLOOKUP(INDIRECT($C$5),Jornada!$C$8:$W$37,21,0),0)-M25),0) -> 0 | Q25: =IF(G25="Normal",P25,IF(G25=0,0,IF(OR(G25="Feriado",G25="Férias"),IF(H25>K25,(K25+1-H25)-IF(J25<I25,$AJ$7+J25-I25,J25-I25),(K25-H25)-IF(J25<I25,$AJ$7+J25-I25,J25-I25)),IF(G25="Folga (DSR)",IF(H25>K25,(K25+1-H25)-IF(J25<I25,$AJ$7+J25-I25,J25-I25),(K25-H25)-IF(J25<I25,$AJ$7+J25-I25,J25-I25)),IF(G25="Falta Justificada",IF(H25>K25,(K25+1-H25)-IF(J25<I25,$AJ$7+J25-I25,J25-I25),(K25-H25)-IF(J25<I25,$AJ$7+J25-I25,J25-I25)),0))))) -> 0 | R25: =IF(Q25>$R$7,1,0) -> 0 | Z25: =IF(SUM(R8:R38)>0,1,0) -> 0 | AB25: =AB24+1 -> 18 | AC25: =WEEKDAY(AB25) -> 4 | AG25: =IF(J25<I25,$AJ$7+J25-I25,J25-I25) -> 0 | AH25: =IF(HLOOKUP($F25,Jornada!$X$7:$AD$37,VLOOKUP(INDIRECT($C$5),Jornada!$C$8:$W$37,21,0),0)=0,0,VLOOKUP(INDIRECT($C$5),Jornada!$C$8:$H$37,4,0)) -> 0 | AI25: =IF(AND(I25=0,J25=0,OR(H25<>0,K25<>0),HLOOKUP($F25,Jornada!$X$7:$AD$37,VLOOKUP(INDIRECT($C$5),Jornada!$C$8:$W$37,21,0),0)>$AK$5,M25>$AK$5),VLOOKUP(INDIRECT($C$5),Jornada!$C$8:$H$37,6,0),IF(AG25>VLOOKUP(INDIRECT($C$5),Jornada!$C$8:$H$37,6,0),IF(VLOOKUP(INDIRECT($C$5),Jornada!$C$8:$H$37,6,0)<AG25,0,ABS(VLOOKUP(INDIRECT($C$5),Jornada!$C$8:$H$37,6,0))-AG25),0)) -> 0 | AJ25: =($AJ$7-K25)+H25 -> 1 | AK25: =IF(AJ25<$AK$7,$AK$7-AJ25,$AI$7) -> 0 | AL25: =HLOOKUP($F25,Jornada!$I$5:$V$37,VLOOKUP(INDIRECT($C$5),Jornada!$C$8:$W$37,21,0)+2,0) -> 0 | AM25: =HLOOKUP($F25,Jornada!$I$4:$V$37,VLOOKUP(INDIRECT($C$5),Jornada!$C$8:$W$37,21,0)+3,0) -> 0 | AN25: =IF(AND(AL25>=$AL$5,AL25<$AN$5,H25>=$AL$5,H25<AL25),AL25-H25,IF(AND(AL25>$AI$7,AL25<=$AM$5,H25>=$AL$5,H25<=$AN$5),$AN$5-H25+AL25,IF(AND(AL25>=$AI$7,AL25<=$AM$5,H25>=$AI$7,H25<=$AM$5,H25<AL25),H25-AL25,0))) -> 0 | AO25: =IF(AP25>Q25,0,AP25) -> 0 | AP25: =IF(Q25=0,0,IF(AND(AM25>=$AL$5,AM25<$AN$5,K25>=$AL$5,K25<$AM$5,K25>AM25),K25-AM25,IF(AND(AM25>=$AL$5,AM25<$AN$5,K25<$AN$5,K25>AM25),K25-$AL$5,IF(AND(AM25>=$AI$7,AM25<$AM$5,K25<$AM$5),K25-AM25,IF(AND(AM25<>AI24,AM25>=$AI$7,AM25<=$AM$5,K25>$AM$5,K25>AM25),$AM$5-AM25,IF(AND(K25>$AL$5,K25<$AN$5),K25-$AL$5,IF(AND(K25>$AI$7,K25<$AM$5),$AN$5-$AL$5+K25,IF(AND(OR(K25>$AL$5,H25>$AO$5),AM25>=$AI$7,AM25<$AM$5,K25>$AM$5),(1+$AM$5-$AL$5)-AG25,0)))))))) -> 0
C26: =IF(Funcionários!C25=0,"",Funcionários!C25) | E26: =Lanç!E26 -> 19 | F26: =Lanç!F26 -> Qui | M26: =IF(AND(H26=K26,H26<>0),$M$6-IF(J26<I26,$AJ$7+J26-I26,J26-I26),IF(H26>K26,(K26+1-H26)-IF(J26<I26,$AJ$7+J26-I26,J26-I26),(K26-H26)-IF(J26<I26,$AJ$7+J26-I26,J26-I26))) -> 0 | O26: =IF(OR(G26=0,G26="Férias",G26="Falta Justificada",G26="Feriado",G26="Folga (DSR)"),0,IF(G26="Falta Injustificada",HLOOKUP($F26,Jornada!$X$7:$AD$37,VLOOKUP(INDIRECT($C$5),Jornada!$C$8:$W$37,21,0),0),IF(HLOOKUP($F26,Jornada!$X$7:$AD$37,VLOOKUP(INDIRECT($C$5),Jornada!$C$8:$W$37,21,0),0)-M26>0,HLOOKUP($F26,Jornada!$X$7:$AD$37,VLOOKUP(INDIRECT($C$5),Jornada!$C$8:$W$37,21,0),0)-M26,0))) -> 0 | P26: =IF(HLOOKUP($F26,Jornada!$X$7:$AD$37,VLOOKUP(INDIRECT($C$5),Jornada!$C$8:$W$37,21,0),0)-M26<0,ABS(HLOOKUP($F26,Jornada!$X$7:$AD$37,VLOOKUP(INDIRECT($C$5),Jornada!$C$8:$W$37,21,0),0)-M26),0) -> 0 | Q26: =IF(G26="Normal",P26,IF(G26=0,0,IF(OR(G26="Feriado",G26="Férias"),IF(H26>K26,(K26+1-H26)-IF(J26<I26,$AJ$7+J26-I26,J26-I26),(K26-H26)-IF(J26<I26,$AJ$7+J26-I26,J26-I26)),IF(G26="Folga (DSR)",IF(H26>K26,(K26+1-H26)-IF(J26<I26,$AJ$7+J26-I26,J26-I26),(K26-H26)-IF(J26<I26,$AJ$7+J26-I26,J26-I26)),IF(G26="Falta Justificada",IF(H26>K26,(K26+1-H26)-IF(J26<I26,$AJ$7+J26-I26,J26-I26),(K26-H26)-IF(J26<I26,$AJ$7+J26-I26,J26-I26)),0))))) -> 0 | R26: =IF(Q26>$R$7,1,0) -> 0 | S26: =IF(COUNTIF(G8:G38,"Folga (DSR)")<DAY(E39)/8,"O mês não está contemplando um DSR (Descanso Semanal Remunerado) por semana. Isso pode configurar uma irregularidade segundo as leis trabalhistas.","Parabéns!! Sua folha de pagamento contempla uma DSR por semana conforme a lei trabalhista.") -> O mês não está contemplando um DSR (Descanso Semanal Remunerado) por semana. Isso pode configurar uma irregularidade segundo as leis trabalhistas. | AB26: =AB25+1 -> 19 | AC26: =WEEKDAY(AB26) -> 5 | AG26: =IF(J26<I26,$AJ$7+J26-I26,J26-I26) -> 0 | AH26: =IF(HLOOKUP($F26,Jornada!$X$7:$AD$37,VLOOKUP(INDIRECT($C$5),Jornada!$C$8:$W$37,21,0),0)=0,0,VLOOKUP(INDIRECT($C$5),Jornada!$C$8:$H$37,4,0)) -> 0 | AI26: =IF(AND(I26=0,J26=0,OR(H26<>0,K26<>0),HLOOKUP($F26,Jornada!$X$7:$AD$37,VLOOKUP(INDIRECT($C$5),Jornada!$C$8:$W$37,21,0),0)>$AK$5,M26>$AK$5),VLOOKUP(INDIRECT($C$5),Jornada!$C$8:$H$37,6,0),IF(AG26>VLOOKUP(INDIRECT($C$5),Jornada!$C$8:$H$37,6,0),IF(VLOOKUP(INDIRECT($C$5),Jornada!$C$8:$H$37,6,0)<AG26,0,ABS(VLOOKUP(INDIRECT($C$5),Jornada!$C$8:$H$37,6,0))-AG26),0)) -> 0 | AJ26: =($AJ$7-K26)+H26 -> 1 | AK26: =IF(AJ26<$AK$7,$AK$7-AJ26,$AI$7) -> 0 | AL26: =HLOOKUP($F26,Jornada!$I$5:$V$37,VLOOKUP(INDIRECT($C$5),Jornada!$C$8:$W$37,21,0)+2,0) -> 0 | AM26: =HLOOKUP($F26,Jornada!$I$4:$V$37,VLOOKUP(INDIRECT($C$5),Jornada!$C$8:$W$37,21,0)+3,0) -> 0 | AN26: =IF(AND(AL26>=$AL$5,AL26<$AN$5,H26>=$AL$5,H26<AL26),AL26-H26,IF(AND(AL26>$AI$7,AL26<=$AM$5,H26>=$AL$5,H26<=$AN$5),$AN$5-H26+AL26,IF(AND(AL26>=$AI$7,AL26<=$AM$5,H26>=$AI$7,H26<=$AM$5,H26<AL26),H26-AL26,0))) -> 0 | AO26: =IF(AP26>Q26,0,AP26) -> 0 | AP26: =IF(Q26=0,0,IF(AND(AM26>=$AL$5,AM26<$AN$5,K26>=$AL$5,K26<$AM$5,K26>AM26),K26-AM26,IF(AND(AM26>=$AL$5,AM26<$AN$5,K26<$AN$5,K26>AM26),K26-$AL$5,IF(AND(AM26>=$AI$7,AM26<$AM$5,K26<$AM$5),K26-AM26,IF(AND(AM26<>AI25,AM26>=$AI$7,AM26<=$AM$5,K26>$AM$5,K26>AM26),$AM$5-AM26,IF(AND(K26>$AL$5,K26<$AN$5),K26-$AL$5,IF(AND(K26>$AI$7,K26<$AM$5),$AN$5-$AL$5+K26,IF(AND(OR(K26>$AL$5,H26>$AO$5),AM26>=$AI$7,AM26<$AM$5,K26>$AM$5),(1+$AM$5-$AL$5)-AG26,0)))))))) -> 0
