Workbook

Sheet BP
A1: A T I V O | B1: 2005 | C1: 2006 | E1: P A S S I V O | F1: =B1 -> 2005 | G1: =C1 -> 2006
A2: Caixa | B2: 35000 | C2: 43800 | E2: Fornecedores | F2: 155000 | G2: 195000
A3: Bancos | B3: 155000 | C3: 192500 | E3: Impostos a pagar | F3: 80325 | G3: 138690
A4: Duplicatas a receber | B4: 200000 | C4: 360000 | E4: Salários a pagar | F4: 118000 | G4: 150000
A5: Estoques | B5: 230000 | C5: 285500 | E5: Empréstimos a pagar | F5: 67500 | G5: 85310
A6: Ativo Circulante | B6: =SUM(B2:B5) -> 620000 | C6: =SUM(C2:C5) -> 881800 | E6: Passivo Circulante | F6: =SUM(F2:F5) -> 420825 | G6: =SUM(G2:G5) -> 569000
A7: Contas a receber | B7: 85535 | C7: 93120 | E7: Empréstimos a pagar | F7: 35000 | G7: 67000
A8: Despesas Antecipadas (LP) | B8: 20290 | C8: 61000 | E8: Empréstimos do exterior | F8: 155000 | G8: 250000
A9: Realizável a Longo Prazo | B9: =SUM(B7:B8) -> 105825 | C9: =SUM(C7:C8) -> 154120 | E9: Exigível a Longo Prazo | F9: =SUM(F7:F8) -> 190000 | G9: =SUM(G7:G8) -> 317000
A10: Investimentos | B10: 700000 | C10: 1300000 | E10: Capital Social | F10: 2000000 | G10: 3500000
A11: Imobilizado | B11: 2500000 | C11: 3400000 | E11: Reservas de capital | F11: 850000 | G11: 762500
A12: Diferido Líquido | B12: 350000 | C12: 450000 | E12: Reserva legal | F12: 200000 | G12: 262878
A13: Ativo Permanente | B13: =SUM(B10:B12) -> 3550000 | C13: =SUM(C10:C12) -> 5150000 | E13: Reserva estatutária | F13: 250000 | G13: 338256
E14: Reserva de contingência | F14: 150000 | G14: 126134
E15: Lucros Acumulados | F15: 215000 | G15: 310152
E16: Patrimônio Líquido | F16: =SUM(F10:F15) -> 3665000 | G16: =SUM(G10:G15) -> 5299920
A17: Total Ativo | B17: =B6+B9+B13 -> 4275825 | C17: =C6+C9+C13 -> 6185920 | E17: Total Passivo | F17: =F6+F9+F16 -> 4275825 | G17: =G6+G9+G16 -> 6185920

Sheet DRE
A1: DRE | B1: =BP!B1 -> 2005 | C1: =BP!C1 -> 2006
A3: Receita Bruta | B3: 18000000 | C3: 29000000
A4: Impostos sobre Receita Bruta | B4: -1750000 | C4: -2850000
A5: Receita Líquida | B5: =SUM(B3:B4) -> 16250000 | C5: =SUM(C3:C4) -> 26150000
A6: CMV | B6: -8750000 | C6: -14100000
A7: Lucro Bruto | B7: =SUM(B5:B6) -> 7500000 | C7: =SUM(C5:C6) -> 12050000
A8: Despesas operacionais | B8: =SUM(B9:B15) -> -7215000 | C8: =SUM(C9:C15) -> -11625000
A9: Despesas com vendas | B9: -1850000 | C9: -3000000
A10: Despesas Administrativas | B10: -4450000 | C10: -7150000
A11: Despesas Financeiras | B11: -570000 | C11: -920000
A12: Despesas de Depreciação | B12: -250000 | C12: -400000
A13: Despesas de Amortização | B13: -80000 | C13: -130000
A14: Variação cambial | B14: -40000 | C14: -65000
A15: Resultado MEP | B15: 25000 | C15: 40000
A16: Lucro Operacional | B16: =B7+B8 -> 285000 | C16: =C7+C8 -> 425000
A17: Resultado não operacional | B17: -55500 | C17: -28750
A18: LAIR | B18: =SUM(B16:B17) -> 229500 | C18: =SUM(C16:C17) -> 396250
A19: Provisão para IR | B19: -80325 | C19: -138690
A20: Lucro líquido | B20: =SUM(B18:B19) -> 149175 | C20: =SUM(C18:C19) -> 257560
A21: Nº de ações | B21: 100000 | C21: 128780
A22: Lucro por ação | B22: =B20/B21 -> 1.49175 | C22: =C20/C21 -> 2

Sheet Índices
A1: A T I V O | B1: 2005 | C1: 2006 | G1: =B1 -> 2005 | H1: =C1 -> 2006
A2: Ativo Circulante | B2: 620000 | C2: 881800 | E2: RSA | F2: (LL + DF)*100/AT | G2: =(DRE!B20+-1*DRE!B11)*100/B4 -> 20.258451 | H2: =(DRE!C20+-1*DRE!C11)*100/C4 -> 22.865243
A3: Realizável a Longo Prazo | B3: 105825 | C3: 154120
A4: Ativo Permanente | B4: 3550000 | C4: 5150000 | E4: CD | F4: (DF*100)/PL | G4: =DRE!B11*100/B9 -> -93.316416 | H4: =DRE!C11*100/C9 -> -103.83747
A6: P A S S I V O | B6: 2005 | C6: 2006 | E6: RSPL | F6: (LL*100)/PL | G6: =DRE!B20*100/B10 -> 4.0702592 | H6: =DRE!C20*100/C10 -> 4.859696
A7: Passivo Circulante | B7: 420825 | C7: 569000
A8: Exigível a Longo Prazo | B8: 190000 | C8: 317000 | E8: GAF | F8: RSA/RSPL | G8: =G6/G2 -> 0.20091661 | H8: =H6/H2 -> 0.21253638
A9: Exigível total | B9: =SUM(B7:B8) -> 610825 | C9: =SUM(C7:C8) -> 886000
A10: Patrimônio Líquido | B10: 3665000 | C10: 5299920
A11: Total Passivo | B11: 4275825 | C11: 6185920
A17: Total Ativo | B17: 4275825 | C17: 6185920

Sheet Análises
B2: Necessidade de Capital de Giro
B3: Contas | C3: =BP!B1 -> 2005 | D3: 2006
B4: Ativo Cíclico | C4: =SUM(C5:C6) -> 430000 | D4: =SUM(D5:D6) -> 645500
B5: =BP!A4 -> Duplicatas a receber | C5: =BP!B4 -> 200000 | D5: =BP!C4 -> 360000
B6: =BP!A5 -> Estoques | C6: =BP!B5 -> 230000 | D6: =BP!C5 -> 285500
B8: Passivo Ciclico | C8: =SUM(C9:C11) -> 353325 | D8: =SUM(D9:D11) -> 483690
B9: =BP!E2 -> Fornecedores | C9: =BP!F2 -> 155000 | D9: =BP!G2 -> 195000
B10: =BP!E3 -> Impostos a pagar | C10: =BP!F3 -> 80325 | D10: =BP!G3 -> 138690
B11: =BP!E4 -> Salários a pagar | C11: =BP!F4 -> 118000 | D11: =BP!G4 -> 150000
B13: Necessidade Líquidad de Capital de Giro | C13: =C4-C8 -> 76675 | D13: =D4-D8 -> 161810
B16: Efeito Tesoura
B17: Contas | C17: =BP!B1 -> 2005 | D17: =BP!C1 -> 2006
B18: Ativo errático | C18: =SUM(C19:C20) -> 190000 | D18: =SUM(D19:D20) -> 236300
B19: =BP!A2 -> Caixa | C19: =BP!B2 -> 35000 | D19: =BP!C2 -> 43800
B20: =BP!A3 -> Bancos | C20: =BP!B3 -> 155000 | D20: =BP!C3 -> 192500
B22: Passivo Errático | C22: =SUM(C23:C24) -> 488325 | D22: =SUM(D23:D24) -> 654310
B23: =BP!E5 -> Empréstimos a pagar | C23: =BP!F5 -> 67500 | D23: =BP!G5 -> 85310
B24: =BP!E6 -> Passivo Circulante | C24: =BP!F6 -> 420825 | D24: =BP!G6 -> 569000
B26: Tesouraria (T) | C26: =C18-C22 -> -298325 | D26: =D18-D22 -> -418010
B29: Contas | C29: =BP!B1 -> 2005 | D29: =BP!C1 -> 2006
B30: =BP!A9 -> Realizável a Longo Prazo | C30: =SUM(C31:C32) -> 105825 | D30: =SUM(D31:D32) -> 154120
B31: =BP!A7 -> Contas a receber | C31: =BP!B7 -> 85535 | D31: =BP!C7 -> 93120
B32: =BP!A8 -> Despesas Antecipadas (LP) | C32: =BP!B8 -> 20290 | D32: =BP!C8 -> 61000
B34: =BP!E9 -> Exigível a Longo Prazo | C34: =SUM(C35:C36) -> 190000 | D34: =SUM(D35:D36) -> 317000
B35: =BP!E7 -> Empréstimos a pagar | C35: =BP!F7 -> 35000 | D35: =BP!G7 -> 67000
B36: =BP!E8 -> Empréstimos do exterior | C36: =BP!F8 -> 155000 | D36: =BP!G8 -> 250000
B38: (=) Longo Prazo | C38: =C30-C34 -> -84175 | D38: =D30-D34 -> -162880
B40: =BP!E16 -> Patrimônio Líquido | C40: =BP!F16 -> 3665000 | D40: =BP!G16 -> 5299920
B41: =BP!A13 -> Ativo Permanente | C41: =SUM(C42:C44) -> 3550000 | D41: =SUM(D42:D44) -> 5150000
B42: =BP!A10 -> Investimentos | C42: =BP!B10 -> 700000 | D42: =BP!C10 -> 1300000
B43: =BP!A11 -> Imobilizado | C43: =BP!B11 -> 2500000 | D43: =BP!C11 -> 3400000
B44: =BP!A12 -> Diferido Líquido | C44: =BP!B12 -> 350000 | D44: =BP!C12 -> 450000
B45: (=) Capital de Giro | C45: =C40-C41 -> 115000 | D45: =D40-D41 -> 149920
