Workbook

Sheet CPC 06 R2 - Árvore de Decisão
B2: FAQ CPC 06 (R2)
B4: 1) | C4: Existe um Ativo Identificado?
B6: 2) | C6: O cliente tem o direito de obter substancialmente todos os benefícios econômicos do uso do ativo durante todo o período de uso?
B9: 3) | C9: O cliente, o fornecedor, ou nenhuma das partes, tem o direito de direcionar como e para qual finalidade o ativo é usado durante todo o período de uso?
B12: 4) | C12: O cliente tem direito de operar o ativo durante todo o período de uso, sem o fornecedor ter o direito de alterar essas instruções operacionais?
B15: 5) | C15: O cliente projetou o ativo de modo que predetermina como e para qual finalidade o ativo será usado durante todo o período de uso?

Sheet Resumo Contratos
B2: Resumo Contratos de Alugueis
B4: # Identificação Contrato | C4: Conforme Contrato | O4: Utilizado para análise
C5: Tipo Contrato | D5: Locador | E5: Ativo Identificado | F5: Valor ao mês | G5: Reajuste | H5: Entrada / Antecipação | I5: Taxa Implícita (a.a.) | J5: Prazo (Meses) | K5: Data Início | L5: Data Final | M5: Observação | O5: Arrendamento conforme CPC 06 ? | P5: Justificativa | Q5: Reajuste Anual | R5: Taxa Incremental (a.a.) | S5: Prazo (Meses) | T5: Data Início | U5: Data Final | V5: Observação
B6: 1 | C6: Instrumento Particular de Contrato de Locação de Imóvel Urbano para fins comerciais | D6: Sandro G de Moraes ME | E6: Terreno urbano de nº 07-B-8, com 5.969m², com três edificações, sendo que a primeira refere-se a um barracão comercial em alvenaria, medindo 700m², a segunda refere-se a uma varanda de aproximadamente 180m², e a terceira trata-se de construção no andar superior mediindo 75m², melhor descrita e caracterizada na Matrícula de nº 1.615, do Cartório de Registro de Imóveis da Comarca de Paranatinga/MT | F6: 9540 | G6: Valor mensal referente a 10 salários mínimos + IPG-M, anualmente | H6: N/A | I6: N/A | J6: =6*12 -> 72 | K6: 43313 | L6: 45550 | O6: Sim | P6: O ativo atende todos os requisitos previstos no CPC 06 (R2) para ser considerado arrendamento | Q6: =Premissas!$F$19 -> 0.049636326 | R6: =Premissas!$N$19 -> 0.10384722 | S6: =5*12 -> 60 | T6: 43466 | U6: =DATE(YEAR(T6),(MONTH(T6)+S6),DAY(T6))-1 -> 45291 | V6: Prazo de 5 anos sugerido pela administração, baseado na expectativa de continuidade operacional da filial. Anualmente o prazo será revisado.
B7: 2 | C7: Instrumento Particular de Contrato de Locação de Imóvel Urbano para fins comerciais | D7: Edualdo Junior Simões | E7: Prédio Comercial com área de 400 m², a qual faz parte de um total da área construída de 800 m² edificada no lote 01, quadra 26, loteamento denominado "Villa Santiago do Norte", com área total de 2.512,35 m², melhor descrita e caracterizada na matrícula de nº 6.040, do Cartório de Registro de Imóveis da Comarca de Paranatinga/MT | F7: 2000 | G7: N/A | H7: N/A | I7: N/A | J7: 24 | K7: 43467 | L7: 44198 | O7: Sim | P7: O ativo atende todos os requisitos previstos no CPC 06 (R2) para ser considerado arrendamento | Q7: =Premissas!$F$19 -> 0.049636326 | R7: =Premissas!$N$19 -> 0.10384722 | S7: =5*12 -> 60 | T7: 43466 | U7: =DATE(YEAR(T7),(MONTH(T7)+S7),DAY(T7))-1 -> 45291 | V7: Prazo de 5 anos sugerido pela administração, baseado na expectativa de continuidade operacional da filial. Anualmente o prazo será revisado.
B8: 3 | C8: Instrumento Particular de Contrato de Locação de Imóvel Urbano para fins comerciais | D8: W.I. Construções e Serviços Ltda ME | E8: 01 Lote de Terreno urbano, constituído do membramento dos lotes 04 e 08, situado na cidade de Chapadão do Céu/GO, com área total de 2.975 m² de área de terreno e 794,23 m² de área construída, melhor descrito e caracterizado na matrícula de nº 2.264, do Cartório de Registro de Imóveis da Comarca de Serranópolis/GO | F8: 18000 | G8: IGP-M, anualmente | H8: R$ 100.000,00, correspondente a 06 meses de aluguel | I8: N/A | J8: =8*12 -> 96 | K8: 43617 | L8: 46537 | O8: Sim | P8: O ativo atende todos os requisitos previstos no CPC 06 (R2) para ser considerado arrendamento | Q8: =Premissas!$F$19 -> 0.049636326 | R8: =Premissas!$N$19 -> 0.10384722 | S8: =5*12 -> 60 | T8: 43466 | U8: =DATE(YEAR(T8),(MONTH(T8)+S8),DAY(T8))-1 -> 45291 | V8: Prazo de 5 anos sugerido pela administração, baseado na expectativa de continuidade operacional da filial. Anualmente o prazo será revisado.
B9: 4 | C9: Instrumento Particular de Contrato de Locação de Terreno | D9: Dirceu Antônio dos Santos | E9: Gleba de terras, denominada "Fazenda Nova Esperança", localizada no município de Chapadão do Sul/MS, com área de 252,939 ha, melhor descrita e caracterizada na matrícula de nº 14.484, do Cartório de Registro de Imóveis da Comarca de Chapadão do Sul/MS | F9: 1000 | G9: N/A | H9: N/A | I9: N/A | J9: 4 | K9: 43040 | L9: 43160 | O9: Sim | P9: O ativo atende todos os requisitos previstos no CPC 06 (R2) para ser considerado arrendamento | Q9: =Premissas!$F$19 -> 0.049636326 | R9: =Premissas!$N$19 -> 0.10384722 | S9: =5*12 -> 60 | T9: 43466 | U9: =DATE(YEAR(T9),(MONTH(T9)+S9),DAY(T9))-1 -> 45291 | V9: Prazo de 5 anos sugerido pela administração, baseado na expectativa de continuidade operacional da filial. Anualmente o prazo será revisado.
B10: 5 | C10: Instrumento Particular de Contrato de Locação de Imóvel Urbano para fins comerciais | D10: Valdir Fedrigo e Evalda Fedrigo | E10: 01 Prédio comercial de 62,15 m², com área total construída de 830,29 m², edificada no lote 10-A, quadra 05, com área total de 1.781,15 m², localizado na Rua Juscelino Kubitschek, 145, Polo Empresarial, CEP: 79.560-000, melhor descrita e caracterizada na matrícula de nº 8.252, do Cartório de Registro de Imóveis da Comarca de Chapadão do Sul/MS | F10: 13000 | G10: N/A | H10: N/A | I10: N/A | J10: =5*12 -> 60 | K10: 43497 | L10: 45323 | O10: Sim | P10: O ativo atende todos os requisitos previstos no CPC 06 (R2) para ser considerado arrendamento | Q10: =Premissas!$F$19 -> 0.049636326 | R10: =Premissas!$N$19 -> 0.10384722 | S10: =5*12 -> 60 | T10: 43466 | U10: =DATE(YEAR(T10),(MONTH(T10)+S10),DAY(T10))-1 -> 45291 | V10: Prazo de 5 anos sugerido pela administração, baseado na expectativa de continuidade operacional da filial. Anualmente o prazo será revisado.
B11: 6 | C11: Instrumento Particular de Contrato de Locação de Imóvel Urbano para fins comerciais | D11: Agro Baggio Máquinas Agrícolas Ltda | E11: 02 Imóveis comerciais, com total de 6.132,846 m² de área de terreno, com total de 1.466,20 m² de área construída, nas seguintes composições: a) - 01 lote de terras denominado 07-B-9, com 1.600 m², com 01 edificação de 1.025,63 m², situado no "Perímetro Urbano" da cidade de Paranatinga/MT, imóvel melhor descrito e caracterizado na matrícula de nº 1.742, do Cartório de Registro de Imóveis da Comarca de Paranatinga/MT; b) - 01 lote de terras denominado 07-B-10A, com 4.532,846 m², com 02 edificações , sendo que a primeira refere- se a um prédio aos fundos, para depósito de óleo, peças grandes, materiais recicláveis , com 149,29 m², e o segundo refere- se à uma rampa de lavagem com 291,28 m², melhor descrita e caracterizada na matrícula de nº 6.538, do Cartório de Registro de Imóveis da Comarca de Paranatinga/MT | F11: 9540 | G11: Valor mensal referente a 10 salários mínimos + IPG-M, anualmente | H11: N/A | I11: N/A | J11: =6*12 -> 72 | K11: 43313 | L11: 45565 | O11: Sim | P11: O ativo atende todos os requisitos previstos no CPC 06 (R2) para ser considerado arrendamento | Q11: =Premissas!$F$19 -> 0.049636326 | R11: =Premissas!$N$19 -> 0.10384722 | S11: =5*12 -> 60 | T11: 43466 | U11: =DATE(YEAR(T11),(MONTH(T11)+S11),DAY(T11))-1 -> 45291 | V11: Prazo de 5 anos sugerido pela administração, baseado na expectativa de continuidade operacional da filial. Anualmente o prazo será revisado.
B12: 7 | C12: Instrumento Particular de Contrato de Locação de Imóvel Urbano | D12: RS Pneus e Equipamentos Ltda | E12: 02 imóveis com total de 1.119 m² de área de terreno, e 800 m², localizado a Rua Juscelino Kubitschek, 344, Anexo A, Castelândia II, município de Primavera do Leste/MT, CEP: 78.850-000, nas seguintes composições: a) - 01 lote de terras nº 17, na quadra 01 do loteamento Parque Castelândia II, na cidade de Primavera do Leste/MS, com área de 559,50 m², melhor descrito e caracterizado na matrícula de nº 2.236, do Cartório de Registro de Imóveis da Comarca de Primavera do Leste/MT; b) - 01 lote de terras nº 18, na quadra 01 do loteamento Parque Castelândia II, na Cidade de Primavera do Leste/MS, com área de 559,50 m², melhor descrito e caracterizado na matrícula de nº 2.237, do Cartório de Registro de Imóveis da Comarca de Primavera do Leste/MT | F12: 3500 | G12: IGP-M, anualmente | H12: N/A | I12: N/A | J12: 24 | K12: 43497 | L12: 44228 | O12: Sim | P12: O ativo atende todos os requisitos previstos no CPC 06 (R2) para ser considerado arrendamento | Q12: =Premissas!$F$19 -> 0.049636326 | R12: =Premissas!$N$19 -> 0.10384722 | S12: =5*12 -> 60 | T12: 43466 | U12: =DATE(YEAR(T12),(MONTH(T12)+S12),DAY(T12))-1 -> 45291 | V12: Prazo de 5 anos sugerido pela administração, baseado na expectativa de continuidade operacional da filial. Anualmente o prazo será revisado.
B13: 8 | C13: Contrato de Locação de Veículos | D13: Ouro Verde Locação e Serviço S/A | E13: 20 Fiat Strada 1.4 CE Hard Working 2019 Manual 2P Flex 578/24F/0 | F13: =1384.05*20 -> 27681 | G13: IGP-M, anualmente | H13: N/A | I13: N/A | J13: 36 | K13: 43516 | L13: =DATE(YEAR(K13),(MONTH(K13)+J13),DAY(K13)) -> 44612 | O13: Não | P13: Possui cláusula prevendo a possibilidade de subtituição do ativo, a pedido do locador | Q13: N/A | R13: N/A | S13: N/A | T13: N/A | U13: N/A | V13: N/A
B14: 9 | C14: Contrato de Locação de Veículos | D14: Arval - BNP Paribas | E14: 01 Fiat Strada Pick-up 1.4 CE Hard Working 18/19 2019 2P | F14: 1303.21 | G14: IGP-M, anualmente | H14: N/A | I14: N/A | J14: 36 | K14: 43469 | L14: =DATE(YEAR(K14),(MONTH(K14)+J14),DAY(K14)) -> 44565 | O14: Não | P14: Possui cláusula prevendo a possibilidade de subtituição do ativo, a pedido do locador | Q14: N/A | R14: N/A | S14: N/A | T14: N/A | U14: N/A | V14: N/A
B15: 10 | C15: Contrato de Locação de Veículos | D15: Arval - BNP Paribas | E15: 01 Fiat Toro Pick-up 1.8 Endurance Auto 18/19 2019 4P | F15: 2117 | G15: IGP-M, anualmente | H15: N/A | I15: N/A | J15: 36 | K15: 43469 | L15: =DATE(YEAR(K15),(MONTH(K15)+J15),DAY(K15)) -> 44565 | O15: Não | P15: Possui cláusula prevendo a possibilidade de subtituição do ativo, a pedido do locador | Q15: N/A | R15: N/A | S15: N/A | T15: N/A | U15: N/A | V15: N/A
B16: 11 | C16: Contrato de Locação de Veículos | D16: Arval - BNP Paribas | E16: 01 Volkswagen Amarok Pick-up 2.0 CS S 4x4 18/19 2019 2P | F16: 2395 | G16: IGP-M, anualmente | H16: N/A | I16: N/A | J16: 36 | K16: 43469 | L16: =DATE(YEAR(K16),(MONTH(K16)+J16),DAY(K16)) -> 44565 | O16: Não | P16: Possui cláusula prevendo a possibilidade de subtituição do ativo, a pedido do locador | Q16: N/A | R16: N/A | S16: N/A | T16: N/A | U16: N/A | V16: N/A

Sheet Premissas
C2: IGP-M | K2: Taxas de Mercado - Financiamento Imobiliário PJ
C4: Data | D4: 189 - Índice geral de preços do mercado (IGP-M) - Var. % mensal | F4: Percentual a.m. % | K4: Data | L4: 20761 - Taxa média de juros das operações de crédito com recursos direcionados - Pessoas jurídicas - Financiamento imobiliário com taxas de mercado - % a.a. | M4: 20762 - Taxa média de juros das operações de crédito com recursos direcionados - Pessoas jurídicas - Financiamento imobiliário com taxas reguladas - % a.a. | N4: 20763 - Taxa média de juros das operações de crédito com recursos direcionados - Pessoas jurídicas - Financiamento imobiliário total - % a.a.
C5: 43344 | D5: 1.52 | F5: =D5% -> 0.0152 | K5: 43344 | L5: 10.64 | M5: 9.71 | N5: 10.33
C6: 43374 | D6: 0.89 | F6: =D6% -> 0.0089 | K6: 43374 | L6: 11.22 | M6: 10.41 | N6: 10.95
C7: 43405 | D7: -0.49 | F7: =D7% -> -0.0049 | K7: 43405 | L7: 10.72 | M7: 10.06 | N7: 10.5
C8: 43435 | D8: -1.08 | F8: =D8% -> -0.0108 | K8: 43435 | L8: 10.46 | M8: 9.6 | N8: 10.18
C9: 43466 | D9: 0.01 | F9: =D9% -> 0.0001 | K9: 43466 | L9: 11.19 | M9: 10.43 | N9: 10.94
C10: 43497 | D10: 0.88 | F10: =D10% -> 0.0088 | K10: 43497 | L10: 10.48 | M10: 10.09 | N10: 10.35
C11: 43525 | D11: 1.26 | F11: =D11% -> 0.0126 | K11: 43525 | L11: 11.01 | M11: 10.05 | N11: 10.72
C12: 43556 | D12: 0.92 | F12: =D12% -> 0.0092 | K12: 43556 | L12: 10.34 | M12: 10.06 | N12: 10.25
C13: 43586 | D13: 0.45 | F13: =D13% -> 0.0045 | K13: 43586 | L13: 10.79 | M13: 9.97 | N13: 10.54
C14: 43617 | D14: 0.8 | F14: =D14% -> 0.008 | K14: 43617 | L14: 10.8 | M14: 10.24 | N14: 10.63
C15: 43647 | D15: 0.4 | F15: =D15% -> 0.004 | K15: 43647 | L15: 10.39 | M15: 10.11 | N15: 10.3
C16: 43678 | D16: -0.67 | F16: =D16% -> -0.0067 | K16: 43678 | L16: 9.75 | M16: 9.86 | N16: 9.78
C17: Fonte: | D17: FGV | K17: Fonte | L17: BCB-DSTAT | M17: BCB-DSTAT | N17: BCB-DSTAT
C19: % IGP-M Médio a.a. - Últimos 12 Meses | F19: =FVSCHEDULE(1,F5:F16)-1 -> 0.049636326 | L19: % Taxa Média a.a. - Últimos 12 Meses | N19: =AVERAGE(L5:N16)% -> 0.10384722
L20: % Taxa Média a.m. - Últimos 12 Meses | N20: =(1+N19)^(1/12)-1 -> 0.0082674509
C27: Fonte: https://www.portalbrasil.net/igpm.htm

Sheet Contabilização
B2: Fluxo de Pagamentos - 5 Anos - Com expectativa de atualização anual pelo IGP-M
B4: # Identificação Contrato | C4: 43466 | D4: 43497 | E4: 43525 | F4: 43556 | G4: 43586 | H4: 43617 | I4: 43647 | J4: 43678 | K4: 43709 | L4: 43739 | M4: 43770 | N4: 43800 | O4: 43831 | P4: 43862 | Q4: 43891 | R4: 43922 | S4: 43952 | T4: 43983 | U4: 44013 | V4: 44044 | W4: 44075 | X4: 44105 | Y4: 44136 | Z4: 44166 | AA4: 44197 | AB4: 44228 | AC4: 44256 | AD4: 44287 | AE4: 44317 | AF4: 44348 | AG4: 44378 | AH4: 44409 | AI4: 44440 | AJ4: 44470 | AK4: 44501 | AL4: 44531 | AM4: 44562 | AN4: 44593 | AO4: 44621 | AP4: 44652 | AQ4: 44682 | AR4: 44713 | AS4: 44743 | AT4: 44774 | AU4: 44805 | AV4: 44835 | AW4: 44866 | AX4: 44896 | AY4: 44927 | AZ4: 44958 | BA4: 44986 | BB4: 45017 | BC4: 45047 | BD4: 45078 | BE4: 45108 | BF4: 45139 | BG4: 45170 | BH4: 45200 | BI4: 45231 | BJ4: 45261 | BK4: TOTAL
B5: 1 | C5: ='Resumo Contratos'!F6 -> 9540 | D5: =C5 -> 9540 | E5: =D5 -> 9540 | F5: =E5 -> 9540 | G5: =F5 -> 9540 | H5: =G5 -> 9540 | I5: =H5 -> 9540 | J5: =I5 -> 9540 | K5: =J5 -> 9540 | ... N5: =M5 -> 9540 | O5: =N5+(N5*Premissas!$F$19) -> 10013.531 | P5: =O5 -> 10013.531 | Q5: =P5 -> 10013.531 | R5: =Q5 -> 10013.531 | S5: =R5 -> 10013.531 | T5: =S5 -> 10013.531 | U5: =T5 -> 10013.531 | V5: =U5 -> 10013.531 | W5: =V5 -> 10013.531 | ... Z5: =Y5 -> 10013.531 | AA5: =Z5+(Z5*Premissas!$F$19) -> 10510.565 | AB5: =AA5 -> 10510.565 | AC5: =AB5 -> 10510.565 | AD5: =AC5 -> 10510.565 | AE5: =AD5 -> 10510.565 | AF5: =AE5 -> 10510.565 | AG5: =AF5 -> 10510.565 | AH5: =AG5 -> 10510.565 | AI5: =AH5 -> 10510.565 | ... AL5: =AK5 -> 10510.565 | AM5: =AL5+(AL5*Premissas!$F$19) -> 11032.271 | AN5: =AM5 -> 11032.271 | AO5: =AN5 -> 11032.271 | AP5: =AO5 -> 11032.271 | AQ5: =AP5 -> 11032.271 | AR5: =AQ5 -> 11032.271 | AS5: =AR5 -> 11032.271 | AT5: =AS5 -> 11032.271 | AU5: =AT5 -> 11032.271 | ... AX5: =AW5 -> 11032.271 | AY5: =AX5+(AX5*Premissas!$F$19) -> 11579.873 | AZ5: =AY5 -> 11579.873 | BA5: =AZ5 -> 11579.873 | BB5: =BA5 -> 11579.873 | BC5: =BB5 -> 11579.873 | BD5: =BC5 -> 11579.873 | BE5: =BD5 -> 11579.873 | BF5: =BE5 -> 11579.873 | BG5: =BF5 -> 11579.873 | ... BJ5: =BI5 -> 11579.873 | BK5: =SUM(C5:BJ5) -> 632114.88
B6: 2 | C6: ='Resumo Contratos'!F7 -> 2000 | D6: =C6 -> 2000 | E6: =D6 -> 2000 | F6: =E6 -> 2000 | G6: =F6 -> 2000 | H6: =G6 -> 2000 | I6: =H6 -> 2000 | J6: =I6 -> 2000 | K6: =J6 -> 2000 | ... N6: =M6 -> 2000 | O6: =N6+(N6*Premissas!$F$19) -> 2099.2727 | P6: =O6 -> 2099.2727 | Q6: =P6 -> 2099.2727 | R6: =Q6 -> 2099.2727 | S6: =R6 -> 2099.2727 | T6: =S6 -> 2099.2727 | U6: =T6 -> 2099.2727 | V6: =U6 -> 2099.2727 | W6: =V6 -> 2099.2727 | ... Z6: =Y6 -> 2099.2727 | AA6: =Z6+(Z6*Premissas!$F$19) -> 2203.4728 | AB6: =AA6 -> 2203.4728 | AC6: =AB6 -> 2203.4728 | AD6: =AC6 -> 2203.4728 | AE6: =AD6 -> 2203.4728 | AF6: =AE6 -> 2203.4728 | AG6: =AF6 -> 2203.4728 | AH6: =AG6 -> 2203.4728 | AI6: =AH6 -> 2203.4728 | ... AL6: =AK6 -> 2203.4728 | AM6: =AL6+(AL6*Premissas!$F$19) -> 2312.8451 | AN6: =AM6 -> 2312.8451 | AO6: =AN6 -> 2312.8451 | AP6: =AO6 -> 2312.8451 | AQ6: =AP6 -> 2312.8451 | AR6: =AQ6 -> 2312.8451 | AS6: =AR6 -> 2312.8451 | AT6: =AS6 -> 2312.8451 | AU6: =AT6 -> 2312.8451 | ... AX6: =AW6 -> 2312.8451 | AY6: =AX6+(AX6*Premissas!$F$19) -> 2427.6463 | AZ6: =AY6 -> 2427.6463 | BA6: =AZ6 -> 2427.6463 | BB6: =BA6 -> 2427.6463 | BC6: =BB6 -> 2427.6463 | BD6: =BC6 -> 2427.6463 | BE6: =BD6 -> 2427.6463 | BF6: =BE6 -> 2427.6463 | BG6: =BF6 -> 2427.6463 | ... BJ6: =BI6 -> 2427.6463 | BK6: =SUM(C6:BJ6) -> 132518.84
B7: 3 | C7: ='Resumo Contratos'!F8 -> 18000 | D7: =C7 -> 18000 | E7: =D7 -> 18000 | F7: =E7 -> 18000 | G7: =F7 -> 18000 | H7: =G7 -> 18000 | I7: =H7 -> 18000 | J7: =I7 -> 18000 | K7: =J7 -> 18000 | ... N7: =M7 -> 18000 | O7: =N7+(N7*Premissas!$F$19) -> 18893.454 | P7: =O7 -> 18893.454 | Q7: =P7 -> 18893.454 | R7: =Q7 -> 18893.454 | S7: =R7 -> 18893.454 | T7: =S7 -> 18893.454 | U7: =T7 -> 18893.454 | V7: =U7 -> 18893.454 | W7: =V7 -> 18893.454 | ... Z7: =Y7 -> 18893.454 | AA7: =Z7+(Z7*Premissas!$F$19) -> 19831.255 | AB7: =AA7 -> 19831.255 | AC7: =AB7 -> 19831.255 | AD7: =AC7 -> 19831.255 | AE7: =AD7 -> 19831.255 | AF7: =AE7 -> 19831.255 | AG7: =AF7 -> 19831.255 | AH7: =AG7 -> 19831.255 | AI7: =AH7 -> 19831.255 | ... AL7: =AK7 -> 19831.255 | AM7: =AL7+(AL7*Premissas!$F$19) -> 20815.606 | AN7: =AM7 -> 20815.606 | AO7: =AN7 -> 20815.606 | AP7: =AO7 -> 20815.606 | AQ7: =AP7 -> 20815.606 | AR7: =AQ7 -> 20815.606 | AS7: =AR7 -> 20815.606 | AT7: =AS7 -> 20815.606 | AU7: =AT7 -> 20815.606 | ... AX7: =AW7 -> 20815.606 | AY7: =AX7+(AX7*Premissas!$F$19) -> 21848.816 | AZ7: =AY7 -> 21848.816 | BA7: =AZ7 -> 21848.816 | BB7: =BA7 -> 21848.816 | BC7: =BB7 -> 21848.816 | BD7: =BC7 -> 21848.816 | BE7: =BD7 -> 21848.816 | BF7: =BE7 -> 21848.816 | BG7: =BF7 -> 21848.816 | ... BJ7: =BI7 -> 21848.816 | BK7: =SUM(C7:BJ7) -> 1192669.6
B8: 4 | C8: ='Resumo Contratos'!F9 -> 1000 | D8: =C8 -> 1000 | E8: =D8 -> 1000 | F8: =E8 -> 1000 | G8: =F8 -> 1000 | H8: =G8 -> 1000 | I8: =H8 -> 1000 | J8: =I8 -> 1000 | K8: =J8 -> 1000 | ... N8: =M8 -> 1000 | O8: =N8+(N8*Premissas!$F$19) -> 1049.6363 | P8: =O8 -> 1049.6363 | Q8: =P8 -> 1049.6363 | R8: =Q8 -> 1049.6363 | S8: =R8 -> 1049.6363 | T8: =S8 -> 1049.6363 | U8: =T8 -> 1049.6363 | V8: =U8 -> 1049.6363 | W8: =V8 -> 1049.6363 | ... Z8: =Y8 -> 1049.6363 | AA8: =Z8+(Z8*Premissas!$F$19) -> 1101.7364 | AB8: =AA8 -> 1101.7364 | AC8: =AB8 -> 1101.7364 | AD8: =AC8 -> 1101.7364 | AE8: =AD8 -> 1101.7364 | AF8: =AE8 -> 1101.7364 | AG8: =AF8 -> 1101.7364 | AH8: =AG8 -> 1101.7364 | AI8: =AH8 -> 1101.7364 | ... AL8: =AK8 -> 1101.7364 | AM8: =AL8+(AL8*Premissas!$F$19) -> 1156.4226 | AN8: =AM8 -> 1156.4226 | AO8: =AN8 -> 1156.4226 | AP8: =AO8 -> 1156.4226 | AQ8: =AP8 -> 1156.4226 | AR8: =AQ8 -> 1156.4226 | AS8: =AR8 -> 1156.4226 | AT8: =AS8 -> 1156.4226 | AU8: =AT8 -> 1156.4226 | ... AX8: =AW8 -> 1156.4226 | AY8: =AX8+(AX8*Premissas!$F$19) -> 1213.8231 | AZ8: =AY8 -> 1213.8231 | BA8: =AZ8 -> 1213.8231 | BB8: =BA8 -> 1213.8231 | BC8: =BB8 -> 1213.8231 | BD8: =BC8 -> 1213.8231 | BE8: =BD8 -> 1213.8231 | BF8: =BE8 -> 1213.8231 | BG8: =BF8 -> 1213.8231 | ... BJ8: =BI8 -> 1213.8231 | BK8: =SUM(C8:BJ8) -> 66259.421
B9: 5 | C9: ='Resumo Contratos'!F10 -> 13000 | D9: =C9 -> 13000 | E9: =D9 -> 13000 | F9: =E9 -> 13000 | G9: =F9 -> 13000 | H9: =G9 -> 13000 | I9: =H9 -> 13000 | J9: =I9 -> 13000 | K9: =J9 -> 13000 | ... N9: =M9 -> 13000 | O9: =N9+(N9*Premissas!$F$19) -> 13645.272 | P9: =O9 -> 13645.272 | Q9: =P9 -> 13645.272 | R9: =Q9 -> 13645.272 | S9: =R9 -> 13645.272 | T9: =S9 -> 13645.272 | U9: =T9 -> 13645.272 | V9: =U9 -> 13645.272 | W9: =V9 -> 13645.272 | ... Z9: =Y9 -> 13645.272 | AA9: =Z9+(Z9*Premissas!$F$19) -> 14322.573 | AB9: =AA9 -> 14322.573 | AC9: =AB9 -> 14322.573 | AD9: =AC9 -> 14322.573 | AE9: =AD9 -> 14322.573 | AF9: =AE9 -> 14322.573 | AG9: =AF9 -> 14322.573 | AH9: =AG9 -> 14322.573 | AI9: =AH9 -> 14322.573 | ... AL9: =AK9 -> 14322.573 | AM9: =AL9+(AL9*Premissas!$F$19) -> 15033.493 | AN9: =AM9 -> 15033.493 | AO9: =AN9 -> 15033.493 | AP9: =AO9 -> 15033.493 | AQ9: =AP9 -> 15033.493 | AR9: =AQ9 -> 15033.493 | AS9: =AR9 -> 15033.493 | AT9: =AS9 -> 15033.493 | AU9: =AT9 -> 15033.493 | ... AX9: =AW9 -> 15033.493 | AY9: =AX9+(AX9*Premissas!$F$19) -> 15779.701 | AZ9: =AY9 -> 15779.701 | BA9: =AZ9 -> 15779.701 | BB9: =BA9 -> 15779.701 | BC9: =BB9 -> 15779.701 | BD9: =BC9 -> 15779.701 | BE9: =BD9 -> 15779.701 | BF9: =BE9 -> 15779.701 | BG9: =BF9 -> 15779.701 | ... BJ9: =BI9 -> 15779.701 | BK9: =SUM(C9:BJ9) -> 861372.48
B10: 6 | C10: ='Resumo Contratos'!F11 -> 9540 | D10: =C10 -> 9540 | E10: =D10 -> 9540 | F10: =E10 -> 9540 | G10: =F10 -> 9540 | H10: =G10 -> 9540 | I10: =H10 -> 9540 | J10: =I10 -> 9540 | K10: =J10 -> 9540 | ... N10: =M10 -> 9540 | O10: =N10+(N10*Premissas!$F$19) -> 10013.531 | P10: =O10 -> 10013.531 | Q10: =P10 -> 10013.531 | R10: =Q10 -> 10013.531 | S10: =R10 -> 10013.531 | T10: =S10 -> 10013.531 | U10: =T10 -> 10013.531 | V10: =U10 -> 10013.531 | W10: =V10 -> 10013.531 | ... Z10: =Y10 -> 10013.531 | AA10: =Z10+(Z10*Premissas!$F$19) -> 10510.565 | AB10: =AA10 -> 10510.565 | AC10: =AB10 -> 10510.565 | AD10: =AC10 -> 10510.565 | AE10: =AD10 -> 10510.565 | AF10: =AE10 -> 10510.565 | AG10: =AF10 -> 10510.565 | AH10: =AG10 -> 10510.565 | AI10: =AH10 -> 10510.565 | ... AL10: =AK10 -> 10510.565 | AM10: =AL10+(AL10*Premissas!$F$19) -> 11032.271 | AN10: =AM10 -> 11032.271 | AO10: =AN10 -> 11032.271 | AP10: =AO10 -> 11032.271 | AQ10: =AP10 -> 11032.271 | AR10: =AQ10 -> 11032.271 | AS10: =AR10 -> 11032.271 | AT10: =AS10 -> 11032.271 | AU10: =AT10 -> 11032.271 | ... AX10: =AW10 -> 11032.271 | AY10: =AX10+(AX10*Premissas!$F$19) -> 11579.873 | AZ10: =AY10 -> 11579.873 | BA10: =AZ10 -> 11579.873 | BB10: =BA10 -> 11579.873 | BC10: =BB10 -> 11579.873 | BD10: =BC10 -> 11579.873 | BE10: =BD10 -> 11579.873 | BF10: =BE10 -> 11579.873 | BG10: =BF10 -> 11579.873 | ... BJ10: =BI10 -> 11579.873 | BK10: =SUM(C10:BJ10) -> 632114.88
B11: 7 | C11: ='Resumo Contratos'!F12 -> 3500 | D11: =C11 -> 3500 | E11: =D11 -> 3500 | F11: =E11 -> 3500 | G11: =F11 -> 3500 | H11: =G11 -> 3500 | I11: =H11 -> 3500 | J11: =I11 -> 3500 | K11: =J11 -> 3500 | ... N11: =M11 -> 3500 | O11: =N11+(N11*Premissas!$F$19) -> 3673.7271 | P11: =O11 -> 3673.7271 | Q11: =P11 -> 3673.7271 | R11: =Q11 -> 3673.7271 | S11: =R11 -> 3673.7271 | T11: =S11 -> 3673.7271 | U11: =T11 -> 3673.7271 | V11: =U11 -> 3673.7271 | W11: =V11 -> 3673.7271 | ... Z11: =Y11 -> 3673.7271 | AA11: =Z11+(Z11*Premissas!$F$19) -> 3856.0775 | AB11: =AA11 -> 3856.0775 | AC11: =AB11 -> 3856.0775 | AD11: =AC11 -> 3856.0775 | AE11: =AD11 -> 3856.0775 | AF11: =AE11 -> 3856.0775 | AG11: =AF11 -> 3856.0775 | AH11: =AG11 -> 3856.0775 | AI11: =AH11 -> 3856.0775 | ... AL11: =AK11 -> 3856.0775 | AM11: =AL11+(AL11*Premissas!$F$19) -> 4047.479 | AN11: =AM11 -> 4047.479 | AO11: =AN11 -> 4047.479 | AP11: =AO11 -> 4047.479 | AQ11: =AP11 -> 4047.479 | AR11: =AQ11 -> 4047.479 | AS11: =AR11 -> 4047.479 | AT11: =AS11 -> 4047.479 | AU11: =AT11 -> 4047.479 | ... AX11: =AW11 -> 4047.479 | AY11: =AX11+(AX11*Premissas!$F$19) -> 4248.381 | AZ11: =AY11 -> 4248.381 | BA11: =AZ11 -> 4248.381 | BB11: =BA11 -> 4248.381 | BC11: =BB11 -> 4248.381 | BD11: =BC11 -> 4248.381 | BE11: =BD11 -> 4248.381 | BF11: =BE11 -> 4248.381 | BG11: =BF11 -> 4248.381 | ... BJ11: =BI11 -> 4248.381 | BK11: =SUM(C11:BJ11) -> 231907.97
B15: TOTAL | C15: =SUM(C5:C14) -> 56580 | D15: =SUM(D5:D14) -> 56580 | E15: =SUM(E5:E14) -> 56580 | F15: =SUM(F5:F14) -> 56580 | G15: =SUM(G5:G14) -> 56580 | H15: =SUM(H5:H14) -> 56580 | I15: =SUM(I5:I14) -> 56580 | J15: =SUM(J5:J14) -> 56580 | ... BK15: =SUM(BK5:BK14) -> 3748958.1
B18: Atualização ao Valor Presente pelas Taxas Médias de Mercado - Financiamento Imobiliário PJ
C20: 1 | D20: 2 | E20: 3 | F20: 4 | G20: 5 | H20: 6 | I20: 7 | J20: 8 | K20: 9 | L20: 10 | M20: 11 | N20: 12 | O20: 13 | P20: 14 | Q20: 15 | R20: 16 | S20: 17 | T20: 18 | U20: 19 | V20: 20 | W20: 21 | X20: 22 | Y20: 23 | Z20: 24 | AA20: 25 | AB20: 26 | AC20: 27 | AD20: 28 | AE20: 29 | AF20: 30 | AG20: 31 | AH20: 32 | AI20: 33 | AJ20: 34 | AK20: 35 | AL20: 36 | AM20: 37 | AN20: 38 | AO20: 39 | AP20: 40 | AQ20: 41 | AR20: 42 | AS20: 43 | AT20: 44 | AU20: 45 | AV20: 46 | AW20: 47 | AX20: 48 | AY20: 49 | AZ20: 50 | BA20: 51 | BB20: 52 | BC20: 53 | BD20: 54 | BE20: 55 | BF20: 56 | BG20: 57 | BH20: 58 | BI20: 59 | BJ20: 60
B21: # Identificação Contrato | C21: 43466 | D21: 43497 | E21: 43525 | F21: 43556 | G21: 43586 | H21: 43617 | I21: 43647 | J21: 43678 | K21: 43709 | L21: 43739 | M21: 43770 | N21: 43800 | O21: 43831 | P21: 43862 | Q21: 43891 | R21: 43922 | S21: 43952 | T21: 43983 | U21: 44013 | V21: 44044 | W21: 44075 | X21: 44105 | Y21: 44136 | Z21: 44166 | AA21: 44197 | AB21: 44228 | AC21: 44256 | AD21: 44287 | AE21: 44317 | AF21: 44348 | AG21: 44378 | AH21: 44409 | AI21: 44440 | AJ21: 44470 | AK21: 44501 | AL21: 44531 | AM21: 44562 | AN21: 44593 | AO21: 44621 | AP21: 44652 | AQ21: 44682 | AR21: 44713 | AS21: 44743 | AT21: 44774 | AU21: 44805 | AV21: 44835 | AW21: 44866 | AX21: 44896 | AY21: 44927 | AZ21: 44958 | BA21: 44986 | BB21: 45017 | BC21: 45047 | BD21: 45078 | BE21: 45108 | BF21: 45139 | BG21: 45170 | BH21: 45200 | BI21: 45231 | BJ21: 45261 | BK21: TOTAL
B22: 1 | C22: =(C5/(1+Premissas!$N$20)^C$20) -> 9461.7752 | D22: =(D5/(1+Premissas!$N$20)^D$20) -> 9384.1919 | E22: =(E5/(1+Premissas!$N$20)^E$20) -> 9307.2447 | F22: =(F5/(1+Premissas!$N$20)^F$20) -> 9230.9285 | G22: =(G5/(1+Premissas!$N$20)^G$20) -> 9155.238 | H22: =(H5/(1+Premissas!$N$20)^H$20) -> 9080.1681 | I22: =(I5/(1+Premissas!$N$20)^I$20) -> 9005.7138 | J22: =(J5/(1+Premissas!$N$20)^J$20) -> 8931.87 | ... BJ22: =(BJ5/(1+Premissas!$N$20)^BJ$20) -> 7065.7609 | BK22: =SUM(C22:BJ22) -> 492031.79 | BM22: =NPV(Premissas!$N$20,Contabilização!C5:BJ5)-BK22 -> -4.6566129e-10
B23: 2 | C23: =(C6/(1+Premissas!$N$20)^C$20) -> 1983.6007 | D23: =(D6/(1+Premissas!$N$20)^D$20) -> 1967.3358 | E23: =(E6/(1+Premissas!$N$20)^E$20) -> 1951.2043 | F23: =(F6/(1+Premissas!$N$20)^F$20) -> 1935.2051 | G23: =(G6/(1+Premissas!$N$20)^G$20) -> 1919.3371 | H23: =(H6/(1+Premissas!$N$20)^H$20) -> 1903.5992 | I23: =(I6/(1+Premissas!$N$20)^I$20) -> 1887.9903 | J23: =(J6/(1+Premissas!$N$20)^J$20) -> 1872.5094 | ... BJ23: =(BJ6/(1+Premissas!$N$20)^BJ$20) -> 1481.2916 | BK23: =SUM(C23:BJ23) -> 103151.32 | BM23: =NPV(Premissas!$N$20,Contabilização!C6:BJ6)-BK23 -> -1.1641532e-10
B24: 3 | C24: =(C7/(1+Premissas!$N$20)^C$20) -> 17852.406 | D24: =(D7/(1+Premissas!$N$20)^D$20) -> 17706.022 | E24: =(E7/(1+Premissas!$N$20)^E$20) -> 17560.839 | F24: =(F7/(1+Premissas!$N$20)^F$20) -> 17416.846 | G24: =(G7/(1+Premissas!$N$20)^G$20) -> 17274.034 | H24: =(H7/(1+Premissas!$N$20)^H$20) -> 17132.393 | I24: =(I7/(1+Premissas!$N$20)^I$20) -> 16991.913 | J24: =(J7/(1+Premissas!$N$20)^J$20) -> 16852.585 | ... BJ24: =(BJ7/(1+Premissas!$N$20)^BJ$20) -> 13331.624 | BK24: =SUM(C24:BJ24) -> 928361.87 | BM24: =NPV(Premissas!$N$20,Contabilização!C7:BJ7)-BK24 -> 0
B25: 4 | C25: =(C8/(1+Premissas!$N$20)^C$20) -> 991.80034 | D25: =(D8/(1+Premissas!$N$20)^D$20) -> 983.66791 | E25: =(E8/(1+Premissas!$N$20)^E$20) -> 975.60217 | F25: =(F8/(1+Premissas!$N$20)^F$20) -> 967.60256 | G25: =(G8/(1+Premissas!$N$20)^G$20) -> 959.66855 | H25: =(H8/(1+Premissas!$N$20)^H$20) -> 951.79959 | I25: =(I8/(1+Premissas!$N$20)^I$20) -> 943.99516 | J25: =(J8/(1+Premissas!$N$20)^J$20) -> 936.25472 | ... BJ25: =(BJ8/(1+Premissas!$N$20)^BJ$20) -> 740.6458 | BK25: =SUM(C25:BJ25) -> 51575.659 | BM25: =NPV(Premissas!$N$20,Contabilização!C8:BJ8)-BK25 -> -5.8207661e-11
B26: 5 | C26: =(C9/(1+Premissas!$N$20)^C$20) -> 12893.404 | D26: =(D9/(1+Premissas!$N$20)^D$20) -> 12787.683 | E26: =(E9/(1+Premissas!$N$20)^E$20) -> 12682.828 | F26: =(F9/(1+Premissas!$N$20)^F$20) -> 12578.833 | G26: =(G9/(1+Premissas!$N$20)^G$20) -> 12475.691 | H26: =(H9/(1+Premissas!$N$20)^H$20) -> 12373.395 | I26: =(I9/(1+Premissas!$N$20)^I$20) -> 12271.937 | J26: =(J9/(1+Premissas!$N$20)^J$20) -> 12171.311 | ... BJ26: =(BJ9/(1+Premissas!$N$20)^BJ$20) -> 9628.3954 | BK26: =SUM(C26:BJ26) -> 670483.57 | BM26: =NPV(Premissas!$N$20,Contabilização!C9:BJ9)-BK26 -> 0
B27: 6 | C27: =(C10/(1+Premissas!$N$20)^C$20) -> 9461.7752 | D27: =(D10/(1+Premissas!$N$20)^D$20) -> 9384.1919 | E27: =(E10/(1+Premissas!$N$20)^E$20) -> 9307.2447 | F27: =(F10/(1+Premissas!$N$20)^F$20) -> 9230.9285 | G27: =(G10/(1+Premissas!$N$20)^G$20) -> 9155.238 | H27: =(H10/(1+Premissas!$N$20)^H$20) -> 9080.1681 | I27: =(I10/(1+Premissas!$N$20)^I$20) -> 9005.7138 | J27: =(J10/(1+Premissas!$N$20)^J$20) -> 8931.87 | ... BJ27: =(BJ10/(1+Premissas!$N$20)^BJ$20) -> 7065.7609 | BK27: =SUM(C27:BJ27) -> 492031.79 | BM27: =NPV(Premissas!$N$20,Contabilização!C10:BJ10)-BK27 -> -4.6566129e-10
B28: 7 | C28: =(C11/(1+Premissas!$N$20)^C$20) -> 3471.3012 | D28: =(D11/(1+Premissas!$N$20)^D$20) -> 3442.8377 | E28: =(E11/(1+Premissas!$N$20)^E$20) -> 3414.6076 | F28: =(F11/(1+Premissas!$N$20)^F$20) -> 3386.609 | G28: =(G11/(1+Premissas!$N$20)^G$20) -> 3358.8399 | H28: =(H11/(1+Premissas!$N$20)^H$20) -> 3331.2986 | I28: =(I11/(1+Premissas!$N$20)^I$20) -> 3303.9831 | J28: =(J11/(1+Premissas!$N$20)^J$20) -> 3276.8915 | ... BJ28: =(BJ11/(1+Premissas!$N$20)^BJ$20) -> 2592.2603 | BK28: =SUM(C28:BJ28) -> 180514.81 | BM28: =NPV(Premissas!$N$20,Contabilização!C11:BJ11)-BK28 -> 0
C29: =(C12/(1+Premissas!$N$20)^C$20) -> 0 | D29: =(D12/(1+Premissas!$N$20)^D$20) -> 0 | E29: =(E12/(1+Premissas!$N$20)^E$20) -> 0 | F29: =(F12/(1+Premissas!$N$20)^F$20) -> 0 | G29: =(G12/(1+Premissas!$N$20)^G$20) -> 0 | H29: =(H12/(1+Premissas!$N$20)^H$20) -> 0 | I29: =(I12/(1+Premissas!$N$20)^I$20) -> 0 | J29: =(J12/(1+Premissas!$N$20)^J$20) -> 0 | ... BJ29: =(BJ12/(1+Premissas!$N$20)^BJ$20) -> 0 | BK29: =SUM(C29:BJ29) -> 0 | BM29: =NPV(Premissas!$N$20,Contabilização!C12:BJ12)-BK29 -> 0
C30: =(C13/(1+Premissas!$N$20)^C$20) -> 0 | D30: =(D13/(1+Premissas!$N$20)^D$20) -> 0 | E30: =(E13/(1+Premissas!$N$20)^E$20) -> 0 | F30: =(F13/(1+Premissas!$N$20)^F$20) -> 0 | G30: =(G13/(1+Premissas!$N$20)^G$20) -> 0 | H30: =(H13/(1+Premissas!$N$20)^H$20) -> 0 | I30: =(I13/(1+Premissas!$N$20)^I$20) -> 0 | J30: =(J13/(1+Premissas!$N$20)^J$20) -> 0 | ... BJ30: =(BJ13/(1+Premissas!$N$20)^BJ$20) -> 0 | BK30: =SUM(C30:BJ30) -> 0 | BM30: =NPV(Premissas!$N$20,Contabilização!C13:BJ13)-BK30 -> 0
C31: =(C14/(1+Premissas!$N$20)^C$20) -> 0 | D31: =(D14/(1+Premissas!$N$20)^D$20) -> 0 | E31: =(E14/(1+Premissas!$N$20)^E$20) -> 0 | F31: =(F14/(1+Premissas!$N$20)^F$20) -> 0 | G31: =(G14/(1+Premissas!$N$20)^G$20) -> 0 | H31: =(H14/(1+Premissas!$N$20)^H$20) -> 0 | I31: =(I14/(1+Premissas!$N$20)^I$20) -> 0 | J31: =(J14/(1+Premissas!$N$20)^J$20) -> 0 | ... BJ31: =(BJ14/(1+Premissas!$N$20)^BJ$20) -> 0 | BK31: =SUM(C31:BJ31) -> 0 | BM31: =NPV(Premissas!$N$20,Contabilização!C14:BJ14)-BK31 -> 0
B32: TOTAL | C32: =SUM(C22:C31) -> 56116.063 | D32: =SUM(D22:D31) -> 55655.931 | E32: =SUM(E22:E31) -> 55199.571 | F32: =SUM(F22:F31) -> 54746.953 | G32: =SUM(G22:G31) -> 54298.047 | H32: =SUM(H22:H31) -> 53852.821 | I32: =SUM(I22:I31) -> 53411.246 | J32: =SUM(J22:J31) -> 52973.292 | ... BK32: =SUM(BK22:BK31) -> 2918150.8
B35: Lançamento de Depreciação Mensal
B37: # Identificação Contrato | C37: 43466 | D37: 43497 | E37: 43525 | F37: 43556 | G37: 43586 | H37: 43617 | I37: 43647 | J37: 43678 | K37: 43709 | L37: 43739 | M37: 43770 | N37: 43800 | O37: 43831 | P37: 43862 | Q37: 43891 | R37: 43922 | S37: 43952 | T37: 43983 | U37: 44013 | V37: 44044 | W37: 44075 | X37: 44105 | Y37: 44136 | Z37: 44166 | AA37: 44197 | AB37: 44228 | AC37: 44256 | AD37: 44287 | AE37: 44317 | AF37: 44348 | AG37: 44378 | AH37: 44409 | AI37: 44440 | AJ37: 44470 | AK37: 44501 | AL37: 44531 | AM37: 44562 | AN37: 44593 | AO37: 44621 | AP37: 44652 | AQ37: 44682 | AR37: 44713 | AS37: 44743 | AT37: 44774 | AU37: 44805 | AV37: 44835 | AW37: 44866 | AX37: 44896 | AY37: 44927 | AZ37: 44958 | BA37: 44986 | BB37: 45017 | BC37: 45047 | BD37: 45078 | BE37: 45108 | BF37: 45139 | BG37: 45170 | BH37: 45200 | BI37: 45231 | BJ37: 45261 | BK37: TOTAL
B38: 1 | C38: =$BK22/$BJ$20 -> 8200.5298 | D38: =$BK22/$BJ$20 -> 8200.5298 | E38: =$BK22/$BJ$20 -> 8200.5298 | F38: =$BK22/$BJ$20 -> 8200.5298 | G38: =$BK22/$BJ$20 -> 8200.5298 | H38: =$BK22/$BJ$20 -> 8200.5298 | I38: =$BK22/$BJ$20 -> 8200.5298 | J38: =$BK22/$BJ$20 -> 8200.5298 | ... BJ38: =$BK22/$BJ$20 -> 8200.5298 | BK38: =SUM(C38:BJ38) -> 492031.79
B39: 2 | C39: =$BK23/$BJ$20 -> 1719.1886 | D39: =$BK23/$BJ$20 -> 1719.1886 | E39: =$BK23/$BJ$20 -> 1719.1886 | F39: =$BK23/$BJ$20 -> 1719.1886 | G39: =$BK23/$BJ$20 -> 1719.1886 | H39: =$BK23/$BJ$20 -> 1719.1886 | I39: =$BK23/$BJ$20 -> 1719.1886 | J39: =$BK23/$BJ$20 -> 1719.1886 | ... BJ39: =$BK23/$BJ$20 -> 1719.1886 | BK39: =SUM(C39:BJ39) -> 103151.32
B40: 3 | C40: =$BK24/$BJ$20 -> 15472.698 | D40: =$BK24/$BJ$20 -> 15472.698 | E40: =$BK24/$BJ$20 -> 15472.698 | F40: =$BK24/$BJ$20 -> 15472.698 | G40: =$BK24/$BJ$20 -> 15472.698 | H40: =$BK24/$BJ$20 -> 15472.698 | I40: =$BK24/$BJ$20 -> 15472.698 | J40: =$BK24/$BJ$20 -> 15472.698 | ... BJ40: =$BK24/$BJ$20 -> 15472.698 | BK40: =SUM(C40:BJ40) -> 928361.87
B41: 4 | C41: =$BK25/$BJ$20 -> 859.59432 | D41: =$BK25/$BJ$20 -> 859.59432 | E41: =$BK25/$BJ$20 -> 859.59432 | F41: =$BK25/$BJ$20 -> 859.59432 | G41: =$BK25/$BJ$20 -> 859.59432 | H41: =$BK25/$BJ$20 -> 859.59432 | I41: =$BK25/$BJ$20 -> 859.59432 | J41: =$BK25/$BJ$20 -> 859.59432 | ... BJ41: =$BK25/$BJ$20 -> 859.59432 | BK41: =SUM(C41:BJ41) -> 51575.659
B42: 5 | C42: =$BK26/$BJ$20 -> 11174.726 | D42: =$BK26/$BJ$20 -> 11174.726 | E42: =$BK26/$BJ$20 -> 11174.726 | F42: =$BK26/$BJ$20 -> 11174.726 | G42: =$BK26/$BJ$20 -> 11174.726 | H42: =$BK26/$BJ$20 -> 11174.726 | I42: =$BK26/$BJ$20 -> 11174.726 | J42: =$BK26/$BJ$20 -> 11174.726 | ... BJ42: =$BK26/$BJ$20 -> 11174.726 | BK42: =SUM(C42:BJ42) -> 670483.57
B43: 6 | C43: =$BK27/$BJ$20 -> 8200.5298 | D43: =$BK27/$BJ$20 -> 8200.5298 | E43: =$BK27/$BJ$20 -> 8200.5298 | F43: =$BK27/$BJ$20 -> 8200.5298 | G43: =$BK27/$BJ$20 -> 8200.5298 | H43: =$BK27/$BJ$20 -> 8200.5298 | I43: =$BK27/$BJ$20 -> 8200.5298 | J43: =$BK27/$BJ$20 -> 8200.5298 | ... BJ43: =$BK27/$BJ$20 -> 8200.5298 | BK43: =SUM(C43:BJ43) -> 492031.79
B44: 7 | C44: =$BK28/$BJ$20 -> 3008.5801 | D44: =$BK28/$BJ$20 -> 3008.5801 | E44: =$BK28/$BJ$20 -> 3008.5801 | F44: =$BK28/$BJ$20 -> 3008.5801 | G44: =$BK28/$BJ$20 -> 3008.5801 | H44: =$BK28/$BJ$20 -> 3008.5801 | I44: =$BK28/$BJ$20 -> 3008.5801 | J44: =$BK28/$BJ$20 -> 3008.5801 | ... BJ44: =$BK28/$BJ$20 -> 3008.5801 | BK44: =SUM(C44:BJ44) -> 180514.81
C45: =$BK29/$BJ$20 -> 0 | D45: =$BK29/$BJ$20 -> 0 | E45: =$BK29/$BJ$20 -> 0 | F45: =$BK29/$BJ$20 -> 0 | G45: =$BK29/$BJ$20 -> 0 | H45: =$BK29/$BJ$20 -> 0 | I45: =$BK29/$BJ$20 -> 0 | J45: =$BK29/$BJ$20 -> 0 | ... BJ45: =$BK29/$BJ$20 -> 0 | BK45: =SUM(C45:BJ45) -> 0
C46: =$BK30/$BJ$20 -> 0 | D46: =$BK30/$BJ$20 -> 0 | E46: =$BK30/$BJ$20 -> 0 | F46: =$BK30/$BJ$20 -> 0 | G46: =$BK30/$BJ$20 -> 0 | H46: =$BK30/$BJ$20 -> 0 | I46: =$BK30/$BJ$20 -> 0 | J46: =$BK30/$BJ$20 -> 0 | ... BJ46: =$BK30/$BJ$20 -> 0 | BK46: =SUM(C46:BJ46) -> 0
C47: =$BK31/$BJ$20 -> 0 | D47: =$BK31/$BJ$20 -> 0 | E47: =$BK31/$BJ$20 -> 0 | F47: =$BK31/$BJ$20 -> 0 | G47: =$BK31/$BJ$20 -> 0 | H47: =$BK31/$BJ$20 -> 0 | I47: =$BK31/$BJ$20 -> 0 | J47: =$BK31/$BJ$20 -> 0 | ... BJ47: =$BK31/$BJ$20 -> 0 | BK47: =SUM(C47:BJ47) -> 0
B48: TOTAL | C48: =SUM(C38:C47) -> 48635.847 | D48: =SUM(D38:D47) -> 48635.847 | E48: =SUM(E38:E47) -> 48635.847 | F48: =SUM(F38:F47) -> 48635.847 | G48: =SUM(G38:G47) -> 48635.847 | H48: =SUM(H38:H47) -> 48635.847 | I48: =SUM(I38:I47) -> 48635.847 | J48: =SUM(J38:J47) -> 48635.847 | ... BK48: =SUM(BK38:BK47) -> 2918150.8
B51: Lançamento de Juros Mensal
B53: # Identificação Contrato | C53: 43466 | D53: 43497 | E53: 43525 | F53: 43556 | G53: 43586 | H53: 43617 | I53: 43647 | J53: 43678 | K53: 43709 | L53: 43739 | M53: 43770 | N53: 43800 | O53: 43831 | P53: 43862 | Q53: 43891 | R53: 43922 | S53: 43952 | T53: 43983 | U53: 44013 | V53: 44044 | W53: 44075 | X53: 44105 | Y53: 44136 | Z53: 44166 | AA53: 44197 | AB53: 44228 | AC53: 44256 | AD53: 44287 | AE53: 44317 | AF53: 44348 | AG53: 44378 | AH53: 44409 | AI53: 44440 | AJ53: 44470 | AK53: 44501 | AL53: 44531 | AM53: 44562 | AN53: 44593 | AO53: 44621 | AP53: 44652 | AQ53: 44682 | AR53: 44713 | AS53: 44743 | AT53: 44774 | AU53: 44805 | AV53: 44835 | AW53: 44866 | AX53: 44896 | AY53: 44927 | AZ53: 44958 | BA53: 44986 | BB53: 45017 | BC53: 45047 | BD53: 45078 | BE53: 45108 | BF53: 45139 | BG53: 45170 | BH53: 45200 | BI53: 45231 | BJ53: 45261 | BK53: TOTAL
B54: 1 | C54: =SUM($C22:$BJ22)*Premissas!$N$20 -> 4067.8487 | D54: =C150*Premissas!$N$20 -> 4022.6079 | E54: =D150*Premissas!$N$20 -> 3976.9931 | F54: =E150*Premissas!$N$20 -> 3931.0013 | G54: =F150*Premissas!$N$20 -> 3884.6291 | H54: =G150*Premissas!$N$20 -> 3837.8736 | I54: =H150*Premissas!$N$20 -> 3790.7316 | J54: =I150*Premissas!$N$20 -> 3743.1998 | K54: =J150*Premissas!$N$20 -> 3695.275 | ... BJ54: =BI150*Premissas!$N$20 -> 94.951026 | BK54: =SUM(C54:BJ54) -> 140083.09
B55: 2 | C55: =SUM($C23:$BJ23)*Premissas!$N$20 -> 852.79846 | D55: =C151*Premissas!$N$20 -> 843.31403 | E55: =D151*Premissas!$N$20 -> 833.75118 | F55: =E151*Premissas!$N$20 -> 824.10928 | G55: =F151*Premissas!$N$20 -> 814.38766 | H55: =G151*Premissas!$N$20 -> 804.58567 | I55: =H151*Premissas!$N$20 -> 794.70264 | J55: =I151*Premissas!$N$20 -> 784.7379 | K55: =J151*Premissas!$N$20 -> 774.69078 | ... BJ55: =BI151*Premissas!$N$20 -> 19.905875 | BK55: =SUM(C55:BJ55) -> 29367.524
B56: 3 | C56: =SUM($C24:$BJ24)*Premissas!$N$20 -> 7675.1862 | D56: =C152*Premissas!$N$20 -> 7589.8263 | E56: =D152*Premissas!$N$20 -> 7503.7607 | F56: =E152*Premissas!$N$20 -> 7416.9835 | G56: =F152*Premissas!$N$20 -> 7329.4889 | H56: =G152*Premissas!$N$20 -> 7241.271 | I56: =H152*Premissas!$N$20 -> 7152.3238 | J56: =I152*Premissas!$N$20 -> 7062.6411 | K56: =J152*Premissas!$N$20 -> 6972.217 | ... BJ56: =BI152*Premissas!$N$20 -> 179.15288 | BK56: =SUM(C56:BJ56) -> 264307.71
B57: 4 | C57: =SUM($C25:$BJ25)*Premissas!$N$20 -> 426.39923 | D57: =C153*Premissas!$N$20 -> 421.65701 | E57: =D153*Premissas!$N$20 -> 416.87559 | F57: =E153*Premissas!$N$20 -> 412.05464 | G57: =F153*Premissas!$N$20 -> 407.19383 | H57: =G153*Premissas!$N$20 -> 402.29283 | I57: =H153*Premissas!$N$20 -> 397.35132 | J57: =I153*Premissas!$N$20 -> 392.36895 | K57: =J153*Premissas!$N$20 -> 387.34539 | ... BJ57: =BI153*Premissas!$N$20 -> 9.9529377 | BK57: =SUM(C57:BJ57) -> 14683.762
B58: 5 | C58: =SUM($C26:$BJ26)*Premissas!$N$20 -> 5543.19 | D58: =C154*Premissas!$N$20 -> 5481.5412 | E58: =D154*Premissas!$N$20 -> 5419.3827 | F58: =E154*Premissas!$N$20 -> 5356.7103 | G58: =F154*Premissas!$N$20 -> 5293.5198 | H58: =G154*Premissas!$N$20 -> 5229.8068 | I58: =H154*Premissas!$N$20 -> 5165.5672 | J58: =I154*Premissas!$N$20 -> 5100.7964 | K58: =J154*Premissas!$N$20 -> 5035.4901 | ... BJ58: =BI154*Premissas!$N$20 -> 129.38819 | BK58: =SUM(C58:BJ58) -> 190888.9
B59: 6 | C59: =SUM($C27:$BJ27)*Premissas!$N$20 -> 4067.8487 | D59: =C155*Premissas!$N$20 -> 4022.6079 | E59: =D155*Premissas!$N$20 -> 3976.9931 | F59: =E155*Premissas!$N$20 -> 3931.0013 | G59: =F155*Premissas!$N$20 -> 3884.6291 | H59: =G155*Premissas!$N$20 -> 3837.8736 | I59: =H155*Premissas!$N$20 -> 3790.7316 | J59: =I155*Premissas!$N$20 -> 3743.1998 | K59: =J155*Premissas!$N$20 -> 3695.275 | ... BJ59: =BI155*Premissas!$N$20 -> 94.951026 | BK59: =SUM(C59:BJ59) -> 140083.09
B60: 7 | C60: =SUM($C28:$BJ28)*Premissas!$N$20 -> 1492.3973 | D60: =C156*Premissas!$N$20 -> 1475.7996 | E60: =D156*Premissas!$N$20 -> 1459.0646 | F60: =E156*Premissas!$N$20 -> 1442.1912 | G60: =F156*Premissas!$N$20 -> 1425.1784 | H60: =G156*Premissas!$N$20 -> 1408.0249 | I60: =H156*Premissas!$N$20 -> 1390.7296 | J60: =I156*Premissas!$N$20 -> 1373.2913 | K60: =J156*Premissas!$N$20 -> 1355.7089 | ... BJ60: =BI156*Premissas!$N$20 -> 34.835282 | BK60: =SUM(C60:BJ60) -> 51393.167
C61: =SUM($C29:$BJ29)*Premissas!$N$20 -> 0 | D61: =C157*Premissas!$N$20 -> 0 | E61: =D157*Premissas!$N$20 -> 0 | F61: =E157*Premissas!$N$20 -> 0 | G61: =F157*Premissas!$N$20 -> 0 | H61: =G157*Premissas!$N$20 -> 0 | I61: =H157*Premissas!$N$20 -> 0 | J61: =I157*Premissas!$N$20 -> 0 | K61: =J157*Premissas!$N$20 -> 0 | ... BJ61: =BI157*Premissas!$N$20 -> 0 | BK61: =SUM(C61:BJ61) -> 0
C62: =SUM($C30:$BJ30)*Premissas!$N$20 -> 0 | D62: =C158*Premissas!$N$20 -> 0 | E62: =D158*Premissas!$N$20 -> 0 | F62: =E158*Premissas!$N$20 -> 0 | G62: =F158*Premissas!$N$20 -> 0 | H62: =G158*Premissas!$N$20 -> 0 | I62: =H158*Premissas!$N$20 -> 0 | J62: =I158*Premissas!$N$20 -> 0 | K62: =J158*Premissas!$N$20 -> 0 | ... BJ62: =BI158*Premissas!$N$20 -> 0 | BK62: =SUM(C62:BJ62) -> 0
C63: =SUM($C31:$BJ31)*Premissas!$N$20 -> 0 | D63: =C159*Premissas!$N$20 -> 0 | E63: =D159*Premissas!$N$20 -> 0 | F63: =E159*Premissas!$N$20 -> 0 | G63: =F159*Premissas!$N$20 -> 0 | H63: =G159*Premissas!$N$20 -> 0 | I63: =H159*Premissas!$N$20 -> 0 | J63: =I159*Premissas!$N$20 -> 0 | K63: =J159*Premissas!$N$20 -> 0 | ... BJ63: =BI159*Premissas!$N$20 -> 0 | BK63: =SUM(C63:BJ63) -> 0
B64: TOTAL | C64: =SUM(C54:C63) -> 24125.668 | D64: =SUM(D54:D63) -> 23857.354 | E64: =SUM(E54:E63) -> 23586.821 | F64: =SUM(F54:F63) -> 23314.052 | G64: =SUM(G54:G63) -> 23039.027 | H64: =SUM(H54:H63) -> 22761.729 | I64: =SUM(I54:I63) -> 22482.138 | J64: =SUM(J54:J63) -> 22200.235 | ... BK64: =SUM(BK54:BK63) -> 830807.25
B67: Saldo Ativo - Direito de uso de Imóveis CPC 06 R2 (Custo)
B69: # Identificação Contrato | C69: 43466 | D69: 43497 | E69: 43525 | F69: 43556 | G69: 43586 | H69: 43617 | I69: 43647 | J69: 43678 | K69: 43709 | L69: 43739 | M69: 43770 | N69: 43800 | O69: 43831 | P69: 43862 | Q69: 43891 | R69: 43922 | S69: 43952 | T69: 43983 | U69: 44013 | V69: 44044 | W69: 44075 | X69: 44105 | Y69: 44136 | Z69: 44166 | AA69: 44197 | AB69: 44228 | AC69: 44256 | AD69: 44287 | AE69: 44317 | AF69: 44348 | AG69: 44378 | AH69: 44409 | AI69: 44440 | AJ69: 44470 | AK69: 44501 | AL69: 44531 | AM69: 44562 | AN69: 44593 | AO69: 44621 | AP69: 44652 | AQ69: 44682 | AR69: 44713 | AS69: 44743 | AT69: 44774 | AU69: 44805 | AV69: 44835 | AW69: 44866 | AX69: 44896 | AY69: 44927 | AZ69: 44958 | BA69: 44986 | BB69: 45017 | BC69: 45047 | BD69: 45078 | BE69: 45108 | BF69: 45139 | BG69: 45170 | BH69: 45200 | BI69: 45231 | BJ69: 45261 | BK69: TOTAL
B70: 1 | C70: =SUM($C22:$BJ22) -> 492031.79 | D70: =SUM($C22:$BJ22) -> 492031.79 | E70: =SUM($C22:$BJ22) -> 492031.79 | F70: =SUM($C22:$BJ22) -> 492031.79 | G70: =SUM($C22:$BJ22) -> 492031.79 | H70: =SUM($C22:$BJ22) -> 492031.79 | I70: =SUM($C22:$BJ22) -> 492031.79 | J70: =SUM($C22:$BJ22) -> 492031.79 | ... BJ70: =SUM($C22:$BJ22) -> 492031.79 | BK70: =BJ70 -> 492031.79
B71: 2 | C71: =SUM($C23:$BJ23) -> 103151.32 | D71: =SUM($C23:$BJ23) -> 103151.32 | E71: =SUM($C23:$BJ23) -> 103151.32 | F71: =SUM($C23:$BJ23) -> 103151.32 | G71: =SUM($C23:$BJ23) -> 103151.32 | H71: =SUM($C23:$BJ23) -> 103151.32 | I71: =SUM($C23:$BJ23) -> 103151.32 | J71: =SUM($C23:$BJ23) -> 103151.32 | ... BJ71: =SUM($C23:$BJ23) -> 103151.32 | BK71: =BJ71 -> 103151.32
B72: 3 | C72: =SUM($C24:$BJ24) -> 928361.87 | D72: =SUM($C24:$BJ24) -> 928361.87 | E72: =SUM($C24:$BJ24) -> 928361.87 | F72: =SUM($C24:$BJ24) -> 928361.87 | G72: =SUM($C24:$BJ24) -> 928361.87 | H72: =SUM($C24:$BJ24) -> 928361.87 | I72: =SUM($C24:$BJ24) -> 928361.87 | J72: =SUM($C24:$BJ24) -> 928361.87 | ... BJ72: =SUM($C24:$BJ24) -> 928361.87 | BK72: =BJ72 -> 928361.87
B73: 4 | C73: =SUM($C25:$BJ25) -> 51575.659 | D73: =SUM($C25:$BJ25) -> 51575.659 | E73: =SUM($C25:$BJ25) -> 51575.659 | F73: =SUM($C25:$BJ25) -> 51575.659 | G73: =SUM($C25:$BJ25) -> 51575.659 | H73: =SUM($C25:$BJ25) -> 51575.659 | I73: =SUM($C25:$BJ25) -> 51575.659 | J73: =SUM($C25:$BJ25) -> 51575.659 | ... BJ73: =SUM($C25:$BJ25) -> 51575.659 | BK73: =BJ73 -> 51575.659
B74: 5 | C74: =SUM($C26:$BJ26) -> 670483.57 | D74: =SUM($C26:$BJ26) -> 670483.57 | E74: =SUM($C26:$BJ26) -> 670483.57 | F74: =SUM($C26:$BJ26) -> 670483.57 | G74: =SUM($C26:$BJ26) -> 670483.57 | H74: =SUM($C26:$BJ26) -> 670483.57 | I74: =SUM($C26:$BJ26) -> 670483.57 | J74: =SUM($C26:$BJ26) -> 670483.57 | ... BJ74: =SUM($C26:$BJ26) -> 670483.57 | BK74: =BJ74 -> 670483.57
B75: 6 | C75: =SUM($C27:$BJ27) -> 492031.79 | D75: =SUM($C27:$BJ27) -> 492031.79 | E75: =SUM($C27:$BJ27) -> 492031.79 | F75: =SUM($C27:$BJ27) -> 492031.79 | G75: =SUM($C27:$BJ27) -> 492031.79 | H75: =SUM($C27:$BJ27) -> 492031.79 | I75: =SUM($C27:$BJ27) -> 492031.79 | J75: =SUM($C27:$BJ27) -> 492031.79 | ... BJ75: =SUM($C27:$BJ27) -> 492031.79 | BK75: =BJ75 -> 492031.79
B76: 7 | C76: =SUM($C28:$BJ28) -> 180514.81 | D76: =SUM($C28:$BJ28) -> 180514.81 | E76: =SUM($C28:$BJ28) -> 180514.81 | F76: =SUM($C28:$BJ28) -> 180514.81 | G76: =SUM($C28:$BJ28) -> 180514.81 | H76: =SUM($C28:$BJ28) -> 180514.81 | I76: =SUM($C28:$BJ28) -> 180514.81 | J76: =SUM($C28:$BJ28) -> 180514.81 | ... BJ76: =SUM($C28:$BJ28) -> 180514.81 | BK76: =BJ76 -> 180514.81
C77: =SUM($C29:$BJ29) -> 0 | D77: =SUM($C29:$BJ29) -> 0 | E77: =SUM($C29:$BJ29) -> 0 | F77: =SUM($C29:$BJ29) -> 0 | G77: =SUM($C29:$BJ29) -> 0 | H77: =SUM($C29:$BJ29) -> 0 | I77: =SUM($C29:$BJ29) -> 0 | J77: =SUM($C29:$BJ29) -> 0 | ... BJ77: =SUM($C29:$BJ29) -> 0 | BK77: =BJ77 -> 0
C78: =SUM($C30:$BJ30) -> 0 | D78: =SUM($C30:$BJ30) -> 0 | E78: =SUM($C30:$BJ30) -> 0 | F78: =SUM($C30:$BJ30) -> 0 | G78: =SUM($C30:$BJ30) -> 0 | H78: =SUM($C30:$BJ30) -> 0 | I78: =SUM($C30:$BJ30) -> 0 | J78: =SUM($C30:$BJ30) -> 0 | ... BJ78: =SUM($C30:$BJ30) -> 0 | BK78: =BJ78 -> 0
C79: =SUM($C31:$BJ31) -> 0 | D79: =SUM($C31:$BJ31) -> 0 | E79: =SUM($C31:$BJ31) -> 0 | F79: =SUM($C31:$BJ31) -> 0 | G79: =SUM($C31:$BJ31) -> 0 | H79: =SUM($C31:$BJ31) -> 0 | I79: =SUM($C31:$BJ31) -> 0 | J79: =SUM($C31:$BJ31) -> 0 | ... BJ79: =SUM($C31:$BJ31) -> 0 | BK79: =BJ79 -> 0
B80: TOTAL | C80: =SUM(C70:C79) -> 2918150.8 | D80: =SUM(D70:D79) -> 2918150.8 | E80: =SUM(E70:E79) -> 2918150.8 | F80: =SUM(F70:F79) -> 2918150.8 | G80: =SUM(G70:G79) -> 2918150.8 | H80: =SUM(H70:H79) -> 2918150.8 | I80: =SUM(I70:I79) -> 2918150.8 | J80: =SUM(J70:J79) -> 2918150.8 | ... BK80: =SUM(BK70:BK79) -> 2918150.8
B83: Saldo Ativo - Direito de uso de Imóveis CPC 06 R2 (Depreciação Acumulada)
B85: # Identificação Contrato | C85: 43466 | D85: 43497 | E85: 43525 | F85: 43556 | G85: 43586 | H85: 43617 | I85: 43647 | J85: 43678 | K85: 43709 | L85: 43739 | M85: 43770 | N85: 43800 | O85: 43831 | P85: 43862 | Q85: 43891 | R85: 43922 | S85: 43952 | T85: 43983 | U85: 44013 | V85: 44044 | W85: 44075 | X85: 44105 | Y85: 44136 | Z85: 44166 | AA85: 44197 | AB85: 44228 | AC85: 44256 | AD85: 44287 | AE85: 44317 | AF85: 44348 | AG85: 44378 | AH85: 44409 | AI85: 44440 | AJ85: 44470 | AK85: 44501 | AL85: 44531 | AM85: 44562 | AN85: 44593 | AO85: 44621 | AP85: 44652 | AQ85: 44682 | AR85: 44713 | AS85: 44743 | AT85: 44774 | AU85: 44805 | AV85: 44835 | AW85: 44866 | AX85: 44896 | AY85: 44927 | AZ85: 44958 | BA85: 44986 | BB85: 45017 | BC85: 45047 | BD85: 45078 | BE85: 45108 | BF85: 45139 | BG85: 45170 | BH85: 45200 | BI85: 45231 | BJ85: 45261 | BK85: TOTAL
B86: 1 | C86: =-SUM($C38:C38) -> -8200.5298 | D86: =-SUM($C38:D38) -> -16401.06 | E86: =-SUM($C38:E38) -> -24601.59 | F86: =-SUM($C38:F38) -> -32802.119 | G86: =-SUM($C38:G38) -> -41002.649 | H86: =-SUM($C38:H38) -> -49203.179 | I86: =-SUM($C38:I38) -> -57403.709 | J86: =-SUM($C38:J38) -> -65604.239 | ... BJ86: =-SUM($C38:BJ38) -> -492031.79 | BK86: =BJ86 -> -492031.79
B87: 2 | C87: =-SUM($C39:C39) -> -1719.1886 | D87: =-SUM($C39:D39) -> -3438.3773 | E87: =-SUM($C39:E39) -> -5157.5659 | F87: =-SUM($C39:F39) -> -6876.7546 | G87: =-SUM($C39:G39) -> -8595.9432 | H87: =-SUM($C39:H39) -> -10315.132 | I87: =-SUM($C39:I39) -> -12034.321 | J87: =-SUM($C39:J39) -> -13753.509 | ... BJ87: =-SUM($C39:BJ39) -> -103151.32 | BK87: =BJ87 -> -103151.32
B88: 3 | C88: =-SUM($C40:C40) -> -15472.698 | D88: =-SUM($C40:D40) -> -30945.396 | E88: =-SUM($C40:E40) -> -46418.093 | F88: =-SUM($C40:F40) -> -61890.791 | G88: =-SUM($C40:G40) -> -77363.489 | H88: =-SUM($C40:H40) -> -92836.187 | I88: =-SUM($C40:I40) -> -108308.88 | J88: =-SUM($C40:J40) -> -123781.58 | ... BJ88: =-SUM($C40:BJ40) -> -928361.87 | BK88: =BJ88 -> -928361.87
B89: 4 | C89: =-SUM($C41:C41) -> -859.59432 | D89: =-SUM($C41:D41) -> -1719.1886 | E89: =-SUM($C41:E41) -> -2578.783 | F89: =-SUM($C41:F41) -> -3438.3773 | G89: =-SUM($C41:G41) -> -4297.9716 | H89: =-SUM($C41:H41) -> -5157.5659 | I89: =-SUM($C41:I41) -> -6017.1603 | J89: =-SUM($C41:J41) -> -6876.7546 | ... BJ89: =-SUM($C41:BJ41) -> -51575.659 | BK89: =BJ89 -> -51575.659
B90: 5 | C90: =-SUM($C42:C42) -> -11174.726 | D90: =-SUM($C42:D42) -> -22349.452 | E90: =-SUM($C42:E42) -> -33524.179 | F90: =-SUM($C42:F42) -> -44698.905 | G90: =-SUM($C42:G42) -> -55873.631 | H90: =-SUM($C42:H42) -> -67048.357 | I90: =-SUM($C42:I42) -> -78223.083 | J90: =-SUM($C42:J42) -> -89397.81 | ... BJ90: =-SUM($C42:BJ42) -> -670483.57 | BK90: =BJ90 -> -670483.57
B91: 6 | C91: =-SUM($C43:C43) -> -8200.5298 | D91: =-SUM($C43:D43) -> -16401.06 | E91: =-SUM($C43:E43) -> -24601.59 | F91: =-SUM($C43:F43) -> -32802.119 | G91: =-SUM($C43:G43) -> -41002.649 | H91: =-SUM($C43:H43) -> -49203.179 | I91: =-SUM($C43:I43) -> -57403.709 | J91: =-SUM($C43:J43) -> -65604.239 | ... BJ91: =-SUM($C43:BJ43) -> -492031.79 | BK91: =BJ91 -> -492031.79
B92: 7 | C92: =-SUM($C44:C44) -> -3008.5801 | D92: =-SUM($C44:D44) -> -6017.1603 | E92: =-SUM($C44:E44) -> -9025.7404 | F92: =-SUM($C44:F44) -> -12034.321 | G92: =-SUM($C44:G44) -> -15042.901 | H92: =-SUM($C44:H44) -> -18051.481 | I92: =-SUM($C44:I44) -> -21060.061 | J92: =-SUM($C44:J44) -> -24068.641 | ... BJ92: =-SUM($C44:BJ44) -> -180514.81 | BK92: =BJ92 -> -180514.81
C93: =-SUM($C45:C45) -> 0 | D93: =-SUM($C45:D45) -> 0 | E93: =-SUM($C45:E45) -> 0 | F93: =-SUM($C45:F45) -> 0 | G93: =-SUM($C45:G45) -> 0 | H93: =-SUM($C45:H45) -> 0 | I93: =-SUM($C45:I45) -> 0 | J93: =-SUM($C45:J45) -> 0 | ... BJ93: =-SUM($C45:BJ45) -> 0 | BK93: =BJ93 -> 0
C94: =-SUM($C46:C46) -> 0 | D94: =-SUM($C46:D46) -> 0 | E94: =-SUM($C46:E46) -> 0 | F94: =-SUM($C46:F46) -> 0 | G94: =-SUM($C46:G46) -> 0 | H94: =-SUM($C46:H46) -> 0 | I94: =-SUM($C46:I46) -> 0 | J94: =-SUM($C46:J46) -> 0 | ... BJ94: =-SUM($C46:BJ46) -> 0 | BK94: =BJ94 -> 0
C95: =-SUM($C47:C47) -> 0 | D95: =-SUM($C47:D47) -> 0 | E95: =-SUM($C47:E47) -> 0 | F95: =-SUM($C47:F47) -> 0 | G95: =-SUM($C47:G47) -> 0 | H95: =-SUM($C47:H47) -> 0 | I95: =-SUM($C47:I47) -> 0 | J95: =-SUM($C47:J47) -> 0 | ... BJ95: =-SUM($C47:BJ47) -> 0 | BK95: =BJ95 -> 0
B96: TOTAL | C96: =SUM(C86:C95) -> -48635.847 | D96: =SUM(D86:D95) -> -97271.694 | E96: =SUM(E86:E95) -> -145907.54 | F96: =SUM(F86:F95) -> -194543.39 | G96: =SUM(G86:G95) -> -243179.23 | H96: =SUM(H86:H95) -> -291815.08 | I96: =SUM(I86:I95) -> -340450.93 | J96: =SUM(J86:J95) -> -389086.77 | ... BK96: =SUM(BK86:BK95) -> -2918150.8
C97: =C80+C96-C112 -> 0 | D97: =D80+D96-D112 -> 0 | E97: =E80+E96-E112 -> 0 | F97: =F80+F96-F112 -> 0 | G97: =G80+G96-G112 -> 0 | H97: =H80+H96-H112 -> 0 | I97: =I80+I96-I112 -> 0 | J97: =J80+J96-J112 -> 0 | ... BJ97: =BJ80+BJ96-BJ112 -> 8.9494279e-10
B99: Saldo Ativo - Direito de uso de Imóveis CPC 06 R2 (Saldo líquido)
B101: # Identificação Contrato | C101: 43466 | D101: 43497 | E101: 43525 | F101: 43556 | G101: 43586 | H101: 43617 | I101: 43647 | J101: 43678 | K101: 43709 | L101: 43739 | M101: 43770 | N101: 43800 | O101: 43831 | P101: 43862 | Q101: 43891 | R101: 43922 | S101: 43952 | T101: 43983 | U101: 44013 | V101: 44044 | W101: 44075 | X101: 44105 | Y101: 44136 | Z101: 44166 | AA101: 44197 | AB101: 44228 | AC101: 44256 | AD101: 44287 | AE101: 44317 | AF101: 44348 | AG101: 44378 | AH101: 44409 | AI101: 44440 | AJ101: 44470 | AK101: 44501 | AL101: 44531 | AM101: 44562 | AN101: 44593 | AO101: 44621 | AP101: 44652 | AQ101: 44682 | AR101: 44713 | AS101: 44743 | AT101: 44774 | AU101: 44805 | AV101: 44835 | AW101: 44866 | AX101: 44896 | AY101: 44927 | AZ101: 44958 | BA101: 44986 | BB101: 45017 | BC101: 45047 | BD101: 45078 | BE101: 45108 | BF101: 45139 | BG101: 45170 | BH101: 45200 | BI101: 45231 | BJ101: 45261 | BK101: TOTAL
B102: 1 | C102: =C70+C86 -> 483831.26 | D102: =D70+D86 -> 475630.73 | E102: =E70+E86 -> 467430.2 | F102: =F70+F86 -> 459229.67 | G102: =G70+G86 -> 451029.14 | H102: =H70+H86 -> 442828.61 | I102: =I70+I86 -> 434628.08 | J102: =J70+J86 -> 426427.55 | ... BJ102: =BJ70+BJ86 -> 8.1490725e-10 | BK102: =BJ102 -> 8.1490725e-10
B103: 2 | C103: =C71+C87 -> 101432.13 | D103: =D71+D87 -> 99712.941 | E103: =E71+E87 -> 97993.753 | F103: =F71+F87 -> 96274.564 | G103: =G71+G87 -> 94555.375 | H103: =H71+H87 -> 92836.187 | I103: =I71+I87 -> 91116.998 | J103: =J71+J87 -> 89397.81 | ... BJ103: =BJ71+BJ87 -> -1.3096724e-10 | BK103: =BJ103 -> -1.3096724e-10
B104: 3 | C104: =C72+C88 -> 912889.17 | D104: =D72+D88 -> 897416.47 | E104: =E72+E88 -> 881943.77 | F104: =F72+F88 -> 866471.08 | G104: =G72+G88 -> 850998.38 | H104: =H72+H88 -> 835525.68 | I104: =I72+I88 -> 820052.98 | J104: =J72+J88 -> 804580.29 | ... BJ104: =BJ72+BJ88 -> 0 | BK104: =BJ104 -> 0
B105: 4 | C105: =C73+C89 -> 50716.065 | D105: =D73+D89 -> 49856.471 | E105: =E73+E89 -> 48996.876 | F105: =F73+F89 -> 48137.282 | G105: =G73+G89 -> 47277.688 | H105: =H73+H89 -> 46418.093 | I105: =I73+I89 -> 45558.499 | J105: =J73+J89 -> 44698.905 | ... BJ105: =BJ73+BJ89 -> -6.5483619e-11 | BK105: =BJ105 -> -6.5483619e-11
B106: 5 | C106: =C74+C90 -> 659308.85 | D106: =D74+D90 -> 648134.12 | E106: =E74+E90 -> 636959.39 | F106: =F74+F90 -> 625784.67 | G106: =G74+G90 -> 614609.94 | H106: =H74+H90 -> 603435.21 | I106: =I74+I90 -> 592260.49 | J106: =J74+J90 -> 581085.76 | ... BJ106: =BJ74+BJ90 -> 0 | BK106: =BJ106 -> 0
B107: 6 | C107: =C75+C91 -> 483831.26 | D107: =D75+D91 -> 475630.73 | E107: =E75+E91 -> 467430.2 | F107: =F75+F91 -> 459229.67 | G107: =G75+G91 -> 451029.14 | H107: =H75+H91 -> 442828.61 | I107: =I75+I91 -> 434628.08 | J107: =J75+J91 -> 426427.55 | ... BJ107: =BJ75+BJ91 -> 8.1490725e-10 | BK107: =BJ107 -> 8.1490725e-10
B108: 7 | C108: =C76+C92 -> 177506.23 | D108: =D76+D92 -> 174497.65 | E108: =E76+E92 -> 171489.07 | F108: =F76+F92 -> 168480.49 | G108: =G76+G92 -> 165471.91 | H108: =H76+H92 -> 162463.33 | I108: =I76+I92 -> 159454.75 | J108: =J76+J92 -> 156446.17 | ... BJ108: =BJ76+BJ92 -> 0 | BK108: =BJ108 -> 0
C109: =C77+C93 -> 0 | D109: =D77+D93 -> 0 | E109: =E77+E93 -> 0 | F109: =F77+F93 -> 0 | G109: =G77+G93 -> 0 | H109: =H77+H93 -> 0 | I109: =I77+I93 -> 0 | J109: =J77+J93 -> 0 | ... BJ109: =BJ77+BJ93 -> 0 | BK109: =BJ109 -> 0
C110: =C78+C94 -> 0 | D110: =D78+D94 -> 0 | E110: =E78+E94 -> 0 | F110: =F78+F94 -> 0 | G110: =G78+G94 -> 0 | H110: =H78+H94 -> 0 | I110: =I78+I94 -> 0 | J110: =J78+J94 -> 0 | ... BJ110: =BJ78+BJ94 -> 0 | BK110: =BJ110 -> 0
C111: =C79+C95 -> 0 | D111: =D79+D95 -> 0 | E111: =E79+E95 -> 0 | F111: =F79+F95 -> 0 | G111: =G79+G95 -> 0 | H111: =H79+H95 -> 0 | I111: =I79+I95 -> 0 | J111: =J79+J95 -> 0 | ... BJ111: =BJ79+BJ95 -> 0 | BK111: =BJ111 -> 0
B112: TOTAL | C112: =SUM(C102:C111) -> 2869515 | D112: =SUM(D102:D111) -> 2820879.1 | E112: =SUM(E102:E111) -> 2772243.3 | F112: =SUM(F102:F111) -> 2723607.4 | G112: =SUM(G102:G111) -> 2674971.6 | H112: =SUM(H102:H111) -> 2626335.7 | I112: =SUM(I102:I111) -> 2577699.9 | J112: =SUM(J102:J111) -> 2529064 | ... BK112: =SUM(BK102:BK111) -> 1.4333636e-09
C113: =$BK$32-SUM($C48:C48)-C112 -> 0 | D113: =$BK$32-SUM($C48:D48)-D112 -> 0 | E113: =$BK$32-SUM($C48:E48)-E112 -> 0 | F113: =$BK$32-SUM($C48:F48)-F112 -> 0 | G113: =$BK$32-SUM($C48:G48)-G112 -> 0 | H113: =$BK$32-SUM($C48:H48)-H112 -> 0 | I113: =$BK$32-SUM($C48:I48)-I112 -> 0 | J113: =$BK$32-SUM($C48:J48)-J112 -> 0 | ... BJ113: =$BK$32-SUM($C48:BJ48)-BJ112 -> -1.4333636e-09
B115: Saldo Passivo - Obrigações por arrendamento CPC 06 R2 (Circulante)
B117: # Identificação Contrato | C117: 43466 | D117: 43497 | E117: 43525 | F117: 43556 | G117: 43586 | H117: 43617 | I117: 43647 | J117: 43678 | K117: 43709 | L117: 43739 | M117: 43770 | N117: 43800 | O117: 43831 | P117: 43862 | Q117: 43891 | R117: 43922 | S117: 43952 | T117: 43983 | U117: 44013 | V117: 44044 | W117: 44075 | X117: 44105 | Y117: 44136 | Z117: 44166 | AA117: 44197 | AB117: 44228 | AC117: 44256 | AD117: 44287 | AE117: 44317 | AF117: 44348 | AG117: 44378 | AH117: 44409 | AI117: 44440 | AJ117: 44470 | AK117: 44501 | AL117: 44531 | AM117: 44562 | AN117: 44593 | AO117: 44621 | AP117: 44652 | AQ117: 44682 | AR117: 44713 | AS117: 44743 | AT117: 44774 | AU117: 44805 | AV117: 44835 | AW117: 44866 | AX117: 44896 | AY117: 44927 | AZ117: 44958 | BA117: 44986 | BB117: 45017 | BC117: 45047 | BD117: 45078 | BE117: 45108 | BF117: 45139 | BG117: 45170 | BH117: 45200 | BI117: 45231 | BJ117: 45261 | BK117: TOTAL
B118: 1 | C118: =SUM(D5:O5)-SUM(D54:O54) -> 69777.34 | D118: =SUM(E5:P5)-SUM(E54:P54) -> 70827.751 | E118: =SUM(F5:Q5)-SUM(F54:Q54) -> 71886.847 | F118: =SUM(G5:R5)-SUM(G54:R54) -> 72954.698 | G118: =SUM(H5:S5)-SUM(H54:S54) -> 74031.378 | H118: =SUM(I5:T5)-SUM(I54:T54) -> 75116.96 | I118: =SUM(J5:U5)-SUM(J54:U54) -> 76211.516 | J118: =SUM(K5:V5)-SUM(K54:V54) -> 77315.121 | ... AW118: =SUM(AX5:BI5)-SUM(AX54:BI54) -> 130146.88 | AX118: =SUM(AY5:$BJ5)-SUM(AY54:$BJ54) -> 131770.46 | AY118: =SUM(AZ5:$BJ5)-SUM(AZ54:$BJ54) -> 121280 | AZ118: =SUM(BA5:$BJ5)-SUM(BA54:$BJ54) -> 110702.8 | BA118: =SUM(BB5:$BJ5)-SUM(BB54:$BJ54) -> 100038.16 | BB118: =SUM(BC5:$BJ5)-SUM(BC54:$BJ54) -> 89285.346 | BC118: =SUM(BD5:$BJ5)-SUM(BD54:$BJ54) -> 78443.636 | BD118: =SUM(BE5:$BJ5)-SUM(BE54:$BJ54) -> 67512.292 | BE118: =SUM(BF5:$BJ5)-SUM(BF54:$BJ54) -> 56490.574 | ... BI118: =SUM(BJ5:$BJ5)-SUM(BJ54:$BJ54) -> 11484.922 | BJ118: 0 | BK118: =BJ118 -> 0
B119: 2 | C119: =SUM(D6:O6)-SUM(D55:O55) -> 14628.373 | D119: =SUM(E6:P6)-SUM(E55:P55) -> 14848.585 | E119: =SUM(F6:Q6)-SUM(F55:Q55) -> 15070.618 | F119: =SUM(G6:R6)-SUM(G55:R55) -> 15294.486 | G119: =SUM(H6:S6)-SUM(H55:S55) -> 15520.205 | H119: =SUM(I6:T6)-SUM(I55:T55) -> 15747.79 | I119: =SUM(J6:U6)-SUM(J55:U55) -> 15977.257 | J119: =SUM(K6:V6)-SUM(K55:V55) -> 16208.621 | ... AW119: =SUM(AX6:BI6)-SUM(AX55:BI55) -> 27284.461 | AX119: =SUM(AY6:$BJ6)-SUM(AY55:$BJ55) -> 27624.835 | AY119: =SUM(AZ6:$BJ6)-SUM(AZ55:$BJ55) -> 25425.576 | AZ119: =SUM(BA6:$BJ6)-SUM(BA55:$BJ55) -> 23208.134 | BA119: =SUM(BB6:$BJ6)-SUM(BB55:$BJ55) -> 20972.36 | BB119: =SUM(BC6:$BJ6)-SUM(BC55:$BJ55) -> 18718.102 | BC119: =SUM(BD6:$BJ6)-SUM(BD55:$BJ55) -> 16445.207 | BD119: =SUM(BE6:$BJ6)-SUM(BE55:$BJ55) -> 14153.52 | BE119: =SUM(BF6:$BJ6)-SUM(BF55:$BJ55) -> 11842.888 | ... BI119: =SUM(BJ6:$BJ6)-SUM(BJ55:$BJ55) -> 2407.7404 | BJ119: 0 | BK119: =BJ119 -> 0
B120: 3 | C120: =SUM(D7:O7)-SUM(D56:O56) -> 131655.36 | D120: =SUM(E7:P7)-SUM(E56:P56) -> 133637.27 | E120: =SUM(F7:Q7)-SUM(F56:Q56) -> 135635.56 | F120: =SUM(G7:R7)-SUM(G56:R56) -> 137650.37 | G120: =SUM(H7:S7)-SUM(H56:S56) -> 139681.85 | H120: =SUM(I7:T7)-SUM(I56:T56) -> 141730.11 | I120: =SUM(J7:U7)-SUM(J56:U56) -> 143795.31 | J120: =SUM(K7:V7)-SUM(K56:V56) -> 145877.59 | ... AW120: =SUM(AX7:BI7)-SUM(AX56:BI56) -> 245560.15 | AX120: =SUM(AY7:$BJ7)-SUM(AY56:$BJ56) -> 248623.52 | AY120: =SUM(AZ7:$BJ7)-SUM(AZ56:$BJ56) -> 228830.18 | AZ120: =SUM(BA7:$BJ7)-SUM(BA56:$BJ56) -> 208873.21 | BA120: =SUM(BB7:$BJ7)-SUM(BB56:$BJ56) -> 188751.24 | BB120: =SUM(BC7:$BJ7)-SUM(BC56:$BJ56) -> 168462.92 | BC120: =SUM(BD7:$BJ7)-SUM(BD56:$BJ56) -> 148006.86 | BD120: =SUM(BE7:$BJ7)-SUM(BE56:$BJ56) -> 127381.68 | BE120: =SUM(BF7:$BJ7)-SUM(BF56:$BJ56) -> 106585.99 | ... BI120: =SUM(BJ7:$BJ7)-SUM(BJ56:$BJ56) -> 21669.663 | BJ120: 0 | BK120: =BJ120 -> 0
B121: 4 | C121: =SUM(D8:O8)-SUM(D57:O57) -> 7314.1866 | D121: =SUM(E8:P8)-SUM(E57:P57) -> 7424.2926 | E121: =SUM(F8:Q8)-SUM(F57:Q57) -> 7535.3089 | F121: =SUM(G8:R8)-SUM(G57:R57) -> 7647.243 | G121: =SUM(H8:S8)-SUM(H57:S57) -> 7760.1025 | H121: =SUM(I8:T8)-SUM(I57:T57) -> 7873.8951 | I121: =SUM(J8:U8)-SUM(J57:U57) -> 7988.6285 | J121: =SUM(K8:V8)-SUM(K57:V57) -> 8104.3104 | ... AW121: =SUM(AX8:BI8)-SUM(AX57:BI57) -> 13642.231 | AX121: =SUM(AY8:$BJ8)-SUM(AY57:$BJ57) -> 13812.418 | AY121: =SUM(AZ8:$BJ8)-SUM(AZ57:$BJ57) -> 12712.788 | AZ121: =SUM(BA8:$BJ8)-SUM(BA57:$BJ57) -> 11604.067 | BA121: =SUM(BB8:$BJ8)-SUM(BB57:$BJ57) -> 10486.18 | BB121: =SUM(BC8:$BJ8)-SUM(BC57:$BJ57) -> 9359.051 | BC121: =SUM(BD8:$BJ8)-SUM(BD57:$BJ57) -> 8222.6033 | BD121: =SUM(BE8:$BJ8)-SUM(BE57:$BJ57) -> 7076.7602 | BE121: =SUM(BF8:$BJ8)-SUM(BF57:$BJ57) -> 5921.4438 | ... BI121: =SUM(BJ8:$BJ8)-SUM(BJ57:$BJ57) -> 1203.8702 | BJ121: 0 | BK121: =BJ121 -> 0
B122: 5 | C122: =SUM(D9:O9)-SUM(D58:O58) -> 95084.426 | D122: =SUM(E9:P9)-SUM(E58:P58) -> 96515.804 | E122: =SUM(F9:Q9)-SUM(F58:Q58) -> 97959.016 | F122: =SUM(G9:R9)-SUM(G58:R58) -> 99414.159 | G122: =SUM(H9:S9)-SUM(H58:S58) -> 100881.33 | H122: =SUM(I9:T9)-SUM(I58:T58) -> 102360.64 | I122: =SUM(J9:U9)-SUM(J58:U58) -> 103852.17 | J122: =SUM(K9:V9)-SUM(K58:V58) -> 105356.04 | ... AW122: =SUM(AX9:BI9)-SUM(AX58:BI58) -> 177349 | AX122: =SUM(AY9:$BJ9)-SUM(AY58:$BJ58) -> 179561.43 | AY122: =SUM(AZ9:$BJ9)-SUM(AZ58:$BJ58) -> 165266.24 | AZ122: =SUM(BA9:$BJ9)-SUM(BA58:$BJ58) -> 150852.87 | BA122: =SUM(BB9:$BJ9)-SUM(BB58:$BJ58) -> 136320.34 | BB122: =SUM(BC9:$BJ9)-SUM(BC58:$BJ58) -> 121667.66 | BC122: =SUM(BD9:$BJ9)-SUM(BD58:$BJ58) -> 106893.84 | BD122: =SUM(BE9:$BJ9)-SUM(BE58:$BJ58) -> 91997.882 | BE122: =SUM(BF9:$BJ9)-SUM(BF58:$BJ58) -> 76978.769 | ... BI122: =SUM(BJ9:$BJ9)-SUM(BJ58:$BJ58) -> 15650.313 | BJ122: 0 | BK122: =BJ122 -> 0
B123: 6 | C123: =SUM(D10:O10)-SUM(D59:O59) -> 69777.34 | D123: =SUM(E10:P10)-SUM(E59:P59) -> 70827.751 | E123: =SUM(F10:Q10)-SUM(F59:Q59) -> 71886.847 | F123: =SUM(G10:R10)-SUM(G59:R59) -> 72954.698 | G123: =SUM(H10:S10)-SUM(H59:S59) -> 74031.378 | H123: =SUM(I10:T10)-SUM(I59:T59) -> 75116.96 | I123: =SUM(J10:U10)-SUM(J59:U59) -> 76211.516 | J123: =SUM(K10:V10)-SUM(K59:V59) -> 77315.121 | ... AW123: =SUM(AX10:BI10)-SUM(AX59:BI59) -> 130146.88 | AX123: =SUM(AY10:$BJ10)-SUM(AY59:$BJ59) -> 131770.46 | AY123: =SUM(AZ10:$BJ10)-SUM(AZ59:$BJ59) -> 121280 | AZ123: =SUM(BA10:$BJ10)-SUM(BA59:$BJ59) -> 110702.8 | BA123: =SUM(BB10:$BJ10)-SUM(BB59:$BJ59) -> 100038.16 | BB123: =SUM(BC10:$BJ10)-SUM(BC59:$BJ59) -> 89285.346 | BC123: =SUM(BD10:$BJ10)-SUM(BD59:$BJ59) -> 78443.636 | BD123: =SUM(BE10:$BJ10)-SUM(BE59:$BJ59) -> 67512.292 | BE123: =SUM(BF10:$BJ10)-SUM(BF59:$BJ59) -> 56490.574 | ... BI123: =SUM(BJ10:$BJ10)-SUM(BJ59:$BJ59) -> 11484.922 | BJ123: 0 | BK123: =BJ123 -> 0
B124: 7 | C124: =SUM(D11:O11)-SUM(D60:O60) -> 25599.653 | D124: =SUM(E11:P11)-SUM(E60:P60) -> 25985.024 | E124: =SUM(F11:Q11)-SUM(F60:Q60) -> 26373.581 | F124: =SUM(G11:R11)-SUM(G60:R60) -> 26765.351 | G124: =SUM(H11:S11)-SUM(H60:S60) -> 27160.359 | H124: =SUM(I11:T11)-SUM(I60:T60) -> 27558.633 | I124: =SUM(J11:U11)-SUM(J60:U60) -> 27960.2 | J124: =SUM(K11:V11)-SUM(K60:V60) -> 28365.086 | ... AW124: =SUM(AX11:BI11)-SUM(AX60:BI60) -> 47747.807 | AX124: =SUM(AY11:$BJ11)-SUM(AY60:$BJ60) -> 48343.462 | AY124: =SUM(AZ11:$BJ11)-SUM(AZ60:$BJ60) -> 44494.758 | AZ124: =SUM(BA11:$BJ11)-SUM(BA60:$BJ60) -> 40614.235 | BA124: =SUM(BB11:$BJ11)-SUM(BB60:$BJ60) -> 36701.63 | BB124: =SUM(BC11:$BJ11)-SUM(BC60:$BJ60) -> 32756.678 | BC124: =SUM(BD11:$BJ11)-SUM(BD60:$BJ60) -> 28779.112 | BD124: =SUM(BE11:$BJ11)-SUM(BE60:$BJ60) -> 24768.661 | BE124: =SUM(BF11:$BJ11)-SUM(BF60:$BJ60) -> 20725.053 | ... BI124: =SUM(BJ11:$BJ11)-SUM(BJ60:$BJ60) -> 4213.5457 | BJ124: 0 | BK124: =BJ124 -> 0
...

Sheet Lançamentos Contábeis
C2: Pelo Lançamento Inicial
C4: Lançamento | D4: 43466 | E4: 43497 | F4: 43525 | G4: 43556 | H4: 43586 | I4: 43617 | J4: 43647 | K4: 43678 | L4: 43709 | M4: 43739 | N4: 43770 | O4: 43800 | P4: 43831 | Q4: 43862 | R4: 43891 | S4: 43922 | T4: 43952 | U4: 43983 | V4: 44013 | W4: 44044 | X4: 44075 | Y4: 44105 | Z4: 44136 | AA4: 44166 | AB4: 44197 | AC4: 44228 | AD4: 44256 | AE4: 44287 | AF4: 44317 | AG4: 44348 | AH4: 44378 | AI4: 44409 | AJ4: 44440 | AK4: 44470 | AL4: 44501 | AM4: 44531 | AN4: 44562 | AO4: 44593 | AP4: 44621 | AQ4: 44652 | AR4: 44682 | AS4: 44713 | AT4: 44743 | AU4: 44774 | AV4: 44805 | AW4: 44835 | AX4: 44866 | AY4: 44896 | AZ4: 44927 | BA4: 44958 | BB4: 44986 | BC4: 45017 | BD4: 45047 | BE4: 45078 | BF4: 45108 | BG4: 45139 | BH4: 45170 | BI4: 45200 | BJ4: 45231 | BK4: 45261
B5: D | C5: Direito de uso de Imóveis CPC 06 R2 (Ativo Não Circulante) | D5: =Contabilização!$C$80 -> 2918150.8 | E5: 0 | F5: 0 | G5: 0 | H5: 0 | I5: 0 | J5: 0 | K5: 0 | L5: 0 | M5: 0 | N5: 0 | O5: 0 | P5: 0 | Q5: 0 | R5: 0 | S5: 0 | T5: 0 | U5: 0 | V5: 0 | W5: 0 | X5: 0 | Y5: 0 | Z5: 0 | AA5: 0 | AB5: 0 | AC5: 0 | AD5: 0 | AE5: 0 | AF5: 0 | AG5: 0 | AH5: 0 | AI5: 0 | AJ5: 0 | AK5: 0 | AL5: 0 | AM5: 0 | AN5: 0 | AO5: 0 | AP5: 0 | AQ5: 0 | AR5: 0 | AS5: 0 | AT5: 0 | AU5: 0 | AV5: 0 | AW5: 0 | AX5: 0 | AY5: 0 | AZ5: 0 | BA5: 0 | BB5: 0 | BC5: 0 | BD5: 0 | BE5: 0 | BF5: 0 | BG5: 0 | BH5: 0 | BI5: 0 | BJ5: 0 | BK5: 0
B6: C | C6: Obrigações por arrendamento CPC 06 R2 (Passivo Circulante) | D6: =D5 -> 2918150.8 | E6: =E5 -> 0 | F6: =F5 -> 0 | G6: =G5 -> 0 | H6: =H5 -> 0 | I6: =I5 -> 0 | J6: =J5 -> 0 | K6: =K5 -> 0 | ... BK6: =BK5 -> 0
C9: Pelo Pagamento do Aluguel
C11: Lançamento | D11: 43466 | E11: 43497 | F11: 43525 | G11: 43556 | H11: 43586 | I11: 43617 | J11: 43647 | K11: 43678 | L11: 43709 | M11: 43739 | N11: 43770 | O11: 43800 | P11: 43831 | Q11: 43862 | R11: 43891 | S11: 43922 | T11: 43952 | U11: 43983 | V11: 44013 | W11: 44044 | X11: 44075 | Y11: 44105 | Z11: 44136 | AA11: 44166 | AB11: 44197 | AC11: 44228 | AD11: 44256 | AE11: 44287 | AF11: 44317 | AG11: 44348 | AH11: 44378 | AI11: 44409 | AJ11: 44440 | AK11: 44470 | AL11: 44501 | AM11: 44531 | AN11: 44562 | AO11: 44593 | AP11: 44621 | AQ11: 44652 | AR11: 44682 | AS11: 44713 | AT11: 44743 | AU11: 44774 | AV11: 44805 | AW11: 44835 | AX11: 44866 | AY11: 44896 | AZ11: 44927 | BA11: 44958 | BB11: 44986 | BC11: 45017 | BD11: 45047 | BE11: 45078 | BF11: 45108 | BG11: 45139 | BH11: 45170 | BI11: 45200 | BJ11: 45231 | BK11: 45261
B12: D | C12: Obrigações por arrendamento CPC 06 R2 (Passivo Circulante) | D12: =D13 -> 56580 | E12: =E13 -> 56580 | F12: =F13 -> 56580 | G12: =G13 -> 56580 | H12: =H13 -> 56580 | I12: =I13 -> 56580 | J12: =J13 -> 56580 | K12: =K13 -> 56580 | ... BK12: =BK13 -> 68678.113
B13: C | C13: Bancos (Ativo Circulante) | D13: =Contabilização!C15 -> 56580 | E13: =Contabilização!D15 -> 56580 | F13: =Contabilização!E15 -> 56580 | G13: =Contabilização!F15 -> 56580 | H13: =Contabilização!G15 -> 56580 | I13: =Contabilização!H15 -> 56580 | J13: =Contabilização!I15 -> 56580 | K13: =Contabilização!J15 -> 56580 | ... BK13: =Contabilização!BJ15 -> 68678.113
D14: =D13-Contabilização!C15 -> 0 | E14: =E13-Contabilização!D15 -> 0 | F14: =F13-Contabilização!E15 -> 0 | G14: =G13-Contabilização!F15 -> 0 | H14: =H13-Contabilização!G15 -> 0 | I14: =I13-Contabilização!H15 -> 0 | J14: =J13-Contabilização!I15 -> 0 | K14: =K13-Contabilização!J15 -> 0 | ... BK14: =BK13-Contabilização!BJ15 -> 0
C16: Pelo Lançamento de Juros
C18: Lançamento | D18: 43466 | E18: 43497 | F18: 43525 | G18: 43556 | H18: 43586 | I18: 43617 | J18: 43647 | K18: 43678 | L18: 43709 | M18: 43739 | N18: 43770 | O18: 43800 | P18: 43831 | Q18: 43862 | R18: 43891 | S18: 43922 | T18: 43952 | U18: 43983 | V18: 44013 | W18: 44044 | X18: 44075 | Y18: 44105 | Z18: 44136 | AA18: 44166 | AB18: 44197 | AC18: 44228 | AD18: 44256 | AE18: 44287 | AF18: 44317 | AG18: 44348 | AH18: 44378 | AI18: 44409 | AJ18: 44440 | AK18: 44470 | AL18: 44501 | AM18: 44531 | AN18: 44562 | AO18: 44593 | AP18: 44621 | AQ18: 44652 | AR18: 44682 | AS18: 44713 | AT18: 44743 | AU18: 44774 | AV18: 44805 | AW18: 44835 | AX18: 44866 | AY18: 44896 | AZ18: 44927 | BA18: 44958 | BB18: 44986 | BC18: 45017 | BD18: 45047 | BE18: 45078 | BF18: 45108 | BG18: 45139 | BH18: 45170 | BI18: 45200 | BJ18: 45231 | BK18: 45261
B19: D | C19: Despesa financeira (Resultado) | D19: =Contabilização!C64 -> 24125.668 | E19: =Contabilização!D64 -> 23857.354 | F19: =Contabilização!E64 -> 23586.821 | G19: =Contabilização!F64 -> 23314.052 | H19: =Contabilização!G64 -> 23039.027 | I19: =Contabilização!H64 -> 22761.729 | J19: =Contabilização!I64 -> 22482.138 | K19: =Contabilização!J64 -> 22200.235 | ... BK19: =Contabilização!BJ64 -> 563.13721
B20: C | C20: Obrigações por arrendamento CPC 06 R2 (Passivo Circulante) | D20: =D19 -> 24125.668 | E20: =E19 -> 23857.354 | F20: =F19 -> 23586.821 | G20: =G19 -> 23314.052 | H20: =H19 -> 23039.027 | I20: =I19 -> 22761.729 | J20: =J19 -> 22482.138 | K20: =K19 -> 22200.235 | ... BK20: =BK19 -> 563.13721
D21: =SUM($D6:D6)+SUM($D20:D20)-SUM($D12:D12)-Contabilização!C160 -> 0 | E21: =SUM($D6:E6)+SUM($D20:E20)-SUM($D12:E12)-Contabilização!D160 -> 0 | F21: =SUM($D6:F6)+SUM($D20:F20)-SUM($D12:F12)-Contabilização!E160 -> 0 | G21: =SUM($D6:G6)+SUM($D20:G20)-SUM($D12:G12)-Contabilização!F160 -> 0 | H21: =SUM($D6:H6)+SUM($D20:H20)-SUM($D12:H12)-Contabilização!G160 -> 0 | I21: =SUM($D6:I6)+SUM($D20:I20)-SUM($D12:I12)-Contabilização!H160 -> 0 | J21: =SUM($D6:J6)+SUM($D20:J20)-SUM($D12:J12)-Contabilização!I160 -> 0 | K21: =SUM($D6:K6)+SUM($D20:K20)-SUM($D12:K12)-Contabilização!J160 -> 0 | ... BK21: =SUM($D6:BK6)+SUM($D20:BK20)-SUM($D12:BK12)-Contabilização!BJ160 -> -5.8207661e-10
C23: Pela Segregação entre Curto e Longo Prazo
C25: Lançamento | D25: 43466 | E25: 43497 | F25: 43525 | G25: 43556 | H25: 43586 | I25: 43617 | J25: 43647 | K25: 43678 | L25: 43709 | M25: 43739 | N25: 43770 | O25: 43800 | P25: 43831 | Q25: 43862 | R25: 43891 | S25: 43922 | T25: 43952 | U25: 43983 | V25: 44013 | W25: 44044 | X25: 44075 | Y25: 44105 | Z25: 44136 | AA25: 44166 | AB25: 44197 | AC25: 44228 | AD25: 44256 | AE25: 44287 | AF25: 44317 | AG25: 44348 | AH25: 44378 | AI25: 44409 | AJ25: 44440 | AK25: 44470 | AL25: 44501 | AM25: 44531 | AN25: 44562 | AO25: 44593 | AP25: 44621 | AQ25: 44652 | AR25: 44682 | AS25: 44713 | AT25: 44743 | AU25: 44774 | AV25: 44805 | AW25: 44835 | AX25: 44866 | AY25: 44896 | AZ25: 44927 | BA25: 44958 | BB25: 44986 | BC25: 45017 | BD25: 45047 | BE25: 45078 | BF25: 45108 | BG25: 45139 | BH25: 45170 | BI25: 45200 | BJ25: 45231 | BK25: 45261
B26: D | C26: Obrigações por arrendamento CPC 06 R2 (Passivo Circulante) | D26: =D27 -> 2471859.8 | E26: 0 | F26: 0 | G26: 0 | H26: 0 | I26: 0 | J26: 0 | K26: 0 | L26: 0 | M26: 0 | N26: 0 | O26: 0 | P26: 0 | Q26: 0 | R26: 0 | S26: 0 | T26: 0 | U26: 0 | V26: 0 | W26: 0 | X26: 0 | Y26: 0 | Z26: 0 | AA26: 0 | AB26: 0 | AC26: 0 | AD26: 0 | AE26: 0 | AF26: 0 | AG26: 0 | AH26: 0 | AI26: 0 | AJ26: 0 | AK26: 0 | AL26: 0 | AM26: 0 | AN26: 0 | AO26: 0 | AP26: 0 | AQ26: 0 | AR26: 0 | AS26: 0 | AT26: 0 | AU26: 0 | AV26: 0 | AW26: 0 | AX26: 0 | AY26: 0 | AZ26: 0 | BA26: 0 | BB26: 0 | BC26: 0 | BD26: 0 | BE26: 0 | BF26: 0 | BG26: 0 | BH26: 0 | BI26: 0 | BJ26: 0 | BK26: 0
B27: C | C27: Obrigações por arrendamento CPC 06 R2 (Passivo Não Circulante) | D27: =Contabilização!C160-Contabilização!C128 -> 2471859.8 | E27: 0 | F27: 0 | G27: 0 | H27: 0 | I27: 0 | J27: 0 | K27: 0 | L27: 0 | M27: 0 | N27: 0 | O27: 0 | P27: 0 | Q27: 0 | R27: 0 | S27: 0 | T27: 0 | U27: 0 | V27: 0 | W27: 0 | X27: 0 | Y27: 0 | Z27: 0 | AA27: 0 | AB27: 0 | AC27: 0 | AD27: 0 | AE27: 0 | AF27: 0 | AG27: 0 | AH27: 0 | AI27: 0 | AJ27: 0 | AK27: 0 | AL27: 0 | AM27: 0 | AN27: 0 | AO27: 0 | AP27: 0 | AQ27: 0 | AR27: 0 | AS27: 0 | AT27: 0 | AU27: 0 | AV27: 0 | AW27: 0 | AX27: 0 | AY27: 0 | AZ27: 0 | BA27: 0 | BB27: 0 | BC27: 0 | BD27: 0 | BE27: 0 | BF27: 0 | BG27: 0 | BH27: 0 | BI27: 0 | BJ27: 0 | BK27: 0
B29: D | C29: Obrigações por arrendamento CPC 06 R2 (Passivo Não Circulante) | D29: 0 | E29: =-(Contabilização!D144-SUM('Lançamentos Contábeis'!$D27:D27)+SUM('Lançamentos Contábeis'!$D29:D29)) -> 38952.444 | F29: =-(Contabilização!E144-SUM('Lançamentos Contábeis'!$D27:E27)+SUM('Lançamentos Contábeis'!$D29:E29)) -> 39274.481 | G29: =-(Contabilização!F144-SUM('Lançamentos Contábeis'!$D27:F27)+SUM('Lançamentos Contábeis'!$D29:F29)) -> 39599.181 | H29: =-(Contabilização!G144-SUM('Lançamentos Contábeis'!$D27:G27)+SUM('Lançamentos Contábeis'!$D29:G29)) -> 39926.565 | I29: =-(Contabilização!H144-SUM('Lançamentos Contábeis'!$D27:H27)+SUM('Lançamentos Contábeis'!$D29:H29)) -> 40256.656 | J29: =-(Contabilização!I144-SUM('Lançamentos Contábeis'!$D27:I27)+SUM('Lançamentos Contábeis'!$D29:I29)) -> 40589.476 | K29: =-(Contabilização!J144-SUM('Lançamentos Contábeis'!$D27:J27)+SUM('Lançamentos Contábeis'!$D29:J29)) -> 40925.048 | L29: =-(Contabilização!K144-SUM('Lançamentos Contábeis'!$D27:K27)+SUM('Lançamentos Contábeis'!$D29:K29)) -> 41263.394 | ... BK29: =-(Contabilização!BJ144-SUM('Lançamentos Contábeis'!$D27:BJ27)+SUM('Lançamentos Contábeis'!$D29:BJ29)) -> 0
B30: C | C30: Obrigações por arrendamento CPC 06 R2 (Passivo Circulante) | D30: 0 | E30: =E29 -> 38952.444 | F30: =F29 -> 39274.481 | G30: =G29 -> 39599.181 | H30: =H29 -> 39926.565 | I30: =I29 -> 40256.656 | J30: =J29 -> 40589.476 | K30: =K29 -> 40925.048 | L30: =L29 -> 41263.394 | ... BK30: =BK29 -> 0
D31: =Contabilização!C128-(SUM($D6:D6)-SUM($D12:D12)+SUM($D20:D20)+SUM($D30:D30)-SUM($D26:D26)) -> 0 | E31: =Contabilização!D128-(SUM($D6:E6)-SUM($D12:E12)+SUM($D20:E20)+SUM($D30:E30)-SUM($D26:E26)) -> -7.2759576e-09 | F31: =Contabilização!E128-(SUM($D6:F6)-SUM($D12:F12)+SUM($D20:F20)+SUM($D30:F30)-SUM($D26:F26)) -> -7.1595423e-09 | G31: =Contabilização!F128-(SUM($D6:G6)-SUM($D12:G12)+SUM($D20:G20)+SUM($D30:G30)-SUM($D26:G26)) -> -7.1013346e-09 | H31: =Contabilização!G128-(SUM($D6:H6)-SUM($D12:H12)+SUM($D20:H20)+SUM($D30:H30)-SUM($D26:H26)) -> -7.043127e-09 | I31: =Contabilização!H128-(SUM($D6:I6)-SUM($D12:I12)+SUM($D20:I20)+SUM($D30:I30)-SUM($D26:I26)) -> -7.043127e-09 | J31: =Contabilização!I128-(SUM($D6:J6)-SUM($D12:J12)+SUM($D20:J20)+SUM($D30:J30)-SUM($D26:J26)) -> -6.693881e-09 | K31: =Contabilização!J128-(SUM($D6:K6)-SUM($D12:K12)+SUM($D20:K20)+SUM($D30:K30)-SUM($D26:K26)) -> -6.2864274e-09 | ... BK31: =Contabilização!BJ128-(SUM($D6:BK6)-SUM($D12:BK12)+SUM($D20:BK20)+SUM($D30:BK30)-SUM($D26:BK26)) -> -6.0535967e-09
D32: =Contabilização!C144+(-SUM($D27:D27)+SUM($D29:D29)) -> -6.519258e-09 | E32: =Contabilização!D144+(-SUM($D27:E27)+SUM($D29:E29)) -> 0 | F32: =Contabilização!E144+(-SUM($D27:F27)+SUM($D29:F29)) -> 0 | G32: =Contabilização!F144+(-SUM($D27:G27)+SUM($D29:G29)) -> 0 | H32: =Contabilização!G144+(-SUM($D27:H27)+SUM($D29:H29)) -> 0 | I32: =Contabilização!H144+(-SUM($D27:I27)+SUM($D29:I29)) -> 0 | J32: =Contabilização!I144+(-SUM($D27:J27)+SUM($D29:J29)) -> 0 | K32: =Contabilização!J144+(-SUM($D27:K27)+SUM($D29:K29)) -> 0 | ... BK32: =Contabilização!BJ144+(-SUM($D27:BK27)+SUM($D29:BK29)) -> 0
C34: Pelo Lançamento de Depreciação
C36: Lançamento | D36: 43466 | E36: 43497 | F36: 43525 | G36: 43556 | H36: 43586 | I36: 43617 | J36: 43647 | K36: 43678 | L36: 43709 | M36: 43739 | N36: 43770 | O36: 43800 | P36: 43831 | Q36: 43862 | R36: 43891 | S36: 43922 | T36: 43952 | U36: 43983 | V36: 44013 | W36: 44044 | X36: 44075 | Y36: 44105 | Z36: 44136 | AA36: 44166 | AB36: 44197 | AC36: 44228 | AD36: 44256 | AE36: 44287 | AF36: 44317 | AG36: 44348 | AH36: 44378 | AI36: 44409 | AJ36: 44440 | AK36: 44470 | AL36: 44501 | AM36: 44531 | AN36: 44562 | AO36: 44593 | AP36: 44621 | AQ36: 44652 | AR36: 44682 | AS36: 44713 | AT36: 44743 | AU36: 44774 | AV36: 44805 | AW36: 44835 | AX36: 44866 | AY36: 44896 | AZ36: 44927 | BA36: 44958 | BB36: 44986 | BC36: 45017 | BD36: 45047 | BE36: 45078 | BF36: 45108 | BG36: 45139 | BH36: 45170 | BI36: 45200 | BJ36: 45231 | BK36: 45261
B37: D | C37: Despesa com depreciação (Resultado) | D37: =Contabilização!C48 -> 48635.847 | E37: =Contabilização!D48 -> 48635.847 | F37: =Contabilização!E48 -> 48635.847 | G37: =Contabilização!F48 -> 48635.847 | H37: =Contabilização!G48 -> 48635.847 | I37: =Contabilização!H48 -> 48635.847 | J37: =Contabilização!I48 -> 48635.847 | K37: =Contabilização!J48 -> 48635.847 | ... BK37: =Contabilização!BJ48 -> 48635.847
B38: C | C38: (-) Dep. Acum. Direito de uso de Imóveis CPC 06 R2 (Ativo Não Circulante) | D38: =D37 -> 48635.847 | E38: =E37 -> 48635.847 | F38: =F37 -> 48635.847 | G38: =G37 -> 48635.847 | H38: =H37 -> 48635.847 | I38: =I37 -> 48635.847 | J38: =J37 -> 48635.847 | K38: =K37 -> 48635.847 | ... BK38: =BK37 -> 48635.847
D39: =Contabilização!C112-(SUM($D5:D5)-SUM($D38:D38)) -> 0 | E39: =Contabilização!D112-(SUM($D5:E5)-SUM($D38:E38)) -> 0 | F39: =Contabilização!E112-(SUM($D5:F5)-SUM($D38:F38)) -> 0 | G39: =Contabilização!F112-(SUM($D5:G5)-SUM($D38:G38)) -> 0 | H39: =Contabilização!G112-(SUM($D5:H5)-SUM($D38:H38)) -> 0 | I39: =Contabilização!H112-(SUM($D5:I5)-SUM($D38:I38)) -> 0 | J39: =Contabilização!I112-(SUM($D5:J5)-SUM($D38:J38)) -> 0 | K39: =Contabilização!J112-(SUM($D5:K5)-SUM($D38:K38)) -> 0 | ... BK39: =Contabilização!BJ112-(SUM($D5:BK5)-SUM($D38:BK38)) -> 1.4333636e-09
C41: Saldo Ativo conforme lançamentos | D41: =SUM($D5:D5)-SUM($D38:D38) -> 2869515 | E41: =SUM($D5:E5)-SUM($D38:E38) -> 2820879.1 | F41: =SUM($D5:F5)-SUM($D38:F38) -> 2772243.3 | G41: =SUM($D5:G5)-SUM($D38:G38) -> 2723607.4 | H41: =SUM($D5:H5)-SUM($D38:H38) -> 2674971.6 | I41: =SUM($D5:I5)-SUM($D38:I38) -> 2626335.7 | J41: =SUM($D5:J5)-SUM($D38:J38) -> 2577699.9 | K41: =SUM($D5:K5)-SUM($D38:K38) -> 2529064 | ... BK41: =SUM($D5:BK5)-SUM($D38:BK38) -> 0
C42: Saldo Passivo conforme lançamentos | D42: =SUM($D6:D6)-SUM($D12:D12)+SUM($D20:D20)-SUM($D26:D26)+SUM($D27:D27)-SUM($D29:D29)+SUM($D30:D30) -> 2885696.5 | E42: =SUM($D6:E6)-SUM($D12:E12)+SUM($D20:E20)-SUM($D26:E26)+SUM($D27:E27)-SUM($D29:E29)+SUM($D30:E30) -> 2852973.8 | F42: =SUM($D6:F6)-SUM($D12:F12)+SUM($D20:F20)-SUM($D26:F26)+SUM($D27:F27)-SUM($D29:F29)+SUM($D30:F30) -> 2819980.6 | G42: =SUM($D6:G6)-SUM($D12:G12)+SUM($D20:G20)-SUM($D26:G26)+SUM($D27:G27)-SUM($D29:G29)+SUM($D30:G30) -> 2786714.7 | H42: =SUM($D6:H6)-SUM($D12:H12)+SUM($D20:H20)-SUM($D26:H26)+SUM($D27:H27)-SUM($D29:H29)+SUM($D30:H30) -> 2753173.7 | I42: =SUM($D6:I6)-SUM($D12:I12)+SUM($D20:I20)-SUM($D26:I26)+SUM($D27:I27)-SUM($D29:I29)+SUM($D30:I30) -> 2719355.5 | J42: =SUM($D6:J6)-SUM($D12:J12)+SUM($D20:J20)-SUM($D26:J26)+SUM($D27:J27)-SUM($D29:J29)+SUM($D30:J30) -> 2685257.6 | K42: =SUM($D6:K6)-SUM($D12:K12)+SUM($D20:K20)-SUM($D26:K26)+SUM($D27:K27)-SUM($D29:K29)+SUM($D30:K30) -> 2650877.8 | ... BK42: =SUM($D6:BK6)-SUM($D12:BK12)+SUM($D20:BK20)-SUM($D26:BK26)+SUM($D27:BK27)-SUM($D29:BK29)+SUM($D30:BK30) -> 6.0535967e-09
C43: Check Saldo Ativo | D43: =D41-Contabilização!C112 -> 0 | E43: =E41-Contabilização!D112 -> 0 | F43: =F41-Contabilização!E112 -> 0 | G43: =G41-Contabilização!F112 -> 0 | H43: =H41-Contabilização!G112 -> 0 | I43: =I41-Contabilização!H112 -> 0 | J43: =J41-Contabilização!I112 -> 0 | K43: =K41-Contabilização!J112 -> 0 | ... BK43: =BK41-Contabilização!BJ112 -> -1.4333636e-09
C44: Check Saldo Passivo | D44: =D42-Contabilização!C160 -> 0 | E44: =E42-Contabilização!D160 -> 0 | F44: =F42-Contabilização!E160 -> 0 | G44: =G42-Contabilização!F160 -> 0 | H44: =H42-Contabilização!G160 -> 0 | I44: =I42-Contabilização!H160 -> 0 | J44: =J42-Contabilização!I160 -> 0 | K44: =K42-Contabilização!J160 -> 0 | ... BK44: =BK42-Contabilização!BJ160 -> -5.8207661e-10
