Workbook

Sheet Início
A1: CONTROLE DE AÇÕES - INÍCIO

Sheet Cadastro
A1: CONTROLE DE AÇÕES - CADASTRO
B4: CORRETORA | C4: CORRETAGEM FIXA | D4: CORRETAGEM VARIÁVEL | E4: DEMAIS CORRETAGENS (%) | F4: DEMAIS CORRETAGENS ($)
B5: CORRETORA 1
B6: CORRETORA 2
B7: CORRETORA 3
B8: CORRETORA 4
B9: CORRETORA 5
B11: IMPOSTOS DE RENDA | E11: DEMAIS TAXAS
B12: DAY TRADE | E12: Liquidação (Day Trade)
B13: OPERAÇÕES COMUNS | E13: Liquidação (Operações Comuns)
E14: Emolumentos

Sheet Operação Comum
A1: CONTROLE DE AÇÕES - OPERAÇÃO COMUM
B4: DADOS DE COMPRA | L4: DADOS DE VENDA
B5: AÇÃO | C5: QUANTIDADE | D5: VALOR UNITÁRIO | E5: VALOR DO PACOTE | F5: DATA | G5: CORRETORA | H5: CORRETAGEM FIXA | I5: CORRETAGEM VARIÁVEL | J5: CUSTOS TOTAIS DA COMPRA | L5: DATA DA VENDA | M5: QUANTIDADE VENDIDA | N5: VALOR DA VENDA | O5: VALOR DO PACOTE | P5: RECEITA | Q5: LUCRO/PREJUÍZO | R5: IR | S5: DIVIDENDOS | T5: JUROS SOBRE O CAPITAL | U5: LUCRO/PREJUÍZO LÍQUIDO | V5: MARGEM DE LUCRO
B6: AÇÃO 1 | E6: =D6*C6 -> 0 | H6: =IF($G6="","",VLOOKUP($G6,Cadastro!$B$5:$F$9,2,FALSE)) | I6: =IF($G6="","",VLOOKUP($G6,Cadastro!$B$5:$F$9,3,FALSE)) | J6: =IF(C6="","",(Cadastro!$F$13+Cadastro!$F$14)*'Operação Comum'!E6+'Operação Comum'!H6+I6*'Operação Comum'!E6+E6) | O6: =M6*N6 -> 0 | P6: =O6-(Cadastro!$F$12+Cadastro!$F$14)*O6 -> 0 | Q6: =IF(J6="","",P6-J6) | U6: =IF(Q6="","",(Q6-R6+S6+T6)) | V6: =IF(U6="","",U6/E6)
B7: AÇÃO 2 | E7: =D7*C7 -> 0 | H7: =IF($G7="","",VLOOKUP($G7,Cadastro!$B$5:$F$9,2,FALSE)) | I7: =IF($G7="","",VLOOKUP($G7,Cadastro!$B$5:$F$9,3,FALSE)) | J7: =IF(C7="","",(Cadastro!$F$13+Cadastro!$F$14)*'Operação Comum'!E7+'Operação Comum'!H7+I7*'Operação Comum'!E7+E7) | O7: =M7*N7 -> 0 | P7: =O7-(Cadastro!$F$12+Cadastro!$F$14)*O7 -> 0 | Q7: =IF(J7="","",P7-J7) | U7: =IF(Q7="","",(Q7-R7+S7+T7)) | V7: =IF(U7="","",U7/E7)
B8: AÇÃO 3 | E8: =D8*C8 -> 0 | H8: =IF($G8="","",VLOOKUP($G8,Cadastro!$B$5:$F$9,2,FALSE)) | I8: =IF($G8="","",VLOOKUP($G8,Cadastro!$B$5:$F$9,3,FALSE)) | J8: =IF(C8="","",(Cadastro!$F$13+Cadastro!$F$14)*'Operação Comum'!E8+'Operação Comum'!H8+I8*'Operação Comum'!E8+E8) | O8: =M8*N8 -> 0 | P8: =O8-(Cadastro!$F$12+Cadastro!$F$14)*O8 -> 0 | Q8: =IF(J8="","",P8-J8) | U8: =IF(Q8="","",(Q8-R8+S8+T8)) | V8: =IF(U8="","",U8/E8)
B9: AÇÃO 4 | E9: =D9*C9 -> 0 | H9: =IF($G9="","",VLOOKUP($G9,Cadastro!$B$5:$F$9,2,FALSE)) | I9: =IF($G9="","",VLOOKUP($G9,Cadastro!$B$5:$F$9,3,FALSE)) | J9: =IF(C9="","",(Cadastro!$F$13+Cadastro!$F$14)*'Operação Comum'!E9+'Operação Comum'!H9+I9*'Operação Comum'!E9+E9) | O9: =M9*N9 -> 0 | P9: =O9-(Cadastro!$F$12+Cadastro!$F$14)*O9 -> 0 | Q9: =IF(J9="","",P9-J9) | U9: =IF(Q9="","",(Q9-R9+S9+T9)) | V9: =IF(U9="","",U9/E9)
B10: AÇÃO 5 | E10: =D10*C10 -> 0 | H10: =IF($G10="","",VLOOKUP($G10,Cadastro!$B$5:$F$9,2,FALSE)) | I10: =IF($G10="","",VLOOKUP($G10,Cadastro!$B$5:$F$9,3,FALSE)) | J10: =IF(C10="","",(Cadastro!$F$13+Cadastro!$F$14)*'Operação Comum'!E10+'Operação Comum'!H10+I10*'Operação Comum'!E10+E10) | O10: =M10*N10 -> 0 | P10: =O10-(Cadastro!$F$12+Cadastro!$F$14)*O10 -> 0 | Q10: =IF(J10="","",P10-J10) | U10: =IF(Q10="","",(Q10-R10+S10+T10)) | V10: =IF(U10="","",U10/E10)
B11: AÇÃO 6 | E11: =D11*C11 -> 0 | H11: =IF($G11="","",VLOOKUP($G11,Cadastro!$B$5:$F$9,2,FALSE)) | I11: =IF($G11="","",VLOOKUP($G11,Cadastro!$B$5:$F$9,3,FALSE)) | J11: =IF(C11="","",(Cadastro!$F$13+Cadastro!$F$14)*'Operação Comum'!E11+'Operação Comum'!H11+I11*'Operação Comum'!E11+E11) | O11: =M11*N11 -> 0 | P11: =O11-(Cadastro!$F$12+Cadastro!$F$14)*O11 -> 0 | Q11: =IF(J11="","",P11-J11) | U11: =IF(Q11="","",(Q11-R11+S11+T11)) | V11: =IF(U11="","",U11/E11)
B12: AÇÃO 7 | E12: =D12*C12 -> 0 | H12: =IF($G12="","",VLOOKUP($G12,Cadastro!$B$5:$F$9,2,FALSE)) | I12: =IF($G12="","",VLOOKUP($G12,Cadastro!$B$5:$F$9,3,FALSE)) | J12: =IF(C12="","",(Cadastro!$F$13+Cadastro!$F$14)*'Operação Comum'!E12+'Operação Comum'!H12+I12*'Operação Comum'!E12+E12) | O12: =M12*N12 -> 0 | P12: =O12-(Cadastro!$F$12+Cadastro!$F$14)*O12 -> 0 | Q12: =IF(J12="","",P12-J12) | U12: =IF(Q12="","",(Q12-R12+S12+T12)) | V12: =IF(U12="","",U12/E12)
B13: AÇÃO 8 | E13: =D13*C13 -> 0 | H13: =IF($G13="","",VLOOKUP($G13,Cadastro!$B$5:$F$9,2,FALSE)) | I13: =IF($G13="","",VLOOKUP($G13,Cadastro!$B$5:$F$9,3,FALSE)) | J13: =IF(C13="","",(Cadastro!$F$13+Cadastro!$F$14)*'Operação Comum'!E13+'Operação Comum'!H13+I13*'Operação Comum'!E13+E13) | O13: =M13*N13 -> 0 | P13: =O13-(Cadastro!$F$12+Cadastro!$F$14)*O13 -> 0 | Q13: =IF(J13="","",P13-J13) | U13: =IF(Q13="","",(Q13-R13+S13+T13)) | V13: =IF(U13="","",U13/E13)
B14: AÇÃO 9 | E14: =D14*C14 -> 0 | H14: =IF($G14="","",VLOOKUP($G14,Cadastro!$B$5:$F$9,2,FALSE)) | I14: =IF($G14="","",VLOOKUP($G14,Cadastro!$B$5:$F$9,3,FALSE)) | J14: =IF(C14="","",(Cadastro!$F$13+Cadastro!$F$14)*'Operação Comum'!E14+'Operação Comum'!H14+I14*'Operação Comum'!E14+E14) | O14: =M14*N14 -> 0 | P14: =O14-(Cadastro!$F$12+Cadastro!$F$14)*O14 -> 0 | Q14: =IF(J14="","",P14-J14) | U14: =IF(Q14="","",(Q14-R14+S14+T14)) | V14: =IF(U14="","",U14/E14)
B15: AÇÃO 10 | E15: =D15*C15 -> 0 | H15: =IF($G15="","",VLOOKUP($G15,Cadastro!$B$5:$F$9,2,FALSE)) | I15: =IF($G15="","",VLOOKUP($G15,Cadastro!$B$5:$F$9,3,FALSE)) | J15: =IF(C15="","",(Cadastro!$F$13+Cadastro!$F$14)*'Operação Comum'!E15+'Operação Comum'!H15+I15*'Operação Comum'!E15+E15) | O15: =M15*N15 -> 0 | P15: =O15-(Cadastro!$F$12+Cadastro!$F$14)*O15 -> 0 | Q15: =IF(J15="","",P15-J15) | U15: =IF(Q15="","",(Q15-R15+S15+T15)) | V15: =IF(U15="","",U15/E15)
B16: AÇÃO 11 | E16: =D16*C16 -> 0 | H16: =IF($G16="","",VLOOKUP($G16,Cadastro!$B$5:$F$9,2,FALSE)) | I16: =IF($G16="","",VLOOKUP($G16,Cadastro!$B$5:$F$9,3,FALSE)) | J16: =IF(C16="","",(Cadastro!$F$13+Cadastro!$F$14)*'Operação Comum'!E16+'Operação Comum'!H16+I16*'Operação Comum'!E16+E16) | O16: =M16*N16 -> 0 | P16: =O16-(Cadastro!$F$12+Cadastro!$F$14)*O16 -> 0 | Q16: =IF(J16="","",P16-J16) | U16: =IF(Q16="","",(Q16-R16+S16+T16)) | V16: =IF(U16="","",U16/E16)
B17: AÇÃO 12 | E17: =D17*C17 -> 0 | H17: =IF($G17="","",VLOOKUP($G17,Cadastro!$B$5:$F$9,2,FALSE)) | I17: =IF($G17="","",VLOOKUP($G17,Cadastro!$B$5:$F$9,3,FALSE)) | J17: =IF(C17="","",(Cadastro!$F$13+Cadastro!$F$14)*'Operação Comum'!E17+'Operação Comum'!H17+I17*'Operação Comum'!E17+E17) | O17: =M17*N17 -> 0 | P17: =O17-(Cadastro!$F$12+Cadastro!$F$14)*O17 -> 0 | Q17: =IF(J17="","",P17-J17) | U17: =IF(Q17="","",(Q17-R17+S17+T17)) | V17: =IF(U17="","",U17/E17)
... B35: AÇÃO 30 | E35: =D35*C35 -> 0 | H35: =IF($G35="","",VLOOKUP($G35,Cadastro!$B$5:$F$9,2,FALSE)) | I35: =IF($G35="","",VLOOKUP($G35,Cadastro!$B$5:$F$9,3,FALSE)) | J35: =IF(C35="","",(Cadastro!$F$13+Cadastro!$F$14)*'Operação Comum'!E35+'Operação Comum'!H35+I35*'Operação Comum'!E35+E35) | O35: =M35*N35 -> 0 | P35: =O35-(Cadastro!$F$12+Cadastro!$F$14)*O35 -> 0 | Q35: =IF(J35="","",P35-J35) | U35: =IF(Q35="","",(Q35-R35+S35+T35)) | V35: =IF(U35="","",U35/E35)

Sheet Operação Day Trade
A1: CONTROLE DE AÇÕES - OPERAÇÃO DAY TRADE
B4: DADOS DE COMPRA | L4: DADOS DE VENDA
B5: AÇÃO | C5: QUANTIDADE | D5: VALOR UNITÁRIO | E5: VALOR DO PACOTE | F5: DATA | G5: CORRETORA | H5: CORRETAGEM FIXA | I5: CORRETAGEM VARIÁVEL | J5: CUSTO TOTAIS DA COMPRA | L5: DATA DA VENDA | M5: QUANTIDADE VENDIDA | N5: VALOR DA VENDA | O5: VALOR DO PACOTE | P5: RECEITA | Q5: LUCRO/PREJUÍZO | R5: IR | S5: DIVIDENDOS | T5: JUROS SOBRE O CAPITAL | U5: LUCRO/PREJUÍZO LÍQUIDO | V5: MARGEM DE LUCRO
B6: AÇÃO 1 | E6: =D6*C6 -> 0 | H6: =IF($G6="","",VLOOKUP($G6,Cadastro!$B$5:$F$9,2,FALSE)) | I6: =IF($G6="","",VLOOKUP($G6,Cadastro!$B$5:$F$9,3,FALSE)) | J6: =IF(C6="","",(Cadastro!$F$12+Cadastro!$F$14)*'Operação Day Trade'!E6+'Operação Day Trade'!H6+I6*'Operação Day Trade'!E6+E6) | O6: =M6*N6 -> 0 | P6: =O6-(Cadastro!$F$12+Cadastro!$F$14)*O6 -> 0 | Q6: =IF(J6="","",P6-J6) | U6: =IF(Q6="","",(Q6-R6+S6+T6)) | V6: =IF(U6="","",U6/E6)
B7: AÇÃO 2 | E7: =D7*C7 -> 0 | H7: =IF($G7="","",VLOOKUP($G7,Cadastro!$B$5:$F$9,2,FALSE)) | I7: =IF($G7="","",VLOOKUP($G7,Cadastro!$B$5:$F$9,3,FALSE)) | J7: =IF(C7="","",(Cadastro!$F$12+Cadastro!$F$14)*'Operação Day Trade'!E7+'Operação Day Trade'!H7+I7*'Operação Day Trade'!E7+E7) | O7: =M7*N7 -> 0 | P7: =O7-(Cadastro!$F$12+Cadastro!$F$14)*O7 -> 0 | Q7: =IF(J7="","",P7-J7) | U7: =IF(Q7="","",(Q7-R7+S7+T7)) | V7: =IF(U7="","",U7/E7)
B8: AÇÃO 3 | E8: =D8*C8 -> 0 | H8: =IF($G8="","",VLOOKUP($G8,Cadastro!$B$5:$F$9,2,FALSE)) | I8: =IF($G8="","",VLOOKUP($G8,Cadastro!$B$5:$F$9,3,FALSE)) | J8: =IF(C8="","",(Cadastro!$F$12+Cadastro!$F$14)*'Operação Day Trade'!E8+'Operação Day Trade'!H8+I8*'Operação Day Trade'!E8+E8) | O8: =M8*N8 -> 0 | P8: =O8-(Cadastro!$F$12+Cadastro!$F$14)*O8 -> 0 | Q8: =IF(J8="","",P8-J8) | U8: =IF(Q8="","",(Q8-R8+S8+T8)) | V8: =IF(U8="","",U8/E8)
B9: AÇÃO 4 | E9: =D9*C9 -> 0 | H9: =IF($G9="","",VLOOKUP($G9,Cadastro!$B$5:$F$9,2,FALSE)) | I9: =IF($G9="","",VLOOKUP($G9,Cadastro!$B$5:$F$9,3,FALSE)) | J9: =IF(C9="","",(Cadastro!$F$12+Cadastro!$F$14)*'Operação Day Trade'!E9+'Operação Day Trade'!H9+I9*'Operação Day Trade'!E9+E9) | O9: =M9*N9 -> 0 | P9: =O9-(Cadastro!$F$12+Cadastro!$F$14)*O9 -> 0 | Q9: =IF(J9="","",P9-J9) | U9: =IF(Q9="","",(Q9-R9+S9+T9)) | V9: =IF(U9="","",U9/E9)
B10: AÇÃO 5 | E10: =D10*C10 -> 0 | H10: =IF($G10="","",VLOOKUP($G10,Cadastro!$B$5:$F$9,2,FALSE)) | I10: =IF($G10="","",VLOOKUP($G10,Cadastro!$B$5:$F$9,3,FALSE)) | J10: =IF(C10="","",(Cadastro!$F$12+Cadastro!$F$14)*'Operação Day Trade'!E10+'Operação Day Trade'!H10+I10*'Operação Day Trade'!E10+E10) | O10: =M10*N10 -> 0 | P10: =O10-(Cadastro!$F$12+Cadastro!$F$14)*O10 -> 0 | Q10: =IF(J10="","",P10-J10) | U10: =IF(Q10="","",(Q10-R10+S10+T10)) | V10: =IF(U10="","",U10/E10)
B11: AÇÃO 6 | E11: =D11*C11 -> 0 | H11: =IF($G11="","",VLOOKUP($G11,Cadastro!$B$5:$F$9,2,FALSE)) | I11: =IF($G11="","",VLOOKUP($G11,Cadastro!$B$5:$F$9,3,FALSE)) | J11: =IF(C11="","",(Cadastro!$F$12+Cadastro!$F$14)*'Operação Day Trade'!E11+'Operação Day Trade'!H11+I11*'Operação Day Trade'!E11+E11) | O11: =M11*N11 -> 0 | P11: =O11-(Cadastro!$F$12+Cadastro!$F$14)*O11 -> 0 | Q11: =IF(J11="","",P11-J11) | U11: =IF(Q11="","",(Q11-R11+S11+T11)) | V11: =IF(U11="","",U11/E11)
B12: AÇÃO 7 | E12: =D12*C12 -> 0 | H12: =IF($G12="","",VLOOKUP($G12,Cadastro!$B$5:$F$9,2,FALSE)) | I12: =IF($G12="","",VLOOKUP($G12,Cadastro!$B$5:$F$9,3,FALSE)) | J12: =IF(C12="","",(Cadastro!$F$12+Cadastro!$F$14)*'Operação Day Trade'!E12+'Operação Day Trade'!H12+I12*'Operação Day Trade'!E12+E12) | O12: =M12*N12 -> 0 | P12: =O12-(Cadastro!$F$12+Cadastro!$F$14)*O12 -> 0 | Q12: =IF(J12="","",P12-J12) | U12: =IF(Q12="","",(Q12-R12+S12+T12)) | V12: =IF(U12="","",U12/E12)
B13: AÇÃO 8 | E13: =D13*C13 -> 0 | H13: =IF($G13="","",VLOOKUP($G13,Cadastro!$B$5:$F$9,2,FALSE)) | I13: =IF($G13="","",VLOOKUP($G13,Cadastro!$B$5:$F$9,3,FALSE)) | J13: =IF(C13="","",(Cadastro!$F$12+Cadastro!$F$14)*'Operação Day Trade'!E13+'Operação Day Trade'!H13+I13*'Operação Day Trade'!E13+E13) | O13: =M13*N13 -> 0 | P13: =O13-(Cadastro!$F$12+Cadastro!$F$14)*O13 -> 0 | Q13: =IF(J13="","",P13-J13) | U13: =IF(Q13="","",(Q13-R13+S13+T13)) | V13: =IF(U13="","",U13/E13)
B14: AÇÃO 9 | E14: =D14*C14 -> 0 | H14: =IF($G14="","",VLOOKUP($G14,Cadastro!$B$5:$F$9,2,FALSE)) | I14: =IF($G14="","",VLOOKUP($G14,Cadastro!$B$5:$F$9,3,FALSE)) | J14: =IF(C14="","",(Cadastro!$F$12+Cadastro!$F$14)*'Operação Day Trade'!E14+'Operação Day Trade'!H14+I14*'Operação Day Trade'!E14+E14) | O14: =M14*N14 -> 0 | P14: =O14-(Cadastro!$F$12+Cadastro!$F$14)*O14 -> 0 | Q14: =IF(J14="","",P14-J14) | U14: =IF(Q14="","",(Q14-R14+S14+T14)) | V14: =IF(U14="","",U14/E14)
B15: AÇÃO 10 | E15: =D15*C15 -> 0 | H15: =IF($G15="","",VLOOKUP($G15,Cadastro!$B$5:$F$9,2,FALSE)) | I15: =IF($G15="","",VLOOKUP($G15,Cadastro!$B$5:$F$9,3,FALSE)) | J15: =IF(C15="","",(Cadastro!$F$12+Cadastro!$F$14)*'Operação Day Trade'!E15+'Operação Day Trade'!H15+I15*'Operação Day Trade'!E15+E15) | O15: =M15*N15 -> 0 | P15: =O15-(Cadastro!$F$12+Cadastro!$F$14)*O15 -> 0 | Q15: =IF(J15="","",P15-J15) | U15: =IF(Q15="","",(Q15-R15+S15+T15)) | V15: =IF(U15="","",U15/E15)
B16: AÇÃO 11 | E16: =D16*C16 -> 0 | H16: =IF($G16="","",VLOOKUP($G16,Cadastro!$B$5:$F$9,2,FALSE)) | I16: =IF($G16="","",VLOOKUP($G16,Cadastro!$B$5:$F$9,3,FALSE)) | J16: =IF(C16="","",(Cadastro!$F$12+Cadastro!$F$14)*'Operação Day Trade'!E16+'Operação Day Trade'!H16+I16*'Operação Day Trade'!E16+E16) | O16: =M16*N16 -> 0 | P16: =O16-(Cadastro!$F$12+Cadastro!$F$14)*O16 -> 0 | Q16: =IF(J16="","",P16-J16) | U16: =IF(Q16="","",(Q16-R16+S16+T16)) | V16: =IF(U16="","",U16/E16)
B17: AÇÃO 12 | E17: =D17*C17 -> 0 | H17: =IF($G17="","",VLOOKUP($G17,Cadastro!$B$5:$F$9,2,FALSE)) | I17: =IF($G17="","",VLOOKUP($G17,Cadastro!$B$5:$F$9,3,FALSE)) | J17: =IF(C17="","",(Cadastro!$F$12+Cadastro!$F$14)*'Operação Day Trade'!E17+'Operação Day Trade'!H17+I17*'Operação Day Trade'!E17+E17) | O17: =M17*N17 -> 0 | P17: =O17-(Cadastro!$F$12+Cadastro!$F$14)*O17 -> 0 | Q17: =IF(J17="","",P17-J17) | U17: =IF(Q17="","",(Q17-R17+S17+T17)) | V17: =IF(U17="","",U17/E17)
... B35: AÇÃO 30 | E35: =D35*C35 -> 0 | H35: =IF($G35="","",VLOOKUP($G35,Cadastro!$B$5:$F$9,2,FALSE)) | I35: =IF($G35="","",VLOOKUP($G35,Cadastro!$B$5:$F$9,3,FALSE)) | J35: =IF(C35="","",(Cadastro!$F$12+Cadastro!$F$14)*'Operação Day Trade'!E35+'Operação Day Trade'!H35+I35*'Operação Day Trade'!E35+E35) | O35: =M35*N35 -> 0 | P35: =O35-(Cadastro!$F$12+Cadastro!$F$14)*O35 -> 0 | Q35: =IF(J35="","",P35-J35) | U35: =IF(Q35="","",(Q35-R35+S35+T35)) | V35: =IF(U35="","",U35/E35)

Sheet Panorama
A1: CONTROLE DE AÇÕES - PANORAMA
