Workbook

Sheet Custos Fixos
A1: MSI&MCI Eletromecânica
A2: PLANILHA CUSTOS FIXOS
A4: Custos Fixos | B4: Projeção | C4: Mês 1 | D4: Mês 2 | E4: Mês 3 | F4: Mês 4 | G4: Mês 5 | H4: Mês 6 | I4: Mês 7 | J4: Mês 8 | K4: Mês 9 | L4: Mês 10 | M4: Mês 11 | N4: Mês 12 | O4: Média
A5: Aluguel | B5: 500
A6: Telefone celular (assinatura de pacote) | B6: 150
A7: Telefone fixo (assinatura de pacote) | B7: 100
A8: Material de expediente/limpeza | B8: 50
A9: Contador (escritório) | B9: 788
A10: Energia Elétrica | B10: 300
A11: Água | B11: 80
A12: Salários | B12: 3000
A13: Encargos previdenciários | B13: 950
A14: Provisão 13.° salário | B14: =B12/12 -> 250
A15: Provisão Férias | B15: =B12/12 -> 250
A16: Benefícios Sociais (creche, seguro etc) | B16: 300
A17: alimentação | B17: 360
A18: Manutenção de Máquinas/equipamentos | B18: 150
A19: Taxa de Condomínio | B19: 60
A20: Seguros | B20: 100
A21: Depreciação | B21: 50
A22: Prestação Veículo | B22: 981
A27: Total | B27: =SUM(B5:B26) -> 8419

Sheet Custos Variáveis
A1: ='Custos Fixos'!A1 -> MSI&MCI Eletromecânica
A2: PLANILHA CUSTOS VARIÁVEIS
A3: Custos Variáveis | B3: Projeção | C3: Mês 1 | D3: Mês 2 | E3: Mês 3 | F3: Mês 4 | G3: Mês 5 | H3: Mês 6 | I3: Mês 7 | J3: Mês 8 | K3: Mês 9 | L3: Mês 12
A5: pequenas peças de reposição | B5: 5
A6: Energia elétrica | B6: 1
A7: Mao-de-obra | B7: 30
A8: Combustível | B8: 6
A17: Total | B17: =SUM(B4:B16) -> 42

Sheet Ponto de Equilibrio
A1: ='Custos Fixos'!A1 -> MSI&MCI Eletromecânica
A2: PLANILHA CUSTOS FIXOS
A3: Preço de Visita | B3: 350
A4: Quantidade de manutenções realizadas | B4: Custos Fixos / Mês | C4: Custos Variáveis | D4: CT = CF + CV | E4: Receita de Vendas | F4: Resultado
A5: 0 | B5: ='Custos Fixos'!$B$27 -> 8419 | C5: ='Custos Variáveis'!$B$17*A5 -> 0 | D5: =B5+C5 -> 8419 | E5: =$B$3*A5 -> 0 | F5: =E5-D5 -> -8419 | G5: CF | H5: ='Custos Fixos'!B27 -> 8419 | I5: Custo Fixo
A6: 10 | B6: ='Custos Fixos'!$B$27 -> 8419 | C6: ='Custos Variáveis'!$B$17*A6 -> 420 | D6: =B6+C6 -> 8839 | E6: =$B$3*A6 -> 3500 | F6: =E6-D6 -> -5339 | G6: CV | H6: ='Custos Variáveis'!B17 -> 42 | I6: Custo Variável
A7: 20 | B7: ='Custos Fixos'!$B$27 -> 8419 | C7: ='Custos Variáveis'!$B$17*A7 -> 840 | D7: =B7+C7 -> 9259 | E7: =$B$3*A7 -> 7000 | F7: =E7-D7 -> -2259 | G7: PV | H7: =B3 -> 350 | I7: Preço de Venda
A8: 25 | B8: ='Custos Fixos'!$B$27 -> 8419 | C8: ='Custos Variáveis'!$B$17*A8 -> 1050 | D8: =B8+C8 -> 9469 | E8: =$B$3*A8 -> 8750 | F8: =E8-D8 -> -719 | G8: MgC | H8: =H7-H6 -> 308 | I8: Margem de Contribuição (lucro por visita)
A9: 27.33 | B9: ='Custos Fixos'!$B$27 -> 8419 | C9: ='Custos Variáveis'!$B$17*A9 -> 1147.86 | D9: =B9+C9 -> 9566.86 | E9: =$B$3*A9 -> 9565.5 | F9: =E9-D9 -> -1.36
A10: 30 | B10: ='Custos Fixos'!$B$27 -> 8419 | C10: ='Custos Variáveis'!$B$17*A10 -> 1260 | D10: =B10+C10 -> 9679 | E10: =$B$3*A10 -> 10500 | F10: =E10-D10 -> 821 | G10: PE | H10: =H5/H8 -> 27.334416 | I10: Ponto de Equilíbrio (quantas visitas devem ser realizadas para pagar as despesas)
A11: 35 | B11: ='Custos Fixos'!$B$27 -> 8419 | C11: ='Custos Variáveis'!$B$17*A11 -> 1470 | D11: =B11+C11 -> 9889 | E11: =$B$3*A11 -> 12250 | F11: =E11-D11 -> 2361
A12: 37.84 | B12: ='Custos Fixos'!$B$27 -> 8419 | C12: ='Custos Variáveis'!$B$17*A12 -> 1589.28 | D12: =B12+C12 -> 10008.28 | E12: =$B$3*A12 -> 13244 | F12: =E12-D12 -> 3235.72
A13: 56 | B13: ='Custos Fixos'!$B$27 -> 8419 | C13: ='Custos Variáveis'!$B$17*A13 -> 2352 | D13: =B13+C13 -> 10771 | E13: =$B$3*A13 -> 19600 | F13: =E13-D13 -> 8829
A14: 60 | B14: ='Custos Fixos'!$B$27 -> 8419 | C14: ='Custos Variáveis'!$B$17*A14 -> 2520 | D14: =B14+C14 -> 10939 | E14: =$B$3*A14 -> 21000 | F14: =E14-D14 -> 10061
A15: 70 | B15: ='Custos Fixos'!$B$27 -> 8419 | C15: ='Custos Variáveis'!$B$17*A15 -> 2940 | D15: =B15+C15 -> 11359 | E15: =$B$3*A15 -> 24500 | F15: =E15-D15 -> 13141
A16: 73 | B16: ='Custos Fixos'!$B$27 -> 8419 | C16: ='Custos Variáveis'!$B$17*A16 -> 3066 | D16: =B16+C16 -> 11485 | E16: =$B$3*A16 -> 25550 | F16: =E16-D16 -> 14065
A17: 80 | B17: ='Custos Fixos'!$B$27 -> 8419 | C17: ='Custos Variáveis'!$B$17*A17 -> 3360 | D17: =B17+C17 -> 11779 | E17: =$B$3*A17 -> 28000 | F17: =E17-D17 -> 16221
A18: 85 | B18: ='Custos Fixos'!$B$27 -> 8419 | C18: ='Custos Variáveis'!$B$17*A18 -> 3570 | D18: =B18+C18 -> 11989 | E18: =$B$3*A18 -> 29750 | F18: =E18-D18 -> 17761
A19: 90 | B19: ='Custos Fixos'!$B$27 -> 8419 | C19: ='Custos Variáveis'!$B$17*A19 -> 3780 | D19: =B19+C19 -> 12199 | E19: =$B$3*A19 -> 31500 | F19: =E19-D19 -> 19301
A20: 99 | B20: ='Custos Fixos'!$B$27 -> 8419 | C20: ='Custos Variáveis'!$B$17*A20 -> 4158 | D20: =B20+C20 -> 12577 | E20: =$B$3*A20 -> 34650 | F20: =E20-D20 -> 22073
A21: 100 | B21: ='Custos Fixos'!$B$27 -> 8419 | C21: ='Custos Variáveis'!$B$17*A21 -> 4200 | D21: =B21+C21 -> 12619 | E21: =$B$3*A21 -> 35000 | F21: =E21-D21 -> 22381
A22: 110 | B22: ='Custos Fixos'!$B$27 -> 8419 | C22: ='Custos Variáveis'!$B$17*A22 -> 4620 | D22: =B22+C22 -> 13039 | E22: =$B$3*A22 -> 38500 | F22: =E22-D22 -> 25461
... A31: 200 | B31: ='Custos Fixos'!$B$27 -> 8419 | C31: ='Custos Variáveis'!$B$17*A31 -> 8400 | D31: =B31+C31 -> 16819 | E31: =$B$3*A31 -> 70000 | F31: =E31-D31 -> 53181
