Workbook

Sheet folha de pagamento
A1: observação: preencher somente os campos em verde | C1: observação: preencher somente os campos em verde | G1: observação: preencher somente os campos em verde
D3: =D4+(D4/3) -> 4902.6667 | F3: =IF((D3-K8)>#REF!,((D3-K8)*#REF!)-#REF!,(IF((D3-K8)>=#REF!,((D3-K8)*#REF!)-#REF!,IF((D3-K8)>=#REF!,((D3-K8)*#REF!)-#REF!,IF(AND((D3-K8)>#REF!,(D3-K8)<=#REF!),((D3-K8)*#REF!)-#REF!,0))))) -> #REF! | G3: =IF(D3>'Tabela INSS salarios'!B5,'Tabela INSS salarios'!C5,(IF(D3>'Tabela INSS salarios'!B4,D3*'Tabela INSS salarios'!A5,(IF(D3>'Tabela INSS salarios'!B3,D3*'Tabela INSS salarios'!A4,D3*'Tabela INSS salarios'!A3))))) -> 1044.8
B4: Salário base do empregado | D4: 3677 | F4: Simples? | H4: <== escrever SIM se for optante pelo Simples, exceto Anexo IV
B6: ponto de vista do empregado | F6: ponto de vista da empresa
B7: salário líquido | C7: salario + beneficios | D7: salario + beneficios + férias/13o + resc. | F7: custo mensal sem férias/13o | G7: custo mensal com férias/13o | H7: custo mensal total com rescisão | I7: bases | K7: =IF((D4-K8)>#REF!,((D4-K8)*#REF!)-#REF!,(IF((D4-K8)>=#REF!,((D4-K8)*#REF!)-#REF!,IF((D4-K8)>=#REF!,((D4-K8)*#REF!)-#REF!,IF(AND((D4-K8)>#REF!,(D4-K8)<=#REF!),((D4-K8)*#REF!)-#REF!,0))))) -> #REF!
A8: totais | B8: =SUM(B10:B25) -> 2749.9604 | C8: =SUM(C10:C25) -> 4510.1204 | D8: =SUM(D10:D25) -> 5524.3916 | F8: =SUM(F10:F25) -> 5495.5563 | G8: =SUM(G10:G25) -> 6254.4803 | H8: =SUM(H10:H25) -> 6701.4401 | K8: =IF(D4>'Tabela INSS salarios'!B5,'Tabela INSS salarios'!C5,(IF(D4>'Tabela INSS salarios'!B4,D4*'Tabela INSS salarios'!A5,(IF(D4>'Tabela INSS salarios'!B3,D4*'Tabela INSS salarios'!A4,D4*'Tabela INSS salarios'!A3))))) -> 1044.8
A9: incremento sobre o salário base | B9: =B8/$D$4-1 -> -0.25211848 | C9: =C8/$D$4-1 -> 0.22657611 | D9: =D8/$D$4-1 -> 0.50241816 | F9: =F8/$D$4-1 -> 0.49457611 | G9: =G8/$D$4-1 -> 0.70097371 | H9: =H8/$D$4-1 -> 0.82252927
A10: salário bruto | B10: =D4 -> 3677 | C10: =B10 -> 3677 | D10: =B10 -> 3677 | F10: =C10 -> 3677 | G10: =D10 -> 3677 | H10: =G10 -> 3677
A11: férias | D11: =(D4/12)+((D4/12)/3) -> 408.55556 | G11: =D11 -> 408.55556 | H11: =G11 -> 408.55556 | I11: 1 salário + 1/3 do salário / 12 meses
A12: 13o salario | D12: =D4/12 -> 306.41667 | G12: =D12 -> 306.41667 | H12: =G12 -> 306.41667 | I12: 1 salário extra / 12 meses
A13: desconto IRRF | B13: =-MAX(0,(((D4+B14)*(LOOKUP(D4,'Tabela IRRF e INSS Pro-Labore'!$A$4:$A$8,'Tabela IRRF e INSS Pro-Labore'!$C$4:$C$8))-(LOOKUP(D4,'Tabela IRRF e INSS Pro-Labore'!A$4:$A$8,'Tabela IRRF e INSS Pro-Labore'!$D$4:$D$8))))) -> -140.69065 | C13: =B13 -> -140.69065 | D13: =-MAX(0,(((SUM(D10:D12)+D14)*(LOOKUP(SUM(D10:D12),'Tabela IRRF e INSS Pro-Labore'!$A$4:$A$8,'Tabela IRRF e INSS Pro-Labore'!$C$4:$C$8))-(LOOKUP(SUM(D10:D12),'Tabela IRRF e INSS Pro-Labore'!A$4:$A$8,'Tabela IRRF e INSS Pro-Labore'!$D$4:$D$8))))) -> -245.4531 | F13: =B13 -> -140.69065 | G13: =D13 -> -245.4531 | H13: =G13 -> -245.4531 | I13: ((salario base) - (INSS retido)) * tabela do IR
A14: desconto INSS | B14: =-'Tabela INSS salarios'!D8 -> -373.729 | C14: =B14 -> -373.729 | D14: =-'Tabela INSS salarios'!I8 -> -473.82511 | F14: =B14 -> -373.729 | G14: =D14 -> -473.82511 | H14: =G14 -> -473.82511 | I14: de 8% a 11% limitado ao teto máximo de 713,10
A15: vale refeição recebido/pago | C15: =J15*22 -> 660 | D15: =C15 -> 660 | F15: =D15 -> 660 | G15: =F15 -> 660 | H15: =G15 -> 660 | I15: indicar valor do vale refeição diário ao lado e em seguida a % de desconto | J15: 30 | K15: 0.2
A16: desconto vale-refeição | B16: =C16 -> -132 | C16: =-C15*K15 -> -132 | D16: =B16 -> -132 | F16: =D16 -> -132 | G16: =F16 -> -132 | H16: =G16 -> -132
A17: vale transporte recebido/pago | C17: =J17*22 -> 506 | D17: =C17 -> 506 | F17: =D17 -> 506 | G17: =F17 -> 506 | H17: =G17 -> 506 | I17: indicar ao lado o valor diário do vale-transporte desconto de 6% do salário | J17: 23
A18: desconto vale-transporte | B18: =-IF(D4*0.06>J17*22,J17*22,D4*0.06) -> -220.62 | C18: =B18 -> -220.62 | D18: =C18 -> -220.62 | F18: =D18 -> -220.62 | G18: =F18 -> -220.62 | H18: =G18 -> -220.62
A19: plano de saúde | C19: =J19 -> 300 | D19: =C19 -> 300 | F19: =D19 -> 300 | G19: =F19 -> 300 | H19: =G19 -> 300 | I19: indicar ao lado o valor total pago do plano de saúde e a porcentagem de desconto em folha | J19: 300 | K19: 0.2
A20: desconto plano de saúde | B20: =-(J19*K19) -> -60 | C20: =B20 -> -60 | D20: =C20 -> -60 | F20: =D20 -> -60 | G20: =F20 -> -60 | H20: =G20 -> -60
A21: outros | B21: =-J21*K21 -> 0 | C21: =J21-(J21*K21) -> 0 | D21: =C21 -> 0 | F21: =C21 -> 0 | G21: =C21 -> 0 | H21: =C21 -> 0 | I21: indicar ao lado o valor total e desconto | J21: 0 | K21: 0.1
A22: FGTS | C22: =C10*0.08 -> 294.16 | D22: =(D10+D11+D12)*0.08 -> 351.35778 | F22: =C22 -> 294.16 | G22: =D22 -> 351.35778 | H22: =G22 -> 351.35778 | I22: 8% sobre salários / férias / 13o salário
A23: INSS empregador | F23: =IF(G4="SIM",0,(D4*0.268)) -> 985.436 | G23: =F23+I26 -> 1177.0486 | H23: =G23 -> 1177.0486 | I23: =IF(G14="SIM","isento se Simples Nacional, exceto Anexo IV","20% de INSS mais 6,8% sistema SAT = 26,8%") -> 20% de INSS mais 6,8% sistema SAT = 26,8%
A24: aviso prévio indenizado | D24: =D4/12 -> 306.41667 | H24: =D24 -> 306.41667
A25: indenização rescisória em base mensal | D25: =D22*0.4 -> 140.54311 | H25: =H22*0.4 -> 140.54311 | I25: 40% sobre o valor depositado no FGTS
B26: =G26+H26 -> #REF! | C26: =IF(K8=J14,0,D26+F26) -> 174.13333 | D26: =G3/12 -> 87.066667 | F26: =K8/12 -> 87.066667 | G26: =F3/12 -> #REF! | H26: =K7/12 -> #REF! | I26: =IF(G4="SIM",0,(D11+D12)*0.268) -> 191.61256

Sheet pro-labore
A1: observação: preencher somente os campos em verde | C1: observação: preencher somente os campos em verde | G1: observação: preencher somente os campos em verde
A3: Calculo de impostos sobre Pro-Labores
A4: Nome do Sócio | D4: Valor | E4: Já recolhe o teto? | F4: Qtd Dependentes | G4: IRRF | H4: INSS Retido | I4: Valor Líquido
A5: Socio 1 | D5: 2000 | E5: sim | F5: 0 | G5: =MAX(0,(((D5-F5*'Tabela IRRF e INSS Pro-Labore'!$D$9)-H5)*(LOOKUP(D5,'Tabela IRRF e INSS Pro-Labore'!$A$4:$A$8,'Tabela IRRF e INSS Pro-Labore'!$C$4:$C$8))-(LOOKUP(D5,'Tabela IRRF e INSS Pro-Labore'!A$4:$A$8,'Tabela IRRF e INSS Pro-Labore'!$D$4:$D$8)))) -> 7.2 | H5: =IF(E5="sim",0,IF(D5>'Tabela IRRF e INSS Pro-Labore'!B13,'Tabela IRRF e INSS Pro-Labore'!B13*'Tabela IRRF e INSS Pro-Labore'!C13,D5*0.11)) -> 0 | I5: =D5-G5-H5 -> 1992.8
E6: não | F6: 0 | G6: =MAX(0,(((D6-F6*'Tabela IRRF e INSS Pro-Labore'!$D$9)-H6)*(LOOKUP(D6,'Tabela IRRF e INSS Pro-Labore'!$A$4:$A$8,'Tabela IRRF e INSS Pro-Labore'!$C$4:$C$8))-(LOOKUP(D6,'Tabela IRRF e INSS Pro-Labore'!A$4:$A$8,'Tabela IRRF e INSS Pro-Labore'!$D$4:$D$8)))) -> 0 | H6: =IF(E6="sim",0,IF(D6>'Tabela IRRF e INSS Pro-Labore'!B14,'Tabela IRRF e INSS Pro-Labore'!B14*'Tabela IRRF e INSS Pro-Labore'!C14,D6*0.11)) -> 0 | I6: =D6-G6-H6 -> 0
E7: não | F7: 0 | G7: =MAX(0,(((D7-F7*'Tabela IRRF e INSS Pro-Labore'!$D$9)-H7)*(LOOKUP(D7,'Tabela IRRF e INSS Pro-Labore'!$A$4:$A$8,'Tabela IRRF e INSS Pro-Labore'!$C$4:$C$8))-(LOOKUP(D7,'Tabela IRRF e INSS Pro-Labore'!A$4:$A$8,'Tabela IRRF e INSS Pro-Labore'!$D$4:$D$8)))) -> 0 | H7: =IF(E7="sim",0,IF(D7>'Tabela IRRF e INSS Pro-Labore'!B15,'Tabela IRRF e INSS Pro-Labore'!B15*'Tabela IRRF e INSS Pro-Labore'!C15,D7*0.11)) -> 0 | I7: =D7-G7-H7 -> 0
E8: não | F8: 0 | G8: =MAX(0,(((D8-F8*'Tabela IRRF e INSS Pro-Labore'!$D$9)-H8)*(LOOKUP(D8,'Tabela IRRF e INSS Pro-Labore'!$A$4:$A$8,'Tabela IRRF e INSS Pro-Labore'!$C$4:$C$8))-(LOOKUP(D8,'Tabela IRRF e INSS Pro-Labore'!A$4:$A$8,'Tabela IRRF e INSS Pro-Labore'!$D$4:$D$8)))) -> 0 | H8: =IF(E8="sim",0,IF(D8>'Tabela IRRF e INSS Pro-Labore'!B16,'Tabela IRRF e INSS Pro-Labore'!B16*'Tabela IRRF e INSS Pro-Labore'!C16,D8*0.11)) -> 0 | I8: =D8-G8-H8 -> 0
E9: não | F9: 0 | G9: =MAX(0,(((D9-F9*'Tabela IRRF e INSS Pro-Labore'!$D$9)-H9)*(LOOKUP(D9,'Tabela IRRF e INSS Pro-Labore'!$A$4:$A$8,'Tabela IRRF e INSS Pro-Labore'!$C$4:$C$8))-(LOOKUP(D9,'Tabela IRRF e INSS Pro-Labore'!A$4:$A$8,'Tabela IRRF e INSS Pro-Labore'!$D$4:$D$8)))) -> 0 | H9: =IF(E9="sim",0,IF(D9>'Tabela IRRF e INSS Pro-Labore'!B17,'Tabela IRRF e INSS Pro-Labore'!B17*'Tabela IRRF e INSS Pro-Labore'!C17,D9*0.11)) -> 0 | I9: =D9-G9-H9 -> 0
A10: Totais | D10: =SUM(D5:D9) -> 2000 | F10: =SUM(F5:F9) -> 0 | G10: =SUM(G5:G9) -> 7.2 | H10: =SUM(H5:H9) -> 0 | I10: =SUM(I5:I9) -> 1992.8

Sheet Tabela IRRF e INSS Pro-Labore
A2: TABELA IRRF atualizada até 10/01/2018
A3: De | B3: Até | C3: Aliquota | D3: Parcela a Deduzir
A4: 0 | B4: 1903.98 | C4: 0 | D4: 0
A5: 1903.99 | B5: 2826.65 | C5: 0.075 | D5: 142.8
A6: 2826.66 | B6: 3751.05 | C6: 0.15 | D6: 354.8
A7: 3751.06 | B7: 4664.68 | C7: 0.225 | D7: 636.13
A8: 4664.68 | B8: 99999999 | C8: 0.275 | D8: 869.36
A9: valor por dependente: | D9: 189.59
A11: INSS sobre Pro Labore
B12: Limite | C12: Aliquota
B13: 5839.45 | C13: 0.11

Sheet Tabela INSS salarios
A1: Tabela INSS
A2: Aliquota | B2: teto | C2: parcela | D2: resultado | F2: Aliquota | G2: teto | H2: parcela | I2: resultado
A3: 0.075 | B3: 1045 | D3: =IF($B$8<=B3,$B$8*A3,B3*A3) -> 78.375 | F3: 0.075 | G3: 1045 | I3: =IF($B$12<=G3,$B$12*F3,G3*F3) -> 78.375
A4: 0.09 | B4: 2089.6 | C4: =IF($B$8<B3,0,IF(($B$8-B3)>(B4-B3),B4-B3,$B$8-B3)) -> 1044.6 | D4: =C4*A4 -> 94.014 | F4: 0.09 | G4: 2089.6 | H4: =IF($B$12<G3,0,IF(($B$12-G3)>(G4-G3),G4-G3,$B$12-G3)) -> 1044.6 | I4: =H4*F4 -> 94.014
A5: 0.12 | B5: 3134.4 | C5: =IF($B$8<B4,0,IF(($B$8-B4)>(B5-B4),B5-B4,$B$8-B4)) -> 1044.8 | D5: =C5*A5 -> 125.376 | F5: 0.12 | G5: 3134.4 | H5: =IF($B$12<G4,0,IF(($B$12-G4)>(G5-G4),G5-G4,$B$12-G4)) -> 1044.8 | I5: =H5*F5 -> 125.376
A6: 0.14 | B6: 6101.06 | C6: =IF($B$8<B5,0,IF(($B$8-B5)>(B6-B5),B6-B5,$B$8-B5)) -> 542.6 | D6: =C6*A6 -> 75.964 | F6: 0.14 | G6: 6101.06 | H6: =IF($B$12<G5,0,IF(($B$12-G5)>(G6-G5),G6-G5,$B$12-G5)) -> 1257.5722 | I6: =H6*F6 -> 176.06011
A8: salario | B8: ='folha de pagamento'!D4 -> 3677 | C8: inss | D8: =SUM(D3:D6) -> 373.729 | H8: inss | I8: =SUM(I3:I6) -> 473.82511
A9: férias | B9: =B8/12 -> 306.41667
A10: adicional 1/3 | B10: =B9/3 -> 102.13889
A11: 13o salário | B11: =B8/12 -> 306.41667
A12: salario + férias + 13o | B12: =SUM(B8:B11) -> 4391.9722
