Workbook

Sheet Planilha1
A1: INSTRUÇÃO PARA UTILIZAÇÃO DE CUSTOS DOS COLABORADORES
A3: Passo 1 - Acesse a aba “ Benefícios” que está no rodapé desta planilha e preencha os campos que solicitam os nomes e cargos. Nessa mesma aba, relacione todos os beneficios de cada
A4: funcionário. Deixe os campos de beneficios que não são utilizados.
A6: Passo 2 - Acesse a aba “Resumo de folha de pagamento” e preencha os campos de numeros de dependentes e quantidade de faltas (em dias) de cada colaborador.
A8: Passo 3 - Na mesma aba, preencha os campos de Salário Bruto e Horas-Extra (em valor) de cada colaborador.
A10: Passo 4 - Com esses preenchimentos, a Folha de Pagamento estará preenchida para análise dos descontos de cada colaborador
A12: Passo 5 - Na aba “Custos da empresa” é possível analisar todas as relacões de descontos e proventos de cada colaborador. É possível saber o custo de cada um para a sua empresa. Os
A13: campos FGTS, Multa FGTS e 13. já estão com os dados calculados que devem ser pagos e previstos para cada mês do ano.
A15: Passo 6 - Acesse a aba “Tabelas” e verifique as tabelas de cálculo de INSS e IRPF. Também é possível ter os descontos na Folha de Pagamento do Vale Transporte, Vale-Refeição e Plano
A16: de Saúde. Esses descontos podem ser alterados de acordo com o acordo de sua empresa.
I19: SOFTEN SISTEMAS
I21: (17)3245 0866 / (11)3522 9234
I22: (21)4063 9103
I23: (31)4063 9272
I24: (61)4063 9165
I25: (41)4042 4979
I27: www.softensistemas.com.br
I28: contato@softensistemas.com.br
I30: https://www.facebook.com/softensistemas
I31: https://www.youtube.com/channel/UCc1HfhfQaHrxAOQ0x1maTaA
I32: https://blog.softensistemas.com.br/

Sheet Benefícios
A2: COLABORADORES | D2: BENEFÍCIOS
D4: Vale Transporte | E4: Vale-Refeição | F4: Plano de Saúde | G4: Seguro de Vida | H4: Outros Benefícios | J4: TOTAL
A5: NOME | B5: CARGO | D5: =SUM(D7:D31) -> 100 | E5: =SUM(E7:E31) -> 220 | F5: =SUM(F7:F31) -> 130 | G5: =SUM(G7:G31) -> 0 | H5: =SUM(H7:H31) -> 0 | J5: =SUM(D5:H5) -> 450
A7: Kléber Prado | B7: Vendedor interno | J7: =SUM(D7:H7) -> 0
A8: Tiago Oliveira | B8: Vendedor interno | J8: =SUM(D8:H8) -> 0
A9: Wanclave Pereira | B9: Gerente | D9: 100 | E9: 220 | F9: 130 | J9: =SUM(D9:H9) -> 450
A10: 4 | J10: =SUM(D10:H10) -> 0
A11: 5 | J11: =SUM(D11:H11) -> 0
A12: 6 | J12: =SUM(D12:H12) -> 0
A13: 7 | J13: =SUM(D13:H13) -> 0
A14: 8 | J14: =SUM(D14:H14) -> 0
A15: 9 | J15: =SUM(D15:H15) -> 0
A16: 10 | J16: =SUM(D16:H16) -> 0
A17: 11 | J17: =SUM(D17:H17) -> 0
A18: 12 | J18: =SUM(D18:H18) -> 0
A19: 13 | J19: =SUM(D19:H19) -> 0
A20: 14 | J20: =SUM(D20:H20) -> 0
A21: 15 | J21: =SUM(D21:H21) -> 0
... A36: 30 | J36: =SUM(D36:H36) -> 0

Sheet Resumo folha pagamento
A2: COLABORADORES | F2: FOLHA DE PAGAMENTO
F3: PROVENTOS | J3: DESCONTOS
F4: Salário Bruto | G4: Hora Extra | H4: TOTAL | J4: Faltas | K4: INSS | L4: IR | M4: Vtransp. | N4: Vrefeic | O4: Pl. Saude | P4: Sindic. | Q4: Outros | R4: TOTAL | T4: SALÁRIO LÍQUIDO
A5: NOME | B5: CARGO | C5: DEPEND. | D5: FALTAS | F5: =SUM(F7:F38) -> 5400 | G5: =SUM(G7:G38) -> 170 | H5: =SUM(H7:H38) -> 5570 | J5: =SUM(J7:J38) -> 0 | K5: =SUM(K7:K38) -> 538.6 | L5: =SUM(L7:L38) -> 64.125 | M5: =SUM(M7:M38) -> 100 | N5: =SUM(N7:N38) -> 22 | O5: =SUM(O7:O38) -> 104 | P5: =SUM(P7:P38) -> 0 | Q5: =SUM(Q7:Q38) -> 0 | R5: =SUM(R7:R38) -> 828.725 | T5: =SUM(T7:T38) -> 4741.275
A7: =Benefícios!A7 -> Kléber Prado | B7: =Benefícios!B7 -> Vendedor interno | F7: 1200 | G7: 10 | H7: =F7+G7 -> 1210 | J7: =F7/30*D7 -> 0 | K7: =IF((F7+G7-J7)*(VLOOKUP((F7+G7-J7),Tabelas!$B$4:$E$6,4,1))>Tabelas!$F$6,Tabelas!$F$6,(F7+G7-J7)*(VLOOKUP((F7+G7-J7),Tabelas!$B$4:$E$6,4,1))) -> 96.8 | L7: =((F7+G7-J7-K7)-(C7*Tabelas!$E$17))*(VLOOKUP((F7+G7-J7-K7)-(C7*Tabelas!$E$17),Tabelas!$B$12:$E$16,4,1))-VLOOKUP((F7+G7-J7-K7)-(C7*Tabelas!$E$17),Tabelas!$B$12:$F$16,5,1) -> 0 | M7: =IF(Benefícios!D7>0,F7*Tabelas!$D$23,0) -> 0 | N7: =Benefícios!E7*Tabelas!$D$24 -> 0 | O7: =Benefícios!F7*Tabelas!$D$25 -> 0 | P7: 0 | Q7: =Benefícios!H7 -> 0 | R7: =SUM(I7:Q7) -> 96.8 | T7: =H7-R7 -> 1113.2
A8: =Benefícios!A8 -> Tiago Oliveira | B8: =Benefícios!B8 -> Vendedor interno | C8: 1 | F8: 1200 | G8: 60 | H8: =F8+G8 -> 1260 | J8: =F8/30*D8 -> 0 | K8: =IF((F8+G8-J8)*(VLOOKUP((F8+G8-J8),Tabelas!$B$4:$E$6,4,1))>Tabelas!$F$6,Tabelas!$F$6,(F8+G8-J8)*(VLOOKUP((F8+G8-J8),Tabelas!$B$4:$E$6,4,1))) -> 100.8 | L8: =((F8+G8-J8-K8)-(C8*Tabelas!$E$17))*(VLOOKUP((F8+G8-J8-K8)-(C8*Tabelas!$E$17),Tabelas!$B$12:$E$16,4,1))-VLOOKUP((F8+G8-J8-K8)-(C8*Tabelas!$E$17),Tabelas!$B$12:$F$16,5,1) -> 0 | M8: =Benefícios!D8 -> 0 | N8: =Benefícios!E8*Tabelas!$D$24 -> 0 | O8: =Benefícios!F8*Tabelas!$D$25 -> 0 | P8: 0 | Q8: =Benefícios!H8 -> 0 | R8: =SUM(I8:Q8) -> 100.8 | T8: =H8-R8 -> 1159.2
A9: =Benefícios!A9 -> Wanclave Pereira | B9: =Benefícios!B9 -> Gerente | F9: 3000 | G9: 100 | H9: =F9+G9 -> 3100 | J9: =F9/30*D9 -> 0 | K9: =IF((F9+G9-J9)*(VLOOKUP((F9+G9-J9),Tabelas!$B$4:$E$6,4,1))>Tabelas!$F$6,Tabelas!$F$6,(F9+G9-J9)*(VLOOKUP((F9+G9-J9),Tabelas!$B$4:$E$6,4,1))) -> 341 | L9: =((F9+G9-J9-K9)-(C9*Tabelas!$E$17))*(VLOOKUP((F9+G9-J9-K9)-(C9*Tabelas!$E$17),Tabelas!$B$12:$E$16,4,1))-VLOOKUP((F9+G9-J9-K9)-(C9*Tabelas!$E$17),Tabelas!$B$12:$F$16,5,1) -> 64.125 | M9: =Benefícios!D9 -> 100 | N9: =Benefícios!E9*Tabelas!$D$24 -> 22 | O9: =Benefícios!F9*Tabelas!$D$25 -> 104 | P9: 0 | Q9: =Benefícios!H9 -> 0 | R9: =SUM(I9:Q9) -> 631.125 | T9: =H9-R9 -> 2468.875
A10: =Benefícios!A10 -> 4 | B10: =Benefícios!B10 -> 0 | H10: =F10+G10 -> 0 | J10: =F10/30*D10 -> 0 | K10: =IF((F10+G10-J10)*(VLOOKUP((F10+G10-J10),Tabelas!$B$4:$E$6,4,1))>Tabelas!$F$6,Tabelas!$F$6,(F10+G10-J10)*(VLOOKUP((F10+G10-J10),Tabelas!$B$4:$E$6,4,1))) -> 0 | L10: =((F10+G10-J10-K10)-(C10*Tabelas!$E$17))*(VLOOKUP((F10+G10-J10-K10)-(C10*Tabelas!$E$17),Tabelas!$B$12:$E$16,4,1))-VLOOKUP((F10+G10-J10-K10)-(C10*Tabelas!$E$17),Tabelas!$B$12:$F$16,5,1) -> 0 | M10: =Benefícios!D10 -> 0 | N10: =Benefícios!E10*Tabelas!$D$24 -> 0 | O10: =Benefícios!F10*Tabelas!$D$25 -> 0 | P10: 0 | Q10: =Benefícios!H10 -> 0 | R10: =SUM(I10:Q10) -> 0 | T10: =H10-R10 -> 0
A11: =Benefícios!A11 -> 5 | B11: =Benefícios!B11 -> 0 | H11: =F11+G11 -> 0 | J11: =F11/30*D11 -> 0 | K11: =IF((F11+G11-J11)*(VLOOKUP((F11+G11-J11),Tabelas!$B$4:$E$6,4,1))>Tabelas!$F$6,Tabelas!$F$6,(F11+G11-J11)*(VLOOKUP((F11+G11-J11),Tabelas!$B$4:$E$6,4,1))) -> 0 | L11: =((F11+G11-J11-K11)-(C11*Tabelas!$E$17))*(VLOOKUP((F11+G11-J11-K11)-(C11*Tabelas!$E$17),Tabelas!$B$12:$E$16,4,1))-VLOOKUP((F11+G11-J11-K11)-(C11*Tabelas!$E$17),Tabelas!$B$12:$F$16,5,1) -> 0 | M11: =Benefícios!D11 -> 0 | N11: =Benefícios!E11*Tabelas!$D$24 -> 0 | O11: =Benefícios!F11*Tabelas!$D$25 -> 0 | P11: 0 | Q11: =Benefícios!H11 -> 0 | R11: =SUM(I11:Q11) -> 0 | T11: =H11-R11 -> 0
A12: =Benefícios!A12 -> 6 | B12: =Benefícios!B12 -> 0 | H12: =F12+G12 -> 0 | J12: =F12/30*D12 -> 0 | K12: =IF((F12+G12-J12)*(VLOOKUP((F12+G12-J12),Tabelas!$B$4:$E$6,4,1))>Tabelas!$F$6,Tabelas!$F$6,(F12+G12-J12)*(VLOOKUP((F12+G12-J12),Tabelas!$B$4:$E$6,4,1))) -> 0 | L12: =((F12+G12-J12-K12)-(C12*Tabelas!$E$17))*(VLOOKUP((F12+G12-J12-K12)-(C12*Tabelas!$E$17),Tabelas!$B$12:$E$16,4,1))-VLOOKUP((F12+G12-J12-K12)-(C12*Tabelas!$E$17),Tabelas!$B$12:$F$16,5,1) -> 0 | M12: =Benefícios!D12 -> 0 | N12: =Benefícios!E12*Tabelas!$D$24 -> 0 | O12: =Benefícios!F12*Tabelas!$D$25 -> 0 | P12: 0 | Q12: =Benefícios!H12 -> 0 | R12: =SUM(I12:Q12) -> 0 | T12: =H12-R12 -> 0
A13: =Benefícios!A13 -> 7 | B13: =Benefícios!B13 -> 0 | H13: =F13+G13 -> 0 | J13: =F13/30*D13 -> 0 | K13: =IF((F13+G13-J13)*(VLOOKUP((F13+G13-J13),Tabelas!$B$4:$E$6,4,1))>Tabelas!$F$6,Tabelas!$F$6,(F13+G13-J13)*(VLOOKUP((F13+G13-J13),Tabelas!$B$4:$E$6,4,1))) -> 0 | L13: =((F13+G13-J13-K13)-(C13*Tabelas!$E$17))*(VLOOKUP((F13+G13-J13-K13)-(C13*Tabelas!$E$17),Tabelas!$B$12:$E$16,4,1))-VLOOKUP((F13+G13-J13-K13)-(C13*Tabelas!$E$17),Tabelas!$B$12:$F$16,5,1) -> 0 | M13: =Benefícios!D13 -> 0 | N13: =Benefícios!E13*Tabelas!$D$24 -> 0 | O13: =Benefícios!F13*Tabelas!$D$25 -> 0 | P13: 0 | Q13: =Benefícios!H13 -> 0 | R13: =SUM(I13:Q13) -> 0 | T13: =H13-R13 -> 0
A14: =Benefícios!A14 -> 8 | B14: =Benefícios!B14 -> 0 | H14: =F14+G14 -> 0 | J14: =F14/30*D14 -> 0 | K14: =IF((F14+G14-J14)*(VLOOKUP((F14+G14-J14),Tabelas!$B$4:$E$6,4,1))>Tabelas!$F$6,Tabelas!$F$6,(F14+G14-J14)*(VLOOKUP((F14+G14-J14),Tabelas!$B$4:$E$6,4,1))) -> 0 | L14: =((F14+G14-J14-K14)-(C14*Tabelas!$E$17))*(VLOOKUP((F14+G14-J14-K14)-(C14*Tabelas!$E$17),Tabelas!$B$12:$E$16,4,1))-VLOOKUP((F14+G14-J14-K14)-(C14*Tabelas!$E$17),Tabelas!$B$12:$F$16,5,1) -> 0 | M14: =Benefícios!D14 -> 0 | N14: =Benefícios!E14*Tabelas!$D$24 -> 0 | O14: =Benefícios!F14*Tabelas!$D$25 -> 0 | P14: 0 | Q14: =Benefícios!H14 -> 0 | R14: =SUM(I14:Q14) -> 0 | T14: =H14-R14 -> 0
A15: =Benefícios!A15 -> 9 | B15: =Benefícios!B15 -> 0 | H15: =F15+G15 -> 0 | J15: =F15/30*D15 -> 0 | K15: =IF((F15+G15-J15)*(VLOOKUP((F15+G15-J15),Tabelas!$B$4:$E$6,4,1))>Tabelas!$F$6,Tabelas!$F$6,(F15+G15-J15)*(VLOOKUP((F15+G15-J15),Tabelas!$B$4:$E$6,4,1))) -> 0 | L15: =((F15+G15-J15-K15)-(C15*Tabelas!$E$17))*(VLOOKUP((F15+G15-J15-K15)-(C15*Tabelas!$E$17),Tabelas!$B$12:$E$16,4,1))-VLOOKUP((F15+G15-J15-K15)-(C15*Tabelas!$E$17),Tabelas!$B$12:$F$16,5,1) -> 0 | M15: =Benefícios!D15 -> 0 | N15: =Benefícios!E15*Tabelas!$D$24 -> 0 | O15: =Benefícios!F15*Tabelas!$D$25 -> 0 | P15: 0 | Q15: =Benefícios!H15 -> 0 | R15: =SUM(I15:Q15) -> 0 | T15: =H15-R15 -> 0
A16: =Benefícios!A16 -> 10 | B16: =Benefícios!B16 -> 0 | H16: =F16+G16 -> 0 | J16: =F16/30*D16 -> 0 | K16: =IF((F16+G16-J16)*(VLOOKUP((F16+G16-J16),Tabelas!$B$4:$E$6,4,1))>Tabelas!$F$6,Tabelas!$F$6,(F16+G16-J16)*(VLOOKUP((F16+G16-J16),Tabelas!$B$4:$E$6,4,1))) -> 0 | L16: =((F16+G16-J16-K16)-(C16*Tabelas!$E$17))*(VLOOKUP((F16+G16-J16-K16)-(C16*Tabelas!$E$17),Tabelas!$B$12:$E$16,4,1))-VLOOKUP((F16+G16-J16-K16)-(C16*Tabelas!$E$17),Tabelas!$B$12:$F$16,5,1) -> 0 | M16: =Benefícios!D16 -> 0 | N16: =Benefícios!E16*Tabelas!$D$24 -> 0 | O16: =Benefícios!F16*Tabelas!$D$25 -> 0 | P16: 0 | Q16: =Benefícios!H16 -> 0 | R16: =SUM(I16:Q16) -> 0 | T16: =H16-R16 -> 0
A17: =Benefícios!A17 -> 11 | B17: =Benefícios!B17 -> 0 | H17: =F17+G17 -> 0 | J17: =F17/30*D17 -> 0 | K17: =IF((F17+G17-J17)*(VLOOKUP((F17+G17-J17),Tabelas!$B$4:$E$6,4,1))>Tabelas!$F$6,Tabelas!$F$6,(F17+G17-J17)*(VLOOKUP((F17+G17-J17),Tabelas!$B$4:$E$6,4,1))) -> 0 | L17: =((F17+G17-J17-K17)-(C17*Tabelas!$E$17))*(VLOOKUP((F17+G17-J17-K17)-(C17*Tabelas!$E$17),Tabelas!$B$12:$E$16,4,1))-VLOOKUP((F17+G17-J17-K17)-(C17*Tabelas!$E$17),Tabelas!$B$12:$F$16,5,1) -> 0 | M17: =Benefícios!D17 -> 0 | N17: =Benefícios!E17*Tabelas!$D$24 -> 0 | O17: =Benefícios!F17*Tabelas!$D$25 -> 0 | P17: 0 | Q17: =Benefícios!H17 -> 0 | R17: =SUM(I17:Q17) -> 0 | T17: =H17-R17 -> 0
A18: =Benefícios!A18 -> 12 | B18: =Benefícios!B18 -> 0 | H18: =F18+G18 -> 0 | J18: =F18/30*D18 -> 0 | K18: =IF((F18+G18-J18)*(VLOOKUP((F18+G18-J18),Tabelas!$B$4:$E$6,4,1))>Tabelas!$F$6,Tabelas!$F$6,(F18+G18-J18)*(VLOOKUP((F18+G18-J18),Tabelas!$B$4:$E$6,4,1))) -> 0 | L18: =((F18+G18-J18-K18)-(C18*Tabelas!$E$17))*(VLOOKUP((F18+G18-J18-K18)-(C18*Tabelas!$E$17),Tabelas!$B$12:$E$16,4,1))-VLOOKUP((F18+G18-J18-K18)-(C18*Tabelas!$E$17),Tabelas!$B$12:$F$16,5,1) -> 0 | M18: =Benefícios!D18 -> 0 | N18: =Benefícios!E18*Tabelas!$D$24 -> 0 | O18: =Benefícios!F18*Tabelas!$D$25 -> 0 | P18: 0 | Q18: =Benefícios!H18 -> 0 | R18: =SUM(I18:Q18) -> 0 | T18: =H18-R18 -> 0
A19: =Benefícios!A19 -> 13 | B19: =Benefícios!B19 -> 0 | H19: =F19+G19 -> 0 | J19: =F19/30*D19 -> 0 | K19: =IF((F19+G19-J19)*(VLOOKUP((F19+G19-J19),Tabelas!$B$4:$E$6,4,1))>Tabelas!$F$6,Tabelas!$F$6,(F19+G19-J19)*(VLOOKUP((F19+G19-J19),Tabelas!$B$4:$E$6,4,1))) -> 0 | L19: =((F19+G19-J19-K19)-(C19*Tabelas!$E$17))*(VLOOKUP((F19+G19-J19-K19)-(C19*Tabelas!$E$17),Tabelas!$B$12:$E$16,4,1))-VLOOKUP((F19+G19-J19-K19)-(C19*Tabelas!$E$17),Tabelas!$B$12:$F$16,5,1) -> 0 | M19: =Benefícios!D19 -> 0 | N19: =Benefícios!E19*Tabelas!$D$24 -> 0 | O19: =Benefícios!F19*Tabelas!$D$25 -> 0 | P19: 0 | Q19: =Benefícios!H19 -> 0 | R19: =SUM(I19:Q19) -> 0 | T19: =H19-R19 -> 0
A20: =Benefícios!A20 -> 14 | B20: =Benefícios!B20 -> 0 | H20: =F20+G20 -> 0 | J20: =F20/30*D20 -> 0 | K20: =IF((F20+G20-J20)*(VLOOKUP((F20+G20-J20),Tabelas!$B$4:$E$6,4,1))>Tabelas!$F$6,Tabelas!$F$6,(F20+G20-J20)*(VLOOKUP((F20+G20-J20),Tabelas!$B$4:$E$6,4,1))) -> 0 | L20: =((F20+G20-J20-K20)-(C20*Tabelas!$E$17))*(VLOOKUP((F20+G20-J20-K20)-(C20*Tabelas!$E$17),Tabelas!$B$12:$E$16,4,1))-VLOOKUP((F20+G20-J20-K20)-(C20*Tabelas!$E$17),Tabelas!$B$12:$F$16,5,1) -> 0 | M20: =Benefícios!D20 -> 0 | N20: =Benefícios!E20*Tabelas!$D$24 -> 0 | O20: =Benefícios!F20*Tabelas!$D$25 -> 0 | P20: 0 | Q20: =Benefícios!H20 -> 0 | R20: =SUM(I20:Q20) -> 0 | T20: =H20-R20 -> 0
A21: =Benefícios!A21 -> 15 | B21: =Benefícios!B21 -> 0 | H21: =F21+G21 -> 0 | J21: =F21/30*D21 -> 0 | K21: =IF((F21+G21-J21)*(VLOOKUP((F21+G21-J21),Tabelas!$B$4:$E$6,4,1))>Tabelas!$F$6,Tabelas!$F$6,(F21+G21-J21)*(VLOOKUP((F21+G21-J21),Tabelas!$B$4:$E$6,4,1))) -> 0 | L21: =((F21+G21-J21-K21)-(C21*Tabelas!$E$17))*(VLOOKUP((F21+G21-J21-K21)-(C21*Tabelas!$E$17),Tabelas!$B$12:$E$16,4,1))-VLOOKUP((F21+G21-J21-K21)-(C21*Tabelas!$E$17),Tabelas!$B$12:$F$16,5,1) -> 0 | M21: =Benefícios!D21 -> 0 | N21: =Benefícios!E21*Tabelas!$D$24 -> 0 | O21: =Benefícios!F21*Tabelas!$D$25 -> 0 | P21: 0 | Q21: =Benefícios!H21 -> 0 | R21: =SUM(I21:Q21) -> 0 | T21: =H21-R21 -> 0
... A36: =Benefícios!A36 -> 30 | B36: =Benefícios!B36 -> 0 | H36: =F36+G36 -> 0 | J36: =F36/30*D36 -> 0 | K36: =IF((F36+G36-J36)*(VLOOKUP((F36+G36-J36),Tabelas!$B$4:$E$6,4,1))>Tabelas!$F$6,Tabelas!$F$6,(F36+G36-J36)*(VLOOKUP((F36+G36-J36),Tabelas!$B$4:$E$6,4,1))) -> 0 | L36: =((F36+G36-J36-K36)-(C36*Tabelas!$E$17))*(VLOOKUP((F36+G36-J36-K36)-(C36*Tabelas!$E$17),Tabelas!$B$12:$E$16,4,1))-VLOOKUP((F36+G36-J36-K36)-(C36*Tabelas!$E$17),Tabelas!$B$12:$F$16,5,1) -> 0 | M36: =Benefícios!D36 -> 0 | N36: =Benefícios!E36*Tabelas!$D$24 -> 0 | O36: =Benefícios!F36*Tabelas!$D$25 -> 0 | P36: 0 | Q36: =Benefícios!H36 -> 0 | R36: =SUM(I36:Q36) -> 0 | T36: =H36-R36 -> 0

Sheet Custo empresa
A2: COLABORADORES | F2: CUSTOS DA EMPRESA
F3: Salário | G3: Horas | H3: Vale | I3: Vale | J3: Plano de | K3: Seguro | L3: Outros | M3: FGTS | N3: Multa | O3: 13. | P3: Férias | Q3: FGTS 13. | S3: TOTAL
F4: Bruto | G4: Extras | H4: Transporte | I4: Refeição | J4: Saúde | K4: de Vida | L4: Benefícios | N4: FGTS | Q4: e Férias
A5: NOME | B5: CARGO | C5: DEPEND. | D5: FALTAS | F5: =SUM(F7:F36) -> 5400 | G5: =SUM(G7:G36) -> 170 | H5: =SUM(H7:H36) -> 0 | I5: =SUM(I7:I36) -> 198 | J5: =SUM(J7:J36) -> 26 | K5: =SUM(K7:K36) -> 0 | L5: =SUM(L7:L36) -> 0 | M5: =SUM(M7:M36) -> 445.6 | ... Q5: =SUM(Q7:Q36) -> 84 | S5: =SUM(S7:S36) -> 7596.4
A7: ='Resumo folha pagamento'!A7 -> Kléber Prado | B7: =Benefícios!B7 -> Vendedor interno | C7: ='Resumo folha pagamento'!C7 -> 0 | D7: ='Resumo folha pagamento'!D7 -> 0 | F7: ='Resumo folha pagamento'!F7 -> 1200 | G7: ='Resumo folha pagamento'!G7 -> 10 | H7: =Benefícios!D7-'Resumo folha pagamento'!M7 -> 0 | I7: =Benefícios!E7-'Resumo folha pagamento'!N7 -> 0 | J7: =Benefícios!F7-'Resumo folha pagamento'!O7 -> 0 | K7: =Benefícios!G7 -> 0 | L7: =Benefícios!H7 -> 0 | M7: =(F7+G7)*0.08 -> 96.8 | N7: =M7*0.5 -> 48.4 | O7: =F7/12 -> 100 | P7: =(F7+(F7/3))/12 -> 133.33333 | Q7: =(O7+P7)*0.08 -> 18.666667 | S7: =SUM(F7:Q7) -> 1607.2
A8: ='Resumo folha pagamento'!A8 -> Tiago Oliveira | B8: =Benefícios!B8 -> Vendedor interno | C8: ='Resumo folha pagamento'!C8 -> 1 | D8: ='Resumo folha pagamento'!D8 -> 0 | F8: ='Resumo folha pagamento'!F8 -> 1200 | G8: ='Resumo folha pagamento'!G8 -> 60 | H8: =Benefícios!D8-'Resumo folha pagamento'!M8 -> 0 | I8: =Benefícios!E8-'Resumo folha pagamento'!N8 -> 0 | J8: =Benefícios!F8-'Resumo folha pagamento'!O8 -> 0 | K8: =Benefícios!G8 -> 0 | L8: =Benefícios!H8 -> 0 | M8: =(F8+G8)*0.08 -> 100.8 | N8: =M8*0.5 -> 50.4 | O8: =F8/12 -> 100 | P8: =(F8+(F8/3))/12 -> 133.33333 | Q8: =(O8+P8)*0.08 -> 18.666667 | S8: =SUM(F8:Q8) -> 1663.2
A9: ='Resumo folha pagamento'!A9 -> Wanclave Pereira | B9: =Benefícios!B9 -> Gerente | C9: ='Resumo folha pagamento'!C9 -> 0 | D9: ='Resumo folha pagamento'!D9 -> 0 | F9: ='Resumo folha pagamento'!F9 -> 3000 | G9: ='Resumo folha pagamento'!G9 -> 100 | H9: =Benefícios!D9-'Resumo folha pagamento'!M9 -> 0 | I9: =Benefícios!E9-'Resumo folha pagamento'!N9 -> 198 | J9: =Benefícios!F9-'Resumo folha pagamento'!O9 -> 26 | K9: =Benefícios!G9 -> 0 | L9: =Benefícios!H9 -> 0 | M9: =(F9+G9)*0.08 -> 248 | N9: =M9*0.5 -> 124 | O9: =F9/12 -> 250 | P9: =(F9+(F9/3))/12 -> 333.33333 | Q9: =(O9+P9)*0.08 -> 46.666667 | S9: =SUM(F9:Q9) -> 4326
A10: ='Resumo folha pagamento'!A10 -> 4 | B10: =Benefícios!B10 -> 0 | C10: ='Resumo folha pagamento'!C10 -> 0 | D10: ='Resumo folha pagamento'!D10 -> 0 | F10: ='Resumo folha pagamento'!F10 -> 0 | G10: ='Resumo folha pagamento'!G10 -> 0 | H10: =Benefícios!D10-'Resumo folha pagamento'!M10 -> 0 | I10: =Benefícios!E10-'Resumo folha pagamento'!N10 -> 0 | J10: =Benefícios!F10-'Resumo folha pagamento'!O10 -> 0 | K10: =Benefícios!G10 -> 0 | L10: =Benefícios!H10 -> 0 | M10: =(F10+G10)*0.08 -> 0 | N10: =M10*0.5 -> 0 | O10: =F10/12 -> 0 | P10: =(F10+(F10/3))/12 -> 0 | Q10: =(O10+P10)*0.08 -> 0 | S10: =SUM(F10:Q10) -> 0
A11: ='Resumo folha pagamento'!A11 -> 5 | B11: =Benefícios!B11 -> 0 | C11: ='Resumo folha pagamento'!C11 -> 0 | D11: ='Resumo folha pagamento'!D11 -> 0 | F11: ='Resumo folha pagamento'!F11 -> 0 | G11: ='Resumo folha pagamento'!G11 -> 0 | H11: =Benefícios!D11-'Resumo folha pagamento'!M11 -> 0 | I11: =Benefícios!E11-'Resumo folha pagamento'!N11 -> 0 | J11: =Benefícios!F11-'Resumo folha pagamento'!O11 -> 0 | K11: =Benefícios!G11 -> 0 | L11: =Benefícios!H11 -> 0 | M11: =(F11+G11)*0.08 -> 0 | N11: =M11*0.5 -> 0 | O11: =F11/12 -> 0 | P11: =(F11+(F11/3))/12 -> 0 | Q11: =(O11+P11)*0.08 -> 0 | S11: =SUM(F11:Q11) -> 0
A12: ='Resumo folha pagamento'!A12 -> 6 | B12: =Benefícios!B12 -> 0 | C12: ='Resumo folha pagamento'!C12 -> 0 | D12: ='Resumo folha pagamento'!D12 -> 0 | F12: ='Resumo folha pagamento'!F12 -> 0 | G12: ='Resumo folha pagamento'!G12 -> 0 | H12: =Benefícios!D12-'Resumo folha pagamento'!M12 -> 0 | I12: =Benefícios!E12-'Resumo folha pagamento'!N12 -> 0 | J12: =Benefícios!F12-'Resumo folha pagamento'!O12 -> 0 | K12: =Benefícios!G12 -> 0 | L12: =Benefícios!H12 -> 0 | M12: =(F12+G12)*0.08 -> 0 | N12: =M12*0.5 -> 0 | O12: =F12/12 -> 0 | P12: =(F12+(F12/3))/12 -> 0 | Q12: =(O12+P12)*0.08 -> 0 | S12: =SUM(F12:Q12) -> 0
A13: ='Resumo folha pagamento'!A13 -> 7 | B13: =Benefícios!B13 -> 0 | C13: ='Resumo folha pagamento'!C13 -> 0 | D13: ='Resumo folha pagamento'!D13 -> 0 | F13: ='Resumo folha pagamento'!F13 -> 0 | G13: ='Resumo folha pagamento'!G13 -> 0 | H13: =Benefícios!D13-'Resumo folha pagamento'!M13 -> 0 | I13: =Benefícios!E13-'Resumo folha pagamento'!N13 -> 0 | J13: =Benefícios!F13-'Resumo folha pagamento'!O13 -> 0 | K13: =Benefícios!G13 -> 0 | L13: =Benefícios!H13 -> 0 | M13: =(F13+G13)*0.08 -> 0 | N13: =M13*0.5 -> 0 | O13: =F13/12 -> 0 | P13: =(F13+(F13/3))/12 -> 0 | Q13: =(O13+P13)*0.08 -> 0 | S13: =SUM(F13:Q13) -> 0
A14: ='Resumo folha pagamento'!A14 -> 8 | B14: =Benefícios!B14 -> 0 | C14: ='Resumo folha pagamento'!C14 -> 0 | D14: ='Resumo folha pagamento'!D14 -> 0 | F14: ='Resumo folha pagamento'!F14 -> 0 | G14: ='Resumo folha pagamento'!G14 -> 0 | H14: =Benefícios!D14-'Resumo folha pagamento'!M14 -> 0 | I14: =Benefícios!E14-'Resumo folha pagamento'!N14 -> 0 | J14: =Benefícios!F14-'Resumo folha pagamento'!O14 -> 0 | K14: =Benefícios!G14 -> 0 | L14: =Benefícios!H14 -> 0 | M14: =(F14+G14)*0.08 -> 0 | N14: =M14*0.5 -> 0 | O14: =F14/12 -> 0 | P14: =(F14+(F14/3))/12 -> 0 | Q14: =(O14+P14)*0.08 -> 0 | S14: =SUM(F14:Q14) -> 0
A15: ='Resumo folha pagamento'!A15 -> 9 | B15: =Benefícios!B15 -> 0 | C15: ='Resumo folha pagamento'!C15 -> 0 | D15: ='Resumo folha pagamento'!D15 -> 0 | F15: ='Resumo folha pagamento'!F15 -> 0 | G15: ='Resumo folha pagamento'!G15 -> 0 | H15: =Benefícios!D15-'Resumo folha pagamento'!M15 -> 0 | I15: =Benefícios!E15-'Resumo folha pagamento'!N15 -> 0 | J15: =Benefícios!F15-'Resumo folha pagamento'!O15 -> 0 | K15: =Benefícios!G15 -> 0 | L15: =Benefícios!H15 -> 0 | M15: =(F15+G15)*0.08 -> 0 | N15: =M15*0.5 -> 0 | O15: =F15/12 -> 0 | P15: =(F15+(F15/3))/12 -> 0 | Q15: =(O15+P15)*0.08 -> 0 | S15: =SUM(F15:Q15) -> 0
A16: ='Resumo folha pagamento'!A16 -> 10 | B16: =Benefícios!B16 -> 0 | C16: ='Resumo folha pagamento'!C16 -> 0 | D16: ='Resumo folha pagamento'!D16 -> 0 | F16: ='Resumo folha pagamento'!F16 -> 0 | G16: ='Resumo folha pagamento'!G16 -> 0 | H16: =Benefícios!D16-'Resumo folha pagamento'!M16 -> 0 | I16: =Benefícios!E16-'Resumo folha pagamento'!N16 -> 0 | J16: =Benefícios!F16-'Resumo folha pagamento'!O16 -> 0 | K16: =Benefícios!G16 -> 0 | L16: =Benefícios!H16 -> 0 | M16: =(F16+G16)*0.08 -> 0 | N16: =M16*0.5 -> 0 | O16: =F16/12 -> 0 | P16: =(F16+(F16/3))/12 -> 0 | Q16: =(O16+P16)*0.08 -> 0 | S16: =SUM(F16:Q16) -> 0
A17: ='Resumo folha pagamento'!A17 -> 11 | B17: =Benefícios!B17 -> 0 | C17: ='Resumo folha pagamento'!C17 -> 0 | D17: ='Resumo folha pagamento'!D17 -> 0 | F17: ='Resumo folha pagamento'!F17 -> 0 | G17: ='Resumo folha pagamento'!G17 -> 0 | H17: =Benefícios!D17-'Resumo folha pagamento'!M17 -> 0 | I17: =Benefícios!E17-'Resumo folha pagamento'!N17 -> 0 | J17: =Benefícios!F17-'Resumo folha pagamento'!O17 -> 0 | K17: =Benefícios!G17 -> 0 | L17: =Benefícios!H17 -> 0 | M17: =(F17+G17)*0.08 -> 0 | N17: =M17*0.5 -> 0 | O17: =F17/12 -> 0 | P17: =(F17+(F17/3))/12 -> 0 | Q17: =(O17+P17)*0.08 -> 0 | S17: =SUM(F17:Q17) -> 0
A18: ='Resumo folha pagamento'!A18 -> 12 | B18: =Benefícios!B18 -> 0 | C18: ='Resumo folha pagamento'!C18 -> 0 | D18: ='Resumo folha pagamento'!D18 -> 0 | F18: ='Resumo folha pagamento'!F18 -> 0 | G18: ='Resumo folha pagamento'!G18 -> 0 | H18: =Benefícios!D18-'Resumo folha pagamento'!M18 -> 0 | I18: =Benefícios!E18-'Resumo folha pagamento'!N18 -> 0 | J18: =Benefícios!F18-'Resumo folha pagamento'!O18 -> 0 | K18: =Benefícios!G18 -> 0 | L18: =Benefícios!H18 -> 0 | M18: =(F18+G18)*0.08 -> 0 | N18: =M18*0.5 -> 0 | O18: =F18/12 -> 0 | P18: =(F18+(F18/3))/12 -> 0 | Q18: =(O18+P18)*0.08 -> 0 | S18: =SUM(F18:Q18) -> 0
... A36: ='Resumo folha pagamento'!A36 -> 30 | B36: =Benefícios!B36 -> 0 | C36: ='Resumo folha pagamento'!C36 -> 0 | D36: ='Resumo folha pagamento'!D36 -> 0 | F36: ='Resumo folha pagamento'!F36 -> 0 | G36: ='Resumo folha pagamento'!G36 -> 0 | H36: =Benefícios!D36-'Resumo folha pagamento'!M36 -> 0 | I36: =Benefícios!E36-'Resumo folha pagamento'!N36 -> 0 | J36: =Benefícios!F36-'Resumo folha pagamento'!O36 -> 0 | K36: =Benefícios!G36 -> 0 | L36: =Benefícios!H36 -> 0 | M36: =(F36+G36)*0.08 -> 0 | N36: =M36*0.5 -> 0 | O36: =F36/12 -> 0 | P36: =(F36+(F36/3))/12 -> 0 | Q36: =(O36+P36)*0.08 -> 0 | S36: =SUM(F36:Q36) -> 0

Sheet Tabelas
B2: TABELA DE CÁCULO DE INSS
B4: 0 | C4: à | D4: 1659.38 | E4: 0.08
B5: 1659.39 | C5: à | D5: 2765.66 | E5: 0.09
B6: 2765.67 | C6: à | D6: 5531.31 | E6: 0.11 | F6: 50000
B10: TABELA DE IRPF 2017
B12: 0 | C12: à | D12: 1903.98 | E12: 0 | F12: 0
B13: 1903.99 | C13: à | D13: 2826.65 | E13: 0.075 | F13: 142.8
B14: 2826.66 | C14: à | D14: 3751.05 | E14: 0.15 | F14: 354.8
B15: 3751.06 | C15: à | D15: 4664.68 | E15: 0.225 | F15: 636.13
B16: 4664.68 | C16: à | D16: 100000 | E16: 0.275 | F16: 869.36
B17: Dedução por dependente | E17: 189.59
C21: TABELA DE DESCONTOS
C23: Vale Transporte | D23: 0.06
C24: Vale-Refeição | D24: 0.1
C25: Plano de Saúde | D25: 0.8
