Workbook
Name CANAIS: [1]Registros!$D$4:$D$13
Name CLIENTES: [1]Registros!$D$16:$D$1048576
Name FORMASPGTO: [1]Registros!$G$4:$G$11
Name MESES: [1]Registros!$I$15:$I$26
Name PRODUTOS: [1]Registros!$A$4:$A$500

Sheet Início
A1: FOLHA DE PAGAMENTO - INÍCIO

Sheet Tabulação
A1: FOLHA DE PAGAMENTO - TABULAÇÃO
A3: MÊS | B3: DATAINICIO | C3: DATAFIM | D3: FERIADOS/RECESSO | J3: DIAS ÚTEIS
C4: =B4+30 -> 30 | J4: =NETWORKDAYS(B4,C4,D4:I4) -> 21
C5: =B5+27 -> 27 | J5: =NETWORKDAYS(B5,C5,D5:I5) -> 20
C6: =B6+30 -> 30 | J6: =NETWORKDAYS(B6,C6,D6:I6) -> 21
C7: =B7+29 -> 29 | J7: =NETWORKDAYS(B7,C7,D7:I7) -> 20
C8: =B8+30 -> 30 | J8: =NETWORKDAYS(B8,C8,D8:I8) -> 21
C9: =B9+29 -> 29 | J9: =NETWORKDAYS(B9,C9,D9:I9) -> 20
C10: =B10+30 -> 30 | J10: =NETWORKDAYS(B10,C10,D10:I10) -> 21
C11: =B11+30 -> 30 | J11: =NETWORKDAYS(B11,C11,D11:I11) -> 21
C12: =B12+29 -> 29 | J12: =NETWORKDAYS(B12,C12,D12:I12) -> 20
C13: =B13+30 -> 30 | J13: =NETWORKDAYS(B13,C13,D13:I13) -> 21
C14: =B14+29 -> 29 | J14: =NETWORKDAYS(B14,C14,D14:I14) -> 20
C15: =B15+30 -> 30 | J15: =NETWORKDAYS(B15,C15,D15:I15) -> 21
C18: PREÇO DA PASSAGEM: | D18: 2.1
A19: FUNCIONÁRIO | B19: CARGO/FUNÇÃO | C19: FORMAÇÃO | D19: QUANTIDADE DE VIAGENS | E19: AUXILIO TRANSPORTE/DIA | G19: TABELA IR | J19: PARCELA A DESCONTAR
E20: =$D$18*D20 -> 0 | G20: 0 | H20: 1787.77 | I20: 0 | J20: 0
E21: =$D$18*D21 -> 0 | G21: 1787.78 | H21: 2679.29 | I21: 0.075 | J21: 134.08
E22: =$D$18*D22 -> 0 | G22: 2679.3 | H22: 3572.43 | I22: 0.15 | J22: 335.03
E23: =$D$18*D23 -> 0 | G23: 3572.44 | H23: 4463.81 | I23: 0.225 | J23: 602.96
E24: =$D$18*D24 -> 0 | G24: 4463.82 | H24: Acima | I24: 0.275 | J24: 826.15
E25: =$D$18*D25 -> 0 | G25: TABELAS INSS
E26: =$D$18*D26 -> 0 | G26: R$- | H26: 1317.07 | I26: 0.08
E27: =$D$18*D27 -> 0 | G27: 1317.08 | H27: 2195.12 | I27: 0.09
E28: =$D$18*D28 -> 0 | G28: 2195.13 | H28: 4390.24 | I28: 0.11
E29: =$D$18*D29 -> 0 | G29: 4390.24 | H29: Acima | I29: =G29*I28 -> 482.9264
E30: =$D$18*D30 -> 0 | G30: ENCARGOS
E31: =$D$18*D31 -> 0 | G31: INSS Empresa | H31: 0.258
E32: =$D$18*D32 -> 0 | G32: SAT | H32: 0.02
E33: =$D$18*D33 -> 0 | G33: FGTS | H33: 0.08
E34: =$D$18*D34 -> 0
E35: =$D$18*D35 -> 0
E36: =$D$18*D36 -> 0
E37: =$D$18*D37 -> 0
E38: =$D$18*D38 -> 0
E39: =$D$18*D39 -> 0
E40: =$D$18*D40 -> 0
E41: =$D$18*D41 -> 0
E42: =$D$18*D42 -> 0
E43: =$D$18*D43 -> 0
E44: =$D$18*D44 -> 0
E45: =$D$18*D45 -> 0
... E50: =$D$18*D50 -> 0

Sheet Pagamentos
A1: FOLHA DE PAGAMENTO - PAGAMENTOS
A3: FUNCIONÁRIO | B3: CARGO/FUNÇÃO | C3: JANEIRO | D3: FEVEREIRO | E3: MARÇO | F3: ABRIL | G3: MAIO | H3: JUNHO | I3: JULHO | J3: AGOSTO | K3: SETEMBRO | L3: OUTUBRO | M3: NOVEMBRO | N3: DEZEMBRO | O3: 13º | P3: TOTAL
C4: =COLUMN(C3)-1 -> 2 | D4: =COLUMN(D3)-1 -> 3 | E4: =COLUMN(E3)-1 -> 4 | F4: =COLUMN(F3)-1 -> 5 | G4: =COLUMN(G3)-1 -> 6 | H4: =COLUMN(H3)-1 -> 7 | I4: =COLUMN(I3)-1 -> 8 | J4: =COLUMN(J3)-1 -> 9 | ... P4: =COLUMN(P3)-1 -> 15
A5: SALÁRIO BRUTO | C5: SALÁRIO BRUTO
A6: =IF($A40="","",$A40) | B6: =IF($B40="","",$B40) | C6: =C40+C74 -> 0 | D6: =D40+D74 -> 0 | E6: =E40+E74 -> 0 | F6: =F40+F74 -> 0 | G6: =G40+G74 -> 0 | H6: =H40+H74 -> 0 | I6: =I40+I74 -> 0 | J6: =J40+J74 -> 0 | ... N6: =N40+N74 -> 0 | O6: =IF(COUNTIF(C40:N40,">0")>0,(SUM(C40:N40)+SUM(C74:N74))/COUNTIF(C40:N40,">0"),0) -> 0 | P6: =SUM(C6:N6) -> 0
A7: =IF($A41="","",$A41) | B7: =IF($B41="","",$B41) | C7: =C41+C75 -> 0 | D7: =D41+D75 -> 0 | E7: =E41+E75 -> 0 | F7: =F41+F75 -> 0 | G7: =G41+G75 -> 0 | H7: =H41+H75 -> 0 | I7: =I41+I75 -> 0 | J7: =J41+J75 -> 0 | ... N7: =N41+N75 -> 0 | O7: =IF(COUNTIF(C41:N41,">0")>0,(SUM(C41:N41)+SUM(C75:N75))/COUNTIF(C41:N41,">0"),0) -> 0 | P7: =SUM(C7:N7) -> 0
A8: =IF($A42="","",$A42) | B8: =IF($B42="","",$B42) | C8: =C42+C76 -> 0 | D8: =D42+D76 -> 0 | E8: =E42+E76 -> 0 | F8: =F42+F76 -> 0 | G8: =G42+G76 -> 0 | H8: =H42+H76 -> 0 | I8: =I42+I76 -> 0 | J8: =J42+J76 -> 0 | ... N8: =N42+N76 -> 0 | O8: =IF(COUNTIF(C42:N42,">0")>0,(SUM(C42:N42)+SUM(C76:N76))/COUNTIF(C42:N42,">0"),0) -> 0 | P8: =SUM(C8:N8) -> 0
A9: =IF($A43="","",$A43) | B9: =IF($B43="","",$B43) | C9: =C43+C77 -> 0 | D9: =D43+D77 -> 0 | E9: =E43+E77 -> 0 | F9: =F43+F77 -> 0 | G9: =G43+G77 -> 0 | H9: =H43+H77 -> 0 | I9: =I43+I77 -> 0 | J9: =J43+J77 -> 0 | ... N9: =N43+N77 -> 0 | O9: =IF(COUNTIF(C43:N43,">0")>0,(SUM(C43:N43)+SUM(C77:N77))/COUNTIF(C43:N43,">0"),0) -> 0 | P9: =SUM(C9:N9) -> 0
A10: =IF($A44="","",$A44) | B10: =IF($B44="","",$B44) | C10: =C44+C78 -> 0 | D10: =D44+D78 -> 0 | E10: =E44+E78 -> 0 | F10: =F44+F78 -> 0 | G10: =G44+G78 -> 0 | H10: =H44+H78 -> 0 | I10: =I44+I78 -> 0 | J10: =J44+J78 -> 0 | ... N10: =N44+N78 -> 0 | O10: =IF(COUNTIF(C44:N44,">0")>0,(SUM(C44:N44)+SUM(C78:N78))/COUNTIF(C44:N44,">0"),0) -> 0 | P10: =SUM(C10:N10) -> 0
A11: =IF($A45="","",$A45) | B11: =IF($B45="","",$B45) | C11: =C45+C79 -> 0 | D11: =D45+D79 -> 0 | E11: =E45+E79 -> 0 | F11: =F45+F79 -> 0 | G11: =G45+G79 -> 0 | H11: =H45+H79 -> 0 | I11: =I45+I79 -> 0 | J11: =J45+J79 -> 0 | ... N11: =N45+N79 -> 0 | O11: =IF(COUNTIF(C45:N45,">0")>0,(SUM(C45:N45)+SUM(C79:N79))/COUNTIF(C45:N45,">0"),0) -> 0 | P11: =SUM(C11:N11) -> 0
A12: =IF($A46="","",$A46) | B12: =IF($B46="","",$B46) | C12: =C46+C80 -> 0 | D12: =D46+D80 -> 0 | E12: =E46+E80 -> 0 | F12: =F46+F80 -> 0 | G12: =G46+G80 -> 0 | H12: =H46+H80 -> 0 | I12: =I46+I80 -> 0 | J12: =J46+J80 -> 0 | ... N12: =N46+N80 -> 0 | O12: =IF(COUNTIF(C46:N46,">0")>0,(SUM(C46:N46)+SUM(C80:N80))/COUNTIF(C46:N46,">0"),0) -> 0 | P12: =SUM(C12:N12) -> 0
A13: =IF($A47="","",$A47) | B13: =IF($B47="","",$B47) | C13: =C47+C81 -> 0 | D13: =D47+D81 -> 0 | E13: =E47+E81 -> 0 | F13: =F47+F81 -> 0 | G13: =G47+G81 -> 0 | H13: =H47+H81 -> 0 | I13: =I47+I81 -> 0 | J13: =J47+J81 -> 0 | ... N13: =N47+N81 -> 0 | O13: =IF(COUNTIF(C47:N47,">0")>0,(SUM(C47:N47)+SUM(C81:N81))/COUNTIF(C47:N47,">0"),0) -> 0 | P13: =SUM(C13:N13) -> 0
A14: =IF($A48="","",$A48) | B14: =IF($B48="","",$B48) | C14: =C48+C82 -> 0 | D14: =D48+D82 -> 0 | E14: =E48+E82 -> 0 | F14: =F48+F82 -> 0 | G14: =G48+G82 -> 0 | H14: =H48+H82 -> 0 | I14: =I48+I82 -> 0 | J14: =J48+J82 -> 0 | ... N14: =N48+N82 -> 0 | O14: =IF(COUNTIF(C48:N48,">0")>0,(SUM(C48:N48)+SUM(C82:N82))/COUNTIF(C48:N48,">0"),0) -> 0 | P14: =SUM(C14:N14) -> 0
A15: =IF($A49="","",$A49) | B15: =IF($B49="","",$B49) | C15: =C49+C83 -> 0 | D15: =D49+D83 -> 0 | E15: =E49+E83 -> 0 | F15: =F49+F83 -> 0 | G15: =G49+G83 -> 0 | H15: =H49+H83 -> 0 | I15: =I49+I83 -> 0 | J15: =J49+J83 -> 0 | ... N15: =N49+N83 -> 0 | O15: =IF(COUNTIF(C49:N49,">0")>0,(SUM(C49:N49)+SUM(C83:N83))/COUNTIF(C49:N49,">0"),0) -> 0 | P15: =SUM(C15:N15) -> 0
A16: =IF($A50="","",$A50) | B16: =IF($B50="","",$B50) | C16: =C50+C84 -> 0 | D16: =D50+D84 -> 0 | E16: =E50+E84 -> 0 | F16: =F50+F84 -> 0 | G16: =G50+G84 -> 0 | H16: =H50+H84 -> 0 | I16: =I50+I84 -> 0 | J16: =J50+J84 -> 0 | ... N16: =N50+N84 -> 0 | O16: =IF(COUNTIF(C50:N50,">0")>0,(SUM(C50:N50)+SUM(C84:N84))/COUNTIF(C50:N50,">0"),0) -> 0 | P16: =SUM(C16:N16) -> 0
A17: =IF($A51="","",$A51) | B17: =IF($B51="","",$B51) | C17: =C51+C85 -> 0 | D17: =D51+D85 -> 0 | E17: =E51+E85 -> 0 | F17: =F51+F85 -> 0 | G17: =G51+G85 -> 0 | H17: =H51+H85 -> 0 | I17: =I51+I85 -> 0 | J17: =J51+J85 -> 0 | ... N17: =N51+N85 -> 0 | O17: =IF(COUNTIF(C51:N51,">0")>0,(SUM(C51:N51)+SUM(C85:N85))/COUNTIF(C51:N51,">0"),0) -> 0 | P17: =SUM(C17:N17) -> 0
... A36: =IF($A70="","",$A70) | B36: =IF($B70="","",$B70) | C36: =C70+C104 -> 0 | D36: =D70+D104 -> 0 | E36: =E70+E104 -> 0 | F36: =F70+F104 -> 0 | G36: =G70+G104 -> 0 | H36: =H70+H104 -> 0 | I36: =I70+I104 -> 0 | J36: =J70+J104 -> 0 | ... N36: =N70+N104 -> 0 | O36: =IF(COUNTIF(C70:N70,">0")>0,(SUM(C70:N70)+SUM(C104:N104))/COUNTIF(C70:N70,">0"),0) -> 0 | P36: =SUM(C36:N36) -> 0
A37: TOTAL | C37: =SUM(C6:C36) -> 0 | D37: =SUM(D6:D36) -> 0 | E37: =SUM(E6:E36) -> 0 | F37: =SUM(F6:F36) -> 0 | G37: =SUM(G6:G36) -> 0 | H37: =SUM(H6:H36) -> 0 | I37: =SUM(I6:I36) -> 0 | J37: =SUM(J6:J36) -> 0 | ... P37: =SUM(P6:P36) -> 0
A39: SALÁRIO BASE | C39: SALÁRIO BASE
A40: =IF(Tabulação!A20<>"",Tabulação!A20,"") | B40: =IF(Tabulação!B20<>"",Tabulação!B20,"") | P40: =SUM(C40:O40) -> 0
A41: =IF(Tabulação!A21<>"",Tabulação!A21,"") | B41: =IF(Tabulação!B21<>"",Tabulação!B21,"") | P41: =SUM(C41:N41) -> 0
A42: =IF(Tabulação!A22<>"",Tabulação!A22,"") | B42: =IF(Tabulação!B22<>"",Tabulação!B22,"") | P42: =SUM(C42:N42) -> 0
A43: =IF(Tabulação!A23<>"",Tabulação!A23,"") | B43: =IF(Tabulação!B23<>"",Tabulação!B23,"") | P43: =SUM(C43:N43) -> 0
A44: =IF(Tabulação!A24<>"",Tabulação!A24,"") | B44: =IF(Tabulação!B24<>"",Tabulação!B24,"") | P44: =SUM(C44:N44) -> 0
A45: =IF(Tabulação!A25<>"",Tabulação!A25,"") | B45: =IF(Tabulação!B25<>"",Tabulação!B25,"") | P45: =SUM(C45:N45) -> 0
A46: =IF(Tabulação!A26<>"",Tabulação!A26,"") | B46: =IF(Tabulação!B26<>"",Tabulação!B26,"") | P46: =SUM(C46:N46) -> 0
A47: =IF(Tabulação!A27<>"",Tabulação!A27,"") | B47: =IF(Tabulação!B27<>"",Tabulação!B27,"") | P47: =SUM(C47:N47) -> 0
A48: =IF(Tabulação!A28<>"",Tabulação!A28,"") | B48: =IF(Tabulação!B28<>"",Tabulação!B28,"") | P48: =SUM(C48:N48) -> 0
A49: =IF(Tabulação!A29<>"",Tabulação!A29,"") | B49: =IF(Tabulação!B29<>"",Tabulação!B29,"") | P49: =SUM(C49:N49) -> 0
A50: =IF(Tabulação!A30<>"",Tabulação!A30,"") | B50: =IF(Tabulação!B30<>"",Tabulação!B30,"") | P50: =SUM(C50:N50) -> 0
A51: =IF(Tabulação!A31<>"",Tabulação!A31,"") | B51: =IF(Tabulação!B31<>"",Tabulação!B31,"") | P51: =SUM(C51:N51) -> 0
A52: =IF(Tabulação!A32<>"",Tabulação!A32,"") | B52: =IF(Tabulação!B32<>"",Tabulação!B32,"") | P52: =SUM(C52:N52) -> 0
... A70: =IF(Tabulação!A50<>"",Tabulação!A50,"") | B70: =IF(Tabulação!B50<>"",Tabulação!B50,"") | P70: =SUM(C70:N70) -> 0
A71: TOTAL | C71: =SUM(C40:C70) -> 0 | D71: =SUM(D40:D70) -> 0 | E71: =SUM(E40:E70) -> 0 | F71: =SUM(F40:F70) -> 0 | G71: =SUM(G40:G70) -> 0 | H71: =SUM(H40:H70) -> 0 | I71: =SUM(I40:I70) -> 0 | J71: =SUM(J40:J70) -> 0 | ... N71: =SUM(N40:N70) -> 0 | P71: =SUM(P40:P70) -> 0
A73: PARTICIPAÇÃO NOS RESULTADOS/ADICIONAIS | C73: PARTICIPAÇÃO NOS RESULTADOS/ADICIONAIS
A74: =IF($A40="","",$A40) | B74: =IF($B40="","",$B40) | P74: =SUM(C74:O74) -> 0
A75: =IF($A41="","",$A41) | B75: =IF($B41="","",$B41) | P75: =SUM(C75:N75) -> 0
A76: =IF($A42="","",$A42) | B76: =IF($B42="","",$B42) | P76: =SUM(C76:N76) -> 0
A77: =IF($A43="","",$A43) | B77: =IF($B43="","",$B43) | P77: =SUM(C77:N77) -> 0
A78: =IF($A44="","",$A44) | B78: =IF($B44="","",$B44) | P78: =SUM(C78:N78) -> 0
A79: =IF($A45="","",$A45) | B79: =IF($B45="","",$B45) | P79: =SUM(C79:N79) -> 0
A80: =IF($A46="","",$A46) | B80: =IF($B46="","",$B46) | P80: =SUM(C80:N80) -> 0
A81: =IF($A47="","",$A47) | B81: =IF($B47="","",$B47) | P81: =SUM(C81:N81) -> 0
A82: =IF($A48="","",$A48) | B82: =IF($B48="","",$B48) | P82: =SUM(C82:N82) -> 0
A83: =IF($A49="","",$A49) | B83: =IF($B49="","",$B49) | P83: =SUM(C83:N83) -> 0
A84: =IF($A50="","",$A50) | B84: =IF($B50="","",$B50) | P84: =SUM(C84:N84) -> 0
A85: =IF($A51="","",$A51) | B85: =IF($B51="","",$B51) | P85: =SUM(C85:N85) -> 0
A86: =IF($A52="","",$A52) | B86: =IF($B52="","",$B52) | P86: =SUM(C86:N86) -> 0
A87: =IF($A53="","",$A53) | B87: =IF($B53="","",$B53) | P87: =SUM(C87:N87) -> 0
A88: =IF($A54="","",$A54) | B88: =IF($B54="","",$B54)
A89: =IF($A55="","",$A55) | B89: =IF($B55="","",$B55)
A90: =IF($A56="","",$A56) | B90: =IF($B56="","",$B56)
A91: =IF($A57="","",$A57) | B91: =IF($B57="","",$B57)
A92: =IF($A58="","",$A58) | B92: =IF($B58="","",$B58)
A93: =IF($A59="","",$A59) | B93: =IF($B59="","",$B59)
A94: =IF($A60="","",$A60) | B94: =IF($B60="","",$B60)
A95: =IF($A61="","",$A61) | B95: =IF($B61="","",$B61)
A96: =IF($A62="","",$A62) | B96: =IF($B62="","",$B62)
A97: =IF($A63="","",$A63) | B97: =IF($B63="","",$B63)
A98: =IF($A64="","",$A64) | B98: =IF($B64="","",$B64)
A99: =IF($A65="","",$A65) | B99: =IF($B65="","",$B65)
... A104: =IF($A70="","",$A70) | B104: =IF($B70="","",$B70)
A105: TOTAL | C105: =SUM(C74:C104) -> 0 | D105: =SUM(D74:D104) -> 0 | E105: =SUM(E74:E104) -> 0 | F105: =SUM(F74:F104) -> 0 | G105: =SUM(G74:G104) -> 0 | H105: =SUM(H74:H104) -> 0 | I105: =SUM(I74:I104) -> 0 | J105: =SUM(J74:J104) -> 0 | ... N105: =SUM(N74:N104) -> 0 | P105: =SUM(P74:P104) -> 0
A107: TRANSPORTE | C107: TRANSPORTE
A108: =IF($A40="","",$A40) | B108: =IF($B40="","",$B40) | C108: =IF(C40=0,0,Tabulação!$E20*VLOOKUP(C$3,Tabulação!$A$3:$J$15,10,0)) -> 0 | D108: =IF(D40=0,0,Tabulação!$E20*VLOOKUP(D$3,Tabulação!$A$3:$J$15,10,0)) -> 0 | E108: =IF(E40=0,0,Tabulação!$E20*VLOOKUP(E$3,Tabulação!$A$3:$J$15,10,0)) -> 0 | F108: =IF(F40=0,0,Tabulação!$E20*VLOOKUP(F$3,Tabulação!$A$3:$J$15,10,0)) -> 0 | G108: =IF(G40=0,0,Tabulação!$E20*VLOOKUP(G$3,Tabulação!$A$3:$J$15,10,0)) -> 0 | H108: =IF(H40=0,0,Tabulação!$E20*VLOOKUP(H$3,Tabulação!$A$3:$J$15,10,0)) -> 0 | I108: =IF(I40=0,0,Tabulação!$E20*VLOOKUP(I$3,Tabulação!$A$3:$J$15,10,0)) -> 0 | J108: =IF(J40=0,0,Tabulação!$E20*VLOOKUP(J$3,Tabulação!$A$3:$J$15,10,0)) -> 0 | ... N108: =IF(N40=0,0,Tabulação!$E20*VLOOKUP(N$3,Tabulação!$A$3:$J$15,10,0)) -> 0 | P108: =SUM(C108:N108) -> 0
A109: =IF($A41="","",$A41) | B109: =IF($B41="","",$B41) | C109: =IF(C41=0,0,Tabulação!$E21*VLOOKUP(C$3,Tabulação!$A$3:$J$15,10,0)) -> 0 | D109: =IF(D41=0,0,Tabulação!$E21*VLOOKUP(D$3,Tabulação!$A$3:$J$15,10,0)) -> 0 | E109: =IF(E41=0,0,Tabulação!$E21*VLOOKUP(E$3,Tabulação!$A$3:$J$15,10,0)) -> 0 | F109: =IF(F41=0,0,Tabulação!$E21*VLOOKUP(F$3,Tabulação!$A$3:$J$15,10,0)) -> 0 | G109: =IF(G41=0,0,Tabulação!$E21*VLOOKUP(G$3,Tabulação!$A$3:$J$15,10,0)) -> 0 | H109: =IF(H41=0,0,Tabulação!$E21*VLOOKUP(H$3,Tabulação!$A$3:$J$15,10,0)) -> 0 | I109: =IF(I41=0,0,Tabulação!$E21*VLOOKUP(I$3,Tabulação!$A$3:$J$15,10,0)) -> 0 | J109: =IF(J41=0,0,Tabulação!$E21*VLOOKUP(J$3,Tabulação!$A$3:$J$15,10,0)) -> 0 | ... N109: =IF(N41=0,0,Tabulação!$E21*VLOOKUP(N$3,Tabulação!$A$3:$J$15,10,0)) -> 0 | P109: =SUM(C109:N109) -> 0
A110: =IF($A42="","",$A42) | B110: =IF($B42="","",$B42) | C110: =IF(C42=0,0,Tabulação!$E22*VLOOKUP(C$3,Tabulação!$A$3:$J$15,10,0)) -> 0 | D110: =IF(D42=0,0,Tabulação!$E22*VLOOKUP(D$3,Tabulação!$A$3:$J$15,10,0)) -> 0 | E110: =IF(E42=0,0,Tabulação!$E22*VLOOKUP(E$3,Tabulação!$A$3:$J$15,10,0)) -> 0 | F110: =IF(F42=0,0,Tabulação!$E22*VLOOKUP(F$3,Tabulação!$A$3:$J$15,10,0)) -> 0 | G110: =IF(G42=0,0,Tabulação!$E22*VLOOKUP(G$3,Tabulação!$A$3:$J$15,10,0)) -> 0 | H110: =IF(H42=0,0,Tabulação!$E22*VLOOKUP(H$3,Tabulação!$A$3:$J$15,10,0)) -> 0 | I110: =IF(I42=0,0,Tabulação!$E22*VLOOKUP(I$3,Tabulação!$A$3:$J$15,10,0)) -> 0 | J110: =IF(J42=0,0,Tabulação!$E22*VLOOKUP(J$3,Tabulação!$A$3:$J$15,10,0)) -> 0 | ... N110: =IF(N42=0,0,Tabulação!$E22*VLOOKUP(N$3,Tabulação!$A$3:$J$15,10,0)) -> 0 | P110: =SUM(C110:N110) -> 0
A111: =IF($A43="","",$A43) | B111: =IF($B43="","",$B43) | C111: =IF(C43=0,0,Tabulação!$E23*VLOOKUP(C$3,Tabulação!$A$3:$J$15,10,0)) -> 0 | D111: =IF(D43=0,0,Tabulação!$E23*VLOOKUP(D$3,Tabulação!$A$3:$J$15,10,0)) -> 0 | E111: =IF(E43=0,0,Tabulação!$E23*VLOOKUP(E$3,Tabulação!$A$3:$J$15,10,0)) -> 0 | F111: =IF(F43=0,0,Tabulação!$E23*VLOOKUP(F$3,Tabulação!$A$3:$J$15,10,0)) -> 0 | G111: =IF(G43=0,0,Tabulação!$E23*VLOOKUP(G$3,Tabulação!$A$3:$J$15,10,0)) -> 0 | H111: =IF(H43=0,0,Tabulação!$E23*VLOOKUP(H$3,Tabulação!$A$3:$J$15,10,0)) -> 0 | I111: =IF(I43=0,0,Tabulação!$E23*VLOOKUP(I$3,Tabulação!$A$3:$J$15,10,0)) -> 0 | J111: =IF(J43=0,0,Tabulação!$E23*VLOOKUP(J$3,Tabulação!$A$3:$J$15,10,0)) -> 0 | ... N111: =IF(N43=0,0,Tabulação!$E23*VLOOKUP(N$3,Tabulação!$A$3:$J$15,10,0)) -> 0 | P111: =SUM(C111:N111) -> 0
A112: =IF($A44="","",$A44) | B112: =IF($B44="","",$B44) | C112: =IF(C44=0,0,Tabulação!$E24*VLOOKUP(C$3,Tabulação!$A$3:$J$15,10,0)) -> 0 | D112: =IF(D44=0,0,Tabulação!$E24*VLOOKUP(D$3,Tabulação!$A$3:$J$15,10,0)) -> 0 | E112: =IF(E44=0,0,Tabulação!$E24*VLOOKUP(E$3,Tabulação!$A$3:$J$15,10,0)) -> 0 | F112: =IF(F44=0,0,Tabulação!$E24*VLOOKUP(F$3,Tabulação!$A$3:$J$15,10,0)) -> 0 | G112: =IF(G44=0,0,Tabulação!$E24*VLOOKUP(G$3,Tabulação!$A$3:$J$15,10,0)) -> 0 | H112: =IF(H44=0,0,Tabulação!$E24*VLOOKUP(H$3,Tabulação!$A$3:$J$15,10,0)) -> 0 | I112: =IF(I44=0,0,Tabulação!$E24*VLOOKUP(I$3,Tabulação!$A$3:$J$15,10,0)) -> 0 | J112: =IF(J44=0,0,Tabulação!$E24*VLOOKUP(J$3,Tabulação!$A$3:$J$15,10,0)) -> 0 | ... N112: =IF(N44=0,0,Tabulação!$E24*VLOOKUP(N$3,Tabulação!$A$3:$J$15,10,0)) -> 0 | P112: =SUM(C112:N112) -> 0
A113: =IF($A45="","",$A45) | B113: =IF($B45="","",$B45) | C113: =IF(C45=0,0,Tabulação!$E25*VLOOKUP(C$3,Tabulação!$A$3:$J$15,10,0)) -> 0 | D113: =IF(D45=0,0,Tabulação!$E25*VLOOKUP(D$3,Tabulação!$A$3:$J$15,10,0)) -> 0 | E113: =IF(E45=0,0,Tabulação!$E25*VLOOKUP(E$3,Tabulação!$A$3:$J$15,10,0)) -> 0 | F113: =IF(F45=0,0,Tabulação!$E25*VLOOKUP(F$3,Tabulação!$A$3:$J$15,10,0)) -> 0 | G113: =IF(G45=0,0,Tabulação!$E25*VLOOKUP(G$3,Tabulação!$A$3:$J$15,10,0)) -> 0 | H113: =IF(H45=0,0,Tabulação!$E25*VLOOKUP(H$3,Tabulação!$A$3:$J$15,10,0)) -> 0 | I113: =IF(I45=0,0,Tabulação!$E25*VLOOKUP(I$3,Tabulação!$A$3:$J$15,10,0)) -> 0 | J113: =IF(J45=0,0,Tabulação!$E25*VLOOKUP(J$3,Tabulação!$A$3:$J$15,10,0)) -> 0 | ... N113: =IF(N45=0,0,Tabulação!$E25*VLOOKUP(N$3,Tabulação!$A$3:$J$15,10,0)) -> 0 | P113: =SUM(C113:N113) -> 0
A114: =IF($A46="","",$A46) | B114: =IF($B46="","",$B46) | C114: =IF(C46=0,0,Tabulação!$E26*VLOOKUP(C$3,Tabulação!$A$3:$J$15,10,0)) -> 0 | D114: =IF(D46=0,0,Tabulação!$E26*VLOOKUP(D$3,Tabulação!$A$3:$J$15,10,0)) -> 0 | E114: =IF(E46=0,0,Tabulação!$E26*VLOOKUP(E$3,Tabulação!$A$3:$J$15,10,0)) -> 0 | F114: =IF(F46=0,0,Tabulação!$E26*VLOOKUP(F$3,Tabulação!$A$3:$J$15,10,0)) -> 0 | G114: =IF(G46=0,0,Tabulação!$E26*VLOOKUP(G$3,Tabulação!$A$3:$J$15,10,0)) -> 0 | H114: =IF(H46=0,0,Tabulação!$E26*VLOOKUP(H$3,Tabulação!$A$3:$J$15,10,0)) -> 0 | I114: =IF(I46=0,0,Tabulação!$E26*VLOOKUP(I$3,Tabulação!$A$3:$J$15,10,0)) -> 0 | J114: =IF(J46=0,0,Tabulação!$E26*VLOOKUP(J$3,Tabulação!$A$3:$J$15,10,0)) -> 0 | ... N114: =IF(N46=0,0,Tabulação!$E26*VLOOKUP(N$3,Tabulação!$A$3:$J$15,10,0)) -> 0 | P114: =SUM(C114:N114) -> 0
A115: =IF($A47="","",$A47) | B115: =IF($B47="","",$B47) | C115: =IF(C47=0,0,Tabulação!$E27*VLOOKUP(C$3,Tabulação!$A$3:$J$15,10,0)) -> 0 | D115: =IF(D47=0,0,Tabulação!$E27*VLOOKUP(D$3,Tabulação!$A$3:$J$15,10,0)) -> 0 | E115: =IF(E47=0,0,Tabulação!$E27*VLOOKUP(E$3,Tabulação!$A$3:$J$15,10,0)) -> 0 | F115: =IF(F47=0,0,Tabulação!$E27*VLOOKUP(F$3,Tabulação!$A$3:$J$15,10,0)) -> 0 | G115: =IF(G47=0,0,Tabulação!$E27*VLOOKUP(G$3,Tabulação!$A$3:$J$15,10,0)) -> 0 | H115: =IF(H47=0,0,Tabulação!$E27*VLOOKUP(H$3,Tabulação!$A$3:$J$15,10,0)) -> 0 | I115: =IF(I47=0,0,Tabulação!$E27*VLOOKUP(I$3,Tabulação!$A$3:$J$15,10,0)) -> 0 | J115: =IF(J47=0,0,Tabulação!$E27*VLOOKUP(J$3,Tabulação!$A$3:$J$15,10,0)) -> 0 | ... N115: =IF(N47=0,0,Tabulação!$E27*VLOOKUP(N$3,Tabulação!$A$3:$J$15,10,0)) -> 0 | P115: =SUM(C115:N115) -> 0
A116: =IF($A48="","",$A48) | B116: =IF($B48="","",$B48) | C116: =IF(C48=0,0,Tabulação!$E28*VLOOKUP(C$3,Tabulação!$A$3:$J$15,10,0)) -> 0 | D116: =IF(D48=0,0,Tabulação!$E28*VLOOKUP(D$3,Tabulação!$A$3:$J$15,10,0)) -> 0 | E116: =IF(E48=0,0,Tabulação!$E28*VLOOKUP(E$3,Tabulação!$A$3:$J$15,10,0)) -> 0 | F116: =IF(F48=0,0,Tabulação!$E28*VLOOKUP(F$3,Tabulação!$A$3:$J$15,10,0)) -> 0 | G116: =IF(G48=0,0,Tabulação!$E28*VLOOKUP(G$3,Tabulação!$A$3:$J$15,10,0)) -> 0 | H116: =IF(H48=0,0,Tabulação!$E28*VLOOKUP(H$3,Tabulação!$A$3:$J$15,10,0)) -> 0 | I116: =IF(I48=0,0,Tabulação!$E28*VLOOKUP(I$3,Tabulação!$A$3:$J$15,10,0)) -> 0 | J116: =IF(J48=0,0,Tabulação!$E28*VLOOKUP(J$3,Tabulação!$A$3:$J$15,10,0)) -> 0 | ... N116: =IF(N48=0,0,Tabulação!$E28*VLOOKUP(N$3,Tabulação!$A$3:$J$15,10,0)) -> 0 | P116: =SUM(C116:N116) -> 0
A117: =IF($A49="","",$A49) | B117: =IF($B49="","",$B49) | C117: =IF(C49=0,0,Tabulação!$E29*VLOOKUP(C$3,Tabulação!$A$3:$J$15,10,0)) -> 0 | D117: =IF(D49=0,0,Tabulação!$E29*VLOOKUP(D$3,Tabulação!$A$3:$J$15,10,0)) -> 0 | E117: =IF(E49=0,0,Tabulação!$E29*VLOOKUP(E$3,Tabulação!$A$3:$J$15,10,0)) -> 0 | F117: =IF(F49=0,0,Tabulação!$E29*VLOOKUP(F$3,Tabulação!$A$3:$J$15,10,0)) -> 0 | G117: =IF(G49=0,0,Tabulação!$E29*VLOOKUP(G$3,Tabulação!$A$3:$J$15,10,0)) -> 0 | H117: =IF(H49=0,0,Tabulação!$E29*VLOOKUP(H$3,Tabulação!$A$3:$J$15,10,0)) -> 0 | I117: =IF(I49=0,0,Tabulação!$E29*VLOOKUP(I$3,Tabulação!$A$3:$J$15,10,0)) -> 0 | J117: =IF(J49=0,0,Tabulação!$E29*VLOOKUP(J$3,Tabulação!$A$3:$J$15,10,0)) -> 0 | ... N117: =IF(N49=0,0,Tabulação!$E29*VLOOKUP(N$3,Tabulação!$A$3:$J$15,10,0)) -> 0 | P117: =SUM(C117:N117) -> 0
A118: =IF($A50="","",$A50) | B118: =IF($B50="","",$B50) | C118: =IF(C50=0,0,Tabulação!$E30*VLOOKUP(C$3,Tabulação!$A$3:$J$15,10,0)) -> 0 | D118: =IF(D50=0,0,Tabulação!$E30*VLOOKUP(D$3,Tabulação!$A$3:$J$15,10,0)) -> 0 | E118: =IF(E50=0,0,Tabulação!$E30*VLOOKUP(E$3,Tabulação!$A$3:$J$15,10,0)) -> 0 | F118: =IF(F50=0,0,Tabulação!$E30*VLOOKUP(F$3,Tabulação!$A$3:$J$15,10,0)) -> 0 | G118: =IF(G50=0,0,Tabulação!$E30*VLOOKUP(G$3,Tabulação!$A$3:$J$15,10,0)) -> 0 | H118: =IF(H50=0,0,Tabulação!$E30*VLOOKUP(H$3,Tabulação!$A$3:$J$15,10,0)) -> 0 | I118: =IF(I50=0,0,Tabulação!$E30*VLOOKUP(I$3,Tabulação!$A$3:$J$15,10,0)) -> 0 | J118: =IF(J50=0,0,Tabulação!$E30*VLOOKUP(J$3,Tabulação!$A$3:$J$15,10,0)) -> 0 | ... N118: =IF(N50=0,0,Tabulação!$E30*VLOOKUP(N$3,Tabulação!$A$3:$J$15,10,0)) -> 0 | P118: =SUM(C118:N118) -> 0
A119: =IF($A51="","",$A51) | B119: =IF($B51="","",$B51) | C119: =IF(C51=0,0,Tabulação!$E31*VLOOKUP(C$3,Tabulação!$A$3:$J$15,10,0)) -> 0 | D119: =IF(D51=0,0,Tabulação!$E31*VLOOKUP(D$3,Tabulação!$A$3:$J$15,10,0)) -> 0 | E119: =IF(E51=0,0,Tabulação!$E31*VLOOKUP(E$3,Tabulação!$A$3:$J$15,10,0)) -> 0 | F119: =IF(F51=0,0,Tabulação!$E31*VLOOKUP(F$3,Tabulação!$A$3:$J$15,10,0)) -> 0 | G119: =IF(G51=0,0,Tabulação!$E31*VLOOKUP(G$3,Tabulação!$A$3:$J$15,10,0)) -> 0 | H119: =IF(H51=0,0,Tabulação!$E31*VLOOKUP(H$3,Tabulação!$A$3:$J$15,10,0)) -> 0 | I119: =IF(I51=0,0,Tabulação!$E31*VLOOKUP(I$3,Tabulação!$A$3:$J$15,10,0)) -> 0 | J119: =IF(J51=0,0,Tabulação!$E31*VLOOKUP(J$3,Tabulação!$A$3:$J$15,10,0)) -> 0 | ... N119: =IF(N51=0,0,Tabulação!$E31*VLOOKUP(N$3,Tabulação!$A$3:$J$15,10,0)) -> 0 | P119: =SUM(C119:N119) -> 0
... A138: =IF($A70="","",$A70) | B138: =IF($B70="","",$B70) | C138: =IF(C70=0,0,Tabulação!$E50*VLOOKUP(C$3,Tabulação!$A$3:$J$15,10,0)) -> 0 | D138: =IF(D70=0,0,Tabulação!$E50*VLOOKUP(D$3,Tabulação!$A$3:$J$15,10,0)) -> 0 | E138: =IF(E70=0,0,Tabulação!$E50*VLOOKUP(E$3,Tabulação!$A$3:$J$15,10,0)) -> 0 | F138: =IF(F70=0,0,Tabulação!$E50*VLOOKUP(F$3,Tabulação!$A$3:$J$15,10,0)) -> 0 | G138: =IF(G70=0,0,Tabulação!$E50*VLOOKUP(G$3,Tabulação!$A$3:$J$15,10,0)) -> 0 | H138: =IF(H70=0,0,Tabulação!$E50*VLOOKUP(H$3,Tabulação!$A$3:$J$15,10,0)) -> 0 | I138: =IF(I70=0,0,Tabulação!$E50*VLOOKUP(I$3,Tabulação!$A$3:$J$15,10,0)) -> 0 | J138: =IF(J70=0,0,Tabulação!$E50*VLOOKUP(J$3,Tabulação!$A$3:$J$15,10,0)) -> 0 | ... N138: =IF(N70=0,0,Tabulação!$E50*VLOOKUP(N$3,Tabulação!$A$3:$J$15,10,0)) -> 0 | P138: =SUM(C138:N138) -> 0
A139: TOTAL | C139: =SUM(C108:C138) -> 0 | D139: =SUM(D108:D138) -> 0 | E139: =SUM(E108:E138) -> 0 | F139: =SUM(F108:F138) -> 0 | G139: =SUM(G108:G138) -> 0 | H139: =SUM(H108:H138) -> 0 | I139: =SUM(I108:I138) -> 0 | J139: =SUM(J108:J138) -> 0 | ... N139: =SUM(N108:N138) -> 0 | P139: =SUM(P108:P138) -> 0
A141: SALÁRIO LÍQUIDO | C141: SALÁRIO LÍQUIDO
A142: =IF($A74="","",$A74) | B142: =IF($B74="","",$B74) | C142: =C6-C278-C176 -> 0 | D142: =D6-D278-D176 -> 0 | E142: =E6-E278-E176 -> 0 | F142: =F6-F278-F176 -> 0 | G142: =G6-G278-G176 -> 0 | H142: =H6-H278-H176 -> 0 | I142: =I6-I278-I176 -> 0 | J142: =J6-J278-J176 -> 0 | ... P142: =P6-P278-P176 -> 0
A143: =IF($A75="","",$A75) | B143: =IF($B75="","",$B75) | C143: =C7-C279-C177 -> 0 | D143: =D7-D279-D177 -> 0 | E143: =E7-E279-E177 -> 0 | F143: =F7-F279-F177 -> 0 | G143: =G7-G279-G177 -> 0 | H143: =H7-H279-H177 -> 0 | I143: =I7-I279-I177 -> 0 | J143: =J7-J279-J177 -> 0 | ... P143: =P7-P279-P177 -> 0
A144: =IF($A76="","",$A76) | B144: =IF($B76="","",$B76) | C144: =C8-C280-C178 -> 0 | D144: =D8-D280-D178 -> 0 | E144: =E8-E280-E178 -> 0 | F144: =F8-F280-F178 -> 0 | G144: =G8-G280-G178 -> 0 | H144: =H8-H280-H178 -> 0 | I144: =I8-I280-I178 -> 0 | J144: =J8-J280-J178 -> 0 | ... P144: =P8-P280-P178 -> 0
A145: =IF($A77="","",$A77) | B145: =IF($B77="","",$B77) | C145: =C9-C281-C179 -> 0 | D145: =D9-D281-D179 -> 0 | E145: =E9-E281-E179 -> 0 | F145: =F9-F281-F179 -> 0 | G145: =G9-G281-G179 -> 0 | H145: =H9-H281-H179 -> 0 | I145: =I9-I281-I179 -> 0 | J145: =J9-J281-J179 -> 0 | ... P145: =P9-P281-P179 -> 0
A146: =IF($A78="","",$A78) | B146: =IF($B78="","",$B78) | C146: =C10-C282-C180 -> 0 | D146: =D10-D282-D180 -> 0 | E146: =E10-E282-E180 -> 0 | F146: =F10-F282-F180 -> 0 | G146: =G10-G282-G180 -> 0 | H146: =H10-H282-H180 -> 0 | I146: =I10-I282-I180 -> 0 | J146: =J10-J282-J180 -> 0 | ... P146: =P10-P282-P180 -> 0
A147: =IF($A79="","",$A79) | B147: =IF($B79="","",$B79) | C147: =C11-C283-C181 -> 0 | D147: =D11-D283-D181 -> 0 | E147: =E11-E283-E181 -> 0 | F147: =F11-F283-F181 -> 0 | G147: =G11-G283-G181 -> 0 | H147: =H11-H283-H181 -> 0 | I147: =I11-I283-I181 -> 0 | J147: =J11-J283-J181 -> 0 | ... P147: =P11-P283-P181 -> 0
A148: =IF($A80="","",$A80) | B148: =IF($B80="","",$B80) | C148: =C12-C284-C182 -> 0 | D148: =D12-D284-D182 -> 0 | E148: =E12-E284-E182 -> 0 | F148: =F12-F284-F182 -> 0 | G148: =G12-G284-G182 -> 0 | H148: =H12-H284-H182 -> 0 | I148: =I12-I284-I182 -> 0 | J148: =J12-J284-J182 -> 0 | ... P148: =P12-P284-P182 -> 0
A149: =IF($A81="","",$A81) | B149: =IF($B81="","",$B81) | C149: =C13-C285-C183 -> 0 | D149: =D13-D285-D183 -> 0 | E149: =E13-E285-E183 -> 0 | F149: =F13-F285-F183 -> 0 | G149: =G13-G285-G183 -> 0 | H149: =H13-H285-H183 -> 0 | I149: =I13-I285-I183 -> 0 | J149: =J13-J285-J183 -> 0 | ... P149: =P13-P285-P183 -> 0
A150: =IF($A82="","",$A82) | B150: =IF($B82="","",$B82) | C150: =C14-C286-C184 -> 0 | D150: =D14-D286-D184 -> 0 | E150: =E14-E286-E184 -> 0 | F150: =F14-F286-F184 -> 0 | G150: =G14-G286-G184 -> 0 | H150: =H14-H286-H184 -> 0 | I150: =I14-I286-I184 -> 0 | J150: =J14-J286-J184 -> 0 | ... P150: =P14-P286-P184 -> 0
A151: =IF($A83="","",$A83) | B151: =IF($B83="","",$B83) | C151: =C15-C287-C185 -> 0 | D151: =D15-D287-D185 -> 0 | E151: =E15-E287-E185 -> 0 | F151: =F15-F287-F185 -> 0 | G151: =G15-G287-G185 -> 0 | H151: =H15-H287-H185 -> 0 | I151: =I15-I287-I185 -> 0 | J151: =J15-J287-J185 -> 0 | ... P151: =P15-P287-P185 -> 0
A152: =IF($A84="","",$A84) | B152: =IF($B84="","",$B84) | C152: =C16-C288-C186 -> 0 | D152: =D16-D288-D186 -> 0 | E152: =E16-E288-E186 -> 0 | F152: =F16-F288-F186 -> 0 | G152: =G16-G288-G186 -> 0 | H152: =H16-H288-H186 -> 0 | I152: =I16-I288-I186 -> 0 | J152: =J16-J288-J186 -> 0 | ... P152: =P16-P288-P186 -> 0
A153: =IF($A85="","",$A85) | B153: =IF($B85="","",$B85) | C153: =C17-C289-C187 -> 0 | D153: =D17-D289-D187 -> 0 | E153: =E17-E289-E187 -> 0 | F153: =F17-F289-F187 -> 0 | G153: =G17-G289-G187 -> 0 | H153: =H17-H289-H187 -> 0 | I153: =I17-I289-I187 -> 0 | J153: =J17-J289-J187 -> 0 | ... P153: =P17-P289-P187 -> 0
... A172: =IF($A104="","",$A104) | B172: =IF($B104="","",$B104) | C172: =C36-C308-C206 -> 0 | D172: =D36-D308-D206 -> 0 | E172: =E36-E308-E206 -> 0 | F172: =F36-F308-F206 -> 0 | G172: =G36-G308-G206 -> 0 | H172: =H36-H308-H206 -> 0 | I172: =I36-I308-I206 -> 0 | J172: =J36-J308-J206 -> 0 | ... P172: =P36-P308-P206 -> 0
A173: Total | C173: =SUM(C142:C172) -> 0 | D173: =SUM(D142:D172) -> 0 | E173: =SUM(E142:E172) -> 0 | F173: =SUM(F142:F172) -> 0 | G173: =SUM(G142:G172) -> 0 | H173: =SUM(H142:H172) -> 0 | I173: =SUM(I142:I172) -> 0 | J173: =SUM(J142:J172) -> 0 | ... P173: =SUM(P142:P172) -> 0
A175: IMPOSTO DE RENDA (IR) | C175: IMPOSTO DE RENDA (IR)
A176: =IF($A108="","",$A108) | B176: =IF($B108="","",$B108) | C176: =IF((C6-C278)<Tabulação!$H$20,0,IF((C6-C278)<Tabulação!$H$21,((C6-C278)*Tabulação!$I$21)-Tabulação!$J$21,IF((C6-C278)<Tabulação!$H$22,((C6-C278)*Tabulação!$I$22)-Tabulação!$J$22,IF((C6-C278)<Tabulação!$H$23,((C6-C278)*Tabulação!$I$23)-Tabulação!$J$23,((C6-C278)*Tabulação!$I$24)-Tabulação!$J$24)))) -> 0 | D176: =IF((D6-D278)<Tabulação!$H$20,0,IF((D6-D278)<Tabulação!$H$21,((D6-D278)*Tabulação!$I$21)-Tabulação!$J$21,IF((D6-D278)<Tabulação!$H$22,((D6-D278)*Tabulação!$I$22)-Tabulação!$J$22,IF((D6-D278)<Tabulação!$H$23,((D6-D278)*Tabulação!$I$23)-Tabulação!$J$23,((D6-D278)*Tabulação!$I$24)-Tabulação!$J$24)))) -> 0 | E176: =IF((E6-E278)<Tabulação!$H$20,0,IF((E6-E278)<Tabulação!$H$21,((E6-E278)*Tabulação!$I$21)-Tabulação!$J$21,IF((E6-E278)<Tabulação!$H$22,((E6-E278)*Tabulação!$I$22)-Tabulação!$J$22,IF((E6-E278)<Tabulação!$H$23,((E6-E278)*Tabulação!$I$23)-Tabulação!$J$23,((E6-E278)*Tabulação!$I$24)-Tabulação!$J$24)))) -> 0 | F176: =IF((F6-F278)<Tabulação!$H$20,0,IF((F6-F278)<Tabulação!$H$21,((F6-F278)*Tabulação!$I$21)-Tabulação!$J$21,IF((F6-F278)<Tabulação!$H$22,((F6-F278)*Tabulação!$I$22)-Tabulação!$J$22,IF((F6-F278)<Tabulação!$H$23,((F6-F278)*Tabulação!$I$23)-Tabulação!$J$23,((F6-F278)*Tabulação!$I$24)-Tabulação!$J$24)))) -> 0 | G176: =IF((G6-G278)<Tabulação!$H$20,0,IF((G6-G278)<Tabulação!$H$21,((G6-G278)*Tabulação!$I$21)-Tabulação!$J$21,IF((G6-G278)<Tabulação!$H$22,((G6-G278)*Tabulação!$I$22)-Tabulação!$J$22,IF((G6-G278)<Tabulação!$H$23,((G6-G278)*Tabulação!$I$23)-Tabulação!$J$23,((G6-G278)*Tabulação!$I$24)-Tabulação!$J$24)))) -> 0 | H176: =IF((H6-H278)<Tabulação!$H$20,0,IF((H6-H278)<Tabulação!$H$21,((H6-H278)*Tabulação!$I$21)-Tabulação!$J$21,IF((H6-H278)<Tabulação!$H$22,((H6-H278)*Tabulação!$I$22)-Tabulação!$J$22,IF((H6-H278)<Tabulação!$H$23,((H6-H278)*Tabulação!$I$23)-Tabulação!$J$23,((H6-H278)*Tabulação!$I$24)-Tabulação!$J$24)))) -> 0 | I176: =IF((I6-I278)<Tabulação!$H$20,0,IF((I6-I278)<Tabulação!$H$21,((I6-I278)*Tabulação!$I$21)-Tabulação!$J$21,IF((I6-I278)<Tabulação!$H$22,((I6-I278)*Tabulação!$I$22)-Tabulação!$J$22,IF((I6-I278)<Tabulação!$H$23,((I6-I278)*Tabulação!$I$23)-Tabulação!$J$23,((I6-I278)*Tabulação!$I$24)-Tabulação!$J$24)))) -> 0 | J176: =IF((J6-J278)<Tabulação!$H$20,0,IF((J6-J278)<Tabulação!$H$21,((J6-J278)*Tabulação!$I$21)-Tabulação!$J$21,IF((J6-J278)<Tabulação!$H$22,((J6-J278)*Tabulação!$I$22)-Tabulação!$J$22,IF((J6-J278)<Tabulação!$H$23,((J6-J278)*Tabulação!$I$23)-Tabulação!$J$23,((J6-J278)*Tabulação!$I$24)-Tabulação!$J$24)))) -> 0 | ... O176: =IF((O6-O278)<Tabulação!$H$20,0,IF((O6-O278)<Tabulação!$H$21,((O6-O278)*Tabulação!$I$21)-Tabulação!$J$21,IF((O6-O278)<Tabulação!$H$22,((O6-O278)*Tabulação!$I$22)-Tabulação!$J$22,IF((O6-O278)<Tabulação!$H$23,((O6-O278)*Tabulação!$I$23)-Tabulação!$J$23,((O6-O278)*Tabulação!$I$24)-Tabulação!$J$24)))) -> 0 | P176: =SUM(C176:N176) -> 0
A177: =IF($A109="","",$A109) | B177: =IF($B109="","",$B109) | C177: =IF((C7-C279)<Tabulação!$H$20,0,IF((C7-C279)<Tabulação!$H$21,((C7-C279)*Tabulação!$I$21)-Tabulação!$J$21,IF((C7-C279)<Tabulação!$H$22,((C7-C279)*Tabulação!$I$22)-Tabulação!$J$22,IF((C7-C279)<Tabulação!$H$23,((C7-C279)*Tabulação!$I$23)-Tabulação!$J$23,((C7-C279)*Tabulação!$I$24)-Tabulação!$J$24)))) -> 0 | D177: =IF((D7-D279)<Tabulação!$H$20,0,IF((D7-D279)<Tabulação!$H$21,((D7-D279)*Tabulação!$I$21)-Tabulação!$J$21,IF((D7-D279)<Tabulação!$H$22,((D7-D279)*Tabulação!$I$22)-Tabulação!$J$22,IF((D7-D279)<Tabulação!$H$23,((D7-D279)*Tabulação!$I$23)-Tabulação!$J$23,((D7-D279)*Tabulação!$I$24)-Tabulação!$J$24)))) -> 0 | E177: =IF((E7-E279)<Tabulação!$H$20,0,IF((E7-E279)<Tabulação!$H$21,((E7-E279)*Tabulação!$I$21)-Tabulação!$J$21,IF((E7-E279)<Tabulação!$H$22,((E7-E279)*Tabulação!$I$22)-Tabulação!$J$22,IF((E7-E279)<Tabulação!$H$23,((E7-E279)*Tabulação!$I$23)-Tabulação!$J$23,((E7-E279)*Tabulação!$I$24)-Tabulação!$J$24)))) -> 0 | F177: =IF((F7-F279)<Tabulação!$H$20,0,IF((F7-F279)<Tabulação!$H$21,((F7-F279)*Tabulação!$I$21)-Tabulação!$J$21,IF((F7-F279)<Tabulação!$H$22,((F7-F279)*Tabulação!$I$22)-Tabulação!$J$22,IF((F7-F279)<Tabulação!$H$23,((F7-F279)*Tabulação!$I$23)-Tabulação!$J$23,((F7-F279)*Tabulação!$I$24)-Tabulação!$J$24)))) -> 0 | G177: =IF((G7-G279)<Tabulação!$H$20,0,IF((G7-G279)<Tabulação!$H$21,((G7-G279)*Tabulação!$I$21)-Tabulação!$J$21,IF((G7-G279)<Tabulação!$H$22,((G7-G279)*Tabulação!$I$22)-Tabulação!$J$22,IF((G7-G279)<Tabulação!$H$23,((G7-G279)*Tabulação!$I$23)-Tabulação!$J$23,((G7-G279)*Tabulação!$I$24)-Tabulação!$J$24)))) -> 0 | H177: =IF((H7-H279)<Tabulação!$H$20,0,IF((H7-H279)<Tabulação!$H$21,((H7-H279)*Tabulação!$I$21)-Tabulação!$J$21,IF((H7-H279)<Tabulação!$H$22,((H7-H279)*Tabulação!$I$22)-Tabulação!$J$22,IF((H7-H279)<Tabulação!$H$23,((H7-H279)*Tabulação!$I$23)-Tabulação!$J$23,((H7-H279)*Tabulação!$I$24)-Tabulação!$J$24)))) -> 0 | I177: =IF((I7-I279)<Tabulação!$H$20,0,IF((I7-I279)<Tabulação!$H$21,((I7-I279)*Tabulação!$I$21)-Tabulação!$J$21,IF((I7-I279)<Tabulação!$H$22,((I7-I279)*Tabulação!$I$22)-Tabulação!$J$22,IF((I7-I279)<Tabulação!$H$23,((I7-I279)*Tabulação!$I$23)-Tabulação!$J$23,((I7-I279)*Tabulação!$I$24)-Tabulação!$J$24)))) -> 0 | J177: =IF((J7-J279)<Tabulação!$H$20,0,IF((J7-J279)<Tabulação!$H$21,((J7-J279)*Tabulação!$I$21)-Tabulação!$J$21,IF((J7-J279)<Tabulação!$H$22,((J7-J279)*Tabulação!$I$22)-Tabulação!$J$22,IF((J7-J279)<Tabulação!$H$23,((J7-J279)*Tabulação!$I$23)-Tabulação!$J$23,((J7-J279)*Tabulação!$I$24)-Tabulação!$J$24)))) -> 0 | ... O177: =IF((O7-O279)<Tabulação!$H$20,0,IF((O7-O279)<Tabulação!$H$21,((O7-O279)*Tabulação!$I$21)-Tabulação!$J$21,IF((O7-O279)<Tabulação!$H$22,((O7-O279)*Tabulação!$I$22)-Tabulação!$J$22,IF((O7-O279)<Tabulação!$H$23,((O7-O279)*Tabulação!$I$23)-Tabulação!$J$23,((O7-O279)*Tabulação!$I$24)-Tabulação!$J$24)))) -> 0 | P177: =SUM(C177:N177) -> 0
A178: =IF($A110="","",$A110) | B178: =IF($B110="","",$B110) | C178: =IF((C8-C280)<Tabulação!$H$20,0,IF((C8-C280)<Tabulação!$H$21,((C8-C280)*Tabulação!$I$21)-Tabulação!$J$21,IF((C8-C280)<Tabulação!$H$22,((C8-C280)*Tabulação!$I$22)-Tabulação!$J$22,IF((C8-C280)<Tabulação!$H$23,((C8-C280)*Tabulação!$I$23)-Tabulação!$J$23,((C8-C280)*Tabulação!$I$24)-Tabulação!$J$24)))) -> 0 | D178: =IF((D8-D280)<Tabulação!$H$20,0,IF((D8-D280)<Tabulação!$H$21,((D8-D280)*Tabulação!$I$21)-Tabulação!$J$21,IF((D8-D280)<Tabulação!$H$22,((D8-D280)*Tabulação!$I$22)-Tabulação!$J$22,IF((D8-D280)<Tabulação!$H$23,((D8-D280)*Tabulação!$I$23)-Tabulação!$J$23,((D8-D280)*Tabulação!$I$24)-Tabulação!$J$24)))) -> 0 | E178: =IF((E8-E280)<Tabulação!$H$20,0,IF((E8-E280)<Tabulação!$H$21,((E8-E280)*Tabulação!$I$21)-Tabulação!$J$21,IF((E8-E280)<Tabulação!$H$22,((E8-E280)*Tabulação!$I$22)-Tabulação!$J$22,IF((E8-E280)<Tabulação!$H$23,((E8-E280)*Tabulação!$I$23)-Tabulação!$J$23,((E8-E280)*Tabulação!$I$24)-Tabulação!$J$24)))) -> 0 | F178: =IF((F8-F280)<Tabulação!$H$20,0,IF((F8-F280)<Tabulação!$H$21,((F8-F280)*Tabulação!$I$21)-Tabulação!$J$21,IF((F8-F280)<Tabulação!$H$22,((F8-F280)*Tabulação!$I$22)-Tabulação!$J$22,IF((F8-F280)<Tabulação!$H$23,((F8-F280)*Tabulação!$I$23)-Tabulação!$J$23,((F8-F280)*Tabulação!$I$24)-Tabulação!$J$24)))) -> 0 | G178: =IF((G8-G280)<Tabulação!$H$20,0,IF((G8-G280)<Tabulação!$H$21,((G8-G280)*Tabulação!$I$21)-Tabulação!$J$21,IF((G8-G280)<Tabulação!$H$22,((G8-G280)*Tabulação!$I$22)-Tabulação!$J$22,IF((G8-G280)<Tabulação!$H$23,((G8-G280)*Tabulação!$I$23)-Tabulação!$J$23,((G8-G280)*Tabulação!$I$24)-Tabulação!$J$24)))) -> 0 | H178: =IF((H8-H280)<Tabulação!$H$20,0,IF((H8-H280)<Tabulação!$H$21,((H8-H280)*Tabulação!$I$21)-Tabulação!$J$21,IF((H8-H280)<Tabulação!$H$22,((H8-H280)*Tabulação!$I$22)-Tabulação!$J$22,IF((H8-H280)<Tabulação!$H$23,((H8-H280)*Tabulação!$I$23)-Tabulação!$J$23,((H8-H280)*Tabulação!$I$24)-Tabulação!$J$24)))) -> 0 | I178: =IF((I8-I280)<Tabulação!$H$20,0,IF((I8-I280)<Tabulação!$H$21,((I8-I280)*Tabulação!$I$21)-Tabulação!$J$21,IF((I8-I280)<Tabulação!$H$22,((I8-I280)*Tabulação!$I$22)-Tabulação!$J$22,IF((I8-I280)<Tabulação!$H$23,((I8-I280)*Tabulação!$I$23)-Tabulação!$J$23,((I8-I280)*Tabulação!$I$24)-Tabulação!$J$24)))) -> 0 | J178: =IF((J8-J280)<Tabulação!$H$20,0,IF((J8-J280)<Tabulação!$H$21,((J8-J280)*Tabulação!$I$21)-Tabulação!$J$21,IF((J8-J280)<Tabulação!$H$22,((J8-J280)*Tabulação!$I$22)-Tabulação!$J$22,IF((J8-J280)<Tabulação!$H$23,((J8-J280)*Tabulação!$I$23)-Tabulação!$J$23,((J8-J280)*Tabulação!$I$24)-Tabulação!$J$24)))) -> 0 | ... O178: =IF((O8-O280)<Tabulação!$H$20,0,IF((O8-O280)<Tabulação!$H$21,((O8-O280)*Tabulação!$I$21)-Tabulação!$J$21,IF((O8-O280)<Tabulação!$H$22,((O8-O280)*Tabulação!$I$22)-Tabulação!$J$22,IF((O8-O280)<Tabulação!$H$23,((O8-O280)*Tabulação!$I$23)-Tabulação!$J$23,((O8-O280)*Tabulação!$I$24)-Tabulação!$J$24)))) -> 0 | P178: =SUM(C178:N178) -> 0
A179: =IF($A111="","",$A111) | B179: =IF($B111="","",$B111) | C179: =IF((C9-C281)<Tabulação!$H$20,0,IF((C9-C281)<Tabulação!$H$21,((C9-C281)*Tabulação!$I$21)-Tabulação!$J$21,IF((C9-C281)<Tabulação!$H$22,((C9-C281)*Tabulação!$I$22)-Tabulação!$J$22,IF((C9-C281)<Tabulação!$H$23,((C9-C281)*Tabulação!$I$23)-Tabulação!$J$23,((C9-C281)*Tabulação!$I$24)-Tabulação!$J$24)))) -> 0 | D179: =IF((D9-D281)<Tabulação!$H$20,0,IF((D9-D281)<Tabulação!$H$21,((D9-D281)*Tabulação!$I$21)-Tabulação!$J$21,IF((D9-D281)<Tabulação!$H$22,((D9-D281)*Tabulação!$I$22)-Tabulação!$J$22,IF((D9-D281)<Tabulação!$H$23,((D9-D281)*Tabulação!$I$23)-Tabulação!$J$23,((D9-D281)*Tabulação!$I$24)-Tabulação!$J$24)))) -> 0 | E179: =IF((E9-E281)<Tabulação!$H$20,0,IF((E9-E281)<Tabulação!$H$21,((E9-E281)*Tabulação!$I$21)-Tabulação!$J$21,IF((E9-E281)<Tabulação!$H$22,((E9-E281)*Tabulação!$I$22)-Tabulação!$J$22,IF((E9-E281)<Tabulação!$H$23,((E9-E281)*Tabulação!$I$23)-Tabulação!$J$23,((E9-E281)*Tabulação!$I$24)-Tabulação!$J$24)))) -> 0 | F179: =IF((F9-F281)<Tabulação!$H$20,0,IF((F9-F281)<Tabulação!$H$21,((F9-F281)*Tabulação!$I$21)-Tabulação!$J$21,IF((F9-F281)<Tabulação!$H$22,((F9-F281)*Tabulação!$I$22)-Tabulação!$J$22,IF((F9-F281)<Tabulação!$H$23,((F9-F281)*Tabulação!$I$23)-Tabulação!$J$23,((F9-F281)*Tabulação!$I$24)-Tabulação!$J$24)))) -> 0 | G179: =IF((G9-G281)<Tabulação!$H$20,0,IF((G9-G281)<Tabulação!$H$21,((G9-G281)*Tabulação!$I$21)-Tabulação!$J$21,IF((G9-G281)<Tabulação!$H$22,((G9-G281)*Tabulação!$I$22)-Tabulação!$J$22,IF((G9-G281)<Tabulação!$H$23,((G9-G281)*Tabulação!$I$23)-Tabulação!$J$23,((G9-G281)*Tabulação!$I$24)-Tabulação!$J$24)))) -> 0 | H179: =IF((H9-H281)<Tabulação!$H$20,0,IF((H9-H281)<Tabulação!$H$21,((H9-H281)*Tabulação!$I$21)-Tabulação!$J$21,IF((H9-H281)<Tabulação!$H$22,((H9-H281)*Tabulação!$I$22)-Tabulação!$J$22,IF((H9-H281)<Tabulação!$H$23,((H9-H281)*Tabulação!$I$23)-Tabulação!$J$23,((H9-H281)*Tabulação!$I$24)-Tabulação!$J$24)))) -> 0 | I179: =IF((I9-I281)<Tabulação!$H$20,0,IF((I9-I281)<Tabulação!$H$21,((I9-I281)*Tabulação!$I$21)-Tabulação!$J$21,IF((I9-I281)<Tabulação!$H$22,((I9-I281)*Tabulação!$I$22)-Tabulação!$J$22,IF((I9-I281)<Tabulação!$H$23,((I9-I281)*Tabulação!$I$23)-Tabulação!$J$23,((I9-I281)*Tabulação!$I$24)-Tabulação!$J$24)))) -> 0 | J179: =IF((J9-J281)<Tabulação!$H$20,0,IF((J9-J281)<Tabulação!$H$21,((J9-J281)*Tabulação!$I$21)-Tabulação!$J$21,IF((J9-J281)<Tabulação!$H$22,((J9-J281)*Tabulação!$I$22)-Tabulação!$J$22,IF((J9-J281)<Tabulação!$H$23,((J9-J281)*Tabulação!$I$23)-Tabulação!$J$23,((J9-J281)*Tabulação!$I$24)-Tabulação!$J$24)))) -> 0 | ... O179: =IF((O9-O281)<Tabulação!$H$20,0,IF((O9-O281)<Tabulação!$H$21,((O9-O281)*Tabulação!$I$21)-Tabulação!$J$21,IF((O9-O281)<Tabulação!$H$22,((O9-O281)*Tabulação!$I$22)-Tabulação!$J$22,IF((O9-O281)<Tabulação!$H$23,((O9-O281)*Tabulação!$I$23)-Tabulação!$J$23,((O9-O281)*Tabulação!$I$24)-Tabulação!$J$24)))) -> 0 | P179: =SUM(C179:N179) -> 0
A180: =IF($A112="","",$A112) | B180: =IF($B112="","",$B112) | C180: =IF((C10-C282)<Tabulação!$H$20,0,IF((C10-C282)<Tabulação!$H$21,((C10-C282)*Tabulação!$I$21)-Tabulação!$J$21,IF((C10-C282)<Tabulação!$H$22,((C10-C282)*Tabulação!$I$22)-Tabulação!$J$22,IF((C10-C282)<Tabulação!$H$23,((C10-C282)*Tabulação!$I$23)-Tabulação!$J$23,((C10-C282)*Tabulação!$I$24)-Tabulação!$J$24)))) -> 0 | D180: =IF((D10-D282)<Tabulação!$H$20,0,IF((D10-D282)<Tabulação!$H$21,((D10-D282)*Tabulação!$I$21)-Tabulação!$J$21,IF((D10-D282)<Tabulação!$H$22,((D10-D282)*Tabulação!$I$22)-Tabulação!$J$22,IF((D10-D282)<Tabulação!$H$23,((D10-D282)*Tabulação!$I$23)-Tabulação!$J$23,((D10-D282)*Tabulação!$I$24)-Tabulação!$J$24)))) -> 0 | E180: =IF((E10-E282)<Tabulação!$H$20,0,IF((E10-E282)<Tabulação!$H$21,((E10-E282)*Tabulação!$I$21)-Tabulação!$J$21,IF((E10-E282)<Tabulação!$H$22,((E10-E282)*Tabulação!$I$22)-Tabulação!$J$22,IF((E10-E282)<Tabulação!$H$23,((E10-E282)*Tabulação!$I$23)-Tabulação!$J$23,((E10-E282)*Tabulação!$I$24)-Tabulação!$J$24)))) -> 0 | F180: =IF((F10-F282)<Tabulação!$H$20,0,IF((F10-F282)<Tabulação!$H$21,((F10-F282)*Tabulação!$I$21)-Tabulação!$J$21,IF((F10-F282)<Tabulação!$H$22,((F10-F282)*Tabulação!$I$22)-Tabulação!$J$22,IF((F10-F282)<Tabulação!$H$23,((F10-F282)*Tabulação!$I$23)-Tabulação!$J$23,((F10-F282)*Tabulação!$I$24)-Tabulação!$J$24)))) -> 0 | G180: =IF((G10-G282)<Tabulação!$H$20,0,IF((G10-G282)<Tabulação!$H$21,((G10-G282)*Tabulação!$I$21)-Tabulação!$J$21,IF((G10-G282)<Tabulação!$H$22,((G10-G282)*Tabulação!$I$22)-Tabulação!$J$22,IF((G10-G282)<Tabulação!$H$23,((G10-G282)*Tabulação!$I$23)-Tabulação!$J$23,((G10-G282)*Tabulação!$I$24)-Tabulação!$J$24)))) -> 0 | H180: =IF((H10-H282)<Tabulação!$H$20,0,IF((H10-H282)<Tabulação!$H$21,((H10-H282)*Tabulação!$I$21)-Tabulação!$J$21,IF((H10-H282)<Tabulação!$H$22,((H10-H282)*Tabulação!$I$22)-Tabulação!$J$22,IF((H10-H282)<Tabulação!$H$23,((H10-H282)*Tabulação!$I$23)-Tabulação!$J$23,((H10-H282)*Tabulação!$I$24)-Tabulação!$J$24)))) -> 0 | I180: =IF((I10-I282)<Tabulação!$H$20,0,IF((I10-I282)<Tabulação!$H$21,((I10-I282)*Tabulação!$I$21)-Tabulação!$J$21,IF((I10-I282)<Tabulação!$H$22,((I10-I282)*Tabulação!$I$22)-Tabulação!$J$22,IF((I10-I282)<Tabulação!$H$23,((I10-I282)*Tabulação!$I$23)-Tabulação!$J$23,((I10-I282)*Tabulação!$I$24)-Tabulação!$J$24)))) -> 0 | J180: =IF((J10-J282)<Tabulação!$H$20,0,IF((J10-J282)<Tabulação!$H$21,((J10-J282)*Tabulação!$I$21)-Tabulação!$J$21,IF((J10-J282)<Tabulação!$H$22,((J10-J282)*Tabulação!$I$22)-Tabulação!$J$22,IF((J10-J282)<Tabulação!$H$23,((J10-J282)*Tabulação!$I$23)-Tabulação!$J$23,((J10-J282)*Tabulação!$I$24)-Tabulação!$J$24)))) -> 0 | ... O180: =IF((O10-O282)<Tabulação!$H$20,0,IF((O10-O282)<Tabulação!$H$21,((O10-O282)*Tabulação!$I$21)-Tabulação!$J$21,IF((O10-O282)<Tabulação!$H$22,((O10-O282)*Tabulação!$I$22)-Tabulação!$J$22,IF((O10-O282)<Tabulação!$H$23,((O10-O282)*Tabulação!$I$23)-Tabulação!$J$23,((O10-O282)*Tabulação!$I$24)-Tabulação!$J$24)))) -> 0 | P180: =SUM(C180:N180) -> 0
A181: =IF($A113="","",$A113) | B181: =IF($B113="","",$B113) | C181: =IF((C11-C283)<Tabulação!$H$20,0,IF((C11-C283)<Tabulação!$H$21,((C11-C283)*Tabulação!$I$21)-Tabulação!$J$21,IF((C11-C283)<Tabulação!$H$22,((C11-C283)*Tabulação!$I$22)-Tabulação!$J$22,IF((C11-C283)<Tabulação!$H$23,((C11-C283)*Tabulação!$I$23)-Tabulação!$J$23,((C11-C283)*Tabulação!$I$24)-Tabulação!$J$24)))) -> 0 | D181: =IF((D11-D283)<Tabulação!$H$20,0,IF((D11-D283)<Tabulação!$H$21,((D11-D283)*Tabulação!$I$21)-Tabulação!$J$21,IF((D11-D283)<Tabulação!$H$22,((D11-D283)*Tabulação!$I$22)-Tabulação!$J$22,IF((D11-D283)<Tabulação!$H$23,((D11-D283)*Tabulação!$I$23)-Tabulação!$J$23,((D11-D283)*Tabulação!$I$24)-Tabulação!$J$24)))) -> 0 | E181: =IF((E11-E283)<Tabulação!$H$20,0,IF((E11-E283)<Tabulação!$H$21,((E11-E283)*Tabulação!$I$21)-Tabulação!$J$21,IF((E11-E283)<Tabulação!$H$22,((E11-E283)*Tabulação!$I$22)-Tabulação!$J$22,IF((E11-E283)<Tabulação!$H$23,((E11-E283)*Tabulação!$I$23)-Tabulação!$J$23,((E11-E283)*Tabulação!$I$24)-Tabulação!$J$24)))) -> 0 | F181: =IF((F11-F283)<Tabulação!$H$20,0,IF((F11-F283)<Tabulação!$H$21,((F11-F283)*Tabulação!$I$21)-Tabulação!$J$21,IF((F11-F283)<Tabulação!$H$22,((F11-F283)*Tabulação!$I$22)-Tabulação!$J$22,IF((F11-F283)<Tabulação!$H$23,((F11-F283)*Tabulação!$I$23)-Tabulação!$J$23,((F11-F283)*Tabulação!$I$24)-Tabulação!$J$24)))) -> 0 | G181: =IF((G11-G283)<Tabulação!$H$20,0,IF((G11-G283)<Tabulação!$H$21,((G11-G283)*Tabulação!$I$21)-Tabulação!$J$21,IF((G11-G283)<Tabulação!$H$22,((G11-G283)*Tabulação!$I$22)-Tabulação!$J$22,IF((G11-G283)<Tabulação!$H$23,((G11-G283)*Tabulação!$I$23)-Tabulação!$J$23,((G11-G283)*Tabulação!$I$24)-Tabulação!$J$24)))) -> 0 | H181: =IF((H11-H283)<Tabulação!$H$20,0,IF((H11-H283)<Tabulação!$H$21,((H11-H283)*Tabulação!$I$21)-Tabulação!$J$21,IF((H11-H283)<Tabulação!$H$22,((H11-H283)*Tabulação!$I$22)-Tabulação!$J$22,IF((H11-H283)<Tabulação!$H$23,((H11-H283)*Tabulação!$I$23)-Tabulação!$J$23,((H11-H283)*Tabulação!$I$24)-Tabulação!$J$24)))) -> 0 | I181: =IF((I11-I283)<Tabulação!$H$20,0,IF((I11-I283)<Tabulação!$H$21,((I11-I283)*Tabulação!$I$21)-Tabulação!$J$21,IF((I11-I283)<Tabulação!$H$22,((I11-I283)*Tabulação!$I$22)-Tabulação!$J$22,IF((I11-I283)<Tabulação!$H$23,((I11-I283)*Tabulação!$I$23)-Tabulação!$J$23,((I11-I283)*Tabulação!$I$24)-Tabulação!$J$24)))) -> 0 | J181: =IF((J11-J283)<Tabulação!$H$20,0,IF((J11-J283)<Tabulação!$H$21,((J11-J283)*Tabulação!$I$21)-Tabulação!$J$21,IF((J11-J283)<Tabulação!$H$22,((J11-J283)*Tabulação!$I$22)-Tabulação!$J$22,IF((J11-J283)<Tabulação!$H$23,((J11-J283)*Tabulação!$I$23)-Tabulação!$J$23,((J11-J283)*Tabulação!$I$24)-Tabulação!$J$24)))) -> 0 | ... O181: =IF((O11-O283)<Tabulação!$H$20,0,IF((O11-O283)<Tabulação!$H$21,((O11-O283)*Tabulação!$I$21)-Tabulação!$J$21,IF((O11-O283)<Tabulação!$H$22,((O11-O283)*Tabulação!$I$22)-Tabulação!$J$22,IF((O11-O283)<Tabulação!$H$23,((O11-O283)*Tabulação!$I$23)-Tabulação!$J$23,((O11-O283)*Tabulação!$I$24)-Tabulação!$J$24)))) -> 0 | P181: =SUM(C181:N181) -> 0
...

Sheet Gráficos
A1: FOLHA DE PAGAMENTO - GRÁFICOS
A4: SELECIONE O MÊS: | B4: FEVEREIRO
D8: =CONCATENATE("Total pago pela empresa no mês de"," ",B4) -> Total pago pela empresa no mês de FEVEREIRO
C9: SALÁRIO LÍQUIDO | D9: =VLOOKUP(C9,Pagamentos!$B:$P,HLOOKUP($B$4,Pagamentos!$3:$4,2,0),0) -> 0
C10: INSS | D10: =VLOOKUP(C10,Pagamentos!$B:$P,HLOOKUP($B$4,Pagamentos!$3:$4,2,0),0) -> 0
C11: IR | D11: =VLOOKUP(C11,Pagamentos!$B:$P,HLOOKUP($B$4,Pagamentos!$3:$4,2,0),0) -> 0
C12: TRANSPORTE | D12: =VLOOKUP(C12,Pagamentos!$B:$P,HLOOKUP($B$4,Pagamentos!$3:$4,2,0),0) -> 0
C13: INSS PAGO PELA EMPRESA | D13: =VLOOKUP(C13,Pagamentos!$B:$P,HLOOKUP($B$4,Pagamentos!$3:$4,2,0),0) -> 0
C14: FGTS | D14: =VLOOKUP(C14,Pagamentos!$B:$P,HLOOKUP($B$4,Pagamentos!$3:$4,2,0),0) -> 0
C15: SAT | D15: =VLOOKUP(C15,Pagamentos!$B:$P,HLOOKUP($B$4,Pagamentos!$3:$4,2,0),0) -> 0
A36: SELECIONE O MÊS: | B36: FEVEREIRO
C38: =CONCATENATE("Participação nos resultados/Adicionais:"," ",B36) -> Participação nos resultados/Adicionais: FEVEREIRO
B39: =IF(Tabulação!A20<>"",Tabulação!A20,"") | C39: =IF(VLOOKUP(B39,Pagamentos!$A$74:$P$104,HLOOKUP($B$36,Pagamentos!$3:$4,2,0)+1,0)<>0,VLOOKUP(B39,Pagamentos!$A$74:$P$104,HLOOKUP($B$36,Pagamentos!$3:$4,2,0)+1,0),"")
B40: =IF(Tabulação!A21<>"",Tabulação!A21,"") | C40: =IF(VLOOKUP(B40,Pagamentos!$A$74:$P$104,HLOOKUP($B$36,Pagamentos!$3:$4,2,0)+1,0)<>0,VLOOKUP(B40,Pagamentos!$A$74:$P$104,HLOOKUP($B$36,Pagamentos!$3:$4,2,0)+1,0),"")
B41: =IF(Tabulação!A22<>"",Tabulação!A22,"") | C41: =IF(VLOOKUP(B41,Pagamentos!$A$74:$P$104,HLOOKUP($B$36,Pagamentos!$3:$4,2,0)+1,0)<>0,VLOOKUP(B41,Pagamentos!$A$74:$P$104,HLOOKUP($B$36,Pagamentos!$3:$4,2,0)+1,0),"")
B42: =IF(Tabulação!A23<>"",Tabulação!A23,"") | C42: =IF(VLOOKUP(B42,Pagamentos!$A$74:$P$104,HLOOKUP($B$36,Pagamentos!$3:$4,2,0)+1,0)<>0,VLOOKUP(B42,Pagamentos!$A$74:$P$104,HLOOKUP($B$36,Pagamentos!$3:$4,2,0)+1,0),"")
B43: =IF(Tabulação!A24<>"",Tabulação!A24,"") | C43: =IF(VLOOKUP(B43,Pagamentos!$A$74:$P$104,HLOOKUP($B$36,Pagamentos!$3:$4,2,0)+1,0)<>0,VLOOKUP(B43,Pagamentos!$A$74:$P$104,HLOOKUP($B$36,Pagamentos!$3:$4,2,0)+1,0),"")
B44: =IF(Tabulação!A25<>"",Tabulação!A25,"") | C44: =IF(VLOOKUP(B44,Pagamentos!$A$74:$P$104,HLOOKUP($B$36,Pagamentos!$3:$4,2,0)+1,0)<>0,VLOOKUP(B44,Pagamentos!$A$74:$P$104,HLOOKUP($B$36,Pagamentos!$3:$4,2,0)+1,0),"")
B45: =IF(Tabulação!A26<>"",Tabulação!A26,"") | C45: =IF(VLOOKUP(B45,Pagamentos!$A$74:$P$104,HLOOKUP($B$36,Pagamentos!$3:$4,2,0)+1,0)<>0,VLOOKUP(B45,Pagamentos!$A$74:$P$104,HLOOKUP($B$36,Pagamentos!$3:$4,2,0)+1,0),"")
B46: =IF(Tabulação!A27<>"",Tabulação!A27,"") | C46: =IF(VLOOKUP(B46,Pagamentos!$A$74:$P$104,HLOOKUP($B$36,Pagamentos!$3:$4,2,0)+1,0)<>0,VLOOKUP(B46,Pagamentos!$A$74:$P$104,HLOOKUP($B$36,Pagamentos!$3:$4,2,0)+1,0),"")
B47: =IF(Tabulação!A28<>"",Tabulação!A28,"") | C47: =IF(VLOOKUP(B47,Pagamentos!$A$74:$P$104,HLOOKUP($B$36,Pagamentos!$3:$4,2,0)+1,0)<>0,VLOOKUP(B47,Pagamentos!$A$74:$P$104,HLOOKUP($B$36,Pagamentos!$3:$4,2,0)+1,0),"")
B48: =IF(Tabulação!A29<>"",Tabulação!A29,"") | C48: =IF(VLOOKUP(B48,Pagamentos!$A$74:$P$104,HLOOKUP($B$36,Pagamentos!$3:$4,2,0)+1,0)<>0,VLOOKUP(B48,Pagamentos!$A$74:$P$104,HLOOKUP($B$36,Pagamentos!$3:$4,2,0)+1,0),"")
B49: =IF(Tabulação!A30<>"",Tabulação!A30,"") | C49: =IF(VLOOKUP(B49,Pagamentos!$A$74:$P$104,HLOOKUP($B$36,Pagamentos!$3:$4,2,0)+1,0)<>0,VLOOKUP(B49,Pagamentos!$A$74:$P$104,HLOOKUP($B$36,Pagamentos!$3:$4,2,0)+1,0),"")
B50: =IF(Tabulação!A31<>"",Tabulação!A31,"") | C50: =IF(VLOOKUP(B50,Pagamentos!$A$74:$P$104,HLOOKUP($B$36,Pagamentos!$3:$4,2,0)+1,0)<>0,VLOOKUP(B50,Pagamentos!$A$74:$P$104,HLOOKUP($B$36,Pagamentos!$3:$4,2,0)+1,0),"")
... B80: =IF(Tabulação!A61<>"",Tabulação!A61,"") | C80: =IF(VLOOKUP(B80,Pagamentos!$A$74:$P$104,HLOOKUP($B$36,Pagamentos!$3:$4,2,0)+1,0)<>0,VLOOKUP(B80,Pagamentos!$A$74:$P$104,HLOOKUP($B$36,Pagamentos!$3:$4,2,0)+1,0),"")
