Workbook
Name FERIADO: FERIADO!$A$2:$A$937

Sheet __FDSCACHE__
B1: This sheet contains Factset binary data for use with this workbook's =FDS codes. Modifying the worksheet's contents may damage the workbook's =FDS functionality.

Sheet Resumo Cenarios
B2: RESUMO RESULTADOS DA MODELAGEM | I2: VICTOR LOPES SCHMUTZLER
C3: (R$ milhões) | I3: +55 (11) 3553-2529
B6: CENÁRIO BASE | D6: 2010 | E6: 2011 | F6: =E6+1 -> 2012 | G6: =F6+1 -> 2013 | H6: =G6+1 -> 2014 | I6: =H6+1 -> 2015 | J6: =I6+1 -> 2016 | K6: =J6+1 -> 2017 | L6: =K6+1 -> 2018 | M6: =L6+1 -> 2019 | ... P6: =O6+1 -> 2022
B8: AG Concessões
B9: Dividendos Recebidos pela AGC (proporcionais a participação)
C10: CEMIG (via AGC Energias) | E10: 93.3 | F10: =PROJ_AGCeAGPar!K59 -> 116.52927 | G10: =PROJ_AGCeAGPar!L59 -> 121.76695 | H10: =PROJ_AGCeAGPar!M59 -> 114.43103 | I10: =PROJ_AGCeAGPar!N59 -> 113.78005 | J10: =PROJ_AGCeAGPar!O59 -> 122.95298 | K10: =PROJ_AGCeAGPar!P59 -> 134.02746 | L10: =PROJ_AGCeAGPar!Q59 -> 150.72766 | M10: =PROJ_AGCeAGPar!R59 -> 143.90413 | ... P10: =PROJ_AGCeAGPar!U59 -> 177.80988
C11: % Payout (Lucro Líq. Ajustado) | E11: =PROJ_AGCeAGPar!J56 -> 0.53583437 | F11: =PROJ_AGCeAGPar!K56 -> 0.5 | G11: =PROJ_AGCeAGPar!L56 -> 0.5 | H11: =PROJ_AGCeAGPar!M56 -> 0.5 | I11: =PROJ_AGCeAGPar!N56 -> 0.5 | J11: =PROJ_AGCeAGPar!O56 -> 0.5 | K11: =PROJ_AGCeAGPar!P56 -> 0.5 | L11: =PROJ_AGCeAGPar!Q56 -> 0.5 | ... P11: =PROJ_AGCeAGPar!U56 -> 0.5
C12: CCR | D12: 141.5 | E12: =PROJ_AGCeAGPar!J78 -> 147.7 | F12: =PROJ_AGCeAGPar!K78 -> 108.38642 | G12: =PROJ_AGCeAGPar!L78 -> 212.08366 | H12: =PROJ_AGCeAGPar!M78 -> 266.29701 | I12: =PROJ_AGCeAGPar!N78 -> 330.23453 | J12: =PROJ_AGCeAGPar!O78 -> 392.09472 | K12: =PROJ_AGCeAGPar!P78 -> 452.03243 | L12: =PROJ_AGCeAGPar!Q78 -> 509.33965 | ... P12: =PROJ_AGCeAGPar!U78 -> 783.4107
C13: % Payout (Lucro Líq. Ajustado) | D13: =PROJ_AGCeAGPar!I75 -> 1.2665914 | E13: =PROJ_AGCeAGPar!J75 -> 0.88609375 | F13: =PROJ_AGCeAGPar!K75 -> 0.85 | G13: =PROJ_AGCeAGPar!L75 -> 0.85 | H13: =PROJ_AGCeAGPar!M75 -> 0.85 | I13: =PROJ_AGCeAGPar!N75 -> 0.85 | J13: =PROJ_AGCeAGPar!O75 -> 0.85 | K13: =PROJ_AGCeAGPar!P75 -> 0.85 | ... P13: =PROJ_AGCeAGPar!U75 -> 0.85
C14: SANEPAR | D14: 2.6 | E14: 2.4 | F14: =PROJ_AGCeAGPar!K94 -> 5.7008304 | G14: =PROJ_AGCeAGPar!L94 -> 12.885385 | H14: =PROJ_AGCeAGPar!M94 -> 14.353805 | I14: =PROJ_AGCeAGPar!N94 -> 15.659714 | J14: =PROJ_AGCeAGPar!O94 -> 17.133528 | K14: =PROJ_AGCeAGPar!P94 -> 18.799764 | L14: =PROJ_AGCeAGPar!Q94 -> 20.470687 | M14: =PROJ_AGCeAGPar!R94 -> 22.311411 | ... P14: =PROJ_AGCeAGPar!U94 -> 29.038832
C15: % Payout (Lucro Líq. Ajustado) | D15: =PROJ_AGCeAGPar!I91 -> 0.29432837 | E15: =PROJ_AGCeAGPar!J91 -> 0.25 | F15: =PROJ_AGCeAGPar!K91 -> 0.5 | G15: =PROJ_AGCeAGPar!L91 -> 0.5 | H15: =PROJ_AGCeAGPar!M91 -> 0.5 | I15: =PROJ_AGCeAGPar!N91 -> 0.5 | J15: =PROJ_AGCeAGPar!O91 -> 0.5 | K15: =PROJ_AGCeAGPar!P91 -> 0.5 | ... P15: =PROJ_AGCeAGPar!U91 -> 0.5
C16: WATERPORT | D16: 12.6 | E16: 19.2 | F16: =PROJ_AGCeAGPar!K110 -> 21.024015 | G16: =PROJ_AGCeAGPar!L110 -> 23.132809 | H16: =PROJ_AGCeAGPar!M110 -> 24.659574 | I16: =PROJ_AGCeAGPar!N110 -> 26.050374 | J16: =PROJ_AGCeAGPar!O110 -> 27.613396 | K16: =PROJ_AGCeAGPar!P110 -> 29.170792 | L16: =PROJ_AGCeAGPar!Q110 -> 30.85103 | M16: =PROJ_AGCeAGPar!R110 -> 32.66507 | ... P16: =PROJ_AGCeAGPar!U110 -> 38.968113
C17: % Payout (Lucro Líq. Ajustado) | D17: =PROJ_AGCeAGPar!I107 -> 0.74117647 | E17: =PROJ_AGCeAGPar!J107 -> 0.96 | F17: =PROJ_AGCeAGPar!K107 -> 0.96 | G17: =PROJ_AGCeAGPar!L107 -> 0.96 | H17: =PROJ_AGCeAGPar!M107 -> 0.96 | I17: =PROJ_AGCeAGPar!N107 -> 0.96 | J17: =PROJ_AGCeAGPar!O107 -> 0.96 | K17: =PROJ_AGCeAGPar!P107 -> 0.96 | ... P17: =PROJ_AGCeAGPar!U107 -> 0.96
C18: Outros | D18: =59.1+2.4 -> 61.5 | E18: 8.4 | F18: =PROJ_AGCeAGPar!K128 -> 6.966 | G18: =PROJ_AGCeAGPar!L128 -> 0 | H18: =PROJ_AGCeAGPar!M128 -> 0 | I18: =PROJ_AGCeAGPar!N128 -> 0 | J18: =PROJ_AGCeAGPar!O128 -> 0 | K18: =PROJ_AGCeAGPar!P128 -> 0 | L18: =PROJ_AGCeAGPar!Q128 -> 0 | M18: =PROJ_AGCeAGPar!R128 -> 0 | ... P18: =PROJ_AGCeAGPar!U128 -> 0
B19: Total Dividendos Recebidos pela AGC (Caixa) | D19: =D10+D12+D14+D16+D18 -> 218.2 | E19: 271.27 | F19: =F10+F12+F14+F16+F18 -> 258.60653 | G19: =G10+G12+G14+G16+G18 -> 369.86879 | H19: =H10+H12+H14+H16+H18 -> 419.74142 | I19: =I10+I12+I14+I16+I18 -> 485.72467 | J19: =J10+J12+J14+J16+J18 -> 559.79462 | K19: =K10+K12+K14+K16+K18 -> 634.03045 | L19: =L10+L12+L14+L16+L18 -> 711.38902 | M19: =M10+M12+M14+M16+M18 -> 776.93778 | ... P19: =P10+P12+P14+P16+P18 -> 1029.2275
C20: Var. YoY% | E20: =E19/D19-1 -> 0.24321723 | F20: =F19/E19-1 -> -0.046682167 | G20: =G19/F19-1 -> 0.43023765 | H20: =H19/G19-1 -> 0.13483871 | I20: =I19/H19-1 -> 0.15719974 | J20: =J19/I19-1 -> 0.1524937 | K20: =K19/J19-1 -> 0.13261262 | L20: =L19/K19-1 -> 0.1220108 | ... P20: =P19/O19-1 -> 0.10643011
B21: Resultado de Equivalência Patrimonial na AGC | D21: =PROJ_AGCeAGPar!I152 -> 398.987 | E21: =PROJ_AGCeAGPar!J152 -> 435.337 | F21: =PROJ_AGCeAGPar!K152 -> 449.14806 | G21: =PROJ_AGCeAGPar!L152 -> 555.83506 | H21: =PROJ_AGCeAGPar!M152 -> 623.93844 | I21: =PROJ_AGCeAGPar!N152 -> 728.5796 | J21: =PROJ_AGCeAGPar!O152 -> 822.3844 | K21: =PROJ_AGCeAGPar!P152 -> 933.81038 | ... P21: =PROJ_AGCeAGPar!U152 -> 1465.2211
C22: Var. YoY% | E22: =E21/D21-1 -> 0.091105725 | F22: =F21/E21-1 -> 0.031724991 | G22: =G21/F21-1 -> 0.23753192 | H22: =H21/G21-1 -> 0.12252444 | I22: =I21/H21-1 -> 0.1677107 | J22: =J21/I21-1 -> 0.12875024 | K22: =K21/J21-1 -> 0.13549135 | L22: =L21/K21-1 -> 0.059374022 | ... P22: =P21/O21-1 -> 0.12833646
B23: Resultado Líquido AGC | D23: =PROJ_AGCeAGPar!I172 -> 661.965 | E23: =PROJ_AGCeAGPar!J172 -> 348.793 | F23: =PROJ_AGCeAGPar!K172 -> 663.25113 | G23: =PROJ_AGCeAGPar!L172 -> 496.44688 | H23: =PROJ_AGCeAGPar!M172 -> 581.06879 | I23: =PROJ_AGCeAGPar!N172 -> 688.22048 | J23: =PROJ_AGCeAGPar!O172 -> 780.21277 | K23: =PROJ_AGCeAGPar!P172 -> 891.28839 | ... P23: =PROJ_AGCeAGPar!U172 -> 1420.4983
C24: Var. YoY% | E24: =E23/D23-1 -> -0.4730945 | F24: =F23/E23-1 -> 0.90156088 | G24: =G23/F23-1 -> -0.25149485 | H24: =H23/G23-1 -> 0.17045512 | I24: =I23/H23-1 -> 0.18440447 | J24: =J23/I23-1 -> 0.13366689 | K24: =K23/J23-1 -> 0.14236581 | L24: =L23/K23-1 -> 0.059827254 | ... P24: =P23/O23-1 -> 0.13304231
B25: Dividendos Pagos pela AGC | D25: =PROJ_AGCeAGPar!I177 -> 157.2164 | E25: =PROJ_AGCeAGPar!J177 -> 82.838 | F25: =PROJ_AGCeAGPar!K177 -> 472.56643 | G25: =PROJ_AGCeAGPar!L177 -> 117.90613 | H25: =PROJ_AGCeAGPar!M177 -> 469.21305 | I25: =PROJ_AGCeAGPar!N177 -> 555.73804 | J25: =PROJ_AGCeAGPar!O177 -> 630.02181 | K25: =PROJ_AGCeAGPar!P177 -> 719.71538 | ... P25: =PROJ_AGCeAGPar!U177 -> 1147.0523
C26: % Payout | D26: =PROJ_AGCeAGPar!I178 -> 0.24999953 | E26: =PROJ_AGCeAGPar!J178 -> 0.24999898 | F26: =PROJ_AGCeAGPar!K178 -> 0.75 | G26: =PROJ_AGCeAGPar!L178 -> 0.25 | H26: =PROJ_AGCeAGPar!M178 -> 0.85 | I26: =PROJ_AGCeAGPar!N178 -> 0.85 | J26: =PROJ_AGCeAGPar!O178 -> 0.85 | K26: =PROJ_AGCeAGPar!P178 -> 0.85 | ... P26: =PROJ_AGCeAGPar!U178 -> 0.85
B27: AG Participações
B28: (=) Resultado Líquido AGPar | D28: =PROJ_AGCeAGPar!I293 -> 310.985 | E28: =PROJ_AGCeAGPar!J293 -> 238.446 | F28: =PROJ_AGCeAGPar!K293 -> 784.92858 | G28: =PROJ_AGCeAGPar!L293 -> 527.97254 | H28: =PROJ_AGCeAGPar!M293 -> 538.23025 | I28: =PROJ_AGCeAGPar!N293 -> 655.10182 | J28: =PROJ_AGCeAGPar!O293 -> 781.30466 | K28: =PROJ_AGCeAGPar!P293 -> 928.49474 | ... P28: =PROJ_AGCeAGPar!U293 -> 1654.8959
C29: Var. YoY% | E29: =E28/D28-1 -> -0.23325562 | F29: =F28/E28-1 -> 2.2918505 | G29: =G28/F28-1 -> -0.32736231 | H29: =H28/G28-1 -> 0.019428496 | I29: =I28/H28-1 -> 0.21714046 | J29: =J28/I28-1 -> 0.19264614 | K29: =K28/J28-1 -> 0.18839012 | L29: =L28/K28-1 -> 0.094896625 | ... P29: =P28/O28-1 -> 0.14309834
C30: (-) Resultado de Equivalência Patrimonial na AGPar | D30: =PROJ_AGCeAGPar!I342 -> -529.116 | E30: =PROJ_AGCeAGPar!J342 -> -263.525 | F30: =PROJ_AGCeAGPar!K342 -> -835.01583 | G30: =PROJ_AGCeAGPar!L342 -> -577.67118 | H30: =PROJ_AGCeAGPar!M342 -> -566.14679 | I30: =PROJ_AGCeAGPar!N342 -> -659.27828 | J30: =PROJ_AGCeAGPar!O342 -> -754.16479 | K30: =PROJ_AGCeAGPar!P342 -> -873.05481 | ... P30: =PROJ_AGCeAGPar!U342 -> -1420.4983
C31: Var. YoY% | E31: =E30/D30-1 -> -0.50195231 | F31: =F30/E30-1 -> 2.1686399 | G31: =G30/F30-1 -> -0.30819135 | H31: =H30/G30-1 -> -0.019949724 | I31: =I30/H30-1 -> 0.16450059 | J31: =J30/I30-1 -> 0.14392482 | K31: =K30/J30-1 -> 0.15764462 | L31: =L30/K30-1 -> 0.067342179 | ... P31: =P30/O30-1 -> 0.13506456
C32: (+) Dividendos e JSCP recebidos de controladas | D32: =PROJ_AGCeAGPar!I343 -> 133.4004 | E32: =PROJ_AGCeAGPar!J343 -> 67 | F32: =PROJ_AGCeAGPar!K343 -> 401.68146 | G32: =PROJ_AGCeAGPar!L343 -> 100.22021 | H32: =PROJ_AGCeAGPar!M343 -> 398.83109 | I32: =PROJ_AGCeAGPar!N343 -> 472.37733 | J32: =PROJ_AGCeAGPar!O343 -> 535.51854 | K32: =PROJ_AGCeAGPar!P343 -> 611.75807 | ... P32: =PROJ_AGCeAGPar!U343 -> 974.99449
C33: (+/-) Variação Contas de Ativo e Passivo | D33: =PROJ_AGCeAGPar!I344 -> -40.612 | E33: =PROJ_AGCeAGPar!J344 -> 70.696 | F33: =PROJ_AGCeAGPar!K344 -> -101.55367 | G33: =PROJ_AGCeAGPar!L344 -> -8.5445853 | H33: =PROJ_AGCeAGPar!M344 -> -54.126451 | I33: =PROJ_AGCeAGPar!N344 -> 13.220023 | J33: =PROJ_AGCeAGPar!O344 -> 6.2198675 | K33: =PROJ_AGCeAGPar!P344 -> -2.995157 | ... P33: =PROJ_AGCeAGPar!U344 -> -5.4454302
C34: (+/-) Investimentos permanentes | D34: =PROJ_AGCeAGPar!I347+PROJ_AGCeAGPar!I348 -> 353.39561 | E34: =PROJ_AGCeAGPar!J347+PROJ_AGCeAGPar!J348 -> -274.162 | F34: =PROJ_AGCeAGPar!K347+PROJ_AGCeAGPar!K348 -> -349.11504 | G34: =PROJ_AGCeAGPar!L347+PROJ_AGCeAGPar!L348 -> 17.68592 | H34: =PROJ_AGCeAGPar!M347+PROJ_AGCeAGPar!M348 -> 70.381958 | I34: =PROJ_AGCeAGPar!N347+PROJ_AGCeAGPar!N348 -> 83.360706 | J34: =PROJ_AGCeAGPar!O347+PROJ_AGCeAGPar!O348 -> 94.503271 | K34: =PROJ_AGCeAGPar!P347+PROJ_AGCeAGPar!P348 -> 107.95731 | ... P34: =PROJ_AGCeAGPar!U347+PROJ_AGCeAGPar!U348 -> 172.05785
B35: (=) FCF operacional após Atividades de Investimento | D35: =D28+D30+D32+D33+D34 -> 228.053 | E35: =E28+E30+E32+E33+E34 -> -161.545 | F35: =F28+F30+F32+F33+F34 -> -99.0745 | G35: =G28+G30+G32+G33+G34 -> 59.662915 | H35: =H28+H30+H32+H33+H34 -> 387.17006 | I35: =I28+I30+I32+I33+I34 -> 564.7816 | J35: =J28+J30+J32+J33+J34 -> 663.38155 | K35: =K28+K30+K32+K33+K34 -> 772.16015 | ... P35: =P28+P30+P32+P33+P34 -> 1376.0045
C36: (+/-) Captação / (Amortização) de dívida | D36: =PROJ_AGCeAGPar!I351 -> -144.941 | E36: =PROJ_AGCeAGPar!J351 -> 119.702 | F36: =PROJ_AGCeAGPar!K351 -> 878.39035 | G36: =PROJ_AGCeAGPar!L351 -> 40.974688 | H36: =PROJ_AGCeAGPar!M351 -> 1.6377812 | I36: =PROJ_AGCeAGPar!N351 -> -0.89489201 | J36: =PROJ_AGCeAGPar!O351 -> -140.24065 | K36: =PROJ_AGCeAGPar!P351 -> -141.11105 | ... P36: =PROJ_AGCeAGPar!U351 -> -153.24672
C37: (+/-) Variação no Capital Social Líquida | D37: =PROJ_AGCeAGPar!I352 -> -75.541 | E37: =PROJ_AGCeAGPar!J352 -> 105.025 | F37: =PROJ_AGCeAGPar!K352 -> -65.100751 | G37: =PROJ_AGCeAGPar!L352 -> -17.555044 | H37: =PROJ_AGCeAGPar!M352 -> -70.381958 | I37: =PROJ_AGCeAGPar!N352 -> -83.360706 | J37: =PROJ_AGCeAGPar!O352 -> -94.503271 | K37: =PROJ_AGCeAGPar!P352 -> -107.95731 | ... P37: =PROJ_AGCeAGPar!U352 -> -172.05785
C38: (-) Dividendos e juros sobre Capital Próprio pagos | D38: =PROJ_AGCeAGPar!I353 -> -40.116 | E38: =PROJ_AGCeAGPar!J353 -> -82.517 | F38: =PROJ_AGCeAGPar!K353 -> -121.31979 | G38: =PROJ_AGCeAGPar!L353 -> -107.83843 | H38: =PROJ_AGCeAGPar!M353 -> -57.447727 | I38: =PROJ_AGCeAGPar!N353 -> -227.81266 | J38: =PROJ_AGCeAGPar!O353 -> -276.61644 | K38: =PROJ_AGCeAGPar!P353 -> -333.07769 | ... P38: =PROJ_AGCeAGPar!U353 -> -614.01768
B39: (=) Fluxo de Caixa Livre | D39: =D35+D36+D37+D38 -> -32.545 | E39: =E35+E36+E37+E38 -> -19.335 | F39: =F35+F36+F37+F38 -> 592.89532 | G39: =G35+G36+G37+G38 -> -24.755876 | H39: =H35+H36+H37+H38 -> 260.97816 | I39: =I35+I36+I37+I38 -> 252.71334 | J39: =J35+J36+J37+J38 -> 152.02119 | K39: =K35+K36+K37+K38 -> 190.0141 | ... P39: =P35+P36+P37+P38 -> 436.68227
B40: Caixa + Aplicações Financeiras | D40: =PROJ_AGCeAGPar!I368 -> 30.927 | E40: =PROJ_AGCeAGPar!J368 -> 11.592 | F40: =PROJ_AGCeAGPar!K368 -> 604.48732 | G40: =PROJ_AGCeAGPar!L368 -> 579.73144 | H40: =PROJ_AGCeAGPar!M368 -> 840.7096 | I40: =PROJ_AGCeAGPar!N368 -> 1093.4229 | J40: =PROJ_AGCeAGPar!O368 -> 1245.4441 | K40: =PROJ_AGCeAGPar!P368 -> 1435.4582 | ... P40: =PROJ_AGCeAGPar!U368 -> 3086.4429
B41: Investimentos Permanentes | D41: =PROJ_AGCeAGPar!I314+PROJ_AGCeAGPar!I315+PROJ_AGCeAGPar!I316 -> 1498.731 | E41: =PROJ_AGCeAGPar!J314+PROJ_AGCeAGPar!J315+PROJ_AGCeAGPar!J316 -> 1969.418 | F41: =PROJ_AGCeAGPar!K314+PROJ_AGCeAGPar!K315+PROJ_AGCeAGPar!K316 -> 2751.8674 | G41: =PROJ_AGCeAGPar!L314+PROJ_AGCeAGPar!L315+PROJ_AGCeAGPar!L316 -> 3211.6324 | H41: =PROJ_AGCeAGPar!M314+PROJ_AGCeAGPar!M315+PROJ_AGCeAGPar!M316 -> 3308.5662 | I41: =PROJ_AGCeAGPar!N314+PROJ_AGCeAGPar!N315+PROJ_AGCeAGPar!N316 -> 3412.1064 | J41: =PROJ_AGCeAGPar!O314+PROJ_AGCeAGPar!O315+PROJ_AGCeAGPar!O316 -> 3536.2494 | K41: =PROJ_AGCeAGPar!P314+PROJ_AGCeAGPar!P315+PROJ_AGCeAGPar!P316 -> 3689.5888 | ... P41: =PROJ_AGCeAGPar!U314+PROJ_AGCeAGPar!U315+PROJ_AGCeAGPar!U316 -> 4786.5075
B42: Patrimônio Líquido | D42: =PROJ_AGCeAGPar!I329 -> 1415.165 | E42: =PROJ_AGCeAGPar!J329 -> 1676.119 | F42: =PROJ_AGCeAGPar!K329 -> 2274.627 | G42: =PROJ_AGCeAGPar!L329 -> 2677.2061 | H42: =PROJ_AGCeAGPar!M329 -> 3087.6067 | I42: =PROJ_AGCeAGPar!N329 -> 3431.5351 | J42: =PROJ_AGCeAGPar!O329 -> 3841.7201 | K42: =PROJ_AGCeAGPar!P329 -> 4329.1798 | ... P42: =PROJ_AGCeAGPar!U329 -> 7798.6233
C43: Divida CP | D43: =PROJ_AGCeAGPar!I365 -> 40.402 | E43: =PROJ_AGCeAGPar!J365 -> 40.196 | F43: =PROJ_AGCeAGPar!K365 -> 0 | G43: =PROJ_AGCeAGPar!L365 -> 14.634678 | H43: =PROJ_AGCeAGPar!M365 -> 14.634678 | I43: =PROJ_AGCeAGPar!N365 -> 147.96801 | J43: =PROJ_AGCeAGPar!O365 -> 585.22674 | K43: =PROJ_AGCeAGPar!P365 -> 583.64895 | ... P43: =PROJ_AGCeAGPar!U365 -> 58.538713
C44: Divida LP | D44: =PROJ_AGCeAGPar!I366 -> 40.004 | E44: =PROJ_AGCeAGPar!J366 -> 159.912 | F44: =PROJ_AGCeAGPar!K366 -> 1078.4984 | G44: =PROJ_AGCeAGPar!L366 -> 1104.8384 | H44: =PROJ_AGCeAGPar!M366 -> 1106.4761 | I44: =PROJ_AGCeAGPar!N366 -> 972.24792 | J44: =PROJ_AGCeAGPar!O366 -> 394.74855 | K44: =PROJ_AGCeAGPar!P366 -> 255.21528 | ... P44: =PROJ_AGCeAGPar!U366 -> 71.165587
B45: Dívida Total | D45: =PROJ_AGCeAGPar!I367 -> 80.406 | E45: =PROJ_AGCeAGPar!J367 -> 200.108 | F45: =PROJ_AGCeAGPar!K367 -> 1078.4984 | G45: =PROJ_AGCeAGPar!L367 -> 1119.473 | H45: =PROJ_AGCeAGPar!M367 -> 1121.1108 | I45: =PROJ_AGCeAGPar!N367 -> 1120.2159 | J45: =PROJ_AGCeAGPar!O367 -> 979.97528 | K45: =PROJ_AGCeAGPar!P367 -> 838.86423 | ... P45: =PROJ_AGCeAGPar!U367 -> 129.7043
B46: Dívida Líquida | D46: =PROJ_AGCeAGPar!I369 -> 49.479 | E46: =PROJ_AGCeAGPar!J369 -> 188.516 | F46: =PROJ_AGCeAGPar!K369 -> 474.01104 | G46: =PROJ_AGCeAGPar!L369 -> 539.7416 | H46: =PROJ_AGCeAGPar!M369 -> 280.40123 | I46: =PROJ_AGCeAGPar!N369 -> 26.79299 | J46: =PROJ_AGCeAGPar!O369 -> -265.46884 | K46: =PROJ_AGCeAGPar!P369 -> -596.59399 | ... P46: =PROJ_AGCeAGPar!U369 -> -2956.7386
B47: Dívida Total / PL | D47: =PROJ_AGCeAGPar!I370 -> 0.056817403 | E47: =PROJ_AGCeAGPar!J370 -> 0.1193877 | F47: =PROJ_AGCeAGPar!K370 -> 0.47414294 | G47: =PROJ_AGCeAGPar!L370 -> 0.41814974 | H47: =PROJ_AGCeAGPar!M370 -> 0.36310027 | I47: =PROJ_AGCeAGPar!N370 -> 0.32644746 | J47: =PROJ_AGCeAGPar!O370 -> 0.25508763 | K47: =PROJ_AGCeAGPar!P370 -> 0.19376978 | ... P47: =PROJ_AGCeAGPar!U370 -> 0.016631692
C48: Serviço da Dívida (Juros + Amort. principal) | D48: =PROJ_AGCeAGPar!I372 -> -161.726 | E48: =PROJ_AGCeAGPar!J372 -> -24.687 | F48: =PROJ_AGCeAGPar!K372 -> -72.709321 | G48: =PROJ_AGCeAGPar!L372 -> -48.733949 | H48: =PROJ_AGCeAGPar!M372 -> -92.965734 | I48: =PROJ_AGCeAGPar!N372 -> -96.3703 | J48: =PROJ_AGCeAGPar!O372 -> -230.90192 | K48: =PROJ_AGCeAGPar!P372 -> -216.97467 | ... P48: =PROJ_AGCeAGPar!U372 -> -162.13091
B49: ICSD (FCF Ops. após Ativ. Invest./Serviço da Dívida) | D49: =D35/-D48 -> 1.4101196 | E49: =E35/-E48 -> -6.5437275 | F49: =F35/-F48 -> -1.3626107 | G49: =G35/-G48 -> 1.2242578 | H49: =H35/-H48 -> 4.1646534 | I49: =I35/-I48 -> 5.8605359 | J49: =J35/-J48 -> 2.8730015 | K49: =K35/-K48 -> 3.5587571 | ... P49: =P35/-P48 -> 8.486997
B52: CENÁRIO BASE | D52: 2010 | E52: 2011 | F52: =E52+1 -> 2012 | G52: =F52+1 -> 2013 | H52: =G52+1 -> 2014 | I52: =H52+1 -> 2015 | J52: =I52+1 -> 2016 | K52: =J52+1 -> 2017 | L52: =K52+1 -> 2018 | M52: =L52+1 -> 2019 | ... P52: =O52+1 -> 2022
B54: Construtora AG
B55: Receita Líquida de Vendas e Serviços | D55: =PROJ_ConsAG!I8 -> 4256.129 | E55: =PROJ_ConsAG!J8 -> 4337.532 | F55: =PROJ_ConsAG!K8 -> 4408.0692 | G55: =PROJ_ConsAG!L8 -> 4518.606 | H55: =PROJ_ConsAG!M8 -> 4618.0153 | I55: =PROJ_ConsAG!N8 -> 4726.5387 | J55: =PROJ_ConsAG!O8 -> 4844.7021 | K55: =PROJ_ConsAG!P8 -> 4958.5526 | ... P55: =PROJ_ConsAG!U8 -> 5605.8785
B56: Var. YoY% | E56: =PROJ_ConsAG!J9 -> 0.019126065 | F56: =PROJ_ConsAG!K9 -> 0.016262061 | G56: =PROJ_ConsAG!L9 -> 0.025076008 | H56: =PROJ_ConsAG!M9 -> 0.022 | I56: =PROJ_ConsAG!N9 -> 0.0235 | J56: =PROJ_ConsAG!O9 -> 0.025 | K56: =PROJ_ConsAG!P9 -> 0.0235 | L56: =PROJ_ConsAG!Q9 -> 0.024 | ... P56: =PROJ_ConsAG!U9 -> 0.025481122
B57: Elasticidade-PIB | E57: =PROJ_ConsAG!J10 -> 0.69988038 | F57: =PROJ_ConsAG!K10 -> 0.5 | G57: =PROJ_ConsAG!L10 -> 0.5 | H57: =PROJ_ConsAG!M10 -> 0.5 | I57: =PROJ_ConsAG!N10 -> 0.5 | J57: =PROJ_ConsAG!O10 -> 0.5 | K57: =PROJ_ConsAG!P10 -> 0.5 | L57: =PROJ_ConsAG!Q10 -> 0.5 | ... P57: =PROJ_ConsAG!U10 -> 0.5
B58: EBITDA | D58: =PROJ_ConsAG!I21 -> 564.021 | E58: =PROJ_ConsAG!J21 -> 682.931 | F58: =PROJ_ConsAG!K21 -> 652.7164 | G58: =PROJ_ConsAG!L21 -> 669.08392 | H58: =PROJ_ConsAG!M21 -> 683.80377 | I58: =PROJ_ConsAG!N21 -> 699.87316 | J58: =PROJ_ConsAG!O21 -> 717.36999 | K58: =PROJ_ConsAG!P21 -> 734.22818 | ... P58: =PROJ_ConsAG!U21 -> 830.07971
B59: Margem EBITDA | D59: =PROJ_ConsAG!I22 -> 0.13251971 | E59: =PROJ_ConsAG!J22 -> 0.15744691 | F59: =PROJ_ConsAG!K22 -> 0.14807308 | G59: =PROJ_ConsAG!L22 -> 0.14807308 | H59: =PROJ_ConsAG!M22 -> 0.14807308 | I59: =PROJ_ConsAG!N22 -> 0.14807308 | J59: =PROJ_ConsAG!O22 -> 0.14807308 | K59: =PROJ_ConsAG!P22 -> 0.14807308 | ... P59: =PROJ_ConsAG!U22 -> 0.14807308
B60: (=) Resultado Líquido | D60: =PROJ_ConsAG!I39 -> 364.1927 | E60: =PROJ_ConsAG!J39 -> 396.279 | F60: =PROJ_ConsAG!K39 -> 449.65118 | G60: =PROJ_ConsAG!L39 -> 463.47551 | H60: =PROJ_ConsAG!M39 -> 462.09428 | I60: =PROJ_ConsAG!N39 -> 450.95186 | J60: =PROJ_ConsAG!O39 -> 440.99893 | K60: =PROJ_ConsAG!P39 -> 433.81203 | ... P60: =PROJ_ConsAG!U39 -> 473.67175
C61: Var. YoY% | E61: =E60/D60-1 -> 0.088102535 | F61: =F60/E60-1 -> 0.13468335 | G61: =G60/F60-1 -> 0.030744561 | H61: =H60/G60-1 -> -0.0029801652 | I61: =I60/H60-1 -> -0.024112862 | J61: =J60/I60-1 -> -0.022070935 | K61: =K60/J60-1 -> -0.016296879 | L61: =L60/K60-1 -> 0.0057338067 | ... P61: =P60/O60-1 -> 0.0216356
C62: (+) Depreciação e Amortização | D62: =PROJ_ConsAG!I114 -> 75.428 | E62: =PROJ_ConsAG!J114 -> 67.101 | F62: =PROJ_ConsAG!K114 -> 84.967877 | G62: =PROJ_ConsAG!L114 -> 103.28278 | H62: =PROJ_ConsAG!M114 -> 122.00062 | I62: =PROJ_ConsAG!N114 -> 141.15832 | J62: =PROJ_ConsAG!O114 -> 160.79497 | K62: =PROJ_ConsAG!P114 -> 180.89307 | ... P62: =PROJ_ConsAG!U114 -> 289.04915
C63: (-) Resultado de Equivalência Patrimonial na AGPar | D63: =PROJ_ConsAG!I115 -> -91.328 | E63: =PROJ_ConsAG!J115 -> -200.847 | F63: =PROJ_ConsAG!K115 -> -198.36311 | G63: =PROJ_ConsAG!L115 -> -203.33727 | H63: =PROJ_ConsAG!M115 -> -207.81069 | I63: =PROJ_ConsAG!N115 -> -212.69424 | J63: =PROJ_ConsAG!O115 -> -218.0116 | K63: =PROJ_ConsAG!P115 -> -223.13487 | ... P63: =PROJ_ConsAG!U115 -> -252.26453
C64: Var. YoY% | E64: =E63/D63-1 -> 1.1991832 | F64: =F63/E63-1 -> -0.012367054 | G64: =G63/F63-1 -> 0.025076008 | H64: =H63/G63-1 -> 0.022 | I64: =I63/H63-1 -> 0.0235 | J64: =J63/I63-1 -> 0.025 | K64: =K63/J63-1 -> 0.0235 | L64: =L63/K63-1 -> 0.024 | ... P64: =P63/O63-1 -> 0.025481122
C65: (+) Dividendos e JSCP recebidos de controladas | D65: =PROJ_ConsAG!I116 -> 55.291 | E65: =PROJ_ConsAG!J116 -> 56.291 | F65: =PROJ_ConsAG!K116 -> 57.291 | G65: =PROJ_ConsAG!L116 -> 58.291 | H65: =PROJ_ConsAG!M116 -> 59.291 | I65: =PROJ_ConsAG!N116 -> 60.291 | J65: =PROJ_ConsAG!O116 -> 61.291 | K65: =PROJ_ConsAG!P116 -> 62.291 | ... P65: =PROJ_ConsAG!U116 -> 67.291
C66: (+/-) Variação Contas de Ativo e Passivo | D66: =PROJ_ConsAG!I117 -> -1498.665 | E66: =PROJ_ConsAG!J117 -> 793.062 | F66: =PROJ_ConsAG!K117 -> -4.8866972 | G66: =PROJ_ConsAG!L117 -> -267.40123 | H66: =PROJ_ConsAG!M117 -> -289.90063 | I66: =PROJ_ConsAG!N117 -> -279.83089 | J66: =PROJ_ConsAG!O117 -> -235.81258 | K66: =PROJ_ConsAG!P117 -> -107.95076 | ... P66: =PROJ_ConsAG!U117 -> -50.655166
C67: (+/-) Investimentos permanentes | D67: =PROJ_ConsAG!I120 -> -450.228 | E67: =PROJ_ConsAG!J120 -> -74.643 | F67: =PROJ_ConsAG!K120 -> 0 | G67: =PROJ_ConsAG!L120 -> 0 | H67: =PROJ_ConsAG!M120 -> 0 | I67: =PROJ_ConsAG!N120 -> 0 | J67: =PROJ_ConsAG!O120 -> 0 | K67: =PROJ_ConsAG!P120 -> 0 | ... P67: =PROJ_ConsAG!U120 -> 0
C68: (+/-) Ativos Fixos | D68: =PROJ_ConsAG!I121 -> -303.238 | E68: =PROJ_ConsAG!J121 -> -121.912 | F68: =PROJ_ConsAG!K121 -> -149.83882 | G68: =PROJ_ConsAG!L121 -> -153.71243 | H68: =PROJ_ConsAG!M121 -> -157.1747 | I68: =PROJ_ConsAG!N121 -> -160.92499 | J68: =PROJ_ConsAG!O121 -> -164.98798 | K68: =PROJ_ConsAG!P121 -> -168.89297 | ... P68: =PROJ_ConsAG!U121 -> -191.00945
B69: (=) FCF operacional após Atividades de Investimento | D69: =D60+D62+D63+D65+D66+D67+D68 -> -1848.5473 | E69: =E60+E62+E63+E65+E66+E67+E68 -> 915.331 | F69: =F60+F62+F63+F65+F66+F67+F68 -> 238.82143 | G69: =G60+G62+G63+G65+G66+G67+G68 -> 0.59837069 | H69: =H60+H62+H63+H65+H66+H67+H68 -> -11.50012 | I69: =I60+I62+I63+I65+I66+I67+I68 -> -1.0489379 | J69: =J60+J62+J63+J65+J66+J67+J68 -> 44.272748 | K69: =K60+K62+K63+K65+K66+K67+K68 -> 177.0175 | ... P69: =P60+P62+P63+P65+P66+P67+P68 -> 336.08276
C70: (+/-) Captação / (Amortização) de dívida | D70: =PROJ_ConsAG!I124 -> 782.746 | E70: =PROJ_ConsAG!J124 -> -333.119 | F70: =PROJ_ConsAG!K124 -> -198.156 | G70: =PROJ_ConsAG!L124 -> -26 | H70: =PROJ_ConsAG!M124 -> -42 | I70: =PROJ_ConsAG!N124 -> -78 | J70: =PROJ_ConsAG!O124 -> -35.702 | K70: =PROJ_ConsAG!P124 -> -25 | ... P70: =PROJ_ConsAG!U124 -> 0
C71: (+/-) Variação no Capital Social Líquida | D71: =PROJ_ConsAG!I125 -> 1970.8203 | E71: =PROJ_ConsAG!J125 -> 123.323 | F71: =PROJ_ConsAG!K125 -> -5.3396078 | G71: =PROJ_ConsAG!L125 -> -5.5037717 | H71: =PROJ_ConsAG!M125 -> -5.4873696 | I71: =PROJ_ConsAG!N125 -> -5.3550534 | J71: =PROJ_ConsAG!O125 -> -5.2368623 | K71: =PROJ_ConsAG!P125 -> -5.1515178 | ... P71: =PROJ_ConsAG!U125 -> -5.624852
C72: (-) Dividendos e juros sobre Capital Próprio pagos | D72: =PROJ_ConsAG!I126 -> -250 | E72: =PROJ_ConsAG!J126 -> -99.281 | F72: =PROJ_ConsAG!K126 -> -101.45255 | G72: =PROJ_ConsAG!L126 -> -104.57166 | H72: =PROJ_ConsAG!M126 -> -104.26002 | I72: =PROJ_ConsAG!N126 -> -101.74601 | J72: =PROJ_ConsAG!O126 -> -99.500385 | K72: =PROJ_ConsAG!P126 -> -97.878839 | ... P72: =PROJ_ConsAG!U126 -> -106.87219
B73: (=) Fluxo de Caixa Livre | D73: =D69+D70+D71+D72 -> 655.019 | E73: =E69+E70+E71+E72 -> 606.254 | F73: =F69+F70+F71+F72 -> -66.126725 | G73: =G69+G70+G71+G72 -> -135.47706 | H73: =H69+H70+H71+H72 -> -163.24751 | I73: =I69+I70+I71+I72 -> -186.15001 | J73: =J69+J70+J71+J72 -> -96.166499 | K73: =K69+K70+K71+K72 -> 48.987147 | ... P73: =P69+P70+P71+P72 -> 223.58572
B74: Caixa + Aplicações Financeiras | D74: =PROJ_ConsAG!I62+PROJ_ConsAG!I64 -> 655.019 | E74: =PROJ_ConsAG!J62+PROJ_ConsAG!J64 -> 1261.273 | F74: =PROJ_ConsAG!K62+PROJ_ConsAG!K64 -> 1195.1463 | G74: =PROJ_ConsAG!L62+PROJ_ConsAG!L64 -> 1059.6692 | H74: =PROJ_ConsAG!M62+PROJ_ConsAG!M64 -> 896.4217 | I74: =PROJ_ConsAG!N62+PROJ_ConsAG!N64 -> 710.27169 | J74: =PROJ_ConsAG!O62+PROJ_ConsAG!O64 -> 614.1052 | K74: =PROJ_ConsAG!P62+PROJ_ConsAG!P64 -> 663.09234 | ... P74: =PROJ_ConsAG!U62+PROJ_ConsAG!U64 -> 1553.4518
B75: Ativos Totais | D75: =PROJ_ConsAG!I82 -> 4665.587 | E75: =PROJ_ConsAG!J82 -> 5441.341 | F75: =PROJ_ConsAG!K82 -> 5287.0979 | G75: =PROJ_ConsAG!L82 -> 5417.531 | H75: =PROJ_ConsAG!M82 -> 5501.321 | I75: =PROJ_ConsAG!N82 -> 5556.4921 | J75: =PROJ_ConsAG!O82 -> 5696.5331 | K75: =PROJ_ConsAG!P82 -> 5966.9098 | ... P75: =PROJ_ConsAG!U82 -> 7829.5571
B76: Patrimônio Líquido | D76: =PROJ_ConsAG!I102 -> 2085.013 | E76: =PROJ_ConsAG!J102 -> 2505.334 | F76: =PROJ_ConsAG!K102 -> 2848.193 | G76: =PROJ_ConsAG!L102 -> 3201.5931 | H76: =PROJ_ConsAG!M102 -> 3553.94 | I76: =PROJ_ConsAG!N102 -> 3897.7908 | J76: =PROJ_ConsAG!O102 -> 4234.0525 | K76: =PROJ_ConsAG!P102 -> 4564.8342 | ... P76: =PROJ_ConsAG!U102 -> 6295.2569
C77: Divida CP | D77: =PROJ_ConsAG!I138 -> 343.408 | E77: =PROJ_ConsAG!J138 -> 198.848 | F77: =PROJ_ConsAG!K138 -> 26 | G77: =PROJ_ConsAG!L138 -> 42 | H77: =PROJ_ConsAG!M138 -> 78 | I77: =PROJ_ConsAG!N138 -> 35.702 | J77: =PROJ_ConsAG!O138 -> 25 | K77: =PROJ_ConsAG!P138 -> 44.769 | ... P77: =PROJ_ConsAG!U138 -> 0
C78: Divida LP | D78: =PROJ_ConsAG!I139 -> 439.338 | E78: =PROJ_ConsAG!J139 -> 250.779 | F78: =PROJ_ConsAG!K139 -> 225.471 | G78: =PROJ_ConsAG!L139 -> 183.471 | H78: =PROJ_ConsAG!M139 -> 105.471 | I78: =PROJ_ConsAG!N139 -> 69.769 | J78: =PROJ_ConsAG!O139 -> 44.769 | K78: =PROJ_ConsAG!P139 -> 0 | ... P78: =PROJ_ConsAG!U139 -> 0
B79: Dívida Total | D79: =PROJ_ConsAG!I140 -> 782.746 | E79: =PROJ_ConsAG!J140 -> 449.627 | F79: =PROJ_ConsAG!K140 -> 251.471 | G79: =PROJ_ConsAG!L140 -> 225.471 | H79: =PROJ_ConsAG!M140 -> 183.471 | I79: =PROJ_ConsAG!N140 -> 105.471 | J79: =PROJ_ConsAG!O140 -> 69.769 | K79: =PROJ_ConsAG!P140 -> 44.769 | ... P79: =PROJ_ConsAG!U140 -> 0
B80: Dívida Líquida | D80: =PROJ_ConsAG!I142 -> 127.727 | E80: =PROJ_ConsAG!J142 -> -811.646 | F80: =PROJ_ConsAG!K142 -> -943.67527 | G80: =PROJ_ConsAG!L142 -> -834.19821 | H80: =PROJ_ConsAG!M142 -> -712.9507 | I80: =PROJ_ConsAG!N142 -> -604.80069 | J80: =PROJ_ConsAG!O142 -> -544.3362 | K80: =PROJ_ConsAG!P142 -> -618.32334 | ... P80: =PROJ_ConsAG!U142 -> -1553.4518
B81: Dívida Líquida / EBITDA | D81: =PROJ_ConsAG!I143 -> 0.22645788 | E81: =PROJ_ConsAG!J143 -> -1.1884744 | F81: =PROJ_ConsAG!K143 -> -1.4457661 | G81: =PROJ_ConsAG!L143 -> -1.2467766 | H81: =PROJ_ConsAG!M143 -> -1.0426247 | I81: =PROJ_ConsAG!N143 -> -0.86415758 | J81: =PROJ_ConsAG!O143 -> -0.75879421 | K81: =PROJ_ConsAG!P143 -> -0.84214057 | ... P81: =PROJ_ConsAG!U143 -> -1.871449
B82: Dívida Total / PL | D82: =PROJ_ConsAG!I144 -> 0.37541541 | E82: =PROJ_ConsAG!J144 -> 0.17946789 | F82: =PROJ_ConsAG!K144 -> 0.088291418 | G82: =PROJ_ConsAG!L144 -> 0.070424627 | H82: =PROJ_ConsAG!M144 -> 0.051624676 | I82: =PROJ_ConsAG!N144 -> 0.027059174 | J82: =PROJ_ConsAG!O144 -> 0.016478067 | K82: =PROJ_ConsAG!P144 -> 0.0098073662 | ... P82: =PROJ_ConsAG!U144 -> 0
B83: EBITDA / Despesas Financeiras Líquidas | D83: =PROJ_ConsAG!I145 -> -26.228655 | E83: =PROJ_ConsAG!J145 -> 26.759571 | F83: =PROJ_ConsAG!K145 -> -7.8905158 | G83: =PROJ_ConsAG!L145 -> -8.2763333 | H83: =PROJ_ConsAG!M145 -> -8.3511584 | I83: =PROJ_ConsAG!N145 -> -9.961758 | J83: =PROJ_ConsAG!O145 -> -12.281814 | K83: =PROJ_ConsAG!P145 -> -14.188643 | ... P83: =PROJ_ConsAG!U145 -> -7.0826857
C84: Serviço da Dívida (Juros + Amort. principal) | D84: =PROJ_ConsAG!I147 -> -153.538 | E84: =PROJ_ConsAG!J147 -> -411.959 | F84: =PROJ_ConsAG!K147 -> -244.56705 | G84: =PROJ_ConsAG!L147 -> -44.059238 | H84: =PROJ_ConsAG!M147 -> -58.817647 | I84: =PROJ_ConsAG!N147 -> -90.482983 | J84: =PROJ_ConsAG!O147 -> -43.547716 | K84: =PROJ_ConsAG!P147 -> -30.261017 | ... P84: =PROJ_ConsAG!U147 -> 0
B85: ICSD (FCF Ops. após Ativ. Invest./Serviço da Dívida) | D85: =D69/-D84 -> -12.039673 | E85: =E69/-E84 -> 2.2218983 | F85: =F69/-F84 -> 0.97650699 | G85: =G69/-G84 -> 0.013581049 | H85: =H69/-H84 -> -0.19552159 | I85: =I69/-I84 -> -0.011592654 | J85: =J69/-J84 -> 1.0166491 | K85: =K69/-K84 -> 5.8496879 | L85: =L69/-L84 -> 5.4807235
B88: COMBINADO AGPar + ConsAG | D88: 2010 | E88: 2011 | F88: 2012 | G88: 2013 | H88: 2014 | I88: 2015 | J88: 2016 | K88: 2017 | L88: 2018 | M88: 2019 | N88: 2020 | O88: 2021 | P88: 2022
B89: Índice de Cobertura do Serviço da Dívida (ICSD)
B90: (A) FCFO após Ativ. Invest. + Caixa Inicial | E90: =D74+E69+D40+E35 -> 1439.732 | F90: =E74+F69+E40+F35 -> 1412.6119 | G90: =F74+G69+F40+G35 -> 1859.8949 | H90: =G74+H69+G40+H35 -> 2015.0706 | I90: =H74+I69+H40+I35 -> 2300.864 | J90: =I74+J69+I40+J35 -> 2511.3489 | K90: =J74+K69+J40+K35 -> 2808.727 | L90: =K74+L69+K40+L35 -> 3202.2431 | ... P90: =O74+P69+O40+P35 -> 5691.714
B91: (B) Serviço da Dívida (Juros + Amort. principal) | E91: =E84+E48 -> -436.646 | F91: =F84+F48 -> -317.27637 | G91: =G84+G48 -> -92.793187 | H91: =H84+H48 -> -151.78338 | I91: =I84+I48 -> -186.85328 | J91: =J84+J48 -> -274.44963 | K91: =K84+K48 -> -247.23569 | L91: =L84+L48 -> -249.59249 | ... P91: =P84+P48 -> -162.13091
B92: ICSD (A/B) | E92: =E90/-E91 -> 3.2972522 | F92: =F90/-F91 -> 4.4523074 | G92: =G90/-G91 -> 20.043442 | H92: =H90/-H91 -> 13.275963 | I92: =I90/-I91 -> 12.313746 | J92: =J90/-J91 -> 9.1504911 | K92: =K90/-K91 -> 11.360524 | L92: =L90/-L91 -> 12.829886 | ... P92: =P90/-P91 -> 35.105669

Sheet Projeção -->

Sheet PROJ_AGCeAGPar
I1: LEGENDA:
B2: MODELAGEM AG Concessões e AG Par (Controladoras) | I2: Dados Realizados Inputados | L2: VICTOR LOPES SCHMUTZLER
C3: (R$ milhões) | I3: Dados Realizados Calculados | L3: +55 (11) 3553-2529
I4: Dados Projetados Inputados
B5: 1. ESTRUTURA ACIONÁRIA AG CONCESSÕES (Controladora) | I5: Dados Projetados Calculados
C7: (Antes da Venda de Quiport e Aeris)
B43: 2. PROJEÇÕES AG CONCESSÕES (Controladora)
E46: 2006 | F46: 2007 | G46: 2008 | H46: 2009 | I46: 2010 | J46: 2011 | K46: 2012 | L46: 2013 | M46: 2014 | N46: 2015 | O46: 2016 | P46: 2017 | Q46: 2018 | R46: 2019 | S46: 2020 | T46: 2021 | U46: 2022
C48: CEMIG
C49: Receita Operacional Líquida | E49: 8605.143 | F49: 10245.914 | G49: 10890.322 | H49: 11705.083 | I49: 12863.33 | J49: 15814 | K49: =J49*(1+K51*K$379) -> 17561.086 | L49: =K49*(1+L51*L$379) -> 17649.159 | M49: =L49*(1+M51*M$379) -> 18581.034 | N49: =M49*(1+N51*N$379) -> 19367.012 | O49: =N49*(1+O51*O$379) -> 20529.033 | P49: =O49*(1+P51*P$379) -> 21879.843 | Q49: =P49*(1+Q51*Q$379) -> 22194.913 | R49: =Q49*(1+R51*R$379) -> 23173.708 | ... U49: =T49*(1+U51*U$379) -> 26862.887
C50: Var. % YoY | F50: =F49/E49-1 -> 0.1906733 | G50: =G49/F49-1 -> 0.062894145 | H50: =H49/G49-1 -> 0.074815143 | I50: =I49/H49-1 -> 0.098952481 | J50: =J49/I49-1 -> 0.22938617 | K50: =K49/J49-1 -> 0.11047719 | L50: =L49/K49-1 -> 0.0050152017 | M50: =M49/L49-1 -> 0.0528 | ... U50: =U49/T49-1 -> 0.061154693
C51: Elasticidade-PIBx | F51: =F50/F$379 -> 3.1281225 | G51: =G50/G$379 -> 1.2166861 | H51: =H50/H$379 -> -22.792259 | I51: =I50/I$379 -> 1.3134793 | J51: =J50/J$379 -> 8.3939315 | K51: 3.2 | L51: 0.1 | M51: 1.2 | N51: 0.9 | O51: 1.2 | P51: 1.4 | Q51: 0.3 | R51: 0.9 | S51: 0.6 | T51: 1.2 | U51: 1.2
C52: Lucro Líquido Ajustado | G52: 1887.035 | H52: 1861.4 | I52: 2257.976 | J52: 2415 | K52: =K54*K49 -> 2704.4073 | L52: =L54*L49 -> 2541.4788 | M52: =M54*M49 -> 2527.0207 | N52: =N54*N49 -> 2730.7487 | O52: =O54*O49 -> 2976.7097 | P52: =P54*P49 -> 3347.616 | Q52: =Q54*Q49 -> 3196.0674 | R52: =R54*R49 -> 3290.6666 | ... U52: =U54*U49 -> 4324.9248
C53: Var. % YoY | H53: =H52/G52-1 -> -0.013584804 | I53: =I52/H52-1 -> 0.21305254 | J53: =J52/I52-1 -> 0.069541926 | K53: =K52/J52-1 -> 0.11983738 | L53: =L52/K52-1 -> -0.060245526 | M53: =M52/L52-1 -> -0.0056888889 | N53: =N52/M52-1 -> 0.080619853 | O53: =O52/N52-1 -> 0.090070922 | ... U53: =U52/T52-1 -> 0.095166061
C54: Mg Líquida | G54: =G52/G49 -> 0.17327633 | H54: =H52/H49 -> 0.15902493 | I54: =I52/I49 -> 0.17553588 | J54: =J52/J49 -> 0.15271279 | K54: 0.154 | L54: 0.144 | M54: 0.136 | N54: 0.141 | O54: 0.145 | P54: 0.153 | Q54: 0.144 | R54: 0.142 | S54: 0.15 | T54: 0.156 | U54: 0.161
C55: Dividendos Distribuidos | G55: 943.517 | H55: 930.702 | I55: 1196.074 | J55: 1294.04 | K55: =K56*K52 -> 1352.2036 | L55: =L56*L52 -> 1270.7394 | M55: =M56*M52 -> 1263.5103 | N55: =N56*N52 -> 1365.3743 | O55: =O56*O52 -> 1488.3549 | P55: =P56*P52 -> 1673.808 | Q55: =Q56*Q52 -> 1598.0337 | R55: =R56*R52 -> 1645.3333 | ... U55: =U56*U52 -> 2162.4624
C56: Payout % (jun/dez ano seguinte) | G56: =G55/G52 -> 0.49999974 | H56: =H55/H52 -> 0.50000107 | I56: =I55/I52 -> 0.52971068 | J56: =J55/J52 -> 0.53583437 | K56: 0.5 | L56: =K56 -> 0.5 | M56: =L56 -> 0.5 | N56: =M56 -> 0.5 | O56: =N56 -> 0.5 | P56: =O56 -> 0.5 | Q56: =P56 -> 0.5 | R56: =Q56 -> 0.5 | S56: =R56 -> 0.5 | ... U56: =T56 -> 0.5
C57: Dividendos Propostos de AGC | G57: =G55*$D$59 -> 135.9608 | H57: =H55*$D$59 -> 134.11416 | I57: =I55*$D$59 -> 172.35426 | J57: =J55*$D$59 -> 186.47116 | K57: =K55*$D$59 -> 194.85254 | L57: =L55*$D$59 -> 183.11355 | M57: =M55*$D$59 -> 182.07184 | N57: =N55*$D$59 -> 196.75044 | ... U57: =U55*$D$59 -> 311.61083
C58: % do payout no período (ano 0) | G58: 0 | H58: 0 | I58: 0 | J58: 0 | K58: =J58 -> 0 | L58: =K58 -> 0 | M58: =L58 -> 0 | N58: =M58 -> 0 | O58: =N58 -> 0 | P58: =O58 -> 0 | Q58: =P58 -> 0 | R58: =Q58 -> 0 | ... U58: =T58 -> 0
C59: Participação de AGC (Dividendos recebidos caixa) | D59: 0.1441 | G59: =(F56*F52*$D$59) -> 0 | H59: 0 | I59: 0 | J59: =I57/J64 -> 107.70735 | K59: =((J57*(1-J58))+(K57*K58))/K64 -> 116.52927 | L59: =((K57*(1-K58))+(L57*L58))/L64 -> 121.76695 | M59: =((L57*(1-L58))+(M57*M58))/M64 -> 114.43103 | N59: =((M57*(1-M58))+(N57*N58))/N64 -> 113.78005 | O59: =((N57*(1-N58))+(O57*O58))/O64 -> 122.95298 | P59: =((O57*(1-O58))+(P57*P58))/P64 -> 134.02746 | Q59: =((P57*(1-P58))+(Q57*Q58))/Q64 -> 150.72766 | R59: =((Q57*(1-Q58))+(R57*R58))/R64 -> 143.90413 | ... U59: =((T57*(1-T58))+(U57*U58))/U64 -> 177.80988
C60: Patrimônio Líquido | E60: 7522.453 | F60: 8390.177 | G60: 9351.634 | H60: 10275.505 | I60: 11476.133 | J60: 11745 | K60: =J60+(1-K56)*K52 -> 13097.204 | L60: =K60+(1-L56)*L52 -> 14367.943 | M60: =L60+(1-M56)*M52 -> 15631.453 | N60: =M60+(1-N56)*N52 -> 16996.828 | O60: =N60+(1-O56)*O52 -> 18485.183 | P60: =O60+(1-P56)*P52 -> 20158.991 | Q60: =P60+(1-Q56)*Q52 -> 21757.024 | R60: =Q60+(1-R56)*R52 -> 23402.358 | ... U60: =T60+(1-U56)*U52 -> 29329.541
C61: Variação PL (Resultado Equivalencia Patrimonial AGC) | F61: =(F60-E60)*$D$59 -> 125.03903 | G61: =(G60-F60)*$D$59 -> 138.54595 | H61: =(H60-G60)*$D$59 -> 133.12981 | I61: =(I60-H60)*$D$59 -> 173.01049 | J61: =(J52*$D$59)/J64 -> 217.47255 | K61: =(K52*$D$59)/K64 -> 243.53389 | L61: =(L52*$D$59)/L64 -> 228.86206 | M61: =(M52*$D$59)/M64 -> 227.56009 | N61: =(N52*$D$59)/N64 -> 245.90595 | O61: =(O52*$D$59)/O64 -> 268.05493 | P61: =(P52*$D$59)/P64 -> 301.45531 | Q61: =(Q52*$D$59)/Q64 -> 287.80825 | ... U61: =(U52*$D$59)/U64 -> 389.4627
F62: =F60*$D$59 -> 1209.0245 | G62: =G60*$D$59 -> 1347.5705 | H62: =H60*$D$59 -> 1480.7003 | I62: =I60*$D$59 -> 1653.7108 | J62: =J60*$D$59 -> 1692.4545 | K62: =K60*$D$59 -> 1887.307 | L62: =L60*$D$59 -> 2070.4206 | M62: =M60*$D$59 -> 2252.4924 | ... U62: =U60*$D$59 -> 4226.3869
H63: PL Holding AGC Energia S.A. => | I63: 913.402 | J63: =1057.646 -> 1057.646 | K63: =K62/K64 -> 1179.4129 | L63: =L62/L64 -> 1293.844 | M63: =M62/M64 -> 1407.624 | N63: =N62/N64 -> 1530.577 | O63: =O62/O64 -> 1664.6045 | P63: =P62/P64 -> 1815.3321 | Q63: =Q62/Q64 -> 1959.2362 | R63: =R62/R64 -> 2107.3997 | ... U63: =U62/U64 -> 2641.147
H64: Ratio ajuste para Equivalencia AGC Energia S.A. => | I64: =I62/I63 -> 1.8104961 | J64: =J62/J63 -> 1.6002089 | K64: =J64 -> 1.6002089 | L64: =K64 -> 1.6002089 | M64: =L64 -> 1.6002089 | N64: =M64 -> 1.6002089 | O64: =N64 -> 1.6002089 | P64: =O64 -> 1.6002089 | Q64: =P64 -> 1.6002089 | R64: =Q64 -> 1.6002089 | ... U64: =T64 -> 1.6002089
C67: CCR
C68: Receita Operacional Líquida | H68: =3817.653-728.316 -> 3089.337 | I68: 3775.8538 | J68: 4577.5718 | K68: =J68*(1+K70*K$379) -> 5162.3074 | L68: =K68*(1+L70*L$379) -> 5809.5577 | M68: =L68*(1+M70*M$379) -> 6499.7331 | N68: =M68*(1+N70*N$379) -> 7171.8056 | O68: =N68*(1+O70*O$379) -> 7817.268 | P68: =O68*(1+P70*P$379) -> 8552.0912 | Q68: =P68*(1+Q70*Q$379) -> 9332.042 | R68: =Q68*(1+R70*R$379) -> 10200.855 | ... U68: =T68*(1+U70*U$379) -> 12513.621
C69: Var. % YoY | I69: =I68/H68-1 -> 0.22222142 | J69: =J68/I68-1 -> 0.21232759 | K69: =K68/J68-1 -> 0.12773925 | L69: =L68/K68-1 -> 0.12538004 | M69: =M68/L68-1 -> 0.1188 | N69: =N68/M68-1 -> 0.1034 | O69: =O68/N68-1 -> 0.09 | P69: =P68/O68-1 -> 0.094 | ... U69: =U68/T68-1 -> 0.061154693
C70: Elasticidade-PIBx | I70: =I69/I$379 -> 2.9497314 | J70: =J69/J$379 -> 7.7697067 | K70: 3.7 | L70: 2.5 | M70: 2.7 | N70: 2.2 | O70: 1.8 | P70: 2 | Q70: 1.9 | R70: 1.9 | S70: 1.8 | T70: 1.2 | U70: 1.2
C71: Lucro Líquido Ajustado | G71: 714 | H71: 709 | I71: 672 | J71: 899.36646 | K71: =K73*K68 -> 1269.9276 | L71: =L73*L68 -> 1638.2953 | M71: =M73*M68 -> 2027.9167 | N71: =N73*N68 -> 2517.3037 | O71: =O73*O68 -> 2915.841 | P71: =P73*P68 -> 3352.4198 | Q71: =Q73*Q68 -> 3732.8168 | R71: =R73*R68 -> 4284.3591 | ... U71: =U73*U68 -> 5806.3201
C72: Var. % YoY | I72: =I71/H71-1 -> -0.052186178 | J72: =J71/I71-1 -> 0.33834295 | K72: =K71/J71-1 -> 0.41202465 | L72: =L71/K71-1 -> 0.2900698 | M72: =M71/L71-1 -> 0.23782128 | N72: =N71/M71-1 -> 0.241325 | O72: =O71/N71-1 -> 0.15831909 | P72: =P71/O71-1 -> 0.14972654 | ... U72: =U71/T71-1 -> 0.14772908
C73: Mg Líquida | H73: =H71/H68 -> 0.22949908 | I73: =I71/I68 -> 0.17797299 | J73: =J71/J68 -> 0.19647239 | K73: 0.246 | L73: 0.282 | M73: 0.312 | N73: 0.351 | O73: 0.373 | P73: 0.392 | Q73: 0.4 | R73: 0.42 | S73: 0.433 | T73: 0.429 | U73: 0.464
C74: Dividendos Distribuidos | G74: 605 | H74: 569.11935 | I74: 851.14942 | J74: 796.923 | K74: =K75*K71 -> 1079.4385 | L74: =L75*L71 -> 1392.551 | M74: =M75*M71 -> 1723.7292 | N74: =N75*N71 -> 2139.7082 | O74: =O75*O71 -> 2478.4648 | P74: =P75*P71 -> 2849.5568 | Q74: =Q75*Q71 -> 3172.8943 | R74: =R75*R71 -> 3641.7053 | ... U74: =U75*U71 -> 4935.3721
C75: Payout % (dez e abr/mai ano seguinte) | G75: =G74/G71 -> 0.84733894 | H75: =H74/H71 -> 0.80270713 | I75: =I74/I71 -> 1.2665914 | J75: =J74/J71 -> 0.88609375 | K75: 0.85 | L75: 0.85 | M75: =L75 -> 0.85 | N75: =M75 -> 0.85 | O75: =N75 -> 0.85 | P75: =O75 -> 0.85 | Q75: =P75 -> 0.85 | R75: =Q75 -> 0.85 | S75: =R75 -> 0.85 | T75: =S75 -> 0.85 | U75: =T75 -> 0.85
C76: Dividendos Propostos de AGC | G76: =G74*$D$78 -> 101.24675 | H76: =H74*$D$78 -> 95.242124 | I76: =I74*$D$78 -> 142.43986 | J76: =J74*$D$78 -> 133.36506 | K76: =K74*$D$78 -> 180.64403 | L76: =L74*$D$78 -> 233.04341 | M76: =M74*$D$78 -> 288.46609 | N76: =N74*$D$78 -> 358.08016 | ... U76: =U74*$D$78 -> 825.93452
C77: % do payout no período (ano 0) | G77: 0 | H77: 0 | I77: 0 | J77: 0 | K77: 0.6 | L77: =K77 -> 0.6 | M77: =L77 -> 0.6 | N77: =M77 -> 0.6 | O77: =N77 -> 0.6 | P77: =O77 -> 0.6 | Q77: =P77 -> 0.6 | R77: =Q77 -> 0.6 | S77: =R77 -> 0.6 | ... U77: =T77 -> 0.6
C78: Participação de AGC (Dividendos recebidos caixa) | D78: 0.16735 | H78: 100.8 | I78: 141.5 | J78: 147.7 | K78: =(K76*K77) -> 108.38642 | L78: =(K76*(1-K77))+(L76*L77) -> 212.08366 | M78: =(L76*(1-L77))+(M76*M77) -> 266.29701 | N78: =(M76*(1-M77))+(N76*N77) -> 330.23453 | O78: =(N76*(1-N77))+(O76*O77) -> 392.09472 | P78: =(O76*(1-O77))+(P76*P77) -> 452.03243 | Q78: =(P76*(1-P77))+(Q76*Q77) -> 509.33965 | R78: =(Q76*(1-Q77))+(R76*R77) -> 578.05717 | S78: =(R76*(1-R77))+(S76*S77) -> 654.6859 | ... U78: =(T76*(1-T77))+(U76*U77) -> 783.4107
C79: Patrimônio Líquido | H79: 3345.171 | I79: 3182.387 | J79: 3267.625 | K79: =J79+(1-K75)*K71+300 -> 3758.1141 | L79: =K79+(1-L75)*L71 -> 4003.8584 | M79: =L79+(1-M75)*M71 -> 4308.0459 | N79: =M79+(1-N75)*N71 -> 4685.6415 | O79: =N79+(1-O75)*O71 -> 5123.0177 | P79: =O79+(1-P75)*P71 -> 5625.8806 | Q79: =P79+(1-Q75)*Q71 -> 6185.8031 | R79: =Q79+(1-R75)*R71 -> 6828.457 | S79: =R79+(1-S75)*S71 -> 7550.6316 | ... U79: =T79+(1-U75)*U71 -> 9180.4243
C80: Variação PL (Resultado Equivalencia Patrimonial AGC) | H80: =(H79-G79)*$D$78 -> 559.81437 | I80: =(I79-H79)*$D$78 -> -27.241902 | J80: =J71*$D$78 -> 150.50898 | K80: =K71*$D$78+360*D78 -> 272.76839 | L80: =L71*$D$78 -> 274.16871 | M80: =M71*$D$78 -> 339.37187 | N80: =N71*$D$78 -> 421.27078 | O80: =O71*$D$78 -> 487.96599 | P80: =P71*$D$78 -> 561.02745 | Q80: =Q71*$D$78 -> 624.68689 | R80: =R71*$D$78 -> 716.9875 | S80: =S71*$D$78 -> 805.70617 | ... U80: =U71*$D$78 -> 971.68767
C83: SANEPAR
C84: Receita Operacional Líquida | I84: 1480 | J84: 1743 | K84: =J84*(1+K379)*(1+K380)*(1+4%) -> 1969.8206 | L84: =K84*(1+L379)*(1+L380) -> 2194.3015 | M84: =L84*(1+M379)*(1+M380) -> 2393.9391 | N84: =M84*(1+N379)*(1+N380) -> 2619.2447 | O84: =N84*(1+O379)*(1+O380) -> 2873.9662 | P84: =O84*(1+P379)*(1+P380) -> 3129.4043 | Q84: =P84*(1+Q379)*(1+Q380) -> 3410.8004 | R84: =Q84*(1+R379)*(1+R380) -> 3721.0468 | S84: =R84*(1+S379)*(1+S380) -> 4063.3831 | ... U84: =T84*(1+U379)*(1+U380) -> 4852.0902
C85: Var. % YoY | J85: =J84/I84-1 -> 0.1777027 | K85: =K84/J84-1 -> 0.13013228 | L85: =L84/K84-1 -> 0.11396011 | M85: =M84/L84-1 -> 0.09098 | N85: =N84/M84-1 -> 0.094115 | O85: =O84/N84-1 -> 0.09725 | P85: =P84/O84-1 -> 0.08888 | Q85: =Q84/P84-1 -> 0.08992 | ... U85: =U84/T84-1 -> 0.093000734
C86: Elasticidade-PIBx | J86: =J85/J$379 -> 6.5026776 | K86: =K85/K$379 -> 3.7693148 | L86: =L85/L$379 -> 2.2722937 | M86: =M85/M$379 -> 2.0677273 | N86: =N85/N$379 -> 2.0024468 | O86: =O85/O$379 -> 1.945 | P86: =P85/P$379 -> 1.8910638 | Q86: =Q85/Q$379 -> 1.8733333 | ... U86: =U85/U$379 -> 1.8248948
C87: Lucro Líquido Ajustado | G87: 133.08108 | H87: 129.00819 | I87: 126.39207 | J87: =J90/J91 -> 237.5346 | K87: =K89*K84 -> 268.44552 | L87: =L89*L84 -> 299.0376 | M87: =M89*M84 -> 326.24404 | N87: =N89*N84 -> 356.9485 | O87: =O89*O84 -> 391.66174 | P87: =P89*P84 -> 426.47264 | Q87: =Q89*Q84 -> 464.82106 | R87: =R89*R84 -> 507.10118 | ... U87: =U89*U84 -> 661.23884
C88: Var. % YoY | J88: =J87/I87-1 -> 0.87934731 | K88: =K87/J87-1 -> 0.13013228 | L88: =L87/K87-1 -> 0.11396011 | M88: =M87/L87-1 -> 0.09098 | N88: =N87/M87-1 -> 0.094115 | O88: =O87/N87-1 -> 0.09725 | P88: =P87/O87-1 -> 0.08888 | Q88: =Q87/P87-1 -> 0.08992 | ... U88: =U87/T87-1 -> 0.093000734
C89: Mg Líquida | I89: =I87/I84 -> 0.085400049 | J89: =J87/J84 -> 0.13627917 | K89: =J89 -> 0.13627917 | L89: =K89 -> 0.13627917 | M89: =L89 -> 0.13627917 | N89: =M89 -> 0.13627917 | O89: =N89 -> 0.13627917 | P89: =O89 -> 0.13627917 | Q89: =P89 -> 0.13627917 | R89: =Q89 -> 0.13627917 | ... U89: =T89 -> 0.13627917
C90: Dividendos Distribuidos | G90: 39.86731 | H90: 39.012281 | I90: 37.200773 | J90: =59.38365 -> 59.38365 | K90: =K91*K87 -> 134.22276 | L90: =L91*L87 -> 149.5188 | M90: =M91*M87 -> 163.12202 | N90: =N91*N87 -> 178.47425 | O90: =O91*O87 -> 195.83087 | P90: =P91*P87 -> 213.23632 | Q90: =Q91*Q87 -> 232.41053 | R90: =R91*R87 -> 253.55059 | ... U90: =U91*U87 -> 330.61942
C91: Payout % (dez e abr/mai ano seguinte) | G91: =G90/G87 -> 0.29957159 | H91: =H90/H87 -> 0.30240158 | I91: =I90/I87 -> 0.29432837 | J91: 0.25 | K91: 0.5 | L91: =K91 -> 0.5 | M91: =L91 -> 0.5 | N91: =M91 -> 0.5 | O91: =N91 -> 0.5 | P91: =O91 -> 0.5 | Q91: =P91 -> 0.5 | R91: =Q91 -> 0.5 | S91: =R91 -> 0.5 | ... U91: =T91 -> 0.5
C92: Dividendos Propostos de AGC | G92: =G90*$D$94 -> 3.8272618 | H92: =H90*$D$94 -> 3.745179 | I92: =I90*$D$94 -> 3.5712742 | J92: =J90*$D$94 -> 5.7008304 | K92: =K90*$D$94 -> 12.885385 | L92: =L90*$D$94 -> 14.353805 | M92: =M90*$D$94 -> 15.659714 | N92: =N90*$D$94 -> 17.133528 | ... U92: =U90*$D$94 -> 31.739464
C93: % do payout no período (ano 0) | G93: 0 | H93: 0 | I93: 0 | J93: 0 | K93: 0 | L93: 0 | M93: 0 | N93: 0 | O93: 0 | P93: 0 | Q93: 0 | R93: 0 | S93: 0 | T93: 0 | U93: 0
C94: Participação de AGC (Dividendos recebidos caixa) | D94: 0.096 | I94: =(H92*(1-H93))+(I92*I93) -> 3.745179 | J94: =(I92*(1-I93))+(J92*J93) -> 3.5712742 | K94: =(J92*(1-J93))+(K92*K93) -> 5.7008304 | L94: =(K92*(1-K93))+(L92*L93) -> 12.885385 | M94: =(L92*(1-L93))+(M92*M93) -> 14.353805 | N94: =(M92*(1-M93))+(N92*N93) -> 15.659714 | O94: =(N92*(1-N93))+(O92*O93) -> 17.133528 | P94: =(O92*(1-O93))+(P92*P93) -> 18.799764 | ... U94: =(T92*(1-T93))+(U92*U93) -> 29.038832
C95: Patrimônio Líquido | H95: 2035.602 | I95: 2179.779 | J95: 2310.399 | K95: =J95+(1-K91)*K87 -> 2444.6218 | L95: =K95+(1-L91)*L87 -> 2594.1406 | M95: =L95+(1-M91)*M87 -> 2757.2626 | N95: =M95+(1-N91)*N87 -> 2935.7368 | O95: =N95+(1-O91)*O87 -> 3131.5677 | P95: =O95+(1-P91)*P87 -> 3344.804 | Q95: =P95+(1-Q91)*Q87 -> 3577.2145 | R95: =Q95+(1-R91)*R87 -> 3830.7651 | ... U95: =T95+(1-U91)*U87 -> 4740.7496
C96: Variação PL (Resultado Equivalencia Patrimonial AGC) | I96: =(I95-H95)*$D$94 -> 13.840992 | J96: =J87*$D$94 -> 22.803322 | K96: =K87*$D$94 -> 25.77077 | L96: =L87*$D$94 -> 28.70761 | M96: =M87*$D$94 -> 31.319428 | N96: =N87*$D$94 -> 34.267056 | O96: =O87*$D$94 -> 37.599527 | P96: =P87*$D$94 -> 40.941373 | Q96: =Q87*$D$94 -> 44.622821 | ... U96: =U87*$D$94 -> 63.478929
C99: WATERPORT
C100: Receita Operacional Líquida | I100: 26 | J100: 28 | K100: =J100*(1+K102*K379) -> 30.416688 | L100: =K100*(1+L102*L379) -> 33.467605 | M100: =L100*(1+M102*M379) -> 35.676467 | N100: =M100*(1+N102*N379) -> 37.68862 | O100: =N100*(1+O102*O379) -> 39.949937 | P100: =O100*(1+P102*P379) -> 42.203113 | Q100: =P100*(1+Q102*Q379) -> 44.634013 | R100: =Q100*(1+R102*R379) -> 47.258493 | ... U100: =T100*(1+U102*U379) -> 56.377479
C101: Var. % YoY | J101: =J100/I100-1 -> 0.076923077 | K101: =K100/J100-1 -> 0.086310303 | L101: =L100/K100-1 -> 0.10030403 | M101: =M100/L100-1 -> 0.066 | N101: =N100/M100-1 -> 0.0564 | O101: =O100/N100-1 -> 0.06 | P101: =P100/O100-1 -> 0.0564 | Q101: =Q100/P100-1 -> 0.0576 | ... U101: =U100/T100-1 -> 0.061154693
C102: Elasticidade-PIBx | J102: =J101/J$379 -> 2.8148473 | K102: 2.5 | L102: 2 | M102: 1.5 | N102: 1.2 | O102: 1.2 | P102: =O102 -> 1.2 | Q102: =P102 -> 1.2 | R102: =Q102 -> 1.2 | S102: =R102 -> 1.2 | T102: =S102 -> 1.2 | U102: =T102 -> 1.2
C103: Lucro Líquido Ajustado | I103: 17 | J103: 20 | K103: =K105*K100 -> 21.900016 | L103: =L105*L100 -> 24.096676 | M103: =M105*M100 -> 25.687056 | N103: =N105*N100 -> 27.135806 | O103: =O105*O100 -> 28.763955 | P103: =P105*P100 -> 30.386242 | Q103: =Q105*Q100 -> 32.136489 | R103: =R105*R100 -> 34.026115 | ... U103: =U105*U100 -> 40.591785
C104: Var. % YoY | J104: =J103/I103-1 -> 0.17647059 | K104: =K103/J103-1 -> 0.095000785 | L104: =L103/K103-1 -> 0.10030403 | M104: =M103/L103-1 -> 0.066 | N104: =N103/M103-1 -> 0.0564 | O104: =O103/N103-1 -> 0.06 | P104: =P103/O103-1 -> 0.0564 | Q104: =Q103/P103-1 -> 0.0576 | ... U104: =U103/T103-1 -> 0.061154693
C105: Mg Líquida | I105: =I103/I100 -> 0.65384615 | J105: =J103/J100 -> 0.71428571 | K105: 0.72 | L105: =K105 -> 0.72 | M105: =L105 -> 0.72 | N105: =M105 -> 0.72 | O105: =N105 -> 0.72 | P105: =O105 -> 0.72 | Q105: =P105 -> 0.72 | R105: =Q105 -> 0.72 | S105: =R105 -> 0.72 | ... U105: =T105 -> 0.72
C106: Dividendos Distribuidos | I106: 12.6 | J106: 19.2 | K106: =K107*K103 -> 21.024015 | L106: =L107*L103 -> 23.132809 | M106: =M107*M103 -> 24.659574 | N106: =N107*N103 -> 26.050374 | O106: =O107*O103 -> 27.613396 | P106: =P107*P103 -> 29.170792 | Q106: =Q107*Q103 -> 30.85103 | R106: =R107*R103 -> 32.66507 | ... U106: =U107*U103 -> 38.968113
C107: Payout % (dez) | I107: =I106/I103 -> 0.74117647 | J107: =J106/J103 -> 0.96 | K107: =J107 -> 0.96 | L107: =K107 -> 0.96 | M107: =L107 -> 0.96 | N107: =M107 -> 0.96 | O107: =N107 -> 0.96 | P107: =O107 -> 0.96 | Q107: =P107 -> 0.96 | R107: =Q107 -> 0.96 | ... U107: =T107 -> 0.96
C108: Dividendos Propostos de AGC | G108: =G106*$D$59 -> 0 | H108: =H106*$D$59 -> 0 | I108: =I106*$D$110 -> 12.6 | J108: =J106*$D$110 -> 19.2 | K108: =K106*$D$110 -> 21.024015 | L108: =L106*$D$110 -> 23.132809 | M108: =M106*$D$110 -> 24.659574 | N108: =N106*$D$110 -> 26.050374 | O108: =O106*$D$110 -> 27.613396 | P108: =P106*$D$110 -> 29.170792 | ... U108: =U106*$D$110 -> 38.968113
C109: % do payout no período (ano 0) | G109: 1 | H109: =G109 -> 1 | I109: =H109 -> 1 | J109: =I109 -> 1 | K109: =J109 -> 1 | L109: =K109 -> 1 | M109: =L109 -> 1 | N109: =M109 -> 1 | O109: =N109 -> 1 | ... U109: =T109 -> 1
C110: Participação de AGC (Dividendos recebidos caixa) | D110: 1 | I110: =(I107*I103*$D$110) -> 12.6 | J110: =(J107*J103*$D$110) -> 19.2 | K110: =(J108*(1-J109))+(K108*K109) -> 21.024015 | L110: =(K108*(1-K109))+(L108*L109) -> 23.132809 | M110: =(M107*M103*$D$110) -> 24.659574 | N110: =(N107*N103*$D$110) -> 26.050374 | O110: =(O107*O103*$D$110) -> 27.613396 | P110: =(P107*P103*$D$110) -> 29.170792 | Q110: =(Q107*Q103*$D$110) -> 30.85103 | R110: =(R107*R103*$D$110) -> 32.66507 | S110: =(S107*S103*$D$110) -> 34.624974 | T110: =(T107*T103*$D$110) -> 36.722368 | U110: =(U107*U103*$D$110) -> 38.968113
C111: Patrimônio Líquido | I111: 56.251 | J111: 56.034 | K111: =J111+(1-K107)*K103 -> 56.910001 | L111: =K111+(1-L107)*L103 -> 57.873868 | M111: =L111+(1-M107)*M103 -> 58.90135 | N111: =M111+(1-N107)*N103 -> 59.986782 | O111: =N111+(1-O107)*O103 -> 61.13734 | P111: =O111+(1-P107)*P103 -> 62.35279 | Q111: =P111+(1-Q107)*Q103 -> 63.63825 | R111: =Q111+(1-R107)*R103 -> 64.999294 | ... U111: =T111+(1-U107)*U103 -> 69.595771
C112: Variação PL (Resultado Equivalencia Patrimonial AGC) | I112: =(I111-H111)*$D$110 -> 56.251 | J112: =J103*$D$110 -> 20 | K112: =K103*$D$110 -> 21.900016 | L112: =L103*$D$110 -> 24.096676 | M112: =M103*$D$110 -> 25.687056 | N112: =N103*$D$110 -> 27.135806 | O112: =O103*$D$110 -> 28.763955 | P112: =P103*$D$110 -> 30.386242 | Q112: =Q103*$D$110 -> 32.136489 | ... U112: =U103*$D$110 -> 40.591785
C115: OUTROS INVESTIMENTOS (Light até fev/2010)
C116: Receita Operacional Líquida | I116: =135.67+61.539-I100 -> 171.209 | J116: =150.559+18.756-J100 -> 141.315 | K116: 60 | L116: 1 | M116: =L116 -> 1 | N116: =M116 -> 1 | O116: =N116 -> 1 | P116: =O116 -> 1 | Q116: =P116 -> 1 | R116: =Q116 -> 1 | S116: =R116 -> 1 | T116: =S116 -> 1 | U116: =T116 -> 1
C117: Var. % YoY | J117: =J116/I116-1 -> -0.17460531 | K117: =K116/J116-1 -> -0.57541662 | L117: =L116/K116-1 -> -0.98333333 | M117: =M116/L116-1 -> 0 | N117: =N116/M116-1 -> 0 | O117: =O116/N116-1 -> 0 | P117: =P116/O116-1 -> 0 | Q117: =Q116/P116-1 -> 0 | ... U117: =U116/T116-1 -> 0
C118: Elasticidade-PIBx | J118: =J117/J$379 -> -6.3893346 | K118: =K117/K$379 -> -16.66709 | L118: =L117/L$379 -> -19.607055 | M118: =M117/M$379 -> 0 | N118: =N117/N$379 -> 0 | O118: =O117/O$379 -> 0 | P118: =P117/P$379 -> 0 | Q118: =Q117/Q$379 -> 0 | ... U118: =U117/U$379 -> 0
C119: EBITDA | K119: 3456.5923 | L119: 3997.2781 | M119: 4597.1821 | N119: 5198.4408 | O119: 5767.6389 | P119: 6397.3123 | Q119: 7074.0471 | R119: 7901.8417 | S119: 8718.1189 | T119: 8110.0148 | U119: 7236.3993
C120: Mg EBITDA | I120: =I119/I116 -> 0 | J120: =J119/J116 -> 0 | K120: =K119/K116 -> 57.609872 | L120: =L119/L116 -> 3997.2781 | M120: =M119/M116 -> 4597.1821 | N120: =N119/N116 -> 5198.4408 | O120: =O119/O116 -> 5767.6389 | P120: =P119/P116 -> 6397.3123 | ... U120: =U119/U116 -> 7236.3993
C121: Lucro Líquido Ajustado | I121: =44.479+44.479-I103 -> 71.958 | J121: =85.719-5.491-J103 -> 60.228 | K121: =K123*K116 -> 25.8 | L121: 0 | M121: 0 | N121: 0 | O121: 0 | P121: 0 | Q121: 0 | R121: 0 | S121: 0 | T121: 0 | U121: 0
C122: Var. % YoY | J122: =J121/I121-1 -> -0.16301176 | K122: =K121/J121-1 -> -0.57162781 | L122: =L121/K121-1 -> -1 | M122: =M121/L121-1 -> #DIV/0! | N122: =N121/M121-1 -> #DIV/0! | O122: =O121/N121-1 -> #DIV/0! | P122: =P121/O121-1 -> #DIV/0! | Q122: =Q121/P121-1 -> #DIV/0! | ... U122: =U121/T121-1 -> #DIV/0!
C123: Mg Líquida | I123: =I121/I116 -> 0.42029333 | J123: =J121/J116 -> 0.42619679 | K123: 0.43 | L123: =L121/L116 -> 0 | M123: =M121/M116 -> 0 | N123: =N121/N116 -> 0 | O123: =O121/O116 -> 0 | P123: =P121/P116 -> 0 | Q123: =Q121/Q116 -> 0 | R123: =R121/R116 -> 0 | S123: =S121/S116 -> 0 | ... U123: =U121/U116 -> 0
C124: Dividendos Distribuidos | H124: =H128 -> 33.625675 | I124: =2*2.4 -> 4.8 | J124: =2*8.4 -> 16.8 | K124: =K125*K121 -> 6.966 | L124: =L125*L121 -> 0 | M124: =M125*M121 -> 0 | N124: =N125*N121 -> 0 | O124: =O125*O121 -> 0 | P124: =P125*P121 -> 0 | Q124: =Q125*Q121 -> 0 | R124: =R125*R121 -> 0 | ... U124: =U125*U121 -> 0
C125: Payout % (dez) | I125: =I124/I121 -> 0.066705578 | J125: =J124/J121 -> 0.27894003 | K125: 0.27 | L125: =K125 -> 0.27 | M125: =L125 -> 0.27 | N125: =M125 -> 0.27 | O125: =N125 -> 0.27 | P125: =O125 -> 0.27 | Q125: =P125 -> 0.27 | R125: =Q125 -> 0.27 | S125: =R125 -> 0.27 | ... U125: =T125 -> 0.27
C126: Dividendos Propostos de AGC | G126: =G124*$D$59 -> 0 | H126: =H124*$D$59 -> 4.8454598 | I126: =I124*$D$59 -> 0.69168 | J126: =J124*$D$59 -> 2.42088 | K126: =K124*$D$59 -> 1.0038006 | L126: =L124*$D$59 -> 0 | M126: =M124*$D$59 -> 0 | N126: =N124*$D$59 -> 0 | ... U126: =U124*$D$59 -> 0
C127: % do payout no período (ano 0) | G127: 0 | H127: 0 | I127: 0 | J127: 0 | K127: =J127 -> 0 | L127: =K127 -> 0
C128: Participação de AGC (Dividendos recebidos caixa) | D128: 1 | H128: 33.625675 | I128: =2.4 -> 2.4 | J128: 8.4 | K128: =K125*K121*$D$128 -> 6.966 | L128: =L125*L121*$D$128 -> 0 | M128: =M125*M121*$D$128 -> 0 | N128: =N125*N121*$D$128 -> 0 | O128: =O125*O121*$D$128 -> 0 | P128: =P125*P121*$D$128 -> 0 | Q128: =Q125*Q121*$D$128 -> 0 | R128: =R125*R121*$D$128 -> 0 | ... U128: =U125*U121*$D$128 -> 0
C129: Patrimônio Líquido Proporcional | I129: =69.439+102.894-0.045 -> 172.288 | J129: =113.758+107.084+7.741+77.022-0.691 -> 304.914 | K129: =113.758+77.022-0.691 -> 190.089 | L129: =K129+(1-L125)*L121 -> 190.089 | M129: =L129+(1-M125)*M121 -> 190.089 | N129: =M129+(1-N125)*N121 -> 190.089 | O129: =N129+(1-O125)*O121 -> 190.089 | P129: =O129+(1-P125)*P121 -> 190.089 | Q129: =P129+(1-Q125)*Q121 -> 190.089 | R129: =Q129+(1-R125)*R121 -> 190.089 | S129: =R129+(1-S125)*S121 -> 190.089 | ... U129: =T129+(1-U125)*U121 -> 190.089
C130: Variação PL (Resultado Equivalencia Patrimonial AGC) | I130: 55 | J130: =J121*50% -> 30.114 | K130: =(K129-J129)*$D$128 -> -114.825 | L130: =(L129-K129)*$D$128 -> 0 | M130: =(M129-L129)*$D$128 -> 0 | N130: =(N129-M129)*$D$128 -> 0 | O130: =(O129-N129)*$D$128 -> 0 | P130: =(P129-O129)*$D$128 -> 0 | Q130: =(Q129-P129)*$D$128 -> 0 | R130: =(R129-Q129)*$D$128 -> 0 | ... U130: =(U129-T129)*$D$128 -> 0
C133: Receita Líquida Consolidada das Controladas | F133: =(F116+F100+F84+F68+F49)*1000 -> 10245914 | G133: =(G116+G100+G84+G68+G49) -> 10890.322 | H133: =(H116+H100+H84+H68+H49) -> 14794.42 | I133: =(I116+I100+I84+I68+I49) -> 18316.393 | J133: =(J116+J100+J84+J68+J49) -> 22303.887 | K133: =(K116+K100+K84+K68+K49) -> 24783.631 | L133: =(L116+L100+L84+L68+L49) -> 25687.485 | M133: =(M116+M100+M84+M68+M49) -> 27511.383 | N133: =(N116+N100+N84+N68+N49) -> 29196.751 | ... U133: =(U116+U100+U84+U68+U49) -> 44285.975
C134: Lucro Líquido Consolidado das Controladas | F134: =F121+F103+F87+F71+F52 -> 0 | G134: =G121+G103+G87+G71+G52 -> 2734.1161 | H134: =H121+H103+H87+H71+H52 -> 2699.4082 | I134: =I121+I103+I87+I71+I52 -> 3145.3261 | J134: =J121+J103+J87+J71+J52 -> 3632.1291 | K134: =K121+K103+K87+K71+K52 -> 4290.4804 | L134: =L121+L103+L87+L71+L52 -> 4502.9084 | M134: =M121+M103+M87+M71+M52 -> 4906.8685 | ... U134: =U121+U103+U87+U71+U52 -> 10833.075
C135: Var. % YoY | J135: =J134/I134-1 -> 0.15477028 | K135: =K134/J134-1 -> 0.1812577 | L135: =L134/K134-1 -> 0.049511462 | M135: =M134/L134-1 -> 0.089710931 | N135: =N134/M134-1 -> 0.14780674 | O135: =O134/N134-1 -> 0.12088479 | P135: =P134/O134-1 -> 0.13367992 | Q135: =Q134/P134-1 -> 0.037578748 | ... U135: =U134/T134-1 -> 0.12244773
C136: Dividendos Distribuidos | F136: =F124+F106+F90+F74+F55 -> 0 | G136: =G124+G106+G90+G74+G55 -> 1588.3843 | H136: =H124+H106+H90+H74+H55 -> 1572.4593 | I136: =I124+I106+I90+I74+I55 -> 2101.8242 | J136: =J124+J106+J90+J74+J55 -> 2186.3466 | K136: =K124+K106+K90+K74+K55 -> 2593.8549 | L136: =L124+L106+L90+L74+L55 -> 2835.942 | M136: =M124+M106+M90+M74+M55 -> 3175.0212 | ... U136: =U124+U106+U90+U74+U55 -> 7467.422
C137: Var. % YoY | J137: =J136/I136-1 -> 0.040213856 | K137: =K136/J136-1 -> 0.18638775 | L137: =L136/K136-1 -> 0.093331019 | M137: =M136/L136-1 -> 0.11956491 | N137: =N136/M136-1 -> 0.16837242 | O137: =O136/N136-1 -> 0.12957081 | P137: =P136/O136-1 -> 0.13734408 | Q137: =Q136/P136-1 -> 0.056321966 | ... U137: =U136/T136-1 -> 0.12905287
C138: Dividendos a receber AG Concessões (proporcional) | F138: =F124+F106+F92+F76+F57 -> 0 | G138: =G124+G106+G92+G76+G57 -> 241.03481 | H138: =H124+H106+H92+H76+H57 -> 266.72714 | I138: =I124+I106+I92+I76+I57 -> 335.76539 | J138: =J124+J106+J92+J76+J57 -> 361.53706 | K138: =K124+K106+K92+K76+K57 -> 416.37197 | L138: =L124+L106+L92+L76+L57 -> 453.64357 | M138: =M124+M106+M92+M76+M57 -> 510.85721 | ... U138: =U124+U106+U92+U76+U57 -> 1208.2529
C139: Var. % YoY | H139: =H138/G138-1 -> 0.10659176 | I139: =I138/H138-1 -> 0.25883477 | J139: =J138/I138-1 -> 0.076754977 | K139: =K138/J138-1 -> 0.15167163 | L139: =L138/K138-1 -> 0.089515144 | M139: =M138/L138-1 -> 0.12612025 | N139: =N138/M138-1 -> 0.1706099 | O139: =O138/N138-1 -> 0.12983243 | ... U139: =U138/T138-1 -> 0.12929369
C140: Dividendos Recebidos AG Concessões (Caixa) | F140: 0 | G140: 180 | H140: 190.742 | I140: 227.108 | J140: 271.275 | K140: =K128+K110+K94+K78+K59 -> 258.60653 | L140: =L128+L110+L94+L78+L59 -> 369.86879 | M140: =M128+M110+M94+M78+M59 -> 419.74142 | N140: =N128+N110+N94+N78+N59 -> 485.72467 | O140: =O128+O110+O94+O78+O59 -> 559.79462 | P140: =P128+P110+P94+P78+P59 -> 634.03045 | Q140: =Q128+Q110+Q94+Q78+Q59 -> 711.38902 | R140: =R128+R110+R94+R78+R59 -> 776.93778 | ... U140: =U128+U110+U94+U78+U59 -> 1029.2275
C141: Var. % YoY | H141: =H140/G140-1 -> 0.059677778 | I141: =I140/H140-1 -> 0.19065544 | J141: =J140/I140-1 -> 0.19447576 | K141: =K140/J140-1 -> -0.046699738 | L141: =L140/K140-1 -> 0.43023765 | M141: =M140/L140-1 -> 0.13483871 | N141: =N140/M140-1 -> 0.15719974 | O141: =O140/N140-1 -> 0.1524937 | ... U141: =U140/T140-1 -> 0.10643011
C142: Equivalencia Patrimonial Bruta | H142: =H130+H112+H96+H80+H61 -> 692.94418 | I142: =I130+I112+I96+I80+I61 -> 270.86058 | J142: =J130+J112+J96+J80+J61 -> 440.89885 | K142: =K130+K112+K96+K80+K61 -> 449.14806 | L142: =L130+L112+L96+L80+L61 -> 555.83506 | M142: =M130+M112+M96+M80+M61 -> 623.93844 | N142: =N130+N112+N96+N80+N61 -> 728.5796 | O142: =O130+O112+O96+O80+O61 -> 822.3844 | ... U142: =U130+U112+U96+U80+U61 -> 1465.2211
C145: DRE | E145: 2006 | F145: 2007 | G145: 2008 | H145: 2009 | I145: 2010 | J145: 2011 | K145: 2012 | L145: 2013 | M145: 2014 | N145: 2015 | O145: 2016 | P145: 2017 | Q145: 2018 | R145: 2019 | S145: 2020 | T145: 2021 | U145: 2022
C146: Receita Líquida de Venda de Bens e/ou Serviços | F146: 8.893 | G146: 8.904 | H146: 10.127 | I146: 16.374 | J146: 19.156 | K146: =K148*K133 -> 24.783631 | L146: =L148*L133 -> 25.687485 | M146: =M148*M133 -> 27.511383 | N146: =N148*N133 -> 29.196751 | O146: =O148*O133 -> 31.261217 | P146: =P148*P133 -> 33.604542 | Q146: =Q148*Q133 -> 34.983389 | R146: =R148*R133 -> 37.143869 | ... U146: =U148*U133 -> 44.285975
C147: Var. % YoY | G147: =G146/F146-1 -> 0.0012369279 | H147: =H146/G146-1 -> 0.137354 | I147: =I146/H146-1 -> 0.6168658 | J147: =J146/I146-1 -> 0.16990351 | K147: =K146/J146-1 -> 0.29377902 | L147: =L146/K146-1 -> 0.036469821 | M147: =M146/L146-1 -> 0.071003347 | N147: =N146/M146-1 -> 0.061260748 | ... U147: =U146/T146-1 -> 0.064551543
C148: % Receita Líquida das Controladas | F148: =F146/F133 -> 8.6795575e-07 | G148: =G146/G133 -> 0.00081760668 | H148: =H146/H133 -> 0.00068451484 | I148: =I146/I133 -> 0.00089395331 | J148: =J146/J133 -> 0.00085886376 | K148: 0.001 | L148: =K148 -> 0.001 | M148: =L148 -> 0.001 | N148: =M148 -> 0.001 | O148: =N148 -> 0.001 | P148: =O148 -> 0.001 | Q148: =P148 -> 0.001 | R148: =Q148 -> 0.001 | S148: =R148 -> 0.001 | ... U148: =T148 -> 0.001
C149: (-) Custo dos Bens e/ou Serviços Vendidos | F149: -5.022 | G149: -5.478 | H149: -5.018 | I149: -5.825 | J149: -9.16 | K149: =-K150*K146 -> -11.851016 | L149: =-L150*L146 -> -12.28322 | M149: =-M150*M146 -> -13.15537 | N149: =-N150*N146 -> -13.961278 | O149: =-O150*O146 -> -14.948462 | P149: =-P150*P146 -> -16.068992 | Q149: =-Q150*Q146 -> -16.728328 | R149: =-R150*R146 -> -17.761424 | ... U149: =-U150*U146 -> -21.176631
C150: % Receita Líquida | F150: =-F149/F146 -> 0.56471382 | G150: =-G149/G146 -> 0.61522911 | H150: =-H149/H146 -> 0.49550706 | I150: =-I149/I146 -> 0.35574692 | J150: =-J149/J146 -> 0.47817916 | K150: =J150 -> 0.47817916 | L150: =K150 -> 0.47817916 | M150: =L150 -> 0.47817916 | N150: =M150 -> 0.47817916 | O150: =N150 -> 0.47817916 | P150: =O150 -> 0.47817916 | Q150: =P150 -> 0.47817916 | R150: =Q150 -> 0.47817916 | ... U150: =T150 -> 0.47817916
C151: (=) Resultado Bruto | F151: =F146+F149 -> 3.871 | G151: =G146+G149 -> 3.426 | H151: =H146+H149 -> 5.109 | I151: =I146+I149 -> 10.549 | J151: =J146+J149 -> 9.996 | K151: =K146+K149 -> 12.932615 | L151: =L146+L149 -> 13.404265 | M151: =M146+M149 -> 14.356013 | ... U151: =U146+U149 -> 23.109345
...

Sheet PROJ_ConsAG
I1: LEGENDA:
B2: MODELAGEM ConAG (Consolidado) | I2: Dados Realizados Inputados | L2: VICTOR LOPES SCHMUTZLER
C3: (R$ milhões) | I3: Dados Realizados Calculados | L3: +55 (11) 3553-2529
I4: Dados Projetados Inputados
I5: Dados Projetados Calculados
C7: DRE | E7: 2006 | F7: 2007 | G7: 2008 | H7: 2009 | I7: 2010 | J7: 2011 | K7: 2012 | L7: 2013 | M7: 2014 | N7: 2015 | O7: 2016 | P7: 2017 | Q7: 2018 | R7: 2019 | S7: 2020 | T7: 2021 | U7: 2022
C8: Receita Líquida de Vendas e Serviços | I8: 4256.129 | J8: 4337.532 | K8: =J8*(1+K10*K207) -> 4408.0692 | L8: =K8*(1+L10*L207) -> 4518.606 | M8: =L8*(1+M10*M207) -> 4618.0153 | N8: =M8*(1+N10*N207) -> 4726.5387 | O8: =N8*(1+O10*O207) -> 4844.7021 | P8: =O8*(1+P10*P207) -> 4958.5526 | Q8: =P8*(1+Q10*Q207) -> 5077.5579 | R8: =Q8*(1+R10*R207) -> 5201.9581 | ... U8: =T8*(1+U10*U207) -> 5605.8785
C9: Var. % YoY | J9: =J8/I8-1 -> 0.019126065 | K9: =K8/J8-1 -> 0.016262061 | L9: =L8/K8-1 -> 0.025076008 | M9: =M8/L8-1 -> 0.022 | N9: =N8/M8-1 -> 0.0235 | O9: =O8/N8-1 -> 0.025 | P9: =P8/O8-1 -> 0.0235 | Q9: =Q8/P8-1 -> 0.024 | ... U9: =U8/T8-1 -> 0.025481122
C10: Elasticidade-PIB | J10: =J9/J207 -> 0.69988038 | K10: 0.5 | L10: =K10 -> 0.5 | M10: =L10 -> 0.5 | N10: =M10 -> 0.5 | O10: =N10 -> 0.5 | P10: =O10 -> 0.5 | Q10: =P10 -> 0.5 | R10: =Q10 -> 0.5 | S10: =R10 -> 0.5 | ... U10: =T10 -> 0.5
C11: (-) Custo dos Bens e/ou Serviços Vendidos | I11: -3327.617 | J11: -3456.696 | K11: =K12*K8 -> -3512.909 | L11: =L12*L8 -> -3600.9987 | M11: =M12*M8 -> -3680.2207 | N11: =N12*N8 -> -3766.7059 | O11: =O12*O8 -> -3860.8735 | P11: =P12*P8 -> -3951.6041 | Q11: =Q12*Q8 -> -4046.4426 | R11: =R12*R8 -> -4145.5804 | ... U11: =U12*U8 -> -4467.4754
C12: % Receita Líquida | I12: =I11/I8 -> -0.7818412 | J12: =J11/J8 -> -0.79692692 | K12: =J12 -> -0.79692692 | L12: =K12 -> -0.79692692 | M12: =L12 -> -0.79692692 | N12: =M12 -> -0.79692692 | O12: =N12 -> -0.79692692 | P12: =O12 -> -0.79692692 | Q12: =P12 -> -0.79692692 | R12: =Q12 -> -0.79692692 | ... U12: =T12 -> -0.79692692
C13: (=) Resultado Bruto | I13: =I8+I11 -> 928.512 | J13: =J8+J11 -> 880.836 | K13: =K8+K11 -> 895.16021 | L13: =L8+L11 -> 917.60725 | M13: =M8+M11 -> 937.79461 | N13: =N8+N11 -> 959.83279 | O13: =O8+O11 -> 983.82861 | P13: =P8+P11 -> 1006.9486 | ... U13: =U8+U11 -> 1138.403
C14: Var. % YoY | J14: =J13/I13-1 -> -0.051346671 | K14: =K13/J13-1 -> 0.016262061 | L14: =L13/K13-1 -> 0.025076008 | M14: =M13/L13-1 -> 0.022 | N14: =N13/M13-1 -> 0.0235 | O14: =O13/N13-1 -> 0.025 | P14: =P13/O13-1 -> 0.0235 | Q14: =Q13/P13-1 -> 0.024 | ... U14: =U13/T13-1 -> 0.025481122
C15: (-) (Despesas)/Receitas Operacionais (ex equiv. Patr) | I15: =-439.919+75.428-I18 -> -455.819 | J15: =-265.006+67.101-J18 -> -398.752 | K15: =K17*K8 -> -440.80692 | L15: =L17*L8 -> -451.8606 | M15: =M17*M8 -> -461.80153 | N15: =N17*N8 -> -472.65387 | O15: =O17*O8 -> -484.47021 | P15: =P17*P8 -> -495.85526 | Q15: =Q17*Q8 -> -507.75579 | R15: =R17*R8 -> -520.19581 | ... U15: =U17*U8 -> -560.58785
C16: Var. % YoY | J16: =J15/I15-1 -> -0.12519662 | K16: =K15/J15-1 -> 0.10546636 | L16: =L15/K15-1 -> 0.025076008 | M16: =M15/L15-1 -> 0.022 | N16: =N15/M15-1 -> 0.0235 | O16: =O15/N15-1 -> 0.025 | P16: =P15/O15-1 -> 0.0235 | Q16: =Q15/P15-1 -> 0.024 | ... U16: =U15/T15-1 -> 0.025481122
C17: % Receita Líquida | I17: =I15/I8 -> -0.10709708 | J17: =J15/J8 -> -0.091930619 | K17: -0.1 | L17: =K17 -> -0.1 | M17: =L17 -> -0.1 | N17: =M17 -> -0.1 | O17: =N17 -> -0.1 | P17: =O17 -> -0.1 | Q17: =P17 -> -0.1 | R17: =Q17 -> -0.1 | S17: =R17 -> -0.1 | ... U17: =T17 -> -0.1
C18: (+/-) Resultado de Equivalência Patrimonial | I18: 91.328 | J18: 200.847 | K18: =K20*K8 -> 198.36311 | L18: =L20*L8 -> 203.33727 | M18: =M20*M8 -> 207.81069 | N18: =N20*N8 -> 212.69424 | O18: =O20*O8 -> 218.0116 | P18: =P20*P8 -> 223.13487 | Q18: =Q20*Q8 -> 228.49011 | R18: =R20*R8 -> 234.08811 | ... U18: =U20*U8 -> 252.26453
C19: Var. % YoY | J19: =J18/I18-1 -> 1.1991832 | K19: =K18/J18-1 -> -0.012367054 | L19: =L18/K18-1 -> 0.025076008 | M19: =M18/L18-1 -> 0.022 | N19: =N18/M18-1 -> 0.0235 | O19: =O18/N18-1 -> 0.025 | P19: =P18/O18-1 -> 0.0235 | Q19: =Q18/P18-1 -> 0.024 | ... U19: =U18/T18-1 -> 0.025481122
C20: % Receita Líquida | I20: =I18/I8 -> 0.021457996 | J20: =J18/J8 -> 0.046304442 | K20: 0.045 | L20: =K20 -> 0.045 | M20: =L20 -> 0.045 | N20: =M20 -> 0.045 | O20: =N20 -> 0.045 | P20: =O20 -> 0.045 | Q20: =P20 -> 0.045 | R20: =Q20 -> 0.045 | S20: =R20 -> 0.045 | ... U20: =T20 -> 0.045
C21: (=) EBITDA | I21: =I13+I15+I18 -> 564.021 | J21: =J13+J15+J18 -> 682.931 | K21: =K13+K15+K18 -> 652.7164 | L21: =L13+L15+L18 -> 669.08392 | M21: =M13+M15+M18 -> 683.80377 | N21: =N13+N15+N18 -> 699.87316 | O21: =O13+O15+O18 -> 717.36999 | P21: =P13+P15+P18 -> 734.22818 | ... U21: =U13+U15+U18 -> 830.07971
C22: % Margem EBITDA | I22: =I21/I8 -> 0.13251971 | J22: =J21/J8 -> 0.15744691 | K22: =K21/K8 -> 0.14807308 | L22: =L21/L8 -> 0.14807308 | M22: =M21/M8 -> 0.14807308 | N22: =N21/N8 -> 0.14807308 | O22: =O21/O8 -> 0.14807308 | P22: =P21/P8 -> 0.14807308 | ... U22: =U21/U8 -> 0.14807308
C23: Var. % YoY | J23: =J21/I21-1 -> 0.21082548 | K23: =K21/J21-1 -> -0.044242534 | L23: =L21/K21-1 -> 0.025076008 | M23: =M21/L21-1 -> 0.022 | N23: =N21/M21-1 -> 0.0235 | O23: =O21/N21-1 -> 0.025 | P23: =P21/O21-1 -> 0.0235 | Q23: =Q21/P21-1 -> 0.024 | ... U23: =U21/T21-1 -> 0.025481122
C24: (-) Depreciação e Amortização | I24: -75.428 | J24: -67.101 | K24: =K50 -> -84.967877 | L24: =L50 -> -103.28278 | M24: =M50 -> -122.00062 | N24: =N50 -> -141.15832 | O24: =O50 -> -160.79497 | P24: =P50 -> -180.89307 | Q24: =Q50 -> -201.47354 | R24: =R50 -> -222.55822 | ... U24: =U50 -> -289.04915
C26: (=) EBIT | I26: =I21+I24 -> 488.593 | J26: =J21+J24 -> 615.83 | K26: =K21+K24 -> 567.74853 | L26: =L21+L24 -> 565.80114 | M26: =M21+M24 -> 561.80315 | N26: =N21+N24 -> 558.71484 | O26: =O21+O24 -> 556.57502 | P26: =P21+P24 -> 553.33511 | ... U26: =U21+U24 -> 541.03056
C27: % Margem EBIT | I27: =I26/I8 -> 0.11479751 | J27: =J26/J8 -> 0.14197705 | K27: =K26/K8 -> 0.12879755 | L27: =L26/L8 -> 0.12521586 | M27: =M26/M8 -> 0.12165467 | N27: =N26/N8 -> 0.11820803 | O27: =O26/O8 -> 0.11488323 | P27: =P26/P8 -> 0.11159206 | ... U27: =U26/U8 -> 0.09651129
C29: (+/-) Resultado Financeiro | I29: =I30+I31+I32 -> -24.2543 | J29: =J30+J31+J32 -> -77.075 | K29: =K30+K31+K32 -> 58.453055 | L29: =L30+L31+L32 -> 78.832877 | M29: =M30+M31+M32 -> 80.98922 | N29: =N30+N31+N32 -> 69.220981 | O29: =O30+O31+O32 -> 58.090226 | P29: =P30+P31+P32 -> 51.747597 | ... U29: =U30+U31+U32 -> 117.19844
C30: Receitas Financeiras | I30: 175.042 | J30: 53.319 | K30: =K199 -> 106.0201 | L30: =L199 -> 96.892115 | M30: =M199 -> 97.806867 | N30: =N199 -> 81.703964 | O30: =O199 -> 65.935942 | P30: =P199 -> 57.008614 | Q30: =Q199 -> 60.028424 | R30: =R199 -> 69.728436 | ... U30: =U199 -> 117.19844
C31: Despesas Financeiras | I31: -153.538 | J31: -78.84 | K31: =K162+K189+K171 -> -23.298464 | L31: =L162+L189+L171 -> -16.049077 | M31: =M162+M189+M171 -> -15.92556 | N31: =N162+N189+N171 -> -11.447976 | O31: =O162+O189+O171 -> -7.5268177 | P31: =P162+P189+P171 -> -5.2610167 | Q31: =Q162+Q189+Q171 -> -2.0053154 | R31: =R162+R189+R171 -> 0 | ... U31: =U162+U189+U171 -> 0
C32: Variação Cambial, líquida | I32: -45.7583 | J32: -51.554 | K32: =-K187 -> -24.268584 | L32: =-L187 -> -2.0101605 | M32: =-M187 -> -0.89208718 | N32: =-N187 -> -1.0350076 | O32: =-O187 -> -0.31889832 | P32: =-P187 -> 0 | Q32: =-Q187 -> 0 | R32: =-R187 -> 0 | ... U32: =-U187 -> 0
C33: (=) EBT | I33: =I26+I29 -> 464.3387 | J33: =J26+J29 -> 538.755 | K33: =K26+K29 -> 626.20158 | L33: =L26+L29 -> 644.63402 | M33: =M26+M29 -> 642.79237 | N33: =N26+N29 -> 627.93582 | O33: =O26+O29 -> 614.66525 | P33: =P26+P29 -> 605.0827 | ... U33: =U26+U29 -> 658.229
C34: (-) Imposto de Renda e Contribuição Social sobre o Lucro | I34: =I36+I38 -> -100.146 | J34: =J36+J38 -> -142.476 | K34: =K36+K38 -> -176.55039 | L34: =L36+L38 -> -181.1585 | M34: =M36+M38 -> -180.69809 | N34: =N36+N38 -> -176.98395 | O34: =O36+O38 -> -173.66631 | P34: =P36+P38 -> -171.27068 | ... U34: =U36+U38 -> -184.55725
C35: % EBT | I35: =I34/I33 -> -0.21567446 | J35: =J34/J33 -> -0.26445416 | K35: =K34/K33 -> -0.2819386 | L35: =L34/L33 -> -0.28102536 | M35: =M34/M33 -> -0.28111425 | N35: =N34/N33 -> -0.28185039 | O35: =O34/O33 -> -0.28253804 | P35: =P34/P33 -> -0.28305333 | ... U35: =U34/U33 -> -0.28038456
C36: Corrente | I36: -108.324 | J36: -107.994 | K36: =K37*K33 -> -156.55039 | L36: =L37*L33 -> -161.1585 | M36: =M37*M33 -> -160.69809 | N36: =N37*N33 -> -156.98395 | O36: =O37*O33 -> -153.66631 | P36: =P37*P33 -> -151.27068 | Q36: =Q37*Q33 -> -152.09981 | R36: =R37*R33 -> -154.36005 | ... U36: =U37*U33 -> -164.55725
C37: % EBT | I37: =I36/I33 -> -0.23328661 | J37: =J36/J33 -> -0.20045104 | K37: -0.25 | L37: =K37 -> -0.25 | M37: =L37 -> -0.25 | N37: =M37 -> -0.25 | O37: =N37 -> -0.25 | P37: =O37 -> -0.25 | Q37: =P37 -> -0.25 | R37: =Q37 -> -0.25 | S37: =R37 -> -0.25 | ... U37: =T37 -> -0.25
C38: Diferido | I38: 8.178 | J38: -34.482 | K38: -20 | L38: -20 | M38: -20 | N38: -20 | O38: -20 | P38: -20 | Q38: -20 | R38: -20 | S38: -20 | T38: -20 | U38: -20
C39: (=) Lucro/Prejuízo do Período | I39: =I33+I34 -> 364.1927 | J39: =J33+J34 -> 396.279 | K39: =K33+K34 -> 449.65118 | L39: =L33+L34 -> 463.47551 | M39: =M33+M34 -> 462.09428 | N39: =N33+N34 -> 450.95186 | O39: =O33+O34 -> 440.99893 | P39: =P33+P34 -> 433.81203 | ... U39: =U33+U34 -> 473.67175
C40: % Receita Líquida | I40: =I39/I8 -> 0.085568999 | J40: =J39/J8 -> 0.091360479 | K40: =K39/K8 -> 0.10200638 | L40: =L39/L8 -> 0.10257046 | M40: =M39/M8 -> 0.10006339 | N40: =N39/N8 -> 0.095408478 | O40: =O39/O8 -> 0.091027048 | P40: =P39/P8 -> 0.087487632 | ... U40: =U39/U8 -> 0.084495544
B42: Mutações PL
C43: (-) Reserva Legal | D43: 0.05 | I43: =I39*5% -> 18.209635 | J43: =J39*5% -> 19.81395 | K43: =K39*5% -> 22.482559 | L43: =L39*5% -> 23.173776 | M43: =M39*5% -> 23.104714 | N43: =N39*5% -> 22.547593 | O43: =O39*5% -> 22.049947 | P43: =P39*5% -> 21.690601 | ... U43: =U39*5% -> 23.683587
C44: (-) Dividendos a pagar | I44: =250+I91 -> 256.742 | J44: =99.281+J91 -> 100.858 | K44: =MAX(0,(K39-K43)*K45) -> 106.79216 | L44: =MAX(0,(L39-L43)*L45) -> 110.07543 | M44: =MAX(0,(M39-M43)*M45) -> 109.74739 | N44: =MAX(0,(N39-N43)*N45) -> 107.10107 | O44: =MAX(0,(O39-O43)*O45) -> 104.73725 | P44: =MAX(0,(P39-P43)*P45) -> 103.03036 | Q44: =MAX(0,(Q39-Q43)*Q45) -> 103.62111 | R44: =MAX(0,(R39-R43)*R45) -> 105.23153 | ... U44: =MAX(0,(U39-U43)*U45) -> 112.49704
C45: % Payout | I45: =I44/(I39-I43) -> 0.74206522 | J45: =J44/(J39-J43) -> 0.267908 | K45: 0.25 | L45: =K45 -> 0.25 | M45: =L45 -> 0.25 | N45: =M45 -> 0.25 | O45: =N45 -> 0.25 | P45: =O45 -> 0.25 | Q45: =P45 -> 0.25 | R45: =Q45 -> 0.25 | S45: =R45 -> 0.25 | ... U45: =T45 -> 0.25
B48: PP&E
C49: Saldo Bruto | I49: 545.46 | J49: 564.079 | K49: =J49+K52 -> 714.27542 | L49: =K49+L52 -> 868.23816 | M49: =L49+M52 -> 1025.5881 | N49: =M49+N52 -> 1186.6357 | O49: =N49+O52 -> 1351.7096 | P49: =O49+P52 -> 1520.6627 | Q49: =P49+Q52 -> 1693.6706 | R49: =Q49+R52 -> 1870.9172 | ... U49: =T49+U52 -> 2429.8678
C50: (-) Depreciação período | I50: =I24 -> -75.428 | J50: =J24 -> -67.101 | K50: =K51*K49 -> -84.967877 | L50: =L51*L49 -> -103.28278 | M50: =M51*M49 -> -122.00062 | N50: =N51*N49 -> -141.15832 | O50: =O51*O49 -> -160.79497 | P50: =P51*P49 -> -180.89307 | Q50: =Q51*Q49 -> -201.47354 | R50: =R51*R49 -> -222.55822 | ... U50: =U51*U49 -> -289.04915
C51: % Taxa Depreciação | I51: =I50/((I49+I55)/2) -> -0.19552026 | J51: =J50/J49 -> -0.11895674 | K51: =J51 -> -0.11895674 | L51: =K51 -> -0.11895674 | M51: =L51 -> -0.11895674 | N51: =M51 -> -0.11895674 | O51: =N51 -> -0.11895674 | P51: =O51 -> -0.11895674 | Q51: =P51 -> -0.11895674 | R51: =Q51 -> -0.11895674 | ... U51: =T51 -> -0.11895674
C52: CAPEX | I52: 102.999 | J52: 147.793 | K52: =K53*K8 -> 150.19642 | L52: =L53*L8 -> 153.96275 | M52: =M53*M8 -> 157.34993 | N52: =N53*N8 -> 161.04765 | O52: =O53*O8 -> 165.07384 | P52: =P53*P8 -> 168.95308 | Q52: =Q53*Q8 -> 173.00795 | R52: =R53*R8 -> 177.24664 | ... U52: =U53*U8 -> 191.00945
C53: % Receita Líquida | I53: =I52/I8 -> 0.024200159 | J53: =J52/J8 -> 0.034073063 | K53: =J53 -> 0.034073063 | L53: =K53 -> 0.034073063 | M53: =L53 -> 0.034073063 | N53: =M53 -> 0.034073063 | O53: =N53 -> 0.034073063 | P53: =O53 -> 0.034073063 | Q53: =P53 -> 0.034073063 | R53: =Q53 -> 0.034073063 | ... U53: =T53 -> 0.034073063
C54: Depreciação acumulada | I54: -319.358 | J54: -282.65 | K54: =J54+K50 -> -367.61788 | L54: =K54+L50 -> -470.90066 | M54: =L54+M50 -> -592.90128 | N54: =M54+N50 -> -734.0596 | O54: =N54+O50 -> -894.85457 | P54: =O54+P50 -> -1075.7476 | Q54: =P54+Q50 -> -1277.2212 | R54: =Q54+R50 -> -1499.7794 | ... U54: =T54+U50 -> -2299.3259
C55: (=) Saldo Final | I55: =I49+I54 -> 226.102 | J55: =J49+J54 -> 281.429 | K55: =K49+K54 -> 346.65754 | L55: =L49+L54 -> 397.3375 | M55: =M49+M54 -> 432.68681 | N55: =N49+N54 -> 452.57614 | O55: =O49+O54 -> 456.85501 | P55: =P49+P54 -> 444.91501 | ... U55: =U49+U54 -> 130.5419
C59: Balanço Patrimonial | E59: 2006 | F59: 2007 | G59: 2008 | H59: 2009 | I59: 2010 | J59: 2011 | K59: 2012 | L59: 2013 | M59: 2014 | N59: 2015 | O59: 2016 | P59: 2017 | Q59: 2018 | R59: 2019 | S59: 2020 | T59: 2021 | U59: 2022
C61: Ativo Circulante | I61: =SUM(I62,I64,I65,I67,I69,I70) -> 2218.866 | J61: =SUM(J62,J64,J65,J67,J69,J70) -> 2885.67 | K61: =SUM(K62,K64,K65,K67,K69,K70) -> 2518.5149 | L61: =SUM(L62,L64,L65,L67,L69,L70) -> 2416.2227 | M61: =SUM(M62,M64,M65,M67,M69,M70) -> 2282.8193 | N61: =SUM(N62,N64,N65,N67,N69,N70) -> 2129.2497 | O61: =SUM(O62,O64,O65,O67,O69,O70) -> 2068.5576 | P61: =SUM(P62,P64,P65,P67,P69,P70) -> 2151.7244 | ... U61: =SUM(U62,U64,U65,U67,U69,U70) -> 3236.4208
C62: Caixa e Equivalentes de Caixa | I62: 432.627 | J62: 1117.179 | K62: =K63*K8 -> 440.80692 | L62: =L63*L8 -> 451.8606 | M62: =M63*M8 -> 461.80153 | N62: =N63*N8 -> 472.65387 | O62: =O63*O8 -> 484.47021 | P62: =P63*P8 -> 495.85526 | Q62: =Q63*Q8 -> 507.75579 | R62: =R63*R8 -> 520.19581 | ... U62: =U63*U8 -> 560.58785
C63: % Receita Líquida | I63: =I62/I8 -> 0.101648 | J63: =J62/J8 -> 0.25756098 | K63: 0.1 | L63: =K63 -> 0.1 | M63: =L63 -> 0.1 | N63: =M63 -> 0.1 | O63: =N63 -> 0.1 | P63: =O63 -> 0.1 | Q63: =P63 -> 0.1 | R63: =Q63 -> 0.1 | S63: =R63 -> 0.1 | ... U63: =T63 -> 0.1
C64: Aplicações Financeiras | I64: 222.392 | J64: 144.094 | K64: =MAX(0,SUM(K85,K87,K89,K91:K92,K94,K102)-SUM(K62,K65,K67,K69:K70,K72:K72,K78)) -> 754.33935 | L64: =MAX(0,SUM(L85,L87,L89,L91:L92,L94,L102)-SUM(L62,L65,L67,L69:L70,L72:L72,L78)) -> 607.80861 | M64: =MAX(0,SUM(M85,M87,M89,M91:M92,M94,M102)-SUM(M62,M65,M67,M69:M70,M72:M72,M78)) -> 434.62017 | N64: =MAX(0,SUM(N85,N87,N89,N91:N92,N94,N102)-SUM(N62,N65,N67,N69:N70,N72:N72,N78)) -> 237.61783 | O64: =MAX(0,SUM(O85,O87,O89,O91:O92,O94,O102)-SUM(O62,O65,O67,O69:O70,O72:O72,O78)) -> 129.63498 | P64: =MAX(0,SUM(P85,P87,P89,P91:P92,P94,P102)-SUM(P62,P65,P67,P69:P70,P72:P72,P78)) -> 167.23708 | Q64: =MAX(0,SUM(Q85,Q87,Q89,Q91:Q92,Q94,Q102)-SUM(Q62,Q65,Q67,Q69:Q70,Q72:Q72,Q78)) -> 263.30353 | R64: =MAX(0,SUM(R85,R87,R89,R91:R92,R94,R102)-SUM(R62,R65,R67,R69:R70,R72:R72,R78)) -> 418.96202 | ... U64: =MAX(0,SUM(U85,U87,U89,U91:U92,U94,U102)-SUM(U62,U65,U67,U69:U70,U72:U72,U78)) -> 992.86397
C65: Contas a Receber | I65: 643.026 | J65: 1052.86 | K65: =K66/365*K$8 -> 1086.9212 | L65: =L66/365*L$8 -> 1114.1768 | M65: =M66/365*M$8 -> 1138.6887 | N65: =N66/365*N$8 -> 1165.4479 | O65: =O66/365*O$8 -> 1194.5841 | P65: =P66/365*P$8 -> 1222.6568 | Q65: =Q66/365*Q$8 -> 1252.0006 | R65: =R66/365*R$8 -> 1282.6746 | ... U65: =U66/365*U$8 -> 1382.2714
C66: Dias de Receita Liquida | I66: =I65*365/I$8 -> 55.14506 | J66: =J65*365/J$8 -> 88.597364 | K66: 90 | L66: =K66 -> 90 | M66: =L66 -> 90 | N66: =M66 -> 90 | O66: =N66 -> 90 | P66: =O66 -> 90 | Q66: =P66 -> 90 | R66: =Q66 -> 90 | S66: =R66 -> 90 | ... U66: =T66 -> 90
C67: Estoques | I67: 75.063 | J67: 59.179 | K67: =-K68/365*K$11 -> 67.370858 | L67: =-L68/365*L$11 -> 69.06025 | M67: =-M68/365*M$11 -> 70.579575 | N67: =-N68/365*N$11 -> 72.238195 | O67: =-O68/365*O$11 -> 74.04415 | P67: =-P68/365*P$11 -> 75.784188 | Q67: =-Q68/365*Q$11 -> 77.603008 | R67: =-R68/365*R$11 -> 79.504282 | ... U67: =-U68/365*U$11 -> 85.677611
C68: Dias de CSV | I68: =-I67*365/I$11 -> 8.2335182 | J68: =-J67*365/J$11 -> 6.2488385 | K68: 7 | L68: =K68 -> 7 | M68: =L68 -> 7 | N68: =M68 -> 7 | O68: =N68 -> 7 | P68: =O68 -> 7 | Q68: =P68 -> 7 | R68: =Q68 -> 7 | S68: =R68 -> 7 | ... U68: =T68 -> 7
C69: Creditos com partes relacionadas | I69: =650.131 -> 650.131 | J69: 365.008 | K69: 0 | L69: 0 | M69: 0 | N69: 0 | O69: 0 | P69: 0 | Q69: 0 | R69: 0 | S69: 0 | T69: 0 | U69: 0
C70: Outros Creditos | I70: =13.181+104.004+4.198+74.244 -> 195.627 | J70: =8.863+46.278+7.757+84.452 -> 147.35 | K70: =K71/365*K$8 -> 169.07663 | L70: =L71/365*L$8 -> 173.31639 | M70: =M71/365*M$8 -> 177.12935 | N70: =N71/365*N$8 -> 181.29189 | O70: =O71/365*O$8 -> 185.82419 | P70: =P71/365*P$8 -> 190.19106 | Q70: =Q71/365*Q$8 -> 194.75565 | R70: =R71/365*R$8 -> 199.52716 | ... U70: =U71/365*U$8 -> 215.02
C71: Dias de Receita Liquida | I71: =I70*365/I$8 -> 16.776713 | J71: =J70*365/J$8 -> 12.39939 | K71: 14 | L71: =K71 -> 14 | M71: =L71 -> 14 | N71: =M71 -> 14 | O71: =N71 -> 14 | P71: =O71 -> 14 | Q71: =P71 -> 14 | R71: =Q71 -> 14 | S71: =R71 -> 14 | ... U71: =T71 -> 14
C72: Ativo Não Circulante | I72: =SUM(I73,I75,I76) -> 1732.646 | J72: =SUM(J73,J75,J76) -> 1567.586 | K72: =SUM(K73,K75,K76) -> 1574.5549 | L72: =SUM(L73,L75,L76) -> 1611.8043 | M72: =SUM(M73,M75,M76) -> 1645.3039 | N72: =SUM(N73,N75,N76) -> 1681.8748 | O72: =SUM(O73,O75,O76) -> 1721.6943 | P72: =SUM(P73,P75,P76) -> 1760.0603 | ... U72: =SUM(U73,U75,U76) -> 1978.2002
C73: Contas a Receber | I73: 1168.202 | J73: 1016.66 | K73: =K74/365*K$8 -> 1026.5367 | L73: =L74/365*L$8 -> 1052.2781 | M73: =M74/365*M$8 -> 1075.4282 | N73: =N74/365*N$8 -> 1100.7008 | O73: =O74/365*O$8 -> 1128.2183 | P73: =P74/365*P$8 -> 1154.7314 | Q73: =Q74/365*Q$8 -> 1182.445 | R73: =R74/365*R$8 -> 1211.4149 | ... U73: =U74/365*U$8 -> 1305.4785
C74: Dias de Receita Liquida | I74: =I73*365/I$8 -> 100.18346 | J74: =J73*365/J$8 -> 85.551161 | K74: 85 | L74: =K74 -> 85 | M74: =L74 -> 85 | N74: =M74 -> 85 | O74: =N74 -> 85 | P74: =O74 -> 85 | Q74: =P74 -> 85 | R74: =Q74 -> 85 | S74: =R74 -> 85 | ... U74: =T74 -> 85
C75: Créditos com Partes Relacionadas | I75: 36.674 | J75: 89.096 | K75: =J75 -> 89.096 | L75: =K75 -> 89.096 | M75: =L75 -> 89.096 | N75: =M75 -> 89.096 | O75: =N75 -> 89.096 | P75: =O75 -> 89.096 | Q75: =P75 -> 89.096 | R75: =Q75 -> 89.096 | ... U75: =T75 -> 89.096
C76: Outros Ativos não circulantes | I76: =47.229+23.307+344.494+19.79+4.208+88.742 -> 527.77 | J76: =40.895+28.727+297.693+8.618+85.897 -> 461.83 | K76: =K77/365*K$8 -> 458.92227 | L76: =L77/365*L$8 -> 470.43021 | M76: =M77/365*M$8 -> 480.77968 | N76: =N77/365*N$8 -> 492.078 | O76: =O77/365*O$8 -> 504.37995 | P76: =P77/365*P$8 -> 516.23288 | Q76: =Q77/365*Q$8 -> 528.62247 | R76: =R77/365*R$8 -> 541.57372 | ... U76: =U77/365*U$8 -> 583.6257
C77: Dias de Receita Liquida | I77: =I76*365/I$8 -> 45.260858 | J77: =J76*365/J$8 -> 38.862641 | K77: 38 | L77: =K77 -> 38 | M77: =L77 -> 38 | N77: =M77 -> 38 | O77: =N77 -> 38 | P77: =O77 -> 38 | Q77: =P77 -> 38 | R77: =Q77 -> 38 | S77: =R77 -> 38 | ... U77: =T77 -> 38
C78: Ativo Fixo | I78: =I79+I80+I81 -> 714.075 | J78: =J79+J80+J81 -> 988.085 | K78: =K79+K80+K81 -> 1194.0281 | L78: =L79+L80+L81 -> 1389.504 | M78: =M79+M80+M81 -> 1573.1977 | N78: =N79+N80+N81 -> 1745.3677 | O78: =O79+O80+O81 -> 1906.2813 | P78: =P79+P80+P81 -> 2055.125 | ... U78: =U79+U80+U81 -> 2614.936
C79: Investimentos | I79: 486.265 | J79: 705.464 | K79: =J79+K18-K116 -> 846.53611 | L79: =K79+L18-L116 -> 991.58238 | M79: =L79+M18-M116 -> 1140.1021 | N79: =M79+N18-N116 -> 1292.5053 | O79: =N79+O18-O116 -> 1449.2259 | P79: =O79+P18-P116 -> 1610.0698 | Q79: =P79+Q18-Q116 -> 1775.2689 | R79: =Q79+R18-R116 -> 1945.066 | ... U79: =T79+U18-U116 -> 2484.3941
C80: Imobilizado | I80: 226.102 | J80: 281.429 | K80: =K55 -> 346.65754 | L80: =L55 -> 397.3375 | M80: =M55 -> 432.68681 | N80: =N55 -> 452.57614 | O80: =O55 -> 456.85501 | P80: =P55 -> 444.91501 | Q80: =Q55 -> 416.44943 | R80: =R55 -> 371.13785 | ... U80: =U55 -> 130.5419
C81: Intangível | I81: 1.708 | J81: 1.192 | K81: =J81*(1-30%) -> 0.8344 | L81: =K81*(1-30%) -> 0.58408 | M81: =L81*(1-30%) -> 0.408856 | N81: =M81*(1-30%) -> 0.2861992 | O81: =N81*(1-30%) -> 0.20033944 | P81: =O81*(1-30%) -> 0.14023761 | Q81: 0 | R81: 0 | S81: 0 | T81: 0 | U81: 0
C82: Ativo Total | I82: =I78+I72+I61 -> 4665.587 | J82: =J78+J72+J61 -> 5441.341 | K82: =K78+K72+K61 -> 5287.0979 | L82: =L78+L72+L61 -> 5417.531 | M82: =M78+M72+M61 -> 5501.321 | N82: =N78+N72+N61 -> 5556.4921 | O82: =O78+O72+O61 -> 5696.5331 | P82: =P78+P72+P61 -> 5966.9098 | ... U82: =U78+U72+U61 -> 7829.5571
C84: Passivo Circulante | I84: =SUM(I85,I86,I87,I89,I91,I92) -> 1229.845 | J84: =SUM(J85,J86,J87,J89,J91,J92) -> 1267.967 | K84: =SUM(K85,K86,K87,K89,K91,K92) -> 1056.3828 | L84: =SUM(L85,L86,L87,L89,L91,L92) -> 1118.7525 | M84: =SUM(M85,M86,M87,M89,M91,M92) -> 1178.3036 | N84: =SUM(N85,N86,N87,N89,N91,N92) -> 1161.6014 | O84: =SUM(O85,O86,O87,O89,O91,O92) -> 979.6975 | P84: =SUM(P85,P86,P87,P89,P91,P92) -> 953.7681 | ... U84: =SUM(U85,U86,U87,U89,U91,U92) -> 1027.4673
C85: Emprestimos e Financiamentos | I85: =339.188+4.22 -> 343.408 | J85: =197.692+1.156 -> 198.848 | K85: =-L161-L186 -> 26 | L85: =-M161-M186 -> 42 | M85: =-N161-N186 -> 78 | N85: =-O161-O186 -> 35.702 | O85: =-P161-P186 -> 25 | P85: =-Q161-Q186 -> 44.769 | Q85: =-R161-R186 -> 0 | R85: =-S161-S186 -> 0 | ... U85: =-V161-V186 -> 0
C86: Dívida de Balanceamento | I86: 0 | J86: 0 | K86: =MAX(0,SUM(K62,K65,K67,K69:K70,K72:K72,K78)-SUM(K85,K87,K89,K91:K92,K94,K102)) -> 0 | L86: =MAX(0,SUM(L62,L65,L67,L69:L70,L72:L72,L78)-SUM(L85,L87,L89,L91:L92,L94,L102)) -> 0 | M86: =MAX(0,SUM(M62,M65,M67,M69:M70,M72:M72,M78)-SUM(M85,M87,M89,M91:M92,M94,M102)) -> 0 | N86: =MAX(0,SUM(N62,N65,N67,N69:N70,N72:N72,N78)-SUM(N85,N87,N89,N91:N92,N94,N102)) -> 0 | O86: =MAX(0,SUM(O62,O65,O67,O69:O70,O72:O72,O78)-SUM(O85,O87,O89,O91:O92,O94,O102)) -> 0 | P86: =MAX(0,SUM(P62,P65,P67,P69:P70,P72:P72,P78)-SUM(P85,P87,P89,P91:P92,P94,P102)) -> 0 | Q86: =MAX(0,SUM(Q62,Q65,Q67,Q69:Q70,Q72:Q72,Q78)-SUM(Q85,Q87,Q89,Q91:Q92,Q94,Q102)) -> 0 | R86: =MAX(0,SUM(R62,R65,R67,R69:R70,R72:R72,R78)-SUM(R85,R87,R89,R91:R92,R94,R102)) -> 0 | ... U86: =MAX(0,SUM(U62,U65,U67,U69:U70,U72:U72,U78)-SUM(U85,U87,U89,U91:U92,U94,U102)) -> 0
C87: Fornecedores e subempreiteiros | I87: 212.435 | J87: 211.275 | K87: =-K88/365*K$11 -> 211.73698 | L87: =-L88/365*L$11 -> 217.0465 | M87: =-M88/365*M$11 -> 221.82152 | N87: =-N88/365*N$11 -> 227.03433 | O87: =-O88/365*O$11 -> 232.71019 | P87: =-P88/365*P$11 -> 238.17888 | Q87: =-Q88/365*Q$11 -> 243.89517 | R87: =-R88/365*R$11 -> 249.8706 | ... U87: =-U88/365*U$11 -> 269.27249
C88: Dias de CSV | I88: =-I87*365/I$11 -> 23.301592 | J88: =-J87*365/J$11 -> 22.308984 | K88: 22 | L88: =K88 -> 22 | M88: =L88 -> 22 | N88: =M88 -> 22 | O88: =N88 -> 22 | P88: =O88 -> 22 | Q88: =P88 -> 22 | R88: =Q88 -> 22 | S88: =R88 -> 22 | ... U88: =T88 -> 22
C89: Adiantamento de clientes | I89: 220.449 | J89: 372.414 | K89: =K90/365*K$8 -> 362.30706 | L89: =L90/365*L$8 -> 371.39227 | M89: =M90/365*M$8 -> 379.5629 | N89: =N90/365*N$8 -> 388.48263 | O89: =O90/365*O$8 -> 199.09735 | P89: =P90/365*P$8 -> 135.85076 | Q89: =Q90/365*Q$8 -> 139.11118 | R89: =R90/365*R$8 -> 142.5194 | ... U89: =U90/365*U$8 -> 153.58571
C90: Dias de Receita Liquida | I90: =I89*365/I$8 -> 18.905415 | J90: =J89*365/J$8 -> 31.338353 | K90: 30 | L90: =K90 -> 30 | M90: =L90 -> 30 | N90: =M90 -> 30 | O90: 15 | P90: 10 | Q90: =P90 -> 10 | R90: =Q90 -> 10 | S90: =R90 -> 10 | T90: =S90 -> 10 | U90: =T90 -> 10
C91: Dividendos e JCP a Pagar | I91: 6.742 | J91: 1.577 | K91: =5%*K44 -> 5.3396078 | L91: =5%*L44 -> 5.5037717 | M91: =5%*M44 -> 5.4873696 | N91: =5%*N44 -> 5.3550534 | O91: =5%*O44 -> 5.2368623 | P91: =5%*P44 -> 5.1515178 | Q91: =5%*Q44 -> 5.1810556 | R91: =5%*R44 -> 5.2615767 | ... U91: =5%*U44 -> 5.624852
C92: Outras Obrigações | I92: =16.589+155.615+129.417+108.871+4.012+32.307 -> 446.811 | J92: =163.598+113.037+159.242+4.012+43.964 -> 483.853 | K92: =K93/365*K$8+K38 -> 450.99918 | L92: =L93/365*L$8 -> 482.80995 | M92: =M93/365*M$8 -> 493.43177 | N92: =N93/365*N$8 -> 505.02742 | O92: =O93/365*O$8 -> 517.65311 | P92: =P93/365*P$8 -> 529.81795 | Q92: =Q93/365*Q$8 -> 542.53358 | R92: =R93/365*R$8 -> 555.82566 | S92: =S93/365*S$8 -> 569.7213 | ... U92: =U93/365*U$8 -> 598.98427
C93: Dias de Receita Liquida | I93: =I92*365/I$8 -> 38.317921 | J93: =J92*365/J$8 -> 40.71586 | K93: 39 | L93: =K93 -> 39 | M93: =L93 -> 39 | N93: =M93 -> 39 | O93: =N93 -> 39 | P93: =O93 -> 39 | Q93: =P93 -> 39 | R93: =Q93 -> 39 | S93: =R93 -> 39 | ... U93: =T93 -> 39
C94: Passivo Não Circulante | I94: =SUM(I95,I96,I98,I100) -> 1350.729 | J94: =SUM(J95,J96,J98,J100) -> 1668.04 | K94: =SUM(K95,K96,K98,K100) -> 1382.5221 | L94: =SUM(L95,L96,L98,L100) -> 1097.1854 | M94: =SUM(M95,M96,M98,M100) -> 769.07742 | N94: =SUM(N95,N96,N98,N100) -> 497.09989 | O94: =SUM(O95,O96,O98,O100) -> 482.78317 | P94: =SUM(P95,P96,P98,P100) -> 448.3075 | ... U94: =SUM(U95,U96,U98,U100) -> 506.83285
C95: Emprestimos e Financiamentos | I95: =437.809+1.529 -> 439.338 | J95: 250.779 | K95: =K164+K191-K85 -> 225.471 | L95: =L164+L191-L85 -> 183.471 | M95: =M164+M191-M85 -> 105.471 | N95: =N164+N191-N85 -> 69.769 | O95: =O164+O191-O85 -> 44.769 | P95: =P164+P191-P85 -> 0 | Q95: =Q164+Q191-Q85 -> 0 | R95: =R164+R191-R85 -> 0 | ... U95: =U164+U191-U85 -> 0
C96: Passivos com Partes Relacionadas | I96: 55.664 | J96: 981.936 | K96: =J96+K97 -> 740.39796 | L96: =K96+L97 -> 492.80311 | M96: =L96+M97 -> 239.76118 | N96: =M96+N97 -> 0 | O96: =N96+O97 -> 0 | P96: =O96+P97 -> 0 | Q96: =P96+Q97 -> 0 | R96: =Q96+R97 -> 0 | ... T96: =S96+T97 -> 0 | U96: 0
C97: Amortização | K97: =-2/3*K89 -> -241.53804 | L97: =-2/3*L89 -> -247.59485 | M97: =-2/3*M89 -> -253.04194 | N97: =-M96 -> -239.76118 | O97: 0 | P97: =O97 -> 0 | Q97: =P97 -> 0 | R97: 0 | S97: 0 | T97: 0 | U97: 0
C98: Adiantamento de clientes | I98: 505.932 | J98: 29.263 | K98: =K99/365*K$8 -> 18.115353 | L98: =L99/365*L$8 -> 12.379742 | M98: =M99/365*M$8 -> 6.3260484 | N98: =N99/365*N$8 -> 0 | O98: =O99/365*O$8 -> 0 | P98: =P99/365*P$8 -> 0 | Q98: =Q99/365*Q$8 -> 0 | R98: =R99/365*R$8 -> 0 | ... U98: =U99/365*U$8 -> 0
C99: Dias de Receita Liquida | I99: =I98*365/I$8 -> 43.38806 | J99: =J98*365/J$8 -> 2.4624591 | K99: 1.5 | L99: 1 | M99: 0.5 | N99: 0 | O99: =N99 -> 0 | P99: =O99 -> 0 | Q99: =P99 -> 0 | R99: =Q99 -> 0 | S99: =R99 -> 0 | T99: =S99 -> 0 | U99: =T99 -> 0
C100: Outros passivos não circulantes | I100: =207.666+60.95+1.022+56.16+23.997 -> 349.795 | J100: =195.347+70.76+66.22+54.7+19.035 -> 406.062 | K100: =K101/365*K$8 -> 398.53776 | L100: =L101/365*L$8 -> 408.5315 | M100: =M101/365*M$8 -> 417.51919 | N100: =N101/365*N$8 -> 427.33089 | O100: =O101/365*O$8 -> 438.01417 | P100: =P101/365*P$8 -> 448.3075 | Q100: =Q101/365*Q$8 -> 459.06688 | R100: =R101/365*R$8 -> 470.31402 | ... U100: =U101/365*U$8 -> 506.83285
C101: Dias de Receita Liquida | I101: =I100*365/I$8 -> 29.997957 | J101: =J100*365/J$8 -> 34.169807 | K101: 33 | L101: =K101 -> 33 | M101: =L101 -> 33 | N101: =M101 -> 33 | O101: =N101 -> 33 | P101: =O101 -> 33 | Q101: =P101 -> 33 | R101: =Q101 -> 33 | S101: =R101 -> 33 | ... U101: =T101 -> 33
C102: Patrimônio Líquido | I102: =SUM(I103:I106) -> 2085.013 | J102: =SUM(J103:J106) -> 2505.334 | K102: =SUM(K103:K106) -> 2848.193 | L102: =SUM(L103:L106) -> 3201.5931 | M102: =SUM(M103:M106) -> 3553.94 | N102: =SUM(N103:N106) -> 3897.7908 | O102: =SUM(O103:O106) -> 4234.0525 | P102: =SUM(P103:P106) -> 4564.8342 | ... U102: =SUM(U103:U106) -> 6295.2569
C103: Capital Social Realizado | I103: 1605.675 | J103: 1698.915 | K103: =J103 -> 1698.915 | L103: =K103 -> 1698.915 | M103: =L103 -> 1698.915 | N103: =M103 -> 1698.915 | O103: =N103 -> 1698.915 | P103: =O103 -> 1698.915 | Q103: =P103 -> 1698.915 | R103: =Q103 -> 1698.915 | ... U103: =T103 -> 1698.915
C104: Reservas de Capital | I104: 0.034 | J104: 0.034 | K104: =J104+K43 -> 22.516559 | L104: =K104+L43 -> 45.690335 | M104: =L104+M43 -> 68.795049 | N104: =M104+N43 -> 91.342642 | O104: =N104+O43 -> 113.39259 | P104: =O104+P43 -> 135.08319 | Q104: =P104+Q43 -> 156.89816 | R104: =Q104+R43 -> 179.05217 | ... U104: =T104+U43 -> 248.55353
C105: Reservas de Lucros | I105: =1.323+573.745 -> 575.068 | J105: =1.323+875.908 -> 877.231 | K105: =J105+(K39-K43)-K44 -> 1197.6075 | L105: =K105+(L39-L43)-L44 -> 1527.8338 | M105: =L105+(M39-M43)-M44 -> 1857.0759 | N105: =M105+(N39-N43)-N44 -> 2178.3791 | O105: =N105+(O39-O43)-O44 -> 2492.5909 | P105: =O105+(P39-P43)-P44 -> 2801.682 | Q105: =P105+(Q39-Q43)-Q44 -> 3112.5453 | R105: =Q105+(R39-R43)-R44 -> 3428.2399 | ... U105: =T105+(U39-U43)-U44 -> 4418.6344
C106: Ajustes de Avaliação Patrimonial | I106: -95.764 | J106: -70.846 | K106: =J106 -> -70.846 | L106: =K106 -> -70.846 | M106: =L106 -> -70.846 | N106: =M106 -> -70.846 | O106: =N106 -> -70.846 | P106: =O106 -> -70.846 | Q106: =P106 -> -70.846 | R106: =Q106 -> -70.846 | ... U106: =T106 -> -70.846
C107: Passivo Total | I107: =I102+I94+I84 -> 4665.587 | J107: =J102+J94+J84 -> 5441.341 | K107: =K102+K94+K84 -> 5287.0979 | L107: =L102+L94+L84 -> 5417.531 | M107: =M102+M94+M84 -> 5501.321 | N107: =N102+N94+N84 -> 5556.4921 | O107: =O102+O94+O84 -> 5696.5331 | P107: =P102+P94+P84 -> 5966.9098 | ... U107: =U102+U94+U84 -> 7829.5571
I108: =IF(ABS(I107-I82)<0.0000001,"ü","û") -> ü | J108: =IF(ABS(J107-J82)<0.0000001,"ü","û") -> ü | K108: =IF(ABS(K107-K82)<0.0000001,"ü","û") -> ü | L108: =IF(ABS(L107-L82)<0.0000001,"ü","û") -> ü | M108: =IF(ABS(M107-M82)<0.0000001,"ü","û") -> ü | N108: =IF(ABS(N107-N82)<0.0000001,"ü","û") -> ü | O108: =IF(ABS(O107-O82)<0.0000001,"ü","û") -> ü | P108: =IF(ABS(P107-P82)<0.0000001,"ü","û") -> ü | ... U108: =IF(ABS(U107-U82)<0.0000001,"ü","û") -> ü
C111: Fluxo de Caixa | E111: 2006 | F111: 2007 | G111: 2008 | I111: 2010 | J111: 2011 | K111: 2012 | L111: 2013 | M111: 2014 | N111: 2015 | O111: 2016 | P111: 2017 | Q111: 2018 | R111: 2019 | S111: 2020 | T111: 2021 | U111: 2022
C113: Lucro Líquido | I113: =I39 -> 364.1927 | J113: =J39 -> 396.279 | K113: =K39 -> 449.65118 | L113: =L39 -> 463.47551 | M113: =M39 -> 462.09428 | N113: =N39 -> 450.95186 | O113: =O39 -> 440.99893 | P113: =P39 -> 433.81203 | ... U113: =U39 -> 473.67175
C114: (+) Depreciação | I114: =-I24 -> 75.428 | J114: =-J24 -> 67.101 | K114: =-K24 -> 84.967877 | L114: =-L24 -> 103.28278 | M114: =-M24 -> 122.00062 | N114: =-N24 -> 141.15832 | O114: =-O24 -> 160.79497 | P114: =-P24 -> 180.89307 | ... U114: =-U24 -> 289.04915
...

Sheet Financiamentos

Sheet DIVIDA AGPar
F1: LEGENDA:
B2: MODELO DE DÍVIDA | F2: Dados Realizados Inputados | I2: VICTOR LOPES SCHMUTZLER
F3: Dados Realizados Calculados | I3: +55 (11) 3553-2529
F4: Dados Projetados Inputados
B5: 1. RESUMO FINANCIAMENTOS | F5: Dados Projetados Calculados
B7: CONSOLIDADO ANUAL | D7: 2009 | E7: 2010 | F7: 2011 | G7: =F7+1 -> 2012 | H7: =G7+1 -> 2013 | I7: =H7+1 -> 2014 | J7: =I7+1 -> 2015 | K7: =J7+1 -> 2016 | L7: =K7+1 -> 2017 | M7: =L7+1 -> 2018 | N7: =M7+1 -> 2019 | ... AD7: =AC7+1 -> 2035
B9: Empréstimos e financiamentos
B10: Saldo inicial (Balanço)
B11: Novo funding (Caixa)
B12: Juros apropriados (DRE)
B13: Juros pagos (Caixa)
B14: Amortização principal (Caixa)
B15: Saldo final (Balanço)
B16: Saldo Curto Prazo (Balanço)
B17: Saldo Longo Prazo (Balanço)
B19: Debêntures
A20: 15 | B20: Saldo inicial (Balanço) | F20: 0 | G20: =F26 -> 200106.7 | H20: =G26 -> 1083015.9 | I20: =H26 -> 1123739.6 | J20: =I26 -> 1125126.4 | K20: =J26 -> 1123980.6 | L20: =K26 -> 983488.94 | M20: =L26 -> 842126.91 | N20: =M26 -> 700974.25 | ... AD20: =AC26 -> 0
A21: 16 | B21: Novo funding (Caixa) | G21: =SUMIF($E$83:$GQ$83,G$7,$E97:$GQ97)+SUMIF($E$113:$GQ$113,G$7,$E127:$GQ127)+SUMIF($E$53:$GQ$53,G$7,$E67:$GQ67)+SUMIF($E$143:$GQ$143,G$7,$E157:$GQ157)+SUMIF($E$173:$GQ$173,G$7,$E187:$GQ187) -> 903512.21 | H21: =SUMIF($E$83:$GQ$83,H$7,$E97:$GQ97)+SUMIF($E$113:$GQ$113,H$7,$E127:$GQ127)+SUMIF($E$53:$GQ$53,H$7,$E67:$GQ67)+SUMIF($E$143:$GQ$143,H$7,$E157:$GQ157)+SUMIF($E$173:$GQ$173,H$7,$E187:$GQ187) -> 0 | I21: =SUMIF($E$83:$GQ$83,I$7,$E97:$GQ97)+SUMIF($E$113:$GQ$113,I$7,$E127:$GQ127)+SUMIF($E$53:$GQ$53,I$7,$E67:$GQ67)+SUMIF($E$143:$GQ$143,I$7,$E157:$GQ157)+SUMIF($E$173:$GQ$173,I$7,$E187:$GQ187) -> 0 | J21: =SUMIF($E$83:$GQ$83,J$7,$E97:$GQ97)+SUMIF($E$113:$GQ$113,J$7,$E127:$GQ127)+SUMIF($E$53:$GQ$53,J$7,$E67:$GQ67)+SUMIF($E$143:$GQ$143,J$7,$E157:$GQ157)+SUMIF($E$173:$GQ$173,J$7,$E187:$GQ187) -> 0 | K21: =SUMIF($E$83:$GQ$83,K$7,$E97:$GQ97)+SUMIF($E$113:$GQ$113,K$7,$E127:$GQ127)+SUMIF($E$53:$GQ$53,K$7,$E67:$GQ67)+SUMIF($E$143:$GQ$143,K$7,$E157:$GQ157)+SUMIF($E$173:$GQ$173,K$7,$E187:$GQ187) -> 0 | L21: =SUMIF($E$83:$GQ$83,L$7,$E97:$GQ97)+SUMIF($E$113:$GQ$113,L$7,$E127:$GQ127)+SUMIF($E$53:$GQ$53,L$7,$E67:$GQ67)+SUMIF($E$143:$GQ$143,L$7,$E157:$GQ157)+SUMIF($E$173:$GQ$173,L$7,$E187:$GQ187) -> 0 | M21: =SUMIF($E$83:$GQ$83,M$7,$E97:$GQ97)+SUMIF($E$113:$GQ$113,M$7,$E127:$GQ127)+SUMIF($E$53:$GQ$53,M$7,$E67:$GQ67)+SUMIF($E$143:$GQ$143,M$7,$E157:$GQ157)+SUMIF($E$173:$GQ$173,M$7,$E187:$GQ187) -> 0 | N21: =SUMIF($E$83:$GQ$83,N$7,$E97:$GQ97)+SUMIF($E$113:$GQ$113,N$7,$E127:$GQ127)+SUMIF($E$53:$GQ$53,N$7,$E67:$GQ67)+SUMIF($E$143:$GQ$143,N$7,$E157:$GQ157)+SUMIF($E$173:$GQ$173,N$7,$E187:$GQ187) -> 0 | ... AD21: =SUMIF($E$83:$GQ$83,AD$7,$E97:$GQ97)+SUMIF($E$113:$GQ$113,AD$7,$E127:$GQ127)+SUMIF($E$53:$GQ$53,AD$7,$E67:$GQ67)+SUMIF($E$143:$GQ$143,AD$7,$E157:$GQ157)+SUMIF($E$173:$GQ$173,AD$7,$E187:$GQ187) -> 0
A22: 17 | B22: Correção Monetária IPCA | G22: =SUMIF($E$83:$GQ$83,G$7,$E98:$GQ98)+SUMIF($E$113:$GQ$113,G$7,$E128:$GQ128)+SUMIF($E$53:$GQ$53,G$7,$E68:$GQ68)+SUMIF($E$143:$GQ$143,G$7,$E158:$GQ158)+SUMIF($E$173:$GQ$173,G$7,$E188:$GQ188) -> 7060.0664 | H22: =SUMIF($E$83:$GQ$83,H$7,$E98:$GQ98)+SUMIF($E$113:$GQ$113,H$7,$E128:$GQ128)+SUMIF($E$53:$GQ$53,H$7,$E68:$GQ68)+SUMIF($E$143:$GQ$143,H$7,$E158:$GQ158)+SUMIF($E$173:$GQ$173,H$7,$E188:$GQ188) -> 16631.86 | I22: =SUMIF($E$83:$GQ$83,I$7,$E98:$GQ98)+SUMIF($E$113:$GQ$113,I$7,$E128:$GQ128)+SUMIF($E$53:$GQ$53,I$7,$E68:$GQ68)+SUMIF($E$143:$GQ$143,I$7,$E158:$GQ158)+SUMIF($E$173:$GQ$173,I$7,$E188:$GQ188) -> 13066.137 | J22: =SUMIF($E$83:$GQ$83,J$7,$E98:$GQ98)+SUMIF($E$113:$GQ$113,J$7,$E128:$GQ128)+SUMIF($E$53:$GQ$53,J$7,$E68:$GQ68)+SUMIF($E$143:$GQ$143,J$7,$E158:$GQ158)+SUMIF($E$173:$GQ$173,J$7,$E188:$GQ188) -> 13654.113 | K22: =SUMIF($E$83:$GQ$83,K$7,$E98:$GQ98)+SUMIF($E$113:$GQ$113,K$7,$E128:$GQ128)+SUMIF($E$53:$GQ$53,K$7,$E68:$GQ68)+SUMIF($E$143:$GQ$143,K$7,$E158:$GQ158)+SUMIF($E$173:$GQ$173,K$7,$E188:$GQ188) -> 14268.548 | L22: =SUMIF($E$83:$GQ$83,L$7,$E98:$GQ98)+SUMIF($E$113:$GQ$113,L$7,$E128:$GQ128)+SUMIF($E$53:$GQ$53,L$7,$E68:$GQ68)+SUMIF($E$143:$GQ$143,L$7,$E158:$GQ158)+SUMIF($E$173:$GQ$173,L$7,$E188:$GQ188) -> 13253.896 | M22: =SUMIF($E$83:$GQ$83,M$7,$E98:$GQ98)+SUMIF($E$113:$GQ$113,M$7,$E128:$GQ128)+SUMIF($E$53:$GQ$53,M$7,$E68:$GQ68)+SUMIF($E$143:$GQ$143,M$7,$E158:$GQ158)+SUMIF($E$173:$GQ$173,M$7,$E188:$GQ188) -> 13784.051 | N22: =SUMIF($E$83:$GQ$83,N$7,$E98:$GQ98)+SUMIF($E$113:$GQ$113,N$7,$E128:$GQ128)+SUMIF($E$53:$GQ$53,N$7,$E68:$GQ68)+SUMIF($E$143:$GQ$143,N$7,$E158:$GQ158)+SUMIF($E$173:$GQ$173,N$7,$E188:$GQ188) -> 14335.414 | ... AD22: =SUMIF($E$83:$GQ$83,AD$7,$E98:$GQ98)+SUMIF($E$113:$GQ$113,AD$7,$E128:$GQ128)+SUMIF($E$53:$GQ$53,AD$7,$E68:$GQ68)+SUMIF($E$143:$GQ$143,AD$7,$E158:$GQ158)+SUMIF($E$173:$GQ$173,AD$7,$E188:$GQ188) -> 0
A23: 18 | B23: Juros apropriados (DRE) | G23: =SUMIF($E$83:$GQ$83,G$7,$E99:$GQ99)+SUMIF($E$113:$GQ$113,G$7,$E129:$GQ129)+SUMIF($E$53:$GQ$53,G$7,$E69:$GQ69)+SUMIF($E$143:$GQ$143,G$7,$E159:$GQ159)+SUMIF($E$173:$GQ$173,G$7,$E189:$GQ189) -> 45046.256 | H23: =SUMIF($E$83:$GQ$83,H$7,$E99:$GQ99)+SUMIF($E$113:$GQ$113,H$7,$E129:$GQ129)+SUMIF($E$53:$GQ$53,H$7,$E69:$GQ69)+SUMIF($E$143:$GQ$143,H$7,$E159:$GQ159)+SUMIF($E$173:$GQ$173,H$7,$E189:$GQ189) -> 72825.801 | I23: =SUMIF($E$83:$GQ$83,I$7,$E99:$GQ99)+SUMIF($E$113:$GQ$113,I$7,$E129:$GQ129)+SUMIF($E$53:$GQ$53,I$7,$E69:$GQ69)+SUMIF($E$143:$GQ$143,I$7,$E159:$GQ159)+SUMIF($E$173:$GQ$173,I$7,$E189:$GQ189) -> 81286.403 | J23: =SUMIF($E$83:$GQ$83,J$7,$E99:$GQ99)+SUMIF($E$113:$GQ$113,J$7,$E129:$GQ129)+SUMIF($E$53:$GQ$53,J$7,$E69:$GQ69)+SUMIF($E$143:$GQ$143,J$7,$E159:$GQ159)+SUMIF($E$173:$GQ$173,J$7,$E189:$GQ189) -> 81570.32 | K23: =SUMIF($E$83:$GQ$83,K$7,$E99:$GQ99)+SUMIF($E$113:$GQ$113,K$7,$E129:$GQ129)+SUMIF($E$53:$GQ$53,K$7,$E69:$GQ69)+SUMIF($E$143:$GQ$143,K$7,$E159:$GQ159)+SUMIF($E$173:$GQ$173,K$7,$E189:$GQ189) -> 76141.744 | L23: =SUMIF($E$83:$GQ$83,L$7,$E99:$GQ99)+SUMIF($E$113:$GQ$113,L$7,$E129:$GQ129)+SUMIF($E$53:$GQ$53,L$7,$E69:$GQ69)+SUMIF($E$143:$GQ$143,L$7,$E159:$GQ159)+SUMIF($E$173:$GQ$173,L$7,$E189:$GQ189) -> 62358.75 | M23: =SUMIF($E$83:$GQ$83,M$7,$E99:$GQ99)+SUMIF($E$113:$GQ$113,M$7,$E129:$GQ129)+SUMIF($E$53:$GQ$53,M$7,$E69:$GQ69)+SUMIF($E$143:$GQ$143,M$7,$E159:$GQ159)+SUMIF($E$173:$GQ$173,M$7,$E189:$GQ189) -> 47881.463 | N23: =SUMIF($E$83:$GQ$83,N$7,$E99:$GQ99)+SUMIF($E$113:$GQ$113,N$7,$E129:$GQ129)+SUMIF($E$53:$GQ$53,N$7,$E69:$GQ69)+SUMIF($E$143:$GQ$143,N$7,$E159:$GQ159)+SUMIF($E$173:$GQ$173,N$7,$E189:$GQ189) -> 34067.337 | ... AD23: =SUMIF($E$83:$GQ$83,AD$7,$E99:$GQ99)+SUMIF($E$113:$GQ$113,AD$7,$E129:$GQ129)+SUMIF($E$53:$GQ$53,AD$7,$E69:$GQ69)+SUMIF($E$143:$GQ$143,AD$7,$E159:$GQ159)+SUMIF($E$173:$GQ$173,AD$7,$E189:$GQ189) -> 0
A24: 19 | B24: Juros pagos (Caixa) | G24: =SUMIF($E$83:$GQ$83,G$7,$E100:$GQ100)+SUMIF($E$113:$GQ$113,G$7,$E130:$GQ130)+SUMIF($E$53:$GQ$53,G$7,$E70:$GQ70)+SUMIF($E$143:$GQ$143,G$7,$E160:$GQ160)+SUMIF($E$173:$GQ$173,G$7,$E190:$GQ190) -> -32514.617 | H24: =SUMIF($E$83:$GQ$83,H$7,$E100:$GQ100)+SUMIF($E$113:$GQ$113,H$7,$E130:$GQ130)+SUMIF($E$53:$GQ$53,H$7,$E70:$GQ70)+SUMIF($E$143:$GQ$143,H$7,$E160:$GQ160)+SUMIF($E$173:$GQ$173,H$7,$E190:$GQ190) -> -48733.949 | I24: =SUMIF($E$83:$GQ$83,I$7,$E100:$GQ100)+SUMIF($E$113:$GQ$113,I$7,$E130:$GQ130)+SUMIF($E$53:$GQ$53,I$7,$E70:$GQ70)+SUMIF($E$143:$GQ$143,I$7,$E160:$GQ160)+SUMIF($E$173:$GQ$173,I$7,$E190:$GQ190) -> -78331.056 | J24: =SUMIF($E$83:$GQ$83,J$7,$E100:$GQ100)+SUMIF($E$113:$GQ$113,J$7,$E130:$GQ130)+SUMIF($E$53:$GQ$53,J$7,$E70:$GQ70)+SUMIF($E$143:$GQ$143,J$7,$E160:$GQ160)+SUMIF($E$173:$GQ$173,J$7,$E190:$GQ190) -> -81735.622 | K24: =SUMIF($E$83:$GQ$83,K$7,$E100:$GQ100)+SUMIF($E$113:$GQ$113,K$7,$E130:$GQ130)+SUMIF($E$53:$GQ$53,K$7,$E70:$GQ70)+SUMIF($E$143:$GQ$143,K$7,$E160:$GQ160)+SUMIF($E$173:$GQ$173,K$7,$E190:$GQ190) -> -82933.906 | L24: =SUMIF($E$83:$GQ$83,L$7,$E100:$GQ100)+SUMIF($E$113:$GQ$113,L$7,$E130:$GQ130)+SUMIF($E$53:$GQ$53,L$7,$E70:$GQ70)+SUMIF($E$143:$GQ$143,L$7,$E160:$GQ160)+SUMIF($E$173:$GQ$173,L$7,$E190:$GQ190) -> -69006.661 | M24: =SUMIF($E$83:$GQ$83,M$7,$E100:$GQ100)+SUMIF($E$113:$GQ$113,M$7,$E130:$GQ130)+SUMIF($E$53:$GQ$53,M$7,$E70:$GQ70)+SUMIF($E$143:$GQ$143,M$7,$E160:$GQ160)+SUMIF($E$173:$GQ$173,M$7,$E190:$GQ190) -> -54850.162 | N24: =SUMIF($E$83:$GQ$83,N$7,$E100:$GQ100)+SUMIF($E$113:$GQ$113,N$7,$E130:$GQ130)+SUMIF($E$53:$GQ$53,N$7,$E70:$GQ70)+SUMIF($E$143:$GQ$143,N$7,$E160:$GQ160)+SUMIF($E$173:$GQ$173,N$7,$E190:$GQ190) -> -40709.883 | ... AD24: =SUMIF($E$83:$GQ$83,AD$7,$E100:$GQ100)+SUMIF($E$113:$GQ$113,AD$7,$E130:$GQ130)+SUMIF($E$53:$GQ$53,AD$7,$E70:$GQ70)+SUMIF($E$143:$GQ$143,AD$7,$E160:$GQ160)+SUMIF($E$173:$GQ$173,AD$7,$E190:$GQ190) -> 0
A25: 20 | B25: Amortização principal (Caixa) | G25: =SUMIF($E$83:$GQ$83,G$7,$E101:$GQ101)+SUMIF($E$113:$GQ$113,G$7,$E131:$GQ131)+SUMIF($E$53:$GQ$53,G$7,$E71:$GQ71)+SUMIF($E$143:$GQ$143,G$7,$E161:$GQ161)+SUMIF($E$173:$GQ$173,G$7,$E191:$GQ191) -> -40194.704 | H25: =SUMIF($E$83:$GQ$83,H$7,$E101:$GQ101)+SUMIF($E$113:$GQ$113,H$7,$E131:$GQ131)+SUMIF($E$53:$GQ$53,H$7,$E71:$GQ71)+SUMIF($E$143:$GQ$143,H$7,$E161:$GQ161)+SUMIF($E$173:$GQ$173,H$7,$E191:$GQ191) -> 0 | I25: =SUMIF($E$83:$GQ$83,I$7,$E101:$GQ101)+SUMIF($E$113:$GQ$113,I$7,$E131:$GQ131)+SUMIF($E$53:$GQ$53,I$7,$E71:$GQ71)+SUMIF($E$143:$GQ$143,I$7,$E161:$GQ161)+SUMIF($E$173:$GQ$173,I$7,$E191:$GQ191) -> -14634.678 | J25: =SUMIF($E$83:$GQ$83,J$7,$E101:$GQ101)+SUMIF($E$113:$GQ$113,J$7,$E131:$GQ131)+SUMIF($E$53:$GQ$53,J$7,$E71:$GQ71)+SUMIF($E$143:$GQ$143,J$7,$E161:$GQ161)+SUMIF($E$173:$GQ$173,J$7,$E191:$GQ191) -> -14634.678 | K25: =SUMIF($E$83:$GQ$83,K$7,$E101:$GQ101)+SUMIF($E$113:$GQ$113,K$7,$E131:$GQ131)+SUMIF($E$53:$GQ$53,K$7,$E71:$GQ71)+SUMIF($E$143:$GQ$143,K$7,$E161:$GQ161)+SUMIF($E$173:$GQ$173,K$7,$E191:$GQ191) -> -147968.01 | L25: =SUMIF($E$83:$GQ$83,L$7,$E101:$GQ101)+SUMIF($E$113:$GQ$113,L$7,$E131:$GQ131)+SUMIF($E$53:$GQ$53,L$7,$E71:$GQ71)+SUMIF($E$143:$GQ$143,L$7,$E161:$GQ161)+SUMIF($E$173:$GQ$173,L$7,$E191:$GQ191) -> -147968.01 | M25: =SUMIF($E$83:$GQ$83,M$7,$E101:$GQ101)+SUMIF($E$113:$GQ$113,M$7,$E131:$GQ131)+SUMIF($E$53:$GQ$53,M$7,$E71:$GQ71)+SUMIF($E$143:$GQ$143,M$7,$E161:$GQ161)+SUMIF($E$173:$GQ$173,M$7,$E191:$GQ191) -> -147968.01 | N25: =SUMIF($E$83:$GQ$83,N$7,$E101:$GQ101)+SUMIF($E$113:$GQ$113,N$7,$E131:$GQ131)+SUMIF($E$53:$GQ$53,N$7,$E71:$GQ71)+SUMIF($E$143:$GQ$143,N$7,$E161:$GQ161)+SUMIF($E$173:$GQ$173,N$7,$E191:$GQ191) -> -147968.01 | ... AD25: =SUMIF($E$83:$GQ$83,AD$7,$E101:$GQ101)+SUMIF($E$113:$GQ$113,AD$7,$E131:$GQ131)+SUMIF($E$53:$GQ$53,AD$7,$E71:$GQ71)+SUMIF($E$143:$GQ$143,AD$7,$E161:$GQ161)+SUMIF($E$173:$GQ$173,AD$7,$E191:$GQ191) -> 0
A26: 21 | B26: Saldo final (Balanço) | F26: =IFERROR(HLOOKUP(DATE(F7,12,1),$E$82:$AA$102,$A26,0),0)+IFERROR(HLOOKUP(DATE(F7,12,1),$E$112:$AA$132,$A26,0),0)+IFERROR(HLOOKUP(DATE(F7,12,1),$E$142:$AA$162,$A26,0),0)+IFERROR(HLOOKUP(DATE(F7,12,1),$E$172:$AA$192,$A26,0),0)+IFERROR(HLOOKUP(DATE(F7,12,1),$E$52:$AA$72,$A26,0),0) -> 200106.7 | G26: =IFERROR(HLOOKUP(DATE(G7,12,1),$E$82:$AC$102,$A26,0),0)+IFERROR(HLOOKUP(DATE(G7,12,1),$E$112:$GQ$132,$A26,0),0)+IFERROR(HLOOKUP(DATE(G7,12,1),$E$142:$GQ$162,$A26,0),0)+IFERROR(HLOOKUP(DATE(G7,12,1),$E$172:$GQ$192,$A26,0),0)+IFERROR(HLOOKUP(DATE(G7,12,1),$E$52:$AC$72,$A26,0),0) -> 1083015.9 | H26: =IFERROR(HLOOKUP(DATE(H7,12,1),$E$82:$AC$102,$A26,0),0)+IFERROR(HLOOKUP(DATE(H7,12,1),$E$112:$GQ$132,$A26,0),0)+IFERROR(HLOOKUP(DATE(H7,12,1),$E$142:$GQ$162,$A26,0),0)+IFERROR(HLOOKUP(DATE(H7,12,1),$E$172:$GQ$192,$A26,0),0)+IFERROR(HLOOKUP(DATE(H7,12,1),$E$52:$AC$72,$A26,0),0) -> 1123739.6 | I26: =IFERROR(HLOOKUP(DATE(I7,12,1),$E$82:$AC$102,$A26,0),0)+IFERROR(HLOOKUP(DATE(I7,12,1),$E$112:$GQ$132,$A26,0),0)+IFERROR(HLOOKUP(DATE(I7,12,1),$E$142:$GQ$162,$A26,0),0)+IFERROR(HLOOKUP(DATE(I7,12,1),$E$172:$GQ$192,$A26,0),0)+IFERROR(HLOOKUP(DATE(I7,12,1),$E$52:$AC$72,$A26,0),0) -> 1125126.4 | J26: =IFERROR(HLOOKUP(DATE(J7,12,1),$E$82:$AC$102,$A26,0),0)+IFERROR(HLOOKUP(DATE(J7,12,1),$E$112:$GQ$132,$A26,0),0)+IFERROR(HLOOKUP(DATE(J7,12,1),$E$142:$GQ$162,$A26,0),0)+IFERROR(HLOOKUP(DATE(J7,12,1),$E$172:$GQ$192,$A26,0),0)+IFERROR(HLOOKUP(DATE(J7,12,1),$E$52:$AC$72,$A26,0),0) -> 1123980.6 | K26: =IFERROR(HLOOKUP(DATE(K7,12,1),$E$82:$AC$102,$A26,0),0)+IFERROR(HLOOKUP(DATE(K7,12,1),$E$112:$GQ$132,$A26,0),0)+IFERROR(HLOOKUP(DATE(K7,12,1),$E$142:$GQ$162,$A26,0),0)+IFERROR(HLOOKUP(DATE(K7,12,1),$E$172:$GQ$192,$A26,0),0)+IFERROR(HLOOKUP(DATE(K7,12,1),$E$52:$AC$72,$A26,0),0) -> 983488.94 | L26: =IFERROR(HLOOKUP(DATE(L7,12,1),$E$82:$AC$102,$A26,0),0)+IFERROR(HLOOKUP(DATE(L7,12,1),$E$112:$GQ$132,$A26,0),0)+IFERROR(HLOOKUP(DATE(L7,12,1),$E$142:$GQ$162,$A26,0),0)+IFERROR(HLOOKUP(DATE(L7,12,1),$E$172:$GQ$192,$A26,0),0)+IFERROR(HLOOKUP(DATE(L7,12,1),$E$52:$AC$72,$A26,0),0) -> 842126.91 | M26: =IFERROR(HLOOKUP(DATE(M7,12,1),$E$82:$AC$102,$A26,0),0)+IFERROR(HLOOKUP(DATE(M7,12,1),$E$112:$GQ$132,$A26,0),0)+IFERROR(HLOOKUP(DATE(M7,12,1),$E$142:$GQ$162,$A26,0),0)+IFERROR(HLOOKUP(DATE(M7,12,1),$E$172:$GQ$192,$A26,0),0)+IFERROR(HLOOKUP(DATE(M7,12,1),$E$52:$AC$72,$A26,0),0) -> 700974.25 | N26: =IFERROR(HLOOKUP(DATE(N7,12,1),$E$82:$AC$102,$A26,0),0)+IFERROR(HLOOKUP(DATE(N7,12,1),$E$112:$GQ$132,$A26,0),0)+IFERROR(HLOOKUP(DATE(N7,12,1),$E$142:$GQ$162,$A26,0),0)+IFERROR(HLOOKUP(DATE(N7,12,1),$E$172:$GQ$192,$A26,0),0)+IFERROR(HLOOKUP(DATE(N7,12,1),$E$52:$AC$72,$A26,0),0) -> 560699.11 | ... AD26: =IFERROR(HLOOKUP(DATE(AD7,12,1),$E$82:$AC$102,$A26,0),0)+IFERROR(HLOOKUP(DATE(AD7,12,1),$E$112:$GQ$132,$A26,0),0)+IFERROR(HLOOKUP(DATE(AD7,12,1),$E$142:$GQ$162,$A26,0),0)+IFERROR(HLOOKUP(DATE(AD7,12,1),$E$172:$GQ$192,$A26,0),0)+IFERROR(HLOOKUP(DATE(AD7,12,1),$E$52:$AC$72,$A26,0),0) -> 0
B27: Saldo Curto Prazo (Balanço) | F27: =IF(F26>0,-SUM(G25),0) -> 40194.704 | G27: =IF(G26>0,-SUM(H25),0) -> 0 | H27: =IF(H26>0,-SUM(I25),0) -> 14634.678 | I27: =IF(I26>0,-SUM(J25),0) -> 14634.678 | J27: =IF(J26>0,-SUM(K25),0) -> 147968.01 | K27: =IF(K26>0,-SUM(L25:O25),0) -> 585226.74 | L27: =IF(L26>0,-SUM(M25:P25),0) -> 583648.95 | M27: =IF(M26>0,-SUM(N25:Q25),0) -> 587382.49 | N27: =IF(N26>0,-SUM(O25:R25),0) -> 454049.16 | O27: =IF(O26>0,-SUM(P25:S25),0) -> 327361.13 | P27: =IF(P26>0,-SUM(Q25:T25),0) -> 195605.59 | Q27: =IF(Q26>0,-SUM(R25:U25),0) -> 58538.713 | R27: =IF(R26>0,-SUM(S25:V25),0) -> 58538.713 | ... AD27: =IF(AD26>0,-SUM(AE25:AH25),0) -> 0
B28: Saldo Longo Prazo (Balanço) | F28: =ROUND(F26-F27+F30,8) -> 159912 | G28: =ROUND(G26-G27+G30,8) -> 1078498.4 | H28: =ROUND(H26-H27+H30,8) -> 1104838.4 | I28: =ROUND(I26-I27+I30,8) -> 1106476.1 | J28: =ROUND(J26-J27+J30,8) -> 972247.92 | K28: =ROUND(K26-K27+K30,8) -> 394748.55 | L28: =ROUND(L26-L27+L30,8) -> 255215.28 | M28: =ROUND(M26-M27+M30,8) -> 110580.06 | ... AB28: =ROUND(AB26-AB27+AB30,8) -> 0 | AC28: =ROUND(AC26-AC27,8) -> 0 | AD28: =ROUND(AD26-AD27,8) -> 0
B30: Custos das Transações | F30: 0 | G30: =-0.5%*(G21) -> -4517.5611 | H30: =G30+H31 -> -4266.5854 | I30: =H30+I31 -> -4015.6098 | J30: =I30+J31 -> -3764.6342 | K30: =J30+K31 -> -3513.6586 | L30: =K30+L31 -> -3262.683 | M30: =L30+M31 -> -3011.7074 | N30: =M30+N31 -> -2760.7318 | O30: =N30+O31 -> -2509.7561 | ... X30: =W30+X31 -> -250.97561 | Y30: 0
G31: =-F30/20 -> 0 | H31: =-G30/18 -> 250.97561 | I31: =H31 -> 250.97561 | J31: =I31 -> 250.97561 | K31: =J31 -> 250.97561 | L31: =K31 -> 250.97561 | M31: =L31 -> 250.97561 | N31: =M31 -> 250.97561 | O31: =N31 -> 250.97561 | P31: =O31 -> 250.97561 | ... Y31: =X31 -> 250.97561
B33: Dívida de Balanceamento
B34: Saldo Inicial | G34: =PROJ_AGCeAGPar!I320 -> 0 | H34: =PROJ_AGCeAGPar!J320 -> 0 | I34: =PROJ_AGCeAGPar!K320 -> 0 | J34: =PROJ_AGCeAGPar!L320 -> 0 | K34: =PROJ_AGCeAGPar!M320 -> 0 | L34: =PROJ_AGCeAGPar!N320 -> 0 | M34: =PROJ_AGCeAGPar!O320 -> 0 | N34: =PROJ_AGCeAGPar!P320 -> 0 | ... AA34: =PROJ_AGCeAGPar!AC320 -> 0
B35: Adição | G35: =MAX(0,G39-G34) -> 0 | H35: =MAX(0,H39-H34) -> 0 | I35: =MAX(0,I39-I34) -> 0 | J35: =MAX(0,J39-J34) -> 0 | K35: =MAX(0,K39-K34) -> 0 | L35: =MAX(0,L39-L34) -> 0 | M35: =MAX(0,M39-M34) -> 0 | N35: =MAX(0,N39-N34) -> 0 | ... Y35: =MAX(0,Y39-Y34) -> 0 | Z35: =Z39-Z34 -> 0 | AA35: =AA39-AA34 -> 0
B36: Amortização | G36: =MIN(0,G39-G34) -> 0 | H36: =MIN(0,H39-H34) -> 0 | I36: =MIN(0,I39-I34) -> 0 | J36: =MIN(0,J39-J34) -> 0 | K36: =MIN(0,K39-K34) -> 0 | L36: =MIN(0,L39-L34) -> 0 | M36: =MIN(0,M39-M34) -> 0 | N36: =MIN(0,N39-N34) -> 0 | ... Y36: =MIN(0,Y39-Y34) -> 0 | Z36: =Z39-Z34 -> 0 | AA36: =AA39-AA34 -> 0
B37: Juros no Período | C37: % CDI | G37: =-G38*(G34) -> 0 | H37: =-H38*(H34) -> 0 | I37: =-I38*(I34) -> 0 | J37: =-J38*(J34) -> 0 | K37: =-K38*(K34) -> 0 | L37: =-L38*(L34) -> 0 | M37: =-M38*(M34) -> 0 | N37: =-N38*(N34) -> 0 | ... AA37: =-AA38*(AA34) -> 0
B38: Custo médio da Dívida | C38: 1 | G38: =$C$38*HLOOKUP(G$7,Macroeconomics!$B$5:$GB$36,Macroeconomics!$A$24,0) -> 0.087560431 | H38: =$C$38*HLOOKUP(H$7,Macroeconomics!$B$5:$GB$36,Macroeconomics!$A$24,0) -> 0.084449317 | I38: =$C$38*HLOOKUP(I$7,Macroeconomics!$B$5:$GB$36,Macroeconomics!$A$24,0) -> 0.096145243 | J38: =$C$38*HLOOKUP(J$7,Macroeconomics!$B$5:$GB$36,Macroeconomics!$A$24,0) -> 0.094942253 | K38: =$C$38*HLOOKUP(K$7,Macroeconomics!$B$5:$GB$36,Macroeconomics!$A$24,0) -> 0.0967 | L38: =$C$38*HLOOKUP(L$7,Macroeconomics!$B$5:$GB$36,Macroeconomics!$A$24,0) -> 0.0967 | M38: =$C$38*HLOOKUP(M$7,Macroeconomics!$B$5:$GB$36,Macroeconomics!$A$24,0) -> 0.0943 | N38: =$C$38*HLOOKUP(N$7,Macroeconomics!$B$5:$GB$36,Macroeconomics!$A$24,0) -> 0.0942 | ... AA38: =$C$38*HLOOKUP(AA$7,Macroeconomics!$B$5:$GB$36,Macroeconomics!$A$24,0) -> 0.0893
B39: Saldo Final | G39: =PROJ_AGCeAGPar!J320 -> 0 | H39: =PROJ_AGCeAGPar!K320 -> 0 | I39: =PROJ_AGCeAGPar!L320 -> 0 | J39: =PROJ_AGCeAGPar!M320 -> 0 | K39: =PROJ_AGCeAGPar!N320 -> 0 | L39: =PROJ_AGCeAGPar!O320 -> 0 | M39: =PROJ_AGCeAGPar!P320 -> 0 | N39: =PROJ_AGCeAGPar!Q320 -> 0 | ... AA39: =PROJ_AGCeAGPar!AD320 -> 0
B41: Receita Financeira
B42: Caixa+AFI+Mútuos Inicial | D42: =PROJ_AGCeAGPar!G305+PROJ_AGCeAGPar!G306+PROJ_AGCeAGPar!G307*20%+PROJ_AGCeAGPar!G312 -> 273.6552 | E42: =PROJ_AGCeAGPar!H305+PROJ_AGCeAGPar!H306+PROJ_AGCeAGPar!H307*20%+PROJ_AGCeAGPar!H312 -> 574.6262 | F42: =PROJ_AGCeAGPar!I305+PROJ_AGCeAGPar!I306+PROJ_AGCeAGPar!I307*20%+PROJ_AGCeAGPar!I312 -> 51.3862 | G42: =PROJ_AGCeAGPar!J305+PROJ_AGCeAGPar!J306+PROJ_AGCeAGPar!J307*20%+PROJ_AGCeAGPar!J312 -> 13.444 | H42: =PROJ_AGCeAGPar!K305+PROJ_AGCeAGPar!K306+PROJ_AGCeAGPar!K307*20%+PROJ_AGCeAGPar!K312 -> 606.33932 | I42: =PROJ_AGCeAGPar!L305+PROJ_AGCeAGPar!L306+PROJ_AGCeAGPar!L307*20%+PROJ_AGCeAGPar!L312 -> 582.39049 | J42: =PROJ_AGCeAGPar!M305+PROJ_AGCeAGPar!M306+PROJ_AGCeAGPar!M307*20%+PROJ_AGCeAGPar!M312 -> 843.33904 | K42: =PROJ_AGCeAGPar!N305+PROJ_AGCeAGPar!N306+PROJ_AGCeAGPar!N307*20%+PROJ_AGCeAGPar!N312 -> 1096.2916 | ... Y42: =PROJ_AGCeAGPar!AB305+PROJ_AGCeAGPar!AB306+PROJ_AGCeAGPar!AB307*20%+PROJ_AGCeAGPar!AB312 -> 0
B43: Caixa+AFI+Mútuos Final | D43: =PROJ_AGCeAGPar!H305+PROJ_AGCeAGPar!H306+PROJ_AGCeAGPar!H307*20%+PROJ_AGCeAGPar!H312 -> 574.6262 | E43: =PROJ_AGCeAGPar!I305+PROJ_AGCeAGPar!I306+PROJ_AGCeAGPar!I307*20%+PROJ_AGCeAGPar!I312 -> 51.3862 | F43: =PROJ_AGCeAGPar!J305+PROJ_AGCeAGPar!J306+PROJ_AGCeAGPar!J307*20%+PROJ_AGCeAGPar!J312 -> 13.444 | G43: =PROJ_AGCeAGPar!K305+PROJ_AGCeAGPar!K306+PROJ_AGCeAGPar!K307*20%+PROJ_AGCeAGPar!K312 -> 606.33932 | H43: =PROJ_AGCeAGPar!L305+PROJ_AGCeAGPar!L306+PROJ_AGCeAGPar!L307*20%+PROJ_AGCeAGPar!L312 -> 582.39049 | I43: =PROJ_AGCeAGPar!M305+PROJ_AGCeAGPar!M306+PROJ_AGCeAGPar!M307*20%+PROJ_AGCeAGPar!M312 -> 843.33904 | J43: =PROJ_AGCeAGPar!N305+PROJ_AGCeAGPar!N306+PROJ_AGCeAGPar!N307*20%+PROJ_AGCeAGPar!N312 -> 1096.2916 | K43: =PROJ_AGCeAGPar!O305+PROJ_AGCeAGPar!O306+PROJ_AGCeAGPar!O307*20%+PROJ_AGCeAGPar!O312 -> 1246.6281 | ... Y43: =PROJ_AGCeAGPar!AC305+PROJ_AGCeAGPar!AC306+PROJ_AGCeAGPar!AC307*20%+PROJ_AGCeAGPar!AC312 -> 0
B44: Saldo Médio | D44: =(D42+D43)/2 -> 424.1407 | E44: =(E42+E43)/2 -> 313.0062 | F44: =(F42+F43)/2 -> 32.4151 | G44: =(G42+G43)/2 -> 309.89166 | H44: =(H42+H43)/2 -> 594.3649 | I44: =(I42+I43)/2 -> 712.86476 | J44: =(J42+J43)/2 -> 969.81534 | K44: =(K42+K43)/2 -> 1171.4599 | ... Y44: =(Y42+Y43)/2 -> 0
B45: Receita Financeiras (% CDI) | C45: 1 | D45: =PROJ_AGCeAGPar!H287 -> 4.533 | E45: =PROJ_AGCeAGPar!I287 -> 4.305 | F45: =PROJ_AGCeAGPar!J287 -> 1.458 | G45: =HLOOKUP(G$7,Macroeconomics!$B$5:$GB$36,Macroeconomics!$A$24,0)*$C$45*G42 -> 1.1771624 | H45: =HLOOKUP(H$7,Macroeconomics!$B$5:$GB$36,Macroeconomics!$A$24,0)*$C$45*H42*50% -> 25.60247 | I45: =HLOOKUP(I$7,Macroeconomics!$B$5:$GB$36,Macroeconomics!$A$24,0)*$C$45*I42 -> 55.994075 | J45: =HLOOKUP(J$7,Macroeconomics!$B$5:$GB$36,Macroeconomics!$A$24,0)*$C$45*J42 -> 80.068508 | K45: =HLOOKUP(K$7,Macroeconomics!$B$5:$GB$36,Macroeconomics!$A$24,0)*$C$45*K42 -> 106.0114 | L45: =HLOOKUP(L$7,Macroeconomics!$B$5:$GB$36,Macroeconomics!$A$24,0)*$C$45*L42 -> 120.54893 | M45: =HLOOKUP(M$7,Macroeconomics!$B$5:$GB$36,Macroeconomics!$A$24,0)*$C$45*M42 -> 135.47539 | N45: =HLOOKUP(N$7,Macroeconomics!$B$5:$GB$36,Macroeconomics!$A$24,0)*$C$45*N42 -> 156.3898 | O45: =HLOOKUP(O$7,Macroeconomics!$B$5:$GB$36,Macroeconomics!$A$24,0)*$C$45*O42 -> 182.25807 | P45: =HLOOKUP(P$7,Macroeconomics!$B$5:$GB$36,Macroeconomics!$A$24,0)*$C$45*P42 -> 214.16591 | ... Y45: =HLOOKUP(Y$7,Macroeconomics!$B$5:$GB$36,Macroeconomics!$A$24,0)*$C$45*Y42 -> 0
B46: % Saldo Médio | D46: =D45/D44 -> 0.010687491 | E46: =E45/E44 -> 0.013753721 | F46: =F45/F44 -> 0.044979038 | G46: =G45/G44 -> 0.0037986257 | H46: =H45/H44 -> 0.04307534 | I46: =I45/I44 -> 0.078547963 | J46: =J45/J44 -> 0.082560571 | K46: =K45/K44 -> 0.090495121 | ... Y46: =Y45/Y44 -> #DIV/0!
B47: % CDI | D47: =D46/HLOOKUP(D$7,Macroeconomics!$B$5:$GB$36,Macroeconomics!$A$24,0) -> 0.10820837 | E47: =E46/HLOOKUP(E$7,Macroeconomics!$B$5:$GB$36,Macroeconomics!$A$24,0) -> 0.14096196 | F47: =F46/HLOOKUP(F$7,Macroeconomics!$B$5:$GB$36,Macroeconomics!$A$24,0) -> 0.38813553 | G47: =G46/HLOOKUP(G$7,Macroeconomics!$B$5:$GB$36,Macroeconomics!$A$24,0) -> 0.043382904 | H47: =H46/HLOOKUP(H$7,Macroeconomics!$B$5:$GB$36,Macroeconomics!$A$24,0) -> 0.51007329 | I47: =I46/HLOOKUP(I$7,Macroeconomics!$B$5:$GB$36,Macroeconomics!$A$24,0) -> 0.81697191 | J47: =J46/HLOOKUP(J$7,Macroeconomics!$B$5:$GB$36,Macroeconomics!$A$24,0) -> 0.86958723 | K47: =K46/HLOOKUP(K$7,Macroeconomics!$B$5:$GB$36,Macroeconomics!$A$24,0) -> 0.93583372 | ... Y47: =Y46/HLOOKUP(Y$7,Macroeconomics!$B$5:$GB$36,Macroeconomics!$A$24,0) -> #DIV/0!
B50: 2. DEBENTURES
B52: 1º Emissão Privada - SUDAM | E52: =C54 -> 40878 | F52: =EDATE(E52,12) -> 41244 | G52: =EDATE(F52,12) -> 41609 | H52: =EDATE(G52,12) -> 41974 | I52: =EDATE(H52,12) -> 42339 | J52: =EDATE(I52,12) -> 42705 | K52: =EDATE(J52,12) -> 43070 | L52: =EDATE(K52,12) -> 43435 | M52: =EDATE(L52,12) -> 43800 | ... AA52: =EDATE(Z52,12) -> 48914
E53: =YEAR(E52) -> 2011 | F53: =YEAR(F52) -> 2012 | G53: =YEAR(G52) -> 2013 | H53: =YEAR(H52) -> 2014 | I53: =YEAR(I52) -> 2015 | J53: =YEAR(J52) -> 2016 | K53: =YEAR(K52) -> 2017 | L53: =YEAR(L52) -> 2018 | ... AA53: =YEAR(AA52) -> 2033
B54: Dt desembolso | C54: 40878
B55: Prazo Total | C55: 48183
B56: Final Carência | C56: 41244
B57: Início Amortização principal | C57: 41974 | D57: Amort => | H57: =1/18 -> 0.055555556 | I57: =1/18 -> 0.055555556 | J57: =1/18 -> 0.055555556 | K57: =1/18 -> 0.055555556 | L57: =1/18 -> 0.055555556 | M57: =1/18 -> 0.055555556 | N57: =1/18 -> 0.055555556 | O57: =1/18 -> 0.055555556 | ... Y57: =1/18 -> 0.055555556
B58: Prazo Amortização (anos) | C58: 6
B59: Indexador | C59: TJLP
B60: Spread a.a. over Indexador | C60: 0.0165 | E60: =HLOOKUP(E53,Macroeconomics!$B$5:$GB$36,Macroeconomics!$A$31,0)+$C60 -> 0.0765 | F60: =(1+VLOOKUP(EOMONTH(F52,0),Macroeconomics!$B$67:$R$380,Macroeconomics!$C$66,0))*(1+$C60)^(1/12)-1 -> 0.0075524505 | G60: =(1+VLOOKUP(EOMONTH(G52,0),Macroeconomics!$B$67:$R$380,Macroeconomics!$C$66,0))*(1+$C60)^(1/12)-1 -> 0.009023723 | H60: =(1+VLOOKUP(EOMONTH(H52,0),Macroeconomics!$B$67:$R$380,Macroeconomics!$C$66,0))*(1+$C60)^(1/12)-1 -> 0.0093931186 | I60: =(1+VLOOKUP(EOMONTH(I52,0),Macroeconomics!$B$67:$R$380,Macroeconomics!$C$66,0))*(1+$C60)^(1/12)-1 -> 0.0093931186 | J60: =(1+VLOOKUP(EOMONTH(J52,0),Macroeconomics!$B$67:$R$380,Macroeconomics!$C$66,0))*(1+$C60)^(1/12)-1 -> 0.0090970476 | K60: =(1+VLOOKUP(EOMONTH(K52,0),Macroeconomics!$B$67:$R$380,Macroeconomics!$C$66,0))*(1+$C60)^(1/12)-1 -> 0.0090970476 | L60: =(1+VLOOKUP(EOMONTH(L52,0),Macroeconomics!$B$67:$R$380,Macroeconomics!$C$66,0))*(1+$C60)^(1/12)-1 -> 0.0089128385 | M60: =(1+VLOOKUP(EOMONTH(M52,0),Macroeconomics!$B$67:$R$380,Macroeconomics!$C$66,0))*(1+$C60)^(1/12)-1 -> 0.0089051551 | ... Z60: =(1+VLOOKUP(EOMONTH(Z52,0),Macroeconomics!$B$67:$R$380,Macroeconomics!$C$66,0))*(1+$C60)^(1/12)-1 -> 0.0085278771
B61: Amortização principal (3=trim, 6=sem, 12 =anual) | C61: 6
B62: Paga juros na carencia? (0=N;1=S) | C62: 1 | D62: Juros Pagos | E62: =IF(OR(E52<=$C54,E52>$C55),0,IF(AND(E52<=$C56,$C62=1,MOD(MONTH(E52)-MONTH($C54),$C61)=0),1,IF(AND(MOD(MONTH(E52)-MONTH($C54),$C61)=0,E52>=$C56),1,0))) -> 0 | F62: =IF(OR(F52<=$C54,F52>$C55),0,IF(AND(F52<=$C56,$C62=1,MOD(MONTH(F52)-MONTH($C54),$C61)=0),1,IF(AND(MOD(MONTH(F52)-MONTH($C54),$C61)=0,F52>=$C56),1,0))) -> 1 | G62: =IF(OR(G52<=$C54,G52>$C55),0,IF(AND(G52<=$C56,$C62=1,MOD(MONTH(G52)-MONTH($C54),$C61)=0),1,IF(AND(MOD(MONTH(G52)-MONTH($C54),$C61)=0,G52>=$C56),1,0))) -> 1 | H62: =IF(OR(H52<=$C54,H52>$C55),0,IF(AND(H52<=$C56,$C62=1,MOD(MONTH(H52)-MONTH($C54),$C61)=0),1,IF(AND(MOD(MONTH(H52)-MONTH($C54),$C61)=0,H52>=$C56),1,0))) -> 1 | I62: =IF(OR(I52<=$C54,I52>$C55),0,IF(AND(I52<=$C56,$C62=1,MOD(MONTH(I52)-MONTH($C54),$C61)=0),1,IF(AND(MOD(MONTH(I52)-MONTH($C54),$C61)=0,I52>=$C56),1,0))) -> 1 | J62: =IF(OR(J52<=$C54,J52>$C55),0,IF(AND(J52<=$C56,$C62=1,MOD(MONTH(J52)-MONTH($C54),$C61)=0),1,IF(AND(MOD(MONTH(J52)-MONTH($C54),$C61)=0,J52>=$C56),1,0))) -> 1 | K62: =IF(OR(K52<=$C54,K52>$C55),0,IF(AND(K52<=$C56,$C62=1,MOD(MONTH(K52)-MONTH($C54),$C61)=0),1,IF(AND(MOD(MONTH(K52)-MONTH($C54),$C61)=0,K52>=$C56),1,0))) -> 1 | L62: =IF(OR(L52<=$C54,L52>$C55),0,IF(AND(L52<=$C56,$C62=1,MOD(MONTH(L52)-MONTH($C54),$C61)=0),1,IF(AND(MOD(MONTH(L52)-MONTH($C54),$C61)=0,L52>=$C56),1,0))) -> 1 | ... Z62: =IF(OR(Z52<=$C54,Z52>$C55),0,IF(AND(Z52<=$C56,$C62=1,MOD(MONTH(Z52)-MONTH($C54),$C61)=0),1,IF(AND(MOD(MONTH(Z52)-MONTH($C54),$C61)=0,Z52>=$C56),1,0))) -> 0
B63: Capitaliza juros no inicio da amort? (0=N;1=S) | C63: 0 | D63: Prestações pagas | E63: =IF(E57<>"",1,0) -> 0 | F63: =IF(F57<>"",1,0) -> 0 | G63: =IF(G57<>"",1,0) -> 0 | H63: =IF(H57<>"",1,0) -> 1 | I63: =IF(I57<>"",1,0) -> 1 | J63: =IF(J57<>"",1,0) -> 1 | K63: =IF(K57<>"",1,0) -> 1 | L63: =IF(L57<>"",1,0) -> 1 | ... Z63: =IF(Z57<>"",1,0) -> 0
B64: Prestações remanescentes | C64: 18 | E64: =MAX(C64-E63,0) -> 18 | F64: =MAX(E64-F63,0) -> 18 | G64: =MAX(F64-G63,0) -> 18 | H64: =MAX(G64-H63,0) -> 17 | I64: =MAX(H64-I63,0) -> 16 | J64: =MAX(I64-J63,0) -> 15 | K64: =MAX(J64-K63,0) -> 14 | L64: =MAX(K64-L63,0) -> 13 | M64: =MAX(L64-M63,0) -> 12 | ... Z64: =MAX(Y64-Z63,0) -> 0
B66: Saldo inicial | E66: =D72 -> 0 | F66: =E72 -> 159912 | G66: =F72 -> 265413.71 | H66: =G72 -> 263424.21 | I66: =H72 -> 248789.53 | J66: =I72 -> 234154.85 | K66: =J72 -> 219520.17 | L66: =K72 -> 204885.5 | ... Z66: =Y72 -> 0
B67: Novo funding | C67: =E67+F67 -> 263424.21 | E67: =+E72 -> 159912 | F67: =263424.21-E72 -> 103512.21 | G67: =(IF(G52<$C54,0,IF(G52=$C54,$C67,0))) -> 0 | H67: =(IF(H52<$C54,0,IF(H52=$C54,$C67,0))) -> 0 | I67: =(IF(I52<$C54,0,IF(I52=$C54,$C67,0))) -> 0 | J67: =(IF(J52<$C54,0,IF(J52=$C54,$C67,0))) -> 0 | K67: =(IF(K52<$C54,0,IF(K52=$C54,$C67,0))) -> 0 | L67: =(IF(L52<$C54,0,IF(L52=$C54,$C67,0))) -> 0 | M67: =(IF(M52<$C54,0,IF(M52=$C54,$C67,0))) -> 0 | N67: =(IF(N52<$C54,0,IF(N52=$C54,$C67,0))) -> 0 | ... Z67: =(IF(Z52<$C54,0,IF(Z52=$C54,$C67,0))) -> 0
B68: Correção Monetária IPCA | E68: =SUM(E66:E67,-D73)*(E76-1) -> 0 | F68: =SUM(F66:F67,-E73)*(F76-1) -> 0 | G68: =SUM(G66:G67,-F73)*(G76-1) -> 0 | H68: =SUM(H66:H67,-G73)*(H76-1) -> 0 | I68: =SUM(I66:I67,-H73)*(I76-1) -> 0 | J68: =SUM(J66:J67,-I73)*(J76-1) -> 0 | K68: =SUM(K66:K67,-J73)*(K76-1) -> 0 | L68: =SUM(L66:L67,-K73)*(L76-1) -> 0 | ... Z68: =SUM(Z66:Z67,-Y73)*(Z76-1) -> 0
B69: Juros apropriados (DRE) | E69: 0 | F69: =SUM(F66:F68)*F60 -> 1989.4983 | G69: =SUM(G66:G68)*G60 -> 2395.0198 | H69: =SUM(H66:H68)*H60 -> 2474.3748 | I69: =SUM(I66:I68)*I60 -> 2336.9096 | J69: =SUM(J66:J68)*J60 -> 2130.1179 | K69: =SUM(K66:K68)*K60 -> 1996.9855 | L69: =SUM(L66:L68)*L60 -> 1826.1113 | M69: =SUM(M66:M68)*M60 -> 1694.213 | ... Z69: =SUM(Z66:Z68)*Z60 -> 0
B70: Juros pagos (Caixa) | E70: =IF(E62=1,-D73-E69,0)*IF(AND(E52=$C57,$C63=1,$C62=0),0,1) -> 0 | F70: 0 | G70: =IF(G62=1,-F73-G69,0)*IF(AND(G52=$C57,$C63=1,$C62=0),0,1) -> -4384.5181 | H70: =IF(H62=1,-G73-H69,0)*IF(AND(H52=$C57,$C63=1,$C62=0),0,1) -> -2474.3748 | I70: =IF(I62=1,-H73-I69,0)*IF(AND(I52=$C57,$C63=1,$C62=0),0,1) -> -2336.9096 | J70: =IF(J62=1,-I73-J69,0)*IF(AND(J52=$C57,$C63=1,$C62=0),0,1) -> -2130.1179 | K70: =IF(K62=1,-J73-K69,0)*IF(AND(K52=$C57,$C63=1,$C62=0),0,1) -> -1996.9855 | L70: =IF(L62=1,-K73-L69,0)*IF(AND(L52=$C57,$C63=1,$C62=0),0,1) -> -1826.1113 | M70: =IF(M62=1,-L73-M69,0)*IF(AND(M52=$C57,$C63=1,$C62=0),0,1) -> -1694.213 | N70: =IF(N62=1,-M73-N69,0)*IF(AND(N52=$C57,$C63=1,$C62=0),0,1) -> -1563.889 | ... Z70: =IF(Z62=1,-Y73-Z69,0)*IF(AND(Z52=$C57,$C63=1,$C62=0),0,1) -> 0
B71: Amortização principal (Caixa) | E71: =-E57*LOOKUP($C54,$E52:$GQ52,$E67:$GQ67) -> 0 | F71: =-F57*LOOKUP($C54,$E52:$GQ52,$E67:$GQ67) -> 0 | G71: =-G57*LOOKUP($C54,$E52:$GQ52,$E67:$GQ67) -> 0 | H71: =-H57*$C$67 -> -14634.678 | I71: =-I57*$C$67 -> -14634.678 | J71: =-J57*$C$67 -> -14634.678 | K71: =-K57*$C$67 -> -14634.678 | L71: =-L57*$C$67 -> -14634.678 | M71: =-M57*$C$67 -> -14634.678 | N71: =-N57*$C$67 -> -14634.678 | O71: =-O57*$C$67 -> -14634.678 | ... Y71: =-Y57*$C$67 -> -14634.678 | Z71: =-Z57*LOOKUP($C54,$E52:$GQ52,$E67:$GQ67) -> 0
B72: Saldo final (Balanço) | E72: 159912 | F72: =IF(SUM(F66:F71)<0.00000001,ROUND(SUM(F66:F71),7),SUM(F66:F71)) -> 265413.71 | G72: =IF(SUM(G66:G71)<0.00000001,ROUND(SUM(G66:G71),7),SUM(G66:G71)) -> 263424.21 | H72: =IF(SUM(H66:H71)<0.00000001,ROUND(SUM(H66:H71),7),SUM(H66:H71)) -> 248789.53 | I72: =IF(SUM(I66:I71)<0.00000001,ROUND(SUM(I66:I71),7),SUM(I66:I71)) -> 234154.85 | J72: =IF(SUM(J66:J71)<0.00000001,ROUND(SUM(J66:J71),7),SUM(J66:J71)) -> 219520.17 | K72: =IF(SUM(K66:K71)<0.00000001,ROUND(SUM(K66:K71),7),SUM(K66:K71)) -> 204885.5 | L72: =IF(SUM(L66:L71)<0.00000001,ROUND(SUM(L66:L71),7),SUM(L66:L71)) -> 190250.82 | M72: =IF(SUM(M66:M71)<0.00000001,ROUND(SUM(M66:M71),7),SUM(M66:M71)) -> 175616.14 | ... Z72: =IF(SUM(Z66:Z71)<0.00000001,ROUND(SUM(Z66:Z71),7),SUM(Z66:Z71)) -> 0
B73: Juros acumulados | E73: =(E69+D73+E70)*IF(AND(E52=$C57,$C63),0,1) -> 0 | F73: =(F69+E73+F70)*IF(AND(F52=$C57,$C63),0,1) -> 1989.4983 | G73: =(G69+F73+G70)*IF(AND(G52=$C57,$C63),0,1) -> 0 | H73: =(H69+G73+H70)*IF(AND(H52=$C57,$C63),0,1) -> 0 | I73: =(I69+H73+I70)*IF(AND(I52=$C57,$C63),0,1) -> 0 | J73: =(J69+I73+J70)*IF(AND(J52=$C57,$C63),0,1) -> 0 | K73: =(K69+J73+K70)*IF(AND(K52=$C57,$C63),0,1) -> 0 | L73: =(L69+K73+L70)*IF(AND(L52=$C57,$C63),0,1) -> 0 | ... Z73: =(Z69+Y73+Z70)*IF(AND(Z52=$C57,$C63),0,1) -> 0
B75: Serviço da divida | E75: =E71+E70 -> 0 | F75: =F71+F70 -> 0 | G75: =G71+G70 -> -4384.5181 | H75: =H71+H70 -> -17109.053 | I75: =I71+I70 -> -16971.588 | J75: =J71+J70 -> -16764.796 | K75: =K71+K70 -> -16631.664 | L75: =L71+L70 -> -16460.79 | ... Z75: =Z71+Z70 -> 0
B76: Correção Monetária no período | C76: 1 | E76: =IF(E52>=$C54,1+E59,1) -> 1 | F76: =IF(F52>=$C54,1+F59,1) -> 1 | G76: =IF(G52>=$C54,1+G59,1) -> 1 | H76: =IF(H52>=$C54,1+H59,1) -> 1 | I76: =IF(I52>=$C54,1+I59,1) -> 1 | J76: =IF(J52>=$C54,1+J59,1) -> 1 | K76: =IF(K52>=$C54,1+K59,1) -> 1 | L76: =IF(L52>=$C54,1+L59,1) -> 1 | ... Z76: =IF(Z52>=$C54,1+Z59,1) -> 1
B77: Correção Monetária Acumulada | C77: 1 | E77: =C77*E76 -> 1 | F77: =D77*F76 -> 0 | G77: =E77*G76 -> 1 | H77: =F77*H76 -> 0 | I77: =G77*I76 -> 1 | J77: =H77*J76 -> 0 | K77: =I77*K76 -> 1 | L77: =J77*L76 -> 0 | ... Z77: =X77*Z76 -> 0
B78: Correção Monetária Acumulada Juros a Capitalizar | C78: 1 | E78: =IF(E52>$C57,(1+E59)*C78,1) -> 1 | F78: =IF(F52>$C57,(1+F59)*D78,1) -> 1 | G78: =IF(G52>$C57,(1+G59)*E78,1) -> 1 | H78: =IF(H52>$C57,(1+H59)*F78,1) -> 1 | I78: =IF(I52>$C57,(1+I59)*G78,1) -> 1 | J78: =IF(J52>$C57,(1+J59)*H78,1) -> 1 | K78: =IF(K52>$C57,(1+K59)*I78,1) -> 1 | L78: =IF(L52>$C57,(1+L59)*J78,1) -> 1 | ... Z78: =IF(Z52>$C57,(1+Z59)*X78,1) -> 1
B79: Saldo Devedor Base (capitalização de juros) | E79: =SUM(E66:E70) -> 159912 | F79: =SUM(F66:F70) -> 265413.71 | G79: =SUM(G66:G70) -> 263424.21 | H79: =SUM(H66:H70) -> 263424.21 | I79: =SUM(I66:I70) -> 248789.53 | J79: =SUM(J66:J70) -> 234154.85 | K79: =SUM(K66:K70) -> 219520.17 | L79: =SUM(L66:L70) -> 204885.5 | ... Z79: =SUM(Z66:Z70) -> 0
B82: 1º Emissão - Série Única | E82: =C84 -> 39052 | F82: =EDATE(E82,12) -> 39417 | G82: =EDATE(F82,12) -> 39783 | H82: =EDATE(G82,12) -> 40148 | I82: =EDATE(H82,12) -> 40513 | J82: =EDATE(I82,12) -> 40878 | K82: =EDATE(J82,12) -> 41244 | L82: =EDATE(K82,12) -> 41609 | M82: =EDATE(L82,12) -> 41974 | ... AC82: =EDATE(AB82,12) -> 47818
E83: =YEAR(E82) -> 2006 | F83: =YEAR(F82) -> 2007 | G83: =YEAR(G82) -> 2008 | H83: =YEAR(H82) -> 2009 | I83: =YEAR(I82) -> 2010 | J83: =YEAR(J82) -> 2011 | K83: =YEAR(K82) -> 2012 | L83: =YEAR(L82) -> 2013 | ... AC83: =YEAR(AC82) -> 2030
B84: Dt desembolso | C84: 39052
B85: Prazo Total | C85: 41244
B86: Final Carência | C86: 40787
B87: Início Amortização principal | C87: 41791 | D87: Amort => | I87: 0.3333 | J87: 0.3333 | K87: 0.3334
B88: Prazo Amortização (anos) | C88: 6
B89: Indexador | C89: % CDI
B90: Spread a.a. over Indexador | C90: 1.041 | E90: =HLOOKUP(E83,Macroeconomics!$B$5:$GB$36,Macroeconomics!$A$24,0)*$C$90 -> 0.1564325 | F90: =HLOOKUP(F83,Macroeconomics!$B$5:$GB$36,Macroeconomics!$A$24,0)*$C$90 -> 0.12300265 | G90: =HLOOKUP(G83,Macroeconomics!$B$5:$GB$36,Macroeconomics!$A$24,0)*$C$90 -> 0.1288532 | H90: =HLOOKUP(H83,Macroeconomics!$B$5:$GB$36,Macroeconomics!$A$24,0)*$C$90 -> 0.10281717 | I90: =HLOOKUP(I83,Macroeconomics!$B$5:$GB$36,Macroeconomics!$A$24,0)*$C$90 -> 0.10157084 | J90: =HLOOKUP(J83,Macroeconomics!$B$5:$GB$36,Macroeconomics!$A$24,0)*$C$90 -> 0.12063615 | K90: =HLOOKUP(K83,Macroeconomics!$B$5:$GB$36,Macroeconomics!$A$24,0)*$C$90 -> 0.091150408 | L90: =HLOOKUP(L83,Macroeconomics!$B$5:$GB$36,Macroeconomics!$A$24,0)*$C$90 -> 0.087911739 | ... AC90: =HLOOKUP(AC83,Macroeconomics!$B$5:$GB$36,Macroeconomics!$A$24,0)*$C$90 -> 0.0929613
B91: Amortização principal (3=trim, 6=sem, 12 =anual) | C91: 3
B92: Paga juros na carencia? (0=N;1=S) | C92: 1 | D92: Juros Pagos | E92: =IF(OR(E$82<=$C$84,E$82>$C$85),0,IF(AND(E$82<=$C$86,$C92=1,MOD(MONTH(E$82)-MONTH($C$84),$C$91)=0),1,IF(AND(MOD(MONTH(E$82)-MONTH($C$84),$C$91)=0,E$82>=$C$86),1,0))) -> 0 | F92: =IF(OR(F$82<=$C$84,F$82>$C$85),0,IF(AND(F$82<=$C$86,$C92=1,MOD(MONTH(F$82)-MONTH($C$84),$C$91)=0),1,IF(AND(MOD(MONTH(F$82)-MONTH($C$84),$C$91)=0,F$82>=$C$86),1,0))) -> 1 | G92: =IF(OR(G$82<=$C$84,G$82>$C$85),0,IF(AND(G$82<=$C$86,$C92=1,MOD(MONTH(G$82)-MONTH($C$84),$C$91)=0),1,IF(AND(MOD(MONTH(G$82)-MONTH($C$84),$C$91)=0,G$82>=$C$86),1,0))) -> 1 | H92: =IF(OR(H$82<=$C$84,H$82>$C$85),0,IF(AND(H$82<=$C$86,$C92=1,MOD(MONTH(H$82)-MONTH($C$84),$C$91)=0),1,IF(AND(MOD(MONTH(H$82)-MONTH($C$84),$C$91)=0,H$82>=$C$86),1,0))) -> 1 | I92: =IF(OR(I$82<=$C$84,I$82>$C$85),0,IF(AND(I$82<=$C$86,$C92=1,MOD(MONTH(I$82)-MONTH($C$84),$C$91)=0),1,IF(AND(MOD(MONTH(I$82)-MONTH($C$84),$C$91)=0,I$82>=$C$86),1,0))) -> 1 | J92: =IF(OR(J$82<=$C$84,J$82>$C$85),0,IF(AND(J$82<=$C$86,$C92=1,MOD(MONTH(J$82)-MONTH($C$84),$C$91)=0),1,IF(AND(MOD(MONTH(J$82)-MONTH($C$84),$C$91)=0,J$82>=$C$86),1,0))) -> 1 | K92: =IF(OR(K$82<=$C$84,K$82>$C$85),0,IF(AND(K$82<=$C$86,$C92=1,MOD(MONTH(K$82)-MONTH($C$84),$C$91)=0),1,IF(AND(MOD(MONTH(K$82)-MONTH($C$84),$C$91)=0,K$82>=$C$86),1,0))) -> 1 | L92: =IF(OR(L$82<=$C$84,L$82>$C$85),0,IF(AND(L$82<=$C$86,$C92=1,MOD(MONTH(L$82)-MONTH($C$84),$C$91)=0),1,IF(AND(MOD(MONTH(L$82)-MONTH($C$84),$C$91)=0,L$82>=$C$86),1,0))) -> 0 | ... AC92: =IF(OR(AC$82<=$C$84,AC$82>$C$85),0,IF(AND(AC$82<=$C$86,$C92=1,MOD(MONTH(AC$82)-MONTH($C$84),$C$91)=0),1,IF(AND(MOD(MONTH(AC$82)-MONTH($C$84),$C$91)=0,AC$82>=$C$86),1,0))) -> 0
B93: Capitaliza juros no inicio da amort? (0=N;1=S) | C93: 0 | D93: Prestações pagas | E93: =IF(E87<>"",1,0) -> 0 | F93: =IF(F87<>"",1,0) -> 0 | G93: =IF(G87<>"",1,0) -> 0 | H93: =IF(H87<>"",1,0) -> 0 | I93: =IF(I87<>"",1,0) -> 1 | J93: =IF(J87<>"",1,0) -> 1 | K93: =IF(K87<>"",1,0) -> 1 | L93: =IF(L87<>"",1,0) -> 0 | ... AC93: =IF(AC87<>"",1,0) -> 0
B94: Prestações remanescentes | C94: 2 | E94: =MAX(C94-E93,0) -> 2 | F94: =MAX(D94-F93,0) -> 0 | G94: =MAX(E94-G93,0) -> 2 | H94: =MAX(F94-H93,0) -> 0 | I94: =MAX(G94-I93,0) -> 1 | J94: =MAX(H94-J93,0) -> 0 | K94: =MAX(I94-K93,0) -> 0 | L94: =MAX(J94-L93,0) -> 0 | ... AC94: =MAX(AA94-AC93,0) -> 0
B96: Saldo inicial | E96: =D102 -> 0 | F96: =E102 -> 139419.5 | G96: =F102 -> 120560 | H96: =G102 -> 120560 | I96: =H102 -> 120560 | J96: =I102 -> 80377.352 | K96: =J102 -> 40194.704 | L96: =K102 -> 0 | ... AC96: =AB102 -> 0
B97: Novo funding | C97: 120560 | E97: =(IF(E82<$C$84,0,IF(E82=$C$84,$C$97,0))) -> 120560 | F97: =(IF(F82<$C$84,0,IF(F82=$C$84,$C$97,0))) -> 0 | G97: =(IF(G82<$C$84,0,IF(G82=$C$84,$C$97,0))) -> 0 | H97: =(IF(H82<$C$84,0,IF(H82=$C$84,$C$97,0))) -> 0 | I97: =(IF(I82<$C$84,0,IF(I82=$C$84,$C$97,0))) -> 0 | J97: =(IF(J82<$C$84,0,IF(J82=$C$84,$C$97,0))) -> 0 | K97: =(IF(K82<$C$84,0,IF(K82=$C$84,$C$97,0))) -> 0 | L97: =(IF(L82<$C$84,0,IF(L82=$C$84,$C$97,0))) -> 0 | ... AC97: =(IF(AC82<$C$84,0,IF(AC82=$C$84,$C$97,0))) -> 0
B98: Correção Monetária IPCA | E98: =SUM(E96:E97,-D103)*(E106-1) -> 0 | F98: =SUM(F96:F97,-E103)*(F106-1) -> 0 | G98: =SUM(G96:G97,-F103)*(G106-1) -> 0 | H98: =SUM(H96:H97,-G103)*(H106-1) -> 0 | I98: =SUM(I96:I97,-H103)*(I106-1) -> 0 | J98: =SUM(J96:J97,-I103)*(J106-1) -> 0 | K98: =SUM(K96:K97,-J103)*(K106-1) -> 0 | L98: =SUM(L96:L97,-K103)*(L106-1) -> 0 | ... AC98: =SUM(AC96:AC97,-AB103)*(AC106-1) -> 0
B99: Juros apropriados (DRE) | E99: =SUM(E96:E98)*E90 -> 18859.502 | F99: =SUM(F96:F98)*F90 -> 17148.969 | G99: =SUM(G96:G98)*G90 -> 15534.542 | H99: =SUM(H96:H98)*H90 -> 12395.638 | I99: =SUM(I96:I98)*I90 -> 12245.38 | J99: =SUM(J96:J98)*J90 -> 9696.4147 | K99: =SUM(K96:K98)*K90 -> 3663.7637 | L99: =SUM(L96:L98)*L90 -> 0 | ... AC99: =SUM(AC96:AC98)*AC90 -> 0
B100: Juros pagos (Caixa) | E100: =IF(E92=1,-D103-E99,0)*IF(AND(E$82=$C$87,$C93=1,$C92=0),0,1) -> 0 | F100: =IF(F92=1,-E103-F99,0)*IF(AND(F$82=$C$87,$C93=1,$C92=0),0,1) -> -36008.471 | G100: =IF(G92=1,-F103-G99,0)*IF(AND(G$82=$C$87,$C93=1,$C92=0),0,1) -> -15534.542 | H100: =IF(H92=1,-G103-H99,0)*IF(AND(H$82=$C$87,$C93=1,$C92=0),0,1) -> -12395.638 | I100: =IF(I92=1,-H103-I99,0)*IF(AND(I$82=$C$87,$C93=1,$C92=0),0,1) -> -12245.38 | J100: =IF(J92=1,-I103-J99,0)*IF(AND(J$82=$C$87,$C93=1,$C92=0),0,1) -> -9696.4147 | K100: =IF(K92=1,-J103-K99,0)*IF(AND(K$82=$C$87,$C93=1,$C92=0),0,1) -> -3663.7637 | L100: =IF(L92=1,-K103-L99,0)*IF(AND(L$82=$C$87,$C93=1,$C92=0),0,1) -> 0 | ... AC100: =IF(AC92=1,-AB103-AC99,0)*IF(AND(AC$82=$C$87,$C93=1,$C92=0),0,1) -> 0
B101: Amortização principal (Caixa) | E101: =-E87*LOOKUP($C$84,$E$82:$GQ$82,$E$97:$GQ$97) -> 0 | F101: =-F87*LOOKUP($C$84,$E$82:$GQ$82,$E$97:$GQ$97) -> 0 | G101: =-G87*LOOKUP($C$84,$E$82:$GQ$82,$E$97:$GQ$97) -> 0 | H101: =-H87*LOOKUP($C$84,$E$82:$GQ$82,$E$97:$GQ$97) -> 0 | I101: =-I87*LOOKUP($C$84,$E$82:$GQ$82,$E$97:$GQ$97) -> -40182.648 | J101: =-J87*LOOKUP($C$84,$E$82:$GQ$82,$E$97:$GQ$97) -> -40182.648 | K101: =-K87*LOOKUP($C$84,$E$82:$GQ$82,$E$97:$GQ$97) -> -40194.704 | L101: =-L87*LOOKUP($C$84,$E$82:$GQ$82,$E$97:$GQ$97) -> 0 | ... AC101: =-AC87*LOOKUP($C$84,$E$82:$GQ$82,$E$97:$GQ$97) -> 0
B102: Saldo final (Balanço) | E102: =IF(SUM(E96:E101)<0.00000001,ROUND(SUM(E96:E101),7),SUM(E96:E101)) -> 139419.5 | F102: =IF(SUM(F96:F101)<0.00000001,ROUND(SUM(F96:F101),7),SUM(F96:F101)) -> 120560 | G102: =IF(SUM(G96:G101)<0.00000001,ROUND(SUM(G96:G101),7),SUM(G96:G101)) -> 120560 | H102: =IF(SUM(H96:H101)<0.00000001,ROUND(SUM(H96:H101),7),SUM(H96:H101)) -> 120560 | I102: =IF(SUM(I96:I101)<0.00000001,ROUND(SUM(I96:I101),7),SUM(I96:I101)) -> 80377.352 | J102: =IF(SUM(J96:J101)<0.00000001,ROUND(SUM(J96:J101),7),SUM(J96:J101)) -> 40194.704 | K102: =IF(SUM(K96:K101)<0.00000001,ROUND(SUM(K96:K101),7),SUM(K96:K101)) -> 0 | L102: =IF(SUM(L96:L101)<0.00000001,ROUND(SUM(L96:L101),7),SUM(L96:L101)) -> 0 | ... AC102: =IF(SUM(AC96:AC101)<0.00000001,ROUND(SUM(AC96:AC101),7),SUM(AC96:AC101)) -> 0
B103: Juros acumulados | E103: =(E99+D103+E100)*IF(AND(E$82=$C$87,$C93),0,1) -> 18859.502 | F103: =(F99+E103+F100)*IF(AND(F$82=$C$87,$C93),0,1) -> 0 | G103: =(G99+F103+G100)*IF(AND(G$82=$C$87,$C93),0,1) -> 0 | H103: =(H99+G103+H100)*IF(AND(H$82=$C$87,$C93),0,1) -> 0 | I103: =(I99+H103+I100)*IF(AND(I$82=$C$87,$C93),0,1) -> 0 | J103: =(J99+I103+J100)*IF(AND(J$82=$C$87,$C93),0,1) -> 0 | K103: =(K99+J103+K100)*IF(AND(K$82=$C$87,$C93),0,1) -> 0 | L103: =(L99+K103+L100)*IF(AND(L$82=$C$87,$C93),0,1) -> 0 | ... AC103: =(AC99+AB103+AC100)*IF(AND(AC$82=$C$87,$C93),0,1) -> 0
B105: Serviço da divida | E105: =E101+E100 -> 0 | F105: =F101+F100 -> -36008.471 | G105: =G101+G100 -> -15534.542 | H105: =H101+H100 -> -12395.638 | I105: =I101+I100 -> -52428.028 | J105: =J101+J100 -> -49879.063 | K105: =K101+K100 -> -43858.468 | L105: =L101+L100 -> 0 | ... AC105: =AC101+AC100 -> 0
B106: Correção Monetária no período | C106: 1 | E106: =IF(E$82>=$C84,1+E89,1) -> 1 | F106: =IF(F$82>=$C84,1+F89,1) -> 1 | G106: =IF(G$82>=$C84,1+G89,1) -> 1 | H106: =IF(H$82>=$C84,1+H89,1) -> 1 | I106: =IF(I$82>=$C84,1+I89,1) -> 1 | J106: =IF(J$82>=$C84,1+J89,1) -> 1 | K106: =IF(K$82>=$C84,1+K89,1) -> 1 | L106: =IF(L$82>=$C84,1+L89,1) -> 1 | ... AC106: =IF(AC$82>=$C84,1+AC89,1) -> 1
B107: Correção Monetária Acumulada | C107: 1 | E107: =C107*E106 -> 1 | F107: =D107*F106 -> 0 | G107: =E107*G106 -> 1 | H107: =F107*H106 -> 0 | I107: =G107*I106 -> 1 | J107: =H107*J106 -> 0 | K107: =I107*K106 -> 1 | L107: =J107*L106 -> 0 | ... AC107: =AA107*AC106 -> 1
B108: Correção Monetária Acumulada Juros a Capitalizar | C108: 1 | E108: =IF(E$82>$C87,(1+E89)*C108,1) -> 1 | F108: =IF(F$82>$C87,(1+F89)*D108,1) -> 1 | G108: =IF(G$82>$C87,(1+G89)*E108,1) -> 1 | H108: =IF(H$82>$C87,(1+H89)*F108,1) -> 1 | I108: =IF(I$82>$C87,(1+I89)*G108,1) -> 1 | J108: =IF(J$82>$C87,(1+J89)*H108,1) -> 1 | K108: =IF(K$82>$C87,(1+K89)*I108,1) -> 1 | L108: =IF(L$82>$C87,(1+L89)*J108,1) -> 1 | ... AC108: =IF(AC$82>$C87,(1+AC89)*AA108,1) -> 1
B109: Saldo Devedor Base (capitalização de juros) | E109: =SUM(E96:E100) -> 139419.5 | F109: =SUM(F96:F100) -> 120560 | G109: =SUM(G96:G100) -> 120560 | H109: =SUM(H96:H100) -> 120560 | I109: =SUM(I96:I100) -> 120560 | J109: =SUM(J96:J100) -> 80377.352 | K109: =SUM(K96:K100) -> 40194.704 | L109: =SUM(L96:L100) -> 0 | ... AC109: =SUM(AC96:AC100) -> 0
B112: 2º Emissão - 1º Série | E112: =C114 -> 41061 | F112: =EDATE(E112,1) -> 41091 | G112: =EDATE(F112,1) -> 41122 | H112: =EDATE(G112,1) -> 41153 | I112: =EDATE(H112,1) -> 41183 | J112: =EDATE(I112,1) -> 41214 | K112: =EDATE(J112,1) -> 41244 | L112: =EDATE(K112,1) -> 41275 | M112: =EDATE(L112,1) -> 41306 | ... GQ112: =EDATE(GP112,1) -> 46966
E113: =YEAR(E112) -> 2012 | F113: =YEAR(F112) -> 2012 | G113: =YEAR(G112) -> 2012 | H113: =YEAR(H112) -> 2012 | I113: =YEAR(I112) -> 2012 | J113: =YEAR(J112) -> 2012 | K113: =YEAR(K112) -> 2012 | L113: =YEAR(L112) -> 2013 | ... GQ113: =YEAR(GQ112) -> 2028
B114: Dt desembolso | C114: 41061
B115: Prazo Total | C115: =DATE(YEAR(C114)+C118,MONTH(C114),DAY(C114)) -> 42887
B116: Final Carência | C116: 41244
B117: Início Amortização principal | C117: 42522 | D117: Amort => | BA117: 0.5 | BM117: 0.5
...

Sheet DIVIDA AGConcessoes
F1: LEGENDA:
B2: MODELO DE DÍVIDA | F2: Dados Realizados Inputados | I2: VICTOR LOPES SCHMUTZLER
F3: Dados Realizados Calculados | I3: +55 (11) 3553-2529
F4: Dados Projetados Inputados
B5: 1. RESUMO FINANCIAMENTOS | F5: Dados Projetados Calculados
B7: CONSOLIDADO ANUAL | D7: 2009 | E7: 2010 | F7: 2011 | G7: =F7+1 -> 2012 | H7: =G7+1 -> 2013 | I7: =H7+1 -> 2014 | J7: =I7+1 -> 2015 | K7: =J7+1 -> 2016 | L7: =K7+1 -> 2017 | M7: =L7+1 -> 2018 | N7: =M7+1 -> 2019 | ... Y7: =X7+1 -> 2030
B9: Debentures
B10: Saldo inicial (Balanço)
B11: Novo funding (Caixa)
B12: Juros apropriados (DRE)
B13: Juros pagos (Caixa)
B14: Amortização principal (Caixa)
B15: Saldo final (Balanço)
B16: Saldo Curto Prazo (Balanço)
B17: Saldo Longo Prazo (Balanço)
B19: Empréstimos e financiamentos
A20: 15 | B20: Saldo inicial (Balanço) | F20: 0 | G20: =F26 -> 335.214 | H20: =G26 -> 292764.24 | I20: =H26 -> 101010.09 | J20: =I26 -> 47500 | K20: =J26 -> 0 | L20: =K26 -> 0 | M20: =L26 -> 0 | N20: =M26 -> 0 | ... Y20: =X26 -> 0
A21: 16 | B21: Novo funding (Caixa) | G21: =SUMIF($E$112:$GQ$112,G$7,$E126:$GQ126)+SUMIF($E$52:$GQ$52,G$7,$E66:$GQ66)+SUMIF($E$82:$GQ$82,G$7,$E96:$GQ96) -> 0 | H21: =SUMIF($E$112:$GQ$112,H$7,$E126:$GQ126)+SUMIF($E$52:$GQ$52,H$7,$E66:$GQ66)+SUMIF($E$82:$GQ$82,H$7,$E96:$GQ96) -> 0 | I21: =SUMIF($E$112:$GQ$112,I$7,$E126:$GQ126)+SUMIF($E$52:$GQ$52,I$7,$E66:$GQ66)+SUMIF($E$82:$GQ$82,I$7,$E96:$GQ96) -> 0 | J21: =SUMIF($E$112:$GQ$112,J$7,$E126:$GQ126)+SUMIF($E$52:$GQ$52,J$7,$E66:$GQ66)+SUMIF($E$82:$GQ$82,J$7,$E96:$GQ96) -> 0 | K21: =SUMIF($E$112:$GQ$112,K$7,$E126:$GQ126)+SUMIF($E$52:$GQ$52,K$7,$E66:$GQ66)+SUMIF($E$82:$GQ$82,K$7,$E96:$GQ96) -> 0 | L21: =SUMIF($E$112:$GQ$112,L$7,$E126:$GQ126)+SUMIF($E$52:$GQ$52,L$7,$E66:$GQ66)+SUMIF($E$82:$GQ$82,L$7,$E96:$GQ96) -> 0 | M21: =SUMIF($E$112:$GQ$112,M$7,$E126:$GQ126)+SUMIF($E$52:$GQ$52,M$7,$E66:$GQ66)+SUMIF($E$82:$GQ$82,M$7,$E96:$GQ96) -> 0 | N21: =SUMIF($E$112:$GQ$112,N$7,$E126:$GQ126)+SUMIF($E$52:$GQ$52,N$7,$E66:$GQ66)+SUMIF($E$82:$GQ$82,N$7,$E96:$GQ96) -> 0 | ... Y21: =SUMIF($E$112:$GQ$112,Y$7,$E126:$GQ126)+SUMIF($E$52:$GQ$52,Y$7,$E66:$GQ66)+SUMIF($E$82:$GQ$82,Y$7,$E96:$GQ96) -> 0
A22: 17 | B22: Correção Monetária IPCA | G22: =SUMIF($E$112:$GQ$112,G$7,$E127:$GQ127)+SUMIF($E$52:$GQ$52,G$7,$E67:$GQ67)+SUMIF($E$82:$GQ$82,G$7,$E97:$GQ97) -> 0 | H22: =SUMIF($E$112:$GQ$112,H$7,$E127:$GQ127)+SUMIF($E$52:$GQ$52,H$7,$E67:$GQ67)+SUMIF($E$82:$GQ$82,H$7,$E97:$GQ97) -> 0 | I22: =SUMIF($E$112:$GQ$112,I$7,$E127:$GQ127)+SUMIF($E$52:$GQ$52,I$7,$E67:$GQ67)+SUMIF($E$82:$GQ$82,I$7,$E97:$GQ97) -> 0 | J22: =SUMIF($E$112:$GQ$112,J$7,$E127:$GQ127)+SUMIF($E$52:$GQ$52,J$7,$E67:$GQ67)+SUMIF($E$82:$GQ$82,J$7,$E97:$GQ97) -> 0 | K22: =SUMIF($E$112:$GQ$112,K$7,$E127:$GQ127)+SUMIF($E$52:$GQ$52,K$7,$E67:$GQ67)+SUMIF($E$82:$GQ$82,K$7,$E97:$GQ97) -> 0 | L22: =SUMIF($E$112:$GQ$112,L$7,$E127:$GQ127)+SUMIF($E$52:$GQ$52,L$7,$E67:$GQ67)+SUMIF($E$82:$GQ$82,L$7,$E97:$GQ97) -> 0 | M22: =SUMIF($E$112:$GQ$112,M$7,$E127:$GQ127)+SUMIF($E$52:$GQ$52,M$7,$E67:$GQ67)+SUMIF($E$82:$GQ$82,M$7,$E97:$GQ97) -> 0 | N22: =SUMIF($E$112:$GQ$112,N$7,$E127:$GQ127)+SUMIF($E$52:$GQ$52,N$7,$E67:$GQ67)+SUMIF($E$82:$GQ$82,N$7,$E97:$GQ97) -> 0 | ... Y22: =SUMIF($E$112:$GQ$112,Y$7,$E127:$GQ127)+SUMIF($E$52:$GQ$52,Y$7,$E67:$GQ67)+SUMIF($E$82:$GQ$82,Y$7,$E97:$GQ97) -> 0
A23: 18 | B23: Juros apropriados (DRE) | G23: =SUMIF($E$112:$GQ$112,G$7,$E128:$GQ128)+SUMIF($E$52:$GQ$52,G$7,$E68:$GQ68)+SUMIF($E$82:$GQ$82,G$7,$E98:$GQ98) -> 32194.982 | H23: =SUMIF($E$112:$GQ$112,H$7,$E128:$GQ128)+SUMIF($E$52:$GQ$52,H$7,$E68:$GQ68)+SUMIF($E$82:$GQ$82,H$7,$E98:$GQ98) -> 17955.927 | I23: =SUMIF($E$112:$GQ$112,I$7,$E128:$GQ128)+SUMIF($E$52:$GQ$52,I$7,$E68:$GQ68)+SUMIF($E$82:$GQ$82,I$7,$E98:$GQ98) -> 10322.943 | J23: =SUMIF($E$112:$GQ$112,J$7,$E128:$GQ128)+SUMIF($E$52:$GQ$52,J$7,$E68:$GQ68)+SUMIF($E$82:$GQ$82,J$7,$E98:$GQ98) -> 4913.4651 | K23: =SUMIF($E$112:$GQ$112,K$7,$E128:$GQ128)+SUMIF($E$52:$GQ$52,K$7,$E68:$GQ68)+SUMIF($E$82:$GQ$82,K$7,$E98:$GQ98) -> 0 | L23: =SUMIF($E$112:$GQ$112,L$7,$E128:$GQ128)+SUMIF($E$52:$GQ$52,L$7,$E68:$GQ68)+SUMIF($E$82:$GQ$82,L$7,$E98:$GQ98) -> 0 | M23: =SUMIF($E$112:$GQ$112,M$7,$E128:$GQ128)+SUMIF($E$52:$GQ$52,M$7,$E68:$GQ68)+SUMIF($E$82:$GQ$82,M$7,$E98:$GQ98) -> 0 | N23: =SUMIF($E$112:$GQ$112,N$7,$E128:$GQ128)+SUMIF($E$52:$GQ$52,N$7,$E68:$GQ68)+SUMIF($E$82:$GQ$82,N$7,$E98:$GQ98) -> 0 | ... Y23: =SUMIF($E$112:$GQ$112,Y$7,$E128:$GQ128)+SUMIF($E$52:$GQ$52,Y$7,$E68:$GQ68)+SUMIF($E$82:$GQ$82,Y$7,$E98:$GQ98) -> 0
A24: 19 | B24: Juros pagos (Caixa) | G24: =SUMIF($E$112:$GQ$112,G$7,$E129:$GQ129)+SUMIF($E$52:$GQ$52,G$7,$E69:$GQ69)+SUMIF($E$82:$GQ$82,G$7,$E99:$GQ99) -> -21235.407 | H24: =SUMIF($E$112:$GQ$112,H$7,$E129:$GQ129)+SUMIF($E$52:$GQ$52,H$7,$E69:$GQ69)+SUMIF($E$82:$GQ$82,H$7,$E99:$GQ99) -> -30425.744 | I24: =SUMIF($E$112:$GQ$112,I$7,$E129:$GQ129)+SUMIF($E$52:$GQ$52,I$7,$E69:$GQ69)+SUMIF($E$82:$GQ$82,I$7,$E99:$GQ99) -> -10423.702 | J24: =SUMIF($E$112:$GQ$112,J$7,$E129:$GQ129)+SUMIF($E$52:$GQ$52,J$7,$E69:$GQ69)+SUMIF($E$82:$GQ$82,J$7,$E99:$GQ99) -> -4913.4651 | K24: =SUMIF($E$112:$GQ$112,K$7,$E129:$GQ129)+SUMIF($E$52:$GQ$52,K$7,$E69:$GQ69)+SUMIF($E$82:$GQ$82,K$7,$E99:$GQ99) -> 0 | L24: =SUMIF($E$112:$GQ$112,L$7,$E129:$GQ129)+SUMIF($E$52:$GQ$52,L$7,$E69:$GQ69)+SUMIF($E$82:$GQ$82,L$7,$E99:$GQ99) -> 0 | M24: =SUMIF($E$112:$GQ$112,M$7,$E129:$GQ129)+SUMIF($E$52:$GQ$52,M$7,$E69:$GQ69)+SUMIF($E$82:$GQ$82,M$7,$E99:$GQ99) -> 0 | N24: =SUMIF($E$112:$GQ$112,N$7,$E129:$GQ129)+SUMIF($E$52:$GQ$52,N$7,$E69:$GQ69)+SUMIF($E$82:$GQ$82,N$7,$E99:$GQ99) -> 0 | ... Y24: =SUMIF($E$112:$GQ$112,Y$7,$E129:$GQ129)+SUMIF($E$52:$GQ$52,Y$7,$E69:$GQ69)+SUMIF($E$82:$GQ$82,Y$7,$E99:$GQ99) -> 0
A25: 20 | B25: Amortização principal (Caixa) | G25: =SUMIF($E$112:$GQ$112,G$7,$E130:$GQ130)+SUMIF($E$52:$GQ$52,G$7,$E70:$GQ70)+SUMIF($E$82:$GQ$82,G$7,$E100:$GQ100) -> -53409.333 | H25: =SUMIF($E$112:$GQ$112,H$7,$E130:$GQ130)+SUMIF($E$52:$GQ$52,H$7,$E70:$GQ70)+SUMIF($E$82:$GQ$82,H$7,$E100:$GQ100) -> -179284.33 | I25: =SUMIF($E$112:$GQ$112,I$7,$E130:$GQ130)+SUMIF($E$52:$GQ$52,I$7,$E70:$GQ70)+SUMIF($E$82:$GQ$82,I$7,$E100:$GQ100) -> -53409.333 | J25: =SUMIF($E$112:$GQ$112,J$7,$E130:$GQ130)+SUMIF($E$52:$GQ$52,J$7,$E70:$GQ70)+SUMIF($E$82:$GQ$82,J$7,$E100:$GQ100) -> -47500 | K25: =SUMIF($E$112:$GQ$112,K$7,$E130:$GQ130)+SUMIF($E$52:$GQ$52,K$7,$E70:$GQ70)+SUMIF($E$82:$GQ$82,K$7,$E100:$GQ100) -> 0 | L25: =SUMIF($E$112:$GQ$112,L$7,$E130:$GQ130)+SUMIF($E$52:$GQ$52,L$7,$E70:$GQ70)+SUMIF($E$82:$GQ$82,L$7,$E100:$GQ100) -> 0 | M25: =SUMIF($E$112:$GQ$112,M$7,$E130:$GQ130)+SUMIF($E$52:$GQ$52,M$7,$E70:$GQ70)+SUMIF($E$82:$GQ$82,M$7,$E100:$GQ100) -> 0 | N25: =SUMIF($E$112:$GQ$112,N$7,$E130:$GQ130)+SUMIF($E$52:$GQ$52,N$7,$E70:$GQ70)+SUMIF($E$82:$GQ$82,N$7,$E100:$GQ100) -> 0 | ... Y25: =SUMIF($E$112:$GQ$112,Y$7,$E130:$GQ130)+SUMIF($E$52:$GQ$52,Y$7,$E70:$GQ70)+SUMIF($E$82:$GQ$82,Y$7,$E100:$GQ100) -> 0
A26: 21 | B26: Saldo final (Balanço) | F26: =PROJ_AGCeAGPar!J238 -> 335.214 | G26: =IFERROR(HLOOKUP(DATE(G7,12,1),$E$81:$GQ$101,$A26,0),0)+IFERROR(HLOOKUP(DATE(G7,12,1),$E$111:$GQ$131,$A26,0),0)+IFERROR(HLOOKUP(DATE(G7,12,1),$E$51:$GQ$71,$A26,0),0) -> 292764.24 | H26: =IFERROR(HLOOKUP(DATE(H7,12,1),$E$81:$GQ$101,$A26,0),0)+IFERROR(HLOOKUP(DATE(H7,12,1),$E$111:$GQ$131,$A26,0),0)+IFERROR(HLOOKUP(DATE(H7,12,1),$E$51:$GQ$71,$A26,0),0) -> 101010.09 | I26: =IFERROR(HLOOKUP(DATE(I7,12,1),$E$81:$GQ$101,$A26,0),0)+IFERROR(HLOOKUP(DATE(I7,12,1),$E$111:$GQ$131,$A26,0),0)+IFERROR(HLOOKUP(DATE(I7,12,1),$E$51:$GQ$71,$A26,0),0) -> 47500 | J26: =IFERROR(HLOOKUP(DATE(J7,12,1),$E$81:$GQ$101,$A26,0),0)+IFERROR(HLOOKUP(DATE(J7,12,1),$E$111:$GQ$131,$A26,0),0)+IFERROR(HLOOKUP(DATE(J7,12,1),$E$51:$GQ$71,$A26,0),0) -> 0 | K26: =IFERROR(HLOOKUP(DATE(K7,12,1),$E$81:$GQ$101,$A26,0),0)+IFERROR(HLOOKUP(DATE(K7,12,1),$E$111:$GQ$131,$A26,0),0)+IFERROR(HLOOKUP(DATE(K7,12,1),$E$51:$GQ$71,$A26,0),0) -> 0 | L26: =IFERROR(HLOOKUP(DATE(L7,12,1),$E$81:$GQ$101,$A26,0),0)+IFERROR(HLOOKUP(DATE(L7,12,1),$E$111:$GQ$131,$A26,0),0)+IFERROR(HLOOKUP(DATE(L7,12,1),$E$51:$GQ$71,$A26,0),0) -> 0 | M26: =IFERROR(HLOOKUP(DATE(M7,12,1),$E$81:$GQ$101,$A26,0),0)+IFERROR(HLOOKUP(DATE(M7,12,1),$E$111:$GQ$131,$A26,0),0)+IFERROR(HLOOKUP(DATE(M7,12,1),$E$51:$GQ$71,$A26,0),0) -> 0 | N26: =IFERROR(HLOOKUP(DATE(N7,12,1),$E$81:$GQ$101,$A26,0),0)+IFERROR(HLOOKUP(DATE(N7,12,1),$E$111:$GQ$131,$A26,0),0)+IFERROR(HLOOKUP(DATE(N7,12,1),$E$51:$GQ$71,$A26,0),0) -> 0 | ... Y26: =IFERROR(HLOOKUP(DATE(Y7,12,1),$E$81:$GQ$101,$A26,0),0)+IFERROR(HLOOKUP(DATE(Y7,12,1),$E$111:$GQ$131,$A26,0),0)+IFERROR(HLOOKUP(DATE(Y7,12,1),$E$51:$GQ$71,$A26,0),0) -> 0
B27: Saldo Curto Prazo (Balanço) | F27: 52464 | G27: =IF(G26>0,-SUM(H25),0) -> 179284.33 | H27: =IF(H26>0,-SUM(I25),0) -> 53409.333 | I27: =IF(I26>0,-SUM(J25),0) -> 47500 | J27: =IF(J26>0,-SUM(K25),0) -> 0 | K27: =IF(K26>0,-SUM(L25:O25),0) -> 0 | L27: =IF(L26>0,-SUM(M25:P25),0) -> 0 | M27: =IF(M26>0,-SUM(N25:Q25),0) -> 0 | N27: =IF(N26>0,-SUM(O25:R25),0) -> 0 | O27: =IF(O26>0,-SUM(P25:S25),0) -> 0 | P27: =IF(P26>0,-SUM(Q25:T25),0) -> 0 | Q27: =IF(Q26>0,-SUM(R25:U25),0) -> 0 | R27: =IF(R26>0,-SUM(S25:V25),0) -> 0 | ... Y27: =IF(Y26>0,-SUM(Z25:AC25),0) -> 0
B28: Saldo Longo Prazo (Balanço) | F28: 282750 | G28: =ROUND(G26-G27+G30,8) -> 113479.91 | H28: =ROUND(H26-H27+H30,8) -> 47600.759 | I28: =ROUND(I26-I27+I30,8) -> 0 | J28: =ROUND(J26-J27+J30,8) -> 0 | K28: =ROUND(K26-K27+K30,8) -> 0 | L28: =ROUND(L26-L27+L30,8) -> 0 | M28: =ROUND(M26-M27+M30,8) -> 0 | N28: =ROUND(N26-N27+N30,8) -> 0 | ... Y28: =ROUND(Y26-Y27+Y30,8) -> 0
B30: Custos das Transações | F30: 0 | G30: =-2%*G21 -> 0 | H30: =G30+H31 -> 0 | I30: =H30+I31 -> 0 | J30: =I30+J31 -> 0 | K30: =J30+K31 -> 0 | L30: =K30+L31 -> 0 | M30: =L30+M31 -> 0 | N30: =M30+N31 -> 0 | O30: =N30+O31 -> 0 | ... X30: =W30+X31 -> 0 | Y30: 0
G31: =-F30/20 -> 0 | H31: =-G30/18 -> 0 | I31: =H31 -> 0 | J31: =I31 -> 0 | K31: =J31 -> 0 | L31: =K31 -> 0 | M31: =L31 -> 0 | N31: =M31 -> 0 | O31: =N31 -> 0 | P31: =O31 -> 0 | ... Y31: =X31 -> 0
B32: Dívida de Balanceamento
B33: Saldo Inicial | G33: =PROJ_AGCeAGPar!I211 -> 0 | H33: =PROJ_AGCeAGPar!J211 -> 0 | I33: =PROJ_AGCeAGPar!K211 -> 0 | J33: =PROJ_AGCeAGPar!L211 -> 0 | K33: =PROJ_AGCeAGPar!M211 -> 0 | L33: =PROJ_AGCeAGPar!N211 -> 0 | M33: =PROJ_AGCeAGPar!O211 -> 0 | N33: =PROJ_AGCeAGPar!P211 -> 0 | ... Y33: =PROJ_AGCeAGPar!AA211 -> 0
B34: Adição | G34: =MAX(0,G38-G33) -> 0 | H34: =MAX(0,H38-H33) -> 0 | I34: =MAX(0,I38-I33) -> 0 | J34: =MAX(0,J38-J33) -> 0 | K34: =MAX(0,K38-K33) -> 0 | L34: =MAX(0,L38-L33) -> 0 | M34: =MAX(0,M38-M33) -> 0 | N34: =MAX(0,N38-N33) -> 0 | ... Y34: =MAX(0,Y38-Y33) -> 0
B35: Amortização | G35: =MIN(0,G38-G33) -> 0 | H35: =MIN(0,H38-H33) -> 0 | I35: =MIN(0,I38-I33) -> 0 | J35: =MIN(0,J38-J33) -> 0 | K35: =MIN(0,K38-K33) -> 0 | L35: =MIN(0,L38-L33) -> 0 | M35: =MIN(0,M38-M33) -> 0 | N35: =MIN(0,N38-N33) -> 0 | ... Y35: =MIN(0,Y38-Y33) -> 0
B36: Juros no Período | C36: % CDI | G36: =-G37*(G33) -> 0 | H36: =-H37*(H33) -> 0 | I36: =-I37*(I33) -> 0 | J36: =-J37*(J33) -> 0 | K36: =-K37*(K33) -> 0 | L36: =-L37*(L33) -> 0 | M36: =-M37*(M33) -> 0 | N36: =-N37*(N33) -> 0 | ... Y36: =-Y37*(Y33) -> 0
B37: Custo médio da Dívida | C37: 1 | G37: =$C$37*HLOOKUP(G$7,Macroeconomics!$B$5:$GB$36,Macroeconomics!$A$24,0) -> 0.087560431 | H37: =$C$37*HLOOKUP(H$7,Macroeconomics!$B$5:$GB$36,Macroeconomics!$A$24,0) -> 0.084449317 | I37: =$C$37*HLOOKUP(I$7,Macroeconomics!$B$5:$GB$36,Macroeconomics!$A$24,0) -> 0.096145243 | J37: =$C$37*HLOOKUP(J$7,Macroeconomics!$B$5:$GB$36,Macroeconomics!$A$24,0) -> 0.094942253 | K37: =$C$37*HLOOKUP(K$7,Macroeconomics!$B$5:$GB$36,Macroeconomics!$A$24,0) -> 0.0967 | L37: =$C$37*HLOOKUP(L$7,Macroeconomics!$B$5:$GB$36,Macroeconomics!$A$24,0) -> 0.0967 | M37: =$C$37*HLOOKUP(M$7,Macroeconomics!$B$5:$GB$36,Macroeconomics!$A$24,0) -> 0.0943 | N37: =$C$37*HLOOKUP(N$7,Macroeconomics!$B$5:$GB$36,Macroeconomics!$A$24,0) -> 0.0942 | ... Y37: =$C$37*HLOOKUP(Y$7,Macroeconomics!$B$5:$GB$36,Macroeconomics!$A$24,0) -> 0.0893
B38: Saldo Final | G38: =PROJ_AGCeAGPar!J211 -> 0 | H38: =PROJ_AGCeAGPar!K211 -> 0 | I38: =PROJ_AGCeAGPar!L211 -> 0 | J38: =PROJ_AGCeAGPar!M211 -> 0 | K38: =PROJ_AGCeAGPar!N211 -> 0 | L38: =PROJ_AGCeAGPar!O211 -> 0 | M38: =PROJ_AGCeAGPar!P211 -> 0 | N38: =PROJ_AGCeAGPar!Q211 -> 0 | ... Y38: =PROJ_AGCeAGPar!AB211 -> 0
B40: Receita Financeira
B41: Caixa+AFI+Mútuos Inicial | D41: =PROJ_AGCeAGPar!G194+PROJ_AGCeAGPar!G195+PROJ_AGCeAGPar!G196+PROJ_AGCeAGPar!G202 -> 62.561 | E41: =PROJ_AGCeAGPar!H194+PROJ_AGCeAGPar!H195+PROJ_AGCeAGPar!H196+PROJ_AGCeAGPar!H202 -> 19.148 | F41: =PROJ_AGCeAGPar!I194+PROJ_AGCeAGPar!I195+PROJ_AGCeAGPar!I196+PROJ_AGCeAGPar!I202 -> 4.631 | G41: =PROJ_AGCeAGPar!J194+PROJ_AGCeAGPar!J195+PROJ_AGCeAGPar!J196+PROJ_AGCeAGPar!J202 -> 16.121 | H41: =PROJ_AGCeAGPar!K194+PROJ_AGCeAGPar!K195+PROJ_AGCeAGPar!K196+PROJ_AGCeAGPar!K202 -> 33.364862 | I41: =PROJ_AGCeAGPar!L194+PROJ_AGCeAGPar!L195+PROJ_AGCeAGPar!L196+PROJ_AGCeAGPar!L202 -> 138.80808 | J41: =PROJ_AGCeAGPar!M194+PROJ_AGCeAGPar!M195+PROJ_AGCeAGPar!M196+PROJ_AGCeAGPar!M202 -> 129.32762 | K41: =PROJ_AGCeAGPar!N194+PROJ_AGCeAGPar!N195+PROJ_AGCeAGPar!N196+PROJ_AGCeAGPar!N202 -> 75.579035 | ... Y41: =PROJ_AGCeAGPar!AB194+PROJ_AGCeAGPar!AB195+PROJ_AGCeAGPar!AB196+PROJ_AGCeAGPar!AB202 -> 0
B42: Caixa+AFI+Mútuos Final | D42: =PROJ_AGCeAGPar!H194+PROJ_AGCeAGPar!H195+PROJ_AGCeAGPar!H196+PROJ_AGCeAGPar!H202 -> 19.148 | E42: =PROJ_AGCeAGPar!I194+PROJ_AGCeAGPar!I195+PROJ_AGCeAGPar!I196+PROJ_AGCeAGPar!I202 -> 4.631 | F42: =PROJ_AGCeAGPar!J194+PROJ_AGCeAGPar!J195+PROJ_AGCeAGPar!J196+PROJ_AGCeAGPar!J202 -> 16.121 | G42: =PROJ_AGCeAGPar!K194+PROJ_AGCeAGPar!K195+PROJ_AGCeAGPar!K196+PROJ_AGCeAGPar!K202 -> 33.364862 | H42: =PROJ_AGCeAGPar!L194+PROJ_AGCeAGPar!L195+PROJ_AGCeAGPar!L196+PROJ_AGCeAGPar!L202 -> 138.80808 | I42: =PROJ_AGCeAGPar!M194+PROJ_AGCeAGPar!M195+PROJ_AGCeAGPar!M196+PROJ_AGCeAGPar!M202 -> 129.32762 | J42: =PROJ_AGCeAGPar!N194+PROJ_AGCeAGPar!N195+PROJ_AGCeAGPar!N196+PROJ_AGCeAGPar!N202 -> 75.579035 | K42: =PROJ_AGCeAGPar!O194+PROJ_AGCeAGPar!O195+PROJ_AGCeAGPar!O196+PROJ_AGCeAGPar!O202 -> 86.527195 | ... Y42: =PROJ_AGCeAGPar!AC194+PROJ_AGCeAGPar!AC195+PROJ_AGCeAGPar!AC196+PROJ_AGCeAGPar!AC202 -> 0
B43: Saldo Médio | D43: =(D41+D42)/2 -> 40.8545 | E43: =(E41+E42)/2 -> 11.8895 | F43: =(F41+F42)/2 -> 10.376 | G43: =(G41+G42)/2 -> 24.742931 | H43: =(H41+H42)/2 -> 86.086473 | I43: =(I41+I42)/2 -> 134.06785 | J43: =(J41+J42)/2 -> 102.45333 | K43: =(K41+K42)/2 -> 81.053115 | ... Y43: =(Y41+Y42)/2 -> 0
B44: Receita Financeiras (% CDI) | C44: 1 | D44: =PROJ_AGCeAGPar!H167 -> 4.148 | E44: =PROJ_AGCeAGPar!I167 -> 22.864 | F44: =PROJ_AGCeAGPar!J167 -> 4.305 | G44: =HLOOKUP(G$7,Macroeconomics!$B$5:$GB$36,Macroeconomics!$A$24,0)*$C$44*G41 -> 1.4115617 | H44: =HLOOKUP(H$7,Macroeconomics!$B$5:$GB$36,Macroeconomics!$A$24,0)*$C$44*H41 -> 2.8176398 | I44: =HLOOKUP(I$7,Macroeconomics!$B$5:$GB$36,Macroeconomics!$A$24,0)*$C$44*I41 -> 13.345737 | J44: =HLOOKUP(J$7,Macroeconomics!$B$5:$GB$36,Macroeconomics!$A$24,0)*$C$44*J41 -> 12.278656 | K44: =HLOOKUP(K$7,Macroeconomics!$B$5:$GB$36,Macroeconomics!$A$24,0)*$C$44*K41 -> 7.3084927 | L44: =HLOOKUP(L$7,Macroeconomics!$B$5:$GB$36,Macroeconomics!$A$24,0)*$C$44*L41 -> 8.3671797 | M44: =HLOOKUP(M$7,Macroeconomics!$B$5:$GB$36,Macroeconomics!$A$24,0)*$C$44*M41 -> 8.2638798 | N44: =HLOOKUP(N$7,Macroeconomics!$B$5:$GB$36,Macroeconomics!$A$24,0)*$C$44*N41 -> 12.406642 | ... Y44: =HLOOKUP(Y$7,Macroeconomics!$B$5:$GB$36,Macroeconomics!$A$24,0)*$C$44*Y41 -> 0
B45: % Saldo Médio | D45: =D44/D43 -> 0.10153104 | E45: =E44/E43 -> 1.9230413 | F45: =F44/F43 -> 0.41489977 | G45: =G44/G43 -> 0.057049091 | H45: =H44/H43 -> 0.032730343 | I45: =I44/I43 -> 0.099544646 | J45: =J44/J43 -> 0.11984633 | K45: =K44/K43 -> 0.090169177 | ... Y45: =Y44/Y43 -> #DIV/0!
B46: % CDI | D46: =D45/HLOOKUP(D$7,Macroeconomics!$B$5:$GB$36,Macroeconomics!$A$24,0) -> 1.0279782 | E46: =E45/HLOOKUP(E$7,Macroeconomics!$B$5:$GB$36,Macroeconomics!$A$24,0) -> 19.70926 | F46: =F45/HLOOKUP(F$7,Macroeconomics!$B$5:$GB$36,Macroeconomics!$A$24,0) -> 3.5802754 | G46: =G45/HLOOKUP(G$7,Macroeconomics!$B$5:$GB$36,Macroeconomics!$A$24,0) -> 0.65153963 | H46: =H45/HLOOKUP(H$7,Macroeconomics!$B$5:$GB$36,Macroeconomics!$A$24,0) -> 0.3875738 | I46: =I45/HLOOKUP(I$7,Macroeconomics!$B$5:$GB$36,Macroeconomics!$A$24,0) -> 1.035357 | J46: =J45/HLOOKUP(J$7,Macroeconomics!$B$5:$GB$36,Macroeconomics!$A$24,0) -> 1.2623077 | K46: =K45/HLOOKUP(K$7,Macroeconomics!$B$5:$GB$36,Macroeconomics!$A$24,0) -> 0.93246305 | ... Y46: =Y45/HLOOKUP(Y$7,Macroeconomics!$B$5:$GB$36,Macroeconomics!$A$24,0) -> #DIV/0!
B49: 2. EMPRESTIMOS E FINANCIAMENTOS
B51: Banco do Brasil - Res. 2.770 | E51: =C53 -> 40878 | F51: =EDATE(E51,1) -> 40909 | G51: =EDATE(F51,1) -> 40940 | H51: =EDATE(G51,1) -> 40969 | I51: =EDATE(H51,1) -> 41000 | J51: =EDATE(I51,1) -> 41030 | K51: =EDATE(J51,1) -> 41061 | L51: =EDATE(K51,1) -> 41091 | M51: =EDATE(L51,1) -> 41122 | ... GQ51: =EDATE(GP51,1) -> 46784
E52: =YEAR(E51) -> 2011 | F52: =YEAR(F51) -> 2012 | G52: =YEAR(G51) -> 2012 | H52: =YEAR(H51) -> 2012 | I52: =YEAR(I51) -> 2012 | J52: =YEAR(J51) -> 2012 | K52: =YEAR(K51) -> 2012 | L52: =YEAR(L51) -> 2012 | ... GQ52: =YEAR(GQ51) -> 2028
B53: Dt desembolso | C53: 40878
B54: Prazo Total | C54: 41365
B55: Final Carência | C55: 41365
B56: Início Amortização principal | C56: 41365 | D56: Amort => | U56: 1
B57: Prazo Amortização (anos) | C57: 3
B58: Indexador | C58: CDI%
B59: Spread a.a. over Indexador | C59: 1.12 | E59: =VLOOKUP(EOMONTH(E51,0),Macroeconomics!$B$67:$R$380,Macroeconomics!$C$66,0)*$C$59 -> 0.01008 | F59: =VLOOKUP(EOMONTH(F51,0),Macroeconomics!$B$67:$R$380,Macroeconomics!$C$66,0)*$C$59 -> 0.009968 | G59: =VLOOKUP(EOMONTH(G51,0),Macroeconomics!$B$67:$R$380,Macroeconomics!$C$66,0)*$C$59 -> 0.008288 | H59: =VLOOKUP(EOMONTH(H51,0),Macroeconomics!$B$67:$R$380,Macroeconomics!$C$66,0)*$C$59 -> 0.009072 | I59: =VLOOKUP(EOMONTH(I51,0),Macroeconomics!$B$67:$R$380,Macroeconomics!$C$66,0)*$C$59 -> 0.00784 | J59: =VLOOKUP(EOMONTH(J51,0),Macroeconomics!$B$67:$R$380,Macroeconomics!$C$66,0)*$C$59 -> 0.0082827179 | K59: =VLOOKUP(EOMONTH(K51,0),Macroeconomics!$B$67:$R$380,Macroeconomics!$C$66,0)*$C$59 -> 0.0071273416 | L59: =VLOOKUP(EOMONTH(L51,0),Macroeconomics!$B$67:$R$380,Macroeconomics!$C$66,0)*$C$59 -> 0.0077571315 | ... GQ59: =VLOOKUP(EOMONTH(GQ51,0),Macroeconomics!$B$67:$R$380,Macroeconomics!$C$66,0)*$C$59 -> 0.0080118135
B60: Amortização principal (3=trim, 6=sem, 12 =anual) | C60: 12
B61: Paga juros na carencia? (0=N;1=S) | C61: 0 | D61: Juros Pagos | E61: =IF(OR(E51<=$C53,E51>$C54),0,IF(AND(E51<=$C55,$C61=1,MOD(MONTH(E51)-MONTH($C53),6)=0),1,IF(AND(MOD(MONTH(E51)-MONTH($C53),$C60)=0,E51>=$C55),1,0))) -> 0 | F61: =IF(OR(F51<=$C53,F51>$C54),0,IF(AND(F51<=$C55,$C61=1,MOD(MONTH(F51)-MONTH($C53),6)=0),1,IF(AND(MOD(MONTH(F51)-MONTH($C53),$C60)=0,F51>=$C55),1,0))) -> 0 | G61: =IF(OR(G51<=$C53,G51>$C54),0,IF(AND(G51<=$C55,$C61=1,MOD(MONTH(G51)-MONTH($C53),6)=0),1,IF(AND(MOD(MONTH(G51)-MONTH($C53),$C60)=0,G51>=$C55),1,0))) -> 0 | H61: =IF(OR(H51<=$C53,H51>$C54),0,IF(AND(H51<=$C55,$C61=1,MOD(MONTH(H51)-MONTH($C53),6)=0),1,IF(AND(MOD(MONTH(H51)-MONTH($C53),$C60)=0,H51>=$C55),1,0))) -> 0 | I61: =IF(OR(I51<=$C53,I51>$C54),0,IF(AND(I51<=$C55,$C61=1,MOD(MONTH(I51)-MONTH($C53),6)=0),1,IF(AND(MOD(MONTH(I51)-MONTH($C53),$C60)=0,I51>=$C55),1,0))) -> 0 | J61: =IF(OR(J51<=$C53,J51>$C54),0,IF(AND(J51<=$C55,$C61=1,MOD(MONTH(J51)-MONTH($C53),6)=0),1,IF(AND(MOD(MONTH(J51)-MONTH($C53),$C60)=0,J51>=$C55),1,0))) -> 0 | K61: =IF(OR(K51<=$C53,K51>$C54),0,IF(AND(K51<=$C55,$C61=1,MOD(MONTH(K51)-MONTH($C53),6)=0),1,IF(AND(MOD(MONTH(K51)-MONTH($C53),$C60)=0,K51>=$C55),1,0))) -> 0 | L61: =IF(OR(L51<=$C53,L51>$C54),0,IF(AND(L51<=$C55,$C61=1,MOD(MONTH(L51)-MONTH($C53),6)=0),1,IF(AND(MOD(MONTH(L51)-MONTH($C53),$C60)=0,L51>=$C55),1,0))) -> 0 | ... T61: =IF(OR(T51<=$C53,T51>$C54),0,IF(AND(T51<=$C55,$C61=1,MOD(MONTH(T51)-MONTH($C53),6)=0),1,IF(AND(MOD(MONTH(T51)-MONTH($C53),$C60)=0,T51>=$C55),1,0))) -> 0 | U61: 1 | V61: =IF(OR(V51<=$C53,V51>$C54),0,IF(AND(V51<=$C55,$C61=1,MOD(MONTH(V51)-MONTH($C53),6)=0),1,IF(AND(MOD(MONTH(V51)-MONTH($C53),$C60)=0,V51>=$C55),1,0))) -> 0 | W61: =IF(OR(W51<=$C53,W51>$C54),0,IF(AND(W51<=$C55,$C61=1,MOD(MONTH(W51)-MONTH($C53),6)=0),1,IF(AND(MOD(MONTH(W51)-MONTH($C53),$C60)=0,W51>=$C55),1,0))) -> 0 | X61: =IF(OR(X51<=$C53,X51>$C54),0,IF(AND(X51<=$C55,$C61=1,MOD(MONTH(X51)-MONTH($C53),6)=0),1,IF(AND(MOD(MONTH(X51)-MONTH($C53),$C60)=0,X51>=$C55),1,0))) -> 0 | Y61: =IF(OR(Y51<=$C53,Y51>$C54),0,IF(AND(Y51<=$C55,$C61=1,MOD(MONTH(Y51)-MONTH($C53),6)=0),1,IF(AND(MOD(MONTH(Y51)-MONTH($C53),$C60)=0,Y51>=$C55),1,0))) -> 0 | Z61: =IF(OR(Z51<=$C53,Z51>$C54),0,IF(AND(Z51<=$C55,$C61=1,MOD(MONTH(Z51)-MONTH($C53),6)=0),1,IF(AND(MOD(MONTH(Z51)-MONTH($C53),$C60)=0,Z51>=$C55),1,0))) -> 0 | AA61: =IF(OR(AA51<=$C53,AA51>$C54),0,IF(AND(AA51<=$C55,$C61=1,MOD(MONTH(AA51)-MONTH($C53),6)=0),1,IF(AND(MOD(MONTH(AA51)-MONTH($C53),$C60)=0,AA51>=$C55),1,0))) -> 0 | AB61: =IF(OR(AB51<=$C53,AB51>$C54),0,IF(AND(AB51<=$C55,$C61=1,MOD(MONTH(AB51)-MONTH($C53),6)=0),1,IF(AND(MOD(MONTH(AB51)-MONTH($C53),$C60)=0,AB51>=$C55),1,0))) -> 0 | AC61: =IF(OR(AC51<=$C53,AC51>$C54),0,IF(AND(AC51<=$C55,$C61=1,MOD(MONTH(AC51)-MONTH($C53),6)=0),1,IF(AND(MOD(MONTH(AC51)-MONTH($C53),$C60)=0,AC51>=$C55),1,0))) -> 0 | ... GQ61: =IF(OR(GQ51<=$C53,GQ51>$C54),0,IF(AND(GQ51<=$C55,$C61=1,MOD(MONTH(GQ51)-MONTH($C53),6)=0),1,IF(AND(MOD(MONTH(GQ51)-MONTH($C53),$C60)=0,GQ51>=$C55),1,0))) -> 0
B62: Capitaliza juros no inicio da amort? (0=N;1=S) | C62: 0 | D62: Prestações pagas | E62: =IF(E56<>"",1,0) -> 0 | F62: =IF(F56<>"",1,0) -> 0 | G62: =IF(G56<>"",1,0) -> 0 | H62: =IF(H56<>"",1,0) -> 0 | I62: =IF(I56<>"",1,0) -> 0 | J62: =IF(J56<>"",1,0) -> 0 | K62: =IF(K56<>"",1,0) -> 0 | L62: =IF(L56<>"",1,0) -> 0 | ... GQ62: =IF(GQ56<>"",1,0) -> 0
B63: Prestações remanescentes | C63: 1 | E63: =MAX(C63-E62,0) -> 1 | F63: =MAX(E63-F62,0) -> 1 | G63: =MAX(F63-G62,0) -> 1 | H63: =MAX(G63-H62,0) -> 1 | I63: =MAX(H63-I62,0) -> 1 | J63: =MAX(I63-J62,0) -> 1 | K63: =MAX(J63-K62,0) -> 1 | L63: =MAX(K63-L62,0) -> 1 | M63: =MAX(L63-M62,0) -> 1 | ... GQ63: =MAX(GP63-GQ62,0) -> 0
B65: Saldo inicial | E65: =D71 -> 0 | F65: =E71 -> 125875 | G65: =F71 -> 127129.72 | H65: =G71 -> 128183.37 | I65: =H71 -> 129346.25 | J65: =I71 -> 130360.33 | K65: =J71 -> 131440.07 | L65: =K71 -> 132376.88 | ... GQ65: =GP71 -> 0
B66: Novo funding | E66: =E71 -> 125875 | F66: =(IF(F51<$C53,0,IF(F51=$C53,$C66,0))) -> 0 | G66: =(IF(G51<$C53,0,IF(G51=$C53,$C66,0))) -> 0 | H66: =(IF(H51<$C53,0,IF(H51=$C53,$C66,0))) -> 0 | I66: =(IF(I51<$C53,0,IF(I51=$C53,$C66,0))) -> 0 | J66: =(IF(J51<$C53,0,IF(J51=$C53,$C66,0))) -> 0 | K66: =(IF(K51<$C53,0,IF(K51=$C53,$C66,0))) -> 0 | L66: =(IF(L51<$C53,0,IF(L51=$C53,$C66,0))) -> 0 | M66: =(IF(M51<$C53,0,IF(M51=$C53,$C66,0))) -> 0 | ... GQ66: =(IF(GQ51<$C53,0,IF(GQ51=$C53,$C66,0))) -> 0
B67: Correção Monetária IPCA | E67: =SUM(E65:E66,-D72)*(E75-1) -> 0 | F67: =SUM(F65:F66,-E72)*(F75-1) -> 0 | G67: =SUM(G65:G66,-F72)*(G75-1) -> 0 | H67: =SUM(H65:H66,-G72)*(H75-1) -> 0 | I67: =SUM(I65:I66,-H72)*(I75-1) -> 0 | J67: =SUM(J65:J66,-I72)*(J75-1) -> 0 | K67: =SUM(K65:K66,-J72)*(K75-1) -> 0 | L67: =SUM(L65:L66,-K72)*(L75-1) -> 0 | ... GQ67: =SUM(GQ65:GQ66,-GP72)*(GQ75-1) -> 0
B68: Juros apropriados (DRE) | E68: 0 | F68: =SUM(F65:F67)*F59 -> 1254.722 | G68: =SUM(G65:G67)*G59 -> 1053.6511 | H68: =SUM(H65:H67)*H59 -> 1162.8796 | I68: =SUM(I65:I67)*I59 -> 1014.0746 | J68: =SUM(J65:J67)*J59 -> 1079.7378 | K68: =SUM(K65:K67)*K59 -> 936.81825 | L68: =SUM(L65:L67)*L59 -> 1026.8649 | M68: =SUM(M65:M67)*M59 -> 1063.7583 | ... GQ68: =SUM(GQ65:GQ67)*GQ59 -> 0
B69: Juros pagos (Caixa) | E69: =IF(E61=1,-D72-E68,0)*IF(AND(E51=$C56,$C62=1,$C61=0),0,1) -> 0 | F69: =IF(F61=1,-E72-F68,0)*IF(AND(F51=$C56,$C62=1,$C61=0),0,1) -> 0 | G69: =IF(G61=1,-F72-G68,0)*IF(AND(G51=$C56,$C62=1,$C61=0),0,1) -> 0 | H69: =IF(H61=1,-G72-H68,0)*IF(AND(H51=$C56,$C62=1,$C61=0),0,1) -> 0 | I69: =IF(I61=1,-H72-I68,0)*IF(AND(I51=$C56,$C62=1,$C61=0),0,1) -> 0 | J69: =IF(J61=1,-I72-J68,0)*IF(AND(J51=$C56,$C62=1,$C61=0),0,1) -> 0 | K69: =IF(K61=1,-J72-K68,0)*IF(AND(K51=$C56,$C62=1,$C61=0),0,1) -> 0 | L69: =IF(L61=1,-K72-L68,0)*IF(AND(L51=$C56,$C62=1,$C61=0),0,1) -> 0 | ... GQ69: =IF(GQ61=1,-GP72-GQ68,0)*IF(AND(GQ51=$C56,$C62=1,$C61=0),0,1) -> 0
B70: Amortização principal (Caixa) | E70: =-E56*LOOKUP($C53,$E51:$GQ51,$E66:$GQ66) -> 0 | F70: =-F56*LOOKUP($C53,$E51:$GQ51,$E66:$GQ66) -> 0 | G70: =-G56*LOOKUP($C53,$E51:$GQ51,$E66:$GQ66) -> 0 | H70: =-H56*LOOKUP($C53,$E51:$GQ51,$E66:$GQ66) -> 0 | I70: =-I56*LOOKUP($C53,$E51:$GQ51,$E66:$GQ66) -> 0 | J70: =-J56*LOOKUP($C53,$E51:$GQ51,$E66:$GQ66) -> 0 | K70: =-K56*LOOKUP($C53,$E51:$GQ51,$E66:$GQ66) -> 0 | L70: =-L56*LOOKUP($C53,$E51:$GQ51,$E66:$GQ66) -> 0 | ... GQ70: =-GQ56*LOOKUP($C53,$E51:$GQ51,$E66:$GQ66) -> 0
B71: Saldo final (Balanço) | E71: 125875 | F71: =IF(SUM(F65:F70)<0.00000001,ROUND(SUM(F65:F70),7),SUM(F65:F70)) -> 127129.72 | G71: =IF(SUM(G65:G70)<0.00000001,ROUND(SUM(G65:G70),7),SUM(G65:G70)) -> 128183.37 | H71: =IF(SUM(H65:H70)<0.00000001,ROUND(SUM(H65:H70),7),SUM(H65:H70)) -> 129346.25 | I71: =IF(SUM(I65:I70)<0.00000001,ROUND(SUM(I65:I70),7),SUM(I65:I70)) -> 130360.33 | J71: =IF(SUM(J65:J70)<0.00000001,ROUND(SUM(J65:J70),7),SUM(J65:J70)) -> 131440.07 | K71: =IF(SUM(K65:K70)<0.00000001,ROUND(SUM(K65:K70),7),SUM(K65:K70)) -> 132376.88 | L71: =IF(SUM(L65:L70)<0.00000001,ROUND(SUM(L65:L70),7),SUM(L65:L70)) -> 133403.75 | M71: =IF(SUM(M65:M70)<0.00000001,ROUND(SUM(M65:M70),7),SUM(M65:M70)) -> 134467.51 | ... GQ71: =IF(SUM(GQ65:GQ70)<0.00000001,ROUND(SUM(GQ65:GQ70),7),SUM(GQ65:GQ70)) -> 0
B72: Juros acumulados | E72: =(E68+D72+E69)*IF(AND(E51=$C56,$C62),0,1) -> 0 | F72: =(F68+E72+F69)*IF(AND(F51=$C56,$C62),0,1) -> 1254.722 | G72: =(G68+F72+G69)*IF(AND(G51=$C56,$C62),0,1) -> 2308.3731 | H72: =(H68+G72+H69)*IF(AND(H51=$C56,$C62),0,1) -> 3471.2527 | I72: =(I68+H72+I69)*IF(AND(I51=$C56,$C62),0,1) -> 4485.3273 | J72: =(J68+I72+J69)*IF(AND(J51=$C56,$C62),0,1) -> 5565.0651 | K72: =(K68+J72+K69)*IF(AND(K51=$C56,$C62),0,1) -> 6501.8834 | L72: =(L68+K72+L69)*IF(AND(L51=$C56,$C62),0,1) -> 7528.7483 | ... GQ72: =(GQ68+GP72+GQ69)*IF(AND(GQ51=$C56,$C62),0,1) -> 0
B74: Serviço da divida | E74: =E70+E69 -> 0 | F74: =F70+F69 -> 0 | G74: =G70+G69 -> 0 | H74: =H70+H69 -> 0 | I74: =I70+I69 -> 0 | J74: =J70+J69 -> 0 | K74: =K70+K69 -> 0 | L74: =L70+L69 -> 0 | ... GQ74: =GQ70+GQ69 -> 0
B75: Correção Monetária no período | C75: 1 | E75: =IF(E51>=$C53,1+E58,1) -> 1 | F75: =IF(F51>=$C53,1+F58,1) -> 1 | G75: =IF(G51>=$C53,1+G58,1) -> 1 | H75: =IF(H51>=$C53,1+H58,1) -> 1 | I75: =IF(I51>=$C53,1+I58,1) -> 1 | J75: =IF(J51>=$C53,1+J58,1) -> 1 | K75: =IF(K51>=$C53,1+K58,1) -> 1 | L75: =IF(L51>=$C53,1+L58,1) -> 1 | ... GQ75: =IF(GQ51>=$C53,1+GQ58,1) -> 1
B76: Correção Monetária Acumulada | C76: 1 | E76: =C76*E75 -> 1 | F76: =E76*F75 -> 1 | G76: =F76*G75 -> 1 | H76: =G76*H75 -> 1 | I76: =H76*I75 -> 1 | J76: =I76*J75 -> 1 | K76: =J76*K75 -> 1 | L76: =K76*L75 -> 1 | M76: =L76*M75 -> 1 | ... GQ76: =GP76*GQ75 -> 1
B77: Correção Monetária Acumulada Juros a Capitalizar | C77: 1 | E77: =IF(E51>$C56,(1+E58)*C77,1) -> 1 | F77: =IF(F51>$C56,(1+F58)*D77,1) -> 1 | G77: =IF(G51>$C56,(1+G58)*E77,1) -> 1 | H77: =IF(H51>$C56,(1+H58)*F77,1) -> 1 | I77: =IF(I51>$C56,(1+I58)*G77,1) -> 1 | J77: =IF(J51>$C56,(1+J58)*H77,1) -> 1 | K77: =IF(K51>$C56,(1+K58)*I77,1) -> 1 | L77: =IF(L51>$C56,(1+L58)*J77,1) -> 1 | ... GQ77: =IF(GQ51>$C56,(1+GQ58)*GO77,1) -> 1
B78: Saldo Devedor Base (capitalização de juros) | E78: =SUM(E65:E69) -> 125875 | F78: =SUM(F65:F69) -> 127129.72 | G78: =SUM(G65:G69) -> 128183.37 | H78: =SUM(H65:H69) -> 129346.25 | I78: =SUM(I65:I69) -> 130360.33 | J78: =SUM(J65:J69) -> 131440.07 | K78: =SUM(K65:K69) -> 132376.88 | L78: =SUM(L65:L69) -> 133403.75 | ... GQ78: =SUM(GQ65:GQ69) -> 0
B81: Banco do Brasil - NCC | E81: =C83 -> 40878 | F81: =EDATE(E81,1) -> 40909 | G81: =EDATE(F81,1) -> 40940 | H81: =EDATE(G81,1) -> 40969 | I81: =EDATE(H81,1) -> 41000 | J81: =EDATE(I81,1) -> 41030 | K81: =EDATE(J81,1) -> 41061 | L81: =EDATE(K81,1) -> 41091 | M81: =EDATE(L81,1) -> 41122 | ... GQ81: =EDATE(GP81,1) -> 46784
E82: =YEAR(E81) -> 2011 | F82: =YEAR(F81) -> 2012 | G82: =YEAR(G81) -> 2012 | H82: =YEAR(H81) -> 2012 | I82: =YEAR(I81) -> 2012 | J82: =YEAR(J81) -> 2012 | K82: =YEAR(K81) -> 2012 | L82: =YEAR(L81) -> 2012 | ... GQ82: =YEAR(GQ81) -> 2028
B83: Dt desembolso | C83: 40878
B84: Prazo Total | C84: 42339
B85: Final Carência | C85: 41244
B86: Início Amortização principal | C86: 41244 | D86: Amort => | Q86: 0.25 | AC86: 0.25 | AO86: 0.25 | BA86: 0.25
B87: Prazo Amortização (anos) | C87: 5
B88: Indexador | C88: CDI%
B89: Spread a.a. over Indexador | C89: 1.0856 | E89: =VLOOKUP(EOMONTH(E81,0),Macroeconomics!$B$67:$R$380,Macroeconomics!$C$66,0)*$C$89 -> 0.0097704 | F89: =VLOOKUP(EOMONTH(F81,0),Macroeconomics!$B$67:$R$380,Macroeconomics!$C$66,0)*$C$89 -> 0.00966184 | G89: =VLOOKUP(EOMONTH(G81,0),Macroeconomics!$B$67:$R$380,Macroeconomics!$C$66,0)*$C$89 -> 0.00803344 | H89: =VLOOKUP(EOMONTH(H81,0),Macroeconomics!$B$67:$R$380,Macroeconomics!$C$66,0)*$C$89 -> 0.00879336 | I89: =VLOOKUP(EOMONTH(I81,0),Macroeconomics!$B$67:$R$380,Macroeconomics!$C$66,0)*$C$89 -> 0.0075992 | J89: =VLOOKUP(EOMONTH(J81,0),Macroeconomics!$B$67:$R$380,Macroeconomics!$C$66,0)*$C$89 -> 0.0080283201 | K89: =VLOOKUP(EOMONTH(K81,0),Macroeconomics!$B$67:$R$380,Macroeconomics!$C$66,0)*$C$89 -> 0.0069084304 | L89: =VLOOKUP(EOMONTH(L81,0),Macroeconomics!$B$67:$R$380,Macroeconomics!$C$66,0)*$C$89 -> 0.0075188768 | ... GQ89: =VLOOKUP(EOMONTH(GQ81,0),Macroeconomics!$B$67:$R$380,Macroeconomics!$C$66,0)*$C$89 -> 0.0077657364
B90: Amortização principal (3=trim, 6=sem, 12 =anual) | C90: 12
B91: Paga juros na carencia? (0=N;1=S) | C91: 0 | D91: Juros Pagos | E91: =IF(OR(E81<=$C83,E81>$C84),0,IF(AND(E81<=$C85,$C91=1,MOD(MONTH(E81)-MONTH($C83),6)=0),1,IF(AND(MOD(MONTH(E81)-MONTH($C83),$C90)=0,E81>=$C85),1,0))) -> 0 | F91: =IF(OR(F81<=$C83,F81>$C84),0,IF(AND(F81<=$C85,$C91=1,MOD(MONTH(F81)-MONTH($C83),6)=0),1,IF(AND(MOD(MONTH(F81)-MONTH($C83),$C90)=0,F81>=$C85),1,0))) -> 0 | G91: =IF(OR(G81<=$C83,G81>$C84),0,IF(AND(G81<=$C85,$C91=1,MOD(MONTH(G81)-MONTH($C83),6)=0),1,IF(AND(MOD(MONTH(G81)-MONTH($C83),$C90)=0,G81>=$C85),1,0))) -> 0 | H91: =IF(OR(H81<=$C83,H81>$C84),0,IF(AND(H81<=$C85,$C91=1,MOD(MONTH(H81)-MONTH($C83),6)=0),1,IF(AND(MOD(MONTH(H81)-MONTH($C83),$C90)=0,H81>=$C85),1,0))) -> 0 | I91: =IF(OR(I81<=$C83,I81>$C84),0,IF(AND(I81<=$C85,$C91=1,MOD(MONTH(I81)-MONTH($C83),6)=0),1,IF(AND(MOD(MONTH(I81)-MONTH($C83),$C90)=0,I81>=$C85),1,0))) -> 0 | J91: =IF(OR(J81<=$C83,J81>$C84),0,IF(AND(J81<=$C85,$C91=1,MOD(MONTH(J81)-MONTH($C83),6)=0),1,IF(AND(MOD(MONTH(J81)-MONTH($C83),$C90)=0,J81>=$C85),1,0))) -> 0 | K91: =IF(OR(K81<=$C83,K81>$C84),0,IF(AND(K81<=$C85,$C91=1,MOD(MONTH(K81)-MONTH($C83),6)=0),1,IF(AND(MOD(MONTH(K81)-MONTH($C83),$C90)=0,K81>=$C85),1,0))) -> 0 | L91: =IF(OR(L81<=$C83,L81>$C84),0,IF(AND(L81<=$C85,$C91=1,MOD(MONTH(L81)-MONTH($C83),6)=0),1,IF(AND(MOD(MONTH(L81)-MONTH($C83),$C90)=0,L81>=$C85),1,0))) -> 0 | ... GQ91: =IF(OR(GQ81<=$C83,GQ81>$C84),0,IF(AND(GQ81<=$C85,$C91=1,MOD(MONTH(GQ81)-MONTH($C83),6)=0),1,IF(AND(MOD(MONTH(GQ81)-MONTH($C83),$C90)=0,GQ81>=$C85),1,0))) -> 0
B92: Capitaliza juros no inicio da amort? (0=N;1=S) | C92: 0 | D92: Prestações pagas | E92: =IF(E86<>"",1,0) -> 0 | F92: =IF(F86<>"",1,0) -> 0 | G92: =IF(G86<>"",1,0) -> 0 | H92: =IF(H86<>"",1,0) -> 0 | I92: =IF(I86<>"",1,0) -> 0 | J92: =IF(J86<>"",1,0) -> 0 | K92: =IF(K86<>"",1,0) -> 0 | L92: =IF(L86<>"",1,0) -> 0 | ... GQ92: =IF(GQ86<>"",1,0) -> 0
B93: Prestações remanescentes | C93: 4 | E93: =MAX(C93-E92,0) -> 4 | F93: =MAX(E93-F92,0) -> 4 | G93: =MAX(F93-G92,0) -> 4 | H93: =MAX(G93-H92,0) -> 4 | I93: =MAX(H93-I92,0) -> 4 | J93: =MAX(I93-J92,0) -> 4 | K93: =MAX(J93-K92,0) -> 4 | L93: =MAX(K93-L92,0) -> 4 | M93: =MAX(L93-M92,0) -> 4 | ... GQ93: =MAX(GP93-GQ92,0) -> 0
B95: Saldo inicial | E95: =D101 -> 0 | F95: =E101 -> 191611 | G95: =F101 -> 193462.31 | H95: =G101 -> 195016.48 | I95: =H101 -> 196731.33 | J95: =I101 -> 198226.33 | K95: =J101 -> 199817.76 | L95: =K101 -> 201198.19 | ... GQ95: =GP101 -> 0
B96: Novo funding | E96: 190000 | F96: =(IF(F81<$C83,0,IF(F81=$C83,$C96,0))) -> 0 | G96: =(IF(G81<$C83,0,IF(G81=$C83,$C96,0))) -> 0 | H96: =(IF(H81<$C83,0,IF(H81=$C83,$C96,0))) -> 0 | I96: =(IF(I81<$C83,0,IF(I81=$C83,$C96,0))) -> 0 | J96: =(IF(J81<$C83,0,IF(J81=$C83,$C96,0))) -> 0 | K96: =(IF(K81<$C83,0,IF(K81=$C83,$C96,0))) -> 0 | L96: =(IF(L81<$C83,0,IF(L81=$C83,$C96,0))) -> 0 | M96: =(IF(M81<$C83,0,IF(M81=$C83,$C96,0))) -> 0 | ... GQ96: =(IF(GQ81<$C83,0,IF(GQ81=$C83,$C96,0))) -> 0
B97: Correção Monetária IPCA | E97: =SUM(E95:E96,-D102)*(E105-1) -> 0 | F97: =SUM(F95:F96,-E102)*(F105-1) -> 0 | G97: =SUM(G95:G96,-F102)*(G105-1) -> 0 | H97: =SUM(H95:H96,-G102)*(H105-1) -> 0 | I97: =SUM(I95:I96,-H102)*(I105-1) -> 0 | J97: =SUM(J95:J96,-I102)*(J105-1) -> 0 | K97: =SUM(K95:K96,-J102)*(K105-1) -> 0 | L97: =SUM(L95:L96,-K102)*(L105-1) -> 0 | ... GQ97: =SUM(GQ95:GQ96,-GP102)*(GQ105-1) -> 0
B98: Juros apropriados (DRE) | E98: 0 | F98: =SUM(F95:F97)*F89 -> 1851.3148 | G98: =SUM(G95:G97)*G89 -> 1554.1679 | H98: =SUM(H95:H97)*H89 -> 1714.8501 | I98: =SUM(I95:I97)*I89 -> 1495.0007 | J98: =SUM(J95:J97)*J89 -> 1591.4245 | K98: =SUM(K95:K97)*K89 -> 1380.4271 | L98: =SUM(L95:L97)*L89 -> 1512.7844 | M98: =SUM(M95:M97)*M89 -> 1566.7654 | ... GQ98: =SUM(GQ95:GQ97)*GQ89 -> 0
B99: Juros pagos (Caixa) | E99: =IF(E91=1,-D102-E98,0)*IF(AND(E81=$C86,$C92=1,$C91=0),0,1) -> 0 | F99: =IF(F91=1,-E102-F98,0)*IF(AND(F81=$C86,$C92=1,$C91=0),0,1) -> 0 | G99: =IF(G91=1,-F102-G98,0)*IF(AND(G81=$C86,$C92=1,$C91=0),0,1) -> 0 | H99: =IF(H91=1,-G102-H98,0)*IF(AND(H81=$C86,$C92=1,$C91=0),0,1) -> 0 | I99: =IF(I91=1,-H102-I98,0)*IF(AND(I81=$C86,$C92=1,$C91=0),0,1) -> 0 | J99: =IF(J91=1,-I102-J98,0)*IF(AND(J81=$C86,$C92=1,$C91=0),0,1) -> 0 | K99: =IF(K91=1,-J102-K98,0)*IF(AND(K81=$C86,$C92=1,$C91=0),0,1) -> 0 | L99: =IF(L91=1,-K102-L98,0)*IF(AND(L81=$C86,$C92=1,$C91=0),0,1) -> 0 | ... GQ99: =IF(GQ91=1,-GP102-GQ98,0)*IF(AND(GQ81=$C86,$C92=1,$C91=0),0,1) -> 0
B100: Amortização principal (Caixa) | E100: =-E86*LOOKUP($C83,$E81:$GQ81,$E96:$GQ96) -> 0 | F100: =-F86*LOOKUP($C83,$E81:$GQ81,$E96:$GQ96) -> 0 | G100: =-G86*LOOKUP($C83,$E81:$GQ81,$E96:$GQ96) -> 0 | H100: =-H86*LOOKUP($C83,$E81:$GQ81,$E96:$GQ96) -> 0 | I100: =-I86*LOOKUP($C83,$E81:$GQ81,$E96:$GQ96) -> 0 | J100: =-J86*LOOKUP($C83,$E81:$GQ81,$E96:$GQ96) -> 0 | K100: =-K86*LOOKUP($C83,$E81:$GQ81,$E96:$GQ96) -> 0 | L100: =-L86*LOOKUP($C83,$E81:$GQ81,$E96:$GQ96) -> 0 | ... GQ100: =-GQ86*LOOKUP($C83,$E81:$GQ81,$E96:$GQ96) -> 0
B101: Saldo final (Balanço) | E101: 191611 | F101: =IF(SUM(F95:F100)<0.00000001,ROUND(SUM(F95:F100),7),SUM(F95:F100)) -> 193462.31 | G101: =IF(SUM(G95:G100)<0.00000001,ROUND(SUM(G95:G100),7),SUM(G95:G100)) -> 195016.48 | H101: =IF(SUM(H95:H100)<0.00000001,ROUND(SUM(H95:H100),7),SUM(H95:H100)) -> 196731.33 | I101: =IF(SUM(I95:I100)<0.00000001,ROUND(SUM(I95:I100),7),SUM(I95:I100)) -> 198226.33 | J101: =IF(SUM(J95:J100)<0.00000001,ROUND(SUM(J95:J100),7),SUM(J95:J100)) -> 199817.76 | K101: =IF(SUM(K95:K100)<0.00000001,ROUND(SUM(K95:K100),7),SUM(K95:K100)) -> 201198.19 | L101: =IF(SUM(L95:L100)<0.00000001,ROUND(SUM(L95:L100),7),SUM(L95:L100)) -> 202710.97 | M101: =IF(SUM(M95:M100)<0.00000001,ROUND(SUM(M95:M100),7),SUM(M95:M100)) -> 204277.73 | ... GQ101: =IF(SUM(GQ95:GQ100)<0.00000001,ROUND(SUM(GQ95:GQ100),7),SUM(GQ95:GQ100)) -> 0
B102: Juros acumulados | E102: 1611 | F102: =(F98+E102+F99)*IF(AND(F81=$C86,$C92),0,1) -> 3462.3148 | G102: =(G98+F102+G99)*IF(AND(G81=$C86,$C92),0,1) -> 5016.4827 | H102: =(H98+G102+H99)*IF(AND(H81=$C86,$C92),0,1) -> 6731.3329 | I102: =(I98+H102+I99)*IF(AND(I81=$C86,$C92),0,1) -> 8226.3336 | J102: =(J98+I102+J99)*IF(AND(J81=$C86,$C92),0,1) -> 9817.7581 | K102: =(K98+J102+K99)*IF(AND(K81=$C86,$C92),0,1) -> 11198.185 | L102: =(L98+K102+L99)*IF(AND(L81=$C86,$C92),0,1) -> 12710.97 | M102: =(M98+L102+M99)*IF(AND(M81=$C86,$C92),0,1) -> 14277.735 | ... GQ102: =(GQ98+GP102+GQ99)*IF(AND(GQ81=$C86,$C92),0,1) -> 0
B104: Serviço da divida | E104: =E100+E99 -> 0 | F104: =F100+F99 -> 0 | G104: =G100+G99 -> 0 | H104: =H100+H99 -> 0 | I104: =I100+I99 -> 0 | J104: =J100+J99 -> 0 | K104: =K100+K99 -> 0 | L104: =L100+L99 -> 0 | ... GQ104: =GQ100+GQ99 -> 0
B105: Correção Monetária no período | C105: 1 | E105: =IF(E81>=$C83,1+E88,1) -> 1 | F105: =IF(F81>=$C83,1+F88,1) -> 1 | G105: =IF(G81>=$C83,1+G88,1) -> 1 | H105: =IF(H81>=$C83,1+H88,1) -> 1 | I105: =IF(I81>=$C83,1+I88,1) -> 1 | J105: =IF(J81>=$C83,1+J88,1) -> 1 | K105: =IF(K81>=$C83,1+K88,1) -> 1 | L105: =IF(L81>=$C83,1+L88,1) -> 1 | ... GQ105: =IF(GQ81>=$C83,1+GQ88,1) -> 1
B106: Correção Monetária Acumulada | C106: 1 | E106: =C106*E105 -> 1 | F106: =E106*F105 -> 1 | G106: =F106*G105 -> 1 | H106: =G106*H105 -> 1 | I106: =H106*I105 -> 1 | J106: =I106*J105 -> 1 | K106: =J106*K105 -> 1 | L106: =K106*L105 -> 1 | M106: =L106*M105 -> 1 | ... GQ106: =GP106*GQ105 -> 1
B107: Correção Monetária Acumulada Juros a Capitalizar | C107: 1 | E107: =IF(E81>$C86,(1+E88)*C107,1) -> 1 | F107: =IF(F81>$C86,(1+F88)*D107,1) -> 1 | G107: =IF(G81>$C86,(1+G88)*E107,1) -> 1 | H107: =IF(H81>$C86,(1+H88)*F107,1) -> 1 | I107: =IF(I81>$C86,(1+I88)*G107,1) -> 1 | J107: =IF(J81>$C86,(1+J88)*H107,1) -> 1 | K107: =IF(K81>$C86,(1+K88)*I107,1) -> 1 | L107: =IF(L81>$C86,(1+L88)*J107,1) -> 1 | ... GQ107: =IF(GQ81>$C86,(1+GQ88)*GO107,1) -> 1
B108: Saldo Devedor Base (capitalização de juros) | E108: =SUM(E95:E99) -> 190000 | F108: =SUM(F95:F99) -> 193462.31 | G108: =SUM(G95:G99) -> 195016.48 | H108: =SUM(H95:H99) -> 196731.33 | I108: =SUM(I95:I99) -> 198226.33 | J108: =SUM(J95:J99) -> 199817.76 | K108: =SUM(K95:K99) -> 201198.19 | L108: =SUM(L95:L99) -> 202710.97 | ... GQ108: =SUM(GQ95:GQ99) -> 0
B111: Caixa Economica Federal | E111: =C113 -> 40817 | F111: =EDATE(E111,1) -> 40848 | G111: =EDATE(F111,1) -> 40878 | H111: =EDATE(G111,1) -> 40909 | I111: =EDATE(H111,1) -> 40940 | J111: =EDATE(I111,1) -> 40969 | K111: =EDATE(J111,1) -> 41000 | L111: =EDATE(K111,1) -> 41030 | M111: =EDATE(L111,1) -> 41061 | ... GQ111: =EDATE(GP111,1) -> 46722
E112: =YEAR(E111) -> 2011 | F112: =YEAR(F111) -> 2011 | G112: =YEAR(G111) -> 2011 | H112: =YEAR(H111) -> 2012 | I112: =YEAR(I111) -> 2012 | J112: =YEAR(J111) -> 2012 | K112: =YEAR(K111) -> 2012 | L112: =YEAR(L111) -> 2012 | ... GQ112: =YEAR(GQ111) -> 2027
B113: Dt desembolso | C113: 40817
B114: Prazo Total | C114: 41913
B115: Final Carência | C115: 40969
B116: Início Amortização principal | C116: 40634 | D116: Amort => | K116: =1/6 -> 0.16666667 | Q116: =1/6 -> 0.16666667 | W116: =1/6 -> 0.16666667 | AC116: =1/6 -> 0.16666667 | AI116: =1/6 -> 0.16666667 | AO116: =1/6 -> 0.16666667
...

Sheet Links -->

Sheet Macroeconomics
B2: 1. PREMISSAS MACROECONOMICAS | W2: =139/116-1 -> 0.19827586
B3: Fonte: Departamento de Pesquisa Macroeconômica do Santander (Brasil) S.A. | H3: Atualização: | I3: 41057 | W3: 0.5295 | X3: =+W3/W2 -> 2.6705217
A5: 1 | C5: 2001 | D5: 2002 | E5: 37711 | F5: 37802 | G5: 37894 | H5: 37986 | I5: 2003 | J5: 38077 | K5: 38168 | L5: 38260 | M5: 38352 | N5: 2004 | O5: 38442 | P5: 38533 | Q5: 38625 | R5: 38717 | S5: 2005 | T5: 38807 | U5: 38898 | V5: 38990 | W5: 39082 | X5: 2006 | Y5: 39172 | Z5: 39263 | AA5: 39355 | AB5: 39447 | AC5: 2007 | AD5: 39538 | AE5: 39629 | AF5: 39721 | AG5: 39813 | AH5: 2008 | AI5: 39903 | AJ5: 39994 | AK5: 40086 | AL5: 40178 | AM5: 2009 | AN5: 40268 | AO5: 40359 | AP5: 40451 | AQ5: 40543 | AR5: 2010 | AS5: 40633 | AT5: 40724 | AU5: 40816 | AV5: 40908 | AW5: 2011 | AX5: 40999 | AY5: 41090 | AZ5: 41182 | BA5: 41274 | BB5: 2012 | BC5: 41364 | BD5: 41455 | BE5: 41547 | BF5: 41639 | BG5: 2013 | BH5: 41729 | BI5: 41820 | BJ5: 41912 | BK5: 42004 | BL5: 2014 | BM5: 42094 | BN5: 42185 | BO5: 42277 | BP5: 42369 | BQ5: 2015 | BR5: 42460 | BS5: 42551 | BT5: 42643 | BU5: 42735 | BV5: 2016 | BW5: 42825 | BX5: 42916 | BY5: 43008 | BZ5: 43100 | CA5: 2017 | CB5: 43190 | CC5: 43281 | CD5: 43373 | CE5: 43465 | CF5: 2018 | CG5: 43555 | CH5: 43646 | CI5: 43738 | CJ5: 43830 | CK5: 2019 | CL5: 43921 | CM5: 44012 | CN5: 44104 | CO5: 44196 | CP5: 2020 | CQ5: 44286 | CR5: 44377 | CS5: 44469 | CT5: 44561 | CU5: 2021 | CV5: 44651 | CW5: 44742 | CX5: 44834 | CY5: 44926 | CZ5: 2022 | DA5: 45016 | DB5: 45107 | DC5: 45199 | DD5: 45291 | DE5: 2023 | DF5: 45382 | DG5: 45473 | DH5: 45565 | DI5: 45657 | DJ5: 2024 | DK5: =DATE(DO5,3,31) -> 45747 | DL5: =DATE(DO5,6,30) -> 45838 | DM5: =DATE(DO5,9,30) -> 45930 | DN5: =DATE(DO5,12,31) -> 46022 | DO5: =+DJ5+1 -> 2025 | DP5: =DATE(DT5,3,31) -> 46112 | DQ5: =DATE(DT5,6,30) -> 46203 | DR5: =DATE(DT5,9,30) -> 46295 | DS5: =DATE(DT5,12,31) -> 46387 | DT5: =+DO5+1 -> 2026 | DU5: =DATE(DY5,3,31) -> 46477 | DV5: =DATE(DY5,6,30) -> 46568 | DW5: =DATE(DY5,9,30) -> 46660 | DX5: =DATE(DY5,12,31) -> 46752 | DY5: =+DT5+1 -> 2027 | DZ5: =DATE(ED5,3,31) -> 46843 | EA5: =DATE(ED5,6,30) -> 46934 | EB5: =DATE(ED5,9,30) -> 47026 | EC5: =DATE(ED5,12,31) -> 47118 | ED5: =+DY5+1 -> 2028 | EE5: =DATE(EI5,3,31) -> 47208 | EF5: =DATE(EI5,6,30) -> 47299 | EG5: =DATE(EI5,9,30) -> 47391 | EH5: =DATE(EI5,12,31) -> 47483 | EI5: =+ED5+1 -> 2029 | EJ5: =DATE(EN5,3,31) -> 47573 | EK5: =DATE(EN5,6,30) -> 47664 | EL5: =DATE(EN5,9,30) -> 47756 | EM5: =DATE(EN5,12,31) -> 47848 | EN5: =+EI5+1 -> 2030 | EO5: =DATE(ES5,3,31) -> 47938 | EP5: =DATE(ES5,6,30) -> 48029 | EQ5: =DATE(ES5,9,30) -> 48121 | ER5: =DATE(ES5,12,31) -> 48213 | ES5: =+EN5+1 -> 2031 | ET5: =DATE(EX5,3,31) -> 48304 | EU5: =DATE(EX5,6,30) -> 48395 | EV5: =DATE(EX5,9,30) -> 48487 | EW5: =DATE(EX5,12,31) -> 48579 | EX5: =+ES5+1 -> 2032 | EY5: =DATE(FC5,3,31) -> 48669 | EZ5: =DATE(FC5,6,30) -> 48760 | FA5: =DATE(FC5,9,30) -> 48852 | FB5: =DATE(FC5,12,31) -> 48944 | FC5: =+EX5+1 -> 2033 | FD5: =DATE(FH5,3,31) -> 49034 | FE5: =DATE(FH5,6,30) -> 49125 | FF5: =DATE(FH5,9,30) -> 49217 | FG5: =DATE(FH5,12,31) -> 49309 | FH5: =+FC5+1 -> 2034 | FI5: =DATE(FM5,3,31) -> 49399 | FJ5: =DATE(FM5,6,30) -> 49490 | FK5: =DATE(FM5,9,30) -> 49582 | FL5: =DATE(FM5,12,31) -> 49674 | FM5: =+FH5+1 -> 2035 | FN5: =DATE(FR5,3,31) -> 49765 | FO5: =DATE(FR5,6,30) -> 49856 | FP5: =DATE(FR5,9,30) -> 49948 | FQ5: =DATE(FR5,12,31) -> 50040 | FR5: =+FM5+1 -> 2036 | FS5: =DATE(FW5,3,31) -> 50130 | FT5: =DATE(FW5,6,30) -> 50221 | FU5: =DATE(FW5,9,30) -> 50313 | FV5: =DATE(FW5,12,31) -> 50405 | FW5: =+FR5+1 -> 2037 | FX5: =DATE(GB5,3,31) -> 50495 | FY5: =DATE(GB5,6,30) -> 50586 | FZ5: =DATE(GB5,9,30) -> 50678 | GA5: =DATE(GB5,12,31) -> 50770 | GB5: =+FW5+1 -> 2038
A6: =A5+1 -> 2
A7: =A6+1 -> 3 | B7: População (milhares | C7: 173808.01 | D7: 176303.92 | E7: 176913.29 | F7: 177522.67 | G7: 178132.04 | H7: 178741.41 | I7: 178741.41 | J7: 179332.46 | K7: 179923.51 | L7: 180514.55 | M7: 181105.6 | N7: 181105.6 | O7: 181675 | P7: 182244.41 | Q7: 182813.81 | R7: 183383.22 | S7: 183383.22 | T7: 183928.47 | U7: 184473.71 | V7: 185018.96 | W7: 185564.21 | X7: 185564.21 | Y7: 186083.59 | Z7: 186602.96 | AA7: 187122.34 | AB7: 187641.71 | AC7: 187641.71 | AD7: 188134.49 | AE7: 188627.26 | AF7: 189120.04 | AG7: 189612.81 | AH7: 189612.81 | AI7: 190079.77 | AJ7: 190546.72 | AK7: 191013.68 | AL7: 191480.63 | AM7: 191480.63 | AN7: 191923.62 | AO7: 192366.62 | AP7: 192809.61 | AQ7: 193252.6 | AR7: 193252.6 | AS7: =AQ7*(1+AS8) -> 193671.26 | AT7: =AS7*(1+AT8) -> 194090.83 | AU7: =AT7*(1+AU8) -> 194511.3 | AV7: =AU7*(1+AV8) -> 194932.68 | AW7: 194932.68 | AX7: =AV7*(1+AX8) -> 195329.87 | AY7: =AX7*(1+AY8) -> 195727.87 | AZ7: =AY7*(1+AZ8) -> 196126.67 | BA7: =AZ7*(1+BA8) -> 196526.29 | BB7: 196526.29 | BC7: =BA7*(1+BC8) -> 196904.46 | BD7: =BC7*(1+BD8) -> 197283.35 | BE7: =BD7*(1+BE8) -> 197662.97 | BF7: =BE7*(1+BF8) -> 198043.32 | BG7: 198043.32 | BH7: =BF7*(1+BH8) -> 198404.61 | BI7: =BH7*(1+BI8) -> 198766.56 | BJ7: =BI7*(1+BJ8) -> 199129.16 | BK7: =BJ7*(1+BK8) -> 199492.43 | BL7: 199492.43 | BM7: =BK7*(1+BM8) -> 199838.84 | BN7: =BM7*(1+BN8) -> 200185.85 | BO7: =BN7*(1+BO8) -> 200533.47 | BP7: =BO7*(1+BP8) -> 200881.68 | BQ7: 200881.68 | BR7: =BP7*(1+BR8) -> 201215.2 | BS7: =BR7*(1+BS8) -> 201549.26 | BT7: =BS7*(1+BT8) -> 201883.88 | BU7: =BT7*(1+BU8) -> 202219.06 | BV7: 202219.06 | BW7: =BU7*(1+BW8) -> 202541.13 | BX7: =BW7*(1+BX8) -> 202863.71 | BY7: =BX7*(1+BY8) -> 203186.81 | BZ7: =BY7*(1+BZ8) -> 203510.42 | CA7: 203510.42 | CB7: =BZ7*(1+CB8) -> 203822.1 | CC7: =CB7*(1+CC8) -> 204134.25 | CD7: =CC7*(1+CD8) -> 204446.88 | CE7: =CD7*(1+CE8) -> 204759.99 | CF7: 204759.99 | CG7: =CE7*(1+CG8) -> 205061.87 | CH7: =CG7*(1+CH8) -> 205364.2 | CI7: =CH7*(1+CI8) -> 205666.97 | CJ7: =CI7*(1+CJ8) -> 205970.18 | CK7: 205970.18 | CL7: =CJ7*(1+CL8) -> 206262.82 | CM7: =CL7*(1+CM8) -> 206555.88 | CN7: =CM7*(1+CN8) -> 206849.35 | CO7: =CN7*(1+CO8) -> 207143.24 | CP7: 207143.24 | CQ7: =CO7*(1+CQ8) -> 207426.91 | CR7: =CQ7*(1+CR8) -> 207710.96 | CS7: =CR7*(1+CS8) -> 207995.41 | CT7: =CS7*(1+CT8) -> 208280.24 | CU7: 208280.24 | CV7: =CT7*(1+CV8) -> 208554.72 | CW7: =CV7*(1+CW8) -> 208829.56 | CX7: =CW7*(1+CX8) -> 209104.76 | CY7: =CX7*(1+CY8) -> 209380.33 | CZ7: 209380.33 | DA7: =CY7*(1+DA8) -> 209645.09 | DB7: =DA7*(1+DB8) -> 209910.18 | DC7: =DB7*(1+DC8) -> 210175.6 | DD7: =DC7*(1+DD8) -> 210441.36 | DE7: 210441.36 | DF7: =DD7*(1+DF8) -> 210695.4 | DG7: =DF7*(1+DG8) -> 210949.74 | DH7: =DG7*(1+DH8) -> 211204.39 | DI7: =DH7*(1+DI8) -> 211459.35 | DJ7: 211459.35 | DK7: =DI7*(1+DK8) -> 211701.61 | DL7: =DK7*(1+DL8) -> 211944.14 | DM7: =DL7*(1+DM8) -> 212186.96 | DN7: =DM7*(1+DN8) -> 212430.05 | DO7: 212430.05 | DP7: =DN7*(1+DP8) -> 212659.28 | DQ7: =DP7*(1+DQ8) -> 212888.77 | DR7: =DQ7*(1+DR8) -> 213118.5 | DS7: =DR7*(1+DS8) -> 213348.48 | DT7: 213348.48 | DU7: =DS7*(1+DU8) -> 213563.38 | DV7: =DU7*(1+DV8) -> 213778.51 | DW7: =DV7*(1+DW8) -> 213993.85 | DX7: =DW7*(1+DX8) -> 214209.41 | DY7: 214209.41 | DZ7: =DX7*(1+DZ8) -> 214409.03 | EA7: =DZ7*(1+EA8) -> 214608.83 | EB7: =EA7*(1+EB8) -> 214808.81 | EC7: =EB7*(1+EC8) -> 215008.98 | ED7: 215008.98 | EE7: =EC7*(1+EE8) -> 215192.4 | EF7: =EE7*(1+EF8) -> 215375.97 | EG7: =EF7*(1+EG8) -> 215559.7 | EH7: =EG7*(1+EH8) -> 215743.58 | EI7: 215743.58 | EJ7: =EH7*(1+EJ8) -> 215910 | EK7: =EJ7*(1+EK8) -> 216076.55 | EL7: =EK7*(1+EL8) -> 216243.23 | EM7: =EL7*(1+EM8) -> 216410.03 | EN7: 216410.03 | EO7: =+EN7 -> 216410.03 | EP7: =+EO7 -> 216410.03 | EQ7: =+EP7 -> 216410.03 | ER7: =+EQ7 -> 216410.03 | ES7: 216410.03 | ET7: =+ES7 -> 216410.03 | EU7: =+ET7 -> 216410.03 | EV7: =+EU7 -> 216410.03 | EW7: =+EV7 -> 216410.03 | EX7: 216410.03 | EY7: =+EX7 -> 216410.03 | EZ7: =+EY7 -> 216410.03 | FA7: =+EZ7 -> 216410.03 | FB7: =+FA7 -> 216410.03 | FC7: 216410.03 | FD7: =+FC7 -> 216410.03 | FE7: =+FD7 -> 216410.03 | FF7: =+FE7 -> 216410.03 | FG7: =+FF7 -> 216410.03 | FH7: 216410.03 | FI7: =+FH7 -> 216410.03 | FJ7: =+FI7 -> 216410.03 | FK7: =+FJ7 -> 216410.03 | FL7: =+FK7 -> 216410.03 | FM7: 216410.03 | FN7: =+FM7 -> 216410.03 | FO7: =+FN7 -> 216410.03 | FP7: =+FO7 -> 216410.03 | FQ7: =+FP7 -> 216410.03 | FR7: =+FQ7 -> 216410.03 | FS7: =+FR7 -> 216410.03 | FT7: =+FS7 -> 216410.03 | FU7: =+FT7 -> 216410.03 | ... GB7: =+GA7 -> 216410.03
A8: =A7+1 -> 4 | B8: Variation | D8: 0.014360149 | E8: 0.0034563795 | F8: 0.0034444741 | G8: 0.0034326504 | H8: 0.0034209076 | I8: 0.013825518 | J8: 0.0033067169 | K8: 0.0032958186 | L8: 0.0032849918 | M8: 0.003274236 | N8: 0.013226868 | O8: 0.0031440427 | P8: 0.0031341887 | Q8: 0.0031243963 | R8: 0.0031146648 | S8: 0.012576171 | T8: 0.0029732765 | U8: 0.0029644623 | V8: 0.0029557002 | W8: 0.0029469898 | X8: 0.011893106 | Y8: 0.0027988991 | Z8: 0.0027910871 | AA8: 0.0027833186 | AB8: 0.0027755933 | AC8: 0.011195596 | AD8: 0.0026261485 | AE8: 0.0026192699 | AF8: 0.0026124272 | AG8: 0.0026056202 | AH8: 0.010504594 | AI8: 0.0024626711 | AJ8: 0.0024566213 | AK8: 0.0024506011 | AL8: 0.0024446103 | AM8: 0.0098506845 | AN8: 0.002313516 | AO8: 0.002308176 | AP8: 0.0023028606 | AQ8: 0.0022975696 | AR8: 0.009254064 | AS8: =(1+AW8)^(1/4)-1 -> 0.0021663761 | AT8: =(1+AW8)^(1/4)-1 -> 0.0021663761 | AU8: =(1+AW8)^(1/4)-1 -> 0.0021663761 | AV8: =(1+AW8)^(1/4)-1 -> 0.0021663761 | AW8: =AW7/AR7-1 -> 0.0086937043 | AX8: =(1+BB8)^(1/4)-1 -> 0.0020375568 | AY8: =(1+BB8)^(1/4)-1 -> 0.0020375568 | AZ8: =(1+BB8)^(1/4)-1 -> 0.0020375568 | BA8: =(1+BB8)^(1/4)-1 -> 0.0020375568 | BB8: =BB7/AW7-1 -> 0.0081751708 | BC8: =(1+BG8)^(1/4)-1 -> 0.0019242404 | BD8: =(1+BG8)^(1/4)-1 -> 0.0019242404 | BE8: =(1+BG8)^(1/4)-1 -> 0.0019242404 | BF8: =(1+BG8)^(1/4)-1 -> 0.0019242404 | BG8: =BG7/BB7-1 -> 0.0077192063 | BH8: =(1+BL8)^(1/4)-1 -> 0.0018242898 | BI8: =(1+BL8)^(1/4)-1 -> 0.0018242898 | BJ8: =(1+BL8)^(1/4)-1 -> 0.0018242898 | BK8: =(1+BL8)^(1/4)-1 -> 0.0018242898 | BL8: =BL7/BG7-1 -> 0.0073171516 | BM8: =(1+BQ8)^(1/4)-1 -> 0.0017364552 | BN8: =(1+BQ8)^(1/4)-1 -> 0.0017364552 | BO8: =(1+BQ8)^(1/4)-1 -> 0.0017364552 | BP8: =(1+BQ8)^(1/4)-1 -> 0.0017364552 | BQ8: =BQ7/BL7-1 -> 0.0069639333 | BR8: =(1+BV8)^(1/4)-1 -> 0.0016602435 | BS8: =(1+BV8)^(1/4)-1 -> 0.0016602435 | BT8: =(1+BV8)^(1/4)-1 -> 0.0016602435 | BU8: =(1+BV8)^(1/4)-1 -> 0.0016602435 | BV8: =BV7/BQ7-1 -> 0.0066575308 | BW8: =(1+CA8)^(1/4)-1 -> 0.0015926788 | BX8: =(1+CA8)^(1/4)-1 -> 0.0015926788 | BY8: =(1+CA8)^(1/4)-1 -> 0.0015926788 | BZ8: =(1+CA8)^(1/4)-1 -> 0.0015926788 | CA8: =CA7/BV7-1 -> 0.0063859509 | CB8: =(1+CF8)^(1/4)-1 -> 0.0015314991 | CC8: =(1+CF8)^(1/4)-1 -> 0.0015314991 | CD8: =(1+CF8)^(1/4)-1 -> 0.0015314991 | CE8: =(1+CF8)^(1/4)-1 -> 0.0015314991 | CF8: =CF7/CA7-1 -> 0.0061400836 | CG8: =(1+CK8)^(1/4)-1 -> 0.0014743066 | CH8: =(1+CK8)^(1/4)-1 -> 0.0014743066 | CI8: =(1+CK8)^(1/4)-1 -> 0.0014743066 | CJ8: =(1+CK8)^(1/4)-1 -> 0.0014743066 | CK8: =CK7/CF7-1 -> 0.0059102805 | CL8: =(1+CP8)^(1/4)-1 -> 0.001420793 | CM8: =(1+CP8)^(1/4)-1 -> 0.001420793 | CN8: =(1+CP8)^(1/4)-1 -> 0.001420793 | CO8: =(1+CP8)^(1/4)-1 -> 0.001420793 | CP8: =CP7/CK7-1 -> 0.0056952953 | CQ8: =(1+CU8)^(1/4)-1 -> 0.0013694209 | CR8: =(1+CU8)^(1/4)-1 -> 0.0013694209 | CS8: =(1+CU8)^(1/4)-1 -> 0.0013694209 | CT8: =(1+CU8)^(1/4)-1 -> 0.0013694209 | CU8: =CU7/CP7-1 -> 0.0054889456 | CV8: =(1+CZ8)^(1/4)-1 -> 0.0013178372 | CW8: =(1+CZ8)^(1/4)-1 -> 0.0013178372 | CX8: =(1+CZ8)^(1/4)-1 -> 0.0013178372 | CY8: =(1+CZ8)^(1/4)-1 -> 0.0013178372 | CZ8: =CZ7/CU7-1 -> 0.005281778 | DA8: =(1+DE8)^(1/4)-1 -> 0.0012644701 | DB8: =(1+DE8)^(1/4)-1 -> 0.0012644701 | DC8: =(1+DE8)^(1/4)-1 -> 0.0012644701 | DD8: =(1+DE8)^(1/4)-1 -> 0.0012644701 | DE8: =DE7/CZ7-1 -> 0.0050674817 | DF8: =(1+DJ8)^(1/4)-1 -> 0.0012071635 | DG8: =(1+DJ8)^(1/4)-1 -> 0.0012071635 | DH8: =(1+DJ8)^(1/4)-1 -> 0.0012071635 | DI8: =(1+DJ8)^(1/4)-1 -> 0.0012071635 | DJ8: =DJ7/DE7-1 -> 0.0048374045 | DK8: =(1+DO8)^(1/4)-1 -> 0.0011456463 | DL8: =(1+DO8)^(1/4)-1 -> 0.0011456463 | DM8: =(1+DO8)^(1/4)-1 -> 0.0011456463 | DN8: =(1+DO8)^(1/4)-1 -> 0.0011456463 | DO8: =DO7/DJ7-1 -> 0.0045904662 | DP8: =(1+DT8)^(1/4)-1 -> 0.001079109 | DQ8: =(1+DT8)^(1/4)-1 -> 0.001079109 | DR8: =(1+DT8)^(1/4)-1 -> 0.001079109 | DS8: =(1+DT8)^(1/4)-1 -> 0.001079109 | DT8: =DT7/DO7-1 -> 0.0043234279 | DU8: =(1+DY8)^(1/4)-1 -> 0.0010073182 | DV8: =(1+DY8)^(1/4)-1 -> 0.0010073182 | DW8: =(1+DY8)^(1/4)-1 -> 0.0010073182 | DX8: =(1+DY8)^(1/4)-1 -> 0.0010073182 | DY8: =DY7/DT7-1 -> 0.0040353651 | DZ8: =(1+ED8)^(1/4)-1 -> 0.00093185825 | EA8: =(1+ED8)^(1/4)-1 -> 0.00093185825 | EB8: =(1+ED8)^(1/4)-1 -> 0.00093185825 | EC8: =(1+ED8)^(1/4)-1 -> 0.00093185825 | ED8: =ED7/DY7-1 -> 0.0037326464 | EE8: =(1+EI8)^(1/4)-1 -> 0.00085305818 | EF8: =(1+EI8)^(1/4)-1 -> 0.00085305818 | EG8: =(1+EI8)^(1/4)-1 -> 0.00085305818 | EH8: =(1+EI8)^(1/4)-1 -> 0.00085305818 | EI8: =EI7/ED7-1 -> 0.0034166015 | EJ8: =(1+EN8)^(1/4)-1 -> 0.00077137564 | EK8: =(1+EN8)^(1/4)-1 -> 0.00077137564 | EL8: =(1+EN8)^(1/4)-1 -> 0.00077137564 | EM8: =(1+EN8)^(1/4)-1 -> 0.00077137564 | EN8: =EN7/EI7-1 -> 0.0030890745 | EO8: =(1+ES8)^(1/4)-1 -> 0.00077137564 | EP8: =(1+ES8)^(1/4)-1 -> 0.00077137564 | EQ8: =(1+ES8)^(1/4)-1 -> 0.00077137564 | ER8: =(1+ES8)^(1/4)-1 -> 0.00077137564 | ES8: =+EN8 -> 0.0030890745 | ET8: =(1+EX8)^(1/4)-1 -> 0.00077137564 | EU8: =(1+EX8)^(1/4)-1 -> 0.00077137564 | EV8: =(1+EX8)^(1/4)-1 -> 0.00077137564 | EW8: =(1+EX8)^(1/4)-1 -> 0.00077137564 | EX8: =+ES8 -> 0.0030890745 | EY8: =(1+FC8)^(1/4)-1 -> 0.00077137564 | EZ8: =(1+FC8)^(1/4)-1 -> 0.00077137564 | FA8: =(1+FC8)^(1/4)-1 -> 0.00077137564 | FB8: =(1+FC8)^(1/4)-1 -> 0.00077137564 | FC8: =+EX8 -> 0.0030890745 | FD8: =(1+FH8)^(1/4)-1 -> 0.00077137564 | FE8: =(1+FH8)^(1/4)-1 -> 0.00077137564 | FF8: =(1+FH8)^(1/4)-1 -> 0.00077137564 | FG8: =(1+FH8)^(1/4)-1 -> 0.00077137564 | FH8: =+FC8 -> 0.0030890745 | FI8: =(1+FM8)^(1/4)-1 -> 0.00077137564 | FJ8: =(1+FM8)^(1/4)-1 -> 0.00077137564 | FK8: =(1+FM8)^(1/4)-1 -> 0.00077137564 | FL8: =(1+FM8)^(1/4)-1 -> 0.00077137564 | FM8: =+FH8 -> 0.0030890745 | FN8: =(1+FR8)^(1/4)-1 -> 0.00077137564 | FO8: =(1+FR8)^(1/4)-1 -> 0.00077137564 | FP8: =(1+FR8)^(1/4)-1 -> 0.00077137564 | FQ8: =(1+FR8)^(1/4)-1 -> 0.00077137564 | FR8: =+FM8 -> 0.0030890745 | FS8: =(1+FW8)^(1/4)-1 -> 0.00077137564 | FT8: =(1+FW8)^(1/4)-1 -> 0.00077137564 | FU8: =(1+FW8)^(1/4)-1 -> 0.00077137564 | FV8: =(1+FW8)^(1/4)-1 -> 0.00077137564 | FW8: =+FR8 -> 0.0030890745 | FX8: =(1+GB8)^(1/4)-1 -> 0.00077137564 | FY8: =(1+GB8)^(1/4)-1 -> 0.00077137564 | FZ8: =(1+GB8)^(1/4)-1 -> 0.00077137564 | GA8: =(1+GB8)^(1/4)-1 -> 0.00077137564 | GB8: =+FW8 -> 0.0030890745
A9: =A8+1 -> 5
A10: =A9+1 -> 6 | B10: Inflação
A11: =A10+1 -> 7 | B11: IGP-M | C11: 0.10372332 | D11: 0.25309713 | E11: 0.0626 | F11: -0.0035 | G11: 0.0114 | H11: 0.0149 | I11: 0.08691368 | J11: 0.0272 | K11: 0.0395 | L11: 0.0325 | M11: 0.0196 | N11: 0.12391424 | O11: 0.0155 | P11: 0.002 | Q11: -0.0152 | R11: 0.0099 | S11: 0.0121 | T11: 0.007 | U11: 0.0071 | V11: 0.0084 | W11: 0.0155 | X11: 0.0385 | Y11: 0.0111 | Z11: 0.0035 | AA11: 0.0257 | AB11: 0.0306 | AC11: 0.077509821 | AD11: 0.0238 | AE11: 0.0434 | AF11: 0.0155 | AG11: 0.0123 | AH11: 0.098054313 | AI11: -0.0092 | AJ11: -0.0032 | AK11: -0.0037 | AL11: -0.0011 | AM11: -0.017122754 | AN11: 0.0277 | AO11: 0.0284 | AP11: 0.020817483 | AQ11: 0.031817201 | AR11: 0.10873468 | AS11: 0.02429047 | AT11: 0.0070034752 | AU11: 0.0097154857 | AV11: 0.0091141082 | AW11: 0.050977446 | AX11: 0.0062066635 | AY11: 0.02265934 | AZ11: 0.007517012 | BA11: 0.010532022 | BB11: 0.047660685 | BC11: 0.011882369 | BD11: 0.010913642 | BE11: 0.007390953 | BF11: 0.013673825 | BG11: 0.045 | BH11: =(1+BL11)^(1/4)-1 -> 0.01106499 | BI11: =(1+BL11)^(1/4)-1 -> 0.01106499 | BJ11: =(1+BL11)^(1/4)-1 -> 0.01106499 | BK11: =(1+BL11)^(1/4)-1 -> 0.01106499 | BL11: 0.045 | BM11: =(1+BQ11)^(1/4)-1 -> 0.01106499 | BN11: =(1+BQ11)^(1/4)-1 -> 0.01106499 | BO11: =(1+BQ11)^(1/4)-1 -> 0.01106499 | BP11: =(1+BQ11)^(1/4)-1 -> 0.01106499 | BQ11: 0.045 | BR11: =(1+BV11)^(1/4)-1 -> 0.01106499 | BS11: =(1+BV11)^(1/4)-1 -> 0.01106499 | BT11: =(1+BV11)^(1/4)-1 -> 0.01106499 | BU11: =(1+BV11)^(1/4)-1 -> 0.01106499 | BV11: 0.045 | BW11: =(1+CA11)^(1/4)-1 -> 0.0098534065 | BX11: =(1+CA11)^(1/4)-1 -> 0.0098534065 | BY11: =(1+CA11)^(1/4)-1 -> 0.0098534065 | BZ11: =(1+CA11)^(1/4)-1 -> 0.0098534065 | CA11: 0.04 | CB11: =(1+CF11)^(1/4)-1 -> 0.0098534065 | CC11: =(1+CF11)^(1/4)-1 -> 0.0098534065 | CD11: =(1+CF11)^(1/4)-1 -> 0.0098534065 | CE11: =(1+CF11)^(1/4)-1 -> 0.0098534065 | CF11: 0.04 | CG11: =(1+CK11)^(1/4)-1 -> 0.0098534065 | CH11: =(1+CK11)^(1/4)-1 -> 0.0098534065 | CI11: =(1+CK11)^(1/4)-1 -> 0.0098534065 | CJ11: =(1+CK11)^(1/4)-1 -> 0.0098534065 | CK11: 0.04 | CL11: =(1+CP11)^(1/4)-1 -> 0.0098534065 | CM11: =(1+CP11)^(1/4)-1 -> 0.0098534065 | CN11: =(1+CP11)^(1/4)-1 -> 0.0098534065 | CO11: =(1+CP11)^(1/4)-1 -> 0.0098534065 | CP11: 0.04 | CQ11: =(1+CU11)^(1/4)-1 -> 0.0098534065 | CR11: =(1+CU11)^(1/4)-1 -> 0.0098534065 | CS11: =(1+CU11)^(1/4)-1 -> 0.0098534065 | CT11: =(1+CU11)^(1/4)-1 -> 0.0098534065 | CU11: 0.04 | CV11: =(1+CZ11)^(1/4)-1 -> 0.0098534065 | CW11: =(1+CZ11)^(1/4)-1 -> 0.0098534065 | CX11: =(1+CZ11)^(1/4)-1 -> 0.0098534065 | CY11: =(1+CZ11)^(1/4)-1 -> 0.0098534065 | CZ11: 0.04 | DA11: =(1+DE11)^(1/4)-1 -> 0.0098534065 | DB11: =(1+DE11)^(1/4)-1 -> 0.0098534065 | DC11: =(1+DE11)^(1/4)-1 -> 0.0098534065 | DD11: =(1+DE11)^(1/4)-1 -> 0.0098534065 | DE11: 0.04 | DF11: =(1+DJ11)^(1/4)-1 -> 0.0098534065 | DG11: =(1+DJ11)^(1/4)-1 -> 0.0098534065 | DH11: =(1+DJ11)^(1/4)-1 -> 0.0098534065 | DI11: =(1+DJ11)^(1/4)-1 -> 0.0098534065 | DJ11: 0.04 | DK11: =(1+DO11)^(1/4)-1 -> 0.008637446 | DL11: =(1+DO11)^(1/4)-1 -> 0.008637446 | DM11: =(1+DO11)^(1/4)-1 -> 0.008637446 | DN11: =(1+DO11)^(1/4)-1 -> 0.008637446 | DO11: 0.035 | DP11: =(1+DT11)^(1/4)-1 -> 0.008637446 | DQ11: =(1+DT11)^(1/4)-1 -> 0.008637446 | DR11: =(1+DT11)^(1/4)-1 -> 0.008637446 | DS11: =(1+DT11)^(1/4)-1 -> 0.008637446 | DT11: 0.035 | DU11: =(1+DY11)^(1/4)-1 -> 0.008637446 | DV11: =(1+DY11)^(1/4)-1 -> 0.008637446 | DW11: =(1+DY11)^(1/4)-1 -> 0.008637446 | DX11: =(1+DY11)^(1/4)-1 -> 0.008637446 | DY11: 0.035 | DZ11: =(1+ED11)^(1/4)-1 -> 0.008637446 | EA11: =(1+ED11)^(1/4)-1 -> 0.008637446 | EB11: =(1+ED11)^(1/4)-1 -> 0.008637446 | EC11: =(1+ED11)^(1/4)-1 -> 0.008637446 | ED11: 0.035 | EE11: =(1+EI11)^(1/4)-1 -> 0.008637446 | EF11: =(1+EI11)^(1/4)-1 -> 0.008637446 | EG11: =(1+EI11)^(1/4)-1 -> 0.008637446 | EH11: =(1+EI11)^(1/4)-1 -> 0.008637446 | EI11: 0.035 | EJ11: =(1+EN11)^(1/4)-1 -> 0.008637446 | EK11: =(1+EN11)^(1/4)-1 -> 0.008637446 | EL11: =(1+EN11)^(1/4)-1 -> 0.008637446 | EM11: =(1+EN11)^(1/4)-1 -> 0.008637446 | EN11: 0.035 | EO11: =(1+ES11)^(1/4)-1 -> 0.008637446 | EP11: =(1+ES11)^(1/4)-1 -> 0.008637446 | EQ11: =(1+ES11)^(1/4)-1 -> 0.008637446 | ER11: =(1+ES11)^(1/4)-1 -> 0.008637446 | ES11: =EN11 -> 0.035 | ET11: =(1+EX11)^(1/4)-1 -> 0.008637446 | EU11: =(1+EX11)^(1/4)-1 -> 0.008637446 | EV11: =(1+EX11)^(1/4)-1 -> 0.008637446 | EW11: =(1+EX11)^(1/4)-1 -> 0.008637446 | EX11: =ES11 -> 0.035 | EY11: =(1+FC11)^(1/4)-1 -> 0.008637446 | EZ11: =(1+FC11)^(1/4)-1 -> 0.008637446 | FA11: =(1+FC11)^(1/4)-1 -> 0.008637446 | FB11: =(1+FC11)^(1/4)-1 -> 0.008637446 | FC11: =EX11 -> 0.035 | FD11: =(1+FH11)^(1/4)-1 -> 0.008637446 | FE11: =(1+FH11)^(1/4)-1 -> 0.008637446 | FF11: =(1+FH11)^(1/4)-1 -> 0.008637446 | FG11: =(1+FH11)^(1/4)-1 -> 0.008637446 | FH11: =FC11 -> 0.035 | FI11: =(1+FM11)^(1/4)-1 -> 0.008637446 | FJ11: =(1+FM11)^(1/4)-1 -> 0.008637446 | FK11: =(1+FM11)^(1/4)-1 -> 0.008637446 | FL11: =(1+FM11)^(1/4)-1 -> 0.008637446 | FM11: =FH11 -> 0.035 | FN11: =(1+FR11)^(1/4)-1 -> 0.008637446 | FO11: =(1+FR11)^(1/4)-1 -> 0.008637446 | FP11: =(1+FR11)^(1/4)-1 -> 0.008637446 | FQ11: =(1+FR11)^(1/4)-1 -> 0.008637446 | FR11: =FM11 -> 0.035 | FS11: =(1+FW11)^(1/4)-1 -> 0.008637446 | FT11: =(1+FW11)^(1/4)-1 -> 0.008637446 | FU11: =(1+FW11)^(1/4)-1 -> 0.008637446 | FV11: =(1+FW11)^(1/4)-1 -> 0.008637446 | FW11: =FR11 -> 0.035 | FX11: =(1+GB11)^(1/4)-1 -> 0.008637446 | FY11: =(1+GB11)^(1/4)-1 -> 0.008637446 | FZ11: =(1+GB11)^(1/4)-1 -> 0.008637446 | GA11: =(1+GB11)^(1/4)-1 -> 0.008637446 | GB11: =FW11 -> 0.035
A12: =A11+1 -> 8 | B12: IPCA | C12: 0.07673263 | D12: 0.12530337 | E12: 0.0513 | F12: 0.0143 | G12: 0.0132 | H12: 0.0115 | I12: 0.092999493 | J12: 0.0185 | K12: 0.016 | L12: 0.0194 | M12: 0.02 | N12: 0.076006441 | O12: 0.0179 | P12: 0.0135 | Q12: 0.0077 | R12: 0.0167 | S12: 0.0569 | T12: 0.0144 | U12: 0.001 | V12: 0.0045 | W12: 0.0112 | X12: 0.0314 | Y12: 0.0126 | Z12: 0.0081 | AA12: 0.0089 | AB12: 0.0086 | AC12: 0.0446 | AD12: 0.0152 | AE12: 0.0209 | AF12: 0.0107 | AG12: 0.0109 | AH12: 0.059023134 | AI12: 0.0123 | AJ12: 0.0132 | AK12: 0.0063 | AL12: 0.0106 | AM12: 0.043120283 | AN12: 0.0206 | AO12: 0.01 | AP12: 0.0050022902 | AQ12: 0.022262182 | AR12: 0.057864472 | AS12: 0.024395695 | AT12: 0.013954844 | AU12: 0.010634041 | AV12: 0.014569972 | AW12: 0.06503109 | AX12: 0.012246463 | AY12: 0.012243007 | AZ12: 0.00660945 | BA12: 0.018411424 | BB12: 0.050401465 | BC12: 0.018753775 | BD12: 0.010674068 | BE12: 0.0089415416 | BF12: 0.021106668 | BG12: 0.060760819 | BH12: =(1+BL12)^(1/4)-1 -> 0.01106499 | BI12: =(1+BL12)^(1/4)-1 -> 0.01106499 | BJ12: =(1+BL12)^(1/4)-1 -> 0.01106499 | BK12: =(1+BL12)^(1/4)-1 -> 0.01106499 | BL12: 0.045 | BM12: =(1+BQ12)^(1/4)-1 -> 0.01106499 | BN12: =(1+BQ12)^(1/4)-1 -> 0.01106499 | BO12: =(1+BQ12)^(1/4)-1 -> 0.01106499 | BP12: =(1+BQ12)^(1/4)-1 -> 0.01106499 | BQ12: 0.045 | BR12: =(1+BV12)^(1/4)-1 -> 0.01106499 | BS12: =(1+BV12)^(1/4)-1 -> 0.01106499 | BT12: =(1+BV12)^(1/4)-1 -> 0.01106499 | BU12: =(1+BV12)^(1/4)-1 -> 0.01106499 | BV12: 0.045 | BW12: =(1+CA12)^(1/4)-1 -> 0.0098534065 | BX12: =(1+CA12)^(1/4)-1 -> 0.0098534065 | BY12: =(1+CA12)^(1/4)-1 -> 0.0098534065 | BZ12: =(1+CA12)^(1/4)-1 -> 0.0098534065 | CA12: 0.04 | CB12: =(1+CF12)^(1/4)-1 -> 0.0098534065 | CC12: =(1+CF12)^(1/4)-1 -> 0.0098534065 | CD12: =(1+CF12)^(1/4)-1 -> 0.0098534065 | CE12: =(1+CF12)^(1/4)-1 -> 0.0098534065 | CF12: 0.04 | CG12: =(1+CK12)^(1/4)-1 -> 0.0098534065 | CH12: =(1+CK12)^(1/4)-1 -> 0.0098534065 | CI12: =(1+CK12)^(1/4)-1 -> 0.0098534065 | CJ12: =(1+CK12)^(1/4)-1 -> 0.0098534065 | CK12: 0.04 | CL12: =(1+CP12)^(1/4)-1 -> 0.0098534065 | CM12: =(1+CP12)^(1/4)-1 -> 0.0098534065 | CN12: =(1+CP12)^(1/4)-1 -> 0.0098534065 | CO12: =(1+CP12)^(1/4)-1 -> 0.0098534065 | CP12: 0.04 | CQ12: =(1+CU12)^(1/4)-1 -> 0.0098534065 | CR12: =(1+CU12)^(1/4)-1 -> 0.0098534065 | CS12: =(1+CU12)^(1/4)-1 -> 0.0098534065 | CT12: =(1+CU12)^(1/4)-1 -> 0.0098534065 | CU12: 0.04 | CV12: =(1+CZ12)^(1/4)-1 -> 0.0098534065 | CW12: =(1+CZ12)^(1/4)-1 -> 0.0098534065 | CX12: =(1+CZ12)^(1/4)-1 -> 0.0098534065 | CY12: =(1+CZ12)^(1/4)-1 -> 0.0098534065 | CZ12: 0.04 | DA12: =(1+DE12)^(1/4)-1 -> 0.0098534065 | DB12: =(1+DE12)^(1/4)-1 -> 0.0098534065 | DC12: =(1+DE12)^(1/4)-1 -> 0.0098534065 | DD12: =(1+DE12)^(1/4)-1 -> 0.0098534065 | DE12: 0.04 | DF12: =(1+DJ12)^(1/4)-1 -> 0.0098534065 | DG12: =(1+DJ12)^(1/4)-1 -> 0.0098534065 | DH12: =(1+DJ12)^(1/4)-1 -> 0.0098534065 | DI12: =(1+DJ12)^(1/4)-1 -> 0.0098534065 | DJ12: 0.04 | DK12: =(1+DO12)^(1/4)-1 -> 0.008637446 | DL12: =(1+DO12)^(1/4)-1 -> 0.008637446 | DM12: =(1+DO12)^(1/4)-1 -> 0.008637446 | DN12: =(1+DO12)^(1/4)-1 -> 0.008637446 | DO12: 0.035 | DP12: =(1+DT12)^(1/4)-1 -> 0.008637446 | DQ12: =(1+DT12)^(1/4)-1 -> 0.008637446 | DR12: =(1+DT12)^(1/4)-1 -> 0.008637446 | DS12: =(1+DT12)^(1/4)-1 -> 0.008637446 | DT12: 0.035 | DU12: =(1+DY12)^(1/4)-1 -> 0.008637446 | DV12: =(1+DY12)^(1/4)-1 -> 0.008637446 | DW12: =(1+DY12)^(1/4)-1 -> 0.008637446 | DX12: =(1+DY12)^(1/4)-1 -> 0.008637446 | DY12: 0.035 | DZ12: =(1+ED12)^(1/4)-1 -> 0.008637446 | EA12: =(1+ED12)^(1/4)-1 -> 0.008637446 | EB12: =(1+ED12)^(1/4)-1 -> 0.008637446 | EC12: =(1+ED12)^(1/4)-1 -> 0.008637446 | ED12: 0.035 | EE12: =(1+EI12)^(1/4)-1 -> 0.008637446 | EF12: =(1+EI12)^(1/4)-1 -> 0.008637446 | EG12: =(1+EI12)^(1/4)-1 -> 0.008637446 | EH12: =(1+EI12)^(1/4)-1 -> 0.008637446 | EI12: 0.035 | EJ12: =(1+EN12)^(1/4)-1 -> 0.008637446 | EK12: =(1+EN12)^(1/4)-1 -> 0.008637446 | EL12: =(1+EN12)^(1/4)-1 -> 0.008637446 | EM12: =(1+EN12)^(1/4)-1 -> 0.008637446 | EN12: 0.035 | EO12: =(1+ES12)^(1/4)-1 -> 0.008637446 | EP12: =(1+ES12)^(1/4)-1 -> 0.008637446 | EQ12: =(1+ES12)^(1/4)-1 -> 0.008637446 | ER12: =(1+ES12)^(1/4)-1 -> 0.008637446 | ES12: =EN12 -> 0.035 | ET12: =(1+EX12)^(1/4)-1 -> 0.008637446 | EU12: =(1+EX12)^(1/4)-1 -> 0.008637446 | EV12: =(1+EX12)^(1/4)-1 -> 0.008637446 | EW12: =(1+EX12)^(1/4)-1 -> 0.008637446 | EX12: =ES12 -> 0.035 | EY12: =(1+FC12)^(1/4)-1 -> 0.008637446 | EZ12: =(1+FC12)^(1/4)-1 -> 0.008637446 | FA12: =(1+FC12)^(1/4)-1 -> 0.008637446 | FB12: =(1+FC12)^(1/4)-1 -> 0.008637446 | FC12: =EX12 -> 0.035 | FD12: =(1+FH12)^(1/4)-1 -> 0.008637446 | FE12: =(1+FH12)^(1/4)-1 -> 0.008637446 | FF12: =(1+FH12)^(1/4)-1 -> 0.008637446 | FG12: =(1+FH12)^(1/4)-1 -> 0.008637446 | FH12: =FC12 -> 0.035 | FI12: =(1+FM12)^(1/4)-1 -> 0.008637446 | FJ12: =(1+FM12)^(1/4)-1 -> 0.008637446 | FK12: =(1+FM12)^(1/4)-1 -> 0.008637446 | FL12: =(1+FM12)^(1/4)-1 -> 0.008637446 | FM12: =FH12 -> 0.035 | FN12: =(1+FR12)^(1/4)-1 -> 0.008637446 | FO12: =(1+FR12)^(1/4)-1 -> 0.008637446 | FP12: =(1+FR12)^(1/4)-1 -> 0.008637446 | FQ12: =(1+FR12)^(1/4)-1 -> 0.008637446 | FR12: =FM12 -> 0.035 | FS12: =(1+FW12)^(1/4)-1 -> 0.008637446 | FT12: =(1+FW12)^(1/4)-1 -> 0.008637446 | FU12: =(1+FW12)^(1/4)-1 -> 0.008637446 | FV12: =(1+FW12)^(1/4)-1 -> 0.008637446 | FW12: =FR12 -> 0.035 | FX12: =(1+GB12)^(1/4)-1 -> 0.008637446 | FY12: =(1+GB12)^(1/4)-1 -> 0.008637446 | FZ12: =(1+GB12)^(1/4)-1 -> 0.008637446 | GA12: =(1+GB12)^(1/4)-1 -> 0.008637446 | GB12: =FW12 -> 0.035
A13: =A12+1 -> 9
A14: =A13+1 -> 10 | B14: PIB
