Workbook

Sheet Tabelas
A1: SALÁRIO LÍQUIDO | I1: IRRF | N1: INSS | R1: INSS Patronal | U1: PIS
B2: Nº DEP | C2: SALÁRIO | D2: INSS | E2: IR | G2: SALÁRIO LÍQUIDO | I2: FAIXA SALARIAL | K2: ALÍQUOTA | L2: PARCELA A DEDUZIR | N2: FAIXA SALARIAL | P2: ALÍQUOTA | S2: ALÍQUOTA | U2: ALÍQUOTA
B3: 1 | C3: 1271 | D3: =IF(C3>=$O$5,$O$5*$P$5,C3*VLOOKUP(C3,$N$3:$P$5,3)) -> 101.68 | E3: =IF((C3-D3-B3*$L$8)<=0,0,(C3-D3-B3*$L$8)*VLOOKUP((C3-D3-B3*$L$8),$I$3:$L$7,3)-VLOOKUP((C3-D3-B3*$L$8),$I$3:$L$7,4)) -> 0 | G3: =SUM(C3-D3-E3-F3) -> 1169.32 | I3: 0 | J3: 1903.98 | K3: 0 | L3: 0 | N3: 0 | O3: 1693.72 | P3: 0.08 | R3: INSS Patronal | S3: 0 | U3: 0
I4: 1903.99 | J4: 2826.65 | K4: 0.075 | L4: 142.8 | N4: 1693.73 | O4: 2822.9 | P4: 0.09 | R4: RAT x FAP | S4: 0
I5: 2826.66 | J5: 3751.05 | K5: 0.15 | L5: 354.8 | N5: 2822.91 | O5: 5645.8 | P5: 0.11 | R5: Outras Entidades | S5: 0
I6: 3751.06 | J6: 4664.68 | K6: 0.225 | L6: 636.13 | S6: =SUM(S3:S5) -> 0
I7: 4664.69 | K7: 0.275 | L7: 869.36
I8: DEPENDENTE | L8: 189.59

Sheet  Func. Condominio
B2: Calculo Mensal Funcionário
B4: EMPRESA / FUNCIONÁRIO
B6: Despesa Mensal
B7: Salário Bruto | C7: =Tabelas!C3 -> 1271
B8: FGTS - 8,0% | C8: =C7*8% -> 101.68
B9: INSS Patronal | C9: =Tabelas!S6*' Func. Condominio'!C7 -> 0
B10: INSS Descontado do funcionário | C10: =Tabelas!D3 -> 101.68
B11: IRRF | C11: =Tabelas!E3 -> 0
B12: PIS | C12: =Tabelas!U3*' Func. Condominio'!C7 -> 0
B13: Salário líquido pago ao funcionário | C13: =C7-C10-C11+C14 -> 1169.32
B14: Ajuda de Custo ( Combustivel, alimentação etc) | D14: (Pode alterar)
B15: Total | C15: =SUM(C8:C14) -> 1372.68
B17: Poupança Mensal
B18: 13º Salário - 01/12 Avos | C18: =C7/12 -> 105.91667
B19: PIS S/ 13º Salário | C19: =Tabelas!U3*' Func. Condominio'!C18 -> 0
B20: Salário Substituição de Férias - 01/12 Avos | C20: =C7/12 -> 105.91667
B21: PIS S/ Substituição de Férias | C21: =Tabelas!U3*' Func. Condominio'!C20 -> 0
B22: FGTS S/ Substituição de Férias | C22: =C20*8% -> 8.4733333
B23: FGTS S/ 13º Salário - 8,0% | C23: =C18*8% -> 8.4733333
B24: Férias - 01/12 Avos | C24: =C7/12 -> 105.91667
B25: 1/3 De Férias | C25: =C24/3 -> 35.305556
B26: PIS S/ Férias | C26: =(C24+C25)*Tabelas!U3 -> 0
B27: FGTS S/ Férias - 8,0% | C27: =(C24+C25)*8% -> 11.297778
B28: Aviso Previo Indenizado | C28: =C7/12 -> 105.91667
B29: FGTS s/ Aviso Indenizado | C29: =C28*8% -> 8.4733333
B30: Multa FGTS - 50% | C30: =(C8+C22+C27+C29+C23)*50% -> 69.198889
B31: INSS Patronal | C31: =(C18+C20+C24+C25)*Tabelas!S6 -> 0
B32: Total | C32: =SUM(C18:C31) -> 564.88889
B34: Total Geral | C34: =C15+C32 -> 1937.5689
B36: Obs.: O quadro da Despensa Mensal serão os custos mensais desembolsados pela empresa.
B37: O quadro de Poupança Mensal são as despesas que incorrem todos os meses na qual orientamos
B38: a empresa a fazer uma provisão e depositar mensalmente em uma poupança no Banco.

Sheet MEI
B2: Calculo Mensal Funcionário
B4: EMPRESA / FUNCIONÁRIO
B6: Despesa Mensal
B7: Salário Bruto | C7: =Tabelas!C3 -> 1271
B8: FGTS - 8,0% | C8: =C7*8% -> 101.68
B9: INSS Patronal | C9: =C7*3% -> 38.13
B10: INSS Descontado do funcionário | C10: =Tabelas!D3 -> 101.68
B11: IRRF | C11: =Tabelas!E3 -> 0
B12: Salário líquido pago ao funcionário | C12: =C7-C10-C11+C13 -> 1169.32
B13: Ajuda de Custo ( Combustivel, alimentação etc) | D13: (Pode alterar)
B14: Total | C14: =SUM(C8:C13) -> 1410.81
B16: Poupança Mensal
B17: 13º Salário - 01/12 Avos | C17: =C7/12 -> 105.91667
B18: FGTS S/ 13º Salário - 8,0% | C18: =C17*8% -> 8.4733333
B19: Férias - 01/12 Avos | C19: =C7/12 -> 105.91667
B20: 1/3 De Férias | C20: =C19/3 -> 35.305556
B21: FGTS S/ Férias - 8,0% | C21: =(C19+C20)*8% -> 11.297778
B22: Aviso Previo Indenizado | C22: =C7/12 -> 105.91667
B23: FGTS s/ Aviso Indenizado | C23: =C22*8% -> 8.4733333
B24: Multa FGTS - 50% | C24: =(C8+C21+C23+C18)*50% -> 64.962222
B25: INSS Patronal | C25: =(C17+C19+C20)*Tabelas!S6 -> 0
B26: Total | C26: =SUM(C17:C25) -> 446.26222
B28: Total Geral | C28: =C14+C26 -> 1857.0722
B30: Obs.: O quadro da Despensa Mensal serão os custos mensais desembolsados pela empresa.
B31: O quadro de Poupança Mensal são as despesas que incorrem todos os meses na qual orientamos
B32: a empresa a fazer uma provisão e depositar mensalmente em uma poupança no Banco.

Sheet Domestico
B2: Calculo Mensal Funcionário
B4: EMPRESA / FUNCIONÁRIO
B6: Despesa Mensal
B7: Salário Bruto | C7: =Tabelas!C3 -> 1271
B8: FGTS - 8,0% | C8: =C7*8% -> 101.68
B9: INSS Patronal | C9: =C7*8% -> 101.68
B10: INSS Descontado do funcionário | C10: =Tabelas!D3 -> 101.68
B11: RAT + MULTA FGTS | C11: =C8*4% -> 4.0672
B12: IR | C12: =Tabelas!E3 -> 0
B13: Salário líquido pago ao funcionário | C13: =C7-C10-C12 -> 1169.32
B14: Ajuda de Custo ( Combustivel, alimentação etc) | C14: 400 | D14: (Pode alterar)
B15: Total | C15: =SUM(C8:C14) -> 1878.4272
B17: Poupança Mensal
B18: 13º Salário - 01/12 Avos | C18: =C7/12 -> 105.91667
B19: FGTS S/ 13º Salário - 8,0% | C19: =C18*20% -> 21.183333
B20: Férias - 01/12 Avos | C20: =C7/12 -> 105.91667
B21: 1/3 De Férias | C21: =C20/3 -> 35.305556
B22: PIS S/ Férias | C22: 0
B23: FGTS S/ Férias - 8,0% | C23: =(C20+C21)*20% -> 28.244444
B24: Aviso Previo Indenizado | C24: =C7/12 -> 105.91667
B25: FGTS s/ Aviso Indenizado | C25: =C24*20% -> 21.183333
B26: Multa FGTS - 50% | C26: 0
B27: INSS Patronal | C27: 0
B28: Total | C28: =SUM(C18:C27) -> 423.66667
B32: Obs.: O quadro da Despensa Mensal serão os custos mensais desembolsados pela empresa.
B33: O quadro de Poupança Mensal são as despesas que incorrem todos os meses na qual orientamos
B34: a empresa a fazer uma provisão e depositar mensalmente em uma poupança no Banco.

Sheet Simples Anexo I,II,III,V,VI
B2: Calculo Mensal Funcionário
B4: EMPRESA / FUNCIONÁRIO
B6: Despesa Mensal
B7: Salário Bruto | C7: =Tabelas!C3 -> 1271
B8: FGTS - 8,0% | C8: =C7*8% -> 101.68
B9: INSS Patronal | C9: 0
B10: INSS Descontado do funcionário | C10: =Tabelas!D3 -> 101.68 | G10: Simples nacional
B11: IRRF | C11: =Tabelas!E3 -> 0 | G11: Tabelas
B12: PIS | G12: Anexos | I12: INSS Patronal
B13: Salário líquido pago ao funcionário | C13: =C7-C10-C11+C14 -> 1169.32 | G13: Industria | H13: I | I13: 0
B14: Ajuda de Custo ( Combustivel, alimentação etc) | D14: (Pode alterar) | G14: comercio | H14: II | I14: 0
B15: Total | C15: =SUM(C8:C14) -> 1372.68 | D15: 4190.4 | E15: =D15-C15 -> 2817.72 | G15: serviços simplificiados | H15: III | I15: 0
G16: Mão de obra | H16: IV | I16: 0.2
B17: Poupança Mensal | G17: Serviços profisioanis | H17: V | I17: 0
B18: 13º Salário - 01/12 Avos | C18: =C7/12 -> 105.91667 | G18: Serviços profissionais | H18: VI
B19: FGTS S/ 13º Salário - 8,0% | C19: =C18*8% -> 8.4733333
B20: Férias - 01/12 Avos | C20: =C7/12 -> 105.91667
B21: 1/3 De Férias | C21: =C20/3 -> 35.305556
B22: FGTS S/ Férias - 8,0% | C22: =(C20+C21)*8% -> 11.297778
B23: Aviso Previo Indenizado | C23: =C7/12 -> 105.91667
B24: FGTS s/ Aviso Indenizado | C24: =C23*8% -> 8.4733333
B25: Multa FGTS - 50% | C25: =(C8+C22+C24+C19)*50% -> 64.962222
B26: INSS Patronal
B27: Total | C27: =SUM(C18:C26) -> 446.26222
B31: Obs.: O quadro da Despensa Mensal serão os custos mensais desembolsados pela empresa.
B32: O quadro de Poupança Mensal são as despesas que incorrem todos os meses na qual orientamos
B33: a empresa a fazer uma provisão e depositar mensalmente em uma poupança no Banco.

Sheet Simples Anexo IV,
B2: Calculo Mensal Funcionário
B4: EMPRESA / FUNCIONÁRIO
B6: Despesa Mensal
B7: Salário Bruto | C7: =Tabelas!C3 -> 1271
B8: FGTS - 8,0% | C8: =C7*8% -> 101.68
B9: INSS Patronal | C9: =C7*21% -> 266.91
B10: INSS Descontado do funcionário | C10: =Tabelas!D3 -> 101.68 | G10: Simples nacional
B11: IRRF | C11: =Tabelas!E3 -> 0 | G11: Tabelas
B12: PIS | G12: Anexos | I12: INSS Patronal
B13: Salário líquido pago ao funcionário | C13: =C7-C10-C11+C14 -> 1169.32 | G13: Industria | H13: I | I13: 0
B14: Ajuda de Custo ( Combustivel, alimentação etc) | D14: (Pode alterar) | G14: comercio | H14: II | I14: 0
B15: Total | C15: =SUM(C8:C14) -> 1639.59 | D15: 4190.4 | E15: =D15-C15 -> 2550.81 | G15: serviços simplificiados | H15: III | I15: 0
G16: Mão de obra | H16: IV | I16: 0.2
B17: Poupança Mensal | G17: Serviços profisioanis | H17: V | I17: 0
B18: 13º Salário - 01/12 Avos | C18: =C7/12 -> 105.91667 | G18: Serviços profissionais | H18: VI
B19: FGTS S/ 13º Salário - 8,0% | C19: =C18*8% -> 8.4733333
B20: Férias - 01/12 Avos | C20: =C7/12 -> 105.91667
B21: 1/3 De Férias | C21: =C20/3 -> 35.305556
B22: FGTS S/ Férias - 8,0% | C22: =(C20+C21)*8% -> 11.297778
B23: Aviso Previo Indenizado | C23: =C7/12 -> 105.91667
B24: FGTS s/ Aviso Indenizado | C24: =C23*8% -> 8.4733333
B25: Multa FGTS - 50% | C25: =(C8+C22+C24+C19)*50% -> 64.962222
B26: INSS Patronal | C26: =(C18+C20+C21+C23)*21% -> 74.141667
B27: Total | C27: =SUM(C18:C26) -> 520.40389
B29: TOTAL MENSAL | C29: =C15+C27 -> 2159.9939
B31: Obs.: O quadro da Despensa Mensal serão os custos mensais desembolsados pela empresa.
B32: O quadro de Poupança Mensal são as despesas que incorrem todos os meses na qual orientamos
B33: a empresa a fazer uma provisão e depositar mensalmente em uma poupança no Banco.

Sheet Autonomo ou Liberal
B2: Calculo Mensal Funcionário
B4: EMPRESA / FUNCIONÁRIO | D4: Cód. 2208
B6: Despesa Mensal | D6: 20% empresa
B7: Salário Bruto | C7: =Tabelas!C3 -> 1271 | D7: 5,8% Outras Entidades
B8: FGTS - 8,0% | C8: =C7*8% -> 101.68 | D8: RAT de 1% a 3%
B9: INSS Patronal | C9: =Tabelas!S6*C7 -> 0
B10: INSS Descontado do funcionário | C10: =Tabelas!D3 -> 101.68
B11: IRRF | C11: =Tabelas!E3 -> 0
B12: Salário líquido pago ao funcionário | C12: =C7-C10-C11+C13 -> 1169.32
B13: Ajuda de Custo ( Combustivel, alimentação etc) | D13: (Pode alterar)
B14: Total | C14: =SUM(C8:C13) -> 1372.68
B16: Poupança Mensal
B17: 13º Salário - 01/12 Avos | C17: =C7/12 -> 105.91667
B18: FGTS S/ 13º Salário - 8,0% | C18: =C17*8% -> 8.4733333
B19: Férias - 01/12 Avos | C19: =C7/12 -> 105.91667
B20: 1/3 De Férias | C20: =C19/3 -> 35.305556
B21: FGTS S/ Férias - 8,0% | C21: =(C19+C20)*8% -> 11.297778
B22: Aviso Previo Indenizado | C22: =C7/12 -> 105.91667
B23: FGTS s/ Aviso Indenizado | C23: =C22*8% -> 8.4733333
B24: Multa FGTS - 50% | C24: =(C8+C21+C23+C18)*50% -> 64.962222
B25: INSS Patronal | C25: =(C17+C19+C20)*Tabelas!S6 -> 0
B26: Total | C26: =SUM(C17:C25) -> 446.26222
B28: Total Geral | C28: =C14+C26 -> 1818.9422
B30: Obs.: O quadro da Despensa Mensal serão os custos mensais desembolsados pela empresa.
B31: O quadro de Poupança Mensal são as despesas que incorrem todos os meses na qual orientamos
B32: a empresa a fazer uma provisão e depositar mensalmente em uma poupança no Banco.
