Workbook
Name _1macro_goto_.Contents: [1]!'[macro-goto].Contents'
Name _1macro_goto_.Contents: [1]!'[macro-goto].Contents'
Name _1macro_goto_.Contents: [1]!'[macro-goto].Contents'
Name _2macro: [1]!'[macro-goto].Contents'
Name _2macro: [1]!'[macro-goto].Contents'
Name _2macro: [1]!'[macro-goto].Contents'
Name area_de_impressaoEST: '[2]BCB IE1-51'!#REF!
Name area_de_impressaoEST: '[2]BCB IE1-51'!#REF!
Name area_de_impressaoEST: '[2]BCB IE1-51'!#REF!
Name area_de_impressaoEST: '[3]BCB IE1-51'!#REF!
Name area_de_impressaoEST: '[2]BCB IE1-51'!#REF!
Name PrintAsia: [4]!PrintAsia
Name PrintAsia: [4]!PrintAsia
Name PrintAsia: [4]!PrintAsia
Name PrintAsia: [5]!PrintAsia
Name PrintAsia: [4]!PrintAsia
Name PrintInterestRates: [1]!PrintInterestRates
Name PrintInterestRates: [1]!PrintInterestRates
Name PrintInterestRates: [1]!PrintInterestRates
Name PrintInterestRates: [1]!PrintInterestRates

Sheet AGPar
A1: AG Participações
C2: IFRS | D2: IFRS | E2: IFRS | F2: IFRS | G2: IFRS | H2: IFRS
A3: R$ mm | C3: 2008 | D3: 2009 | E3: 2010 | F3: 1T11 | G3: 2T11 | H3: 3T11 | I3: 4T11 | J3: 2011 | K3: 2012E | L3: 2013E | M3: 2014E | N3: 2015E | O3: 2016E | P3: 2017E | Q3: 2018E | R3: 2019E | S3: 2020E | T3: 2021E | U3: 2022E
A5: Ativo | C5: =+C7+C13+C15 -> 1243.085 | D5: =+D7+D13+D15 -> 2055.051 | E5: =+E7+E13+E15 -> 1573.022 | F5: =+F7+F13+F15 -> 1597.283 | G5: =+G7+G13+G15 -> 1655.57 | H5: =+H7+H13+H15 -> 1856.969 | I5: =+I7+I13+I15 -> 1999.053 | J5: =I5 -> 1999.053 | K5: =+K7+K13+K15 -> 3141.4371 | L5: =+L7+L13+L15 -> 3841.7907 | M5: =+M7+M13+M15 -> 4268.7343 | N5: =+N7+N13+N15 -> 4787.164 | O5: =+O7+O13+O15 -> 4975.0512 | P5: =+P7+P13+P15 -> 5249.4087 | Q5: =+Q7+Q13+Q15 -> 5523.6451 | R5: =+R7+R13+R15 -> 6070.6965 | ... U5: =+U7+U13+U15 -> 7229.4237
A7: Ativo Circulante | C7: =+SUM(C8:C11) -> 73.536 | D7: =+SUM(D8:D11) -> 88.08 | E7: =+SUM(E8:E11) -> 54.587 | F7: =+SUM(F8:F11) -> 24.005 | G7: =+SUM(G8:G11) -> 10.574 | H7: =+SUM(H8:H11) -> 4.966 | I7: =+SUM(I8:I11) -> 28.46 | J7: =I7 -> 28.46 | K7: =+SUM(K8:K12) -> 368.87695 | L7: =+SUM(L8:L12) -> 356.54272 | M7: =+SUM(M8:M12) -> 420.86139 | N7: =+SUM(N8:N12) -> 588.19996 | O7: =+SUM(O8:O12) -> 386.93272 | P7: =+SUM(P8:P12) -> 237.7532 | Q7: =+SUM(Q8:Q12) -> 50.733777 | R7: =+SUM(R8:R12) -> 65.457151 | ... U7: =+SUM(U8:U12) -> 64.644889
A8: Caixa | C8: =0.063+27.997 -> 28.06 | D8: =0.081+63.391 -> 63.472 | E8: 30.927 | F8: 0.277 | G8: 5.5 | H8: =1.581 -> 1.581 | I8: 11.592 | J8: =I8 -> 11.592 | K8: =J8+K107 -> 32.008952 | L8: =K8+L107 -> 19.674718 | M8: =L8+M107 -> 83.993392 | N8: =M8+N107 -> 251.33196 | O8: =N8+O107 -> 210.06472 | P8: =O8+P107 -> 220.8852 | Q8: =P8+Q107 -> 33.865777 | R8: =Q8+R107 -> 48.589151 | ... U8: =T8+U107 -> 47.776889
A9: Tributos a Recuperar | C9: 2.276 | D9: 2.971 | E9: 3.776 | F9: 3.844 | G9: 3.865 | H9: 3.385 | I9: 3.385 | J9: =I9 -> 3.385 | K9: =J9 -> 3.385 | L9: =K9 -> 3.385 | M9: =L9 -> 3.385 | N9: =M9 -> 3.385 | O9: =N9 -> 3.385 | P9: =O9 -> 3.385 | Q9: =P9 -> 3.385 | ... U9: =T9 -> 3.385
A10: Dividendos e JCP a receber | C10: 43.2 | D10: 21.637 | E10: 19.884 | F10: 19.884 | G10: 0 | H10: 0 | I10: 13.483 | J10: =I10 -> 13.483 | K10: =J10 -> 13.483 | L10: =K10 -> 13.483 | M10: =L10 -> 13.483 | N10: =M10 -> 13.483 | O10: =N10 -> 13.483 | P10: =O10 -> 13.483 | Q10: =P10 -> 13.483 | ... U10: =T10 -> 13.483
A11: Mútuos a Receber | C11: =73.536-SUM(C8:C10) -> 0 | D11: =88.08-SUM(D8:D10) -> 0 | E11: =54.587-SUM(E8:E10) -> 0 | F11: =24.005-SUM(F8:F10) -> 0 | G11: 1.209 | H11: =4.966-SUM(H8:H10) -> 0 | I11: 0 | J11: =I11 -> 0 | K11: =J11-K100 -> 320 | L11: =K11-L100 -> 320 | M11: =L11-M100 -> 320 | N11: =M11-N100 -> 320 | O11: =N11-O100 -> 160 | P11: =O11-P100 -> 0 | Q11: =P11-Q100 -> 0 | R11: =Q11-R100 -> 0 | ... U11: =T11-U100 -> 0
A13: Realizável Longo Prazo | C13: 123.397 | D13: 510.56 | E13: 19.704 | F13: 19.704 | G13: 1.175 | H13: 1.175 | I13: 1.175 | J13: =I13 -> 1.175 | K13: =J13 -> 1.175 | L13: =K13 -> 1.175 | M13: =L13 -> 1.175 | N13: =M13 -> 1.175 | O13: =N13 -> 1.175 | P13: =O13 -> 1.175 | Q13: =P13 -> 1.175 | ... U13: =T13 -> 1.175
A15: Ativos Fixos | C15: =SUM(C16:C18) -> 1046.152 | D15: =SUM(D16:D18) -> 1456.411 | E15: =SUM(E16:E18) -> 1498.731 | F15: =SUM(F16:F18) -> 1553.574 | G15: =SUM(G16:G18) -> 1643.821 | H15: =SUM(H16:H18) -> 1850.828 | I15: =SUM(I16:I18) -> 1969.418 | J15: =I15 -> 1969.418 | K15: =J15+K73-K87+K51 -> 2771.3851 | L15: =K15+L73-L87+L51 -> 3484.073 | M15: =L15+M73-M87+M51 -> 3846.6979 | N15: =M15+N73-N87+N51 -> 4197.789 | O15: =N15+O73-O87+O51 -> 4586.9435 | P15: =O15+P73-P87+P51 -> 5010.4805 | Q15: =P15+Q73-Q87+Q51 -> 5471.7363 | R15: =Q15+R73-R87+R51 -> 6004.0644 | ... U15: =T15+U73-U87+U51 -> 7163.6038
A16: Investimentos | C16: 1046.152 | D16: 1456.411 | E16: 1498.731 | F16: 1553.574 | G16: 1643.821 | H16: 1850.828 | I16: 1969.418 | J16: =I16 -> 1969.418
A17: Imobilizado
A18: Intangível
A20: Exigível de Curto Prazo | C20: =+SUM(C21:C24) -> 140.214 | D20: =+SUM(D21:D24) -> 263.411 | E20: =+SUM(E21:E24) -> 114.324 | F20: =+SUM(F21:F24) -> 126.672 | G20: =+SUM(G21:G24) -> 114.237 | H20: =+SUM(H21:H24) -> 116.906 | I20: =+SUM(I21:I24) -> 117.243 | J20: =I20 -> 117.243 | K20: =+SUM(K21:K24) -> 77.047 | L20: =+SUM(L21:L24) -> 43.737829 | M20: =+SUM(M21:M24) -> 43.737829 | N20: =+SUM(N21:N24) -> 443.73783 | O20: =+SUM(O21:O24) -> 443.73783 | P20: =+SUM(P21:P24) -> 471.31301 | Q20: =+SUM(Q21:Q24) -> 185.17305 | R20: =+SUM(R21:R24) -> 205.07728 | ... U20: =+SUM(U21:U24) -> 34.6
A21: Dívida CP | C21: 139.039 | D21: 145.347 | E21: 40.402 | F21: 52.371 | G21: 40.375 | H21: 42.895 | I21: 40.196 | J21: =I21 -> 40.196 | K21: =L117 -> 42.447 | L21: =M117 -> 9.1378286 | M21: =N117 -> 9.1378286 | N21: =O117 -> 409.13783 | O21: =P117 -> 409.13783 | P21: =Q117 -> 436.71301 | Q21: =R117 -> 150.57305 | R21: =S117 -> 170.47728 | ... U21: =V117 -> 0
A22: Obrigações Fiscais | C22: 0.002 | D22: 0.001 | E22: 0.054 | F22: 0.005 | G22: 0.003 | H22: 0.15 | I22: 0.186 | J22: =I22 -> 0.186 | K22: =J22 -> 0.186 | L22: =K22 -> 0.186 | M22: =L22 -> 0.186 | N22: =M22 -> 0.186 | O22: =N22 -> 0.186 | P22: =O22 -> 0.186 | Q22: =P22 -> 0.186 | ... U22: =T22 -> 0.186
A23: Dividendos e JCP a pagar | C23: 1.173 | D23: 118.058 | E23: 73.859 | F23: 73.859 | G23: 73.859 | H23: 73.859 | I23: 34.414 | J23: =I23 -> 34.414 | K23: =J23 -> 34.414 | L23: =K23 -> 34.414 | M23: =L23 -> 34.414 | N23: =M23 -> 34.414 | O23: =N23 -> 34.414 | P23: =O23 -> 34.414 | Q23: =P23 -> 34.414 | ... U23: =T23 -> 34.414
A24: Outros | C24: =140.214-SUM(C21:C23) -> 0 | D24: =263.411-SUM(D21:D23) -> 0.005 | E24: =114.324-SUM(E21:E23) -> 0.009 | F24: =0.428+0.009 -> 0.437 | G24: =114.237-SUM(G21:G23) -> 0 | H24: =116.906-SUM(H21:H23) -> 0.002 | I24: 42.447 | J24: =I24 -> 42.447 | K24: 0 | L24: 0 | M24: 0 | N24: 0 | O24: 0 | P24: 0 | Q24: 0 | R24: 0 | S24: 0 | T24: 0 | U24: 0
A26: Passivo Não Circulante | C26: =+SUM(C27:C30) -> 121.724 | D26: =+SUM(D27:D30) -> 571.803 | E26: =+SUM(E27:E30) -> 43.533 | F26: =+SUM(F27:F30) -> 43.537 | G26: =+SUM(G27:G30) -> 87.504 | H26: =+SUM(H27:H30) -> 267.242 | I26: =+SUM(I27:I30) -> 205.691 | J26: =I26 -> 205.691 | K26: =+SUM(K27:K30) -> 963.244 | L26: =+SUM(L27:L30) -> 1381.6814 | M26: =+SUM(M27:M30) -> 1513.9788 | N26: =+SUM(N27:N30) -> 1266.1804 | O26: =+SUM(O27:O30) -> 1036.3732 | P26: =+SUM(P27:P30) -> 799.57221 | Q26: =+SUM(Q27:Q30) -> 845.67358 | R26: =+SUM(R27:R30) -> 864.91546 | ... U26: =+SUM(U27:U30) -> 1181.35
A27: Dívida LP | C27: 120 | D27: 80 | E27: 40.004 | F27: 40.008 | G27: 40.008 | H27: 40.008 | I27: 159.912 | J27: =I27 -> 159.912 | K27: =K79-K21 -> 961.54 | L27: =L79-L21 -> 1379.9774 | M27: =M79-M21 -> 1512.2748 | N27: =N79-N21 -> 1264.4764 | O27: =O79-O21 -> 1034.6692 | P27: =P79-P21 -> 797.86821 | Q27: =Q79-Q21 -> 843.96958 | R27: =R79-R21 -> 863.21146 | ... U27: =U79-U21 -> 1179.646
A28: Passivos com Partes Relacionadas | C28: 1.724 | D28: 477.46 | E28: 1.607 | F28: 1.607 | G28: 1.607 | H28: 84.258 | I28: 44.075 | J28: =I28 -> 44.075 | K28: 0 | L28: 0 | M28: 0 | N28: 0 | O28: 0 | P28: 0 | Q28: 0 | R28: 0 | S28: 0 | T28: 0 | U28: 0
A29: AFAC | D29: 0 | E29: 0 | F29: 0 | G29: 43.967 | H29: 141.236 | I29: 0 | J29: =I29 -> 0 | K29: =J29 -> 0 | L29: =K29 -> 0 | M29: =L29 -> 0 | N29: =M29 -> 0 | O29: =N29 -> 0 | P29: =O29 -> 0 | Q29: =P29 -> 0 | ... U29: =T29 -> 0
A30: Outros | D30: =571.803-SUM(D27:D29) -> 14.343 | E30: =43.533-SUM(E27:E29) -> 1.922 | F30: 1.922 | G30: 1.922 | H30: =267.242-SUM(H27:H29) -> 1.74 | I30: 1.704 | J30: =I30 -> 1.704 | K30: =J30 -> 1.704 | L30: =K30 -> 1.704 | M30: =L30 -> 1.704 | N30: =M30 -> 1.704 | O30: =N30 -> 1.704 | P30: =O30 -> 1.704 | Q30: =P30 -> 1.704 | ... U30: =T30 -> 1.704
A32: Patrimônio Líquido | C32: 981.147 | D32: 1219.837 | E32: 1415.165 | F32: 1427.074 | G32: 1453.829 | H32: 1472.821 | I32: 1676.119 | J32: =I32 -> 1676.119 | K32: =J32+K66+K99+K103 -> 2101.1461 | L32: =K32+L66+L99+L103 -> 2416.3715 | M32: =L32+M66+M99+M103 -> 2711.0177 | N32: =M32+N66+N99+N103 -> 3077.2458 | O32: =N32+O66+O99+O103 -> 3494.9402 | P32: =O32+P66+P99+P103 -> 3978.5234 | Q32: =P32+Q66+Q99+Q103 -> 4492.7985 | R32: =Q32+R66+R99+R103 -> 5000.7038 | ... U32: =T32+U66+U99+U103 -> 6013.4737
A34: Passivo | C34: =C32+C26+C20 -> 1243.085 | D34: =D32+D26+D20 -> 2055.051 | E34: =E32+E26+E20 -> 1573.022 | F34: =F32+F26+F20 -> 1597.283 | G34: =G32+G26+G20 -> 1655.57 | H34: =H32+H26+H20 -> 1856.969 | I34: =I32+I26+I20 -> 1999.053 | J34: =I34 -> 1999.053 | K34: =K32+K26+K20 -> 3141.4371 | L34: =L32+L26+L20 -> 3841.7907 | M34: =M32+M26+M20 -> 4268.7343 | N34: =N32+N26+N20 -> 4787.164 | O34: =O32+O26+O20 -> 4975.0512 | P34: =P32+P26+P20 -> 5249.4087 | Q34: =Q32+Q26+Q20 -> 5523.6451 | R34: =R32+R26+R20 -> 6070.6965 | ... U34: =U32+U26+U20 -> 7229.4237
A36: Check | C36: =C5-C34 -> 0 | D36: =D5-D34 -> 0 | E36: =E5-E34 -> 0 | F36: =F5-F34 -> 0 | G36: =G5-G34 -> 0 | H36: =H5-H34 -> 0 | I36: =I5-I34 -> 0 | J36: =J5-J34 -> 0 | ... U36: =U5-U34 -> 0
C38: LS | D38: IFRS | E38: IFRS | F38: IFRS | G38: IFRS | H38: IFRS
A39: DRE (R$mm) | C39: =C3 -> 2008 | D39: =D3 -> 2009 | E39: =E3 -> 2010 | F39: =F3 -> 1T11 | G39: =G3 -> 2T11 | H39: =H3 -> 3T11 | I39: =I3 -> 4T11 | J39: =J3 -> 2011 | ... U39: =U3 -> 2022E
A40: Receita Bruta
A42: Deduções
A44: Receita Líquida
A46: CPV
A48: Lucro Bruto
A50: G&A | C50: -1.741 | D50: -2.652 | E50: -2.847 | F50: -0.326 | G50: -0.28 | H50: -0.143 | J50: -2.74 | K50: =J50*(1+(Cenário!W9/100)) -> -2.88248 | L50: =K50*(1+(Cenário!X9/100)) -> -3.0352514 | M50: =L50*(1+(Cenário!Y9/100)) -> -3.187014 | N50: =M50*(1+(Cenário!Z9/100)) -> -3.3463647 | O50: =N50*(1+(Cenário!AA9/100)) -> -3.4969511 | P50: =O50*(1+(Cenário!AB9/100)) -> -3.6543139 | Q50: =P50*(1+(Cenário!AC9/100)) -> -3.8187581 | R50: =Q50*(1+(Cenário!AD9/100)) -> -3.9906022 | ... U50: =T50*(1+(Cenário!AG9/100)) -> -4.55394
A51: Equivalência Patrimonial | C51: 104.657 | D51: 528.805 | E51: 529.116 | F51: 14.861 | G51: 35.436 | H51: 86.768 | J51: 263.525 | K51: ='AG Concessões'!G65*0.85 -> 515.2969 | L51: ='AG Concessões'!H65*0.85 -> 563.73798 | M51: ='AG Concessões'!I65*0.85 -> 626.92542 | N51: ='AG Concessões'!J65*0.85 -> 709.62323 | O51: ='AG Concessões'!K65*0.85 -> 787.66712 | P51: ='AG Concessões'!L65*0.85 -> 867.78583 | Q51: ='AG Concessões'!M65*0.85 -> 952.94193 | R51: ='AG Concessões'!N65*0.85 -> 1074.3828 | ... U51: ='AG Concessões'!Q65*0.85 -> 1165.1601
A52: Outras Receitas Operacionais | D52: =0.286+0.113 -> 0.399 | E52: 34.859 | F52: 0 | G52: 0.979 | H52: 0 | J52: 0.89 | K52: 1 | L52: =K52 -> 1 | M52: =L52 -> 1 | N52: =M52 -> 1 | O52: =N52 -> 1 | P52: =O52 -> 1 | Q52: =P52 -> 1 | R52: =Q52 -> 1 | S52: =R52 -> 1 | ... U52: =T52 -> 1
A53: Outras Despesas Operacionais | C53: -65.865 | D53: -8.605 | E53: -237.663 | F53: -0.001 | G53: 0 | H53: 0
A55: EBIT | C55: =SUM(C50:C53) -> 37.051 | D55: =SUM(D50:D53) -> 517.947 | E55: =SUM(E50:E53) -> 323.465 | F55: =SUM(F50:F53) -> 14.534 | G55: =SUM(G50:G53) -> 36.135 | H55: =SUM(H50:H53) -> 86.625 | I55: =J55-H55-G55-F55 -> 124.381 | J55: =SUM(J50:J53) -> 261.675 | K55: =SUM(K50:K53) -> 513.41442 | L55: =SUM(L50:L53) -> 561.70272 | M55: =SUM(M50:M53) -> 624.73841 | N55: =SUM(N50:N53) -> 707.27687 | O55: =SUM(O50:O53) -> 785.17017 | P55: =SUM(P50:P53) -> 865.13151 | Q55: =SUM(Q50:Q53) -> 950.12317 | ... U55: =SUM(U50:U53) -> 1161.6062
A57: Depreciação
A59: EBITDA
A61: Resultado Financeiro Líquido | C61: -27.619 | D61: -20.863 | E61: -12.48 | F61: -4.912 | G61: -2.396 | H61: -10.36 | I61: =J61-H61-G61-F61 -> -5.561 | J61: -23.229 | K61: =K112 -> -28.775851 | L61: =L112 -> -101.08572 | M61: =M112 -> -145.84541 | N61: =N112 -> -149.4916 | O61: =O112 -> -144.36165 | P61: =P112 -> -125.22485 | Q61: =Q112 -> -102.89015 | R61: =R112 -> -97.508701 | ... U61: =U112 -> -106.36723
A63: EBT | C63: =+C55+C61 -> 9.432 | D63: =+D55+D61 -> 497.084 | E63: =+E55+E61 -> 310.985 | F63: =+F55+F61 -> 9.622 | G63: =+G55+G61 -> 33.739 | H63: =+H55+H61 -> 76.265 | I63: =+I55+I61 -> 118.82 | J63: =+J55+J61 -> 238.446 | ... U63: =+U55+U61 -> 1055.239
A64: Impostos | C64: 0 | D64: 0 | E64: 0 | F64: 0 | G64: 0 | H64: 0 | I64: 0 | J64: 0 | K64: =J64 -> 0 | L64: =K64 -> 0 | M64: =L64 -> 0 | N64: =M64 -> 0 | O64: =N64 -> 0 | P64: =O64 -> 0 | Q64: =P64 -> 0 | R64: =Q64 -> 0 | ... U64: =T64 -> 0
A66: Lucro Líquido | C66: =C63+C64 -> 9.432 | D66: =D63+D64 -> 497.084 | E66: =E63+E64 -> 310.985 | F66: =F63+F64 -> 9.622 | G66: =G63+G64 -> 33.739 | H66: =H63+H64 -> 76.265 | I66: =I63+I64 -> 118.82 | J66: =J63+J64 -> 238.446 | ... U66: =U63+U64 -> 1055.239
A68: Dividend payout | J68: =J103/E66 -> 0.30894095 | K68: 0.25 | L68: 0.3 | M68: 0.4 | N68: 0.4 | O68: 0.4 | P68: 0.4 | Q68: 0.45 | R68: 0.55 | S68: 0.6 | T68: 0.7 | U68: 0.8
A70: Imobilizado | C70: =C39 -> 2008 | D70: =D39 -> 2009 | E70: =E39 -> 2010 | F70: =F39 -> 1T11 | G70: =G39 -> 2T11 | H70: =H39 -> 3T11 | I70: =I39 -> 4T11 | J70: =J39 -> 2011 | ... U70: =U39 -> 2022E
A71: Investimentos | C71: =+C15 -> 1046.152 | D71: =+D15 -> 1456.411 | E71: =+E15 -> 1498.731 | F71: =+F15 -> 1553.574 | G71: =+G15 -> 1643.821 | H71: =+H15 -> 1850.828 | I71: =+I15 -> 1969.418 | J71: =I71 -> 1969.418 | K71: =J71+K73 -> 2406.418 | L71: =K71+L73 -> 2840.418 | M71: =L71+M73 -> 2890.418 | N71: =M71+N73 -> 2890.418 | O71: =N71+O73 -> 2890.418 | P71: =O71+P73 -> 2890.418 | Q71: =P71+Q73 -> 2890.418 | R71: =Q71+R73 -> 2890.418 | ... U71: =T71+U73 -> 2890.418
A73: Capex Total | I73: =SUM(I74:I76) -> 0 | J73: =SUM(J74:J76) -> 0 | K73: =SUM(K74:K76) -> 437 | L73: =SUM(L74:L76) -> 434 | M73: =SUM(M74:M76) -> 50 | N73: =SUM(N74:N76) -> 0 | O73: =SUM(O74:O76) -> 0 | P73: =SUM(P74:P76) -> 0 | ... U73: =SUM(U74:U76) -> 0
A74: -- Holding | K74: 0
A75: -- Aporte AG Concessões | K75: 80 | L75: =254+63 -> 317 | M75: 31
A76: -- Aporte Santo Antônio | K76: 357 | L76: 117 | M76: 19
A78: Métricas de Crédito | C78: =C70 -> 2008 | D78: =D70 -> 2009 | E78: =E70 -> 2010 | F78: =F70 -> 1T11 | G78: =G70 -> 2T11 | H78: =H70 -> 3T11 | I78: =I70 -> 4T11 | J78: =J70 -> 2011 | ... U78: =U70 -> 2022E
A79: Dívida Total | C79: =C21+C27+C28+C24 -> 260.763 | D79: =D21+D27+D28+D24 -> 702.812 | E79: =E21+E27+E28+E24 -> 82.022 | F79: =F21+F27+F28+F24 -> 94.423 | G79: =G21+G27+G28+G24 -> 81.99 | H79: =H21+H27+H28+H24 -> 167.163 | I79: =I21+I27+I28+I24 -> 286.63 | J79: =I79 -> 286.63 | K79: =J79-K117+K121 -> 1003.987 | L79: =K79-L117+L121 -> 1389.1152 | M79: =L79-M117+M121 -> 1521.4126 | N79: =M79-N117+N121 -> 1673.6142 | O79: =N79-O117+O121 -> 1443.807 | P79: =O79-P117+P121 -> 1234.5812 | Q79: =P79-Q117+Q121 -> 994.54263 | R79: =Q79-R117+R121 -> 1033.6887 | ... U79: =T79-U117+U121 -> 1179.646
A80: Dívida Líquida | C80: =C79-C8 -> 232.703 | D80: =D79-D8 -> 639.34 | E80: =E79-E8 -> 51.095 | F80: =F79-F8 -> 94.146 | G80: =G79-G8 -> 76.49 | H80: =H79-H8 -> 165.582 | I80: =I79-I8 -> 275.038 | J80: =I80 -> 275.038 | K80: =K79-K8 -> 971.97805 | L80: =L79-L8 -> 1369.4405 | M80: =M79-M8 -> 1437.4192 | N80: =N79-N8 -> 1422.2822 | O80: =O79-O8 -> 1233.7423 | P80: =P79-P8 -> 1013.696 | Q80: =Q79-Q8 -> 960.67686 | R80: =R79-R8 -> 985.09959 | ... U80: =U79-U8 -> 1131.8691
A81: Divida Total / PL | C81: =C79/C32 -> 0.26577363 | D81: =D79/D32 -> 0.57615239 | E81: =E79/E32 -> 0.057959319 | F81: =F79/F32 -> 0.066165455 | G81: =G79/G32 -> 0.056395904 | H81: =H79/H32 -> 0.11349852 | I81: =I79/I32 -> 0.17100814 | J81: =I81 -> 0.17100814 | K81: =K79/K32 -> 0.47782827 | L81: =L79/L32 -> 0.5748765 | M81: =M79/M32 -> 0.56119611 | N81: =N79/N32 -> 0.54386758 | O81: =O79/O32 -> 0.41311352 | P81: =P79/P32 -> 0.31031141 | Q81: =Q79/Q32 -> 0.22136373 | R81: =R79/R32 -> 0.20670865 | ... U81: =U79/U32 -> 0.19616715
A82: Dívida Bruta / Dividendos Recebidos | J82: =J79/J87 -> 3.7270659 | K82: =K79/K87 -> 6.6785635 | L82: =L79/L87 -> 4.8732313 | M82: =M79/M87 -> 4.8406304 | N82: =N79/N87 -> 4.6679619 | O82: =O79/O87 -> 3.6229896 | P82: =P79/P87 -> 2.7790305 | Q82: =Q79/Q87 -> 2.0227188 | ... U82: =U79/U87 -> 1.3249714
A83: Dívida Líquida / Dividendos Recebidos | J83: =J80/J87 -> 3.5763344 | K83: =K80/K87 -> 6.4656386 | L83: =L80/L87 -> 4.8042094 | M83: =M80/M87 -> 4.5733913 | N83: =N80/N87 -> 3.9669592 | O83: =O80/O87 -> 3.0958677 | P83: =P80/P87 -> 2.28182 | Q83: =Q80/Q87 -> 1.953842 | ... U83: =U80/U87 -> 1.2713086
A84: Interest Coverage Ratio | J84: =J87/ABS(J61) -> 3.3107323 | K84: =K87/ABS(K61) -> 5.2241647 | L84: =L87/ABS(L61) -> 2.8198853 | M84: =M87/ABS(M61) -> 2.155025 | N84: =N87/ABS(N61) -> 2.3983429 | O84: =O87/ABS(O61) -> 2.7605159 | P84: =P87/ABS(P61) -> 3.5476098 | Q84: =Q87/ABS(Q61) -> 4.7787479 | ... U84: =U87/ABS(U61) -> 8.3702294
A86: Cash Flow (R$mm) | C86: =C78 -> 2008 | D86: =D78 -> 2009 | E86: =E78 -> 2010 | F86: =F78 -> 1T11 | G86: =G78 -> 2T11 | H86: =H78 -> 3T11 | I86: =I78 -> 4T11 | J86: =J78 -> 2011 | ... U86: =U78 -> 2022E
A87: Dividendos Recebidos | J87: 76.905 | K87: =K88+K89 -> 150.32978 | L87: =L88+L89 -> 285.05012 | M87: =M88+M89 -> 314.3005 | N87: =N88+N89 -> 358.53211 | O87: =O88+O89 -> 398.51262 | P87: =P88+P89 -> 444.24889 | Q87: =Q88+Q89 -> 491.68606 | R87: =R88+R89 -> 542.05474 | ... U87: =U88+U89 -> 890.31813
A88: -- AG Concessões (90.35%) | D88: 21.563 | E88: 1.753 | K88: =ABS('AG Concessões'!G108*0.862) -> 150.32978 | L88: =ABS('AG Concessões'!H108*0.9404) -> 285.05012 | M88: =ABS('AG Concessões'!I108*0.9478) -> 314.3005 | N88: =ABS('AG Concessões'!J108*0.9478) -> 349.52936 | O88: =ABS('AG Concessões'!K108*0.9478) -> 395.63582 | P88: =ABS('AG Concessões'!L108*0.9478) -> 439.14759 | Q88: =ABS('AG Concessões'!M108*0.9478) -> 483.81612 | R88: =ABS('AG Concessões'!N108*0.9478) -> 531.29315 | S88: =ABS('AG Concessões'!O108*0.9478) -> 658.9 | T88: =ABS('AG Concessões'!P108*0.9478) -> 795.55013 | U88: =ABS('AG Concessões'!Q108*0.9478) -> 858.96243
A89: -- Santo Antônio (12.4%) | N89: 9.0027458 | O89: 2.8767943 | P89: 5.1012996 | Q89: 7.8699415 | R89: 10.761585 | S89: 14.94113 | T89: 20.133588 | U89: 31.355704
A91: Equivalência Patrimonial | K91: =-K51 -> -515.2969 | L91: =-L51 -> -563.73798 | M91: =-M51 -> -626.92542 | N91: =-N51 -> -709.62323 | O91: =-O51 -> -787.66712 | P91: =-P51 -> -867.78583 | Q91: =-Q51 -> -952.94193 | R91: =-R51 -> -1074.3828 | ... U91: =-U51 -> -1165.1601
A92: EBIT | K92: =K55 -> 513.41442 | L92: =L55 -> 561.70272 | M92: =M55 -> 624.73841 | N92: =N55 -> 707.27687 | O92: =O55 -> 785.17017 | P92: =P55 -> 865.13151 | Q92: =Q55 -> 950.12317 | R92: =R55 -> 1071.3922 | ... U92: =U55 -> 1161.6062
A93: Resultado Finaceiro Líquido | K93: =K61 -> -28.775851 | L93: =L61 -> -101.08572 | M93: =M61 -> -145.84541 | N93: =N61 -> -149.4916 | O93: =O61 -> -144.36165 | P93: =P61 -> -125.22485 | Q93: =Q61 -> -102.89015 | R93: =R61 -> -97.508701 | ... U93: =U61 -> -106.36723
A94: Fluxo de Caixa Operacional | K94: =K93+K92+K87+K91 -> 119.67145 | L94: =L93+L92+L87+L91 -> 181.92915 | M94: =M93+M92+M87+M91 -> 166.26808 | N94: =N93+N92+N87+N91 -> 206.69415 | O94: =O93+O92+O87+O91 -> 251.65402 | P94: =P93+P92+P87+P91 -> 316.36973 | Q94: =Q93+Q92+Q87+Q91 -> 385.97716 | R94: =R93+R92+R87+R91 -> 441.55543 | ... U94: =U93+U92+U87+U91 -> 780.39696
A96: Capex | K96: =-K73 -> -437 | L96: =-L73 -> -434 | M96: =-M73 -> -50 | N96: =-N73 -> 0 | O96: =-O73 -> 0 | P96: =-P73 -> 0 | Q96: =-Q73 -> 0 | R96: =-R73 -> 0 | ... U96: =-U73 -> 0
A97: Fluxo de Caixa de Investimentos | K97: =K96 -> -437 | L97: =L96 -> -434 | M97: =M96 -> -50 | N97: =N96 -> 0 | O97: =O96 -> 0 | P97: =P96 -> 0 | Q97: =Q96 -> 0 | R97: =R96 -> 0 | ... U97: =U96 -> 0
A99: Novos aportes de Capital | K99: 0 | L99: 0 | M99: 0 | N99: 0 | O99: 0 | P99: 0 | Q99: 0 | R99: 0 | S99: 0 | T99: 0 | U99: 0
A100: Mútuos Cedidos | K100: -320 | L100: 0 | M100: 0 | N100: 0 | O100: 160 | P100: 160 | Q100: 0 | R100: 0 | S100: 0 | T100: 0 | U100: 0
A101: Novas Dívidas | K101: =K121 -> 800 | L101: =L121 -> 427.57518 | M101: =M121 -> 141.43523 | N101: =N121 -> 161.33945 | O101: =O121 -> 179.33068 | P101: =P121 -> 199.912 | Q101: =Q121 -> 196.67443 | R101: =R121 -> 189.71916 | ... U101: =U121 -> 267.09544
A102: Amortização de Dívidas | K102: =-K117 -> -82.643 | L102: =-L117 -> -42.447 | M102: =-M117 -> -9.1378286 | N102: =-N117 -> -9.1378286 | O102: =-O117 -> -409.13783 | P102: =-P117 -> -409.13783 | Q102: =-Q117 -> -436.71301 | R102: =-R117 -> -150.57305 | ... U102: =-U117 -> -209.04983
A103: Dividendos pagos | J103: 96.076 | K103: =-J66*K68 -> -59.6115 | L103: =-K66*L68 -> -145.39157 | M103: =-L66*M68 -> -184.2468 | N103: =-M66*N68 -> -191.5572 | O103: =-N66*O68 -> -223.11411 | P103: =-O66*P68 -> -256.32341 | Q103: =-P66*Q68 -> -332.958 | R103: =-Q66*R68 -> -465.97816 | ... U103: =-T66*U68 -> -864.31307
A104: Mútuos Pagos
A105: Fluxo de Caixa de Financiamentos | K105: =SUM(K99:K104) -> 337.7455 | L105: =SUM(L99:L104) -> 239.73661 | M105: =SUM(M99:M104) -> -51.949406 | N105: =SUM(N99:N104) -> -39.355579 | O105: =SUM(O99:O104) -> -292.92126 | P105: =SUM(P99:P104) -> -305.54924 | Q105: =SUM(Q99:Q104) -> -572.99659 | R105: =SUM(R99:R104) -> -426.83206 | ... U105: =SUM(U99:U104) -> -806.26746
A107: Variação de Caixa | K107: =K94+K97+K105 -> 20.416952 | L107: =L94+L97+L105 -> -12.334234 | M107: =M94+M97+M105 -> 64.318673 | N107: =N94+N97+N105 -> 167.33857 | O107: =O94+O97+O105 -> -41.267241 | P107: =P94+P97+P105 -> 10.820488 | Q107: =Q94+Q97+Q105 -> -187.01943 | R107: =R94+R97+R105 -> 14.723374 | ... U107: =U94+U97+U105 -> -25.870496
A108: Caixa Inicial | K108: =J8 -> 11.592 | L108: =K8 -> 32.008952 | M108: =L8 -> 19.674718 | N108: =M8 -> 83.993392 | O108: =N8 -> 251.33196 | P108: =O8 -> 210.06472 | Q108: =P8 -> 220.8852 | R108: =Q8 -> 33.865777 | ... U108: =T8 -> 73.647385
A109: Caixa Final | K109: =K107+K108 -> 32.008952 | L109: =L107+L108 -> 19.674718 | M109: =M107+M108 -> 83.993392 | N109: =N107+N108 -> 251.33196 | O109: =O107+O108 -> 210.06472 | P109: =P107+P108 -> 220.8852 | Q109: =Q107+Q108 -> 33.865777 | R109: =R107+R108 -> 48.589151 | ... U109: =U107+U108 -> 47.776889
A111: Dívida e Resultado Financeiro | C111: =C86 -> 2008 | D111: =D86 -> 2009 | E111: =E86 -> 2010 | F111: =F86 -> 1T11 | G111: =G86 -> 2T11 | H111: =H86 -> 3T11 | I111: =I86 -> 4T11 | J111: =J86 -> 2011 | ... U111: =U86 -> 2022E
A112: Resultado Financeiro Líquido | C112: =+C61 -> -27.619 | D112: =+D61 -> -20.863 | E112: =+E61 -> -12.48 | F112: =+F61 -> -4.912 | G112: =+G61 -> -2.396 | H112: =+H61 -> -10.36 | I112: =+I61 -> -5.561 | J112: =SUM(F112:I112) -> -23.229 | K112: =-K113*J80 -> -28.775851 | L112: =-L113*K80 -> -101.08572 | M112: =-M113*L80 -> -145.84541 | N112: =-N113*M80 -> -149.4916 | O112: =-O113*N80 -> -144.36165 | P112: =-P113*O80 -> -125.22485 | Q112: =-Q113*P80 -> -102.89015 | R112: =-R113*Q80 -> -97.508701 | ... U112: =-U113*T80 -> -106.36723
A113: Custo Médio de Dívida | D113: =-D112/AVERAGE(C80:D80) -> 0.047848558 | E113: =-E112/AVERAGE(D80:E80) -> 0.036151122 | J113: =-J112/AVERAGE(J80,E80) -> 0.14245109 | K113: =K114+K115 -> 0.104625 | L113: =L114+L115 -> 0.104 | M113: =M114+M115 -> 0.1065 | N113: =N114+N115 -> 0.104 | O113: =O114+O115 -> 0.1015 | P113: =P114+P115 -> 0.1015 | Q113: =Q114+Q115 -> 0.1015 | R113: =R114+R115 -> 0.1015 | ... U113: =U114+U115 -> 0.1015
A114: -- Selic Média | D114: ='AG Concessões'!D119 -> 0.099166667 | E114: ='AG Concessões'!E119 -> 0.1 | J114: ='AG Concessões'!F119 -> 0.11708333 | K114: ='AG Concessões'!G119 -> 0.093125 | L114: ='AG Concessões'!H119 -> 0.0925 | M114: ='AG Concessões'!I119 -> 0.095 | N114: ='AG Concessões'!J119 -> 0.0925 | O114: ='AG Concessões'!K119 -> 0.09 | P114: ='AG Concessões'!L119 -> 0.09 | Q114: ='AG Concessões'!M119 -> 0.09 | ... U114: ='AG Concessões'!Q119 -> 0.09
A115: -- Spread Médio | D115: =D113-D114 -> -0.051318109 | E115: =E113-E114 -> -0.063848878 | J115: =J113-J114 -> 0.025367753 | K115: 0.0115 | L115: 0.0115 | M115: 0.0115 | N115: 0.0115 | O115: 0.0115 | P115: 0.0115 | Q115: 0.0115 | R115: 0.0115 | S115: 0.0115 | T115: 0.0115 | U115: 0.0115
A117: Cronograma de Amortização de Dívida | J117: =J118+J119 -> 0 | K117: =K118+K119 -> 82.643 | L117: =L118+L119 -> 42.447 | M117: =M118+M119 -> 9.1378286 | N117: =N118+N119 -> 9.1378286 | O117: =O118+O119 -> 409.13783 | P117: =P118+P119 -> 409.13783 | Q117: =Q118+Q119 -> 436.71301 | ... U117: =U118+U119 -> 209.04983
A118: -- Dívida Antiga | K118: =J21+J24 -> 82.643 | L118: 42.447 | M118: =159.912/35*2 -> 9.1378286 | N118: =159.912/35*2 -> 9.1378286 | O118: =159.912/35*2 -> 9.1378286 | P118: =159.912/35*2 -> 9.1378286 | Q118: =159.912/35*2 -> 9.1378286 | R118: =159.912/35*2 -> 9.1378286 | S118: =159.912/35*2 -> 9.1378286 | T118: =159.912/35*2 -> 9.1378286 | U118: =159.912/35*2 -> 9.1378286
A119: -- Novas Dívidas | O119: =K121/2 -> 400 | P119: =K121/2 -> 400 | Q119: =L121 -> 427.57518 | R119: =M121 -> 141.43523 | S119: =N121 -> 161.33945 | T119: =O121 -> 179.33068 | U119: =P121 -> 199.912
A121: Novas Dívidas | K121: 800 | L121: =L122*L87 -> 427.57518 | M121: =M122*M87 -> 141.43523 | N121: =N122*N87 -> 161.33945 | O121: =O122*O87 -> 179.33068 | P121: =P122*P87 -> 199.912 | Q121: =Q122*Q87 -> 196.67443 | R121: =R122*R87 -> 189.71916 | S121: =S122*S87 -> 202.15234 | ... U121: =U122*U87 -> 267.09544
L122: 1.5 | M122: 0.45 | N122: 0.45 | O122: 0.45 | P122: 0.45 | Q122: 0.4 | R122: 0.35 | S122: 0.3 | T122: 0.3 | U122: 0.3

Sheet AG Concessões
A1: AG Concessões
C2: IFRS | D2: IFRS | E2: IFRS | F2: IFRS
A3: R$ mm | C3: 2008 | D3: 2009 | E3: 2010 | F3: 2011 | G3: 2012E | H3: 2013E | I3: 2014E | J3: 2015E | K3: 2016E | L3: 2017E | M3: 2018E | N3: 2019E | O3: 2020E | P3: 2021E | Q3: 2022E
A5: Ativo | C5: =+C7+C13+C15 -> 1221.314 | D5: =+D7+D13+D15 -> 1390.26 | E5: =+E7+E13+E15 -> 2204.382 | F5: =+F7+F13+F15 -> 2453.495 | G5: =+G7+G13+G15 -> 2961.6046 | H5: =+H7+H13+H15 -> 3331.5912 | I5: =+I7+I13+I15 -> 3886.4528 | J5: =+J7+J13+J15 -> 4496.3922 | ... Q5: =+Q7+Q13+Q15 -> 8940.4336
A7: Ativo Circulante | C7: =+SUM(C8:C11) -> 107.841 | D7: =+SUM(D8:D11) -> 55.419 | E7: =+SUM(E8:E11) -> 61.7 | F7: =+SUM(F8:F11) -> 41.373 | G7: =+SUM(G8:G11) -> 123.04768 | H7: =+SUM(H8:H11) -> 47.733812 | I7: =+SUM(I8:I11) -> 77.932314 | J7: =+SUM(J8:J11) -> 127.67317 | ... Q7: =+SUM(Q8:Q11) -> 66.95787
A8: Caixa | C8: 54.917 | D8: 13.047 | E8: 1.688 | F8: 13.125 | G8: =F8+G112 -> 94.799681 | H8: =G8+H112 -> 19.485812 | I8: =H8+I112 -> 49.684314 | J8: =I8+J112 -> 99.425166 | K8: =J8+K112 -> 77.853849 | L8: =K8+L112 -> 38.831131 | M8: =L8+M112 -> 12.756713 | N8: =M8+N112 -> 41.78706 | ... Q8: =P8+Q112 -> 38.70987
A9: Tributos a Recuperar | C9: 1.709 | D9: 1.738 | E9: 12.154 | F9: 9.392 | G9: =F9 -> 9.392 | H9: =G9 -> 9.392 | I9: =H9 -> 9.392 | J9: =I9 -> 9.392 | K9: =J9 -> 9.392 | L9: =K9 -> 9.392 | M9: =L9 -> 9.392 | N9: =M9 -> 9.392 | ... Q9: =P9 -> 9.392
A10: Dividendos e JCP a receber | C10: 51.112 | D10: 40.548 | E10: 47.858 | F10: 8.679 | G10: =F10 -> 8.679 | H10: =G10 -> 8.679 | I10: =H10 -> 8.679 | J10: =I10 -> 8.679 | K10: =J10 -> 8.679 | L10: =K10 -> 8.679 | M10: =L10 -> 8.679 | N10: =M10 -> 8.679 | ... Q10: =P10 -> 8.679
A11: Outros | C11: =107.841-SUM(C8:C10) -> 0.103 | D11: =55.419-SUM(D8:D10) -> 0.086 | E11: =61.7-SUM(E8:E10) -> 0 | F11: =41.373-SUM(F8:F10) -> 10.177 | G11: =F11 -> 10.177 | H11: =G11 -> 10.177 | I11: =H11 -> 10.177 | J11: =I11 -> 10.177 | K11: =J11 -> 10.177 | L11: =K11 -> 10.177 | M11: =L11 -> 10.177 | N11: =M11 -> 10.177 | ... Q11: =P11 -> 10.177
A13: Realizável Longo Prazo | C13: 7.751 | D13: 6.147 | E13: 3.05 | F13: 3.076 | G13: =F13 -> 3.076 | H13: =G13 -> 3.076 | I13: =H13 -> 3.076 | J13: =I13 -> 3.076 | K13: =J13 -> 3.076 | L13: =K13 -> 3.076 | M13: =L13 -> 3.076 | N13: =M13 -> 3.076 | ... Q13: =P13 -> 3.076
A15: Ativos Fixos | C15: =SUM(C16:C18) -> 1105.722 | D15: =SUM(D16:D18) -> 1328.694 | E15: =SUM(E16:E18) -> 2139.632 | F15: =SUM(F16:F18) -> 2409.046 | G15: =SUM(G16:G18) -> 2835.481 | H15: =SUM(H16:H18) -> 3280.7814 | I15: =SUM(I16:I18) -> 3805.4445 | J15: =SUM(J16:J18) -> 4365.643 | ... Q15: =SUM(Q16:Q18) -> 8870.3997
A16: Investimentos | C16: 1062.928 | D16: 1284.359 | E16: 1925.209 | F16: 2177.408 | G16: =F16+G50+G73-G89 -> 2604.198 | H16: =G16+H50+H73-H89 -> 3049.4984 | I16: =H16+I50+I73-I89 -> 3574.1615 | J16: =I16+J50+J73-J89 -> 4134.36 | K16: =J16+K50+K73-K89 -> 4720.125 | L16: =K16+L50+L73-L89 -> 5336.3531 | M16: =L16+M50+M73-M89 -> 5987.0914 | N16: =M16+N50+N73-N89 -> 6710.55 | ... Q16: =P16+Q50+Q73-Q89 -> 8639.1167
A17: Imobilizado | C17: 0.122 | D17: 0.311 | E17: 0.333 | F17: 0.355
A18: Intangível | C18: 42.672 | D18: 44.024 | E18: 214.09 | F18: 231.283 | G18: =F18 -> 231.283 | H18: =G18 -> 231.283 | I18: =H18 -> 231.283 | J18: =I18 -> 231.283 | K18: =J18 -> 231.283 | L18: =K18 -> 231.283 | M18: =L18 -> 231.283 | N18: =M18 -> 231.283 | ... Q18: =P18 -> 231.283
A20: Exigível de Curto Prazo | C20: =+SUM(C21:C24) -> 102.462 | D20: =+SUM(D21:D24) -> 50.535 | E20: =+SUM(E21:E24) -> 207.017 | F20: =+SUM(F21:F24) -> 94.633 | G20: =+SUM(G21:G24) -> 226.545 | H20: =+SUM(H21:H24) -> 92.544 | I20: =+SUM(I21:I24) -> 89.669 | J20: =+SUM(J21:J24) -> 171.2625 | ... Q20: =+SUM(Q21:Q24) -> 42.169
A21: Dívida CP | C21: 43.28 | E21: 153.248 | F21: 52.464 | G21: =H122 -> 184.376 | H21: =I122 -> 50.375 | I21: =J122 -> 47.5 | J21: =K122 -> 129.0935 | K21: =L122 -> 194.25724 | L21: =M122 -> 199.28785 | M21: =N122 -> 191.36819 | N21: =O122 -> 184.04535 | ... Q21: =R122 -> 0
A22: Obrigações Fiscais | C22: 0.122 | D22: 0.077 | E22: 0.074 | F22: 0.467 | G22: =F22 -> 0.467 | H22: =G22 -> 0.467 | I22: =H22 -> 0.467 | J22: =I22 -> 0.467 | K22: =J22 -> 0.467 | L22: =K22 -> 0.467 | M22: =L22 -> 0.467 | N22: =M22 -> 0.467 | ... Q22: =P22 -> 0.467
A23: Dividendos e JCP a pagar | C23: 45 | D23: 25.6 | E23: 23.816 | F23: 15.838 | G23: =F23 -> 15.838 | H23: =G23 -> 15.838 | I23: =H23 -> 15.838 | J23: =I23 -> 15.838 | K23: =J23 -> 15.838 | L23: =K23 -> 15.838 | M23: =L23 -> 15.838 | N23: =M23 -> 15.838 | ... Q23: =P23 -> 15.838
A24: Outros | C24: =102.462-SUM(C21:C23) -> 14.06 | D24: =50.535-SUM(D21:D23) -> 24.858 | E24: =207.017-SUM(E21:E23) -> 29.879 | F24: =94.633-SUM(F21:F23) -> 25.864 | G24: =F24 -> 25.864 | H24: =G24 -> 25.864 | I24: =H24 -> 25.864 | J24: =I24 -> 25.864 | K24: =J24 -> 25.864 | L24: =K24 -> 25.864 | M24: =L24 -> 25.864 | N24: =M24 -> 25.864 | ... Q24: =P24 -> 25.864
A26: Passivo Não Circulante | C26: =+SUM(C27:C29) -> 190.379 | D26: =+SUM(D27:D29) -> 163.316 | E26: =+SUM(E27:E29) -> 217.817 | F26: =+SUM(F27:F29) -> 286.676 | G26: =+SUM(G27:G29) -> 231.3935 | H26: =+SUM(H27:H29) -> 375.27573 | I26: =+SUM(I27:I29) -> 527.06358 | J26: =+SUM(J27:J29) -> 589.33827 | ... Q26: =+SUM(Q27:Q29) -> 1058.4132
A27: Dívida LP | C27: 148.091 | D27: 130.147 | E27: 209.831 | F27: 282.75 | G27: =G81-G21 -> 227.4675 | H27: =H81-H21 -> 371.34973 | I27: =I81-I21 -> 523.13758 | J27: =J81-J21 -> 585.41227 | K27: =K81-K21 -> 575.20039 | L27: =L81-L21 -> 589.78434 | M27: =M81-M21 -> 611.72189 | N27: =N81-N21 -> 668.10799 | ... Q27: =Q81-Q21 -> 1054.4872
A28: Passivos com Partes Relacionadas | C28: 42.288 | D28: 33.169 | E28: 7.986 | F28: 3.926 | G28: =F28 -> 3.926 | H28: =G28 -> 3.926 | I28: =H28 -> 3.926 | J28: =I28 -> 3.926 | K28: =J28 -> 3.926 | L28: =K28 -> 3.926 | M28: =L28 -> 3.926 | N28: =M28 -> 3.926 | ... Q28: =P28 -> 3.926
A29: Outros | C29: 0 | D29: 0 | E29: 0 | F29: 0 | G29: =F29 -> 0 | H29: =G29 -> 0 | I29: =H29 -> 0 | J29: =I29 -> 0 | K29: =J29 -> 0 | L29: =K29 -> 0 | M29: =L29 -> 0 | N29: =M29 -> 0 | ... Q29: =P29 -> 0
A31: Patrimônio Líquido | C31: 928.473 | D31: 1176.409 | E31: 1779.548 | F31: 2072.186 | G31: =F31+G65+G104+G108 -> 2504.0212 | H31: =G31+H65+H104+H108 -> 2864.1265 | I31: =H31+I65+I104+I108 -> 3270.0752 | J31: =I31+J65+J104+J108 -> 3736.1464 | K31: =J31+K65+K104+K108 -> 4245.3882 | L31: =K31+L65+L104+L108 -> 4802.9791 | M31: =L31+M65+M104+M108 -> 5413.625 | N31: =M31+N65+N104+N108 -> 6117.0507 | ... Q31: =P31+Q65+Q104+Q108 -> 7840.2065
A33: Passivo | C33: =C31+C26+C20 -> 1221.314 | D33: =D31+D26+D20 -> 1390.26 | E33: =E31+E26+E20 -> 2204.382 | F33: =F31+F26+F20 -> 2453.495 | G33: =G31+G26+G20 -> 2961.9596 | H33: =H31+H26+H20 -> 3331.9462 | I33: =I31+I26+I20 -> 3886.8078 | J33: =J31+J26+J20 -> 4496.7472 | ... Q33: =Q31+Q26+Q20 -> 8940.7886
A35: Check | C35: =C5-C33 -> 0 | D35: =D5-D33 -> 0 | E35: =E5-E33 -> 0 | F35: =F5-F33 -> 0 | G35: =G5-G33 -> -0.355 | H35: =H5-H33 -> -0.355 | I35: =I5-I33 -> -0.355 | J35: =J5-J33 -> -0.355 | ... Q35: =Q5-Q33 -> -0.355
C37: LS | D37: IFRS | E37: IFRS | F37: IFRS
A38: R$ mm | C38: =C3 -> 2008 | D38: =D3 -> 2009 | E38: =E3 -> 2010 | F38: =F3 -> 2011 | G38: =G3 -> 2012E | H38: =H3 -> 2013E | I38: =I3 -> 2014E | J38: =J3 -> 2015E | ... Q38: =Q3 -> 2022E
A39: Receita Bruta
A41: Deduções
A43: Receita Líquida | D43: 10.127 | E43: 16.374 | F43: 19.156
A45: CPV | D45: -5.018 | E45: -5.825 | F45: -9.16
A47: Lucro Bruto | D47: =D43+D45 -> 5.109 | E47: =E43+E45 -> 10.549 | F47: =F43+F45 -> 9.996 | G47: =+F47 -> 9.996 | H47: =+G47 -> 9.996 | I47: =+H47 -> 9.996 | J47: =+I47 -> 9.996 | K47: =+J47 -> 9.996 | L47: =+K47 -> 9.996 | M47: =+L47 -> 9.996 | N47: =+M47 -> 9.996 | ... Q47: =+P47 -> 9.996
A49: G&A | D49: -42.223 | E49: -107.014 | F49: -52.322 | G49: =F49*(1+(Cenário!W9/100)) -> -55.042744 | H49: =G49*(1+(Cenário!X9/100)) -> -57.960009 | I49: =H49*(1+(Cenário!Y9/100)) -> -60.85801 | J49: =I49*(1+(Cenário!Z9/100)) -> -63.90091 | K49: =J49*(1+(Cenário!AA9/100)) -> -66.776451 | L49: =K49*(1+(Cenário!AB9/100)) -> -69.781392 | M49: =L49*(1+(Cenário!AC9/100)) -> -72.921554 | N49: =M49*(1+(Cenário!AD9/100)) -> -76.203024 | ... Q49: =P49*(1+(Cenário!AG9/100)) -> -86.96031
A50: Equivalência Patrimonial | D50: 263.864 | E50: 398.987 | F50: 435.337 | G50: =('Cash Flow CCR'!G31*0.17)+('Cash Flow Cemig'!G4*0.144)+('AG Concessões'!G93+'AG Concessões'!G133*0.096) -> 684.97696 | H50: =('Cash Flow CCR'!H31*0.17)+('Cash Flow Cemig'!H4*0.144)+('AG Concessões'!H93+'AG Concessões'!H133*0.096) -> 744.15771 | I50: =('Cash Flow CCR'!I31*0.17)+('Cash Flow Cemig'!I4*0.144)+('AG Concessões'!I93+'AG Concessões'!I133*0.096) -> 831.25977 | J50: =('Cash Flow CCR'!J31*0.17)+('Cash Flow Cemig'!J4*0.144)+('AG Concessões'!J93+'AG Concessões'!J133*0.096) -> 942.93491 | K50: =('Cash Flow CCR'!K31*0.17)+('Cash Flow Cemig'!K4*0.144)+('AG Concessões'!K93+'AG Concessões'!K133*0.096) -> 1045.8783 | L50: =('Cash Flow CCR'!L31*0.17)+('Cash Flow Cemig'!L4*0.144)+('AG Concessões'!L93+'AG Concessões'!L133*0.096) -> 1150.9077 | M50: =('Cash Flow CCR'!M31*0.17)+('Cash Flow Cemig'!M4*0.144)+('AG Concessões'!M93+'AG Concessões'!M133*0.096) -> 1260.1832 | N50: =('Cash Flow CCR'!N31*0.17)+('Cash Flow Cemig'!N4*0.144)+('AG Concessões'!N93+'AG Concessões'!N133*0.096) -> 1410.4056 | ... Q50: =('Cash Flow CCR'!Q31*0.17)+('Cash Flow Cemig'!Q4*0.144)+('AG Concessões'!Q93+'AG Concessões'!Q133*0.096) -> 1537.487
A51: Outras Receitas Operacionais
A52: Outras Despesas Operacionais | D52: 161.815 | E52: 438.975 | F52: 0
A54: EBIT | C54: =SUM(C49:C52) -> 0 | D54: =SUM(D49:D52)+D47 -> 388.565 | E54: =SUM(E49:E52)+E47 -> 741.497 | F54: =SUM(F49:F52)+F47 -> 393.011 | G54: =SUM(G49:G52)+G47 -> 639.93021 | H54: =SUM(H49:H52)+H47 -> 696.19371 | I54: =SUM(I49:I52)+I47 -> 780.39776 | J54: =SUM(J49:J52)+J47 -> 889.03 | K54: =SUM(K49:K52)+K47 -> 989.09789 | ... Q54: =SUM(Q49:Q52)+Q47 -> 1460.5227
A56: Depreciação | D56: 0.226 | E56: 0.471 | F56: 0.579 | G56: =F56 -> 0.579 | H56: =G56 -> 0.579 | I56: =H56 -> 0.579 | J56: =I56 -> 0.579 | K56: =J56 -> 0.579 | L56: =K56 -> 0.579 | M56: =L56 -> 0.579 | N56: =M56 -> 0.579 | ... Q56: =P56 -> 0.579
A58: EBITDA | D58: =D56+D54 -> 388.791 | E58: =E56+E54 -> 741.968 | F58: =F56+F54 -> 393.59 | G58: =G56+G54 -> 640.50921 | H58: =H56+H54 -> 696.77271 | I58: =I56+I54 -> 780.97676 | J58: =J56+J54 -> 889.609 | K58: =K56+K54 -> 989.67689 | ... Q58: =Q56+Q54 -> 1461.1017
A60: Resultado Financeiro Líquido | D60: =4.148-23.81 -> -19.662 | E60: -13.502 | F60: -44.218 | G60: =+G117 -> -33.698562 | H60: =+H117 -> -32.972557 | I60: =+I117 -> -42.838445 | J60: =+J117 -> -54.179139 | K60: =+K117 -> -62.430681 | L60: =+L117 -> -70.197783 | M60: =+M117 -> -76.149467 | N60: =+N117 -> -80.218836 | ... Q60: =+Q117 -> -89.746048
A62: EBT | C62: =+C54+C60 -> 0 | D62: =+D54+D60 -> 368.903 | E62: =+E54+E60 -> 727.995 | F62: =+F54+F60 -> 348.793 | G62: =+G54+G60 -> 606.23165 | H62: =+H54+H60 -> 663.22115 | I62: =+I54+I60 -> 737.55932 | J62: =+J54+J60 -> 834.85086 | ... Q62: =+Q54+Q60 -> 1370.7766
A63: Impostos
A65: Lucro Líquido | C65: =C62+C63 -> 0 | D65: =D62+D63 -> 368.903 | E65: =E62+E63 -> 727.995 | F65: =F62+F63 -> 348.793 | G65: =G62+G63 -> 606.23165 | H65: =H62+H63 -> 663.22115 | I65: =I62+I63 -> 737.55932 | J65: =J62+J63 -> 834.85086 | ... Q65: =Q62+Q63 -> 1370.7766
A67: Dividend payout | D67: =D108/D65 -> -0.51705191 | E67: =E108/E65 -> -0.21840809 | F67: =F108/F65 -> -0.2603722 | G67: 0.5 | H67: 0.5 | I67: 0.5 | J67: 0.5 | K67: 0.5 | L67: 0.5 | M67: 0.5 | N67: 0.5 | O67: 0.55 | P67: 0.6 | Q67: 0.65
A68: Tax Rate
A70: Imobilizado | C70: =C38 -> 2008 | D70: =D38 -> 2009 | E70: =E38 -> 2010 | F70: =F38 -> 2011 | G70: =G38 -> 2012E | H70: =H38 -> 2013E | I70: =I38 -> 2014E | J70: =J38 -> 2015E | ... Q70: =Q38 -> 2022E
A71: Investimentos | C71: =+C16 -> 1062.928 | D71: =+D16 -> 1284.359 | E71: =+E16 -> 1925.209 | F71: =+F16 -> 2177.408
A73: Capex Total | G73: =SUM(G74:G80) -> 0 | H73: =SUM(H74:H80) -> 0 | I73: =SUM(I74:I80) -> 0 | J73: =SUM(J74:J80) -> 0 | K73: =SUM(K74:K80) -> 0 | L73: =SUM(L74:L80) -> 0 | M73: =SUM(M74:M80) -> 0 | N73: =SUM(N74:N80) -> 0 | ... Q73: =SUM(Q74:Q80) -> 0
A74: -- Holding
A75: -- Aporte CCR
A76: -- Aporte Cemig
A77: -- Aporte Sanepar
A78: -- Aporte Water Port
A80: Métricas de Crédito | C80: =C70 -> 2008 | D80: =D70 -> 2009 | E80: =E70 -> 2010 | F80: =F70 -> 2011 | G80: =G70 -> 2012E | H80: =H70 -> 2013E | I80: =I70 -> 2014E | J80: =J70 -> 2015E | ... Q80: =Q70 -> 2022E
A81: Dívida Total | C81: =C21+C27 -> 191.371 | D81: =D21+D27 -> 130.147 | E81: =E21+E27 -> 363.079 | F81: =F21+F27 -> 335.214 | G81: =F81+G126-G122 -> 411.8435 | H81: =G81+H126-H122 -> 421.72473 | I81: =H81+I126-I122 -> 570.63758 | J81: =I81+J126-J122 -> 714.50576 | K81: =J81+K126-K122 -> 769.45762 | L81: =K81+L126-L122 -> 789.07219 | M81: =L81+M126-M122 -> 803.09008 | N81: =M81+N126-N122 -> 852.15335 | ... Q81: =P81+Q126-Q122 -> 1054.4872
A82: Dívida Líquida | C82: =C81-C8 -> 136.454 | D82: =D81-D8 -> 117.1 | E82: =E81-E8 -> 361.391 | F82: =F81-F8 -> 322.089 | G82: =G81-G8 -> 317.04381 | H82: =H81-H8 -> 402.23892 | I82: =I81-I8 -> 520.95326 | J82: =J81-J8 -> 615.0806 | ... Q82: =Q81-Q8 -> 1015.7773
A83: Divida Total / PL | C83: =C81/C31 -> 0.20611369 | D83: =D81/D31 -> 0.11063074 | E83: =E81/E31 -> 0.20402878 | F83: =F81/F31 -> 0.1617683 | G83: =G81/G31 -> 0.16447285 | H83: =H81/H31 -> 0.14724375 | I83: =I81/I31 -> 0.17450289 | J83: =J81/J31 -> 0.19124137 | ... Q83: =Q81/Q31 -> 0.13449737
A84: Dívida Bruta / Dividendos Recebidos | D84: =D81/D89 -> 0.68139791 | E84: =E81/E89 -> 1.6655 | F84: =F81/F89 -> 1.236952 | G84: =G81/G89 -> 1.5951365 | H84: =H81/H89 -> 1.4111241 | I84: =I81/I89 -> 1.8611994 | J84: =J81/J89 -> 1.8668353 | K84: =K81/K89 -> 1.6723217 | ... Q84: =Q81/Q89 -> 1.1201262
A85: Dívida Líquida / Dividendos Recebidos | D85: =D82/D89 -> 0.61308901 | E85: =E82/E89 -> 1.6577569 | F85: =F82/F89 -> 1.1885203 | G85: =G82/G89 -> 1.227962 | H85: =H82/H89 -> 1.3459231 | I85: =I82/I89 -> 1.6991484 | J85: =J82/J89 -> 1.6070607 | K85: =K82/K89 -> 1.503116 | ... Q85: =Q82/Q89 -> 1.0790068
A86: Interest Coverage Ratio | D86: =D89/ABS(D60) -> 9.7141695 | E86: =E89/ABS(E60) -> 16.145756 | F86: =F89/ABS(F60) -> 6.1287259 | G86: =G89/ABS(G60) -> 7.6616621 | H86: =H89/ABS(H60) -> 9.063819 | I86: =I89/ABS(I60) -> 7.1570452 | J86: =J89/ABS(J60) -> 7.0642756 | K86: =K89/ABS(K60) -> 7.3699883 | ... Q86: =Q89/ABS(Q60) -> 10.489602
A88: Cash Flow (R$mm) | C88: =C80 -> 2008 | D88: =D80 -> 2009 | E88: =E80 -> 2010 | F88: =F80 -> 2011 | G88: =G80 -> 2012E | H88: =H80 -> 2013E | I88: =I80 -> 2014E | J88: =J80 -> 2015E | ... Q88: =Q80 -> 2022E
A89: Dividendos Recebidos | D89: =SUM(D90:D94) -> 191 | E89: =SUM(E90:E94) -> 218 | F89: =SUM(F90:F94) -> 271 | G89: =SUM(G90:G94) -> 258.18699 | H89: =SUM(H90:H94) -> 298.85729 | I89: =SUM(I90:I94) -> 306.59669 | J89: =SUM(J90:J94) -> 382.73637 | K89: =SUM(K90:K94) -> 460.11339 | ... Q89: =SUM(Q90:Q94) -> 941.40029
A90: -- CCR (17%) | D90: 101 | E90: 141 | F90: 148 | G90: =ABS('Cash Flow CCR'!G16)*0.17 -> 122.31459 | H90: =ABS('Cash Flow CCR'!H16)*0.17 -> 175.1272 | I90: =ABS('Cash Flow CCR'!I16)*0.17 -> 197.8494 | J90: =ABS('Cash Flow CCR'!J16)*0.17 -> 250.5307 | K90: =ABS('Cash Flow CCR'!K16)*0.17 -> 303.0335 | L90: =ABS('Cash Flow CCR'!L16)*0.17 -> 357.3451 | M90: =ABS('Cash Flow CCR'!M16)*0.17 -> 414.001 | N90: =ABS('Cash Flow CCR'!N16)*0.17 -> 472.8703 | ... Q90: =ABS('Cash Flow CCR'!Q16)*0.17 -> 619.4426
A91: -- Cemig (14.4%) | F91: 93 | G91: ='Cash Flow Cemig'!G22 -> 111.17357 | H91: ='Cash Flow Cemig'!H22 -> 93.293993 | I91: ='Cash Flow Cemig'!I22 -> 99.009315 | J91: ='Cash Flow Cemig'!J22 -> 121.98081 | K91: ='Cash Flow Cemig'!K22 -> 146.3949 | L91: ='Cash Flow Cemig'!L22 -> 164.57347 | M91: ='Cash Flow Cemig'!M22 -> 182.10879 | N91: ='Cash Flow Cemig'!N22 -> 200.14146 | ... Q91: ='Cash Flow Cemig'!Q22 -> 306.05526
A92: -- Light | D92: 75 | E92: 59
A93: -- Water Port (100%) | D93: 13 | E93: 13 | F93: 19 | G93: =(G90+G91)*G129 -> 18.407781 | H93: =(H90+H91)*H129 -> 21.161837 | I93: =(I90+I91)*I129 -> 0 | J93: =(J90+J91)*J129 -> 0 | K93: =(K90+K91)*K129 -> 0 | L93: =(L90+L91)*L129 -> 0 | M93: =(M90+M91)*M129 -> 0 | N93: =(N90+N91)*N129 -> 0 | ... Q93: =(Q90+Q91)*Q129 -> 0
A94: -- Sanepar (9.6%) + Aeris | D94: 2 | E94: 5 | F94: 11 | G94: =G133*0.25*0.096 -> 6.2910442 | H94: =H133*0.35*0.096 -> 9.2742573 | I94: =I133*0.35*0.096 -> 9.7379702 | J94: =J133*0.35*0.096 -> 10.224869 | K94: =K133*0.35*0.096 -> 10.684988 | L94: =L133*0.4*0.096 -> 12.760928 | M94: =M133*0.4*0.096 -> 13.33517 | N94: =N133*0.4*0.096 -> 13.935253 | O94: =O133*0.4*0.096 -> 14.562339 | P94: =P133*0.4*0.096 -> 15.217644 | Q94: =Q133*0.4*0.096 -> 15.902438
A96: Equivalência Patrimonial | G96: =-G50 -> -684.97696 | H96: =-H50 -> -744.15771 | I96: =-I50 -> -831.25977 | J96: =-J50 -> -942.93491 | K96: =-K50 -> -1045.8783 | L96: =-L50 -> -1150.9077 | M96: =-M50 -> -1260.1832 | N96: =-N50 -> -1410.4056 | ... Q96: =-Q50 -> -1537.487
A97: EBIT | G97: =G54 -> 639.93021 | H97: =H54 -> 696.19371 | I97: =I54 -> 780.39776 | J97: =J54 -> 889.03 | K97: =K54 -> 989.09789 | L97: =L54 -> 1091.1223 | M97: =M54 -> 1197.2576 | N97: =N54 -> 1344.1986 | ... Q97: =Q54 -> 1460.5227
A98: Resultado Financeiro Líquido | G98: =G60 -> -33.698562 | H98: =H60 -> -32.972557 | I98: =I60 -> -42.838445 | J98: =J60 -> -54.179139 | K98: =K60 -> -62.430681 | L98: =L60 -> -70.197783 | M98: =M60 -> -76.149467 | N98: =N60 -> -80.218836 | ... Q98: =Q60 -> -89.746048
A99: Fluxo de Caixa Operacional | G99: =SUM(G96:G98)+G89 -> 179.44169 | H99: =SUM(H96:H98)+H89 -> 217.92072 | I99: =SUM(I96:I98)+I89 -> 212.89623 | J99: =SUM(J96:J98)+J89 -> 274.65232 | K99: =SUM(K96:K98)+K89 -> 340.90225 | L99: =SUM(L96:L98)+L89 -> 404.69632 | M99: =SUM(M96:M98)+M89 -> 470.36994 | N99: =SUM(N96:N98)+N89 -> 540.52115 | ... Q99: =SUM(Q96:Q98)+Q89 -> 774.68994
A101: Capex | G101: =-G73 -> 0 | H101: =-H73 -> 0 | I101: =-I73 -> 0 | J101: =-J73 -> 0 | K101: =-K73 -> 0 | L101: =-L73 -> 0 | M101: =-M73 -> 0 | N101: =-N73 -> 0 | ... Q101: =-Q73 -> 0
A102: Fluxo de Caixa de Investimentos | G102: =G101 -> 0 | H102: =H101 -> 0 | I102: =I101 -> 0 | J102: =J101 -> 0 | K102: =K101 -> 0 | L102: =L101 -> 0 | M102: =M101 -> 0 | N102: =N101 -> 0 | ... Q102: =Q101 -> 0
A104: Novos aportes de Capital | G104: 0 | H104: 0 | I104: 0 | J104: 0 | K104: 0 | L104: 0 | M104: 0 | N104: 0 | O104: 0 | P104: 0 | Q104: 0
A105: Mútuos Recebidos | G105: 0 | H105: 0 | I105: 0 | J105: 0 | K105: 0 | L105: 0 | M105: 0 | N105: 0 | O105: 0 | P105: 0 | Q105: 0
A106: Novas Dívidas | G106: =G126 -> 129.0935 | H106: =H126 -> 194.25724 | I106: =I126 -> 199.28785 | J106: =J126 -> 191.36819 | K106: =K126 -> 184.04535 | L106: =L126 -> 213.8718 | M106: =M126 -> 213.30574 | N106: =N126 -> 240.43146 | ... Q106: =Q126 -> 282.42009
A107: Amortização de Dívidas | G107: =-G122 -> -52.464 | H107: =-H122 -> -184.376 | I107: =-I122 -> -50.375 | J107: =-J122 -> -47.5 | K107: =-K122 -> -129.0935 | L107: =-L122 -> -194.25724 | M107: =-M122 -> -199.28785 | N107: =-N122 -> -191.36819 | ... Q107: =-Q122 -> -213.30574
A108: Dividendos pagos | D108: -190.742 | E108: -159 | F108: -90.816 | G108: =-F65*G67 -> -174.3965 | H108: =-G65*H67 -> -303.11583 | I108: =-H65*I67 -> -331.61057 | J108: =-I65*J67 -> -368.77966 | K108: =-J65*K67 -> -417.42543 | L108: =-K65*L67 -> -463.3336 | M108: =-L65*M67 -> -510.46225 | N108: =-M65*N67 -> -560.55408 | ... Q108: =-P65*Q67 -> -906.26971
A109: Mútuos Pagos
A110: Fluxo de Caixa de Financiamentos | G110: =SUM(G104:G109) -> -97.767005 | H110: =SUM(H104:H109) -> -293.23459 | I110: =SUM(I104:I109) -> -182.69773 | J110: =SUM(J104:J109) -> -224.91147 | K110: =SUM(K104:K109) -> -362.47357 | L110: =SUM(L104:L109) -> -443.71904 | M110: =SUM(M104:M109) -> -496.44436 | N110: =SUM(N104:N109) -> -511.49081 | ... Q110: =SUM(Q104:Q109) -> -837.15536
A112: Variação de Caixa | G112: =G99+G102+G110 -> 81.674681 | H112: =H99+H102+H110 -> -75.313869 | I112: =I99+I102+I110 -> 30.198502 | J112: =J99+J102+J110 -> 49.740852 | K112: =K99+K102+K110 -> -21.571316 | L112: =L99+L102+L110 -> -39.022718 | M112: =M99+M102+M110 -> -26.074418 | N112: =N99+N102+N110 -> 29.030347 | ... Q112: =Q99+Q102+Q110 -> -62.465421
A113: Caixa Inicial | G113: =F8 -> 13.125 | H113: =G114 -> 94.799681 | I113: =H114 -> 19.485812 | J113: =I114 -> 49.684314 | K113: =J114 -> 99.425166 | L113: =K114 -> 77.853849 | M113: =L114 -> 38.831131 | N113: =M114 -> 12.756713 | O113: =N114 -> 41.78706 | ... Q113: =P114 -> 101.17529
A114: Caixa Final | G114: =G112+G113 -> 94.799681 | H114: =H112+H113 -> 19.485812 | I114: =I112+I113 -> 49.684314 | J114: =J112+J113 -> 99.425166 | K114: =K112+K113 -> 77.853849 | L114: =L112+L113 -> 38.831131 | M114: =M112+M113 -> 12.756713 | N114: =N112+N113 -> 41.78706 | ... Q114: =Q112+Q113 -> 38.70987
A116: Dívida e Resultado Financeiro | C116: =C88 -> 2008 | D116: =D88 -> 2009 | E116: =E88 -> 2010 | F116: =F88 -> 2011 | G116: =G88 -> 2012E | H116: =H88 -> 2013E | I116: =I88 -> 2014E | J116: =J88 -> 2015E | ... Q116: =Q88 -> 2022E
A117: Resultado Financeiro Líquido | D117: =D60 -> -19.662 | E117: =E60 -> -13.502 | F117: =F60 -> -44.218 | G117: =-F82*G118 -> -33.698562 | H117: =-G82*H118 -> -32.972557 | I117: =-H82*I118 -> -42.838445 | J117: =-I82*J118 -> -54.179139 | K117: =-J82*K118 -> -62.430681 | L117: =-K82*L118 -> -70.197783 | M117: =-L82*M118 -> -76.149467 | N117: =-M82*N118 -> -80.218836 | ... Q117: =-P82*Q118 -> -89.746048
A118: Custo Médio de Dívida | D118: =-D117/AVERAGE(C82:D82) -> 0.15509122 | E118: =-E117/AVERAGE(D82:E82) -> 0.056435753 | F118: =-F117/AVERAGE(E82:F82) -> 0.12939076 | G118: =G119+G120 -> 0.104625 | H118: =H119+H120 -> 0.104 | I118: =I119+I120 -> 0.1065 | J118: =J119+J120 -> 0.104 | K118: =K119+K120 -> 0.1015 | L118: =L119+L120 -> 0.1015 | M118: =M119+M120 -> 0.1015 | N118: =N119+N120 -> 0.1015 | ... Q118: =Q119+Q120 -> 0.1015
A119: -- Selic Média | D119: =Cenário!L19/100 -> 0.099166667 | E119: =Cenário!M19/100 -> 0.1 | F119: =Cenário!R19/100 -> 0.11708333 | G119: =Cenário!W19/100 -> 0.093125 | H119: =Cenário!X19/100 -> 0.0925 | I119: =Cenário!Y19/100 -> 0.095 | J119: =Cenário!Z19/100 -> 0.0925 | K119: =Cenário!AA19/100 -> 0.09 | L119: =Cenário!AB19/100 -> 0.09 | M119: =Cenário!AC19/100 -> 0.09 | N119: =M119 -> 0.09 | O119: =N119 -> 0.09 | P119: =O119 -> 0.09 | Q119: =P119 -> 0.09
A120: -- Spread Médio | D120: =+D118-D119 -> 0.055924557 | E120: =+E118-E119 -> -0.043564247 | F120: =+F118-F119 -> 0.012307432 | G120: 0.0115 | H120: 0.0115 | I120: 0.0115 | J120: 0.0115 | K120: 0.0115 | L120: 0.0115 | M120: 0.0115 | N120: 0.0115 | O120: 0.0115 | P120: 0.0115 | Q120: 0.0115
A122: Cronograma de Amortização de Dívida | G122: =+G123+G124 -> 52.464 | H122: =+H123+H124 -> 184.376 | I122: =+I123+I124 -> 50.375 | J122: =+J123+J124 -> 47.5 | K122: =+K123+K124 -> 129.0935 | L122: =+L123+L124 -> 194.25724 | M122: =+M123+M124 -> 199.28785 | N122: =+N123+N124 -> 191.36819 | ... Q122: =+Q123+Q124 -> 213.30574
A123: -- Dívida Antiga | G123: =+F21 -> 52.464 | H123: =(2.875*2)+37.5+10+127.126+4 -> 184.376 | I123: =2.875+37.5+10 -> 50.375 | J123: =37.5+10 -> 47.5 | K123: =G126 -> 129.0935 | L123: =H126 -> 194.25724 | M123: =I126 -> 199.28785 | N123: =J126 -> 191.36819 | O123: =K126 -> 184.04535 | P123: =L126 -> 213.8718 | Q123: =M126 -> 213.30574
A124: -- Novas Dívidas
A126: Novas Dívidas | G126: =G127*G89 -> 129.0935 | H126: =H127*H89 -> 194.25724 | I126: =I127*I89 -> 199.28785 | J126: =J127*J89 -> 191.36819 | K126: =K127*K89 -> 184.04535 | L126: =L127*L89 -> 213.8718 | M126: =M127*M89 -> 213.30574 | N126: =N127*N89 -> 240.43146 | ... Q126: =Q127*Q89 -> 282.42009
G127: 0.5 | H127: 0.65 | I127: 0.65 | J127: 0.5 | K127: 0.4 | L127: 0.4 | M127: 0.35 | N127: 0.35 | O127: 0.3 | P127: 0.3 | Q127: 0.3
A128: Receita / (CCR + Cemig) | C128: =C116 -> 2008 | D128: =D116 -> 2009 | E128: =E116 -> 2010 | F128: =F116 -> 2011 | G128: =G116 -> 2012E | H128: =H116 -> 2013E | I128: =I116 -> 2014E | J128: =J116 -> 2015E | ... Q128: =Q116 -> 2022E
A129: Water Port | F129: =F93/(F90+F91) -> 0.078838174 | G129: 0.078838174 | H129: 0.078838174 | I129: 0 | J129: 0 | K129: 0 | L129: 0 | M129: 0 | N129: 0 | O129: 0 | P129: 0 | Q129: 0
A130: Sanepar | F130: =F94/(F90+F91) -> 0.045643154 | G130: =G94/(G90+G91) -> 0.026943739 | H130: =H94/(H90+H91) -> 0.034551137 | I130: =I94/(I90+I91) -> 0.032803383 | J130: =J94/(J90+J91) -> 0.027448464 | K130: =K94/(K90+K91) -> 0.023774616 | L130: =L94/(L90+L91) -> 0.024450037 | M130: =M94/(M90+M91) -> 0.022370325 | ... Q130: =Q94/(Q90+Q91) -> 0.017182577
A133: Lucro Líquido Sanepar | F133: 249.17 | G133: =F133*(1+(Cenário!W9/100)) -> 262.12684 | H133: =G133*(1+(Cenário!X9/100)) -> 276.01956 | I133: =H133*(1+(Cenário!Y9/100)) -> 289.82054 | J133: =I133*(1+(Cenário!Z9/100)) -> 304.31157 | K133: =J133*(1+(Cenário!AA9/100)) -> 318.00559 | L133: =K133*(1+(Cenário!AB9/100)) -> 332.31584 | M133: =L133*(1+(Cenário!AC9/100)) -> 347.27005 | N133: =M133*(1+(Cenário!AD9/100)) -> 362.8972 | ... Q133: =P133*(1+(Cenário!AG9/100)) -> 414.126

Sheet Cash Flow CCR
A1: CCR
A3: Cash Flow | C3: 2008 | D3: 2009 | E3: 2010 | F3: 2011 | G3: 2012E | H3: 2013E | I3: 2014E | J3: 2015E | K3: 2016E | L3: 2017E | M3: 2018E | N3: 2019E | O3: 2020E | P3: 2021E | Q3: 2022E
A4: EBITDA | G4: 3416.5 | H4: 3975.5 | I4: 4459.5 | J4: 5035.4 | K4: 5592.1 | L4: 6273 | M4: 6972.9 | N4: 8010.4 | O4: 8891.1 | P4: 8198.6 | Q4: 7470.2
A5: Variação de Capital de Giro | G5: 67.5 | H5: 20.2 | I5: 19.4 | J5: 14.7 | K5: 18.1 | L5: 23.9 | M5: 26.4 | N5: 23.1 | O5: 31.9 | P5: -32.1 | Q5: -30.2
A6: Resultado Financeiro Líquido | G6: -704.4 | H6: -689.9 | I6: -498.3 | J6: -369.5 | K6: -194.5 | L6: -12.5 | M6: 196.6 | N6: 422.9 | O6: 725.8 | P6: 1013 | Q6: 1095
A7: IR | G7: -627.5 | H7: -735.8 | I7: -977.3 | J7: -1228.2 | K7: -1456 | L7: -1766.5 | M7: -2092.4 | N7: -2538.8 | O7: -2948.4 | P7: -2831.8 | Q7: -2629.7
A8: Fluxo de Caixa Operacional | C8: 690.701 | D8: 403.695 | E8: 1357.065 | F8: 1890.267 | G8: =SUM(G4:G7) -> 2152.1 | H8: =SUM(H4:H7) -> 2570 | I8: =SUM(I4:I7) -> 3003.3 | J8: =SUM(J4:J7) -> 3452.4 | K8: =SUM(K4:K7) -> 3959.7 | L8: =SUM(L4:L7) -> 4517.9 | M8: =SUM(M4:M7) -> 5103.5 | N8: =SUM(N4:N7) -> 5917.6 | ... Q8: =SUM(Q4:Q7) -> 5905.3
A10: Capex | G10: -676 | H10: -822 | I10: -802 | J10: -555 | K10: -356 | L10: -360 | M10: -359 | N10: -320 | O10: -327 | P10: -334 | Q10: -200
A11: Fluxo de Caixa de Investimentos | C11: -1112.136 | D11: -931.477 | E11: -2237.474 | F11: -658.736 | G11: =G10 -> -676 | H11: =H10 -> -822 | I11: =I10 -> -802 | J11: =J10 -> -555 | K11: =K10 -> -356 | L11: =L10 -> -360 | M11: =M10 -> -359 | N11: =N10 -> -320 | ... Q11: =Q10 -> -200
A14: Novas Dívidas | G14: 271 | H14: 329 | I14: 321 | J14: 222 | K14: 143 | L14: 144 | M14: 143 | N14: 128 | O14: 131 | P14: 133 | Q14: 80
A15: Novos aportes de Capital | G15: -71
A16: Dividendos Pagos | C16: -604.653 | D16: -603.385 | E16: -851.898 | F16: -806.766 | G16: =-F31*G43 -> -719.4976 | H16: =-G31*H43 -> -1030.16 | I16: =-H31*I43 -> -1163.82 | J16: =-I31*J43 -> -1473.71 | K16: =-J31*K43 -> -1782.55 | L16: =-K31*L43 -> -2102.03 | M16: =-L31*M43 -> -2435.3 | N16: =-M31*N43 -> -2781.59 | ... Q16: =-P31*Q43 -> -3643.78
A17: Fluxo de Caixa de Financiamentos | C17: 678.938 | D17: 1611.056 | E17: -62.067 | F17: -1646.869 | G17: =SUM(G14:G16) -> -519.4976 | H17: =SUM(H14:H16) -> -701.16 | I17: =SUM(I14:I16) -> -842.82 | J17: =SUM(J14:J16) -> -1251.71 | K17: =SUM(K14:K16) -> -1639.55 | L17: =SUM(L14:L16) -> -1958.03 | M17: =SUM(M14:M16) -> -2292.3 | N17: =SUM(N14:N16) -> -2653.59 | ... Q17: =SUM(Q14:Q16) -> -3563.78
A19: Variação de Caixa | C19: =C8+C11+C17 -> 257.503 | D19: =D8+D11+D17 -> 1083.274 | E19: =E8+E11+E17 -> -942.476 | F19: =F8+F11+F17 -> -415.338 | G19: =G8+G11+G17 -> 956.6024 | H19: =H8+H11+H17 -> 1046.84 | I19: =I8+I11+I17 -> 1358.48 | J19: =J8+J11+J17 -> 1645.69 | ... Q19: =Q8+Q11+Q17 -> 2141.52
A20: Caixa Inicial | D20: =C21 -> 1038 | E20: =D21 -> 2121.274 | F20: =E21 -> 1178.798 | G20: =F21 -> 763.46 | H20: =G21 -> 1720.0624 | I20: =H21 -> 2766.9024 | J20: =I21 -> 4125.3824 | K20: =J21 -> 5771.0724 | ... Q20: =P21 -> 20933.752
A21: Caixa Final | C21: =C34 -> 1038 | D21: =D19+D20 -> 2121.274 | E21: =E19+E20 -> 1178.798 | F21: =F20+F19 -> 763.46 | G21: =G20+G19 -> 1720.0624 | H21: =H20+H19 -> 2766.9024 | I21: =I20+I19 -> 4125.3824 | J21: =J20+J19 -> 5771.0724 | K21: =K20+K19 -> 7735.2224 | L21: =L20+L19 -> 9935.0924 | M21: =M20+M19 -> 12387.292 | ... Q21: =Q20+Q19 -> 23075.272
A23: Destaques | C23: =C3 -> 2008 | D23: =D3 -> 2009 | E23: =E3 -> 2010 | F23: =F3 -> 2011 | G23: =G3 -> 2012E | H23: =H3 -> 2013E | I23: =I3 -> 2014E | J23: =J3 -> 2015E | ... Q23: =Q3 -> 2022E
A25: Receita Bruta | C25: 2832.122 | D25: 4108.405 | E25: 5043.7052 | F25: 5599.2855 | G25: 6186.9628 | H25: 6961.3516 | I25: 7702.1486 | J25: 8264.83 | K25: 8958.2001 | L25: 9872.6284 | M25: 10883.259 | N25: 11766.426 | O25: 12985.458 | P25: 11759.031 | Q25: 10604.534
A26: Receita Líquida | C26: 2614.76 | D26: 3810.412 | E26: 4657.4452 | F26: 5134.2949 | G26: 5673.1687 | H26: 6383.2487 | I26: 7062.5264 | J26: 7578.4802 | K26: 8214.2697 | L26: 9052.7596 | M26: 9979.4629 | N26: 10789.287 | O26: 11907.085 | P26: 10782.507 | Q26: 9723.8844
A28: EBITDA | C28: 1600.7158 | D28: 2104.1459 | E28: 2260.3201 | F28: 2930.7326 | G28: 3416.5246 | H28: 3975.5338 | I28: 4459.4876 | J28: 5035.3919 | K28: 5592.1349 | L28: 6272.9875 | M28: 6972.9374 | N28: 8010.439 | O28: 8891.1325 | P28: 8198.5891 | Q28: 7470.2202
A29: --Mg. EBITDA Aj. (Ex Receitas de Construção) | C29: 0.61218461 | D29: 0.68269957 | E29: 0.598595 | F29: 0.64023752 | G29: 0.66052801 | H29: 0.6758245 | I29: 0.68267408 | J29: 0.69296391 | K29: 0.70293438 | L29: 0.71329686 | M29: 0.71722784 | N29: 0.76097864 | O29: 0.76391354 | P29: 0.78014815 | Q29: 0.78076224
A31: Lucro Líquido | C31: 594.1 | D31: 708.741 | E31: 671.722 | F31: 899.372 | G31: 1287.7 | H31: 1662.6 | I31: 2105.3 | J31: 2546.5 | K31: 3002.9 | L31: 3479 | M31: 3973.7 | N31: 4702.6 | O31: 5366.9 | P31: 5205.4 | Q31: 4942.8
A33: Dívida Total | C33: 3722 | D33: 5035 | E33: 6711 | F33: 6948 | G33: 7248 | H33: 7591 | I33: 7936 | J33: 8181 | K33: 8346 | L33: 8510 | M33: 8675 | N33: 8824 | O33: 8976 | P33: 9130 | Q33: 9231
A34: Caixa | C34: 1038 | D34: 2121 | E34: 1179 | F34: 763 | G34: 1746 | H34: 3862 | I34: 5488 | J34: 7493 | K34: 9705 | L34: 12218 | M34: 14912 | N34: 18450 | O34: 21818 | P34: 22876 | Q34: 24889
A35: Dívida Líquida | C35: =C33-C34 -> 2684 | D35: =D33-D34 -> 2914 | E35: =E33-E34 -> 5532 | F35: =F33-F34 -> 6185 | G35: =G33-G34 -> 5502 | H35: =H33-H34 -> 3729 | I35: =I33-I34 -> 2448 | J35: =J33-J34 -> 688 | ... Q35: =Q33-Q34 -> -15658
A37: Patrimônio Líquido | C37: 1579 | D37: 2890 | E37: 3109 | F37: 3205 | G37: 3729 | H37: 4362 | I37: 5303 | J37: 6376 | K37: 7596 | L37: 8973 | M37: 10512 | N37: 12433 | O37: 14508 | P37: 15956 | Q37: 17255
A39: Dívida Liquida / EBITDA | C39: =C35/C28 -> 1.6767498 | D39: =D35/D28 -> 1.384885 | E39: =E35/E28 -> 2.4474409 | F39: =F35/F28 -> 2.1103938 | G39: =G35/G28 -> 1.6104084 | H39: =H35/H28 -> 0.93798724 | I39: =I35/I28 -> 0.54894199 | J39: =J35/J28 -> 0.13663286 | ... Q39: =Q35/Q28 -> -2.096056
A40: Dívida Total / PL | C40: =C33/C37 -> 2.3571881 | D40: =D33/D37 -> 1.7422145 | E40: =E33/E37 -> 2.1585719 | F40: =F33/F37 -> 2.1678627 | G40: =G33/G37 -> 1.9436846 | H40: =H33/H37 -> 1.7402568 | I40: =I33/I37 -> 1.4965114 | J40: =J33/J37 -> 1.2830928 | ... Q40: =Q33/Q37 -> 0.53497537
A41: Dívida Líquida / PL | C41: =C35/C37 -> 1.69981 | D41: =D35/D37 -> 1.0083045 | E41: =E35/E37 -> 1.7793503 | F41: =F35/F37 -> 1.9297972 | G41: =G35/G37 -> 1.4754626 | H41: =H35/H37 -> 0.85488308 | I41: =I35/I37 -> 0.4616255 | J41: =J35/J37 -> 0.10790464 | ... Q41: =Q35/Q37 -> -0.90744712
A42: FCF / Dívida Total | C42: =(C8+C11)/C33 -> -0.1132281 | D42: =(D8+D11)/D33 -> -0.10482264 | E42: N/A | F42: =(F8+F11)/F33 -> 0.17724971 | G42: =(G8+G11)/G33 -> 0.20365618 | H42: =(H8+H11)/H33 -> 0.23027269 | I42: =(I8+I11)/I33 -> 0.27738155 | J42: =(J8+J11)/J33 -> 0.35416208 | K42: =(K8+K11)/K33 -> 0.43178768 | L42: =(L8+L11)/L33 -> 0.48858989 | M42: =(M8+M11)/M33 -> 0.54691643 | ... Q42: =(Q8+Q11)/Q33 -> 0.61805872
A43: Payout Dividendos | C43: =ABS(C16/C31) -> 1.017763 | D43: =ABS(D16/D31) -> 0.85134767 | E43: =ABS(E16/E31) -> 1.26823 | F43: =ABS(F16/E31) -> 1.2010415 | G43: 0.8 | H43: 0.8 | I43: 0.7 | J43: 0.7 | K43: 0.7 | L43: 0.7 | M43: 0.7 | N43: 0.7 | O43: 0.7 | P43: 0.7 | Q43: 0.7
F47: =F23 -> 2011 | G47: =G23 -> 2012E | H47: =H23 -> 2013E | I47: =I23 -> 2014E | J47: =J23 -> 2015E | K47: =K23 -> 2016E | L47: =L23 -> 2017E | M47: =M23 -> 2018E | ... Q47: =Q23 -> 2022E
E48: Lucro Líquido | F48: =F31 -> 899.372 | G48: =G31 -> 1287.7 | H48: =H31 -> 1662.6 | I48: =I31 -> 2105.3 | J48: =J31 -> 2546.5 | K48: =K31 -> 3002.9 | L48: =L31 -> 3479 | M48: =M31 -> 3973.7 | ... Q48: =Q31 -> 4942.8
E49: Payout | F49: =F43 -> 1.2010415 | G49: =G43 -> 0.8 | H49: =H43 -> 0.8 | I49: =I43 -> 0.7 | J49: =J43 -> 0.7 | K49: =K43 -> 0.7 | L49: =L43 -> 0.7 | M49: =M43 -> 0.7 | ... Q49: =Q43 -> 0.7

Sheet Cash Flow Cemig
A1: Cemig
A3: Cash Flow | C3: 2008 | D3: 2009 | E3: 2010 | F3: 2011 | G3: 2012E | H3: 2013E | I3: 2014E | J3: 2015E | K3: 2016E | L3: 2017E | M3: 2018E | N3: 2019E | O3: 2020E | P3: 2021E | Q3: 2022E
A4: Lucro Líquido | E4: 2257.976 | F4: 2415.45 | G4: 2934 | H4: 2874 | I4: 3094 | J4: 3339 | K4: =J4*(1+(Cenário!Z9/100)) -> 3505.95 | L4: =K4*(1+(Cenário!AA9/100)) -> 3663.7178 | M4: =L4*(1+(Cenário!AB9/100)) -> 3828.585 | N4: =M4*(1+(Cenário!AC9/100)) -> 4000.8714 | O4: =N4*(1+(Cenário!AD9/100)) -> 4180.9106 | P4: =O4*(1+(Cenário!AE9/100)) -> 4369.0516 | Q4: =P4*(1+(Cenário!AF9/100)) -> 4565.6589
A5: Depreciação | G5: 1015 | H5: 1050 | I5: 1066 | J5: 1081 | K5: =J5*(1+(Cenário!Z9/100)) -> 1135.05 | L5: =K5*(1+(Cenário!AA9/100)) -> 1186.1272 | M5: =L5*(1+(Cenário!AB9/100)) -> 1239.503 | N5: =M5*(1+(Cenário!AC9/100)) -> 1295.2806 | O5: =N5*(1+(Cenário!AD9/100)) -> 1353.5682 | P5: =O5*(1+(Cenário!AE9/100)) -> 1414.4788 | Q5: =P5*(1+(Cenário!AF9/100)) -> 1478.1304
A6: Variação de Capital de Giro | G6: -133 | H6: -116 | I6: -128 | J6: -77 | K6: =J6*(1+(Cenário!Z9/100)) -> -80.85 | L6: =K6*(1+(Cenário!AA9/100)) -> -84.48825 | M6: =L6*(1+(Cenário!AB9/100)) -> -88.290221 | N6: =M6*(1+(Cenário!AC9/100)) -> -92.263281 | O6: =N6*(1+(Cenário!AD9/100)) -> -96.415129 | P6: =O6*(1+(Cenário!AE9/100)) -> -100.75381 | Q6: =P6*(1+(Cenário!AF9/100)) -> -105.28773
A7: Fluxo de Caixa Operacional | G7: =SUM(G4:G6) -> 3816 | H7: =SUM(H4:H6) -> 3808 | I7: =SUM(I4:I6) -> 4032 | J7: =SUM(J4:J6) -> 4343 | K7: =SUM(K4:K6) -> 4560.15 | L7: =SUM(L4:L6) -> 4765.3567 | M7: =SUM(M4:M6) -> 4979.7978 | N7: =SUM(N4:N6) -> 5203.8887 | ... Q7: =SUM(Q4:Q6) -> 5938.5015
A9: Capex | G9: -2755 | H9: -1367 | I9: -1382 | J9: -1291 | K9: =J9*(1+(Cenário!Z9/100)) -> -1355.55 | L9: =K9*(1+(Cenário!AA9/100)) -> -1416.5497 | M9: =L9*(1+(Cenário!AB9/100)) -> -1480.2945 | N9: =M9*(1+(Cenário!AC9/100)) -> -1546.9077 | O9: =N9*(1+(Cenário!AD9/100)) -> -1616.5186 | P9: =O9*(1+(Cenário!AE9/100)) -> -1689.2619 | Q9: =P9*(1+(Cenário!AF9/100)) -> -1765.2787
A10: Fluxo de Caixa de Investimentos | G10: =G9 -> -2755 | H10: =H9 -> -1367 | I10: =I9 -> -1382 | J10: =J9 -> -1291 | K10: =K9 -> -1355.55 | L10: =L9 -> -1416.5497 | M10: =M9 -> -1480.2945 | N10: =N9 -> -1546.9077 | ... Q10: =Q9 -> -1765.2787
A12: Dividendos Pagos | E12: -1828.882 | F12: -2035.62 | G12: =-G4*G40 -> -2347.2 | H12: =-H4*H40 -> -2299.2 | I12: =-H4*I40 -> -2299.2 | J12: =-I4*J40 -> -2475.2 | K12: =-J4*K40 -> -2671.2 | L12: =-K4*L40 -> -2804.76 | M12: =-L4*M40 -> -2930.9742 | N12: =-M4*N40 -> -3062.868 | O12: =-N4*O40 -> -3200.6971 | P12: =-O4*P40 -> -3344.7285 | Q12: =-P4*Q40 -> -3495.2413
A13: Fluxo de Caixa de Financiamentos | G13: =SUM(G12:G12) -> -2347.2 | H13: =SUM(H12:H12) -> -2299.2 | I13: =SUM(I12:I12) -> -2299.2 | J13: =SUM(J12:J12) -> -2475.2 | K13: =SUM(K12:K12) -> -2671.2 | L13: =SUM(L12:L12) -> -2804.76 | M13: =SUM(M12:M12) -> -2930.9742 | N13: =SUM(N12:N12) -> -3062.868 | ... Q13: =SUM(Q12:Q12) -> -3495.2413
A15: Variação de Caixa | C15: =C6+C8+C13 -> 0 | D15: =D6+D8+D13 -> 0 | E15: =E6+E8+E13 -> 0 | F15: =F6+F8+F13 -> 0 | G15: =G7+G10+G13 -> -1286.2 | H15: =H7+H10+H13 -> 141.8 | I15: =I7+I10+I13 -> 350.8 | J15: =J7+J10+J13 -> 576.8 | K15: =K7+K10+K13 -> 533.4 | L15: =L7+L10+L13 -> 544.047 | M15: =M7+M10+M13 -> 568.52911 | N15: =N7+N10+N13 -> 594.11293 | ... Q15: =Q7+Q10+Q13 -> 677.98154
A16: Caixa Inicial | D16: =C17 -> 0 | E16: =D17 -> 0 | F16: =E17 -> 0 | G16: =F17 -> 0 | H16: =G17 -> -1286.2 | I16: =H17 -> -1144.4 | J16: =I17 -> -793.6 | K16: =J17 -> -216.8 | ... Q16: =P17 -> 3292.9232
A17: Caixa Final | C17: =C31 -> 0 | D17: =D15+D16 -> 0 | E17: =E15+E16 -> 0 | F17: =F16+F15 -> 0 | G17: =G16+G15 -> -1286.2 | H17: =H16+H15 -> -1144.4 | I17: =I16+I15 -> -793.6 | J17: =J16+J15 -> -216.8 | K17: =K16+K15 -> 316.6 | L17: =L16+L15 -> 860.647 | M17: =M16+M15 -> 1429.1761 | ... Q17: =Q16+Q15 -> 3970.9048
A19: Destaques | C19: =C3 -> 2008 | D19: =D3 -> 2009 | E19: =E3 -> 2010 | F19: =F3 -> 2011 | G19: =G3 -> 2012E | H19: =H3 -> 2013E | I19: =I3 -> 2014E | J19: =J3 -> 2015E | ... Q19: =Q3 -> 2022E
A21: Dividendos Participação AGC (14.4%) | G21: =ABS(G12)*0.144 -> 337.9968 | H21: =ABS(H12)*0.144 -> 331.0848 | I21: =ABS(I12)*0.144 -> 331.0848 | J21: =ABS(J12)*0.144 -> 356.4288 | K21: =ABS(K12)*0.144 -> 384.6528 | L21: =ABS(L12)*0.144 -> 403.88544 | M21: =ABS(M12)*0.144 -> 422.06028 | N21: =ABS(N12)*0.144 -> 441.053 | ... Q21: =ABS(Q12)*0.144 -> 503.31474
A22: AGC (após encargos e perpétua) | G22: =(G21-G30-G32)*0.6081 -> 111.17357 | H22: =(H21-H30-H32)*0.6081 -> 93.293993 | I22: =(I21-I30-I32)*0.6081 -> 99.009315 | J22: =(J21-J30-J32)*0.6081 -> 121.98081 | K22: =(K21-K30-K32)*0.6081 -> 146.3949 | L22: =(L21-L30-L32)*0.6081 -> 164.57347 | M22: =(M21-M30-M32)*0.6081 -> 182.10879 | N22: =(N21-N30-N32)*0.6081 -> 200.14146 | ... Q22: =(Q21-Q30-Q32)*0.6081 -> 306.05526
A24: Dívida e Resultado Financeiro | C24: =C19 -> 2008 | D24: =D19 -> 2009 | E24: =E19 -> 2010 | F24: =F19 -> 2011 | G24: =G19 -> 2012E | H24: =H19 -> 2013E | I24: =I19 -> 2014E | J24: =J19 -> 2015E | ... Q24: =Q19 -> 2022E
A25: Custo Médio de Dívida | D25: =D26+D27 -> 0.11416667 | E25: =E26+E27 -> 0.115 | F25: =F26+F27 -> 0.13208333 | G25: =G26+G27 -> 0.108125 | H25: =H26+H27 -> 0.1075 | I25: =I26+I27 -> 0.11 | J25: =J26+J27 -> 0.1075 | K25: =K26+K27 -> 0.105 | ... Q25: =Q26+Q27 -> 0.105
A26: -- Selic Média | D26: ='AG Concessões'!D119 -> 0.099166667 | E26: ='AG Concessões'!E119 -> 0.1 | F26: ='AG Concessões'!F119 -> 0.11708333 | G26: ='AG Concessões'!G119 -> 0.093125 | H26: ='AG Concessões'!H119 -> 0.0925 | I26: ='AG Concessões'!I119 -> 0.095 | J26: ='AG Concessões'!J119 -> 0.0925 | K26: ='AG Concessões'!K119 -> 0.09 | ... Q26: ='AG Concessões'!Q119 -> 0.09
A27: -- Spread Médio | D27: 0.015 | E27: 0.015 | F27: 0.015 | G27: 0.015 | H27: 0.015 | I27: 0.015 | J27: 0.015 | K27: 0.015 | L27: 0.015 | M27: 0.015 | N27: 0.015 | O27: 0.015 | P27: 0.015 | Q27: 0.015
A29: Dívida Inicial | G29: =F31 -> 828.308 | H29: =G31 -> 758.94317 | I29: =H31 -> 657.40597 | J29: =I31 -> 555.86877 | K29: =J31 -> 454.33157 | L29: =K31 -> 352.79437 | M29: =L31 -> 251.25717 | N29: =M31 -> 149.71997 | ... Q29: =P31 -> 0.16346
A30: Amortização | G30: =(D31*0.02632)+(D31*0.05921) -> 69.36483 | H30: =$D$31*$D$32 -> 101.5372 | I30: =$D$31*$D$32 -> 101.5372 | J30: =$D$31*$D$32 -> 101.5372 | K30: =$D$31*$D$32 -> 101.5372 | L30: =$D$31*$D$32 -> 101.5372 | M30: =$D$31*$D$32 -> 101.5372 | N30: =$D$31*$D$32 -> 101.5372 | O30: =$D$31*0.05921 -> 48.01931
A31: Dívida Final | D31: 811 | F31: 828.308 | G31: =G29-G30 -> 758.94317 | H31: =H29-H30 -> 657.40597 | I31: =I29-I30 -> 555.86877 | J31: =J29-J30 -> 454.33157 | K31: =K29-K30 -> 352.79437 | L31: =L29-L30 -> 251.25717 | M31: =M29-M30 -> 149.71997 | N31: =N29-N30 -> 48.18277 | ... Q31: =Q29-Q30 -> 0.16346
A32: Juros | D32: 0.1252 | G32: =AVERAGE(G29,G31)*G25 -> 85.810766 | H32: =AVERAGE(H29,H31)*H25 -> 76.128766 | I32: =AVERAGE(I29,I31)*I25 -> 66.730111 | J32: =AVERAGE(J29,J31)*J25 -> 54.298268 | K32: =AVERAGE(K29,K31)*K25 -> 42.374112 | L32: =AVERAGE(L29,L31)*L25 -> 31.712706 | M32: =AVERAGE(M29,M31)*M25 -> 21.0513 | N32: =AVERAGE(N29,N31)*N25 -> 10.389894 | ... Q32: =AVERAGE(Q29,Q31)*Q25 -> 0.0171633
A40: Payout Dividendos | C40: =ABS(C12/C28) -> #DIV/0! | D40: =ABS(D12/D28) -> #DIV/0! | E40: =ABS(E12/E4) -> 0.80996521 | F40: =ABS(F12/F4) -> 0.8427498 | G40: 0.8 | H40: 0.8 | I40: 0.8 | J40: 0.8 | K40: 0.8 | L40: 0.8 | M40: 0.8 | N40: 0.8 | O40: 0.8 | P40: 0.8 | Q40: 0.8
F43: =F24 -> 2011 | G43: =G24 -> 2012E | H43: =H24 -> 2013E | I43: =I24 -> 2014E | J43: =J24 -> 2015E | K43: =K24 -> 2016E | L43: =L24 -> 2017E | M43: =M24 -> 2018E | ... Q43: =Q24 -> 2022E
E44: Lucro Líquido | F44: =F4 -> 2415.45 | G44: =G4 -> 2934 | H44: =H4 -> 2874 | I44: =I4 -> 3094 | J44: =J4 -> 3339 | K44: =K4 -> 3505.95 | L44: =L4 -> 3663.7178 | M44: =M4 -> 3828.585 | ... Q44: =Q4 -> 4565.6589
E45: Payout | F45: =F40 -> 0.8427498 | G45: =G40 -> 0.8 | H45: =H40 -> 0.8 | I45: =I40 -> 0.8 | J45: =J40 -> 0.8 | K45: =K40 -> 0.8 | L45: =L40 -> 0.8 | M45: =M40 -> 0.8 | ... Q45: =Q40 -> 0.8

Sheet Cenário
A2: Indicadores Econômicos
C3: 0Q2000 | D3: 0Q2001 | E3: 0Q2002 | F3: 0Q2003 | G3: 0Q2004 | H3: 0Q2005 | I3: 0Q2006 | J3: 0Q2007 | K3: 0Q2008 | L3: 0Q2009 | M3: 0Q2010 | N3: 1Q2011 | O3: 2Q2011 | P3: 3Q2011 | Q3: 4Q2011 | R3: 0Q2011 | S3: 1Q2012 | T3: 2Q2012 | U3: 3Q2012 | V3: 4Q2012 | W3: 0Q2012 | X3: 0Q2013 | Y3: 0Q2014 | Z3: 0Q2015 | AA3: 0Q2016 | AB3: 0Q2017 | AC3: 0Q2018
C4: 2000 | D4: 2001 | E4: 2002 | F4: 2003 | G4: 2004 | H4: 2005 | I4: 2006 | J4: 2007 | K4: 2008 | L4: 2009 | M4: 2010 | N4: 1Q11 | O4: 2Q11 | P4: 3Q11 | Q4: 4Q11 | R4: 2011 | S4: 1Q12 | T4: 2Q12 | U4: 3Q12 | V4: 4Q12 | W4: 2012 | X4: 2013 | Y4: 2014 | Z4: 2015 | AA4: 2016 | AB4: 2017 | AC4: 2018 | AD4: 2019 | AE4: 2020 | AF4: 2021 | AG4: 2022
A5: PIB
A6: Crescimento Real | B6: ECO_GDP_REAL_GROWTH | C6: ='[6]Cen. Basico'!C6 -> 4.31 | D6: ='[6]Cen. Basico'!D6 -> 1.31 | E6: ='[6]Cen. Basico'!E6 -> 2.66 | F6: ='[6]Cen. Basico'!F6 -> 1.15 | G6: ='[6]Cen. Basico'!G6 -> 5.71 | H6: ='[6]Cen. Basico'!H6 -> 3.16 | I6: ='[6]Cen. Basico'!I6 -> 3.97 | J6: ='[6]Cen. Basico'!J6 -> 6.1 | ... AC6: ='[6]Cen. Basico'!AC6 -> 4.5 | AD6: 4.5 | AE6: 4.5 | AF6: 4.5 | AG6: 4.5
A8: Inflação
A9: IPCA | B9: ECO_IPCA | C9: ='[6]Cen. Basico'!C9 -> 6 | D9: ='[6]Cen. Basico'!D9 -> 7.7 | E9: ='[6]Cen. Basico'!E9 -> 12.5 | F9: ='[6]Cen. Basico'!F9 -> 9.3 | G9: ='[6]Cen. Basico'!G9 -> 7.6 | H9: ='[6]Cen. Basico'!H9 -> 5.7 | I9: ='[6]Cen. Basico'!I9 -> 3.14 | J9: ='[6]Cen. Basico'!J9 -> 4.46 | ... AC9: ='[6]Cen. Basico'!AC9 -> 4.5 | AD9: 4.5 | AE9: 4.5 | AF9: 4.5 | AG9: 4.5
A10: IGPM | B10: ECO_IGPM | C10: ='[6]Cen. Basico'!C10 -> 9.81 | D10: ='[6]Cen. Basico'!D10 -> 10.4 | E10: ='[6]Cen. Basico'!E10 -> 25.3 | F10: ='[6]Cen. Basico'!F10 -> 8.71 | G10: ='[6]Cen. Basico'!G10 -> 12.41 | H10: ='[6]Cen. Basico'!H10 -> 1.2 | I10: ='[6]Cen. Basico'!I10 -> 3.85 | J10: ='[6]Cen. Basico'!J10 -> 7.75 | ... AC10: ='[6]Cen. Basico'!AC10 -> 4.5 | AD10: 4.5 | AE10: 4.5 | AF10: 4.5 | AG10: 4.5
A12: Taxa de Câmbio
A13: Variação Nominal | B13: ECO_FX_NOMINAL_VARIATION | C13: ='[6]Cen. Basico'!C13 -> 9 | D13: ='[6]Cen. Basico'!D13 -> 19 | E13: ='[6]Cen. Basico'!E13 -> 53.546713 | F13: ='[6]Cen. Basico'!F13 -> -18.176702 | G13: ='[6]Cen. Basico'!G13 -> -8.1268171 | H13: ='[6]Cen. Basico'!H13 -> -11.818113 | I13: ='[6]Cen. Basico'!I13 -> -8.6598026 | J13: ='[6]Cen. Basico'!J13 -> -17.151543 | ... AC13: ='[6]Cen. Basico'!AC13 -> 2.4509804 | AD13: 2.4509804
A14: R$/US$ (fim de período) | B14: ECO_FX_USD | C14: ='[6]Cen. Basico'!C14 -> 1.9554 | D14: ='[6]Cen. Basico'!D14 -> 2.3204 | E14: ='[6]Cen. Basico'!E14 -> 3.5333 | F14: ='[6]Cen. Basico'!F14 -> 2.8892 | G14: ='[6]Cen. Basico'!G14 -> 2.6544 | H14: ='[6]Cen. Basico'!H14 -> 2.3407 | I14: ='[6]Cen. Basico'!I14 -> 2.138 | J14: ='[6]Cen. Basico'!J14 -> 1.7713 | ... AC14: ='[6]Cen. Basico'!AC14 -> 2.054265 | AD14: 2.054265
A15: R$/US$ (média) | B15: ECO_FX_USD_AVG | C15: ='[6]Cen. Basico'!C15 -> 1.8301417 | D15: ='[6]Cen. Basico'!D15 -> 2.3505 | E15: ='[6]Cen. Basico'!E15 -> 2.9284262 | F15: ='[6]Cen. Basico'!F15 -> 3.0715261 | G15: ='[6]Cen. Basico'!G15 -> 2.924932 | H15: ='[6]Cen. Basico'!H15 -> 2.4340873 | I15: ='[6]Cen. Basico'!I15 -> 2.177 | J15: ='[6]Cen. Basico'!J15 -> 1.948 | ... AC15: ='[6]Cen. Basico'!AC15 -> 2.0296924 | AD15: 2.0296924
A17: Taxa de Juros
A18: Selic (fim de período) | B18: ECO_IR_EOP | C18: ='[6]Cen. Basico'!C18 -> 15.75 | D18: ='[6]Cen. Basico'!D18 -> 19 | E18: ='[6]Cen. Basico'!E18 -> 25 | F18: ='[6]Cen. Basico'!F18 -> 16.5 | G18: ='[6]Cen. Basico'!G18 -> 17.75 | H18: ='[6]Cen. Basico'!H18 -> 18 | I18: ='[6]Cen. Basico'!I18 -> 13.25 | J18: ='[6]Cen. Basico'!J18 -> 11.25 | ... AC18: ='[6]Cen. Basico'!AC18 -> 9 | AD18: 9 | AE18: 9 | AF18: 9 | AG18: 9
A19: Selic (média) | B19: ECO_IR_AVG | C19: ='[6]Cen. Basico'!C19 -> 17.6 | D19: ='[6]Cen. Basico'!D19 -> 17.4 | E19: ='[6]Cen. Basico'!E19 -> 19.1 | F19: ='[6]Cen. Basico'!F19 -> 23.35 | G19: ='[6]Cen. Basico'!G19 -> 16.25 | H19: ='[6]Cen. Basico'!H19 -> 19.1 | I19: ='[6]Cen. Basico'!I19 -> 15.06 | J19: ='[6]Cen. Basico'!J19 -> 11.979167 | ... AC19: ='[6]Cen. Basico'!AC19 -> 9 | AD19: 9 | AE19: 9 | AF19: 9 | AG19: 9
A20: Real - IPCA (média) | B20: ECO_SELIC_REAL_IPCA_AVG | C20: ='[6]Cen. Basico'!C20 -> 10.943396 | D20: ='[6]Cen. Basico'!D20 -> 9.0064995 | E20: ='[6]Cen. Basico'!E20 -> 5.8666667 | F20: ='[6]Cen. Basico'!F20 -> 12.854529 | G20: ='[6]Cen. Basico'!G20 -> 8.0390335 | H20: ='[6]Cen. Basico'!H20 -> 12.677389 | I20: ='[6]Cen. Basico'!I20 -> 11.557107 | J20: ='[6]Cen. Basico'!J20 -> 7.1981301 | ... AC20: ='[6]Cen. Basico'!AC20 -> 4.3062201 | AD20: 4.3062201 | AE20: 4.3062201 | AF20: 4.3062201 | AG20: 4.3062201
A21: Real - IGPM (média) | B21: ECO_SELIC_REAL_IGPM_AVG | C21: ='[6]Cen. Basico'!C21 -> 7.0940716 | D21: ='[6]Cen. Basico'!D21 -> 6.3405797 | E21: ='[6]Cen. Basico'!E21 -> -4.9481245 | F21: ='[6]Cen. Basico'!F21 -> 13.467022 | G21: ='[6]Cen. Basico'!G21 -> 3.4160662 | H21: ='[6]Cen. Basico'!H21 -> 17.687747 | I21: ='[6]Cen. Basico'!I21 -> 10.794415 | J21: ='[6]Cen. Basico'!J21 -> 3.9249807 | ... AC21: ='[6]Cen. Basico'!AC21 -> 4.3062201 | AD21: 4.3062201 | AE21: 4.3062201 | AF21: 4.3062201 | AG21: 4.3062201
A22: Selic média (US$) - (fim de período) | B22: ECO_IR_SELIC_USD_AVG | C22: ='[6]Cen. Basico'!C22 -> 7.8899083 | D22: ='[6]Cen. Basico'!D22 -> -1.3445378 | E22: ='[6]Cen. Basico'!E22 -> -22.434028 | F22: ='[6]Cen. Basico'!F22 -> 50.751685 | G22: ='[6]Cen. Basico'!G22 -> 26.533115 | H22: ='[6]Cen. Basico'!H22 -> 35.061751 | I22: ='[6]Cen. Basico'!I22 -> 25.968635 | J22: ='[6]Cen. Basico'!J22 -> 35.16144 | ... AC22: ='[6]Cen. Basico'!AC22 -> 6.3923445 | AD22: 6.3923445 | AE22: 6.3923445 | AF22: 6.3923445 | AG22: 6.3923445
A24: Contas Públicas
A25: Superávit Primário - % do PIB | B25: ECO_SURPLUS_GDP | H25: ='[6]Cen. Basico'!H25 -> 3.785602 | I25: ='[6]Cen. Basico'!I25 -> 3.2038801 | J25: ='[6]Cen. Basico'!J25 -> 3.30953 | K25: ='[6]Cen. Basico'!K25 -> 3.4165002 | L25: ='[6]Cen. Basico'!L25 -> 1.9994062 | M25: ='[6]Cen. Basico'!M25 -> 2.6974469 | N25: ='[6]Cen. Basico'!N25 | O25: ='[6]Cen. Basico'!O25 | ... AC25: ='[6]Cen. Basico'!AC25 -> 2.9 | AD25: 2.9
A26: Dívida Pública Líquida - % do PIB | B26: ECO_DEBT_GDP | H26: ='[6]Cen. Basico'!H26 -> 48.436442 | I26: ='[6]Cen. Basico'!I26 -> 47.269901 | J26: ='[6]Cen. Basico'!J26 -> 45.531982 | K26: ='[6]Cen. Basico'!K26 -> 38.52771 | L26: ='[6]Cen. Basico'!L26 -> 42.066711 | M26: ='[6]Cen. Basico'!M26 -> 39.145541 | N26: ='[6]Cen. Basico'!N26 | O26: ='[6]Cen. Basico'!O26 | ... AC26: ='[6]Cen. Basico'!AC26 -> 23.456712 | AD26: 23.456712
