Workbook

Sheet Frente
B2: ORÇAMENTO DE OBRA
B3: Código do Orçamento: | D3: Data: | E3: 42911
B4: Orçamentista: | D4: Revisão: | E4: 00
B6: OBRA:
B7: Nome do Empreendimento: | C7: ----------------------
B8: Incorporador: | C8: ----------------------
B9: Endereço: | C9: ----------------------
B10: Bairro: | C10: ----------------------
B11: Cidade: | C11: ----------------------
B13: PRAZO DA OBRA:
B14: Data de início: | C14: ----------------------
B15: Data de término: | C15: ----------------------
B17: ENCARGOS SOCIAIS: | C17: ----------------------
B19: BDI GERAL: | C19: ---------------------- | D19: 0.1
B21: CUSTO DE CONSTRUÇÃO RASO: | C21: ---------------------- | D21: =ORC_Custo!G33 -> 0
B22: Data base: | C22: ---------------------- | D22: 42887
B23: CUB de Referência | C23: ---------------------- | D23: R16-A
B24: CUB ("n - 1"): | C24: ---------------------- | D24: 1620
B25: Quantidade de CUBs: | C25: ---------------------- | D25: =IF(D24=0,"",D21/D24) -> 0
B27: ÍNDICES (ÁREA EQUIVALENTE):
B28: ÁREA EQUIVALENTE (AE): | C28: ---------------------- | D28: 1500
B29: Custo por m2: | C29: ---------------------- | D29: =IF(D28=0,"",$D$21/D28) -> 0
B30: Custo por m2 em CUBs: | C30: ---------------------- | D30: =IF(D24=0,"",$D29/$D$24) -> 0
B32: ÍNDICES (ÁREA CONSTRUÍDA):
B33: ÁREA CONSTRUÍDA (AC): | C33: ---------------------- | D33: 1750
B34: Custo por m2: | C34: ---------------------- | D34: =IF(D33=0,"",D21/D33) -> 0
B35: Custo por m2 em CUBs: | C35: ---------------------- | D35: =IF(D24=0,"",D25/D33) -> 0
B37: EVENTUAIS | C37: ---------------------- | D37: 0.05
B39: ASSISTÊNCIA TÉCNICA | C39: ---------------------- | D39: 0.015
B41: CUSTO TOTAL DA OBRA: | C41: ---------------------- | D41: =ORC_Custo!G33 -> 0
B42: Data base: | C42: ---------------------- | D42: =D22 -> 42887
B43: =B24 -> CUB ("n - 1"): | C43: ---------------------- | D43: =D24 -> 1620
B44: Quantidade de INCC: | C44: ---------------------- | D44: =D41/D43 -> 0
B46: CUSTO TOTAL DA OBRA COM BDI: | C46: ---------------------- | D46: =D41*(1+D19) -> 0

Sheet ORC_Custo
B2: RESUMO DOS GRUPOS - CUSTOS
B4: GRUPOS | C4: DISCRIMINAÇÃO | D4: PERC. | E4: C.UNIT. (AC) | F4: CUSTO TOTAL | G4: CUSTO TOTAL
D5: % | E5: CUB / m² | F5: CUB's | G5: R$
B7: 01. | C7: SERVIÇOS TÉCNICOS | D7: =IF(G7<>0,G7/$G$33,"") | E7: =IF($E$4="C.UNIT. (AC)",G7/Frente!$D$33,ORC_Custo!G7/Frente!$D$28) -> 0 | F7: =G7/'[1]Folha Frente'!$D$26 -> 0 | G7: ='01.'!K34 -> 0
B8: 02. | C8: GASTOS GERAIS | D8: =IF(G8<>0,G8/$G$33,"") | E8: =IF($E$4="C.UNIT. (AC)",G8/Frente!$D$33,ORC_Custo!G8/Frente!$D$28) -> 0 | F8: =G8/'[1]Folha Frente'!$D$26 -> 0 | G8: ='02.'!K34 -> 0
B9: 03. | C9: PESSOAL PERMANENTE | D9: =IF(G9<>0,G9/$G$33,"") | E9: =IF($E$4="C.UNIT. (AC)",G9/Frente!$D$33,ORC_Custo!G9/Frente!$D$28) -> 0 | F9: =G9/'[1]Folha Frente'!$D$26 -> 0 | G9: ='03.'!K34 -> 0
B10: 04. | C10: IMPLANTAÇÃO DE CANTEIRO | D10: =IF(G10<>0,G10/$G$33,"") | E10: =IF($E$4="C.UNIT. (AC)",G10/Frente!$D$33,ORC_Custo!G10/Frente!$D$28) -> 0 | F10: =G10/'[1]Folha Frente'!$D$26 -> 0 | G10: ='04.'!K34 -> 0
B11: 05. | C11: OPERAÇÃO DE CANTEIRO | D11: =IF(G11<>0,G11/$G$33,"") | E11: =IF($E$4="C.UNIT. (AC)",G11/Frente!$D$33,ORC_Custo!G11/Frente!$D$28) -> 0 | F11: =G11/'[1]Folha Frente'!$D$26 -> 0 | G11: ='05.'!K34 -> 0
B12: 06. | C12: SEGURANÇA E MEDICINA DO TRABALHO | D12: =IF(G12<>0,G12/$G$33,"") | E12: =IF($E$4="C.UNIT. (AC)",G12/Frente!$D$33,ORC_Custo!G12/Frente!$D$28) -> 0 | F12: =G12/'[1]Folha Frente'!$D$26 -> 0 | G12: ='06.'!$K$34 -> 0
B13: 07. | C13: MOVIMENTO DE TERRA | D13: =IF(G13<>0,G13/$G$33,"") | E13: =IF($E$4="C.UNIT. (AC)",G13/Frente!$D$33,ORC_Custo!G13/Frente!$D$28) -> 0 | F13: =G13/'[1]Folha Frente'!$D$26 -> 0 | G13: ='07.'!K34 -> 0
B14: 08. | C14: FUNDAÇÕES E CONTENÇÕES | D14: =IF(G14<>0,G14/$G$33,"") | E14: =IF($E$4="C.UNIT. (AC)",G14/Frente!$D$33,ORC_Custo!G14/Frente!$D$28) -> 0 | F14: =G14/'[1]Folha Frente'!$D$26 -> 0 | G14: ='08.'!K34 -> 0
B15: 09. | C15: SUPERESTRUTURA | D15: =IF(G15<>0,G15/$G$33,"") | E15: =IF($E$4="C.UNIT. (AC)",G15/Frente!$D$33,ORC_Custo!G15/Frente!$D$28) -> 0 | F15: =G15/'[1]Folha Frente'!$D$26 -> 0 | G15: ='09.'!K34 -> 0
B16: 10. | C16: PAREDES E PAINÉIS | D16: =IF(G16<>0,G16/$G$33,"") | E16: =IF($E$4="C.UNIT. (AC)",G16/Frente!$D$33,ORC_Custo!G16/Frente!$D$28) -> 0 | F16: =G16/'[1]Folha Frente'!$D$26 -> 0 | G16: ='10.'!$K$34 -> 0
B17: 11. | C17: COBERTURA | D17: =IF(G17<>0,G17/$G$33,"") | E17: =IF($E$4="C.UNIT. (AC)",G17/Frente!$D$33,ORC_Custo!G17/Frente!$D$28) -> 0 | F17: =G17/'[1]Folha Frente'!$D$26 -> 0 | G17: ='11.'!$K$34 -> 0
B18: 12. | C18: IMPERMEABILIZAÇÃO E TRATAMENTOS | D18: =IF(G18<>0,G18/$G$33,"") | E18: =IF($E$4="C.UNIT. (AC)",G18/Frente!$D$33,ORC_Custo!G18/Frente!$D$28) -> 0 | F18: =G18/'[1]Folha Frente'!$D$26 -> 0 | G18: ='12.'!$K$34 -> 0
B19: 13. | C19: REVESTIMENTOS INTERNOS | D19: =IF(G19<>0,G19/$G$33,"") | E19: =IF($E$4="C.UNIT. (AC)",G19/Frente!$D$33,ORC_Custo!G19/Frente!$D$28) -> 0 | F19: =G19/'[1]Folha Frente'!$D$26 -> 0 | G19: ='13.'!$K$34 -> 0
B20: 14. | C20: REVESTIMENTO EXTERNO | D20: =IF(G20<>0,G20/$G$33,"") | E20: =IF($E$4="C.UNIT. (AC)",G20/Frente!$D$33,ORC_Custo!G20/Frente!$D$28) -> 0 | F20: =G20/'[1]Folha Frente'!$D$26 -> 0 | G20: ='14.'!$K$34 -> 0
B21: 15. | C21: ESQUADRIAS DE MADEIRA | D21: =IF(G21<>0,G21/$G$33,"") | E21: =IF($E$4="C.UNIT. (AC)",G21/Frente!$D$33,ORC_Custo!G21/Frente!$D$28) -> 0 | F21: =G21/'[1]Folha Frente'!$D$26 -> 0 | G21: ='15.'!$K$34 -> 0
B22: 16. | C22: ESQUADRIAS DE ALUMÍNIO E VIDROS | D22: =IF(G22<>0,G22/$G$33,"") | E22: =IF($E$4="C.UNIT. (AC)",G22/Frente!$D$33,ORC_Custo!G22/Frente!$D$28) -> 0 | F22: =G22/'[1]Folha Frente'!$D$26 -> 0 | G22: ='16.'!$K$34 -> 0
B23: 17. | C23: ESQUADRIAS DE FERRO | D23: =IF(G23<>0,G23/$G$33,"") | E23: =IF($E$4="C.UNIT. (AC)",G23/Frente!$D$33,ORC_Custo!G23/Frente!$D$28) -> 0 | F23: =G23/'[1]Folha Frente'!$D$26 -> 0 | G23: ='17.'!$K$34 -> 0
B24: 18. | C24: PISOS INTERNOS | D24: =IF(G24<>0,G24/$G$33,"") | E24: =IF($E$4="C.UNIT. (AC)",G24/Frente!$D$33,ORC_Custo!G24/Frente!$D$28) -> 0 | F24: =G24/'[1]Folha Frente'!$D$26 -> 0 | G24: ='18.'!$K$34 -> 0
B25: 19. | C25: INSTALAÇÕES ELÉTRICAS E ESPECIAIS | D25: =IF(G25<>0,G25/$G$33,"") | E25: =IF($E$4="C.UNIT. (AC)",G25/Frente!$D$33,ORC_Custo!G25/Frente!$D$28) -> 0 | F25: =G25/'[1]Folha Frente'!$D$26 -> 0 | G25: ='19.'!$K$34 -> 0
B26: 20. | C26: INSTALAÇÕES HIDROSSANITÁRIAS | D26: =IF(G26<>0,G26/$G$33,"") | E26: =IF($E$4="C.UNIT. (AC)",G26/Frente!$D$33,ORC_Custo!G26/Frente!$D$28) -> 0 | F26: =G26/'[1]Folha Frente'!$D$26 -> 0 | G26: ='20.'!K34 -> 0
B27: 21. | C27: ELEVADOR E EQUIPAMENTOS MECÂNICOS | D27: =IF(G27<>0,G27/$G$33,"") | E27: =IF($E$4="C.UNIT. (AC)",G27/Frente!$D$33,ORC_Custo!G27/Frente!$D$28) -> 0 | F27: =G27/'[1]Folha Frente'!$D$26 -> 0 | G27: ='21.'!$K$34 -> 0
B28: 22. | C28: LOUÇAS E METAIS | D28: =IF(G28<>0,G28/$G$33,"") | E28: =IF($E$4="C.UNIT. (AC)",G28/Frente!$D$33,ORC_Custo!G28/Frente!$D$28) -> 0 | F28: =G28/'[1]Folha Frente'!$D$26 -> 0 | G28: ='22.'!K34 -> 0
B29: 23. | C29: PINTURA E LIMPEZA | D29: =IF(G29<>0,G29/$G$33,"") | E29: =IF($E$4="C.UNIT. (AC)",G29/Frente!$D$33,ORC_Custo!G29/Frente!$D$28) -> 0 | F29: =G29/'[1]Folha Frente'!$D$26 -> 0 | G29: ='23.'!K34 -> 0
B30: 24. | C30: ASSISTÊNCIA TÉCNICA | D30: =IF(G30<>0,G30/$G$33,"") | E30: =IF($E$4="C.UNIT. (AC)",G30/Frente!$D$33,ORC_Custo!G30/Frente!$D$28) -> 0 | F30: =G30/'[1]Folha Frente'!$D$26 -> 0 | G30: =SUM(G7:G29)*Frente!D39 -> 0
B31: 25. | C31: EVENTUAIS | D31: =IF(G31<>0,G31/$G$33,"") | E31: =IF($E$4="C.UNIT. (AC)",G31/Frente!$D$33,ORC_Custo!G31/Frente!$D$28) -> 0 | F31: =G31/'[1]Folha Frente'!$D$26 -> 0 | G31: =SUM(G7:G29)*Frente!D37 -> 0
B33: TOTAL GERAL | D33: =SUM(D6:D32) -> 0 | E33: =SUM(E6:E32) -> 0 | F33: =SUM(F6:F32) -> 0 | G33: =SUM(G6:G32) -> 0

Sheet ORC_PV
B2: RESUMO DOS GRUPOS - PREÇO DE VENDA
B4: GRUPOS | C4: DISCRIMINAÇÃO | D4: CUSTO | E4: BDI | G4: CUSTO TOTAL
D5: R$ | E5: GERAL | F5: % | G5: R$
B7: 01. | C7: SERVIÇOS TÉCNICOS | D7: =ORC_Custo!G7 -> 0 | E7: SIM | G7: =IF(E7="SIM",D7*(1+Frente!$D$19),ORC_PV!D7*(1+ORC_PV!F7)) -> 0
B8: 02. | C8: GASTOS GERAIS | D8: =ORC_Custo!G8 -> 0 | E8: SIM | G8: =IF(E8="SIM",D8*(1+Frente!$D$19),ORC_PV!D8*(1+ORC_PV!F8)) -> 0
B9: 03. | C9: PESSOAL PERMANENTE | D9: =ORC_Custo!G9 -> 0 | E9: SIM | G9: =IF(E9="SIM",D9*(1+Frente!$D$19),ORC_PV!D9*(1+ORC_PV!F9)) -> 0
B10: 04. | C10: IMPLANTAÇÃO DE CANTEIRO | D10: =ORC_Custo!G10 -> 0 | E10: SIM | G10: =IF(E10="SIM",D10*(1+Frente!$D$19),ORC_PV!D10*(1+ORC_PV!F10)) -> 0
B11: 05. | C11: OPERAÇÃO DE CANTEIRO | D11: =ORC_Custo!G11 -> 0 | E11: SIM | G11: =IF(E11="SIM",D11*(1+Frente!$D$19),ORC_PV!D11*(1+ORC_PV!F11)) -> 0
B12: 06. | C12: SEGURANÇA E MEDICINA DO TRABALHO | D12: =ORC_Custo!G12 -> 0 | E12: SIM | G12: =IF(E12="SIM",D12*(1+Frente!$D$19),ORC_PV!D12*(1+ORC_PV!F12)) -> 0
B13: 07. | C13: MOVIMENTO DE TERRA | D13: =ORC_Custo!G13 -> 0 | E13: SIM | G13: =IF(E13="SIM",D13*(1+Frente!$D$19),ORC_PV!D13*(1+ORC_PV!F13)) -> 0
B14: 08. | C14: FUNDAÇÕES E CONTENÇÕES | D14: =ORC_Custo!G14 -> 0 | E14: SIM | G14: =IF(E14="SIM",D14*(1+Frente!$D$19),ORC_PV!D14*(1+ORC_PV!F14)) -> 0
B15: 09. | C15: SUPERESTRUTURA | D15: =ORC_Custo!G15 -> 0 | E15: SIM | G15: =IF(E15="SIM",D15*(1+Frente!$D$19),ORC_PV!D15*(1+ORC_PV!F15)) -> 0
B16: 10. | C16: PAREDES E PAINÉIS | D16: =ORC_Custo!G16 -> 0 | E16: SIM | G16: =IF(E16="SIM",D16*(1+Frente!$D$19),ORC_PV!D16*(1+ORC_PV!F16)) -> 0
B17: 11. | C17: COBERTURA | D17: =ORC_Custo!G17 -> 0 | E17: SIM | G17: =IF(E17="SIM",D17*(1+Frente!$D$19),ORC_PV!D17*(1+ORC_PV!F17)) -> 0
B18: 12. | C18: IMPERMEABILIZAÇÃO E TRATAMENTOS | D18: =ORC_Custo!G18 -> 0 | E18: SIM | G18: =IF(E18="SIM",D18*(1+Frente!$D$19),ORC_PV!D18*(1+ORC_PV!F18)) -> 0
... B31: 25. | C31: EVENTUAIS | D31: =ORC_Custo!G31 -> 0 | E31: SIM | G31: =IF(E31="SIM",D31*(1+Frente!$D$19),ORC_PV!D31*(1+ORC_PV!F31)) -> 0
B33: TOTAL GERAL | D33: =SUM(D6:D32) -> 0 | F33: =IF(G33=0, "",(G33/D33)-1) | G33: =SUM(G6:G32) -> 0

Sheet 01.
B2: 01. SERVIÇOS TÉCNICOS
C3: RESUMO
C5: Exemplos de itens do Grupo: Projetos (arquitetura e complementares); elaboração de levantamentos, orçamento e planejamento; gerenciamento e fiscalização de obra; consultorias e auditorias; vistoria cautelar de vizinhança e de entrega de obra; levantamento topográfico; sondagem; controle tencológico; ensaios laboratoriais, etc. | G5: Material | H5: Mão-de-obra | I5: Equipamento | J5: Serviço | K5: Total
G6: =SUMPRODUCT(E13:E33,G13:G33) -> 0 | H6: =SUMPRODUCT(E13:E33,H13:H33) -> 0 | I6: =SUMPRODUCT(E13:E33,I13:I33) -> 0 | J6: =SUMPRODUCT(E13:E33,J13:J33) -> 0 | K6: =K34 -> 0
G7: =IF(K34<>0,G6/K34,0) -> 0 | H7: =IF(K34<>0,H6/K34,0) -> 0 | I7: =IF(K34<>0,I6/K34,0) -> 0 | J7: =IF(K34<>0,J6/K34,0) -> 0 | K7: =IF(K34<>0,K6/ORC_Custo!G33,0) -> 0
B10: CÓDIGO | D10: DESCRIÇÃO | E10: QUANT. | F10: UN. | G10: VALOR UNITÁRIO | K10: TOTAL
G11: MATERIAL | H11: MÃO DE OBRA | I11: EQUIPAMENTO | J11: SERVIÇO
C13: 01.01 | F13: m | K13: =(G13+H13+I13+J13)*E13 -> 0
C14: 01.02 | F14: m | K14: =(G14+H14+I14+J14)*E14 -> 0
C15: 01.03 | F15: m | K15: =(G15+H15+I15+J15)*E15 -> 0
C16: 01.04 | F16: m | K16: =(G16+H16+I16+J16)*E16 -> 0
C17: 01.05 | F17: m | K17: =(G17+H17+I17+J17)*E17 -> 0
C18: 01.06 | F18: m | K18: =(G18+H18+I18+J18)*E18 -> 0
C19: 01.07 | F19: m | K19: =(G19+H19+I19+J19)*E19 -> 0
C20: 01.08 | F20: m | K20: =(G20+H20+I20+J20)*E20 -> 0
C21: 01.09 | F21: m | K21: =(G21+H21+I21+J21)*E21 -> 0
C22: 01.10 | F22: m | K22: =(G22+H22+I22+J22)*E22 -> 0
C23: 01.11 | F23: m | K23: =(G23+H23+I23+J23)*E23 -> 0
C24: 01.12 | F24: m | K24: =(G24+H24+I24+J24)*E24 -> 0
... C32: 01.20 | F32: m | K32: =(G32+H32+I32+J32)*E32 -> 0
D34: TOTAL DO GRUPO | K34: =SUM(K13:K33) -> 0

Sheet 02.
B2: 02. GASTOS GERAIS
C3: RESUMO
C5: Exemplos de itens do Grupo: Alvará de construção; taxas para aprovações e legalizações; seguros; outros gastos não relacionados diretamente a exeução da obra. | G5: Material | H5: Mão-de-obra | I5: Equipamento | J5: Serviço | K5: Total
G6: =SUMPRODUCT(E13:E33,G13:G33) -> 0 | H6: =SUMPRODUCT(E13:E33,H13:H33) -> 0 | I6: =SUMPRODUCT(E13:E33,I13:I33) -> 0 | J6: =SUMPRODUCT(E13:E33,J13:J33) -> 0 | K6: =K34 -> 0
G7: =IF(K34<>0,G6/K34,0) -> 0 | H7: =IF(K34<>0,H6/K34,0) -> 0 | I7: =IF(K34<>0,I6/K34,0) -> 0 | J7: =IF(K34<>0,J6/K34,0) -> 0 | K7: =IF(K34<>0,K6/ORC_Custo!G33,0) -> 0
B10: CÓDIGO | D10: DESCRIÇÃO | E10: QUANT. | F10: UN. | G10: VALOR UNITÁRIO | K10: TOTAL
G11: MATERIAL | H11: MÃO DE OBRA | I11: EQUIPAMENTO | J11: SERVIÇO
C13: 02.01 | F13: m | K13: =(G13+H13+I13+J13)*E13 -> 0
C14: 02.02 | F14: m | K14: =(G14+H14+I14+J14)*E14 -> 0
C15: 02.03 | F15: m | K15: =(G15+H15+I15+J15)*E15 -> 0
C16: 02.04 | D16: VOLTAR | F16: m | K16: =(G16+H16+I16+J16)*E16 -> 0
C17: 02.05 | F17: m | K17: =(G17+H17+I17+J17)*E17 -> 0
C18: 02.06 | F18: m | K18: =(G18+H18+I18+J18)*E18 -> 0
C19: 02.07 | F19: m | K19: =(G19+H19+I19+J19)*E19 -> 0
C20: 02.08 | F20: m | K20: =(G20+H20+I20+J20)*E20 -> 0
C21: 02.09 | F21: m | K21: =(G21+H21+I21+J21)*E21 -> 0
C22: 02.10 | F22: m | K22: =(G22+H22+I22+J22)*E22 -> 0
C23: 02.11 | F23: m | K23: =(G23+H23+I23+J23)*E23 -> 0
C24: 02.12 | F24: m | K24: =(G24+H24+I24+J24)*E24 -> 0
C25: 02.13 | F25: m | K25: =(G25+H25+I25+J25)*E25 -> 0
C26: 02.14 | F26: m | K26: =(G26+H26+I26+J26)*E26 -> 0
C27: 02.15 | F27: m | K27: =(G27+H27+I27+J27)*E27 -> 0
C28: 02.16 | F28: m | K28: =(G28+H28+I28+J28)*E28 -> 0
... C32: 02.20 | F32: m | K32: =(G32+H32+I32+J32)*E32 -> 0
D34: TOTAL DO GRUPO | K34: =SUM(K13:K33) -> 0

Sheet 03.
B2: 03. PESSOAL PERMANENTE
C3: RESUMO
C5: Exemplos de itens do Grupo: Engenheiro, mestre-de-obra, encarregado, técnicos; estagiários, auxiliar adsministrativo, benefícios e outras despesas com pessoal próprio na obra, não relacionados a produção de serviços. | G5: Material | H5: Mão-de-obra | I5: Equipamento | J5: Serviço | K5: Total
G6: =SUMPRODUCT(E13:E33,G13:G33) -> 0 | H6: =SUMPRODUCT(E13:E33,H13:H33) -> 0 | I6: =SUMPRODUCT(E13:E33,I13:I33) -> 0 | J6: =SUMPRODUCT(E13:E33,J13:J33) -> 0 | K6: =K34 -> 0
G7: =IF(K34<>0,G6/K34,0) -> 0 | H7: =IF(K34<>0,H6/K34,0) -> 0 | I7: =IF(K34<>0,I6/K34,0) -> 0 | J7: =IF(K34<>0,J6/K34,0) -> 0 | K7: =IF(K34<>0,K6/ORC_Custo!G33,0) -> 0
B10: CÓDIGO | D10: DESCRIÇÃO | E10: QUANT. | F10: UN. | G10: VALOR UNITÁRIO | K10: TOTAL
G11: MATERIAL | H11: MÃO DE OBRA | I11: EQUIPAMENTO | J11: SERVIÇO
C13: 03.01 | F13: m | K13: =(G13+H13+I13+J13)*E13 -> 0
C14: 03.02 | F14: m | K14: =(G14+H14+I14+J14)*E14 -> 0
C15: 03.03 | F15: m | K15: =(G15+H15+I15+J15)*E15 -> 0
C16: 03.04 | F16: m | K16: =(G16+H16+I16+J16)*E16 -> 0
C17: 03.05 | F17: m | K17: =(G17+H17+I17+J17)*E17 -> 0
C18: 03.06 | F18: m | K18: =(G18+H18+I18+J18)*E18 -> 0
C19: 03.07 | F19: m | K19: =(G19+H19+I19+J19)*E19 -> 0
C20: 03.08 | F20: m | K20: =(G20+H20+I20+J20)*E20 -> 0
C21: 03.09 | F21: m | K21: =(G21+H21+I21+J21)*E21 -> 0
C22: 03.10 | F22: m | K22: =(G22+H22+I22+J22)*E22 -> 0
C23: 03.11 | F23: m | K23: =(G23+H23+I23+J23)*E23 -> 0
C24: 03.12 | F24: m | K24: =(G24+H24+I24+J24)*E24 -> 0
... C32: 03.20 | F32: m | K32: =(G32+H32+I32+J32)*E32 -> 0
D34: TOTAL DO GRUPO | K34: =SUM(K13:K33) -> 0

Sheet 04.
B2: 04. IMPLANTAÇÃO DE CANTEIRO
C3: RESUMO
C5: Exemplos de itens do Grupo: Tapume, limpeza de terreno, barraco de obra, instalações provisórias, controle de acesso, etc. | G5: Material | H5: Mão-de-obra | I5: Equipamento | J5: Serviço | K5: Total
G6: =SUMPRODUCT(E13:E33,G13:G33) -> 0 | H6: =SUMPRODUCT(E13:E33,H13:H33) -> 0 | I6: =SUMPRODUCT(E13:E33,I13:I33) -> 0 | J6: =SUMPRODUCT(E13:E33,J13:J33) -> 0 | K6: =K34 -> 0
G7: =IF(K34<>0,G6/K34,0) -> 0 | H7: =IF(K34<>0,H6/K34,0) -> 0 | I7: =IF(K34<>0,I6/K34,0) -> 0 | J7: =IF(K34<>0,J6/K34,0) -> 0 | K7: =IF(K34<>0,K6/ORC_Custo!G33,0) -> 0
B10: CÓDIGO | D10: DESCRIÇÃO | E10: QUANT. | F10: UN. | G10: VALOR UNITÁRIO | K10: TOTAL
G11: MATERIAL | H11: MÃO DE OBRA | I11: EQUIPAMENTO | J11: SERVIÇO
C13: 04.01 | F13: m | K13: =(G13+H13+I13+J13)*E13 -> 0
C14: 04.02 | F14: m | K14: =(G14+H14+I14+J14)*E14 -> 0
C15: 04.03 | F15: m | K15: =(G15+H15+I15+J15)*E15 -> 0
C16: 04.04 | F16: m | K16: =(G16+H16+I16+J16)*E16 -> 0
C17: 04.05 | F17: m | K17: =(G17+H17+I17+J17)*E17 -> 0
C18: 04.06 | F18: m | K18: =(G18+H18+I18+J18)*E18 -> 0
C19: 04.07 | F19: m | K19: =(G19+H19+I19+J19)*E19 -> 0
C20: 04.08 | F20: m | K20: =(G20+H20+I20+J20)*E20 -> 0
C21: 04.09 | F21: m | K21: =(G21+H21+I21+J21)*E21 -> 0
C22: 04.10 | F22: m | K22: =(G22+H22+I22+J22)*E22 -> 0
C23: 04.11 | F23: m | K23: =(G23+H23+I23+J23)*E23 -> 0
C24: 04.12 | F24: m | K24: =(G24+H24+I24+J24)*E24 -> 0
... C32: 04.20 | F32: m | K32: =(G32+H32+I32+J32)*E32 -> 0
D34: TOTAL DO GRUPO | K34: =SUM(K13:K33) -> 0

Sheet 05.
B2: 05. OPERAÇÃO DE CANTEIRO
C3: RESUMO
C5: Exemplos de itens do Grupo: Gastos periódicos ou eventuais necessários a operação e manutenção do canteiro, como: coleta de entulho, consumos de água e energia, vigilância, material de expediente, plotagens, etc. | G5: Material | H5: Mão-de-obra | I5: Equipamento | J5: Serviço | K5: Total
G6: =SUMPRODUCT(E13:E33,G13:G33) -> 0 | H6: =SUMPRODUCT(E13:E33,H13:H33) -> 0 | I6: =SUMPRODUCT(E13:E33,I13:I33) -> 0 | J6: =SUMPRODUCT(E13:E33,J13:J33) -> 0 | K6: =K34 -> 0
G7: =IF(K34<>0,G6/K34,0) -> 0 | H7: =IF(K34<>0,H6/K34,0) -> 0 | I7: =IF(K34<>0,I6/K34,0) -> 0 | J7: =IF(K34<>0,J6/K34,0) -> 0 | K7: =IF(K34<>0,K6/ORC_Custo!G33,0) -> 0
B10: CÓDIGO | D10: DESCRIÇÃO | E10: QUANT. | F10: UN. | G10: VALOR UNITÁRIO | K10: TOTAL
G11: MATERIAL | H11: MÃO DE OBRA | I11: EQUIPAMENTO | J11: SERVIÇO
C13: 05.01 | F13: m | K13: =(G13+H13+I13+J13)*E13 -> 0
C14: 05.02 | F14: m | K14: =(G14+H14+I14+J14)*E14 -> 0
C15: 05.03 | F15: m | K15: =(G15+H15+I15+J15)*E15 -> 0
C16: 05.04 | F16: m | K16: =(G16+H16+I16+J16)*E16 -> 0
C17: 05.05 | F17: m | K17: =(G17+H17+I17+J17)*E17 -> 0
C18: 05.06 | F18: m | K18: =(G18+H18+I18+J18)*E18 -> 0
C19: 05.07 | F19: m | K19: =(G19+H19+I19+J19)*E19 -> 0
C20: 05.08 | F20: m | K20: =(G20+H20+I20+J20)*E20 -> 0
C21: 05.09 | F21: m | K21: =(G21+H21+I21+J21)*E21 -> 0
C22: 05.10 | F22: m | K22: =(G22+H22+I22+J22)*E22 -> 0
C23: 05.11 | F23: m | K23: =(G23+H23+I23+J23)*E23 -> 0
C24: 05.12 | F24: m | K24: =(G24+H24+I24+J24)*E24 -> 0
... C32: 05.20 | F32: m | K32: =(G32+H32+I32+J32)*E32 -> 0
D34: TOTAL DO GRUPO | K34: =SUM(K13:K33) -> 0

Sheet 06.
B2: 06. SEGURANÇA E MEDICINA DO TRABALHO
C3: RESUMO
C5: Exemplos de itens do Grupo: Programas de medicina e saúde ocupacional, proteções coletivas e demais gastos relacionados a segurança do trabalho. | G5: Material | H5: Mão-de-obra | I5: Equipamento | J5: Serviço | K5: Total
G6: =SUMPRODUCT(E13:E33,G13:G33) -> 0 | H6: =SUMPRODUCT(E13:E33,H13:H33) -> 0 | I6: =SUMPRODUCT(E13:E33,I13:I33) -> 0 | J6: =SUMPRODUCT(E13:E33,J13:J33) -> 0 | K6: =K34 -> 0
G7: =IF(K34<>0,G6/K34,0) -> 0 | H7: =IF(K34<>0,H6/K34,0) -> 0 | I7: =IF(K34<>0,I6/K34,0) -> 0 | J7: =IF(K34<>0,J6/K34,0) -> 0 | K7: =IF(K34<>0,K6/ORC_Custo!G33,0) -> 0
B10: CÓDIGO | D10: DESCRIÇÃO | E10: QUANT. | F10: UN. | G10: VALOR UNITÁRIO | K10: TOTAL
G11: MATERIAL | H11: MÃO DE OBRA | I11: EQUIPAMENTO | J11: SERVIÇO
C13: 06.01 | F13: m | K13: =(G13+H13+I13+J13)*E13 -> 0
C14: 06.02 | F14: m | K14: =(G14+H14+I14+J14)*E14 -> 0
C15: 06.03 | F15: m | K15: =(G15+H15+I15+J15)*E15 -> 0
C16: 06.04 | F16: m | K16: =(G16+H16+I16+J16)*E16 -> 0
C17: 06.05 | F17: m | K17: =(G17+H17+I17+J17)*E17 -> 0
C18: 06.06 | F18: m | K18: =(G18+H18+I18+J18)*E18 -> 0
C19: 06.07 | F19: m | K19: =(G19+H19+I19+J19)*E19 -> 0
C20: 06.08 | F20: m | K20: =(G20+H20+I20+J20)*E20 -> 0
C21: 06.09 | F21: m | K21: =(G21+H21+I21+J21)*E21 -> 0
C22: 06.10 | F22: m | K22: =(G22+H22+I22+J22)*E22 -> 0
C23: 06.11 | F23: m | K23: =(G23+H23+I23+J23)*E23 -> 0
C24: 06.12 | F24: m | K24: =(G24+H24+I24+J24)*E24 -> 0
... C32: 06.20 | F32: m | K32: =(G32+H32+I32+J32)*E32 -> 0
D34: TOTAL DO GRUPO | K34: =SUM(K13:K33) -> 0

Sheet 07.
B2: 07. MOVIMENTO DE TERRA
C3: RESUMO
C5: Exemplos de itens do Grupo: Nivelamento de terreno, cortes, aterros, escavações, bota-fora de material, etc. | G5: Material | H5: Mão-de-obra | I5: Equipamento | J5: Serviço | K5: Total
G6: =SUMPRODUCT(E13:E33,G13:G33) -> 0 | H6: =SUMPRODUCT(E13:E33,H13:H33) -> 0 | I6: =SUMPRODUCT(E13:E33,I13:I33) -> 0 | J6: =SUMPRODUCT(E13:E33,J13:J33) -> 0 | K6: =K34 -> 0
G7: =IF(K34<>0,G6/K34,0) -> 0 | H7: =IF(K34<>0,H6/K34,0) -> 0 | I7: =IF(K34<>0,I6/K34,0) -> 0 | J7: =IF(K34<>0,J6/K34,0) -> 0 | K7: =IF(K34<>0,K6/ORC_Custo!G33,0) -> 0
B10: CÓDIGO | D10: DESCRIÇÃO | E10: QUANT. | F10: UN. | G10: VALOR UNITÁRIO | K10: TOTAL
G11: MATERIAL | H11: MÃO DE OBRA | I11: EQUIPAMENTO | J11: SERVIÇO
C13: 07.01 | F13: m | K13: =(G13+H13+I13+J13)*E13 -> 0
C14: 07.02 | F14: m | K14: =(G14+H14+I14+J14)*E14 -> 0
C15: 07.03 | F15: m | K15: =(G15+H15+I15+J15)*E15 -> 0
C16: 07.04 | F16: m | K16: =(G16+H16+I16+J16)*E16 -> 0
C17: 07.05 | F17: m | K17: =(G17+H17+I17+J17)*E17 -> 0
C18: 07.06 | F18: m | K18: =(G18+H18+I18+J18)*E18 -> 0
C19: 07.07 | F19: m | K19: =(G19+H19+I19+J19)*E19 -> 0
C20: 07.08 | F20: m | K20: =(G20+H20+I20+J20)*E20 -> 0
C21: 07.09 | F21: m | K21: =(G21+H21+I21+J21)*E21 -> 0
C22: 07.10 | F22: m | K22: =(G22+H22+I22+J22)*E22 -> 0
C23: 07.11 | F23: m | K23: =(G23+H23+I23+J23)*E23 -> 0
C24: 07.12 | F24: m | K24: =(G24+H24+I24+J24)*E24 -> 0
... C32: 07.20 | F32: m | K32: =(G32+H32+I32+J32)*E32 -> 0
D34: TOTAL DO GRUPO | K34: =SUM(K13:K33) -> 0

Sheet 08.
B2: 08. FUNDAÇÕES E CONTENÇÕES
C3: RESUMO
C5: Exemplos de itens do Grupo: Estacas, blocos, sapatas, cortinas, contenções, etc. | G5: Material | H5: Mão-de-obra | I5: Equipamento | J5: Serviço | K5: Total
G6: =SUMPRODUCT(E13:E33,G13:G33) -> 0 | H6: =SUMPRODUCT(E13:E33,H13:H33) -> 0 | I6: =SUMPRODUCT(E13:E33,I13:I33) -> 0 | J6: =SUMPRODUCT(E13:E33,J13:J33) -> 0 | K6: =K34 -> 0
G7: =IF(K34<>0,G6/K34,0) -> 0 | H7: =IF(K34<>0,H6/K34,0) -> 0 | I7: =IF(K34<>0,I6/K34,0) -> 0 | J7: =IF(K34<>0,J6/K34,0) -> 0 | K7: =IF(K34<>0,K6/ORC_Custo!G33,0) -> 0
B10: CÓDIGO | D10: DESCRIÇÃO | E10: QUANT. | F10: UN. | G10: VALOR UNITÁRIO | K10: TOTAL
G11: MATERIAL | H11: MÃO DE OBRA | I11: EQUIPAMENTO | J11: SERVIÇO
C13: 08.01 | F13: m | K13: =(G13+H13+I13+J13)*E13 -> 0
C14: 08.02 | F14: m | K14: =(G14+H14+I14+J14)*E14 -> 0
C15: 08.03 | F15: m | K15: =(G15+H15+I15+J15)*E15 -> 0
C16: 08.04 | F16: m | K16: =(G16+H16+I16+J16)*E16 -> 0
C17: 08.05 | F17: m | K17: =(G17+H17+I17+J17)*E17 -> 0
C18: 08.06 | F18: m | K18: =(G18+H18+I18+J18)*E18 -> 0
C19: 08.07 | F19: m | K19: =(G19+H19+I19+J19)*E19 -> 0
C20: 08.08 | F20: m | K20: =(G20+H20+I20+J20)*E20 -> 0
C21: 08.09 | F21: m | K21: =(G21+H21+I21+J21)*E21 -> 0
C22: 08.10 | F22: m | K22: =(G22+H22+I22+J22)*E22 -> 0
C23: 08.11 | F23: m | K23: =(G23+H23+I23+J23)*E23 -> 0
C24: 08.12 | F24: m | K24: =(G24+H24+I24+J24)*E24 -> 0
... C32: 08.20 | F32: m | K32: =(G32+H32+I32+J32)*E32 -> 0
D34: TOTAL DO GRUPO | K34: =SUM(K13:K33) -> 0

Sheet 09.
B2: 09. SUPERESTRUTURA
C3: RESUMO
C5: Exemplos de itens do Grupo: Forma, aço e concreto para vigas, pilares, lajes, escadas, rampas, etc. | G5: Material | H5: Mão-de-obra | I5: Equipamento | J5: Serviço | K5: Total
G6: =SUMPRODUCT(E13:E33,G13:G33) -> 0 | H6: =SUMPRODUCT(E13:E33,H13:H33) -> 0 | I6: =SUMPRODUCT(E13:E33,I13:I33) -> 0 | J6: =SUMPRODUCT(E13:E33,J13:J33) -> 0 | K6: =K34 -> 0
G7: =IF(K34<>0,G6/K34,0) -> 0 | H7: =IF(K34<>0,H6/K34,0) -> 0 | I7: =IF(K34<>0,I6/K34,0) -> 0 | J7: =IF(K34<>0,J6/K34,0) -> 0 | K7: =IF(K34<>0,K6/ORC_Custo!G33,0) -> 0
B10: CÓDIGO | D10: DESCRIÇÃO | E10: QUANT. | F10: UN. | G10: VALOR UNITÁRIO | K10: TOTAL
G11: MATERIAL | H11: MÃO DE OBRA | I11: EQUIPAMENTO | J11: SERVIÇO
C13: 09.01 | F13: m | K13: =(G13+H13+I13+J13)*E13 -> 0
C14: 09.02 | F14: m | K14: =(G14+H14+I14+J14)*E14 -> 0
C15: 09.03 | F15: m | K15: =(G15+H15+I15+J15)*E15 -> 0
C16: 09.04 | F16: m | K16: =(G16+H16+I16+J16)*E16 -> 0
C17: 09.05 | F17: m | K17: =(G17+H17+I17+J17)*E17 -> 0
C18: 09.06 | F18: m | K18: =(G18+H18+I18+J18)*E18 -> 0
C19: 09.07 | F19: m | K19: =(G19+H19+I19+J19)*E19 -> 0
C20: 09.08 | F20: m | K20: =(G20+H20+I20+J20)*E20 -> 0
C21: 09.09 | F21: m | K21: =(G21+H21+I21+J21)*E21 -> 0
C22: 09.10 | F22: m | K22: =(G22+H22+I22+J22)*E22 -> 0
C23: 09.11 | F23: m | K23: =(G23+H23+I23+J23)*E23 -> 0
C24: 09.12 | F24: m | K24: =(G24+H24+I24+J24)*E24 -> 0
... C32: 09.20 | F32: m | K32: =(G32+H32+I32+J32)*E32 -> 0
D34: TOTAL DO GRUPO | K34: =SUM(K13:K33) -> 0

Sheet 10.
B2: 10. PAREDES E PAINÉIS
C3: RESUMO
C5: Exemplos de itens do Grupo: Tijolo cerâmico, bloco de concreto de vedação, gesso acartonado, divisórias, etc. | G5: Material | H5: Mão-de-obra | I5: Equipamento | J5: Serviço | K5: Total
G6: =SUMPRODUCT(E13:E33,G13:G33) -> 0 | H6: =SUMPRODUCT(E13:E33,H13:H33) -> 0 | I6: =SUMPRODUCT(E13:E33,I13:I33) -> 0 | J6: =SUMPRODUCT(E13:E33,J13:J33) -> 0 | K6: =K34 -> 0
G7: =IF(K34<>0,G6/K34,0) -> 0 | H7: =IF(K34<>0,H6/K34,0) -> 0 | I7: =IF(K34<>0,I6/K34,0) -> 0 | J7: =IF(K34<>0,J6/K34,0) -> 0 | K7: =IF(K34<>0,K6/ORC_Custo!G33,0) -> 0
B10: CÓDIGO | D10: DESCRIÇÃO | E10: QUANT. | F10: UN. | G10: VALOR UNITÁRIO | K10: TOTAL
G11: MATERIAL | H11: MÃO DE OBRA | I11: EQUIPAMENTO | J11: SERVIÇO
C13: 10.01 | F13: m | K13: =(G13+H13+I13+J13)*E13 -> 0
C14: 10.02 | F14: m | K14: =(G14+H14+I14+J14)*E14 -> 0
C15: 10.03 | F15: m | K15: =(G15+H15+I15+J15)*E15 -> 0
C16: 10.04 | F16: m | K16: =(G16+H16+I16+J16)*E16 -> 0
C17: 10.05 | F17: m | K17: =(G17+H17+I17+J17)*E17 -> 0
C18: 10.06 | F18: m | K18: =(G18+H18+I18+J18)*E18 -> 0
C19: 10.07 | F19: m | K19: =(G19+H19+I19+J19)*E19 -> 0
C20: 10.08 | F20: m | K20: =(G20+H20+I20+J20)*E20 -> 0
C21: 10.09 | F21: m | K21: =(G21+H21+I21+J21)*E21 -> 0
C22: 10.10 | F22: m | K22: =(G22+H22+I22+J22)*E22 -> 0
C23: 10.11 | F23: m | K23: =(G23+H23+I23+J23)*E23 -> 0
C24: 10.12 | F24: m | K24: =(G24+H24+I24+J24)*E24 -> 0
... C32: 10.20 | F32: m | K32: =(G32+H32+I32+J32)*E32 -> 0
D34: TOTAL DO GRUPO | K34: =SUM(K13:K33) -> 0

Sheet 11.
B2: 11. COBERTURA
C3: RESUMO
C5: Exemplos de itens do Grupo: Telhas e estrutura de telhados e coberturas. | G5: Material | H5: Mão-de-obra | I5: Equipamento | J5: Serviço | K5: Total
G6: =SUMPRODUCT(E13:E33,G13:G33) -> 0 | H6: =SUMPRODUCT(E13:E33,H13:H33) -> 0 | I6: =SUMPRODUCT(E13:E33,I13:I33) -> 0 | J6: =SUMPRODUCT(E13:E33,J13:J33) -> 0 | K6: =K34 -> 0
G7: =IF(K34<>0,G6/K34,0) -> 0 | H7: =IF(K34<>0,H6/K34,0) -> 0 | I7: =IF(K34<>0,I6/K34,0) -> 0 | J7: =IF(K34<>0,J6/K34,0) -> 0 | K7: =IF(K34<>0,K6/ORC_Custo!G33,0) -> 0
B10: CÓDIGO | D10: DESCRIÇÃO | E10: QUANT. | F10: UN. | G10: VALOR UNITÁRIO | K10: TOTAL
G11: MATERIAL | H11: MÃO DE OBRA | I11: EQUIPAMENTO | J11: SERVIÇO
C13: 11.01 | F13: m | K13: =(G13+H13+I13+J13)*E13 -> 0
C14: 11.02 | F14: m | K14: =(G14+H14+I14+J14)*E14 -> 0
C15: 11.03 | F15: m | K15: =(G15+H15+I15+J15)*E15 -> 0
C16: 11.04 | F16: m | K16: =(G16+H16+I16+J16)*E16 -> 0
C17: 11.05 | F17: m | K17: =(G17+H17+I17+J17)*E17 -> 0
C18: 11.06 | F18: m | K18: =(G18+H18+I18+J18)*E18 -> 0
C19: 11.07 | F19: m | K19: =(G19+H19+I19+J19)*E19 -> 0
C20: 11.08 | F20: m | K20: =(G20+H20+I20+J20)*E20 -> 0
C21: 11.09 | F21: m | K21: =(G21+H21+I21+J21)*E21 -> 0
C22: 11.10 | F22: m | K22: =(G22+H22+I22+J22)*E22 -> 0
C23: 11.11 | F23: m | K23: =(G23+H23+I23+J23)*E23 -> 0
C24: 11.12 | F24: m | K24: =(G24+H24+I24+J24)*E24 -> 0
... C32: 11.20 | F32: m | K32: =(G32+H32+I32+J32)*E32 -> 0
D34: TOTAL DO GRUPO | K34: =SUM(K13:K33) -> 0

Sheet 12.
B2: 12. IMPERMEABILIZAÇÃO E TRATAMENTOS
C3: RESUMO
C5: Exemplos de itens do Grupo: Impermeabilizações e tratamentos especiais como térmico e acústico. | G5: Material | H5: Mão-de-obra | I5: Equipamento | J5: Serviço | K5: Total
G6: =SUMPRODUCT(E13:E33,G13:G33) -> 0 | H6: =SUMPRODUCT(E13:E33,H13:H33) -> 0 | I6: =SUMPRODUCT(E13:E33,I13:I33) -> 0 | J6: =SUMPRODUCT(E13:E33,J13:J33) -> 0 | K6: =K34 -> 0
G7: =IF(K34<>0,G6/K34,0) -> 0 | H7: =IF(K34<>0,H6/K34,0) -> 0 | I7: =IF(K34<>0,I6/K34,0) -> 0 | J7: =IF(K34<>0,J6/K34,0) -> 0 | K7: =IF(K34<>0,K6/ORC_Custo!G33,0) -> 0
B10: CÓDIGO | D10: DESCRIÇÃO | E10: QUANT. | F10: UN. | G10: VALOR UNITÁRIO | K10: TOTAL
G11: MATERIAL | H11: MÃO DE OBRA | I11: EQUIPAMENTO | J11: SERVIÇO
C13: 12.01 | F13: m | K13: =(G13+H13+I13+J13)*E13 -> 0
C14: 12.02 | F14: m | K14: =(G14+H14+I14+J14)*E14 -> 0
C15: 12.03 | F15: m | K15: =(G15+H15+I15+J15)*E15 -> 0
C16: 12.04 | F16: m | K16: =(G16+H16+I16+J16)*E16 -> 0
C17: 12.05 | F17: m | K17: =(G17+H17+I17+J17)*E17 -> 0
C18: 12.06 | F18: m | K18: =(G18+H18+I18+J18)*E18 -> 0
C19: 12.07 | F19: m | K19: =(G19+H19+I19+J19)*E19 -> 0
C20: 12.08 | F20: m | K20: =(G20+H20+I20+J20)*E20 -> 0
C21: 12.09 | F21: m | K21: =(G21+H21+I21+J21)*E21 -> 0
C22: 12.10 | F22: m | K22: =(G22+H22+I22+J22)*E22 -> 0
C23: 12.11 | F23: m | K23: =(G23+H23+I23+J23)*E23 -> 0
C24: 12.12 | F24: m | K24: =(G24+H24+I24+J24)*E24 -> 0
... C32: 12.20 | F32: m | K32: =(G32+H32+I32+J32)*E32 -> 0
D34: TOTAL DO GRUPO | K34: =SUM(K13:K33) -> 0

Sheet 13.
B2: 13. REVESTIMENTOS INTERNOS
C3: RESUMO
C5: Exemplos de itens do Grupo: Revestimentos internos de parede e teto, como: reboco, azulejo, gesso, etc. | G5: Material | H5: Mão-de-obra | I5: Equipamento | J5: Serviço | K5: Total
G6: =SUMPRODUCT(E13:E33,G13:G33) -> 0 | H6: =SUMPRODUCT(E13:E33,H13:H33) -> 0 | I6: =SUMPRODUCT(E13:E33,I13:I33) -> 0 | J6: =SUMPRODUCT(E13:E33,J13:J33) -> 0 | K6: =K34 -> 0
G7: =IF(K34<>0,G6/K34,0) -> 0 | H7: =IF(K34<>0,H6/K34,0) -> 0 | I7: =IF(K34<>0,I6/K34,0) -> 0 | J7: =IF(K34<>0,J6/K34,0) -> 0 | K7: =IF(K34<>0,K6/ORC_Custo!G33,0) -> 0
B10: CÓDIGO | D10: DESCRIÇÃO | E10: QUANT. | F10: UN. | G10: VALOR UNITÁRIO | K10: TOTAL
G11: MATERIAL | H11: MÃO DE OBRA | I11: EQUIPAMENTO | J11: SERVIÇO
C13: 13.01 | F13: m | K13: =(G13+H13+I13+J13)*E13 -> 0
C14: 13.02 | F14: m | K14: =(G14+H14+I14+J14)*E14 -> 0
C15: 13.03 | F15: m | K15: =(G15+H15+I15+J15)*E15 -> 0
C16: 13.04 | F16: m | K16: =(G16+H16+I16+J16)*E16 -> 0
C17: 13.05 | F17: m | K17: =(G17+H17+I17+J17)*E17 -> 0
C18: 13.06 | F18: m | K18: =(G18+H18+I18+J18)*E18 -> 0
C19: 13.07 | F19: m | K19: =(G19+H19+I19+J19)*E19 -> 0
C20: 13.08 | F20: m | K20: =(G20+H20+I20+J20)*E20 -> 0
C21: 13.09 | F21: m | K21: =(G21+H21+I21+J21)*E21 -> 0
C22: 13.10 | F22: m | K22: =(G22+H22+I22+J22)*E22 -> 0
C23: 13.11 | F23: m | K23: =(G23+H23+I23+J23)*E23 -> 0
C24: 13.12 | F24: m | K24: =(G24+H24+I24+J24)*E24 -> 0
... C32: 13.20 | F32: m | K32: =(G32+H32+I32+J32)*E32 -> 0
D34: TOTAL DO GRUPO | K34: =SUM(K13:K33) -> 0

Sheet 14.
B2: 14. REVESTIMENTO EXTERNO
C3: RESUMO
C5: Exemplos de itens do Grupo: Chapisco, emboço, cerâmica de fachada e outros locais externos da edificação. | G5: Material | H5: Mão-de-obra | I5: Equipamento | J5: Serviço | K5: Total
G6: =SUMPRODUCT(E13:E33,G13:G33) -> 0 | H6: =SUMPRODUCT(E13:E33,H13:H33) -> 0 | I6: =SUMPRODUCT(E13:E33,I13:I33) -> 0 | J6: =SUMPRODUCT(E13:E33,J13:J33) -> 0 | K6: =K34 -> 0
G7: =IF(K34<>0,G6/K34,0) -> 0 | H7: =IF(K34<>0,H6/K34,0) -> 0 | I7: =IF(K34<>0,I6/K34,0) -> 0 | J7: =IF(K34<>0,J6/K34,0) -> 0 | K7: =IF(K34<>0,K6/ORC_Custo!G33,0) -> 0
B10: CÓDIGO | D10: DESCRIÇÃO | E10: QUANT. | F10: UN. | G10: VALOR UNITÁRIO | K10: TOTAL
G11: MATERIAL | H11: MÃO DE OBRA | I11: EQUIPAMENTO | J11: SERVIÇO
C13: 14.01 | F13: m | K13: =(G13+H13+I13+J13)*E13 -> 0
C14: 14.02 | F14: m | K14: =(G14+H14+I14+J14)*E14 -> 0
C15: 14.03 | F15: m | K15: =(G15+H15+I15+J15)*E15 -> 0
C16: 14.04 | F16: m | K16: =(G16+H16+I16+J16)*E16 -> 0
C17: 14.05 | F17: m | K17: =(G17+H17+I17+J17)*E17 -> 0
C18: 14.06 | F18: m | K18: =(G18+H18+I18+J18)*E18 -> 0
C19: 14.07 | F19: m | K19: =(G19+H19+I19+J19)*E19 -> 0
C20: 14.08 | F20: m | K20: =(G20+H20+I20+J20)*E20 -> 0
C21: 14.09 | F21: m | K21: =(G21+H21+I21+J21)*E21 -> 0
C22: 14.10 | F22: m | K22: =(G22+H22+I22+J22)*E22 -> 0
C23: 14.11 | F23: m | K23: =(G23+H23+I23+J23)*E23 -> 0
C24: 14.12 | F24: m | K24: =(G24+H24+I24+J24)*E24 -> 0
... C32: 14.20 | F32: m | K32: =(G32+H32+I32+J32)*E32 -> 0
D34: TOTAL DO GRUPO | K34: =SUM(K13:K33) -> 0

Sheet 15.
B2: 15. ESQUADRIAS DE MADEIRA
C3: RESUMO
C5: Exemplos de itens do Grupo: Portas, janelas e outros elementos de madeira. | G5: Material | H5: Mão-de-obra | I5: Equipamento | J5: Serviço | K5: Total
G6: =SUMPRODUCT(E13:E33,G13:G33) -> 0 | H6: =SUMPRODUCT(E13:E33,H13:H33) -> 0 | I6: =SUMPRODUCT(E13:E33,I13:I33) -> 0 | J6: =SUMPRODUCT(E13:E33,J13:J33) -> 0 | K6: =K34 -> 0
G7: =IF(K34<>0,G6/K34,0) -> 0 | H7: =IF(K34<>0,H6/K34,0) -> 0 | I7: =IF(K34<>0,I6/K34,0) -> 0 | J7: =IF(K34<>0,J6/K34,0) -> 0 | K7: =IF(K34<>0,K6/ORC_Custo!G33,0) -> 0
B10: CÓDIGO | D10: DESCRIÇÃO | E10: QUANT. | F10: UN. | G10: VALOR UNITÁRIO | K10: TOTAL
G11: MATERIAL | H11: MÃO DE OBRA | I11: EQUIPAMENTO | J11: SERVIÇO
C13: 15.01 | F13: m | K13: =(G13+H13+I13+J13)*E13 -> 0
C14: 15.02 | F14: m | K14: =(G14+H14+I14+J14)*E14 -> 0
C15: 15.03 | F15: m | K15: =(G15+H15+I15+J15)*E15 -> 0
C16: 15.04 | F16: m | K16: =(G16+H16+I16+J16)*E16 -> 0
C17: 15.05 | F17: m | K17: =(G17+H17+I17+J17)*E17 -> 0
C18: 15.06 | F18: m | K18: =(G18+H18+I18+J18)*E18 -> 0
C19: 15.07 | F19: m | K19: =(G19+H19+I19+J19)*E19 -> 0
C20: 15.08 | F20: m | K20: =(G20+H20+I20+J20)*E20 -> 0
C21: 15.09 | F21: m | K21: =(G21+H21+I21+J21)*E21 -> 0
C22: 15.10 | F22: m | K22: =(G22+H22+I22+J22)*E22 -> 0
C23: 15.11 | F23: m | K23: =(G23+H23+I23+J23)*E23 -> 0
C24: 15.12 | F24: m | K24: =(G24+H24+I24+J24)*E24 -> 0
... C32: 15.20 | F32: m | K32: =(G32+H32+I32+J32)*E32 -> 0
D34: TOTAL DO GRUPO | K34: =SUM(K13:K33) -> 0

Sheet 16.
B2: 16. ESQUADRIAS DE ALUMÍNIO E VIDROS
C3: RESUMO
C5: Exemplos de itens do Grupo: Portas, janelas e outros elementos de alumínio e vidro. | G5: Material | H5: Mão-de-obra | I5: Equipamento | J5: Serviço | K5: Total
G6: =SUMPRODUCT(E13:E33,G13:G33) -> 0 | H6: =SUMPRODUCT(E13:E33,H13:H33) -> 0 | I6: =SUMPRODUCT(E13:E33,I13:I33) -> 0 | J6: =SUMPRODUCT(E13:E33,J13:J33) -> 0 | K6: =K34 -> 0
G7: =IF(K34<>0,G6/K34,0) -> 0 | H7: =IF(K34<>0,H6/K34,0) -> 0 | I7: =IF(K34<>0,I6/K34,0) -> 0 | J7: =IF(K34<>0,J6/K34,0) -> 0 | K7: =IF(K34<>0,K6/ORC_Custo!G33,0) -> 0
B10: CÓDIGO | D10: DESCRIÇÃO | E10: QUANT. | F10: UN. | G10: VALOR UNITÁRIO | K10: TOTAL
G11: MATERIAL | H11: MÃO DE OBRA | I11: EQUIPAMENTO | J11: SERVIÇO
C13: 16.01 | F13: m | K13: =(G13+H13+I13+J13)*E13 -> 0
C14: 16.02 | F14: m | K14: =(G14+H14+I14+J14)*E14 -> 0
C15: 16.03 | F15: m | K15: =(G15+H15+I15+J15)*E15 -> 0
C16: 16.04 | F16: m | K16: =(G16+H16+I16+J16)*E16 -> 0
C17: 16.05 | F17: m | K17: =(G17+H17+I17+J17)*E17 -> 0
C18: 16.06 | F18: m | K18: =(G18+H18+I18+J18)*E18 -> 0
C19: 16.07 | F19: m | K19: =(G19+H19+I19+J19)*E19 -> 0
C20: 16.08 | F20: m | K20: =(G20+H20+I20+J20)*E20 -> 0
C21: 16.09 | F21: m | K21: =(G21+H21+I21+J21)*E21 -> 0
C22: 16.10 | F22: m | K22: =(G22+H22+I22+J22)*E22 -> 0
C23: 16.11 | F23: m | K23: =(G23+H23+I23+J23)*E23 -> 0
C24: 16.12 | F24: m | K24: =(G24+H24+I24+J24)*E24 -> 0
... C32: 16.20 | F32: m | K32: =(G32+H32+I32+J32)*E32 -> 0
D34: TOTAL DO GRUPO | K34: =SUM(K13:K33) -> 0

Sheet 17.
B2: 17. ESQUADRIAS DE FERRO
C3: RESUMO
C5: Exemplos de itens do Grupo: Portões, portas, janelas, guarda-corpo, escadas e outros elementos de ferro. | G5: Material | H5: Mão-de-obra | I5: Equipamento | J5: Serviço | K5: Total
G6: =SUMPRODUCT(E13:E33,G13:G33) -> 0 | H6: =SUMPRODUCT(E13:E33,H13:H33) -> 0 | I6: =SUMPRODUCT(E13:E33,I13:I33) -> 0 | J6: =SUMPRODUCT(E13:E33,J13:J33) -> 0 | K6: =K34 -> 0
G7: =IF(K34<>0,G6/K34,0) -> 0 | H7: =IF(K34<>0,H6/K34,0) -> 0 | I7: =IF(K34<>0,I6/K34,0) -> 0 | J7: =IF(K34<>0,J6/K34,0) -> 0 | K7: =IF(K34<>0,K6/ORC_Custo!G33,0) -> 0
B10: CÓDIGO | D10: DESCRIÇÃO | E10: QUANT. | F10: UN. | G10: VALOR UNITÁRIO | K10: TOTAL
G11: MATERIAL | H11: MÃO DE OBRA | I11: EQUIPAMENTO | J11: SERVIÇO
C13: 17.01 | F13: m | K13: =(G13+H13+I13+J13)*E13 -> 0
C14: 17.02 | F14: m | K14: =(G14+H14+I14+J14)*E14 -> 0
C15: 17.03 | F15: m | K15: =(G15+H15+I15+J15)*E15 -> 0
C16: 17.04 | F16: m | K16: =(G16+H16+I16+J16)*E16 -> 0
C17: 17.05 | F17: m | K17: =(G17+H17+I17+J17)*E17 -> 0
C18: 17.06 | F18: m | K18: =(G18+H18+I18+J18)*E18 -> 0
C19: 17.07 | F19: m | K19: =(G19+H19+I19+J19)*E19 -> 0
C20: 17.08 | F20: m | K20: =(G20+H20+I20+J20)*E20 -> 0
C21: 17.09 | F21: m | K21: =(G21+H21+I21+J21)*E21 -> 0
C22: 17.10 | F22: m | K22: =(G22+H22+I22+J22)*E22 -> 0
C23: 17.11 | F23: m | K23: =(G23+H23+I23+J23)*E23 -> 0
C24: 17.12 | F24: m | K24: =(G24+H24+I24+J24)*E24 -> 0
... C32: 17.20 | F32: m | K32: =(G32+H32+I32+J32)*E32 -> 0
D34: TOTAL DO GRUPO | K34: =SUM(K13:K33) -> 0

Sheet 18.
B2: 18. PISOS INTERNOS
C3: RESUMO
C5: Exemplos de itens do Grupo: Enchimentos, contrapiso e revestimentos de pisos internos. | G5: Material | H5: Mão-de-obra | I5: Equipamento | J5: Serviço | K5: Total
G6: =SUMPRODUCT(E13:E33,G13:G33) -> 0 | H6: =SUMPRODUCT(E13:E33,H13:H33) -> 0 | I6: =SUMPRODUCT(E13:E33,I13:I33) -> 0 | J6: =SUMPRODUCT(E13:E33,J13:J33) -> 0 | K6: =K34 -> 0
G7: =IF(K34<>0,G6/K34,0) -> 0 | H7: =IF(K34<>0,H6/K34,0) -> 0 | I7: =IF(K34<>0,I6/K34,0) -> 0 | J7: =IF(K34<>0,J6/K34,0) -> 0 | K7: =IF(K34<>0,K6/ORC_Custo!G33,0) -> 0
B10: CÓDIGO | D10: DESCRIÇÃO | E10: QUANT. | F10: UN. | G10: VALOR UNITÁRIO | K10: TOTAL
G11: MATERIAL | H11: MÃO DE OBRA | I11: EQUIPAMENTO | J11: SERVIÇO
C13: 18.01 | F13: m | K13: =(G13+H13+I13+J13)*E13 -> 0
C14: 18.02 | F14: m | K14: =(G14+H14+I14+J14)*E14 -> 0
C15: 18.03 | F15: m | K15: =(G15+H15+I15+J15)*E15 -> 0
C16: 18.04 | F16: m | K16: =(G16+H16+I16+J16)*E16 -> 0
C17: 18.05 | F17: m | K17: =(G17+H17+I17+J17)*E17 -> 0
C18: 18.06 | F18: m | K18: =(G18+H18+I18+J18)*E18 -> 0
C19: 18.07 | F19: m | K19: =(G19+H19+I19+J19)*E19 -> 0
C20: 18.08 | F20: m | K20: =(G20+H20+I20+J20)*E20 -> 0
C21: 18.09 | F21: m | K21: =(G21+H21+I21+J21)*E21 -> 0
C22: 18.10 | F22: m | K22: =(G22+H22+I22+J22)*E22 -> 0
C23: 18.11 | F23: m | K23: =(G23+H23+I23+J23)*E23 -> 0
C24: 18.12 | F24: m | K24: =(G24+H24+I24+J24)*E24 -> 0
... C32: 18.20 | F32: m | K32: =(G32+H32+I32+J32)*E32 -> 0
D34: TOTAL DO GRUPO | K34: =SUM(K13:K33) -> 0

Sheet 19.
B2: 19. INSTALAÇÕES ELÉTRICAS E ESPECIAIS
C3: RESUMO
C5: Exemplos de itens do Grupo: Elementos de instalações elétrica, telefonia, TV e outros, contendo quadros, caixas, cabos, fios, interruptores, tomadas e outros. | G5: Material | H5: Mão-de-obra | I5: Equipamento | J5: Serviço | K5: Total
G6: =SUMPRODUCT(E13:E33,G13:G33) -> 0 | H6: =SUMPRODUCT(E13:E33,H13:H33) -> 0 | I6: =SUMPRODUCT(E13:E33,I13:I33) -> 0 | J6: =SUMPRODUCT(E13:E33,J13:J33) -> 0 | K6: =K34 -> 0
G7: =IF(K34<>0,G6/K34,0) -> 0 | H7: =IF(K34<>0,H6/K34,0) -> 0 | I7: =IF(K34<>0,I6/K34,0) -> 0 | J7: =IF(K34<>0,J6/K34,0) -> 0 | K7: =IF(K34<>0,K6/ORC_Custo!G33,0) -> 0
B10: CÓDIGO | D10: DESCRIÇÃO | E10: QUANT. | F10: UN. | G10: VALOR UNITÁRIO | K10: TOTAL
G11: MATERIAL | H11: MÃO DE OBRA | I11: EQUIPAMENTO | J11: SERVIÇO
C13: 19.01 | F13: m | K13: =(G13+H13+I13+J13)*E13 -> 0
C14: 19.02 | F14: m | K14: =(G14+H14+I14+J14)*E14 -> 0
C15: 19.03 | F15: m | K15: =(G15+H15+I15+J15)*E15 -> 0
C16: 19.04 | F16: m | K16: =(G16+H16+I16+J16)*E16 -> 0
C17: 19.05 | F17: m | K17: =(G17+H17+I17+J17)*E17 -> 0
C18: 19.06 | F18: m | K18: =(G18+H18+I18+J18)*E18 -> 0
C19: 19.07 | F19: m | K19: =(G19+H19+I19+J19)*E19 -> 0
C20: 19.08 | F20: m | K20: =(G20+H20+I20+J20)*E20 -> 0
C21: 19.09 | F21: m | K21: =(G21+H21+I21+J21)*E21 -> 0
C22: 19.10 | F22: m | K22: =(G22+H22+I22+J22)*E22 -> 0
C23: 19.11 | F23: m | K23: =(G23+H23+I23+J23)*E23 -> 0
C24: 19.12 | F24: m | K24: =(G24+H24+I24+J24)*E24 -> 0
... C32: 19.20 | F32: m | K32: =(G32+H32+I32+J32)*E32 -> 0
D34: TOTAL DO GRUPO | K34: =SUM(K13:K33) -> 0

Sheet 20.
B2: 20. INSTALAÇÕES HIDROSSANITÁRIAS
C3: RESUMO
C5: Exemplos de itens do Grupo: Elementos de instalações hidráulica, esgoto, águas pluviais, gás e outros, contendo caixas, tubos, registros e outros. | G5: Material | H5: Mão-de-obra | I5: Equipamento | J5: Serviço | K5: Total
G6: =SUMPRODUCT(E13:E33,G13:G33) -> 0 | H6: =SUMPRODUCT(E13:E33,H13:H33) -> 0 | I6: =SUMPRODUCT(E13:E33,I13:I33) -> 0 | J6: =SUMPRODUCT(E13:E33,J13:J33) -> 0 | K6: =K34 -> 0
G7: =IF(K34<>0,G6/K34,0) -> 0 | H7: =IF(K34<>0,H6/K34,0) -> 0 | I7: =IF(K34<>0,I6/K34,0) -> 0 | J7: =IF(K34<>0,J6/K34,0) -> 0 | K7: =IF(K34<>0,K6/ORC_Custo!G33,0) -> 0
B10: CÓDIGO | D10: DESCRIÇÃO | E10: QUANT. | F10: UN. | G10: VALOR UNITÁRIO | K10: TOTAL
G11: MATERIAL | H11: MÃO DE OBRA | I11: EQUIPAMENTO | J11: SERVIÇO
C13: 20.01 | F13: m | K13: =(G13+H13+I13+J13)*E13 -> 0
C14: 20.02 | F14: m | K14: =(G14+H14+I14+J14)*E14 -> 0
C15: 20.03 | F15: m | K15: =(G15+H15+I15+J15)*E15 -> 0
C16: 20.04 | F16: m | K16: =(G16+H16+I16+J16)*E16 -> 0
C17: 20.05 | F17: m | K17: =(G17+H17+I17+J17)*E17 -> 0
C18: 20.06 | F18: m | K18: =(G18+H18+I18+J18)*E18 -> 0
C19: 20.07 | F19: m | K19: =(G19+H19+I19+J19)*E19 -> 0
C20: 20.08 | F20: m | K20: =(G20+H20+I20+J20)*E20 -> 0
C21: 20.09 | F21: m | K21: =(G21+H21+I21+J21)*E21 -> 0
C22: 20.10 | F22: m | K22: =(G22+H22+I22+J22)*E22 -> 0
C23: 20.11 | F23: m | K23: =(G23+H23+I23+J23)*E23 -> 0
C24: 20.12 | F24: m | K24: =(G24+H24+I24+J24)*E24 -> 0
... C32: 20.20 | F32: m | K32: =(G32+H32+I32+J32)*E32 -> 0
D34: TOTAL DO GRUPO | K34: =SUM(K13:K33) -> 0

Sheet 21.
B2: 21. ELEVADOR E EQUIPAMENTOS MECÂNICOS
C3: RESUMO
C5: Exemplos de itens do Grupo: Elevador, escada rolante, monta-carga, ventilação mecânica, pressurização de escada e outros. | G5: Material | H5: Mão-de-obra | I5: Equipamento | J5: Serviço | K5: Total
G6: =SUMPRODUCT(E13:E33,G13:G33) -> 0 | H6: =SUMPRODUCT(E13:E33,H13:H33) -> 0 | I6: =SUMPRODUCT(E13:E33,I13:I33) -> 0 | J6: =SUMPRODUCT(E13:E33,J13:J33) -> 0 | K6: =K34 -> 0
G7: =IF(K34<>0,G6/K34,0) -> 0 | H7: =IF(K34<>0,H6/K34,0) -> 0 | I7: =IF(K34<>0,I6/K34,0) -> 0 | J7: =IF(K34<>0,J6/K34,0) -> 0 | K7: =IF(K34<>0,K6/ORC_Custo!G33,0) -> 0
B10: CÓDIGO | D10: DESCRIÇÃO | E10: QUANT. | F10: UN. | G10: VALOR UNITÁRIO | K10: TOTAL
G11: MATERIAL | H11: MÃO DE OBRA | I11: EQUIPAMENTO | J11: SERVIÇO
C13: 21.01 | F13: m | K13: =(G13+H13+I13+J13)*E13 -> 0
C14: 21.02 | F14: m | K14: =(G14+H14+I14+J14)*E14 -> 0
C15: 21.03 | F15: m | K15: =(G15+H15+I15+J15)*E15 -> 0
C16: 21.04 | F16: m | K16: =(G16+H16+I16+J16)*E16 -> 0
C17: 21.05 | F17: m | K17: =(G17+H17+I17+J17)*E17 -> 0
C18: 21.06 | F18: m | K18: =(G18+H18+I18+J18)*E18 -> 0
C19: 21.07 | F19: m | K19: =(G19+H19+I19+J19)*E19 -> 0
C20: 21.08 | F20: m | K20: =(G20+H20+I20+J20)*E20 -> 0
C21: 21.09 | F21: m | K21: =(G21+H21+I21+J21)*E21 -> 0
C22: 21.10 | F22: m | K22: =(G22+H22+I22+J22)*E22 -> 0
C23: 21.11 | F23: m | K23: =(G23+H23+I23+J23)*E23 -> 0
C24: 21.12 | F24: m | K24: =(G24+H24+I24+J24)*E24 -> 0
... C32: 21.20 | F32: m | K32: =(G32+H32+I32+J32)*E32 -> 0
D34: TOTAL DO GRUPO | K34: =SUM(K13:K33) -> 0

Sheet 22.
B2: 22. LOUÇAS E METAIS
C3: RESUMO
C5: Exemplos de itens do Grupo: Vaso sanitário, mictório, cubas, lavatórios, torneiras, chuveiro e outros. | G5: Material | H5: Mão-de-obra | I5: Equipamento | J5: Serviço | K5: Total
G6: =SUMPRODUCT(E13:E33,G13:G33) -> 0 | H6: =SUMPRODUCT(E13:E33,H13:H33) -> 0 | I6: =SUMPRODUCT(E13:E33,I13:I33) -> 0 | J6: =SUMPRODUCT(E13:E33,J13:J33) -> 0 | K6: =K34 -> 0
G7: =IF(K34<>0,G6/K34,0) -> 0 | H7: =IF(K34<>0,H6/K34,0) -> 0 | I7: =IF(K34<>0,I6/K34,0) -> 0 | J7: =IF(K34<>0,J6/K34,0) -> 0 | K7: =IF(K34<>0,K6/ORC_Custo!G33,0) -> 0
B10: CÓDIGO | D10: DESCRIÇÃO | E10: QUANT. | F10: UN. | G10: VALOR UNITÁRIO | K10: TOTAL
G11: MATERIAL | H11: MÃO DE OBRA | I11: EQUIPAMENTO | J11: SERVIÇO
C13: 22.01 | F13: m | K13: =(G13+H13+I13+J13)*E13 -> 0
C14: 22.02 | F14: m | K14: =(G14+H14+I14+J14)*E14 -> 0
C15: 22.03 | F15: m | K15: =(G15+H15+I15+J15)*E15 -> 0
C16: 22.04 | F16: m | K16: =(G16+H16+I16+J16)*E16 -> 0
C17: 22.05 | F17: m | K17: =(G17+H17+I17+J17)*E17 -> 0
C18: 22.06 | F18: m | K18: =(G18+H18+I18+J18)*E18 -> 0
C19: 22.07 | F19: m | K19: =(G19+H19+I19+J19)*E19 -> 0
C20: 22.08 | F20: m | K20: =(G20+H20+I20+J20)*E20 -> 0
C21: 22.09 | F21: m | K21: =(G21+H21+I21+J21)*E21 -> 0
C22: 22.10 | F22: m | K22: =(G22+H22+I22+J22)*E22 -> 0
C23: 22.11 | F23: m | K23: =(G23+H23+I23+J23)*E23 -> 0
C24: 22.12 | F24: m | K24: =(G24+H24+I24+J24)*E24 -> 0
... C32: 22.20 | F32: m | K32: =(G32+H32+I32+J32)*E32 -> 0
D34: TOTAL DO GRUPO | K34: =SUM(K13:K33) -> 0

Sheet 23.
B2: 23. PINTURA E LIMPEZA
C3: RESUMO
C5: Exemplos de itens do Grupo: Pintura interna e externa, limpeza grossa e limpeza fina. | G5: Material | H5: Mão-de-obra | I5: Equipamento | J5: Serviço | K5: Total
G6: =SUMPRODUCT(E13:E33,G13:G33) -> 0 | H6: =SUMPRODUCT(E13:E33,H13:H33) -> 0 | I6: =SUMPRODUCT(E13:E33,I13:I33) -> 0 | J6: =SUMPRODUCT(E13:E33,J13:J33) -> 0 | K6: =K34 -> 0
G7: =IF(K34<>0,G6/K34,0) -> 0 | H7: =IF(K34<>0,H6/K34,0) -> 0 | I7: =IF(K34<>0,I6/K34,0) -> 0 | J7: =IF(K34<>0,J6/K34,0) -> 0 | K7: =IF(K34<>0,K6/ORC_Custo!G33,0) -> 0
B10: CÓDIGO | D10: DESCRIÇÃO | E10: QUANT. | F10: UN. | G10: VALOR UNITÁRIO | K10: TOTAL
G11: MATERIAL | H11: MÃO DE OBRA | I11: EQUIPAMENTO | J11: SERVIÇO
C13: 23.01 | F13: m | K13: =(G13+H13+I13+J13)*E13 -> 0
C14: 23.02 | F14: m | K14: =(G14+H14+I14+J14)*E14 -> 0
C15: 23.03 | F15: m | K15: =(G15+H15+I15+J15)*E15 -> 0
C16: 23.04 | F16: m | K16: =(G16+H16+I16+J16)*E16 -> 0
C17: 23.05 | F17: m | K17: =(G17+H17+I17+J17)*E17 -> 0
C18: 23.06 | F18: m | K18: =(G18+H18+I18+J18)*E18 -> 0
C19: 23.07 | F19: m | K19: =(G19+H19+I19+J19)*E19 -> 0
C20: 23.08 | F20: m | K20: =(G20+H20+I20+J20)*E20 -> 0
C21: 23.09 | F21: m | K21: =(G21+H21+I21+J21)*E21 -> 0
C22: 23.10 | F22: m | K22: =(G22+H22+I22+J22)*E22 -> 0
C23: 23.11 | F23: m | K23: =(G23+H23+I23+J23)*E23 -> 0
C24: 23.12 | F24: m | K24: =(G24+H24+I24+J24)*E24 -> 0
... C32: 23.20 | F32: m | K32: =(G32+H32+I32+J32)*E32 -> 0
D34: TOTAL DO GRUPO | K34: =SUM(K13:K33) -> 0

Sheet DSHB

Sheet Dados
C2: 01. | D2: 02. | E2: 03. | F2: 04. | G2: 05. | H2: 06. | I2: 07. | J2: 08. | K2: 09. | L2: 10. | M2: 11. | N2: 12. | O2: 13. | P2: 14. | Q2: 15. | R2: 16. | S2: 17. | T2: 18. | U2: 19. | V2: 20. | W2: 21. | X2: 22. | Y2: 23.
B3: Material | C3: ='01.'!G6 -> 0 | D3: ='02.'!G6 -> 0 | E3: ='03.'!G6 -> 0 | F3: ='04.'!G6 -> 0 | G3: ='05.'!G6 -> 0 | H3: ='06.'!G6 -> 0 | I3: ='07.'!G6 -> 0 | J3: ='08.'!G6 -> 0 | K3: ='09.'!G6 -> 0 | L3: ='10.'!G6 -> 0 | M3: ='11.'!G6 -> 0 | N3: ='12.'!G6 -> 0 | O3: ='13.'!G6 -> 0 | P3: ='14.'!G6 -> 0 | Q3: ='15.'!G6 -> 0 | R3: ='16.'!G6 -> 0 | S3: ='17.'!G6 -> 0 | T3: ='18.'!G6 -> 0 | U3: ='19.'!G6 -> 0 | V3: ='20.'!G6 -> 0 | W3: ='21.'!G6 -> 0 | X3: ='22.'!G6 -> 0 | Y3: ='23.'!G6 -> 0 | Z3: =SUM(C3:Y3) -> 0
B4: Mão-de-obra | C4: ='01.'!H6 -> 0 | D4: ='02.'!H6 -> 0 | E4: ='03.'!H6 -> 0 | F4: ='04.'!H6 -> 0 | G4: ='05.'!H6 -> 0 | H4: ='06.'!H6 -> 0 | I4: ='07.'!H6 -> 0 | J4: ='08.'!H6 -> 0 | K4: ='09.'!H6 -> 0 | L4: ='10.'!H6 -> 0 | M4: ='11.'!H6 -> 0 | N4: ='12.'!H6 -> 0 | O4: ='13.'!H6 -> 0 | P4: ='14.'!H6 -> 0 | Q4: ='15.'!H6 -> 0 | R4: ='16.'!H6 -> 0 | S4: ='17.'!H6 -> 0 | T4: ='18.'!H6 -> 0 | U4: ='19.'!H6 -> 0 | V4: ='20.'!H6 -> 0 | W4: ='21.'!H6 -> 0 | X4: ='22.'!H6 -> 0 | Y4: ='23.'!H6 -> 0 | Z4: =SUM(C4:Y4) -> 0
B5: Equipamento | C5: ='01.'!I6 -> 0 | D5: ='02.'!I6 -> 0 | E5: ='03.'!I6 -> 0 | F5: ='04.'!I6 -> 0 | G5: ='05.'!I6 -> 0 | H5: ='06.'!I6 -> 0 | I5: ='07.'!I6 -> 0 | J5: ='08.'!I6 -> 0 | K5: ='09.'!I6 -> 0 | L5: ='10.'!I6 -> 0 | M5: ='11.'!I6 -> 0 | N5: ='12.'!I6 -> 0 | O5: ='13.'!I6 -> 0 | P5: ='14.'!I6 -> 0 | Q5: ='15.'!I6 -> 0 | R5: ='16.'!I6 -> 0 | S5: ='17.'!I6 -> 0 | T5: ='18.'!I6 -> 0 | U5: ='19.'!I6 -> 0 | V5: ='20.'!I6 -> 0 | W5: ='21.'!I6 -> 0 | X5: ='22.'!I6 -> 0 | Y5: ='23.'!I6 -> 0 | Z5: =SUM(C5:Y5) -> 0
B6: Serviço | C6: ='01.'!J6 -> 0 | D6: ='02.'!J6 -> 0 | E6: ='03.'!J6 -> 0 | F6: ='04.'!J6 -> 0 | G6: ='05.'!J6 -> 0 | H6: ='06.'!J6 -> 0 | I6: ='07.'!J6 -> 0 | J6: ='08.'!J6 -> 0 | K6: ='09.'!J6 -> 0 | L6: ='10.'!J6 -> 0 | M6: ='11.'!J6 -> 0 | N6: ='12.'!J6 -> 0 | O6: ='13.'!J6 -> 0 | P6: ='14.'!J6 -> 0 | Q6: ='15.'!J6 -> 0 | R6: ='16.'!J6 -> 0 | S6: ='17.'!J6 -> 0 | T6: ='18.'!J6 -> 0 | U6: ='19.'!J6 -> 0 | V6: ='20.'!J6 -> 0 | W6: ='21.'!J6 -> 0 | X6: ='22.'!J6 -> 0 | Y6: ='23.'!J6 -> 0 | Z6: =SUM(C6:Y6) -> 0
B7: Total | C7: ='01.'!K6 -> 0 | D7: ='02.'!K6 -> 0 | E7: ='03.'!K6 -> 0 | F7: ='04.'!K6 -> 0 | G7: ='05.'!K6 -> 0 | H7: ='06.'!K6 -> 0 | I7: ='07.'!K6 -> 0 | J7: ='08.'!K6 -> 0 | K7: ='09.'!K6 -> 0 | L7: ='10.'!K6 -> 0 | M7: ='11.'!K6 -> 0 | N7: ='12.'!K6 -> 0 | O7: ='13.'!K6 -> 0 | P7: ='14.'!K6 -> 0 | Q7: ='15.'!K6 -> 0 | R7: ='16.'!K6 -> 0 | S7: ='17.'!K6 -> 0 | T7: ='18.'!K6 -> 0 | U7: ='19.'!K6 -> 0 | V7: ='20.'!K6 -> 0 | W7: ='21.'!K6 -> 0 | X7: ='22.'!K6 -> 0 | Y7: ='23.'!K6 -> 0 | Z7: =SUM(C7:Y7) -> 0
