Workbook

Sheet Custos Gerais
B2: PLANILHA PARA CÁLCULO DE HONORÁRIOS CONTÁBEIS
B4: Data/Base: | E4: 39845
B5: Descrição | D5: Depto.Fiscal | E5: Depto.Contábil | F5: Depto.Pessoal | G5: Administrativo
B6: Custo Salarial | D6: 2100 | E6: 2300 | F6: 2400 | G6: 1100
B7: INSS | C7: 0.288 | D7: =D6*$C$7 -> 604.8 | E7: =E6*$C$7 -> 662.4 | F7: =F6*$C$7 -> 691.2 | G7: =G6*$C$7 -> 316.8 | I7: Instruções
B8: FGTS | C8: 0.08 | D8: =D6*$C$8 -> 168 | E8: =E6*$C$8 -> 184 | F8: =F6*$C$8 -> 192 | G8: =G6*$C$8 -> 88
B9: 13º Salário | C9: =1/12 -> 0.083333333 | D9: =D6*$C$9 -> 175 | E9: =E6*$C$9 -> 191.66667 | F9: =F6*$C$9 -> 200 | G9: =G6*$C$9 -> 91.666667 | I9: Preencha as células de cor amarela.
B10: Férias | C10: =1/12*1.3333 -> 0.11110833 | D10: =D6*$C$10 -> 233.3275 | E10: =E6*$C$10 -> 255.54917 | F10: =F6*$C$10 -> 266.66 | G10: =G6*$C$10 -> 122.21917
B11: INSS+FGTS s/ 13º e Férias | C11: =SUM(C7:C8)*(SUM(C9:C10)) -> 0.071554533 | D11: =D7*$C$10 -> 67.19832 | E11: =E7*$C$10 -> 73.59816 | F11: =F7*$C$10 -> 76.79808 | G11: =G7*$C$10 -> 35.19912
B12: Multa Rescisória 50% FGTS | C12: =(C8+C10*C8)*50% -> 0.044444333 | D12: =D6*$C$12 -> 93.3331 | E12: =E6*$C$12 -> 102.22197 | F12: =F6*$C$12 -> 106.6664 | G12: =G6*$C$12 -> 48.888767
B13: Vale Transporte e Refeição | C13: 0.085 | D13: =D6*$C$13 -> 178.5 | E13: =E6*$C$13 -> 195.5 | F13: =F6*$C$13 -> 204 | G13: =G6*$C$13 -> 93.5
B14: Soma Encargos | C14: =SUM(C7:C13) -> 0.76344053 | D14: =SUM(D7:D13) -> 1520.1589 | E14: =SUM(E7:E13) -> 1664.936 | F14: =SUM(F7:F13) -> 1737.3245 | G14: =SUM(G7:G13) -> 796.27372
B15: TOTAL CUSTOS | D15: =SUM(D6+D14) -> 3620.1589 | E15: =SUM(E6+E14) -> 3964.936 | F15: =SUM(F6+F14) -> 4137.3245 | G15: =SUM(G6+G14) -> 1896.2737
B16: Participação custo salarial total | C16: =D15+E15+F15 -> 11722.419 | D16: =D15/$C$16 -> 0.30882353 | E16: =E15/$C$16 -> 0.33823529 | F16: =F15/C16 -> 0.35294118
B18: CUSTOS FIXOS MENSAIS
B19: Propaganda e publicidade | C19: 500
B20: Treinamento Pessoal | C20: 1200
B21: Aluguel | C21: 600
B22: Energia Eletrica | C22: 450
B23: Manutenções diversas | C23: 400
B24: Manutenções softwares | C24: 250
B25: Material escritório | C25: 750
B26: Telefones | C26: 500
B27: Pró - labore | C27: 5100
B28: Despesas Gerais (CRC, Cont. Sindical, Depreciação, etc.) | C28: 1000
B29: Tarifas Bancárias | C29: 400
B31: TOTAL CUSTO FIXO | C31: =SUM(C19:C30) -> 11150
B33: RATEIO DOS CUSTOS | D33: D.Fiscal | E33: D.Contábil | F33: D.Pessoal
B34: Custo Salarial + encargos | D34: =D15 -> 3620.1589 | E34: =E15 -> 3964.936 | F34: =F15 -> 4137.3245
B35: Rateio salarial administrativos | D35: =G15*D16 -> 585.61394 | E35: =G15*E16 -> 641.3867 | F35: =G15*F16 -> 669.27308
B36: Rateio custos fixos | D36: =C31*D16 -> 3443.3824 | E36: =C31*E16 -> 3771.3235 | F36: =C31*F16 -> 3935.2941
B38: CUSTO TOTAL | D38: =SUM(D34:D37) -> 7649.1552 | E38: =SUM(E34:E37) -> 8377.6462 | F38: =SUM(F34:F37) -> 8741.8917
B39: CUSTO TOTAL GERAL | C39: =D38+E38+F38 -> 24768.693
B40: CUSTO INDIVIDUALIZADO | D40: =D38/Clientes!G41 -> 2.3341945 | E40: =E38/Clientes!H41 -> 1.5629937 | F40: =F38/Clientes!I41 -> 31.221042

Sheet Clientes
B2: PLANILHA PARA CÁLCULO DE HONORÁRIOS CONTÁBEIS
B4: Nº | C4: EMPRESA | D4: NFs Entrada | E4: NFs Saída | F4: NFs Serv | G4: Tot.NFs | H4: Nº Lançam. Contábeis | I4: Empregados
B5: 001 | C5: JS | D5: 22 | E5: 271 | G5: =SUM(D5:F5) -> 293 | H5: 350 | I5: 26
B6: 006 | C6: ABC | F6: 10 | G6: =SUM(D6:F6) -> 10 | H6: 20 | I6: 1 | K6: Instruções
B7: 013 | C7: XYZ | D7: 34 | E7: 203 | F7: 3 | G7: =SUM(D7:F7) -> 240 | H7: 300 | I7: 4
B8: 015 | C8: VVV | F8: 28 | G8: =SUM(D8:F8) -> 28 | H8: 200 | I8: 51 | K8: Preencha as células de cor amarela.
B9: 016 | C9: TAB | D9: 3 | E9: 50 | F9: 26 | G9: =SUM(D9:F9) -> 79 | H9: 80 | I9: 5
B10: 023 | C10: YO0O | D10: 46 | E10: 36 | G10: =SUM(D10:F10) -> 82 | H10: 150 | I10: 3
B11: 024 | C11: UIO | D11: 7 | E11: 23 | G11: =SUM(D11:F11) -> 30 | H11: 50 | I11: 2
B12: 025 | C12: IEO | D12: 180 | E12: 171 | G12: =SUM(D12:F12) -> 351 | H12: 430 | I12: 9
B13: 027 | C13: OEI | D13: 162 | E13: 124 | G13: =SUM(D13:F13) -> 286 | H13: 520 | I13: 7
B14: 028 | C14: OEUI | D14: 26 | E14: 35 | F14: 28 | G14: =SUM(D14:F14) -> 89 | H14: 100 | I14: 8
B15: 030 | C15: ONM | D15: 14 | E15: 32 | F15: 48 | G15: =SUM(D15:F15) -> 94 | H15: 100 | I15: 7
B16: 031 | C16: IOMB | D16: 5 | E16: 3 | F16: 4 | G16: =SUM(D16:F16) -> 12 | H16: 40 | I16: 5
B17: 036 | C17: IOO | D17: 4 | E17: 27 | G17: =SUM(D17:F17) -> 31 | H17: 70 | I17: 2
B18: 041 | C18: MNN | D18: 31 | E18: 121 | F18: 64 | G18: =SUM(D18:F18) -> 216 | H18: 250 | I18: 8
B19: 042 | C19: MM | D19: 13 | E19: 11 | F19: 12 | G19: =SUM(D19:F19) -> 36 | H19: 80 | I19: 3
B20: 044 | C20: MEB | D20: 25 | E20: 36 | G20: =SUM(D20:F20) -> 61 | H20: 80 | I20: 4
B21: 046 | C21: EAD | D21: 29 | E21: 10 | G21: =SUM(D21:F21) -> 39 | H21: 70 | I21: 5
B22: 055 | C22: EIA | E22: 20 | F22: 1 | G22: =SUM(D22:F22) -> 21 | H22: 20 | I22: 6
B23: 062 | C23: ILMNB | E23: 5 | F23: 5 | G23: =SUM(D23:F23) -> 10 | H23: 40 | I23: 3
B24: 063 | C24: IMM | D24: 14 | E24: 62 | F24: 32 | G24: =SUM(D24:F24) -> 108 | H24: 200 | I24: 8
B25: 066 | C25: IMMB | D25: 85 | E25: 80 | G25: =SUM(D25:F25) -> 165 | H25: 200 | I25: 21
B26: 073 | C26: NBU | E26: 5 | G26: =SUM(D26:F26) -> 5 | I26: 2
B27: 076 | C27: FIL | D27: 36 | E27: 209 | F27: 61 | G27: =SUM(D27:F27) -> 306 | H27: 350 | I27: 8
B28: 081 | C28: INN | D28: 10 | G28: =SUM(D28:F28) -> 10 | I28: 3
B29: 082 | C29: NBI | D29: 4 | E29: 26 | F29: 8 | G29: =SUM(D29:F29) -> 38 | H29: 70 | I29: 10
B30: 083 | C30: UIB | G30: =SUM(D30:F30) -> 0 | H30: 320 | I30: 8
B31: 090 | C31: UOO | D31: 11 | E31: 64 | G31: =SUM(D31:F31) -> 75 | H31: 120 | I31: 8
B32: 093 | C32: NMB | D32: 4 | F32: 9 | G32: =SUM(D32:F32) -> 13 | H32: 120 | I32: 12
B33: 105 | C33: ABD | D33: 4 | F33: 13 | G33: =SUM(D33:F33) -> 17 | H33: 80 | I33: 13
B34: 118 | C34: OIP | D34: 21 | E34: 68 | G34: =SUM(D34:F34) -> 89 | H34: 100 | I34: 5
B35: 148 | C35: OOOU | D35: 36 | E35: 111 | F35: 13 | G35: =SUM(D35:F35) -> 160 | H35: 300 | I35: 8
B36: 158 | C36: IUI | D36: 54 | E36: 78 | G36: =SUM(D36:F36) -> 132 | H36: 300 | I36: 3
B37: 162 | C37: XLC | D37: 14 | E37: 8 | F37: 31 | G37: =SUM(D37:F37) -> 53 | H37: 70 | I37: 4
B38: 165 | C38: UOX | D38: 21 | E38: 18 | G38: =SUM(D38:F38) -> 39 | H38: 50 | I38: 4
B39: 166 | C39: ZZI | D39: 5 | E39: 24 | G39: =SUM(D39:F39) -> 29 | H39: 80 | I39: 1
B40: 168 | C40: ZIO | D40: 9 | E40: 10 | F40: 11 | G40: =SUM(D40:F40) -> 30 | H40: 50 | I40: 3
B41: TOTAL | D41: =SUM(D5:D40) -> 929 | E41: =SUM(E5:E40) -> 1941 | F41: =SUM(F5:F40) -> 407 | G41: =SUM(G5:G40) -> 3277 | H41: =SUM(H5:H40) -> 5360 | I41: =SUM(I5:I40) -> 280

Sheet Custos x Honorários
B2: PLANILHA PARA CÁLCULO DE HONORÁRIOS CONTÁBEIS
B4: ENCARGOS S/RECEITA BRUTA
B5: Pis | C5: 0.0065 | M5: Instruções
B6: Cofins | C6: 0.03
B7: Contr. social s/lucro | C7: 0.0108 | M7: Preencha as células de cor amarela.
B8: IRPJ | C8: 0.048
B9: Total Encargos s/receita
B10: =SUM(C5:C8) -> 0.0953
B11: Margem Lucro
B12: 0.3
B14: Nº | C14: EMPRESA | D14: Custo DF | E14: Custo DC | F14: Custo DP | G14: C.Total | H14: Hon.Ideal | I14: Honorário | J14: Deficit | K14: Superavit
B15: =Clientes!B5 -> 001 | C15: =Clientes!C5 -> JS | D15: =Clientes!G5*$E$53 -> 683.91897 | E15: =Clientes!H5*$E$54 -> 547.04779 | F15: =Clientes!I5*$E$55 -> 811.74708 | G15: =SUM(D15:F15) -> 2042.7139 | H15: =(G15/(100%-$B$12))/(100%-$B$10) -> 3225.5584 | I15: 2000 | J15: =IF(I15<H15,(H15-I15),0) -> 1225.5584 | K15: =IF(I15>H15,(I15-H15),0) -> 0
B16: =Clientes!B6 -> 006 | C16: =Clientes!C6 -> ABC | D16: =Clientes!G6*$E$53 -> 23.341945 | E16: =Clientes!H6*$E$54 -> 31.259874 | F16: =Clientes!I6*$E$55 -> 31.221042 | G16: =SUM(D16:F16) -> 85.82286 | H16: =(G16/(100%-$B$12))/(100%-$B$10) -> 135.51905 | I16: 180 | J16: =IF(I16<H16,(H16-I16),0) -> 0 | K16: =IF(I16>H16,(I16-H16),0) -> 44.480949
B17: =Clientes!B7 -> 013 | C17: =Clientes!C7 -> XYZ | D17: =Clientes!G7*$E$53 -> 560.20667 | E17: =Clientes!H7*$E$54 -> 468.89811 | F17: =Clientes!I7*$E$55 -> 124.88417 | G17: =SUM(D17:F17) -> 1153.9889 | H17: =(G17/(100%-$B$12))/(100%-$B$10) -> 1822.2125 | I17: 1500 | J17: =IF(I17<H17,(H17-I17),0) -> 322.21248 | K17: =IF(I17>H17,(I17-H17),0) -> 0
B18: =Clientes!B8 -> 015 | C18: =Clientes!C8 -> VVV | D18: =Clientes!G8*$E$53 -> 65.357445 | E18: =Clientes!H8*$E$54 -> 312.59874 | F18: =Clientes!I8*$E$55 -> 1592.2731 | G18: =SUM(D18:F18) -> 1970.2293 | H18: =(G18/(100%-$B$12))/(100%-$B$10) -> 3111.1012 | I18: 2000 | J18: =IF(I18<H18,(H18-I18),0) -> 1111.1012 | K18: =IF(I18>H18,(I18-H18),0) -> 0
B19: =Clientes!B9 -> 016 | C19: =Clientes!C9 -> TAB | D19: =Clientes!G9*$E$53 -> 184.40136 | E19: =Clientes!H9*$E$54 -> 125.0395 | F19: =Clientes!I9*$E$55 -> 156.10521 | G19: =SUM(D19:F19) -> 465.54607 | H19: =(G19/(100%-$B$12))/(100%-$B$10) -> 735.12303 | I19: 750 | J19: =IF(I19<H19,(H19-I19),0) -> 0 | K19: =IF(I19>H19,(I19-H19),0) -> 14.876967
B20: =Clientes!B10 -> 023 | C20: =Clientes!C10 -> YO0O | D20: =Clientes!G10*$E$53 -> 191.40394 | E20: =Clientes!H10*$E$54 -> 234.44905 | F20: =Clientes!I10*$E$55 -> 93.663125 | G20: =SUM(D20:F20) -> 519.51612 | H20: =(G20/(100%-$B$12))/(100%-$B$10) -> 820.34475 | I20: 450 | J20: =IF(I20<H20,(H20-I20),0) -> 370.34475 | K20: =IF(I20>H20,(I20-H20),0) -> 0
B21: =Clientes!B11 -> 024 | C21: =Clientes!C11 -> UIO | D21: =Clientes!G11*$E$53 -> 70.025834 | E21: =Clientes!H11*$E$54 -> 78.149685 | F21: =Clientes!I11*$E$55 -> 62.442083 | G21: =SUM(D21:F21) -> 210.6176 | H21: =(G21/(100%-$B$12))/(100%-$B$10) -> 332.57686 | I21: 400 | J21: =IF(I21<H21,(H21-I21),0) -> 0 | K21: =IF(I21>H21,(I21-H21),0) -> 67.423137
B22: =Clientes!B12 -> 025 | C22: =Clientes!C12 -> IEO | D22: =Clientes!G12*$E$53 -> 819.30225 | E22: =Clientes!H12*$E$54 -> 672.08729 | F22: =Clientes!I12*$E$55 -> 280.98938 | G22: =SUM(D22:F22) -> 1772.3789 | H22: =(G22/(100%-$B$12))/(100%-$B$10) -> 2798.6845 | I22: 2500 | J22: =IF(I22<H22,(H22-I22),0) -> 298.68451 | K22: =IF(I22>H22,(I22-H22),0) -> 0
B23: =Clientes!B13 -> 027 | C23: =Clientes!C13 -> OEI | D23: =Clientes!G13*$E$53 -> 667.57961 | E23: =Clientes!H13*$E$54 -> 812.75672 | F23: =Clientes!I13*$E$55 -> 218.54729 | G23: =SUM(D23:F23) -> 1698.8836 | H23: =(G23/(100%-$B$12))/(100%-$B$10) -> 2682.6314 | I23: 2500 | J23: =IF(I23<H23,(H23-I23),0) -> 182.63138 | K23: =IF(I23>H23,(I23-H23),0) -> 0
B24: =Clientes!B14 -> 028 | C24: =Clientes!C14 -> OEUI | D24: =Clientes!G14*$E$53 -> 207.74331 | E24: =Clientes!H14*$E$54 -> 156.29937 | F24: =Clientes!I14*$E$55 -> 249.76833 | G24: =SUM(D24:F24) -> 613.81101 | H24: =(G24/(100%-$B$12))/(100%-$B$10) -> 969.24159 | I24: 900 | J24: =IF(I24<H24,(H24-I24),0) -> 69.241594 | K24: =IF(I24>H24,(I24-H24),0) -> 0
B25: =Clientes!B15 -> 030 | C25: =Clientes!C15 -> ONM | D25: =Clientes!G15*$E$53 -> 219.41428 | E25: =Clientes!H15*$E$54 -> 156.29937 | F25: =Clientes!I15*$E$55 -> 218.54729 | G25: =SUM(D25:F25) -> 594.26094 | H25: =(G25/(100%-$B$12))/(100%-$B$10) -> 938.37095 | I25: 800 | J25: =IF(I25<H25,(H25-I25),0) -> 138.37095 | K25: =IF(I25>H25,(I25-H25),0) -> 0
B26: =Clientes!B16 -> 031 | C26: =Clientes!C16 -> IOMB | D26: =Clientes!G16*$E$53 -> 28.010333 | E26: =Clientes!H16*$E$54 -> 62.519748 | F26: =Clientes!I16*$E$55 -> 156.10521 | G26: =SUM(D26:F26) -> 246.63529 | H26: =(G26/(100%-$B$12))/(100%-$B$10) -> 389.45079 | I26: 290 | J26: =IF(I26<H26,(H26-I26),0) -> 99.450788 | K26: =IF(I26>H26,(I26-H26),0) -> 0
... B50: =Clientes!B40 -> 168 | C50: =Clientes!C40 -> ZIO | D50: =Clientes!G40*$E$53 -> 70.025834 | E50: =Clientes!H40*$E$54 -> 78.149685 | F50: =Clientes!I40*$E$55 -> 93.663125 | G50: =SUM(D50:F50) -> 241.83864 | H50: =(G50/(100%-$B$12))/(100%-$B$10) -> 381.87662 | I50: 250 | J50: =IF(I50<H50,(H50-I50),0) -> 131.87662 | K50: =IF(I50>H50,(I50-H50),0) -> 0
B51: =Clientes!B41 -> TOTAL | D51: =SUM(D15:D50) -> 7649.1552 | E51: =SUM(E15:E50) -> 8377.6462 | F51: =SUM(F15:F50) -> 8741.8917 | G51: =SUM(G15:G50) -> 24768.693 | H51: =SUM(H15:H50) -> 39111.139 | I51: =SUM(I15:I50) -> 34470 | J51: =SUM(J15:J50) -> 7124.2655 | K51: =SUM(K15:K50) -> 2483.1267
C53: Custo Depº Fiscal | D53: ='Custos Gerais'!D38 -> 7649.1552 | E53: =D53/Clientes!G41 -> 2.3341945
C54: Custo Depº Contábil | D54: ='Custos Gerais'!E38 -> 8377.6462 | E54: =D54/Clientes!H41 -> 1.5629937
C55: Custo Depº Pessoal | D55: ='Custos Gerais'!F38 -> 8741.8917 | E55: =D55/Clientes!I41 -> 31.221042

Sheet Custos Individualizados
B2: PLANILHA PARA CÁLCULO DE HONORÁRIOS CONTÁBEIS
B4: PLANILHA DE CUSTOS DE HONORÁRIOS
B5: Empresa: | C5: JS
B6: Data: | C6: 42447 | I6: Instruções
B7: Honorário Atual: | C7: 1500
I8: Preencha as células de cor amarela.
B9: DESCRIÇÃO DOS CUSTOS
B10: Custos | C10: Quantid. | D10: Vr Unitar. | E10: Custo
B11: Notas Fiscais/mês | C11: 293 | D11: ='Custos x Honorários'!E53 -> 2.3341945 | E11: =C11*D11 -> 683.91897
B12: Lançamentos Contábeis/mês | C12: 350 | D12: ='Custos x Honorários'!E54 -> 1.5629937 | E12: =C12*D12 -> 547.04779
B13: Empregados | C13: 26 | D13: ='Custos x Honorários'!E55 -> 31.221042 | E13: =C13*D13 -> 811.74708
B14: Custo Total | E14: =SUM(E11:E13) -> 2042.7139
B16: RESULTADO
B17: Descrição | E17: Custo
B18: Receita Bruta | E18: =(E14/(100%-C23))/(100%-C19) -> 3225.5584
B19: Tributos Federais | C19: ='Custos x Honorários'!B10 -> 0.0953 | E19: =E18*C19 -> 307.39571
B20: Receita Líquida | E20: =E18-E19 -> 2918.1626
B21: Custo Total | E21: =E14 -> 2042.7139
B22: Lucro Líquido | E22: =E20-E21 -> 875.44879
B23: Margem de Lucro | C23: ='Custos x Honorários'!B12 -> 0.3

Sheet Dicas Equip NIBO
B2: ORIENTAÇÕES E DICAS DE CAPACITAÇÃO
B4: Olá amigo Contador algumas Orientações e Dicas de Capacitação:
B6: 1 – Procure mostrar sua forma de trabalho e autoridade no assunto em reunião e lembre de sempre colocar no contrato de prestação de serviço também.
B7: 2 – Acredite no seu potencial.
B8: 3 – Mostre que você veio pra acrescentar e ajudar o seu cliente a prosperar.
B9: 4 – Seja um Contador Consultor
B10: 5 – Invista em Automação de Processos, Marketing e na capacitação da Equipe.
B12: Aqui segue uma lista de Cursos que Recomendamos para evolução do escritório:
B14: Negociação De Honorários e Captação de Clientes com Anderson Hernandes >> | I14: http://bit.ly/negociandocomcliente
B15: Formação em SPED com Felipe Guerra >> | G15: http://bit.ly/treinamentosped
B16: Esocial De Uma Forma Simples e Descomplicado com Aline Portela >> | H16: http://bit.ly/esocialdescomplicado
B17: Marketing Digital Para Contadores >> | G17: http://bit.ly/marketingparacontador
B18: Tudo sobre ICMS da Teoria a Prática com Deise Parisotto >> | H18: http://bit.ly/praticanoicms
B19: Manual do Contador Iniciantes com Francisco >> | G19: http://bit.ly/cursoscontadoriniciante
