Workbook

Sheet Inicio
C1: Planilha - Planejamento Tributário
A2: Menu
A4: Início
A5: 1. Entrada de Dados
A6: 2. Aliquota de Imposto
A7: 3. Resultados
A8: 4. Tabelas SN
A10: Sobre a Capital Social

Sheet Entrada de Dados
C1: 1. Entrada de dados
A2: Menu
A4: Início | D4: NOME DA EMPRESA: | E4: Exemplo | G4: RECEITAS | J4: GASTOS
A5: 1. Entrada de Dados | D5: ÁREA DE ATUAÇÃO: | E5: SERVIÇOS | G5: Comércio | H5: 30000 | J5: Salários | K5: 0
A6: 2. Aliquota de Imposto | D6: ENQUADRAMENTO ATUAL: | E6: Simples Nacional | G6: Comércio - ST Substituido | H6: 30000 | J6: Compras Internas | K6: 0
A7: 3. Resultados | D7: DESONERADO: | E7: Não | G7: Indústria | H7: 30000 | J7: Compras Interestaduais | K7: 0
A8: 4. Tabelas SN | D8: ALIQUOTA DESONERAÇÂO | E8: 0.025 | G8: Serviços Tabela III | H8: 30000 | J8: Compras Importados | K8: 0
G9: Serviços Tabela IV | H9: 30000 | J9: Insumo para P.Serviços | K9: 0
A10: Sobre a Capital Social | D10: MARKUP MULTIPLICADOR | E10: 1 | G10: Serviços Tabela V | H10: 30000 | J10: Energia/Aluguel/Fretes | K10: 0
D11: REFERENCIA CUSTOS | E11: =H5/E10 -> 30000 | G11: Serviços Tabela VI | H11: 30000 | J11: Depreciação | K11: 0
G12: Total das Vendas | H12: =SUM(H5:H11) -> 210000 | J12: Demais Despesas | K12: =600*12 -> 7200
D13: RESUMO DE CARGA TRIBUTÁRIA | J13: Total de Despesas | K13: =SUM(K5:K12) -> 7200
D14: enquadramento | E14: valor dos impostos | F14: % s/ Fat.
D15: SIMPLES NACIONAL | E15: =Resultados!M21 -> 19512 | F15: =Resultados!L21 -> 0.092914286
D16: LUCRO PRESUMIDO | E16: =Resultados!G21 -> 37233 | F16: =Resultados!F21 -> 0.1773
D17: LUCRO REAL | E17: =Resultados!J21 -> 77703 | F17: =Resultados!I21 -> 0.37001429

Sheet Sheet1
A5: anual | B5: ='Aliquota de Impostos'!#REF! -> #REF! | C5: ='Aliquota de Impostos'!#REF! -> #REF! | D5: ='Aliquota de Impostos'!#REF! -> #REF! | E5: ='Aliquota de Impostos'!#REF! -> #REF! | F5: ='Aliquota de Impostos'!#REF! -> #REF! | G5: ='Aliquota de Impostos'!#REF! -> #REF! | H5: ='Aliquota de Impostos'!#REF! -> #REF! | I5: ='Aliquota de Impostos'!#REF! -> #REF! | ... L5: ='Aliquota de Impostos'!#REF! -> #REF! | N5: =L5/#REF! -> #REF!
A13: mensal | B13: ='Aliquota de Impostos'!#REF! -> #REF! | C13: ='Entrada de Dados'!#REF! -> #REF! | D13: ='Entrada de Dados'!#REF! -> #REF! | E13: ='Entrada de Dados'!#REF! -> #REF! | F13: ='Entrada de Dados'!#REF! -> #REF! | G13: ='Entrada de Dados'!#REF! -> #REF! | H13: ='Entrada de Dados'!#REF! -> #REF! | I13: ='Entrada de Dados'!#REF! -> #REF! | J13: ='Entrada de Dados'!#REF! -> #REF! | ... DS13: ='Entrada de Dados'!#REF! -> #REF!

Sheet Aliquota de Impostos
C1: 2. Aliquota de Impostos
A2: Menu
A4: Início | D4: TRIBUTOS EM GERAL | G4: TRIBUTOS LUCRO PRESUMIDO | J4: TRIBUTOS LUCRO REAL | M4: TRIBUTOS SIMPLES NACIONAL
A5: 1. Entrada de Dados | D5: IPI | E5: 0.05 | G5: PIS/PASEP | H5: 0.0065 | J5: PIS/PASEP | K5: 0.0165 | M5: TABELA I | N5: =VLOOKUP(SUM('Entrada de Dados'!H5:H11),'Tabela Simples Nacional'!D6:F25,3,1) -> 0.0547
A6: 2. Aliquota de Imposto | D6: ISS | E6: 0.05 | G6: COFINS | H6: 0.03 | J6: COFINS | K6: 0.076 | M6: TABELA II | N6: =VLOOKUP(SUM('Entrada de Dados'!H5:H11),'Tabela Simples Nacional'!D29:F48,3,1) -> 0.0597
A7: 3. Resultados | D7: ICMS | E7: 0.18 | G7: IRPJ | H7: 0.15 | J7: IRPJ | K7: 0.15 | M7: TABELA III | N7: =VLOOKUP(SUM('Entrada de Dados'!H5:H11),'Tabela Simples Nacional'!D52:F71,3,1) -> 0.0821
A8: 4. Tabelas SN | D8: RAT | E8: 0.01 | G8: ADICIONAL IRPJ | H8: 0.1 | J8: ADICIONAL IRPJ | K8: 0.1 | M8: TABELA IV | N8: =VLOOKUP(SUM('Entrada de Dados'!H5:H11),'Tabela Simples Nacional'!D75:F94,3,1) -> 0.0654
D9: CPRB | E9: =IF('Entrada de Dados'!E7="Sim",'Entrada de Dados'!E8,0) -> 0 | G9: CSLL | H9: 0.09 | J9: CSLL | K9: 0.09 | M9: TABELA V | N9: {=INDEX('Tabela Simples Nacional'!F142:F301,MATCH(Auxiliar!C16&Auxiliar!C17,'Tabela Simples Nacional'!D142:D301&'Tabela Simples Nacional'!E142:E301,0))} -> 0.1752
A10: Sobre a Capital Social | D10: INSS | E10: 0.2 | M10: TABELA VI | N10: =VLOOKUP(SUM('Entrada de Dados'!H5:H11),'Tabela Simples Nacional'!D121:F140,3,1) -> 0.1772
D11: INSS TERCEIROS | E11: 0.058 | M11: TABELA I s/ICMS | N11: =VLOOKUP(SUM('Entrada de Dados'!H5:H11),'Tabela Simples Nacional'!D6:F25,3,1)-VLOOKUP(SUM('Entrada de Dados'!H5:H11),'Tabela Simples Nacional'!D6:L25,9,1) -> 0.0361
D12: ICMS INTERNO | E12: 0.18
D13: ICMS INTEREST. | E13: 0.12
D14: ICMS IMPORT. | E14: 0.04
D15: IPI ENTRADA | E15: 0.05
D16: FGTS | E16: 0.08

Sheet Resultados
C1: 3. Resultado dos Impostos
A2: Menu
A4: Início | D4: TRIBUTOS | F4: LUCRO PRESUMIDO | I4: LUCRO REAL | L4: SIMPLES NACIONAL
A5: 1. Entrada de Dados | F5: % tributos s/ Fat. | G5: Valor | I5: % tributos s/ Fat. | J5: Valor | L5: % tributos s/ Fat. | M5: Valor
A6: 2. Aliquota de Imposto | D6: PIS/PASEP | F6: ='Aliquota de Impostos'!H5 -> 0.0065 | G6: ='Entrada de Dados'!H12*Resultados!F6 -> 1365 | I6: =J6/'Entrada de Dados'!$H$12 -> 0.0165 | J6: =(('Entrada de Dados'!H12)*'Aliquota de Impostos'!K5)-(SUM('Entrada de Dados'!K6:K11)*'Aliquota de Impostos'!K5) -> 3465 | L6: =M6/'Entrada de Dados'!$H$12 -> 0 | M6: 0
A7: 3. Resultado dos Impostos | D7: COFINS | F7: ='Aliquota de Impostos'!H6 -> 0.03 | G7: ='Entrada de Dados'!H12*Resultados!F7 -> 6300 | I7: =J7/'Entrada de Dados'!$H$12 -> 0.076 | J7: =(('Entrada de Dados'!H12)*'Aliquota de Impostos'!K6)-(SUM('Entrada de Dados'!K6:K11)*'Aliquota de Impostos'!K6) -> 15960 | L7: =M7/'Entrada de Dados'!$H$12 -> 0 | M7: 0
A8: 4. Tabelas SN | D8: IRPJ | F8: =G8/'Entrada de Dados'!$H$12 -> 0.032571429 | G8: =(((SUM('Entrada de Dados'!H5:H7)*8%)+(SUM('Entrada de Dados'!H8:H11)*32%))*'Aliquota de Impostos'!H7) -> 6840 | I8: =J8/'Entrada de Dados'!$H$12 -> 0.11898214 | J8: =('Entrada de Dados'!H12-'Entrada de Dados'!K13-J6-J7-J12-J13-J16-J17-J18-J20)*'Aliquota de Impostos'!K7 -> 24986.25 | L8: =M8/'Entrada de Dados'!$H$12 -> 0 | M8: 0
D9: ADICIONAL IRPJ | F9: =G9/'Entrada de Dados'!$H$12 -> 0 | G9: =IF(((SUM('Entrada de Dados'!H5:H7)*8%)+(SUM('Entrada de Dados'!H8:H11)*32%))>240000,(((SUM('Entrada de Dados'!H5:H7)*8%)+(SUM('Entrada de Dados'!H8:H11)*32%))-240000)*'Aliquota de Impostos'!H8,0) -> 0 | I9: =J9/'Entrada de Dados'!$H$12 -> 0 | J9: =IF(('Entrada de Dados'!H12-'Entrada de Dados'!K13-J6-J7-J12-J13-J16-J17-J18-J20)>240000,(('Entrada de Dados'!H12-'Entrada de Dados'!K13-J6-J7-J12-J13-J16-J17-J18-J20)-240000)*'Aliquota de Impostos'!K8,0) -> 0 | L9: =M9/'Entrada de Dados'!$H$12 -> 0 | M9: 0
A10: Sobre a Capital Social | D10: CSLL | F10: =G10/'Entrada de Dados'!$H$12 -> 0.021085714 | G10: =(((SUM('Entrada de Dados'!H5:H7)*12%)+(SUM('Entrada de Dados'!H8:H11)*32%))*'Aliquota de Impostos'!H9) -> 4428 | I10: =J10/'Entrada de Dados'!$H$12 -> 0.071389286 | J10: =('Entrada de Dados'!H12-'Entrada de Dados'!K13-J6-J7-J12-J13-J16-J17-J18-J20)*'Aliquota de Impostos'!K9 -> 14991.75 | L10: =M10/'Entrada de Dados'!$H$12 -> 0 | M10: 0
D11: IPI | F11: =G11/'Entrada de Dados'!$H$12 -> 0.0071428571 | G11: =IF('Entrada de Dados'!H7>0,'Entrada de Dados'!H7*'Aliquota de Impostos'!E5-SUM('Entrada de Dados'!K5)*'Aliquota de Impostos'!E15,0) -> 1500 | I11: =J11/'Entrada de Dados'!$H$12 -> 0.0071428571 | J11: =IF('Entrada de Dados'!H7>0,'Entrada de Dados'!H7*'Aliquota de Impostos'!E5-SUM('Entrada de Dados'!K5)*'Aliquota de Impostos'!E15,0) -> 1500 | L11: =M11/'Entrada de Dados'!$H$12 -> 0 | M11: 0
D12: ISS | F12: =G12/'Entrada de Dados'!$H$12 -> 0.028571429 | G12: =SUM('Entrada de Dados'!H8:H11)*'Aliquota de Impostos'!E6 -> 6000 | I12: =J12/'Entrada de Dados'!$H$12 -> 0.028571429 | J12: =SUM('Entrada de Dados'!H8:H11)*'Aliquota de Impostos'!E6 -> 6000 | L12: =M12/'Entrada de Dados'!$H$12 -> 0 | M12: 0
D13: ICMS | F13: =G13/'Entrada de Dados'!$H$12 -> 0.051428571 | G13: =(SUM(('Entrada de Dados'!H5+'Entrada de Dados'!H7)*'Aliquota de Impostos'!E12)-('Entrada de Dados'!K6*'Aliquota de Impostos'!E12)-('Entrada de Dados'!K7*'Aliquota de Impostos'!E13)-('Entrada de Dados'!K8*'Aliquota de Impostos'!E14)) -> 10800 | I13: =J13/'Entrada de Dados'!$H$12 -> 0.051428571 | J13: =(SUM(('Entrada de Dados'!H5+'Entrada de Dados'!H7)*'Aliquota de Impostos'!E12)-('Entrada de Dados'!K6*'Aliquota de Impostos'!E12)-('Entrada de Dados'!K7*'Aliquota de Impostos'!E13)-('Entrada de Dados'!K8*'Aliquota de Impostos'!E14)) -> 10800 | L13: =M13/'Entrada de Dados'!$H$12 -> 0 | M13: 0
D14: Dif Aliquota - ICMS | F14: 0 | G14: 0 | I14: =J14/'Entrada de Dados'!$H$12 -> 0 | J14: 0 | L14: =M14/'Entrada de Dados'!$H$12 -> 0 | M14: =('Entrada de Dados'!K7*('Aliquota de Impostos'!E12-'Aliquota de Impostos'!E13))+('Entrada de Dados'!K8*('Aliquota de Impostos'!E12-'Aliquota de Impostos'!E14)) -> 0
D15: SIMPLES NACIONAL | F15: 0 | G15: 0 | I15: =J15/'Entrada de Dados'!$H$12 -> 0 | J15: 0 | L15: =M15/'Entrada de Dados'!$H$12 -> 0.092914286 | M15: =('Entrada de Dados'!H5*'Aliquota de Impostos'!N5)+('Entrada de Dados'!H6*'Aliquota de Impostos'!N11)+('Entrada de Dados'!H7*'Aliquota de Impostos'!N6)+('Entrada de Dados'!H8*'Aliquota de Impostos'!N7)+('Entrada de Dados'!H9*'Aliquota de Impostos'!N8)+('Entrada de Dados'!H10*'Aliquota de Impostos'!N9)+('Entrada de Dados'!H11*'Aliquota de Impostos'!N10) -> 19512
D16: INSS | F16: =G16/'Entrada de Dados'!$H$12 -> 0 | G16: =IF(F19>0,0,'Entrada de Dados'!K5*'Aliquota de Impostos'!E10) -> 0 | I16: =J16/'Entrada de Dados'!$H$12 -> 0 | J16: =IF(F19>0,0,'Entrada de Dados'!K5*'Aliquota de Impostos'!E10) -> 0 | L16: =M16/'Entrada de Dados'!$H$12 -> 0 | M16: =IF('Entrada de Dados'!H9=0,0,IF(F19>0,0,'Entrada de Dados'!K5*'Aliquota de Impostos'!E10)) -> 0
D17: INSS TERCEIROS | F17: =G17/'Entrada de Dados'!$H$12 -> 0 | G17: ='Entrada de Dados'!K5*'Aliquota de Impostos'!E11 -> 0 | I17: =J17/'Entrada de Dados'!$H$12 -> 0 | J17: ='Entrada de Dados'!K5*'Aliquota de Impostos'!E11 -> 0 | L17: =M17/'Entrada de Dados'!$H$12 -> 0 | M17: 0
D18: RAT | F18: =G18/'Entrada de Dados'!$H$12 -> 0 | G18: ='Entrada de Dados'!K5*'Aliquota de Impostos'!E8 -> 0 | I18: =J18/'Entrada de Dados'!$H$12 -> 0 | J18: ='Entrada de Dados'!K5*'Aliquota de Impostos'!E8 -> 0 | L18: =M18/'Entrada de Dados'!$H$12 -> 0 | M18: =IF('Entrada de Dados'!H9=0,0,IF(F19>0,0,'Entrada de Dados'!K5*'Aliquota de Impostos'!E8)) -> 0
D19: CPP | F19: ='Aliquota de Impostos'!E9 -> 0 | G19: ='Entrada de Dados'!H12*Resultados!F19 -> 0 | I19: ='Aliquota de Impostos'!E9 -> 0 | J19: ='Entrada de Dados'!K5*Resultados!F19 -> 0 | L19: =M19/'Entrada de Dados'!$H$12 -> 0 | M19: =IF('Aliquota de Impostos'!E9>0,'Entrada de Dados'!H9*'Aliquota de Impostos'!E9,0) -> 0
D20: FGTS | F20: =G20/'Entrada de Dados'!$H$12 -> 0 | G20: ='Entrada de Dados'!K5*'Aliquota de Impostos'!E16 -> 0 | I20: =J20/'Entrada de Dados'!$H$12 -> 0 | J20: ='Entrada de Dados'!K5*'Aliquota de Impostos'!E16 -> 0 | L20: =M20/'Entrada de Dados'!$H$12 -> 0 | M20: ='Entrada de Dados'!K5*'Aliquota de Impostos'!E16 -> 0
F21: =SUM(F6:F20) -> 0.1773 | G21: =SUM(G6:G20) -> 37233 | I21: =SUM(I6:I20) -> 0.37001429 | J21: =SUM(J6:J20) -> 77703 | L21: =SUM(L6:L20) -> 0.092914286 | M21: =SUM(M6:M20) -> 19512

Sheet Tabela Simples Nacional
C1: 4. TABELAS DO SIMPLES NACIONAL
A2: Menu
A4: Início | D4: TABELA 1
A5: 1. Entrada de Dados | D5: Receita Bruta em 12 meses (em R$) | F5: Alíquota | G5: IRPJ | H5: CSLL | I5: Cofins | J5: PIS/Pasep | K5: CPP | L5: ICMS
A6: 2. Aliquota de Imposto | D6: 0 | E6: 180000 | F6: 0.04 | G6: 0 | H6: 0 | I6: 0 | J6: 0 | K6: 0.0275 | L6: 0.0125
A7: 3. Resultados | D7: 180000.01 | E7: 360000 | F7: 0.0547 | G7: 0 | H7: 0 | I7: 0.0086 | J7: 0 | K7: 0.0275 | L7: 0.0186
A8: 4. Tabelas SN | D8: 360000.01 | E8: 540000 | F8: 0.0684 | G8: 0.0027 | H8: 0.0031 | I8: 0.0095 | J8: 0.0023 | K8: 0.0275 | L8: 0.0233
D9: 540000.01 | E9: 720000 | F9: 0.0754 | G9: 0.0035 | H9: 0.0035 | I9: 0.0104 | J9: 0.0025 | K9: 0.0299 | L9: 0.0256
A10: Sobre a Capital Social | D10: 720000.01 | E10: 900000 | F10: 0.076 | G10: 0.0035 | H10: 0.0035 | I10: 0.0105 | J10: 0.0025 | K10: 0.0302 | L10: 0.0258
D11: 900000.01 | E11: 1080000 | F11: 0.0828 | G11: 0.0038 | H11: 0.0038 | I11: 0.0115 | J11: 0.0027 | K11: 0.0328 | L11: 0.0282
D12: 1080000 | E12: 1260000 | F12: 0.0836 | G12: 0.0039 | H12: 0.0039 | I12: 0.0116 | J12: 0.0028 | K12: 0.033 | L12: 0.0284
D13: 1260000 | E13: 1440000 | F13: 0.0845 | G13: 0.0039 | H13: 0.0039 | I13: 0.0117 | J13: 0.0028 | K13: 0.0335 | L13: 0.0287
D14: 1440000 | E14: 1620000 | F14: 0.0903 | G14: 0.0042 | H14: 0.0042 | I14: 0.0125 | J14: 0.003 | K14: 0.0357 | L14: 0.0307
D15: 1620000 | E15: 1800000 | F15: 0.0912 | G15: 0.0043 | H15: 0.0043 | I15: 0.0126 | J15: 0.003 | K15: 0.036 | L15: 0.031
D16: 1800000 | E16: 1980000 | F16: 0.0995 | G16: 0.0046 | H16: 0.0046 | I16: 0.0138 | J16: 0.0033 | K16: 0.0394 | L16: 0.0338
D17: 1980000 | E17: 2160000 | F17: 0.1004 | G17: 0.0046 | H17: 0.0046 | I17: 0.0139 | J17: 0.0033 | K17: 0.0399 | L17: 0.0341
D18: 2160000 | E18: 2340000 | F18: 0.1013 | G18: 0.0047 | H18: 0.0047 | I18: 0.014 | J18: 0.0033 | K18: 0.0401 | L18: 0.0345
D19: 2340000 | E19: 2520000 | F19: 0.1023 | G19: 0.0047 | H19: 0.0047 | I19: 0.0142 | J19: 0.0034 | K19: 0.0405 | L19: 0.0348
D20: 2520000 | E20: 2700000 | F20: 0.1032 | G20: 0.0048 | H20: 0.0048 | I20: 0.0143 | J20: 0.0034 | K20: 0.0408 | L20: 0.0351
D21: 2700000 | E21: 2880000 | F21: 0.1123 | G21: 0.0052 | H21: 0.0052 | I21: 0.0156 | J21: 0.0037 | K21: 0.0444 | L21: 0.0382
D22: 2880000 | E22: 3060000 | F22: 0.1132 | G22: 0.0052 | H22: 0.0052 | I22: 0.0157 | J22: 0.0037 | K22: 0.0449 | L22: 0.0385
... D25: 3420000 | E25: 3600000 | F25: 0.1161 | G25: 0.0054 | H25: 0.0054 | I25: 0.016 | J25: 0.0038 | K25: 0.046 | L25: 0.0395
D27: TABELA 2
D28: Receita Bruta em 12 meses (em R$) | F28: Alíquota | G28: IRPJ | H28: CSLL | I28: Cofins | J28: PIS/Pasep | K28: CPP | L28: ICMS | M28: IPI
D29: 0 | E29: 180000 | F29: 0.045 | G29: 0 | H29: 0 | I29: 0 | J29: 0 | K29: 0.0275 | L29: 0.0125 | M29: 0.005
D30: 180000.01 | E30: 360000 | F30: 0.0597 | G30: 0 | H30: 0 | I30: 0.0086 | J30: 0 | K30: 0.0275 | L30: 0.0186 | M30: 0.005
D31: 360000.01 | E31: 540000 | F31: 0.0734 | G31: 0.0027 | H31: 0.0031 | I31: 0.0095 | J31: 0.0023 | K31: 0.0275 | L31: 0.0233 | M31: 0.005
D32: 540000.01 | E32: 720000 | F32: 0.0804 | G32: 0.0035 | H32: 0.0035 | I32: 0.0104 | J32: 0.0025 | K32: 0.0299 | L32: 0.0256 | M32: 0.005
D33: 720000.01 | E33: 900000 | F33: 0.081 | G33: 0.0035 | H33: 0.0035 | I33: 0.0105 | J33: 0.0025 | K33: 0.0302 | L33: 0.0258 | M33: 0.005
D34: 900000.01 | E34: 1080000 | F34: 0.0878 | G34: 0.0038 | H34: 0.0038 | I34: 0.0115 | J34: 0.0027 | K34: 0.0328 | L34: 0.0282 | M34: 0.005
D35: 1080000 | E35: 1260000 | F35: 0.0886 | G35: 0.0039 | H35: 0.0039 | I35: 0.0116 | J35: 0.0028 | K35: 0.033 | L35: 0.0284 | M35: 0.005
D36: 1260000 | E36: 1440000 | F36: 0.0895 | G36: 0.0039 | H36: 0.0039 | I36: 0.0117 | J36: 0.0028 | K36: 0.0335 | L36: 0.0287 | M36: 0.005
D37: 1440000 | E37: 1620000 | F37: 0.0953 | G37: 0.0042 | H37: 0.0042 | I37: 0.0125 | J37: 0.003 | K37: 0.0357 | L37: 0.0307 | M37: 0.005
D38: 1620000 | E38: 1800000 | F38: 0.0962 | G38: 0.0042 | H38: 0.0042 | I38: 0.0126 | J38: 0.003 | K38: 0.0362 | L38: 0.031 | M38: 0.005
D39: 1800000 | E39: 1980000 | F39: 0.1045 | G39: 0.0046 | H39: 0.0046 | I39: 0.0138 | J39: 0.0033 | K39: 0.0394 | L39: 0.0338 | M39: 0.005
D40: 1980000 | E40: 2160000 | F40: 0.1054 | G40: 0.0046 | H40: 0.0046 | I40: 0.0139 | J40: 0.0033 | K40: 0.0399 | L40: 0.0341 | M40: 0.005
... D48: 3420000 | E48: 3600000 | F48: 0.1211 | G48: 0.0054 | H48: 0.0054 | I48: 0.016 | J48: 0.0038 | K48: 0.046 | L48: 0.0395 | M48: 0.005
D50: TABELA 3
D51: Receita Bruta em 12 meses (em R$) | F51: Alíquota | G51: IRPJ | H51: CSLL | I51: Cofins | J51: PIS/Pasep | K51: CPP | L51: ISS
D52: 0 | E52: 180000 | F52: 0.06 | G52: 0 | H52: 0 | I52: 0 | J52: 0 | K52: 0.04 | L52: 0.02
D53: 180000.01 | E53: 360000 | F53: 0.0821 | G53: 0 | H53: 0 | I53: 0.0142 | J53: 0 | K53: 0.04 | L53: 0.0279
D54: 360000.01 | E54: 540000 | F54: 0.1026 | G54: 0.0048 | H54: 0.0043 | I54: 0.0143 | J54: 0.0035 | K54: 0.0407 | L54: 0.035
D55: 540000.01 | E55: 720000 | F55: 0.1131 | G55: 0.0053 | H55: 0.0053 | I55: 0.0156 | J55: 0.0038 | K55: 0.0447 | L55: 0.0384
D56: 720000.01 | E56: 900000 | F56: 0.114 | G56: 0.0053 | H56: 0.0052 | I56: 0.0158 | J56: 0.0038 | K56: 0.0452 | L56: 0.0387
D57: 900000.01 | E57: 1080000 | F57: 0.1242 | G57: 0.0057 | H57: 0.0057 | I57: 0.0173 | J57: 0.004 | K57: 0.0492 | L57: 0.0423
D58: 1080000 | E58: 1260000 | F58: 0.1254 | G58: 0.0059 | H58: 0.0056 | I58: 0.0174 | J58: 0.0042 | K58: 0.0497 | L58: 0.0426
D59: 1260000 | E59: 1440000 | F59: 0.1268 | G59: 0.0059 | H59: 0.0057 | I59: 0.0176 | J59: 0.0042 | K59: 0.0503 | L59: 0.0431
D60: 1440000 | E60: 1620000 | F60: 0.1355 | G60: 0.0063 | H60: 0.0061 | I60: 0.0188 | J60: 0.0045 | K60: 0.0537 | L60: 0.0461
D61: 1620000 | E61: 1800000 | F61: 0.1368 | G61: 0.0063 | H61: 0.0064 | I61: 0.0189 | J61: 0.0045 | K61: 0.0542 | L61: 0.0465
D62: 1800000 | E62: 1980000 | F62: 0.1493 | G62: 0.0069 | H62: 0.0069 | I62: 0.0207 | J62: 0.005 | K62: 0.0598 | L62: 0.05
D63: 1980000 | E63: 2160000 | F63: 0.1506 | G63: 0.0069 | H63: 0.0069 | I63: 0.0209 | J63: 0.005 | K63: 0.0609 | L63: 0.05
... D71: 3420000 | E71: 3600000 | F71: 0.1742 | G71: 0.0081 | H71: 0.0079 | I71: 0.0242 | J71: 0.0057 | K71: 0.0783 | L71: 0.05
D73: TABELA 4
D74: Receita Bruta em 12 meses (em R$) | F74: Alíquota | G74: IRPJ | H74: CSLL | I74: Cofins | J74: PIS/Pasep | K74: ISS
D75: 0 | E75: 180000 | F75: 0.045 | G75: 0 | H75: 0.0122 | I75: 0.0128 | J75: 0 | K75: 0.02
D76: 180000.01 | E76: 360000 | F76: 0.0654 | G76: 0 | H76: 0.0184 | I76: 0.0191 | J76: 0 | K76: 0.0279
D77: 360000.01 | E77: 540000 | F77: 0.077 | G77: 0.0016 | H77: 0.0185 | I77: 0.0195 | J77: 0.0024 | K77: 0.035
D78: 540000.01 | E78: 720000 | F78: 0.0849 | G78: 0.0052 | H78: 0.0187 | I78: 0.0199 | J78: 0.0027 | K78: 0.0384
D79: 720000.01 | E79: 900000 | F79: 0.0897 | G79: 0.0089 | H79: 0.0189 | I79: 0.0203 | J79: 0.0029 | K79: 0.0387
D80: 900000.01 | E80: 1080000 | F80: 0.0978 | G80: 0.0125 | H80: 0.0191 | I80: 0.0207 | J80: 0.0032 | K80: 0.0423
D81: 1080000 | E81: 1260000 | F81: 0.1026 | G81: 0.0162 | H81: 0.0193 | I81: 0.0211 | J81: 0.0034 | K81: 0.0426
D82: 1260000 | E82: 1440000 | F82: 0.1076 | G82: 0.02 | H82: 0.0195 | I82: 0.0215 | J82: 0.0035 | K82: 0.0431
D83: 1440000 | E83: 1620000 | F83: 0.1151 | G83: 0.0237 | H83: 0.0197 | I83: 0.0219 | J83: 0.0037 | K83: 0.0461
D84: 1620000 | E84: 1800000 | F84: 0.12 | G84: 0.0274 | H84: 0.02 | I84: 0.0223 | J84: 0.0038 | K84: 0.0465
D85: 1800000 | E85: 1980000 | F85: 0.128 | G85: 0.0312 | H85: 0.0201 | I85: 0.0227 | J85: 0.004 | K85: 0.05
D86: 1980000 | E86: 2160000 | F86: 0.1325 | G86: 0.0349 | H86: 0.0203 | I86: 0.0231 | J86: 0.0042 | K86: 0.05
... D94: 3420000 | E94: 3600000 | F94: 0.1685 | G94: 0.0612 | H94: 0.0253 | I94: 0.0263 | J94: 0.0057 | K94: 0.05
D96: tabela 5
D97: Receita Bruta em 12 meses (em R$) | F97: (r)<0,10 | G97: 0,10=< (r) e (r) < 0,15 | H97: 0,15=< (r) e (r) < 0,20 | I97: 0,20=< (r) e (r) < 0,25 | J97: 0,25=< (r) e (r) < 0,30 | K97: 0,30=< (r) e (r) < 0,35 | L97: 0,35=< (r) e (r) < 0,40 | M97: (r)>= 0,40
D98: 0 | E98: 180000 | F98: 0.175 | G98: 0.157 | H98: 0.137 | I98: 0.1182 | J98: 0.1047 | K98: 0.0997 | L98: 0.088 | M98: 0.08
D99: 180000.01 | E99: 360000 | F99: 0.1752 | G99: 0.1575 | H99: 0.139 | I99: 0.126 | J99: 0.1233 | K99: 0.1072 | L99: 0.091 | M99: 0.0848
D100: 360000.01 | E100: 540000 | F100: 0.1755 | G100: 0.1595 | H100: 0.142 | I100: 0.129 | J100: 0.1264 | K100: 0.1111 | L100: 0.0958 | M100: 0.0903
D101: 540000.01 | E101: 720000 | F101: 0.1795 | G101: 0.167 | H101: 0.15 | I101: 0.137 | J101: 0.1345 | K101: 0.12 | L101: 0.1056 | M101: 0.0934
D102: 720000.01 | E102: 900000 | F102: 0.1815 | G102: 0.1695 | H102: 0.153 | I102: 0.1403 | J102: 0.1353 | K102: 0.124 | L102: 0.1104 | M102: 0.1006
D103: 900000.01 | E103: 1080000 | F103: 0.1845 | G103: 0.172 | H103: 0.154 | I103: 0.141 | J103: 0.136 | K103: 0.126 | L103: 0.116 | M103: 0.106
D104: 1080000 | E104: 1260000 | F104: 0.1855 | G104: 0.173 | H104: 0.155 | I104: 0.1411 | J104: 0.1368 | K104: 0.1268 | L104: 0.1168 | M104: 0.1068
D105: 1260000 | E105: 1440000 | F105: 0.1862 | G105: 0.1732 | H105: 0.156 | I105: 0.1412 | J105: 0.1369 | K105: 0.1269 | L105: 0.1169 | M105: 0.1069
D106: 1440000 | E106: 1620000 | F106: 0.1872 | G106: 0.1742 | H106: 0.157 | I106: 0.1413 | J106: 0.1408 | K106: 0.1308 | L106: 0.1208 | M106: 0.1108
D107: 1620000 | E107: 1800000 | F107: 0.1886 | G107: 0.1756 | H107: 0.158 | I107: 0.1414 | J107: 0.1409 | K107: 0.1309 | L107: 0.1209 | M107: 0.1109
D108: 1800000 | E108: 1980000 | F108: 0.1896 | G108: 0.1766 | H108: 0.159 | I108: 0.1449 | J108: 0.1445 | K108: 0.1361 | L108: 0.1278 | M108: 0.1187
D109: 1980000 | E109: 2160000 | F109: 0.1906 | G109: 0.1776 | H109: 0.16 | I109: 0.1467 | J109: 0.1464 | K109: 0.1389 | L109: 0.1315 | M109: 0.1228
... D117: 3420000 | E117: 3600000 | F117: 0.229 | G117: 0.218 | H117: 0.2 | I117: 0.186 | J117: 0.184 | K117: 0.1785 | L117: 0.176 | M117: 0.1718
D119: Tabela 6
D120: Receita Bruta em 12 meses (em R$) | F120: Alíquota | G120: IRPJ, PIS/Pasep, CSLL, Cofins e CPP | H120: ISS
D121: 0 | E121: 180000 | F121: 0.1693 | G121: 0.1493 | H121: 0.02
D122: 180000.01 | E122: 360000 | F122: 0.1772 | G122: 0.1493 | H122: 0.0279
D123: 360000.01 | E123: 540000 | F123: 0.1843 | G123: 0.1493 | H123: 0.035
D124: 540000.01 | E124: 720000 | F124: 0.1877 | G124: 0.1493 | H124: 0.0384
D125: 720000.01 | E125: 900000 | F125: 0.1904 | G125: 0.1517 | H125: 0.0387
D126: 900000.01 | E126: 1080000 | F126: 0.1994 | G126: 0.1571 | H126: 0.0423
D127: 1080000 | E127: 1260000 | F127: 0.2034 | G127: 0.1608 | H127: 0.0426
D128: 1260000 | E128: 1440000 | F128: 0.2066 | G128: 0.1635 | H128: 0.0431
D129: 1440000 | E129: 1620000 | F129: 0.2117 | G129: 0.1656 | H129: 0.0461
D130: 1620000 | E130: 1800000 | F130: 0.2138 | G130: 0.1673 | H130: 0.0465
D131: 1800000 | E131: 1980000 | F131: 0.2186 | G131: 0.1686 | H131: 0.05
D132: 1980000 | E132: 2160000 | F132: 0.2197 | G132: 0.1697 | H132: 0.05
... D140: 3420000 | E140: 3600000 | F140: 0.2245 | G140: 0.1745 | H140: 0.05
D142: 0 | E142: (r)<0,10 | F142: 0.175
D143: 180000,01 | E143: (r)<0,10 | F143: 0.1752
D144: 360000,01 | E144: (r)<0,10 | F144: 0.1755
...

Sheet Auxiliar
A3: Sim
A4: Não
A6: MEI
A7: Simples Nacional
A8: Lucro Presumido
A9: Lucro Real
B13: Faturamento | C13: ='Entrada de Dados'!H12 -> 210000
B14: Folha Total | C14: =SUM(Resultados!G16:G20) -> 0
B15: Relação r | C15: =C14/C13 -> 0
B16: Corresp FAT | C16: =VLOOKUP(C13,B20:D39,3,1) -> 180000,01
B17: Corresp R | C17: =VLOOKUP(C15,F20:H27,3,1) -> (r)<0,10
B20: 0 | C20: 180000 | D20: 0 | F20: 0 | G20: 0.09 | H20: (r)<0,10
B21: 180000.01 | C21: 360000 | D21: 180000,01 | F21: 0.1 | G21: 0.14 | H21: 0,10=< (r) e (r) < 0,15
B22: 360000.01 | C22: 540000 | D22: 360000,01 | F22: 0.15 | G22: 0.19 | H22: 0,15=< (r) e (r) < 0,20
B23: 540000.01 | C23: 720000 | D23: 540000,01 | F23: 0.2 | G23: 0.24 | H23: 0,20=< (r) e (r) < 0,25
B24: 720000.01 | C24: 900000 | D24: 720000,01 | F24: 0.25 | G24: 0.29 | H24: 0,25=< (r) e (r) < 0,30
B25: 900000.01 | C25: 1080000 | D25: 900000,01 | F25: 0.3 | G25: 0.34 | H25: 0,30=< (r) e (r) < 0,35
B26: 1080000 | C26: 1260000 | D26: 1080000,01 | F26: 0.35 | G26: 0.39 | H26: 0,35=< (r) e (r) < 0,40
B27: 1260000 | C27: 1440000 | D27: 1260000,01 | F27: 0.4 | H27: (r)>= 0,40
B28: 1440000 | C28: 1620000 | D28: 1440000,01
B29: 1620000 | C29: 1800000 | D29: 1620000,01
B30: 1800000 | C30: 1980000 | D30: 1800000,01
B31: 1980000 | C31: 2160000 | D31: 1980000,01
B32: 2160000 | C32: 2340000 | D32: 2160000,01
B33: 2340000 | C33: 2520000 | D33: 2340000,01
B34: 2520000 | C34: 2700000 | D34: 2520000,01
B35: 2700000 | C35: 2880000 | D35: 2700000,01
B36: 2880000 | C36: 3060000 | D36: 2880000,01
B37: 3060000 | C37: 3240000 | D37: 3060000,01
B38: 3240000 | C38: 3420000 | D38: 3240000,01
B39: 3420000 | C39: 3600000 | D39: 3420000,01
