Workbook

Sheet FC-FAMILIAR
A1: Preencha esta tabela mensalmente com sua renda (quanto sua família ganha) e despesas (quanto vai sair) e saiba se você está organizando bem seu orçamento. Se tiver dúvidas, siga nosso passo a passo na segunda edição do nosso informativo. Disponível em http://www.poa.ifsuldeminas.edu.br/index.php?option=com_content&view=article&id=169&Itemid=132
C4: jan | D4: fev | E4: mar | F4: abr | G4: mai | H4: jun | I4: jul | J4: ago | K4: set | L4: out | M4: nov | N4: dez
B5: Saldo Anterior | D5: =C6 -> 0 | E5: =D6 -> 0 | F5: =E6 -> 0 | G5: =F6 -> 0 | H5: =G6 -> 0 | I5: =H6 -> 0 | J5: =I6 -> 0 | K5: =J6 -> 0 | ... N5: =M6 -> 0
A6: 1- Total do saldo | C6: =SUM(C5:C5) -> 0 | D6: =SUM(D5:D5) -> 0 | E6: =SUM(E5:E5) -> 0 | F6: =SUM(F5:F5) -> 0 | G6: =SUM(G5:G5) -> 0 | H6: =SUM(H5:H5) -> 0 | I6: =SUM(I5:I5) -> 0 | J6: =SUM(J5:J5) -> 0 | ... N6: =SUM(N5:N5) -> 0
A8: Rendas/Quanto vai entrar
C9: jan | D9: fev | E9: mar | F9: abr | G9: mai | H9: jun | I9: jul | J9: ago | K9: set | L9: out | M9: nov | N9: dez
B10: Salário da família 1
B11: Salário da família 2
B12: Aposentadoria
B13: Renda extra
B14: Entrada Banco | C14: ='Banco Conta Corrente'!C20+'Banco Conta Corrente'!C21+'Banco Conta Corrente'!C22 -> 0 | D14: ='Banco Conta Corrente'!D20+'Banco Conta Corrente'!D21+'Banco Conta Corrente'!D22 -> 0 | E14: ='Banco Conta Corrente'!E20+'Banco Conta Corrente'!E21+'Banco Conta Corrente'!E22 -> 0 | F14: ='Banco Conta Corrente'!F20+'Banco Conta Corrente'!F21+'Banco Conta Corrente'!F22 -> 0 | G14: ='Banco Conta Corrente'!G20+'Banco Conta Corrente'!G21+'Banco Conta Corrente'!G22 -> 0 | H14: ='Banco Conta Corrente'!H20+'Banco Conta Corrente'!H21+'Banco Conta Corrente'!H22 -> 0 | I14: ='Banco Conta Corrente'!I20+'Banco Conta Corrente'!I21+'Banco Conta Corrente'!I22 -> 0 | J14: ='Banco Conta Corrente'!J20+'Banco Conta Corrente'!J21+'Banco Conta Corrente'!J22 -> 0 | ... N14: ='Banco Conta Corrente'!N20+'Banco Conta Corrente'!N21+'Banco Conta Corrente'!N22 -> 0
B15: Entrada Poupança | C15: ='Poupança-Investimento'!C20 -> 0 | D15: ='Poupança-Investimento'!D20 -> 0 | E15: ='Poupança-Investimento'!E20 -> 0 | F15: ='Poupança-Investimento'!F20 -> 0 | G15: ='Poupança-Investimento'!G20 -> 0 | H15: ='Poupança-Investimento'!H20 -> 0 | I15: ='Poupança-Investimento'!I20 -> 0 | J15: ='Poupança-Investimento'!J20 -> 0 | ... N15: ='Poupança-Investimento'!N20 -> 0
A16: 2- Total de renda da família | C16: =SUM(C10:C15) -> 0 | D16: =SUM(D10:D15) -> 0 | E16: =SUM(E10:E15) -> 0 | F16: =SUM(F10:F15) -> 0 | G16: =SUM(G10:G15) -> 0 | H16: =SUM(H10:H15) -> 0 | I16: =SUM(I10:I15) -> 0 | J16: =SUM(J10:J15) -> 0 | ... N16: =SUM(N10:N15) -> 0
A18: Gastos/Quanto vai sair
A19: Principais gastos | C19: jan | D19: fev | E19: mar | F19: abr | G19: mai | H19: jun | I19: jul | J19: ago | K19: set | L19: out | M19: nov | N19: dez
B20: Aluguel
B21: Prestação da casa
B22: Condomínio
B23: Prestações do carro
B24: Transporte (ônibus, táxi, gasolina, metrô)
B25: Mensalidade escolar
B26: Seguros
B27: Consórcio
B28: Poupança, capitalização, outros investimentos | C28: =(C10+C11+C13)*10% -> 0 | D28: =(D10+D11+D13)*10% -> 0 | E28: =(E10+E11+E13)*10% -> 0 | F28: =(F10+F11+F13)*10% -> 0 | G28: =(G10+G11+G13)*10% -> 0 | H28: =(H10+H11+H13)*10% -> 0 | I28: =(I10+I11+I13)*10% -> 0 | J28: =(J10+J11+J13)*10% -> 0 | ... N28: =(N10+N11+N13)*10% -> 0
B29: Supermercado e/ou sacolão
B30: Fatura do cartão de crédito
B31: Fatura de internet
B32: Conta de telefone
B33: Conta de água
B34: Conta de luz
B35: Gás
B36: Cheques pré-datados
B37: Saúde (consultas, planos)
B38: Remédios
B39: Outras prestações (empréstimos, financiamentos, carnês)
A41: Outros gastos | C41: jan | D41: fev | E41: mar | F41: abr | G41: mai | H41: jun | I41: jul | J41: ago | K41: set | L41: out | M41: nov | N41: dez
B42: Roupas
B43: Gastos com beleza (manicure, cabelo)
B44: Presentes
B45: Lazer (passeios, cinema, lanchonete)
B46: DVD, CD, livros
B47: Emergências
B48: Restaurantes
B49: Gastos do dia a dia*
A51: 3- Total de despesas do mês | C51: =SUM(C20:C40)+SUM(C42:C50) -> 0 | D51: =SUM(D20:D40)+SUM(D42:D50) -> 0 | E51: =SUM(E20:E40)+SUM(E42:E50) -> 0 | F51: =SUM(F20:F40)+SUM(F42:F50) -> 0 | G51: =SUM(G20:G40)+SUM(G42:G50) -> 0 | H51: =SUM(H20:H40)+SUM(H42:H50) -> 0 | I51: =SUM(I20:I40)+SUM(I42:I50) -> 0 | J51: =SUM(J20:J40)+SUM(J42:J50) -> 0 | ... N51: =SUM(N20:N40)+SUM(N42:N50) -> 0
A54: Seu bolso mês a mês | C54: jan | D54: fev | E54: mar | F54: abr | G54: mai | H54: jun | I54: jul | J54: ago | K54: set | L54: out | M54: nov | N54: dez
A55: 1 | B55: TOTAL de quanto entra | C55: =C6+C16 -> 0 | D55: =D6+D16 -> 0 | E55: =E6+E16 -> 0 | F55: =F6+F16 -> 0 | G55: =G6+G16 -> 0 | H55: =H6+H16 -> 0 | I55: =I6+I16 -> 0 | J55: =J6+J16 -> 0 | ... N55: =N6+N16 -> 0
A56: 3 | B56: TOTAL de quanto sai | C56: =-C51 -> 0 | D56: =-D51 -> 0 | E56: =-E51 -> 0 | F56: =-F51 -> 0 | G56: =-G51 -> 0 | H56: =-H51 -> 0 | I56: =-I51 -> 0 | J56: =-J51 -> 0 | ... N56: =-N51 -> 0
A57: SALDO | C57: =SUM(C55:C56) -> 0 | D57: =SUM(D55:D56) -> 0 | E57: =SUM(E55:E56) -> 0 | F57: =SUM(F55:F56) -> 0 | G57: =SUM(G55:G56) -> 0 | H57: =SUM(H55:H56) -> 0 | I57: =SUM(I55:I56) -> 0 | J57: =SUM(J55:J56) -> 0 | ... N57: =SUM(N55:N56) -> 0
B58: * www.meubolsoemdia.com.br
B59: *São gastos que você anotou na nossa Tabela Dia a Dia. Basta anotar diariamente e, no final do mês, somar tudo com uma calculadora.

Sheet FC-ESTUDANTE
A1: Preencha esta tabela mensalmente com sua renda (quanto sua família ganha) e despesas (quanto vai sair) e saiba se você está organizando bem seu orçamento. Se tiver dúvidas, siga nosso passo a passo na segunda edição do nosso informativo. Disponível em http://www.poa.ifsuldeminas.edu.br/index.php?option=com_content&view=article&id=169&Itemid=132
C4: jan | D4: fev | E4: mar | F4: abr | G4: mai | H4: jun | I4: jul | J4: ago | K4: set | L4: out | M4: nov | N4: dez
B5: Saldo Anterior | D5: =C6 -> 0 | E5: =D6 -> 0 | F5: =E6 -> 0 | G5: =F6 -> 0 | H5: =G6 -> 0 | I5: =H6 -> 0 | J5: =I6 -> 0 | K5: =J6 -> 0 | ... N5: =M6 -> 0
A6: 1- Total do saldo | C6: =SUM(C5:C5) -> 0 | D6: =SUM(D5:D5) -> 0 | E6: =SUM(E5:E5) -> 0 | F6: =SUM(F5:F5) -> 0 | G6: =SUM(G5:G5) -> 0 | H6: =SUM(H5:H5) -> 0 | I6: =SUM(I5:I5) -> 0 | J6: =SUM(J5:J5) -> 0 | ... N6: =SUM(N5:N5) -> 0
A8: Rendas/Quanto vai entrar
C9: jan | D9: fev | E9: mar | F9: abr | G9: mai | H9: jun | I9: jul | J9: ago | K9: set | L9: out | M9: nov | N9: dez
B10: Salário
B11: Mesada
B12: Renda extra
B13: Entrada Banco | C13: ='Banco Conta Corrente'!C20+'Banco Conta Corrente'!C21+'Banco Conta Corrente'!C22 -> 0 | D13: ='Banco Conta Corrente'!D20+'Banco Conta Corrente'!D21+'Banco Conta Corrente'!D22 -> 0 | E13: ='Banco Conta Corrente'!E20+'Banco Conta Corrente'!E21+'Banco Conta Corrente'!E22 -> 0 | F13: ='Banco Conta Corrente'!F20+'Banco Conta Corrente'!F21+'Banco Conta Corrente'!F22 -> 0 | G13: ='Banco Conta Corrente'!G20+'Banco Conta Corrente'!G21+'Banco Conta Corrente'!G22 -> 0 | H13: ='Banco Conta Corrente'!H20+'Banco Conta Corrente'!H21+'Banco Conta Corrente'!H22 -> 0 | I13: ='Banco Conta Corrente'!I20+'Banco Conta Corrente'!I21+'Banco Conta Corrente'!I22 -> 0 | J13: ='Banco Conta Corrente'!J20+'Banco Conta Corrente'!J21+'Banco Conta Corrente'!J22 -> 0 | ... N13: ='Banco Conta Corrente'!N20+'Banco Conta Corrente'!N21+'Banco Conta Corrente'!N22 -> 0
B14: Entrada Poupança | C14: ='Poupança-Investimento'!C20 -> 0 | D14: ='Poupança-Investimento'!D20 -> 0 | E14: ='Poupança-Investimento'!E20 -> 0 | F14: ='Poupança-Investimento'!F20 -> 0 | G14: ='Poupança-Investimento'!G20 -> 0 | H14: ='Poupança-Investimento'!H20 -> 0 | I14: ='Poupança-Investimento'!I20 -> 0 | J14: ='Poupança-Investimento'!J20 -> 0 | ... N14: ='Poupança-Investimento'!N20 -> 0
A15: 2- Total de renda da família | C15: =SUM(C10:C14) -> 0 | D15: =SUM(D10:D14) -> 0 | E15: =SUM(E10:E14) -> 0 | F15: =SUM(F10:F14) -> 0 | G15: =SUM(G10:G14) -> 0 | H15: =SUM(H10:H14) -> 0 | I15: =SUM(I10:I14) -> 0 | J15: =SUM(J10:J14) -> 0 | ... N15: =SUM(N10:N14) -> 0
A17: Gastos/Quanto vai sair
A18: Principais gastos | C18: jan | D18: fev | E18: mar | F18: abr | G18: mai | H18: jun | I18: jul | J18: ago | K18: set | L18: out | M18: nov | N18: dez
B19: Aluguel/Condomínio
B20: Mensalidade escolar/faculdade
B21: Material Escolar
B22: Prestações do carro
B23: Seguro do Carro
B24: Transporte (ônibus, táxi, gasolina, metrô)
B25: Poupança, capitalização, outros investimentos | C25: =(C10+C11+C12)*10% -> 0 | D25: =(D10+D11+D12)*10% -> 0 | E25: =(E10+E11+E12)*10% -> 0 | F25: =(F10+F11+F12)*10% -> 0 | G25: =(G10+G11+G12)*10% -> 0 | H25: =(H10+H11+H12)*10% -> 0 | I25: =(I10+I11+I12)*10% -> 0 | J25: =(J10+J11+J12)*10% -> 0 | ... N25: =(N10+N11+N12)*10% -> 0
B26: Supermercado e/ou sacolão
B27: Fatura do cartão de crédito
B28: Fatura de internet
B29: Conta de celular
B30: Conta de telefone
B31: Conta de água
B32: Conta de luz
B33: Gás
B34: Cheques pré-datados
A36: Outros gastos | C36: jan | D36: fev | E36: mar | F36: abr | G36: mai | H36: jun | I36: jul | J36: ago | K36: set | L36: out | M36: nov | N36: dez
B37: Roupas
B38: Gastos com beleza (manicure, cabelo)
B39: Presentes
B40: Lazer (festas, passeios, cinema, lanchonete, restaurante)
B41: DVD, CD, livros
B42: Emergências
B43: Remédios
B44: Gastos do dia a dia*
A46: 3- Total de despesas do mês | C46: =SUM(C19:C35)+SUM(C37:C45) -> 0 | D46: =SUM(D19:D35)+SUM(D37:D45) -> 0 | E46: =SUM(E19:E35)+SUM(E37:E45) -> 0 | F46: =SUM(F19:F35)+SUM(F37:F45) -> 0 | G46: =SUM(G19:G35)+SUM(G37:G45) -> 0 | H46: =SUM(H19:H35)+SUM(H37:H45) -> 0 | I46: =SUM(I19:I35)+SUM(I37:I45) -> 0 | J46: =SUM(J19:J35)+SUM(J37:J45) -> 0 | ... N46: =SUM(N19:N35)+SUM(N37:N45) -> 0
A49: Seu bolso mês a mês | C49: jan | D49: fev | E49: mar | F49: abr | G49: mai | H49: jun | I49: jul | J49: ago | K49: set | L49: out | M49: nov | N49: dez
A50: 1 | B50: TOTAL de quanto entra | C50: =C6+C15 -> 0 | D50: =D6+D15 -> 0 | E50: =E6+E15 -> 0 | F50: =F6+F15 -> 0 | G50: =G6+G15 -> 0 | H50: =H6+H15 -> 0 | I50: =I6+I15 -> 0 | J50: =J6+J15 -> 0 | ... N50: =N6+N15 -> 0
A51: 3 | B51: TOTAL de quanto sai | C51: =-C46 -> 0 | D51: =-D46 -> 0 | E51: =-E46 -> 0 | F51: =-F46 -> 0 | G51: =-G46 -> 0 | H51: =-H46 -> 0 | I51: =-I46 -> 0 | J51: =-J46 -> 0 | ... N51: =-N46 -> 0
A52: SALDO | C52: =SUM(C50:C51) -> 0 | D52: =SUM(D50:D51) -> 0 | E52: =SUM(E50:E51) -> 0 | F52: =SUM(F50:F51) -> 0 | G52: =SUM(G50:G51) -> 0 | H52: =SUM(H50:H51) -> 0 | I52: =SUM(I50:I51) -> 0 | J52: =SUM(J50:J51) -> 0 | ... N52: =SUM(N50:N51) -> 0
B53: * www.meubolsoemdia.com.br
B54: *São gastos que você anotou na nossa Tabela Dia a Dia. Basta anotar diariamente e, no final do mês, somar tudo com uma calculadora.

Sheet FC-DONA DE CASA
A1: Preencha esta tabela mensalmente com sua renda (quanto sua família ganha) e despesas (quanto vai sair) e saiba se você está organizando bem seu orçamento. Se tiver dúvidas, siga nosso passo a passo na segunda edição do nosso informativo. Disponível em http://www.poa.ifsuldeminas.edu.br/index.php?option=com_content&view=article&id=169&Itemid=132
C4: jan | D4: fev | E4: mar | F4: abr | G4: mai | H4: jun | I4: jul | J4: ago | K4: set | L4: out | M4: nov | N4: dez
B5: Saldo Anterior | D5: =C6 -> 0 | E5: =D6 -> 0 | F5: =E6 -> 0 | G5: =F6 -> 0 | H5: =G6 -> 0 | I5: =H6 -> 0 | J5: =I6 -> 0 | K5: =J6 -> 0 | ... N5: =M6 -> 0
A6: 1- Total do saldo | C6: =SUM(C5:C5) -> 0 | D6: =SUM(D5:D5) -> 0 | E6: =SUM(E5:E5) -> 0 | F6: =SUM(F5:F5) -> 0 | G6: =SUM(G5:G5) -> 0 | H6: =SUM(H5:H5) -> 0 | I6: =SUM(I5:I5) -> 0 | J6: =SUM(J5:J5) -> 0 | ... N6: =SUM(N5:N5) -> 0
A8: Rendas/Quanto vai entrar
C9: jan | D9: fev | E9: mar | F9: abr | G9: mai | H9: jun | I9: jul | J9: ago | K9: set | L9: out | M9: nov | N9: dez
B10: Salário total da família
B11: Renda extra
B12: Entrada Banco | C12: ='Banco Conta Corrente'!C20+'Banco Conta Corrente'!C21+'Banco Conta Corrente'!C22 -> 0 | D12: ='Banco Conta Corrente'!D20+'Banco Conta Corrente'!D21+'Banco Conta Corrente'!D22 -> 0 | E12: ='Banco Conta Corrente'!E20+'Banco Conta Corrente'!E21+'Banco Conta Corrente'!E22 -> 0 | F12: ='Banco Conta Corrente'!F20+'Banco Conta Corrente'!F21+'Banco Conta Corrente'!F22 -> 0 | G12: ='Banco Conta Corrente'!G20+'Banco Conta Corrente'!G21+'Banco Conta Corrente'!G22 -> 0 | H12: ='Banco Conta Corrente'!H20+'Banco Conta Corrente'!H21+'Banco Conta Corrente'!H22 -> 0 | I12: ='Banco Conta Corrente'!I20+'Banco Conta Corrente'!I21+'Banco Conta Corrente'!I22 -> 0 | J12: ='Banco Conta Corrente'!J20+'Banco Conta Corrente'!J21+'Banco Conta Corrente'!J22 -> 0 | ... N12: ='Banco Conta Corrente'!N20+'Banco Conta Corrente'!N21+'Banco Conta Corrente'!N22 -> 0
B13: Entrada Poupança | C13: ='Poupança-Investimento'!C20 -> 0 | D13: ='Poupança-Investimento'!D20 -> 0 | E13: ='Poupança-Investimento'!E20 -> 0 | F13: ='Poupança-Investimento'!F20 -> 0 | G13: ='Poupança-Investimento'!G20 -> 0 | H13: ='Poupança-Investimento'!H20 -> 0 | I13: ='Poupança-Investimento'!I20 -> 0 | J13: ='Poupança-Investimento'!J20 -> 0 | ... N13: ='Poupança-Investimento'!N20 -> 0
A14: 2- Total de renda da família | C14: =SUM(C10:C13) -> 0 | D14: =SUM(D10:D13) -> 0 | E14: =SUM(E10:E13) -> 0 | F14: =SUM(F10:F13) -> 0 | G14: =SUM(G10:G13) -> 0 | H14: =SUM(H10:H13) -> 0 | I14: =SUM(I10:I13) -> 0 | J14: =SUM(J10:J13) -> 0 | ... N14: =SUM(N10:N13) -> 0
A16: Gastos/Quanto vai sair
A17: Principais gastos | C17: jan | D17: fev | E17: mar | F17: abr | G17: mai | H17: jun | I17: jul | J17: ago | K17: set | L17: out | M17: nov | N17: dez
B18: Aluguel
B19: Conta de luz
B20: Conta de água
B21: Conta de gás
B22: Conta de telefone (e/ou internet)
B23: Conta de celular
B24: Conta de TV a cabo
B25: Manutenção da casa (eletricista, encanador...)
A27: Família | C27: jan | D27: fev | E27: mar | F27: abr | G27: mai | H27: jun | I27: jul | J27: ago | K27: set | L27: out | M27: nov | N27: dez
B28: Supermercado
B29: Açougue
B30: Padaria
B31: Feira e/ou sacolão
B32: Farmácia
B33: Transporte
B34: Escola
B35: Atividades extracurriculares dos filhos
B36: Alimentação dos filhos na escola
B37: Transporte escolar
B38: Mesada para os filhos
A41: Saúde | C41: jan | D41: fev | E41: mar | F41: abr | G41: mai | H41: jun | I41: jul | J41: ago | K41: set | L41: out | M41: nov | N41: dez
B42: Plano de saúde
B43: Consultas médicas
B44: Exames
A47: Financeiro | C47: jan | D47: fev | E47: mar | F47: abr | G47: mai | H47: jun | I47: jul | J47: ago | K47: set | L47: out | M47: nov | N47: dez
B48: Seguro do Carro
B49: Prestações do carro
B50: Estacionamento
B51: Álcool/Gasolina
B52: Fatura do Cartão de Crédito
B53: Aplicações Financeiras
B54: Aplicações na Poupança | C54: =(C10+C11)*10% -> 0 | D54: =(D10+D11)*10% -> 0 | E54: =(E10+E11)*10% -> 0 | F54: =(F10+F11)*10% -> 0 | G54: =(G10+G11)*10% -> 0 | H54: =(H10+H11)*10% -> 0 | I54: =(I10+I11)*10% -> 0 | J54: =(J10+J11)*10% -> 0 | ... N54: =(N10+N11)*10% -> 0
A57: Financeiro | C57: jan | D57: fev | E57: mar | F57: abr | G57: mai | H57: jun | I57: jul | J57: ago | K57: set | L57: out | M57: nov | N57: dez
B58: Roupas
B59: Gastos com beleza (manicure, cabelo)
B60: Presentes
B61: Lazer (passeios, cinema, parques, clubes)
B62: Viagens
B63: Emergências
B64: Gastos do dia a dia*
A67: 3- Total de despesas do mês | C67: =SUM(C18:C26)+SUM(C28:C66) -> 0 | D67: =SUM(D18:D26)+SUM(D28:D66) -> 0 | E67: =SUM(E18:E26)+SUM(E28:E66) -> 0 | F67: =SUM(F18:F26)+SUM(F28:F66) -> 0 | G67: =SUM(G18:G26)+SUM(G28:G66) -> 0 | H67: =SUM(H18:H26)+SUM(H28:H66) -> 0 | I67: =SUM(I18:I26)+SUM(I28:I66) -> 0 | J67: =SUM(J18:J26)+SUM(J28:J66) -> 0 | ... N67: =SUM(N18:N26)+SUM(N28:N66) -> 0
A70: Seu bolso mês a mês | C70: jan | D70: fev | E70: mar | F70: abr | G70: mai | H70: jun | I70: jul | J70: ago | K70: set | L70: out | M70: nov | N70: dez
A71: 1 | B71: TOTAL de quanto entra | C71: =C6+C14 -> 0 | D71: =D6+D14 -> 0 | E71: =E6+E14 -> 0 | F71: =F6+F14 -> 0 | G71: =G6+G14 -> 0 | H71: =H6+H14 -> 0 | I71: =I6+I14 -> 0 | J71: =J6+J14 -> 0 | ... N71: =N6+N14 -> 0
A72: 3 | B72: TOTAL de quanto sai | C72: =-C67 -> 0 | D72: =-D67 -> 0 | E72: =-E67 -> 0 | F72: =-F67 -> 0 | G72: =-G67 -> 0 | H72: =-H67 -> 0 | I72: =-I67 -> 0 | J72: =-J67 -> 0 | ... N72: =-N67 -> 0
A73: SALDO | C73: =SUM(C71:C72) -> 0 | D73: =SUM(D71:D72) -> 0 | E73: =SUM(E71:E72) -> 0 | F73: =SUM(F71:F72) -> 0 | G73: =SUM(G71:G72) -> 0 | H73: =SUM(H71:H72) -> 0 | I73: =SUM(I71:I72) -> 0 | J73: =SUM(J71:J72) -> 0 | ... N73: =SUM(N71:N72) -> 0
B74: * www.meubolsoemdia.com.br
B75: *São gastos que você anotou na nossa Tabela Dia a Dia. Basta anotar diariamente e, no final do mês, somar tudo com uma calculadora.

Sheet Poupança-Investimento
C2: jan | D2: fev | E2: mar | F2: abr | G2: mai | H2: jun | I2: jul | J2: ago | K2: set | L2: out | M2: nov | N2: dez
B3: Saldo anterior | D3: =C4 -> 0 | E3: =D4 -> 0 | F3: =E4 -> 0 | G3: =F4 -> 0 | H3: =G4 -> 0 | I3: =H4 -> 0 | J3: =I4 -> 0 | K3: =J4 -> 0 | ... N3: =M4 -> 0
A4: 1- Total do saldo | C4: =SUM(C3:C3) -> 0 | D4: =SUM(D3:D3) -> 0 | E4: =SUM(E3:E3) -> 0 | F4: =SUM(F3:F3) -> 0 | G4: =SUM(G3:G3) -> 0 | H4: =SUM(H3:H3) -> 0 | I4: =SUM(I3:I3) -> 0 | J4: =SUM(J3:J3) -> 0 | ... N4: =SUM(N3:N3) -> 0
A6: Entrada na Poupança
C7: jan | D7: fev | E7: mar | F7: abr | G7: mai | H7: jun | I7: jul | J7: ago | K7: set | L7: out | M7: nov | N7: dez
B8: Entrada Poupança 1
B9: Entrada Poupança 2
B10: Rendimentos da Poupança
A13: 2- Total de créditos | C13: =SUM(C8:C12) -> 0 | D13: =SUM(D8:D12) -> 0 | E13: =SUM(E8:E12) -> 0 | F13: =SUM(F8:F12) -> 0 | G13: =SUM(G8:G12) -> 0 | H13: =SUM(H8:H12) -> 0 | I13: =SUM(I8:I12) -> 0 | J13: =SUM(J8:J12) -> 0 | ... N13: =SUM(N8:N12) -> 0
A15: Saídas da Poupança
C16: jan | D16: fev | E16: mar | F16: abr | G16: mai | H16: jun | I16: jul | J16: ago | K16: set | L16: out | M16: nov | N16: dez
B17: Saída 1
B18: Saída 2
B19: Saída 3
A20: 3- Total de débitos | C20: =SUM(C17:C19) -> 0 | D20: =SUM(D17:D19) -> 0 | E20: =SUM(E17:E19) -> 0 | F20: =SUM(F17:F19) -> 0 | G20: =SUM(G17:G19) -> 0 | H20: =SUM(H17:H19) -> 0 | I20: =SUM(I17:I19) -> 0 | J20: =SUM(J17:J19) -> 0 | ... N20: =SUM(N17:N19) -> 0
A23: Saldo mês a mês | C23: jan | D23: fev | E23: mar | F23: abr | G23: mai | H23: jun | I23: jul | J23: ago | K23: set | L23: out | M23: nov | N23: dez
A24: 1 | B24: TOTAL de quanto entra | C24: =C4+C13 -> 0 | D24: =D4+D13 -> 0 | E24: =E4+E13 -> 0 | F24: =F4+F13 -> 0 | G24: =G4+G13 -> 0 | H24: =H4+H13 -> 0 | I24: =I4+I13 -> 0 | J24: =J4+J13 -> 0 | ... N24: =N4+N13 -> 0
A25: 3 | B25: TOTAL de quanto sai | C25: =-C20 -> 0 | D25: =-D20 -> 0 | E25: =-E20 -> 0 | F25: =-F20 -> 0 | G25: =-G20 -> 0 | H25: =-H20 -> 0 | I25: =-I20 -> 0 | J25: =-J20 -> 0 | ... N25: =-N20 -> 0
A26: SALDO | C26: =SUM(C24:C25) -> 0 | D26: =SUM(D24:D25) -> 0 | E26: =SUM(E24:E25) -> 0 | F26: =SUM(F24:F25) -> 0 | G26: =SUM(G24:G25) -> 0 | H26: =SUM(H24:H25) -> 0 | I26: =SUM(I24:I25) -> 0 | J26: =SUM(J24:J25) -> 0 | ... N26: =SUM(N24:N25) -> 0

Sheet Banco Conta Corrente
C2: jan | D2: fev | E2: mar | F2: abr | G2: mai | H2: jun | I2: jul | J2: ago | K2: set | L2: out | M2: nov | N2: dez
B3: Saldo anterior | D3: =C4 -> 0 | E3: =D4 -> 0 | F3: =E4 -> 0 | G3: =F4 -> 0 | H3: =G4 -> 0 | I3: =H4 -> 0 | J3: =I4 -> 0 | K3: =J4 -> 0 | ... N3: =M4 -> 0
A4: 1- Total do saldo | C4: =SUM(C3:C3) -> 0 | D4: =SUM(D3:D3) -> 0 | E4: =SUM(E3:E3) -> 0 | F4: =SUM(F3:F3) -> 0 | G4: =SUM(G3:G3) -> 0 | H4: =SUM(H3:H3) -> 0 | I4: =SUM(I3:I3) -> 0 | J4: =SUM(J3:J3) -> 0 | ... N4: =SUM(N3:N3) -> 0
A6: Crédito no Banco
C7: jan | D7: fev | E7: mar | F7: abr | G7: mai | H7: jun | I7: jul | J7: ago | K7: set | L7: out | M7: nov | N7: dez
B8: Entrada Salário
B9: Entrada 1
B10: Entrada 2
A13: 2- Total Créditos | C13: =SUM(C8:C12) -> 0 | D13: =SUM(D8:D12) -> 0 | E13: =SUM(E8:E12) -> 0 | F13: =SUM(F8:F12) -> 0 | G13: =SUM(G8:G12) -> 0 | H13: =SUM(H8:H12) -> 0 | I13: =SUM(I8:I12) -> 0 | J13: =SUM(J8:J12) -> 0 | ... N13: =SUM(N8:N12) -> 0
A15: Saídas da Poupança
C16: jan | D16: fev | E16: mar | F16: abr | G16: mai | H16: jun | I16: jul | J16: ago | K16: set | L16: out | M16: nov | N16: dez
B17: Contas em Débito
B18: Cartão de Crédito | C18: ='Cartão de Crédito'!D10 -> 0 | D18: ='Cartão de Crédito'!E10 -> 0 | E18: ='Cartão de Crédito'!F10 -> 0 | F18: ='Cartão de Crédito'!G10 -> 0 | G18: ='Cartão de Crédito'!H10 -> 0 | H18: ='Cartão de Crédito'!I10 -> 0 | I18: ='Cartão de Crédito'!J10 -> 0 | J18: ='Cartão de Crédito'!K10 -> 0 | ... N18: ='Cartão de Crédito'!O10 -> 0
B19: Contas Financiamento
B20: Saque 1
B21: Saque 2
B22: Saque 3
B23: Taxa Bancária | C23: 13.5
A24: 3- Total de débitos | C24: =SUM(C17:C23) -> 13.5 | D24: =SUM(D17:D23) -> 0 | E24: =SUM(E17:E23) -> 0 | F24: =SUM(F17:F23) -> 0 | G24: =SUM(G17:G23) -> 0 | H24: =SUM(H17:H23) -> 0 | I24: =SUM(I17:I23) -> 0 | J24: =SUM(J17:J23) -> 0 | ... N24: =SUM(N17:N23) -> 0
A27: Saldo mês a mês | C27: jan | D27: fev | E27: mar | F27: abr | G27: mai | H27: jun | I27: jul | J27: ago | K27: set | L27: out | M27: nov | N27: dez
A28: 1 | B28: TOTAL de quanto entra | C28: =C4+C13 -> 0 | D28: =D4+D13 -> 0 | E28: =E4+E13 -> 0 | F28: =F4+F13 -> 0 | G28: =G4+G13 -> 0 | H28: =H4+H13 -> 0 | I28: =I4+I13 -> 0 | J28: =J4+J13 -> 0 | ... N28: =N4+N13 -> 0
A29: 3 | B29: TOTAL de quanto sai | C29: =-C24 -> -13.5 | D29: =-D24 -> 0 | E29: =-E24 -> 0 | F29: =-F24 -> 0 | G29: =-G24 -> 0 | H29: =-H24 -> 0 | I29: =-I24 -> 0 | J29: =-J24 -> 0 | ... N29: =-N24 -> 0
A30: SALDO | C30: =SUM(C28:C29) -> -13.5 | D30: =SUM(D28:D29) -> 0 | E30: =SUM(E28:E29) -> 0 | F30: =SUM(F28:F29) -> 0 | G30: =SUM(G28:G29) -> 0 | H30: =SUM(H28:H29) -> 0 | I30: =SUM(I28:I29) -> 0 | J30: =SUM(J28:J29) -> 0 | ... N30: =SUM(N28:N29) -> 0

Sheet Cartão de Crédito
A1: Cartão de Crédito
D2: jan | E2: fev | F2: mar | G2: abr | H2: mai | I2: jun | J2: jul | K2: ago | L2: set | M2: out | N2: nov | O2: dez
C3: Valor Total da Despesa
B5: Despesa 1 | C5: R$
B6: Despesa 2 | C6: R$
B7: Despesa 3 | C7: R$
B8: Despesa 3 | C8: R$
B9: Estorno Mês anterior | C9: R$
A10: 1- Total | C10: =SUM(C5:C9) -> 0 | D10: =SUM(D5:D9) -> 0 | E10: =SUM(E5:E9) -> 0 | F10: =SUM(F5:F9) -> 0 | G10: =SUM(G5:G9) -> 0 | H10: =SUM(H5:H9) -> 0 | I10: =SUM(I5:I9) -> 0 | J10: =SUM(J5:J9) -> 0 | ... O10: =SUM(O5:O9) -> 0
A12: Limite do Cartão/data vencimento | C12: 5000
C13: 10/mês | D13: jan | E13: fev | F13: mar | G13: abr | H13: mai | I13: jun | J13: jul | K13: ago | L13: set | M13: out | N13: nov | O13: dez
C14: Saldo do mês | D14: =D10 -> 0 | E14: =E10 -> 0 | F14: =F10 -> 0 | G14: =G10 -> 0 | H14: =H10 -> 0 | I14: =I10 -> 0 | J14: =J10 -> 0 | K14: =K10 -> 0 | ... O14: =O10 -> 0
A15: 2- Controle do Limite ate a data do vencimento | D15: 0 | E15: 0 | F15: 0 | G15: 0 | H15: 0 | I15: 0 | J15: 0 | K15: 0 | L15: 0 | M15: 0 | N15: 0 | O15: 0
