Workbook

Sheet Resumo
A1: Resumo modelo RDT
B2: 2012 | C2: =+B2+1 -> 2013 | D2: =+C2+1 -> 2014 | E2: =+D2+1 -> 2015 | F2: =+E2+1 -> 2016 | G2: =+F2+1 -> 2017 | H2: =+G2+1 -> 2018 | I2: =+H2+1 -> 2019 | J2: =+I2+1 -> 2020 | ... R2: =+Q2+1 -> 2028
A3: Tráfego | B3: =+'Dados Financeiros'!L3 -> 2012 | C3: =+'Dados Financeiros'!Q3 -> 2013 | D3: =+'Dados Financeiros'!V3 -> 2014 | E3: =+'Dados Financeiros'!AA3 -> 2015E | F3: =+'Dados Financeiros'!AB3 -> 2016E | G3: =+'Dados Financeiros'!AC3 -> 2017E | H3: =+'Dados Financeiros'!AD3 -> 2018E | I3: =+'Dados Financeiros'!AE3 -> 2019E | J3: =+'Dados Financeiros'!AF3 -> 2020E | K3: =+'Dados Financeiros'!AG3 -> 2021E | L3: =+'Dados Financeiros'!AH3 -> 2022E | ... R3: =+'Dados Financeiros'!AN3 -> 2028E
A4: Tráfego (Mil Veículos Equivalentes) | B4: =+HLOOKUP(B3,Tráfego!$O$14:$CV$31,18,0) -> 43011.533 | C4: =+HLOOKUP(C3,Tráfego!$O$14:$CV$31,18,0) -> 46302.8 | D4: =+HLOOKUP(D3,Tráfego!$O$14:$CV$31,18,0) -> 48528.447 | E4: =+HLOOKUP(E3,Tráfego!$O$14:$CV$31,18,0) -> 46736.441 | F4: =+HLOOKUP(F3,Tráfego!$O$14:$CV$31,18,0) -> 48379.368 | G4: =+HLOOKUP(G3,Tráfego!$O$14:$CV$31,18,0) -> 51329.815 | H4: =+HLOOKUP(H3,Tráfego!$O$14:$CV$31,18,0) -> 55382.484 | I4: =+HLOOKUP(I3,Tráfego!$O$14:$CV$31,18,0) -> 58661.515 | ... R4: =+HLOOKUP(R3,Tráfego!$O$14:$CV$31,18,0) -> 83187.57
A5: YoY | C5: =+C4/B4-1 -> 0.076520569 | D5: =+D4/C4-1 -> 0.048067223 | E5: =+E4/D4-1 -> -0.036926918 | F5: =+F4/E4-1 -> 0.035153015 | G5: =+G4/F4-1 -> 0.060985643 | H5: =+H4/G4-1 -> 0.078953524 | I5: =+I4/H4-1 -> 0.059206988 | J5: =+J4/I4-1 -> 0.060351696 | ... R5: =+R4/Q4-1 -> 0.020203947
A6: Elasticidade PIB | B6: 2 | C6: =+C5/(HLOOKUP(C3,Despesas!$B$3:$AF$4,2,0)/100) -> 2.78892 | D6: =+D5/(HLOOKUP(D3,Despesas!$B$3:$AF$4,2,0)/100) -> 33.245214 | E6: =+E5/(HLOOKUP(E3,Despesas!$B$3:$AF$4,2,0)/100) -> 1.1911909 | F6: =+F5/(HLOOKUP(F3,Despesas!$B$3:$AF$4,2,0)/100) -> -1.7576508 | G6: =+G5/(HLOOKUP(G3,Despesas!$B$3:$AF$4,2,0)/100) -> 6.0985643 | H6: =+H5/(HLOOKUP(H3,Despesas!$B$3:$AF$4,2,0)/100) -> 3.9476762 | I6: =+I5/(HLOOKUP(I3,Despesas!$B$3:$AF$4,2,0)/100) -> 2.9603494 | J6: =+J5/(HLOOKUP(J3,Despesas!$B$3:$AF$4,2,0)/100) -> 3.0175848 | ... R6: =+R5/(HLOOKUP(R3,Despesas!$B$3:$AF$4,2,0)/100) -> 1.0101973
A7: Tráfego médio mensal por Km* | B7: =+(B4/12)/HLOOKUP(B3,Tráfego!$F$14:$CV$19,6,0) -> 8.8209244 | C7: =+(C4/12)/HLOOKUP(C3,Tráfego!$F$14:$CV$19,6,0) -> 9.4976596 | D7: =+(D4/12)/HLOOKUP(D3,Tráfego!$F$14:$CV$19,6,0) -> 9.9541857 | E7: =+(E4/12)/HLOOKUP(E3,Tráfego!$F$14:$CV$19,6,0) -> 9.5866083 | F7: =+(F4/12)/HLOOKUP(F3,Tráfego!$F$14:$CV$19,6,0) -> 9.7113394 | G7: =+(G4/12)/HLOOKUP(G3,Tráfego!$F$14:$CV$19,6,0) -> 10.303592 | H7: =+(H4/12)/HLOOKUP(H3,Tráfego!$F$14:$CV$19,6,0) -> 11.117097 | I7: =+(I4/12)/HLOOKUP(I3,Tráfego!$F$14:$CV$19,6,0) -> 11.775306 | ... R7: =+(R4/12)/HLOOKUP(R3,Tráfego!$F$14:$CV$19,6,0) -> 16.698497
A8: CAGR por fases
A9: Fase I (2012-2015) | B9: =+(E4/B4)^(1/(E2-B2))-1 -> 0.028072097
A10: Fase II (2015-2018) | B10: =+(H4/E4)^(1/(H2-E2))-1 -> 0.058210985 | D10: CAGR Total | F10: =+(R4/B4)^(1/(R2-B2))-1 -> 0.04208848
A11: Fase III (2018-2028) | B11: =+(R4/H4)^(1/(R2-H2))-1 -> 0.041522366 | D11: Haircut VTM | F11: =1-SUM(C4:R4)/1288075 -> 0.21420235 | G11: => Redução de tráfego em relação ao cenário da VTM (consultor de tráfego) durante os 15 anos
A12: *Em mil veículos equivalentes
A14: Dados Financeiros (R$ mm) | B14: =+B3 -> 2012 | C14: =+C3 -> 2013 | D14: =+D3 -> 2014 | E14: =+E3 -> 2015E | F14: =+F3 -> 2016E | G14: =+G3 -> 2017E | H14: =+H3 -> 2018E | I14: =+I3 -> 2019E | ... R14: =+R3 -> 2028E
A15: Receita Bruta de Pedágio | B15: =+HLOOKUP(B14,Tráfego!$J$14:$CV$35,22,0) -> 172.4 | C15: =+HLOOKUP(C14,Tráfego!$J$14:$CV$35,22,0) -> 186.1 | D15: =+HLOOKUP(D14,Tráfego!$J$14:$CV$35,22,0) -> 203.452 | E15: =+HLOOKUP(E14,Tráfego!$J$14:$CV$35,22,0) -> 211.33738 | F15: =+HLOOKUP(F14,Tráfego!$J$14:$CV$35,22,0) -> 248.19037 | G15: =+HLOOKUP(G14,Tráfego!$J$14:$CV$35,22,0) -> 280.91898 | H15: =+HLOOKUP(H14,Tráfego!$J$14:$CV$35,22,0) -> 325.02646 | I15: =+HLOOKUP(I14,Tráfego!$J$14:$CV$35,22,0) -> 362.68459 | ... R15: =+HLOOKUP(R14,Tráfego!$J$14:$CV$35,22,0) -> 765.00712
A16: Receita Operacional Líquida | B16: =+'Dados Financeiros'!L46-'Dados Financeiros'!L42 -> 161.73 | C16: =+'Dados Financeiros'!Q46-'Dados Financeiros'!Q42 -> 174.9 | D16: =+'Dados Financeiros'!V46-'Dados Financeiros'!V42 -> 190.743 | E16: =+'Dados Financeiros'!AA46-'Dados Financeiros'!AA42 -> 198.14047 | F16: =+'Dados Financeiros'!AB46-'Dados Financeiros'!AB42 -> 231.73988 | G16: =+'Dados Financeiros'!AC46-'Dados Financeiros'!AC42 -> 267.02458 | H16: =+'Dados Financeiros'!AD46-'Dados Financeiros'!AD42 -> 306.39217 | I16: =+'Dados Financeiros'!AE46-'Dados Financeiros'!AE42 -> 340.75006 | J16: =+'Dados Financeiros'!AF46-'Dados Financeiros'!AF42 -> 376.39341 | K16: =+'Dados Financeiros'!AG46-'Dados Financeiros'!AG42 -> 408.98416 | L16: =+'Dados Financeiros'!AH46-'Dados Financeiros'!AH42 -> 444.15966 | ... R16: =+'Dados Financeiros'!AN46-'Dados Financeiros'!AN42 -> 707.67175
A17: EBITDA Ajustado | B17: =+'Dados Financeiros'!L65 -> 93.047 | C17: =+'Dados Financeiros'!Q65 -> 99.085 | D17: =+'Dados Financeiros'!V65 -> 116.531 | E17: =+'Dados Financeiros'!AA65 -> 117.23565 | F17: =+'Dados Financeiros'!AB65 -> 162.92792 | G17: =+'Dados Financeiros'!AC65 -> 196.92392 | H17: =+'Dados Financeiros'!AD65 -> 232.15608 | I17: =+'Dados Financeiros'!AE65 -> 263.0321 | J17: =+'Dados Financeiros'!AF65 -> 295.00341 | K17: =+'Dados Financeiros'!AG65 -> 323.20869 | L17: =+'Dados Financeiros'!AH65 -> 353.75076 | ... R17: =+'Dados Financeiros'!AN65 -> 583.98648 | S17: =+SUM(B17:R17) -> 5156.9109
A18: Margem Ebitda Ajustada | B18: =+'Dados Financeiros'!L66 -> 0.57532307 | C18: =+'Dados Financeiros'!Q66 -> 0.56652373 | D18: =+'Dados Financeiros'!V66 -> 0.61093199 | E18: =+'Dados Financeiros'!AA66 -> 0.59167948 | F18: =+'Dados Financeiros'!AB66 -> 0.70306382 | G18: =+'Dados Financeiros'!AC66 -> 0.73747485 | H18: =+'Dados Financeiros'!AD66 -> 0.75770892 | I18: =+'Dados Financeiros'!AE66 -> 0.77192093 | J18: =+'Dados Financeiros'!AF66 -> 0.7837635 | K18: =+'Dados Financeiros'!AG66 -> 0.79027191 | L18: =+'Dados Financeiros'!AH66 -> 0.79644954 | ... R18: =+'Dados Financeiros'!AN66 -> 0.82522227
A20: Fluxo de Caixa Livre | C20: =+'Dados Financeiros'!Q206+'Dados Financeiros'!Q209 -> -66.548 | D20: =+'Dados Financeiros'!V206+'Dados Financeiros'!V209 -> -31.642 | E20: =+'Dados Financeiros'!AA206+'Dados Financeiros'!AA209 -> 49.615461 | F20: =+'Dados Financeiros'!AB206+'Dados Financeiros'!AB209 -> 1.224062 | G20: =+'Dados Financeiros'!AC206+'Dados Financeiros'!AC209 -> 25.753318 | H20: =+'Dados Financeiros'!AD206+'Dados Financeiros'!AD209 -> 88.453211 | I20: =+'Dados Financeiros'!AE206+'Dados Financeiros'!AE209 -> 104.01165 | J20: =+'Dados Financeiros'!AF206+'Dados Financeiros'!AF209 -> 126.93222 | K20: =+'Dados Financeiros'!AG206+'Dados Financeiros'!AG209 -> 84.870236 | L20: =+'Dados Financeiros'!AH206+'Dados Financeiros'!AH209 -> 129.31723 | ... R20: =+'Dados Financeiros'!AN206+'Dados Financeiros'!AN209 -> 292.52639
A22: Dívida Bruta | B22: =+'Dados Financeiros'!L105 -> 627 | C22: =+'Dados Financeiros'!Q105 -> 1068.1 | D22: =+'Dados Financeiros'!V105 -> 1107.232 | E22: =+'Dados Financeiros'!AA105 -> 1236.7545 | F22: =+'Dados Financeiros'!AB105 -> 1330.8547 | G22: =+'Dados Financeiros'!AC105 -> 1389.7638 | H22: =+'Dados Financeiros'!AD105 -> 1401.1626 | I22: =+'Dados Financeiros'!AE105 -> 1371.4743 | J22: =+'Dados Financeiros'!AF105 -> 1319.2578 | K22: =+'Dados Financeiros'!AG105 -> 1249.6896 | L22: =+'Dados Financeiros'!AH105 -> 1150.0385 | ... R22: =+'Dados Financeiros'!AN105 -> 56.557868
A23: Dívida Líquida | B23: =+'Dados Financeiros'!L106 -> 579.1 | C23: =+'Dados Financeiros'!Q106 -> 717.3 | D23: =+'Dados Financeiros'!V106 -> 858.38 | E23: =+'Dados Financeiros'!AA106 -> 954.71003 | F23: =+'Dados Financeiros'!AB106 -> 1047.5862 | G23: =+'Dados Financeiros'!AC106 -> 1087.7709 | H23: =+'Dados Financeiros'!AD106 -> 1048.098 | I23: =+'Dados Financeiros'!AE106 -> 981.96529 | J23: =+'Dados Financeiros'!AF106 -> 893.04547 | K23: =+'Dados Financeiros'!AG106 -> 818.96526 | L23: =+'Dados Financeiros'!AH106 -> 708.38692 | ... R23: =+'Dados Financeiros'!AN106 -> -584.40948
A25: Índices de Alavancagem
A26: Dívida Líquida / Ebitda | B26: =+'Dados Financeiros'!L109 -> 6.2237364 | C26: =+'Dados Financeiros'!Q109 -> 7.239239 | D26: =+'Dados Financeiros'!V109 -> 7.3661086 | E26: =+'Dados Financeiros'!AA109 -> 8.1435131 | F26: =+'Dados Financeiros'!AB109 -> 6.4297522 | G26: =+'Dados Financeiros'!AC109 -> 5.5238132 | H26: =+'Dados Financeiros'!AD109 -> 4.5146268 | I26: =+'Dados Financeiros'!AE109 -> 3.7332527 | J26: =+'Dados Financeiros'!AF109 -> 3.0272377 | K26: =+'Dados Financeiros'!AG109 -> 2.533859 | L26: =+'Dados Financeiros'!AH109 -> 2.0025029 | ... R26: =+'Dados Financeiros'!AN109 -> -1.0007243
A27: ICSD | E27: =+'Dados Financeiros'!AA237 -> 2.2558049 | F27: =+'Dados Financeiros'!AB237 -> 1.0118794 | G27: =+'Dados Financeiros'!AC237 -> 1.1577709 | H27: =+'Dados Financeiros'!AD237 -> 1.3129103 | I27: =+'Dados Financeiros'!AE237 -> 1.2425415 | J27: =+'Dados Financeiros'!AF237 -> 1.2845538 | K27: =+'Dados Financeiros'!AG237 -> 1.1483317 | L27: =+'Dados Financeiros'!AH237 -> 1.1677689 | ... O27: =+'Dados Financeiros'!AK237 -> 1.2454026 | P27: =+'Dados Financeiros'!AL237+0.009 -> 1.3093176 | Q27: =+'Dados Financeiros'!AM237 -> 1.191559 | R27: =+'Dados Financeiros'!AN237 -> 2.5874854
A28: Limite Covenant | E28: 1.15 | F28: 1.15 | G28: 1.15 | H28: 1.15 | I28: 1.15 | J28: 1.15 | K28: 1.15 | L28: 1.15 | M28: 1.15 | N28: 1.15 | O28: 1.15 | P28: 1.15 | Q28: 1.15 | R28: 1.15
A29: Teste | E29: =+IF(E27>1.14,"ok","verificar") -> ok | F29: =+IF(F27>1.14,"ok","verificar") -> verificar | G29: =+IF(G27>1.14,"ok","verificar") -> ok | H29: =+IF(H27>1.14,"ok","verificar") -> ok | I29: =+IF(I27>1.14,"ok","verificar") -> ok | J29: =+IF(J27>1.14,"ok","verificar") -> ok | K29: =+IF(K27>1.14,"ok","verificar") -> ok | L29: =+IF(L27>1.14,"ok","verificar") -> ok | ... R29: =+IF(R27>1.14,"ok","verificar") -> ok
A30: Dívida Bruta / Capital Total | C30: =+'Dados Financeiros'!Q235 -> 0.84082608 | D30: =+'Dados Financeiros'!V235 -> 0.84350315 | E30: =+'Dados Financeiros'!AA235 -> 0.86265546 | F30: =+'Dados Financeiros'!AB235 -> 0.86408774 | G30: =+'Dados Financeiros'!AC235 -> 0.84444334 | H30: =+'Dados Financeiros'!AD235 -> 0.80432645 | I30: =+'Dados Financeiros'!AE235 -> 0.74701595 | J30: =+'Dados Financeiros'!AF235 -> 0.68821629 | K30: =+'Dados Financeiros'!AG235 -> 0.62380026 | L30: =+'Dados Financeiros'!AH235 -> 0.55720351 | ... R30: =+'Dados Financeiros'!AN235 -> 0
A31: Limite Covenant | C31: 0.85 | D31: 0.85 | E31: 0.85 | F31: 0.85 | G31: 0.85 | H31: 0.85 | I31: 0.75 | J31: 0.75 | K31: 0.75 | L31: 0.75 | M31: 0.75 | N31: 0.75 | O31: 0.75 | P31: 0.75 | Q31: 0.75 | R31: 0.75
A32: Limite < 85% até 2018 e < 75% após | C32: =+IF(C30<=C31,"ok","verificar") -> ok | D32: =+IF(D30<=D31,"ok","verificar") -> ok | E32: =+IF(E30<=E31,"ok","verificar") -> verificar | F32: =+IF(F30<=F31,"ok","verificar") -> verificar | G32: =+IF(G30<=G31,"ok","verificar") -> ok | H32: =+IF(H30<=H31,"ok","verificar") -> ok | I32: =+IF(I30<=I31,"ok","verificar") -> ok | J32: =+IF(J30<=J31,"ok","verificar") -> ok | ... R32: =+IF(R30<=R31,"ok","verificar") -> ok
A34: Contas Reservas | B34: =+B14 -> 2012 | C34: =+C14 -> 2013 | D34: =+D14 -> 2014 | E34: =+E14 -> 2015E | F34: =+F14 -> 2016E | G34: =+G14 -> 2017E | H34: =+H14 -> 2018E | I34: =+I14 -> 2019E | ... R34: =+R14 -> 2028E
A35: =+'Dados Financeiros'!A225 -> Conta Reserva de Capex | C35: =+'Dados Financeiros'!Q225 -> 43.558037 | D35: =+'Dados Financeiros'!V225 -> 67.232978 | E35: =+'Dados Financeiros'!AA225 -> 90.214368 | F35: =+'Dados Financeiros'!AB225 -> 76.353182 | G35: =+'Dados Financeiros'!AC225 -> 63.112916 | H35: =+'Dados Financeiros'!AD225 -> 72.505883 | I35: =+'Dados Financeiros'!AE225 -> 74.119505 | J35: =+'Dados Financeiros'!AF225 -> 73.978922 | K35: =+'Dados Financeiros'!AG225 -> 62.32066 | L35: =+'Dados Financeiros'!AH225 -> 55.163442 | ... R35: =+'Dados Financeiros'!AN225 -> 102.84459
A36: =+'Dados Financeiros'!A226 -> Conta de Serviço de Dívida | C36: =+'Dados Financeiros'!Q226 -> 0 | D36: =+'Dados Financeiros'!V226 -> 98.202331 | E36: =+'Dados Financeiros'!AA226 -> 103.04091 | F36: =+'Dados Financeiros'!AB226 -> 118.68046 | G36: =+'Dados Financeiros'!AC226 -> 163.2152 | H36: =+'Dados Financeiros'!AD226 -> 191.72658 | I36: =+'Dados Financeiros'!AE226 -> 206.16739 | J36: =+'Dados Financeiros'!AF226 -> 214.30177 | K36: =+'Dados Financeiros'!AG226 -> 233.76343 | L36: =+'Dados Financeiros'!AH226 -> 268.86253 | ... R36: =+'Dados Financeiros'!AN226 -> 0
A37: =+'Dados Financeiros'!A227 -> Reserva para Despesas Operacionais | C37: =+'Dados Financeiros'!Q227 -> 16.45375 | D37: =+'Dados Financeiros'!V227 -> 16.27925 | E37: =+'Dados Financeiros'!AA227 -> 17.826543 | F37: =+'Dados Financeiros'!AB227 -> 15.031081 | G37: =+'Dados Financeiros'!AC227 -> 15.458659 | H37: =+'Dados Financeiros'!AD227 -> 16.345735 | I37: =+'Dados Financeiros'!AE227 -> 17.134572 | J37: =+'Dados Financeiros'!AF227 -> 17.941687 | K37: =+'Dados Financeiros'!AG227 -> 18.850449 | L37: =+'Dados Financeiros'!AH227 -> 19.807204 | ... R37: =+'Dados Financeiros'!AN227 -> 26.628492
A38: =+'Dados Financeiros'!A228 -> Conta de pré-financimanto de juros | C38: =+'Dados Financeiros'!Q228 -> 115.302 | D38: =+'Dados Financeiros'!V228 -> 29.393 | E38: =+'Dados Financeiros'!AA228 -> 29.393 | F38: =+'Dados Financeiros'!AB228 -> 0 | G38: =+'Dados Financeiros'!AC228 -> 0 | H38: =+'Dados Financeiros'!AD228 -> 0 | I38: =+'Dados Financeiros'!AE228 -> 0 | J38: =+'Dados Financeiros'!AF228 -> 0 | K38: =+'Dados Financeiros'!AG228 -> 0 | L38: =+'Dados Financeiros'!AH228 -> 0 | ... R38: =+'Dados Financeiros'!AN228 -> 0
A39: TOTAL DE RESERVAS | C39: =+SUM(C35:C38) -> 175.31379 | D39: =+SUM(D35:D38) -> 211.10756 | E39: =+SUM(E35:E38) -> 240.47482 | F39: =+SUM(F35:F38) -> 210.06472 | G39: =+SUM(G35:G38) -> 241.78677 | H39: =+SUM(H35:H38) -> 280.5782 | I39: =+SUM(I35:I38) -> 297.42147 | J39: =+SUM(J35:J38) -> 306.22238 | ... R39: =+SUM(R35:R38) -> 129.47308
A41: Caixa Final | C41: =+'Dados Financeiros'!Q7 -> 350.8 | D41: =+'Dados Financeiros'!V7 -> 248.852 | E41: =+'Dados Financeiros'!AA7 -> 282.04446 | F41: =+'Dados Financeiros'!AB7 -> 283.26852 | G41: =+'Dados Financeiros'!AC7 -> 301.99284 | H41: =+'Dados Financeiros'!AD7 -> 353.06455 | I41: =+'Dados Financeiros'!AE7 -> 389.50903 | J41: =+'Dados Financeiros'!AF7 -> 426.21234 | K41: =+'Dados Financeiros'!AG7 -> 430.72433 | L41: =+'Dados Financeiros'!AH7 -> 441.65162 | ... R41: =+'Dados Financeiros'!AN7 -> 640.96734
A42: Enquadramento | C42: =+IF(C41>C39,"ok", "verificar") -> ok | D42: =+IF(D41>D39,"ok", "verificar") -> ok | E42: =+IF(E41>E39,"ok", "verificar") -> ok | F42: =+IF(F41>F39,"ok", "verificar") -> ok | G42: =+IF(G41>G39,"ok", "verificar") -> ok | H42: =+IF(H41>H39,"ok", "verificar") -> ok | I42: =+IF(I41>I39,"ok", "verificar") -> ok | J42: =+IF(J41>J39,"ok", "verificar") -> ok | ... R42: =+IF(R41>R39,"ok", "verificar") -> ok

Sheet Dados Financeiros
A1: Rodovias do Tiete
A3: Balanço Patrimonial (R$ mn) | B3: 2010 | C3: 1T11 | D3: 2T11 | E3: 3T11 | F3: 4T11 | G3: 2011 | H3: 1T12 | I3: 2T12 | J3: 3T12 | K3: 4T12 | L3: 2012 | M3: 1T13 | N3: 2T13 | O3: 3T13 | P3: 4T13 | Q3: 2013 | R3: 1T14 | S3: 2T14 | T3: 3T14 | U3: 4T14 | V3: 2014 | W3: 1T15 | X3: 2T15 | Y3: 3T15 | Z3: 4T15E | AA3: 2015E | AB3: 2016E | AC3: 2017E | AD3: 2018E | AE3: 2019E | AF3: 2020E | AG3: 2021E | AH3: 2022E | AI3: 2023E | AJ3: 2024E | AK3: 2025E | AL3: 2026E | AM3: 2027E | AN3: 2028E
A4: Ativo Total | B4: 807.85 | C4: =+C6+C12+C14 -> 814.45 | D4: =+D6+D12+D14 -> 796.708 | E4: =+E6+E12+E14 -> 825.35 | F4: =+F6+F12+F14 -> 792.37 | G4: =+G6+G12+G14 -> 792.37 | H4: =+H6+H12+H14 -> 799.39 | I4: =+I6+I12+I14 -> 796.5 | J4: =+J6+J12+J14 -> 893.97 | ... AN4: =+AN6+AN12+AN14 -> 2613.1925
A6: Ativo Circulante | B6: 84.55 | C6: =+SUM(C7:C10) -> 92.36 | D6: =+SUM(D7:D10) -> 15.1 | E6: =+SUM(E7:E10) -> 89.9 | F6: =+SUM(F7:F10) -> 41.17 | G6: =+SUM(G7:G10) -> 41.17 | H6: =+SUM(H7:H10) -> 39.45 | I6: =+SUM(I7:I10) -> 14.8 | J6: =+SUM(J7:J10) -> 83.57 | ... AN6: =+SUM(AN7:AN10) -> 741.69985
A7: Caixa | B7: 75.1 | C7: 80 | D7: 3.9 | E7: 74 | F7: 27.3 | G7: =+F7 -> 27.3 | H7: 22.17 | I7: 3.9 | J7: 62.9 | K7: 47.9 | L7: =+K7 -> 47.9 | M7: 37.56 | N7: 5 | O7: =1.4+89.9+301.3 -> 392.6 | P7: =2.7+93.3+254.8 -> 350.8 | Q7: =+P7 -> 350.8 | R7: =3.6+114.3+236.7 -> 354.6 | S7: =16.848+67.915+209.436 -> 294.199 | T7: =3.299+77.501+203.58 -> 284.38 | U7: =11.966+29.361+207.525 -> 248.852 | V7: =11.966+29.361+207.525 -> 248.852 | W7: =22.958+24.334+213.805 -> 261.097 | X7: =70.869+28.411+177.222 -> 276.502 | Y7: =84.946+28.411+185.136 -> 298.493 | Z7: =Z222 -> 282.04446 | AA7: =AA222 -> 282.04446 | AB7: =AB222 -> 283.26852 | AC7: =AC222 -> 301.99284 | AD7: =AD222 -> 353.06455 | AE7: =AE222 -> 389.50903 | AF7: =AF222 -> 426.21234 | AG7: =AG222 -> 430.72433 | ... AN7: =AN222 -> 640.96734
A8: Contas a Receber | B8: 7.7 | C8: 10.36 | D8: 8 | E8: 12.6 | F8: 9.9 | G8: =+F8 -> 9.9 | H8: 12.28 | I8: 8 | J8: 10.9 | K8: 14.1 | L8: =+K8 -> 14.1 | M8: 10.59 | N8: 11 | O8: 13.9 | P8: 16.7 | Q8: =+P8 -> 16.7 | R8: 10.6 | S8: 14.311 | T8: 17.088 | U8: 18.218 | V8: 18.218 | W8: 11.227 | X8: 17.666 | Y8: 17.749 | Z8: =Z112 -> 19.398964 | AA8: =+AA112 -> 19.398964 | AB8: =+AB112 -> 22.337133 | AC8: =+AC112 -> 25.282708 | AD8: =+AD112 -> 29.252381 | AE8: =+AE112 -> 32.641613 | AF8: =+AF112 -> 36.157966 | AG8: =+AG112 -> 39.371979 | AH8: =+AH112 -> 42.841738 | ... AN8: =+AN112 -> 68.85064
A9: Tributos a Recuperar | B9: 0.2 | C9: 0 | D9: 1.9 | E9: 1.3 | F9: 1.8 | G9: =+F9 -> 1.8 | H9: 2 | I9: 1.9 | J9: 1.9 | K9: 3.8 | L9: =+K9 -> 3.8 | M9: 4.4 | N9: 5.3 | O9: 5.2 | P9: 5.4 | Q9: =+P9 -> 5.4 | R9: 6.1 | S9: 11.082 | T9: 11.211 | U9: 0.313 | V9: 0.313 | W9: 0.382 | X9: 0.312 | Y9: 0.324 | Z9: =Z115 -> 0.324 | AA9: =+AA115 -> 0.324 | AB9: =+AB115 -> 16.58172 | AC9: =+AC115 -> 16.58172 | AD9: =+AD115 -> 16.58172 | AE9: =+AE115 -> 16.58172 | AF9: =+AF115 -> 16.58172 | AG9: =+AG115 -> 16.58172 | AH9: =+AH115 -> 16.58172 | ... AN9: =+AN115 -> 16.58172
A10: Outros | B10: 1.55 | C10: 2 | D10: 1.3 | E10: 2 | F10: =41.17-F9-F8-F7 -> 2.17 | G10: =+F10 -> 2.17 | H10: 3 | I10: 1 | J10: =83.57-J9-J8-J7 -> 7.87 | K10: =70.6-K9-K8-K7 -> 4.8 | L10: =+K10 -> 4.8 | M10: =55.54-53 -> 2.54 | N10: 2 | O10: 3.8 | P10: =2+1.2 -> 3.2 | Q10: =+P10 -> 3.2 | R10: 3 | S10: =1.929+1.996 -> 3.925 | T10: =1.974+0.832 -> 2.806 | U10: =0.788+1.572 -> 2.36 | V10: =0.788+1.572 -> 2.36 | W10: =0.825+1.16 -> 1.985 | X10: =0.441+1.158 -> 1.599 | Y10: =2.039+1.835 -> 3.874 | Z10: =Z118 -> 4.2341306 | AA10: =+AA118 -> 4.2341306 | AB10: =+AB118 -> 4.9638074 | AC10: =+AC118 -> 5.6183797 | AD10: =+AD118 -> 6.5005292 | AE10: =+AE118 -> 7.2536918 | AF10: =+AF118 -> 8.0351036 | AG10: =+AG118 -> 8.7493286 | AH10: =+AH118 -> 9.5203863 | ... AN10: =+AN118 -> 15.300142
A12: Realizável a Longo Prazo | B12: 5.9 | C12: 4 | D12: 17.388 | E12: 5.5 | F12: 11.2 | G12: =+F12 -> 11.2 | H12: 8.9 | I12: 17.4 | J12: 18.7 | K12: 18.7 | L12: =+K12 -> 18.7 | M12: 21 | N12: 25.1 | O12: =3.7+22.7+1.8 -> 28.2 | P12: =27+0.24 -> 27.24 | Q12: =+P12 -> 27.24 | R12: 32.8 | S12: =37.251+0.179 -> 37.43 | T12: =40.019+0.318 -> 40.337 | U12: =13.311+46.207+0.374 -> 59.892 | V12: =13.311+46.207+0.374 -> 59.892 | W12: =63.703+0.348+13.312 -> 77.363 | X12: =74.128+0.461+15.679 -> 90.268 | Y12: =82.228+0.454+15.69 -> 98.372 | Z12: =Y12 -> 98.372 | AA12: =Z12 -> 98.372 | AB12: =AA12 -> 98.372 | AC12: =+AB12 -> 98.372 | AD12: =+AC12 -> 98.372 | AE12: =+AD12 -> 98.372 | AF12: =+AE12 -> 98.372 | AG12: =+AF12 -> 98.372 | AH12: =+AG12 -> 98.372 | AI12: =+AH12 -> 98.372 | AJ12: =+AI12 -> 98.372 | ... AN12: =+AM12 -> 98.372
A14: Ativos Fixos | B14: 717.4 | C14: =+C15+C16 -> 718.09 | D14: =+D15+D16 -> 764.22 | E14: =+E15+E16 -> 729.95 | F14: =+F15+F16 -> 740 | G14: =+G15+G16 -> 740 | H14: =+H15+H16 -> 751.04 | I14: =+I15+I16 -> 764.3 | J14: =+J15+J16 -> 791.7 | ... AN14: =+AN15+AN16 -> 1773.1206
A15: Imobilizado | B15: 1.6 | C15: 1.6 | D15: 8.87 | E15: 3.3 | F15: 6.5 | G15: =+F15 -> 6.5 | H15: 7.6 | I15: 8.9 | J15: 9.3 | K15: 9.4 | L15: =+K15 -> 9.4 | M15: 8.9 | N15: 8.7 | O15: 8.4 | P15: 9 | Q15: =+P15 -> 9 | R15: 9.6 | S15: 9.628 | T15: 10.214 | U15: 10.615 | V15: 10.615 | W15: 11.382 | X15: 11.707 | Y15: 11.432 | Z15: =Y15 -> 11.432 | AA15: =Z15 -> 11.432 | AB15: =AA15 -> 11.432 | AC15: =AB15 -> 11.432 | AD15: =AC15 -> 11.432 | AE15: =AD15 -> 11.432 | AF15: =AE15 -> 11.432 | AG15: =AF15 -> 11.432 | ... AN15: =AM15 -> 11.432
A16: Intangível | B16: 715.8 | C16: 716.49 | D16: 755.35 | E16: 726.65 | F16: 733.5 | G16: =+F16 -> 733.5 | H16: 743.44 | I16: 755.4 | J16: 782.4 | K16: 811.78 | L16: =+K16 -> 811.78 | M16: 838.98 | N16: 885.2 | O16: 911.9 | P16: 932.9 | Q16: =+P16 -> 932.9 | R16: 960.4 | S16: 994.155 | T16: 1033.605 | U16: 1064.798 | V16: 1064.798 | W16: 1073.348 | X16: 1083.925 | Y16: 1100.665 | Z16: =+Z83 -> 1138.503 | AA16: =+AA83 -> 1138.503 | AB16: =+AB83 -> 1220.1741 | AC16: =+AC83 -> 1298.8316 | AD16: =+AD83 -> 1335.996 | AE16: =+AE83 -> 1372.1336 | AF16: =+AF83 -> 1408.0311 | AG16: =+AG83 -> 1471.1904 | ... AN16: =+AN83 -> 1761.6886
A18: Passivo Total | B18: 807.89 | C18: =+C20+C28+C34 -> 814.37 | D18: =+D20+D28+D34 -> 796.559 | E18: =+E20+E28+E34 -> 825.19 | F18: =+F20+F28+F34 -> 792.37 | G18: =+G20+G28+G34 -> 792.37 | H18: =+H20+H28+H34 -> 799.6 | I18: =+I20+I28+I34 -> 796.65 | J18: =+J20+J28+J34 -> 893.76 | ... AN18: =+AN20+AN28+AN34 -> 2613.1925
A20: Passivo Circulante | B20: 548.79 | C20: =+SUM(C21:C26) -> 560.67 | D20: =+SUM(D21:D26) -> 546.259 | E20: =+SUM(E21:E26) -> 568.67 | F20: =+SUM(F21:F26) -> 533.17 | G20: =+SUM(G21:G26) -> 533.17 | H20: =+SUM(H21:H26) -> 545.4 | I20: =+SUM(I21:I26) -> 546.25 | J20: =+SUM(J21:J26) -> 644.2 | ... AN20: =+SUM(AN21:AN26) -> 146.16626
A21: Fornecedores | B21: 9.9 | C21: 7.9 | D21: 18.149 | E21: 9.4 | F21: 21.2 | G21: =+F21 -> 21.2 | H21: 24.9 | I21: 18.1 | J21: 14.5 | K21: 20.2 | L21: =+K21 -> 20.2 | M21: 27.8 | N21: 29.6 | O21: 28.1 | P21: 22.6 | Q21: =+P21 -> 22.6 | R21: 24.2 | S21: 33.684 | T21: 35.292 | U21: 34.735 | V21: 34.735 | W21: 25.638 | X21: =22.108 -> 22.108 | Y21: 28.861 | Z21: =Z121 -> 31.543945 | AA21: =+AA121 -> 31.543945 | AB21: =+AB121 -> 37.044575 | AC21: =+AC121 -> 41.929606 | AD21: =+AD121 -> 48.513031 | AE21: =+AE121 -> 54.133834 | AF21: =+AF121 -> 59.965461 | AG21: =+AG121 -> 65.295676 | AH21: =+AH121 -> 71.05003 | ... AN21: =+AN121 -> 114.18398
A22: Dívida CP | B22: 449.47 | C22: 466.37 | D22: 518.55 | E22: 504.1 | F22: 481.4 | G22: =+F22 -> 481.4 | H22: 501.1 | I22: 518.55 | J22: 602.1 | K22: 603.6 | L22: =+K22 -> 603.6 | M22: 604.9 | N22: 607.9 | O22: =51.97 -> 51.97 | P22: =37.8+3.3 -> 41.1 | Q22: =+P22 -> 41.1 | R22: 54 | S22: 3.123 | T22: 26.48 | U22: =3.911 -> 3.911 | V22: =3.911 -> 3.911 | W22: 26.774 | X22: =4.152 -> 4.152 | Y22: =25.267 -> 25.267 | Z22: =-AB158-AB159 -> 0 | AA22: =-AB158-AB159 -> 0 | AB22: =-AC158-AC159 -> 7.029 | AC22: =-AD158-AD159 -> 37.3815 | AD22: =-AE158-AE159 -> 57.51 | AE22: =-AF158-AF159 -> 68.2665 | AF22: =-AG158-AG159 -> 75.0825 | AG22: =-AH158-AH159 -> 90.099 | AH22: =-AI158-AI159 -> 112.251 | ... AN22: =-AO158-AO159 -> 0
A23: Derivativos | B23: 0 | C23: 0 | D23: 0 | E23: 0 | F23: 0 | G23: =+F23 -> 0 | H23: 0 | I23: 0 | J23: 6.2 | K23: 23.4 | L23: =+K23 -> 23.4 | M23: 30.2 | N23: 34.9 | O23: 0 | P23: 0 | Q23: =+P23 -> 0 | R23: 0 | S23: 0 | T23: 0 | U23: 0 | V23: 0 | W23: 0 | X23: 0 | Y23: 0 | Z23: 0 | AA23: 0 | AB23: 0 | AC23: 0 | AD23: 0 | AE23: 0 | AF23: 0 | AG23: 0 | AH23: 0 | AI23: 0 | AJ23: 0 | AK23: 0 | AL23: 0 | AM23: 0 | AN23: 0
A24: Provisões Sociais e Trabalhistas | B24: 2.1 | C24: 1.4 | D24: 3.2 | E24: 2 | F24: 3.5 | G24: =+F24 -> 3.5 | H24: 3.3 | I24: 3.2 | J24: 4 | K24: 3.6 | L24: =+K24 -> 3.6 | M24: 2.4 | N24: 3.4 | O24: 4 | P24: =2.2+3.7 -> 5.9 | Q24: =+P24 -> 5.9 | R24: =1.9+2.4 -> 4.3 | S24: =3.645+2.169 -> 5.814 | T24: =4.371+1.974 -> 6.345 | U24: =1.911+4.423 -> 6.334 | V24: =1.911+4.423 -> 6.334 | W24: 5.974 | X24: =4.607+1.994 -> 6.601 | Y24: =4.359+2.601 -> 6.96 | Z24: =Z124 -> 7.6070081 | AA24: =+AA124 -> 7.6070081 | AB24: =+AB124 -> 7.4457111 | AC24: =+AC124 -> 5.6183797 | AD24: =+AD124 -> 6.5005292 | AE24: =+AE124 -> 7.2536918 | AF24: =+AF124 -> 8.0351036 | AG24: =+AG124 -> 8.7493286 | AH24: =+AH124 -> 9.5203863 | ... AN24: =+AN124 -> 15.300142
A25: Provisão para Manutenção | B25: 84.7 | C25: 83 | D25: 3.36 | E25: 51.17 | F25: 23.2 | G25: =+F25 -> 23.2 | H25: 13.1 | I25: 3.4 | J25: 9.7 | K25: 3.6 | L25: =+K25 -> 3.6 | M25: 3.8 | N25: 7.1 | O25: 7.1 | P25: 0.8 | Q25: =+P25 -> 0.8 | R25: 0.9 | S25: 0.971 | T25: 0.997 | U25: 1.067 | V25: 1.067 | W25: 1.224 | X25: 1.322 | Y25: 1.382 | Z25: =+Y25 -> 1.382 | AA25: =+Z25 -> 1.382 | AB25: =+AA25 -> 1.382 | AC25: =+AB25 -> 1.382 | AD25: =+AC25 -> 1.382 | AE25: =+AD25 -> 1.382 | AF25: =+AE25 -> 1.382 | AG25: =+AF25 -> 1.382 | ... AN25: =+AM25 -> 1.382
A26: Outros | B26: 2.62 | C26: 2 | D26: 3 | E26: 2 | F26: =533.17-SUM(F21:F25) -> 3.87 | G26: =+F26 -> 3.87 | H26: 3 | I26: 3 | J26: =644.7-637 -> 7.7 | K26: =658.3-SUM(K21:K25) -> 3.9 | L26: =+K26 -> 3.9 | M26: =672.544-SUM(M21:M25) -> 3.444 | N26: 2.8 | O26: 3 | P26: 1 | Q26: =+P26 -> 1 | R26: 1 | S26: =45.667-SUM(S21:S25) -> 2.075 | T26: =69.903-SUM(T21:T25) -> 0.789 | U26: =0.229+0.267 -> 0.496 | V26: =0.229+0.267 -> 0.496 | W26: =2.04+0.487 -> 2.527 | X26: =0.468 -> 0.468 | Y26: =0.762 -> 0.762 | Z26: =+Z129 -> 0.83283623 | AA26: =+AA129 -> 0.83283623 | AB26: =+AB129 -> 4.9638074 | AC26: =+AC129 -> 5.6183797 | AD26: =+AD129 -> 6.5005292 | AE26: =+AE129 -> 7.2536918 | AF26: =+AF129 -> 8.0351036 | AG26: =+AG129 -> 8.7493286 | ... AN26: =+AN129 -> 15.300142
A28: Exigível de Longo Prazo | B28: 40.5 | C28: =+SUM(C29:C32) -> 38.7 | D28: =+SUM(D29:D32) -> 52.3 | E28: =+SUM(E29:E32) -> 45.35 | F28: =+SUM(F29:F32) -> 51.8 | G28: =+SUM(G29:G32) -> 51.8 | H28: =+SUM(H29:H32) -> 49.2 | I28: =+SUM(I29:I32) -> 52.4 | J28: =+SUM(J29:J32) -> 56.66 | ... AN28: =+SUM(AN29:AN32) -> 229.93512
A29: Dívida LP | B29: 0 | C29: 0 | D29: 0 | E29: 0 | F29: 0 | G29: =+F29 -> 0 | H29: 0 | I29: 0 | J29: 0 | K29: 0 | L29: =+K29 -> 0 | M29: 0 | N29: 0 | O29: 1020.8 | P29: 1027 | Q29: =+P29 -> 1027 | R29: 1056.6 | S29: 1073.856 | T29: 1082.87 | U29: 1103.321 | V29: 1103.321 | W29: 1144.89 | X29: 1175.374 | Y29: =1199.375 -> 1199.375 | Z29: =+Z136-Z22-Z177 -> 1236.7545 | AA29: =+AA136-AA22-AA177 -> 1236.7545 | AB29: =+AB136-AB22-AB177 -> 1323.8257 | AC29: =+AC136-AC22-AC177 -> 1352.3823 | AD29: =+AD136-AD22-AD177 -> 1343.6526 | AE29: =+AE136-AE22-AE177 -> 1303.2078 | AF29: =+AF136-AF22-AF177 -> 1244.1753 | AG29: =+AG136-AG22-AG177 -> 1159.5906 | ... AN29: =+AN136-AN22-AN177 -> 56.557868
A30: Provisões | B30: 6.5 | C30: 3.7 | D30: 9.3 | E30: 8.2 | F30: 10.4 | G30: =+F30 -> 10.4 | H30: 7 | I30: 9.4 | J30: 12.49 | K30: 19.2 | L30: =+K30 -> 19.2 | M30: 23.45 | N30: 28.3 | O30: 32.77 | P30: 36.3 | Q30: =+P30 -> 36.3 | R30: 41.9 | S30: 36.728 | T30: 41.848 | U30: 47.289 | V30: 47.289 | W30: 54.569 | X30: 59.43 | Y30: 68.519 | Z30: =+Z102 -> 72.595925 | AA30: =+AA102 -> 72.595925 | AB30: =+AB102 -> 75.877617 | AC30: =+AC102 -> 83.19062 | AD30: =+AD102 -> 86.462461 | AE30: =+AE102 -> 76.515665 | AF30: =+AF102 -> 79.633797 | AG30: =+AG102 -> 72.958486 | ... AN30: =+AN102 -> 100.23925
A31: Mútuos a Pagar | B31: 34 | C31: 35 | D31: 40 | E31: 37.15 | F31: 38.2 | G31: =+F31 -> 38.2 | H31: 39.2 | I31: 40 | J31: 40.87 | K31: 41.6 | L31: =+K31 -> 41.6 | M31: 42.33 | N31: 43.1 | O31: 44.1 | P31: 45.2 | Q31: =+P31 -> 45.2 | R31: 46.3 | S31: 57.362 | T31: 59.653 | U31: 62.229 | V31: 62.229 | W31: 64.84 | X31: 69.946 | Y31: 70.84 | Z31: =+Y31 -> 70.84 | AA31: =+Z31 -> 70.84 | AB31: =+AA31 -> 70.84 | AC31: =+AB31 -> 70.84 | AD31: =+AC31 -> 70.84 | AE31: =+AD31 -> 70.84 | AF31: =+AE31 -> 70.84 | AG31: =+AF31 -> 70.84 | ... AN31: =+AM31 -> 70.84
A32: Outros | B32: 0 | C32: 0 | D32: 3 | E32: 0 | F32: 3.2 | G32: =+F32 -> 3.2 | H32: 3 | I32: 3 | J32: =56.3-53 -> 3.3 | K32: 2.9 | L32: =+K32 -> 2.9 | M32: =68.66-M31-M30-M29 -> 2.88 | N32: 3.4 | O32: 1 | P32: 2.7 | Q32: =+P32 -> 2.7 | R32: 2 | S32: =1170.529-SUM(S29:S31) -> 2.583 | T32: =1186.896-SUM(T29:T31) -> 2.525 | U32: 2.468 | V32: 2.468 | W32: 2.412 | X32: 0 | Y32: 2.298 | Z32: =+Y32 -> 2.298 | AA32: =+Z32 -> 2.298 | AB32: =+AA32 -> 2.298 | AC32: =+AB32 -> 2.298 | AD32: =+AC32 -> 2.298 | AE32: =+AD32 -> 2.298 | AF32: =+AE32 -> 2.298 | AG32: =+AF32 -> 2.298 | ... AN32: =+AM32 -> 2.298
A34: Patrimônio Líquido | B34: 218.6 | C34: 215 | D34: 198 | E34: 211.17 | F34: 207.4 | G34: =+F34 -> 207.4 | H34: 205 | I34: 198 | J34: 192.9 | K34: 188.2 | L34: =+K34 -> 188.2 | M34: 183 | N34: 181.4 | O34: 170.9 | P34: 163 | Q34: =+P34 -> 163 | R34: 145.4 | S34: 148.534 | T34: 142.842 | U34: 143.198 | V34: 143.198 | W34: 107.936 | X34: 142.578 | Y34: 126.645 | Z34: =+Y34+Z78+Z211+Z216+Z101 -> 130.45438 | AA34: =Z34 -> 130.45438 | AB34: =+AA34+AB78+AB211+AB216+AB101 -> 126.42285 | AC34: =+AB34+AC78+AC211+AC216+AC101 -> 157.4705 | AD34: =+AC34+AD78+AD211+AD216+AD101 -> 227.54001 | AE34: =+AD34+AE78+AE211+AE216+AE101 -> 336.77244 | AF34: =+AE34+AF78+AF211+AF216+AF101 -> 455.37498 | AG34: =+AF34+AG78+AG211+AG216+AG101 -> 596.45935 | AH34: =+AG34+AH78+AH211+AH216+AH101 -> 740.78736 | AI34: =+AH34+AI78+AI211+AI216+AI101 -> 921.14638 | ... AN34: =+AM34+AN78+AN211+AN216+AN101 -> 2237.0911
A36: Check | B36: =+B18-B4 -> 0.04 | C36: =+C18-C4 -> -0.08 | D36: =+D18-D4 -> -0.149 | E36: =+E18-E4 -> -0.16 | F36: =+F18-F4 -> 0 | G36: =+G18-G4 -> 0 | H36: =+H18-H4 -> 0.21 | I36: =+I18-I4 -> 0.15 | ... AN36: =+AN18-AN4 -> 0
A38: Demonstração de Resultados (R$ mm) | B38: =+B3 -> 2010 | C38: =+C3 -> 1T11 | D38: =+D3 -> 2T11 | E38: =+E3 -> 3T11 | F38: =+F3 -> 4T11 | G38: =+G3 -> 2011 | H38: =+H3 -> 1T12 | I38: =+I3 -> 2T12 | ... AN38: =+AN3 -> 2028E
A39: Receita Bruta | B39: =+SUM(B40:B42) -> 185.09 | C39: =+SUM(C40:C42) -> 39.06 | D39: =+SUM(D40:D42) -> 52.54 | E39: =+SUM(E40:E42) -> 84.433 | F39: =+SUM(F40:F42) -> 80.577 | G39: =+SUM(G40:G42) -> 256.61 | H39: =+SUM(H40:H42) -> 69.077 | I39: =+SUM(I40:I42) -> 65.513 | ... AN39: =+SUM(AN40:AN42) -> 883.50402
A40: -- Receita com Pedágio | B40: 147.1 | C40: 35.3 | D40: =73-C40 -> 37.7 | E40: 43.36 | F40: =+G40-SUM(C40:E40) -> 42.32 | G40: 158.68 | H40: 40 | I40: =79.8-H40 -> 39.8 | J40: =126-I40-H40 -> 46.2 | K40: =+L40-SUM(H40:J40) -> 46.4 | L40: 172.4 | M40: 43.39 | N40: 44.1 | O40: =138.96-N40-M40 -> 51.47 | P40: =186.1-O40-N40-M40 -> 47.14 | Q40: =+SUM(M40:P40) -> 186.1 | R40: 48.4 | S40: 48.838 | T40: 52.821 | U40: =+V40-SUM(R40:T40) -> 53.393 | V40: 203.452 | W40: 48.391 | X40: =97.631-W40 -> 49.24 | Y40: =151.959-X40-W40 -> 54.328 | Z40: =HLOOKUP(Z38,Tráfego!$AH$14:$CV$35,22,0) -> 59.378381 | AA40: =HLOOKUP(AA38,Tráfego!$AI$14:$CV$35,22,0) -> 211.33738 | AB40: =HLOOKUP(AB38,Tráfego!$AI$14:$CV$35,22,0) -> 248.19037 | AC40: =HLOOKUP(AC38,Tráfego!$AI$14:$CV$35,22,0) -> 280.91898 | AD40: =HLOOKUP(AD38,Tráfego!$AI$14:$CV$35,22,0) -> 325.02646 | AE40: =HLOOKUP(AE38,Tráfego!$AI$14:$CV$35,22,0) -> 362.68459 | AF40: =HLOOKUP(AF38,Tráfego!$AI$14:$CV$35,22,0) -> 401.75518 | AG40: =HLOOKUP(AG38,Tráfego!$AI$14:$CV$35,22,0) -> 437.46643 | AH40: =HLOOKUP(AH38,Tráfego!$AI$14:$CV$35,22,0) -> 476.01931 | ... AN40: =HLOOKUP(AN38,Tráfego!$AI$14:$CV$35,22,0) -> 765.00712
A41: -- Receitas Acessórias | B41: 0.52 | C41: 0.1 | D41: =0.2-C41 -> 0.1 | E41: 0.126 | F41: =+G41-SUM(C41:E41) -> 0.254 | G41: 0.58 | H41: 0.077 | I41: =0.3-H41 -> 0.223 | J41: =0.6-I41-H41 -> 0.3 | K41: =+L41-SUM(H41:J41) -> 4.2 | L41: 4.8 | M41: 0.68 | N41: 1.1 | O41: =1.6-N41-M41 -> -0.18 | P41: =5.4-O41-N41-M41 -> 3.8 | Q41: =+SUM(M41:P41) -> 5.4 | R41: 0.4 | S41: 2.722 | T41: 1.56 | U41: =+V41-SUM(R41:T41) -> 1.558 | V41: 6.24 | W41: 0.392 | X41: =3.284-W41 -> 2.892 | Y41: =5.017-X41-W41 -> 1.733 | Z41: =HLOOKUP(Z38,Tráfego!$AH$14:$CV$38,25,0) -> 1.59695 | AA41: =HLOOKUP(AA38,Tráfego!$AI$14:$CV$38,25,0) -> 6.61395 | AB41: =HLOOKUP(AB38,Tráfego!$AI$14:$CV$38,25,0) -> 6.7197732 | AC41: =HLOOKUP(AC38,Tráfego!$AI$14:$CV$38,25,0) -> 12.80377 | AD41: =HLOOKUP(AD38,Tráfego!$AI$14:$CV$38,25,0) -> 12 | AE41: =HLOOKUP(AE38,Tráfego!$AI$14:$CV$38,25,0) -> 12.135 | AF41: =HLOOKUP(AF38,Tráfego!$AI$14:$CV$38,25,0) -> 12.271519 | AG41: =HLOOKUP(AG38,Tráfego!$AI$14:$CV$38,25,0) -> 12.409573 | AH41: =HLOOKUP(AH38,Tráfego!$AI$14:$CV$38,25,0) -> 12.549181 | ... AN41: =HLOOKUP(AN38,Tráfego!$AI$14:$CV$38,25,0) -> 13.420435
A42: -- Receita com Construção | B42: 37.47 | C42: 3.66 | D42: =18.4-C42 -> 14.74 | E42: 40.947 | F42: =+G42-SUM(C42:E42) -> 38.003 | G42: 97.35 | H42: 29 | I42: =54.49-H42 -> 25.49 | J42: =78.89-I42-H42 -> 24.4 | K42: =+L42-SUM(H42:J42) -> 34.58 | L42: 113.47 | M42: 30.4 | N42: 46.6 | O42: =107.2-N42-M42 -> 30.2 | P42: =142.2-O42-N42-M42 -> 35 | Q42: =+SUM(M42:P42) -> 142.2 | R42: 31.6 | S42: 36.776 | T42: 43.962 | U42: =+V42-SUM(R42:T42) -> 35.496 | V42: 147.834 | W42: 12.537 | X42: =26.967-W42 -> 14.43 | Y42: =45.949-X42-W42 -> 18.982 | Z42: =+Z92 -> 43.558037 | AA42: =+AA92 -> 89.558037 | AB42: =+AB92 -> 104.4411 | AC42: =+AC92 -> 103.061 | AD42: =+AD92 -> 63.141 | AE42: =+AE92 -> 62.857545 | AF42: =+AF92 -> 63.340201 | AG42: =+AG92 -> 91.319903 | ... AN42: =+AN92 -> 105.07647
A44: Impostos | B44: -12.7 | C44: -3 | D44: =-6.3-C44 -> -3.3 | E44: -3.7 | F44: =+G44-SUM(C44:E44) -> -4.2 | G44: -14.2 | H44: -3.44 | I44: =-6.9-H44 -> -3.46 | J44: =-10.89-I44-H44 -> -3.99 | K44: =+L44-SUM(H44:J44) -> -4.58 | L44: -15.47 | M44: -3.8 | N44: -3.9 | O44: =-12.1-N44-M44 -> -4.4 | P44: =-16.6-O44-N44-M44 -> -4.5 | Q44: =+SUM(M44:P44) -> -16.6 | R44: -4.8 | S44: -4.542 | T44: -4.712 | U44: =+V44-SUM(R44:T44) -> -4.895 | V44: -18.949 | W44: -4.227 | X44: =-8.74-W44 -> -4.513 | Y44: =-14.043-X44-W44 -> -5.303 | Z44: =HLOOKUP(Z38,Tráfego!$AH$14:$CV$41,28,0) -> -5.7678633 | AA44: =HLOOKUP(AA38,Tráfego!$AI$14:$CV$41,28,0) -> -19.810863 | AB44: =HLOOKUP(AB38,Tráfego!$AI$14:$CV$41,28,0) -> -23.170264 | AC44: =HLOOKUP(AC38,Tráfego!$AI$14:$CV$41,28,0) -> -26.698168 | AD44: =HLOOKUP(AD38,Tráfego!$AI$14:$CV$41,28,0) -> -30.634294 | AE44: =HLOOKUP(AE38,Tráfego!$AI$14:$CV$41,28,0) -> -34.069531 | AF44: =HLOOKUP(AF38,Tráfego!$AI$14:$CV$41,28,0) -> -37.633293 | AG44: =HLOOKUP(AG38,Tráfego!$AI$14:$CV$41,28,0) -> -40.891845 | AH44: =HLOOKUP(AH38,Tráfego!$AI$14:$CV$41,28,0) -> -44.40883 | ... AN44: =HLOOKUP(AN38,Tráfego!$AI$14:$CV$41,28,0) -> -70.755804
A46: Receita Líquida | B46: =+B39+B44 -> 172.39 | C46: =+C39+C44 -> 36.06 | D46: =+D39+D44 -> 49.24 | E46: =+E39+E44 -> 80.733 | F46: =+F39+F44 -> 76.377 | G46: =+G39+G44 -> 242.41 | H46: =+H39+H44 -> 65.637 | I46: =+I39+I44 -> 62.053 | ... R46: =+R39+R44 -> 75.6 | S46: 83.793 | T46: =T39+T44 -> 93.631 | U46: =U39+U44 -> 85.552 | V46: 338.577 | W46: =W39+W44 -> 57.093 | X46: =X39+X44 -> 62.049 | Y46: =Y39+Y44 -> 69.74 | Z46: =Z39+Z44 -> 98.765505 | AA46: =+AA39+AA44 -> 287.69851 | AB46: =+AB39+AB44 -> 336.18098 | AC46: =+AC39+AC44 -> 370.08558 | AD46: =+AD39+AD44 -> 369.53317 | AE46: =+AE39+AE44 -> 403.6076 | AF46: =+AF39+AF44 -> 439.73361 | AG46: =+AG39+AG44 -> 500.30406 | AH46: =+AH39+AH44 -> 511.85807 | ... AN46: =+AN39+AN44 -> 812.74822
A48: Custos e Despesas | B48: =+SUM(B49:B58) -> -108.89 | C48: =+SUM(C49:C58) -> -21.036 | D48: =+SUM(D49:D58) -> -33.664 | E48: =+SUM(E49:E58) -> -61.807 | F48: =+SUM(F49:F58) -> -61.089 | G48: =+SUM(G49:G58) -> -177.596 | H48: =+SUM(H49:H58) -> -48.913 | I48: =+SUM(I49:I58) -> -47.773 | ... AN48: =+SUM(AN49:AN58) -> -323.38207
A49: -- Pessoal | B49: -14.9 | C49: -3.8 | D49: =-8.2-C49 -> -4.4 | E49: -4.3 | F49: =+G49-SUM(C49:E49) -> -5.5 | G49: -18 | H49: -4.971 | I49: =-10.1-H49 -> -5.129 | J49: -5.1 | K49: =+L49-SUM(H49:J49) -> -4.1 | L49: -19.3 | M49: -4.657 | N49: -5.9 | O49: -5.7 | P49: =-20.1-O49-N49-M49 -> -3.843 | Q49: =+SUM(M49:P49) -> -20.1 | R49: -3.9 | S49: =-8.352-R49 -> -4.452 | T49: =-12.744-S49-R49 -> -4.392 | U49: =V49-SUM(R49:T49) -> -4.661 | V49: =-17.405 -> -17.405 | W49: -4.645 | X49: =-7.454-W49 -> -2.809 | Y49: =-12.213-X49-W49 -> -4.759 | Z49: =+Despesas!R21 -> -4.759 | AA49: =+Despesas!S21 -> -16.972 | AB49: =+Despesas!T21 -> -18.058208 | AC49: =+Despesas!U21 -> -18.961118 | AD49: =+Despesas!V21 -> -19.909174 | AE49: =+Despesas!W21 -> -20.805087 | AF49: =+Despesas!X21 -> -21.741316 | AG49: =+Despesas!Y21 -> -22.719675 | ... AN49: =+Despesas!AF21 -> -30.918339
A50: -- Serviços de Terceiros | B50: -22.76 | C50: -5.5 | D50: =-10.3-C50 -> -4.8 | E50: -6.3 | F50: =+G50-SUM(C50:E50) -> -6.3 | G50: -22.9 | H50: -1.43 | I50: =-10.1-H50 -> -8.67 | J50: -7.5 | K50: =+L50-SUM(H50:J50) -> -7.183 | L50: -24.783 | M50: -3.6 | N50: -0.3 | O50: -4.5 | P50: =-28.011-O50-N50-M50 -> -19.611 | Q50: =+SUM(M50:P50) -> -28.011 | R50: -2.3 | S50: =-4.222-R50 -> -1.922 | T50: =-6.295-S50-R50 -> -2.073 | U50: =V50-SUM(R50:T50) -> -2.017 | V50: -8.312 | W50: -2.296 | X50: =-4.126-W50 -> -1.83 | Y50: =-6.927-X50-W50 -> -2.801 | Z50: =+Despesas!R30 -> -2.3751353 | AA50: =+Despesas!S30 -> -9.3021353 | AB50: =+Despesas!T30 -> -4.4674266 | AC50: =+Despesas!U30 -> -3.0901088 | AD50: =+Despesas!V30 -> -3.2502646 | AE50: =+Despesas!W30 -> -3.2641613 | AF50: =+Despesas!X30 -> -3.2140415 | AG50: =+Despesas!Y30 -> -3.4997315 | ... AN50: =+Despesas!AF30 -> -6.1200569
A51: -- Depreciação e Amortização | B51: -9.8 | C51: -3 | D51: =-6-C51 -> -3 | E51: -2.8 | F51: =+G51-SUM(C51:E51) -> -4 | G51: -12.8 | H51: -3.6 | I51: =-7.3-H51 -> -3.7 | J51: -3.88 | K51: =+L51-SUM(H51:J51) -> -3.42 | L51: -14.6 | M51: -4.26 | N51: -4.35 | O51: -4.6 | P51: =-17.8-O51-N51-M51 -> -4.59 | Q51: =+SUM(M51:P51) -> -17.8 | R51: -5.1 | S51: =-9.573-R51 -> -4.473 | T51: =-14.03-S51-R51 -> -4.457 | U51: =V51-SUM(R51:T51) -> -6.441 | V51: -20.471 | W51: -5.58 | X51: =-11.225-W51 -> -5.645 | Y51: =-16.945-X51-W51 -> -5.72 | Z51: =-Z96 -> -5.72 | AA51: =-AA96 -> -22.665 | AB51: =-AB96 -> -22.770061 | AC51: =-AC96 -> -24.403482 | AD51: =-AD96 -> -25.976632 | AE51: =-AE96 -> -26.719919 | AF51: =-AF96 -> -27.442672 | AG51: =-AG96 -> -28.160622 | ... AN51: =-AN96 -> -33.808411
A52: -- Ônus variável da concessão | B52: -4.4 | C52: -1.06 | D52: =-2.2-C52 -> -1.14 | E52: -1.3 | F52: =+G52-SUM(C52:E52) -> -1.3 | G52: -4.8 | H52: -1.2 | I52: =-2.4-H52 -> -1.2 | J52: -1.39 | K52: =+L52-SUM(H52:J52) -> -1.51 | L52: -5.3 | M52: -1.3 | N52: -1.37 | O52: -0.7 | P52: =-4.479-O52-N52-M52 -> -1.109 | Q52: =+SUM(M52:P52) -> -4.479 | R52: -0.8 | S52: =-1.526-R52 -> -0.726 | T52: =-2.324-S52-R52 -> -0.798 | U52: =V52-SUM(R52:T52) -> -0.814 | V52: -3.138 | W52: -0.799 | X52: =-1.543-W52 -> -0.744 | Y52: =-2.42-X52-W52 -> -0.877 | Z52: =+Despesas!R33 -> -0.89067572 | AA52: =+Despesas!S33 -> -3.3106757 | AB52: =+Despesas!T33 -> -3.7228555 | AC52: =+Despesas!U33 -> -4.2137847 | AD52: =+Despesas!V33 -> -4.8753969 | AE52: =+Despesas!W33 -> -5.4402688 | AF52: =+Despesas!X33 -> -6.0263277 | AG52: =+Despesas!Y33 -> -6.5619965 | ... AN52: =+Despesas!AF33 -> -11.475107
A53: -- Manutenção e conservação | B53: -8.56 | C53: -2.07 | D53: =-4.7-C53 -> -2.63 | E53: -3.38 | F53: =+G53-SUM(C53:E53) -> -2.92 | G53: -11 | H53: -5.7 | I53: =-5.2-H53 -> 0.5 | J53: -1.9 | K53: =+L53-SUM(H53:J53) -> -2 | L53: -9.1 | M53: -6.6 | N53: -4.8 | O53: -10.6 | P53: =-13.225-O53-N53-M53 -> 8.775 | Q53: =+SUM(M53:P53) -> -13.225 | R53: -7 | S53: =-13.93-R53 -> -6.93 | T53: =-26.12-S53-R53 -> -12.19 | U53: =V53-SUM(R53:T53) -> -10.142 | V53: -36.262 | W53: -10.379 | X53: =-21.955-W53 -> -11.576 | Y53: =-31.971-X53-W53 -> -10.016 | Z53: =+Despesas!R36 -> -9.75036 | AA53: =+Despesas!S36 -> -41.72136 | AB53: =+Despesas!T36 -> -33.875832 | AC53: =+Despesas!U36 -> -35.569624 | AD53: =+Despesas!V36 -> -37.348105 | AE53: =+Despesas!W36 -> -39.028769 | AF53: =+Despesas!X36 -> -40.785064 | AG53: =+Despesas!Y36 -> -42.620392 | ... AN53: =+Despesas!AF36 -> -58.000465
A54: -- Custo de construção | B54: -37.47 | C54: -3.65 | D54: =-18.4-C54 -> -14.75 | E54: -40.947 | F54: =+G54-SUM(C54:E54) -> -38.003 | G54: -97.35 | H54: -29 | I54: =-54.49-H54 -> -25.49 | J54: -24.4 | K54: =+L54-SUM(H54:J54) -> -34.58 | L54: -113.47 | M54: -30.43 | N54: -46.6 | O54: -30.2 | P54: =-142.2-O54-N54-M54 -> -34.97 | Q54: =+SUM(M54:P54) -> -142.2 | R54: -31.7 | S54: =-68.429-R54 -> -36.729 | T54: =-112.391-S54-R54 -> -43.962 | U54: =V54-SUM(R54:T54) -> -35.442 | V54: -147.833 | W54: -12.537 | X54: =-26.967-W54 -> -14.43 | Y54: =-45.949-X54-W54 -> -18.982 | Z54: =-Z42 -> -43.558037 | AA54: =-AA42 -> -89.558037 | AB54: =-AB42 -> -104.4411 | AC54: =-AC42 -> -103.061 | AD54: =-AD42 -> -63.141 | AE54: =-AE42 -> -62.857545 | AF54: =-AF42 -> -63.340201 | AG54: =-AG42 -> -91.319903 | ... AN54: =-AN42 -> -105.07647
A55: -- Serviços de manutenção em rodovias | B55: -1.7 | C55: -0.756 | D55: =-1.5-C55 -> -0.744 | E55: -0.78 | F55: =+G55-SUM(C55:E55) -> 0.88 | G55: -1.4 | H55: -1.695 | I55: =-3.49-H55 -> -1.795 | J55: -3.1 | K55: =+L55-SUM(H55:J55) -> -2.4 | L55: -8.99 | M55: -4.2 | N55: -4.3 | O55: -4.4 | P55: =-18.4-O55-N55-M55 -> -5.5 | Q55: =+SUM(M55:P55) -> -18.4 | R55: -5.6 | S55: =-0.414-R55 -> 5.186 | T55: =-5.534-S55-R55 -> -5.12 | U55: =V55-SUM(R55:T55) -> -5.441 | V55: -10.975 | W55: -7.28 | X55: =-12.141-W55 -> -4.861 | Y55: =-21.23-X55-W55 -> -9.089 | Z55: =-Z101 -> -2.6949246 | AA55: =-AA101 -> -23.694925 | AB55: =-AB101 -> -24.844862 | AC55: =-AC101 -> -28.125003 | AD55: =-AD101 -> -29.840841 | AE55: =-AE101 -> -31.439964 | AF55: =-AF101 -> -31.46193 | AG55: =-AG101 -> -33.196376 | ... AN55: =-AN101 -> -60.811917
A56: -- Seguros e Garantias | B56: -5.9 | C56: -0.9 | D56: 0.2 | E56: -2 | F56: =+G56-SUM(C56:E56) -> 0.22 | G56: -2.48 | H56: -0.506 | I56: 0 | J56: -3 | K56: =+L56-SUM(H56:J56) -> -1.794 | L56: -5.3 | M56: -2 | N56: -2 | O56: -0.9 | P56: =-5.9-O56-N56-M56 -> -1 | Q56: =+SUM(M56:P56) -> -5.9 | R56: -0.9 | S56: =-1.87-R56 -> -0.97 | T56: =-1.448-S56-R56 -> 0.422 | U56: =V56-SUM(R56:T56) -> -1.859 | V56: -3.307 | W56: -0.701 | X56: =-1.403-W56 -> -0.702 | Y56: =-1.889-X56-W56 -> -0.486 | Z56: =+Despesas!R39 -> -1.458 | AA56: =+Despesas!S39 -> -3.347 | AB56: =+Despesas!T39 -> -1.9864913 | AC56: =+Despesas!U39 -> -2.0858158 | AD56: =+Despesas!V39 -> -2.1901066 | AE56: =+Despesas!W39 -> -2.2886614 | AF56: =+Despesas!X39 -> -2.3916512 | AG56: =+Despesas!Y39 -> -2.4992755 | ... AN56: =+Despesas!AF39 -> -3.4011686
A57: -- Honorários da administração | B57: -1.1 | C57: 0.4 | D57: 0 | E57: 0 | F57: =+G57-SUM(C57:E57) -> -1.766 | G57: -1.366 | H57: 0 | I57: -0.3 | J57: 0.4 | K57: =+L57-SUM(H57:J57) -> -1.4 | L57: -1.3 | M57: 0 | N57: 0 | O57: 0 | P57: =-1.7-O57-N57-M57 -> -1.7 | Q57: =+SUM(M57:P57) -> -1.7 | R57: 0 | S57: =-0.957-R57 -> -0.957 | T57: =-1.448-S57-R57 -> -0.491 | U57: =V57-SUM(R57:T57) -> -0.491 | V57: -1.939 | W57: -0.495 | X57: =-1.014-W57 -> -0.519 | Y57: =-1.513-X57-W57 -> -0.499 | Z57: =+Despesas!R42 -> -0.41564867 | AA57: =+Despesas!S42 -> -1.9286487 | AB57: =+Despesas!T42 -> -2.2337133 | AC57: =+Despesas!U42 -> -1.9664329 | AD57: =+Despesas!V42 -> -2.112672 | AE57: =+Despesas!W42 -> -2.1761075 | AF57: =+Despesas!X42 -> -2.4105311 | AG57: =+Despesas!Y42 -> -2.6247986 | ... AN57: =+Despesas!AF42 -> -4.5900427
A58: -- Outros | B58: -2.3 | C58: -0.7 | D58: =-3.1-C58 -> -2.4 | E58: 0 | F58: =+G58-SUM(C58:E58) -> -2.4 | G58: =-1.4-4.1 -> -5.5 | H58: -0.811 | I58: =-2.8-H58 -> -1.989 | J58: 0.7 | K58: =+L58-SUM(H58:J58) -> -1.5 | L58: =-0.2-3.4 -> -3.6 | M58: -0.58 | N58: -1.6 | O58: 0.1 | P58: =-2.4-O58-N58-M58 -> -0.32 | Q58: =+SUM(M58:P58) -> -2.4 | R58: -1.4 | S58: =-1.981-R58 -> -0.581 | T58: =-2.994-S58-R58 -> -1.013 | U58: =V58-SUM(R58:T58) -> -0.856 | V58: =-3.862+0.012 -> -3.85 | W58: -2.77 | X58: =-2.9-W58 -> -0.13 | Y58: =-4.323-X58-W58 -> -1.423 | Z58: =+Despesas!R45 -> 0 | AA58: =+Despesas!S45 -> -4.323 | AB58: =+Despesas!T45 -> -4.4674266 | AC58: =+Despesas!U45 -> -4.2137847 | AD58: =+Despesas!V45 -> -4.5503704 | AE58: =+Despesas!W45 -> -4.7148996 | AF58: =+Despesas!X45 -> -4.8210622 | AG58: =+Despesas!Y45 -> -5.2495972 | ... AN58: =+Despesas!AF45 -> -9.1800854
A60: EBIT | B60: =+B46+B48 -> 63.5 | C60: =+C46+C48 -> 15.024 | D60: =+D46+D48 -> 15.576 | E60: =+E46+E48 -> 18.926 | F60: =+F46+F48 -> 15.288 | G60: =+G46+G48 -> 64.814 | H60: =+H46+H48 -> 16.724 | I60: =+I46+I48 -> 14.28 | ... AN60: =+AN46+AN48 -> 489.36615
A62: =+A51 -> -- Depreciação e Amortização | B62: =-B51 -> 9.8 | C62: =-C51 -> 3 | D62: =-D51 -> 3 | E62: =-E51 -> 2.8 | F62: =-F51 -> 4 | G62: =-G51 -> 12.8 | H62: =-H51 -> 3.6 | I62: =-I51 -> 3.7 | ... P62: =-P51 -> 4.59 | Q62: =+SUM(M62:P62) -> 17.8 | R62: =-R51 -> 5.1 | S62: =-S51 -> 4.473 | T62: =-T51 -> 4.457 | U62: =-U51 -> 6.441 | V62: =-V51 -> 20.471 | W62: =-W51 -> 5.58 | X62: =-X51 -> 5.645 | Y62: =-Y51 -> 5.72 | ... AN62: =-AN51 -> 33.808411
A63: =+A55 -> -- Serviços de manutenção em rodovias | B63: =-B55 -> 1.7 | C63: =-C55 -> 0.756 | D63: =-D55 -> 0.744 | E63: =-E55 -> 0.78 | F63: =-F55 -> -0.88 | G63: =-G55 -> 1.4 | H63: =-H55 -> 1.695 | I63: =-I55 -> 1.795 | ... P63: =-P55 -> 5.5 | Q63: =+SUM(M63:P63) -> 18.4 | R63: =-R55 -> 5.6 | S63: =-S55 -> -5.186 | T63: =-T55 -> 5.12 | U63: =-U55 -> 5.441 | V63: =-V55 -> 10.975 | W63: =-W55 -> 7.28 | X63: =-X55 -> 4.861 | Y63: =-Y55 -> 9.089 | ... AN63: =-AN55 -> 60.811917
A65: EBITDA | B65: =+B63+B62+B60 -> 75 | C65: =+C63+C62+C60 -> 18.78 | D65: =+D63+D62+D60 -> 19.32 | E65: =+E63+E62+E60 -> 22.506 | F65: =+F63+F62+F60 -> 18.408 | G65: =+G63+G62+G60 -> 79.014 | H65: =+H63+H62+H60 -> 22.019 | I65: =+I63+I62+I60 -> 19.775 | ... AN65: =+AN63+AN62+AN60 -> 583.98648
A66: Margem EBITDA | B66: =+B65/(B46-B42) -> 0.55588497 | C66: =+C65/(C46-C42) -> 0.57962963 | D66: =+D65/(D46-D42) -> 0.56 | E66: =+E65/(E46-E42) -> 0.56567637 | F66: =+F65/(F46-F42) -> 0.4796998 | G66: =+G65/(G46-G42) -> 0.54469875 | H66: =+H65/(H46-H42) -> 0.60100445 | I66: =+I65/(I46-I42) -> 0.5408473 | ... AN66: =+AN65/(AN46-AN42) -> 0.82522227
A68: Resultado Financeiro | B68: =+B69+B70 -> -64.78 | C68: =+C69+C70 -> -19.35 | D68: =+D69+D70 -> -19.4 | E68: =+E69+E70 -> -20.8 | F68: =+F69+F70 -> -21.25 | G68: =+G69+G70 -> -80.8 | H68: =+H69+H70 -> -21.032 | I68: =+I69+I70 -> -22.72 | ... AN68: =+AN69+AN70 -> 24.106454
A69: Despesas Financeiras | B69: -65.18 | C69: 1.87 | D69: 1.9 | E69: 2.1 | F69: =+G69-SUM(C69:E69) -> -94.27 | G69: -88.4 | H69: 0.668 | I69: 1.48 | J69: 0.4 | K69: =+L69-SUM(H69:J69) -> -90.418 | L69: -87.87 | M69: -17.1 | N69: -39.4 | O69: -55.8 | P69: =-140.4-O69-N69-M69 -> -28.1 | Q69: =+P69+O69+N69+M69 -> -140.4 | R69: -48.8 | S69: =-103.987-R69 -> -55.187 | T69: =-138.71-S69-R69 -> -34.723 | U69: =V69-SUM(R69:T69) -> -44.76 | V69: -183.47 | W69: -69.322 | X69: =-126.378-W69 -> -57.056 | Y69: =-175.026-X69-W69 -> -48.648 | Z69: =+Z175 -> -36.663079 | AA69: =+SUM(W69:Z69) -> -211.68908 | AB69: =+AB175 -> -197.14112 | AC69: =+AC175 -> -177.58952 | AD69: =+AD175 -> -174.61402 | AE69: =+AE175 -> -162.03831 | AF69: =+AF175 -> -153.95089 | AG69: =+AG175 -> -144.73354 | AH69: =+AH175 -> -134.11237 | AI69: =+AI175 -> -121.10127 | ... AN69: =+AN175 -> -38.939565
A70: Receitas Financeiras | B70: 0.4 | C70: -21.22 | D70: -21.3 | E70: -22.9 | F70: =+G70-SUM(C70:E70) -> 73.02 | G70: 7.6 | H70: -21.7 | I70: -24.2 | J70: -25.6 | K70: =+L70-SUM(H70:J70) -> 81.28 | L70: 9.78 | M70: 3.8 | N70: 3.3 | O70: 11.1 | P70: =22.4-O70-N70-M70 -> 4.2 | Q70: =+SUM(M70:P70) -> 22.4 | R70: 8.3 | S70: =18.896-R70 -> 10.596 | T70: =26.578-S70-R70 -> 7.682 | U70: =V70-SUM(R70:T70) -> 7.595 | V70: 34.173 | W70: 6.93 | X70: =14.402-W70 -> 7.472 | Y70: =23.927-X70-W70 -> 9.525 | Z70: =+Z171 -> 10.633813 | AA70: =+AA171 -> 34.560813 | AB70: =+AB171 -> 38.076002 | AC70: =+AC171 -> 36.116737 | AD70: =+AD171 -> 38.504087 | AE70: =+AE171 -> 45.01573 | AF70: =+AF171 -> 49.662402 | AG70: =+AG171 -> 54.342074 | ... AN70: =+AN171 -> 63.046019
A72: EBT | B72: =+B60+B68 -> -1.28 | C72: =+C60+C68 -> -4.326 | D72: =+D60+D68 -> -3.824 | E72: =+E60+E68 -> -1.874 | F72: =+F60+F68 -> -5.962 | G72: =+G60+G68 -> -15.986 | H72: =+H60+H68 -> -4.308 | I72: =+I60+I68 -> -8.44 | ... AN72: =+AN60+AN68 -> 513.47261
A74: IR | B74: =+B75+B76 -> 0.409 | C74: =+C75+C76 -> 1.6 | D74: =+D75+D76 -> 1.1 | E74: =+E75+E76 -> 0.6 | F74: =+F75+F76 -> 1.7 | G74: =+G75+G76 -> 5 | H74: =+H75+H76 -> 1.3 | I74: =+I75+I76 -> 2.77 | ... AN74: =+AN75+AN76 -> -174.58069
A75: -- Corrente | B75: -0.372 | C75: 1.6 | D75: 1.1 | E75: 0.6 | F75: =+G75-SUM(C75:E75) -> -3.3 | G75: 0 | H75: 1.3 | I75: 2.77 | J75: 2.77 | K75: =+L75-SUM(H75:J75) -> -6.84 | L75: 0 | M75: 0 | N75: 6.3 | O75: 14.4 | P75: =18.8-O75-N75-M75 -> -1.9 | Q75: =+SUM(M75:P75) -> 18.8 | R75: 5.8 | S75: =10.233-R75 -> 4.433 | T75: =13.001-S75-R75 -> 2.768 | U75: =V75-SUM(R75:T75) -> 6.188 | V75: 19.189 | W75: 17.496 | X75: =27.921-W75 -> 10.425 | Y75: =36.021-X75-W75 -> 8.1 | Z75: =IF(Z195<0,0,-Z195) -> 0 | AA75: =IF(AA195<0,0,-AA195) -> 0 | AB75: =IF(AB195<0,0,-AB195) -> 0 | AC75: =IF(AC195<0,0,-AC195) -> 0 | AD75: =IF(AD195<0,0,-AD195) -> 0 | AE75: =IF(AE195<0,0,-AE195) -> 0 | AF75: =IF(AF195<0,0,-AF195) -> -22.707316 | AG75: =IF(AG195<0,0,-AG195) -> -58.296476 | ... AN75: =IF(AN195<0,0,-AN195) -> -174.58069
A76: -- Diferido | B76: 0.781 | C76: 0 | D76: 0 | E76: 0 | F76: =+G76-SUM(C76:E76) -> 5 | G76: 5 | H76: 0 | I76: 0 | J76: 0 | K76: =+L76-SUM(H76:J76) -> 0.967 | L76: 0.967 | M76: 0 | N76: 0 | O76: 0 | P76: 0 | Q76: =+SUM(M76:P76) -> 0 | R76: 0 | S76: 0 | T76: 0 | U76: =V76-SUM(R76:T76) -> 0 | V76: 0 | W76: 0 | X76: 0 | Y76: 0 | Z76: =+Z197 -> 0 | AA76: =+AA197 -> 0 | AB76: =+AB197 -> 14.87572 | AC76: =+AC197 -> 0 | AD76: =+AD197 -> 0 | AE76: =+AE197 -> 0 | AF76: =+AF197 -> 0 | AG76: =+AG197 -> 0 | ... AN76: =+AN197 -> 0
A78: Resultado do Exercício | B78: =+B72+B74 -> -0.871 | C78: =+C72+C74 -> -2.726 | D78: =+D72+D74 -> -2.724 | E78: =+E72+E74 -> -1.274 | F78: =+F72+F74 -> -4.262 | G78: =+G72+G74 -> -10.986 | H78: =+H72+H74 -> -3.008 | I78: =+I72+I74 -> -5.67 | ... AN78: =+AN72+AN74 -> 338.89192
A80: Dividend Payout | K80: =7.75-6.3 -> 1.45 | O80: =326/AA92 -> 3.6400976 | AE80: 0.25 | AF80: 0.25 | AG80: 0.25 | AH80: 0.25 | AI80: 0.25 | AJ80: =+AI80 -> 0.25 | AK80: =+AJ80 -> 0.25 | AL80: =+AK80 -> 0.25 | AM80: =+AL80 -> 0.25 | AN80: =+AM80 -> 0.25
A82: Intangível e Capex | B82: =+B38 -> 2010 | C82: =+C38 -> 1T11 | D82: =+D38 -> 2T11 | E82: =+E38 -> 3T11 | F82: =+F38 -> 4T11 | G82: =+G38 -> 2011 | H82: =+H38 -> 1T12 | I82: =+I38 -> 2T12 | ... AN82: =+AN38 -> 2028E
A83: =+A16 -> Intangível | B83: =+B16 -> 715.8 | C83: =+C16 -> 716.49 | D83: =+D16 -> 755.35 | E83: =+E16 -> 726.65 | F83: =+F16 -> 733.5 | G83: =+G16 -> 733.5 | H83: =+H16 -> 743.44 | ... P83: =+P16 -> 932.9 | Q83: =+P83 -> 932.9 | R83: =+R16 -> 960.4 | S83: =+S16 -> 994.155 | T83: =+T16 -> 1033.605 | U83: =+U16 -> 1064.798 | V83: =+V16 -> 1064.798 | W83: =+W16 -> 1073.348 | X83: =+X16 -> 1083.925 | Y83: =+Y16 -> 1100.665 | Z83: =+Y83+Z93-Z96 -> 1138.503 | AA83: =+Z83 -> 1138.503 | AB83: =+AA83+AB92-AB96 -> 1220.1741 | AC83: =+AB83+AC92-AC96 -> 1298.8316 | AD83: =+AC83+AD92-AD96 -> 1335.996 | AE83: =+AD83+AE92-AE96 -> 1372.1336 | AF83: =+AE83+AF92-AF96 -> 1408.0311 | AG83: =+AF83+AG92-AG96 -> 1471.1904 | AH83: =+AG83+AH92-AH96 -> 1509.465 | AI83: =+AH83+AI92-AI96 -> 1542.1942 | ... AN83: =+AM83+AN92-AN96 -> 1761.6886
A85: Capex
A86: Ampliações | Q86: 85.94316 | V86: =67.1888637+20 -> 87.188864 | AA86: 30.559196 | AB86: 57.953 | AC86: 36.327 | AD86: 9.253 | AE86: 5.3448314 | AF86: 6.9784278 | AG86: 12.883996 | AH86: 25.912314 | AI86: 7.6991405 | AJ86: 5.1565072 | AK86: 7.1841318 | AL86: 7.5074177 | AM86: 19.614114 | AN86: 30.744094 | AO86: 26.537567 | AP86: 46.281188 | AQ86: 27.740689 | AR86: 22.817923 | AS86: 37.222613
A87: Melhoramentos | Q87: 54.226192 | V87: 56.920901 | AA87: 34.664666 | AB87: 17.617 | AC87: 28.271 | AD87: 25.525 | AE87: 16.08161 | AF87: 24.128359 | AG87: 33.145193 | AH87: 9.9816016 | AI87: 19.724606 | AJ87: 9.679244 | AK87: 1.0177971 | AL87: 23.913982 | AM87: 26.562709 | AN87: 6.3510474 | AO87: 0 | AP87: 0 | AQ87: 0 | AR87: 0 | AS87: 0
A88: Equipamentos, veículos e sistemas de controle | Q88: 2.08692 | V88: 10.424007 | AA88: 4.4285154 | AB88: 5.467 | AC88: 0 | AD88: 1.312 | AE88: 21.391797 | AF88: 13.090888 | AG88: 21.824407 | AH88: 6.87263 | AI88: 0 | AJ88: 13.120945 | AK88: 6.5182326 | AL88: 1.1428021 | AM88: 4.6369949 | AN88: 1.5589309 | AO88: 8.8139302 | AP88: 6.1181298 | AQ88: 20.510517 | AR88: 9.4275969 | AS88: 8.0917451
A89: Desapropriações | Q89: 10.15529 | V89: 4.991217 | AA89: 2.4088986 | AB89: 7.307933 | AC89: 17.651 | AD89: 1.794 | AE89: 0.044343947 | AF89: 3.8896155 | AG89: 5.4190265 | AH89: 1.4153253 | AI89: 0 | AJ89: 0 | AK89: 0 | AL89: 0 | AM89: 0 | AN89: 0 | AO89: 0 | AP89: 0 | AQ89: 0 | AR89: 0 | AS89: 0
A90: Conservação especial | Q90: 13.13811 | V90: 17.698346 | AA90: 17.102831 | AB90: 13.331 | AC90: 19.788 | AD90: 24.799 | AE90: 19.525194 | AF90: 14.762003 | AG90: 17.534281 | AH90: 22.980455 | AI90: 34.934499 | AJ90: 27.803003 | AK90: 30.894835 | AL90: 30.621816 | AM90: 56.491329 | AN90: 65.724279 | AO90: 54.055006 | AP90: 66.449973 | AQ90: 49.415113 | AR90: 53.096091 | AS90: 52.632951
A91: Elementos de segurança | Q91: 1.460844 | V91: 2.1403578 | AA91: 0.39392986 | AB91: 2.76517 | AC91: 1.024 | AD91: 0.458 | AE91: 0.46976869 | AF91: 0.49090828 | AG91: 0.51299916 | AH91: 0.53608412 | AI91: 0.5602079 | AJ91: 0.58541726 | AK91: 0.61176103 | AL91: 0.63929028 | AM91: 0.66805834 | AN91: 0.69812097 | AO91: 0.83252224 | AP91: 0.86998574 | AQ91: 0.9091351 | AR91: 0.95004618 | AS91: 0.99279826
A92: Investimentos Totais | B92: 34.48 | G92: 102.7 | L92: 115.89 | M92: 30.7 | N92: =77.1-M92 -> 46.4 | O92: 36.6 | P92: =+Q92-O92-N92-M92 -> 30.4 | Q92: =1.1+4.9+138.1 -> 144.1 | R92: =32.168+1.053 -> 33.221 | S92: =70.005+1.434-R92 -> 38.218 | T92: =113.543+2.368-S92-R92 -> 44.472 | U92: =V92-SUM(R92:T92) -> 38.071 | V92: =150.835+3.147 -> 153.982 | W92: =13.75+1.147 -> 14.897 | X92: =1.889+28.465-W92 -> 15.457 | Y92: =2.048+50.319-X92-W92 -> 22.013 | Z92: =+AA92-46 -> 43.558037 | AA92: =+SUM(AA86:AA91) -> 89.558037 | AB92: =+SUM(AB86:AB91) -> 104.4411 | AC92: =+SUM(AC86:AC91) -> 103.061 | AD92: =+SUM(AD86:AD91) -> 63.141 | AE92: =+SUM(AE86:AE91) -> 62.857545 | AF92: =+SUM(AF86:AF91) -> 63.340201 | AG92: =+SUM(AG86:AG91) -> 91.319903 | AH92: =+SUM(AH86:AH91) -> 67.69841 | ... AS92: =+SUM(AS86:AS91) -> 98.940107
A93: -- Fluxo de Caixa | Z93: =Z92 -> 43.558037 | AB93: =+AB86+AB87+AB89 -> 82.877933 | AC93: =+AC86+AC87+AC89 -> 82.249 | AD93: =+AD86+AD87+AD89 -> 36.572 | AE93: =+AE86+AE87+AE89 -> 21.470785 | AF93: =+AF86+AF87+AF89 -> 34.996403 | AG93: =+AG86+AG87+AG89 -> 51.448216 | AH93: =+AH86+AH87+AH89 -> 37.309241 | AI93: =+AI86+AI87+AI89 -> 27.423747 | ... AS93: =+AS86+AS87+AS89 -> 37.222613
A94: -- DRE | AB94: =+AB88+AB90+AB91 -> 21.56317 | AC94: =+AC88+AC90+AC91 -> 20.812 | AD94: =+AD88+AD90+AD91 -> 26.569 | AE94: =+AE88+AE90+AE91 -> 41.38676 | AF94: =+AF88+AF90+AF91 -> 28.343799 | AG94: =+AG88+AG90+AG91 -> 39.871687 | AH94: =+AH88+AH90+AH91 -> 30.38917 | AI94: =+AI88+AI90+AI91 -> 35.494707 | ... AS94: =+AS88+AS90+AS91 -> 61.717494
A96: Depreciação | B96: =+B62 -> 9.8 | C96: =+C62 -> 3 | D96: =+D62 -> 3 | E96: =+E62 -> 2.8 | F96: =+F62 -> 4 | G96: =+G62 -> 12.8 | H96: =+H62 -> 3.6 | I96: =+I62 -> 3.7 | ... P96: =+P62 -> 4.59 | Q96: =+SUM(M96:P96) -> 17.8 | R96: =+R62 -> 5.1 | S96: =+S62 -> 4.473 | T96: =+T62 -> 4.457 | U96: =+U62 -> 6.441 | V96: =+V62 -> 20.471 | W96: =+W62 -> 5.58 | X96: =+X62 -> 5.645 | Y96: =+Y62 -> 5.72 | Z96: =+Y83*Z97/4 -> 5.72 | AA96: =SUM(W96:Z96) -> 22.665 | AB96: =+AA83*AB97 -> 22.770061 | AC96: =+AB83*AC97 -> 24.403482 | AD96: =+AC83*AD97 -> 25.976632 | AE96: =+AD83*AE97 -> 26.719919 | AF96: =+AE83*AF97 -> 27.442672 | AG96: =+AF83*AG97 -> 28.160622 | AH96: =+AG83*AH97 -> 29.423808 | AI96: =+AH83*AI97 -> 30.1893 | ... AN96: =+AM83*AN97 -> 33.808411
A97: -- Taxa de Depreciação | B97: =+B96/B83 -> 0.013690975 | C97: =+C96*4/C83 -> 0.016748315 | D97: =+D96*4/D83 -> 0.015886675 | E97: =+E96*4/E83 -> 0.015413198 | F97: =+F96*4/F83 -> 0.021813224 | G97: =+G96/G83 -> 0.017450579 | H97: =+H96*4/H83 -> 0.019369418 | I97: =+I96*4/I83 -> 0.019592269 | J97: =+J96*4/J83 -> 0.019836401 | K97: =+K96*4/K83 -> 0.016851856 | L97: =+L96/L83 -> 0.017985168 | M97: =+M96*4/M83 -> 0.020310377 | N97: =+N96*4/N83 -> 0.019656575 | O97: =+O96*4/O83 -> 0.020177651 | P97: =+P96*4/P83 -> 0.019680566 | Q97: =+Q96/Q83 -> 0.019080287 | R97: =+R96*4/R83 -> 0.02124115 | S97: =+S96*4/S83 -> 0.017997194 | T97: =+T96*4/T83 -> 0.017248369 | U97: =+U96*4/U83 -> 0.024196139 | V97: =+V96/V83 -> 0.019225243 | W97: =+W96*4/W83 -> 0.020794747 | X97: =+X96*4/X83 -> 0.0208317 | Y97: =+Y96*4/Y83 -> 0.020787433 | Z97: =+Y97 -> 0.020787433 | AA97: =+AA96/AA83 -> 0.01990772 | AB97: 0.02 | AC97: =AB97 -> 0.02 | AD97: =AC97 -> 0.02 | AE97: =AD97 -> 0.02 | AF97: =AE97 -> 0.02 | AG97: =AF97 -> 0.02 | AH97: =AG97 -> 0.02 | AI97: =AH97 -> 0.02 | AJ97: =AI97 -> 0.02 | ... AN97: =AM97 -> 0.02
A99: Saldo Provisão de Manutenção a Realizar - VF | Q99: 0 | V99: =+Q99+1 -> 1 | AA99: =+V99+1 -> 2 | AB99: =+AA99+1 -> 3 | AC99: =+AB99+1 -> 4 | AD99: =+AC99+1 -> 5 | AE99: =+AD99+1 -> 6 | AF99: =+AE99+1 -> 7 | AG99: =+AF99+1 -> 8 | AH99: =+AG99+1 -> 9 | AI99: =+AH99+1 -> 10
A100: Contas de Conservação | Q100: =+Q88+Q90+Q91 -> 16.685874 | V100: =+V88+V90+V91 -> 30.262711 | AA100: =+AA88+AA90+AA91 -> 21.925276 | AB100: =+AB88+AB90+AB91 -> 21.56317 | AC100: =+AC88+AC90+AC91 -> 20.812 | AD100: =+AD88+AD90+AD91 -> 26.569 | AE100: =+AE88+AE90+AE91 -> 41.38676 | AF100: =+AF88+AF90+AF91 -> 28.343799 | AG100: =+AG88+AG90+AG91 -> 39.871687 | AH100: =+AH88+AH90+AH91 -> 30.38917 | ... AS100: =+AS88+AS90+AS91 -> 61.717494
A101: Provisão | L101: =-L55 -> 8.99 | M101: =-M55 -> 4.2 | N101: =-N55 -> 4.3 | O101: =-O55 -> 4.4 | P101: =-P55 -> 5.5 | Q101: =-Q55 -> 18.4 | R101: =-R55 -> 5.6 | S101: =-S55 -> -5.186 | ... Y101: =-Y55 -> 9.089 | Z101: =+AA101-21 -> 2.6949246 | AA101: =+(AA100*0.2+AB100*0.2+AC100*0.2+AD100*0.2+AE100*0.2)/((1.045)^(2.5)) -> 23.694925 | AB101: =+(AB100*0.2+AC100*0.2+AD100*0.2+AE100*0.2+AF100*0.2)/((1.045)^(2.5)) -> 24.844862 | AC101: =+(AC100*0.2+AD100*0.2+AE100*0.2+AF100*0.2+AG100*0.2)/((1.045)^(2.5)) -> 28.125003 | AD101: =+(AD100*0.2+AE100*0.2+AF100*0.2+AG100*0.2+AH100*0.2)/((1.045)^(2.5)) -> 29.840841 | AE101: =+(AE100*0.2+AF100*0.2+AG100*0.2+AH100*0.2+AI100*0.2)/((1.045)^(2.5)) -> 31.439964 | AF101: =+(AF100*0.2+AG100*0.2+AH100*0.2+AI100*0.2+AJ100*0.2)/((1.045)^(2.5)) -> 31.46193 | AG101: =+(AG100*0.2+AH100*0.2+AI100*0.2+AJ100*0.2+AK100*0.2)/((1.045)^(2.5)) -> 33.196376 | AH101: =+(AH100*0.2+AI100*0.2+AJ100*0.2+AK100*0.2+AL100*0.2)/((1.045)^(2.5)) -> 31.858455 | ... AN101: =+(AN100*0.2+AO100*0.2+AP100*0.2+AQ100*0.2+AR100*0.2)/((1.045)^(2.5)) -> 60.811917 | AX101: =1024.2+837.8 -> 1862
A102: Saldo | B102: =+B30+B25 -> 91.2 | C102: =+C30+C25 -> 86.7 | D102: =+D30+D25 -> 12.66 | E102: =+E30+E25 -> 59.37 | F102: =+F30+F25 -> 33.6 | G102: =+G30+G25 -> 33.6 | H102: =+H30+H25 -> 20.1 | I102: =+I30+I25 -> 12.8 | ... P102: =+P30+P25 -> 37.1 | Q102: =+P102 -> 37.1 | R102: =+R30+R25 -> 42.8 | S102: =+S30+S25 -> 37.699 | T102: =+T30+T25 -> 42.845 | U102: =+U30+U25 -> 48.356 | V102: =+V30+V25 -> 48.356 | W102: =+W30+W25 -> 55.793 | X102: =+X30+X25 -> 60.752 | Y102: =+Y30+Y25 -> 69.901 | Z102: =+Y102+Z101-Z94 -> 72.595925 | AA102: =Z102 -> 72.595925 | AB102: =+AA102+AB101-AB94 -> 75.877617 | AC102: =+AB102+AC101-AC94 -> 83.19062 | AD102: =+AC102+AD101-AD94 -> 86.462461 | AE102: =+AD102+AE101-AE94 -> 76.515665 | AF102: =+AE102+AF101-AF94 -> 79.633797 | AG102: =+AF102+AG101-AG94 -> 72.958486 | AH102: =+AG102+AH101-AH94 -> 74.427771 | AI102: =+AH102+AI101-AI94 -> 76.418412 | ... AN102: =+AM102+AN101-AN94 -> 100.23925 | AX102: =+(AX101+450)/(2751-450) -> 1.0047805
A104: Métricas em Crédito | B104: =+B82 -> 2010 | C104: =+C82 -> 1T11 | D104: =+D82 -> 2T11 | E104: =+E82 -> 3T11 | F104: =+F82 -> 4T11 | G104: =+G82 -> 2011 | H104: =+H82 -> 1T12 | I104: =+I82 -> 2T12 | ... AN104: =+AN82 -> 2028E
A105: Dívida Bruta | B105: =+B22+B29+B23 -> 449.47 | C105: =+C22+C29+C23 -> 466.37 | D105: =+D22+D29+D23 -> 518.55 | E105: =+E22+E29+E23 -> 504.1 | F105: =+F22+F29+F23 -> 481.4 | G105: =+G22+G29+G23 -> 481.4 | H105: =+H22+H29+H23 -> 501.1 | I105: =+I22+I29+I23 -> 518.55 | ... AN105: =+AN22+AN29+AN23 -> 56.557868
A106: Dívida Líquida | B106: =+B105-B7 -> 374.37 | C106: =+C105-C7 -> 386.37 | D106: =+D105-D7 -> 514.65 | E106: =+E105-E7 -> 430.1 | F106: =+F105-F7 -> 454.1 | G106: =+G105-G7 -> 454.1 | H106: =+H105-H7 -> 478.93 | I106: =+I105-I7 -> 514.65 | ... AN106: =+AN105-AN7 -> -584.40948
A107: Dívida Bruta / P.L. | B107: =+B105/B34 -> 2.0561299 | C107: =+C105/C34 -> 2.1691628 | D107: =+D105/D34 -> 2.6189394 | E107: =+E105/E34 -> 2.3871762 | F107: =+F105/F34 -> 2.3211186 | G107: =+G105/G34 -> 2.3211186 | H107: =+H105/H34 -> 2.4443902 | I107: =+I105/I34 -> 2.6189394 | ... AN107: =+AN105/AN34 -> 0.02528188
A108: Dívida Bruta / EBITDA | B108: =+B105/B$65 -> 5.9929333 | G108: =+G105/G$65 -> 6.0925912 | H108: =+H105/(H$65+F$65+E$65+D$65) -> 6.092179 | I108: =+I105/(I$65+H$65+F$65+E$65) -> 6.2696474 | J108: =+J105/(J$65+I$65+H$65+F$65) -> 7.1630437 | K108: =+K105/(K$65+J$65+I$65+H$65) -> 6.73853 | L108: =+L105/L$65 -> 6.73853 | M108: =+M105/(M$65+K$65+J$65+I$65) -> 6.8636457 | N108: =+N105/(N$65+M$65+K$65+J$65) -> 6.5534327 | O108: =+O105/(O$65+N$65+M$65+K$65) -> 10.95155 | P108: =+P105/(P$65+O$65+N$65+M$65) -> 10.779634 | Q108: =+Q105/Q$65 -> 10.779634 | R108: =+R105/(R$65+P$65+O$65+N$65) -> 10.558841 | S108: =+S105/(S$65+R$65+P$65+O$65) -> 9.7571889 | T108: =+T105/(T$65+S$65+R$65+P$65) -> 9.653069 | U108: =+U105/(U$65+T$65+S$65+R$65) -> 9.5016906 | V108: =+V105/(V$65) -> 9.501609 | W108: =+W105/(W$65+U$65+T$65+S$65) -> 10.517536 | X108: =+X105/(X$65+W$65+U$65+T$65) -> 10.705057 | Y108: =+Y105/(Y$65+X$65+W$65+U$65) -> 11.038081 | Z108: =+Z105/(Z$65+Y$65+X$65+W$65) -> 10.549304 | AA108: =+AA105/AA$65 -> 10.549304 | AB108: =+AB105/AB$65 -> 8.1683647 | AC108: =+AC105/AC$65 -> 7.0573641 | AD108: =+AD105/AD$65 -> 6.0354336 | AE108: =+AE105/AE$65 -> 5.2140948 | AF108: =+AF105/AF$65 -> 4.4720086 | AG108: =+AG105/AG$65 -> 3.8665098 | AH108: =+AH105/AH$65 -> 3.2509853 | ... AN108: =+AN105/AN$65 -> 0.096847906
A109: Dívida Líquida / EBITDA | B109: =+B106/B$65 -> 4.9916 | G109: =+G106/G$65 -> 5.7470828 | H109: =+H106/(H$65+F$65+E$65+D$65) -> 5.8226448 | I109: =+I106/(I$65+H$65+F$65+E$65) -> 6.2224936 | J109: =+J106/(J$65+I$65+H$65+F$65) -> 6.4223641 | K109: =+K106/(K$65+J$65+I$65+H$65) -> 6.2237364 | L109: =+L106/L$65 -> 6.2237364 | M109: =+M106/(M$65+K$65+J$65+I$65) -> 6.4577277 | N109: =+N106/(N$65+M$65+K$65+J$65) -> 6.502457 | O109: =+O106/(O$65+N$65+M$65+K$65) -> 6.9436278 | P109: =+P106/(P$65+O$65+N$65+M$65) -> 7.239239 | Q109: =+Q106/Q$65 -> 7.239239 | R109: =+R106/(R$65+P$65+O$65+N$65) -> 7.1875416 | S109: =+S106/(S$65+R$65+P$65+O$65) -> 7.0918118 | T109: =+T106/(T$65+S$65+R$65+P$65) -> 7.1785211 | U109: =+U106/(U$65+T$65+S$65+R$65) -> 7.3661718 | V109: =+V106/(V$65) -> 7.3661086 | W109: =+W106/(W$65+U$65+T$65+S$65) -> 8.1737776 | X109: =+X106/(X$65+W$65+U$65+T$65) -> 8.1956001 | Y109: =+Y106/(Y$65+X$65+W$65+U$65) -> 8.3476705 | Z109: =+Z106/(Z$65+Y$65+X$65+W$65) -> 8.1435131 | AA109: =+AA106/AA$65 -> 8.1435131 | AB109: =+AB106/AB$65 -> 6.4297522 | AC109: =+AC106/AC$65 -> 5.5238132 | AD109: =+AD106/AD$65 -> 4.5146268 | AE109: =+AE106/AE$65 -> 3.7332527 | AF109: =+AF106/AF$65 -> 3.0272377 | AG109: =+AG106/AG$65 -> 2.533859 | AH109: =+AH106/AH$65 -> 2.0025029 | ... AN109: =+AN106/AN$65 -> -1.0007243
A111: Capital de Giro | B111: =+B104 -> 2010 | C111: =+C104 -> 1T11 | D111: =+D104 -> 2T11 | E111: =+E104 -> 3T11 | F111: =+F104 -> 4T11 | G111: =+G104 -> 2011 | H111: =+H104 -> 1T12 | I111: =+I104 -> 2T12 | ... AN111: =+AN104 -> 2028E
A112: =+A8 -> Contas a Receber | B112: =+B8 -> 7.7 | C112: =+C8 -> 10.36 | D112: =+D8 -> 8 | E112: =+E8 -> 12.6 | F112: =+F8 -> 9.9 | G112: =+G8 -> 9.9 | H112: =+H8 -> 12.28 | ... Y112: =+Y8 -> 17.749 | Z112: =+Z113*(Z40*4) -> 19.398964 | AA112: =Z112 -> 19.398964 | AB112: =+AB113*AB$40 -> 22.337133 | AC112: =+AC113*AC$40 -> 25.282708 | AD112: =+AD113*AD$40 -> 29.252381 | AE112: =+AE113*AE$40 -> 32.641613 | AF112: =+AF113*AF$40 -> 36.157966 | AG112: =+AG113*AG$40 -> 39.371979 | AH112: =+AH113*AH$40 -> 42.841738 | AI112: =+AI113*AI$40 -> 46.617397 | ... AN112: =+AN113*AN$40 -> 68.85064
A113: % Receitas de Pedágio | B113: =+B112/B$40 -> 0.052345343 | C113: =+C112/(C$40*4) -> 0.073371105 | D113: =+D112/(D$40*4) -> 0.053050398 | E113: =+E112/(E$40*4) -> 0.072647601 | F113: =+F112/(F$40*4) -> 0.058482987 | G113: =+G112/G$40 -> 0.062389715 | H113: =+H112/(H$40*4) -> 0.07675 | I113: =+I112/(I$40*4) -> 0.050251256 | J113: =+J112/(J$40*4) -> 0.058982684 | K113: =+K112/(K$40*4) -> 0.075969828 | L113: =+L112/L$40 -> 0.081786543 | M113: =+M112/(M$40*4) -> 0.061016363 | N113: =+N112/(N$40*4) -> 0.062358277 | O113: =+O112/(O$40*4) -> 0.067515057 | P113: =+P112/(P$40*4) -> 0.088565974 | Q113: =+Q112/Q$40 -> 0.089736701 | R113: =+R112/(R$40*4) -> 0.054752066 | S113: =+S112/(S$40*4) -> 0.073257504 | T113: =+T112/(T$40*4) -> 0.080876924 | U113: =+U112/(U$40*4) -> 0.085301444 | V113: =+V112/V$40 -> 0.089544463 | W113: =+W112/(W$40*4) -> 0.058001488 | X113: =+X112/(X$40*4) -> 0.089693339 | Y113: =+Y112/(Y$40*4) -> 0.081675195 | Z113: =Y113 -> 0.081675195 | AA113: =+AA112/(AA$40) -> 0.091791444 | AB113: 0.09 | AC113: 0.09 | AD113: 0.09 | AE113: 0.09 | AF113: 0.09 | AG113: 0.09 | AH113: 0.09 | AI113: 0.09 | AJ113: 0.09 | AK113: 0.09 | AL113: 0.09 | AM113: 0.09 | AN113: 0.09
A115: =+A9 -> Tributos a Recuperar | B115: =+B9 -> 0.2 | C115: =+C9 -> 0 | D115: =+D9 -> 1.9 | E115: =+E9 -> 1.3 | F115: =+F9 -> 1.8 | G115: =+G9 -> 1.8 | H115: =+H9 -> 2 | ... Y115: =+Y9 -> 0.324 | Z115: =+Z199 -> 0.324 | AA115: =+Z115 -> 0.324 | AB115: =+AB199 -> 16.58172 | AC115: =+AC199 -> 16.58172 | AD115: =+AD199 -> 16.58172 | AE115: =+AE199 -> 16.58172 | AF115: =+AF199 -> 16.58172 | AG115: =+AG199 -> 16.58172 | AH115: =+AH199 -> 16.58172 | AI115: =+AI199 -> 16.58172 | ... AN115: =+AN199 -> 16.58172
A116: % Receitas de Pedágio | B116: =+B115/B$40 -> 0.0013596193 | C116: =+C115/(C$40*4) -> 0 | D116: =+D115/(D$40*4) -> 0.012599469 | E116: =+E115/(E$40*4) -> 0.0074953875 | F116: =+F115/(F$40*4) -> 0.01063327 | G116: =+G115/G$40 -> 0.011343585 | H116: =+H115/(H$40*4) -> 0.0125 | I116: =+I115/(I$40*4) -> 0.011934673 | J116: =+J115/(J$40*4) -> 0.010281385 | K116: =+K115/(K$40*4) -> 0.020474138 | L116: =+L115/L$40 -> 0.022041763 | M116: =+M115/(M$40*4) -> 0.025351463 | N116: =+N115/(N$40*4) -> 0.030045351 | O116: =+O115/(O$40*4) -> 0.025257432 | P116: =+P115/(P$40*4) -> 0.028638099 | Q116: =+Q115/Q$40 -> 0.029016658 | R116: =+R115/(R$40*4) -> 0.031508264 | S116: =+S115/(S$40*4) -> 0.056728367 | T116: =+T115/(T$40*4) -> 0.053061282 | U116: =+U115/(U$40*4) -> 0.0014655479 | V116: =+V115/V$40 -> 0.0015384464 | W116: =+W115/(W$40*4) -> 0.0019735075 | X116: =+X115/(X$40*4) -> 0.001584078 | Y116: =+Y115/(Y$40*4) -> 0.0014909439 | AA116: =+AA115/(AA$40) -> 0.0015330937
A118: =+A10 -> Outros | B118: =+B10 -> 1.55 | C118: =+C10 -> 2 | D118: =+D10 -> 1.3 | E118: =+E10 -> 2 | F118: =+F10 -> 2.17 | G118: =+G10 -> 2.17 | H118: =+H10 -> 3 | ... Y118: =+Y10 -> 3.874 | Z118: =+Z119*(Z40*4) -> 4.2341306 | AA118: =Z118 -> 4.2341306 | AB118: =+AB119*AB$40 -> 4.9638074 | AC118: =+AC119*AC$40 -> 5.6183797 | AD118: =+AD119*AD$40 -> 6.5005292 | AE118: =+AE119*AE$40 -> 7.2536918 | AF118: =+AF119*AF$40 -> 8.0351036 | AG118: =+AG119*AG$40 -> 8.7493286 | AH118: =+AH119*AH$40 -> 9.5203863 | AI118: =+AI119*AI$40 -> 10.359422 | ... AN118: =+AN119*AN$40 -> 15.300142
A119: % Receitas de Pedágio | B119: =+B118/B$40 -> 0.01053705 | C119: =+C118/(C$40*4) -> 0.014164306 | D119: =+D118/(D$40*4) -> 0.0086206897 | E119: =+E118/(E$40*4) -> 0.011531365 | F119: =+F118/(F$40*4) -> 0.012818998 | G119: =+G118/G$40 -> 0.013675321 | H119: =+H118/(H$40*4) -> 0.01875 | I119: =+I118/(I$40*4) -> 0.006281407 | J119: =+J118/(J$40*4) -> 0.04258658 | K119: =+K118/(K$40*4) -> 0.025862069 | L119: =+L118/L$40 -> 0.027842227 | M119: =+M118/(M$40*4) -> 0.014634708 | N119: =+N118/(N$40*4) -> 0.011337868 | O119: =+O118/(O$40*4) -> 0.018457354 | P119: =+P118/(P$40*4) -> 0.016970725 | Q119: =+Q118/Q$40 -> 0.017195056 | R119: =+R118/(R$40*4) -> 0.015495868 | S119: =+S118/(S$40*4) -> 0.020091937 | T119: =+T118/(T$40*4) -> 0.013280703 | U119: =+U118/(U$40*4) -> 0.011050138 | V119: =+V118/V$40 -> 0.011599788 | W119: =+W118/(W$40*4) -> 0.010255006 | X119: =+X118/(X$40*4) -> 0.0081183997 | Y119: =+Y118/(Y$40*4) -> 0.017826903 | Z119: =Y119 -> 0.017826903 | AA119: =+AA118/AA$40 -> 0.020034935 | AB119: 0.02 | AC119: 0.02 | AD119: 0.02 | AE119: 0.02 | AF119: 0.02 | AG119: 0.02 | AH119: 0.02 | AI119: 0.02 | AJ119: 0.02 | AK119: 0.02 | AL119: 0.02 | AM119: 0.02 | AN119: 0.02
A121: =+A21 -> Fornecedores | B121: =+B21 -> 9.9 | C121: =+C21 -> 7.9 | D121: =+D21 -> 18.149 | E121: =+E21 -> 9.4 | F121: =+F21 -> 21.2 | G121: =+G21 -> 21.2 | H121: =+H21 -> 24.9 | ... Y121: =+Y21 -> 28.861 | Z121: =+Z122*(Z40*4) -> 31.543945 | AA121: =Z121 -> 31.543945 | AB121: =+AB122*AB$40 -> 37.044575 | AC121: =+AC122*AC$40 -> 41.929606 | AD121: =+AD122*AD$40 -> 48.513031 | AE121: =+AE122*AE$40 -> 54.133834 | AF121: =+AF122*AF$40 -> 59.965461 | AG121: =+AG122*AG$40 -> 65.295676 | AH121: =+AH122*AH$40 -> 71.05003 | AI121: =+AI122*AI$40 -> 77.311696 | ... AN121: =+AN122*AN$40 -> 114.18398
A122: % Receitas de Pedágio | B122: =+B121/B$40 -> 0.067301156 | C122: =+C121/(C$40*4) -> 0.055949008 | D122: =+D121/(D$40*4) -> 0.12035146 | E122: =+E121/(E$40*4) -> 0.054197417 | F122: =+F121/(F$40*4) -> 0.12523629 | G122: =+G121/G$40 -> 0.13360222 | H122: =+H121/(H$40*4) -> 0.155625 | I122: =+I121/(I$40*4) -> 0.11369347 | J122: =+J121/(J$40*4) -> 0.078463203 | K122: =+K121/(K$40*4) -> 0.10883621 | L122: =+L121/L$40 -> 0.11716937 | M122: =+M121/(M$40*4) -> 0.16017516 | N122: =+N121/(N$40*4) -> 0.16780045 | O122: =+O121/(O$40*4) -> 0.13648727 | P122: =+P121/(P$40*4) -> 0.11985575 | Q122: =+Q121/Q$40 -> 0.12144009 | R122: =+R121/(R$40*4) -> 0.125 | S122: =+S121/(S$40*4) -> 0.17242721 | T122: =+T121/(T$40*4) -> 0.16703584 | U122: =+U121/(U$40*4) -> 0.16263836 | V122: =+V121/V$40 -> 0.17072823 | W122: =+W121/(W$40*4) -> 0.13245232 | X122: =+X121/(X$40*4) -> 0.11224614 | Y122: =+Y121/(Y$40*4) -> 0.13280905 | Z122: =Y122 -> 0.13280905 | AA122: =+AA121/AA$40 -> 0.14925871 | AB122: =+AA122 -> 0.14925871 | AC122: =+AB122 -> 0.14925871 | AD122: =+AC122 -> 0.14925871 | AE122: =+AD122 -> 0.14925871 | AF122: =+AE122 -> 0.14925871 | AG122: =+AF122 -> 0.14925871 | AH122: =+AG122 -> 0.14925871 | AI122: =+AH122 -> 0.14925871 | ... AN122: =+AM122 -> 0.14925871
A124: =+A24 -> Provisões Sociais e Trabalhistas | B124: =+B24 -> 2.1 | C124: =+C24 -> 1.4 | D124: =+D24 -> 3.2 | E124: =+E24 -> 2 | F124: =+F24 -> 3.5 | G124: =+G24 -> 3.5 | H124: =+H24 -> 3.3 | ... Y124: =+Y24 -> 6.96 | Z124: =+Z125*(Z40*4) -> 7.6070081 | AA124: =Z124 -> 7.6070081 | AB124: =+AB125*AB$40 -> 7.4457111 | AC124: =+AC125*AC$40 -> 5.6183797 | AD124: =+AD125*AD$40 -> 6.5005292 | AE124: =+AE125*AE$40 -> 7.2536918 | AF124: =+AF125*AF$40 -> 8.0351036 | AG124: =+AG125*AG$40 -> 8.7493286 | AH124: =+AH125*AH$40 -> 9.5203863 | AI124: =+AI125*AI$40 -> 10.359422 | ... AN124: =+AN125*AN$40 -> 15.300142
A125: % Receitas de Pedágio | B125: =+B124/B$40 -> 0.014276003 | C125: =+C124/(C$40*4) -> 0.0099150142 | D125: =+D124/(D$40*4) -> 0.021220159 | E125: =+E124/(E$40*4) -> 0.011531365 | F125: =+F124/(F$40*4) -> 0.020675803 | G125: =+G124/G$40 -> 0.02205697 | H125: =+H124/(H$40*4) -> 0.020625 | I125: =+I124/(I$40*4) -> 0.020100503 | J125: =+J124/(J$40*4) -> 0.021645022 | K125: =+K124/(K$40*4) -> 0.019396552 | L125: =+L124/L$40 -> 0.020881671 | M125: =+M124/(M$40*4) -> 0.013828071 | N125: =+N124/(N$40*4) -> 0.019274376 | O125: =+O124/(O$40*4) -> 0.019428793 | P125: =+P124/(P$40*4) -> 0.031289775 | Q125: =+Q124/Q$40 -> 0.031703385 | R125: =+R124/(R$40*4) -> 0.022210744 | S125: =+S124/(S$40*4) -> 0.029761661 | T125: =+T124/(T$40*4) -> 0.03003067 | U125: =+U124/(U$40*4) -> 0.029657446 | V125: =+V124/V$40 -> 0.03113265 | W125: =+W124/(W$40*4) -> 0.030863177 | X125: =+X124/(X$40*4) -> 0.033514419 | Y125: =+Y124/(Y$40*4) -> 0.032027684 | Z125: =Y125 -> 0.032027684 | AA125: =+AA124/AA$40 -> 0.035994617 | AB125: 0.03 | AC125: 0.02 | AD125: 0.02 | AE125: 0.02 | AF125: 0.02 | AG125: 0.02 | AH125: 0.02 | AI125: 0.02 | AJ125: 0.02 | AK125: 0.02 | AL125: 0.02 | AM125: 0.02 | AN125: 0.02
A127: =+A30 -> Provisões | B127: =+B30 -> 6.5 | C127: =+C30+C25 -> 86.7 | D127: =+D30+D25 -> 12.66 | E127: =+E30+E25 -> 59.37 | F127: =+F30+F25 -> 33.6 | G127: =+G30 -> 10.4 | H127: =+H30+H25 -> 20.1 | I127: =+I30+I25 -> 12.8 | J127: =+J30+J25 -> 22.19 | K127: =+K30+K25 -> 22.8 | L127: =+L30 -> 19.2 | M127: =+M30+M25 -> 27.25 | N127: =+N30+N25 -> 35.4 | O127: =+O30+O25 -> 39.87 | P127: =+P30+P25 -> 37.1 | Q127: =+Q30 -> 36.3 | R127: =+R30+R25 -> 42.8 | S127: =+S30+S25 -> 37.699 | T127: =+T30+T25 -> 42.845 | U127: =+U30+U25 -> 48.356 | V127: =+V30 -> 47.289 | W127: =+W30+W25 -> 55.793 | X127: =+X30+X25 -> 60.752 | Y127: =+Y30+Y25 -> 69.901 | Z127: =+Z30+Z25 -> 73.977925 | AA127: =Z127 -> 73.977925 | AB127: =+AB30 -> 75.877617 | AC127: =+AC30 -> 83.19062 | AD127: =+AD30 -> 86.462461 | AE127: =+AE30 -> 76.515665 | AF127: =+AF30 -> 79.633797 | AG127: =+AG30 -> 72.958486 | AH127: =+AH30 -> 74.427771 | AI127: =+AI30 -> 76.418412 | ... AN127: =+AN30 -> 100.23925
A129: =+A26 -> Outros | B129: =+B26 -> 2.62 | C129: =+C26 -> 2 | D129: =+D26 -> 3 | E129: =+E26 -> 2 | F129: =+F26 -> 3.87 | G129: =+G26 -> 3.87 | H129: =+H26 -> 3 | ... Y129: =+Y26 -> 0.762 | Z129: =+Z130*(Z40*4) -> 0.83283623 | AA129: =Z129 -> 0.83283623 | AB129: =+AB130*AB$40 -> 4.9638074 | AC129: =+AC130*AC$40 -> 5.6183797 | AD129: =+AD130*AD$40 -> 6.5005292 | AE129: =+AE130*AE$40 -> 7.2536918 | AF129: =+AF130*AF$40 -> 8.0351036 | AG129: =+AG130*AG$40 -> 8.7493286 | AH129: =+AH130*AH$40 -> 9.5203863 | AI129: =+AI130*AI$40 -> 10.359422 | ... AN129: =+AN130*AN$40 -> 15.300142
A130: % Receitas de Pedágio | B130: =+B129/B$40 -> 0.017811013 | C130: =+C129/(C$40*4) -> 0.014164306 | D130: =+D129/(D$40*4) -> 0.019893899 | E130: =+E129/(E$40*4) -> 0.011531365 | F130: =+F129/(F$40*4) -> 0.022861531 | G130: =+G129/G$40 -> 0.024388707 | H130: =+H129/(H$40*4) -> 0.01875 | I130: =+I129/(I$40*4) -> 0.018844221 | J130: =+J129/(J$40*4) -> 0.041666667 | K130: =+K129/(K$40*4) -> 0.021012931 | L130: =+L129/L$40 -> 0.02262181 | M130: =+M129/(M$40*4) -> 0.019843282 | N130: =+N129/(N$40*4) -> 0.015873016 | O130: =+O129/(O$40*4) -> 0.014571595 | P130: =+P129/(P$40*4) -> 0.0053033517 | Q130: =+Q129/Q$40 -> 0.0053734551 | R130: =+R129/(R$40*4) -> 0.0051652893 | S130: =+S129/(S$40*4) -> 0.010621852 | T130: =+T129/(T$40*4) -> 0.0037343102 | U130: =+U129/(U$40*4) -> 0.0023224018 | V130: =+V129/V$40 -> 0.0024379215 | W130: =+W129/(W$40*4) -> 0.013055114 | X130: =+X129/(X$40*4) -> 0.002376117 | Y130: =+Y129/(Y$40*4) -> 0.0035064792 | Z130: =Y130 -> 0.0035064792 | AA130: =+AA129/AA$40 -> 0.0039407899 | AB130: 0.02 | AC130: =AB130 -> 0.02 | AD130: =AC130 -> 0.02 | AE130: =AD130 -> 0.02 | AF130: =AE130 -> 0.02 | AG130: =AF130 -> 0.02 | AH130: =AG130 -> 0.02 | AI130: =AH130 -> 0.02 | AJ130: =AI130 -> 0.02 | ... AN130: =AM130 -> 0.02
A132: Capital de Giro | B132: =+(B112+B115+B118)-(B121+B124+B129+B127) -> -11.67 | C132: =+(C112+C118)-(C121+C124+C129+C127) -> -85.64 | D132: =+(D112+D118)-(D121+D124+D129+D127) -> -27.709 | E132: =+(E112+E118)-(E121+E124+E129+E127) -> -58.17 | F132: =+(F112+F118)-(F121+F124+F129+F127) -> -50.1 | G132: =+(G112+G115+G118)-(G121+G124+G129+G127) -> -25.1 | H132: =+(H112+H118)-(H121+H124+H129+H127) -> -36.02 | I132: =+(I112+I118)-(I121+I124+I129+I127) -> -28.1 | J132: =+(J112+J118)-(J121+J124+J129+J127) -> -29.62 | K132: =+(K112+K118)-(K121+K124+K129+K127) -> -31.6 | L132: =+(L112+L115+L118)-(L121+L124+L129+L127) -> -24.2 | M132: =+(M112+M118)-(M121+M124+M129+M127) -> -47.764 | N132: =+(N112+N118)-(N121+N124+N129+N127) -> -58.2 | O132: =+(O112+O118)-(O121+O124+O129+O127) -> -57.27 | P132: =+(P112+P118)-(P121+P124+P129+P127) -> -46.7 | Q132: =+(Q112+Q115+Q118)-(Q121+Q124+Q129+Q127) -> -40.5 | R132: =+(R112+R118)-(R121+R124+R129+R127) -> -58.7 | S132: =+(S112+S118)-(S121+S124+S129+S127) -> -61.036 | T132: =+(T112+T118)-(T121+T124+T129+T127) -> -65.377 | U132: =+(U112+U118)-(U121+U124+U129+U127) -> -69.343 | V132: =+(V112+V118)-(V121+V124+V129+V127) -> -68.276 | W132: =+(W112+W118)-(W121+W124+W129+W127) -> -76.72 | X132: =+(X112+X118)-(X121+X124+X129+X127) -> -70.664 | Y132: =+(Y112+Y118)-(Y121+Y124+Y129+Y127) -> -84.861 | ... AN132: =+(AN112+AN118)-(AN121+AN124+AN129+AN127) -> -160.87273
A133: Variação de CDG (Uso de Caixa) | C133: =+C132-B132 -> -73.97 | D133: =+D132-C132 -> 57.931 | E133: =+E132-D132 -> -30.461 | F133: =+F132-E132 -> 8.07 | G133: =+G132-B132 -> -13.43 | H133: =+H132-G132 -> -10.92 | I133: =+I132-H132 -> 7.92 | J133: =+J132-I132 -> -1.52 | K133: =+K132-J132 -> -1.98 | L133: =+L132-G132 -> 0.9 | M133: =+M132-L132 -> -23.564 | N133: =+N132-M132 -> -10.436 | O133: =+O132-N132 -> 0.93 | P133: =+P132-O132 -> 10.57 | Q133: =+Q132-L132 -> -16.3 | R133: =+R132-Q132 -> -18.2 | S133: =+S132-R132 -> -2.336 | T133: =+T132-S132 -> -4.341 | U133: =+U132-T132 -> -3.966 | V133: =+V132-Q132 -> -27.776 | W133: =+W132-V132 -> -8.444 | X133: =+X132-W132 -> 6.056 | Y133: =+Y132-X132 -> -14.197 | Z133: =+Z132-Y132 -> -5.4676201 | AA133: =+AA132-V132 -> -22.05262 | AB133: =+AB132-AA132 -> -7.7021496 | AC133: =+AC132-AB132 -> -7.4251268 | AD133: =+AD132-AC132 -> -6.7677432 | AE133: =+AE132-AD132 -> 6.9620611 | AF133: =+AF132-AE132 -> -6.2148163 | AG133: =+AG132-AF132 -> 3.8448827 | AH133: =+AH132-AG132 -> -4.5249367 | AI133: =+AI132-AH132 -> -5.3156837 | ... AN133: =+AN132-AM132 -> 3.4103705
A135: Dívida e Resultado Financeiro | B135: =+B111 -> 2010 | C135: =+C111 -> 1T11 | D135: =+D111 -> 2T11 | E135: =+E111 -> 3T11 | F135: =+F111 -> 4T11 | G135: =+G111 -> 2011 | H135: =+H111 -> 1T12 | I135: =+I111 -> 2T12 | ... AN135: =+AN111 -> 2028E
...

Sheet Tráfego
A1: Rodovias do Tiete | Z1: =65*0.3 -> 19.5
A3: Dados Macro | B3: 2T09 | C3: 3T09 | D3: 4T09 | E3: 2009 | F3: 1T10 | G3: 2T10 | H3: 3T10 | I3: 4T10 | J3: 2010 | K3: 1T11 | L3: 2T11 | M3: 3T11 | N3: 4T11 | O3: 2011 | P3: 1T12 | Q3: 2T12 | R3: 3T12 | S3: 4T12 | T3: 2012 | U3: 1T13 | V3: 2T13 | W3: 3T13 | X3: 4T13 | Y3: 2013 | Z3: 1T14 | AA3: 2T14 | AB3: 3T14 | AC3: 4T14 | AD3: 2014 | AE3: 1T15 | AF3: 2T15 | AG3: 3T15 | AH3: 4T15E | AI3: 2015E | AJ3: 1T16E | AK3: 2T16E | AL3: 3T16E | AM3: 4T16E | AN3: 2016E | AO3: 1T17E | AP3: 2T17E | AQ3: 3T17E | AR3: 4T17E | AS3: 2017E | AT3: 1T18E | AU3: 2T18E | AV3: 3T18E | AW3: 4T18E | AX3: 2018E | AY3: 1T19E | AZ3: 2T19E | BA3: 3T19E | BB3: 4T19E | BC3: 2019E | BD3: 1T20E | BE3: 2T20E | BF3: 3T20E | BG3: 4T20E | BH3: 2020E | BI3: 1T21E | BJ3: 2T21E | BK3: 3T21E | BL3: 4T21E | BM3: 2021E | BN3: 1T22E | BO3: 2T22E | BP3: 3T22E | BQ3: 4T22E | BR3: 2022E | BS3: 1T23E | BT3: 2T23E | BU3: 3T23E | BV3: 4T23E | BW3: 2023E | BX3: 1T24E | BY3: 2T24E | BZ3: 3T24E | CA3: 4T24E | CB3: 2024E | CC3: 1T25E | CD3: 2T25E | CE3: 3T25E | CF3: 4T25E | CG3: 2025E | CH3: 1T26E | CI3: 2T26E | CJ3: 3T26E | CK3: 4T26E | CL3: 2026E | CM3: 1T27E | CN3: 2T27E | CO3: 3T27E | CP3: 4T27E | CQ3: 2027E | CR3: 1T28E | CS3: 2T28E | CT3: 3T28E | CU3: 4T28E | CV3: 2028E
A4: PIB | E4: -0.32824804 | J4: 7.5336155 | K4: 4.235654 | L4: 3.314358 | M4: 2.1219664 | N4: 1.3664596 | O4: 2.7325092 | P4: 0.75274305 | Q4: 0.48977593 | R4: 0.6 | S4: 2.95 | T4: 1 | U4: 2.706666 | V4: 3.3 | W4: 3.8386618 | X4: 3.4717008 | Y4: 3.3 | Z4: 2 | AA4: 2 | AB4: 2 | AC4: 2 | AD4: =Despesas!N4 -> 0.14458389 | AE4: =AI4 -> -3.1 | AF4: =AI4 -> -3.1 | AG4: =AI4 -> -3.1 | AH4: =AI4 -> -3.1 | AI4: =Despesas!S4 -> -3.1 | AJ4: =AN4 -> -2 | AK4: =AN4 -> -2 | AL4: =AN4 -> -2 | AM4: =AN4 -> -2 | AN4: =Despesas!T4 -> -2 | AO4: =AS4 -> 1 | AP4: =AS4 -> 1 | AQ4: =AS4 -> 1 | AR4: =AS4 -> 1 | AS4: =Despesas!U4 -> 1 | AT4: =AX4 -> 2 | AU4: =AX4 -> 2 | AV4: =AX4 -> 2 | AW4: =AX4 -> 2 | AX4: =Despesas!V4 -> 2 | AY4: =BC4 -> 2 | AZ4: =BC4 -> 2 | BA4: =BC4 -> 2 | BB4: =BC4 -> 2 | BC4: =Despesas!W4 -> 2 | BD4: =BH4 -> 2 | BE4: =BH4 -> 2 | BF4: =BH4 -> 2 | BG4: =BH4 -> 2 | BH4: =Despesas!X4 -> 2 | BI4: =BM4 -> 2 | BJ4: =BM4 -> 2 | BK4: =BM4 -> 2 | BL4: =BM4 -> 2 | BM4: =Despesas!Y4 -> 2 | BN4: =BR4 -> 2 | BO4: =BR4 -> 2 | BP4: =BR4 -> 2 | BQ4: =BR4 -> 2 | BR4: =Despesas!Z4 -> 2 | BS4: =BW4 -> 2 | BT4: =BW4 -> 2 | BU4: =BW4 -> 2 | BV4: =BW4 -> 2 | BW4: =Despesas!AA4 -> 2 | BX4: =CB4 -> 2 | BY4: =CB4 -> 2 | BZ4: =CB4 -> 2 | CA4: =CB4 -> 2 | CB4: =Despesas!AB4 -> 2 | CC4: =CG4 -> 2 | CD4: =CG4 -> 2 | CE4: =CG4 -> 2 | CF4: =CG4 -> 2 | CG4: =Despesas!AC4 -> 2 | CH4: =CL4 -> 2 | CI4: =CL4 -> 2 | CJ4: =CL4 -> 2 | CK4: =CL4 -> 2 | CL4: =Despesas!AD4 -> 2 | CM4: =CQ4 -> 2 | CN4: =CQ4 -> 2 | CO4: =CQ4 -> 2 | CP4: =CQ4 -> 2 | CQ4: =Despesas!AE4 -> 2 | CR4: =CV4 -> 2 | CS4: =CV4 -> 2 | CT4: =CV4 -> 2 | CU4: =CV4 -> 2 | CV4: =Despesas!AF4 -> 2
A5: IPCA | E5: 4.3116501 | J5: 5.9086887 | K5: 2.439696 | L5: 1.3956003 | M5: 1.0634041 | N5: 1.4569972 | O5: 6.5033527 | P5: 1.224539 | Q5: 1.08289 | R5: 1.416561 | S5: 1.9018948 | T5: 5.84 | U5: =+Y5/4 -> 1.35 | V5: =+Y5/4 -> 1.35 | W5: 0 | X5: =+Y5/4 -> 1.35 | Y5: 5.4 | Z5: =+AD5/4 -> 1.6025 | AA5: =+AD5/4 -> 1.6025 | AB5: =+AD5/4 -> 1.6025 | AC5: =+AD5/4 -> 1.6025 | AD5: =Despesas!N5 -> 6.41 | AE5: =AI5/4 -> 2.5 | AF5: =AI5/4 -> 2.5 | AG5: =AI5/4 -> 2.5 | AH5: =AI5/4 -> 2.5 | AI5: =Despesas!S5 -> 10 | AJ5: =AN5/4 -> 1.6 | AK5: =AN5/4 -> 1.6 | AL5: =AN5/4 -> 1.6 | AM5: =AN5/4 -> 1.6 | AN5: =Despesas!T5 -> 6.4 | AO5: =AS5/4 -> 1.25 | AP5: =AS5/4 -> 1.25 | AQ5: =AS5/4 -> 1.25 | AR5: =AS5/4 -> 1.25 | AS5: =Despesas!U5 -> 5 | AT5: =AX5/4 -> 1.25 | AU5: =AX5/4 -> 1.25 | AV5: =AX5/4 -> 1.25 | AW5: =AX5/4 -> 1.25 | AX5: =Despesas!V5 -> 5 | AY5: =BC5/4 -> 1.125 | AZ5: =BC5/4 -> 1.125 | BA5: =BC5/4 -> 1.125 | BB5: =BC5/4 -> 1.125 | BC5: =Despesas!W5 -> 4.5 | BD5: =BH5/4 -> 1.125 | BE5: =BH5/4 -> 1.125 | BF5: =BH5/4 -> 1.125 | BG5: =BH5/4 -> 1.125 | BH5: =Despesas!X5 -> 4.5 | BI5: =BM5/4 -> 1.125 | BJ5: =BM5/4 -> 1.125 | BK5: =BM5/4 -> 1.125 | BL5: =BM5/4 -> 1.125 | BM5: =Despesas!Y5 -> 4.5 | BN5: =BR5/4 -> 1.125 | BO5: =BR5/4 -> 1.125 | BP5: =BR5/4 -> 1.125 | BQ5: =BR5/4 -> 1.125 | BR5: =Despesas!Z5 -> 4.5 | BS5: =BW5/4 -> 1.125 | BT5: =BW5/4 -> 1.125 | BU5: =BW5/4 -> 1.125 | BV5: =BW5/4 -> 1.125 | BW5: =Despesas!AA5 -> 4.5 | BX5: =CB5/4 -> 1.125 | BY5: =CB5/4 -> 1.125 | BZ5: =CB5/4 -> 1.125 | CA5: =CB5/4 -> 1.125 | CB5: =Despesas!AB5 -> 4.5 | CC5: =CG5/4 -> 1.125 | CD5: =CG5/4 -> 1.125 | CE5: =CG5/4 -> 1.125 | CF5: =CG5/4 -> 1.125 | CG5: =Despesas!AC5 -> 4.5 | CH5: =CL5/4 -> 1.125 | CI5: =CL5/4 -> 1.125 | CJ5: =CL5/4 -> 1.125 | CK5: =CL5/4 -> 1.125 | CL5: =Despesas!AD5 -> 4.5 | CM5: =CQ5/4 -> 1.125 | CN5: =CQ5/4 -> 1.125 | CO5: =CQ5/4 -> 1.125 | CP5: =CQ5/4 -> 1.125 | CQ5: =Despesas!AE5 -> 4.5 | CR5: =CV5/4 -> 1.125 | CS5: =CV5/4 -> 1.125 | CT5: =CV5/4 -> 1.125 | CU5: =CV5/4 -> 1.125 | CV5: =Despesas!AF5 -> 4.5
A6: IGPM | E6: -1.7192492 | J6: 11.323143 | K6: 2.4312626 | L6: 0.69680368 | M6: 0.97144444 | N6: 0.91198891 | O6: 5.096813 | P6: 0.61573961 | Q6: 2.5570914 | R6: 3.7862169 | S6: 0.66992596 | T6: 7.82 | U6: =+Y6/4 -> 1.25 | V6: =+Y6/4 -> 1.25 | W6: =+Y6/4 -> 1.25 | X6: =+Y6/4 -> 1.25 | Y6: 5 | Z6: =+AD6/4 -> 0.9225 | AA6: =+AD6/4 -> 0.9225 | AB6: =+AD6/4 -> 0.9225 | AC6: =+AD6/4 -> 0.9225 | AD6: =Despesas!N6 -> 3.69 | AE6: =AI6/4 -> 2.475 | AF6: =AI6/4 -> 2.475 | AG6: =AI6/4 -> 2.475 | AH6: =AI6/4 -> 2.475 | AI6: =Despesas!S6 -> 9.9 | AJ6: =AN6/4 -> 1.625 | AK6: =AN6/4 -> 1.625 | AL6: =AN6/4 -> 1.625 | AM6: =AN6/4 -> 1.625 | AN6: =Despesas!T6 -> 6.5 | AO6: =AS6/4 -> 1.375 | AP6: =AS6/4 -> 1.375 | AQ6: =AS6/4 -> 1.375 | AR6: =AS6/4 -> 1.375 | AS6: =Despesas!U6 -> 5.5 | AT6: =AX6/4 -> 1.375 | AU6: =AX6/4 -> 1.375 | AV6: =AX6/4 -> 1.375 | AW6: =AX6/4 -> 1.375 | AX6: =Despesas!V6 -> 5.5 | AY6: =BC6/4 -> 1.375 | AZ6: =BC6/4 -> 1.375 | BA6: =BC6/4 -> 1.375 | BB6: =BC6/4 -> 1.375 | BC6: =Despesas!W6 -> 5.5 | BD6: =BH6/4 -> 1.375 | BE6: =BH6/4 -> 1.375 | BF6: =BH6/4 -> 1.375 | BG6: =BH6/4 -> 1.375 | BH6: =Despesas!X6 -> 5.5 | BI6: =BM6/4 -> 1.375 | BJ6: =BM6/4 -> 1.375 | BK6: =BM6/4 -> 1.375 | BL6: =BM6/4 -> 1.375 | BM6: =Despesas!Y6 -> 5.5 | BN6: =BR6/4 -> 1.375 | BO6: =BR6/4 -> 1.375 | BP6: =BR6/4 -> 1.375 | BQ6: =BR6/4 -> 1.375 | BR6: =Despesas!Z6 -> 5.5 | BS6: =BW6/4 -> 1.375 | BT6: =BW6/4 -> 1.375 | BU6: =BW6/4 -> 1.375 | BV6: =BW6/4 -> 1.375 | BW6: =Despesas!AA6 -> 5.5 | BX6: =CB6/4 -> 1.375 | BY6: =CB6/4 -> 1.375 | BZ6: =CB6/4 -> 1.375 | CA6: =CB6/4 -> 1.375 | CB6: =Despesas!AB6 -> 5.5 | CC6: =CG6/4 -> 1.375 | CD6: =CG6/4 -> 1.375 | CE6: =CG6/4 -> 1.375 | CF6: =CG6/4 -> 1.375 | CG6: =Despesas!AC6 -> 5.5 | CH6: =CL6/4 -> 1.375 | CI6: =CL6/4 -> 1.375 | CJ6: =CL6/4 -> 1.375 | CK6: =CL6/4 -> 1.375 | CL6: =Despesas!AD6 -> 5.5 | CM6: =CQ6/4 -> 1.375 | CN6: =CQ6/4 -> 1.375 | CO6: =CQ6/4 -> 1.375 | CP6: =CQ6/4 -> 1.375 | CQ6: =Despesas!AE6 -> 5.5 | CR6: =CV6/4 -> 1.375 | CS6: =CV6/4 -> 1.375 | CT6: =CV6/4 -> 1.375 | CU6: =CV6/4 -> 1.375 | CV6: =Despesas!AF6 -> 5.5
A7: Selic (fim de período) | E7: 8.75 | J7: 10.75 | K7: 11.75 | L7: 12.25 | M7: 12 | N7: 11 | O7: 11 | P7: 9.75 | Q7: 8.5 | R7: 7.5 | S7: 7.25 | T7: 7.25 | U7: =+Y7 -> 8.75 | V7: =+Y7 -> 8.75 | W7: =+Y7 -> 8.75 | X7: =+Y7 -> 8.75 | Y7: 8.75 | Z7: =+AD7 -> 11.75 | AA7: =+AD7 -> 11.75 | AB7: =+AD7 -> 11.75 | AC7: =+AD7 -> 11.75 | AD7: =Despesas!N7 -> 11.75 | AE7: =AI7 -> 14.25 | AF7: =AI7 -> 14.25 | AG7: =AI7 -> 14.25 | AH7: =AI7 -> 14.25 | AI7: =Despesas!S7 -> 14.25 | AJ7: =AN7 -> 12.75 | AK7: =AN7 -> 12.75 | AL7: =AN7 -> 12.75 | AM7: =AN7 -> 12.75 | AN7: =Despesas!T7 -> 12.75 | AO7: =AS7 -> 12.75 | AP7: =AS7 -> 12.75 | AQ7: =AS7 -> 12.75 | AR7: =AS7 -> 12.75 | AS7: =Despesas!U7 -> 12.75 | AT7: =AX7 -> 12.75 | AU7: =AX7 -> 12.75 | AV7: =AX7 -> 12.75 | AW7: =AX7 -> 12.75 | AX7: =Despesas!V7 -> 12.75 | AY7: =BC7 -> 12.75 | AZ7: =BC7 -> 12.75 | BA7: =BC7 -> 12.75 | BB7: =BC7 -> 12.75 | BC7: =Despesas!W7 -> 12.75 | BD7: =BH7 -> 12.75 | BE7: =BH7 -> 12.75 | BF7: =BH7 -> 12.75 | BG7: =BH7 -> 12.75 | BH7: =Despesas!X7 -> 12.75 | BI7: =BM7 -> 12.75 | BJ7: =BM7 -> 12.75 | BK7: =BM7 -> 12.75 | BL7: =BM7 -> 12.75 | BM7: =Despesas!Y7 -> 12.75 | BN7: =BR7 -> 12.75 | BO7: =BR7 -> 12.75 | BP7: =BR7 -> 12.75 | BQ7: =BR7 -> 12.75 | BR7: =Despesas!Z7 -> 12.75 | BS7: =BW7 -> 12.75 | BT7: =BW7 -> 12.75 | BU7: =BW7 -> 12.75 | BV7: =BW7 -> 12.75 | BW7: =Despesas!AA7 -> 12.75 | BX7: =CB7 -> 12.75 | BY7: =CB7 -> 12.75 | BZ7: =CB7 -> 12.75 | CA7: =CB7 -> 12.75 | CB7: =Despesas!AB7 -> 12.75 | CC7: =CG7 -> 12.75 | CD7: =CG7 -> 12.75 | CE7: =CG7 -> 12.75 | CF7: =CG7 -> 12.75 | CG7: =Despesas!AC7 -> 12.75 | CH7: =CL7 -> 12.75 | CI7: =CL7 -> 12.75 | CJ7: =CL7 -> 12.75 | CK7: =CL7 -> 12.75 | CL7: =Despesas!AD7 -> 12.75 | CM7: =CQ7 -> 12.75 | CN7: =CQ7 -> 12.75 | CO7: =CQ7 -> 12.75 | CP7: =CQ7 -> 12.75 | CQ7: =Despesas!AE7 -> 12.75 | CR7: =CV7 -> 12.75 | CS7: =CV7 -> 12.75 | CT7: =CV7 -> 12.75 | CU7: =CV7 -> 12.75 | CV7: =Despesas!AF7 -> 12.75
A8: Selic (média) | E8: 9.9166667 | J8: 10 | K8: 11.333333 | L8: 12.012097 | M8: 12.280769 | N8: 11.415385 | O8: 11.708333 | P8: 10.380952 | Q8: 8.6666667 | R8: 7.6666667 | S8: 7.25 | T8: 8.4583333 | U8: =+AVERAGE(T7:U7) -> 8 | V8: =+AVERAGE(U7:V7) -> 8.75 | W8: =+AVERAGE(V7:W7) -> 8.75 | X8: =+AVERAGE(W7:X7) -> 8.75 | Y8: 7.7291667 | Z8: =+AVERAGE(Y7:Z7) -> 10.25 | AA8: =+AVERAGE(Z7:AA7) -> 11.75 | AB8: =+AVERAGE(AA7:AB7) -> 11.75 | AC8: =+AVERAGE(AB7:AC7) -> 11.75 | AD8: =Despesas!N8 -> 11.020833 | AE8: =AVERAGE(AD7:AE7) -> 13 | AF8: =AVERAGE(AE7:AF7) -> 14.25 | AG8: =AVERAGE(AF7:AG7) -> 14.25 | AH8: =AVERAGE(AG7:AH7) -> 14.25 | AI8: =Despesas!S8 -> 13.58 | AJ8: =AVERAGE(AI7:AJ7) -> 13.5 | AK8: =AVERAGE(AJ7:AK7) -> 12.75 | AL8: =AVERAGE(AK7:AL7) -> 12.75 | AM8: =AVERAGE(AL7:AM7) -> 12.75 | AN8: =Despesas!T8 -> 13.5 | AO8: =AVERAGE(AN7:AO7) -> 12.75 | AP8: =AVERAGE(AO7:AP7) -> 12.75 | AQ8: =AVERAGE(AP7:AQ7) -> 12.75 | AR8: =AVERAGE(AQ7:AR7) -> 12.75 | AS8: =Despesas!U8 -> 12.75 | AT8: =AVERAGE(AS7:AT7) -> 12.75 | AU8: =AVERAGE(AT7:AU7) -> 12.75 | AV8: =AVERAGE(AU7:AV7) -> 12.75 | AW8: =AVERAGE(AV7:AW7) -> 12.75 | AX8: =Despesas!V8 -> 12.75 | AY8: =AVERAGE(AX7:AY7) -> 12.75 | AZ8: =AVERAGE(AY7:AZ7) -> 12.75 | BA8: =AVERAGE(AZ7:BA7) -> 12.75 | BB8: =AVERAGE(BA7:BB7) -> 12.75 | BC8: =Despesas!W8 -> 12.75 | BD8: =AVERAGE(BC7:BD7) -> 12.75 | BE8: =AVERAGE(BD7:BE7) -> 12.75 | BF8: =AVERAGE(BE7:BF7) -> 12.75 | BG8: =AVERAGE(BF7:BG7) -> 12.75 | BH8: =Despesas!X8 -> 12.75 | BI8: =AVERAGE(BH7:BI7) -> 12.75 | BJ8: =AVERAGE(BI7:BJ7) -> 12.75 | BK8: =AVERAGE(BJ7:BK7) -> 12.75 | BL8: =AVERAGE(BK7:BL7) -> 12.75 | BM8: =Despesas!Y8 -> 12.75 | BN8: =AVERAGE(BM7:BN7) -> 12.75 | BO8: =AVERAGE(BN7:BO7) -> 12.75 | BP8: =AVERAGE(BO7:BP7) -> 12.75 | BQ8: =AVERAGE(BP7:BQ7) -> 12.75 | BR8: =Despesas!Z8 -> 12.75 | BS8: =AVERAGE(BR7:BS7) -> 12.75 | BT8: =AVERAGE(BS7:BT7) -> 12.75 | BU8: =AVERAGE(BT7:BU7) -> 12.75 | BV8: =AVERAGE(BU7:BV7) -> 12.75 | BW8: =Despesas!AA8 -> 12.75 | BX8: =AVERAGE(BW7:BX7) -> 12.75 | BY8: =AVERAGE(BX7:BY7) -> 12.75 | BZ8: =AVERAGE(BY7:BZ7) -> 12.75 | CA8: =AVERAGE(BZ7:CA7) -> 12.75 | CB8: =Despesas!AB8 -> 12.75 | CC8: =AVERAGE(CB7:CC7) -> 12.75 | CD8: =AVERAGE(CC7:CD7) -> 12.75 | CE8: =AVERAGE(CD7:CE7) -> 12.75 | CF8: =AVERAGE(CE7:CF7) -> 12.75 | CG8: =Despesas!AC8 -> 12.75 | CH8: =AVERAGE(CG7:CH7) -> 12.75 | CI8: =AVERAGE(CH7:CI7) -> 12.75 | CJ8: =AVERAGE(CI7:CJ7) -> 12.75 | CK8: =AVERAGE(CJ7:CK7) -> 12.75 | CL8: =Despesas!AD8 -> 12.75 | CM8: =AVERAGE(CL7:CM7) -> 12.75 | CN8: =AVERAGE(CM7:CN7) -> 12.75 | CO8: =AVERAGE(CN7:CO7) -> 12.75 | CP8: =AVERAGE(CO7:CP7) -> 12.75 | CQ8: =Despesas!AE8 -> 12.75 | CR8: =AVERAGE(CQ7:CR7) -> 12.75 | CS8: =AVERAGE(CR7:CS7) -> 12.75 | CT8: =AVERAGE(CS7:CT7) -> 12.75 | CU8: =AVERAGE(CT7:CU7) -> 12.75 | CV8: =Despesas!AF8 -> 12.75
A10: Base Tarifária (R$ por Km) | B10: 2T09 | C10: 3T09 | D10: 4T09 | E10: =E3 -> 2009 | F10: =F3 -> 1T10 | G10: =G3 -> 2T10 | H10: =H3 -> 3T10 | I10: =I3 -> 4T10 | J10: =J3 -> 2010 | K10: =K3 -> 1T11 | L10: =L3 -> 2T11 | ... CV10: =CV3 -> 2028E
A11: Pista Simples | U11: 0.08294 | V11: =+U11 -> 0.08294 | W11: =+V11*(1+(W$5/100)*4) -> 0.08294 | X11: =+W11 -> 0.08294 | Z11: =+X11 -> 0.08294 | AA11: =+Z11 -> 0.08294 | AB11: =+AA11*(1+(AB$5/100)*4) -> 0.088256454 | AC11: =+AB11 -> 0.088256454 | AE11: =+AC11 -> 0.088256454 | AF11: =+AE11 -> 0.088256454 | AG11: =+AF11*(1+(AG$5/100)*4) -> 0.097082099 | AH11: =+AG11 -> 0.097082099 | AJ11: =+AH11 -> 0.097082099 | AK11: =+AJ11 -> 0.097082099 | AL11: =+AK11*(1+(AL$5/100)*4) -> 0.10329535 | AM11: =+AL11 -> 0.10329535 | AO11: =+AM11 -> 0.10329535 | AP11: =+AO11 -> 0.10329535 | AQ11: =+AP11*(1+(AQ$5/100)*4) -> 0.10846012 | AR11: =+AQ11 -> 0.10846012 | AT11: =+AR11 -> 0.10846012 | AU11: =+AT11 -> 0.10846012 | AV11: =+AU11*(1+(AV$5/100)*4) -> 0.11388313 | AW11: =+AV11 -> 0.11388313 | AY11: =+AW11 -> 0.11388313 | AZ11: =+AY11 -> 0.11388313 | BA11: =+AZ11*(1+(BA$5/100)*4) -> 0.11900787 | BB11: =+BA11 -> 0.11900787 | BD11: =+BB11 -> 0.11900787 | BE11: =+BD11 -> 0.11900787 | BF11: =+BE11*(1+(BF$5/100)*4) -> 0.12436322 | BG11: =+BF11 -> 0.12436322 | BI11: =+BG11 -> 0.12436322 | BJ11: =+BI11 -> 0.12436322 | BK11: =+BJ11*(1+(BK$5/100)*4) -> 0.12995957 | BL11: =+BK11 -> 0.12995957 | BN11: =+BL11 -> 0.12995957 | BO11: =+BN11 -> 0.12995957 | BP11: =+BO11*(1+(BP$5/100)*4) -> 0.13580775 | BQ11: =+BP11 -> 0.13580775 | BS11: =+BQ11 -> 0.13580775 | BT11: =+BS11 -> 0.13580775 | BU11: =+BT11*(1+(BU$5/100)*4) -> 0.1419191 | BV11: =+BU11 -> 0.1419191 | BX11: =+BV11 -> 0.1419191 | BY11: =+BX11 -> 0.1419191 | BZ11: =+BY11*(1+(BZ$5/100)*4) -> 0.14830546 | CA11: =+BZ11 -> 0.14830546 | CC11: =+CA11 -> 0.14830546 | CD11: =+CC11 -> 0.14830546 | CE11: =+CD11*(1+(CE$5/100)*4) -> 0.1549792 | CF11: =+CE11 -> 0.1549792 | CH11: =+CF11 -> 0.1549792 | CI11: =+CH11 -> 0.1549792 | CJ11: =+CI11*(1+(CJ$5/100)*4) -> 0.16195327 | CK11: =+CJ11 -> 0.16195327 | CM11: =+CK11 -> 0.16195327 | CN11: =+CM11 -> 0.16195327 | CO11: =+CN11*(1+(CO$5/100)*4) -> 0.16924116 | CP11: =+CO11 -> 0.16924116 | CR11: =+CP11 -> 0.16924116 | CS11: =+CR11 -> 0.16924116 | CT11: =+CS11*(1+(CT$5/100)*4) -> 0.17685701 | CU11: =+CT11 -> 0.17685701
A12: Pista Dupla | U12: 0.116112 | V12: =+U12 -> 0.116112 | W12: =+V12*(1+(W$5/100)*4) -> 0.116112 | X12: =+W12 -> 0.116112 | Z12: =+X12 -> 0.116112 | AA12: =+Z12 -> 0.116112 | AB12: =+AA12*(1+(AB$5/100)*4) -> 0.12355478 | AC12: =+AB12 -> 0.12355478 | AE12: =+AC12 -> 0.12355478 | AF12: =+AE12 -> 0.12355478 | AG12: =+AF12*(1+(AG$5/100)*4) -> 0.13591026 | AH12: =+AG12 -> 0.13591026 | AJ12: =+AH12 -> 0.13591026 | AK12: =+AJ12 -> 0.13591026 | AL12: =+AK12*(1+(AL$5/100)*4) -> 0.14460851 | AM12: =+AL12 -> 0.14460851 | AO12: =+AM12 -> 0.14460851 | AP12: =+AO12 -> 0.14460851 | AQ12: =+AP12*(1+(AQ$5/100)*4) -> 0.15183894 | AR12: =+AQ12 -> 0.15183894 | AT12: =+AR12 -> 0.15183894 | AU12: =+AT12 -> 0.15183894 | AV12: =+AU12*(1+(AV$5/100)*4) -> 0.15943089 | AW12: =+AV12 -> 0.15943089 | AY12: =+AW12 -> 0.15943089 | AZ12: =+AY12 -> 0.15943089 | BA12: =+AZ12*(1+(BA$5/100)*4) -> 0.16660528 | BB12: =+BA12 -> 0.16660528 | BD12: =+BB12 -> 0.16660528 | BE12: =+BD12 -> 0.16660528 | BF12: =+BE12*(1+(BF$5/100)*4) -> 0.17410251 | BG12: =+BF12 -> 0.17410251 | BI12: =+BG12 -> 0.17410251 | BJ12: =+BI12 -> 0.17410251 | BK12: =+BJ12*(1+(BK$5/100)*4) -> 0.18193713 | BL12: =+BK12 -> 0.18193713 | BN12: =+BL12 -> 0.18193713 | BO12: =+BN12 -> 0.18193713 | BP12: =+BO12*(1+(BP$5/100)*4) -> 0.1901243 | BQ12: =+BP12 -> 0.1901243 | BS12: =+BQ12 -> 0.1901243 | BT12: =+BS12 -> 0.1901243 | BU12: =+BT12*(1+(BU$5/100)*4) -> 0.19867989 | BV12: =+BU12 -> 0.19867989 | BX12: =+BV12 -> 0.19867989 | BY12: =+BX12 -> 0.19867989 | BZ12: =+BY12*(1+(BZ$5/100)*4) -> 0.20762049 | CA12: =+BZ12 -> 0.20762049 | CC12: =+CA12 -> 0.20762049 | CD12: =+CC12 -> 0.20762049 | CE12: =+CD12*(1+(CE$5/100)*4) -> 0.21696341 | CF12: =+CE12 -> 0.21696341 | CH12: =+CF12 -> 0.21696341 | CI12: =+CH12 -> 0.21696341 | CJ12: =+CI12*(1+(CJ$5/100)*4) -> 0.22672676 | CK12: =+CJ12 -> 0.22672676 | CM12: =+CK12 -> 0.22672676 | CN12: =+CM12 -> 0.22672676 | CO12: =+CN12*(1+(CO$5/100)*4) -> 0.23692947 | CP12: =+CO12 -> 0.23692947 | CR12: =+CP12 -> 0.23692947 | CS12: =+CR12 -> 0.23692947 | CT12: =+CS12*(1+(CT$5/100)*4) -> 0.24759129 | CU12: =+CT12 -> 0.24759129
A14: Dados Operacionais | B14: 2T09 | C14: 3T09 | D14: 4T09 | E14: =E3 -> 2009 | F14: =F3 -> 1T10 | G14: =G3 -> 2T10 | H14: =H3 -> 3T10 | I14: =I3 -> 4T10 | J14: =J3 -> 2010 | K14: =K3 -> 1T11 | L14: =L3 -> 2T11 | ... CV14: =CV3 -> 2028E
A15: Consolidado
A16: Tarifa (R$) | J16: =+J35*1000/J31 -> 3.5306709 | K16: =+K35*1000/K31 -> 3.6037024 | L16: =+L35*1000/L31 -> 3.5994226 | M16: =+M35*1000/M31 -> 3.9045793 | N16: =+N35*1000/N31 -> 3.9207041 | O16: =+O35*1000/O31 -> 3.7630187 | P16: =+P35*1000/P31 -> 3.918603 | Q16: =+Q35*1000/Q31 -> 3.8893874 | ... CV16: =+CV35*1000/CV31 -> 9.1961709
A17: Y/Y (%) | O17: =+O16/J16-1 -> 0.065808408 | P17: =+P16/K16-1 -> 0.08738252 | Q17: =+Q16/L16-1 -> 0.080558682 | R17: =+R16/M16-1 -> 0.050691189 | S17: =+S16/N16-1 -> 0.046436979 | T17: =+T16/O16-1 -> 0.065162719 | U17: =+U16/P16-1 -> 0.048984036 | V17: =+V16/Q16-1 -> 0.029285433 | ... CV17: =+CV16/CQ16-1 -> 0.044980984
A19: Distância Total (km) | T19: =+U19 -> 406.34 | U19: =+U20+U21 -> 406.34 | V19: =+V20+V21 -> 406.265 | W19: =+W20+W21 -> 406.265 | X19: =+X20+X21 -> 406.265 | Y19: =+Y20+Y21 -> 406.265 | Z19: =+Z20+Z21 -> 406.265 | AA19: =+AA20+AA21 -> 406.265 | AB19: =+AB20+AB21 -> 406.265 | ... CV19: =+CV20+CV21 -> 415.145
A20: -- Pista Simples | T20: =+U20 -> 276.59 | U20: =+U50+U66+U82+U98+U114+U130+U146+U162+U178 -> 276.59 | V20: =+V50+V66+V82+V98+V114+V130+V146+V162+V178 -> 276.615 | W20: =+W50+W66+W82+W98+W114+W130+W146+W162+W178 -> 276.615 | X20: =+X50+X66+X82+X98+X114+X130+X146+X162+X178 -> 276.615 | Y20: =+Y50+Y66+Y82+Y98+Y114+Y130+Y146+Y162+Y178 -> 276.615 | Z20: =+Z50+Z66+Z82+Z98+Z114+Z130+Z146+Z162+Z178 -> 276.615 | AA20: =+AA50+AA66+AA82+AA98+AA114+AA130+AA146+AA162+AA178 -> 276.615 | AB20: =+AB50+AB66+AB82+AB98+AB114+AB130+AB146+AB162+AB178 -> 276.615 | ... CV20: =+CV50+CV66+CV82+CV98+CV114+CV130+CV146+CV162+CV178 -> 189.465
A21: -- Pista Dupla | T21: =+U21 -> 129.75 | U21: =+U51+U67+U83+U99+U115+U131+U147+U163+U179 -> 129.75 | V21: =+V51+V67+V83+V99+V115+V131+V147+V163+V179 -> 129.65 | W21: =+W51+W67+W83+W99+W115+W131+W147+W163+W179 -> 129.65 | X21: =+X51+X67+X83+X99+X115+X131+X147+X163+X179 -> 129.65 | Y21: =+Y51+Y67+Y83+Y99+Y115+Y131+Y147+Y163+Y179 -> 129.65 | Z21: =+Z51+Z67+Z83+Z99+Z115+Z131+Z147+Z163+Z179 -> 129.65 | AA21: =+AA51+AA67+AA83+AA99+AA115+AA131+AA147+AA163+AA179 -> 129.65 | AB21: =+AB51+AB67+AB83+AB99+AB115+AB131+AB147+AB163+AB179 -> 129.65 | ... CV21: =+CV51+CV67+CV83+CV99+CV115+CV131+CV147+CV163+CV179 -> 225.68
A22: % Pista Dupla | T22: =+U22 -> 0.31931388 | U22: =+U21/U19 -> 0.31931388 | V22: =+V21/V19 -> 0.31912668 | W22: =+W21/W19 -> 0.31912668 | X22: =+X21/X19 -> 0.31912668 | Y22: =+Y21/Y19 -> 0.31912668 | Z22: =+Z21/Z19 -> 0.31912668 | AA22: =+AA21/AA19 -> 0.31912668 | AB22: =+AB21/AB19 -> 0.31912668 | ... CV22: =+CV21/CV19 -> 0.54361729
A24: Tráfego (Mil Veículos Equivalentes) | E24: 6823.633 | F24: 9669.69 | G24: 10433.29 | H24: 10872.442 | I24: 10688.048 | J24: 41663.469 | K24: 9795.4815 | L24: 10473.902 | M24: 11104.909 | N24: 10793.979 | O24: 42168.272 | P24: 10207.719 | Q24: 10232.974 | R24: 11261.406 | S24: 11309.433 | T24: 43011.533 | U24: 10556.414 | V24: 11016.224 | W24: 12312.954 | X24: 12418.737 | Y24: 46304.327 | Z24: 11857.7 | AA24: 11828.568 | AB24: 12301.005 | AC24: 12541.166 | AD24: 48528.438 | AI24: =AD24*(1+AI28) -> 48528.438 | AN24: =AI24*(1+AN28) -> 46102.016 | AS24: =AN24*(1+AS28) -> 47208.464 | AX24: =AS24*(1+AX28) -> 49285.637 | BC24: =AX24*(1+BC28) -> 51257.062 | BH24: =BC24*(1+BH28) -> 53102.317 | BM24: =BH24*(1+BM28) -> 54801.591 | BR24: =BM24*(1+BR28) -> 56336.035 | BW24: =BR24*(1+BW28) -> 57688.1 | CB24: =BW24*(1+CB28) -> 58841.862 | CG24: =CB24*(1+CG28) -> 60018.699 | CL24: =CG24*(1+CL28) -> 61219.073 | CQ24: =CL24*(1+CQ28) -> 62443.455 | CV24: =CQ24*(1+CV28) -> 63692.324
A25: -- Passeio | T25: 18886.22 | U25: 4722.977 | V25: 4605.887 | W25: 4888.425 | X25: 5227.354 | Y25: 19444.642 | Z25: 4919.201 | AA25: 4970.699 | AB25: 4928.103 | AC25: 5322.021 | AD25: 20140.024 | AI25: 20140.024 | AN25: 20140.024 | AS25: 20140.024 | AX25: 20140.024 | BC25: 20140.024 | BH25: 20140.024 | BM25: 20140.024 | BR25: 20140.024 | BW25: 20140.024 | CB25: 20140.024 | CG25: 20140.024 | CL25: 20140.024 | CQ25: 20140.024 | CV25: 20140.024
A26: -- Comerciais Leves | T26: 11063.325 | U26: 2605.754 | V26: 2747.915 | W26: 2706.963 | X26: 2638.449 | Y26: 10699.081 | Z26: 2450.924 | AA26: 2474.432 | AB26: 2553.544 | AC26: 2532.297 | AD26: 10011.197 | AI26: 10011.197 | AN26: 10011.197 | AS26: 10011.197 | AX26: 10011.197 | BC26: 10011.197 | BH26: 10011.197 | BM26: 10011.197 | BR26: 10011.197 | BW26: 10011.197 | CB26: 10011.197 | CG26: 10011.197 | CL26: 10011.197 | CQ26: 10011.197 | CV26: 10011.197
A27: -- Comerciais Pesados | T27: 13061.988 | U27: 3227.683 | V27: 3662.422 | W27: 4717.566 | X27: 4552.934 | Y27: 16160.605 | Z27: 4487.575 | AA27: 4383.437 | AB27: 4819.358 | AC27: 4686.848 | AD27: 18377.218 | AI27: 18377.218 | AN27: 18377.218 | AS27: 18377.218 | AX27: 18377.218 | BC27: 18377.218 | BH27: 18377.218 | BM27: 18377.218 | BR27: 18377.218 | BW27: 18377.218 | CB27: 18377.218 | CG27: 18377.218 | CL27: 18377.218 | CQ27: 18377.218 | CV27: 18377.218
A28: Y/Y (%) | J28: =J24/E24-1 -> 5.1057606 | K28: =K24/F24-1 -> 0.013008845 | L28: =L24/G24-1 -> 0.0038925401 | M28: =M24/H24-1 -> 0.021381351 | N28: =N24/I24-1 -> 0.0099112583 | O28: =O24/J24-1 -> 0.012116202 | P28: =P24/K24-1 -> 0.042084506 | Q28: =Q24/L24-1 -> -0.023002698 | ... AD28: =AD24/Y24-1 -> 0.048032466 | AI28: =+AI29*(AI4/100) -> 0 | AN28: =+AN29*(AN4/100) -> -0.05 | AS28: =+AS29*(AS4/100) -> 0.024 | AX28: =+AX29*(AX4/100) -> 0.044 | BC28: =+BC29*(BC4/100) -> 0.04 | BH28: =+BH29*(BH4/100) -> 0.036 | BM28: =+BM29*(BM4/100) -> 0.032 | BR28: =+BR29*(BR4/100) -> 0.028 | BW28: =+BW29*(BW4/100) -> 0.024 | CB28: =+CB29*(CB4/100) -> 0.02 | CG28: =+CG29*(CG4/100) -> 0.02 | CL28: =+CL29*(CL4/100) -> 0.02 | CQ28: =+CQ29*(CQ4/100) -> 0.02 | CV28: =+CV29*(CV4/100) -> 0.02
A29: Elasticidade PIB | J29: =J28/(J4/100) -> 67.773045 | K29: =K28/(K4/100) -> 0.30712719 | L29: =L28/(L4/100) -> 0.11744477 | M29: =M28/(M4/100) -> 1.0076197 | N29: =N28/(N4/100) -> 0.72532391 | O29: =O28/(O4/100) -> 0.44340936 | P29: =P28/(P4/100) -> 5.5908196 | Q29: =Q28/(Q4/100) -> -4.6965758 | ... AD29: =AD28/(AD4/100) -> 33.221175 | AI29: 0 | AJ29: 2.479146 | AK29: 2.4826541 | AL29: 2.4819548 | AM29: 2.4835089 | AN29: 2.5 | AO29: 2.3975313 | AP29: 2.4023649 | AQ29: 2.4014015 | AR29: 2.4035426 | AS29: 2.4 | AT29: 1.8219226 | AU29: 1.8192892 | AV29: 1.8202779 | AW29: 1.8218359 | AX29: 2.2 | AY29: 1.4240488 | AZ29: 1.4251451 | BA29: 1.4251458 | BB29: 1.4259412 | BC29: 2 | BD29: 1.2666039 | BE29: 1.2670195 | BF29: 1.2671312 | BG29: 1.2675859 | BH29: 1.8 | BI29: 1.1840088 | BJ29: 1.1840425 | BK29: 1.1838026 | BL29: 1.1841302 | BM29: 1.6 | BN29: 0.99 | BO29: 0.99 | BP29: 0.99 | BQ29: 0.99 | BR29: 1.4 | BS29: 0.9 | BT29: 0.9 | BU29: 0.9 | BV29: 0.9 | BW29: 1.2 | BX29: 0.8 | BY29: 0.8 | BZ29: 0.8 | CA29: 0.8 | CB29: 1 | CC29: 0.7 | CD29: 0.7 | CE29: 0.7 | CF29: 0.7 | CG29: 1 | CH29: 0.63 | CI29: 0.62737312 | CJ29: 0.62480637 | CK29: 0.62496944 | CL29: 1 | CM29: 0.59147298 | CN29: 0.59133167 | CO29: 0.61297112 | CP29: 0.60882593 | CQ29: 1 | CR29: 0.58239528 | CS29: 0.58237341 | CT29: 0.57981333 | CU29: 0.53505775 | CV29: 1
A31: Tráfego (Mil Veículos Equivalentes) | D31: =+D54+D70+D86+D102+D118+D134+D150+D166+D182 -> 5225.6625 | E31: =+E54+E70+E86+E102+E118+E134+E150+E166+E182 -> 6823.633 | F31: =+F54+F70+F86+F102+F118+F134+F150+F166+F182 -> 9669.69 | G31: =+G54+G70+G86+G102+G118+G134+G150+G166+G182 -> 10433.29 | H31: =+H54+H70+H86+H102+H118+H134+H150+H166+H182 -> 10872.442 | I31: =+I54+I70+I86+I102+I118+I134+I150+I166+I182 -> 10688.048 | J31: =+J54+J70+J86+J102+J118+J134+J150+J166+J182 -> 41663.469 | K31: =+K54+K70+K86+K102+K118+K134+K150+K166+K182 -> 9795.4815 | ... CV31: =+CV54+CV70+CV86+CV102+CV118+CV134+CV150+CV166+CV182 -> 83187.57
A32: YoY (%) | I32: =+I31/D31-1 -> 1.0453 | J32: =+J31/E31-1 -> 5.1057606 | K32: =+K31/F31-1 -> 0.013008845 | L32: =+L31/G31-1 -> 0.0038925401 | M32: =+M31/H31-1 -> 0.021381351 | N32: =+N31/I31-1 -> 0.0099112583 | O32: =+O31/J31-1 -> 0.012116202 | P32: =+P31/K31-1 -> 0.042084506 | ... CV32: =+CV31/CQ31-1 -> 0.020203947
A33: Elasticidade PIB | J33: =+J32/(J$4/100) -> 67.773045 | K33: =+K32/(K$4/100) -> 0.30712719 | L33: =+L32/(L$4/100) -> 0.11744477 | M33: =+M32/(M$4/100) -> 1.0076197 | N33: =+N32/(N$4/100) -> 0.72532391 | O33: =+O32/(O$4/100) -> 0.44340936 | P33: =+P32/(P$4/100) -> 5.5908196 | Q33: =+Q32/(Q$4/100) -> -4.6965758 | ... CV33: =+CV32/(CV$4/100) -> 1.0101973
A35: Receita de Pedágio | J35: =+'Dados Financeiros'!B40 -> 147.1 | K35: =+'Dados Financeiros'!C40 -> 35.3 | L35: =+'Dados Financeiros'!D40 -> 37.7 | M35: =+'Dados Financeiros'!E40 -> 43.36 | N35: =+'Dados Financeiros'!F40 -> 42.32 | O35: =+'Dados Financeiros'!G40 -> 158.68 | P35: =+'Dados Financeiros'!H40 -> 40 | Q35: =+'Dados Financeiros'!I40 -> 39.8 | ... AG35: =+'Dados Financeiros'!Y40 -> 54.328 | AH35: =+AH58+AH74+AH90+AH106+AH122+AH138+AH154+AH170+AH186 -> 59.378381 | AI35: =SUM(AE35:AH35) -> 211.33738 | AJ35: =+AJ58+AJ74+AJ90+AJ106+AJ122+AJ138+AJ154+AJ170+AJ186 -> 57.934413 | AK35: =+AK58+AK74+AK90+AK106+AK122+AK138+AK154+AK170+AK186 -> 59.932718 | AL35: =+AL58+AL74+AL90+AL106+AL122+AL138+AL154+AL170+AL186 -> 64.665052 | AM35: =+AM58+AM74+AM90+AM106+AM122+AM138+AM154+AM170+AM186 -> 65.658186 | AN35: =+AN58+AN74+AN90+AN106+AN122+AN138+AN154+AN170+AN186 -> 248.19037 | AO35: =+AO58+AO74+AO90+AO106+AO122+AO138+AO154+AO170+AO186 -> 64.074812 | AP35: =+AP58+AP74+AP90+AP106+AP122+AP138+AP154+AP170+AP186 -> 65.962554 | AQ35: =+AQ58+AQ74+AQ90+AQ106+AQ122+AQ138+AQ154+AQ170+AQ186 -> 74.268979 | ... CV35: =+CV58+CV74+CV90+CV106+CV122+CV138+CV154+CV170+CV186 -> 765.00712
A36: % Y/Y | O36: =+O35/J35-1 -> 0.078721958 | P36: =+P35/K35-1 -> 0.13314448 | Q36: =+Q35/L35-1 -> 0.055702918 | R36: =+R35/M35-1 -> 0.065498155 | S36: =+S35/N35-1 -> 0.096408318 | T36: =+T35/O35-1 -> 0.086463322 | U36: =+U35/P35-1 -> 0.08475 | V36: =+V35/Q35-1 -> 0.1080402 | ... CV36: =+CV35/CQ35-1 -> 0.066093725
A38: Receitas Acessórias | J38: =+'Dados Financeiros'!B41 -> 0.52 | K38: =+'Dados Financeiros'!C41 -> 0.1 | L38: =+'Dados Financeiros'!D41 -> 0.1 | M38: =+'Dados Financeiros'!E41 -> 0.126 | N38: =+'Dados Financeiros'!F41 -> 0.254 | O38: =+'Dados Financeiros'!G41 -> 0.58 | P38: =+'Dados Financeiros'!H41 -> 0.077 | Q38: =+'Dados Financeiros'!I41 -> 0.223 | ... AG38: =+'Dados Financeiros'!Y41 -> 1.733 | AH38: =AC38*(1+AH5/100) -> 1.59695 | AI38: =SUM(AE38:AH38) -> 6.61395 | AJ38: =AE38*(1+AJ5/100) -> 0.398272 | AK38: =AF38*(1+AK5/100) -> 2.938272 | AL38: =AG38*(1+AL5/100) -> 1.760728 | AM38: =AH38*(1+AM5/100) -> 1.6225012 | AN38: =+SUM(AJ38:AM38) -> 6.7197732 | AO38: =AJ38*(1+AO5/100)+3 -> 3.4032504 | AP38: =AK38*(1+AP5/100)+1 -> 3.9750004 | AQ38: =AL38*(1+AQ5/100)+1 -> 2.7827371 | AR38: =AM38*(1+AR5/100)+1 -> 2.6427825 | AS38: =+SUM(AO38:AR38) -> 12.80377 | AT38: 3 | AU38: 3 | AV38: 3 | AW38: 3 | AX38: =+SUM(AT38:AW38) -> 12 | AY38: =AT38*(1+AY5/100) -> 3.03375 | AZ38: =AU38*(1+AZ5/100) -> 3.03375 | BA38: =AV38*(1+BA5/100) -> 3.03375 | BB38: =AW38*(1+BB5/100) -> 3.03375 | BC38: =+SUM(AY38:BB38) -> 12.135 | BD38: =AY38*(1+BD5/100) -> 3.0678797 | BE38: =AZ38*(1+BE5/100) -> 3.0678797 | BF38: =BA38*(1+BF5/100) -> 3.0678797 | BG38: =BB38*(1+BG5/100) -> 3.0678797 | BH38: =+SUM(BD38:BG38) -> 12.271519 | BI38: =BD38*(1+BI5/100) -> 3.1023933 | BJ38: =BE38*(1+BJ5/100) -> 3.1023933 | BK38: =BF38*(1+BK5/100) -> 3.1023933 | BL38: =BG38*(1+BL5/100) -> 3.1023933 | BM38: =+SUM(BI38:BL38) -> 12.409573 | BN38: =BI38*(1+BN5/100) -> 3.1372953 | BO38: =BJ38*(1+BO5/100) -> 3.1372953 | BP38: =BK38*(1+BP5/100) -> 3.1372953 | BQ38: =BL38*(1+BQ5/100) -> 3.1372953 | BR38: =+SUM(BN38:BQ38) -> 12.549181 | BS38: =BN38*(1+BS5/100) -> 3.1725898 | BT38: =BO38*(1+BT5/100) -> 3.1725898 | BU38: =BP38*(1+BU5/100) -> 3.1725898 | BV38: =BQ38*(1+BV5/100) -> 3.1725898 | BW38: =+SUM(BS38:BV38) -> 12.690359 | BX38: =BS38*(1+BX5/100) -> 3.2082815 | BY38: =BT38*(1+BY5/100) -> 3.2082815 | BZ38: =BU38*(1+BZ5/100) -> 3.2082815 | CA38: =BV38*(1+CA5/100) -> 3.2082815 | CB38: =+SUM(BX38:CA38) -> 12.833126 | CC38: =BX38*(1+CC5/100) -> 3.2443746 | CD38: =BY38*(1+CD5/100) -> 3.2443746 | CE38: =BZ38*(1+CE5/100) -> 3.2443746 | CF38: =CA38*(1+CF5/100) -> 3.2443746 | CG38: =+SUM(CC38:CF38) -> 12.977499 | CH38: =CC38*(1+CH5/100) -> 3.2808738 | CI38: =CD38*(1+CI5/100) -> 3.2808738 | CJ38: =CE38*(1+CJ5/100) -> 3.2808738 | CK38: =CF38*(1+CK5/100) -> 3.2808738 | CL38: =+SUM(CH38:CK38) -> 13.123495 | CM38: =CH38*(1+CM5/100) -> 3.3177837 | CN38: =CI38*(1+CN5/100) -> 3.3177837 | CO38: =CJ38*(1+CO5/100) -> 3.3177837 | CP38: =CK38*(1+CP5/100) -> 3.3177837 | CQ38: =+SUM(CM38:CP38) -> 13.271135 | CR38: =CM38*(1+CR5/100) -> 3.3551087 | CS38: =CN38*(1+CS5/100) -> 3.3551087 | CT38: =CO38*(1+CT5/100) -> 3.3551087 | CU38: =CP38*(1+CU5/100) -> 3.3551087 | CV38: =+SUM(CR38:CU38) -> 13.420435
A39: Rec. Acessórias / Rec. Pedágios | J39: =+J38/J35 -> 0.0035350102 | K39: =+K38/K35 -> 0.0028328612 | L39: =+L38/L35 -> 0.0026525199 | M39: =+M38/M35 -> 0.0029059041 | N39: =+N38/N35 -> 0.0060018904 | O39: =+O38/O35 -> 0.003655155 | P39: =+P38/P35 -> 0.001925 | Q39: =+Q38/Q35 -> 0.0056030151 | ... CV39: =+CV38/CV35 -> 0.017542889
A41: Impostos | J41: =+'Dados Financeiros'!B44 -> -12.7 | K41: =+'Dados Financeiros'!C44 -> -3 | L41: =+'Dados Financeiros'!D44 -> -3.3 | M41: =+'Dados Financeiros'!E44 -> -3.7 | N41: =+'Dados Financeiros'!F44 -> -4.2 | O41: =+'Dados Financeiros'!G44 -> -14.2 | P41: =+'Dados Financeiros'!H44 -> -3.44 | Q41: =+'Dados Financeiros'!I44 -> -3.46 | ... AG41: =+'Dados Financeiros'!Y44 -> -5.303 | AH41: =-AH42*(AH38+AH35) -> -5.7678633 | AI41: =SUM(AE41:AH41) -> -19.810863 | AJ41: =-AJ42*(AJ38+AJ35) -> -5.3021968 | AK41: =-AK42*(AK38+AK35) -> -5.7147097 | AL41: =-AL42*(AL38+AL35) -> -6.0378252 | AM41: =-AM42*(AM38+AM35) -> -6.1155327 | AN41: =-AN42*(AN38+AN35) -> -23.170264 | AO41: =-AO42*(AO38+AO35) -> -6.1334733 | AP41: =-AP42*(AP38+AP35) -> -6.3570308 | AQ41: =-AQ42*(AQ38+AQ35) -> -7.0036783 | ... CV41: =-CV42*(CV38+CV35) -> -70.755804
A42: Impostos / Rec. Bruta Operacional | J42: =-J41/(J38+J35) -> 0.086031703 | K42: =-K41/(K38+K35) -> 0.084745763 | L42: =-L41/(L38+L35) -> 0.087301587 | M42: =-M41/(M38+M35) -> 0.085084855 | N42: =-N41/(N38+N35) -> 0.098651759 | O42: =-O41/(O38+O35) -> 0.089162376 | P42: =-P41/(P38+P35) -> 0.085834768 | Q42: =-Q41/(Q38+Q35) -> 0.086450291 | ... AG42: =-AG41/(AG38+AG35) -> 0.094593389 | AH42: =+AG42 -> 0.094593389 | AI42: =-AI41/(AI38+AI35) -> 0.090895812 | AJ42: =+AI42 -> 0.090895812 | AK42: =+AJ42 -> 0.090895812 | AL42: =+AK42 -> 0.090895812 | AM42: =+AL42 -> 0.090895812 | AN42: =AI42 -> 0.090895812 | AO42: =+AN42 -> 0.090895812 | AP42: =+AO42 -> 0.090895812 | AQ42: =+AP42 -> 0.090895812 | AR42: =+AQ42 -> 0.090895812 | AS42: =AN42 -> 0.090895812 | AT42: =+AS42 -> 0.090895812 | AU42: =+AT42 -> 0.090895812 | AV42: =+AU42 -> 0.090895812 | AW42: =+AV42 -> 0.090895812 | AX42: =AS42 -> 0.090895812 | AY42: =+AX42 -> 0.090895812 | AZ42: =+AY42 -> 0.090895812 | BA42: =+AZ42 -> 0.090895812 | BB42: =+BA42 -> 0.090895812 | BC42: =AX42 -> 0.090895812 | BD42: =+BC42 -> 0.090895812 | BE42: =+BD42 -> 0.090895812 | BF42: =+BE42 -> 0.090895812 | BG42: =+BF42 -> 0.090895812 | BH42: =BC42 -> 0.090895812 | BI42: =+BH42 -> 0.090895812 | BJ42: =+BI42 -> 0.090895812 | BK42: =+BJ42 -> 0.090895812 | BL42: =+BK42 -> 0.090895812 | BM42: =BH42 -> 0.090895812 | BN42: =+BM42 -> 0.090895812 | BO42: =+BN42 -> 0.090895812 | BP42: =+BO42 -> 0.090895812 | BQ42: =+BP42 -> 0.090895812 | BR42: =BM42 -> 0.090895812 | BS42: =+BR42 -> 0.090895812 | BT42: =+BS42 -> 0.090895812 | BU42: =+BT42 -> 0.090895812 | BV42: =+BU42 -> 0.090895812 | BW42: =BR42 -> 0.090895812 | BX42: =+BW42 -> 0.090895812 | BY42: =+BX42 -> 0.090895812 | BZ42: =+BY42 -> 0.090895812 | CA42: =+BZ42 -> 0.090895812 | CB42: =BW42 -> 0.090895812 | CC42: =+CB42 -> 0.090895812 | CD42: =+CC42 -> 0.090895812 | CE42: =+CD42 -> 0.090895812 | CF42: =+CE42 -> 0.090895812 | CG42: =CB42 -> 0.090895812 | CH42: =+CG42 -> 0.090895812 | CI42: =+CH42 -> 0.090895812 | CJ42: =+CI42 -> 0.090895812 | CK42: =+CJ42 -> 0.090895812 | CL42: =CG42 -> 0.090895812 | CM42: =+CL42 -> 0.090895812 | CN42: =+CM42 -> 0.090895812 | CO42: =+CN42 -> 0.090895812 | CP42: =+CO42 -> 0.090895812 | CQ42: =CL42 -> 0.090895812 | CR42: =+CQ42 -> 0.090895812 | CS42: =+CR42 -> 0.090895812 | CT42: =+CS42 -> 0.090895812 | CU42: =+CT42 -> 0.090895812 | CV42: =CQ42 -> 0.090895812
A45: Praça Monte Mor (Industrial) | U45: =+U58/U$35 -> 0.073765845 | Y45: =+Y58/Y$35 -> 0.074793392 | AD45: =+AD58/AD$35 -> 0.072204545 | AI45: =+AI58/AI$35 -> 0.073649785 | AN45: =+AN58/AN$35 -> 0.076818187 | AS45: =+AS58/AS$35 -> 0.080844917 | AX45: =+AX58/AX$35 -> 0.079721303 | BC45: =+BC58/BC$35 -> 0.077305125 | BH45: =+BH58/BH$35 -> 0.076407219 | BM45: =+BM58/BM$35 -> 0.076432812 | BR45: =+BR58/BR$35 -> 0.0764414 | BW45: =+BW58/BW$35 -> 0.076379395 | CB45: =+CB58/CB$35 -> 0.076361045 | CG45: =+CG58/CG$35 -> 0.076357749 | CL45: =+CL58/CL$35 -> 0.076348702 | CQ45: =+CQ58/CQ$35 -> 0.076333811 | CV45: =+CV58/CV$35 -> 0.076304976
A46: Tarifa (R$) | R46: 4.7 | S46: 4.7 | T46: 4.7 | U46: 4.7 | V46: =+V50*V$11+V51*V$12 -> 4.7150934 | W46: =+W50*W$11+W51*W$12 -> 4.7150934 | X46: =+X50*X$11+X51*X$12 -> 4.7150934 | Y46: =+Y58*1000/Y54 -> 4.7116141 | Z46: =+Z50*Z$11+Z51*Z$12 -> 4.7150934 | AA46: =+AA50*AA$11+AA51*AA$12 -> 4.7150934 | AB46: =+AB50*AB$11+AB51*AB$12 -> 5.0173309 | AC46: =+AC50*AC$11+AC51*AC$12 -> 5.0173309 | AD46: =+AD58*1000/AD54 -> 4.8723983 | AE46: =+AE50*AE$11+AE51*AE$12 -> 5.0173309 | AF46: =+AF50*AF$11+AF51*AF$12 -> 5.1316975 | AG46: =+AG50*AG$11+AG51*AG$12 -> 5.6448672 | AH46: =+AH50*AH$11+AH51*AH$12 -> 5.6448672 | AI46: =+AI58*1000/AI54 -> 5.3600112 | AJ46: =+AJ50*AJ$11+AJ51*AJ$12 -> 6.0743066 | AK46: =+AK50*AK$11+AK51*AK$12 -> 6.0743066 | AL46: =+AL50*AL$11+AL51*AL$12 -> 6.4630623 | AM46: =+AM50*AM$11+AM51*AM$12 -> 6.4630623 | AN46: =+AN58*1000/AN54 -> 6.2671538 | AO46: =+AO50*AO$11+AO51*AO$12 -> 6.4630623 | AP46: =+AP50*AP$11+AP51*AP$12 -> 7.1674516 | AQ46: =+AQ50*AQ$11+AQ51*AQ$12 -> 7.5258242 | AR46: =+AR50*AR$11+AR51*AR$12 -> 7.5258242 | AS46: =+AS58*1000/AS54 -> 7.1826116 | AT46: =+AT50*AT$11+AT51*AT$12 -> 7.5258242 | AU46: =+AU50*AU$11+AU51*AU$12 -> 7.5258242 | AV46: =+AV50*AV$11+AV51*AV$12 -> 7.9021154 | AW46: =+AW50*AW$11+AW51*AW$12 -> 7.9021154 | AX46: =+AX58*1000/AX54 -> 7.7221792 | AY46: =+AY50*AY$11+AY51*AY$12 -> 7.9021154 | AZ46: =+AZ50*AZ$11+AZ51*AZ$12 -> 7.9021154 | BA46: =+BA50*BA$11+BA51*BA$12 -> 8.2577106 | BB46: =+BB50*BB$11+BB51*BB$12 -> 8.2577106 | BC46: =+BC58*1000/BC54 -> 8.0890833 | BD46: =+BD50*BD$11+BD51*BD$12 -> 8.2577106 | BE46: =+BE50*BE$11+BE51*BE$12 -> 8.2577106 | BF46: =+BF50*BF$11+BF51*BF$12 -> 8.6293076 | BG46: =+BG50*BG$11+BG51*BG$12 -> 8.6293076 | BH46: =+BH58*1000/BH54 -> 8.4515532 | BI46: =+BI50*BI$11+BI51*BI$12 -> 8.6293076 | BJ46: =+BJ50*BJ$11+BJ51*BJ$12 -> 8.6293076 | BK46: =+BK50*BK$11+BK51*BK$12 -> 9.0176264 | BL46: =+BL50*BL$11+BL51*BL$12 -> 9.0176264 | BM46: =+BM58*1000/BM54 -> 8.8318633 | BN46: =+BN50*BN$11+BN51*BN$12 -> 9.0176264 | BO46: =+BO50*BO$11+BO51*BO$12 -> 9.0176264 | BP46: =+BP50*BP$11+BP51*BP$12 -> 9.4234196 | BQ46: =+BQ50*BQ$11+BQ51*BQ$12 -> 9.4234196 | BR46: =+BR58*1000/BR54 -> 9.2292899 | BS46: =+BS50*BS$11+BS51*BS$12 -> 9.4234196 | BT46: =+BT50*BT$11+BT51*BT$12 -> 9.4234196 | BU46: =+BU50*BU$11+BU51*BU$12 -> 9.8474735 | BV46: =+BV50*BV$11+BV51*BV$12 -> 9.8474735 | BW46: =+BW58*1000/BW54 -> 9.6446034 | BX46: =+BX50*BX$11+BX51*BX$12 -> 9.8474735 | BY46: =+BY50*BY$11+BY51*BY$12 -> 9.8474735 | BZ46: =+BZ50*BZ$11+BZ51*BZ$12 -> 10.29061 | CA46: =+CA50*CA$11+CA51*CA$12 -> 10.29061 | CB46: =+CB58*1000/CB54 -> 10.078609 | CC46: =+CC50*CC$11+CC51*CC$12 -> 10.29061 | CD46: =+CD50*CD$11+CD51*CD$12 -> 10.29061 | CE46: =+CE50*CE$11+CE51*CE$12 -> 10.753687 | CF46: =+CF50*CF$11+CF51*CF$12 -> 10.753687 | CG46: =+CG58*1000/CG54 -> 10.532148 | CH46: =+CH50*CH$11+CH51*CH$12 -> 10.753687 | CI46: =+CI50*CI$11+CI51*CI$12 -> 10.753687 | CJ46: =+CJ50*CJ$11+CJ51*CJ$12 -> 11.237603 | CK46: =+CK50*CK$11+CK51*CK$12 -> 11.237603 | CL46: =+CL58*1000/CL54 -> 11.006101 | CM46: =+CM50*CM$11+CM51*CM$12 -> 11.237603 | CN46: =+CN50*CN$11+CN51*CN$12 -> 11.237603 | CO46: =+CO50*CO$11+CO51*CO$12 -> 11.743295 | CP46: =+CP50*CP$11+CP51*CP$12 -> 11.743295 | CQ46: =+CQ58*1000/CQ54 -> 11.501385 | CR46: =+CR50*CR$11+CR51*CR$12 -> 11.743295 | CS46: =+CS50*CS$11+CS51*CS$12 -> 11.743295 | CT46: =+CT50*CT$11+CT51*CT$12 -> 12.271744 | CU46: =+CU50*CU$11+CU51*CU$12 -> 12.271744 | CV46: =+CV58*1000/CV54 -> 12.018947
A47: YoY (%)
R48: 0.9
A49: Distância Total (km) | U49: =+U50+U51 -> 52.29 | V49: =+V50+V51 -> 52.29 | W49: =+W50+W51 -> 52.29 | X49: =+X50+X51 -> 52.29 | Y49: =+Y50+Y51 -> 52.29 | Z49: =+Z50+Z51 -> 52.29 | AA49: =+AA50+AA51 -> 52.29 | AB49: =+AB50+AB51 -> 52.29 | ... CV49: =+CV50+CV51 -> 52.29
A50: Pista Simples | U50: 40.89 | V50: 40.89 | W50: 40.89 | X50: 40.89 | Y50: 40.89 | Z50: 40.89 | AA50: 40.89 | AB50: 40.89 | AC50: 40.89 | AD50: 40.89 | AE50: 40.89 | AF50: 37.65 | AG50: 37.65 | AH50: 37.65 | AI50: 37.65 | AJ50: 26.59 | AK50: 26.59 | AL50: 26.59 | AM50: 26.59 | AN50: 26.59 | AO50: 26.59 | AP50: 9.54 | AQ50: 9.54 | AR50: 9.54 | AS50: 9.54 | AT50: 9.54 | AU50: 9.54 | AV50: 9.54 | AW50: 9.54 | AX50: 9.54 | AY50: 9.54 | AZ50: 9.54 | BA50: 9.54 | BB50: 9.54 | BC50: 9.54 | BD50: 9.54 | BE50: 9.54 | BF50: 9.54 | BG50: 9.54 | BH50: 9.54 | BI50: 9.54 | BJ50: 9.54 | BK50: 9.54 | BL50: 9.54 | BM50: 9.54 | BN50: 9.54 | BO50: 9.54 | BP50: 9.54 | BQ50: 9.54 | BR50: 9.54 | BS50: 9.54 | BT50: 9.54 | BU50: 9.54 | BV50: 9.54 | BW50: 9.54 | BX50: 9.54 | BY50: 9.54 | BZ50: 9.54 | CA50: 9.54 | CB50: 9.54 | CC50: 9.54 | CD50: 9.54 | CE50: 9.54 | CF50: 9.54 | CG50: 9.54 | CH50: 9.54 | CI50: 9.54 | CJ50: 9.54 | CK50: 9.54 | CL50: 9.54 | CM50: 9.54 | CN50: 9.54 | CO50: 9.54 | CP50: 9.54 | CQ50: 9.54 | CR50: 9.54 | CS50: 9.54 | CT50: 9.54 | CU50: 9.54 | CV50: 9.54
A51: Pista Dupla | U51: 11.4 | V51: 11.4 | W51: 11.4 | X51: 11.4 | Y51: 11.4 | Z51: 11.4 | AA51: 11.4 | AB51: 11.4 | AC51: 11.4 | AD51: 11.4 | AE51: 11.4 | AF51: 14.64 | AG51: 14.64 | AH51: 14.64 | AI51: 14.64 | AJ51: 25.7 | AK51: 25.7 | AL51: 25.7 | AM51: 25.7 | AN51: 25.7 | AO51: 25.7 | AP51: 42.75 | AQ51: 42.75 | AR51: 42.75 | AS51: 42.75 | AT51: 42.75 | AU51: 42.75 | AV51: 42.75 | AW51: 42.75 | AX51: 42.75 | AY51: 42.75 | AZ51: 42.75 | BA51: 42.75 | BB51: 42.75 | BC51: 42.75 | BD51: 42.75 | BE51: 42.75 | BF51: 42.75 | BG51: 42.75 | BH51: 42.75 | BI51: 42.75 | BJ51: 42.75 | BK51: 42.75 | BL51: 42.75 | BM51: 42.75 | BN51: 42.75 | BO51: 42.75 | BP51: 42.75 | BQ51: 42.75 | BR51: 42.75 | BS51: 42.75 | BT51: 42.75 | BU51: 42.75 | BV51: 42.75 | BW51: 42.75 | BX51: 42.75 | BY51: 42.75 | BZ51: 42.75 | CA51: 42.75 | CB51: 42.75 | CC51: 42.75 | CD51: 42.75 | CE51: 42.75 | CF51: 42.75 | CG51: 42.75 | CH51: 42.75 | CI51: 42.75 | CJ51: 42.75 | CK51: 42.75 | CL51: 42.75 | CM51: 42.75 | CN51: 42.75 | CO51: 42.75 | CP51: 42.75 | CQ51: 42.75 | CR51: 42.75 | CS51: 42.75 | CT51: 42.75 | CU51: 42.75 | CV51: 42.75
A52: % Pista Dupla | U52: =+U51/U49 -> 0.21801492 | V52: =+V51/V49 -> 0.21801492 | W52: =+W51/W49 -> 0.21801492 | X52: =+X51/X49 -> 0.21801492 | Y52: =+Y51/Y49 -> 0.21801492 | Z52: =+Z51/Z49 -> 0.21801492 | AA52: =+AA51/AA49 -> 0.21801492 | AB52: =+AB51/AB49 -> 0.21801492 | ... CV52: =+CV51/CV49 -> 0.81755594
A54: Tráfego (Mil Veículos Equivalentes) | D54: 326.314 | E54: 326.314 | F54: 666.426 | G54: 690.842 | H54: 722.3125 | I54: 703.8825 | J54: =+SUM(F54:I54) -> 2783.463 | K54: 672.1335 | L54: 681.1565 | M54: 732.393 | N54: 708.4595 | O54: =+SUM(K54:N54) -> 2794.1425 | P54: 670.9265 | Q54: 661.2355 | R54: 713.2205 | S54: 702.572 | T54: =+SUM(P54:S54) -> 2747.9545 | U54: 681 | V54: 706.6 | W54: 790.2 | X54: 776.4 | Y54: =+SUM(U54:X54) -> 2954.2 | Z54: 717.441 | AA54: 728.336 | AB54: 784.382 | AC54: 784.816 | AD54: =+SUM(Z54:AC54) -> 3014.975 | AE54: 742.5635 | AF54: 703.8775 | AG54: 699.574 | AH54: =AC54*(1+AH55) -> 757.888 | AI54: =+SUM(AE54:AH54) -> 2903.903 | AJ54: =AE54*(1+AJ55) -> 787.024 | AK54: =AF54*(1+AK55) -> 746.022 | AL54: =AG54*(1+AL55) -> 741.461 | AM54: =AH54*(1+AM55) -> 767.629 | AN54: =+SUM(AJ54:AM54) -> 3042.136 | AO54: =AJ54*(1+AO55) -> 771.556 | AP54: =AK54*(1+AP55) -> 740.101 | AQ54: =AL54*(1+AQ55) -> 820.047 | AR54: =AM54*(1+AR55) -> 830.22 | AS54: =+SUM(AO54:AR54) -> 3161.924 | AT54: =AO54*(1+AT55) -> 818.894 | AU54: =AP54*(1+AU55) -> 785.636 | AV54: =AQ54*(1+AV55) -> 869.905 | AW54: =AR54*(1+AW55) -> 881.034 | AX54: =+SUM(AT54:AW54) -> 3355.469 | AY54: =AT54*(1+AY55) -> 825.58 | AZ54: =AU54*(1+AZ55) -> 818.073 | BA54: =AV54*(1+BA55) -> 905.262 | BB54: =AW54*(1+BB55) -> 917.161 | BC54: =+SUM(AY54:BB54) -> 3466.076 | BD54: =AY54*(1+BD55) -> 886.606 | BE54: =AZ54*(1+BE55) -> 850.825 | BF54: =BA54*(1+BF55) -> 941.018 | BG54: =BB54*(1+BG55) -> 953.664 | BH54: =+SUM(BD54:BG54) -> 3632.113 | BI54: =BD54*(1+BI55) -> 924.183 | BJ54: =BE54*(1+BJ55) -> 886.921 | BK54: =BF54*(1+BK55) -> 980.774 | BL54: =BG54*(1+BL55) -> 994.049 | BM54: =+SUM(BI54:BL54) -> 3785.927 | BN54: =BI54*(1+BN55) -> 962.456 | BO54: =BJ54*(1+BO55) -> 923.677 | BP54: =BK54*(1+BP55) -> 1021.297 | BQ54: =BL54*(1+BQ55) -> 1035.19 | BR54: =+SUM(BN54:BQ54) -> 3942.62 | BS54: =BN54*(1+BS55) -> 1001.381 | BT54: =BO54*(1+BT55) -> 961.05 | BU54: =BP54*(1+BU55) -> 1062.544 | BV54: =BQ54*(1+BV55) -> 1077.041 | BW54: =+SUM(BS54:BV54) -> 4102.016 | BX54: =BS54*(1+BX55) -> 1040.909 | BY54: =BT54*(1+BY55) -> 998.991 | BZ54: =BU54*(1+BZ55) -> 1104.468 | CA54: =BV54*(1+CA55) -> 1119.551 | CB54: =+SUM(BX54:CA54) -> 4263.919 | CC54: =BX54*(1+CC55) -> 1080.987 | CD54: =BY54*(1+CD55) -> 1037.449 | CE54: =BZ54*(1+CE55) -> 1147.018 | CF54: =CA54*(1+CF55) -> 1162.664 | CG54: =+SUM(CC54:CF54) -> 4428.118 | CH54: =CC54*(1+CH55) -> 1121.562 | CI54: =CD54*(1+CI55) -> 1076.37 | CJ54: =CE54*(1+CJ55) -> 1190.141 | CK54: =CF54*(1+CK55) -> 1206.323 | CL54: =+SUM(CH54:CK54) -> 4594.396 | CM54: =CH54*(1+CM55) -> 1162.575 | CN54: =CI54*(1+CN55) -> 1115.697 | CO54: =CJ54*(1+CO55) -> 1233.781 | CP54: =CK54*(1+CP55) -> 1250.468 | CQ54: =+SUM(CM54:CP54) -> 4762.521 | CR54: =+CM54*(1+CR55) -> 1185.594 | CS54: =+CN54*(1+CS55) -> 1137.7878 | CT54: =+CO54*(1+CT55) -> 1258.2099 | CU54: =+CP54*(1+CU55) -> 1275.2273 | CV54: =+SUM(CR54:CU54) -> 4856.8189
A55: YoY (%) | I55: =+I54/D54-1 -> 1.1570711 | J55: =+J54/E54-1 -> 7.530014 | K55: =+K54/F54-1 -> 0.0085643417 | L55: =+L54/G54-1 -> -0.014019848 | M55: =+M54/H54-1 -> 0.013955871 | N55: =+N54/I54-1 -> 0.0065025057 | O55: =+O54/J54-1 -> 0.0038367674 | P55: =+P54/K54-1 -> -0.0017957742 | ... AG55: =+AG54/AB54-1 -> -0.10812079 | AH55: -0.034311227 | AI55: =+AI54/AD54-1 -> -0.036840106 | AJ55: 0.059874341 | AK55: 0.059874765 | AL55: 0.05987501 | AM55: 0.012852823 | AN55: =+AN54/AI54-1 -> 0.047602485 | AO55: -0.019653784 | AP55: -0.0079367633 | AQ55: 0.10598804 | AR55: 0.081538087 | AS55: =+AS54/AN54-1 -> 0.03937628 | AT55: 0.061353939 | AU55: 0.061525386 | AV55: 0.060798954 | AW55: 0.061205464 | AX55: =+AX54/AS54-1 -> 0.061211149 | AY55: 0.0081646709 | AZ55: 0.041287568 | BA55: 0.040644668 | BB55: 0.041005228 | BC55: =+BC54/AX54-1 -> 0.032963201 | BD55: 0.073918942 | BE55: 0.040035547 | BF55: 0.039497957 | BG55: 0.039799991 | BH55: =+BH54/BC54-1 -> 0.04790345 | BI55: 0.042382975 | BJ55: 0.042424705 | BK55: 0.042247863 | BL55: 0.0423472 | BM55: =+BM54/BH54-1 -> 0.042348352 | BN55: 0.041412794 | BO55: 0.041442248 | BP55: 0.041317368 | BQ55: 0.041387296 | BR55: =+BR54/BM54-1 -> 0.041388278 | BS55: 0.040443407 | BT55: 0.040461114 | BU55: 0.040386881 | BV55: 0.040428327 | BW55: =+BW54/BR54-1 -> 0.040428953 | BX55: 0.039473487 | BY55: 0.039478695 | BZ55: 0.039456248 | CA55: 0.03946925 | CB55: =+CB54/BW54-1 -> 0.039469129 | CC55: 0.038502885 | CD55: 0.038496843 | CE55: 0.038525335 | CF55: 0.038509188 | CG55: =+CG54/CB54-1 -> 0.03850894 | CH55: 0.037535141 | CI55: 0.037516061 | CJ55: 0.037595748 | CK55: 0.037550832 | CL55: =+CL54/CG54-1 -> 0.03755049 | CM55: 0.036567751 | CN55: 0.036536693 | CO55: 0.036667924 | CP55: 0.036594677 | CQ55: =+CQ54/CL54-1 -> 0.036593493 | CR55: 0.0198 | CS55: 0.0198 | CT55: 0.0198 | CU55: 0.0198 | CV55: =+CV54/CQ54-1 -> 0.0198
A56: Elasticidade PIB | J56: =+J55/(J$4/100) -> 99.952195 | K56: =+K55/(K$4/100) -> 0.20219644 | L56: =+L55/(L$4/100) -> -0.42300344 | M56: =+M55/(M$4/100) -> 0.65768576 | N56: =+N55/(N$4/100) -> 0.47586519 | O56: =+O55/(O$4/100) -> 0.14041187 | P56: =+P55/(P$4/100) -> -0.23856404 | Q56: =+Q55/(Q$4/100) -> -5.9712712 | ... X56: =+X55/(X$4/100) -> 3.0268296 | Y56: =(+Y55/(Y$4/100)) -> 2.2743694 | Z56: =+Z55/(Z$4/100) -> 2.6755507 | AA56: =+AA55/(AA$4/100) -> 1.5380696 | AB56: =+AB55/(AB$4/100) -> -0.36813465 | AC56: =+AC55/(AC$4/100) -> 0.54198867 | AD56: =(+AD55/(AD$4/100)) -> 14.228698 | AE56: =+AE55/(AE$4/100) -> -1.1295747 | AF56: =+AF55/(AF$4/100) -> 1.0832691 | AG56: =+AG55/(AG$4/100) -> 3.4877674 | AH56: =+AH55/(AH$4/100) -> 1.1068138 | AI56: =(+AI55/(AI$4/100)) -> 1.1883905 | AJ56: =+AJ55/(AJ$4/100) -> -2.993717 | AK56: =+AK55/(AK$4/100) -> -2.9937383 | AL56: =+AL55/(AL$4/100) -> -2.9937505 | AM56: =+AM55/(AM$4/100) -> -0.64264113 | AN56: =(+AN55/(AN$4/100)) -> -2.3801243 | AO56: =+AO55/(AO$4/100) -> -1.9653784 | AP56: =+AP55/(AP$4/100) -> -0.79367633 | AQ56: =+AQ55/(AQ$4/100) -> 10.598804 | AR56: =+AR55/(AR$4/100) -> 8.1538087 | AS56: =(+AS55/(AS$4/100)) -> 3.937628 | AT56: =+AT55/(AT$4/100) -> 3.067697 | AU56: =+AU55/(AU$4/100) -> 3.0762693 | AV56: =+AV55/(AV$4/100) -> 3.0399477 | AW56: =+AW55/(AW$4/100) -> 3.0602732 | AX56: =(+AX55/(AX$4/100)) -> 3.0605574 | AY56: =+AY55/(AY$4/100) -> 0.40823354 | AZ56: =+AZ55/(AZ$4/100) -> 2.0643784 | BA56: =+BA55/(BA$4/100) -> 2.0322334 | BB56: =+BB55/(BB$4/100) -> 2.0502614 | BC56: =(+BC55/(BC$4/100)) -> 1.6481601 | BD56: =+BD55/(BD$4/100) -> 3.6959471 | BE56: =+BE55/(BE$4/100) -> 2.0017773 | BF56: =+BF55/(BF$4/100) -> 1.9748979 | BG56: =+BG55/(BG$4/100) -> 1.9899996 | BH56: =(+BH55/(BH$4/100)) -> 2.3951725 | BI56: =+BI55/(BI$4/100) -> 2.1191488 | BJ56: =+BJ55/(BJ$4/100) -> 2.1212353 | BK56: =+BK55/(BK$4/100) -> 2.1123932 | BL56: =+BL55/(BL$4/100) -> 2.11736 | BM56: =(+BM55/(BM$4/100)) -> 2.1174176 | BN56: =+BN55/(BN$4/100) -> 2.0706397 | BO56: =+BO55/(BO$4/100) -> 2.0721124 | BP56: =+BP55/(BP$4/100) -> 2.0658684 | BQ56: =+BQ55/(BQ$4/100) -> 2.0693648 | BR56: =(+BR55/(BR$4/100)) -> 2.0694139 | BS56: =+BS55/(BS$4/100) -> 2.0221704 | BT56: =+BT55/(BT$4/100) -> 2.0230557 | BU56: =+BU55/(BU$4/100) -> 2.019344 | BV56: =+BV55/(BV$4/100) -> 2.0214164 | BW56: =(+BW55/(BW$4/100)) -> 2.0214477 | BX56: =+BX55/(BX$4/100) -> 1.9736744 | BY56: =+BY55/(BY$4/100) -> 1.9739348 | BZ56: =+BZ55/(BZ$4/100) -> 1.9728124 | CA56: =+CA55/(CA$4/100) -> 1.9734625 | CB56: =(+CB55/(CB$4/100)) -> 1.9734565 | CC56: =+CC55/(CC$4/100) -> 1.9251443 | CD56: =+CD55/(CD$4/100) -> 1.9248422 | CE56: =+CE55/(CE$4/100) -> 1.9262668 | CF56: =+CF55/(CF$4/100) -> 1.9254594 | CG56: =(+CG55/(CG$4/100)) -> 1.925447 | CH56: =+CH55/(CH$4/100) -> 1.8767571 | CI56: =+CI55/(CI$4/100) -> 1.8758031 | CJ56: =+CJ55/(CJ$4/100) -> 1.8797874 | CK56: =+CK55/(CK$4/100) -> 1.8775416 | CL56: =(+CL55/(CL$4/100)) -> 1.8775245 | CM56: =+CM55/(CM$4/100) -> 1.8283876 | CN56: =+CN55/(CN$4/100) -> 1.8268346 | CO56: =+CO55/(CO$4/100) -> 1.8333962 | CP56: =+CP55/(CP$4/100) -> 1.8297338 | CQ56: =(+CQ55/(CQ$4/100)) -> 1.8296747 | CR56: =+CR55/(CR$4/100) -> 0.99 | CS56: =+CS55/(CS$4/100) -> 0.99 | CT56: =+CT55/(CT$4/100) -> 0.99 | CU56: =+CU55/(CU$4/100) -> 0.99 | CV56: =(+CV55/(CV$4/100)) -> 0.99
A58: Receita de Pedágio | R58: =+R54*R46/1000 -> 3.3521364 | S58: =+S54*S46/1000 -> 3.3020884 | T58: =+T54*T46/1000 -> 12.915386 | U58: =+U54*U46/1000 -> 3.2007 | V58: =+V54*V46/1000 -> 3.331685 | W58: =+W54*W46/1000 -> 3.7258668 | X58: =+X54*X46/1000 -> 3.6607985 | Y58: =+SUM(U58:X58) -> 13.91905 | Z58: =+Z54*Z46/1000 -> 3.3828013 | AA58: =+AA54*AA46/1000 -> 3.4341723 | AB58: =+AB54*AB46/1000 -> 3.935504 | AC58: =+AC54*AC46/1000 -> 3.9376816 | AD58: =+SUM(Z58:AC58) -> 14.690159 | AE58: =+AE54*AE46/1000 -> 3.7256868 | AF58: =+AF54*AF46/1000 -> 3.6120864 | AG58: =+AG54*AG46/1000 -> 3.9490023 | AH58: =+AH54*AH46/1000 -> 4.2781771 | AI58: =+SUM(AE58:AH58) -> 15.564953 | AJ58: =+AJ54*AJ46/1000 -> 4.7806251 | AK58: =+AK54*AK46/1000 -> 4.5315664 | AL58: =+AL54*AL46/1000 -> 4.7921086 | AM58: =+AM54*AM46/1000 -> 4.961234 | AN58: =+SUM(AJ58:AM58) -> 19.065534 | AO58: =+AO54*AO46/1000 -> 4.9866145 | AP58: =+AP54*AP46/1000 -> 5.3046381 | AQ58: =+AQ54*AQ46/1000 -> 6.1715296 | AR58: =+AR54*AR46/1000 -> 6.2480898 | AS58: =+SUM(AO58:AR58) -> 22.710872 | AT58: =+AT54*AT46/1000 -> 6.1628523 | AU58: =+AU54*AU46/1000 -> 5.9125584 | AV58: =+AV54*AV46/1000 -> 6.8740897 | AW58: =+AW54*AW46/1000 -> 6.9620324 | AX58: =+SUM(AT58:AW58) -> 25.911533 | AY58: =+AY54*AY46/1000 -> 6.5238285 | AZ58: =+AZ54*AZ46/1000 -> 6.4645073 | BA58: =+BA54*BA46/1000 -> 7.4753916 | BB58: =+BB54*BB46/1000 -> 7.5736501 | BC58: =+SUM(AY58:BB58) -> 28.037377 | BD58: =+BD54*BD46/1000 -> 7.3213358 | BE58: =+BE54*BE46/1000 -> 7.0258666 | BF58: =+BF54*BF46/1000 -> 8.1203338 | BG58: =+BG54*BG46/1000 -> 8.22946 | BH58: =+SUM(BD58:BG58) -> 30.696996 | BI58: =+BI54*BI46/1000 -> 7.9750594 | BJ58: =+BJ54*BJ46/1000 -> 7.6535141 | BK58: =+BK54*BK46/1000 -> 8.8442535 | BL58: =+BL54*BL46/1000 -> 8.9639625 | BM58: =+SUM(BI58:BL58) -> 33.43679 | BN58: =+BN54*BN46/1000 -> 8.6790687 | BO58: =+BO54*BO46/1000 -> 8.3293741 | BP58: =+BP54*BP46/1000 -> 9.6241102 | BQ58: =+BQ54*BQ46/1000 -> 9.7550298 | BR58: =+SUM(BN58:BQ58) -> 36.387583 | BS58: =+BS54*BS46/1000 -> 9.4364334 | BT58: =+BT54*BT46/1000 -> 9.0563774 | BU58: =+BU54*BU46/1000 -> 10.463374 | BV58: =+BV54*BV46/1000 -> 10.606133 | BW58: =+SUM(BS58:BV58) -> 39.562317 | BX58: =+BX54*BX46/1000 -> 10.250324 | BY58: =+BY54*BY46/1000 -> 9.8375374 | BZ58: =+BZ54*BZ46/1000 -> 11.365649 | CA58: =+CA54*CA46/1000 -> 11.520863 | CB58: =+SUM(BX58:CA58) -> 42.974373 | CC58: =+CC54*CC46/1000 -> 11.124015 | CD58: =+CD54*CD46/1000 -> 10.675983 | CE58: =+CE54*CE46/1000 -> 12.334673 | CF58: =+CF54*CF46/1000 -> 12.502925 | CG58: =+SUM(CC58:CF58) -> 46.637596 | CH58: =+CH54*CH46/1000 -> 12.060927 | CI58: =+CI54*CI46/1000 -> 11.574946 | CJ58: =+CJ54*CJ46/1000 -> 13.374332 | CK58: =+CK54*CK46/1000 -> 13.556179 | CL58: =+SUM(CH58:CK58) -> 50.566385 | CM58: =+CM54*CM46/1000 -> 13.064557 | CN58: =+CN54*CN46/1000 -> 12.53776 | CO58: =+CO54*CO46/1000 -> 14.488655 | CP58: =+CP54*CP46/1000 -> 14.684615 | CQ58: =+SUM(CM58:CP58) -> 54.775586 | CR58: =+CR54*CR46/1000 -> 13.92278 | CS58: =+CS54*CS46/1000 -> 13.361378 | CT58: =+CT54*CT46/1000 -> 15.440429 | CU58: =+CU54*CU46/1000 -> 15.649262 | CV58: =+SUM(CR58:CU58) -> 58.373849
A59: % Y/Y
A61: Praça Rafard | U61: =+U74/U$35 -> 0.041843512 | Y61: =+Y74/Y$35 -> 0.044303044 | AD61: =+AD74/AD$35 -> 0.044820036 | AI61: =+AI74/AI$35 -> 0.042210472 | AN61: =+AN74/AN$35 -> 0.040934798 | AS61: =+AS74/AS$35 -> 0.042875119 | AX61: =+AX74/AX$35 -> 0.041186155 | BC61: =+BC74/BC$35 -> 0.040150212 | BH61: =+BH74/BH$35 -> 0.039308359 | BM61: =+BM74/BM$35 -> 0.039296577 | BR61: =+BR74/BR$35 -> 0.03928332 | BW61: =+BW74/BW$35 -> 0.039241011 | CB61: =+CB74/CB$35 -> 0.039228382 | CG61: =+CG74/CG$35 -> 0.039230742 | CL61: =+CL74/CL$35 -> 0.039237369 | CQ61: =+CQ74/CQ$35 -> 0.039248258 | CV61: =+CV74/CV$35 -> 0.039048767
A62: Tarifa (R$) | R62: 3.7 | S62: 3.7 | T62: 3.7 | U62: 3.7 | V62: =+V66*V$11+V67*V$12 -> 3.686683 | W62: =+W66*W$11+W67*W$12 -> 3.686683 | X62: =+X66*X$11+X67*X$12 -> 3.686683 | Y62: =+Y74*1000/Y70 -> 3.6896073 | Z62: =+Z66*Z$11+Z67*Z$12 -> 3.686683 | AA62: =+AA66*AA$11+AA67*AA$12 -> 3.686683 | AB62: =+AB66*AB$11+AB67*AB$12 -> 3.9229994 | AC62: =+AC66*AC$11+AC67*AC$12 -> 3.9229994 | AD62: =+AD74*1000/AD70 -> 3.8097523 | AE62: =+AE66*AE$11+AE67*AE$12 -> 3.9229994 | AF62: =+AF66*AF$11+AF67*AF$12 -> 3.9759469 | AG62: =+AG66*AG$11+AG67*AG$12 -> 4.3735416 | AH62: =+AH66*AH$11+AH67*AH$12 -> 4.3735416 | AI62: =+AI74*1000/AI70 -> 4.1454292 | AJ62: =+AJ66*AJ$11+AJ67*AJ$12 -> 4.3735416 | AK62: =+AK66*AK$11+AK67*AK$12 -> 4.3735416 | AL62: =+AL66*AL$11+AL67*AL$12 -> 4.6534482 | AM62: =+AM66*AM$11+AM67*AM$12 -> 4.6534482 | AN62: =+AN74*1000/AN70 -> 4.5017665 | AO62: =+AO66*AO$11+AO67*AO$12 -> 4.6534482 | AP62: =+AP66*AP$11+AP67*AP$12 -> 4.6534482 | AQ62: =+AQ66*AQ$11+AQ67*AQ$12 -> 4.8861206 | AR62: =+AR66*AR$11+AR67*AR$12 -> 4.8861206 | AS62: =+AS74*1000/AS70 -> 4.7735877 | AT62: =+AT66*AT$11+AT67*AT$12 -> 4.8861206 | AU62: =+AU66*AU$11+AU67*AU$12 -> 4.8861206 | AV62: =+AV66*AV$11+AV67*AV$12 -> 5.1304267 | AW62: =+AW66*AW$11+AW67*AW$12 -> 5.1304267 | AX62: =+AX74*1000/AX70 -> 5.0122587 | AY62: =+AY66*AY$11+AY67*AY$12 -> 5.1304267 | AZ62: =+AZ66*AZ$11+AZ67*AZ$12 -> 5.1304267 | BA62: =+BA66*BA$11+BA67*BA$12 -> 5.3612959 | BB62: =+BB66*BB$11+BB67*BB$12 -> 5.3612959 | BC62: =+BC74*1000/BC70 -> 5.2496199 | BD62: =+BD66*BD$11+BD67*BD$12 -> 5.3612959 | BE62: =+BE66*BE$11+BE67*BE$12 -> 5.3612959 | BF62: =+BF66*BF$11+BF67*BF$12 -> 5.6025542 | BG62: =+BG66*BG$11+BG67*BG$12 -> 5.6025542 | BH62: =+BH74*1000/BH70 -> 5.4858465 | BI62: =+BI66*BI$11+BI67*BI$12 -> 5.6025542 | BJ62: =+BJ66*BJ$11+BJ67*BJ$12 -> 5.6025542 | BK62: =+BK66*BK$11+BK67*BK$12 -> 5.8546691 | BL62: =+BL66*BL$11+BL67*BL$12 -> 5.8546691 | BM62: =+BM74*1000/BM70 -> 5.7327074 | BN62: =+BN66*BN$11+BN67*BN$12 -> 5.8546691 | BO62: =+BO66*BO$11+BO67*BO$12 -> 5.8546691 | BP62: =+BP66*BP$11+BP67*BP$12 -> 6.1181292 | BQ62: =+BQ66*BQ$11+BQ67*BQ$12 -> 6.1181292 | BR62: =+BR74*1000/BR70 -> 5.9906777 | BS62: =+BS66*BS$11+BS67*BS$12 -> 6.1181292 | BT62: =+BT66*BT$11+BT67*BT$12 -> 6.1181292 | BU62: =+BU66*BU$11+BU67*BU$12 -> 6.393445 | BV62: =+BV66*BV$11+BV67*BV$12 -> 6.393445 | BW62: =+BW74*1000/BW70 -> 6.2602571 | BX62: =+BX66*BX$11+BX67*BX$12 -> 6.393445 | BY62: =+BY66*BY$11+BY67*BY$12 -> 6.393445 | BZ62: =+BZ66*BZ$11+BZ67*BZ$12 -> 6.6811501 | CA62: =+CA66*CA$11+CA67*CA$12 -> 6.6811501 | CB62: =+CB74*1000/CB70 -> 6.5419684 | CC62: =+CC66*CC$11+CC67*CC$12 -> 6.6811501 | CD62: =+CD66*CD$11+CD67*CD$12 -> 6.6811501 | CE62: =+CE66*CE$11+CE67*CE$12 -> 6.9818018 | CF62: =+CF66*CF$11+CF67*CF$12 -> 6.9818018 | CG62: =+CG74*1000/CG70 -> 6.8363574 | CH62: =+CH66*CH$11+CH67*CH$12 -> 6.9818018 | CI62: =+CI66*CI$11+CI67*CI$12 -> 6.9818018 | CJ62: =+CJ66*CJ$11+CJ67*CJ$12 -> 7.2959829 | CK62: =+CK66*CK$11+CK67*CK$12 -> 7.2959829 | CL62: =+CL74*1000/CL70 -> 7.1439947 | CM62: =+CM66*CM$11+CM67*CM$12 -> 7.2959829 | CN62: =+CN66*CN$11+CN67*CN$12 -> 7.2959829 | CO62: =+CO66*CO$11+CO67*CO$12 -> 7.6243021 | CP62: =+CP66*CP$11+CP67*CP$12 -> 7.6243021 | CQ62: =+CQ74*1000/CQ70 -> 7.4654766 | CR62: =+CR66*CR$11+CR67*CR$12 -> 7.6243021 | CS62: =+CS66*CS$11+CS67*CS$12 -> 7.6243021 | CT62: =+CT66*CT$11+CT67*CT$12 -> 7.9673957 | CU62: =+CU66*CU$11+CU67*CU$12 -> 7.9673957 | CV62: =+CV74*1000/CV70 -> 7.801423
A63: YoY (%)
A65: Distância Total (km) | U65: =+U66+U67 -> 44.5 | V65: =+V66+V67 -> 44.45 | W65: =+W66+W67 -> 44.45 | X65: =+X66+X67 -> 44.45 | Y65: =+Y66+Y67 -> 44.45 | Z65: =+Z66+Z67 -> 44.45 | AA65: =+AA66+AA67 -> 44.45 | AB65: =+AB66+AB67 -> 44.45 | ... CV65: =+CV66+CV67 -> 44.45
A66: Pista Simples | U66: 44.5 | V66: 44.45 | W66: 44.45 | X66: 44.45 | Y66: 44.45 | Z66: 44.45 | AA66: 44.45 | AB66: 44.45 | AC66: 44.45 | AD66: 44.45 | AE66: 44.45 | AF66: 42.95 | AG66: 42.95 | AH66: 42.95 | AI66: 42.95 | AJ66: 42.95 | AK66: 42.95 | AL66: 42.95 | AM66: 42.95 | AN66: 42.95 | AO66: 42.95 | AP66: 42.95 | AQ66: 42.95 | AR66: 42.95 | AS66: 42.95 | AT66: 42.95 | AU66: 42.95 | AV66: 42.95 | AW66: 42.95 | AX66: 42.95 | AY66: 42.95 | AZ66: 42.95 | BA66: 42.95 | BB66: 42.95 | BC66: 42.95 | BD66: 42.95 | BE66: 42.95 | BF66: 42.95 | BG66: 42.95 | BH66: 42.95 | BI66: 42.95 | BJ66: 42.95 | BK66: 42.95 | BL66: 42.95 | BM66: 42.95 | BN66: 42.95 | BO66: 42.95 | BP66: 42.95 | BQ66: 42.95 | BR66: 42.95 | BS66: 42.95 | BT66: 42.95 | BU66: 42.95 | BV66: 42.95 | BW66: 42.95 | BX66: 42.95 | BY66: 42.95 | BZ66: 42.95 | CA66: 42.95 | CB66: 42.95 | CC66: 42.95 | CD66: 42.95 | CE66: 42.95 | CF66: 42.95 | CG66: 42.95 | CH66: 42.95 | CI66: 42.95 | CJ66: 42.95 | CK66: 42.95 | CL66: 42.95 | CM66: 42.95 | CN66: 42.95 | CO66: 42.95 | CP66: 42.95 | CQ66: 42.95 | CR66: 42.95 | CS66: 42.95 | CT66: 42.95 | CU66: 42.95 | CV66: 42.95
A67: Pista Dupla | U67: 0 | V67: 0 | W67: 0 | X67: 0 | Y67: 0 | Z67: 0 | AA67: 0 | AB67: 0 | AC67: 0 | AD67: 0 | AE67: 0 | AF67: 1.5 | AG67: 1.5 | AH67: 1.5 | AI67: 1.5 | AJ67: 1.5 | AK67: 1.5 | AL67: 1.5 | AM67: 1.5 | AN67: 1.5 | AO67: 1.5 | AP67: 1.5 | AQ67: 1.5 | AR67: 1.5 | AS67: 1.5 | AT67: 1.5 | AU67: 1.5 | AV67: 1.5 | AW67: 1.5 | AX67: 1.5 | AY67: 1.5 | AZ67: 1.5 | BA67: 1.5 | BB67: 1.5 | BC67: 1.5 | BD67: 1.5 | BE67: 1.5 | BF67: 1.5 | BG67: 1.5 | BH67: 1.5 | BI67: 1.5 | BJ67: 1.5 | BK67: 1.5 | BL67: 1.5 | BM67: 1.5 | BN67: 1.5 | BO67: 1.5 | BP67: 1.5 | BQ67: 1.5 | BR67: 1.5 | BS67: 1.5 | BT67: 1.5 | BU67: 1.5 | BV67: 1.5 | BW67: 1.5 | BX67: 1.5 | BY67: 1.5 | BZ67: 1.5 | CA67: 1.5 | CB67: 1.5 | CC67: 1.5 | CD67: 1.5 | CE67: 1.5 | CF67: 1.5 | CG67: 1.5 | CH67: 1.5 | CI67: 1.5 | CJ67: 1.5 | CK67: 1.5 | CL67: 1.5 | CM67: 1.5 | CN67: 1.5 | CO67: 1.5 | CP67: 1.5 | CQ67: 1.5 | CR67: 1.5 | CS67: 1.5 | CT67: 1.5 | CU67: 1.5 | CV67: 1.5
A68: % Pista Dupla | U68: =+U67/U65 -> 0 | V68: =+V67/V65 -> 0 | W68: =+W67/W65 -> 0 | X68: =+X67/X65 -> 0 | Y68: =+Y67/Y65 -> 0 | Z68: =+Z67/Z65 -> 0 | AA68: =+AA67/AA65 -> 0 | AB68: =+AB67/AB65 -> 0 | ... CV68: =+CV67/CV65 -> 0.033745782
A70: Tráfego (Mil Veículos Equivalentes) | D70: 231.582 | E70: 231.582 | F70: 479.608 | G70: 492.7085 | H70: 520.2655 | I70: 503.887 | J70: 1996.469 | K70: 466.27 | L70: 471.195 | M70: 514.0335 | N70: 488.4205 | O70: 1939.919 | P70: 474.762 | Q70: 468.3235 | R70: 530.9655 | S70: 527.991 | T70: 2002.042 | U70: 490.7 | V70: 505.8 | W70: 614 | X70: 624.1 | Y70: =+SUM(U70:X70) -> 2234.6 | Z70: 558.369 | AA70: 588.65 | AB70: 617.848 | AC70: 628.655 | AD70: =+SUM(Z70:AC70) -> 2393.522 | AE70: 606.3495 | AF70: 547.529 | AG70: 489.69 | AH70: =AC70*(1+AH71) -> 508.356 | AI70: =+SUM(AE70:AH70) -> 2151.9245 | AJ70: =AE70*(1+AJ71) -> 642.655 | AK70: =AF70*(1+AK71) -> 580.312 | AL70: =AG70*(1+AL71) -> 519.01 | AM70: =AH70*(1+AM71) -> 514.831 | AN70: =+SUM(AJ70:AM70) -> 2256.808 | AO70: =AJ70*(1+AO71) -> 626.126 | AP70: =AK70*(1+AP71) -> 594.201 | AQ70: =AL70*(1+AQ71) -> 641.25 | AR70: =AM70*(1+AR71) -> 661.564 | AS70: =+SUM(AO70:AR70) -> 2523.141 | AT70: =AO70*(1+AT71) -> 662.719 | AU70: =AP70*(1+AU71) -> 629.101 | AV70: =AQ70*(1+AV71) -> 678.659 | AW70: =AR70*(1+AW71) -> 700.291 | AX70: =+SUM(AT70:AW70) -> 2670.77 | AY70: =AT70*(1+AY71) -> 688.268 | AZ70: =AU70*(1+AZ71) -> 653.516 | BA70: =AV70*(1+BA71) -> 704.757 | BB70: =AW70*(1+BB71) -> 727.348 | BC70: =+SUM(AY70:BB70) -> 2773.889 | BD70: =AY70*(1+BD71) -> 714.251 | BE70: =AZ70*(1+BE71) -> 678.328 | BF70: =BA70*(1+BF71) -> 731.306 | BG70: =BB70*(1+BG71) -> 754.857 | BH70: =+SUM(BD70:BG70) -> 2878.742 | BI70: =BD70*(1+BI71) -> 744.014 | BJ70: =BE70*(1+BJ71) -> 706.642 | BK70: =BF70*(1+BK71) -> 761.76 | BL70: =BG70*(1+BL71) -> 786.33 | BM70: =+SUM(BI70:BL70) -> 2998.746 | BN70: =BI70*(1+BN71) -> 774.45 | BO70: =BJ70*(1+BO71) -> 735.585 | BP70: =BK70*(1+BP71) -> 792.908 | BQ70: =BL70*(1+BQ71) -> 818.51 | BR70: =+SUM(BN70:BQ70) -> 3121.453 | BS70: =BN70*(1+BS71) -> 805.54 | BT70: =BO70*(1+BT71) -> 765.138 | BU70: =BP70*(1+BU71) -> 824.73 | BV70: =BQ70*(1+BV71) -> 851.377 | BW70: =+SUM(BS70:BV70) -> 3246.785 | BX70: =BS70*(1+BX71) -> 837.264 | BY70: =BT70*(1+BY71) -> 795.277 | BZ70: =BU70*(1+BZ71) -> 857.207 | CA70: =BV70*(1+CA71) -> 884.909 | CB70: =+SUM(BX70:CA70) -> 3374.657 | CC70: =BX70*(1+CC71) -> 869.598 | CD70: =BY70*(1+CD71) -> 825.981 | CE70: =BZ70*(1+CE71) -> 890.315 | CF70: =CA70*(1+CF71) -> 919.08 | CG70: =+SUM(CC70:CF70) -> 3504.974 | CH70: =CC70*(1+CH71) -> 902.518 | CI70: =CD70*(1+CI71) -> 857.223 | CJ70: =CE70*(1+CJ71) -> 924.03 | CK70: =CF70*(1+CK71) -> 953.863 | CL70: =+SUM(CH70:CK70) -> 3637.634 | CM70: =CH70*(1+CM71) -> 935.998 | CN70: =CI70*(1+CN71) -> 888.977 | CO70: =CJ70*(1+CO71) -> 958.326 | CP70: =CK70*(1+CP71) -> 989.231 | CQ70: =+SUM(CM70:CP70) -> 3772.532 | CR70: =+CM70*(1+CR71) -> 950.03797 | CS70: =+CN70*(1+CS71) -> 902.31166 | CT70: =+CO70*(1+CT71) -> 972.70089 | CU70: =+CP70*(1+CU71) -> 1004.0695 | CV70: =+SUM(CR70:CU70) -> 3829.12
A71: YoY (%) | I71: =+I70/D70-1 -> 1.175847 | J71: =+J70/E70-1 -> 7.6210025 | K71: =+K70/F70-1 -> -0.027810212 | L71: =+L70/G70-1 -> -0.043663748 | M71: =+M70/H70-1 -> -0.011978499 | N71: =+N70/I70-1 -> -0.030694382 | O71: =+O70/J70-1 -> -0.028325008 | P71: =+P70/K70-1 -> 0.018212624 | ... AG71: =+AG70/AB70-1 -> -0.20742642 | AH71: -0.19135933 | AI71: =+AI70/AD70-1 -> -0.10093807 | AJ71: 0.059875534 | AK71: 0.059874454 | AL71: 0.059874615 | AM71: 0.012737137 | AN71: =+AN70/AI70-1 -> 0.048739396 | AO71: -0.025719865 | AP71: 0.023933677 | AQ71: 0.23552533 | AR71: 0.28501197 | AS71: =+AS70/AN70-1 -> 0.11801314 | AT71: 0.058443508 | AU71: 0.058734334 | AV71: 0.058337622 | AW71: 0.058538554 | AX71: =+AX70/AS70-1 -> 0.058510008 | AY71: 0.038551784 | AZ71: 0.038809349 | BA71: 0.038455248 | BB71: 0.038636795 | BC71: =+BC70/AX70-1 -> 0.038610214 | BD71: 0.037751283 | BE71: 0.037966936 | BF71: 0.037671141 | BG71: 0.037820961 | BH71: =+BH70/BC70-1 -> 0.037799998 | BI71: 0.041670225 | BJ71: 0.041740869 | BK71: 0.041643307 | BL71: 0.04169399 | BM71: =+BM70/BH70-1 -> 0.041686264 | BN71: 0.040907832 | BO71: 0.040958505 | BP71: 0.040889519 | BQ71: 0.040924294 | BR71: =+BR70/BM70-1 -> 0.040919438 | BS71: 0.040144619 | BT71: 0.040176186 | BU71: 0.040133282 | BV71: 0.040154671 | BW71: =+BW70/BR70-1 -> 0.040151814 | BX71: 0.039382278 | BY71: 0.03939028 | BZ71: 0.039378948 | CA71: 0.039385607 | CB71: =+CB70/BW70-1 -> 0.039384191 | CC71: 0.038618644 | CD71: 0.038607932 | CE71: 0.03862311 | CF71: 0.03861527 | CG71: =+CG70/CB70-1 -> 0.038616369 | CH71: 0.037856573 | CI71: 0.037824115 | CJ71: 0.03786862 | CK71: 0.037845454 | CL71: =+CL70/CG70-1 -> 0.037849068 | CM71: 0.037096213 | CN71: 0.03704287 | CO71: 0.037115678 | CP71: 0.0370787 | CQ71: =+CQ70/CL70-1 -> 0.037083995 | CR71: 0.015 | CS71: 0.015 | CT71: 0.015 | CU71: 0.015 | CV71: =+CV70/CQ70-1 -> 0.015
A72: Elasticidade PIB | J72: =+J71/(J$4/100) -> 101.15996 | K72: =+K71/(K$4/100) -> -0.65657421 | L72: =+L71/(L$4/100) -> -1.317412 | M72: =+M71/(M$4/100) -> -0.56449996 | N72: =+N71/(N$4/100) -> -2.2462707 | O72: =+O71/(O$4/100) -> -1.0365933 | P72: =+P71/(P$4/100) -> 2.4195007 | Q72: =+Q71/(Q$4/100) -> -1.2442588 | ... S72: =+S71/(S$4/100) -> 2.7463484 | T72: =(+T71/(T$4/100)) -> 3.2023502 | U72: =+U71/(U$4/100) -> 1.2402899 | V72: =(+V71/(V$4/100)) -> 2.4249296 | W72: =(+W71/(W$4/100)) -> 4.0739193 | X72: =(+X71/(X$4/100)) -> 5.2431858 | Y72: =(+Y71/(Y$4/100)) -> 3.5200121 | Z72: =+Z71/(Z$4/100) -> 6.8951498 | AA72: =(+AA71/(AA$4/100)) -> 8.189996 | AB72: =(+AB71/(AB$4/100)) -> 0.31335505 | AC72: =(+AC71/(AC$4/100)) -> 0.36492549 | AD72: =(+AD71/(AD$4/100)) -> 49.188585 | AE72: =+AE71/(AE$4/100) -> -2.7719269 | AF72: =+AF71/(AF$4/100) -> 2.2534339 | AG72: =+AG71/(AG$4/100) -> 6.6911749 | AH72: =+AH71/(AH$4/100) -> 6.1728816 | AI72: =(+AI71/(AI$4/100)) -> 3.2560669 | AJ72: =+AJ71/(AJ$4/100) -> -2.9937767 | AK72: =+AK71/(AK$4/100) -> -2.9937227 | AL72: =+AL71/(AL$4/100) -> -2.9937307 | AM72: =+AM71/(AM$4/100) -> -0.63685685 | AN72: =(+AN71/(AN$4/100)) -> -2.4369698 | AO72: =+AO71/(AO$4/100) -> -2.5719865 | AP72: =+AP71/(AP$4/100) -> 2.3933677 | AQ72: =+AQ71/(AQ$4/100) -> 23.552533 | AR72: =+AR71/(AR$4/100) -> 28.501197 | AS72: =(+AS71/(AS$4/100)) -> 11.801314 | AT72: =+AT71/(AT$4/100) -> 2.9221754 | AU72: =+AU71/(AU$4/100) -> 2.9367167 | AV72: =+AV71/(AV$4/100) -> 2.9168811 | AW72: =+AW71/(AW$4/100) -> 2.9269277 | AX72: =(+AX71/(AX$4/100)) -> 2.9255004 | AY72: =+AY71/(AY$4/100) -> 1.9275892 | AZ72: =+AZ71/(AZ$4/100) -> 1.9404674 | BA72: =+BA71/(BA$4/100) -> 1.9227624 | BB72: =+BB71/(BB$4/100) -> 1.9318398 | BC72: =(+BC71/(BC$4/100)) -> 1.9305107 | BD72: =+BD71/(BD$4/100) -> 1.8875641 | BE72: =+BE71/(BE$4/100) -> 1.8983468 | BF72: =+BF71/(BF$4/100) -> 1.883557 | BG72: =+BG71/(BG$4/100) -> 1.891048 | BH72: =(+BH71/(BH$4/100)) -> 1.8899999 | BI72: =+BI71/(BI$4/100) -> 2.0835113 | BJ72: =+BJ71/(BJ$4/100) -> 2.0870434 | BK72: =+BK71/(BK$4/100) -> 2.0821653 | BL72: =+BL71/(BL$4/100) -> 2.0846995 | BM72: =(+BM71/(BM$4/100)) -> 2.0843132 | BN72: =+BN71/(BN$4/100) -> 2.0453916 | BO72: =+BO71/(BO$4/100) -> 2.0479253 | BP72: =+BP71/(BP$4/100) -> 2.044476 | BQ72: =+BQ71/(BQ$4/100) -> 2.0462147 | BR72: =(+BR71/(BR$4/100)) -> 2.0459719 | BS72: =+BS71/(BS$4/100) -> 2.0072309 | BT72: =+BT71/(BT$4/100) -> 2.0088093 | BU72: =+BU71/(BU$4/100) -> 2.0066641 | BV72: =+BV71/(BV$4/100) -> 2.0077336 | BW72: =(+BW71/(BW$4/100)) -> 2.0075907 | BX72: =+BX71/(BX$4/100) -> 1.9691139 | BY72: =+BY71/(BY$4/100) -> 1.969514 | BZ72: =+BZ71/(BZ$4/100) -> 1.9689474 | CA72: =+CA71/(CA$4/100) -> 1.9692804 | CB72: =(+CB71/(CB$4/100)) -> 1.9692095 | CC72: =+CC71/(CC$4/100) -> 1.9309322 | CD72: =+CD71/(CD$4/100) -> 1.9303966 | CE72: =+CE71/(CE$4/100) -> 1.9311555 | CF72: =+CF71/(CF$4/100) -> 1.9307635 | CG72: =(+CG71/(CG$4/100)) -> 1.9308185 | CH72: =+CH71/(CH$4/100) -> 1.8928286 | CI72: =+CI71/(CI$4/100) -> 1.8912057 | CJ72: =+CJ71/(CJ$4/100) -> 1.893431 | CK72: =+CK71/(CK$4/100) -> 1.8922727 | CL72: =(+CL71/(CL$4/100)) -> 1.8924534 | CM72: =+CM71/(CM$4/100) -> 1.8548107 | CN72: =+CN71/(CN$4/100) -> 1.8521435 | CO72: =+CO71/(CO$4/100) -> 1.8557839 | CP72: =+CP71/(CP$4/100) -> 1.853935 | CQ72: =(+CQ71/(CQ$4/100)) -> 1.8541997 | CR72: =+CR71/(CR$4/100) -> 0.75 | CS72: =+CS71/(CS$4/100) -> 0.75 | CT72: =+CT71/(CT$4/100) -> 0.75 | CU72: =+CU71/(CU$4/100) -> 0.75 | CV72: =(+CV71/(CV$4/100)) -> 0.75
A74: Receita de Pedágio | R74: =+R70*R62/1000 -> 1.9645724 | S74: =+S70*S62/1000 -> 1.9535667 | T74: =+T70*T62/1000 -> 7.4075554 | U74: =+U70*U62/1000 -> 1.81559 | V74: =+V70*V62/1000 -> 1.8647243 | W74: =+W70*W62/1000 -> 2.2636234 | X74: =+X70*X62/1000 -> 2.3008589 | Y74: =+SUM(U74:X74) -> 8.2447965 | Z74: =+Z70*Z62/1000 -> 2.0585295 | AA74: =+AA70*AA62/1000 -> 2.1701659 | AB74: =+AB70*AB62/1000 -> 2.4238173 | AC74: =+AC70*AC62/1000 -> 2.4662132 | AD74: =+SUM(Z74:AC74) -> 9.1187259 | AE74: =+AE70*AE62/1000 -> 2.3787087 | AF74: =+AF70*AF62/1000 -> 2.1769462 | AG74: =+AG70*AG62/1000 -> 2.1416796 | AH74: =+AH70*AH62/1000 -> 2.2233161 | AI74: =+SUM(AE74:AH74) -> 8.9206506 | AJ74: =+AJ70*AJ62/1000 -> 2.8106783 | AK74: =+AK70*AK62/1000 -> 2.5380186 | AL74: =+AL70*AL62/1000 -> 2.4151862 | AM74: =+AM70*AM62/1000 -> 2.3957394 | AN74: =+SUM(AJ74:AM74) -> 10.159623 | AO74: =+AO70*AO62/1000 -> 2.9136449 | AP74: =+AP70*AP62/1000 -> 2.7650836 | AQ74: =+AQ70*AQ62/1000 -> 3.1332249 | AR74: =+AR70*AR62/1000 -> 3.2324815 | AS74: =+SUM(AO74:AR74) -> 12.044435 | AT74: =+AT70*AT62/1000 -> 3.238125 | AU74: =+AU70*AU62/1000 -> 3.0738634 | AV74: =+AV70*AV62/1000 -> 3.4818102 | AW74: =+AW70*AW62/1000 -> 3.5927916 | AX74: =+SUM(AT74:AW74) -> 13.38659 | AY74: =+AY70*AY62/1000 -> 3.5311085 | AZ74: =+AZ70*AZ62/1000 -> 3.3528159 | BA74: =+BA70*BA62/1000 -> 3.7784108 | BB74: =+BB70*BB62/1000 -> 3.8995278 | BC74: =+SUM(AY74:BB74) -> 14.561863 | BD74: =+BD70*BD62/1000 -> 3.8293109 | BE74: =+BE70*BE62/1000 -> 3.6367171 | BF74: =+BF70*BF62/1000 -> 4.0971815 | BG74: =+BG70*BG62/1000 -> 4.2291272 | BH74: =+SUM(BD74:BG74) -> 15.792337 | BI74: =+BI70*BI62/1000 -> 4.1683787 | BJ74: =+BJ70*BJ62/1000 -> 3.9590001 | BK74: =+BK70*BK62/1000 -> 4.4598527 | BL74: =+BL70*BL62/1000 -> 4.603702 | BM74: =+SUM(BI74:BL74) -> 17.190934 | BN74: =+BN70*BN62/1000 -> 4.5341485 | BO74: =+BO70*BO62/1000 -> 4.3066068 | BP74: =+BP70*BP62/1000 -> 4.8511136 | BQ74: =+BQ70*BQ62/1000 -> 5.0077499 | BR74: =+SUM(BN74:BQ74) -> 18.699619 | BS74: =+BS70*BS62/1000 -> 4.9283978 | BT74: =+BT70*BT62/1000 -> 4.6812132 | BU74: =+BU70*BU62/1000 -> 5.2728659 | BV74: =+BV70*BV62/1000 -> 5.4432321 | BW74: =+SUM(BS74:BV74) -> 20.325709 | BX74: =+BX70*BX62/1000 -> 5.3530014 | BY74: =+BY70*BY62/1000 -> 5.0845598 | BZ74: =+BZ70*BZ62/1000 -> 5.7271286 | CA74: =+CA70*CA62/1000 -> 5.9122098 | CB74: =+SUM(BX74:CA74) -> 22.0769 | CC74: =+CC70*CC62/1000 -> 5.8099147 | CD74: =+CD70*CD62/1000 -> 5.518503 | CE74: =+CE70*CE62/1000 -> 6.2160029 | CF74: =+CF70*CF62/1000 -> 6.4168344 | CG74: =+SUM(CC74:CF74) -> 23.961255 | CH74: =+CH70*CH62/1000 -> 6.3012018 | CI74: =+CI70*CI62/1000 -> 5.9849611 | CJ74: =+CJ70*CJ62/1000 -> 6.7417071 | CK74: =+CK70*CK62/1000 -> 6.9593681 | CL74: =+SUM(CH74:CK74) -> 25.987238 | CM74: =+CM70*CM62/1000 -> 6.8290254 | CN74: =+CN70*CN62/1000 -> 6.485961 | CO74: =+CO70*CO62/1000 -> 7.306567 | CP74: =+CP70*CP62/1000 -> 7.542196 | CQ74: =+SUM(CM74:CP74) -> 28.163749 | CR74: =+CR70*CR62/1000 -> 7.2433765 | CS74: =+CS70*CS62/1000 -> 6.8794967 | CT74: =+CT70*CT62/1000 -> 7.7498929 | CU74: =+CU70*CU62/1000 -> 7.9998188 | CV74: =+SUM(CR74:CU74) -> 29.872585
A75: % Y/Y
A77: Praça Conchas | U77: =+U90/$U$35 -> 0.077195206
A78: Tarifa (R$) | R78: 5 | S78: 5 | T78: 5 | U78: 5 | V78: =+V82*V$11+V83*V$12 -> 4.988009 | W78: =+W82*W$11+W83*W$12 -> 4.988009 | X78: =+X82*X$11+X83*X$12 -> 4.988009 | Y78: =+Y90*1000/Y86 -> 4.9907765 | Z78: =+Z82*Z$11+Z83*Z$12 -> 4.988009 | AA78: =+AA82*AA$11+AA83*AA$12 -> 4.988009 | AB78: =+AB82*AB$11+AB83*AB$12 -> 5.3077404 | AC78: =+AC82*AC$11+AC83*AC$12 -> 5.3077404 | AD78: =+AD90*1000/AD86 -> 5.1466989 | AE78: =+AE82*AE$11+AE83*AE$12 -> 5.3077404 | AF78: =+AF82*AF$11+AF83*AF$12 -> 5.3077404 | AG78: =+AG82*AG$11+AG83*AG$12 -> 5.8385144 | AH78: =+AH82*AH$11+AH83*AH$12 -> 5.8385144 | AI78: =+AI90*1000/AI86 -> 5.5843164 | AJ78: =+AJ82*AJ$11+AJ83*AJ$12 -> 5.8385144 | AK78: =+AK82*AK$11+AK83*AK$12 -> 5.8385144 | AL78: =+AL82*AL$11+AL83*AL$12 -> 6.2121793 | AM78: =+AM82*AM$11+AM83*AM$12 -> 6.2121793 | AN78: =+AN90*1000/AN86 -> 6.031156 | AO78: =+AO82*AO$11+AO83*AO$12 -> 6.2121793 | AP78: =+AP82*AP$11+AP83*AP$12 -> 6.2121793 | AQ78: =+AQ82*AQ$11+AQ83*AQ$12 -> 6.5227883 | AR78: =+AR82*AR$11+AR83*AR$12 -> 6.5227883 | AS78: =+AS90*1000/AS86 -> 6.3725919 | AT78: =+AT82*AT$11+AT83*AT$12 -> 6.5227883 | AU78: =+AU82*AU$11+AU83*AU$12 -> 6.5227883 | AV78: =+AV82*AV$11+AV83*AV$12 -> 6.8489277 | AW78: =+AW82*AW$11+AW83*AW$12 -> 6.8489277 | AX78: =+AX90*1000/AX86 -> 6.6912173 | AY78: =+AY82*AY$11+AY83*AY$12 -> 6.8489277 | AZ78: =+AZ82*AZ$11+AZ83*AZ$12 -> 6.8489277 | BA78: =+BA82*BA$11+BA83*BA$12 -> 7.1571295 | BB78: =+BB82*BB$11+BB83*BB$12 -> 7.1571295 | BC78: =+BC90*1000/BC86 -> 7.0080896 | BD78: =+BD82*BD$11+BD83*BD$12 -> 7.1571295 | BE78: =+BE82*BE$11+BE83*BE$12 -> 7.1571295 | BF78: =+BF82*BF$11+BF83*BF$12 -> 7.4792003 | BG78: =+BG82*BG$11+BG83*BG$12 -> 7.4792003 | BH78: =+BH90*1000/BH86 -> 7.3234505 | BI78: =+BI82*BI$11+BI83*BI$12 -> 7.4792003 | BJ78: =+BJ82*BJ$11+BJ83*BJ$12 -> 7.4792003 | BK78: =+BK82*BK$11+BK83*BK$12 -> 7.8157643 | BL78: =+BL82*BL$11+BL83*BL$12 -> 7.8157643 | BM78: =+BM90*1000/BM86 -> 7.6530047 | BN78: =+BN82*BN$11+BN83*BN$12 -> 7.8157643 | BO78: =+BO82*BO$11+BO83*BO$12 -> 7.8157643 | BP78: =+BP82*BP$11+BP83*BP$12 -> 8.1674737 | BQ78: =+BQ82*BQ$11+BQ83*BQ$12 -> 8.1674737 | BR78: =+BR90*1000/BR86 -> 7.9973891 | BS78: =+BS82*BS$11+BS83*BS$12 -> 8.1674737 | BT78: =+BT82*BT$11+BT83*BT$12 -> 8.3304233 | BU78: =+BU82*BU$11+BU83*BU$12 -> 8.7052924 | BV78: =+BV82*BV$11+BV83*BV$12 -> 8.7052924 | BW78: =+BW90*1000/BW86 -> 8.4856944 | BX78: =+BX82*BX$11+BX83*BX$12 -> 8.7052924 | BY78: =+BY82*BY$11+BY83*BY$12 -> 8.7052924 | BZ78: =+BZ82*BZ$11+BZ83*BZ$12 -> 9.0970306 | CA78: =+CA82*CA$11+CA83*CA$12 -> 9.0970306 | CB78: =+CB90*1000/CB86 -> 8.9075862 | CC78: =+CC82*CC$11+CC83*CC$12 -> 9.0970306 | CD78: =+CD82*CD$11+CD83*CD$12 -> 9.0970306 | CE78: =+CE82*CE$11+CE83*CE$12 -> 9.5063969 | CF78: =+CF82*CF$11+CF83*CF$12 -> 9.5063969 | CG78: =+CG90*1000/CG86 -> 9.3084292 | CH78: =+CH82*CH$11+CH83*CH$12 -> 9.5063969 | CI78: =+CI82*CI$11+CI83*CI$12 -> 9.5063969 | CJ78: =+CJ82*CJ$11+CJ83*CJ$12 -> 9.9341848 | CK78: =+CK82*CK$11+CK83*CK$12 -> 9.9341848 | CL78: =+CL90*1000/CL86 -> 9.7273092 | CM78: =+CM82*CM$11+CM83*CM$12 -> 9.9341848 | CN78: =+CN82*CN$11+CN83*CN$12 -> 9.9341848 | CO78: =+CO82*CO$11+CO83*CO$12 -> 10.381223 | CP78: =+CP82*CP$11+CP83*CP$12 -> 10.381223 | CQ78: =+CQ90*1000/CQ86 -> 10.165039 | CR78: =+CR82*CR$11+CR83*CR$12 -> 10.381223 | CS78: =+CS82*CS$11+CS83*CS$12 -> 10.381223 | CT78: =+CT82*CT$11+CT83*CT$12 -> 10.848378 | CU78: =+CU82*CU$11+CU83*CU$12 -> 10.848378 | CV78: =+CV90*1000/CV86 -> 10.622466
A79: YoY (%)
A81: Distância Total (km) | U81: =+U82+U83 -> 59.9 | V81: =+V82+V83 -> 59.88 | W81: =+W82+W83 -> 59.88 | X81: =+X82+X83 -> 59.88 | Y81: =+Y82+Y83 -> 59.88 | Z81: =+Z82+Z83 -> 59.88 | AA81: =+AA82+AA83 -> 59.88 | AB81: =+AB82+AB83 -> 59.88 | ... CV81: =+CV82+CV83 -> 59.88
A82: Pista Simples | U82: 59.2 | V82: 59.23 | W82: 59.23 | X82: 59.23 | Y82: 59.23 | Z82: 59.23 | AA82: 59.23 | AB82: 59.23 | AC82: 59.23 | AD82: 59.23 | AE82: 59.23 | AF82: 59.23 | AG82: 59.23 | AH82: 59.23 | AI82: 59.23 | AJ82: 59.23 | AK82: 59.23 | AL82: 59.23 | AM82: 59.23 | AN82: 59.23 | AO82: 59.23 | AP82: 59.23 | AQ82: 59.23 | AR82: 59.23 | AS82: 59.23 | AT82: 59.23 | AU82: 59.23 | AV82: 59.23 | AW82: 59.23 | AX82: 59.23 | AY82: 59.23 | AZ82: 59.23 | BA82: 59.23 | BB82: 59.23 | BC82: 59.23 | BD82: 59.23 | BE82: 59.23 | BF82: 59.23 | BG82: 59.23 | BH82: 59.23 | BI82: 59.23 | BJ82: 59.23 | BK82: 59.23 | BL82: 59.23 | BM82: 59.23 | BN82: 59.23 | BO82: 59.23 | BP82: 59.23 | BQ82: 59.23 | BR82: 59.23 | BS82: 59.23 | BT82: 56.23 | BU82: 56.23 | BV82: 56.23 | BW82: 56.23 | BX82: 56.23 | BY82: 56.23 | BZ82: 56.23 | CA82: 56.23 | CB82: 56.23 | CC82: 56.23 | CD82: 56.23 | CE82: 56.23 | CF82: 56.23 | CG82: 56.23 | CH82: 56.23 | CI82: 56.23 | CJ82: 56.23 | CK82: 56.23 | CL82: 56.23 | CM82: 56.23 | CN82: 56.23 | CO82: 56.23 | CP82: 56.23 | CQ82: 56.23 | CR82: 56.23 | CS82: 56.23 | CT82: 56.23 | CU82: 56.23 | CV82: 56.23
A83: Pista Dupla | U83: 0.7 | V83: 0.65 | W83: 0.65 | X83: 0.65 | Y83: 0.65 | Z83: 0.65 | AA83: 0.65 | AB83: 0.65 | AC83: 0.65 | AD83: 0.65 | AE83: 0.65 | AF83: 0.65 | AG83: 0.65 | AH83: 0.65 | AI83: 0.65 | AJ83: 0.65 | AK83: 0.65 | AL83: 0.65 | AM83: 0.65 | AN83: 0.65 | AO83: 0.65 | AP83: 0.65 | AQ83: 0.65 | AR83: 0.65 | AS83: 0.65 | AT83: 0.65 | AU83: 0.65 | AV83: 0.65 | AW83: 0.65 | AX83: 0.65 | AY83: 0.65 | AZ83: 0.65 | BA83: 0.65 | BB83: 0.65 | BC83: 0.65 | BD83: 0.65 | BE83: 0.65 | BF83: 0.65 | BG83: 0.65 | BH83: 0.65 | BI83: 0.65 | BJ83: 0.65 | BK83: 0.65 | BL83: 0.65 | BM83: 0.65 | BN83: 0.65 | BO83: 0.65 | BP83: 0.65 | BQ83: 0.65 | BR83: 0.65 | BS83: 0.65 | BT83: 3.65 | BU83: 3.65 | BV83: 3.65 | BW83: 3.65 | BX83: 3.65 | BY83: 3.65 | BZ83: 3.65 | CA83: 3.65 | CB83: 3.65 | CC83: 3.65 | CD83: 3.65 | CE83: 3.65 | CF83: 3.65 | CG83: 3.65 | CH83: 3.65 | CI83: 3.65 | CJ83: 3.65 | CK83: 3.65 | CL83: 3.65 | CM83: 3.65 | CN83: 3.65 | CO83: 3.65 | CP83: 3.65 | CQ83: 3.65 | CR83: 3.65 | CS83: 3.65 | CT83: 3.65 | CU83: 3.65 | CV83: 3.65
A84: % Pista Dupla | U84: =+U83/U81 -> 0.011686144 | V84: =+V83/V81 -> 0.010855043 | W84: =+W83/W81 -> 0.010855043 | X84: =+X83/X81 -> 0.010855043 | Y84: =+Y83/Y81 -> 0.010855043 | Z84: =+Z83/Z81 -> 0.010855043 | AA84: =+AA83/AA81 -> 0.010855043 | AB84: =+AB83/AB81 -> 0.010855043 | ... CV84: =+CV83/CV81 -> 0.060955244
A86: Tráfego (Mil Veículos Equivalentes) | D86: 228.328 | E86: 228.328 | F86: 515.3885 | G86: 586.6735 | H86: 593.9405 | I86: 553.6545 | J86: 2249.657 | K86: 517.737 | L86: 633.343 | M86: 694.714 | N86: 641.2305 | O86: 2487.0245 | P86: 615.723 | Q86: 606.638 | R86: 700.117 | S86: 655.694 | T86: 2578.172 | U86: 669.9 | V86: 707.9 | W86: 773.4 | X86: 751.3 | Y86: =+SUM(U86:X86) -> 2902.5 | Z86: 715.073 | AA86: 721.617 | AB86: 714.746 | AC86: 700.965 | AD86: =+SUM(Z86:AC86) -> 2852.401 | AE86: 651.632 | AF86: 694.384 | AG86: 742.4595 | AH86: =AC86*(1+AH87) -> 722.051 | AI86: =+SUM(AE86:AH86) -> 2810.5265 | AJ86: =AE86*(1+AJ87) -> 677.106 | AK86: =AF86*(1+AK87) -> 721.53 | AL86: =AG86*(1+AL87) -> 771.485 | AM86: =AH86*(1+AM87) -> 716.916 | AN86: =+SUM(AJ86:AM86) -> 2887.037 | AO86: =AJ86*(1+AO87) -> 675.208 | AP86: =AK86*(1+AP87) -> 714.424 | AQ86: =AL86*(1+AQ87) -> 744.627 | AR86: =AM86*(1+AR87) -> 739.525 | AS86: =+SUM(AO86:AR86) -> 2873.784 | AT86: =AO86*(1+AT87) -> 715.762 | AU86: =AP86*(1+AU87) -> 757.043 | AV86: =AQ86*(1+AV87) -> 788.959 | AW86: =AR86*(1+AW87) -> 783.943 | AX86: =+SUM(AT86:AW86) -> 3045.707 | AY86: =AT86*(1+AY87) -> 744.386 | AZ86: =AU86*(1+AZ87) -> 787.043 | BA86: =AV86*(1+BA87) -> 820.141 | BB86: =AW86*(1+BB87) -> 815.294 | BC86: =+SUM(AY86:BB86) -> 3166.864 | BD86: =AY86*(1+BD87) -> 773.382 | BE86: =AZ86*(1+BE87) -> 817.463 | BF86: =BA86*(1+BF87) -> 851.768 | BG86: =BB86*(1+BG87) -> 847.053 | BH86: =+SUM(BD86:BG86) -> 3289.666 | BI86: =BD86*(1+BI87) -> 805.917 | BJ86: =BE86*(1+BJ87) -> 851.77 | BK86: =BF86*(1+BK87) -> 887.49 | BL86: =BG86*(1+BL87) -> 882.686 | BM86: =+SUM(BI86:BL86) -> 3427.863 | BN86: =BI86*(1+BN87) -> 839.112 | BO86: =BJ86*(1+BO87) -> 886.793 | BP86: =BK86*(1+BP87) -> 923.964 | BQ86: =BL86*(1+BQ87) -> 919.044 | BR86: =+SUM(BN86:BQ86) -> 3568.913 | BS86: =BN86*(1+BS87) -> 872.938 | BT86: =BO86*(1+BT87) -> 922.505 | BU86: =BP86*(1+BU87) -> 961.161 | BV86: =BQ86*(1+BV87) -> 956.093 | BW86: =+SUM(BS86:BV86) -> 3712.697 | BX86: =BS86*(1+BX87) -> 907.361 | BY86: =BT86*(1+BY87) -> 958.87 | BZ86: =BU86*(1+BZ87) -> 999.047 | CA86: =BV86*(1+CA87) -> 993.764 | CB86: =+SUM(BX86:CA86) -> 3859.042 | CC86: =BX86*(1+CC87) -> 942.344 | CD86: =BY86*(1+CD87) -> 995.854 | CE86: =BZ86*(1+CE87) -> 1037.585 | CF86: =CA86*(1+CF87) -> 1032.109 | CG86: =+SUM(CC86:CF86) -> 4007.892 | CH86: =CC86*(1+CH87) -> 977.848 | CI86: =CD86*(1+CI87) -> 1033.42 | CJ86: =CE86*(1+CJ87) -> 1076.739 | CK86: =CF86*(1+CK87) -> 1070.996 | CL86: =+SUM(CH86:CK86) -> 4159.003 | CM86: =CH86*(1+CM87) -> 1013.834 | CN86: =CI86*(1+CN87) -> 1071.528 | CO86: =CJ86*(1+CO87) -> 1116.467 | CP86: =CK86*(1+CP87) -> 1110.41 | CQ86: =+SUM(CM86:CP86) -> 4312.239 | CR86: =CM86*(1+CR87) -> 1029.5484 | CS86: =CN86*(1+CS87) -> 1088.1367 | CT86: =CO86*(1+CT87) -> 1133.7722 | CU86: =CP86*(1+CU87) -> 1127.6214 | CV86: =+SUM(CR86:CU86) -> 4379.0787
A87: YoY (%) | I87: =+I86/D86-1 -> 1.4248209 | J87: =+J86/E86-1 -> 8.8527425 | K87: =+K86/F86-1 -> 0.0045567567 | L87: =+L86/G86-1 -> 0.079549358 | M87: =+M86/H86-1 -> 0.16966935 | N87: =+N86/I86-1 -> 0.15817807 | O87: =+O86/J86-1 -> 0.10551275 | P87: =+P86/K86-1 -> 0.18925825 | ... AG87: =+AG86/AB86-1 -> 0.038773914 | AH87: 0.030081388 | AI87: =+AI86/AD86-1 -> -0.014680439 | AJ87: 0.039092617 | AK87: 0.039093643 | AL87: 0.039093715 | AM87: -0.007111686 | AN87: =+AN86/AI86-1 -> 0.027222835 | AO87: -0.0028031062 | AP87: -0.0098485163 | AQ87: -0.034813379 | AR87: 0.03153647 | AS87: =+AS86/AN86-1 -> -0.0045905196 | AT87: 0.060061492 | AU87: 0.059655051 | AV87: 0.059535848 | AW87: 0.060062878 | AX87: =+AX86/AS86-1 -> 0.059824608 | AY87: 0.039990947 | AZ87: 0.039627868 | BA87: 0.039522966 | BB87: 0.039991428 | BC87: =+BC86/AX86-1 -> 0.039779598 | BD87: 0.038952909 | BE87: 0.038651001 | BF87: 0.038562881 | BG87: 0.038954046 | BH87: =+BH86/BC86-1 -> 0.038777163 | BI87: 0.042068473 | BJ87: 0.041967649 | BK87: 0.04193865 | BL87: 0.042067025 | BM87: =+BM86/BH86-1 -> 0.042009432 | BN87: 0.041189105 | BO87: 0.041117907 | BP87: 0.041097928 | BQ87: 0.041190185 | BR87: =+BR86/BM86-1 -> 0.041148086 | BS87: 0.040311663 | BT87: 0.040270954 | BU87: 0.040258062 | BV87: 0.040312542 | BW87: =+BW86/BR86-1 -> 0.040287897 | BX87: 0.039433499 | BY87: 0.039419841 | BZ87: 0.039416914 | CA87: 0.039400979 | CB87: =+CB86/BW86-1 -> 0.039417437 | CC87: 0.038554666 | CD87: 0.038570401 | CE87: 0.038574762 | CF87: 0.03858562 | CG87: =+CG86/CB86-1 -> 0.038571749 | CH87: 0.037676263 | CI87: 0.037722397 | CJ87: 0.037735704 | CK87: 0.037677222 | CL87: =+CL86/CG86-1 -> 0.037703361 | CM87: 0.036801221 | CN87: 0.036875617 | CO87: 0.036896592 | CP87: 0.036801258 | CQ87: =+CQ86/CL86-1 -> 0.036844407 | CR87: 0.0155 | CS87: 0.0155 | CT87: 0.0155 | CU87: 0.0155 | CV87: =+CV86/CQ86-1 -> 0.0155
A88: Elasticidade PIB | J88: =+J87/(J$4/100) -> 117.50988 | K88: =+K87/(K$4/100) -> 0.10758095 | L88: =+L87/(L$4/100) -> 2.4001438 | M88: =+M87/(M$4/100) -> 7.9958548 | N88: =+N87/(N$4/100) -> 11.575759 | O88: =+O87/(O$4/100) -> 3.8613868 | P88: =+P87/(P$4/100) -> 25.142478 | Q88: =+Q87/(Q$4/100) -> -8.6090687 | ... X88: =+X87/(X$4/100) -> 4.1999261 | Y88: =(+Y87/(Y$4/100)) -> 3.8120502 | Z88: =+Z87/(Z$4/100) -> 3.3716226 | AA88: =+AA87/(AA$4/100) -> 0.96885153 | AB88: =+AB87/(AB$4/100) -> -3.7919576 | AC88: =+AC87/(AC$4/100) -> -3.3498602 | AD88: =(+AD87/(AD$4/100)) -> -11.938147 | AE88: =+AE87/(AE$4/100) -> 2.861923 | AF88: =+AF87/(AF$4/100) -> 1.2173824 | AG88: =+AG87/(AG$4/100) -> -1.2507714 | AH88: =+AH87/(AH$4/100) -> -0.97036735 | AI88: =(+AI87/(AI$4/100)) -> 0.47356256 | AJ88: =+AJ87/(AJ$4/100) -> -1.9546308 | AK88: =+AK87/(AK$4/100) -> -1.9546821 | AL88: =+AL87/(AL$4/100) -> -1.9546857 | AM88: =+AM87/(AM$4/100) -> 0.3555843 | AN88: =(+AN87/(AN$4/100)) -> -1.3611418 | AO88: =+AO87/(AO$4/100) -> -0.28031062 | AP88: =+AP87/(AP$4/100) -> -0.98485163 | AQ88: =+AQ87/(AQ$4/100) -> -3.4813379 | AR88: =+AR87/(AR$4/100) -> 3.153647 | AS88: =(+AS87/(AS$4/100)) -> -0.45905196 | AT88: =+AT87/(AT$4/100) -> 3.0030746 | AU88: =+AU87/(AU$4/100) -> 2.9827525 | AV88: =+AV87/(AV$4/100) -> 2.9767924 | AW88: =+AW87/(AW$4/100) -> 3.0031439 | AX88: =(+AX87/(AX$4/100)) -> 2.9912304 | AY88: =+AY87/(AY$4/100) -> 1.9995473 | AZ88: =+AZ87/(AZ$4/100) -> 1.9813934 | BA88: =+BA87/(BA$4/100) -> 1.9761483 | BB88: =+BB87/(BB$4/100) -> 1.9995714 | BC88: =(+BC87/(BC$4/100)) -> 1.9889799 | BD88: =+BD87/(BD$4/100) -> 1.9476454 | BE88: =+BE87/(BE$4/100) -> 1.9325501 | BF88: =+BF87/(BF$4/100) -> 1.9281441 | BG88: =+BG87/(BG$4/100) -> 1.9477023 | BH88: =(+BH87/(BH$4/100)) -> 1.9388581 | BI88: =+BI87/(BI$4/100) -> 2.1034237 | BJ88: =+BJ87/(BJ$4/100) -> 2.0983824 | BK88: =+BK87/(BK$4/100) -> 2.0969325 | BL88: =+BL87/(BL$4/100) -> 2.1033513 | BM88: =(+BM87/(BM$4/100)) -> 2.1004716 | BN88: =+BN87/(BN$4/100) -> 2.0594553 | BO88: =+BO87/(BO$4/100) -> 2.0558954 | BP88: =+BP87/(BP$4/100) -> 2.0548964 | BQ88: =+BQ87/(BQ$4/100) -> 2.0595093 | BR88: =(+BR87/(BR$4/100)) -> 2.0574043 | BS88: =+BS87/(BS$4/100) -> 2.0155831 | BT88: =+BT87/(BT$4/100) -> 2.0135477 | BU88: =+BU87/(BU$4/100) -> 2.0129031 | BV88: =+BV87/(BV$4/100) -> 2.0156271 | BW88: =(+BW87/(BW$4/100)) -> 2.0143949 | BX88: =+BX87/(BX$4/100) -> 1.971675 | BY88: =+BY87/(BY$4/100) -> 1.970992 | BZ88: =+BZ87/(BZ$4/100) -> 1.9708457 | CA88: =+CA87/(CA$4/100) -> 1.9700489 | CB88: =(+CB87/(CB$4/100)) -> 1.9708718 | CC88: =+CC87/(CC$4/100) -> 1.9277333 | CD88: =+CD87/(CD$4/100) -> 1.92852 | CE88: =+CE87/(CE$4/100) -> 1.9287381 | CF88: =+CF87/(CF$4/100) -> 1.929281 | CG88: =(+CG87/(CG$4/100)) -> 1.9285875 | CH88: =+CH87/(CH$4/100) -> 1.8838131 | CI88: =+CI87/(CI$4/100) -> 1.8861199 | CJ88: =+CJ87/(CJ$4/100) -> 1.8867852 | CK88: =+CK87/(CK$4/100) -> 1.8838611 | CL88: =(+CL87/(CL$4/100)) -> 1.8851681 | CM88: =+CM87/(CM$4/100) -> 1.840061 | CN88: =+CN87/(CN$4/100) -> 1.8437808 | CO88: =+CO87/(CO$4/100) -> 1.8448296 | CP88: =+CP87/(CP$4/100) -> 1.8400629 | CQ88: =(+CQ87/(CQ$4/100)) -> 1.8422204 | CR88: =+CR87/(CR$4/100) -> 0.775 | CS88: =+CS87/(CS$4/100) -> 0.775 | CT88: =+CT87/(CT$4/100) -> 0.775 | CU88: =+CU87/(CU$4/100) -> 0.775 | CV88: =(+CV87/(CV$4/100)) -> 0.775
A90: Receita de Pedágio | R90: =+R86*R78/1000 -> 3.500585 | S90: =+S86*S78/1000 -> 3.27847 | T90: =+T86*T78/1000 -> 12.89086 | U90: =+U86*U78/1000 -> 3.3495 | V90: =+V86*V78/1000 -> 3.5310116 | W90: =+W86*W78/1000 -> 3.8577262 | X90: =+X86*X78/1000 -> 3.7474912 | Y90: =+SUM(U90:X90) -> 14.485729 | Z90: =+Z86*Z78/1000 -> 3.5667906 | AA90: =+AA86*AA78/1000 -> 3.5994321 | AB90: =+AB86*AB78/1000 -> 3.7936862 | AC90: =+AC86*AC78/1000 -> 3.7205402 | AD90: =+SUM(Z90:AC90) -> 14.680449 | AE90: =+AE86*AE78/1000 -> 3.4586935 | AF90: =+AF86*AF78/1000 -> 3.68561 | AG90: =+AG86*AG78/1000 -> 4.3348605 | AH90: =+AH86*AH78/1000 -> 4.2157052 | AI90: =+SUM(AE90:AH90) -> 15.694869 | AJ90: =+AJ86*AJ78/1000 -> 3.9532931 | AK90: =+AK86*AK78/1000 -> 4.2126633 | AL90: =+AL86*AL78/1000 -> 4.7926032 | AM90: =+AM86*AM78/1000 -> 4.4536108 | AN90: =+SUM(AJ90:AM90) -> 17.41217 | AO90: =+AO86*AO78/1000 -> 4.1945132 | AP90: =+AP86*AP78/1000 -> 4.43813 | AQ90: =+AQ86*AQ78/1000 -> 4.8570443 | AR90: =+AR86*AR78/1000 -> 4.823765 | AS90: =+SUM(AO90:AR90) -> 18.313453 | AT90: =+AT86*AT78/1000 -> 4.668764 | AU90: =+AU86*AU78/1000 -> 4.9380312 | AV90: =+AV86*AV78/1000 -> 5.4035232 | AW90: =+AW86*AW78/1000 -> 5.3691689 | AX90: =+SUM(AT90:AW90) -> 20.379487 | AY90: =+AY86*AY78/1000 -> 5.0982459 | AZ90: =+AZ86*AZ78/1000 -> 5.3904006 | BA90: =+BA86*BA78/1000 -> 5.8698553 | BB90: =+BB86*BB78/1000 -> 5.8351647 | BC90: =+SUM(AY90:BB90) -> 22.193667 | BD90: =+BD86*BD78/1000 -> 5.5351951 | BE90: =+BE86*BE78/1000 -> 5.8506885 | BF90: =+BF86*BF78/1000 -> 6.3705435 | BG90: =+BG86*BG78/1000 -> 6.335279 | BH90: =+SUM(BD90:BG90) -> 24.091706 | BI90: =+BI86*BI78/1000 -> 6.0276147 | BJ90: =+BJ86*BJ78/1000 -> 6.3705584 | BK90: =+BK86*BK78/1000 -> 6.9364127 | BL90: =+BL86*BL78/1000 -> 6.8988657 | BM90: =+SUM(BI90:BL90) -> 26.233451 | BN90: =+BN86*BN78/1000 -> 6.5583016 | BO90: =+BO86*BO78/1000 -> 6.9309651 | BP90: =+BP86*BP78/1000 -> 7.5464517 | BQ90: =+BQ86*BQ78/1000 -> 7.5062677 | BR90: =+SUM(BN90:BQ90) -> 28.541986 | BS90: =+BS86*BS78/1000 -> 7.1296982 | BT90: =+BT86*BT78/1000 -> 7.6848572 | BU90: =+BU86*BU78/1000 -> 8.3671875 | BV90: =+BV86*BV78/1000 -> 8.3230691 | BW90: =+SUM(BS90:BV90) -> 31.504812 | BX90: =+BX86*BX78/1000 -> 7.8988428 | BY90: =+BY86*BY78/1000 -> 8.3472437 | BZ90: =+BZ86*BZ78/1000 -> 9.0883611 | CA90: =+CA86*CA78/1000 -> 9.0403015 | CB90: =+SUM(BX90:CA90) -> 34.374749 | CC90: =+CC86*CC78/1000 -> 8.5725322 | CD90: =+CD86*CD78/1000 -> 9.0593143 | CE90: =+CE86*CE78/1000 -> 9.8636949 | CF90: =+CF86*CF78/1000 -> 9.8116378 | CG90: =+SUM(CC90:CF90) -> 37.307179 | CH90: =+CH86*CH78/1000 -> 9.2958112 | CI90: =+CI86*CI78/1000 -> 9.8241007 | CJ90: =+CJ86*CJ78/1000 -> 10.696524 | CK90: =+CK86*CK78/1000 -> 10.639472 | CL90: =+SUM(CH90:CK90) -> 40.455908 | CM90: =+CM86*CM78/1000 -> 10.071614 | CN90: =+CN86*CN78/1000 -> 10.644757 | CO90: =+CO86*CO78/1000 -> 11.590293 | CP90: =+CP86*CP78/1000 -> 11.527414 | CQ90: =+SUM(CM90:CP90) -> 43.834078 | CR90: =+CR86*CR78/1000 -> 10.687972 | CS90: =+CS86*CS78/1000 -> 11.29619 | CT90: =+CT86*CT78/1000 -> 12.29959 | CU90: =+CU86*CU78/1000 -> 12.232863 | CV90: =+SUM(CR90:CU90) -> 46.516614
A91: % Y/Y
A93: Praça Anhembi | U93: =+U106/$U$35 -> 0.063834063
A94: Tarifa (R$) | R94: 5.6 | S94: 5.6 | T94: 5.6 | U94: 5.6 | V94: =+V98*V$11+V99*V$12 -> 5.6328279 | W94: =+W98*W$11+W99*W$12 -> 5.6328279 | X94: =+X98*X$11+X99*X$12 -> 5.6328279 | Y94: =+Y106*1000/Y102 -> 5.6248252 | Z94: =+Z98*Z$11+Z99*Z$12 -> 5.6328279 | AA94: =+AA98*AA$11+AA99*AA$12 -> 5.6328279 | AB94: =+AB98*AB$11+AB99*AB$12 -> 5.9938922 | AC94: =+AC98*AC$11+AC99*AC$12 -> 5.9938922 | AD94: =+AD106*1000/AD102 -> 5.8156776 | AE94: =+AE98*AE$11+AE99*AE$12 -> 5.9938922 | AF94: =+AF98*AF$11+AF99*AF$12 -> 5.9938922 | AG94: =+AG98*AG$11+AG99*AG$12 -> 6.5932814 | AH94: =+AH98*AH$11+AH99*AH$12 -> 6.5932814 | AI94: =+AI106*1000/AI102 -> 6.3126892 | AJ94: =+AJ98*AJ$11+AJ99*AJ$12 -> 6.5932814 | AK94: =+AK98*AK$11+AK99*AK$12 -> 6.5932814 | AL94: =+AL98*AL$11+AL99*AL$12 -> 7.0152514 | AM94: =+AM98*AM$11+AM99*AM$12 -> 7.0152514 | AN94: =+AN106*1000/AN102 -> 6.815279 | AO94: =+AO98*AO$11+AO99*AO$12 -> 7.0152514 | AP94: =+AP98*AP$11+AP99*AP$12 -> 7.0152514 | AQ94: =+AQ98*AQ$11+AQ99*AQ$12 -> 7.366014 | AR94: =+AR98*AR$11+AR99*AR$12 -> 7.366014 | AS94: =+AS106*1000/AS102 -> 7.1974222 | AT94: =+AT98*AT$11+AT99*AT$12 -> 7.366014 | AU94: =+AU98*AU$11+AU99*AU$12 -> 7.366014 | AV94: =+AV98*AV$11+AV99*AV$12 -> 7.7343147 | AW94: =+AW98*AW$11+AW99*AW$12 -> 7.7343147 | AX94: =+AX106*1000/AX102 -> 7.557283 | AY94: =+AY98*AY$11+AY99*AY$12 -> 7.7343147 | AZ94: =+AZ98*AZ$11+AZ99*AZ$12 -> 7.7343147 | BA94: =+BA98*BA$11+BA99*BA$12 -> 8.0823588 | BB94: =+BB98*BB$11+BB99*BB$12 -> 8.0823588 | BC94: =+BC106*1000/BC102 -> 7.9150551 | BD94: =+BD98*BD$11+BD99*BD$12 -> 8.0823588 | BE94: =+BE98*BE$11+BE99*BE$12 -> 8.0823588 | BF94: =+BF98*BF$11+BF99*BF$12 -> 8.446065 | BG94: =+BG98*BG$11+BG99*BG$12 -> 8.446065 | BH94: =+BH106*1000/BH102 -> 8.271225 | BI94: =+BI98*BI$11+BI99*BI$12 -> 8.446065 | BJ94: =+BJ98*BJ$11+BJ99*BJ$12 -> 8.446065 | BK94: =+BK98*BK$11+BK99*BK$12 -> 8.8261379 | BL94: =+BL98*BL$11+BL99*BL$12 -> 8.8261379 | BM94: =+BM106*1000/BM102 -> 8.6434274 | BN94: =+BN98*BN$11+BN99*BN$12 -> 8.8261379 | BO94: =+BO98*BO$11+BO99*BO$12 -> 8.8261379 | BP94: =+BP98*BP$11+BP99*BP$12 -> 9.2233141 | BQ94: =+BQ98*BQ$11+BQ99*BQ$12 -> 9.2233141 | BR94: =+BR106*1000/BR102 -> 9.0323797 | BS94: =+BS98*BS$11+BS99*BS$12 -> 9.2233141 | BT94: =+BT98*BT$11+BT99*BT$12 -> 9.2233141 | BU94: =+BU98*BU$11+BU99*BU$12 -> 9.6383632 | BV94: =+BV98*BV$11+BV99*BV$12 -> 9.6383632 | BW94: =+BW106*1000/BW102 -> 9.4388356 | BX94: =+BX98*BX$11+BX99*BX$12 -> 9.6383632 | BY94: =+BY98*BY$11+BY99*BY$12 -> 9.6383632 | BZ94: =+BZ98*BZ$11+BZ99*BZ$12 -> 10.07209 | CA94: =+CA98*CA$11+CA99*CA$12 -> 10.07209 | CB94: =+CB106*1000/CB102 -> 9.8635828 | CC94: =+CC98*CC$11+CC99*CC$12 -> 10.07209 | CD94: =+CD98*CD$11+CD99*CD$12 -> 10.07209 | CE94: =+CE98*CE$11+CE99*CE$12 -> 10.525334 | CF94: =+CF98*CF$11+CF99*CF$12 -> 10.525334 | CG94: =+CG106*1000/CG102 -> 10.307445 | CH94: =+CH98*CH$11+CH99*CH$12 -> 10.525334 | CI94: =+CI98*CI$11+CI99*CI$12 -> 10.525334 | CJ94: =+CJ98*CJ$11+CJ99*CJ$12 -> 10.998974 | CK94: =+CK98*CK$11+CK99*CK$12 -> 10.998974 | CL94: =+CL106*1000/CL102 -> 10.771281 | CM94: =+CM98*CM$11+CM99*CM$12 -> 10.998974 | CN94: =+CN98*CN$11+CN99*CN$12 -> 10.998974 | CO94: =+CO98*CO$11+CO99*CO$12 -> 11.493927 | CP94: =+CP98*CP$11+CP99*CP$12 -> 11.493927 | CQ94: =+CQ106*1000/CQ102 -> 11.255991 | CR94: =+CR98*CR$11+CR99*CR$12 -> 11.493927 | CS94: =+CS98*CS$11+CS99*CS$12 -> 11.493927 | CT94: =+CT98*CT$11+CT99*CT$12 -> 12.011154 | CU94: =+CU98*CU$11+CU99*CU$12 -> 12.011154 | CV94: =+CV106*1000/CV102 -> 11.762511
A95: YoY (%)
A97: Distância Total (km) | U97: =+U98+U99 -> 63.7 | V97: =+V98+V99 -> 63.695 | W97: =+W98+W99 -> 63.695 | X97: =+X98+X99 -> 63.695 | Y97: =+Y98+Y99 -> 63.695 | Z97: =+Z98+Z99 -> 63.695 | AA97: =+AA98+AA99 -> 63.695 | AB97: =+AB98+AB99 -> 63.695 | ... CV97: =+CV98+CV99 -> 63.695
A98: Pista Simples | U98: 53.1 | V98: 53.145 | W98: 53.145 | X98: 53.145 | Y98: 53.145 | Z98: 53.145 | AA98: 53.145 | AB98: 53.145 | AC98: 53.145 | AD98: 53.145 | AE98: 53.145 | AF98: 53.145 | AG98: 53.145 | AH98: 53.145 | AI98: 53.145 | AJ98: 53.145 | AK98: 53.145 | AL98: 53.145 | AM98: 53.145 | AN98: 53.145 | AO98: 53.145 | AP98: 53.145 | AQ98: 53.145 | AR98: 53.145 | AS98: 53.145 | AT98: 53.145 | AU98: 53.145 | AV98: 53.145 | AW98: 53.145 | AX98: 53.145 | AY98: 53.145 | AZ98: 53.145 | BA98: 53.145 | BB98: 53.145 | BC98: 53.145 | BD98: 53.145 | BE98: 53.145 | BF98: 53.145 | BG98: 53.145 | BH98: 53.145 | BI98: 53.145 | BJ98: 53.145 | BK98: 53.145 | BL98: 53.145 | BM98: 53.145 | BN98: 53.145 | BO98: 53.145 | BP98: 53.145 | BQ98: 53.145 | BR98: 53.145 | BS98: 53.145 | BT98: 53.145 | BU98: 53.145 | BV98: 53.145 | BW98: 53.145 | BX98: 53.145 | BY98: 53.145 | BZ98: 53.145 | CA98: 53.145 | CB98: 53.145 | CC98: 53.145 | CD98: 53.145 | CE98: 53.145 | CF98: 53.145 | CG98: 53.145 | CH98: 53.145 | CI98: 53.145 | CJ98: 53.145 | CK98: 53.145 | CL98: 53.145 | CM98: 53.145 | CN98: 53.145 | CO98: 53.145 | CP98: 53.145 | CQ98: 53.145 | CR98: 53.145 | CS98: 53.145 | CT98: 53.145 | CU98: 53.145 | CV98: 53.145
A99: Pista Dupla | U99: 10.6 | V99: 10.55 | W99: 10.55 | X99: 10.55 | Y99: 10.55 | Z99: 10.55 | AA99: 10.55 | AB99: 10.55 | AC99: 10.55 | AD99: 10.55 | AE99: 10.55 | AF99: 10.55 | AG99: 10.55 | AH99: 10.55 | AI99: 10.55 | AJ99: 10.55 | AK99: 10.55 | AL99: 10.55 | AM99: 10.55 | AN99: 10.55 | AO99: 10.55 | AP99: 10.55 | AQ99: 10.55 | AR99: 10.55 | AS99: 10.55 | AT99: 10.55 | AU99: 10.55 | AV99: 10.55 | AW99: 10.55 | AX99: 10.55 | AY99: 10.55 | AZ99: 10.55 | BA99: 10.55 | BB99: 10.55 | BC99: 10.55 | BD99: 10.55 | BE99: 10.55 | BF99: 10.55 | BG99: 10.55 | BH99: 10.55 | BI99: 10.55 | BJ99: 10.55 | BK99: 10.55 | BL99: 10.55 | BM99: 10.55 | BN99: 10.55 | BO99: 10.55 | BP99: 10.55 | BQ99: 10.55 | BR99: 10.55 | BS99: 10.55 | BT99: 10.55 | BU99: 10.55 | BV99: 10.55 | BW99: 10.55 | BX99: 10.55 | BY99: 10.55 | BZ99: 10.55 | CA99: 10.55 | CB99: 10.55 | CC99: 10.55 | CD99: 10.55 | CE99: 10.55 | CF99: 10.55 | CG99: 10.55 | CH99: 10.55 | CI99: 10.55 | CJ99: 10.55 | CK99: 10.55 | CL99: 10.55 | CM99: 10.55 | CN99: 10.55 | CO99: 10.55 | CP99: 10.55 | CQ99: 10.55 | CR99: 10.55 | CS99: 10.55 | CT99: 10.55 | CU99: 10.55 | CV99: 10.55
A100: % Pista Dupla | U100: =+U99/U97 -> 0.16640502 | V100: =+V99/V97 -> 0.1656331 | W100: =+W99/W97 -> 0.1656331 | X100: =+X99/X97 -> 0.1656331 | Y100: =+Y99/Y97 -> 0.1656331 | Z100: =+Z99/Z97 -> 0.1656331 | AA100: =+AA99/AA97 -> 0.1656331 | AB100: =+AB99/AB97 -> 0.1656331 | ... CV100: =+CV99/CV97 -> 0.1656331
A102: Tráfego (Mil Veículos Equivalentes) | D102: 164.254 | E102: 164.254 | F102: 353.106 | G102: 372.9955 | H102: 385.3175 | I102: 374.573 | J102: 1485.992 | K102: 362.978 | L102: 410.3355 | M102: 468.9575 | N102: 448.233 | O102: 1690.504 | P102: 429.243 | Q102: 425.2115 | R102: 482.6945 | S102: 486.017 | T102: 1823.166 | U102: 494.6 | V102: 479.2 | W102: 512.9 | X102: 542.2 | Y102: =+SUM(U102:X102) -> 2028.9 | Z102: 508.969 | AA102: 505.422 | AB102: 529.346 | AC102: 511.428 | AD102: =+SUM(Z102:AC102) -> 2055.165 | AE102: 483.692 | AF102: 497.094 | AG102: 540.272 | AH102: =AC102*(1+AH103) -> 574.056 | AI102: =+SUM(AE102:AH102) -> 2095.114 | AJ102: =AE102*(1+AJ103) -> 502.601 | AK102: =AF102*(1+AK103) -> 516.527 | AL102: =AG102*(1+AL103) -> 561.393 | AM102: =AH102*(1+AM103) -> 569.983 | AN102: =+SUM(AJ102:AM102) -> 2150.504 | AO102: =AJ102*(1+AO103) -> 501.738 | AP102: =AK102*(1+AP103) -> 510.121 | AQ102: =AL102*(1+AQ103) -> 552.826 | AR102: =AM102*(1+AR103) -> 540.532 | AS102: =+SUM(AO102:AR102) -> 2105.217 | AT102: =AO102*(1+AT103) -> 532.129 | AU102: =AP102*(1+AU103) -> 541.168 | AV102: =AQ102*(1+AV103) -> 586.145 | AW102: =AR102*(1+AW103) -> 573.47 | AX102: =+SUM(AT102:AW102) -> 2232.912 | AY102: =AT102*(1+AY103) -> 553.65 | AZ102: =AU102*(1+AZ103) -> 563.193 | BA102: =AV102*(1+BA103) -> 609.694 | BB102: =AW102*(1+BB103) -> 596.847 | BC102: =+SUM(AY102:BB102) -> 2323.384 | BD102: =AY102*(1+BD103) -> 575.425 | BE102: =AZ102*(1+BE103) -> 585.465 | BF102: =BA102*(1+BF103) -> 633.538 | BG102: =BB102*(1+BG103) -> 620.482 | BH102: =+SUM(BD102:BG102) -> 2414.91 | BI102: =BD102*(1+BI103) -> 599.704 | BJ102: =BE102*(1+BJ103) -> 610.208 | BK102: =BF102*(1+BK103) -> 660.221 | BL102: =BG102*(1+BL103) -> 646.717 | BM102: =+SUM(BI102:BL102) -> 2516.85 | BN102: =BI102*(1+BN103) -> 624.459 | BO102: =BJ102*(1+BO103) -> 635.427 | BP102: =BK102*(1+BP103) -> 687.44 | BQ102: =BL102*(1+BQ103) -> 673.453 | BR102: =+SUM(BN102:BQ102) -> 2620.779 | BS102: =BN102*(1+BS103) -> 649.664 | BT102: =BO102*(1+BT103) -> 661.094 | BU102: =BP102*(1+BU103) -> 715.166 | BV102: =BQ102*(1+BV103) -> 700.661 | BW102: =+SUM(BS102:BV102) -> 2726.585 | BX102: =BS102*(1+BX103) -> 675.293 | BY102: =BT102*(1+BY103) -> 687.18 | BZ102: =BU102*(1+BZ103) -> 743.372 | CA102: =BV102*(1+CA103) -> 728.309 | CB102: =+SUM(BX102:CA102) -> 2834.154 | CC102: =BX102*(1+CC103) -> 701.315 | CD102: =BY102*(1+CD103) -> 713.652 | CE102: =BZ102*(1+CE103) -> 772.026 | CF102: =CA102*(1+CF103) -> 756.364 | CG102: =+SUM(CC102:CF102) -> 2943.357 | CH102: =CC102*(1+CH103) -> 727.699 | CI102: =CD102*(1+CI103) -> 740.477 | CJ102: =CE102*(1+CJ103) -> 801.096 | CK102: =CF102*(1+CK103) -> 784.788 | CL102: =+SUM(CH102:CK102) -> 3054.06 | CM102: =CH102*(1+CM103) -> 754.412 | CN102: =CI102*(1+CN103) -> 767.621 | CO102: =CJ102*(1+CO103) -> 830.547 | CP102: =CK102*(1+CP103) -> 813.546 | CQ102: =+SUM(CM102:CP102) -> 3166.126 | CR102: =CM102*(1+CR103) -> 769.72656 | CS102: =CN102*(1+CS103) -> 783.20371 | CT102: =CO102*(1+CT103) -> 847.4071 | CU102: =CP102*(1+CU103) -> 830.06098 | CV102: =+SUM(CR102:CU102) -> 3230.3984
A103: YoY (%) | I103: =+I102/D102-1 -> 1.2804498 | J103: =+J102/E102-1 -> 8.0469151 | K103: =+K102/F102-1 -> 0.02795761 | L103: =+L102/G102-1 -> 0.10010845 | M103: =+M102/H102-1 -> 0.21706774 | N103: =+N102/I102-1 -> 0.19665059 | O103: =+O102/J102-1 -> 0.13762658 | P103: =+P102/K102-1 -> 0.18255927 | ... AG103: =+AG102/AB102-1 -> 0.020640564 | AH103: 0.12245712 | AI103: =+AI102/AD102-1 -> 0.019438342 | AJ103: 0.039093059 | AK103: 0.03909321 | AL103: 0.039093272 | AM103: -0.0070951266 | AN103: =+AN102/AI102-1 -> 0.026437702 | AO103: -0.0017170678 | AP103: -0.012402062 | AQ103: -0.015260254 | AR103: -0.051669962 | AS103: =+AS102/AN102-1 -> -0.021058784 | AT103: 0.060571454 | AU103: 0.060862031 | AV103: 0.06027032 | AW103: 0.060936263 | AX103: =+AX102/AS102-1 -> 0.060656455 | AY103: 0.040443201 | AZ103: 0.040699007 | BA103: 0.040176066 | BB103: 0.04076412 | BC103: =+BC102/AX102-1 -> 0.040517495 | BD103: 0.039329902 | BE103: 0.039545946 | BF103: 0.039108143 | BG103: 0.039599763 | BH103: =+BH102/BC102-1 -> 0.039393402 | BI103: 0.042193162 | BJ103: 0.042262134 | BK103: 0.042117442 | BL103: 0.042281646 | BM103: =+BM102/BH102-1 -> 0.042212753 | BN103: 0.041278697 | BO103: 0.041328531 | BP103: 0.041227104 | BQ103: 0.041341112 | BR103: =+BR102/BM102-1 -> 0.041293283 | BS103: 0.040362938 | BT103: 0.04039331 | BU103: 0.040332247 | BV103: 0.040400741 | BW103: =+BW102/BR102-1 -> 0.040371966 | BX103: 0.039449623 | BY103: 0.039458836 | BZ103: 0.039439794 | CA103: 0.039459881 | CB103: =+CB102/BW102-1 -> 0.039451915 | CC103: 0.038534384 | CD103: 0.038522658 | CE103: 0.038545977 | CF103: 0.038520738 | CG103: =+CG102/CB102-1 -> 0.038531075 | CH103: 0.037620755 | CI103: 0.037588348 | CJ103: 0.037654172 | CK103: 0.03757979 | CL103: =+CL102/CG102-1 -> 0.037611136 | CM103: 0.036708859 | CN103: 0.036657452 | CO103: 0.036763384 | CP103: 0.036644291 | CQ103: =+CQ102/CL102-1 -> 0.036694106 | CR103: 0.0203 | CS103: 0.0203 | CT103: 0.0203 | CU103: 0.0203 | CV103: =+CV102/CQ102-1 -> 0.0203
A104: Elasticidade PIB | J104: =+J103/(J$4/100) -> 106.81346 | K104: =+K103/(K$4/100) -> 0.66005417 | L104: =+L103/(L$4/100) -> 3.0204476 | M104: =+M103/(M$4/100) -> 10.229556 | N104: =+N103/(N$4/100) -> 14.391247 | O104: =+O103/(O$4/100) -> 5.0366374 | P104: =+P103/(P$4/100) -> 24.252535 | Q104: =+Q103/(Q$4/100) -> 7.4020096 | ... X104: =+X103/(X$4/100) -> 3.3297465 | Y104: =(+Y103/(Y$4/100)) -> 3.4195261 | Z104: =+Z103/(Z$4/100) -> 1.4525879 | AA104: =+AA103/(AA$4/100) -> 2.7360184 | AB104: =+AB103/(AB$4/100) -> 1.6032365 | AC104: =+AC103/(AC$4/100) -> -2.8376983 | AD104: =(+AD103/(AD$4/100)) -> 8.953583 | AE104: =+AE103/(AE$4/100) -> 1.6020369 | AF104: =+AF103/(AF$4/100) -> 0.53152645 | AG104: =+AG103/(AG$4/100) -> -0.66582465 | AH104: =+AH103/(AH$4/100) -> -3.9502297 | AI104: =(+AI103/(AI$4/100)) -> -0.62704329 | AJ104: =+AJ103/(AJ$4/100) -> -1.954653 | AK104: =+AK103/(AK$4/100) -> -1.9546605 | AL104: =+AL103/(AL$4/100) -> -1.9546636 | AM104: =+AM103/(AM$4/100) -> 0.35475633 | AN104: =(+AN103/(AN$4/100)) -> -1.3218851 | AO104: =+AO103/(AO$4/100) -> -0.17170678 | AP104: =+AP103/(AP$4/100) -> -1.2402062 | AQ104: =+AQ103/(AQ$4/100) -> -1.5260254 | AR104: =+AR103/(AR$4/100) -> -5.1669962 | AS104: =(+AS103/(AS$4/100)) -> -2.1058784 | AT104: =+AT103/(AT$4/100) -> 3.0285727 | AU104: =+AU103/(AU$4/100) -> 3.0431015 | AV104: =+AV103/(AV$4/100) -> 3.013516 | AW104: =+AW103/(AW$4/100) -> 3.0468131 | AX104: =(+AX103/(AX$4/100)) -> 3.0328227 | AY104: =+AY103/(AY$4/100) -> 2.02216 | AZ104: =+AZ103/(AZ$4/100) -> 2.0349503 | BA104: =+BA103/(BA$4/100) -> 2.0088033 | BB104: =+BB103/(BB$4/100) -> 2.038206 | BC104: =(+BC103/(BC$4/100)) -> 2.0258747 | BD104: =+BD103/(BD$4/100) -> 1.9664951 | BE104: =+BE103/(BE$4/100) -> 1.9772973 | BF104: =+BF103/(BF$4/100) -> 1.9554071 | BG104: =+BG103/(BG$4/100) -> 1.9799882 | BH104: =(+BH103/(BH$4/100)) -> 1.9696701 | BI104: =+BI103/(BI$4/100) -> 2.1096581 | BJ104: =+BJ103/(BJ$4/100) -> 2.1131067 | BK104: =+BK103/(BK$4/100) -> 2.1058721 | BL104: =+BL103/(BL$4/100) -> 2.1140823 | BM104: =(+BM103/(BM$4/100)) -> 2.1106377 | BN104: =+BN103/(BN$4/100) -> 2.0639349 | BO104: =+BO103/(BO$4/100) -> 2.0664265 | BP104: =+BP103/(BP$4/100) -> 2.0613552 | BQ104: =+BQ103/(BQ$4/100) -> 2.0670556 | BR104: =(+BR103/(BR$4/100)) -> 2.0646642 | BS104: =+BS103/(BS$4/100) -> 2.0181469 | BT104: =+BT103/(BT$4/100) -> 2.0196655 | BU104: =+BU103/(BU$4/100) -> 2.0166124 | BV104: =+BV103/(BV$4/100) -> 2.020037 | BW104: =(+BW103/(BW$4/100)) -> 2.0185983 | BX104: =+BX103/(BX$4/100) -> 1.9724812 | BY104: =+BY103/(BY$4/100) -> 1.9729418 | BZ104: =+BZ103/(BZ$4/100) -> 1.9719897 | CA104: =+CA103/(CA$4/100) -> 1.9729941 | CB104: =(+CB103/(CB$4/100)) -> 1.9725958 | CC104: =+CC103/(CC$4/100) -> 1.9267192 | CD104: =+CD103/(CD$4/100) -> 1.9261329 | CE104: =+CE103/(CE$4/100) -> 1.9272988 | CF104: =+CF103/(CF$4/100) -> 1.9260369 | CG104: =(+CG103/(CG$4/100)) -> 1.9265537 | CH104: =+CH103/(CH$4/100) -> 1.8810378 | CI104: =+CI103/(CI$4/100) -> 1.8794174 | CJ104: =+CJ103/(CJ$4/100) -> 1.8827086 | CK104: =+CK103/(CK$4/100) -> 1.8789895 | CL104: =(+CL103/(CL$4/100)) -> 1.8805568 | CM104: =+CM103/(CM$4/100) -> 1.835443 | CN104: =+CN103/(CN$4/100) -> 1.8328726 | CO104: =+CO103/(CO$4/100) -> 1.8381692 | CP104: =+CP103/(CP$4/100) -> 1.8322146 | CQ104: =(+CQ103/(CQ$4/100)) -> 1.8347053 | CR104: 0.585 | CS104: 0.585 | CT104: 0.585 | CU104: 0.54 | CV104: =(+CV103/(CV$4/100)) -> 1.015
A106: Receita de Pedágio | R106: =+R102*R94/1000 -> 2.7030892 | S106: =+S102*S94/1000 -> 2.7216952 | T106: =+T102*T94/1000 -> 10.20973 | U106: =+U102*U94/1000 -> 2.76976 | V106: =+V102*V94/1000 -> 2.6992511 | W106: =+W102*W94/1000 -> 2.8890774 | X106: =+X102*X94/1000 -> 3.0541193 | Y106: =+SUM(U106:X106) -> 11.412208 | Z106: =+Z102*Z94/1000 -> 2.8669348 | AA106: =+AA102*AA94/1000 -> 2.8469551 | AB106: =+AB102*AB94/1000 -> 3.1728428 | AC106: =+AC102*AC94/1000 -> 3.0654443 | AD106: =+SUM(Z106:AC106) -> 11.952177 | AE106: =+AE102*AE94/1000 -> 2.8991977 | AF106: =+AF102*AF94/1000 -> 2.9795278 | AG106: =+AG102*AG94/1000 -> 3.5621653 | AH106: =+AH102*AH94/1000 -> 3.7849127 | AI106: =+SUM(AE106:AH106) -> 13.225804 | AJ106: =+AJ102*AJ94/1000 -> 3.3137898 | AK106: =+AK102*AK94/1000 -> 3.4056079 | AL106: =+AL102*AL94/1000 -> 3.938313 | AM106: =+AM102*AM94/1000 -> 3.998574 | AN106: =+SUM(AJ106:AM106) -> 14.656285 | AO106: =+AO102*AO94/1000 -> 3.5198182 | AP106: =+AP102*AP94/1000 -> 3.5786271 | AQ106: =+AQ102*AQ94/1000 -> 4.072124 | AR106: =+AR102*AR94/1000 -> 3.9815663 | AS106: =+SUM(AO106:AR106) -> 15.152136 | AT106: =+AT102*AT94/1000 -> 3.9196696 | AU106: =+AU102*AU94/1000 -> 3.986251 | AV106: =+AV102*AV94/1000 -> 4.5334299 | AW106: =+AW102*AW94/1000 -> 4.4353974 | AX106: =+SUM(AT106:AW106) -> 16.874748 | AY106: =+AY102*AY94/1000 -> 4.2821033 | AZ106: =+AZ102*AZ94/1000 -> 4.3559119 | BA106: =+BA102*BA94/1000 -> 4.9277657 | BB106: =+BB102*BB94/1000 -> 4.8239316 | BC106: =+SUM(AY106:BB106) -> 18.389712 | BD106: =+BD102*BD94/1000 -> 4.6507913 | BE106: =+BE102*BE94/1000 -> 4.7319382 | BF106: =+BF102*BF94/1000 -> 5.3509031 | BG106: =+BG102*BG94/1000 -> 5.2406313 | BH106: =+SUM(BD106:BG106) -> 19.974264 | BI106: =+BI102*BI94/1000 -> 5.0651389 | BJ106: =+BJ102*BJ94/1000 -> 5.1538564 | BK106: =+BK102*BK94/1000 -> 5.8272016 | BL106: =+BL102*BL94/1000 -> 5.7080134 | BM106: =+SUM(BI106:BL106) -> 21.75421 | BN106: =+BN102*BN94/1000 -> 5.5115612 | BO106: =+BO102*BO94/1000 -> 5.6083663 | BP106: =+BP102*BP94/1000 -> 6.340475 | BQ106: =+BQ102*BQ94/1000 -> 6.2114685 | BR106: =+SUM(BN106:BQ106) -> 23.671871 | BS106: =+BS102*BS94/1000 -> 5.9920551 | BT106: =+BT102*BT94/1000 -> 6.0974776 | BU106: =+BU102*BU94/1000 -> 6.8930297 | BV106: =+BV102*BV94/1000 -> 6.7532252 | BW106: =+SUM(BS106:BV106) -> 25.735788 | BX106: =+BX102*BX94/1000 -> 6.5087192 | BY106: =+BY102*BY94/1000 -> 6.6232904 | BZ106: =+BZ102*BZ94/1000 -> 7.4873094 | CA106: =+CA102*CA94/1000 -> 7.3355935 | CB106: =+SUM(BX106:CA106) -> 27.954913 | CC106: =+CC102*CC94/1000 -> 7.0637075 | CD106: =+CD102*CD94/1000 -> 7.1879669 | CE106: =+CE102*CE94/1000 -> 8.1258312 | CF106: =+CF102*CF94/1000 -> 7.9609834 | CG106: =+SUM(CC106:CF106) -> 30.338489 | CH106: =+CH102*CH94/1000 -> 7.6592747 | CI106: =+CI102*CI94/1000 -> 7.7937675 | CJ106: =+CJ102*CJ94/1000 -> 8.8112338 | CK106: =+CK102*CK94/1000 -> 8.6318625 | CL106: =+SUM(CH106:CK106) -> 32.896138 | CM106: =+CM102*CM94/1000 -> 8.2977577 | CN106: =+CN102*CN94/1000 -> 8.4430431 | CO106: =+CO102*CO94/1000 -> 9.5462469 | CP106: =+CP102*CP94/1000 -> 9.3508387 | CQ106: =+SUM(CM106:CP106) -> 35.637886 | CR106: =+CR102*CR94/1000 -> 8.8471813 | CS106: =+CS102*CS94/1000 -> 9.0020866 | CT106: =+CT102*CT94/1000 -> 10.178337 | CU106: =+CU102*CU94/1000 -> 9.9699904 | CV106: =+SUM(CR106:CU106) -> 37.997596
A107: % Y/Y
A109: Praça Botucatu | U109: =+U122/$U$35 -> 0.20023116
A110: Tarifa (R$) | R110: 3.9 | S110: 3.9 | T110: 3.9 | U110: 3.9 | V110: =+V114*V$11+V115*V$12 -> 3.9445274 | W110: =+W114*W$11+W115*W$12 -> 3.9445274 | X110: =+X114*X$11+X115*X$12 -> 3.9445274 | Y110: =+Y122*1000/Y118 -> 3.9342105 | Z110: =+Z114*Z$11+Z115*Z$12 -> 3.9445274 | AA110: =+AA114*AA$11+AA115*AA$12 -> 3.9445274 | AB110: =+AB114*AB$11+AB115*AB$12 -> 4.1973716 | AC110: =+AC114*AC$11+AC115*AC$12 -> 4.1973716 | AD110: =+AD122*1000/AD118 -> 4.0745549 | AE110: =+AE114*AE$11+AE115*AE$12 -> 4.1973716 | AF110: =+AF114*AF$11+AF115*AF$12 -> 4.1973716 | AG110: =+AG114*AG$11+AG115*AG$12 -> 4.6171088 | AH110: =+AH114*AH$11+AH115*AH$12 -> 4.6171088 | AI110: =+AI122*1000/AI118 -> 4.419391 | AJ110: =+AJ114*AJ$11+AJ115*AJ$12 -> 4.6171088 | AK110: =+AK114*AK$11+AK115*AK$12 -> 4.6171088 | AL110: =+AL114*AL$11+AL115*AL$12 -> 4.9126037 | AM110: =+AM114*AM$11+AM115*AM$12 -> 4.9126037 | AN110: =+AN122*1000/AN118 -> 4.7717033 | AO110: =+AO114*AO$11+AO115*AO$12 -> 4.9126037 | AP110: =+AP114*AP$11+AP115*AP$12 -> 4.9126037 | AQ110: =+AQ114*AQ$11+AQ115*AQ$12 -> 5.1582339 | AR110: =+AR114*AR$11+AR115*AR$12 -> 5.1582339 | AS110: =+AS122*1000/AS118 -> 5.0432537 | AT110: =+AT114*AT$11+AT115*AT$12 -> 5.1582339 | AU110: =+AU114*AU$11+AU115*AU$12 -> 5.1582339 | AV110: =+AV114*AV$11+AV115*AV$12 -> 5.4161456 | AW110: =+AW114*AW$11+AW115*AW$12 -> 5.4161456 | AX110: =+AX122*1000/AX118 -> 5.2953776 | AY110: =+AY114*AY$11+AY115*AY$12 -> 5.4161456 | AZ110: =+AZ114*AZ$11+AZ115*AZ$12 -> 5.4161456 | BA110: =+BA114*BA$11+BA115*BA$12 -> 5.6598722 | BB110: =+BB114*BB$11+BB115*BB$12 -> 5.6598722 | BC110: =+BC122*1000/BC118 -> 5.5457132 | BD110: =+BD114*BD$11+BD115*BD$12 -> 5.6598722 | BE110: =+BE114*BE$11+BE115*BE$12 -> 5.6598722 | BF110: =+BF114*BF$11+BF115*BF$12 -> 5.9145664 | BG110: =+BG114*BG$11+BG115*BG$12 -> 5.9145664 | BH110: =+BH122*1000/BH118 -> 5.7952414 | BI110: =+BI114*BI$11+BI115*BI$12 -> 5.9145664 | BJ110: =+BJ114*BJ$11+BJ115*BJ$12 -> 5.9145664 | BK110: =+BK114*BK$11+BK115*BK$12 -> 6.1807219 | BL110: =+BL114*BL$11+BL115*BL$12 -> 6.1807219 | BM110: =+BM122*1000/BM118 -> 6.0560173 | BN110: =+BN114*BN$11+BN115*BN$12 -> 6.1807219 | BO110: =+BO114*BO$11+BO115*BO$12 -> 6.1807219 | BP110: =+BP114*BP$11+BP115*BP$12 -> 6.4588544 | BQ110: =+BQ114*BQ$11+BQ115*BQ$12 -> 6.4588544 | BR110: =+BR122*1000/BR118 -> 6.3285307 | BS110: =+BS114*BS$11+BS115*BS$12 -> 6.4588544 | BT110: =+BT114*BT$11+BT115*BT$12 -> 6.4588544 | BU110: =+BU114*BU$11+BU115*BU$12 -> 6.7495028 | BV110: =+BV114*BV$11+BV115*BV$12 -> 6.7495028 | BW110: =+BW122*1000/BW118 -> 6.6133101 | BX110: =+BX114*BX$11+BX115*BX$12 -> 6.7495028 | BY110: =+BY114*BY$11+BY115*BY$12 -> 6.7495028 | BZ110: =+BZ114*BZ$11+BZ115*BZ$12 -> 7.0532305 | CA110: =+CA114*CA$11+CA115*CA$12 -> 7.0532305 | CB110: =+CB122*1000/CB118 -> 6.9109076 | CC110: =+CC114*CC$11+CC115*CC$12 -> 7.0532305 | CD110: =+CD114*CD$11+CD115*CD$12 -> 7.0532305 | CE110: =+CE114*CE$11+CE115*CE$12 -> 7.3706258 | CF110: =+CF114*CF$11+CF115*CF$12 -> 7.3706258 | CG110: =+CG122*1000/CG118 -> 7.2219003 | CH110: =+CH114*CH$11+CH115*CH$12 -> 7.3706258 | CI110: =+CI114*CI$11+CI115*CI$12 -> 7.3706258 | CJ110: =+CJ114*CJ$11+CJ115*CJ$12 -> 7.702304 | CK110: =+CK114*CK$11+CK115*CK$12 -> 7.702304 | CL110: =+CL122*1000/CL118 -> 7.5468915 | CM110: =+CM114*CM$11+CM115*CM$12 -> 7.702304 | CN110: =+CN114*CN$11+CN115*CN$12 -> 7.702304 | CO110: =+CO114*CO$11+CO115*CO$12 -> 8.0489077 | CP110: =+CP114*CP$11+CP115*CP$12 -> 8.0489077 | CQ110: =+CQ122*1000/CQ118 -> 7.8865112 | CR110: =+CR114*CR$11+CR115*CR$12 -> 8.0489077 | CS110: =+CS114*CS$11+CS115*CS$12 -> 8.0489077 | CT110: =+CT114*CT$11+CT115*CT$12 -> 8.4111085 | CU110: =+CU114*CU$11+CU115*CU$12 -> 8.4111085 | CV110: =+CV122*1000/CV118 -> 8.2414042
A111: YoY (%)
A113: Distância Total (km) | U113: =+U114+U115 -> 37.66 | V113: =+V114+V115 -> 37.66 | W113: =+W114+W115 -> 37.66 | X113: =+X114+X115 -> 37.66 | Y113: =+Y114+Y115 -> 37.66 | Z113: =+Z114+Z115 -> 37.66 | AA113: =+AA114+AA115 -> 37.66 | AB113: =+AB114+AB115 -> 37.66 | ... CV113: =+CV114+CV115 -> 37.66
A114: Pista Simples | U114: 12.91 | V114: 12.91 | W114: 12.91 | X114: 12.91 | Y114: 12.91 | Z114: 12.91 | AA114: 12.91 | AB114: 12.91 | AC114: 12.91 | AD114: 12.91 | AE114: 12.91 | AF114: 12.91 | AG114: 12.91 | AH114: 12.91 | AI114: 12.91 | AJ114: 12.91 | AK114: 12.91 | AL114: 12.91 | AM114: 12.91 | AN114: 12.91 | AO114: 12.91 | AP114: 12.91 | AQ114: 12.91 | AR114: 12.91 | AS114: 12.91 | AT114: 12.91 | AU114: 12.91 | AV114: 12.91 | AW114: 12.91 | AX114: 12.91 | AY114: 12.91 | AZ114: 12.91 | BA114: 12.91 | BB114: 12.91 | BC114: 12.91 | BD114: 12.91 | BE114: 12.91 | BF114: 12.91 | BG114: 12.91 | BH114: 12.91 | BI114: 12.91 | BJ114: 12.91 | BK114: 12.91 | BL114: 12.91 | BM114: 12.91 | BN114: 12.91 | BO114: 12.91 | BP114: 12.91 | BQ114: 12.91 | BR114: 12.91 | BS114: 12.91 | BT114: 12.91 | BU114: 12.91 | BV114: 12.91 | BW114: 12.91 | BX114: 12.91 | BY114: 12.91 | BZ114: 12.91 | CA114: 12.91 | CB114: 12.91 | CC114: 12.91 | CD114: 12.91 | CE114: 12.91 | CF114: 12.91 | CG114: 12.91 | CH114: 12.91 | CI114: 12.91 | CJ114: 12.91 | CK114: 12.91 | CL114: 12.91 | CM114: 12.91 | CN114: 12.91 | CO114: 12.91 | CP114: 12.91 | CQ114: 12.91 | CR114: 12.91 | CS114: 12.91 | CT114: 12.91 | CU114: 12.91 | CV114: 12.91
A115: Pista Dupla | U115: 24.75 | V115: 24.75 | W115: 24.75 | X115: 24.75 | Y115: 24.75 | Z115: 24.75 | AA115: 24.75 | AB115: 24.75 | AC115: 24.75 | AD115: 24.75 | AE115: 24.75 | AF115: 24.75 | AG115: 24.75 | AH115: 24.75 | AI115: 24.75 | AJ115: 24.75 | AK115: 24.75 | AL115: 24.75 | AM115: 24.75 | AN115: 24.75 | AO115: 24.75 | AP115: 24.75 | AQ115: 24.75 | AR115: 24.75 | AS115: 24.75 | AT115: 24.75 | AU115: 24.75 | AV115: 24.75 | AW115: 24.75 | AX115: 24.75 | AY115: 24.75 | AZ115: 24.75 | BA115: 24.75 | BB115: 24.75 | BC115: 24.75 | BD115: 24.75 | BE115: 24.75 | BF115: 24.75 | BG115: 24.75 | BH115: 24.75 | BI115: 24.75 | BJ115: 24.75 | BK115: 24.75 | BL115: 24.75 | BM115: 24.75 | BN115: 24.75 | BO115: 24.75 | BP115: 24.75 | BQ115: 24.75 | BR115: 24.75 | BS115: 24.75 | BT115: 24.75 | BU115: 24.75 | BV115: 24.75 | BW115: 24.75 | BX115: 24.75 | BY115: 24.75 | BZ115: 24.75 | CA115: 24.75 | CB115: 24.75 | CC115: 24.75 | CD115: 24.75 | CE115: 24.75 | CF115: 24.75 | CG115: 24.75 | CH115: 24.75 | CI115: 24.75 | CJ115: 24.75 | CK115: 24.75 | CL115: 24.75 | CM115: 24.75 | CN115: 24.75 | CO115: 24.75 | CP115: 24.75 | CQ115: 24.75 | CR115: 24.75 | CS115: 24.75 | CT115: 24.75 | CU115: 24.75 | CV115: 24.75
A116: % Pista Dupla | U116: =+U115/U113 -> 0.65719596 | V116: =+V115/V113 -> 0.65719596 | W116: =+W115/W113 -> 0.65719596 | X116: =+X115/X113 -> 0.65719596 | Y116: =+Y115/Y113 -> 0.65719596 | Z116: =+Z115/Z113 -> 0.65719596 | AA116: =+AA115/AA113 -> 0.65719596 | AB116: =+AB115/AB113 -> 0.65719596 | ... CV116: =+CV115/CV113 -> 0.65719596
A118: Tráfego (Mil Veículos Equivalentes) | D118: 1003.504 | E118: 1003.504 | F118: 2076.0345 | G118: 2209.4065 | H118: 2286.1555 | I118: 2251.967 | J118: 8823.5635 | K118: 2021.382 | L118: 2178.1825 | M118: 2306.0965 | N118: 2244.3955 | O118: 8750.0565 | P118: 2110.512 | Q118: 2129.848 | R118: 2362.5135 | S118: 2381.67 | T118: 8984.5435 | U118: 2227.7 | V118: 2291.9 | W118: 2529.2 | X118: 2565.9 | Y118: =+SUM(U118:X118) -> 9614.7 | Z118: 2412.092 | AA118: 2408.483 | AB118: 2532.854 | AC118: 2570.748 | AD118: =+SUM(Z118:AC118) -> 9924.177 | AE118: 2188.7185 | AF118: 2311.9905 | AG118: 2446.8295 | AH118: =AC118*(1+AH119) -> 2607.064 | AI118: =+SUM(AE118:AH118) -> 9554.6025 | AJ118: =AE118*(1+AJ119) -> 2274.282 | AK118: =AF118*(1+AK119) -> 2402.373 | AL118: =AG118*(1+AL119) -> 2542.484 | AM118: =AH118*(1+AM119) -> 2588.697 | AN118: =+SUM(AJ118:AM118) -> 9807.836 | AO118: =AJ118*(1+AO119) -> 2275.056 | AP118: =AK118*(1+AP119) -> 2445.377 | AQ118: =AL118*(1+AQ119) -> 2646.446 | AR118: =AM118*(1+AR119) -> 2717.302 | AS118: =+SUM(AO118:AR118) -> 10084.181 | AT118: =AO118*(1+AT119) -> 2415.052 | AU118: =AP118*(1+AU119) -> 2594.992 | AV118: =AQ118*(1+AV119) -> 2806.493 | AW118: =AR118*(1+AW119) -> 2882.893 | AX118: =+SUM(AT118:AW118) -> 10699.43 | AY118: =AT118*(1+AY119) -> 2514.786 | AZ118: =AU118*(1+AZ119) -> 2701.346 | BA118: =AV118*(1+BA119) -> 2919.756 | BB118: =AW118*(1+BB119) -> 3000.426 | BC118: =+SUM(AY118:BB118) -> 11136.314 | BD118: =AY118*(1+BD119) -> 2615.483 | BE118: =AZ118*(1+BE119) -> 2808.812 | BF118: =BA118*(1+BF119) -> 3034.385 | BG118: =BB118*(1+BG119) -> 3119.25 | BH118: =+SUM(BD118:BG118) -> 11577.93 | BI118: =BD118*(1+BI119) -> 2726.451 | BJ118: =BE118*(1+BJ119) -> 2927.741 | BK118: =BF118*(1+BK119) -> 3162.342 | BL118: =BG118*(1+BL119) -> 3251.139 | BM118: =+SUM(BI118:BL118) -> 12067.673 | BN118: =BI118*(1+BN119) -> 2839.446 | BO118: =BJ118*(1+BO119) -> 3048.901 | BP118: =BK118*(1+BP119) -> 3292.825 | BQ118: =BL118*(1+BQ119) -> 3385.546 | BR118: =+SUM(BN118:BQ118) -> 12566.718 | BS118: =BN118*(1+BS119) -> 2954.336 | BT118: =BO118*(1+BT119) -> 3172.157 | BU118: =BP118*(1+BU119) -> 3425.704 | BV118: =BQ118*(1+BV119) -> 3522.327 | BW118: =+SUM(BS118:BV118) -> 13074.524 | BX118: =BS118*(1+BX119) -> 3070.969 | BY118: =BT118*(1+BY119) -> 3297.355 | BZ118: =BU118*(1+BZ119) -> 3560.834 | CA118: =BV118*(1+CA119) -> 3661.319 | CB118: =+SUM(BX118:CA118) -> 13590.477 | CC118: =BX118*(1+CC119) -> 3189.19 | CD118: =BY118*(1+CD119) -> 3424.337 | CE118: =BZ118*(1+CE119) -> 3698.062 | CF118: =CA118*(1+CF119) -> 3802.353 | CG118: =+SUM(CC118:CF118) -> 14113.942 | CH118: =CC118*(1+CH119) -> 3308.832 | CI118: =CD118*(1+CI119) -> 3552.933 | CJ118: =CE118*(1+CJ119) -> 3837.224 | CK118: =CF118*(1+CK119) -> 3945.246 | CL118: =+SUM(CH118:CK118) -> 14644.235 | CM118: =CH118*(1+CM119) -> 3429.723 | CN118: =CI118*(1+CN119) -> 3682.966 | CO118: =CJ118*(1+CO119) -> 3978.152 | CP118: =CK118*(1+CP119) -> 4089.811 | CQ118: =+SUM(CM118:CP118) -> 15180.652 | CR118: =CM118*(1+CR119) -> 3499.3464 | CS118: =CN118*(1+CS119) -> 3757.7302 | CT118: =CO118*(1+CT119) -> 4058.9085 | CU118: =CP118*(1+CU119) -> 4172.8342 | CV118: =+SUM(CR118:CU118) -> 15488.819
A119: YoY (%) | I119: =+I118/D118-1 -> 1.2441037 | J119: =+J118/E118-1 -> 7.7927537 | K119: =+K118/F118-1 -> -0.02632543 | L119: =+L118/G118-1 -> -0.014132302 | M119: =+M118/H118-1 -> 0.0087225038 | N119: =+N118/I118-1 -> -0.0033621718 | O119: =+O118/J118-1 -> -0.0083307611 | P119: =+P118/K118-1 -> 0.044093595 | ... AG119: =+AG118/AB118-1 -> -0.033963466 | AH119: 0.014126628 | AI119: =+AI118/AD118-1 -> -0.037239813 | AJ119: 0.039092967 | AK119: 0.039092937 | AL119: 0.039093243 | AM119: -0.0070450898 | AN119: =+AN118/AI118-1 -> 0.026503824 | AO119: 0.00034032719 | AP119: 0.017900634 | AQ119: 0.040889933 | AR119: 0.049679433 | AS119: =+AS118/AN118-1 -> 0.02817594 | AT119: 0.061535189 | AU119: 0.061182795 | AV119: 0.060476201 | AW119: 0.060939491 | AX119: =+AX118/AS118-1 -> 0.061011301 | AY119: 0.041296833 | AZ119: 0.040984327 | BA119: 0.040357485 | BB119: 0.040769116 | BC119: =+BC118/AX118-1 -> 0.040832456 | BD119: 0.040041976 | BE119: 0.03978239 | BF119: 0.039259787 | BG119: 0.039602376 | BH119: =+BH118/BC118-1 -> 0.039655491 | BI119: 0.042427345 | BJ119: 0.042341388 | BK119: 0.042169006 | BL119: 0.042282279 | BM119: =+BM118/BH118-1 -> 0.042299703 | BN119: 0.041443987 | BO119: 0.041383442 | BP119: 0.041261508 | BQ119: 0.041341511 | BR119: =+BR118/BM118-1 -> 0.041353872 | BS119: 0.040462118 | BT119: 0.04042637 | BU119: 0.040354103 | BV119: 0.04040146 | BW119: =+BW118/BR118-1 -> 0.0404088 | BX119: 0.039478583 | BY119: 0.039467782 | BZ119: 0.039445907 | CA119: 0.039460277 | CB119: =+CB118/BW118-1 -> 0.039462469 | CC119: 0.038496318 | CD119: 0.03851026 | CE119: 0.038538163 | CF119: 0.038519998 | CG119: =+CG118/CB118-1 -> 0.038517044 | CH119: 0.037514855 | CI119: 0.037553547 | CJ119: 0.037631062 | CK119: 0.037580151 | CL119: =+CL118/CG118-1 -> 0.037572281 | CM119: 0.036535853 | CN119: 0.036598776 | CO119: 0.03672655 | CP119: 0.036642835 | CQ119: =+CQ118/CL118-1 -> 0.036629909 | CR119: 0.0203 | CS119: 0.0203 | CT119: 0.0203 | CU119: 0.0203 | CV119: =+CV118/CQ118-1 -> 0.0203
A120: Elasticidade PIB | J120: =+J119/(J$4/100) -> 103.43976 | K120: =+K119/(K$4/100) -> -0.62151984 | L120: =+L119/(L$4/100) -> -0.42639637 | M120: =+M119/(M$4/100) -> 0.41105758 | N120: =+N119/(N$4/100) -> -0.24604985 | O120: =+O119/(O$4/100) -> -0.30487586 | P120: =+P119/(P$4/100) -> 5.857722 | Q120: =+Q119/(Q$4/100) -> -4.5307023 | ... CV120: =+CV119/(CV$4/100) -> 1.015
A122: Receita de Pedágio | R122: =+R118*R110/1000 -> 9.2138026 | S122: =+S118*S110/1000 -> 9.288513 | T122: =+T118*T110/1000 -> 35.03972 | U122: =+U118*U110/1000 -> 8.68803 | V122: =+V118*V110/1000 -> 9.0404623 | W122: =+W118*W110/1000 -> 9.9764987 | X122: =+X118*X110/1000 -> 10.121263 | Y122: =+SUM(U122:X122) -> 37.826254 | Z122: =+Z118*Z110/1000 -> 9.514563 | AA122: =+AA118*AA110/1000 -> 9.5003272 | AB122: =+AB118*AB110/1000 -> 10.631329 | AC122: =+AC118*AC110/1000 -> 10.790385 | AD122: =+SUM(Z122:AC122) -> 40.436604 | AE122: =+AE118*AE110/1000 -> 9.1868649 | AF122: =+AF118*AF110/1000 -> 9.7042833 | AG122: =+AG118*AG110/1000 -> 11.297278 | AH122: =+AH118*AH110/1000 -> 12.037098 | AI122: =+SUM(AE122:AH122) -> 42.225524 | AJ122: =+AJ118*AJ110/1000 -> 10.500607 | AK122: =+AK118*AK110/1000 -> 11.092017 | AL122: =+AL118*AL110/1000 -> 12.490216 | AM122: =+AM118*AM110/1000 -> 12.717243 | AN122: =+SUM(AJ122:AM122) -> 46.800084 | AO122: =+AO118*AO110/1000 -> 11.176449 | AP122: =+AP118*AP110/1000 -> 12.013168 | AQ122: =+AQ118*AQ110/1000 -> 13.650988 | AR122: =+AR118*AR110/1000 -> 14.016479 | AS122: =+SUM(AO122:AR122) -> 50.857084 | AT122: =+AT118*AT110/1000 -> 12.457403 | AU122: =+AU118*AU110/1000 -> 13.385576 | AV122: =+AV118*AV110/1000 -> 15.200375 | AW122: =+AW118*AW110/1000 -> 15.614168 | AX122: =+SUM(AT122:AW122) -> 56.657522 | AY122: =+AY118*AY110/1000 -> 13.620447 | AZ122: =+AZ118*AZ110/1000 -> 14.630883 | BA122: =+BA118*BA110/1000 -> 16.525446 | BB122: =+BB118*BB110/1000 -> 16.982028 | BC122: =+SUM(AY122:BB122) -> 61.758804 | BD122: =+BD118*BD110/1000 -> 14.803299 | BE122: =+BE118*BE110/1000 -> 15.897517 | BF122: =+BF118*BF110/1000 -> 17.947072 | BG122: =+BG118*BG110/1000 -> 18.449011 | BH122: =+SUM(BD122:BG122) -> 67.096899 | BI122: =+BI118*BI110/1000 -> 16.125776 | BJ122: =+BJ118*BJ110/1000 -> 17.316319 | BK122: =+BK118*BK110/1000 -> 19.545556 | BL122: =+BL118*BL110/1000 -> 20.094386 | BM122: =+SUM(BI122:BL122) -> 73.082037 | BN122: =+BN118*BN110/1000 -> 17.549826 | BO122: =+BO118*BO110/1000 -> 18.844409 | BP122: =+BP118*BP110/1000 -> 21.267877 | BQ122: =+BQ118*BQ110/1000 -> 21.866749 | BR122: =+SUM(BN122:BQ122) -> 79.528861 | BS122: =+BS118*BS110/1000 -> 19.081626 | BT122: =+BT118*BT110/1000 -> 20.4885 | BU122: =+BU118*BU110/1000 -> 23.121799 | BV122: =+BV118*BV110/1000 -> 23.773956 | BW122: =+SUM(BS122:BV122) -> 86.465881 | BX122: =+BX118*BX110/1000 -> 20.727514 | BY122: =+BY118*BY110/1000 -> 22.255507 | BZ122: =+BZ118*BZ110/1000 -> 25.115383 | CA122: =+CA118*CA110/1000 -> 25.824127 | CB122: =+SUM(BX122:CA122) -> 93.92253 | CC122: =+CC118*CC110/1000 -> 22.494092 | CD122: =+CD118*CD110/1000 -> 24.152638 | CE122: =+CE118*CE110/1000 -> 27.257031 | CF122: =+CF118*CF110/1000 -> 28.025721 | CG122: =+SUM(CC122:CF122) -> 101.92948 | CH122: =+CH118*CH110/1000 -> 24.388163 | CI122: =+CI118*CI110/1000 -> 26.18734 | CJ122: =+CJ118*CJ110/1000 -> 29.555466 | CK122: =+CK118*CK110/1000 -> 30.387484 | CL122: =+SUM(CH122:CK122) -> 110.51845 | CM122: =+CM118*CM110/1000 -> 26.416769 | CN122: =+CN118*CN110/1000 -> 28.367324 | CO122: =+CO118*CO110/1000 -> 32.019778 | CP122: =+CP118*CP110/1000 -> 32.918511 | CQ122: =+SUM(CM122:CP122) -> 119.72238 | CR122: =+CR118*CR110/1000 -> 28.165916 | CS122: =+CS118*CS110/1000 -> 30.245624 | CT122: =+CT118*CT110/1000 -> 34.13992 | CU122: =+CU118*CU110/1000 -> 35.098161 | CV122: =+SUM(CR122:CU122) -> 127.64962
A123: % Y/Y
A125: Praça Areiópolis | U125: =+U138/$U$35 -> 0.20411579
