Workbook

Sheet Planilha2
A1: Tabelas de Alíquotas Simples Nacional | I1: 0.28
I2: Alíquota mês | K2: Receita Bruta 12 | M2: Fator R | N2: Alíquota Rep | O2: Dedução | P2: Alíquota Com | Q2: Dedução
A3: Receita Bruta Total em 12 meses | E3: Alíquota | F3: Quanto descontar do valor recolhido | I3: Mês 01 | K3: =Planilha1!D11*12 -> 0 | M3: =((Planilha1!$B$3+Planilha1!$D$3)*12)/Planilha2!K3 -> #DIV/0! | N3: =IF(M3>=$I$1,(LOOKUP($K3,$B$12:$D$17,$E$12:$E$17)),(LOOKUP(K3,$B$20:$D$25,$E$20:$E$25))) -> #DIV/0! | O3: =LOOKUP($K3,$B$12:$D$17,$F$12:$F$17) -> 0 | P3: =LOOKUP($K3,$B$4:$D$9,$E$4:$E$9) -> 0.04 | Q3: =LOOKUP($K3,$B$12:$D$17,$F$12:$F$17) -> 0
A4: De | B4: 0 | C4: Até | D4: 180000 | E4: 0.04 | F4: 0 | I4: Mês 02 | K4: =((Planilha1!D12+Planilha1!D11)/2)*12 -> 0 | M4: =((Planilha1!$B$3+Planilha1!$D$3)*12)/Planilha2!K4 -> #DIV/0! | N4: =IF(M4>=$I$1,(LOOKUP($K4,$B$12:$D$17,$E$12:$E$17)),(LOOKUP(K4,$B$20:$D$25,$E$20:$E$25))) -> #DIV/0! | O4: =LOOKUP($K4,$B$12:$D$17,$F$12:$F$17) -> 0 | P4: =LOOKUP($K4,$B$4:$D$9,$E$4:$E$9) -> 0.04 | Q4: =LOOKUP($K4,$B$12:$D$17,$F$12:$F$17) -> 0
A5: De | B5: 180000.01 | C5: Até | D5: 360000 | E5: 0.073 | F5: 5940 | I5: Mês 03 | K5: =((Planilha1!D11+Planilha1!D12+Planilha1!D13)/3)*12 -> 0 | M5: =((Planilha1!$B$3+Planilha1!$D$3)*12)/Planilha2!K5 -> #DIV/0! | N5: =IF(M5>=$I$1,(LOOKUP($K5,$B$12:$D$17,$E$12:$E$17)),(LOOKUP(K5,$B$20:$D$25,$E$20:$E$25))) -> #DIV/0! | O5: =LOOKUP($K5,$B$12:$D$17,$F$12:$F$17) -> 0 | P5: =LOOKUP($K5,$B$4:$D$9,$E$4:$E$9) -> 0.04 | Q5: =LOOKUP($K5,$B$12:$D$17,$F$12:$F$17) -> 0
A6: De | B6: 360000.01 | C6: Até | D6: 720000 | E6: 0.095 | F6: 13860 | I6: Mês 04 | K6: =((Planilha1!D11+Planilha1!D12+Planilha1!D13+Planilha1!D14)/4)*12 -> 0 | M6: =((Planilha1!$B$3+Planilha1!$D$3)*12)/Planilha2!K6 -> #DIV/0! | N6: =IF(M6>=$I$1,(LOOKUP($K6,$B$12:$D$17,$E$12:$E$17)),(LOOKUP(K6,$B$20:$D$25,$E$20:$E$25))) -> #DIV/0! | O6: =LOOKUP($K6,$B$12:$D$17,$F$12:$F$17) -> 0 | P6: =LOOKUP($K6,$B$4:$D$9,$E$4:$E$9) -> 0.04 | Q6: =LOOKUP($K6,$B$12:$D$17,$F$12:$F$17) -> 0
A7: De | B7: 720000.01 | C7: Até | D7: 1800000 | E7: 0.107 | F7: 22500 | I7: Mês 05 | K7: =((Planilha1!D15+Planilha1!D14+Planilha1!D13+Planilha1!D12+Planilha1!D11)/5)*12 -> 0 | M7: =((Planilha1!$B$3+Planilha1!$D$3)*12)/Planilha2!K7 -> #DIV/0! | N7: =IF(M7>=$I$1,(LOOKUP($K7,$B$12:$D$17,$E$12:$E$17)),(LOOKUP(K7,$B$20:$D$25,$E$20:$E$25))) -> #DIV/0! | O7: =LOOKUP($K7,$B$12:$D$17,$F$12:$F$17) -> 0 | P7: =LOOKUP($K7,$B$4:$D$9,$E$4:$E$9) -> 0.04 | Q7: =LOOKUP($K7,$B$12:$D$17,$F$12:$F$17) -> 0
A8: De | B8: 1800000 | C8: Até | D8: 3600000 | E8: 0.143 | F8: 87300 | I8: Mês 06 | K8: =((Planilha1!D11+Planilha1!D12+Planilha1!D13+Planilha1!D14+Planilha1!D15+Planilha1!D16)/6)*12 -> 0 | M8: =((Planilha1!$B$3+Planilha1!$D$3)*12)/Planilha2!K8 -> #DIV/0! | N8: =IF(M8>=$I$1,(LOOKUP($K8,$B$12:$D$17,$E$12:$E$17)),(LOOKUP(K8,$B$20:$D$25,$E$20:$E$25))) -> #DIV/0! | O8: =LOOKUP($K8,$B$12:$D$17,$F$12:$F$17) -> 0 | P8: =LOOKUP($K8,$B$4:$D$9,$E$4:$E$9) -> 0.04 | Q8: =LOOKUP($K8,$B$12:$D$17,$F$12:$F$17) -> 0
A9: De | B9: 3600000 | C9: Até | D9: 4800000 | E9: 0.19 | F9: 378000 | I9: Mês 07 | K9: =((Planilha1!D11+Planilha1!D12+Planilha1!D13+Planilha1!D14+Planilha1!D15+Planilha1!D16+Planilha1!D17)/7)*12 -> 0 | M9: =((Planilha1!$B$3+Planilha1!$D$3)*12)/Planilha2!K9 -> #DIV/0! | N9: =IF(M9>=$I$1,(LOOKUP($K9,$B$12:$D$17,$E$12:$E$17)),(LOOKUP(K9,$B$20:$D$25,$E$20:$E$25))) -> #DIV/0! | O9: =LOOKUP($K9,$B$12:$D$17,$F$12:$F$17) -> 0 | P9: =LOOKUP($K9,$B$4:$D$9,$E$4:$E$9) -> 0.04 | Q9: =LOOKUP($K9,$B$12:$D$17,$F$12:$F$17) -> 0
I10: Mês 08 | K10: =((Planilha1!D11+Planilha1!D12+Planilha1!D13+Planilha1!D14+Planilha1!D15+Planilha1!D16+Planilha1!D17+Planilha1!D18)/8)*12 -> 0 | M10: =((Planilha1!$B$3+Planilha1!$D$3)*12)/Planilha2!K10 -> #DIV/0! | N10: =IF(M10>=$I$1,(LOOKUP($K10,$B$12:$D$17,$E$12:$E$17)),(LOOKUP(K10,$B$20:$D$25,$E$20:$E$25))) -> #DIV/0! | O10: =LOOKUP($K10,$B$12:$D$17,$F$12:$F$17) -> 0 | P10: =LOOKUP($K10,$B$4:$D$9,$E$4:$E$9) -> 0.04 | Q10: =LOOKUP($K10,$B$12:$D$17,$F$12:$F$17) -> 0
A11: Receita Bruta Total em 12 meses | E11: Alíquota | F11: Quanto descontar do valor recolhido | I11: Mês 09 | K11: =(SUM(Planilha1!D11:D19)/9)*12 -> 0 | M11: =((Planilha1!$B$3+Planilha1!$D$3)*12)/Planilha2!K11 -> #DIV/0! | N11: =IF(M11>=$I$1,(LOOKUP($K11,$B$12:$D$17,$E$12:$E$17)),(LOOKUP(K11,$B$20:$D$25,$E$20:$E$25))) -> #DIV/0! | O11: =LOOKUP($K11,$B$12:$D$17,$F$12:$F$17) -> 0 | P11: =LOOKUP($K11,$B$4:$D$9,$E$4:$E$9) -> 0.04 | Q11: =LOOKUP($K11,$B$12:$D$17,$F$12:$F$17) -> 0
A12: De | B12: 0 | C12: Até | D12: 180000 | E12: 0.06 | F12: 0 | I12: Mês 10 | K12: =(SUM(Planilha1!D11:D20)/10)*12 -> 0 | M12: =((Planilha1!$B$3+Planilha1!$D$3)*12)/Planilha2!K12 -> #DIV/0! | N12: =IF(M12>=$I$1,(LOOKUP($K12,$B$12:$D$17,$E$12:$E$17)),(LOOKUP(K12,$B$20:$D$25,$E$20:$E$25))) -> #DIV/0! | O12: =LOOKUP($K12,$B$12:$D$17,$F$12:$F$17) -> 0 | P12: =LOOKUP($K12,$B$4:$D$9,$E$4:$E$9) -> 0.04 | Q12: =LOOKUP($K12,$B$12:$D$17,$F$12:$F$17) -> 0
A13: De | B13: 180000.01 | C13: Até | D13: 360000 | E13: 0.112 | F13: 9360 | I13: Mês 11 | K13: =(SUM(Planilha1!$D$11:D21)/11)*12 -> 0 | M13: =((Planilha1!$B$3+Planilha1!$D$3)*12)/Planilha2!K13 -> #DIV/0! | N13: =IF(M13>=$I$1,(LOOKUP($K13,$B$12:$D$17,$E$12:$E$17)),(LOOKUP(K13,$B$20:$D$25,$E$20:$E$25))) -> #DIV/0! | O13: =LOOKUP($K13,$B$12:$D$17,$F$12:$F$17) -> 0 | P13: =LOOKUP($K13,$B$4:$D$9,$E$4:$E$9) -> 0.04 | Q13: =LOOKUP($K13,$B$12:$D$17,$F$12:$F$17) -> 0
A14: De | B14: 360000.01 | C14: Até | D14: 720000 | E14: 0.135 | F14: 17640 | I14: Mês 12 | K14: =(SUM(Planilha1!$D$11:D22)) -> 0 | M14: =((Planilha1!$B$3+Planilha1!$D$3)*12)/Planilha2!K14 -> #DIV/0! | N14: =IF(M14>=$I$1,(LOOKUP($K14,$B$12:$D$17,$E$12:$E$17)),(LOOKUP(K14,$B$20:$D$25,$E$20:$E$25))) -> #DIV/0! | O14: =LOOKUP($K14,$B$12:$D$17,$F$12:$F$17) -> 0 | P14: =LOOKUP($K14,$B$4:$D$9,$E$4:$E$9) -> 0.04 | Q14: =LOOKUP($K14,$B$12:$D$17,$F$12:$F$17) -> 0
A15: De | B15: 720000.01 | C15: Até | D15: 1800000 | E15: 0.16 | F15: 35640
A16: De | B16: 1800000 | C16: Até | D16: 3600000 | E16: 0.21 | F16: 125640
A17: De | B17: 3600000 | C17: Até | D17: 4800000 | E17: 0.33 | F17: 648000
A19: Receita Bruta Total em 12 meses | E19: Alíquota | F19: Quanto descontar do valor recolhido
A20: De | B20: 0 | C20: Até | D20: 180000 | E20: 0.155 | F20: 0
A21: De | B21: 180000.01 | C21: Até | D21: 360000 | E21: 0.18 | F21: 4500
A22: De | B22: 360000.01 | C22: Até | D22: 720000 | E22: 0.195 | F22: 9900
A23: De | B23: 720000.01 | C23: Até | D23: 1800000 | E23: 0.205 | F23: 17100
A24: De | B24: 1800000 | C24: Até | D24: 3600000 | E24: 0.23 | F24: 62100
A25: De | B25: 3600000 | C25: Até | D25: 4800000 | E25: 0.305 | F25: 540000

Sheet Planilha1
A1: Planilha para Cálculo do Simples Nacional - Representantação e Comércio
A3: Pró-Labore | C3: INSS Pró-Labore | D3: =IF(B3<=5645.8,B3*11%,5645.8*11%) -> 0 | E3: Esse é o salário do sócio da empresa. Ao menos um dos sócios é obrigado a ter um salário de pelo menos um salário mínimo nacional vigênte.
A4: OBS: | B4: Quando a soma de Pró-Labore + INSS Acumulado nos últimos 12 meses for igual ou superior a 28% do valor da receita Bruta também dos últimos 12 mêses, a alíquota do Imposto será menor.
A5: Simulação | B5: =IFERROR((((B3+D3)*12)/($D11*12)),0) -> 0 | C5: =IFERROR(((($B$3+$D$3)*12)/((($D12+$D11)/2)*12)),0) -> 0 | D5: =IFERROR(((($B$3+$D$3)*12)/((($D12+$D11+D13)/3)*12)),0) -> 0 | E5: =IFERROR(((($B$3+$D$3)*12)/((($D12+$D11+$D$13+$D$14)/4)*12)),0) -> 0 | F5: =IFERROR(((($B$3+$D$3)*12)/((($D12+$D11+$D$13+$D$14+$D$15)/5)*12)),0) -> 0 | G5: =IFERROR(((($B$3+$D$3)*12)/((($D12+$D11+$D$13+$D$14+$D$15+$D$16)/6)*12)),0) -> 0 | H5: =IFERROR(((($B$3+$D$3)*12)/((($D12+$D11+$D$13+$D$14+$D$15+$D$16+$D$17)/7)*12)),0) -> 0 | I5: =IFERROR(((($B$3+$D$3)*12)/((($D12+$D11+$D$13+$D$14+$D$15+$D$16+$D$17+$D$18)/8)*12)),0) -> 0 | J5: =IFERROR(((($B$3+$D$3)*12)/((($D12+$D11+$D$13+$D$14+$D$15+$D$16+$D$17+$D$18+D19)/9)*12)),0) -> 0 | K5: =IFERROR(((($B$3+$D$3)*12)/((SUM($D12:$D$20)/10)*12)),0) -> 0 | L5: =IFERROR(((($B$3+$D$3)*12)/((SUM($D12:$D$21)/11)*12)),0) -> 0 | M5: =IFERROR((($B$3+$D$3)*12)/SUM($D12:$D$22),0) -> 0
A7: Honorários Contábeis | B7: 300 | C7: Valor negociável dependendo da quantidade de empresas.
A9: Receita Bruta | F9: Custo Mensal
A10: Faturamento | B10: Representação | C10: Comércio | D10: Total | F10: Mês | G10: Simples Nacional | H10: INSS | I10: Contabilidade | J10: Total
A11: Mês 01 | D11: =B11+C11 -> 0 | F11: Mês 01 | G11: =H28 -> 0 | H11: =$D$3 -> 0 | I11: =$B$7 -> 300 | J11: =I11+H11+G11 -> 300
A12: Mês 02 | D12: =B12+C12 -> 0 | F12: Mês 02 | G12: =H29 -> 0 | H12: =$D$3 -> 0 | I12: =$B$7 -> 300 | J12: =I12+H12+G12 -> 300
A13: Mês 03 | D13: =B13+C13 -> 0 | F13: Mês 03 | G13: =H30 -> 0 | H13: =$D$3 -> 0 | I13: =$B$7 -> 300 | J13: =I13+H13+G13 -> 300
A14: Mês 04 | D14: =B14+C14 -> 0 | F14: Mês 04 | G14: =H31 -> 0 | H14: =$D$3 -> 0 | I14: =$B$7 -> 300 | J14: =I14+H14+G14 -> 300
A15: Mês 05 | D15: =B15+C15 -> 0 | F15: Mês 05 | G15: =H32 -> 0 | H15: =$D$3 -> 0 | I15: =$B$7 -> 300 | J15: =I15+H15+G15 -> 300
A16: Mês 06 | D16: =B16+C16 -> 0 | F16: Mês 06 | G16: =H33 -> 0 | H16: =$D$3 -> 0 | I16: =$B$7 -> 300 | J16: =I16+H16+G16 -> 300
A17: Mês 07 | D17: =B17+C17 -> 0 | F17: Mês 07 | G17: =H34 -> 0 | H17: =$D$3 -> 0 | I17: =$B$7 -> 300 | J17: =I17+H17+G17 -> 300
A18: Mês 08 | D18: =B18+C18 -> 0 | F18: Mês 08 | G18: =H35 -> 0 | H18: =$D$3 -> 0 | I18: =$B$7 -> 300 | J18: =I18+H18+G18 -> 300
A19: Mês 09 | D19: =B19+C19 -> 0 | F19: Mês 09 | G19: =H36 -> 0 | H19: =$D$3 -> 0 | I19: =$B$7 -> 300 | J19: =I19+H19+G19 -> 300
A20: Mês 10 | D20: =B20+C20 -> 0 | F20: Mês 10 | G20: =H37 -> 0 | H20: =$D$3 -> 0 | I20: =$B$7 -> 300 | J20: =I20+H20+G20 -> 300
A21: Mês 11 | D21: =B21+C21 -> 0 | F21: Mês 11 | G21: =H38 -> 0 | H21: =$D$3 -> 0 | I21: =$B$7 -> 300 | J21: =I21+H21+G21 -> 300
A22: Mês 12 | D22: =B22+C22 -> 0 | F22: Mês 12 | G22: =H39 -> 0 | H22: =$D$3 -> 0 | I22: =$B$7 -> 300 | J22: =I22+H22+G22 -> 300
A23: Total | B23: =SUM(B11:B22) -> 0 | C23: =SUM(C11:C22) -> 0 | D23: =B23+C23 -> 0 | F23: Total | G23: =SUM(G11:G22) -> 0 | H23: =SUM(H11:H22) -> 0 | I23: =SUM(I11:I22) -> 3600 | J23: =SUM(J11:J22) -> 3600
A25: Cálculo Simples Nacional
A26: Competência | B26: Representação | E26: Comércio | H26: Total a pagar
B27: Alíquota Efetiva | C27: Base de Cálculo | D27: Imposto | E27: Alíquota Efetiva | F27: Base de Cálculo | G27: Imposto
A28: Mês 01 | B28: =IFERROR((Planilha2!K3*Planilha2!N3-Planilha2!O3)/Planilha2!K3,) -> 0 | C28: =B11 -> 0 | D28: =C28*B28 -> 0 | E28: =IFERROR((Planilha2!K3*Planilha2!P3-Planilha2!Q3)/Planilha2!K3,0) -> 0 | F28: =C11 -> 0 | G28: =F28*E28 -> 0 | H28: =G28+D28 -> 0
A29: Mês 02 | B29: =IFERROR((Planilha2!K4*Planilha2!N4-Planilha2!O4)/Planilha2!K4,0) -> 0 | C29: =B12 -> 0 | D29: =C29*B29 -> 0 | E29: =IFERROR((Planilha2!K4*Planilha2!P4-Planilha2!Q4)/Planilha2!K4,0) -> 0 | F29: =C12 -> 0 | G29: =F29*E29 -> 0 | H29: =G29+D29 -> 0
A30: Mês 03 | B30: =IFERROR((Planilha2!K5*Planilha2!N5-Planilha2!O5)/Planilha2!K5,0) -> 0 | C30: =B13 -> 0 | D30: =C30*B30 -> 0 | E30: =IFERROR((Planilha2!K5*Planilha2!P5-Planilha2!Q5)/Planilha2!K5,0) -> 0 | F30: =C13 -> 0 | G30: =F30*E30 -> 0 | H30: =G30+D30 -> 0
A31: Mês 04 | B31: =IFERROR((Planilha2!K6*Planilha2!N6-Planilha2!O6)/Planilha2!K6,0) -> 0 | C31: =B14 -> 0 | D31: =C31*B31 -> 0 | E31: =IFERROR((Planilha2!K6*Planilha2!P6-Planilha2!Q6)/Planilha2!K6,0) -> 0 | F31: =C14 -> 0 | G31: =F31*E31 -> 0 | H31: =G31+D31 -> 0
A32: Mês 05 | B32: =IFERROR((Planilha2!K7*Planilha2!N7-Planilha2!O7)/Planilha2!K7,0) -> 0 | C32: =B15 -> 0 | D32: =C32*B32 -> 0 | E32: =IFERROR((Planilha2!K7*Planilha2!P7-Planilha2!Q7)/Planilha2!K7,0) -> 0 | F32: =C15 -> 0 | G32: =F32*E32 -> 0 | H32: =G32+D32 -> 0
A33: Mês 06 | B33: =IFERROR((Planilha2!K8*Planilha2!N8-Planilha2!O8)/Planilha2!K8,0) -> 0 | C33: =B16 -> 0 | D33: =C33*B33 -> 0 | E33: =IFERROR((Planilha2!K8*Planilha2!P8-Planilha2!Q8)/Planilha2!K8,0) -> 0 | F33: =C16 -> 0 | G33: =F33*E33 -> 0 | H33: =G33+D33 -> 0
A34: Mês 07 | B34: =IFERROR((Planilha2!K9*Planilha2!N9-Planilha2!O9)/Planilha2!K9,0) -> 0 | C34: =B17 -> 0 | D34: =C34*B34 -> 0 | E34: =IFERROR((Planilha2!K9*Planilha2!P9-Planilha2!Q9)/Planilha2!K9,0) -> 0 | F34: =C17 -> 0 | G34: =F34*E34 -> 0 | H34: =G34+D34 -> 0
A35: Mês 08 | B35: =IFERROR((Planilha2!K10*Planilha2!N10-Planilha2!O10)/Planilha2!K10,0) -> 0 | C35: =B18 -> 0 | D35: =C35*B35 -> 0 | E35: =IFERROR((Planilha2!K10*Planilha2!P10-Planilha2!Q10)/Planilha2!K10,0) -> 0 | F35: =C18 -> 0 | G35: =F35*E35 -> 0 | H35: =G35+D35 -> 0
A36: Mês 09 | B36: =IFERROR((Planilha2!K11*Planilha2!N11-Planilha2!O11)/Planilha2!K11,0) -> 0 | C36: =B19 -> 0 | D36: =C36*B36 -> 0 | E36: =IFERROR((Planilha2!K11*Planilha2!P11-Planilha2!Q11)/Planilha2!K11,0) -> 0 | F36: =C19 -> 0 | G36: =F36*E36 -> 0 | H36: =G36+D36 -> 0
A37: Mês 10 | B37: =IFERROR((Planilha2!K12*Planilha2!N12-Planilha2!O12)/Planilha2!K12,0) -> 0 | C37: =B20 -> 0 | D37: =C37*B37 -> 0 | E37: =IFERROR((Planilha2!K12*Planilha2!P12-Planilha2!Q12)/Planilha2!K12,0) -> 0 | F37: =C20 -> 0 | G37: =F37*E37 -> 0 | H37: =G37+D37 -> 0
A38: Mês 11 | B38: =IFERROR((Planilha2!K13*Planilha2!N13-Planilha2!O13)/Planilha2!K13,0) -> 0 | C38: =B21 -> 0 | D38: =C38*B38 -> 0 | E38: =IFERROR((Planilha2!K13*Planilha2!P13-Planilha2!Q13)/Planilha2!K13,0) -> 0 | F38: =C21 -> 0 | G38: =F38*E38 -> 0 | H38: =G38+D38 -> 0
A39: Mês 12 | B39: =IFERROR((Planilha2!K14*Planilha2!N14-Planilha2!O14)/Planilha2!K14,0) -> 0 | C39: =B22 -> 0 | D39: =C39*B39 -> 0 | E39: =IFERROR((Planilha2!K14*Planilha2!P14-Planilha2!Q14)/Planilha2!K14,0) -> 0 | F39: =C22 -> 0 | G39: =F39*E39 -> 0 | H39: =G39+D39 -> 0
