Workbook

Sheet Tabelas
B2: Tabelas Imposto de Renda e INSS
B3: Imposto de Renda da Pessoa Física
B4: Início | C4: Término | D4: Alíquota | E4: Dedução | F4: Dependentes
B5: 0 | C5: 1903.98 | D5: 0 | E5: 0 | F5: 189.59
B6: =C5+0.01 -> 1903.99 | C6: 2826.65 | D6: 0.075 | E6: 142.8
B7: =C6+0.01 -> 2826.66 | C7: 3751.05 | D7: 0.15 | E7: 354.8
B8: =C7+0.01 -> 3751.06 | C8: 4664.68 | D8: 0.225 | E8: 636.13
B9: =C8+0.01 -> 4664.69 | D9: 0.275 | E9: 869.36
B11: Contribuição Previdenciária
B12: Início | C12: Término | D12: Alíquota
B13: 0 | C13: 1659.38 | D13: 0.08
B14: =C13+0.01 -> 1659.39 | C14: 2765.66 | D14: 0.09
B15: =C14+0.01 -> 2765.67 | C15: 5531.31 | D15: 0.11 | F15: Versão: 05/11/2017
C16: Valor máximo para desconto a 11%: | D16: =C15*D15 -> 608.4441

Sheet Simulador
B3: SIMULAÇÃO DE CÁLCULO DA FOLHA DE PAGAMENTO INDIVIDUAL
B5: COMPETÊNCIA | C5: 43009
B7: DSR S/ VARIÁVEIS | E7: DESCONTOS MENSAIS
B8: SALÁRIO BASE | C8: 2000 | E8: VALE-TRANSPORTE | F8: 0 | G8: =F8*C8 -> 0 | I8: Tabela do Imposto de Renda da Pessoa Física
B9: VALOR ADICIONAIS | C9: 0 | E9: ALIMENTAÇÃO | G9: 0 | I9: FAIXA | K9: Alíquota | L9: Dedução | M9: Dependentes
B10: VALOR HORAS EXTRAS | C10: 0 | E10: CONV. FARMÁCIA | G10: 0 | I10: =Tabelas!B5 -> 0 | J10: =Tabelas!C5 -> 1903.98 | K10: =Tabelas!D5 -> 0 | L10: =Tabelas!E5 -> 0 | M10: =Tabelas!F5 -> 189.59
B11: COMISSÕES | C11: 0 | E11: CONV. ODONTOLÓGICO | G11: 0 | I11: =Tabelas!B6 -> 1903.99 | J11: =Tabelas!C6 -> 2826.65 | K11: =Tabelas!D6 -> 0.075 | L11: =Tabelas!E6 -> 142.8
B12: DSR S/ VARIÁVEIS | C12: 0 | E12: PLANO DE SAÚDE | G12: 0 | I12: =Tabelas!B7 -> 2826.66 | J12: =Tabelas!C7 -> 3751.05 | K12: =Tabelas!D7 -> 0.15 | L12: =Tabelas!E7 -> 354.8
C13: 0 | E13: FALTAS + ATRASOS + RSR | G13: 0 | I13: =Tabelas!B8 -> 3751.06 | J13: =Tabelas!C8 -> 4664.68 | K13: =Tabelas!D8 -> 0.225 | L13: =Tabelas!E8 -> 636.13
C14: 0 | G14: 0 | I14: =Tabelas!B9 -> 4664.69 | J14: =Tabelas!C9 -> 0 | K14: =Tabelas!D9 -> 0.275 | L14: =Tabelas!E9 -> 869.36
C15: 0 | G15: 0
B16: REMUNERAÇÃO BRUTA | C16: =SUM(C8:C15) -> 2000 | E16: TOTAL DE DESCONTOS | G16: =SUM(G8:G15) -> 0 | I16: Tabela Contribuição Previdenciária
B18: Resumo da Base de Cálculo para INSS e IR | E18: INFORMAÇÕES COMPLEMENTARES | I18: FAIXA | K18: Alíquota
B19: Base Cálc. INSS - Inicial | C19: =IF(C16-G13<=J21,C16-G13,J21) -> 2000 | E19: Base Cálc. INSS Outras Fontes | G19: 0 | I19: =Tabelas!B13 -> 0 | J19: =Tabelas!C13 -> 1659.38 | K19: =Tabelas!D13 -> 0.08
B20: Base Cálc. INSS - Final | C20: =IF(C19+G19<=J21,C19,J21-G19) -> 2000 | E20: Outras Deduções Base IRRF | G20: 0 | I20: =Tabelas!B14 -> 1659.39 | J20: =Tabelas!C14 -> 2765.66 | K20: =Tabelas!D14 -> 0.09
B21: Base de Cálculo I.R.R.F. | C21: =IF(C16,(C16-G13-C24-G20-(G21*M10)),0) -> 1630.41 | E21: Nº Dependentes para IRRF | G21: 1 | I21: =Tabelas!B15 -> 2765.67 | J21: =Tabelas!C15 -> 5531.31 | K21: =Tabelas!D15 -> 0.11
B23: DESCONTO DO INSS E IRRF | J23: =Tabelas!C16 -> Valor máximo para desconto a 11%: | K23: =Tabelas!D16 -> 608.4441
B24: I.N.S.S. | C24: =C20*D24 -> 180 | D24: =IF(C20,VLOOKUP((C20+G19),I19:K21,3,TRUE),0) -> 0.09 | E24: =IF(G19, " Alíquota definida considerando Outras Fontes R$ "&G19,"")
B25: I.R.R.F | C25: =IF(C21,(C21*D25)-VLOOKUP(D25,K10:L14,2,FALSE),0) -> 0 | D25: =IF(C21,VLOOKUP(C21,I10:K14,3,TRUE),0) -> 0 | E25: =IF(C25<10," O valor do I.R. é inferior ao limite para recohimento em DARF","") -> O valor do I.R. é inferior ao limite para recohimento em DARF
E27: RESUMO DE CÁLCULO
E28: REMUNERAÇÃO BRUTA | G28: =C16 -> 2000
E29: DESCONTOS MENSAIS | G29: =G16 -> 0
E30: DESC. I.N.S.S | F30: =D24 -> 0.09 | G30: =C24 -> 180
B31: Fagner C. Aguiar | E31: DESC. I.R.R.F. | F31: =D25 -> 0 | G31: =C25 -> 0
B32: Versão: 05/11/2017 | E32: VALOR LÍQUIDO | G32: =G28-G29-G30-G31 -> 1820
