Workbook

Sheet Ini
C2: PLANILHA DE
C3: INDICADORES DE RH 3.0
C4: Seja bem-vindo(a). Com esta planilha, é possível ter o controle sobre os indicadores de RH da empresa. Tenha indicadores importantes para tomar decisões acertivas direcionadas.
C5: IMPORTANTE: LEIA OS PASSOS E ENTENDA A PLANILHA
C6: Dúvidas? Clique nos Links presentes em toda a planilha para ver vídeos explicativos sobre o método, preenchimento e análise de cada aba!
C7: Passo 1 | D7: CADASTRO
C8: Inicialmente, você irá realizar alguns cadastros necessários para serem utilizados posteriormente nas etapas de lançamentos.
C9: 1.1. Cadastros iniciais: Cadastrar o nome da empresa e o ano de vigência para a planilha apurar os resultados consolidados.
C10: 1.2. Cadastro de cargos: Cadastrar os cargos da empresa e classificá-los em grupos para posteriormente serem analisados.
C11: 1.3. Funcionários: Registrar funcionários com alguns dados necessários para análise posterior.
C12: 1.4. Outros cadastros: Esta parte já vem toda preenchida com informações padronizadas, mas é possível alterá-las caso seja necessário.
C14: Passo 2 | D14: LANÇAMENTOS
C15: Nesta etapa você irá realizar os lançamentos da movimentação da sua equipe e o registro das receitas e custos de RH.
C16: 2.1. Receitas e custos: Registrar a receita bruta da sua empresa, os custos de RH e os custos dos benefícios oferecidos aos seus funcionários.
C17: 2.2. Férias e licenças: Lançar as movimentações de férias, licenças e faltas não justificadas.
C18: 2.3. Demissões: Lançar as demissões e classificá-las (motivo da demissão).
C19: 2.4. Treinamentos: Registrar os treinamentos oferecidos à equipe, carga horária, custo e número de funcionários participantes.
C20: 2.5. Promoções: Registrar as mudanças de cargo oferecidas aos funcionários.
C22: Passo 3 | D22: RESULTADOS CONSOLIDADOS
C23: Aqui você poderá conferir os resultados consolidados, calculados automaticamente com base nas informações fornecidas anteriormente.
C24: 3.1. Geral: Visão geral de alguns indicadores calculados com base nos registros feitos anteriormente.
C25: 3.2. Rotatividade: Visão mensal da análise da rotatividade da equipe e a taxa de turnover.
C26: 3.3. Perfil da equipe: Visão mensal da sua equipe agrupada de acordo com os cadastros realizados anteriormente.
C27: 3.4. Eventos de RH: Visão mensal dos treinamentos oferecidos à equipe, das promoções, férias e licenças.
C28: 3.5. Receitas e custos: Visão mensal das receitas, despesas com benefícios oferecidos e custos de RH.
C30: Passo 4 | D30: GRÁFICOS
C31: Faça uma análise gráfica de forma rápida e eficiente dos resultados da sua planilha.
C33: Passo 5 | D33: ALERTAS E DICAS
C34: Esta planilha avaliará todos os dados preenchidos por você e retornará com dicas importantes para sua análise. Este retorno será exibido através da análise da performance mensal de alguns pontos específicos.
C36: Passo 6 | D36: RELATÓRIO PARA IMPRESSÃO
C37: Imprima o relatório dos seus indicadores. Apenas o que importa, com formatação econômica para gastar menos tinta e ter um melhor aproveitamento do papel.

Sheet Cad
C1: 1. CADASTRO | U1: Operacional
U2: Gerencial
U3: Diretoria
C6: Cadastro de cargos
C7: Nome do cargo | D7: Tipo do cargo | E7: Salário
C8: Designer I | D8: Operacional | E8: 1500
C9: Designer II | D9: Operacional | E9: 2000
C10: Designer III | D10: Operacional | E10: 2500
C11: Dir de Arte | D11: Gerencial | E11: 3000
C12: Dir de Criação | D12: Diretoria | E12: 3500
C13: Sócio | D13: Diretoria | E13: 5000

Sheet Cad_Inicial
C1: 1. CADASTRO
C6: Cadastros iniciais
C7: Nome da empresa | D7: LUZ Planilhas Empresariais
C8: Ano de vigência da planilha | D8: 2015

Sheet Lanç
C1: 2. LANÇAMENTOS | T1: =IF(ISERROR(IF(Cad_Outros!C9="","",Cad_Outros!C9)),"",IF(Cad_Outros!C9="","",Cad_Outros!C9)) -> Pedido de demissão | U1: =IF(ISERROR(IF(Cad_Func!C8="","",Cad_Func!C8)),"",IF(Cad_Func!C8="","",Cad_Func!C8)) -> ze 1
T2: =IF(ISERROR(IF(Cad_Outros!C10="","",Cad_Outros!C10)),"",IF(Cad_Outros!C10="","",Cad_Outros!C10)) -> Dispensa sem justa causa | U2: =IF(ISERROR(IF(Cad_Func!C9="","",Cad_Func!C9)),"",IF(Cad_Func!C9="","",Cad_Func!C9)) -> ze 2
T3: =IF(ISERROR(IF(Cad_Outros!C11="","",Cad_Outros!C11)),"",IF(Cad_Outros!C11="","",Cad_Outros!C11)) -> Dispensa com justa causa | U3: =IF(ISERROR(IF(Cad_Func!C10="","",Cad_Func!C10)),"",IF(Cad_Func!C10="","",Cad_Func!C10)) -> ze 3
T5: =IF(ISERROR(IF(Cad_Outros!C12="","",Cad_Outros!C12)),"",IF(Cad_Outros!C12="","",Cad_Outros!C12)) -> Término de contrato de experiência | U5: =IF(ISERROR(IF(Cad_Func!C11="","",Cad_Func!C11)),"",IF(Cad_Func!C11="","",Cad_Func!C11)) -> ze 4
C6: Registro das demissões | T6: =IF(ISERROR(IF(Cad_Outros!C13="","",Cad_Outros!C13)),"",IF(Cad_Outros!C13="","",Cad_Outros!C13)) -> Rescisão antecipada do contrato de experiência por iniciativa do empregador | U6: =IF(ISERROR(IF(Cad_Func!C12="","",Cad_Func!C12)),"",IF(Cad_Func!C12="","",Cad_Func!C12)) -> ze 5
C7: Nome do funcionário | D7: Data de demissão | E7: Motivo da demissão | F7: Observações | T7: =IF(ISERROR(IF(Cad_Outros!C14="","",Cad_Outros!C14)),"",IF(Cad_Outros!C14="","",Cad_Outros!C14)) -> Rescisão antecipada do contrato de experiência por iniciativa do empregado | U7: =IF(ISERROR(IF(Cad_Func!C13="","",Cad_Func!C13)),"",IF(Cad_Func!C13="","",Cad_Func!C13)) -> ze 6
C8: ze 1 | D8: 42075 | E8: Pedido de demissão | T8: =IF(ISERROR(IF(Cad_Outros!C15="","",Cad_Outros!C15)),"",IF(Cad_Outros!C15="","",Cad_Outros!C15)) -> Falecimento do empregado | U8: =IF(ISERROR(IF(Cad_Func!C14="","",Cad_Func!C14)),"",IF(Cad_Func!C14="","",Cad_Func!C14)) -> ze 7
T9: =IF(ISERROR(IF(Cad_Outros!C16="","",Cad_Outros!C16)),"",IF(Cad_Outros!C16="","",Cad_Outros!C16)) -> Outro | U9: =IF(ISERROR(IF(Cad_Func!C15="","",Cad_Func!C15)),"",IF(Cad_Func!C15="","",Cad_Func!C15)) -> ze 8
U10: =IF(ISERROR(IF(Cad_Func!C16="","",Cad_Func!C16)),"",IF(Cad_Func!C16="","",Cad_Func!C16)) -> ze 9
U11: =IF(ISERROR(IF(Cad_Func!C17="","",Cad_Func!C17)),"",IF(Cad_Func!C17="","",Cad_Func!C17)) -> ze 10
U12: =IF(ISERROR(IF(Cad_Func!C18="","",Cad_Func!C18)),"",IF(Cad_Func!C18="","",Cad_Func!C18)) -> ze 11
U13: =IF(ISERROR(IF(Cad_Func!C19="","",Cad_Func!C19)),"",IF(Cad_Func!C19="","",Cad_Func!C19)) -> ze 12
U14: =IF(ISERROR(IF(Cad_Func!C20="","",Cad_Func!C20)),"",IF(Cad_Func!C20="","",Cad_Func!C20))
U15: =IF(ISERROR(IF(Cad_Func!C21="","",Cad_Func!C21)),"",IF(Cad_Func!C21="","",Cad_Func!C21))
U16: =IF(ISERROR(IF(Cad_Func!C22="","",Cad_Func!C22)),"",IF(Cad_Func!C22="","",Cad_Func!C22))
U17: =IF(ISERROR(IF(Cad_Func!C23="","",Cad_Func!C23)),"",IF(Cad_Func!C23="","",Cad_Func!C23))
U18: =IF(ISERROR(IF(Cad_Func!C24="","",Cad_Func!C24)),"",IF(Cad_Func!C24="","",Cad_Func!C24))
U19: =IF(ISERROR(IF(Cad_Func!C25="","",Cad_Func!C25)),"",IF(Cad_Func!C25="","",Cad_Func!C25))
U20: =IF(ISERROR(IF(Cad_Func!C26="","",Cad_Func!C26)),"",IF(Cad_Func!C26="","",Cad_Func!C26))
U21: =IF(ISERROR(IF(Cad_Func!C27="","",Cad_Func!C27)),"",IF(Cad_Func!C27="","",Cad_Func!C27))
... U202: =IF(ISERROR(IF(Cad_Func!C208="","",Cad_Func!C208)),"",IF(Cad_Func!C208="","",Cad_Func!C208))

Sheet RC
C1: 3. RESULTADOS CONSOLIDADOS
C6: ="Indicadores de rotatividade para "&Cad_Inicial!$D$8 -> Indicadores de rotatividade para 2015 | F6: Resultado
C7: Média de permanência de funcionários na empresa | F7: =IF(ISERROR(ROUND(AVERAGEIF(Cad_Func!$U$8:$U$208,"SIM",Cad_Func!$T$8:$T$208),0)&" meses"),"",ROUND(AVERAGEIF(Cad_Func!$U$8:$U$208,"SIM",Cad_Func!$T$8:$T$208),0)&" meses") -> 86 meses
C8: ="Admissões em "&Cad_Inicial!$D$8 -> Admissões em 2015 | F8: =IF(ISERROR(COUNTIF(Cad_Func!$W$8:$W$208,Cad_Inicial!$D$8)),"",COUNTIF(Cad_Func!$W$8:$W$208,Cad_Inicial!$D$8)) -> 3
C9: ="Demissões em "&Cad_Inicial!$D$8 -> Demissões em 2015 | F9: =IF(ISERROR(COUNTIF(Cad_Func!$Y$8:$Y$208,Cad_Inicial!$D$8)),"",COUNTIF(Cad_Func!$Y$8:$Y$208,Cad_Inicial!$D$8)) -> 1
C10: ="Total de funcionários em "&Cad_Inicial!$D$8 -> Total de funcionários em 2015 | F10: =IF(ISERROR(SUM(Cad_Func!$AA$8:$AA$208)),"",SUM(Cad_Func!$AA$8:$AA$208)) -> 11
C11: Índice de aprovação após período de experiência | F11: =IF(ISERROR(COUNTIF(Cad_Func!$V$8:$V$208,"SIM")/COUNTIF(Cad_Func!$W$8:$W$208,Cad_Inicial!$D$8)),"",COUNTIF(Cad_Func!$V$8:$V$208,"SIM")/COUNTIF(Cad_Func!$W$8:$W$208,Cad_Inicial!$D$8)) -> 1
C12: Índice de Turnover (rotatividade) | F12: =IF(ISERROR((F8+F9)/2/F10),"",(F8+F9)/2/F10) -> 0.18181818
C14: ="Indicadores de treinamento para "&Cad_Inicial!$D$8 -> Indicadores de treinamento para 2015 | F14: Resultado
C15: Total de horas de treinamento | F15: =IF(ISERROR(SUMIF(Lanç_Terinamentos!$U$8:$U$2008,Cad_Inicial!$D$8,Lanç_Terinamentos!$D$8:$D$2008)&" horas"),"",SUMIF(Lanç_Terinamentos!$U$8:$U$2008,Cad_Inicial!$D$8,Lanç_Terinamentos!$D$8:$D$2008)&" horas") -> 140 horas
C16: Média de horas de treinamento por funcionário treinado | F16: =IF(ISERROR(ROUND(SUMIF(Lanç_Terinamentos!$U$8:$U$2008,Cad_Inicial!$D$8,Lanç_Terinamentos!$D$8:$D$2008)/SUMIF(Lanç_Terinamentos!$U$8:$U$2008,Cad_Inicial!$D$8,Lanç_Terinamentos!$G$8:$G$2008),0)&" horas"),"",ROUND(SUMIF(Lanç_Terinamentos!$U$8:$U$2008,Cad_Inicial!$D$8,Lanç_Terinamentos!$D$8:$D$2008)/SUMIF(Lanç_Terinamentos!$U$8:$U$2008,Cad_Inicial!$D$8,Lanç_Terinamentos!$G$8:$G$2008),0)&" horas") -> 18 horas
C17: Número de funcionários treinados | F17: =IF(ISERROR(SUMIF(Lanç_Terinamentos!$U$8:$U$2008,Cad_Inicial!$D$8,Lanç_Terinamentos!$G$8:$G$2008)&" funcionários"),"",SUMIF(Lanç_Terinamentos!$U$8:$U$2008,Cad_Inicial!$D$8,Lanç_Terinamentos!$G$8:$G$2008)&" funcionários") -> 8 funcionários
C19: ="Custos para "&Cad_Inicial!$D$8 -> Custos para 2015 | F19: Resultado
C20: Custo total com hora extra | F20: =IF(ISERROR(SUMIF(Lanç_Receitas!$C$9:$C$20,"Hora extra",Lanç_Receitas!$P$9:$P$20)),"",SUMIF(Lanç_Receitas!$C$9:$C$20,"Hora extra",Lanç_Receitas!$P$9:$P$20)) -> 3012
C21: Custo total com folha de pagamento (benefícios + custos) | F21: =IF(ISERROR(SUM(Lanç_Receitas!$P$9:$P$20,Lanç_Receitas!$P$22:$P$33)),"",SUM(Lanç_Receitas!$P$9:$P$20,Lanç_Receitas!$P$22:$P$33)) -> 315142
C22: % do custo total de treinamentos sobre o total da folha de pagamento | F22: =IF(ISERROR(SUMIF(Lanç_Terinamentos!$U$8:$U$2008,Cad_Inicial!$D$8,Lanç_Terinamentos!$Q$8:$Q$2008)/F21),"",SUMIF(Lanç_Terinamentos!$U$8:$U$2008,Cad_Inicial!$D$8,Lanç_Terinamentos!$Q$8:$Q$2008)/F21) -> 0
C23: Custo médio por funcionário treinado | F23: =IF(ISERROR(SUMIF(Lanç_Terinamentos!$U$8:$U$2008,Cad_Inicial!$D$8,Lanç_Terinamentos!$Q$8:$Q$2008)/SUMIF(Lanç_Terinamentos!$U$8:$U$2008,Cad_Inicial!$D$8,Lanç_Terinamentos!$G$8:$G$2008)),"",SUMIF(Lanç_Terinamentos!$U$8:$U$2008,Cad_Inicial!$D$8,Lanç_Terinamentos!$Q$8:$Q$2008)/SUMIF(Lanç_Terinamentos!$U$8:$U$2008,Cad_Inicial!$D$8,Lanç_Terinamentos!$G$8:$G$2008)) -> 0
C24: % dos benefícios sobre a folha de pagamento | F24: =F25/F21 -> 0.066655666
C25: Custo dos benefícios sobre a folha de pagamento | F25: =IF(ISERROR(SUM(Lanç_Receitas!$P$22:$P$33)),"",SUM(Lanç_Receitas!$P$22:$P$33)) -> 21006
C26: Custo médio dos benefícios para cada funcionário | F26: =IF(ISERROR(F25/F10),"",F25/F10) -> 1909.6364
C27: Receita gerada por cada funcionário | F27: =IF(ISERROR(Lanç_Receitas!P7/F10),"",Lanç_Receitas!P7/F10) -> 163636.91
C28: Custo médio da folha gerado por cada funcionário | F28: =IF(ISERROR(SUM(Lanç_Receitas!$P$9:$P$20)/F10),"",SUM(Lanç_Receitas!$P$9:$P$20)/F10) -> 26739.636

Sheet Graf
C1: 4. GRÁFICOS
C6: 1. Rotatividade
C17: 1.1. Motivos de desligamento | J17: 1.2. Funcionários no fim do mês
C32: 2.Equipe
C33: 2.1. Nível de escolaridade | J33: 2.1. Tipos de cargos
C44: 2.3. Sexo | J44: 2.4. Faixa etária
C52: Total no fim do ano | E52: Total no fim do ano
C53: ='Graf Aux'!N38&" homens" -> 7 homens | E53: ='Graf Aux'!N39&" mulheres" -> 4 mulheres
C55: 3.Treinamentos
C66: 4. Receitas e Custos
C74: Total no fim do ano | J74: Total no fim do ano
C75: ='Graf Aux'!N49 -> 163636.91 | J75: ='Graf Aux'!N50 -> 29513
C77: 4.1. Custos | J77: 4.2. Benefícios

Sheet Graf Aux
A1: Ano | B1: =Cad_Inicial!$D$8 -> 2015
B2: 1 | C2: 2 | D2: 3 | E2: 4 | F2: 5 | G2: 6 | H2: 7 | I2: 8 | J2: 9 | K2: 10 | L2: 11 | M2: 12
A3: ="<"&B1 -> <2015 | B3: ="<="&B2 -> <=1 | C3: ="<="&C2 -> <=2 | D3: ="<="&D2 -> <=3 | E3: ="<="&E2 -> <=4 | F3: ="<="&F2 -> <=5 | G3: ="<="&G2 -> <=6 | H3: ="<="&H2 -> <=7 | I3: ="<="&I2 -> <=8 | ... M3: ="<="&M2 -> <=12
B4: =">="&B2 -> >=1 | C4: =">="&C2 -> >=2 | D4: =">="&D2 -> >=3 | E4: =">="&E2 -> >=4 | F4: =">="&F2 -> >=5 | G4: =">="&G2 -> >=6 | H4: =">="&H2 -> >=7 | I4: =">="&I2 -> >=8 | ... M4: =">="&M2 -> >=12
A5: Indicador | B5: Jan | C5: Fev | D5: Mar | E5: Abr | F5: Mai | G5: Jun | H5: Jul | I5: Ago | J5: Set | K5: Out | L5: Nov | M5: Dez
A6: Admissões | B6: =RC_Rotatividade!E9 -> 1 | C6: =RC_Rotatividade!F9 -> 2 | D6: =RC_Rotatividade!G9 -> 0 | E6: =RC_Rotatividade!H9 -> 0 | F6: =RC_Rotatividade!I9 -> 0 | G6: =RC_Rotatividade!J9 -> 0 | H6: =RC_Rotatividade!K9 -> 0 | I6: =RC_Rotatividade!L9 -> 0 | ... M6: =RC_Rotatividade!P9 -> 0
A7: Demissões | B7: =RC_Rotatividade!E10 -> 0 | C7: =RC_Rotatividade!F10 -> 0 | D7: =RC_Rotatividade!G10 -> 1 | E7: =RC_Rotatividade!H10 -> 0 | F7: =RC_Rotatividade!I10 -> 0 | G7: =RC_Rotatividade!J10 -> 0 | H7: =RC_Rotatividade!K10 -> 0 | I7: =RC_Rotatividade!L10 -> 0 | ... M7: =RC_Rotatividade!P10 -> 0
A8: Funcionários no início do mês | B8: =RC_Rotatividade!E12 -> 9 | C8: =RC_Rotatividade!F12 -> 10 | D8: =RC_Rotatividade!G12 -> 12 | E8: =RC_Rotatividade!H12 -> 11 | F8: =RC_Rotatividade!I12 -> 11 | G8: =RC_Rotatividade!J12 -> 11 | H8: =RC_Rotatividade!K12 -> 11 | I8: =RC_Rotatividade!L12 -> 11 | ... M8: =RC_Rotatividade!P12 -> 11
A9: Funcionários no fim do mês | B9: =RC_Rotatividade!E13 -> 10 | C9: =RC_Rotatividade!F13 -> 12 | D9: =RC_Rotatividade!G13 -> 11 | E9: =RC_Rotatividade!H13 -> 11 | F9: =RC_Rotatividade!I13 -> 11 | G9: =RC_Rotatividade!J13 -> 11 | H9: =RC_Rotatividade!K13 -> 11 | I9: =RC_Rotatividade!L13 -> 11 | ... M9: =RC_Rotatividade!P13 -> 11 | N9: =IF(ISERROR(IF(C9="",B9,IF(D9="",C9,IF(E9="",D9,IF(F9="",E9,IF(G9="",F9,IF(H9="",G9,IF(I9="",H9,IF(J9="",I9,IF(K9="",J9,IF(L9="",K9,IF(M9="",L9,M9)))))))))))),"",IF(C9="",B9,IF(D9="",C9,IF(E9="",D9,IF(F9="",E9,IF(G9="",F9,IF(H9="",G9,IF(I9="",H9,IF(J9="",I9,IF(K9="",J9,IF(L9="",K9,IF(M9="",L9,M9)))))))))))) -> 11
A10: Turnover | B10: =RC_Rotatividade!E14 -> 0.05 | C10: =RC_Rotatividade!F14 -> 0.083333333 | D10: =RC_Rotatividade!G14 -> 0.045454545 | E10: =RC_Rotatividade!H14 -> 0 | F10: =RC_Rotatividade!I14 -> 0 | G10: =RC_Rotatividade!J14 -> 0 | H10: =RC_Rotatividade!K14 -> 0 | I10: =RC_Rotatividade!L14 -> 0 | ... M10: =RC_Rotatividade!P14 -> 0
A12: Indicador | B12: Jan | C12: Fev | D12: Mar | E12: Abr | F12: Mai | G12: Jun | H12: Jul | I12: Ago | J12: Set | K12: Out | L12: Nov | M12: Dez | N12: Total
A13: Pedido de demissão | B13: =RC_Rotatividade!E16 -> 0 | C13: =RC_Rotatividade!F16 -> 0 | D13: =RC_Rotatividade!G16 -> 1 | E13: =RC_Rotatividade!H16 -> 0 | F13: =RC_Rotatividade!I16 -> 0 | G13: =RC_Rotatividade!J16 -> 0 | H13: =RC_Rotatividade!K16 -> 0 | I13: =RC_Rotatividade!L16 -> 0 | ... M13: =RC_Rotatividade!P16 -> 0 | N13: =SUM(B13:M13) -> 1
A14: Dispensa sem justa causa | B14: =RC_Rotatividade!E17 -> 0 | C14: =RC_Rotatividade!F17 -> 0 | D14: =RC_Rotatividade!G17 -> 0 | E14: =RC_Rotatividade!H17 -> 0 | F14: =RC_Rotatividade!I17 -> 0 | G14: =RC_Rotatividade!J17 -> 0 | H14: =RC_Rotatividade!K17 -> 0 | I14: =RC_Rotatividade!L17 -> 0 | ... M14: =RC_Rotatividade!P17 -> 0 | N14: =SUM(B14:M14) -> 0
A15: Dispensa com justa causa | B15: =RC_Rotatividade!E18 -> 0 | C15: =RC_Rotatividade!F18 -> 0 | D15: =RC_Rotatividade!G18 -> 0 | E15: =RC_Rotatividade!H18 -> 0 | F15: =RC_Rotatividade!I18 -> 0 | G15: =RC_Rotatividade!J18 -> 0 | H15: =RC_Rotatividade!K18 -> 0 | I15: =RC_Rotatividade!L18 -> 0 | ... M15: =RC_Rotatividade!P18 -> 0 | N15: =SUM(B15:M15) -> 0
A16: Término de contrato de experiêcia | B16: =RC_Rotatividade!E19 -> 0 | C16: =RC_Rotatividade!F19 -> 0 | D16: =RC_Rotatividade!G19 -> 0 | E16: =RC_Rotatividade!H19 -> 0 | F16: =RC_Rotatividade!I19 -> 0 | G16: =RC_Rotatividade!J19 -> 0 | H16: =RC_Rotatividade!K19 -> 0 | I16: =RC_Rotatividade!L19 -> 0 | ... M16: =RC_Rotatividade!P19 -> 0 | N16: =SUM(B16:M16) -> 0
A17: Rescisão antecipada do contrato de experiêcia por iniciativa do empregador | B17: =RC_Rotatividade!E20 -> 0 | C17: =RC_Rotatividade!F20 -> 0 | D17: =RC_Rotatividade!G20 -> 0 | E17: =RC_Rotatividade!H20 -> 0 | F17: =RC_Rotatividade!I20 -> 0 | G17: =RC_Rotatividade!J20 -> 0 | H17: =RC_Rotatividade!K20 -> 0 | I17: =RC_Rotatividade!L20 -> 0 | ... M17: =RC_Rotatividade!P20 -> 0 | N17: =SUM(B17:M17) -> 0
A18: Rescisão antecipada do contrato de experiêcia por iniciativa do empregado | B18: =RC_Rotatividade!E21 -> 0 | C18: =RC_Rotatividade!F21 -> 0 | D18: =RC_Rotatividade!G21 -> 0 | E18: =RC_Rotatividade!H21 -> 0 | F18: =RC_Rotatividade!I21 -> 0 | G18: =RC_Rotatividade!J21 -> 0 | H18: =RC_Rotatividade!K21 -> 0 | I18: =RC_Rotatividade!L21 -> 0 | ... M18: =RC_Rotatividade!P21 -> 0 | N18: =SUM(B18:M18) -> 0
A19: Falecimento do empregado | B19: =RC_Rotatividade!E22 -> 0 | C19: =RC_Rotatividade!F22 -> 0 | D19: =RC_Rotatividade!G22 -> 0 | E19: =RC_Rotatividade!H22 -> 0 | F19: =RC_Rotatividade!I22 -> 0 | G19: =RC_Rotatividade!J22 -> 0 | H19: =RC_Rotatividade!K22 -> 0 | I19: =RC_Rotatividade!L22 -> 0 | ... M19: =RC_Rotatividade!P22 -> 0 | N19: =SUM(B19:M19) -> 0
A20: Outro | B20: =RC_Rotatividade!E23 -> 0 | C20: =RC_Rotatividade!F23 -> 0 | D20: =RC_Rotatividade!G23 -> 0 | E20: =RC_Rotatividade!H23 -> 0 | F20: =RC_Rotatividade!I23 -> 0 | G20: =RC_Rotatividade!J23 -> 0 | H20: =RC_Rotatividade!K23 -> 0 | I20: =RC_Rotatividade!L23 -> 0 | ... M20: =RC_Rotatividade!P23 -> 0 | N20: =SUM(B20:M20) -> 0
A22: Indicador | B22: Jan | C22: Fev | D22: Mar | E22: Abr | F22: Mai | G22: Jun | H22: Jul | I22: Ago | J22: Set | K22: Out | L22: Nov | M22: Dez | N22: Total
A23: =RC_Perfil!C11 -> Ensino fundamental | B23: =RC_Perfil!E11 -> 2 | C23: =RC_Perfil!F11 -> 2 | D23: =RC_Perfil!G11 -> 1 | E23: =RC_Perfil!H11 -> 1 | F23: =RC_Perfil!I11 -> 1 | G23: =RC_Perfil!J11 -> 1 | H23: =RC_Perfil!K11 -> 1 | I23: =RC_Perfil!L11 -> 1 | ... M23: =RC_Perfil!P11 -> 1 | N23: =SUM(B23:M23) -> 14
A24: =RC_Perfil!C12 -> Ensino médio | B24: =RC_Perfil!E12 -> 0 | C24: =RC_Perfil!F12 -> 0 | D24: =RC_Perfil!G12 -> 0 | E24: =RC_Perfil!H12 -> 0 | F24: =RC_Perfil!I12 -> 0 | G24: =RC_Perfil!J12 -> 0 | H24: =RC_Perfil!K12 -> 0 | I24: =RC_Perfil!L12 -> 0 | ... M24: =RC_Perfil!P12 -> 0 | N24: =SUM(B24:M24) -> 0
A25: =RC_Perfil!C13 -> Superior completo | B25: =RC_Perfil!E13 -> 4 | C25: =RC_Perfil!F13 -> 6 | D25: =RC_Perfil!G13 -> 6 | E25: =RC_Perfil!H13 -> 6 | F25: =RC_Perfil!I13 -> 6 | G25: =RC_Perfil!J13 -> 6 | H25: =RC_Perfil!K13 -> 6 | I25: =RC_Perfil!L13 -> 6 | ... M25: =RC_Perfil!P13 -> 6 | N25: =SUM(B25:M25) -> 70
A26: =RC_Perfil!C14 -> Superior incompleto | B26: =RC_Perfil!E14 -> 2 | C26: =RC_Perfil!F14 -> 2 | D26: =RC_Perfil!G14 -> 2 | E26: =RC_Perfil!H14 -> 2 | F26: =RC_Perfil!I14 -> 2 | G26: =RC_Perfil!J14 -> 2 | H26: =RC_Perfil!K14 -> 2 | I26: =RC_Perfil!L14 -> 2 | ... M26: =RC_Perfil!P14 -> 2 | N26: =SUM(B26:M26) -> 24
A27: =RC_Perfil!C15 -> Pós-graduação completa | B27: =RC_Perfil!E15 -> 2 | C27: =RC_Perfil!F15 -> 2 | D27: =RC_Perfil!G15 -> 2 | E27: =RC_Perfil!H15 -> 2 | F27: =RC_Perfil!I15 -> 2 | G27: =RC_Perfil!J15 -> 2 | H27: =RC_Perfil!K15 -> 2 | I27: =RC_Perfil!L15 -> 2 | ... M27: =RC_Perfil!P15 -> 2 | N27: =SUM(B27:M27) -> 24
A28: =RC_Perfil!C16 -> Pós-graduação incompleta | B28: =RC_Perfil!E16 -> 0 | C28: =RC_Perfil!F16 -> 0 | D28: =RC_Perfil!G16 -> 0 | E28: =RC_Perfil!H16 -> 0 | F28: =RC_Perfil!I16 -> 0 | G28: =RC_Perfil!J16 -> 0 | H28: =RC_Perfil!K16 -> 0 | I28: =RC_Perfil!L16 -> 0 | ... M28: =RC_Perfil!P16 -> 0 | N28: =SUM(B28:M28) -> 0
A29: =RC_Perfil!C17 -> Mestre | B29: =RC_Perfil!E17 -> 0 | C29: =RC_Perfil!F17 -> 0 | D29: =RC_Perfil!G17 -> 0 | E29: =RC_Perfil!H17 -> 0 | F29: =RC_Perfil!I17 -> 0 | G29: =RC_Perfil!J17 -> 0 | H29: =RC_Perfil!K17 -> 0 | I29: =RC_Perfil!L17 -> 0 | ... M29: =RC_Perfil!P17 -> 0 | N29: =SUM(B29:M29) -> 0
A30: =RC_Perfil!C18 -> Doutor | B30: =RC_Perfil!E18 -> 0 | C30: =RC_Perfil!F18 -> 0 | D30: =RC_Perfil!G18 -> 0 | E30: =RC_Perfil!H18 -> 0 | F30: =RC_Perfil!I18 -> 0 | G30: =RC_Perfil!J18 -> 0 | H30: =RC_Perfil!K18 -> 0 | I30: =RC_Perfil!L18 -> 0 | ... M30: =RC_Perfil!P18 -> 0 | N30: =SUM(B30:M30) -> 0
A32: Indicador | B32: Jan | C32: Fev | D32: Mar | E32: Abr | F32: Mai | G32: Jun | H32: Jul | I32: Ago | J32: Set | K32: Out | L32: Nov | M32: Dez | N32: Total
A33: Operacional | B33: =RC_Perfil!E20 -> 6 | C33: =RC_Perfil!F20 -> 7 | D33: =RC_Perfil!G20 -> 6 | E33: =RC_Perfil!H20 -> 6 | F33: =RC_Perfil!I20 -> 6 | G33: =RC_Perfil!J20 -> 6 | H33: =RC_Perfil!K20 -> 6 | I33: =RC_Perfil!L20 -> 6 | ... M33: =RC_Perfil!P20 -> 6 | N33: =SUM(B33:M33) -> 73
A34: Gerencial | B34: =RC_Perfil!E21 -> 1 | C34: =RC_Perfil!F21 -> 1 | D34: =RC_Perfil!G21 -> 1 | E34: =RC_Perfil!H21 -> 1 | F34: =RC_Perfil!I21 -> 1 | G34: =RC_Perfil!J21 -> 1 | H34: =RC_Perfil!K21 -> 1 | I34: =RC_Perfil!L21 -> 1 | ... M34: =RC_Perfil!P21 -> 1 | N34: =SUM(B34:M34) -> 12
A35: Diretoria | B35: =RC_Perfil!E22 -> 3 | C35: =RC_Perfil!F22 -> 4 | D35: =RC_Perfil!G22 -> 4 | E35: =RC_Perfil!H22 -> 4 | F35: =RC_Perfil!I22 -> 4 | G35: =RC_Perfil!J22 -> 4 | H35: =RC_Perfil!K22 -> 4 | I35: =RC_Perfil!L22 -> 4 | ... M35: =RC_Perfil!P22 -> 4 | N35: =SUM(B35:M35) -> 47
A37: Indicador | B37: Jan | C37: Fev | D37: Mar | E37: Abr | F37: Mai | G37: Jun | H37: Jul | I37: Ago | J37: Set | K37: Out | L37: Nov | M37: Dez | N37: Total
A38: Masculino | B38: =RC_Perfil!E24 -> 7 | C38: =RC_Perfil!F24 -> 8 | D38: =RC_Perfil!G24 -> 7 | E38: =RC_Perfil!H24 -> 7 | F38: =RC_Perfil!I24 -> 7 | G38: =RC_Perfil!J24 -> 7 | H38: =RC_Perfil!K24 -> 7 | I38: =RC_Perfil!L24 -> 7 | ... M38: =RC_Perfil!P24 -> 7 | N38: =IF(ISERROR(IF(C38="",B38,IF(D38="",C38,IF(E38="",D38,IF(F38="",E38,IF(G38="",F38,IF(H38="",G38,IF(I38="",H38,IF(J38="",I38,IF(K38="",J38,IF(L38="",K38,IF(M38="",L38,M38)))))))))))),"",IF(C38="",B38,IF(D38="",C38,IF(E38="",D38,IF(F38="",E38,IF(G38="",F38,IF(H38="",G38,IF(I38="",H38,IF(J38="",I38,IF(K38="",J38,IF(L38="",K38,IF(M38="",L38,M38)))))))))))) -> 7
A39: Feminino | B39: =RC_Perfil!E25 -> 3 | C39: =RC_Perfil!F25 -> 4 | D39: =RC_Perfil!G25 -> 4 | E39: =RC_Perfil!H25 -> 4 | F39: =RC_Perfil!I25 -> 4 | G39: =RC_Perfil!J25 -> 4 | H39: =RC_Perfil!K25 -> 4 | I39: =RC_Perfil!L25 -> 4 | ... M39: =RC_Perfil!P25 -> 4 | N39: =IF(ISERROR(IF(C39="",B39,IF(D39="",C39,IF(E39="",D39,IF(F39="",E39,IF(G39="",F39,IF(H39="",G39,IF(I39="",H39,IF(J39="",I39,IF(K39="",J39,IF(L39="",K39,IF(M39="",L39,M39)))))))))))),"",IF(C39="",B39,IF(D39="",C39,IF(E39="",D39,IF(F39="",E39,IF(G39="",F39,IF(H39="",G39,IF(I39="",H39,IF(J39="",I39,IF(K39="",J39,IF(L39="",K39,IF(M39="",L39,M39)))))))))))) -> 4
A41: Indicador | B41: Jan | C41: Fev | D41: Mar | E41: Abr | F41: Mai | G41: Jun | H41: Jul | I41: Ago | J41: Set | K41: Out | L41: Nov | M41: Dez | N41: Total
A42: Custo total | B42: =RC_Eventos!E14 -> 900 | C42: =RC_Eventos!F14 -> 501 | D42: =RC_Eventos!G14 -> 600 | E42: =RC_Eventos!H14 -> 400 | F42: =RC_Eventos!I14 -> 100 | G42: =RC_Eventos!J14 -> 0 | H42: =RC_Eventos!K14 -> 0 | I42: =RC_Eventos!L14 -> 0 | ... M42: =RC_Eventos!P14 -> 0 | N42: =SUM(B42:M42) -> 2501
A43: Horas totais | B43: =RC_Eventos!E15 -> 0 | C43: =RC_Eventos!F15 -> 20 | D43: =RC_Eventos!G15 -> 140 | E43: =RC_Eventos!H15 -> 120 | F43: =RC_Eventos!I15 -> 0 | G43: =RC_Eventos!J15 -> 0 | H43: =RC_Eventos!K15 -> 0 | I43: =RC_Eventos!L15 -> 0 | ... M43: =RC_Eventos!P15 -> 0 | N43: =SUM(B43:M43) -> 280
A44: Funcionários em treinamento | B44: =RC_Eventos!E13 -> 0 | C44: =RC_Eventos!F13 -> 3 | D44: =RC_Eventos!G13 -> 8 | E44: =RC_Eventos!H13 -> 5 | F44: =RC_Eventos!I13 -> 0 | G44: =RC_Eventos!J13 -> 0 | H44: =RC_Eventos!K13 -> 0 | I44: =RC_Eventos!L13 -> 0 | ... M44: =RC_Eventos!P13 -> 0 | N44: =IF(ISERROR(SUMIFS(Lanç_Terinamentos!$G$8:$G$2008,Lanç_Terinamentos!$X$8:$X$2008,$B$1)),"",SUMIFS(Lanç_Terinamentos!$G$8:$G$2008,Lanç_Terinamentos!$X$8:$X$2008,$B$1)) -> 8
A46: Indicador | B46: Jan | C46: Fev | D46: Mar | E46: Abr | F46: Mai | G46: Jun | H46: Jul | I46: Ago | J46: Set | K46: Out | L46: Nov | M46: Dez | N46: Total
A47: Receita Bruta | B47: =RC_Receitas!F11 -> 400000 | C47: =RC_Receitas!G11 -> 200001 | D47: =RC_Receitas!H11 -> 200002 | E47: =RC_Receitas!I11 -> 200003 | F47: =RC_Receitas!J11 -> 300000 | G47: =RC_Receitas!K11 -> 200000 | H47: =RC_Receitas!L11 -> 300000 | I47: =RC_Receitas!M11 | ... M47: =RC_Receitas!Q11 | N47: =SUM(B47:M47) -> 1800006
A48: Custo total | B48: =SUM(B53:B55,B58:B69,B42) -> 67400 | C48: =SUM(C53:C55,C58:C69,C42) -> 64606 | D48: =SUM(D53:D55,D58:D69,D42) -> 60610 | E48: =SUM(E53:E55,E58:E69,E42) -> 58915 | F48: =SUM(F53:F55,F58:F69,F42) -> 41606 | G48: =SUM(G53:G55,G58:G69,G42) -> 31506 | H48: =SUM(H53:H55,H58:H69,H42) -> 0 | I48: =SUM(I53:I55,I58:I69,I42) -> 0 | ... M48: =SUM(M53:M55,M58:M69,M42) -> 0 | N48: =SUM(B48:M48) -> 324643
A49: Receita média por funcionário | B49: =IF(ISERROR(B47/B9),"",B47/B9) -> 40000 | C49: =IF(ISERROR(C47/C9),"",C47/C9) -> 16666.75 | D49: =IF(ISERROR(D47/D9),"",D47/D9) -> 18182 | E49: =IF(ISERROR(E47/E9),"",E47/E9) -> 18182.091 | F49: =IF(ISERROR(F47/F9),"",F47/F9) -> 27272.727 | G49: =IF(ISERROR(G47/G9),"",G47/G9) -> 18181.818 | H49: =IF(ISERROR(H47/H9),"",H47/H9) -> 27272.727 | I49: =IF(ISERROR(I47/I9),"",I47/I9) | ... N49: =IF(ISERROR(N47/N9),"",N47/N9) -> 163636.91
A50: Custo médio por funcionário | B50: =IF(ISERROR(B48/B9),"",B48/B9) -> 6740 | C50: =IF(ISERROR(C48/C9),"",C48/C9) -> 5383.8333 | D50: =IF(ISERROR(D48/D9),"",D48/D9) -> 5510 | E50: =IF(ISERROR(E48/E9),"",E48/E9) -> 5355.9091 | F50: =IF(ISERROR(F48/F9),"",F48/F9) -> 3782.3636 | G50: =IF(ISERROR(G48/G9),"",G48/G9) -> 2864.1818 | H50: =IF(ISERROR(H48/H9),"",H48/H9) -> 0 | I50: =IF(ISERROR(I48/I9),"",I48/I9) -> 0 | ... N50: =IF(ISERROR(N48/N9),"",N48/N9) -> 29513
A52: Indicador | B52: Jan | C52: Fev | D52: Mar | E52: Abr | F52: Mai | G52: Jun | H52: Jul | I52: Ago | J52: Set | K52: Out | L52: Nov | M52: Dez | N52: Total
A53: Custo com folha de pagamento | B53: =SUM(RC_Receitas!F14,RC_Receitas!F16) -> 53500 | C53: =SUM(RC_Receitas!G14,RC_Receitas!G16) -> 55102 | D53: =SUM(RC_Receitas!H14,RC_Receitas!H16) -> 51004 | E53: =SUM(RC_Receitas!I14,RC_Receitas!I16) -> 49506 | F53: =SUM(RC_Receitas!J14,RC_Receitas!J16) -> 38503 | G53: =SUM(RC_Receitas!K14,RC_Receitas!K16) -> 28503 | H53: =SUM(RC_Receitas!L14,RC_Receitas!L16) -> 0 | I53: =SUM(RC_Receitas!M14,RC_Receitas!M16) -> 0 | ... M53: =SUM(RC_Receitas!Q14,RC_Receitas!Q16) -> 0 | N53: =SUM(B53:M53) -> 276118
A54: Impostos | B54: =RC_Receitas!F18 -> 3000 | C54: =RC_Receitas!G18 -> 3001 | D54: =RC_Receitas!H18 -> 3002 | E54: =RC_Receitas!I18 -> 3003 | F54: =RC_Receitas!J18 -> 3003 | G54: =RC_Receitas!K18 -> 3003 | H54: =RC_Receitas!L18 | I54: =RC_Receitas!M18 | ... M54: =RC_Receitas!Q18 | N54: =SUM(B54:M54) -> 18012
A55: Outros custos | B55: =RC_Receitas!F19 -> 1000 | C55: =RC_Receitas!G19 -> 1001 | D55: =RC_Receitas!H19 -> 1002 | E55: =RC_Receitas!I19 -> 1003 | F55: =RC_Receitas!J19 -> 0 | G55: =RC_Receitas!K19 -> 0 | H55: =RC_Receitas!L19 | I55: =RC_Receitas!M19 | ... M55: =RC_Receitas!Q19 | N55: =SUM(B55:M55) -> 4006
A57: Indicador | B57: Jan | C57: Fev | D57: Mar | E57: Abr | F57: Mai | G57: Jun | H57: Jul | I57: Ago | J57: Set | K57: Out | L57: Nov | M57: Dez | N57: Total
A58: =RC_Receitas!C22 -> Alimentação | B58: =RC_Receitas!F22 -> 3000 | C58: =RC_Receitas!G22 -> 3001 | D58: =RC_Receitas!H22 -> 3002 | E58: =RC_Receitas!I22 -> 3003 | F58: =RC_Receitas!J22 -> 0 | G58: =RC_Receitas!K22 -> 0 | H58: =RC_Receitas!L22 -> 0 | I58: =RC_Receitas!M22 -> 0 | ... M58: =RC_Receitas!Q22 -> 0 | N58: =SUM(B58:M58) -> 12006
A59: =RC_Receitas!C23 -> Saúde | B59: =RC_Receitas!F23 -> 3000 | C59: =RC_Receitas!G23 -> 1000 | D59: =RC_Receitas!H23 -> 1000 | E59: =RC_Receitas!I23 -> 1000 | F59: =RC_Receitas!J23 -> 0 | G59: =RC_Receitas!K23 -> 0 | H59: =RC_Receitas!L23 -> 0 | I59: =RC_Receitas!M23 -> 0 | ... M59: =RC_Receitas!Q23 -> 0 | N59: =SUM(B59:M59) -> 6000
A60: =RC_Receitas!C24 -> Odonto | B60: =RC_Receitas!F24 -> 3000 | C60: =RC_Receitas!G24 -> 1000 | D60: =RC_Receitas!H24 -> 1000 | E60: =RC_Receitas!I24 -> 1000 | F60: =RC_Receitas!J24 -> 0 | G60: =RC_Receitas!K24 -> 0 | H60: =RC_Receitas!L24 -> 0 | I60: =RC_Receitas!M24 -> 0 | ... M60: =RC_Receitas!Q24 -> 0 | N60: =SUM(B60:M60) -> 6000
A61: =RC_Receitas!C25 -> Transporte | B61: =RC_Receitas!F25 -> 0 | C61: =RC_Receitas!G25 -> 0 | D61: =RC_Receitas!H25 -> 0 | E61: =RC_Receitas!I25 -> 0 | F61: =RC_Receitas!J25 -> 0 | G61: =RC_Receitas!K25 -> 0 | H61: =RC_Receitas!L25 -> 0 | I61: =RC_Receitas!M25 -> 0 | ... M61: =RC_Receitas!Q25 -> 0 | N61: =SUM(B61:M61) -> 0
A62: =RC_Receitas!C26 -> Seguro de vida | B62: =RC_Receitas!F26 -> 0 | C62: =RC_Receitas!G26 -> 0 | D62: =RC_Receitas!H26 -> 0 | E62: =RC_Receitas!I26 -> 0 | F62: =RC_Receitas!J26 -> 0 | G62: =RC_Receitas!K26 -> 0 | H62: =RC_Receitas!L26 -> 0 | I62: =RC_Receitas!M26 -> 0 | ... M62: =RC_Receitas!Q26 -> 0 | N62: =SUM(B62:M62) -> 0
A63: =RC_Receitas!C27 -> Vale academia | B63: =RC_Receitas!F27 -> 0 | C63: =RC_Receitas!G27 -> 0 | D63: =RC_Receitas!H27 -> 0 | E63: =RC_Receitas!I27 -> 0 | F63: =RC_Receitas!J27 -> 0 | G63: =RC_Receitas!K27 -> 0 | H63: =RC_Receitas!L27 -> 0 | I63: =RC_Receitas!M27 -> 0 | ... M63: =RC_Receitas!Q27 -> 0 | N63: =SUM(B63:M63) -> 0
A64: =RC_Receitas!C28 -> Creche | B64: =RC_Receitas!F28 -> 0 | C64: =RC_Receitas!G28 -> 0 | D64: =RC_Receitas!H28 -> 0 | E64: =RC_Receitas!I28 -> 0 | F64: =RC_Receitas!J28 -> 0 | G64: =RC_Receitas!K28 -> 0 | H64: =RC_Receitas!L28 -> 0 | I64: =RC_Receitas!M28 -> 0 | ... M64: =RC_Receitas!Q28 -> 0 | N64: =SUM(B64:M64) -> 0
A65: =RC_Receitas!C29 -> Vale combustível | B65: =RC_Receitas!F29 -> 0 | C65: =RC_Receitas!G29 -> 0 | D65: =RC_Receitas!H29 -> 0 | E65: =RC_Receitas!I29 -> 0 | F65: =RC_Receitas!J29 -> 0 | G65: =RC_Receitas!K29 -> 0 | H65: =RC_Receitas!L29 -> 0 | I65: =RC_Receitas!M29 -> 0 | ... M65: =RC_Receitas!Q29 -> 0 | N65: =SUM(B65:M65) -> 0
A66: =RC_Receitas!C30 -> Salário família | B66: =RC_Receitas!F30 -> 0 | C66: =RC_Receitas!G30 -> 0 | D66: =RC_Receitas!H30 -> 0 | E66: =RC_Receitas!I30 -> 0 | F66: =RC_Receitas!J30 -> 0 | G66: =RC_Receitas!K30 -> 0 | H66: =RC_Receitas!L30 -> 0 | I66: =RC_Receitas!M30 -> 0 | ... M66: =RC_Receitas!Q30 -> 0 | N66: =SUM(B66:M66) -> 0
A67: =RC_Receitas!C31 | B67: =RC_Receitas!F31 -> 0 | C67: =RC_Receitas!G31 -> 0 | D67: =RC_Receitas!H31 -> 0 | E67: =RC_Receitas!I31 -> 0 | F67: =RC_Receitas!J31 -> 0 | G67: =RC_Receitas!K31 -> 0 | H67: =RC_Receitas!L31 -> 0 | I67: =RC_Receitas!M31 -> 0 | ... M67: =RC_Receitas!Q31 -> 0 | N67: =SUM(B67:M67) -> 0
A68: =RC_Receitas!C32 | B68: =RC_Receitas!F32 -> 0 | C68: =RC_Receitas!G32 -> 0 | D68: =RC_Receitas!H32 -> 0 | E68: =RC_Receitas!I32 -> 0 | F68: =RC_Receitas!J32 -> 0 | G68: =RC_Receitas!K32 -> 0 | H68: =RC_Receitas!L32 -> 0 | I68: =RC_Receitas!M32 -> 0 | ... M68: =RC_Receitas!Q32 -> 0 | N68: =SUM(B68:M68) -> 0
A69: =RC_Receitas!C33 | B69: =RC_Receitas!F33 -> 0 | C69: =RC_Receitas!G33 -> 0 | D69: =RC_Receitas!H33 -> 0 | E69: =RC_Receitas!I33 -> 0 | F69: =RC_Receitas!J33 -> 0 | G69: =RC_Receitas!K33 -> 0 | H69: =RC_Receitas!L33 -> 0 | I69: =RC_Receitas!M33 -> 0 | ... M69: =RC_Receitas!Q33 -> 0 | N69: =SUM(B69:M69) -> 0
A71: Faixa etária | B71: ="Total "&B1 -> Total 2015
A72: 18 a 23 anos | B72: =SUMIF(Cad_Func!$O$8:$O$208,'Graf Aux'!A72,Cad_Func!$P$8:$P$208) -> 0
A73: 24 a 33 anos | B73: =SUMIF(Cad_Func!$O$8:$O$208,'Graf Aux'!A73,Cad_Func!$P$8:$P$208) -> 2
A74: 34 a 43 anos | B74: =SUMIF(Cad_Func!$O$8:$O$208,'Graf Aux'!A74,Cad_Func!$P$8:$P$208) -> 9
A75: 44 a 53 anos | B75: =SUMIF(Cad_Func!$O$8:$O$208,'Graf Aux'!A75,Cad_Func!$P$8:$P$208) -> 0
A76: 54 a 60 anos | B76: =SUMIF(Cad_Func!$O$8:$O$208,'Graf Aux'!A76,Cad_Func!$P$8:$P$208) -> 0
A77: Mais de 60 anos | B77: =SUMIF(Cad_Func!$O$8:$O$208,'Graf Aux'!A77,Cad_Func!$P$8:$P$208) -> 0

Sheet AD
C1: 5. ALERTAS E DICAS | T1: Janeiro | U1: 1
T2: Fevereiro | U2: 2
T3: Março | U3: 3
T5: Abril | U5: 4
C6: Indique o mês | D6: Fevereiro | I6: =VLOOKUP(D6,$T$1:$U$13,2,0) -> 2 | T6: Maio | U6: 5
T7: Junho | U7: 6
C8: Alertas e dicas sobre os pontos analisados com base nas informações lançadas | T8: Julho | U8: 7
C9: Turnover | E9: Treinamentos | G9: Retorno | T9: Agosto | U9: 8
C10: =IF(ISERROR(IF(D17="",D20,IF(D17>0,D18,D19))),"",IF(D17="",D20,IF(D17>0,D18,D19))) -> A Taxa de Turnover aumentou em relação ao mês anterior em 67%. O que houve para que esta taxa tenha aumentado? Houve maior número de demissões? Faltou valorização do profissional? É importante manter essa taxa a menor possível. Isso pode ser um indicador de uma boa equipe, logo, bons resultados. | E10: =IF(ISERROR(IF(OR(D22=0,D22=""),D25,IF(D22>0,D23,D24))),"",IF(OR(D22=0,D22=""),D25,IF(D22>0,D23,D24))) -> Não foi possível comparar com o mês anterior por falta de dados. Ou seja, não há comentários a serem exibidos para este item. | G10: =IF(ISERROR(IF(D27="",D30,IF(D27>0,D28,D29))),"",IF(D27="",D30,IF(D27>0,D28,D29))) -> Notícias não muito boas para este mês. A receita média gerada por cada funcionário foi 100% menor em relação ao mês anterior. É importante procurar extrair uma receita maior por cada funcionário. Isso pode ser um dos indicadores de resultados mais lucrativos. A Planilha de Fluxo de Caixa LUZ ajuda a controlar melhor esses indicadores de resultados financeiros. | T10: Setembro | U10: 9
T11: Outubro | U11: 10
T12: Novembro | U12: 11
T13: Dezembro | U13: 12
C17: Turnover | D17: =IF(ISERROR(ROUND(INDEX('AD Aux'!$B$11:$N$11,1,MATCH(AD!$I$6,'AD Aux'!$C$2:$N$2,0)+1),2)*100),"",ROUND(INDEX('AD Aux'!$B$11:$N$11,1,MATCH(AD!$I$6,'AD Aux'!$C$2:$N$2,0)+1),2)*100) -> 67
C18: Negativo: | D18: ="A Taxa de Turnover aumentou em relação ao mês anterior em "&D17&"%. O que houve para que esta taxa tenha aumentado? Houve maior número de demissões? Faltou valorização do profissional? É importante manter essa taxa a menor possível. Isso pode ser um indicador de uma boa equipe, logo, bons resultados." -> A Taxa de Turnover aumentou em relação ao mês anterior em 67%. O que houve para que esta taxa tenha aumentado? Houve maior número de demissões? Faltou valorização do profissional? É importante manter essa taxa a menor possível. Isso pode ser um indicador de uma boa equipe, logo, bons resultados.
C19: Positivo: | D19: A Taxa de Turnover diminuiu ou se manteve estável em relação ao mês anterior. Isso pode ser um bom sinal de satisfação dos funcionários em relação a empresa e da empresa em relação aos funcionários. É importante manter essa taxa a menor possível. Isso pode ser um indicador de uma boa equipe, logo, bons resultados.
C20: Neutro: | D20: Não foi possível comparar com o mês anterior por falta de dados. Ou seja, não há comentários a serem exibidos para este item.
C22: Treinamentos | D22: =IF(ISERROR(ROUND(INDEX('AD Aux'!$B$15:$N$15,1,MATCH(AD!$I$6,'AD Aux'!$C$2:$N$2,0)+1),2)),"",ROUND(INDEX('AD Aux'!$B$15:$N$15,1,MATCH(AD!$I$6,'AD Aux'!$C$2:$N$2,0)+1),2)) -> 0
C23: Negativo: | D23: Seu custo com treinamentos aumentou em relação ao mês anterior. Isso é ruim no ponto de vista "redução de custos", porém, não é motivo para alarde. É importante se dedicar a equipe através de treinamentos, pois eles podem diminuir outros custos muito mais significativos para a empresa. Cerifique-se do retorno que o investimento traz para o cotidiano da empresa.
C24: Positivo: | D24: Seu custo com treinamentos diminuiu em relação ao mês anterior. Isso é bom no ponto de vista "redução de custos", porém, fique atento, pois é importante se dedicar a equipe através de treinamentos, pois eles podem diminuir outros custos muito mais significativos para a empresa.
C25: Neutro: | D25: Não foi possível comparar com o mês anterior por falta de dados. Ou seja, não há comentários a serem exibidos para este item.
C27: Receita | D27: =IF(ISERROR(ROUND(INDEX('AD Aux'!$B$20:$N$20,1,MATCH(AD!$I$6,'AD Aux'!$C$2:$N$2,0)+1),2)*100),"",ROUND(INDEX('AD Aux'!$B$20:$N$20,1,MATCH(AD!$I$6,'AD Aux'!$C$2:$N$2,0)+1),2)*100) -> 100
C28: Negativo: | D28: ="Notícias não muito boas para este mês. A receita média gerada por cada funcionário foi "&D27&"% menor em relação ao mês anterior. É importante procurar extrair uma receita maior por cada funcionário. Isso pode ser um dos indicadores de resultados mais lucrativos."&" A Planilha de Fluxo de Caixa LUZ ajuda a controlar melhor esses indicadores de resultados financeiros." -> Notícias não muito boas para este mês. A receita média gerada por cada funcionário foi 100% menor em relação ao mês anterior. É importante procurar extrair uma receita maior por cada funcionário. Isso pode ser um dos indicadores de resultados mais lucrativos. A Planilha de Fluxo de Caixa LUZ ajuda a controlar melhor esses indicadores de resultados financeiros.
C29: Positivo: | D29: ="Boas notícias para este mês! A receita média gerada por cada funcionário foi "&D27&"% maior em relação ao mês anterior. Se os gastos totais da empresa (incluindo custos diretos, fixos, impostos, folha, etc) for menor que a receita bruta gerada, significa que a empresa está lucrativa."&" A Planilha de Fluxo de Caixa LUZ ajuda a controlar melhor esses indicadores de resultados financeiros." -> Boas notícias para este mês! A receita média gerada por cada funcionário foi 100% maior em relação ao mês anterior. Se os gastos totais da empresa (incluindo custos diretos, fixos, impostos, folha, etc) for menor que a receita bruta gerada, significa que a empresa está lucrativa. A Planilha de Fluxo de Caixa LUZ ajuda a controlar melhor esses indicadores de resultados financeiros.
C30: Neutro: | D30: Não foi possível comparar com o mês anterior por falta de dados. Ou seja, não há comentários a serem exibidos para este item.

Sheet AD Aux
A1: Ano | B1: =C1-1 -> 2014 | C1: =Cad_Inicial!$D$8 -> 2015
B2: 12 | C2: 1 | D2: 2 | E2: 3 | F2: 4 | G2: 5 | H2: 6 | I2: 7 | J2: 8 | K2: 9 | L2: 10 | M2: 11 | N2: 12
A3: ="<"&C1 -> <2015 | B3: ="<="&B2 -> <=12 | C3: ="<="&C2 -> <=1 | D3: ="<="&D2 -> <=2 | E3: ="<="&E2 -> <=3 | F3: ="<="&F2 -> <=4 | G3: ="<="&G2 -> <=5 | H3: ="<="&H2 -> <=6 | I3: ="<="&I2 -> <=7 | ... N3: ="<="&N2 -> <=12
B4: =">="&B2 -> >=12 | C4: =">="&C2 -> >=1 | D4: =">="&D2 -> >=2 | E4: =">="&E2 -> >=3 | F4: =">="&F2 -> >=4 | G4: =">="&G2 -> >=5 | H4: =">="&H2 -> >=6 | I4: =">="&I2 -> >=7 | ... N4: =">="&N2 -> >=12
A5: Indicador | B5: ="Dez "&B1 -> Dez 2014 | C5: Jan | D5: Fev | E5: Mar | F5: Abr | G5: Mai | H5: Jun | I5: Jul | J5: Ago | K5: Set | L5: Out | M5: Nov | N5: Dez
A6: Admissões | B6: =IF(ISERROR(IF(AND($B$1>=YEAR(TODAY()),MONTH(TODAY())<B$2),"",COUNTIFS(Cad_Func!$W$8:$W$208,$B$1,Cad_Func!$X$8:$X$208,B$2))),"",IF(AND($B$1>=YEAR(TODAY()),MONTH(TODAY())<B$2),"",COUNTIFS(Cad_Func!$W$8:$W$208,$B$1,Cad_Func!$X$8:$X$208,B$2))) -> 1 | C6: =IF(ISERROR(IF(AND($C$1>=YEAR(TODAY()),MONTH(TODAY())<C$2),"",COUNTIFS(Cad_Func!$W$8:$W$208,$C$1,Cad_Func!$X$8:$X$208,C$2))),"",IF(AND($C$1>=YEAR(TODAY()),MONTH(TODAY())<C$2),"",COUNTIFS(Cad_Func!$W$8:$W$208,$C$1,Cad_Func!$X$8:$X$208,C$2))) -> 1 | D6: =IF(ISERROR(IF(AND($C$1>=YEAR(TODAY()),MONTH(TODAY())<D$2),"",COUNTIFS(Cad_Func!$W$8:$W$208,$C$1,Cad_Func!$X$8:$X$208,D$2))),"",IF(AND($C$1>=YEAR(TODAY()),MONTH(TODAY())<D$2),"",COUNTIFS(Cad_Func!$W$8:$W$208,$C$1,Cad_Func!$X$8:$X$208,D$2))) -> 2 | E6: =IF(ISERROR(IF(AND($C$1>=YEAR(TODAY()),MONTH(TODAY())<E$2),"",COUNTIFS(Cad_Func!$W$8:$W$208,$C$1,Cad_Func!$X$8:$X$208,E$2))),"",IF(AND($C$1>=YEAR(TODAY()),MONTH(TODAY())<E$2),"",COUNTIFS(Cad_Func!$W$8:$W$208,$C$1,Cad_Func!$X$8:$X$208,E$2))) -> 0 | F6: =IF(ISERROR(IF(AND($C$1>=YEAR(TODAY()),MONTH(TODAY())<F$2),"",COUNTIFS(Cad_Func!$W$8:$W$208,$C$1,Cad_Func!$X$8:$X$208,F$2))),"",IF(AND($C$1>=YEAR(TODAY()),MONTH(TODAY())<F$2),"",COUNTIFS(Cad_Func!$W$8:$W$208,$C$1,Cad_Func!$X$8:$X$208,F$2))) -> 0 | G6: =IF(ISERROR(IF(AND($C$1>=YEAR(TODAY()),MONTH(TODAY())<G$2),"",COUNTIFS(Cad_Func!$W$8:$W$208,$C$1,Cad_Func!$X$8:$X$208,G$2))),"",IF(AND($C$1>=YEAR(TODAY()),MONTH(TODAY())<G$2),"",COUNTIFS(Cad_Func!$W$8:$W$208,$C$1,Cad_Func!$X$8:$X$208,G$2))) -> 0 | H6: =IF(ISERROR(IF(AND($C$1>=YEAR(TODAY()),MONTH(TODAY())<H$2),"",COUNTIFS(Cad_Func!$W$8:$W$208,$C$1,Cad_Func!$X$8:$X$208,H$2))),"",IF(AND($C$1>=YEAR(TODAY()),MONTH(TODAY())<H$2),"",COUNTIFS(Cad_Func!$W$8:$W$208,$C$1,Cad_Func!$X$8:$X$208,H$2))) -> 0 | I6: =IF(ISERROR(IF(AND($C$1>=YEAR(TODAY()),MONTH(TODAY())<I$2),"",COUNTIFS(Cad_Func!$W$8:$W$208,$C$1,Cad_Func!$X$8:$X$208,I$2))),"",IF(AND($C$1>=YEAR(TODAY()),MONTH(TODAY())<I$2),"",COUNTIFS(Cad_Func!$W$8:$W$208,$C$1,Cad_Func!$X$8:$X$208,I$2))) -> 0 | J6: =IF(ISERROR(IF(AND($C$1>=YEAR(TODAY()),MONTH(TODAY())<J$2),"",COUNTIFS(Cad_Func!$W$8:$W$208,$C$1,Cad_Func!$X$8:$X$208,J$2))),"",IF(AND($C$1>=YEAR(TODAY()),MONTH(TODAY())<J$2),"",COUNTIFS(Cad_Func!$W$8:$W$208,$C$1,Cad_Func!$X$8:$X$208,J$2))) -> 0 | ... N6: =IF(ISERROR(IF(AND($C$1>=YEAR(TODAY()),MONTH(TODAY())<N$2),"",COUNTIFS(Cad_Func!$W$8:$W$208,$C$1,Cad_Func!$X$8:$X$208,N$2))),"",IF(AND($C$1>=YEAR(TODAY()),MONTH(TODAY())<N$2),"",COUNTIFS(Cad_Func!$W$8:$W$208,$C$1,Cad_Func!$X$8:$X$208,N$2))) -> 0
A7: Demissões | B7: =IF(ISERROR(IF(AND($B$1>=YEAR(TODAY()),MONTH(TODAY())<B$2),"",COUNTIFS(Cad_Func!$Y$8:$Y$208,RC_Rotatividade!#REF!,Cad_Func!$Z$8:$Z$208,RC_Rotatividade!D$6))),"",IF(AND($B$1>=YEAR(TODAY()),MONTH(TODAY())<B$2),"",COUNTIFS(Cad_Func!$Y$8:$Y$208,RC_Rotatividade!#REF!,Cad_Func!$Z$8:$Z$208,RC_Rotatividade!D$6))) -> 0 | C7: =IF(ISERROR(IF(AND($C$1>=YEAR(TODAY()),MONTH(TODAY())<C$2),"",COUNTIFS(Cad_Func!$Y$8:$Y$208,RC_Rotatividade!#REF!,Cad_Func!$Z$8:$Z$208,RC_Rotatividade!E$6))),"",IF(AND($C$1>=YEAR(TODAY()),MONTH(TODAY())<C$2),"",COUNTIFS(Cad_Func!$Y$8:$Y$208,RC_Rotatividade!#REF!,Cad_Func!$Z$8:$Z$208,RC_Rotatividade!E$6))) -> 0 | D7: =IF(ISERROR(IF(AND($C$1>=YEAR(TODAY()),MONTH(TODAY())<D$2),"",COUNTIFS(Cad_Func!$Y$8:$Y$208,RC_Rotatividade!#REF!,Cad_Func!$Z$8:$Z$208,RC_Rotatividade!F$6))),"",IF(AND($C$1>=YEAR(TODAY()),MONTH(TODAY())<D$2),"",COUNTIFS(Cad_Func!$Y$8:$Y$208,RC_Rotatividade!#REF!,Cad_Func!$Z$8:$Z$208,RC_Rotatividade!F$6))) -> 0 | E7: =IF(ISERROR(IF(AND($C$1>=YEAR(TODAY()),MONTH(TODAY())<E$2),"",COUNTIFS(Cad_Func!$Y$8:$Y$208,RC_Rotatividade!#REF!,Cad_Func!$Z$8:$Z$208,RC_Rotatividade!G$6))),"",IF(AND($C$1>=YEAR(TODAY()),MONTH(TODAY())<E$2),"",COUNTIFS(Cad_Func!$Y$8:$Y$208,RC_Rotatividade!#REF!,Cad_Func!$Z$8:$Z$208,RC_Rotatividade!G$6))) -> 0 | F7: =IF(ISERROR(IF(AND($C$1>=YEAR(TODAY()),MONTH(TODAY())<F$2),"",COUNTIFS(Cad_Func!$Y$8:$Y$208,RC_Rotatividade!#REF!,Cad_Func!$Z$8:$Z$208,RC_Rotatividade!H$6))),"",IF(AND($C$1>=YEAR(TODAY()),MONTH(TODAY())<F$2),"",COUNTIFS(Cad_Func!$Y$8:$Y$208,RC_Rotatividade!#REF!,Cad_Func!$Z$8:$Z$208,RC_Rotatividade!H$6))) -> 0 | G7: =IF(ISERROR(IF(AND($C$1>=YEAR(TODAY()),MONTH(TODAY())<G$2),"",COUNTIFS(Cad_Func!$Y$8:$Y$208,RC_Rotatividade!#REF!,Cad_Func!$Z$8:$Z$208,RC_Rotatividade!I$6))),"",IF(AND($C$1>=YEAR(TODAY()),MONTH(TODAY())<G$2),"",COUNTIFS(Cad_Func!$Y$8:$Y$208,RC_Rotatividade!#REF!,Cad_Func!$Z$8:$Z$208,RC_Rotatividade!I$6))) -> 0 | H7: =IF(ISERROR(IF(AND($C$1>=YEAR(TODAY()),MONTH(TODAY())<H$2),"",COUNTIFS(Cad_Func!$Y$8:$Y$208,RC_Rotatividade!#REF!,Cad_Func!$Z$8:$Z$208,RC_Rotatividade!J$6))),"",IF(AND($C$1>=YEAR(TODAY()),MONTH(TODAY())<H$2),"",COUNTIFS(Cad_Func!$Y$8:$Y$208,RC_Rotatividade!#REF!,Cad_Func!$Z$8:$Z$208,RC_Rotatividade!J$6))) -> 0 | I7: =IF(ISERROR(IF(AND($C$1>=YEAR(TODAY()),MONTH(TODAY())<I$2),"",COUNTIFS(Cad_Func!$Y$8:$Y$208,RC_Rotatividade!#REF!,Cad_Func!$Z$8:$Z$208,RC_Rotatividade!K$6))),"",IF(AND($C$1>=YEAR(TODAY()),MONTH(TODAY())<I$2),"",COUNTIFS(Cad_Func!$Y$8:$Y$208,RC_Rotatividade!#REF!,Cad_Func!$Z$8:$Z$208,RC_Rotatividade!K$6))) -> 0 | J7: =IF(ISERROR(IF(AND($C$1>=YEAR(TODAY()),MONTH(TODAY())<J$2),"",COUNTIFS(Cad_Func!$Y$8:$Y$208,RC_Rotatividade!#REF!,Cad_Func!$Z$8:$Z$208,RC_Rotatividade!L$6))),"",IF(AND($C$1>=YEAR(TODAY()),MONTH(TODAY())<J$2),"",COUNTIFS(Cad_Func!$Y$8:$Y$208,RC_Rotatividade!#REF!,Cad_Func!$Z$8:$Z$208,RC_Rotatividade!L$6))) -> 0 | ... N7: =IF(ISERROR(IF(AND($C$1>=YEAR(TODAY()),MONTH(TODAY())<N$2),"",COUNTIFS(Cad_Func!$Y$8:$Y$208,RC_Rotatividade!#REF!,Cad_Func!$Z$8:$Z$208,RC_Rotatividade!P$6))),"",IF(AND($C$1>=YEAR(TODAY()),MONTH(TODAY())<N$2),"",COUNTIFS(Cad_Func!$Y$8:$Y$208,RC_Rotatividade!#REF!,Cad_Func!$Z$8:$Z$208,RC_Rotatividade!P$6))) -> 0
A8: Funcionários no início do mês | B8: =IF(ISERROR(SUM(Cad_Func!$Q$8:$Q$208)),"",SUM(Cad_Func!$Q$8:$Q$208)) -> 9 | C8: =IF(ISERROR(SUM(Cad_Func!$Q$8:$Q$208)),"",SUM(Cad_Func!$Q$8:$Q$208)) -> 9 | D8: =IF(ISERROR(IF(AND($C$1>=YEAR(TODAY()),MONTH(TODAY())<D$2),"",C9)),"",IF(AND($C$1>=YEAR(TODAY()),MONTH(TODAY())<D$2),"",C9)) -> 10 | E8: =IF(ISERROR(IF(AND($C$1>=YEAR(TODAY()),MONTH(TODAY())<E$2),"",D9)),"",IF(AND($C$1>=YEAR(TODAY()),MONTH(TODAY())<E$2),"",D9)) -> 12 | F8: =IF(ISERROR(IF(AND($C$1>=YEAR(TODAY()),MONTH(TODAY())<F$2),"",E9)),"",IF(AND($C$1>=YEAR(TODAY()),MONTH(TODAY())<F$2),"",E9)) -> 12 | G8: =IF(ISERROR(IF(AND($C$1>=YEAR(TODAY()),MONTH(TODAY())<G$2),"",F9)),"",IF(AND($C$1>=YEAR(TODAY()),MONTH(TODAY())<G$2),"",F9)) -> 12 | H8: =IF(ISERROR(IF(AND($C$1>=YEAR(TODAY()),MONTH(TODAY())<H$2),"",G9)),"",IF(AND($C$1>=YEAR(TODAY()),MONTH(TODAY())<H$2),"",G9)) -> 12 | I8: =IF(ISERROR(IF(AND($C$1>=YEAR(TODAY()),MONTH(TODAY())<I$2),"",H9)),"",IF(AND($C$1>=YEAR(TODAY()),MONTH(TODAY())<I$2),"",H9)) -> 12 | J8: =IF(ISERROR(IF(AND($C$1>=YEAR(TODAY()),MONTH(TODAY())<J$2),"",I9)),"",IF(AND($C$1>=YEAR(TODAY()),MONTH(TODAY())<J$2),"",I9)) -> 12 | K8: =IF(ISERROR(IF(AND($C$1>=YEAR(TODAY()),MONTH(TODAY())<K$2),"",J9)),"",IF(AND($C$1>=YEAR(TODAY()),MONTH(TODAY())<K$2),"",J9)) -> 12 | ... N8: =IF(ISERROR(IF(AND($C$1>=YEAR(TODAY()),MONTH(TODAY())<N$2),"",M9)),"",IF(AND($C$1>=YEAR(TODAY()),MONTH(TODAY())<N$2),"",M9)) -> 12
A9: Funcionários no fim do mês | B9: =IF(ISERROR(B8+B6-B7),"",B8+B6-B7) -> 10 | C9: =IF(ISERROR(C8+C6-C7),"",C8+C6-C7) -> 10 | D9: =IF(ISERROR(D8+D6-D7),"",D8+D6-D7) -> 12 | E9: =IF(ISERROR(E8+E6-E7),"",E8+E6-E7) -> 12 | F9: =IF(ISERROR(F8+F6-F7),"",F8+F6-F7) -> 12 | G9: =IF(ISERROR(G8+G6-G7),"",G8+G6-G7) -> 12 | H9: =IF(ISERROR(H8+H6-H7),"",H8+H6-H7) -> 12 | I9: =IF(ISERROR(I8+I6-I7),"",I8+I6-I7) -> 12 | ... N9: =IF(ISERROR(N8+N6-N7),"",N8+N6-N7) -> 12 | O9: =IF(ISERROR(IF(D9="",C9,IF(E9="",D9,IF(F9="",E9,IF(G9="",F9,IF(H9="",G9,IF(I9="",H9,IF(J9="",I9,IF(K9="",J9,IF(L9="",K9,IF(M9="",L9,IF(N9="",M9,N9)))))))))))),"",IF(D9="",C9,IF(E9="",D9,IF(F9="",E9,IF(G9="",F9,IF(H9="",G9,IF(I9="",H9,IF(J9="",I9,IF(K9="",J9,IF(L9="",K9,IF(M9="",L9,IF(N9="",M9,N9)))))))))))) -> 12
A10: Turnover | B10: =IF(ISERROR(IF((B6+B7)/2/B9=0,"",(B6+B7)/2/B9)),"",IF((B6+B7)/2/B9=0,"",(B6+B7)/2/B9)) -> 0.05 | C10: =IF(ISERROR(IF((C6+C7)/2/C9=0,"",(C6+C7)/2/C9)),"",IF((C6+C7)/2/C9=0,"",(C6+C7)/2/C9)) -> 0.05 | D10: =IF(ISERROR(IF((D6+D7)/2/D9=0,"",(D6+D7)/2/D9)),"",IF((D6+D7)/2/D9=0,"",(D6+D7)/2/D9)) -> 0.083333333 | E10: =IF(ISERROR(IF((E6+E7)/2/E9=0,"",(E6+E7)/2/E9)),"",IF((E6+E7)/2/E9=0,"",(E6+E7)/2/E9)) | F10: =IF(ISERROR(IF((F6+F7)/2/F9=0,"",(F6+F7)/2/F9)),"",IF((F6+F7)/2/F9=0,"",(F6+F7)/2/F9)) | G10: =IF(ISERROR(IF((G6+G7)/2/G9=0,"",(G6+G7)/2/G9)),"",IF((G6+G7)/2/G9=0,"",(G6+G7)/2/G9)) | H10: =IF(ISERROR(IF((H6+H7)/2/H9=0,"",(H6+H7)/2/H9)),"",IF((H6+H7)/2/H9=0,"",(H6+H7)/2/H9)) | I10: =IF(ISERROR(IF((I6+I7)/2/I9=0,"",(I6+I7)/2/I9)),"",IF((I6+I7)/2/I9=0,"",(I6+I7)/2/I9)) | ... N10: =IF(ISERROR(IF((N6+N7)/2/N9=0,"",(N6+N7)/2/N9)),"",IF((N6+N7)/2/N9=0,"",(N6+N7)/2/N9))
A11: Variação % | C11: =IF(ISERROR(C10/B10-1),C10,C10/B10-1) -> 0 | D11: =IF(ISERROR(D10/C10-1),D10,D10/C10-1) -> 0.66666667 | E11: =IF(ISERROR(E10/D10-1),E10,E10/D10-1) | F11: =IF(ISERROR(F10/E10-1),F10,F10/E10-1) | G11: =IF(ISERROR(G10/F10-1),G10,G10/F10-1) | H11: =IF(ISERROR(H10/G10-1),H10,H10/G10-1) | I11: =IF(ISERROR(I10/H10-1),I10,I10/H10-1) | J11: =IF(ISERROR(J10/I10-1),J10,J10/I10-1) | ... N11: =IF(ISERROR(N10/M10-1),N10,N10/M10-1)
A13: Indicador | B13: ="Dez "&$B$1 -> Dez 2014 | C13: Jan | D13: Fev | E13: Mar | F13: Abr | G13: Mai | H13: Jun | I13: Jul | J13: Ago | K13: Set | L13: Out | M13: Nov | N13: Dez | O13: Total
A14: Custo total | B14: =IF(ISERROR(IF(AND($B$1>=YEAR(TODAY()),MONTH(TODAY())<B$2),"",ROUND(SUMIFS(Lanç_Terinamentos!$AA$8:$AA$2008,Lanç_Terinamentos!$X$8:$X$2008,$B$1,Lanç_Terinamentos!$W$8:$W$2008,B$4,Lanç_Terinamentos!$V$8:$V$2008,B$3),2))),"",IF(AND($B$1>=YEAR(TODAY()),MONTH(TODAY())<B$2),"",ROUND(SUMIFS(Lanç_Terinamentos!$AA$8:$AA$2008,Lanç_Terinamentos!$X$8:$X$2008,$B$1,Lanç_Terinamentos!$W$8:$W$2008,B$4,Lanç_Terinamentos!$V$8:$V$2008,B$3),2))) -> 0 | C14: =IF(ISERROR(IF(AND($C$1>=YEAR(TODAY()),MONTH(TODAY())<C$2),"",ROUND(SUMIFS(Lanç_Terinamentos!$AA$8:$AA$2008,Lanç_Terinamentos!$X$8:$X$2008,$C$1,Lanç_Terinamentos!$W$8:$W$2008,C$4,Lanç_Terinamentos!$V$8:$V$2008,C$3),2))),"",IF(AND($C$1>=YEAR(TODAY()),MONTH(TODAY())<C$2),"",ROUND(SUMIFS(Lanç_Terinamentos!$AA$8:$AA$2008,Lanç_Terinamentos!$X$8:$X$2008,$C$1,Lanç_Terinamentos!$W$8:$W$2008,C$4,Lanç_Terinamentos!$V$8:$V$2008,C$3),2))) -> 0 | D14: =IF(ISERROR(IF(AND($C$1>=YEAR(TODAY()),MONTH(TODAY())<D$2),"",ROUND(SUMIFS(Lanç_Terinamentos!$AA$8:$AA$2008,Lanç_Terinamentos!$X$8:$X$2008,$C$1,Lanç_Terinamentos!$W$8:$W$2008,D$4,Lanç_Terinamentos!$V$8:$V$2008,D$3),2))),"",IF(AND($C$1>=YEAR(TODAY()),MONTH(TODAY())<D$2),"",ROUND(SUMIFS(Lanç_Terinamentos!$AA$8:$AA$2008,Lanç_Terinamentos!$X$8:$X$2008,$C$1,Lanç_Terinamentos!$W$8:$W$2008,D$4,Lanç_Terinamentos!$V$8:$V$2008,D$3),2))) -> 0 | E14: =IF(ISERROR(IF(AND($C$1>=YEAR(TODAY()),MONTH(TODAY())<E$2),"",ROUND(SUMIFS(Lanç_Terinamentos!$AA$8:$AA$2008,Lanç_Terinamentos!$X$8:$X$2008,$C$1,Lanç_Terinamentos!$W$8:$W$2008,E$4,Lanç_Terinamentos!$V$8:$V$2008,E$3),2))),"",IF(AND($C$1>=YEAR(TODAY()),MONTH(TODAY())<E$2),"",ROUND(SUMIFS(Lanç_Terinamentos!$AA$8:$AA$2008,Lanç_Terinamentos!$X$8:$X$2008,$C$1,Lanç_Terinamentos!$W$8:$W$2008,E$4,Lanç_Terinamentos!$V$8:$V$2008,E$3),2))) -> 0 | F14: =IF(ISERROR(IF(AND($C$1>=YEAR(TODAY()),MONTH(TODAY())<F$2),"",ROUND(SUMIFS(Lanç_Terinamentos!$AA$8:$AA$2008,Lanç_Terinamentos!$X$8:$X$2008,$C$1,Lanç_Terinamentos!$W$8:$W$2008,F$4,Lanç_Terinamentos!$V$8:$V$2008,F$3),2))),"",IF(AND($C$1>=YEAR(TODAY()),MONTH(TODAY())<F$2),"",ROUND(SUMIFS(Lanç_Terinamentos!$AA$8:$AA$2008,Lanç_Terinamentos!$X$8:$X$2008,$C$1,Lanç_Terinamentos!$W$8:$W$2008,F$4,Lanç_Terinamentos!$V$8:$V$2008,F$3),2))) -> 0 | G14: =IF(ISERROR(IF(AND($C$1>=YEAR(TODAY()),MONTH(TODAY())<G$2),"",ROUND(SUMIFS(Lanç_Terinamentos!$AA$8:$AA$2008,Lanç_Terinamentos!$X$8:$X$2008,$C$1,Lanç_Terinamentos!$W$8:$W$2008,G$4,Lanç_Terinamentos!$V$8:$V$2008,G$3),2))),"",IF(AND($C$1>=YEAR(TODAY()),MONTH(TODAY())<G$2),"",ROUND(SUMIFS(Lanç_Terinamentos!$AA$8:$AA$2008,Lanç_Terinamentos!$X$8:$X$2008,$C$1,Lanç_Terinamentos!$W$8:$W$2008,G$4,Lanç_Terinamentos!$V$8:$V$2008,G$3),2))) -> 0 | H14: =IF(ISERROR(IF(AND($C$1>=YEAR(TODAY()),MONTH(TODAY())<H$2),"",ROUND(SUMIFS(Lanç_Terinamentos!$AA$8:$AA$2008,Lanç_Terinamentos!$X$8:$X$2008,$C$1,Lanç_Terinamentos!$W$8:$W$2008,H$4,Lanç_Terinamentos!$V$8:$V$2008,H$3),2))),"",IF(AND($C$1>=YEAR(TODAY()),MONTH(TODAY())<H$2),"",ROUND(SUMIFS(Lanç_Terinamentos!$AA$8:$AA$2008,Lanç_Terinamentos!$X$8:$X$2008,$C$1,Lanç_Terinamentos!$W$8:$W$2008,H$4,Lanç_Terinamentos!$V$8:$V$2008,H$3),2))) -> 0 | I14: =IF(ISERROR(IF(AND($C$1>=YEAR(TODAY()),MONTH(TODAY())<I$2),"",ROUND(SUMIFS(Lanç_Terinamentos!$AA$8:$AA$2008,Lanç_Terinamentos!$X$8:$X$2008,$C$1,Lanç_Terinamentos!$W$8:$W$2008,I$4,Lanç_Terinamentos!$V$8:$V$2008,I$3),2))),"",IF(AND($C$1>=YEAR(TODAY()),MONTH(TODAY())<I$2),"",ROUND(SUMIFS(Lanç_Terinamentos!$AA$8:$AA$2008,Lanç_Terinamentos!$X$8:$X$2008,$C$1,Lanç_Terinamentos!$W$8:$W$2008,I$4,Lanç_Terinamentos!$V$8:$V$2008,I$3),2))) -> 0 | J14: =IF(ISERROR(IF(AND($C$1>=YEAR(TODAY()),MONTH(TODAY())<J$2),"",ROUND(SUMIFS(Lanç_Terinamentos!$AA$8:$AA$2008,Lanç_Terinamentos!$X$8:$X$2008,$C$1,Lanç_Terinamentos!$W$8:$W$2008,J$4,Lanç_Terinamentos!$V$8:$V$2008,J$3),2))),"",IF(AND($C$1>=YEAR(TODAY()),MONTH(TODAY())<J$2),"",ROUND(SUMIFS(Lanç_Terinamentos!$AA$8:$AA$2008,Lanç_Terinamentos!$X$8:$X$2008,$C$1,Lanç_Terinamentos!$W$8:$W$2008,J$4,Lanç_Terinamentos!$V$8:$V$2008,J$3),2))) -> 0 | ... N14: =IF(ISERROR(IF(AND($C$1>=YEAR(TODAY()),MONTH(TODAY())<N$2),"",ROUND(SUMIFS(Lanç_Terinamentos!$AA$8:$AA$2008,Lanç_Terinamentos!$X$8:$X$2008,$C$1,Lanç_Terinamentos!$W$8:$W$2008,N$4,Lanç_Terinamentos!$V$8:$V$2008,N$3),2))),"",IF(AND($C$1>=YEAR(TODAY()),MONTH(TODAY())<N$2),"",ROUND(SUMIFS(Lanç_Terinamentos!$AA$8:$AA$2008,Lanç_Terinamentos!$X$8:$X$2008,$C$1,Lanç_Terinamentos!$W$8:$W$2008,N$4,Lanç_Terinamentos!$V$8:$V$2008,N$3),2))) -> 0
A15: Variação | C15: =IF(ISERROR(C14-B14),"",C14-B14) -> 0 | D15: =IF(ISERROR(D14-C14),"",D14-C14) -> 0 | E15: =IF(ISERROR(E14-D14),"",E14-D14) -> 0 | F15: =IF(ISERROR(F14-E14),"",F14-E14) -> 0 | G15: =IF(ISERROR(G14-F14),"",G14-F14) -> 0 | H15: =IF(ISERROR(H14-G14),"",H14-G14) -> 0 | I15: =IF(ISERROR(I14-H14),"",I14-H14) -> 0 | J15: =IF(ISERROR(J14-I14),"",J14-I14) -> 0 | ... N15: =IF(ISERROR(N14-M14),"",N14-M14) -> 0
A17: Indicador | B17: ="Dez "&$B$1 -> Dez 2014 | C17: Jan | D17: Fev | E17: Mar | F17: Abr | G17: Mai | H17: Jun | I17: Jul | J17: Ago | K17: Set | L17: Out | M17: Nov | N17: Dez | O17: Total
A18: Receita Bruta | B18: =IF(ISERROR(IF(AND($B$1>=YEAR(TODAY()),MONTH(TODAY())<B$2),"",SUMIFS(Lanç_Receitas!$C$6:$C$33,Lanç_Receitas!$E$6:$E$33,$B$1,Lanç_Receitas!$O$6:$O$33,B$2))),"",IF(AND($B$1>=YEAR(TODAY()),MONTH(TODAY())<B$2),"",SUMIFS(Lanç_Receitas!$C$6:$C$33,Lanç_Receitas!$E$6:$E$33,$B$1,Lanç_Receitas!$O$6:$O$33,B$2))) -> 0 | C18: =IF(ISERROR(IF(AND($C$1>=YEAR(TODAY()),MONTH(TODAY())<C$2),"",SUMIFS(Lanç_Receitas!$C$6:$C$33,Lanç_Receitas!$E$6:$E$33,$C$1,Lanç_Receitas!$O$6:$O$33,C$2))),"",IF(AND($C$1>=YEAR(TODAY()),MONTH(TODAY())<C$2),"",SUMIFS(Lanç_Receitas!$C$6:$C$33,Lanç_Receitas!$E$6:$E$33,$C$1,Lanç_Receitas!$O$6:$O$33,C$2))) -> 0 | D18: =IF(ISERROR(IF(AND($C$1>=YEAR(TODAY()),MONTH(TODAY())<D$2),"",SUMIFS(Lanç_Receitas!$C$6:$C$33,Lanç_Receitas!$E$6:$E$33,$C$1,Lanç_Receitas!$O$6:$O$33,D$2))),"",IF(AND($C$1>=YEAR(TODAY()),MONTH(TODAY())<D$2),"",SUMIFS(Lanç_Receitas!$C$6:$C$33,Lanç_Receitas!$E$6:$E$33,$C$1,Lanç_Receitas!$O$6:$O$33,D$2))) -> 0 | E18: =IF(ISERROR(IF(AND($C$1>=YEAR(TODAY()),MONTH(TODAY())<E$2),"",SUMIFS(Lanç_Receitas!$C$6:$C$33,Lanç_Receitas!$E$6:$E$33,$C$1,Lanç_Receitas!$O$6:$O$33,E$2))),"",IF(AND($C$1>=YEAR(TODAY()),MONTH(TODAY())<E$2),"",SUMIFS(Lanç_Receitas!$C$6:$C$33,Lanç_Receitas!$E$6:$E$33,$C$1,Lanç_Receitas!$O$6:$O$33,E$2))) -> 0 | F18: =IF(ISERROR(IF(AND($C$1>=YEAR(TODAY()),MONTH(TODAY())<F$2),"",SUMIFS(Lanç_Receitas!$C$6:$C$33,Lanç_Receitas!$E$6:$E$33,$C$1,Lanç_Receitas!$O$6:$O$33,F$2))),"",IF(AND($C$1>=YEAR(TODAY()),MONTH(TODAY())<F$2),"",SUMIFS(Lanç_Receitas!$C$6:$C$33,Lanç_Receitas!$E$6:$E$33,$C$1,Lanç_Receitas!$O$6:$O$33,F$2))) -> 0 | G18: =IF(ISERROR(IF(AND($C$1>=YEAR(TODAY()),MONTH(TODAY())<G$2),"",SUMIFS(Lanç_Receitas!$C$6:$C$33,Lanç_Receitas!$E$6:$E$33,$C$1,Lanç_Receitas!$O$6:$O$33,G$2))),"",IF(AND($C$1>=YEAR(TODAY()),MONTH(TODAY())<G$2),"",SUMIFS(Lanç_Receitas!$C$6:$C$33,Lanç_Receitas!$E$6:$E$33,$C$1,Lanç_Receitas!$O$6:$O$33,G$2))) -> 0 | H18: =IF(ISERROR(IF(AND($C$1>=YEAR(TODAY()),MONTH(TODAY())<H$2),"",SUMIFS(Lanç_Receitas!$C$6:$C$33,Lanç_Receitas!$E$6:$E$33,$C$1,Lanç_Receitas!$O$6:$O$33,H$2))),"",IF(AND($C$1>=YEAR(TODAY()),MONTH(TODAY())<H$2),"",SUMIFS(Lanç_Receitas!$C$6:$C$33,Lanç_Receitas!$E$6:$E$33,$C$1,Lanç_Receitas!$O$6:$O$33,H$2))) -> 0 | I18: =IF(ISERROR(IF(AND($C$1>=YEAR(TODAY()),MONTH(TODAY())<I$2),"",SUMIFS(Lanç_Receitas!$C$6:$C$33,Lanç_Receitas!$E$6:$E$33,$C$1,Lanç_Receitas!$O$6:$O$33,I$2))),"",IF(AND($C$1>=YEAR(TODAY()),MONTH(TODAY())<I$2),"",SUMIFS(Lanç_Receitas!$C$6:$C$33,Lanç_Receitas!$E$6:$E$33,$C$1,Lanç_Receitas!$O$6:$O$33,I$2))) -> 0 | J18: =IF(ISERROR(IF(AND($C$1>=YEAR(TODAY()),MONTH(TODAY())<J$2),"",SUMIFS(Lanç_Receitas!$C$6:$C$33,Lanç_Receitas!$E$6:$E$33,$C$1,Lanç_Receitas!$O$6:$O$33,J$2))),"",IF(AND($C$1>=YEAR(TODAY()),MONTH(TODAY())<J$2),"",SUMIFS(Lanç_Receitas!$C$6:$C$33,Lanç_Receitas!$E$6:$E$33,$C$1,Lanç_Receitas!$O$6:$O$33,J$2))) -> 0 | ... N18: =IF(ISERROR(IF(AND($C$1>=YEAR(TODAY()),MONTH(TODAY())<N$2),"",SUMIFS(Lanç_Receitas!$C$6:$C$33,Lanç_Receitas!$E$6:$E$33,$C$1,Lanç_Receitas!$O$6:$O$33,N$2))),"",IF(AND($C$1>=YEAR(TODAY()),MONTH(TODAY())<N$2),"",SUMIFS(Lanç_Receitas!$C$6:$C$33,Lanç_Receitas!$E$6:$E$33,$C$1,Lanç_Receitas!$O$6:$O$33,N$2))) -> 0
A19: Receita média por funcionário | B19: =B18/B26 -> 0 | C19: =C18/C26 -> 0 | D19: =D18/D26 -> 0 | E19: =E18/E26 -> 0 | F19: =IF(ISERROR(F18/F26),"",F18/F26) -> 0 | G19: =IF(ISERROR(G18/G26),"",G18/G26) -> 0 | H19: =IF(ISERROR(H18/H26),"",H18/H26) -> 0 | I19: =IF(ISERROR(I18/I26),"",I18/I26) -> 0 | J19: =IF(ISERROR(J18/J26),"",J18/J26) -> 0 | K19: =IF(ISERROR(K18/K26),"",K18/K26) -> 0 | L19: =IF(ISERROR(L18/L26),"",L18/L26) -> 0 | M19: =IF(ISERROR(M18/M26),"",M18/M26) -> 0 | N19: =IF(ISERROR(N18/N26),"",N18/N26) -> 0
A20: Variação % | C20: =IF(ISERROR(IF(C19="","",C19/B19-1)),1,IF(C19="","",C19/B19-1)) -> 1 | D20: =IF(ISERROR(IF(D19="","",D19/C19-1)),1,IF(D19="","",D19/C19-1)) -> 1 | E20: =IF(ISERROR(IF(E19="","",E19/D19-1)),1,IF(E19="","",E19/D19-1)) -> 1 | F20: =IF(ISERROR(IF(F19="","",F19/E19-1)),1,IF(F19="","",F19/E19-1)) -> 1 | G20: =IF(ISERROR(IF(G19="","",G19/F19-1)),1,IF(G19="","",G19/F19-1)) -> 1 | H20: =IF(ISERROR(IF(H19="","",H19/G19-1)),1,IF(H19="","",H19/G19-1)) -> 1 | I20: =IF(ISERROR(IF(I19="","",I19/H19-1)),1,IF(I19="","",I19/H19-1)) -> 1 | J20: =IF(ISERROR(IF(J19="","",J19/I19-1)),1,IF(J19="","",J19/I19-1)) -> 1 | ... N20: =IF(ISERROR(IF(N19="","",N19/M19-1)),1,IF(N19="","",N19/M19-1)) -> 1
A22: Indicador | B22: ="Dez "&$B$1 -> Dez 2014 | C22: Jan | D22: Fev | E22: Mar | F22: Abr | G22: Mai | H22: Jun | I22: Jul | J22: Ago | K22: Set | L22: Out | M22: Nov | N22: Dez | O22: Total
A23: Admissões | B23: =IF(ISERROR(IF(AND($B$1>=YEAR(TODAY()),MONTH(TODAY())<B$2),"",COUNTIFS(Cad_Func!$W$8:$W$208,$B$1,Cad_Func!$X$8:$X$208,B$2))),"",IF(AND($B$1>=YEAR(TODAY()),MONTH(TODAY())<B$2),"",COUNTIFS(Cad_Func!$W$8:$W$208,$B$1,Cad_Func!$X$8:$X$208,B$2))) -> 1 | C23: =IF(ISERROR(IF(AND($C$1>=YEAR(TODAY()),MONTH(TODAY())<C$2),"",COUNTIFS(Cad_Func!$W$8:$W$208,$C$1,Cad_Func!$X$8:$X$208,C$2))),"",IF(AND($C$1>=YEAR(TODAY()),MONTH(TODAY())<C$2),"",COUNTIFS(Cad_Func!$W$8:$W$208,$C$1,Cad_Func!$X$8:$X$208,C$2))) -> 1 | D23: =IF(ISERROR(IF(AND($C$1>=YEAR(TODAY()),MONTH(TODAY())<D$2),"",COUNTIFS(Cad_Func!$W$8:$W$208,$C$1,Cad_Func!$X$8:$X$208,D$2))),"",IF(AND($C$1>=YEAR(TODAY()),MONTH(TODAY())<D$2),"",COUNTIFS(Cad_Func!$W$8:$W$208,$C$1,Cad_Func!$X$8:$X$208,D$2))) -> 2 | E23: =IF(ISERROR(IF(AND($C$1>=YEAR(TODAY()),MONTH(TODAY())<E$2),"",COUNTIFS(Cad_Func!$W$8:$W$208,$C$1,Cad_Func!$X$8:$X$208,E$2))),"",IF(AND($C$1>=YEAR(TODAY()),MONTH(TODAY())<E$2),"",COUNTIFS(Cad_Func!$W$8:$W$208,$C$1,Cad_Func!$X$8:$X$208,E$2))) -> 0 | F23: =IF(ISERROR(IF(AND($C$1>=YEAR(TODAY()),MONTH(TODAY())<F$2),"",COUNTIFS(Cad_Func!$W$8:$W$208,$C$1,Cad_Func!$X$8:$X$208,F$2))),"",IF(AND($C$1>=YEAR(TODAY()),MONTH(TODAY())<F$2),"",COUNTIFS(Cad_Func!$W$8:$W$208,$C$1,Cad_Func!$X$8:$X$208,F$2))) -> 0 | G23: =IF(ISERROR(IF(AND($C$1>=YEAR(TODAY()),MONTH(TODAY())<G$2),"",COUNTIFS(Cad_Func!$W$8:$W$208,$C$1,Cad_Func!$X$8:$X$208,G$2))),"",IF(AND($C$1>=YEAR(TODAY()),MONTH(TODAY())<G$2),"",COUNTIFS(Cad_Func!$W$8:$W$208,$C$1,Cad_Func!$X$8:$X$208,G$2))) -> 0 | H23: =IF(ISERROR(IF(AND($C$1>=YEAR(TODAY()),MONTH(TODAY())<H$2),"",COUNTIFS(Cad_Func!$W$8:$W$208,$C$1,Cad_Func!$X$8:$X$208,H$2))),"",IF(AND($C$1>=YEAR(TODAY()),MONTH(TODAY())<H$2),"",COUNTIFS(Cad_Func!$W$8:$W$208,$C$1,Cad_Func!$X$8:$X$208,H$2))) -> 0 | I23: =IF(ISERROR(IF(AND($C$1>=YEAR(TODAY()),MONTH(TODAY())<I$2),"",COUNTIFS(Cad_Func!$W$8:$W$208,$C$1,Cad_Func!$X$8:$X$208,I$2))),"",IF(AND($C$1>=YEAR(TODAY()),MONTH(TODAY())<I$2),"",COUNTIFS(Cad_Func!$W$8:$W$208,$C$1,Cad_Func!$X$8:$X$208,I$2))) -> 0 | J23: =IF(ISERROR(IF(AND($C$1>=YEAR(TODAY()),MONTH(TODAY())<J$2),"",COUNTIFS(Cad_Func!$W$8:$W$208,$C$1,Cad_Func!$X$8:$X$208,J$2))),"",IF(AND($C$1>=YEAR(TODAY()),MONTH(TODAY())<J$2),"",COUNTIFS(Cad_Func!$W$8:$W$208,$C$1,Cad_Func!$X$8:$X$208,J$2))) -> 0 | ... N23: =IF(ISERROR(IF(AND($C$1>=YEAR(TODAY()),MONTH(TODAY())<N$2),"",COUNTIFS(Cad_Func!$W$8:$W$208,$C$1,Cad_Func!$X$8:$X$208,N$2))),"",IF(AND($C$1>=YEAR(TODAY()),MONTH(TODAY())<N$2),"",COUNTIFS(Cad_Func!$W$8:$W$208,$C$1,Cad_Func!$X$8:$X$208,N$2))) -> 0
A24: Demissões | B24: =IF(ISERROR(IF(AND($B$1>=YEAR(TODAY()),MONTH(TODAY())<B$2),"",COUNTIFS(Cad_Func!$Y$8:$Y$208,RC_Rotatividade!#REF!,Cad_Func!$Z$8:$Z$208,RC_Rotatividade!E$6))),"",IF(AND($B$1>=YEAR(TODAY()),MONTH(TODAY())<B$2),"",COUNTIFS(Cad_Func!$Y$8:$Y$208,RC_Rotatividade!#REF!,Cad_Func!$Z$8:$Z$208,RC_Rotatividade!E$6))) -> 0 | C24: =IF(ISERROR(IF(AND($C$1>=YEAR(TODAY()),MONTH(TODAY())<C$2),"",COUNTIFS(Cad_Func!$Y$8:$Y$208,RC_Rotatividade!#REF!,Cad_Func!$Z$8:$Z$208,RC_Rotatividade!F$6))),"",IF(AND($C$1>=YEAR(TODAY()),MONTH(TODAY())<C$2),"",COUNTIFS(Cad_Func!$Y$8:$Y$208,RC_Rotatividade!#REF!,Cad_Func!$Z$8:$Z$208,RC_Rotatividade!F$6))) -> 0 | D24: =IF(ISERROR(IF(AND($C$1>=YEAR(TODAY()),MONTH(TODAY())<D$2),"",COUNTIFS(Cad_Func!$Y$8:$Y$208,RC_Rotatividade!#REF!,Cad_Func!$Z$8:$Z$208,RC_Rotatividade!G$6))),"",IF(AND($C$1>=YEAR(TODAY()),MONTH(TODAY())<D$2),"",COUNTIFS(Cad_Func!$Y$8:$Y$208,RC_Rotatividade!#REF!,Cad_Func!$Z$8:$Z$208,RC_Rotatividade!G$6))) -> 0 | E24: =IF(ISERROR(IF(AND($C$1>=YEAR(TODAY()),MONTH(TODAY())<E$2),"",COUNTIFS(Cad_Func!$Y$8:$Y$208,RC_Rotatividade!#REF!,Cad_Func!$Z$8:$Z$208,RC_Rotatividade!H$6))),"",IF(AND($C$1>=YEAR(TODAY()),MONTH(TODAY())<E$2),"",COUNTIFS(Cad_Func!$Y$8:$Y$208,RC_Rotatividade!#REF!,Cad_Func!$Z$8:$Z$208,RC_Rotatividade!H$6))) -> 0 | F24: =IF(ISERROR(IF(AND($C$1>=YEAR(TODAY()),MONTH(TODAY())<F$2),"",COUNTIFS(Cad_Func!$Y$8:$Y$208,RC_Rotatividade!#REF!,Cad_Func!$Z$8:$Z$208,RC_Rotatividade!I$6))),"",IF(AND($C$1>=YEAR(TODAY()),MONTH(TODAY())<F$2),"",COUNTIFS(Cad_Func!$Y$8:$Y$208,RC_Rotatividade!#REF!,Cad_Func!$Z$8:$Z$208,RC_Rotatividade!I$6))) -> 0 | G24: =IF(ISERROR(IF(AND($C$1>=YEAR(TODAY()),MONTH(TODAY())<G$2),"",COUNTIFS(Cad_Func!$Y$8:$Y$208,RC_Rotatividade!#REF!,Cad_Func!$Z$8:$Z$208,RC_Rotatividade!J$6))),"",IF(AND($C$1>=YEAR(TODAY()),MONTH(TODAY())<G$2),"",COUNTIFS(Cad_Func!$Y$8:$Y$208,RC_Rotatividade!#REF!,Cad_Func!$Z$8:$Z$208,RC_Rotatividade!J$6))) -> 0 | H24: =IF(ISERROR(IF(AND($C$1>=YEAR(TODAY()),MONTH(TODAY())<H$2),"",COUNTIFS(Cad_Func!$Y$8:$Y$208,RC_Rotatividade!#REF!,Cad_Func!$Z$8:$Z$208,RC_Rotatividade!K$6))),"",IF(AND($C$1>=YEAR(TODAY()),MONTH(TODAY())<H$2),"",COUNTIFS(Cad_Func!$Y$8:$Y$208,RC_Rotatividade!#REF!,Cad_Func!$Z$8:$Z$208,RC_Rotatividade!K$6))) -> 0 | I24: =IF(ISERROR(IF(AND($C$1>=YEAR(TODAY()),MONTH(TODAY())<I$2),"",COUNTIFS(Cad_Func!$Y$8:$Y$208,RC_Rotatividade!#REF!,Cad_Func!$Z$8:$Z$208,RC_Rotatividade!L$6))),"",IF(AND($C$1>=YEAR(TODAY()),MONTH(TODAY())<I$2),"",COUNTIFS(Cad_Func!$Y$8:$Y$208,RC_Rotatividade!#REF!,Cad_Func!$Z$8:$Z$208,RC_Rotatividade!L$6))) -> 0 | J24: =IF(ISERROR(IF(AND($C$1>=YEAR(TODAY()),MONTH(TODAY())<J$2),"",COUNTIFS(Cad_Func!$Y$8:$Y$208,RC_Rotatividade!#REF!,Cad_Func!$Z$8:$Z$208,RC_Rotatividade!M$6))),"",IF(AND($C$1>=YEAR(TODAY()),MONTH(TODAY())<J$2),"",COUNTIFS(Cad_Func!$Y$8:$Y$208,RC_Rotatividade!#REF!,Cad_Func!$Z$8:$Z$208,RC_Rotatividade!M$6))) -> 0 | ... N24: =IF(ISERROR(IF(AND($C$1>=YEAR(TODAY()),MONTH(TODAY())<N$2),"",COUNTIFS(Cad_Func!$Y$8:$Y$208,RC_Rotatividade!#REF!,Cad_Func!$Z$8:$Z$208,RC_Rotatividade!Q$6))),"",IF(AND($C$1>=YEAR(TODAY()),MONTH(TODAY())<N$2),"",COUNTIFS(Cad_Func!$Y$8:$Y$208,RC_Rotatividade!#REF!,Cad_Func!$Z$8:$Z$208,RC_Rotatividade!Q$6))) -> 0
A25: Funcionários no início do mês | C25: =IF(ISERROR(IF(AND($C$1>=YEAR(TODAY()),MONTH(TODAY())<C$2),"",B26)),"",IF(AND($C$1>=YEAR(TODAY()),MONTH(TODAY())<C$2),"",B26)) -> 9 | D25: =IF(ISERROR(IF(AND($C$1>=YEAR(TODAY()),MONTH(TODAY())<D$2),"",C26)),"",IF(AND($C$1>=YEAR(TODAY()),MONTH(TODAY())<D$2),"",C26)) -> 10 | E25: =IF(ISERROR(IF(AND($C$1>=YEAR(TODAY()),MONTH(TODAY())<E$2),"",D26)),"",IF(AND($C$1>=YEAR(TODAY()),MONTH(TODAY())<E$2),"",D26)) -> 12 | F25: =IF(ISERROR(IF(AND($C$1>=YEAR(TODAY()),MONTH(TODAY())<F$2),"",E26)),"",IF(AND($C$1>=YEAR(TODAY()),MONTH(TODAY())<F$2),"",E26)) -> 12 | G25: =IF(ISERROR(IF(AND($C$1>=YEAR(TODAY()),MONTH(TODAY())<G$2),"",F26)),"",IF(AND($C$1>=YEAR(TODAY()),MONTH(TODAY())<G$2),"",F26)) -> 12 | H25: =IF(ISERROR(IF(AND($C$1>=YEAR(TODAY()),MONTH(TODAY())<H$2),"",G26)),"",IF(AND($C$1>=YEAR(TODAY()),MONTH(TODAY())<H$2),"",G26)) -> 12 | I25: =IF(ISERROR(IF(AND($C$1>=YEAR(TODAY()),MONTH(TODAY())<I$2),"",H26)),"",IF(AND($C$1>=YEAR(TODAY()),MONTH(TODAY())<I$2),"",H26)) -> 12 | J25: =IF(ISERROR(IF(AND($C$1>=YEAR(TODAY()),MONTH(TODAY())<J$2),"",I26)),"",IF(AND($C$1>=YEAR(TODAY()),MONTH(TODAY())<J$2),"",I26)) -> 12 | ... N25: =IF(ISERROR(IF(AND($C$1>=YEAR(TODAY()),MONTH(TODAY())<N$2),"",M26)),"",IF(AND($C$1>=YEAR(TODAY()),MONTH(TODAY())<N$2),"",M26)) -> 12
A26: Funcionários no fim do mês | B26: =IF(ISERROR(SUM(Cad_Func!$Q$8:$Q$208)),"",SUM(Cad_Func!$Q$8:$Q$208)) -> 9 | C26: =IF(ISERROR(C25+C23-C24),"",C25+C23-C24) -> 10 | D26: =IF(ISERROR(D25+D23-D24),"",D25+D23-D24) -> 12 | E26: =IF(ISERROR(E25+E23-E24),"",E25+E23-E24) -> 12 | F26: =IF(ISERROR(F25+F23-F24),"",F25+F23-F24) -> 12 | G26: =IF(ISERROR(G25+G23-G24),"",G25+G23-G24) -> 12 | H26: =IF(ISERROR(H25+H23-H24),"",H25+H23-H24) -> 12 | I26: =IF(ISERROR(I25+I23-I24),"",I25+I23-I24) -> 12 | J26: =IF(ISERROR(J25+J23-J24),"",J25+J23-J24) -> 12 | ... N26: =IF(ISERROR(N25+N23-N24),"",N25+N23-N24) -> 12

Sheet RI
C1: 6. RELATÓRIO PARA IMPRESSÃO
C6: RELATÓRIO IMPRESSO
C7: PLANILHA DE INDICADORES DE RH 3.0
C9: =Cad_Inicial!D7&" - "&Cad_Inicial!D8 -> LUZ Planilhas Empresariais - 2015
C11: 1. Geral
C12: 2. Rotatividade
C13: 3. Perfil da equipe
C14: 4. Eventos de RH
C15: 5. Receitas e Custos
C16: 6. Gráficos
C17: 7. Alertas e dicas
C19: 1. Geral
C20: ='RC'!C6:E6 -> Indicadores de rotatividade para 2015 | F20: Resultado
C21: Média de permanência de funcionários na empresa | F21: ='RC'!F7 -> 86 meses
C22: ='RC'!C8:E8 -> Admissões em 2015 | F22: ='RC'!F8 -> 3
C23: ='RC'!C9:E9 -> Demissões em 2015 | F23: ='RC'!F9 -> 1
C24: ='RC'!C10:E10 -> Total de funcionários em 2015 | F24: ='RC'!F10 -> 11
C25: Índice de aprovação após período de experiência | F25: ='RC'!F11 -> 1
C26: Índice de Turnover (rotatividade) | F26: ='RC'!F12 -> 0.18181818
C28: ='RC'!C14:E14 -> Indicadores de treinamento para 2015 | F28: Resultado
C29: Total de horas de treinamento | F29: ='RC'!F15 -> 140 horas
C30: Média de horas de treinamento por funcionário treinado | F30: ='RC'!F16 -> 18 horas
C31: Número de funcionários treinados | F31: ='RC'!F17 -> 8 funcionários
C33: ='RC'!C19:E19 -> Custos para 2015 | F33: Resultado
C34: Custo total com hora extra | F34: ='RC'!F20 -> 3012
C35: Custo total com folha de pagamento (benefícios + custos) | F35: ='RC'!F21 -> 315142
C36: % do custo total de treinamentos sobre o total da folha de pagamento | F36: ='RC'!F22 -> 0
C37: Custo médio por funcionário treinado | F37: ='RC'!F23 -> 0
C38: % dos benefícios sobre a folha de pagamento | F38: ='RC'!F24 -> 0.066655666
C39: Custo dos benefícios sobre a folha de pagamento | F39: ='RC'!F25 -> 21006
C40: Custo médio dos benefícios para cada funcionário | F40: ='RC'!F26 -> 1909.6364
C41: Receita gerada por cada funcionário | F41: ='RC'!F27 -> 163636.91
C42: Custo gerado por cada funcionário | F42: ='RC'!F28 -> 26739.636
C44: 2. Rotatividade
C45: =RC_Rotatividade!C7 -> Resumo de indicadores de rotatividade (mensal) para 2015
C46: Indicador | E46: Jan | F46: Fev | G46: Mar | H46: Abr | I46: Mai | L46: Jun | M46: Jul | N46: Ago | O46: Set | P46: Out | Q46: Nov | S46: Dez | T46: Média | U46: Total
C47: Número de novas contratações | E47: =RC_Rotatividade!E9 -> 1 | F47: =RC_Rotatividade!F9 -> 2 | G47: =RC_Rotatividade!G9 -> 0 | H47: =RC_Rotatividade!H9 -> 0 | I47: =RC_Rotatividade!I9 -> 0 | L47: =RC_Rotatividade!J9 -> 0 | M47: =RC_Rotatividade!K9 -> 0 | N47: =RC_Rotatividade!L9 -> 0 | O47: =RC_Rotatividade!M9 -> 0 | P47: =RC_Rotatividade!N9 -> 0 | Q47: =RC_Rotatividade!O9 -> 0 | S47: =RC_Rotatividade!P9 -> 0 | T47: =RC_Rotatividade!Q9 -> 0.25 | U47: =RC_Rotatividade!R9 -> 3
C48: Total de desligamentos | E48: =RC_Rotatividade!E10 -> 0 | F48: =RC_Rotatividade!F10 -> 0 | G48: =RC_Rotatividade!G10 -> 1 | H48: =RC_Rotatividade!H10 -> 0 | I48: =RC_Rotatividade!I10 -> 0 | L48: =RC_Rotatividade!J10 -> 0 | M48: =RC_Rotatividade!K10 -> 0 | N48: =RC_Rotatividade!L10 -> 0 | O48: =RC_Rotatividade!M10 -> 0 | P48: =RC_Rotatividade!N10 -> 0 | Q48: =RC_Rotatividade!O10 -> 0 | S48: =RC_Rotatividade!P10 -> 0 | T48: =RC_Rotatividade!Q10 -> 0.08 | U48: =RC_Rotatividade!R10 -> 1
C49: Variação do número de funcionários | E49: =RC_Rotatividade!E11 -> 1 | F49: =RC_Rotatividade!F11 -> 2 | G49: =RC_Rotatividade!G11 -> -1 | H49: =RC_Rotatividade!H11 -> 0 | I49: =RC_Rotatividade!I11 -> 0 | L49: =RC_Rotatividade!J11 -> 0 | M49: =RC_Rotatividade!K11 -> 0 | N49: =RC_Rotatividade!L11 -> 0 | O49: =RC_Rotatividade!M11 -> 0 | P49: =RC_Rotatividade!N11 -> 0 | Q49: =RC_Rotatividade!O11 -> 0 | S49: =RC_Rotatividade!P11 -> 0 | T49: =RC_Rotatividade!Q11 -> 0.17 | U49: =RC_Rotatividade!R11 -> 0
C50: Número de funcionários no início do mês | E50: =RC_Rotatividade!E12 -> 9 | F50: =RC_Rotatividade!F12 -> 10 | G50: =RC_Rotatividade!G12 -> 12 | H50: =RC_Rotatividade!H12 -> 11 | I50: =RC_Rotatividade!I12 -> 11 | L50: =RC_Rotatividade!J12 -> 11 | M50: =RC_Rotatividade!K12 -> 11 | N50: =RC_Rotatividade!L12 -> 11 | O50: =RC_Rotatividade!M12 -> 11 | P50: =RC_Rotatividade!N12 -> 11 | Q50: =RC_Rotatividade!O12 -> 11 | S50: =RC_Rotatividade!P12 -> 11 | T50: =RC_Rotatividade!Q12 -> 10.83 | U50: =RC_Rotatividade!R12 -> 11
C51: Número de funcionários no final do mês | E51: =RC_Rotatividade!E13 -> 10 | F51: =RC_Rotatividade!F13 -> 12 | G51: =RC_Rotatividade!G13 -> 11 | H51: =RC_Rotatividade!H13 -> 11 | I51: =RC_Rotatividade!I13 -> 11 | L51: =RC_Rotatividade!J13 -> 11 | M51: =RC_Rotatividade!K13 -> 11 | N51: =RC_Rotatividade!L13 -> 11 | O51: =RC_Rotatividade!M13 -> 11 | P51: =RC_Rotatividade!N13 -> 11 | Q51: =RC_Rotatividade!O13 -> 11 | S51: =RC_Rotatividade!P13 -> 11 | T51: =RC_Rotatividade!Q13 -> 11 | U51: =RC_Rotatividade!R13 -> 11
C52: Taxa de Turnover | E52: =RC_Rotatividade!E14 -> 0.05 | F52: =RC_Rotatividade!F14 -> 0.083333333 | G52: =RC_Rotatividade!G14 -> 0.045454545 | H52: =RC_Rotatividade!H14 -> 0 | I52: =RC_Rotatividade!I14 -> 0 | L52: =RC_Rotatividade!J14 -> 0 | M52: =RC_Rotatividade!K14 -> 0 | N52: =RC_Rotatividade!L14 -> 0 | O52: =RC_Rotatividade!M14 -> 0 | P52: =RC_Rotatividade!N14 -> 0 | Q52: =RC_Rotatividade!O14 -> 0 | S52: =RC_Rotatividade!P14 -> 0 | T52: =RC_Rotatividade!Q14 -> 0.015 | U52: =RC_Rotatividade!R14 -> 0.18181818
C53: =RC_Rotatividade!C15 -> Detalhamento dos indicadores de rotatividade (mensal) para 2015
C54: =RC_Rotatividade!C16 -> Pedido de demissão | E54: =RC_Rotatividade!E16 -> 0 | F54: =RC_Rotatividade!F16 -> 0 | G54: =RC_Rotatividade!G16 -> 1 | H54: =RC_Rotatividade!H16 -> 0 | I54: =RC_Rotatividade!I16 -> 0 | L54: =RC_Rotatividade!J16 -> 0 | M54: =RC_Rotatividade!K16 -> 0 | N54: =RC_Rotatividade!L16 -> 0 | O54: =RC_Rotatividade!M16 -> 0 | P54: =RC_Rotatividade!N16 -> 0 | Q54: =RC_Rotatividade!O16 -> 0 | S54: =RC_Rotatividade!P16 -> 0 | T54: =RC_Rotatividade!Q16 -> 0.08 | U54: =RC_Rotatividade!R16 -> 1
C55: =RC_Rotatividade!C17 -> Dispensa sem justa causa | E55: =RC_Rotatividade!E17 -> 0 | F55: =RC_Rotatividade!F17 -> 0 | G55: =RC_Rotatividade!G17 -> 0 | H55: =RC_Rotatividade!H17 -> 0 | I55: =RC_Rotatividade!I17 -> 0 | L55: =RC_Rotatividade!J17 -> 0 | M55: =RC_Rotatividade!K17 -> 0 | N55: =RC_Rotatividade!L17 -> 0 | O55: =RC_Rotatividade!M17 -> 0 | P55: =RC_Rotatividade!N17 -> 0 | Q55: =RC_Rotatividade!O17 -> 0 | S55: =RC_Rotatividade!P17 -> 0 | T55: =RC_Rotatividade!Q17 -> 0 | U55: =RC_Rotatividade!R17 -> 0
C56: =RC_Rotatividade!C18 -> Dispensa com justa causa | E56: =RC_Rotatividade!E18 -> 0 | F56: =RC_Rotatividade!F18 -> 0 | G56: =RC_Rotatividade!G18 -> 0 | H56: =RC_Rotatividade!H18 -> 0 | I56: =RC_Rotatividade!I18 -> 0 | L56: =RC_Rotatividade!J18 -> 0 | M56: =RC_Rotatividade!K18 -> 0 | N56: =RC_Rotatividade!L18 -> 0 | O56: =RC_Rotatividade!M18 -> 0 | P56: =RC_Rotatividade!N18 -> 0 | Q56: =RC_Rotatividade!O18 -> 0 | S56: =RC_Rotatividade!P18 -> 0 | T56: =RC_Rotatividade!Q18 -> 0 | U56: =RC_Rotatividade!R18 -> 0
C57: =RC_Rotatividade!C19 -> Término de contrato de experiência | E57: =RC_Rotatividade!E19 -> 0 | F57: =RC_Rotatividade!F19 -> 0 | G57: =RC_Rotatividade!G19 -> 0 | H57: =RC_Rotatividade!H19 -> 0 | I57: =RC_Rotatividade!I19 -> 0 | L57: =RC_Rotatividade!J19 -> 0 | M57: =RC_Rotatividade!K19 -> 0 | N57: =RC_Rotatividade!L19 -> 0 | O57: =RC_Rotatividade!M19 -> 0 | P57: =RC_Rotatividade!N19 -> 0 | Q57: =RC_Rotatividade!O19 -> 0 | S57: =RC_Rotatividade!P19 -> 0 | T57: =RC_Rotatividade!Q19 -> 0 | U57: =RC_Rotatividade!R19 -> 0
C58: =RC_Rotatividade!C20 -> Rescisão antecipada do contrato de experiência por iniciativa do empregador | E58: =RC_Rotatividade!E20 -> 0 | F58: =RC_Rotatividade!F20 -> 0 | G58: =RC_Rotatividade!G20 -> 0 | H58: =RC_Rotatividade!H20 -> 0 | I58: =RC_Rotatividade!I20 -> 0 | L58: =RC_Rotatividade!J20 -> 0 | M58: =RC_Rotatividade!K20 -> 0 | N58: =RC_Rotatividade!L20 -> 0 | O58: =RC_Rotatividade!M20 -> 0 | P58: =RC_Rotatividade!N20 -> 0 | Q58: =RC_Rotatividade!O20 -> 0 | S58: =RC_Rotatividade!P20 -> 0 | T58: =RC_Rotatividade!Q20 -> 0 | U58: =RC_Rotatividade!R20 -> 0
C59: =RC_Rotatividade!C21 -> Rescisão antecipada do contrato de experiência por iniciativa do empregado | E59: =RC_Rotatividade!E21 -> 0 | F59: =RC_Rotatividade!F21 -> 0 | G59: =RC_Rotatividade!G21 -> 0 | H59: =RC_Rotatividade!H21 -> 0 | I59: =RC_Rotatividade!I21 -> 0 | L59: =RC_Rotatividade!J21 -> 0 | M59: =RC_Rotatividade!K21 -> 0 | N59: =RC_Rotatividade!L21 -> 0 | O59: =RC_Rotatividade!M21 -> 0 | P59: =RC_Rotatividade!N21 -> 0 | Q59: =RC_Rotatividade!O21 -> 0 | S59: =RC_Rotatividade!P21 -> 0 | T59: =RC_Rotatividade!Q21 -> 0 | U59: =RC_Rotatividade!R21 -> 0
C60: =RC_Rotatividade!C22 -> Falecimento do empregado | E60: =RC_Rotatividade!E22 -> 0 | F60: =RC_Rotatividade!F22 -> 0 | G60: =RC_Rotatividade!G22 -> 0 | H60: =RC_Rotatividade!H22 -> 0 | I60: =RC_Rotatividade!I22 -> 0 | L60: =RC_Rotatividade!J22 -> 0 | M60: =RC_Rotatividade!K22 -> 0 | N60: =RC_Rotatividade!L22 -> 0 | O60: =RC_Rotatividade!M22 -> 0 | P60: =RC_Rotatividade!N22 -> 0 | Q60: =RC_Rotatividade!O22 -> 0 | S60: =RC_Rotatividade!P22 -> 0 | T60: =RC_Rotatividade!Q22 -> 0 | U60: =RC_Rotatividade!R22 -> 0
C61: =RC_Rotatividade!C23 -> Outro | E61: =RC_Rotatividade!E23 -> 0 | F61: =RC_Rotatividade!F23 -> 0 | G61: =RC_Rotatividade!G23 -> 0 | H61: =RC_Rotatividade!H23 -> 0 | I61: =RC_Rotatividade!I23 -> 0 | L61: =RC_Rotatividade!J23 -> 0 | M61: =RC_Rotatividade!K23 -> 0 | N61: =RC_Rotatividade!L23 -> 0 | O61: =RC_Rotatividade!M23 -> 0 | P61: =RC_Rotatividade!N23 -> 0 | Q61: =RC_Rotatividade!O23 -> 0 | S61: =RC_Rotatividade!P23 -> 0 | T61: =RC_Rotatividade!Q23 -> 0 | U61: =RC_Rotatividade!R23 -> 0
C63: 3. Perfil da equipe
C64: =RC_Perfil!C8 -> Detalhamento dos indicadores de equipe (mensal) para 2015
C65: Indicador | E65: Jan | F65: Fev | G65: Mar | H65: Abr | I65: Mai | L65: Jun | M65: Jul | N65: Ago | O65: Set | P65: Out | Q65: Nov | S65: Dez | T65: Média | U65: Total
C66: =RC_Perfil!C10 -> Escolaridade (mensal) para 2015
C67: =RC_Perfil!C11 -> Ensino fundamental | E67: =RC_Perfil!E11 -> 2 | F67: =RC_Perfil!F11 -> 2 | G67: =RC_Perfil!G11 -> 1 | H67: =RC_Perfil!H11 -> 1 | I67: =RC_Perfil!I11 -> 1 | L67: =RC_Perfil!J11 -> 1 | M67: =RC_Perfil!K11 -> 1 | N67: =RC_Perfil!L11 -> 1 | O67: =RC_Perfil!M11 -> 1 | P67: =RC_Perfil!N11 -> 1 | Q67: =RC_Perfil!O11 -> 1 | S67: =RC_Perfil!P11 -> 1 | T67: =RC_Perfil!Q11 -> 1.17 | U67: =RC_Perfil!R11 -> 1
C68: =RC_Perfil!C12 -> Ensino médio | E68: =RC_Perfil!E12 -> 0 | F68: =RC_Perfil!F12 -> 0 | G68: =RC_Perfil!G12 -> 0 | H68: =RC_Perfil!H12 -> 0 | I68: =RC_Perfil!I12 -> 0 | L68: =RC_Perfil!J12 -> 0 | M68: =RC_Perfil!K12 -> 0 | N68: =RC_Perfil!L12 -> 0 | O68: =RC_Perfil!M12 -> 0 | P68: =RC_Perfil!N12 -> 0 | Q68: =RC_Perfil!O12 -> 0 | S68: =RC_Perfil!P12 -> 0 | T68: =RC_Perfil!Q12 -> 0 | U68: =RC_Perfil!R12 -> 0
C69: =RC_Perfil!C13 -> Superior completo | E69: =RC_Perfil!E13 -> 4 | F69: =RC_Perfil!F13 -> 6 | G69: =RC_Perfil!G13 -> 6 | H69: =RC_Perfil!H13 -> 6 | I69: =RC_Perfil!I13 -> 6 | L69: =RC_Perfil!J13 -> 6 | M69: =RC_Perfil!K13 -> 6 | N69: =RC_Perfil!L13 -> 6 | O69: =RC_Perfil!M13 -> 6 | P69: =RC_Perfil!N13 -> 6 | Q69: =RC_Perfil!O13 -> 6 | S69: =RC_Perfil!P13 -> 6 | T69: =RC_Perfil!Q13 -> 5.83 | U69: =RC_Perfil!R13 -> 6
C70: =RC_Perfil!C14 -> Superior incompleto | E70: =RC_Perfil!E14 -> 2 | F70: =RC_Perfil!F14 -> 2 | G70: =RC_Perfil!G14 -> 2 | H70: =RC_Perfil!H14 -> 2 | I70: =RC_Perfil!I14 -> 2 | L70: =RC_Perfil!J14 -> 2 | M70: =RC_Perfil!K14 -> 2 | N70: =RC_Perfil!L14 -> 2 | O70: =RC_Perfil!M14 -> 2 | P70: =RC_Perfil!N14 -> 2 | Q70: =RC_Perfil!O14 -> 2 | S70: =RC_Perfil!P14 -> 2 | T70: =RC_Perfil!Q14 -> 2 | U70: =RC_Perfil!R14 -> 2
C71: =RC_Perfil!C15 -> Pós-graduação completa | E71: =RC_Perfil!E15 -> 2 | F71: =RC_Perfil!F15 -> 2 | G71: =RC_Perfil!G15 -> 2 | H71: =RC_Perfil!H15 -> 2 | I71: =RC_Perfil!I15 -> 2 | L71: =RC_Perfil!J15 -> 2 | M71: =RC_Perfil!K15 -> 2 | N71: =RC_Perfil!L15 -> 2 | O71: =RC_Perfil!M15 -> 2 | P71: =RC_Perfil!N15 -> 2 | Q71: =RC_Perfil!O15 -> 2 | S71: =RC_Perfil!P15 -> 2 | T71: =RC_Perfil!Q15 -> 2 | U71: =RC_Perfil!R15 -> 2
C72: =RC_Perfil!C16 -> Pós-graduação incompleta | E72: =RC_Perfil!E16 -> 0 | F72: =RC_Perfil!F16 -> 0 | G72: =RC_Perfil!G16 -> 0 | H72: =RC_Perfil!H16 -> 0 | I72: =RC_Perfil!I16 -> 0 | L72: =RC_Perfil!J16 -> 0 | M72: =RC_Perfil!K16 -> 0 | N72: =RC_Perfil!L16 -> 0 | O72: =RC_Perfil!M16 -> 0 | P72: =RC_Perfil!N16 -> 0 | Q72: =RC_Perfil!O16 -> 0 | S72: =RC_Perfil!P16 -> 0 | T72: =RC_Perfil!Q16 -> 0 | U72: =RC_Perfil!R16 -> 0
C73: =RC_Perfil!C17 -> Mestre | E73: =RC_Perfil!E17 -> 0 | F73: =RC_Perfil!F17 -> 0 | G73: =RC_Perfil!G17 -> 0 | H73: =RC_Perfil!H17 -> 0 | I73: =RC_Perfil!I17 -> 0 | L73: =RC_Perfil!J17 -> 0 | M73: =RC_Perfil!K17 -> 0 | N73: =RC_Perfil!L17 -> 0 | O73: =RC_Perfil!M17 -> 0 | P73: =RC_Perfil!N17 -> 0 | Q73: =RC_Perfil!O17 -> 0 | S73: =RC_Perfil!P17 -> 0 | T73: =RC_Perfil!Q17 -> 0 | U73: =RC_Perfil!R17 -> 0
C74: =RC_Perfil!C18 -> Doutor | E74: =RC_Perfil!E18 -> 0 | F74: =RC_Perfil!F18 -> 0 | G74: =RC_Perfil!G18 -> 0 | H74: =RC_Perfil!H18 -> 0 | I74: =RC_Perfil!I18 -> 0 | L74: =RC_Perfil!J18 -> 0 | M74: =RC_Perfil!K18 -> 0 | N74: =RC_Perfil!L18 -> 0 | O74: =RC_Perfil!M18 -> 0 | P74: =RC_Perfil!N18 -> 0 | Q74: =RC_Perfil!O18 -> 0 | S74: =RC_Perfil!P18 -> 0 | T74: =RC_Perfil!Q18 -> 0 | U74: =RC_Perfil!R18 -> 0
C75: =RC_Perfil!C19 -> Tipo de Cargo (mensal) para 2015
C76: Operacional | E76: =RC_Perfil!E20 -> 6 | F76: =RC_Perfil!F20 -> 7 | G76: =RC_Perfil!G20 -> 6 | H76: =RC_Perfil!H20 -> 6 | I76: =RC_Perfil!I20 -> 6 | L76: =RC_Perfil!J20 -> 6 | M76: =RC_Perfil!K20 -> 6 | N76: =RC_Perfil!L20 -> 6 | O76: =RC_Perfil!M20 -> 6 | P76: =RC_Perfil!N20 -> 6 | Q76: =RC_Perfil!O20 -> 6 | S76: =RC_Perfil!P20 -> 6 | T76: =RC_Perfil!Q20 -> 6.08 | U76: =RC_Perfil!R20 -> 6
C77: Gerencial | E77: =RC_Perfil!E21 -> 1 | F77: =RC_Perfil!F21 -> 1 | G77: =RC_Perfil!G21 -> 1 | H77: =RC_Perfil!H21 -> 1 | I77: =RC_Perfil!I21 -> 1 | L77: =RC_Perfil!J21 -> 1 | M77: =RC_Perfil!K21 -> 1 | N77: =RC_Perfil!L21 -> 1 | O77: =RC_Perfil!M21 -> 1 | P77: =RC_Perfil!N21 -> 1 | Q77: =RC_Perfil!O21 -> 1 | S77: =RC_Perfil!P21 -> 1 | T77: =RC_Perfil!Q21 -> 1 | U77: =RC_Perfil!R21 -> 1
C78: Diretoria | E78: =RC_Perfil!E22 -> 3 | F78: =RC_Perfil!F22 -> 4 | G78: =RC_Perfil!G22 -> 4 | H78: =RC_Perfil!H22 -> 4 | I78: =RC_Perfil!I22 -> 4 | L78: =RC_Perfil!J22 -> 4 | M78: =RC_Perfil!K22 -> 4 | N78: =RC_Perfil!L22 -> 4 | O78: =RC_Perfil!M22 -> 4 | P78: =RC_Perfil!N22 -> 4 | Q78: =RC_Perfil!O22 -> 4 | S78: =RC_Perfil!P22 -> 4 | T78: =RC_Perfil!Q22 -> 3.92 | U78: =RC_Perfil!R22 -> 4
C79: =RC_Perfil!C23 -> Sexo (mensal) para 2015
C80: Masculino | E80: =RC_Perfil!E24 -> 7 | F80: =RC_Perfil!F24 -> 8 | G80: =RC_Perfil!G24 -> 7 | H80: =RC_Perfil!H24 -> 7 | I80: =RC_Perfil!I24 -> 7 | L80: =RC_Perfil!J24 -> 7 | M80: =RC_Perfil!K24 -> 7 | N80: =RC_Perfil!L24 -> 7 | O80: =RC_Perfil!M24 -> 7 | P80: =RC_Perfil!N24 -> 7 | Q80: =RC_Perfil!O24 -> 7 | S80: =RC_Perfil!P24 -> 7 | T80: =RC_Perfil!Q24 -> 7.08 | U80: =RC_Perfil!R24 -> 7
C81: Feminino | E81: =RC_Perfil!E25 -> 3 | F81: =RC_Perfil!F25 -> 4 | G81: =RC_Perfil!G25 -> 4 | H81: =RC_Perfil!H25 -> 4 | I81: =RC_Perfil!I25 -> 4 | L81: =RC_Perfil!J25 -> 4 | M81: =RC_Perfil!K25 -> 4 | N81: =RC_Perfil!L25 -> 4 | O81: =RC_Perfil!M25 -> 4 | P81: =RC_Perfil!N25 -> 4 | Q81: =RC_Perfil!O25 -> 4 | S81: =RC_Perfil!P25 -> 4 | T81: =RC_Perfil!Q25 -> 3.92 | U81: =RC_Perfil!R25 -> 4
C83: 4. Eventos de RH
C84: =RC_Eventos!C9 -> Detalhamento dos eventos de RH (mensal) para 2015
C85: Indicador | E85: Jan | F85: Fev | G85: Mar | H85: Abr | I85: Mai | L85: Jun | M85: Jul | N85: Ago | O85: Set | P85: Out | Q85: Nov | S85: Dez | T85: Média | U85: Total
C86: =RC_Eventos!C11 -> Treinamentos (mensal) para 2015
C87: Treinamentos em andamento | E87: =RC_Eventos!E12 -> 0 | F87: =RC_Eventos!F12 -> 1 | G87: =RC_Eventos!G12 -> 3 | H87: =RC_Eventos!H12 -> 2 | I87: =RC_Eventos!I12 -> 0 | L87: =RC_Eventos!J12 -> 0 | M87: =RC_Eventos!K12 -> 0 | N87: =RC_Eventos!L12 -> 0 | O87: =RC_Eventos!M12 -> 0 | P87: =RC_Eventos!N12 -> 0 | Q87: =RC_Eventos!O12 -> 0 | S87: =RC_Eventos!P12 -> 0 | T87: =RC_Eventos!Q12 -> 0.5 | U87: =RC_Eventos!R12 -> 3
C88: Funcionários em treinamento | E88: =RC_Eventos!E13 -> 0 | F88: =RC_Eventos!F13 -> 3 | G88: =RC_Eventos!G13 -> 8 | H88: =RC_Eventos!H13 -> 5 | I88: =RC_Eventos!I13 -> 0 | L88: =RC_Eventos!J13 -> 0 | M88: =RC_Eventos!K13 -> 0 | N88: =RC_Eventos!L13 -> 0 | O88: =RC_Eventos!M13 -> 0 | P88: =RC_Eventos!N13 -> 0 | Q88: =RC_Eventos!O13 -> 0 | S88: =RC_Eventos!P13 -> 0 | T88: =RC_Eventos!Q13 -> 1.33 | U88: =RC_Eventos!R13 -> 8
C89: Custo total com treinamentos | E89: =RC_Eventos!E14 -> 900 | F89: =RC_Eventos!F14 -> 501 | G89: =RC_Eventos!G14 -> 600 | H89: =RC_Eventos!H14 -> 400 | I89: =RC_Eventos!I14 -> 100 | L89: =RC_Eventos!J14 -> 0 | M89: =RC_Eventos!K14 -> 0 | N89: =RC_Eventos!L14 -> 0 | O89: =RC_Eventos!M14 -> 0 | P89: =RC_Eventos!N14 -> 0 | Q89: =RC_Eventos!O14 -> 0 | S89: =RC_Eventos!P14 -> 0 | T89: =RC_Eventos!Q14 -> 208.42 | U89: =RC_Eventos!R14 -> 2501
C90: Horas totais da equipe em treinamento | E90: =RC_Eventos!E15 -> 0 | F90: =RC_Eventos!F15 -> 20 | G90: =RC_Eventos!G15 -> 140 | H90: =RC_Eventos!H15 -> 120 | I90: =RC_Eventos!I15 -> 0 | L90: =RC_Eventos!J15 -> 0 | M90: =RC_Eventos!K15 -> 0 | N90: =RC_Eventos!L15 -> 0 | O90: =RC_Eventos!M15 -> 0 | P90: =RC_Eventos!N15 -> 0 | Q90: =RC_Eventos!O15 -> 0 | S90: =RC_Eventos!P15 -> 0 | T90: =RC_Eventos!Q15 -> 23.33 | U90: =RC_Eventos!R15 -> 280
C91: Custo médio de treinamento por funcionário | E91: =RC_Eventos!E16 -> 0 | F91: =RC_Eventos!F16 -> 167 | G91: =RC_Eventos!G16 -> 75 | H91: =RC_Eventos!H16 -> 80 | I91: =RC_Eventos!I16 -> 0 | L91: =RC_Eventos!J16 -> 0 | M91: =RC_Eventos!K16 -> 0 | N91: =RC_Eventos!L16 -> 0 | O91: =RC_Eventos!M16 -> 0 | P91: =RC_Eventos!N16 -> 0 | Q91: =RC_Eventos!O16 -> 0 | S91: =RC_Eventos!P16 -> 0 | T91: =RC_Eventos!Q16 -> 26.83 | U91: =RC_Eventos!R16 -> 322
C92: =RC_Eventos!C17 -> Promoções (mensal) para 2015
C93: Promoções | E93: =RC_Eventos!E18 -> 0 | F93: =RC_Eventos!F18 -> 3 | G93: =RC_Eventos!G18 -> 1 | H93: =RC_Eventos!H18 -> 0 | I93: =RC_Eventos!I18 -> 0 | L93: =RC_Eventos!J18 -> 0 | M93: =RC_Eventos!K18 -> 0 | N93: =RC_Eventos!L18 -> 0 | O93: =RC_Eventos!M18 -> 0 | P93: =RC_Eventos!N18 -> 0 | Q93: =RC_Eventos!O18 -> 0 | S93: =RC_Eventos!P18 -> 0 | T93: =RC_Eventos!Q18 -> 0.33 | U93: =RC_Eventos!R18 -> 4
C94: Aumento do custo com promoções em relação ao mês anterior | E94: =RC_Eventos!E19 -> 0 | F94: =RC_Eventos!F19 -> 1 | G94: =RC_Eventos!G19 -> 0.66666667 | H94: =RC_Eventos!H19 -> -1 | I94: =RC_Eventos!I19 -> 0 | L94: =RC_Eventos!J19 -> 0 | M94: =RC_Eventos!K19 -> 0 | N94: =RC_Eventos!L19 -> 0 | O94: =RC_Eventos!M19 -> 0 | P94: =RC_Eventos!N19 -> 0 | Q94: =RC_Eventos!O19 -> 0 | S94: =RC_Eventos!P19 -> 0 | T94: =RC_Eventos!Q19 -> 0.06 | U94: =RC_Eventos!R19 -> 0.44444444
C95: =RC_Eventos!C20 -> Férias e Licenças (mensal) para 2015
C96: Funcionários em licença | E96: =RC_Eventos!E21 -> 0 | F96: =RC_Eventos!F21 -> 1 | G96: =RC_Eventos!G21 -> 1 | H96: =RC_Eventos!H21 -> 0 | I96: =RC_Eventos!I21 -> 0 | L96: =RC_Eventos!J21 -> 0 | M96: =RC_Eventos!K21 -> 0 | N96: =RC_Eventos!L21 -> 0 | O96: =RC_Eventos!M21 -> 0 | P96: =RC_Eventos!N21 -> 0 | Q96: =RC_Eventos!O21 -> 0 | S96: =RC_Eventos!P21 -> 0 | T96: =RC_Eventos!Q21 -> 0.17 | U96: =RC_Eventos!R21 -> 2
C97: Funcionário em férias | E97: =RC_Eventos!E22 -> 1 | F97: =RC_Eventos!F22 -> 1 | G97: =RC_Eventos!G22 -> 1 | H97: =RC_Eventos!H22 -> 0 | I97: =RC_Eventos!I22 -> 0 | L97: =RC_Eventos!J22 -> 0 | M97: =RC_Eventos!K22 -> 0 | N97: =RC_Eventos!L22 -> 0 | O97: =RC_Eventos!M22 -> 0 | P97: =RC_Eventos!N22 -> 0 | Q97: =RC_Eventos!O22 -> 0 | S97: =RC_Eventos!P22 -> 0 | T97: =RC_Eventos!Q22 -> 0.25 | U97: =RC_Eventos!R22 -> 3
C98: Faltas sem justificativa | E98: =RC_Eventos!E23 -> 0 | F98: =RC_Eventos!F23 -> 0 | G98: =RC_Eventos!G23 -> 1 | H98: =RC_Eventos!H23 -> 0 | I98: =RC_Eventos!I23 -> 0 | L98: =RC_Eventos!J23 -> 0 | M98: =RC_Eventos!K23 -> 0 | N98: =RC_Eventos!L23 -> 0 | O98: =RC_Eventos!M23 -> 0 | P98: =RC_Eventos!N23 -> 0 | Q98: =RC_Eventos!O23 -> 0 | S98: =RC_Eventos!P23 -> 0 | T98: =RC_Eventos!Q23 -> 0.08 | U98: =RC_Eventos!R23 -> 1
C100: 5. Receitas e Custos
C101: =RC_Receitas!C9 -> Resumo dos indicadores de receitas e custos (mensal) para 2015
C102: Indicador | E102: Jan | F102: Fev | G102: Mar | H102: Abr | I102: Mai | L102: Jun | M102: Jul | N102: Ago | O102: Set | P102: Out | Q102: Nov | S102: Dez | T102: Média | U102: Total
C103: Receitas brutas | E103: =RC_Receitas!F11 -> 400000 | F103: =RC_Receitas!G11 -> 200001 | G103: =RC_Receitas!H11 -> 200002 | H103: =RC_Receitas!I11 -> 200003 | I103: =RC_Receitas!J11 -> 300000 | L103: =RC_Receitas!K11 -> 200000 | M103: =RC_Receitas!L11 -> 300000 | N103: =RC_Receitas!M11 | O103: =RC_Receitas!N11 | P103: =RC_Receitas!O11 | Q103: =RC_Receitas!P11 | S103: =RC_Receitas!Q11 | T103: =RC_Receitas!R11 -> 257143.71 | U103: =RC_Receitas!S11 -> 1800006
C104: Receita média por funcionário | E104: =RC_Receitas!F12 -> 40000 | F104: =RC_Receitas!G12 -> 16666.75 | G104: =RC_Receitas!H12 -> 18182 | H104: =RC_Receitas!I12 -> 18182.091 | I104: =RC_Receitas!J12 -> 27272.727 | L104: =RC_Receitas!K12 -> 18181.818 | M104: =RC_Receitas!L12 -> 27272.727 | N104: =RC_Receitas!M12 | O104: =RC_Receitas!N12 | P104: =RC_Receitas!O12 | Q104: =RC_Receitas!P12 | S104: =RC_Receitas!Q12 | T104: =RC_Receitas!R12 -> 23376.701 | U104: =RC_Receitas!S12 -> 163636.91
C105: Custo médio por funcionário | E105: =RC_Receitas!F13 -> 6740 | F105: =RC_Receitas!G13 -> 5383.8333 | G105: =RC_Receitas!H13 -> 5510 | H105: =RC_Receitas!I13 -> 5355.9091 | I105: =RC_Receitas!J13 -> 3782.3636 | L105: =RC_Receitas!K13 -> 2864.1818 | M105: =RC_Receitas!L13 -> 0 | N105: =RC_Receitas!M13 -> 0 | O105: =RC_Receitas!N13 -> 0 | P105: =RC_Receitas!O13 -> 0 | Q105: =RC_Receitas!P13 -> 0 | S105: =RC_Receitas!Q13 -> 0 | T105: =RC_Receitas!R13 -> 5051.4473 | U105: =RC_Receitas!S13 -> 29513
C106: Custo com folha de pagamento | E106: =RC_Receitas!F14 -> 53500 | F106: =RC_Receitas!G14 -> 53602 | G106: =RC_Receitas!H14 -> 48504 | H106: =RC_Receitas!I14 -> 49506 | I106: =RC_Receitas!J14 -> 38503 | L106: =RC_Receitas!K14 -> 28503 | M106: =RC_Receitas!L14 | N106: =RC_Receitas!M14 | O106: =RC_Receitas!N14 | P106: =RC_Receitas!O14 | Q106: =RC_Receitas!P14 | S106: =RC_Receitas!Q14 | T106: =RC_Receitas!R14 -> 45353 | U106: =RC_Receitas!S14 -> 272118
C107: Custo com benefícios | E107: =RC_Receitas!F15 -> 9000 | F107: =RC_Receitas!G15 -> 5001 | G107: =RC_Receitas!H15 -> 5002 | H107: =RC_Receitas!I15 -> 5003 | I107: =RC_Receitas!J15 | L107: =RC_Receitas!K15 | M107: =RC_Receitas!L15 | N107: =RC_Receitas!M15 | O107: =RC_Receitas!N15 | P107: =RC_Receitas!O15 | Q107: =RC_Receitas!P15 | S107: =RC_Receitas!Q15 | T107: =RC_Receitas!R15 -> 6001.5 | U107: =RC_Receitas!S15 -> 24006
C108: Custo com promoções | E108: =RC_Receitas!F16 -> 0 | F108: =RC_Receitas!G16 -> 1500 | G108: =RC_Receitas!H16 -> 2500 | H108: =RC_Receitas!I16 -> 0 | I108: =RC_Receitas!J16 -> 0 | L108: =RC_Receitas!K16 -> 0 | M108: =RC_Receitas!L16 -> 0 | N108: =RC_Receitas!M16 -> 0 | O108: =RC_Receitas!N16 -> 0 | P108: =RC_Receitas!O16 -> 0 | Q108: =RC_Receitas!P16 -> 0 | S108: =RC_Receitas!Q16 -> 0 | T108: =RC_Receitas!R16 -> 333.33 | U108: =RC_Receitas!S16 -> 4000
C109: Custo com treinamentos | E109: =RC_Receitas!F17 -> 900 | F109: =RC_Receitas!G17 -> 501 | G109: =RC_Receitas!H17 -> 600 | H109: =RC_Receitas!I17 -> 400 | I109: =RC_Receitas!J17 -> 100 | L109: =RC_Receitas!K17 -> 0 | M109: =RC_Receitas!L17 -> 0 | N109: =RC_Receitas!M17 -> 0 | O109: =RC_Receitas!N17 -> 0 | P109: =RC_Receitas!O17 -> 0 | Q109: =RC_Receitas!P17 -> 0 | S109: =RC_Receitas!Q17 -> 0 | T109: =RC_Receitas!R17 -> 208.42 | U109: =RC_Receitas!S17 -> 2501
C110: Impostos | E110: =RC_Receitas!F18 -> 3000 | F110: =RC_Receitas!G18 -> 3001 | G110: =RC_Receitas!H18 -> 3002 | H110: =RC_Receitas!I18 -> 3003 | I110: =RC_Receitas!J18 -> 3003 | L110: =RC_Receitas!K18 -> 3003 | M110: =RC_Receitas!L18 | N110: =RC_Receitas!M18 | O110: =RC_Receitas!N18 | P110: =RC_Receitas!O18 | Q110: =RC_Receitas!P18 | S110: =RC_Receitas!Q18 | T110: =RC_Receitas!R18 -> 3002 | U110: =RC_Receitas!S18 -> 18012
C111: Outros | E111: =RC_Receitas!F19 -> 1000 | F111: =RC_Receitas!G19 -> 1001 | G111: =RC_Receitas!H19 -> 1002 | H111: =RC_Receitas!I19 -> 1003 | I111: =RC_Receitas!J19 -> 0 | L111: =RC_Receitas!K19 -> 0 | M111: =RC_Receitas!L19 | N111: =RC_Receitas!M19 | O111: =RC_Receitas!N19 | P111: =RC_Receitas!O19 | Q111: =RC_Receitas!P19 | S111: =RC_Receitas!Q19 | T111: =RC_Receitas!R19 -> 667.67 | U111: =RC_Receitas!S19 -> 4006
C112: Receita sobre custo | E112: =RC_Receitas!F20 -> 332600 | F112: =RC_Receitas!G20 -> 135395 | G112: =RC_Receitas!H20 -> 139392 | H112: =RC_Receitas!I20 -> 141088 | I112: =RC_Receitas!J20 -> 258394 | L112: =RC_Receitas!K20 -> 168494 | M112: =RC_Receitas!L20 -> 300000 | N112: =RC_Receitas!M20 | O112: =RC_Receitas!N20 | P112: =RC_Receitas!O20 | Q112: =RC_Receitas!P20 | S112: =RC_Receitas!Q20 | T112: =RC_Receitas!R20 -> 210766.14 | U112: =RC_Receitas!S20 -> 1475363
C113: =RC_Receitas!C21 -> Detalhamento dos custos com benefícios (mensal) para 2015
...

Sheet Dúvidas
C1: DÚVIDAS FREQUENTES
C4: Clique abaixo para selecionar sua dúvida:
C5: 1. Posso adicionar mais linhas e colunas na planilha?
C6: Veja a resposta abaixo:
C7: =IFERROR(VLOOKUP(C5,C59:J73,8,FALSE),"") -> Nós recomendamos fortemente que você utilize a estrutura pronta apresentada, pois existem diversas fórmulas que podem ser afetadas pela adição de linhas e colunas. Além disso, para facilitar o preenchimento mantemos a planilha desbloqueada apenas nos locais para preenchimento.
C59: =IF(E59="","",D59&". "&E59) -> 1. Posso adicionar mais linhas e colunas na planilha? | D59: 1 | E59: Posso adicionar mais linhas e colunas na planilha? | J59: Nós recomendamos fortemente que você utilize a estrutura pronta apresentada, pois existem diversas fórmulas que podem ser afetadas pela adição de linhas e colunas. Além disso, para facilitar o preenchimento mantemos a planilha desbloqueada apenas nos locais para preenchimento.
C60: =IF(E60="","",D60&". "&E60) -> 2. Posso remover linhas? | D60: 2 | E60: Posso remover linhas? | J60: Nós recomendamos fortemente que você utilize a estrutura pronta apresentada, pois existem diversas fórmulas que podem ser afetadas pela adição de linhas e colunas. Além disso, para facilitar o preenchimento mantemos a planilha desbloqueada apenas nos locais para preenchimento.
C61: =IF(E61="","",D61&". "&E61) -> 3. Para que servem os alertas? | D61: 3 | E61: Para que servem os alertas? | J61: Eles são avisos sobre como a sua projeção está. A partir deles, você pode refinar suas projeções e pensar em medidas mais agressivas para tornar seu projeto mais agressivo.
C62: =IF(E62="","",D62&". "&E62) -> 4. Essa planilha pode ser apresentada para instituições financeiras? | D62: 4 | E62: Essa planilha pode ser apresentada para instituições financeiras? | J62: Sim. Porém esses dados não garantem aprovações ou reprovações por parte dessas instituições. Sendo usados como dados complementares.
C63: =IF(E63="","",D63&". "&E63) -> 5. Como desbloquear a planilha? | D63: 5 | E63: Como desbloquear a planilha? | J63: Basta entrar no menu superior "Revisão" e escolher o item desproteger planilha no grupo Alterações. As planilhas não possuem senhas, apenas estão bloqueadas para melhorar a usabilidade delas.
C64: =IF(E64="","",D64&". "&E64) -> 6. Como redimensiono uma coluna ou linha da planilha? | D64: 6 | E64: Como redimensiono uma coluna ou linha da planilha? | J64: Com a planilha desbloqueada(ver pergunta 5), clique sobre o número da linha com o botão diretiro e escolha a opção altura da linha no caso das linhas ou na letra da coluna com o botão direito e escolha a opção largura da coluna no caso de colunas.
C65: =IF(E65="","",D65&". "&E65) -> 7. Como faço para imprimir uma planilha? | D65: 7 | E65: Como faço para imprimir uma planilha? | J65: Escolha Opção Arquivo e vá ao item imprimir no seu menu superior.
C66: =IF(E66="","",D66&". "&E66) -> 8. Como mudo a moeda da planilha? | D66: 8 | E66: Como mudo a moeda da planilha? | J66: Selecione os campos que deseja mudar a moeda. Clique com o botão direito escolha a opção formatar células. Altere o símbolo para o formato que desejar na guia Número.
C67: =IF(E67="","",D67&". "&E67) | D67: 9
C68: =IF(E68="","",D68&". "&E68) | D68: 10
C69: =IF(E69="","",D69&". "&E69) | D69: 11
C70: =IF(E70="","",D70&". "&E70) | D70: 12
C71: =IF(E71="","",D71&". "&E71) | D71: 13
C72: =IF(E72="","",D72&". "&E72) | D72: 14
C73: =IF(E73="","",D73&". "&E73) | D73: 15

Sheet Cad_Func
C1: 1. CADASTRO | AE1: Masculino | AF1: =IF(ISERROR(IF(Cad_Outros!E9="","",Cad_Outros!E9)),"",IF(Cad_Outros!E9="","",Cad_Outros!E9)) -> Ensino fundamental | AG1: =IF(ISERROR(IF(Cad!C8="","",Cad!C8)),"",IF(Cad!C8="","",Cad!C8)) -> Designer I
AE2: Feminino | AF2: =IF(ISERROR(IF(Cad_Outros!E10="","",Cad_Outros!E10)),"",IF(Cad_Outros!E10="","",Cad_Outros!E10)) -> Ensino médio | AG2: =IF(ISERROR(IF(Cad!C9="","",Cad!C9)),"",IF(Cad!C9="","",Cad!C9)) -> Designer II
AF3: =IF(ISERROR(IF(Cad_Outros!E11="","",Cad_Outros!E11)),"",IF(Cad_Outros!E11="","",Cad_Outros!E11)) -> Superior completo | AG3: =IF(ISERROR(IF(Cad!C10="","",Cad!C10)),"",IF(Cad!C10="","",Cad!C10)) -> Designer III
AF5: =IF(ISERROR(IF(Cad_Outros!E12="","",Cad_Outros!E12)),"",IF(Cad_Outros!E12="","",Cad_Outros!E12)) -> Superior incompleto | AG5: =IF(ISERROR(IF(Cad!C11="","",Cad!C11)),"",IF(Cad!C11="","",Cad!C11)) -> Dir de Arte
C6: Cadastro de funcionários | AF6: =IF(ISERROR(IF(Cad_Outros!E13="","",Cad_Outros!E13)),"",IF(Cad_Outros!E13="","",Cad_Outros!E13)) -> Pós-graduação completa | AG6: =IF(ISERROR(IF(Cad!C12="","",Cad!C12)),"",IF(Cad!C12="","",Cad!C12)) -> Dir de Criação
C7: Nome do funcionário | D7: Sexo | E7: Data de nascimento | F7: Escolaridade | G7: Cargo | H7: Data de admissão | I7: Data de demissão | J7: Tempo de empresa | L7: Cargo após a promoção | M7: Nível | N7: Idade | O7: Faixa etária | P7: ="aux gráfico faixa etária "&Cad_Inicial!$D$8 -> aux gráfico faixa etária 2015 | Q7: ="aux gráfico func no início de "&Cad_Inicial!$D$8 -> aux gráfico func no início de 2015 | R7: Anos | S7: Meses | T7: Meses total | U7: Média de permanência | V7: Passou na experiência? | W7: ano adm | X7: mês adm | Y7: ano dem | Z7: mês dem | AA7: ="total de func em "&Cad_Inicial!$D$8 -> total de func em 2015 | AB7: ="total de func no início de "&Cad_Inicial!$D$8 -> total de func no início de 2015 | AC7: Motivo | AF7: =IF(ISERROR(IF(Cad_Outros!E14="","",Cad_Outros!E14)),"",IF(Cad_Outros!E14="","",Cad_Outros!E14)) -> Pós-graduação incompleta | AG7: =IF(ISERROR(IF(Cad!C13="","",Cad!C13)),"",IF(Cad!C13="","",Cad!C13)) -> Sócio
C8: ze 1 | D8: Masculino | E8: 31310 | F8: Ensino fundamental | G8: Designer I | H8: 41640 | I8: =IF(ISERROR(IF(C8="","",IFERROR(VLOOKUP(C8,Lanç!$C$8:$D$208,2,0),"Ativo"))),"",IF(C8="","",IFERROR(VLOOKUP(C8,Lanç!$C$8:$D$208,2,0),"Ativo"))) -> 42075 | J8: =IF(ISERROR(IF(I8="","",R8&" anos e "&S8&" meses")),"",IF(I8="","",R8&" anos e "&S8&" meses")) -> 1 anos e 2 meses | L8: =IF(ISERROR(IF(G8="","",VLOOKUP(C8,Lanç_Promoções!$C$8:$F$2008,4,0))),G8,IF(G8="","",VLOOKUP(C8,Lanç_Promoções!$C$8:$F$2008,4,0))) -> Designer II | M8: =IF(ISERROR(IF(L8="","",VLOOKUP(L8,Cad!$C$8:$D$208,2,0))),"",IF(L8="","",VLOOKUP(L8,Cad!$C$8:$D$208,2,0))) -> Operacional | N8: =IF(ISERROR(IF(E8="","",ROUND((TODAY()-E8)/365,0))),"",IF(E8="","",ROUND((TODAY()-E8)/365,0))) -> 36 | O8: =IF(ISERROR(IF(N8="","",IF(N8>60,"Mais de 60 anos",IF(N8>54,"54 a 60 anos",IF(N8>44,"44 a 53 anos",IF(N8>34,"34 a 43 anos",IF(N8>24,"24 a 33 anos","18 a 23 anos"))))))),"",IF(N8="","",IF(N8>60,"Mais de 60 anos",IF(N8>54,"54 a 60 anos",IF(N8>44,"44 a 53 anos",IF(N8>34,"34 a 43 anos",IF(N8>24,"24 a 33 anos","18 a 23 anos"))))))) -> 34 a 43 anos | P8: =IF(ISERROR(IF(W8="","",IF(AND(W8<=Cad_Inicial!$D$8,Y8>Cad_Inicial!$D$8),1,0))),"",IF(W8="","",IF(AND(W8<=Cad_Inicial!$D$8,Y8>Cad_Inicial!$D$8),1,0))) -> 0 | Q8: =IF(ISERROR(IF(W8="","",IF(AND(W8<=(Cad_Inicial!$D$8-1),Y8>Cad_Inicial!$D$8-1),1,0))),"",IF(W8="","",IF(W8="","",IF(AND(W8<=(Cad_Inicial!$D$8-1),Y8>Cad_Inicial!$D$8-1),1,0)))) -> 1 | R8: =IF(ISERROR(IF(I8="","",IF(I8="Ativo",TRUNC((TODAY()-H8)/30/12,0),TRUNC((I8-H8)/30/12,0)))),"",IF(I8="","",IF(I8="Ativo",TRUNC((TODAY()-H8)/30/12,0),TRUNC((I8-H8)/30/12,0)))) -> 1 | S8: =IF(ISERROR(IF(I8="","",IF(I8="Ativo",TRUNC(MOD((TODAY()-H8)/30,12),0),TRUNC(MOD((I8-H8)/30,12),0)))),"",IF(I8="","",IF(I8="Ativo",TRUNC(MOD((TODAY()-H8)/30,12),0),TRUNC(MOD((I8-H8)/30,12),0)))) -> 2 | T8: =IF(ISERROR((R8*12+S8)),"",(R8*12+S8)) -> 14 | U8: =IF(ISERROR(IF(H8="","",IF(YEAR(H8)<=Cad_Inicial!$D$8,"SIM",""))),"",IF(H8="","",IF(YEAR(H8)<=Cad_Inicial!$D$8,"SIM",""))) -> SIM | V8: =IF(ISERROR(IF(H8="","",IF(AND(YEAR(H8)=Cad_Inicial!$D$8,I8="Ativo",TODAY()-H8>90),"SIM",IF(AND(YEAR(H8)=Cad_Inicial!$D$8,I8-H8>90),"SIM","")))),"",IF(H8="","",IF(AND(YEAR(H8)=Cad_Inicial!$D$8,I8="Ativo",TODAY()-H8>90),"SIM",IF(AND(YEAR(H8)=Cad_Inicial!$D$8,I8-H8>90),"SIM","")))) | W8: =IF(ISERROR(IF(H8="","",YEAR(H8))),"",IF(H8="","",YEAR(H8))) -> 2014 | X8: =IF(ISERROR(IF(H8="","",MONTH(H8))),"",IF(H8="","",MONTH(H8))) -> 1 | Y8: =IF(ISERROR(IF(I8="","",YEAR(I8))),"",IF(I8="","",YEAR(I8))) -> 2015 | Z8: =IF(ISERROR(IF(OR(I8="",I8="Ativo"),"",MONTH(I8))),"",IF(OR(I8="",I8="Ativo"),"",MONTH(I8))) -> 3 | AA8: =IF(ISERROR(IF(W8="","",IF(AND(W8<=Cad_Inicial!$D$8,Y8>Cad_Inicial!$D$8),1,0))),"",IF(W8="","",IF(AND(W8<=Cad_Inicial!$D$8,Y8>Cad_Inicial!$D$8),1,0))) -> 0 | AB8: =IF(ISERROR(IF(W8="","",IF(AND(W8<=(Cad_Inicial!$D$8-1),Y8>Cad_Inicial!$D$8-1),1,0))),"",IF(W8="","",IF(W8="","",IF(AND(W8<=(Cad_Inicial!$D$8-1),Y8>Cad_Inicial!$D$8-1),1,0)))) -> 1 | AC8: =IF(ISERROR(IF(I8="Ativo","",VLOOKUP(C8,Lanç!$C$8:$E$208,3,0))),"",IF(I8="Ativo","",VLOOKUP(C8,Lanç!$C$8:$E$208,3,0))) -> Pedido de demissão | AF8: =IF(ISERROR(IF(Cad_Outros!E15="","",Cad_Outros!E15)),"",IF(Cad_Outros!E15="","",Cad_Outros!E15)) -> Mestre | AG8: =IF(ISERROR(IF(Cad!C14="","",Cad!C14)),"",IF(Cad!C14="","",Cad!C14))
C9: ze 2 | D9: Masculino | E9: 29264 | F9: Superior incompleto | G9: Designer II | H9: 41975 | I9: =IF(ISERROR(IF(C9="","",IFERROR(VLOOKUP(C9,Lanç!$C$8:$D$208,2,0),"Ativo"))),"",IF(C9="","",IFERROR(VLOOKUP(C9,Lanç!$C$8:$D$208,2,0),"Ativo"))) -> Ativo | J9: =IF(ISERROR(IF(I9="","",R9&" anos e "&S9&" meses")),"",IF(I9="","",R9&" anos e "&S9&" meses")) -> 7 anos e 1 meses | L9: =IF(ISERROR(IF(G9="","",VLOOKUP(C9,Lanç_Promoções!$C$8:$F$2008,4,0))),G9,IF(G9="","",VLOOKUP(C9,Lanç_Promoções!$C$8:$F$2008,4,0))) -> Designer III | M9: =IF(ISERROR(IF(L9="","",VLOOKUP(L9,Cad!$C$8:$D$208,2,0))),"",IF(L9="","",VLOOKUP(L9,Cad!$C$8:$D$208,2,0))) -> Operacional | N9: =IF(ISERROR(IF(E9="","",ROUND((TODAY()-E9)/365,0))),"",IF(E9="","",ROUND((TODAY()-E9)/365,0))) -> 42 | O9: =IF(ISERROR(IF(N9="","",IF(N9>60,"Mais de 60 anos",IF(N9>54,"54 a 60 anos",IF(N9>44,"44 a 53 anos",IF(N9>34,"34 a 43 anos",IF(N9>24,"24 a 33 anos","18 a 23 anos"))))))),"",IF(N9="","",IF(N9>60,"Mais de 60 anos",IF(N9>54,"54 a 60 anos",IF(N9>44,"44 a 53 anos",IF(N9>34,"34 a 43 anos",IF(N9>24,"24 a 33 anos","18 a 23 anos"))))))) -> 34 a 43 anos | P9: =IF(ISERROR(IF(W9="","",IF(AND(W9<=Cad_Inicial!$D$8,Y9>Cad_Inicial!$D$8),1,0))),"",IF(W9="","",IF(AND(W9<=Cad_Inicial!$D$8,Y9>Cad_Inicial!$D$8),1,0))) -> 1 | Q9: =IF(ISERROR(IF(W9="","",IF(AND(W9<=(Cad_Inicial!$D$8-1),Y9>Cad_Inicial!$D$8-1),1,0))),"",IF(W9="","",IF(W9="","",IF(AND(W9<=(Cad_Inicial!$D$8-1),Y9>Cad_Inicial!$D$8-1),1,0)))) -> 1 | R9: =IF(ISERROR(IF(I9="","",IF(I9="Ativo",TRUNC((TODAY()-H9)/30/12,0),TRUNC((I9-H9)/30/12,0)))),"",IF(I9="","",IF(I9="Ativo",TRUNC((TODAY()-H9)/30/12,0),TRUNC((I9-H9)/30/12,0)))) -> 7 | S9: =IF(ISERROR(IF(I9="","",IF(I9="Ativo",TRUNC(MOD((TODAY()-H9)/30,12),0),TRUNC(MOD((I9-H9)/30,12),0)))),"",IF(I9="","",IF(I9="Ativo",TRUNC(MOD((TODAY()-H9)/30,12),0),TRUNC(MOD((I9-H9)/30,12),0)))) -> 1 | T9: =IF(ISERROR((R9*12+S9)),"",(R9*12+S9)) -> 85 | U9: =IF(ISERROR(IF(H9="","",IF(YEAR(H9)<=Cad_Inicial!$D$8,"SIM",""))),"",IF(H9="","",IF(YEAR(H9)<=Cad_Inicial!$D$8,"SIM",""))) -> SIM | V9: =IF(ISERROR(IF(H9="","",IF(AND(YEAR(H9)=Cad_Inicial!$D$8,I9="Ativo",TODAY()-H9>90),"SIM",IF(AND(YEAR(H9)=Cad_Inicial!$D$8,I9-H9>90),"SIM","")))),"",IF(H9="","",IF(AND(YEAR(H9)=Cad_Inicial!$D$8,I9="Ativo",TODAY()-H9>90),"SIM",IF(AND(YEAR(H9)=Cad_Inicial!$D$8,I9-H9>90),"SIM","")))) | W9: =IF(ISERROR(IF(H9="","",YEAR(H9))),"",IF(H9="","",YEAR(H9))) -> 2014 | X9: =IF(ISERROR(IF(H9="","",MONTH(H9))),"",IF(H9="","",MONTH(H9))) -> 12 | Y9: =IF(ISERROR(IF(I9="","",YEAR(I9))),"",IF(I9="","",YEAR(I9))) | Z9: =IF(ISERROR(IF(OR(I9="",I9="Ativo"),"",MONTH(I9))),"",IF(OR(I9="",I9="Ativo"),"",MONTH(I9))) | AA9: =IF(ISERROR(IF(W9="","",IF(AND(W9<=Cad_Inicial!$D$8,Y9>Cad_Inicial!$D$8),1,0))),"",IF(W9="","",IF(AND(W9<=Cad_Inicial!$D$8,Y9>Cad_Inicial!$D$8),1,0))) -> 1 | AB9: =IF(ISERROR(IF(W9="","",IF(AND(W9<=(Cad_Inicial!$D$8-1),Y9>Cad_Inicial!$D$8-1),1,0))),"",IF(W9="","",IF(W9="","",IF(AND(W9<=(Cad_Inicial!$D$8-1),Y9>Cad_Inicial!$D$8-1),1,0)))) -> 1 | AC9: =IF(ISERROR(IF(I9="Ativo","",VLOOKUP(C9,Lanç!$C$8:$E$208,3,0))),"",IF(I9="Ativo","",VLOOKUP(C9,Lanç!$C$8:$E$208,3,0))) | AF9: =IF(ISERROR(IF(Cad_Outros!E16="","",Cad_Outros!E16)),"",IF(Cad_Outros!E16="","",Cad_Outros!E16)) -> Doutor | AG9: =IF(ISERROR(IF(Cad!C15="","",Cad!C15)),"",IF(Cad!C15="","",Cad!C15))
C10: ze 3 | D10: Feminino | E10: 29774 | F10: Superior completo | G10: Designer III | H10: 42038 | I10: =IF(ISERROR(IF(C10="","",IFERROR(VLOOKUP(C10,Lanç!$C$8:$D$208,2,0),"Ativo"))),"",IF(C10="","",IFERROR(VLOOKUP(C10,Lanç!$C$8:$D$208,2,0),"Ativo"))) -> Ativo | J10: =IF(ISERROR(IF(I10="","",R10&" anos e "&S10&" meses")),"",IF(I10="","",R10&" anos e "&S10&" meses")) -> 6 anos e 11 meses | L10: =IF(ISERROR(IF(G10="","",VLOOKUP(C10,Lanç_Promoções!$C$8:$F$2008,4,0))),G10,IF(G10="","",VLOOKUP(C10,Lanç_Promoções!$C$8:$F$2008,4,0))) -> Designer III | M10: =IF(ISERROR(IF(L10="","",VLOOKUP(L10,Cad!$C$8:$D$208,2,0))),"",IF(L10="","",VLOOKUP(L10,Cad!$C$8:$D$208,2,0))) -> Operacional | N10: =IF(ISERROR(IF(E10="","",ROUND((TODAY()-E10)/365,0))),"",IF(E10="","",ROUND((TODAY()-E10)/365,0))) -> 40 | O10: =IF(ISERROR(IF(N10="","",IF(N10>60,"Mais de 60 anos",IF(N10>54,"54 a 60 anos",IF(N10>44,"44 a 53 anos",IF(N10>34,"34 a 43 anos",IF(N10>24,"24 a 33 anos","18 a 23 anos"))))))),"",IF(N10="","",IF(N10>60,"Mais de 60 anos",IF(N10>54,"54 a 60 anos",IF(N10>44,"44 a 53 anos",IF(N10>34,"34 a 43 anos",IF(N10>24,"24 a 33 anos","18 a 23 anos"))))))) -> 34 a 43 anos | P10: =IF(ISERROR(IF(W10="","",IF(AND(W10<=Cad_Inicial!$D$8,Y10>Cad_Inicial!$D$8),1,0))),"",IF(W10="","",IF(AND(W10<=Cad_Inicial!$D$8,Y10>Cad_Inicial!$D$8),1,0))) -> 1 | Q10: =IF(ISERROR(IF(W10="","",IF(AND(W10<=(Cad_Inicial!$D$8-1),Y10>Cad_Inicial!$D$8-1),1,0))),"",IF(W10="","",IF(W10="","",IF(AND(W10<=(Cad_Inicial!$D$8-1),Y10>Cad_Inicial!$D$8-1),1,0)))) -> 0 | R10: =IF(ISERROR(IF(I10="","",IF(I10="Ativo",TRUNC((TODAY()-H10)/30/12,0),TRUNC((I10-H10)/30/12,0)))),"",IF(I10="","",IF(I10="Ativo",TRUNC((TODAY()-H10)/30/12,0),TRUNC((I10-H10)/30/12,0)))) -> 6 | S10: =IF(ISERROR(IF(I10="","",IF(I10="Ativo",TRUNC(MOD((TODAY()-H10)/30,12),0),TRUNC(MOD((I10-H10)/30,12),0)))),"",IF(I10="","",IF(I10="Ativo",TRUNC(MOD((TODAY()-H10)/30,12),0),TRUNC(MOD((I10-H10)/30,12),0)))) -> 11 | T10: =IF(ISERROR((R10*12+S10)),"",(R10*12+S10)) -> 83 | U10: =IF(ISERROR(IF(H10="","",IF(YEAR(H10)<=Cad_Inicial!$D$8,"SIM",""))),"",IF(H10="","",IF(YEAR(H10)<=Cad_Inicial!$D$8,"SIM",""))) -> SIM | V10: =IF(ISERROR(IF(H10="","",IF(AND(YEAR(H10)=Cad_Inicial!$D$8,I10="Ativo",TODAY()-H10>90),"SIM",IF(AND(YEAR(H10)=Cad_Inicial!$D$8,I10-H10>90),"SIM","")))),"",IF(H10="","",IF(AND(YEAR(H10)=Cad_Inicial!$D$8,I10="Ativo",TODAY()-H10>90),"SIM",IF(AND(YEAR(H10)=Cad_Inicial!$D$8,I10-H10>90),"SIM","")))) -> SIM | W10: =IF(ISERROR(IF(H10="","",YEAR(H10))),"",IF(H10="","",YEAR(H10))) -> 2015 | X10: =IF(ISERROR(IF(H10="","",MONTH(H10))),"",IF(H10="","",MONTH(H10))) -> 2 | Y10: =IF(ISERROR(IF(I10="","",YEAR(I10))),"",IF(I10="","",YEAR(I10))) | Z10: =IF(ISERROR(IF(OR(I10="",I10="Ativo"),"",MONTH(I10))),"",IF(OR(I10="",I10="Ativo"),"",MONTH(I10))) | AA10: =IF(ISERROR(IF(W10="","",IF(AND(W10<=Cad_Inicial!$D$8,Y10>Cad_Inicial!$D$8),1,0))),"",IF(W10="","",IF(AND(W10<=Cad_Inicial!$D$8,Y10>Cad_Inicial!$D$8),1,0))) -> 1 | AB10: =IF(ISERROR(IF(W10="","",IF(AND(W10<=(Cad_Inicial!$D$8-1),Y10>Cad_Inicial!$D$8-1),1,0))),"",IF(W10="","",IF(W10="","",IF(AND(W10<=(Cad_Inicial!$D$8-1),Y10>Cad_Inicial!$D$8-1),1,0)))) -> 0 | AC10: =IF(ISERROR(IF(I10="Ativo","",VLOOKUP(C10,Lanç!$C$8:$E$208,3,0))),"",IF(I10="Ativo","",VLOOKUP(C10,Lanç!$C$8:$E$208,3,0))) | AG10: =IF(ISERROR(IF(Cad!C16="","",Cad!C16)),"",IF(Cad!C16="","",Cad!C16))
C11: ze 4 | D11: Masculino | E11: 30764 | F11: Superior completo | G11: Dir de Arte | H11: 42039 | I11: Ativo | J11: 0 anos e 2 meses | L11: =IF(ISERROR(IF(G11="","",VLOOKUP(C11,Lanç_Promoções!$C$8:$F$2008,4,0))),G11,IF(G11="","",VLOOKUP(C11,Lanç_Promoções!$C$8:$F$2008,4,0))) -> Dir de Criação | M11: =IF(ISERROR(IF(L11="","",VLOOKUP(L11,Cad!$C$8:$D$208,2,0))),"",IF(L11="","",VLOOKUP(L11,Cad!$C$8:$D$208,2,0))) -> Diretoria | N11: =IF(ISERROR(IF(E11="","",ROUND((TODAY()-E11)/365,0))),"",IF(E11="","",ROUND((TODAY()-E11)/365,0))) -> 38 | O11: =IF(ISERROR(IF(N11="","",IF(N11>60,"Mais de 60 anos",IF(N11>54,"54 a 60 anos",IF(N11>44,"44 a 53 anos",IF(N11>34,"34 a 43 anos",IF(N11>24,"24 a 33 anos","18 a 23 anos"))))))),"",IF(N11="","",IF(N11>60,"Mais de 60 anos",IF(N11>54,"54 a 60 anos",IF(N11>44,"44 a 53 anos",IF(N11>34,"34 a 43 anos",IF(N11>24,"24 a 33 anos","18 a 23 anos"))))))) -> 34 a 43 anos | P11: =IF(ISERROR(IF(W11="","",IF(AND(W11<=Cad_Inicial!$D$8,Y11>Cad_Inicial!$D$8),1,0))),"",IF(W11="","",IF(AND(W11<=Cad_Inicial!$D$8,Y11>Cad_Inicial!$D$8),1,0))) -> 1 | Q11: =IF(ISERROR(IF(W11="","",IF(AND(W11<=(Cad_Inicial!$D$8-1),Y11>Cad_Inicial!$D$8-1),1,0))),"",IF(W11="","",IF(W11="","",IF(AND(W11<=(Cad_Inicial!$D$8-1),Y11>Cad_Inicial!$D$8-1),1,0)))) -> 0 | R11: =IF(ISERROR(IF(I11="","",IF(I11="Ativo",TRUNC((TODAY()-H11)/30/12,0),TRUNC((I11-H11)/30/12,0)))),"",IF(I11="","",IF(I11="Ativo",TRUNC((TODAY()-H11)/30/12,0),TRUNC((I11-H11)/30/12,0)))) -> 6 | S11: =IF(ISERROR(IF(I11="","",IF(I11="Ativo",TRUNC(MOD((TODAY()-H11)/30,12),0),TRUNC(MOD((I11-H11)/30,12),0)))),"",IF(I11="","",IF(I11="Ativo",TRUNC(MOD((TODAY()-H11)/30,12),0),TRUNC(MOD((I11-H11)/30,12),0)))) -> 11 | T11: =IF(ISERROR((R11*12+S11)),"",(R11*12+S11)) -> 83 | U11: =IF(ISERROR(IF(H11="","",IF(YEAR(H11)<=Cad_Inicial!$D$8,"SIM",""))),"",IF(H11="","",IF(YEAR(H11)<=Cad_Inicial!$D$8,"SIM",""))) -> SIM | V11: =IF(ISERROR(IF(H11="","",IF(AND(YEAR(H11)=Cad_Inicial!$D$8,I11="Ativo",TODAY()-H11>90),"SIM",IF(AND(YEAR(H11)=Cad_Inicial!$D$8,I11-H11>90),"SIM","")))),"",IF(H11="","",IF(AND(YEAR(H11)=Cad_Inicial!$D$8,I11="Ativo",TODAY()-H11>90),"SIM",IF(AND(YEAR(H11)=Cad_Inicial!$D$8,I11-H11>90),"SIM","")))) -> SIM | W11: =IF(ISERROR(IF(H11="","",YEAR(H11))),"",IF(H11="","",YEAR(H11))) -> 2015 | X11: =IF(ISERROR(IF(H11="","",MONTH(H11))),"",IF(H11="","",MONTH(H11))) -> 2 | Y11: =IF(ISERROR(IF(I11="","",YEAR(I11))),"",IF(I11="","",YEAR(I11))) | Z11: =IF(ISERROR(IF(OR(I11="",I11="Ativo"),"",MONTH(I11))),"",IF(OR(I11="",I11="Ativo"),"",MONTH(I11))) | AA11: =IF(ISERROR(IF(W11="","",IF(AND(W11<=Cad_Inicial!$D$8,Y11>Cad_Inicial!$D$8),1,0))),"",IF(W11="","",IF(AND(W11<=Cad_Inicial!$D$8,Y11>Cad_Inicial!$D$8),1,0))) -> 1 | AB11: =IF(ISERROR(IF(W11="","",IF(AND(W11<=(Cad_Inicial!$D$8-1),Y11>Cad_Inicial!$D$8-1),1,0))),"",IF(W11="","",IF(W11="","",IF(AND(W11<=(Cad_Inicial!$D$8-1),Y11>Cad_Inicial!$D$8-1),1,0)))) -> 0 | AC11: =IF(ISERROR(IF(I11="Ativo","",VLOOKUP(C11,Lanç!$C$8:$E$208,3,0))),"",IF(I11="Ativo","",VLOOKUP(C11,Lanç!$C$8:$E$208,3,0))) | AG11: =IF(ISERROR(IF(Cad!C17="","",Cad!C17)),"",IF(Cad!C17="","",Cad!C17))
C12: ze 5 | D12: Feminino | E12: 28622 | F12: Superior completo | G12: Designer III | H12: 42009 | I12: Ativo | J12: 0 anos e 3 meses | L12: =IF(ISERROR(IF(G12="","",VLOOKUP(C12,Lanç_Promoções!$C$8:$F$2008,4,0))),G12,IF(G12="","",VLOOKUP(C12,Lanç_Promoções!$C$8:$F$2008,4,0))) -> Sócio | M12: =IF(ISERROR(IF(L12="","",VLOOKUP(L12,Cad!$C$8:$D$208,2,0))),"",IF(L12="","",VLOOKUP(L12,Cad!$C$8:$D$208,2,0))) -> Diretoria | N12: =IF(ISERROR(IF(E12="","",ROUND((TODAY()-E12)/365,0))),"",IF(E12="","",ROUND((TODAY()-E12)/365,0))) -> 44 | O12: =IF(ISERROR(IF(N12="","",IF(N12>60,"Mais de 60 anos",IF(N12>54,"54 a 60 anos",IF(N12>44,"44 a 53 anos",IF(N12>34,"34 a 43 anos",IF(N12>24,"24 a 33 anos","18 a 23 anos"))))))),"",IF(N12="","",IF(N12>60,"Mais de 60 anos",IF(N12>54,"54 a 60 anos",IF(N12>44,"44 a 53 anos",IF(N12>34,"34 a 43 anos",IF(N12>24,"24 a 33 anos","18 a 23 anos"))))))) -> 34 a 43 anos | P12: =IF(ISERROR(IF(W12="","",IF(AND(W12<=Cad_Inicial!$D$8,Y12>Cad_Inicial!$D$8),1,0))),"",IF(W12="","",IF(AND(W12<=Cad_Inicial!$D$8,Y12>Cad_Inicial!$D$8),1,0))) -> 1 | Q12: =IF(ISERROR(IF(W12="","",IF(AND(W12<=(Cad_Inicial!$D$8-1),Y12>Cad_Inicial!$D$8-1),1,0))),"",IF(W12="","",IF(W12="","",IF(AND(W12<=(Cad_Inicial!$D$8-1),Y12>Cad_Inicial!$D$8-1),1,0)))) -> 0 | R12: =IF(ISERROR(IF(I12="","",IF(I12="Ativo",TRUNC((TODAY()-H12)/30/12,0),TRUNC((I12-H12)/30/12,0)))),"",IF(I12="","",IF(I12="Ativo",TRUNC((TODAY()-H12)/30/12,0),TRUNC((I12-H12)/30/12,0)))) -> 7 | S12: =IF(ISERROR(IF(I12="","",IF(I12="Ativo",TRUNC(MOD((TODAY()-H12)/30,12),0),TRUNC(MOD((I12-H12)/30,12),0)))),"",IF(I12="","",IF(I12="Ativo",TRUNC(MOD((TODAY()-H12)/30,12),0),TRUNC(MOD((I12-H12)/30,12),0)))) -> 0 | T12: =IF(ISERROR((R12*12+S12)),"",(R12*12+S12)) -> 84 | U12: =IF(ISERROR(IF(H12="","",IF(YEAR(H12)<=Cad_Inicial!$D$8,"SIM",""))),"",IF(H12="","",IF(YEAR(H12)<=Cad_Inicial!$D$8,"SIM",""))) -> SIM | V12: =IF(ISERROR(IF(H12="","",IF(AND(YEAR(H12)=Cad_Inicial!$D$8,I12="Ativo",TODAY()-H12>90),"SIM",IF(AND(YEAR(H12)=Cad_Inicial!$D$8,I12-H12>90),"SIM","")))),"",IF(H12="","",IF(AND(YEAR(H12)=Cad_Inicial!$D$8,I12="Ativo",TODAY()-H12>90),"SIM",IF(AND(YEAR(H12)=Cad_Inicial!$D$8,I12-H12>90),"SIM","")))) -> SIM | W12: =IF(ISERROR(IF(H12="","",YEAR(H12))),"",IF(H12="","",YEAR(H12))) -> 2015 | X12: =IF(ISERROR(IF(H12="","",MONTH(H12))),"",IF(H12="","",MONTH(H12))) -> 1 | Y12: =IF(ISERROR(IF(I12="","",YEAR(I12))),"",IF(I12="","",YEAR(I12))) | Z12: =IF(ISERROR(IF(OR(I12="",I12="Ativo"),"",MONTH(I12))),"",IF(OR(I12="",I12="Ativo"),"",MONTH(I12))) | AA12: =IF(ISERROR(IF(W12="","",IF(AND(W12<=Cad_Inicial!$D$8,Y12>Cad_Inicial!$D$8),1,0))),"",IF(W12="","",IF(AND(W12<=Cad_Inicial!$D$8,Y12>Cad_Inicial!$D$8),1,0))) -> 1 | AB12: =IF(ISERROR(IF(W12="","",IF(AND(W12<=(Cad_Inicial!$D$8-1),Y12>Cad_Inicial!$D$8-1),1,0))),"",IF(W12="","",IF(W12="","",IF(AND(W12<=(Cad_Inicial!$D$8-1),Y12>Cad_Inicial!$D$8-1),1,0)))) -> 0 | AC12: =IF(ISERROR(IF(I12="Ativo","",VLOOKUP(C12,Lanç!$C$8:$E$208,3,0))),"",IF(I12="Ativo","",VLOOKUP(C12,Lanç!$C$8:$E$208,3,0))) | AG12: =IF(ISERROR(IF(Cad!C18="","",Cad!C18)),"",IF(Cad!C18="","",Cad!C18))
C13: ze 6 | D13: Masculino | E13: 34211 | F13: Pós-graduação completa | G13: Sócio | H13: 41704 | I13: Ativo | J13: 1 anos e 1 meses | L13: =IF(ISERROR(IF(G13="","",VLOOKUP(C13,Lanç_Promoções!$C$8:$F$2008,4,0))),G13,IF(G13="","",VLOOKUP(C13,Lanç_Promoções!$C$8:$F$2008,4,0))) -> Sócio | M13: =IF(ISERROR(IF(L13="","",VLOOKUP(L13,Cad!$C$8:$D$208,2,0))),"",IF(L13="","",VLOOKUP(L13,Cad!$C$8:$D$208,2,0))) -> Diretoria | N13: =IF(ISERROR(IF(E13="","",ROUND((TODAY()-E13)/365,0))),"",IF(E13="","",ROUND((TODAY()-E13)/365,0))) -> 28 | O13: =IF(ISERROR(IF(N13="","",IF(N13>60,"Mais de 60 anos",IF(N13>54,"54 a 60 anos",IF(N13>44,"44 a 53 anos",IF(N13>34,"34 a 43 anos",IF(N13>24,"24 a 33 anos","18 a 23 anos"))))))),"",IF(N13="","",IF(N13>60,"Mais de 60 anos",IF(N13>54,"54 a 60 anos",IF(N13>44,"44 a 53 anos",IF(N13>34,"34 a 43 anos",IF(N13>24,"24 a 33 anos","18 a 23 anos"))))))) -> 24 a 33 anos | P13: =IF(ISERROR(IF(W13="","",IF(AND(W13<=Cad_Inicial!$D$8,Y13>Cad_Inicial!$D$8),1,0))),"",IF(W13="","",IF(AND(W13<=Cad_Inicial!$D$8,Y13>Cad_Inicial!$D$8),1,0))) -> 1 | Q13: =IF(ISERROR(IF(W13="","",IF(AND(W13<=(Cad_Inicial!$D$8-1),Y13>Cad_Inicial!$D$8-1),1,0))),"",IF(W13="","",IF(W13="","",IF(AND(W13<=(Cad_Inicial!$D$8-1),Y13>Cad_Inicial!$D$8-1),1,0)))) -> 1 | R13: =IF(ISERROR(IF(I13="","",IF(I13="Ativo",TRUNC((TODAY()-H13)/30/12,0),TRUNC((I13-H13)/30/12,0)))),"",IF(I13="","",IF(I13="Ativo",TRUNC((TODAY()-H13)/30/12,0),TRUNC((I13-H13)/30/12,0)))) -> 7 | S13: =IF(ISERROR(IF(I13="","",IF(I13="Ativo",TRUNC(MOD((TODAY()-H13)/30,12),0),TRUNC(MOD((I13-H13)/30,12),0)))),"",IF(I13="","",IF(I13="Ativo",TRUNC(MOD((TODAY()-H13)/30,12),0),TRUNC(MOD((I13-H13)/30,12),0)))) -> 10 | T13: =IF(ISERROR((R13*12+S13)),"",(R13*12+S13)) -> 94 | U13: =IF(ISERROR(IF(H13="","",IF(YEAR(H13)<=Cad_Inicial!$D$8,"SIM",""))),"",IF(H13="","",IF(YEAR(H13)<=Cad_Inicial!$D$8,"SIM",""))) -> SIM | V13: =IF(ISERROR(IF(H13="","",IF(AND(YEAR(H13)=Cad_Inicial!$D$8,I13="Ativo",TODAY()-H13>90),"SIM",IF(AND(YEAR(H13)=Cad_Inicial!$D$8,I13-H13>90),"SIM","")))),"",IF(H13="","",IF(AND(YEAR(H13)=Cad_Inicial!$D$8,I13="Ativo",TODAY()-H13>90),"SIM",IF(AND(YEAR(H13)=Cad_Inicial!$D$8,I13-H13>90),"SIM","")))) | W13: =IF(ISERROR(IF(H13="","",YEAR(H13))),"",IF(H13="","",YEAR(H13))) -> 2014 | X13: =IF(ISERROR(IF(H13="","",MONTH(H13))),"",IF(H13="","",MONTH(H13))) -> 3 | Y13: =IF(ISERROR(IF(I13="","",YEAR(I13))),"",IF(I13="","",YEAR(I13))) | Z13: =IF(ISERROR(IF(OR(I13="",I13="Ativo"),"",MONTH(I13))),"",IF(OR(I13="",I13="Ativo"),"",MONTH(I13))) | AA13: =IF(ISERROR(IF(W13="","",IF(AND(W13<=Cad_Inicial!$D$8,Y13>Cad_Inicial!$D$8),1,0))),"",IF(W13="","",IF(AND(W13<=Cad_Inicial!$D$8,Y13>Cad_Inicial!$D$8),1,0))) -> 1 | AB13: =IF(ISERROR(IF(W13="","",IF(AND(W13<=(Cad_Inicial!$D$8-1),Y13>Cad_Inicial!$D$8-1),1,0))),"",IF(W13="","",IF(W13="","",IF(AND(W13<=(Cad_Inicial!$D$8-1),Y13>Cad_Inicial!$D$8-1),1,0)))) -> 1 | AC13: =IF(ISERROR(IF(I13="Ativo","",VLOOKUP(C13,Lanç!$C$8:$E$208,3,0))),"",IF(I13="Ativo","",VLOOKUP(C13,Lanç!$C$8:$E$208,3,0))) | AG13: =IF(ISERROR(IF(Cad!C19="","",Cad!C19)),"",IF(Cad!C19="","",Cad!C19))
C14: ze 7 | D14: Masculino | E14: 31310 | F14: Ensino fundamental | G14: Designer I | H14: 41275 | I14: Ativo | J14: 2 anos e 3 meses | L14: =IF(ISERROR(IF(G14="","",VLOOKUP(C14,Lanç_Promoções!$C$8:$F$2008,4,0))),G14,IF(G14="","",VLOOKUP(C14,Lanç_Promoções!$C$8:$F$2008,4,0))) -> Designer I | M14: =IF(ISERROR(IF(L14="","",VLOOKUP(L14,Cad!$C$8:$D$208,2,0))),"",IF(L14="","",VLOOKUP(L14,Cad!$C$8:$D$208,2,0))) -> Operacional | N14: =IF(ISERROR(IF(E14="","",ROUND((TODAY()-E14)/365,0))),"",IF(E14="","",ROUND((TODAY()-E14)/365,0))) -> 36 | O14: =IF(ISERROR(IF(N14="","",IF(N14>60,"Mais de 60 anos",IF(N14>54,"54 a 60 anos",IF(N14>44,"44 a 53 anos",IF(N14>34,"34 a 43 anos",IF(N14>24,"24 a 33 anos","18 a 23 anos"))))))),"",IF(N14="","",IF(N14>60,"Mais de 60 anos",IF(N14>54,"54 a 60 anos",IF(N14>44,"44 a 53 anos",IF(N14>34,"34 a 43 anos",IF(N14>24,"24 a 33 anos","18 a 23 anos"))))))) -> 34 a 43 anos | P14: =IF(ISERROR(IF(W14="","",IF(AND(W14<=Cad_Inicial!$D$8,Y14>Cad_Inicial!$D$8),1,0))),"",IF(W14="","",IF(AND(W14<=Cad_Inicial!$D$8,Y14>Cad_Inicial!$D$8),1,0))) -> 1 | Q14: =IF(ISERROR(IF(W14="","",IF(AND(W14<=(Cad_Inicial!$D$8-1),Y14>Cad_Inicial!$D$8-1),1,0))),"",IF(W14="","",IF(W14="","",IF(AND(W14<=(Cad_Inicial!$D$8-1),Y14>Cad_Inicial!$D$8-1),1,0)))) -> 1 | R14: =IF(ISERROR(IF(I14="","",IF(I14="Ativo",TRUNC((TODAY()-H14)/30/12,0),TRUNC((I14-H14)/30/12,0)))),"",IF(I14="","",IF(I14="Ativo",TRUNC((TODAY()-H14)/30/12,0),TRUNC((I14-H14)/30/12,0)))) -> 9 | S14: =IF(ISERROR(IF(I14="","",IF(I14="Ativo",TRUNC(MOD((TODAY()-H14)/30,12),0),TRUNC(MOD((I14-H14)/30,12),0)))),"",IF(I14="","",IF(I14="Ativo",TRUNC(MOD((TODAY()-H14)/30,12),0),TRUNC(MOD((I14-H14)/30,12),0)))) -> 0 | T14: =IF(ISERROR((R14*12+S14)),"",(R14*12+S14)) -> 108 | U14: =IF(ISERROR(IF(H14="","",IF(YEAR(H14)<=Cad_Inicial!$D$8,"SIM",""))),"",IF(H14="","",IF(YEAR(H14)<=Cad_Inicial!$D$8,"SIM",""))) -> SIM | V14: =IF(ISERROR(IF(H14="","",IF(AND(YEAR(H14)=Cad_Inicial!$D$8,I14="Ativo",TODAY()-H14>90),"SIM",IF(AND(YEAR(H14)=Cad_Inicial!$D$8,I14-H14>90),"SIM","")))),"",IF(H14="","",IF(AND(YEAR(H14)=Cad_Inicial!$D$8,I14="Ativo",TODAY()-H14>90),"SIM",IF(AND(YEAR(H14)=Cad_Inicial!$D$8,I14-H14>90),"SIM","")))) | W14: =IF(ISERROR(IF(H14="","",YEAR(H14))),"",IF(H14="","",YEAR(H14))) -> 2013 | X14: =IF(ISERROR(IF(H14="","",MONTH(H14))),"",IF(H14="","",MONTH(H14))) -> 1 | Y14: =IF(ISERROR(IF(I14="","",YEAR(I14))),"",IF(I14="","",YEAR(I14))) | Z14: =IF(ISERROR(IF(OR(I14="",I14="Ativo"),"",MONTH(I14))),"",IF(OR(I14="",I14="Ativo"),"",MONTH(I14))) | AA14: =IF(ISERROR(IF(W14="","",IF(AND(W14<=Cad_Inicial!$D$8,Y14>Cad_Inicial!$D$8),1,0))),"",IF(W14="","",IF(AND(W14<=Cad_Inicial!$D$8,Y14>Cad_Inicial!$D$8),1,0))) -> 1 | AB14: =IF(ISERROR(IF(W14="","",IF(AND(W14<=(Cad_Inicial!$D$8-1),Y14>Cad_Inicial!$D$8-1),1,0))),"",IF(W14="","",IF(W14="","",IF(AND(W14<=(Cad_Inicial!$D$8-1),Y14>Cad_Inicial!$D$8-1),1,0)))) -> 1 | AC14: =IF(ISERROR(IF(I14="Ativo","",VLOOKUP(C14,Lanç!$C$8:$E$208,3,0))),"",IF(I14="Ativo","",VLOOKUP(C14,Lanç!$C$8:$E$208,3,0))) | AG14: =IF(ISERROR(IF(Cad!C20="","",Cad!C20)),"",IF(Cad!C20="","",Cad!C20))
C15: ze 8 | D15: Masculino | E15: 29264 | F15: Superior incompleto | G15: Designer II | H15: 41610 | I15: Ativo | J15: 1 anos e 4 meses | L15: =IF(ISERROR(IF(G15="","",VLOOKUP(C15,Lanç_Promoções!$C$8:$F$2008,4,0))),G15,IF(G15="","",VLOOKUP(C15,Lanç_Promoções!$C$8:$F$2008,4,0))) -> Designer II | M15: =IF(ISERROR(IF(L15="","",VLOOKUP(L15,Cad!$C$8:$D$208,2,0))),"",IF(L15="","",VLOOKUP(L15,Cad!$C$8:$D$208,2,0))) -> Operacional | N15: =IF(ISERROR(IF(E15="","",ROUND((TODAY()-E15)/365,0))),"",IF(E15="","",ROUND((TODAY()-E15)/365,0))) -> 42 | O15: =IF(ISERROR(IF(N15="","",IF(N15>60,"Mais de 60 anos",IF(N15>54,"54 a 60 anos",IF(N15>44,"44 a 53 anos",IF(N15>34,"34 a 43 anos",IF(N15>24,"24 a 33 anos","18 a 23 anos"))))))),"",IF(N15="","",IF(N15>60,"Mais de 60 anos",IF(N15>54,"54 a 60 anos",IF(N15>44,"44 a 53 anos",IF(N15>34,"34 a 43 anos",IF(N15>24,"24 a 33 anos","18 a 23 anos"))))))) -> 34 a 43 anos | P15: =IF(ISERROR(IF(W15="","",IF(AND(W15<=Cad_Inicial!$D$8,Y15>Cad_Inicial!$D$8),1,0))),"",IF(W15="","",IF(AND(W15<=Cad_Inicial!$D$8,Y15>Cad_Inicial!$D$8),1,0))) -> 1 | Q15: =IF(ISERROR(IF(W15="","",IF(AND(W15<=(Cad_Inicial!$D$8-1),Y15>Cad_Inicial!$D$8-1),1,0))),"",IF(W15="","",IF(W15="","",IF(AND(W15<=(Cad_Inicial!$D$8-1),Y15>Cad_Inicial!$D$8-1),1,0)))) -> 1 | R15: =IF(ISERROR(IF(I15="","",IF(I15="Ativo",TRUNC((TODAY()-H15)/30/12,0),TRUNC((I15-H15)/30/12,0)))),"",IF(I15="","",IF(I15="Ativo",TRUNC((TODAY()-H15)/30/12,0),TRUNC((I15-H15)/30/12,0)))) -> 8 | S15: =IF(ISERROR(IF(I15="","",IF(I15="Ativo",TRUNC(MOD((TODAY()-H15)/30,12),0),TRUNC(MOD((I15-H15)/30,12),0)))),"",IF(I15="","",IF(I15="Ativo",TRUNC(MOD((TODAY()-H15)/30,12),0),TRUNC(MOD((I15-H15)/30,12),0)))) -> 1 | T15: =IF(ISERROR((R15*12+S15)),"",(R15*12+S15)) -> 97 | U15: =IF(ISERROR(IF(H15="","",IF(YEAR(H15)<=Cad_Inicial!$D$8,"SIM",""))),"",IF(H15="","",IF(YEAR(H15)<=Cad_Inicial!$D$8,"SIM",""))) -> SIM | V15: =IF(ISERROR(IF(H15="","",IF(AND(YEAR(H15)=Cad_Inicial!$D$8,I15="Ativo",TODAY()-H15>90),"SIM",IF(AND(YEAR(H15)=Cad_Inicial!$D$8,I15-H15>90),"SIM","")))),"",IF(H15="","",IF(AND(YEAR(H15)=Cad_Inicial!$D$8,I15="Ativo",TODAY()-H15>90),"SIM",IF(AND(YEAR(H15)=Cad_Inicial!$D$8,I15-H15>90),"SIM","")))) | W15: =IF(ISERROR(IF(H15="","",YEAR(H15))),"",IF(H15="","",YEAR(H15))) -> 2013 | X15: =IF(ISERROR(IF(H15="","",MONTH(H15))),"",IF(H15="","",MONTH(H15))) -> 12 | Y15: =IF(ISERROR(IF(I15="","",YEAR(I15))),"",IF(I15="","",YEAR(I15))) | Z15: =IF(ISERROR(IF(OR(I15="",I15="Ativo"),"",MONTH(I15))),"",IF(OR(I15="",I15="Ativo"),"",MONTH(I15))) | AA15: =IF(ISERROR(IF(W15="","",IF(AND(W15<=Cad_Inicial!$D$8,Y15>Cad_Inicial!$D$8),1,0))),"",IF(W15="","",IF(AND(W15<=Cad_Inicial!$D$8,Y15>Cad_Inicial!$D$8),1,0))) -> 1 | AB15: =IF(ISERROR(IF(W15="","",IF(AND(W15<=(Cad_Inicial!$D$8-1),Y15>Cad_Inicial!$D$8-1),1,0))),"",IF(W15="","",IF(W15="","",IF(AND(W15<=(Cad_Inicial!$D$8-1),Y15>Cad_Inicial!$D$8-1),1,0)))) -> 1 | AC15: =IF(ISERROR(IF(I15="Ativo","",VLOOKUP(C15,Lanç!$C$8:$E$208,3,0))),"",IF(I15="Ativo","",VLOOKUP(C15,Lanç!$C$8:$E$208,3,0))) | AG15: =IF(ISERROR(IF(Cad!C21="","",Cad!C21)),"",IF(Cad!C21="","",Cad!C21))
C16: ze 9 | D16: Feminino | E16: 29774 | F16: Superior completo | G16: Designer III | H16: 41673 | I16: Ativo | J16: 1 anos e 2 meses | L16: =IF(ISERROR(IF(G16="","",VLOOKUP(C16,Lanç_Promoções!$C$8:$F$2008,4,0))),G16,IF(G16="","",VLOOKUP(C16,Lanç_Promoções!$C$8:$F$2008,4,0))) -> Designer III | M16: =IF(ISERROR(IF(L16="","",VLOOKUP(L16,Cad!$C$8:$D$208,2,0))),"",IF(L16="","",VLOOKUP(L16,Cad!$C$8:$D$208,2,0))) -> Operacional | N16: =IF(ISERROR(IF(E16="","",ROUND((TODAY()-E16)/365,0))),"",IF(E16="","",ROUND((TODAY()-E16)/365,0))) -> 40 | O16: =IF(ISERROR(IF(N16="","",IF(N16>60,"Mais de 60 anos",IF(N16>54,"54 a 60 anos",IF(N16>44,"44 a 53 anos",IF(N16>34,"34 a 43 anos",IF(N16>24,"24 a 33 anos","18 a 23 anos"))))))),"",IF(N16="","",IF(N16>60,"Mais de 60 anos",IF(N16>54,"54 a 60 anos",IF(N16>44,"44 a 53 anos",IF(N16>34,"34 a 43 anos",IF(N16>24,"24 a 33 anos","18 a 23 anos"))))))) -> 34 a 43 anos | P16: =IF(ISERROR(IF(W16="","",IF(AND(W16<=Cad_Inicial!$D$8,Y16>Cad_Inicial!$D$8),1,0))),"",IF(W16="","",IF(AND(W16<=Cad_Inicial!$D$8,Y16>Cad_Inicial!$D$8),1,0))) -> 1 | Q16: =IF(ISERROR(IF(W16="","",IF(AND(W16<=(Cad_Inicial!$D$8-1),Y16>Cad_Inicial!$D$8-1),1,0))),"",IF(W16="","",IF(W16="","",IF(AND(W16<=(Cad_Inicial!$D$8-1),Y16>Cad_Inicial!$D$8-1),1,0)))) -> 1 | R16: =IF(ISERROR(IF(I16="","",IF(I16="Ativo",TRUNC((TODAY()-H16)/30/12,0),TRUNC((I16-H16)/30/12,0)))),"",IF(I16="","",IF(I16="Ativo",TRUNC((TODAY()-H16)/30/12,0),TRUNC((I16-H16)/30/12,0)))) -> 7 | S16: =IF(ISERROR(IF(I16="","",IF(I16="Ativo",TRUNC(MOD((TODAY()-H16)/30,12),0),TRUNC(MOD((I16-H16)/30,12),0)))),"",IF(I16="","",IF(I16="Ativo",TRUNC(MOD((TODAY()-H16)/30,12),0),TRUNC(MOD((I16-H16)/30,12),0)))) -> 11 | T16: =IF(ISERROR((R16*12+S16)),"",(R16*12+S16)) -> 95 | U16: =IF(ISERROR(IF(H16="","",IF(YEAR(H16)<=Cad_Inicial!$D$8,"SIM",""))),"",IF(H16="","",IF(YEAR(H16)<=Cad_Inicial!$D$8,"SIM",""))) -> SIM | V16: =IF(ISERROR(IF(H16="","",IF(AND(YEAR(H16)=Cad_Inicial!$D$8,I16="Ativo",TODAY()-H16>90),"SIM",IF(AND(YEAR(H16)=Cad_Inicial!$D$8,I16-H16>90),"SIM","")))),"",IF(H16="","",IF(AND(YEAR(H16)=Cad_Inicial!$D$8,I16="Ativo",TODAY()-H16>90),"SIM",IF(AND(YEAR(H16)=Cad_Inicial!$D$8,I16-H16>90),"SIM","")))) | W16: =IF(ISERROR(IF(H16="","",YEAR(H16))),"",IF(H16="","",YEAR(H16))) -> 2014 | X16: =IF(ISERROR(IF(H16="","",MONTH(H16))),"",IF(H16="","",MONTH(H16))) -> 2 | Y16: =IF(ISERROR(IF(I16="","",YEAR(I16))),"",IF(I16="","",YEAR(I16))) | Z16: =IF(ISERROR(IF(OR(I16="",I16="Ativo"),"",MONTH(I16))),"",IF(OR(I16="",I16="Ativo"),"",MONTH(I16))) | AA16: =IF(ISERROR(IF(W16="","",IF(AND(W16<=Cad_Inicial!$D$8,Y16>Cad_Inicial!$D$8),1,0))),"",IF(W16="","",IF(AND(W16<=Cad_Inicial!$D$8,Y16>Cad_Inicial!$D$8),1,0))) -> 1 | AB16: =IF(ISERROR(IF(W16="","",IF(AND(W16<=(Cad_Inicial!$D$8-1),Y16>Cad_Inicial!$D$8-1),1,0))),"",IF(W16="","",IF(W16="","",IF(AND(W16<=(Cad_Inicial!$D$8-1),Y16>Cad_Inicial!$D$8-1),1,0)))) -> 1 | AC16: =IF(ISERROR(IF(I16="Ativo","",VLOOKUP(C16,Lanç!$C$8:$E$208,3,0))),"",IF(I16="Ativo","",VLOOKUP(C16,Lanç!$C$8:$E$208,3,0))) | AG16: =IF(ISERROR(IF(Cad!C22="","",Cad!C22)),"",IF(Cad!C22="","",Cad!C22))
C17: ze 10 | D17: Masculino | E17: 30764 | F17: Superior completo | G17: Dir de Arte | H17: 41674 | I17: Ativo | J17: 1 anos e 2 meses | L17: =IF(ISERROR(IF(G17="","",VLOOKUP(C17,Lanç_Promoções!$C$8:$F$2008,4,0))),G17,IF(G17="","",VLOOKUP(C17,Lanç_Promoções!$C$8:$F$2008,4,0))) -> Dir de Arte | M17: =IF(ISERROR(IF(L17="","",VLOOKUP(L17,Cad!$C$8:$D$208,2,0))),"",IF(L17="","",VLOOKUP(L17,Cad!$C$8:$D$208,2,0))) -> Gerencial | N17: =IF(ISERROR(IF(E17="","",ROUND((TODAY()-E17)/365,0))),"",IF(E17="","",ROUND((TODAY()-E17)/365,0))) -> 38 | O17: =IF(ISERROR(IF(N17="","",IF(N17>60,"Mais de 60 anos",IF(N17>54,"54 a 60 anos",IF(N17>44,"44 a 53 anos",IF(N17>34,"34 a 43 anos",IF(N17>24,"24 a 33 anos","18 a 23 anos"))))))),"",IF(N17="","",IF(N17>60,"Mais de 60 anos",IF(N17>54,"54 a 60 anos",IF(N17>44,"44 a 53 anos",IF(N17>34,"34 a 43 anos",IF(N17>24,"24 a 33 anos","18 a 23 anos"))))))) -> 34 a 43 anos | P17: =IF(ISERROR(IF(W17="","",IF(AND(W17<=Cad_Inicial!$D$8,Y17>Cad_Inicial!$D$8),1,0))),"",IF(W17="","",IF(AND(W17<=Cad_Inicial!$D$8,Y17>Cad_Inicial!$D$8),1,0))) -> 1 | Q17: =IF(ISERROR(IF(W17="","",IF(AND(W17<=(Cad_Inicial!$D$8-1),Y17>Cad_Inicial!$D$8-1),1,0))),"",IF(W17="","",IF(W17="","",IF(AND(W17<=(Cad_Inicial!$D$8-1),Y17>Cad_Inicial!$D$8-1),1,0)))) -> 1 | R17: =IF(ISERROR(IF(I17="","",IF(I17="Ativo",TRUNC((TODAY()-H17)/30/12,0),TRUNC((I17-H17)/30/12,0)))),"",IF(I17="","",IF(I17="Ativo",TRUNC((TODAY()-H17)/30/12,0),TRUNC((I17-H17)/30/12,0)))) -> 7 | S17: =IF(ISERROR(IF(I17="","",IF(I17="Ativo",TRUNC(MOD((TODAY()-H17)/30,12),0),TRUNC(MOD((I17-H17)/30,12),0)))),"",IF(I17="","",IF(I17="Ativo",TRUNC(MOD((TODAY()-H17)/30,12),0),TRUNC(MOD((I17-H17)/30,12),0)))) -> 11 | T17: =IF(ISERROR((R17*12+S17)),"",(R17*12+S17)) -> 95 | U17: =IF(ISERROR(IF(H17="","",IF(YEAR(H17)<=Cad_Inicial!$D$8,"SIM",""))),"",IF(H17="","",IF(YEAR(H17)<=Cad_Inicial!$D$8,"SIM",""))) -> SIM | V17: =IF(ISERROR(IF(H17="","",IF(AND(YEAR(H17)=Cad_Inicial!$D$8,I17="Ativo",TODAY()-H17>90),"SIM",IF(AND(YEAR(H17)=Cad_Inicial!$D$8,I17-H17>90),"SIM","")))),"",IF(H17="","",IF(AND(YEAR(H17)=Cad_Inicial!$D$8,I17="Ativo",TODAY()-H17>90),"SIM",IF(AND(YEAR(H17)=Cad_Inicial!$D$8,I17-H17>90),"SIM","")))) | W17: =IF(ISERROR(IF(H17="","",YEAR(H17))),"",IF(H17="","",YEAR(H17))) -> 2014 | X17: =IF(ISERROR(IF(H17="","",MONTH(H17))),"",IF(H17="","",MONTH(H17))) -> 2 | Y17: =IF(ISERROR(IF(I17="","",YEAR(I17))),"",IF(I17="","",YEAR(I17))) | Z17: =IF(ISERROR(IF(OR(I17="",I17="Ativo"),"",MONTH(I17))),"",IF(OR(I17="",I17="Ativo"),"",MONTH(I17))) | AA17: =IF(ISERROR(IF(W17="","",IF(AND(W17<=Cad_Inicial!$D$8,Y17>Cad_Inicial!$D$8),1,0))),"",IF(W17="","",IF(AND(W17<=Cad_Inicial!$D$8,Y17>Cad_Inicial!$D$8),1,0))) -> 1 | AB17: =IF(ISERROR(IF(W17="","",IF(AND(W17<=(Cad_Inicial!$D$8-1),Y17>Cad_Inicial!$D$8-1),1,0))),"",IF(W17="","",IF(W17="","",IF(AND(W17<=(Cad_Inicial!$D$8-1),Y17>Cad_Inicial!$D$8-1),1,0)))) -> 1 | AC17: =IF(ISERROR(IF(I17="Ativo","",VLOOKUP(C17,Lanç!$C$8:$E$208,3,0))),"",IF(I17="Ativo","",VLOOKUP(C17,Lanç!$C$8:$E$208,3,0))) | AG17: =IF(ISERROR(IF(Cad!C23="","",Cad!C23)),"",IF(Cad!C23="","",Cad!C23))
C18: ze 11 | D18: Feminino | E18: 28622 | F18: Superior completo | G18: Designer III | H18: 41644 | I18: Ativo | J18: 1 anos e 3 meses | L18: =IF(ISERROR(IF(G18="","",VLOOKUP(C18,Lanç_Promoções!$C$8:$F$2008,4,0))),G18,IF(G18="","",VLOOKUP(C18,Lanç_Promoções!$C$8:$F$2008,4,0))) -> Designer III | M18: =IF(ISERROR(IF(L18="","",VLOOKUP(L18,Cad!$C$8:$D$208,2,0))),"",IF(L18="","",VLOOKUP(L18,Cad!$C$8:$D$208,2,0))) -> Operacional | N18: =IF(ISERROR(IF(E18="","",ROUND((TODAY()-E18)/365,0))),"",IF(E18="","",ROUND((TODAY()-E18)/365,0))) -> 44 | O18: =IF(ISERROR(IF(N18="","",IF(N18>60,"Mais de 60 anos",IF(N18>54,"54 a 60 anos",IF(N18>44,"44 a 53 anos",IF(N18>34,"34 a 43 anos",IF(N18>24,"24 a 33 anos","18 a 23 anos"))))))),"",IF(N18="","",IF(N18>60,"Mais de 60 anos",IF(N18>54,"54 a 60 anos",IF(N18>44,"44 a 53 anos",IF(N18>34,"34 a 43 anos",IF(N18>24,"24 a 33 anos","18 a 23 anos"))))))) -> 34 a 43 anos | P18: =IF(ISERROR(IF(W18="","",IF(AND(W18<=Cad_Inicial!$D$8,Y18>Cad_Inicial!$D$8),1,0))),"",IF(W18="","",IF(AND(W18<=Cad_Inicial!$D$8,Y18>Cad_Inicial!$D$8),1,0))) -> 1 | Q18: =IF(ISERROR(IF(W18="","",IF(AND(W18<=(Cad_Inicial!$D$8-1),Y18>Cad_Inicial!$D$8-1),1,0))),"",IF(W18="","",IF(W18="","",IF(AND(W18<=(Cad_Inicial!$D$8-1),Y18>Cad_Inicial!$D$8-1),1,0)))) -> 1 | R18: =IF(ISERROR(IF(I18="","",IF(I18="Ativo",TRUNC((TODAY()-H18)/30/12,0),TRUNC((I18-H18)/30/12,0)))),"",IF(I18="","",IF(I18="Ativo",TRUNC((TODAY()-H18)/30/12,0),TRUNC((I18-H18)/30/12,0)))) -> 8 | S18: =IF(ISERROR(IF(I18="","",IF(I18="Ativo",TRUNC(MOD((TODAY()-H18)/30,12),0),TRUNC(MOD((I18-H18)/30,12),0)))),"",IF(I18="","",IF(I18="Ativo",TRUNC(MOD((TODAY()-H18)/30,12),0),TRUNC(MOD((I18-H18)/30,12),0)))) -> 0 | T18: =IF(ISERROR((R18*12+S18)),"",(R18*12+S18)) -> 96 | U18: =IF(ISERROR(IF(H18="","",IF(YEAR(H18)<=Cad_Inicial!$D$8,"SIM",""))),"",IF(H18="","",IF(YEAR(H18)<=Cad_Inicial!$D$8,"SIM",""))) -> SIM | V18: =IF(ISERROR(IF(H18="","",IF(AND(YEAR(H18)=Cad_Inicial!$D$8,I18="Ativo",TODAY()-H18>90),"SIM",IF(AND(YEAR(H18)=Cad_Inicial!$D$8,I18-H18>90),"SIM","")))),"",IF(H18="","",IF(AND(YEAR(H18)=Cad_Inicial!$D$8,I18="Ativo",TODAY()-H18>90),"SIM",IF(AND(YEAR(H18)=Cad_Inicial!$D$8,I18-H18>90),"SIM","")))) | W18: =IF(ISERROR(IF(H18="","",YEAR(H18))),"",IF(H18="","",YEAR(H18))) -> 2014 | X18: =IF(ISERROR(IF(H18="","",MONTH(H18))),"",IF(H18="","",MONTH(H18))) -> 1 | Y18: =IF(ISERROR(IF(I18="","",YEAR(I18))),"",IF(I18="","",YEAR(I18))) | Z18: =IF(ISERROR(IF(OR(I18="",I18="Ativo"),"",MONTH(I18))),"",IF(OR(I18="",I18="Ativo"),"",MONTH(I18))) | AA18: =IF(ISERROR(IF(W18="","",IF(AND(W18<=Cad_Inicial!$D$8,Y18>Cad_Inicial!$D$8),1,0))),"",IF(W18="","",IF(AND(W18<=Cad_Inicial!$D$8,Y18>Cad_Inicial!$D$8),1,0))) -> 1 | AB18: =IF(ISERROR(IF(W18="","",IF(AND(W18<=(Cad_Inicial!$D$8-1),Y18>Cad_Inicial!$D$8-1),1,0))),"",IF(W18="","",IF(W18="","",IF(AND(W18<=(Cad_Inicial!$D$8-1),Y18>Cad_Inicial!$D$8-1),1,0)))) -> 1 | AC18: =IF(ISERROR(IF(I18="Ativo","",VLOOKUP(C18,Lanç!$C$8:$E$208,3,0))),"",IF(I18="Ativo","",VLOOKUP(C18,Lanç!$C$8:$E$208,3,0))) | AG18: =IF(ISERROR(IF(Cad!C24="","",Cad!C24)),"",IF(Cad!C24="","",Cad!C24))
C19: ze 12 | D19: Masculino | E19: 34211 | F19: Pós-graduação completa | G19: Sócio | H19: 41704 | I19: Ativo | J19: 1 anos e 1 meses | L19: =IF(ISERROR(IF(G19="","",VLOOKUP(C19,Lanç_Promoções!$C$8:$F$2008,4,0))),G19,IF(G19="","",VLOOKUP(C19,Lanç_Promoções!$C$8:$F$2008,4,0))) -> Sócio | M19: =IF(ISERROR(IF(L19="","",VLOOKUP(L19,Cad!$C$8:$D$208,2,0))),"",IF(L19="","",VLOOKUP(L19,Cad!$C$8:$D$208,2,0))) -> Diretoria | N19: =IF(ISERROR(IF(E19="","",ROUND((TODAY()-E19)/365,0))),"",IF(E19="","",ROUND((TODAY()-E19)/365,0))) -> 28 | O19: =IF(ISERROR(IF(N19="","",IF(N19>60,"Mais de 60 anos",IF(N19>54,"54 a 60 anos",IF(N19>44,"44 a 53 anos",IF(N19>34,"34 a 43 anos",IF(N19>24,"24 a 33 anos","18 a 23 anos"))))))),"",IF(N19="","",IF(N19>60,"Mais de 60 anos",IF(N19>54,"54 a 60 anos",IF(N19>44,"44 a 53 anos",IF(N19>34,"34 a 43 anos",IF(N19>24,"24 a 33 anos","18 a 23 anos"))))))) -> 24 a 33 anos | P19: =IF(ISERROR(IF(W19="","",IF(AND(W19<=Cad_Inicial!$D$8,Y19>Cad_Inicial!$D$8),1,0))),"",IF(W19="","",IF(AND(W19<=Cad_Inicial!$D$8,Y19>Cad_Inicial!$D$8),1,0))) -> 1 | Q19: =IF(ISERROR(IF(W19="","",IF(AND(W19<=(Cad_Inicial!$D$8-1),Y19>Cad_Inicial!$D$8-1),1,0))),"",IF(W19="","",IF(W19="","",IF(AND(W19<=(Cad_Inicial!$D$8-1),Y19>Cad_Inicial!$D$8-1),1,0)))) -> 1 | R19: =IF(ISERROR(IF(I19="","",IF(I19="Ativo",TRUNC((TODAY()-H19)/30/12,0),TRUNC((I19-H19)/30/12,0)))),"",IF(I19="","",IF(I19="Ativo",TRUNC((TODAY()-H19)/30/12,0),TRUNC((I19-H19)/30/12,0)))) -> 7 | S19: =IF(ISERROR(IF(I19="","",IF(I19="Ativo",TRUNC(MOD((TODAY()-H19)/30,12),0),TRUNC(MOD((I19-H19)/30,12),0)))),"",IF(I19="","",IF(I19="Ativo",TRUNC(MOD((TODAY()-H19)/30,12),0),TRUNC(MOD((I19-H19)/30,12),0)))) -> 10 | T19: =IF(ISERROR((R19*12+S19)),"",(R19*12+S19)) -> 94 | U19: =IF(ISERROR(IF(H19="","",IF(YEAR(H19)<=Cad_Inicial!$D$8,"SIM",""))),"",IF(H19="","",IF(YEAR(H19)<=Cad_Inicial!$D$8,"SIM",""))) -> SIM | V19: =IF(ISERROR(IF(H19="","",IF(AND(YEAR(H19)=Cad_Inicial!$D$8,I19="Ativo",TODAY()-H19>90),"SIM",IF(AND(YEAR(H19)=Cad_Inicial!$D$8,I19-H19>90),"SIM","")))),"",IF(H19="","",IF(AND(YEAR(H19)=Cad_Inicial!$D$8,I19="Ativo",TODAY()-H19>90),"SIM",IF(AND(YEAR(H19)=Cad_Inicial!$D$8,I19-H19>90),"SIM","")))) | W19: =IF(ISERROR(IF(H19="","",YEAR(H19))),"",IF(H19="","",YEAR(H19))) -> 2014 | X19: =IF(ISERROR(IF(H19="","",MONTH(H19))),"",IF(H19="","",MONTH(H19))) -> 3 | Y19: =IF(ISERROR(IF(I19="","",YEAR(I19))),"",IF(I19="","",YEAR(I19))) | Z19: =IF(ISERROR(IF(OR(I19="",I19="Ativo"),"",MONTH(I19))),"",IF(OR(I19="",I19="Ativo"),"",MONTH(I19))) | AA19: =IF(ISERROR(IF(W19="","",IF(AND(W19<=Cad_Inicial!$D$8,Y19>Cad_Inicial!$D$8),1,0))),"",IF(W19="","",IF(AND(W19<=Cad_Inicial!$D$8,Y19>Cad_Inicial!$D$8),1,0))) -> 1 | AB19: =IF(ISERROR(IF(W19="","",IF(AND(W19<=(Cad_Inicial!$D$8-1),Y19>Cad_Inicial!$D$8-1),1,0))),"",IF(W19="","",IF(W19="","",IF(AND(W19<=(Cad_Inicial!$D$8-1),Y19>Cad_Inicial!$D$8-1),1,0)))) -> 1 | AC19: =IF(ISERROR(IF(I19="Ativo","",VLOOKUP(C19,Lanç!$C$8:$E$208,3,0))),"",IF(I19="Ativo","",VLOOKUP(C19,Lanç!$C$8:$E$208,3,0))) | AG19: =IF(ISERROR(IF(Cad!C25="","",Cad!C25)),"",IF(Cad!C25="","",Cad!C25))
L20: =IF(ISERROR(IF(G20="","",VLOOKUP(C20,Lanç_Promoções!$C$8:$F$2008,4,0))),G20,IF(G20="","",VLOOKUP(C20,Lanç_Promoções!$C$8:$F$2008,4,0))) | M20: =IF(ISERROR(IF(L20="","",VLOOKUP(L20,Cad!$C$8:$D$208,2,0))),"",IF(L20="","",VLOOKUP(L20,Cad!$C$8:$D$208,2,0))) | N20: =IF(ISERROR(IF(E20="","",ROUND((TODAY()-E20)/365,0))),"",IF(E20="","",ROUND((TODAY()-E20)/365,0))) | O20: =IF(ISERROR(IF(N20="","",IF(N20>60,"Mais de 60 anos",IF(N20>54,"54 a 60 anos",IF(N20>44,"44 a 53 anos",IF(N20>34,"34 a 43 anos",IF(N20>24,"24 a 33 anos","18 a 23 anos"))))))),"",IF(N20="","",IF(N20>60,"Mais de 60 anos",IF(N20>54,"54 a 60 anos",IF(N20>44,"44 a 53 anos",IF(N20>34,"34 a 43 anos",IF(N20>24,"24 a 33 anos","18 a 23 anos"))))))) | P20: =IF(ISERROR(IF(W20="","",IF(AND(W20<=Cad_Inicial!$D$8,Y20>Cad_Inicial!$D$8),1,0))),"",IF(W20="","",IF(AND(W20<=Cad_Inicial!$D$8,Y20>Cad_Inicial!$D$8),1,0))) | Q20: =IF(ISERROR(IF(W20="","",IF(AND(W20<=(Cad_Inicial!$D$8-1),Y20>Cad_Inicial!$D$8-1),1,0))),"",IF(W20="","",IF(W20="","",IF(AND(W20<=(Cad_Inicial!$D$8-1),Y20>Cad_Inicial!$D$8-1),1,0)))) | R20: =IF(ISERROR(IF(I20="","",IF(I20="Ativo",TRUNC((TODAY()-H20)/30/12,0),TRUNC((I20-H20)/30/12,0)))),"",IF(I20="","",IF(I20="Ativo",TRUNC((TODAY()-H20)/30/12,0),TRUNC((I20-H20)/30/12,0)))) | S20: =IF(ISERROR(IF(I20="","",IF(I20="Ativo",TRUNC(MOD((TODAY()-H20)/30,12),0),TRUNC(MOD((I20-H20)/30,12),0)))),"",IF(I20="","",IF(I20="Ativo",TRUNC(MOD((TODAY()-H20)/30,12),0),TRUNC(MOD((I20-H20)/30,12),0)))) | T20: =IF(ISERROR((R20*12+S20)),"",(R20*12+S20)) | U20: =IF(ISERROR(IF(H20="","",IF(YEAR(H20)<=Cad_Inicial!$D$8,"SIM",""))),"",IF(H20="","",IF(YEAR(H20)<=Cad_Inicial!$D$8,"SIM",""))) | V20: =IF(ISERROR(IF(H20="","",IF(AND(YEAR(H20)=Cad_Inicial!$D$8,I20="Ativo",TODAY()-H20>90),"SIM",IF(AND(YEAR(H20)=Cad_Inicial!$D$8,I20-H20>90),"SIM","")))),"",IF(H20="","",IF(AND(YEAR(H20)=Cad_Inicial!$D$8,I20="Ativo",TODAY()-H20>90),"SIM",IF(AND(YEAR(H20)=Cad_Inicial!$D$8,I20-H20>90),"SIM","")))) | W20: =IF(ISERROR(IF(H20="","",YEAR(H20))),"",IF(H20="","",YEAR(H20))) | X20: =IF(ISERROR(IF(H20="","",MONTH(H20))),"",IF(H20="","",MONTH(H20))) | Y20: =IF(ISERROR(IF(I20="","",YEAR(I20))),"",IF(I20="","",YEAR(I20))) | Z20: =IF(ISERROR(IF(OR(I20="",I20="Ativo"),"",MONTH(I20))),"",IF(OR(I20="",I20="Ativo"),"",MONTH(I20))) | AA20: =IF(ISERROR(IF(W20="","",IF(AND(W20<=Cad_Inicial!$D$8,Y20>Cad_Inicial!$D$8),1,0))),"",IF(W20="","",IF(AND(W20<=Cad_Inicial!$D$8,Y20>Cad_Inicial!$D$8),1,0))) | AB20: =IF(ISERROR(IF(W20="","",IF(AND(W20<=(Cad_Inicial!$D$8-1),Y20>Cad_Inicial!$D$8-1),1,0))),"",IF(W20="","",IF(W20="","",IF(AND(W20<=(Cad_Inicial!$D$8-1),Y20>Cad_Inicial!$D$8-1),1,0)))) | AC20: =IF(ISERROR(IF(I20="Ativo","",VLOOKUP(C20,Lanç!$C$8:$E$208,3,0))),"",IF(I20="Ativo","",VLOOKUP(C20,Lanç!$C$8:$E$208,3,0))) | AG20: =IF(ISERROR(IF(Cad!C26="","",Cad!C26)),"",IF(Cad!C26="","",Cad!C26))
L21: =IF(ISERROR(IF(G21="","",VLOOKUP(C21,Lanç_Promoções!$C$8:$F$2008,4,0))),G21,IF(G21="","",VLOOKUP(C21,Lanç_Promoções!$C$8:$F$2008,4,0))) | M21: =IF(ISERROR(IF(L21="","",VLOOKUP(L21,Cad!$C$8:$D$208,2,0))),"",IF(L21="","",VLOOKUP(L21,Cad!$C$8:$D$208,2,0))) | N21: =IF(ISERROR(IF(E21="","",ROUND((TODAY()-E21)/365,0))),"",IF(E21="","",ROUND((TODAY()-E21)/365,0))) | O21: =IF(ISERROR(IF(N21="","",IF(N21>60,"Mais de 60 anos",IF(N21>54,"54 a 60 anos",IF(N21>44,"44 a 53 anos",IF(N21>34,"34 a 43 anos",IF(N21>24,"24 a 33 anos","18 a 23 anos"))))))),"",IF(N21="","",IF(N21>60,"Mais de 60 anos",IF(N21>54,"54 a 60 anos",IF(N21>44,"44 a 53 anos",IF(N21>34,"34 a 43 anos",IF(N21>24,"24 a 33 anos","18 a 23 anos"))))))) | P21: =IF(ISERROR(IF(W21="","",IF(AND(W21<=Cad_Inicial!$D$8,Y21>Cad_Inicial!$D$8),1,0))),"",IF(W21="","",IF(AND(W21<=Cad_Inicial!$D$8,Y21>Cad_Inicial!$D$8),1,0))) | Q21: =IF(ISERROR(IF(W21="","",IF(AND(W21<=(Cad_Inicial!$D$8-1),Y21>Cad_Inicial!$D$8-1),1,0))),"",IF(W21="","",IF(W21="","",IF(AND(W21<=(Cad_Inicial!$D$8-1),Y21>Cad_Inicial!$D$8-1),1,0)))) | R21: =IF(ISERROR(IF(I21="","",IF(I21="Ativo",TRUNC((TODAY()-H21)/30/12,0),TRUNC((I21-H21)/30/12,0)))),"",IF(I21="","",IF(I21="Ativo",TRUNC((TODAY()-H21)/30/12,0),TRUNC((I21-H21)/30/12,0)))) | S21: =IF(ISERROR(IF(I21="","",IF(I21="Ativo",TRUNC(MOD((TODAY()-H21)/30,12),0),TRUNC(MOD((I21-H21)/30,12),0)))),"",IF(I21="","",IF(I21="Ativo",TRUNC(MOD((TODAY()-H21)/30,12),0),TRUNC(MOD((I21-H21)/30,12),0)))) | T21: =IF(ISERROR((R21*12+S21)),"",(R21*12+S21)) | U21: =IF(ISERROR(IF(H21="","",IF(YEAR(H21)<=Cad_Inicial!$D$8,"SIM",""))),"",IF(H21="","",IF(YEAR(H21)<=Cad_Inicial!$D$8,"SIM",""))) | V21: =IF(ISERROR(IF(H21="","",IF(AND(YEAR(H21)=Cad_Inicial!$D$8,I21="Ativo",TODAY()-H21>90),"SIM",IF(AND(YEAR(H21)=Cad_Inicial!$D$8,I21-H21>90),"SIM","")))),"",IF(H21="","",IF(AND(YEAR(H21)=Cad_Inicial!$D$8,I21="Ativo",TODAY()-H21>90),"SIM",IF(AND(YEAR(H21)=Cad_Inicial!$D$8,I21-H21>90),"SIM","")))) | W21: =IF(ISERROR(IF(H21="","",YEAR(H21))),"",IF(H21="","",YEAR(H21))) | X21: =IF(ISERROR(IF(H21="","",MONTH(H21))),"",IF(H21="","",MONTH(H21))) | Y21: =IF(ISERROR(IF(I21="","",YEAR(I21))),"",IF(I21="","",YEAR(I21))) | Z21: =IF(ISERROR(IF(OR(I21="",I21="Ativo"),"",MONTH(I21))),"",IF(OR(I21="",I21="Ativo"),"",MONTH(I21))) | AA21: =IF(ISERROR(IF(W21="","",IF(AND(W21<=Cad_Inicial!$D$8,Y21>Cad_Inicial!$D$8),1,0))),"",IF(W21="","",IF(AND(W21<=Cad_Inicial!$D$8,Y21>Cad_Inicial!$D$8),1,0))) | AB21: =IF(ISERROR(IF(W21="","",IF(AND(W21<=(Cad_Inicial!$D$8-1),Y21>Cad_Inicial!$D$8-1),1,0))),"",IF(W21="","",IF(W21="","",IF(AND(W21<=(Cad_Inicial!$D$8-1),Y21>Cad_Inicial!$D$8-1),1,0)))) | AC21: =IF(ISERROR(IF(I21="Ativo","",VLOOKUP(C21,Lanç!$C$8:$E$208,3,0))),"",IF(I21="Ativo","",VLOOKUP(C21,Lanç!$C$8:$E$208,3,0))) | AG21: =IF(ISERROR(IF(Cad!C27="","",Cad!C27)),"",IF(Cad!C27="","",Cad!C27))
L22: =IF(ISERROR(IF(G22="","",VLOOKUP(C22,Lanç_Promoções!$C$8:$F$2008,4,0))),G22,IF(G22="","",VLOOKUP(C22,Lanç_Promoções!$C$8:$F$2008,4,0))) | M22: =IF(ISERROR(IF(L22="","",VLOOKUP(L22,Cad!$C$8:$D$208,2,0))),"",IF(L22="","",VLOOKUP(L22,Cad!$C$8:$D$208,2,0))) | N22: =IF(ISERROR(IF(E22="","",ROUND((TODAY()-E22)/365,0))),"",IF(E22="","",ROUND((TODAY()-E22)/365,0))) | O22: =IF(ISERROR(IF(N22="","",IF(N22>60,"Mais de 60 anos",IF(N22>54,"54 a 60 anos",IF(N22>44,"44 a 53 anos",IF(N22>34,"34 a 43 anos",IF(N22>24,"24 a 33 anos","18 a 23 anos"))))))),"",IF(N22="","",IF(N22>60,"Mais de 60 anos",IF(N22>54,"54 a 60 anos",IF(N22>44,"44 a 53 anos",IF(N22>34,"34 a 43 anos",IF(N22>24,"24 a 33 anos","18 a 23 anos"))))))) | P22: =IF(ISERROR(IF(W22="","",IF(AND(W22<=Cad_Inicial!$D$8,Y22>Cad_Inicial!$D$8),1,0))),"",IF(W22="","",IF(AND(W22<=Cad_Inicial!$D$8,Y22>Cad_Inicial!$D$8),1,0))) | Q22: =IF(ISERROR(IF(W22="","",IF(AND(W22<=(Cad_Inicial!$D$8-1),Y22>Cad_Inicial!$D$8-1),1,0))),"",IF(W22="","",IF(W22="","",IF(AND(W22<=(Cad_Inicial!$D$8-1),Y22>Cad_Inicial!$D$8-1),1,0)))) | R22: =IF(ISERROR(IF(I22="","",IF(I22="Ativo",TRUNC((TODAY()-H22)/30/12,0),TRUNC((I22-H22)/30/12,0)))),"",IF(I22="","",IF(I22="Ativo",TRUNC((TODAY()-H22)/30/12,0),TRUNC((I22-H22)/30/12,0)))) | S22: =IF(ISERROR(IF(I22="","",IF(I22="Ativo",TRUNC(MOD((TODAY()-H22)/30,12),0),TRUNC(MOD((I22-H22)/30,12),0)))),"",IF(I22="","",IF(I22="Ativo",TRUNC(MOD((TODAY()-H22)/30,12),0),TRUNC(MOD((I22-H22)/30,12),0)))) | T22: =IF(ISERROR((R22*12+S22)),"",(R22*12+S22)) | U22: =IF(ISERROR(IF(H22="","",IF(YEAR(H22)<=Cad_Inicial!$D$8,"SIM",""))),"",IF(H22="","",IF(YEAR(H22)<=Cad_Inicial!$D$8,"SIM",""))) | V22: =IF(ISERROR(IF(H22="","",IF(AND(YEAR(H22)=Cad_Inicial!$D$8,I22="Ativo",TODAY()-H22>90),"SIM",IF(AND(YEAR(H22)=Cad_Inicial!$D$8,I22-H22>90),"SIM","")))),"",IF(H22="","",IF(AND(YEAR(H22)=Cad_Inicial!$D$8,I22="Ativo",TODAY()-H22>90),"SIM",IF(AND(YEAR(H22)=Cad_Inicial!$D$8,I22-H22>90),"SIM","")))) | W22: =IF(ISERROR(IF(H22="","",YEAR(H22))),"",IF(H22="","",YEAR(H22))) | X22: =IF(ISERROR(IF(H22="","",MONTH(H22))),"",IF(H22="","",MONTH(H22))) | Y22: =IF(ISERROR(IF(I22="","",YEAR(I22))),"",IF(I22="","",YEAR(I22))) | Z22: =IF(ISERROR(IF(OR(I22="",I22="Ativo"),"",MONTH(I22))),"",IF(OR(I22="",I22="Ativo"),"",MONTH(I22))) | AA22: =IF(ISERROR(IF(W22="","",IF(AND(W22<=Cad_Inicial!$D$8,Y22>Cad_Inicial!$D$8),1,0))),"",IF(W22="","",IF(AND(W22<=Cad_Inicial!$D$8,Y22>Cad_Inicial!$D$8),1,0))) | AB22: =IF(ISERROR(IF(W22="","",IF(AND(W22<=(Cad_Inicial!$D$8-1),Y22>Cad_Inicial!$D$8-1),1,0))),"",IF(W22="","",IF(W22="","",IF(AND(W22<=(Cad_Inicial!$D$8-1),Y22>Cad_Inicial!$D$8-1),1,0)))) | AC22: =IF(ISERROR(IF(I22="Ativo","",VLOOKUP(C22,Lanç!$C$8:$E$208,3,0))),"",IF(I22="Ativo","",VLOOKUP(C22,Lanç!$C$8:$E$208,3,0))) | AG22: =IF(ISERROR(IF(Cad!C28="","",Cad!C28)),"",IF(Cad!C28="","",Cad!C28))
L23: =IF(ISERROR(IF(G23="","",VLOOKUP(C23,Lanç_Promoções!$C$8:$F$2008,4,0))),G23,IF(G23="","",VLOOKUP(C23,Lanç_Promoções!$C$8:$F$2008,4,0))) | M23: =IF(ISERROR(IF(L23="","",VLOOKUP(L23,Cad!$C$8:$D$208,2,0))),"",IF(L23="","",VLOOKUP(L23,Cad!$C$8:$D$208,2,0))) | N23: =IF(ISERROR(IF(E23="","",ROUND((TODAY()-E23)/365,0))),"",IF(E23="","",ROUND((TODAY()-E23)/365,0))) | O23: =IF(ISERROR(IF(N23="","",IF(N23>60,"Mais de 60 anos",IF(N23>54,"54 a 60 anos",IF(N23>44,"44 a 53 anos",IF(N23>34,"34 a 43 anos",IF(N23>24,"24 a 33 anos","18 a 23 anos"))))))),"",IF(N23="","",IF(N23>60,"Mais de 60 anos",IF(N23>54,"54 a 60 anos",IF(N23>44,"44 a 53 anos",IF(N23>34,"34 a 43 anos",IF(N23>24,"24 a 33 anos","18 a 23 anos"))))))) | P23: =IF(ISERROR(IF(W23="","",IF(AND(W23<=Cad_Inicial!$D$8,Y23>Cad_Inicial!$D$8),1,0))),"",IF(W23="","",IF(AND(W23<=Cad_Inicial!$D$8,Y23>Cad_Inicial!$D$8),1,0))) | Q23: =IF(ISERROR(IF(W23="","",IF(AND(W23<=(Cad_Inicial!$D$8-1),Y23>Cad_Inicial!$D$8-1),1,0))),"",IF(W23="","",IF(W23="","",IF(AND(W23<=(Cad_Inicial!$D$8-1),Y23>Cad_Inicial!$D$8-1),1,0)))) | R23: =IF(ISERROR(IF(I23="","",IF(I23="Ativo",TRUNC((TODAY()-H23)/30/12,0),TRUNC((I23-H23)/30/12,0)))),"",IF(I23="","",IF(I23="Ativo",TRUNC((TODAY()-H23)/30/12,0),TRUNC((I23-H23)/30/12,0)))) | S23: =IF(ISERROR(IF(I23="","",IF(I23="Ativo",TRUNC(MOD((TODAY()-H23)/30,12),0),TRUNC(MOD((I23-H23)/30,12),0)))),"",IF(I23="","",IF(I23="Ativo",TRUNC(MOD((TODAY()-H23)/30,12),0),TRUNC(MOD((I23-H23)/30,12),0)))) | T23: =IF(ISERROR((R23*12+S23)),"",(R23*12+S23)) | U23: =IF(ISERROR(IF(H23="","",IF(YEAR(H23)<=Cad_Inicial!$D$8,"SIM",""))),"",IF(H23="","",IF(YEAR(H23)<=Cad_Inicial!$D$8,"SIM",""))) | V23: =IF(ISERROR(IF(H23="","",IF(AND(YEAR(H23)=Cad_Inicial!$D$8,I23="Ativo",TODAY()-H23>90),"SIM",IF(AND(YEAR(H23)=Cad_Inicial!$D$8,I23-H23>90),"SIM","")))),"",IF(H23="","",IF(AND(YEAR(H23)=Cad_Inicial!$D$8,I23="Ativo",TODAY()-H23>90),"SIM",IF(AND(YEAR(H23)=Cad_Inicial!$D$8,I23-H23>90),"SIM","")))) | W23: =IF(ISERROR(IF(H23="","",YEAR(H23))),"",IF(H23="","",YEAR(H23))) | X23: =IF(ISERROR(IF(H23="","",MONTH(H23))),"",IF(H23="","",MONTH(H23))) | Y23: =IF(ISERROR(IF(I23="","",YEAR(I23))),"",IF(I23="","",YEAR(I23))) | Z23: =IF(ISERROR(IF(OR(I23="",I23="Ativo"),"",MONTH(I23))),"",IF(OR(I23="",I23="Ativo"),"",MONTH(I23))) | AA23: =IF(ISERROR(IF(W23="","",IF(AND(W23<=Cad_Inicial!$D$8,Y23>Cad_Inicial!$D$8),1,0))),"",IF(W23="","",IF(AND(W23<=Cad_Inicial!$D$8,Y23>Cad_Inicial!$D$8),1,0))) | AB23: =IF(ISERROR(IF(W23="","",IF(AND(W23<=(Cad_Inicial!$D$8-1),Y23>Cad_Inicial!$D$8-1),1,0))),"",IF(W23="","",IF(W23="","",IF(AND(W23<=(Cad_Inicial!$D$8-1),Y23>Cad_Inicial!$D$8-1),1,0)))) | AC23: =IF(ISERROR(IF(I23="Ativo","",VLOOKUP(C23,Lanç!$C$8:$E$208,3,0))),"",IF(I23="Ativo","",VLOOKUP(C23,Lanç!$C$8:$E$208,3,0))) | AG23: =IF(ISERROR(IF(Cad!C29="","",Cad!C29)),"",IF(Cad!C29="","",Cad!C29))
L24: =IF(ISERROR(IF(G24="","",VLOOKUP(C24,Lanç_Promoções!$C$8:$F$2008,4,0))),G24,IF(G24="","",VLOOKUP(C24,Lanç_Promoções!$C$8:$F$2008,4,0))) | M24: =IF(ISERROR(IF(L24="","",VLOOKUP(L24,Cad!$C$8:$D$208,2,0))),"",IF(L24="","",VLOOKUP(L24,Cad!$C$8:$D$208,2,0))) | N24: =IF(ISERROR(IF(E24="","",ROUND((TODAY()-E24)/365,0))),"",IF(E24="","",ROUND((TODAY()-E24)/365,0))) | O24: =IF(ISERROR(IF(N24="","",IF(N24>60,"Mais de 60 anos",IF(N24>54,"54 a 60 anos",IF(N24>44,"44 a 53 anos",IF(N24>34,"34 a 43 anos",IF(N24>24,"24 a 33 anos","18 a 23 anos"))))))),"",IF(N24="","",IF(N24>60,"Mais de 60 anos",IF(N24>54,"54 a 60 anos",IF(N24>44,"44 a 53 anos",IF(N24>34,"34 a 43 anos",IF(N24>24,"24 a 33 anos","18 a 23 anos"))))))) | P24: =IF(ISERROR(IF(W24="","",IF(AND(W24<=Cad_Inicial!$D$8,Y24>Cad_Inicial!$D$8),1,0))),"",IF(W24="","",IF(AND(W24<=Cad_Inicial!$D$8,Y24>Cad_Inicial!$D$8),1,0))) | Q24: =IF(ISERROR(IF(W24="","",IF(AND(W24<=(Cad_Inicial!$D$8-1),Y24>Cad_Inicial!$D$8-1),1,0))),"",IF(W24="","",IF(W24="","",IF(AND(W24<=(Cad_Inicial!$D$8-1),Y24>Cad_Inicial!$D$8-1),1,0)))) | R24: =IF(ISERROR(IF(I24="","",IF(I24="Ativo",TRUNC((TODAY()-H24)/30/12,0),TRUNC((I24-H24)/30/12,0)))),"",IF(I24="","",IF(I24="Ativo",TRUNC((TODAY()-H24)/30/12,0),TRUNC((I24-H24)/30/12,0)))) | S24: =IF(ISERROR(IF(I24="","",IF(I24="Ativo",TRUNC(MOD((TODAY()-H24)/30,12),0),TRUNC(MOD((I24-H24)/30,12),0)))),"",IF(I24="","",IF(I24="Ativo",TRUNC(MOD((TODAY()-H24)/30,12),0),TRUNC(MOD((I24-H24)/30,12),0)))) | T24: =IF(ISERROR((R24*12+S24)),"",(R24*12+S24)) | U24: =IF(ISERROR(IF(H24="","",IF(YEAR(H24)<=Cad_Inicial!$D$8,"SIM",""))),"",IF(H24="","",IF(YEAR(H24)<=Cad_Inicial!$D$8,"SIM",""))) | V24: =IF(ISERROR(IF(H24="","",IF(AND(YEAR(H24)=Cad_Inicial!$D$8,I24="Ativo",TODAY()-H24>90),"SIM",IF(AND(YEAR(H24)=Cad_Inicial!$D$8,I24-H24>90),"SIM","")))),"",IF(H24="","",IF(AND(YEAR(H24)=Cad_Inicial!$D$8,I24="Ativo",TODAY()-H24>90),"SIM",IF(AND(YEAR(H24)=Cad_Inicial!$D$8,I24-H24>90),"SIM","")))) | W24: =IF(ISERROR(IF(H24="","",YEAR(H24))),"",IF(H24="","",YEAR(H24))) | X24: =IF(ISERROR(IF(H24="","",MONTH(H24))),"",IF(H24="","",MONTH(H24))) | Y24: =IF(ISERROR(IF(I24="","",YEAR(I24))),"",IF(I24="","",YEAR(I24))) | Z24: =IF(ISERROR(IF(OR(I24="",I24="Ativo"),"",MONTH(I24))),"",IF(OR(I24="",I24="Ativo"),"",MONTH(I24))) | AA24: =IF(ISERROR(IF(W24="","",IF(AND(W24<=Cad_Inicial!$D$8,Y24>Cad_Inicial!$D$8),1,0))),"",IF(W24="","",IF(AND(W24<=Cad_Inicial!$D$8,Y24>Cad_Inicial!$D$8),1,0))) | AB24: =IF(ISERROR(IF(W24="","",IF(AND(W24<=(Cad_Inicial!$D$8-1),Y24>Cad_Inicial!$D$8-1),1,0))),"",IF(W24="","",IF(W24="","",IF(AND(W24<=(Cad_Inicial!$D$8-1),Y24>Cad_Inicial!$D$8-1),1,0)))) | AC24: =IF(ISERROR(IF(I24="Ativo","",VLOOKUP(C24,Lanç!$C$8:$E$208,3,0))),"",IF(I24="Ativo","",VLOOKUP(C24,Lanç!$C$8:$E$208,3,0))) | AG24: =IF(ISERROR(IF(Cad!C30="","",Cad!C30)),"",IF(Cad!C30="","",Cad!C30))
L25: =IF(ISERROR(IF(G25="","",VLOOKUP(C25,Lanç_Promoções!$C$8:$F$2008,4,0))),G25,IF(G25="","",VLOOKUP(C25,Lanç_Promoções!$C$8:$F$2008,4,0))) | M25: =IF(ISERROR(IF(L25="","",VLOOKUP(L25,Cad!$C$8:$D$208,2,0))),"",IF(L25="","",VLOOKUP(L25,Cad!$C$8:$D$208,2,0))) | N25: =IF(ISERROR(IF(E25="","",ROUND((TODAY()-E25)/365,0))),"",IF(E25="","",ROUND((TODAY()-E25)/365,0))) | O25: =IF(ISERROR(IF(N25="","",IF(N25>60,"Mais de 60 anos",IF(N25>54,"54 a 60 anos",IF(N25>44,"44 a 53 anos",IF(N25>34,"34 a 43 anos",IF(N25>24,"24 a 33 anos","18 a 23 anos"))))))),"",IF(N25="","",IF(N25>60,"Mais de 60 anos",IF(N25>54,"54 a 60 anos",IF(N25>44,"44 a 53 anos",IF(N25>34,"34 a 43 anos",IF(N25>24,"24 a 33 anos","18 a 23 anos"))))))) | P25: =IF(ISERROR(IF(W25="","",IF(AND(W25<=Cad_Inicial!$D$8,Y25>Cad_Inicial!$D$8),1,0))),"",IF(W25="","",IF(AND(W25<=Cad_Inicial!$D$8,Y25>Cad_Inicial!$D$8),1,0))) | Q25: =IF(ISERROR(IF(W25="","",IF(AND(W25<=(Cad_Inicial!$D$8-1),Y25>Cad_Inicial!$D$8-1),1,0))),"",IF(W25="","",IF(W25="","",IF(AND(W25<=(Cad_Inicial!$D$8-1),Y25>Cad_Inicial!$D$8-1),1,0)))) | R25: =IF(ISERROR(IF(I25="","",IF(I25="Ativo",TRUNC((TODAY()-H25)/30/12,0),TRUNC((I25-H25)/30/12,0)))),"",IF(I25="","",IF(I25="Ativo",TRUNC((TODAY()-H25)/30/12,0),TRUNC((I25-H25)/30/12,0)))) | S25: =IF(ISERROR(IF(I25="","",IF(I25="Ativo",TRUNC(MOD((TODAY()-H25)/30,12),0),TRUNC(MOD((I25-H25)/30,12),0)))),"",IF(I25="","",IF(I25="Ativo",TRUNC(MOD((TODAY()-H25)/30,12),0),TRUNC(MOD((I25-H25)/30,12),0)))) | T25: =IF(ISERROR((R25*12+S25)),"",(R25*12+S25)) | U25: =IF(ISERROR(IF(H25="","",IF(YEAR(H25)<=Cad_Inicial!$D$8,"SIM",""))),"",IF(H25="","",IF(YEAR(H25)<=Cad_Inicial!$D$8,"SIM",""))) | V25: =IF(ISERROR(IF(H25="","",IF(AND(YEAR(H25)=Cad_Inicial!$D$8,I25="Ativo",TODAY()-H25>90),"SIM",IF(AND(YEAR(H25)=Cad_Inicial!$D$8,I25-H25>90),"SIM","")))),"",IF(H25="","",IF(AND(YEAR(H25)=Cad_Inicial!$D$8,I25="Ativo",TODAY()-H25>90),"SIM",IF(AND(YEAR(H25)=Cad_Inicial!$D$8,I25-H25>90),"SIM","")))) | W25: =IF(ISERROR(IF(H25="","",YEAR(H25))),"",IF(H25="","",YEAR(H25))) | X25: =IF(ISERROR(IF(H25="","",MONTH(H25))),"",IF(H25="","",MONTH(H25))) | Y25: =IF(ISERROR(IF(I25="","",YEAR(I25))),"",IF(I25="","",YEAR(I25))) | Z25: =IF(ISERROR(IF(OR(I25="",I25="Ativo"),"",MONTH(I25))),"",IF(OR(I25="",I25="Ativo"),"",MONTH(I25))) | AA25: =IF(ISERROR(IF(W25="","",IF(AND(W25<=Cad_Inicial!$D$8,Y25>Cad_Inicial!$D$8),1,0))),"",IF(W25="","",IF(AND(W25<=Cad_Inicial!$D$8,Y25>Cad_Inicial!$D$8),1,0))) | AB25: =IF(ISERROR(IF(W25="","",IF(AND(W25<=(Cad_Inicial!$D$8-1),Y25>Cad_Inicial!$D$8-1),1,0))),"",IF(W25="","",IF(W25="","",IF(AND(W25<=(Cad_Inicial!$D$8-1),Y25>Cad_Inicial!$D$8-1),1,0)))) | AC25: =IF(ISERROR(IF(I25="Ativo","",VLOOKUP(C25,Lanç!$C$8:$E$208,3,0))),"",IF(I25="Ativo","",VLOOKUP(C25,Lanç!$C$8:$E$208,3,0))) | AG25: =IF(ISERROR(IF(Cad!C31="","",Cad!C31)),"",IF(Cad!C31="","",Cad!C31))
L26: =IF(ISERROR(IF(G26="","",VLOOKUP(C26,Lanç_Promoções!$C$8:$F$2008,4,0))),G26,IF(G26="","",VLOOKUP(C26,Lanç_Promoções!$C$8:$F$2008,4,0))) | M26: =IF(ISERROR(IF(L26="","",VLOOKUP(L26,Cad!$C$8:$D$208,2,0))),"",IF(L26="","",VLOOKUP(L26,Cad!$C$8:$D$208,2,0))) | N26: =IF(ISERROR(IF(E26="","",ROUND((TODAY()-E26)/365,0))),"",IF(E26="","",ROUND((TODAY()-E26)/365,0))) | O26: =IF(ISERROR(IF(N26="","",IF(N26>60,"Mais de 60 anos",IF(N26>54,"54 a 60 anos",IF(N26>44,"44 a 53 anos",IF(N26>34,"34 a 43 anos",IF(N26>24,"24 a 33 anos","18 a 23 anos"))))))),"",IF(N26="","",IF(N26>60,"Mais de 60 anos",IF(N26>54,"54 a 60 anos",IF(N26>44,"44 a 53 anos",IF(N26>34,"34 a 43 anos",IF(N26>24,"24 a 33 anos","18 a 23 anos"))))))) | P26: =IF(ISERROR(IF(W26="","",IF(AND(W26<=Cad_Inicial!$D$8,Y26>Cad_Inicial!$D$8),1,0))),"",IF(W26="","",IF(AND(W26<=Cad_Inicial!$D$8,Y26>Cad_Inicial!$D$8),1,0))) | Q26: =IF(ISERROR(IF(W26="","",IF(AND(W26<=(Cad_Inicial!$D$8-1),Y26>Cad_Inicial!$D$8-1),1,0))),"",IF(W26="","",IF(W26="","",IF(AND(W26<=(Cad_Inicial!$D$8-1),Y26>Cad_Inicial!$D$8-1),1,0)))) | R26: =IF(ISERROR(IF(I26="","",IF(I26="Ativo",TRUNC((TODAY()-H26)/30/12,0),TRUNC((I26-H26)/30/12,0)))),"",IF(I26="","",IF(I26="Ativo",TRUNC((TODAY()-H26)/30/12,0),TRUNC((I26-H26)/30/12,0)))) | S26: =IF(ISERROR(IF(I26="","",IF(I26="Ativo",TRUNC(MOD((TODAY()-H26)/30,12),0),TRUNC(MOD((I26-H26)/30,12),0)))),"",IF(I26="","",IF(I26="Ativo",TRUNC(MOD((TODAY()-H26)/30,12),0),TRUNC(MOD((I26-H26)/30,12),0)))) | T26: =IF(ISERROR((R26*12+S26)),"",(R26*12+S26)) | U26: =IF(ISERROR(IF(H26="","",IF(YEAR(H26)<=Cad_Inicial!$D$8,"SIM",""))),"",IF(H26="","",IF(YEAR(H26)<=Cad_Inicial!$D$8,"SIM",""))) | V26: =IF(ISERROR(IF(H26="","",IF(AND(YEAR(H26)=Cad_Inicial!$D$8,I26="Ativo",TODAY()-H26>90),"SIM",IF(AND(YEAR(H26)=Cad_Inicial!$D$8,I26-H26>90),"SIM","")))),"",IF(H26="","",IF(AND(YEAR(H26)=Cad_Inicial!$D$8,I26="Ativo",TODAY()-H26>90),"SIM",IF(AND(YEAR(H26)=Cad_Inicial!$D$8,I26-H26>90),"SIM","")))) | W26: =IF(ISERROR(IF(H26="","",YEAR(H26))),"",IF(H26="","",YEAR(H26))) | X26: =IF(ISERROR(IF(H26="","",MONTH(H26))),"",IF(H26="","",MONTH(H26))) | Y26: =IF(ISERROR(IF(I26="","",YEAR(I26))),"",IF(I26="","",YEAR(I26))) | Z26: =IF(ISERROR(IF(OR(I26="",I26="Ativo"),"",MONTH(I26))),"",IF(OR(I26="",I26="Ativo"),"",MONTH(I26))) | AA26: =IF(ISERROR(IF(W26="","",IF(AND(W26<=Cad_Inicial!$D$8,Y26>Cad_Inicial!$D$8),1,0))),"",IF(W26="","",IF(AND(W26<=Cad_Inicial!$D$8,Y26>Cad_Inicial!$D$8),1,0))) | AB26: =IF(ISERROR(IF(W26="","",IF(AND(W26<=(Cad_Inicial!$D$8-1),Y26>Cad_Inicial!$D$8-1),1,0))),"",IF(W26="","",IF(W26="","",IF(AND(W26<=(Cad_Inicial!$D$8-1),Y26>Cad_Inicial!$D$8-1),1,0)))) | AC26: =IF(ISERROR(IF(I26="Ativo","",VLOOKUP(C26,Lanç!$C$8:$E$208,3,0))),"",IF(I26="Ativo","",VLOOKUP(C26,Lanç!$C$8:$E$208,3,0))) | AG26: =IF(ISERROR(IF(Cad!C32="","",Cad!C32)),"",IF(Cad!C32="","",Cad!C32))
L27: =IF(ISERROR(IF(G27="","",VLOOKUP(C27,Lanç_Promoções!$C$8:$F$2008,4,0))),G27,IF(G27="","",VLOOKUP(C27,Lanç_Promoções!$C$8:$F$2008,4,0))) | M27: =IF(ISERROR(IF(L27="","",VLOOKUP(L27,Cad!$C$8:$D$208,2,0))),"",IF(L27="","",VLOOKUP(L27,Cad!$C$8:$D$208,2,0))) | N27: =IF(ISERROR(IF(E27="","",ROUND((TODAY()-E27)/365,0))),"",IF(E27="","",ROUND((TODAY()-E27)/365,0))) | O27: =IF(ISERROR(IF(N27="","",IF(N27>60,"Mais de 60 anos",IF(N27>54,"54 a 60 anos",IF(N27>44,"44 a 53 anos",IF(N27>34,"34 a 43 anos",IF(N27>24,"24 a 33 anos","18 a 23 anos"))))))),"",IF(N27="","",IF(N27>60,"Mais de 60 anos",IF(N27>54,"54 a 60 anos",IF(N27>44,"44 a 53 anos",IF(N27>34,"34 a 43 anos",IF(N27>24,"24 a 33 anos","18 a 23 anos"))))))) | P27: =IF(ISERROR(IF(W27="","",IF(AND(W27<=Cad_Inicial!$D$8,Y27>Cad_Inicial!$D$8),1,0))),"",IF(W27="","",IF(AND(W27<=Cad_Inicial!$D$8,Y27>Cad_Inicial!$D$8),1,0))) | Q27: =IF(ISERROR(IF(W27="","",IF(AND(W27<=(Cad_Inicial!$D$8-1),Y27>Cad_Inicial!$D$8-1),1,0))),"",IF(W27="","",IF(W27="","",IF(AND(W27<=(Cad_Inicial!$D$8-1),Y27>Cad_Inicial!$D$8-1),1,0)))) | R27: =IF(ISERROR(IF(I27="","",IF(I27="Ativo",TRUNC((TODAY()-H27)/30/12,0),TRUNC((I27-H27)/30/12,0)))),"",IF(I27="","",IF(I27="Ativo",TRUNC((TODAY()-H27)/30/12,0),TRUNC((I27-H27)/30/12,0)))) | S27: =IF(ISERROR(IF(I27="","",IF(I27="Ativo",TRUNC(MOD((TODAY()-H27)/30,12),0),TRUNC(MOD((I27-H27)/30,12),0)))),"",IF(I27="","",IF(I27="Ativo",TRUNC(MOD((TODAY()-H27)/30,12),0),TRUNC(MOD((I27-H27)/30,12),0)))) | T27: =IF(ISERROR((R27*12+S27)),"",(R27*12+S27)) | U27: =IF(ISERROR(IF(H27="","",IF(YEAR(H27)<=Cad_Inicial!$D$8,"SIM",""))),"",IF(H27="","",IF(YEAR(H27)<=Cad_Inicial!$D$8,"SIM",""))) | V27: =IF(ISERROR(IF(H27="","",IF(AND(YEAR(H27)=Cad_Inicial!$D$8,I27="Ativo",TODAY()-H27>90),"SIM",IF(AND(YEAR(H27)=Cad_Inicial!$D$8,I27-H27>90),"SIM","")))),"",IF(H27="","",IF(AND(YEAR(H27)=Cad_Inicial!$D$8,I27="Ativo",TODAY()-H27>90),"SIM",IF(AND(YEAR(H27)=Cad_Inicial!$D$8,I27-H27>90),"SIM","")))) | W27: =IF(ISERROR(IF(H27="","",YEAR(H27))),"",IF(H27="","",YEAR(H27))) | X27: =IF(ISERROR(IF(H27="","",MONTH(H27))),"",IF(H27="","",MONTH(H27))) | Y27: =IF(ISERROR(IF(I27="","",YEAR(I27))),"",IF(I27="","",YEAR(I27))) | Z27: =IF(ISERROR(IF(OR(I27="",I27="Ativo"),"",MONTH(I27))),"",IF(OR(I27="",I27="Ativo"),"",MONTH(I27))) | AA27: =IF(ISERROR(IF(W27="","",IF(AND(W27<=Cad_Inicial!$D$8,Y27>Cad_Inicial!$D$8),1,0))),"",IF(W27="","",IF(AND(W27<=Cad_Inicial!$D$8,Y27>Cad_Inicial!$D$8),1,0))) | AB27: =IF(ISERROR(IF(W27="","",IF(AND(W27<=(Cad_Inicial!$D$8-1),Y27>Cad_Inicial!$D$8-1),1,0))),"",IF(W27="","",IF(W27="","",IF(AND(W27<=(Cad_Inicial!$D$8-1),Y27>Cad_Inicial!$D$8-1),1,0)))) | AC27: =IF(ISERROR(IF(I27="Ativo","",VLOOKUP(C27,Lanç!$C$8:$E$208,3,0))),"",IF(I27="Ativo","",VLOOKUP(C27,Lanç!$C$8:$E$208,3,0))) | AG27: =IF(ISERROR(IF(Cad!C33="","",Cad!C33)),"",IF(Cad!C33="","",Cad!C33))
L28: =IF(ISERROR(IF(G28="","",VLOOKUP(C28,Lanç_Promoções!$C$8:$F$2008,4,0))),G28,IF(G28="","",VLOOKUP(C28,Lanç_Promoções!$C$8:$F$2008,4,0))) | M28: =IF(ISERROR(IF(L28="","",VLOOKUP(L28,Cad!$C$8:$D$208,2,0))),"",IF(L28="","",VLOOKUP(L28,Cad!$C$8:$D$208,2,0))) | N28: =IF(ISERROR(IF(E28="","",ROUND((TODAY()-E28)/365,0))),"",IF(E28="","",ROUND((TODAY()-E28)/365,0))) | O28: =IF(ISERROR(IF(N28="","",IF(N28>60,"Mais de 60 anos",IF(N28>54,"54 a 60 anos",IF(N28>44,"44 a 53 anos",IF(N28>34,"34 a 43 anos",IF(N28>24,"24 a 33 anos","18 a 23 anos"))))))),"",IF(N28="","",IF(N28>60,"Mais de 60 anos",IF(N28>54,"54 a 60 anos",IF(N28>44,"44 a 53 anos",IF(N28>34,"34 a 43 anos",IF(N28>24,"24 a 33 anos","18 a 23 anos"))))))) | P28: =IF(ISERROR(IF(W28="","",IF(AND(W28<=Cad_Inicial!$D$8,Y28>Cad_Inicial!$D$8),1,0))),"",IF(W28="","",IF(AND(W28<=Cad_Inicial!$D$8,Y28>Cad_Inicial!$D$8),1,0))) | Q28: =IF(ISERROR(IF(W28="","",IF(AND(W28<=(Cad_Inicial!$D$8-1),Y28>Cad_Inicial!$D$8-1),1,0))),"",IF(W28="","",IF(W28="","",IF(AND(W28<=(Cad_Inicial!$D$8-1),Y28>Cad_Inicial!$D$8-1),1,0)))) | R28: =IF(ISERROR(IF(I28="","",IF(I28="Ativo",TRUNC((TODAY()-H28)/30/12,0),TRUNC((I28-H28)/30/12,0)))),"",IF(I28="","",IF(I28="Ativo",TRUNC((TODAY()-H28)/30/12,0),TRUNC((I28-H28)/30/12,0)))) | S28: =IF(ISERROR(IF(I28="","",IF(I28="Ativo",TRUNC(MOD((TODAY()-H28)/30,12),0),TRUNC(MOD((I28-H28)/30,12),0)))),"",IF(I28="","",IF(I28="Ativo",TRUNC(MOD((TODAY()-H28)/30,12),0),TRUNC(MOD((I28-H28)/30,12),0)))) | T28: =IF(ISERROR((R28*12+S28)),"",(R28*12+S28)) | U28: =IF(ISERROR(IF(H28="","",IF(YEAR(H28)<=Cad_Inicial!$D$8,"SIM",""))),"",IF(H28="","",IF(YEAR(H28)<=Cad_Inicial!$D$8,"SIM",""))) | V28: =IF(ISERROR(IF(H28="","",IF(AND(YEAR(H28)=Cad_Inicial!$D$8,I28="Ativo",TODAY()-H28>90),"SIM",IF(AND(YEAR(H28)=Cad_Inicial!$D$8,I28-H28>90),"SIM","")))),"",IF(H28="","",IF(AND(YEAR(H28)=Cad_Inicial!$D$8,I28="Ativo",TODAY()-H28>90),"SIM",IF(AND(YEAR(H28)=Cad_Inicial!$D$8,I28-H28>90),"SIM","")))) | W28: =IF(ISERROR(IF(H28="","",YEAR(H28))),"",IF(H28="","",YEAR(H28))) | X28: =IF(ISERROR(IF(H28="","",MONTH(H28))),"",IF(H28="","",MONTH(H28))) | Y28: =IF(ISERROR(IF(I28="","",YEAR(I28))),"",IF(I28="","",YEAR(I28))) | Z28: =IF(ISERROR(IF(OR(I28="",I28="Ativo"),"",MONTH(I28))),"",IF(OR(I28="",I28="Ativo"),"",MONTH(I28))) | AA28: =IF(ISERROR(IF(W28="","",IF(AND(W28<=Cad_Inicial!$D$8,Y28>Cad_Inicial!$D$8),1,0))),"",IF(W28="","",IF(AND(W28<=Cad_Inicial!$D$8,Y28>Cad_Inicial!$D$8),1,0))) | AB28: =IF(ISERROR(IF(W28="","",IF(AND(W28<=(Cad_Inicial!$D$8-1),Y28>Cad_Inicial!$D$8-1),1,0))),"",IF(W28="","",IF(W28="","",IF(AND(W28<=(Cad_Inicial!$D$8-1),Y28>Cad_Inicial!$D$8-1),1,0)))) | AC28: =IF(ISERROR(IF(I28="Ativo","",VLOOKUP(C28,Lanç!$C$8:$E$208,3,0))),"",IF(I28="Ativo","",VLOOKUP(C28,Lanç!$C$8:$E$208,3,0))) | AG28: =IF(ISERROR(IF(Cad!C34="","",Cad!C34)),"",IF(Cad!C34="","",Cad!C34))
L29: =IF(ISERROR(IF(G29="","",VLOOKUP(C29,Lanç_Promoções!$C$8:$F$2008,4,0))),G29,IF(G29="","",VLOOKUP(C29,Lanç_Promoções!$C$8:$F$2008,4,0))) | M29: =IF(ISERROR(IF(L29="","",VLOOKUP(L29,Cad!$C$8:$D$208,2,0))),"",IF(L29="","",VLOOKUP(L29,Cad!$C$8:$D$208,2,0))) | N29: =IF(ISERROR(IF(E29="","",ROUND((TODAY()-E29)/365,0))),"",IF(E29="","",ROUND((TODAY()-E29)/365,0))) | O29: =IF(ISERROR(IF(N29="","",IF(N29>60,"Mais de 60 anos",IF(N29>54,"54 a 60 anos",IF(N29>44,"44 a 53 anos",IF(N29>34,"34 a 43 anos",IF(N29>24,"24 a 33 anos","18 a 23 anos"))))))),"",IF(N29="","",IF(N29>60,"Mais de 60 anos",IF(N29>54,"54 a 60 anos",IF(N29>44,"44 a 53 anos",IF(N29>34,"34 a 43 anos",IF(N29>24,"24 a 33 anos","18 a 23 anos"))))))) | P29: =IF(ISERROR(IF(W29="","",IF(AND(W29<=Cad_Inicial!$D$8,Y29>Cad_Inicial!$D$8),1,0))),"",IF(W29="","",IF(AND(W29<=Cad_Inicial!$D$8,Y29>Cad_Inicial!$D$8),1,0))) | Q29: =IF(ISERROR(IF(W29="","",IF(AND(W29<=(Cad_Inicial!$D$8-1),Y29>Cad_Inicial!$D$8-1),1,0))),"",IF(W29="","",IF(W29="","",IF(AND(W29<=(Cad_Inicial!$D$8-1),Y29>Cad_Inicial!$D$8-1),1,0)))) | R29: =IF(ISERROR(IF(I29="","",IF(I29="Ativo",TRUNC((TODAY()-H29)/30/12,0),TRUNC((I29-H29)/30/12,0)))),"",IF(I29="","",IF(I29="Ativo",TRUNC((TODAY()-H29)/30/12,0),TRUNC((I29-H29)/30/12,0)))) | S29: =IF(ISERROR(IF(I29="","",IF(I29="Ativo",TRUNC(MOD((TODAY()-H29)/30,12),0),TRUNC(MOD((I29-H29)/30,12),0)))),"",IF(I29="","",IF(I29="Ativo",TRUNC(MOD((TODAY()-H29)/30,12),0),TRUNC(MOD((I29-H29)/30,12),0)))) | T29: =IF(ISERROR((R29*12+S29)),"",(R29*12+S29)) | U29: =IF(ISERROR(IF(H29="","",IF(YEAR(H29)<=Cad_Inicial!$D$8,"SIM",""))),"",IF(H29="","",IF(YEAR(H29)<=Cad_Inicial!$D$8,"SIM",""))) | V29: =IF(ISERROR(IF(H29="","",IF(AND(YEAR(H29)=Cad_Inicial!$D$8,I29="Ativo",TODAY()-H29>90),"SIM",IF(AND(YEAR(H29)=Cad_Inicial!$D$8,I29-H29>90),"SIM","")))),"",IF(H29="","",IF(AND(YEAR(H29)=Cad_Inicial!$D$8,I29="Ativo",TODAY()-H29>90),"SIM",IF(AND(YEAR(H29)=Cad_Inicial!$D$8,I29-H29>90),"SIM","")))) | W29: =IF(ISERROR(IF(H29="","",YEAR(H29))),"",IF(H29="","",YEAR(H29))) | X29: =IF(ISERROR(IF(H29="","",MONTH(H29))),"",IF(H29="","",MONTH(H29))) | Y29: =IF(ISERROR(IF(I29="","",YEAR(I29))),"",IF(I29="","",YEAR(I29))) | Z29: =IF(ISERROR(IF(OR(I29="",I29="Ativo"),"",MONTH(I29))),"",IF(OR(I29="",I29="Ativo"),"",MONTH(I29))) | AA29: =IF(ISERROR(IF(W29="","",IF(AND(W29<=Cad_Inicial!$D$8,Y29>Cad_Inicial!$D$8),1,0))),"",IF(W29="","",IF(AND(W29<=Cad_Inicial!$D$8,Y29>Cad_Inicial!$D$8),1,0))) | AB29: =IF(ISERROR(IF(W29="","",IF(AND(W29<=(Cad_Inicial!$D$8-1),Y29>Cad_Inicial!$D$8-1),1,0))),"",IF(W29="","",IF(W29="","",IF(AND(W29<=(Cad_Inicial!$D$8-1),Y29>Cad_Inicial!$D$8-1),1,0)))) | AC29: =IF(ISERROR(IF(I29="Ativo","",VLOOKUP(C29,Lanç!$C$8:$E$208,3,0))),"",IF(I29="Ativo","",VLOOKUP(C29,Lanç!$C$8:$E$208,3,0))) | AG29: =IF(ISERROR(IF(Cad!C35="","",Cad!C35)),"",IF(Cad!C35="","",Cad!C35))
L30: =IF(ISERROR(IF(G30="","",VLOOKUP(C30,Lanç_Promoções!$C$8:$F$2008,4,0))),G30,IF(G30="","",VLOOKUP(C30,Lanç_Promoções!$C$8:$F$2008,4,0))) | M30: =IF(ISERROR(IF(L30="","",VLOOKUP(L30,Cad!$C$8:$D$208,2,0))),"",IF(L30="","",VLOOKUP(L30,Cad!$C$8:$D$208,2,0))) | N30: =IF(ISERROR(IF(E30="","",ROUND((TODAY()-E30)/365,0))),"",IF(E30="","",ROUND((TODAY()-E30)/365,0))) | O30: =IF(ISERROR(IF(N30="","",IF(N30>60,"Mais de 60 anos",IF(N30>54,"54 a 60 anos",IF(N30>44,"44 a 53 anos",IF(N30>34,"34 a 43 anos",IF(N30>24,"24 a 33 anos","18 a 23 anos"))))))),"",IF(N30="","",IF(N30>60,"Mais de 60 anos",IF(N30>54,"54 a 60 anos",IF(N30>44,"44 a 53 anos",IF(N30>34,"34 a 43 anos",IF(N30>24,"24 a 33 anos","18 a 23 anos"))))))) | P30: =IF(ISERROR(IF(W30="","",IF(AND(W30<=Cad_Inicial!$D$8,Y30>Cad_Inicial!$D$8),1,0))),"",IF(W30="","",IF(AND(W30<=Cad_Inicial!$D$8,Y30>Cad_Inicial!$D$8),1,0))) | Q30: =IF(ISERROR(IF(W30="","",IF(AND(W30<=(Cad_Inicial!$D$8-1),Y30>Cad_Inicial!$D$8-1),1,0))),"",IF(W30="","",IF(W30="","",IF(AND(W30<=(Cad_Inicial!$D$8-1),Y30>Cad_Inicial!$D$8-1),1,0)))) | R30: =IF(ISERROR(IF(I30="","",IF(I30="Ativo",TRUNC((TODAY()-H30)/30/12,0),TRUNC((I30-H30)/30/12,0)))),"",IF(I30="","",IF(I30="Ativo",TRUNC((TODAY()-H30)/30/12,0),TRUNC((I30-H30)/30/12,0)))) | S30: =IF(ISERROR(IF(I30="","",IF(I30="Ativo",TRUNC(MOD((TODAY()-H30)/30,12),0),TRUNC(MOD((I30-H30)/30,12),0)))),"",IF(I30="","",IF(I30="Ativo",TRUNC(MOD((TODAY()-H30)/30,12),0),TRUNC(MOD((I30-H30)/30,12),0)))) | T30: =IF(ISERROR((R30*12+S30)),"",(R30*12+S30)) | U30: =IF(ISERROR(IF(H30="","",IF(YEAR(H30)<=Cad_Inicial!$D$8,"SIM",""))),"",IF(H30="","",IF(YEAR(H30)<=Cad_Inicial!$D$8,"SIM",""))) | V30: =IF(ISERROR(IF(H30="","",IF(AND(YEAR(H30)=Cad_Inicial!$D$8,I30="Ativo",TODAY()-H30>90),"SIM",IF(AND(YEAR(H30)=Cad_Inicial!$D$8,I30-H30>90),"SIM","")))),"",IF(H30="","",IF(AND(YEAR(H30)=Cad_Inicial!$D$8,I30="Ativo",TODAY()-H30>90),"SIM",IF(AND(YEAR(H30)=Cad_Inicial!$D$8,I30-H30>90),"SIM","")))) | W30: =IF(ISERROR(IF(H30="","",YEAR(H30))),"",IF(H30="","",YEAR(H30))) | X30: =IF(ISERROR(IF(H30="","",MONTH(H30))),"",IF(H30="","",MONTH(H30))) | Y30: =IF(ISERROR(IF(I30="","",YEAR(I30))),"",IF(I30="","",YEAR(I30))) | Z30: =IF(ISERROR(IF(OR(I30="",I30="Ativo"),"",MONTH(I30))),"",IF(OR(I30="",I30="Ativo"),"",MONTH(I30))) | AA30: =IF(ISERROR(IF(W30="","",IF(AND(W30<=Cad_Inicial!$D$8,Y30>Cad_Inicial!$D$8),1,0))),"",IF(W30="","",IF(AND(W30<=Cad_Inicial!$D$8,Y30>Cad_Inicial!$D$8),1,0))) | AB30: =IF(ISERROR(IF(W30="","",IF(AND(W30<=(Cad_Inicial!$D$8-1),Y30>Cad_Inicial!$D$8-1),1,0))),"",IF(W30="","",IF(W30="","",IF(AND(W30<=(Cad_Inicial!$D$8-1),Y30>Cad_Inicial!$D$8-1),1,0)))) | AC30: =IF(ISERROR(IF(I30="Ativo","",VLOOKUP(C30,Lanç!$C$8:$E$208,3,0))),"",IF(I30="Ativo","",VLOOKUP(C30,Lanç!$C$8:$E$208,3,0))) | AG30: =IF(ISERROR(IF(Cad!C36="","",Cad!C36)),"",IF(Cad!C36="","",Cad!C36))
L31: =IF(ISERROR(IF(G31="","",VLOOKUP(C31,Lanç_Promoções!$C$8:$F$2008,4,0))),G31,IF(G31="","",VLOOKUP(C31,Lanç_Promoções!$C$8:$F$2008,4,0))) | M31: =IF(ISERROR(IF(L31="","",VLOOKUP(L31,Cad!$C$8:$D$208,2,0))),"",IF(L31="","",VLOOKUP(L31,Cad!$C$8:$D$208,2,0))) | N31: =IF(ISERROR(IF(E31="","",ROUND((TODAY()-E31)/365,0))),"",IF(E31="","",ROUND((TODAY()-E31)/365,0))) | O31: =IF(ISERROR(IF(N31="","",IF(N31>60,"Mais de 60 anos",IF(N31>54,"54 a 60 anos",IF(N31>44,"44 a 53 anos",IF(N31>34,"34 a 43 anos",IF(N31>24,"24 a 33 anos","18 a 23 anos"))))))),"",IF(N31="","",IF(N31>60,"Mais de 60 anos",IF(N31>54,"54 a 60 anos",IF(N31>44,"44 a 53 anos",IF(N31>34,"34 a 43 anos",IF(N31>24,"24 a 33 anos","18 a 23 anos"))))))) | P31: =IF(ISERROR(IF(W31="","",IF(AND(W31<=Cad_Inicial!$D$8,Y31>Cad_Inicial!$D$8),1,0))),"",IF(W31="","",IF(AND(W31<=Cad_Inicial!$D$8,Y31>Cad_Inicial!$D$8),1,0))) | Q31: =IF(ISERROR(IF(W31="","",IF(AND(W31<=(Cad_Inicial!$D$8-1),Y31>Cad_Inicial!$D$8-1),1,0))),"",IF(W31="","",IF(W31="","",IF(AND(W31<=(Cad_Inicial!$D$8-1),Y31>Cad_Inicial!$D$8-1),1,0)))) | R31: =IF(ISERROR(IF(I31="","",IF(I31="Ativo",TRUNC((TODAY()-H31)/30/12,0),TRUNC((I31-H31)/30/12,0)))),"",IF(I31="","",IF(I31="Ativo",TRUNC((TODAY()-H31)/30/12,0),TRUNC((I31-H31)/30/12,0)))) | S31: =IF(ISERROR(IF(I31="","",IF(I31="Ativo",TRUNC(MOD((TODAY()-H31)/30,12),0),TRUNC(MOD((I31-H31)/30,12),0)))),"",IF(I31="","",IF(I31="Ativo",TRUNC(MOD((TODAY()-H31)/30,12),0),TRUNC(MOD((I31-H31)/30,12),0)))) | T31: =IF(ISERROR((R31*12+S31)),"",(R31*12+S31)) | U31: =IF(ISERROR(IF(H31="","",IF(YEAR(H31)<=Cad_Inicial!$D$8,"SIM",""))),"",IF(H31="","",IF(YEAR(H31)<=Cad_Inicial!$D$8,"SIM",""))) | V31: =IF(ISERROR(IF(H31="","",IF(AND(YEAR(H31)=Cad_Inicial!$D$8,I31="Ativo",TODAY()-H31>90),"SIM",IF(AND(YEAR(H31)=Cad_Inicial!$D$8,I31-H31>90),"SIM","")))),"",IF(H31="","",IF(AND(YEAR(H31)=Cad_Inicial!$D$8,I31="Ativo",TODAY()-H31>90),"SIM",IF(AND(YEAR(H31)=Cad_Inicial!$D$8,I31-H31>90),"SIM","")))) | W31: =IF(ISERROR(IF(H31="","",YEAR(H31))),"",IF(H31="","",YEAR(H31))) | X31: =IF(ISERROR(IF(H31="","",MONTH(H31))),"",IF(H31="","",MONTH(H31))) | Y31: =IF(ISERROR(IF(I31="","",YEAR(I31))),"",IF(I31="","",YEAR(I31))) | Z31: =IF(ISERROR(IF(OR(I31="",I31="Ativo"),"",MONTH(I31))),"",IF(OR(I31="",I31="Ativo"),"",MONTH(I31))) | AA31: =IF(ISERROR(IF(W31="","",IF(AND(W31<=Cad_Inicial!$D$8,Y31>Cad_Inicial!$D$8),1,0))),"",IF(W31="","",IF(AND(W31<=Cad_Inicial!$D$8,Y31>Cad_Inicial!$D$8),1,0))) | AB31: =IF(ISERROR(IF(W31="","",IF(AND(W31<=(Cad_Inicial!$D$8-1),Y31>Cad_Inicial!$D$8-1),1,0))),"",IF(W31="","",IF(W31="","",IF(AND(W31<=(Cad_Inicial!$D$8-1),Y31>Cad_Inicial!$D$8-1),1,0)))) | AC31: =IF(ISERROR(IF(I31="Ativo","",VLOOKUP(C31,Lanç!$C$8:$E$208,3,0))),"",IF(I31="Ativo","",VLOOKUP(C31,Lanç!$C$8:$E$208,3,0))) | AG31: =IF(ISERROR(IF(Cad!C37="","",Cad!C37)),"",IF(Cad!C37="","",Cad!C37))
... L208: =IF(ISERROR(IF(G208="","",VLOOKUP(C208,Lanç_Promoções!$C$8:$F$2008,4,0))),G208,IF(G208="","",VLOOKUP(C208,Lanç_Promoções!$C$8:$F$2008,4,0))) | M208: =IF(ISERROR(IF(L208="","",VLOOKUP(L208,Cad!$C$8:$D$208,2,0))),"",IF(L208="","",VLOOKUP(L208,Cad!$C$8:$D$208,2,0))) | N208: =IF(ISERROR(IF(E208="","",ROUND((TODAY()-E208)/365,0))),"",IF(E208="","",ROUND((TODAY()-E208)/365,0))) | O208: =IF(ISERROR(IF(N208="","",IF(N208>60,"Mais de 60 anos",IF(N208>54,"54 a 60 anos",IF(N208>44,"44 a 53 anos",IF(N208>34,"34 a 43 anos",IF(N208>24,"24 a 33 anos","18 a 23 anos"))))))),"",IF(N208="","",IF(N208>60,"Mais de 60 anos",IF(N208>54,"54 a 60 anos",IF(N208>44,"44 a 53 anos",IF(N208>34,"34 a 43 anos",IF(N208>24,"24 a 33 anos","18 a 23 anos"))))))) | P208: =IF(ISERROR(IF(W208="","",IF(AND(W208<=Cad_Inicial!$D$8,Y208>Cad_Inicial!$D$8),1,0))),"",IF(W208="","",IF(AND(W208<=Cad_Inicial!$D$8,Y208>Cad_Inicial!$D$8),1,0))) | Q208: =IF(ISERROR(IF(W208="","",IF(AND(W208<=(Cad_Inicial!$D$8-1),Y208>Cad_Inicial!$D$8-1),1,0))),"",IF(W208="","",IF(W208="","",IF(AND(W208<=(Cad_Inicial!$D$8-1),Y208>Cad_Inicial!$D$8-1),1,0)))) | R208: =IF(ISERROR(IF(I208="","",IF(I208="Ativo",TRUNC((TODAY()-H208)/30/12,0),TRUNC((I208-H208)/30/12,0)))),"",IF(I208="","",IF(I208="Ativo",TRUNC((TODAY()-H208)/30/12,0),TRUNC((I208-H208)/30/12,0)))) | S208: =IF(ISERROR(IF(I208="","",IF(I208="Ativo",TRUNC(MOD((TODAY()-H208)/30,12),0),TRUNC(MOD((I208-H208)/30,12),0)))),"",IF(I208="","",IF(I208="Ativo",TRUNC(MOD((TODAY()-H208)/30,12),0),TRUNC(MOD((I208-H208)/30,12),0)))) | T208: =IF(ISERROR((R208*12+S208)),"",(R208*12+S208)) | U208: =IF(ISERROR(IF(H208="","",IF(YEAR(H208)<=Cad_Inicial!$D$8,"SIM",""))),"",IF(H208="","",IF(YEAR(H208)<=Cad_Inicial!$D$8,"SIM",""))) | V208: =IF(ISERROR(IF(H208="","",IF(AND(YEAR(H208)=Cad_Inicial!$D$8,I208="Ativo",TODAY()-H208>90),"SIM",IF(AND(YEAR(H208)=Cad_Inicial!$D$8,I208-H208>90),"SIM","")))),"",IF(H208="","",IF(AND(YEAR(H208)=Cad_Inicial!$D$8,I208="Ativo",TODAY()-H208>90),"SIM",IF(AND(YEAR(H208)=Cad_Inicial!$D$8,I208-H208>90),"SIM","")))) | W208: =IF(ISERROR(IF(H208="","",YEAR(H208))),"",IF(H208="","",YEAR(H208))) | X208: =IF(ISERROR(IF(H208="","",MONTH(H208))),"",IF(H208="","",MONTH(H208))) | Y208: =IF(ISERROR(IF(I208="","",YEAR(I208))),"",IF(I208="","",YEAR(I208))) | Z208: =IF(ISERROR(IF(OR(I208="",I208="Ativo"),"",MONTH(I208))),"",IF(OR(I208="",I208="Ativo"),"",MONTH(I208))) | AA208: =IF(ISERROR(IF(W208="","",IF(AND(W208<=Cad_Inicial!$D$8,Y208>Cad_Inicial!$D$8),1,0))),"",IF(W208="","",IF(AND(W208<=Cad_Inicial!$D$8,Y208>Cad_Inicial!$D$8),1,0))) | AB208: =IF(ISERROR(IF(W208="","",IF(AND(W208<=(Cad_Inicial!$D$8-1),Y208>Cad_Inicial!$D$8-1),1,0))),"",IF(W208="","",IF(W208="","",IF(AND(W208<=(Cad_Inicial!$D$8-1),Y208>Cad_Inicial!$D$8-1),1,0)))) | AC208: =IF(ISERROR(IF(I208="Ativo","",VLOOKUP(C208,Lanç!$C$8:$E$208,3,0))),"",IF(I208="Ativo","",VLOOKUP(C208,Lanç!$C$8:$E$208,3,0))) | AG208: =IF(ISERROR(IF(Cad!C214="","",Cad!C214)),"",IF(Cad!C214="","",Cad!C214))

Sheet Cad_Outros
C1: 1. CADASTRO
C6: Atenção! Esta parte da planilha já vem preenchida para facilitar, mas você pode alterar as opções se achar necessário.
C8: Motivos para desligamento | E8: Escolaridade
C9: Pedido de demissão | E9: Ensino fundamental
C10: Dispensa sem justa causa | E10: Ensino médio
C11: Dispensa com justa causa | E11: Superior completo
C12: Término de contrato de experiência | E12: Superior incompleto
C13: Rescisão antecipada do contrato de experiência por iniciativa do empregador | E13: Pós-graduação completa
C14: Rescisão antecipada do contrato de experiência por iniciativa do empregado | E14: Pós-graduação incompleta
C15: Falecimento do empregado | E15: Mestre | G15: Benefícios | N15: Custos
C16: Outro | E16: Doutor | G16: 2014 | H16: 2015 | I16: 2016 | J16: 2017 | K16: 2018 | L16: 2019 | N16: 2014 | O16: 2015 | P16: 2016 | Q16: 2017 | R16: 2018 | S16: 2019
G17: =IF(ISERROR(SUMIFS(Lanç_Receitas!$I$6:$I$33,Lanç_Receitas!$G$6:$G$33,$C19,Lanç_Receitas!$M$6:$M$33,G$16)),"",SUMIFS(Lanç_Receitas!$I$6:$I$33,Lanç_Receitas!$G$6:$G$33,$C19,Lanç_Receitas!$M$6:$M$33,G$16)) -> 0 | H17: =IF(ISERROR(SUMIFS(Lanç_Receitas!$I$6:$I$33,Lanç_Receitas!$G$6:$G$33,$C19,Lanç_Receitas!$M$6:$M$33,H$16)),"",SUMIFS(Lanç_Receitas!$I$6:$I$33,Lanç_Receitas!$G$6:$G$33,$C19,Lanç_Receitas!$M$6:$M$33,H$16)) -> 0 | I17: =IF(ISERROR(SUMIFS(Lanç_Receitas!$I$6:$I$33,Lanç_Receitas!$G$6:$G$33,$C19,Lanç_Receitas!$M$6:$M$33,I$16)),"",SUMIFS(Lanç_Receitas!$I$6:$I$33,Lanç_Receitas!$G$6:$G$33,$C19,Lanç_Receitas!$M$6:$M$33,I$16)) -> 0 | J17: =IF(ISERROR(SUMIFS(Lanç_Receitas!$I$6:$I$33,Lanç_Receitas!$G$6:$G$33,$C19,Lanç_Receitas!$M$6:$M$33,J$16)),"",SUMIFS(Lanç_Receitas!$I$6:$I$33,Lanç_Receitas!$G$6:$G$33,$C19,Lanç_Receitas!$M$6:$M$33,J$16)) -> 0 | K17: =IF(ISERROR(SUMIFS(Lanç_Receitas!$I$6:$I$33,Lanç_Receitas!$G$6:$G$33,$C19,Lanç_Receitas!$M$6:$M$33,K$16)),"",SUMIFS(Lanç_Receitas!$I$6:$I$33,Lanç_Receitas!$G$6:$G$33,$C19,Lanç_Receitas!$M$6:$M$33,K$16)) -> 0 | L17: =IF(ISERROR(SUMIFS(Lanç_Receitas!$I$6:$I$33,Lanç_Receitas!$G$6:$G$33,$C19,Lanç_Receitas!$M$6:$M$33,L$16)),"",SUMIFS(Lanç_Receitas!$I$6:$I$33,Lanç_Receitas!$G$6:$G$33,$C19,Lanç_Receitas!$M$6:$M$33,L$16)) -> 0 | N17: =IF(ISERROR(SUMIFS(Lanç_Receitas!$I$6:$I$33,Lanç_Receitas!$G$6:$G$33,$E19,Lanç_Receitas!$M$6:$M$33,N$16)),"",SUMIFS(Lanç_Receitas!$I$6:$I$33,Lanç_Receitas!$G$6:$G$33,$E19,Lanç_Receitas!$M$6:$M$33,N$16)) -> 0 | O17: =IF(ISERROR(SUMIFS(Lanç_Receitas!$I$6:$I$33,Lanç_Receitas!$G$6:$G$33,$E19,Lanç_Receitas!$M$6:$M$33,O$16)),"",SUMIFS(Lanç_Receitas!$I$6:$I$33,Lanç_Receitas!$G$6:$G$33,$E19,Lanç_Receitas!$M$6:$M$33,O$16)) -> 0 | P17: =IF(ISERROR(SUMIFS(Lanç_Receitas!$I$6:$I$33,Lanç_Receitas!$G$6:$G$33,$E19,Lanç_Receitas!$M$6:$M$33,P$16)),"",SUMIFS(Lanç_Receitas!$I$6:$I$33,Lanç_Receitas!$G$6:$G$33,$E19,Lanç_Receitas!$M$6:$M$33,P$16)) -> 0 | Q17: =IF(ISERROR(SUMIFS(Lanç_Receitas!$I$6:$I$33,Lanç_Receitas!$G$6:$G$33,$E19,Lanç_Receitas!$M$6:$M$33,Q$16)),"",SUMIFS(Lanç_Receitas!$I$6:$I$33,Lanç_Receitas!$G$6:$G$33,$E19,Lanç_Receitas!$M$6:$M$33,Q$16)) -> 0 | R17: =IF(ISERROR(SUMIFS(Lanç_Receitas!$I$6:$I$33,Lanç_Receitas!$G$6:$G$33,$E19,Lanç_Receitas!$M$6:$M$33,R$16)),"",SUMIFS(Lanç_Receitas!$I$6:$I$33,Lanç_Receitas!$G$6:$G$33,$E19,Lanç_Receitas!$M$6:$M$33,R$16)) -> 0 | S17: =IF(ISERROR(SUMIFS(Lanç_Receitas!$I$6:$I$33,Lanç_Receitas!$G$6:$G$33,$E19,Lanç_Receitas!$M$6:$M$33,S$16)),"",SUMIFS(Lanç_Receitas!$I$6:$I$33,Lanç_Receitas!$G$6:$G$33,$E19,Lanç_Receitas!$M$6:$M$33,S$16)) -> 0
C18: Cadasto de benefícios | E18: Custos com folha | G18: =IF(ISERROR(SUMIFS(Lanç_Receitas!$I$6:$I$33,Lanç_Receitas!$G$6:$G$33,$C20,Lanç_Receitas!$M$6:$M$33,G$16)),"",SUMIFS(Lanç_Receitas!$I$6:$I$33,Lanç_Receitas!$G$6:$G$33,$C20,Lanç_Receitas!$M$6:$M$33,G$16)) -> 0 | H18: =IF(ISERROR(SUMIFS(Lanç_Receitas!$I$6:$I$33,Lanç_Receitas!$G$6:$G$33,$C20,Lanç_Receitas!$M$6:$M$33,H$16)),"",SUMIFS(Lanç_Receitas!$I$6:$I$33,Lanç_Receitas!$G$6:$G$33,$C20,Lanç_Receitas!$M$6:$M$33,H$16)) -> 0 | I18: =IF(ISERROR(SUMIFS(Lanç_Receitas!$I$6:$I$33,Lanç_Receitas!$G$6:$G$33,$C20,Lanç_Receitas!$M$6:$M$33,I$16)),"",SUMIFS(Lanç_Receitas!$I$6:$I$33,Lanç_Receitas!$G$6:$G$33,$C20,Lanç_Receitas!$M$6:$M$33,I$16)) -> 0 | J18: =IF(ISERROR(SUMIFS(Lanç_Receitas!$I$6:$I$33,Lanç_Receitas!$G$6:$G$33,$C20,Lanç_Receitas!$M$6:$M$33,J$16)),"",SUMIFS(Lanç_Receitas!$I$6:$I$33,Lanç_Receitas!$G$6:$G$33,$C20,Lanç_Receitas!$M$6:$M$33,J$16)) -> 0 | K18: =IF(ISERROR(SUMIFS(Lanç_Receitas!$I$6:$I$33,Lanç_Receitas!$G$6:$G$33,$C20,Lanç_Receitas!$M$6:$M$33,K$16)),"",SUMIFS(Lanç_Receitas!$I$6:$I$33,Lanç_Receitas!$G$6:$G$33,$C20,Lanç_Receitas!$M$6:$M$33,K$16)) -> 0 | L18: =IF(ISERROR(SUMIFS(Lanç_Receitas!$I$6:$I$33,Lanç_Receitas!$G$6:$G$33,$C20,Lanç_Receitas!$M$6:$M$33,L$16)),"",SUMIFS(Lanç_Receitas!$I$6:$I$33,Lanç_Receitas!$G$6:$G$33,$C20,Lanç_Receitas!$M$6:$M$33,L$16)) -> 0 | N18: =IF(ISERROR(SUMIFS(Lanç_Receitas!$I$6:$I$33,Lanç_Receitas!$G$6:$G$33,$E20,Lanç_Receitas!$M$6:$M$33,N$16)),"",SUMIFS(Lanç_Receitas!$I$6:$I$33,Lanç_Receitas!$G$6:$G$33,$E20,Lanç_Receitas!$M$6:$M$33,N$16)) -> 0 | O18: =IF(ISERROR(SUMIFS(Lanç_Receitas!$I$6:$I$33,Lanç_Receitas!$G$6:$G$33,$E20,Lanç_Receitas!$M$6:$M$33,O$16)),"",SUMIFS(Lanç_Receitas!$I$6:$I$33,Lanç_Receitas!$G$6:$G$33,$E20,Lanç_Receitas!$M$6:$M$33,O$16)) -> 0 | P18: =IF(ISERROR(SUMIFS(Lanç_Receitas!$I$6:$I$33,Lanç_Receitas!$G$6:$G$33,$E20,Lanç_Receitas!$M$6:$M$33,P$16)),"",SUMIFS(Lanç_Receitas!$I$6:$I$33,Lanç_Receitas!$G$6:$G$33,$E20,Lanç_Receitas!$M$6:$M$33,P$16)) -> 0 | Q18: =IF(ISERROR(SUMIFS(Lanç_Receitas!$I$6:$I$33,Lanç_Receitas!$G$6:$G$33,$E20,Lanç_Receitas!$M$6:$M$33,Q$16)),"",SUMIFS(Lanç_Receitas!$I$6:$I$33,Lanç_Receitas!$G$6:$G$33,$E20,Lanç_Receitas!$M$6:$M$33,Q$16)) -> 0 | R18: =IF(ISERROR(SUMIFS(Lanç_Receitas!$I$6:$I$33,Lanç_Receitas!$G$6:$G$33,$E20,Lanç_Receitas!$M$6:$M$33,R$16)),"",SUMIFS(Lanç_Receitas!$I$6:$I$33,Lanç_Receitas!$G$6:$G$33,$E20,Lanç_Receitas!$M$6:$M$33,R$16)) -> 0 | S18: =IF(ISERROR(SUMIFS(Lanç_Receitas!$I$6:$I$33,Lanç_Receitas!$G$6:$G$33,$E20,Lanç_Receitas!$M$6:$M$33,S$16)),"",SUMIFS(Lanç_Receitas!$I$6:$I$33,Lanç_Receitas!$G$6:$G$33,$E20,Lanç_Receitas!$M$6:$M$33,S$16)) -> 0
C19: Alimentação | E19: Salários | G19: =IF(ISERROR(SUMIFS(Lanç_Receitas!$I$6:$I$33,Lanç_Receitas!$G$6:$G$33,$C21,Lanç_Receitas!$M$6:$M$33,G$16)),"",SUMIFS(Lanç_Receitas!$I$6:$I$33,Lanç_Receitas!$G$6:$G$33,$C21,Lanç_Receitas!$M$6:$M$33,G$16)) -> 0 | H19: =IF(ISERROR(SUMIFS(Lanç_Receitas!$I$6:$I$33,Lanç_Receitas!$G$6:$G$33,$C21,Lanç_Receitas!$M$6:$M$33,H$16)),"",SUMIFS(Lanç_Receitas!$I$6:$I$33,Lanç_Receitas!$G$6:$G$33,$C21,Lanç_Receitas!$M$6:$M$33,H$16)) -> 0 | I19: =IF(ISERROR(SUMIFS(Lanç_Receitas!$I$6:$I$33,Lanç_Receitas!$G$6:$G$33,$C21,Lanç_Receitas!$M$6:$M$33,I$16)),"",SUMIFS(Lanç_Receitas!$I$6:$I$33,Lanç_Receitas!$G$6:$G$33,$C21,Lanç_Receitas!$M$6:$M$33,I$16)) -> 0 | J19: =IF(ISERROR(SUMIFS(Lanç_Receitas!$I$6:$I$33,Lanç_Receitas!$G$6:$G$33,$C21,Lanç_Receitas!$M$6:$M$33,J$16)),"",SUMIFS(Lanç_Receitas!$I$6:$I$33,Lanç_Receitas!$G$6:$G$33,$C21,Lanç_Receitas!$M$6:$M$33,J$16)) -> 0 | K19: =IF(ISERROR(SUMIFS(Lanç_Receitas!$I$6:$I$33,Lanç_Receitas!$G$6:$G$33,$C21,Lanç_Receitas!$M$6:$M$33,K$16)),"",SUMIFS(Lanç_Receitas!$I$6:$I$33,Lanç_Receitas!$G$6:$G$33,$C21,Lanç_Receitas!$M$6:$M$33,K$16)) -> 0 | L19: =IF(ISERROR(SUMIFS(Lanç_Receitas!$I$6:$I$33,Lanç_Receitas!$G$6:$G$33,$C21,Lanç_Receitas!$M$6:$M$33,L$16)),"",SUMIFS(Lanç_Receitas!$I$6:$I$33,Lanç_Receitas!$G$6:$G$33,$C21,Lanç_Receitas!$M$6:$M$33,L$16)) -> 0 | N19: =IF(ISERROR(SUMIFS(Lanç_Receitas!$I$6:$I$33,Lanç_Receitas!$G$6:$G$33,$E21,Lanç_Receitas!$M$6:$M$33,N$16)),"",SUMIFS(Lanç_Receitas!$I$6:$I$33,Lanç_Receitas!$G$6:$G$33,$E21,Lanç_Receitas!$M$6:$M$33,N$16)) -> 0 | O19: =IF(ISERROR(SUMIFS(Lanç_Receitas!$I$6:$I$33,Lanç_Receitas!$G$6:$G$33,$E21,Lanç_Receitas!$M$6:$M$33,O$16)),"",SUMIFS(Lanç_Receitas!$I$6:$I$33,Lanç_Receitas!$G$6:$G$33,$E21,Lanç_Receitas!$M$6:$M$33,O$16)) -> 0 | P19: =IF(ISERROR(SUMIFS(Lanç_Receitas!$I$6:$I$33,Lanç_Receitas!$G$6:$G$33,$E21,Lanç_Receitas!$M$6:$M$33,P$16)),"",SUMIFS(Lanç_Receitas!$I$6:$I$33,Lanç_Receitas!$G$6:$G$33,$E21,Lanç_Receitas!$M$6:$M$33,P$16)) -> 0 | Q19: =IF(ISERROR(SUMIFS(Lanç_Receitas!$I$6:$I$33,Lanç_Receitas!$G$6:$G$33,$E21,Lanç_Receitas!$M$6:$M$33,Q$16)),"",SUMIFS(Lanç_Receitas!$I$6:$I$33,Lanç_Receitas!$G$6:$G$33,$E21,Lanç_Receitas!$M$6:$M$33,Q$16)) -> 0 | R19: =IF(ISERROR(SUMIFS(Lanç_Receitas!$I$6:$I$33,Lanç_Receitas!$G$6:$G$33,$E21,Lanç_Receitas!$M$6:$M$33,R$16)),"",SUMIFS(Lanç_Receitas!$I$6:$I$33,Lanç_Receitas!$G$6:$G$33,$E21,Lanç_Receitas!$M$6:$M$33,R$16)) -> 0 | S19: =IF(ISERROR(SUMIFS(Lanç_Receitas!$I$6:$I$33,Lanç_Receitas!$G$6:$G$33,$E21,Lanç_Receitas!$M$6:$M$33,S$16)),"",SUMIFS(Lanç_Receitas!$I$6:$I$33,Lanç_Receitas!$G$6:$G$33,$E21,Lanç_Receitas!$M$6:$M$33,S$16)) -> 0
C20: Saúde | E20: Bolsa de estágio | G20: =IF(ISERROR(SUMIFS(Lanç_Receitas!$I$6:$I$33,Lanç_Receitas!$G$6:$G$33,$C22,Lanç_Receitas!$M$6:$M$33,G$16)),"",SUMIFS(Lanç_Receitas!$I$6:$I$33,Lanç_Receitas!$G$6:$G$33,$C22,Lanç_Receitas!$M$6:$M$33,G$16)) -> 0 | H20: =IF(ISERROR(SUMIFS(Lanç_Receitas!$I$6:$I$33,Lanç_Receitas!$G$6:$G$33,$C22,Lanç_Receitas!$M$6:$M$33,H$16)),"",SUMIFS(Lanç_Receitas!$I$6:$I$33,Lanç_Receitas!$G$6:$G$33,$C22,Lanç_Receitas!$M$6:$M$33,H$16)) -> 0 | I20: =IF(ISERROR(SUMIFS(Lanç_Receitas!$I$6:$I$33,Lanç_Receitas!$G$6:$G$33,$C22,Lanç_Receitas!$M$6:$M$33,I$16)),"",SUMIFS(Lanç_Receitas!$I$6:$I$33,Lanç_Receitas!$G$6:$G$33,$C22,Lanç_Receitas!$M$6:$M$33,I$16)) -> 0 | J20: =IF(ISERROR(SUMIFS(Lanç_Receitas!$I$6:$I$33,Lanç_Receitas!$G$6:$G$33,$C22,Lanç_Receitas!$M$6:$M$33,J$16)),"",SUMIFS(Lanç_Receitas!$I$6:$I$33,Lanç_Receitas!$G$6:$G$33,$C22,Lanç_Receitas!$M$6:$M$33,J$16)) -> 0 | K20: =IF(ISERROR(SUMIFS(Lanç_Receitas!$I$6:$I$33,Lanç_Receitas!$G$6:$G$33,$C22,Lanç_Receitas!$M$6:$M$33,K$16)),"",SUMIFS(Lanç_Receitas!$I$6:$I$33,Lanç_Receitas!$G$6:$G$33,$C22,Lanç_Receitas!$M$6:$M$33,K$16)) -> 0 | L20: =IF(ISERROR(SUMIFS(Lanç_Receitas!$I$6:$I$33,Lanç_Receitas!$G$6:$G$33,$C22,Lanç_Receitas!$M$6:$M$33,L$16)),"",SUMIFS(Lanç_Receitas!$I$6:$I$33,Lanç_Receitas!$G$6:$G$33,$C22,Lanç_Receitas!$M$6:$M$33,L$16)) -> 0 | N20: =IF(ISERROR(SUMIFS(Lanç_Receitas!$I$6:$I$33,Lanç_Receitas!$G$6:$G$33,$E22,Lanç_Receitas!$M$6:$M$33,N$16)),"",SUMIFS(Lanç_Receitas!$I$6:$I$33,Lanç_Receitas!$G$6:$G$33,$E22,Lanç_Receitas!$M$6:$M$33,N$16)) -> 0 | O20: =IF(ISERROR(SUMIFS(Lanç_Receitas!$I$6:$I$33,Lanç_Receitas!$G$6:$G$33,$E22,Lanç_Receitas!$M$6:$M$33,O$16)),"",SUMIFS(Lanç_Receitas!$I$6:$I$33,Lanç_Receitas!$G$6:$G$33,$E22,Lanç_Receitas!$M$6:$M$33,O$16)) -> 0 | P20: =IF(ISERROR(SUMIFS(Lanç_Receitas!$I$6:$I$33,Lanç_Receitas!$G$6:$G$33,$E22,Lanç_Receitas!$M$6:$M$33,P$16)),"",SUMIFS(Lanç_Receitas!$I$6:$I$33,Lanç_Receitas!$G$6:$G$33,$E22,Lanç_Receitas!$M$6:$M$33,P$16)) -> 0 | Q20: =IF(ISERROR(SUMIFS(Lanç_Receitas!$I$6:$I$33,Lanç_Receitas!$G$6:$G$33,$E22,Lanç_Receitas!$M$6:$M$33,Q$16)),"",SUMIFS(Lanç_Receitas!$I$6:$I$33,Lanç_Receitas!$G$6:$G$33,$E22,Lanç_Receitas!$M$6:$M$33,Q$16)) -> 0 | R20: =IF(ISERROR(SUMIFS(Lanç_Receitas!$I$6:$I$33,Lanç_Receitas!$G$6:$G$33,$E22,Lanç_Receitas!$M$6:$M$33,R$16)),"",SUMIFS(Lanç_Receitas!$I$6:$I$33,Lanç_Receitas!$G$6:$G$33,$E22,Lanç_Receitas!$M$6:$M$33,R$16)) -> 0 | S20: =IF(ISERROR(SUMIFS(Lanç_Receitas!$I$6:$I$33,Lanç_Receitas!$G$6:$G$33,$E22,Lanç_Receitas!$M$6:$M$33,S$16)),"",SUMIFS(Lanç_Receitas!$I$6:$I$33,Lanç_Receitas!$G$6:$G$33,$E22,Lanç_Receitas!$M$6:$M$33,S$16)) -> 0
C21: Odonto | E21: Pró-labore | G21: =IF(ISERROR(SUMIFS(Lanç_Receitas!$I$6:$I$33,Lanç_Receitas!$G$6:$G$33,$C23,Lanç_Receitas!$M$6:$M$33,G$16)),"",SUMIFS(Lanç_Receitas!$I$6:$I$33,Lanç_Receitas!$G$6:$G$33,$C23,Lanç_Receitas!$M$6:$M$33,G$16)) -> 0 | H21: =IF(ISERROR(SUMIFS(Lanç_Receitas!$I$6:$I$33,Lanç_Receitas!$G$6:$G$33,$C23,Lanç_Receitas!$M$6:$M$33,H$16)),"",SUMIFS(Lanç_Receitas!$I$6:$I$33,Lanç_Receitas!$G$6:$G$33,$C23,Lanç_Receitas!$M$6:$M$33,H$16)) -> 0 | I21: =IF(ISERROR(SUMIFS(Lanç_Receitas!$I$6:$I$33,Lanç_Receitas!$G$6:$G$33,$C23,Lanç_Receitas!$M$6:$M$33,I$16)),"",SUMIFS(Lanç_Receitas!$I$6:$I$33,Lanç_Receitas!$G$6:$G$33,$C23,Lanç_Receitas!$M$6:$M$33,I$16)) -> 0 | J21: =IF(ISERROR(SUMIFS(Lanç_Receitas!$I$6:$I$33,Lanç_Receitas!$G$6:$G$33,$C23,Lanç_Receitas!$M$6:$M$33,J$16)),"",SUMIFS(Lanç_Receitas!$I$6:$I$33,Lanç_Receitas!$G$6:$G$33,$C23,Lanç_Receitas!$M$6:$M$33,J$16)) -> 0 | K21: =IF(ISERROR(SUMIFS(Lanç_Receitas!$I$6:$I$33,Lanç_Receitas!$G$6:$G$33,$C23,Lanç_Receitas!$M$6:$M$33,K$16)),"",SUMIFS(Lanç_Receitas!$I$6:$I$33,Lanç_Receitas!$G$6:$G$33,$C23,Lanç_Receitas!$M$6:$M$33,K$16)) -> 0 | L21: =IF(ISERROR(SUMIFS(Lanç_Receitas!$I$6:$I$33,Lanç_Receitas!$G$6:$G$33,$C23,Lanç_Receitas!$M$6:$M$33,L$16)),"",SUMIFS(Lanç_Receitas!$I$6:$I$33,Lanç_Receitas!$G$6:$G$33,$C23,Lanç_Receitas!$M$6:$M$33,L$16)) -> 0 | N21: =IF(ISERROR(SUMIFS(Lanç_Receitas!$I$6:$I$33,Lanç_Receitas!$G$6:$G$33,$E23,Lanç_Receitas!$M$6:$M$33,N$16)),"",SUMIFS(Lanç_Receitas!$I$6:$I$33,Lanç_Receitas!$G$6:$G$33,$E23,Lanç_Receitas!$M$6:$M$33,N$16)) -> 0 | O21: =IF(ISERROR(SUMIFS(Lanç_Receitas!$I$6:$I$33,Lanç_Receitas!$G$6:$G$33,$E23,Lanç_Receitas!$M$6:$M$33,O$16)),"",SUMIFS(Lanç_Receitas!$I$6:$I$33,Lanç_Receitas!$G$6:$G$33,$E23,Lanç_Receitas!$M$6:$M$33,O$16)) -> 0 | P21: =IF(ISERROR(SUMIFS(Lanç_Receitas!$I$6:$I$33,Lanç_Receitas!$G$6:$G$33,$E23,Lanç_Receitas!$M$6:$M$33,P$16)),"",SUMIFS(Lanç_Receitas!$I$6:$I$33,Lanç_Receitas!$G$6:$G$33,$E23,Lanç_Receitas!$M$6:$M$33,P$16)) -> 0 | Q21: =IF(ISERROR(SUMIFS(Lanç_Receitas!$I$6:$I$33,Lanç_Receitas!$G$6:$G$33,$E23,Lanç_Receitas!$M$6:$M$33,Q$16)),"",SUMIFS(Lanç_Receitas!$I$6:$I$33,Lanç_Receitas!$G$6:$G$33,$E23,Lanç_Receitas!$M$6:$M$33,Q$16)) -> 0 | R21: =IF(ISERROR(SUMIFS(Lanç_Receitas!$I$6:$I$33,Lanç_Receitas!$G$6:$G$33,$E23,Lanç_Receitas!$M$6:$M$33,R$16)),"",SUMIFS(Lanç_Receitas!$I$6:$I$33,Lanç_Receitas!$G$6:$G$33,$E23,Lanç_Receitas!$M$6:$M$33,R$16)) -> 0 | S21: =IF(ISERROR(SUMIFS(Lanç_Receitas!$I$6:$I$33,Lanç_Receitas!$G$6:$G$33,$E23,Lanç_Receitas!$M$6:$M$33,S$16)),"",SUMIFS(Lanç_Receitas!$I$6:$I$33,Lanç_Receitas!$G$6:$G$33,$E23,Lanç_Receitas!$M$6:$M$33,S$16)) -> 0
C22: Transporte | E22: Férias | G22: =IF(ISERROR(SUMIFS(Lanç_Receitas!$I$6:$I$33,Lanç_Receitas!$G$6:$G$33,$C24,Lanç_Receitas!$M$6:$M$33,G$16)),"",SUMIFS(Lanç_Receitas!$I$6:$I$33,Lanç_Receitas!$G$6:$G$33,$C24,Lanç_Receitas!$M$6:$M$33,G$16)) -> 0 | H22: =IF(ISERROR(SUMIFS(Lanç_Receitas!$I$6:$I$33,Lanç_Receitas!$G$6:$G$33,$C24,Lanç_Receitas!$M$6:$M$33,H$16)),"",SUMIFS(Lanç_Receitas!$I$6:$I$33,Lanç_Receitas!$G$6:$G$33,$C24,Lanç_Receitas!$M$6:$M$33,H$16)) -> 0 | I22: =IF(ISERROR(SUMIFS(Lanç_Receitas!$I$6:$I$33,Lanç_Receitas!$G$6:$G$33,$C24,Lanç_Receitas!$M$6:$M$33,I$16)),"",SUMIFS(Lanç_Receitas!$I$6:$I$33,Lanç_Receitas!$G$6:$G$33,$C24,Lanç_Receitas!$M$6:$M$33,I$16)) -> 0 | J22: =IF(ISERROR(SUMIFS(Lanç_Receitas!$I$6:$I$33,Lanç_Receitas!$G$6:$G$33,$C24,Lanç_Receitas!$M$6:$M$33,J$16)),"",SUMIFS(Lanç_Receitas!$I$6:$I$33,Lanç_Receitas!$G$6:$G$33,$C24,Lanç_Receitas!$M$6:$M$33,J$16)) -> 0 | K22: =IF(ISERROR(SUMIFS(Lanç_Receitas!$I$6:$I$33,Lanç_Receitas!$G$6:$G$33,$C24,Lanç_Receitas!$M$6:$M$33,K$16)),"",SUMIFS(Lanç_Receitas!$I$6:$I$33,Lanç_Receitas!$G$6:$G$33,$C24,Lanç_Receitas!$M$6:$M$33,K$16)) -> 0 | L22: =IF(ISERROR(SUMIFS(Lanç_Receitas!$I$6:$I$33,Lanç_Receitas!$G$6:$G$33,$C24,Lanç_Receitas!$M$6:$M$33,L$16)),"",SUMIFS(Lanç_Receitas!$I$6:$I$33,Lanç_Receitas!$G$6:$G$33,$C24,Lanç_Receitas!$M$6:$M$33,L$16)) -> 0 | N22: =IF(ISERROR(SUMIFS(Lanç_Receitas!$I$6:$I$33,Lanç_Receitas!$G$6:$G$33,$E24,Lanç_Receitas!$M$6:$M$33,N$16)),"",SUMIFS(Lanç_Receitas!$I$6:$I$33,Lanç_Receitas!$G$6:$G$33,$E24,Lanç_Receitas!$M$6:$M$33,N$16)) -> 0 | O22: =IF(ISERROR(SUMIFS(Lanç_Receitas!$I$6:$I$33,Lanç_Receitas!$G$6:$G$33,$E24,Lanç_Receitas!$M$6:$M$33,O$16)),"",SUMIFS(Lanç_Receitas!$I$6:$I$33,Lanç_Receitas!$G$6:$G$33,$E24,Lanç_Receitas!$M$6:$M$33,O$16)) -> 0 | P22: =IF(ISERROR(SUMIFS(Lanç_Receitas!$I$6:$I$33,Lanç_Receitas!$G$6:$G$33,$E24,Lanç_Receitas!$M$6:$M$33,P$16)),"",SUMIFS(Lanç_Receitas!$I$6:$I$33,Lanç_Receitas!$G$6:$G$33,$E24,Lanç_Receitas!$M$6:$M$33,P$16)) -> 0 | Q22: =IF(ISERROR(SUMIFS(Lanç_Receitas!$I$6:$I$33,Lanç_Receitas!$G$6:$G$33,$E24,Lanç_Receitas!$M$6:$M$33,Q$16)),"",SUMIFS(Lanç_Receitas!$I$6:$I$33,Lanç_Receitas!$G$6:$G$33,$E24,Lanç_Receitas!$M$6:$M$33,Q$16)) -> 0 | R22: =IF(ISERROR(SUMIFS(Lanç_Receitas!$I$6:$I$33,Lanç_Receitas!$G$6:$G$33,$E24,Lanç_Receitas!$M$6:$M$33,R$16)),"",SUMIFS(Lanç_Receitas!$I$6:$I$33,Lanç_Receitas!$G$6:$G$33,$E24,Lanç_Receitas!$M$6:$M$33,R$16)) -> 0 | S22: =IF(ISERROR(SUMIFS(Lanç_Receitas!$I$6:$I$33,Lanç_Receitas!$G$6:$G$33,$E24,Lanç_Receitas!$M$6:$M$33,S$16)),"",SUMIFS(Lanç_Receitas!$I$6:$I$33,Lanç_Receitas!$G$6:$G$33,$E24,Lanç_Receitas!$M$6:$M$33,S$16)) -> 0
C23: Seguro de vida | E23: 13º Salário | G23: =IF(ISERROR(SUMIFS(Lanç_Receitas!$I$6:$I$33,Lanç_Receitas!$G$6:$G$33,$C25,Lanç_Receitas!$M$6:$M$33,G$16)),"",SUMIFS(Lanç_Receitas!$I$6:$I$33,Lanç_Receitas!$G$6:$G$33,$C25,Lanç_Receitas!$M$6:$M$33,G$16)) -> 0 | H23: =IF(ISERROR(SUMIFS(Lanç_Receitas!$I$6:$I$33,Lanç_Receitas!$G$6:$G$33,$C25,Lanç_Receitas!$M$6:$M$33,H$16)),"",SUMIFS(Lanç_Receitas!$I$6:$I$33,Lanç_Receitas!$G$6:$G$33,$C25,Lanç_Receitas!$M$6:$M$33,H$16)) -> 0 | I23: =IF(ISERROR(SUMIFS(Lanç_Receitas!$I$6:$I$33,Lanç_Receitas!$G$6:$G$33,$C25,Lanç_Receitas!$M$6:$M$33,I$16)),"",SUMIFS(Lanç_Receitas!$I$6:$I$33,Lanç_Receitas!$G$6:$G$33,$C25,Lanç_Receitas!$M$6:$M$33,I$16)) -> 0 | J23: =IF(ISERROR(SUMIFS(Lanç_Receitas!$I$6:$I$33,Lanç_Receitas!$G$6:$G$33,$C25,Lanç_Receitas!$M$6:$M$33,J$16)),"",SUMIFS(Lanç_Receitas!$I$6:$I$33,Lanç_Receitas!$G$6:$G$33,$C25,Lanç_Receitas!$M$6:$M$33,J$16)) -> 0 | K23: =IF(ISERROR(SUMIFS(Lanç_Receitas!$I$6:$I$33,Lanç_Receitas!$G$6:$G$33,$C25,Lanç_Receitas!$M$6:$M$33,K$16)),"",SUMIFS(Lanç_Receitas!$I$6:$I$33,Lanç_Receitas!$G$6:$G$33,$C25,Lanç_Receitas!$M$6:$M$33,K$16)) -> 0 | L23: =IF(ISERROR(SUMIFS(Lanç_Receitas!$I$6:$I$33,Lanç_Receitas!$G$6:$G$33,$C25,Lanç_Receitas!$M$6:$M$33,L$16)),"",SUMIFS(Lanç_Receitas!$I$6:$I$33,Lanç_Receitas!$G$6:$G$33,$C25,Lanç_Receitas!$M$6:$M$33,L$16)) -> 0 | N23: =IF(ISERROR(SUMIFS(Lanç_Receitas!$I$6:$I$33,Lanç_Receitas!$G$6:$G$33,$E25,Lanç_Receitas!$M$6:$M$33,N$16)),"",SUMIFS(Lanç_Receitas!$I$6:$I$33,Lanç_Receitas!$G$6:$G$33,$E25,Lanç_Receitas!$M$6:$M$33,N$16)) -> 0 | O23: =IF(ISERROR(SUMIFS(Lanç_Receitas!$I$6:$I$33,Lanç_Receitas!$G$6:$G$33,$E25,Lanç_Receitas!$M$6:$M$33,O$16)),"",SUMIFS(Lanç_Receitas!$I$6:$I$33,Lanç_Receitas!$G$6:$G$33,$E25,Lanç_Receitas!$M$6:$M$33,O$16)) -> 0 | P23: =IF(ISERROR(SUMIFS(Lanç_Receitas!$I$6:$I$33,Lanç_Receitas!$G$6:$G$33,$E25,Lanç_Receitas!$M$6:$M$33,P$16)),"",SUMIFS(Lanç_Receitas!$I$6:$I$33,Lanç_Receitas!$G$6:$G$33,$E25,Lanç_Receitas!$M$6:$M$33,P$16)) -> 0 | Q23: =IF(ISERROR(SUMIFS(Lanç_Receitas!$I$6:$I$33,Lanç_Receitas!$G$6:$G$33,$E25,Lanç_Receitas!$M$6:$M$33,Q$16)),"",SUMIFS(Lanç_Receitas!$I$6:$I$33,Lanç_Receitas!$G$6:$G$33,$E25,Lanç_Receitas!$M$6:$M$33,Q$16)) -> 0 | R23: =IF(ISERROR(SUMIFS(Lanç_Receitas!$I$6:$I$33,Lanç_Receitas!$G$6:$G$33,$E25,Lanç_Receitas!$M$6:$M$33,R$16)),"",SUMIFS(Lanç_Receitas!$I$6:$I$33,Lanç_Receitas!$G$6:$G$33,$E25,Lanç_Receitas!$M$6:$M$33,R$16)) -> 0 | S23: =IF(ISERROR(SUMIFS(Lanç_Receitas!$I$6:$I$33,Lanç_Receitas!$G$6:$G$33,$E25,Lanç_Receitas!$M$6:$M$33,S$16)),"",SUMIFS(Lanç_Receitas!$I$6:$I$33,Lanç_Receitas!$G$6:$G$33,$E25,Lanç_Receitas!$M$6:$M$33,S$16)) -> 0
C24: Vale academia | E24: Encargos | G24: =IF(ISERROR(SUMIFS(Lanç_Receitas!$I$6:$I$33,Lanç_Receitas!$G$6:$G$33,$C26,Lanç_Receitas!$M$6:$M$33,G$16)),"",SUMIFS(Lanç_Receitas!$I$6:$I$33,Lanç_Receitas!$G$6:$G$33,$C26,Lanç_Receitas!$M$6:$M$33,G$16)) -> 0 | H24: =IF(ISERROR(SUMIFS(Lanç_Receitas!$I$6:$I$33,Lanç_Receitas!$G$6:$G$33,$C26,Lanç_Receitas!$M$6:$M$33,H$16)),"",SUMIFS(Lanç_Receitas!$I$6:$I$33,Lanç_Receitas!$G$6:$G$33,$C26,Lanç_Receitas!$M$6:$M$33,H$16)) -> 0 | I24: =IF(ISERROR(SUMIFS(Lanç_Receitas!$I$6:$I$33,Lanç_Receitas!$G$6:$G$33,$C26,Lanç_Receitas!$M$6:$M$33,I$16)),"",SUMIFS(Lanç_Receitas!$I$6:$I$33,Lanç_Receitas!$G$6:$G$33,$C26,Lanç_Receitas!$M$6:$M$33,I$16)) -> 0 | J24: =IF(ISERROR(SUMIFS(Lanç_Receitas!$I$6:$I$33,Lanç_Receitas!$G$6:$G$33,$C26,Lanç_Receitas!$M$6:$M$33,J$16)),"",SUMIFS(Lanç_Receitas!$I$6:$I$33,Lanç_Receitas!$G$6:$G$33,$C26,Lanç_Receitas!$M$6:$M$33,J$16)) -> 0 | K24: =IF(ISERROR(SUMIFS(Lanç_Receitas!$I$6:$I$33,Lanç_Receitas!$G$6:$G$33,$C26,Lanç_Receitas!$M$6:$M$33,K$16)),"",SUMIFS(Lanç_Receitas!$I$6:$I$33,Lanç_Receitas!$G$6:$G$33,$C26,Lanç_Receitas!$M$6:$M$33,K$16)) -> 0 | L24: =IF(ISERROR(SUMIFS(Lanç_Receitas!$I$6:$I$33,Lanç_Receitas!$G$6:$G$33,$C26,Lanç_Receitas!$M$6:$M$33,L$16)),"",SUMIFS(Lanç_Receitas!$I$6:$I$33,Lanç_Receitas!$G$6:$G$33,$C26,Lanç_Receitas!$M$6:$M$33,L$16)) -> 0 | N24: =IF(ISERROR(SUMIFS(Lanç_Receitas!$I$6:$I$33,Lanç_Receitas!$G$6:$G$33,$E26,Lanç_Receitas!$M$6:$M$33,N$16)),"",SUMIFS(Lanç_Receitas!$I$6:$I$33,Lanç_Receitas!$G$6:$G$33,$E26,Lanç_Receitas!$M$6:$M$33,N$16)) -> 0 | O24: =IF(ISERROR(SUMIFS(Lanç_Receitas!$I$6:$I$33,Lanç_Receitas!$G$6:$G$33,$E26,Lanç_Receitas!$M$6:$M$33,O$16)),"",SUMIFS(Lanç_Receitas!$I$6:$I$33,Lanç_Receitas!$G$6:$G$33,$E26,Lanç_Receitas!$M$6:$M$33,O$16)) -> 0 | P24: =IF(ISERROR(SUMIFS(Lanç_Receitas!$I$6:$I$33,Lanç_Receitas!$G$6:$G$33,$E26,Lanç_Receitas!$M$6:$M$33,P$16)),"",SUMIFS(Lanç_Receitas!$I$6:$I$33,Lanç_Receitas!$G$6:$G$33,$E26,Lanç_Receitas!$M$6:$M$33,P$16)) -> 0 | Q24: =IF(ISERROR(SUMIFS(Lanç_Receitas!$I$6:$I$33,Lanç_Receitas!$G$6:$G$33,$E26,Lanç_Receitas!$M$6:$M$33,Q$16)),"",SUMIFS(Lanç_Receitas!$I$6:$I$33,Lanç_Receitas!$G$6:$G$33,$E26,Lanç_Receitas!$M$6:$M$33,Q$16)) -> 0 | R24: =IF(ISERROR(SUMIFS(Lanç_Receitas!$I$6:$I$33,Lanç_Receitas!$G$6:$G$33,$E26,Lanç_Receitas!$M$6:$M$33,R$16)),"",SUMIFS(Lanç_Receitas!$I$6:$I$33,Lanç_Receitas!$G$6:$G$33,$E26,Lanç_Receitas!$M$6:$M$33,R$16)) -> 0 | S24: =IF(ISERROR(SUMIFS(Lanç_Receitas!$I$6:$I$33,Lanç_Receitas!$G$6:$G$33,$E26,Lanç_Receitas!$M$6:$M$33,S$16)),"",SUMIFS(Lanç_Receitas!$I$6:$I$33,Lanç_Receitas!$G$6:$G$33,$E26,Lanç_Receitas!$M$6:$M$33,S$16)) -> 0
C25: Creche | E25: Hora extra | G25: =IF(ISERROR(SUMIFS(Lanç_Receitas!$I$6:$I$33,Lanç_Receitas!$G$6:$G$33,$C27,Lanç_Receitas!$M$6:$M$33,G$16)),"",SUMIFS(Lanç_Receitas!$I$6:$I$33,Lanç_Receitas!$G$6:$G$33,$C27,Lanç_Receitas!$M$6:$M$33,G$16)) -> 0 | H25: =IF(ISERROR(SUMIFS(Lanç_Receitas!$I$6:$I$33,Lanç_Receitas!$G$6:$G$33,$C27,Lanç_Receitas!$M$6:$M$33,H$16)),"",SUMIFS(Lanç_Receitas!$I$6:$I$33,Lanç_Receitas!$G$6:$G$33,$C27,Lanç_Receitas!$M$6:$M$33,H$16)) -> 0 | I25: =IF(ISERROR(SUMIFS(Lanç_Receitas!$I$6:$I$33,Lanç_Receitas!$G$6:$G$33,$C27,Lanç_Receitas!$M$6:$M$33,I$16)),"",SUMIFS(Lanç_Receitas!$I$6:$I$33,Lanç_Receitas!$G$6:$G$33,$C27,Lanç_Receitas!$M$6:$M$33,I$16)) -> 0 | J25: =IF(ISERROR(SUMIFS(Lanç_Receitas!$I$6:$I$33,Lanç_Receitas!$G$6:$G$33,$C27,Lanç_Receitas!$M$6:$M$33,J$16)),"",SUMIFS(Lanç_Receitas!$I$6:$I$33,Lanç_Receitas!$G$6:$G$33,$C27,Lanç_Receitas!$M$6:$M$33,J$16)) -> 0 | K25: =IF(ISERROR(SUMIFS(Lanç_Receitas!$I$6:$I$33,Lanç_Receitas!$G$6:$G$33,$C27,Lanç_Receitas!$M$6:$M$33,K$16)),"",SUMIFS(Lanç_Receitas!$I$6:$I$33,Lanç_Receitas!$G$6:$G$33,$C27,Lanç_Receitas!$M$6:$M$33,K$16)) -> 0 | L25: =IF(ISERROR(SUMIFS(Lanç_Receitas!$I$6:$I$33,Lanç_Receitas!$G$6:$G$33,$C27,Lanç_Receitas!$M$6:$M$33,L$16)),"",SUMIFS(Lanç_Receitas!$I$6:$I$33,Lanç_Receitas!$G$6:$G$33,$C27,Lanç_Receitas!$M$6:$M$33,L$16)) -> 0 | N25: =IF(ISERROR(SUMIFS(Lanç_Receitas!$I$6:$I$33,Lanç_Receitas!$G$6:$G$33,$E27,Lanç_Receitas!$M$6:$M$33,N$16)),"",SUMIFS(Lanç_Receitas!$I$6:$I$33,Lanç_Receitas!$G$6:$G$33,$E27,Lanç_Receitas!$M$6:$M$33,N$16)) -> 0 | O25: =IF(ISERROR(SUMIFS(Lanç_Receitas!$I$6:$I$33,Lanç_Receitas!$G$6:$G$33,$E27,Lanç_Receitas!$M$6:$M$33,O$16)),"",SUMIFS(Lanç_Receitas!$I$6:$I$33,Lanç_Receitas!$G$6:$G$33,$E27,Lanç_Receitas!$M$6:$M$33,O$16)) -> 0 | P25: =IF(ISERROR(SUMIFS(Lanç_Receitas!$I$6:$I$33,Lanç_Receitas!$G$6:$G$33,$E27,Lanç_Receitas!$M$6:$M$33,P$16)),"",SUMIFS(Lanç_Receitas!$I$6:$I$33,Lanç_Receitas!$G$6:$G$33,$E27,Lanç_Receitas!$M$6:$M$33,P$16)) -> 0 | Q25: =IF(ISERROR(SUMIFS(Lanç_Receitas!$I$6:$I$33,Lanç_Receitas!$G$6:$G$33,$E27,Lanç_Receitas!$M$6:$M$33,Q$16)),"",SUMIFS(Lanç_Receitas!$I$6:$I$33,Lanç_Receitas!$G$6:$G$33,$E27,Lanç_Receitas!$M$6:$M$33,Q$16)) -> 0 | R25: =IF(ISERROR(SUMIFS(Lanç_Receitas!$I$6:$I$33,Lanç_Receitas!$G$6:$G$33,$E27,Lanç_Receitas!$M$6:$M$33,R$16)),"",SUMIFS(Lanç_Receitas!$I$6:$I$33,Lanç_Receitas!$G$6:$G$33,$E27,Lanç_Receitas!$M$6:$M$33,R$16)) -> 0 | S25: =IF(ISERROR(SUMIFS(Lanç_Receitas!$I$6:$I$33,Lanç_Receitas!$G$6:$G$33,$E27,Lanç_Receitas!$M$6:$M$33,S$16)),"",SUMIFS(Lanç_Receitas!$I$6:$I$33,Lanç_Receitas!$G$6:$G$33,$E27,Lanç_Receitas!$M$6:$M$33,S$16)) -> 0
C26: Vale combustível | E26: Outros custos | G26: =IF(ISERROR(SUMIFS(Lanç_Receitas!$I$6:$I$33,Lanç_Receitas!$G$6:$G$33,$C28,Lanç_Receitas!$M$6:$M$33,G$16)),"",SUMIFS(Lanç_Receitas!$I$6:$I$33,Lanç_Receitas!$G$6:$G$33,$C28,Lanç_Receitas!$M$6:$M$33,G$16)) -> 0 | H26: =IF(ISERROR(SUMIFS(Lanç_Receitas!$I$6:$I$33,Lanç_Receitas!$G$6:$G$33,$C28,Lanç_Receitas!$M$6:$M$33,H$16)),"",SUMIFS(Lanç_Receitas!$I$6:$I$33,Lanç_Receitas!$G$6:$G$33,$C28,Lanç_Receitas!$M$6:$M$33,H$16)) -> 0 | I26: =IF(ISERROR(SUMIFS(Lanç_Receitas!$I$6:$I$33,Lanç_Receitas!$G$6:$G$33,$C28,Lanç_Receitas!$M$6:$M$33,I$16)),"",SUMIFS(Lanç_Receitas!$I$6:$I$33,Lanç_Receitas!$G$6:$G$33,$C28,Lanç_Receitas!$M$6:$M$33,I$16)) -> 0 | J26: =IF(ISERROR(SUMIFS(Lanç_Receitas!$I$6:$I$33,Lanç_Receitas!$G$6:$G$33,$C28,Lanç_Receitas!$M$6:$M$33,J$16)),"",SUMIFS(Lanç_Receitas!$I$6:$I$33,Lanç_Receitas!$G$6:$G$33,$C28,Lanç_Receitas!$M$6:$M$33,J$16)) -> 0 | K26: =IF(ISERROR(SUMIFS(Lanç_Receitas!$I$6:$I$33,Lanç_Receitas!$G$6:$G$33,$C28,Lanç_Receitas!$M$6:$M$33,K$16)),"",SUMIFS(Lanç_Receitas!$I$6:$I$33,Lanç_Receitas!$G$6:$G$33,$C28,Lanç_Receitas!$M$6:$M$33,K$16)) -> 0 | L26: =IF(ISERROR(SUMIFS(Lanç_Receitas!$I$6:$I$33,Lanç_Receitas!$G$6:$G$33,$C28,Lanç_Receitas!$M$6:$M$33,L$16)),"",SUMIFS(Lanç_Receitas!$I$6:$I$33,Lanç_Receitas!$G$6:$G$33,$C28,Lanç_Receitas!$M$6:$M$33,L$16)) -> 0 | N26: =IF(ISERROR(SUMIFS(Lanç_Receitas!$I$6:$I$33,Lanç_Receitas!$G$6:$G$33,$E28,Lanç_Receitas!$M$6:$M$33,N$16)),"",SUMIFS(Lanç_Receitas!$I$6:$I$33,Lanç_Receitas!$G$6:$G$33,$E28,Lanç_Receitas!$M$6:$M$33,N$16)) -> 0 | O26: =IF(ISERROR(SUMIFS(Lanç_Receitas!$I$6:$I$33,Lanç_Receitas!$G$6:$G$33,$E28,Lanç_Receitas!$M$6:$M$33,O$16)),"",SUMIFS(Lanç_Receitas!$I$6:$I$33,Lanç_Receitas!$G$6:$G$33,$E28,Lanç_Receitas!$M$6:$M$33,O$16)) -> 0 | P26: =IF(ISERROR(SUMIFS(Lanç_Receitas!$I$6:$I$33,Lanç_Receitas!$G$6:$G$33,$E28,Lanç_Receitas!$M$6:$M$33,P$16)),"",SUMIFS(Lanç_Receitas!$I$6:$I$33,Lanç_Receitas!$G$6:$G$33,$E28,Lanç_Receitas!$M$6:$M$33,P$16)) -> 0 | Q26: =IF(ISERROR(SUMIFS(Lanç_Receitas!$I$6:$I$33,Lanç_Receitas!$G$6:$G$33,$E28,Lanç_Receitas!$M$6:$M$33,Q$16)),"",SUMIFS(Lanç_Receitas!$I$6:$I$33,Lanç_Receitas!$G$6:$G$33,$E28,Lanç_Receitas!$M$6:$M$33,Q$16)) -> 0 | R26: =IF(ISERROR(SUMIFS(Lanç_Receitas!$I$6:$I$33,Lanç_Receitas!$G$6:$G$33,$E28,Lanç_Receitas!$M$6:$M$33,R$16)),"",SUMIFS(Lanç_Receitas!$I$6:$I$33,Lanç_Receitas!$G$6:$G$33,$E28,Lanç_Receitas!$M$6:$M$33,R$16)) -> 0 | S26: =IF(ISERROR(SUMIFS(Lanç_Receitas!$I$6:$I$33,Lanç_Receitas!$G$6:$G$33,$E28,Lanç_Receitas!$M$6:$M$33,S$16)),"",SUMIFS(Lanç_Receitas!$I$6:$I$33,Lanç_Receitas!$G$6:$G$33,$E28,Lanç_Receitas!$M$6:$M$33,S$16)) -> 0
