Workbook

Sheet Mod - Est Susp.Reduc 01
A1: EMPRESA XYZ
A2: CÁLCULO DO IRPJ E DA CSLL
A3: ELENCO DE RUBRICAS | C3: jan | D3: fev | E3: mar | F3: abr | G3: mai | H3: jun | I3: jul | J3: ago | K3: set | L3: out | M3: nov | N3: dez
A5: RECEITA BRUTA | C5: 300000 | D5: 698000 | E5: 1350000 | F5: 1700000 | G5: 2120000 | H5: 2300000 | I5: 2450000 | J5: 2712000 | K5: 3120000 | L5: 3200000 | M5: 3550000 | N5: 4200000
B6: BASE DE CÁLCULO ESTIMATIVA RECEITA (8%) | C6: =C5*8% -> 24000 | D6: =D5*8% -> 55840 | E6: =E5*8% -> 108000 | F6: =F5*8% -> 136000 | G6: =G5*8% -> 169600 | H6: =H5*8% -> 184000 | I6: =I5*8% -> 196000 | J6: =J5*8% -> 216960 | ... N6: =N5*8% -> 336000
A8: LUCRO REAL | C8: 32000 | D8: -7000 | E8: -32000 | F8: 118000 | G8: 120000 | H8: 125000 | I8: 160000 | J8: 230000 | K8: 250000 | L8: 269000 | M8: 315000 | N8: 418000
A11: IRPJ 15%
B12: ESTIMATIVA | C12: =C6*15% -> 3600 | D12: =D6*15% -> 8376 | E12: =E6*15% -> 16200 | F12: =F6*15% -> 20400 | G12: =G6*15% -> 25440 | H12: =H6*15% -> 27600 | I12: =I6*15% -> 29400 | J12: =J6*15% -> 32544 | ... N12: =N6*15% -> 50400
B14: REDUÇÃO / SUSPENSÃO | C14: =C8*15% -> 4800 | F14: =F8*15% -> 17700 | G14: =G8*15% -> 18000 | H14: =H8*15% -> 18750 | I14: =I8*15% -> 24000 | J14: =J8*15% -> 34500 | K14: =K8*15% -> 37500 | L14: =L8*15% -> 40350 | M14: =M8*15% -> 47250 | N14: =N8*15% -> 62700
A16: Check | C16: =C12-C14 -> -1200 | D16: =D12-D14 -> 8376 | E16: =E12-E14 -> 16200 | F16: =F12-F14 -> 2700 | G16: =G12-G14 -> 7440 | H16: =H12-H14 -> 8850 | I16: =I12-I14 -> 5400 | J16: =J12-J14 -> -1956 | ... N16: =N12-N14 -> -12300

Sheet Mod - Est Susp.Reduc 02
A1: EMPRESA XYZ
A2: CÁLCULO DO IRPJ E DA CSLL
A3: ELENCO DE RUBRICAS | C3: jan | D3: fev | E3: mar | F3: abr | G3: mai | H3: jun | I3: jul | J3: ago | K3: set | L3: out | M3: nov | N3: dez
A5: LUCRO REAL | C5: 32000 | D5: -7000 | E5: -32000 | F5: 118000 | G5: 100000 | H5: 125000 | I5: 121000 | J5: 230000 | K5: 250000 | L5: 269000 | M5: 315000 | N5: 418000
A7: IRPJ 15%
B8: REDUÇÃO / SUSPENSÃO | C8: =C5*15% -> 4800 | F8: =F5*15% -> 17700 | G8: =G5*15% -> 15000 | H8: =H5*15% -> 18750 | I8: =I5*15% -> 18150 | J8: =J5*15% -> 34500 | K8: =K5*15% -> 37500 | L8: =L5*15% -> 40350 | M8: =M5*15% -> 47250 | N8: =N5*15% -> 62700
A10: SALDO A PAGAR
B11: ACUMULADOO | D11: =C12 -> 4800 | E11: =D11 -> 4800 | F11: =E11 -> 4800 | G11: =F11+F12 -> 17700 | H11: =G11 -> 17700 | I11: =H11+H12 -> 18750 | J11: =I11 -> 18750 | K11: =J11+J12 -> 34500 | L11: =K11+K12 -> 37500 | M11: =L11+L12 -> 40350 | N11: =M11+M12 -> 47250
B12: IRPJ A PAGAR NO MÊS | C12: =C8 -> 4800 | F12: =F8-F11 -> 12900 | H12: =H8-H11 -> 1050 | J12: =J8-J11 -> 15750 | K12: =K8-K11 -> 3000 | L12: =L8-L11 -> 2850 | M12: =M8-M11 -> 6900 | N12: =N8-N11 -> 15450

Sheet Mod - Alíquota IRPJ
A1: ANUAL
A3: Descrição | B3: Jan | C3: Fev | D3: Mar | E3: Abr | F3: Mai | G3: Jun | H3: Jul | I3: Ago | J3: Set | K3: Out | L3: Nov | M3: Dez
A4: Base de Cálculo IRPJ | B4: 15000 | C4: 45000 | D4: 59000 | E4: 120000 | F4: 150000 | G4: 12000 | H4: 67000 | I4: 180000 | J4: 250000 | K4: 300000 | L4: 280000 | M4: 240000
A6: IRPJ 15% | B6: =B4*15% -> 2250 | C6: =C4*15% -> 6750 | D6: =D4*15% -> 8850 | E6: =E4*15% -> 18000 | F6: =F4*15% -> 22500 | G6: =G4*15% -> 1800 | H6: =H4*15% -> 10050 | I6: =I4*15% -> 27000 | ... M6: =M4*15% -> 36000
A8: Adicional IRPJ
A9: Limite Mês | B9: 20000 | C9: 20000 | D9: 20000 | E9: 20000 | F9: 20000 | G9: 20000 | H9: 20000 | I9: 20000 | J9: 20000 | K9: 20000 | L9: 20000 | M9: 20000
A10: Limite Adicional | B10: =B9 -> 20000 | C10: =C9+B10 -> 40000 | D10: =D9+C10 -> 60000 | E10: =E9+D10 -> 80000 | F10: =F9+E10 -> 100000 | G10: =G9+F10 -> 120000 | H10: =H9+G10 -> 140000 | I10: =I9+H10 -> 160000 | J10: =J9+I10 -> 180000 | ... M10: =M9+L10 -> 240000
A12: Base Adicional | B12: =B4-B10 -> -5000 | C12: =C4-C10 -> 5000 | D12: =D4-D10 -> -1000 | E12: =E4-E10 -> 40000 | F12: =F4-F10 -> 50000 | G12: =G4-G10 -> -108000 | H12: =H4-H10 -> -73000 | I12: =I4-I10 -> 20000 | ... M12: =M4-M10 -> 0
A14: IRPJ Adicional 10% | C14: =C12*10% -> 500 | E14: =E12*10% -> 4000 | F14: =F12*10% -> 5000 | I14: =I12*10% -> 2000 | J14: =J12*10% -> 7000 | K14: =K12*10% -> 10000 | L14: =L12*10% -> 6000
A16: Total IRPJ Recolher | B16: =B6+B14 -> 2250 | C16: =C6+C14 -> 7250 | D16: =D6+D14 -> 8850 | E16: =E6+E14 -> 22000 | F16: =F6+F14 -> 27500 | G16: =G6+G14 -> 1800 | H16: =H6+H14 -> 10050 | I16: =I6+I14 -> 29000 | ... M16: =M6+M14 -> 36000
A19: TRIMESTRAL
A21: Descrição | B21: 1ºTrim | C21: 2ºTrim | D21: 3ºTrim | E21: 4ºTrim
A22: Base de Cálculo IRPJ | B22: 62000 | C22: 59000 | D22: 250000 | E22: 60000
A24: IRPJ 15% | B24: =B22*15% -> 9300 | C24: =C22*15% -> 8850 | D24: =D22*15% -> 37500 | E24: =E22*15% -> 9000
A26: Adicional IRPJ
A27: Limite Trimestre | B27: =20000*3 -> 60000 | C27: =20000*3 -> 60000 | D27: =20000*3 -> 60000 | E27: =20000*3 -> 60000
A28: Limite Adicional | B28: =B27 -> 60000 | C28: =C27 -> 60000 | D28: =D27 -> 60000 | E28: =E27 -> 60000
A30: Base Adicional | B30: =B22-B28 -> 2000 | C30: =C22-C28 -> -1000 | D30: =D22-D28 -> 190000 | E30: =E22-E28 -> 0
A32: IRPJ Adicional 10% | B32: =B30*10% -> 200 | D32: =D30*10% -> 19000
A34: Total IRPJ Recolher | B34: =B24+B32 -> 9500 | C34: =C24+C32 -> 8850 | D34: =D24+D32 -> 56500 | E34: =E24+E32 -> 9000

Sheet Mod - Alíquota CSLL
A1: ANUAL
A3: Descrição | B3: Jan | C3: Fev | D3: Mar | E3: Abr | F3: Mai | G3: Jun | H3: Jul | I3: Ago | J3: Set | K3: Out | L3: Nov | M3: Dez
A4: Base de Cálculo CSLL | B4: 15000 | C4: 45000 | D4: 59000 | E4: 120000 | F4: 150000 | G4: 12000 | H4: 67000 | I4: 180000 | J4: 250000 | K4: 300000 | L4: 280000 | M4: 240000
A6: CSLL 9% | B6: =B4*9% -> 1350 | C6: =C4*9% -> 4050 | D6: =D4*9% -> 5310 | E6: =E4*9% -> 10800 | F6: =F4*9% -> 13500 | G6: =G4*9% -> 1080 | H6: =H4*9% -> 6030 | I6: =I4*9% -> 16200 | ... M6: =M4*9% -> 21600
A9: TRIMESTRAL
A11: Descrição | B11: 1ºTrim | C11: 2ºTrim | D11: 3ºTrim | E11: 4ºTrim
A12: Base de Cálculo IRPJ | B12: 62000 | C12: 59000 | D12: 250000 | E12: 60000
A14: CSLL 9% | B14: =B12*9% -> 5580 | C14: =C12*9% -> 5310 | D14: =D12*9% -> 22500 | E14: =E12*9% -> 5400

Sheet Mod - Ded e Comp
A1: EMPRESA XYZ
A2: CÁLCULO DO IRPJ E DA CSLL
A4: ELENCO DE RUBRICAS | C4: IV TRIMESTRE
C5: IRPJ | D5: CSLL
A6: LUCRO REAL ANTES DO PREJUÍZO FISCAL | C6: 12500000 | D6: =C6 -> 12500000
B7: Saldo Prejuízo Fiscal/Base Cálculo Negativa CSLL | C7: =[1]Memória_Cálculo_Prej_Fiscal!$C$18 -> 249170.96 | D7: =C7 -> 249170.96
B8: Compensação do Prejuízo Fiscal/Base Negativa | C8: -750000 | D8: =C8 -> -750000
A9: LUCRO REAL TRIBUTÁVEL (BASE PARA O IRPJ/CSLL) | C9: =C6+C8 -> 11750000 | D9: =D6+D8 -> 11750000
B10: Adicional | C10: 60000
A11: IRPJ (15%) / CSLL (9%) | C11: =IF(C9>0,ROUND(C9*15%,2),0) -> 1762500 | D11: =IF(D9>0,ROUND(D9*9%,2),0) -> 1057500
A12: IRPJ (adicional - 10%) | C12: =ROUND(IF(C9>C10,(C9-C10)*10%,0),2) -> 1169000
A13: TOTAL GERADO DE IRPJ/CSLL | C13: =SUM(C11:C12) -> 2931500 | D13: =D11 -> 1057500 | F13: =C13+D13 -> 3989000
A15: DEDUÇÕES
A16: 1.1.02.04.0003 | B16: ( - ) Imposto de Renda Retido na Fonte | C16: 1100000
B17: ( - ) PAT | C17: 36000
A18: TOTAL DAS DEDUÇÕES | C18: =-SUM(C16:C17) -> -1136000
A19: IRPJ / CSLL A PAGAR | C19: =C13+C18 -> 1795500 | D19: =D13+D18 -> 1057500 | F19: =C19+D19 -> 2853000
B20: DCOMP - PIS
B21: 4º Trim | D21: -850000
B22: DCOMP - COFINS
B23: 4º Trim | C23: -520000
B24: DCOMP - Saldo Negativo - 3º Trim | C24: -33000
B26: Valor a ser pago por DARF | C26: =SUM(C19:C25) -> 1242500 | D26: =SUM(D19:D25) -> 207500 | F26: =C26+D26 -> 1450000
E28: REDUÇÃO | F28: =F13-F26 -> 2539000

Sheet Mod - Pgto Anual
A1: ESTIMATIVA MENSAL / BALANÇO REDUÇÃO OU SUSPENSÃO
A3: Mês | B3: Jan | C3: Fev | D3: Mar | E3: Abr | F3: Mai | G3: Jun | H3: Jul | I3: Ago | J3: Set | K3: Out | L3: Nov | M3: Dez
A5: Data Vencimento | B5: último dia útil fev | C5: último dia útil mar | D5: último dia útil abr | E5: último dia útil mai | F5: último dia útil jun | G5: último dia útil jul | H5: último dia útil ago | I5: último dia útil set | J5: último dia útil out | K5: último dia útil nov | L5: último dia útil dez | M5: último dia útil jan
A9: APURAÇÃO ANUAL
A11: Valor IRPJ | B11: 325200
A13: Pagamento em Quota Única em Março.
A15: SELIC - 2015
A16: Período | B16: Taxa
A17: fev | B17: 0.0082
A18: mar | B18: 0.01
A19: Total Encargos | B19: =SUM(B17:B18) -> 0.0182
A21: Total Juros | B21: =B11*B19 -> 5918.64
A23: IRPJ a Recolher | B23: =B11+B21 -> 331118.64

Sheet Mod - Pgto Trim
A1: APURAÇÃO TRIMESTRAL - PAGAMENTO COTA ÚNICA
A3: Mês | B3: 1º Trim | C3: 2º Trim | D3: 3º Trim | E3: 4º Trim
A5: Data Vencimento | B5: último dia útil abr | C5: último dia útil jul | D5: último dia útil out | E5: último dia útil jan
A9: APURAÇÃO TRIMESTRAL - PAGAMENTO PARCELADO
A11: Valor IRPJ | B11: 325200
A13: Pagamento em Quota Única em Março.
A15: SELIC - 2015
A16: Período | B16: Taxa
A17: fev | B17: 0.0082
A18: mar | B18: 0.01
A19: Total Encargos | B19: =SUM(B17:B18) -> 0.0182
A21: Parcela 01
A22: Principal | B22: =B11/3 -> 108400
A23: Juros | B23: 0
A24: Total a Pagar | B24: =SUM(B22:B23) -> 108400
A26: Parcela 02
A27: Principal | B27: =B11/3 -> 108400
A28: Juros | B28: =B27*1% -> 1084
A29: Total a Pagar | B29: =SUM(B27:B28) -> 109484
A31: Parcela 03
A32: Principal | B32: =B11/3 -> 108400
A33: Juros | B33: =(B17+B18)*B32 -> 1972.88
A34: Total a Pagar | B34: =SUM(B32:B33) -> 110372.88 | D34: =B34+B29+B24 -> 328256.88
D36: =B11 -> 325200
D38: =D34-D36 -> 3056.88 | E38: >>> ENCARGOS SOBRE A ATUALIZAÇÃO

Sheet Mod - Prej.Fiscal
A1: EMPRESA XYZ
A2: CÁLCULO DO IRPJ E DA CSLL
A3: ELENCO DE RUBRICAS | C3: 1ºTrimestre | E3: 2ºTrimestre | G3: 3ºTrimestre | I3: 4ºTrimestre
C4: IRPJ | D4: CSLL | E4: IRPJ | F4: CSLL | G4: IRPJ | H4: CSLL | I4: IRPJ | J4: CSLL
A5: LUCRO REAL ANTES DO PREJUÍZO FISCAL | C5: -3000000 | D5: =C5 -> -3000000 | E5: 3000000 | F5: =E5 -> 3000000 | G5: 2500000 | H5: =G5 -> 2500000 | I5: 5000000 | J5: =I5 -> 5000000
B6: Compensação do Prejuízo Fiscal/Base Negativa | E6: =-E5*30% -> -900000 | F6: =-F5*30% -> -900000 | G6: =-G5*30% -> -750000 | H6: =-H5*30% -> -750000 | I6: =I7 -> -1350000 | J6: =J7 -> -1350000
B7: Saldo Prejuízo Fiscal | E7: =-'Mod - Prej.Fiscal - Controle'!E16 -> -3000000 | F7: =E7 -> -3000000 | G7: =-'Mod - Prej.Fiscal - Controle'!E17 -> -2100000 | H7: =-'Mod - Prej.Fiscal - Controle'!E17 -> -2100000 | I7: =-'Mod - Prej.Fiscal - Controle'!E18 -> -1350000 | J7: =-'Mod - Prej.Fiscal - Controle'!E18 -> -1350000
A8: LUCRO REAL TRIBUTÁVEL (BASE PARA O IRPJ/CSLL) | C8: =C5+C6 -> -3000000 | D8: =D5+D6 -> -3000000 | E8: =E5+E6 -> 2100000 | F8: =F5+F6 -> 2100000 | G8: =G5+G6 -> 1750000 | H8: =H5+H6 -> 1750000 | I8: =I5+I6 -> 3650000 | J8: =J5+J6 -> 3650000
I11: =I5*30% -> 1500000

Sheet Mod - Prej.Fiscal - Controle
A1: Empresa XYZ
A2: Controle dos Saldos de Prejuízos Fiscais.
A4: Data | B4: Histórico | C4: CONTROLE DE VALORES | G4: SALDOS TRIB DIF
C5: Aumento | D5: Redução | E5: Saldo
E6: R$ | F6: D/C | G6: IRPJ | H6: CSLL
A7: 41274 | B7: Prejuízo Fiscal - 4º Trimestre de 2012 | C7: ='[1]1.2.01.04.0001_2_Abr_Jun.13'!D15 -> 1288556.2 | E7: =C7 -> 1288556.2 | F7: =IF(E7>0,"C","D") -> C | G7: =E7*25% -> 322139.06 | H7: =E7*9% -> 115970.06 | J7: =C7*25% -> 322139.06 | K7: =C7*9% -> 115970.06
A8: 41363 | B8: Compensação Prejuízo Fiscal | C8: 0 | D8: =C7 -> 1288556.2 | E8: =E7+C8-D8 -> 0 | F8: =IF(E8>0,"C","D") -> D | G8: =E8*25% -> 0 | H8: =E8*9% -> 0 | J8: =-D8*25% -> -322139.06 | K8: =-D8*9% -> -115970.06
A9: 41455 | B9: Prejuízo Fiscal - 2º Trimestre de 2013 | C9: 13316978 | E9: =E8+C9-D9 -> 13316978 | F9: =IF(E9>0,"C","D") -> C | G9: =E9*25% -> 3329244.4 | H9: =E9*9% -> 1198528 | J9: =C9*25% -> 3329244.4 | K9: =C9*9% -> 1198528
A10: 41547 | B10: Compensação Prejuízo Fiscal | D10: 2354705.3 | E10: =E9+C10-D10 -> 10962272 | F10: =IF(E10>0,"C","D") -> C | G10: =E10*25% -> 2740568.1 | H10: =E10*9% -> 986604.51 | J10: =-D10*25% -> -588676.32 | K10: =-D10*9% -> -211923.48
A11: 41639 | B11: Prejuízo Fiscal - 4º Trimestre de 2013 | C11: 4328200.7 | E11: =E10+C11-D11 -> 15290473 | F11: =IF(E11>0,"C","D") -> C | G11: =E11*25% -> 3822618.3 | H11: =E11*9% -> 1376142.6 | J11: =C11*25% -> 1082050.2 | K11: =C11*9% -> 389538.07
A12: 41759 | B12: Compensação Prejuízo Fiscal | D12: ='[1]1.2.01.04.0001_2_Jan_Mar.14'!D56 -> 8512755.2 | E12: =E11+C12-D12 -> 6777717.9 | F12: =IF(E12>0,"C","D") -> C | G12: =E12*25% -> 1694429.5 | H12: =E12*9% -> 609994.61 | J12: =SUM(J7:J11) -> 3822618.3 | K12: =SUM(K7:K11) -> 1376142.6
A13: 41820 | B13: Compensação Prejuízo Fiscal | D13: 1775456.3 | E13: =E12+C13-D13 -> 5002261.6 | F13: =IF(E13>0,"C","D") -> C | G13: =E13*25% -> 1250565.4 | H13: =E13*9% -> 450203.54
A14: 41912 | B14: Compensação Prejuízo Fiscal | D14: 2247417.5 | E14: =E13+C14-D14 -> 2754844.1 | F14: =IF(E14>0,"C","D") -> C | G14: =E14*25% -> 688711.02 | H14: =E14*9% -> 247935.97
A15: 42004 | B15: Compensação Prejuízo Fiscal | D15: =E14 -> 2754844.1 | E15: =E14+C15-D15 -> 0 | F15: =IF(E15>0,"C","D") -> D | G15: =E15*25% -> 0 | H15: =E15*9% -> 0
A16: 42094 | B16: Prejuízo Fiscal - 1º Trimestre de 2015 | C16: =-'Mod - Prej.Fiscal'!C5 -> 3000000 | E16: =E15+C16-D16 -> 3000000 | F16: =IF(E16>0,"C","D") -> C | G16: =E16*25% -> 750000 | H16: =E16*9% -> 270000
A17: 42185 | B17: Compensação Prejuízo Fiscal | D17: =-'Mod - Prej.Fiscal'!E6 -> 900000 | E17: =E16+C17-D17 -> 2100000 | F17: =IF(E17>0,"C","D") -> C | G17: =E17*25% -> 525000 | H17: =E17*9% -> 189000
A18: 42277 | B18: Compensação Prejuízo Fiscal | D18: =-'Mod - Prej.Fiscal'!G6 -> 750000 | E18: =E17+C18-D18 -> 1350000 | F18: =IF(E18>0,"C","D") -> C | G18: =E18*25% -> 337500 | H18: =E18*9% -> 121500
A19: 42369 | B19: Compensação Prejuízo Fiscal | D19: =-'Mod - Prej.Fiscal'!I7 -> 1350000 | E19: =E18+C19-D19 -> 0 | F19: =IF(E19>0,"C","D") -> D | G19: =E19*25% -> 0 | H19: =E19*9% -> 0
A52: =#REF! -> #REF!
A54: PARTE B - CONTROLE DE VALORES QUE CONSTITUIRÃO AJUSTE DO LUCRO LÍQUIDO DE EXERCÍCIOS FUTUROS
A56: CONTA: | B56: 2 CRÉDITOS DE PIS/COFINS SOBRE TRANSFERÊNCIAS
A58: Data do Lançamento | B58: Histórico | C58: CONTROLE DE VALORES
C59: Aumento | D59: Redução | E59: Saldo
E60: R$ | F60: D/C
A61: 40909 | B61: Saldo Inicial | C61: 1161007.7 | E61: =C61 -> 1161007.7 | F61: =IF(E61>0,"C","D") -> C
A63: 40999 | B63: Créditos de PIS/COFINS sobre transferências | C63: ='[2]parte A'!C7 -> #REF! | E63: =E61+C63-D63 -> #REF! | F63: =IF(E63>0,"C","D") -> #REF!
A65: 41090 | B65: Créditos de PIS/COFINS sobre transferências | C65: ='[2]parte A'!C55 -> #REF! | E65: =E63+C65-D65 -> #REF! | F65: =IF(E65>0,"C","D") -> #REF!
A67: 41182 | B67: Créditos de PIS/COFINS sobre transferências | C67: ='[2]parte A'!C103 -> 240088.71 | E67: =E65+C67-D67 -> #REF! | F67: =IF(E67>0,"C","D") -> #REF!
A69: 41274 | B69: Créditos de PIS/COFINS sobre transferências | C69: ='[2]parte A'!C157 -> Adições | E69: =E67+C69-D69 -> #REF! | F69: =IF(E69>0,"C","D") -> #REF!

Sheet Mod - Con.Long_Prazo
A1: EMPRESA XYZ.
A2: CÁLCULO DO IRPJ E DA CSLL
A3: ELENCO DE RUBRICAS | C3: 2014 | E3: 2015
C4: IRPJ | D4: CSLL | E4: IRPJ | F4: CSLL
A5: LUCRO LÍQUIDO ANTES DO IRPJ (RESULTADO CONTÁBIL) | C5: 12532000 | D5: 12532000 | E5: 3200000 | F5: 3200000
A6: ADIÇÕES
A7: 2.3.04.01.0002 | B7: CONTRATOS DE LONGO PRAZO | E7: 3500000 | F7: =E7 -> 3500000
A8: EXCLUSÕES
A9: 3.2.01.03.0001 | B9: CONTRATOS DE LONGO PRAZO | C9: 3500000 | D9: =C9 -> 3500000
A10: LUCRO REAL TRIBUTÁVEL (BASE PARA O IRPJ/CSLL) | C10: =C5+C7-C9 -> 9032000 | D10: =D5+D7-D9 -> 9032000 | E10: =E5+E7-E9 -> 6700000 | F10: =F5+F7-F9 -> 6700000
B11: Adicional | C11: 60000 | E11: 60000
A12: IRPJ (15%) / CSLL (9%) | C12: =IF(C10>0,ROUND(C10*15%,2),0) -> 1354800 | D12: =IF(D10>0,ROUND(D10*9%,2),0) -> 812880 | E12: =IF(E10>0,ROUND(E10*15%,2),0) -> 1005000 | F12: =IF(F10>0,ROUND(F10*9%,2),0) -> 603000
A13: IRPJ (adicional - 10%) | C13: =ROUND(IF(C10>C11,(C10-C11)*10%,0),2) -> 897200 | E13: =ROUND(IF(E10>E11,(E10-E11)*10%,0),2) -> 664000
A14: TOTAL GERADO DE IRPJ/CSLL | C14: =SUM(C12:C13) -> 2252000 | D14: =D12 -> 812880 | E14: =SUM(E12:E13) -> 1669000 | F14: =F12 -> 603000

Sheet Mod - Perdas - Dados
A1: Perdas no Recebimento de Créditos
A3: Lucro antes do IRPJ/CSLL | B3: 13282000
A5: Saldo de Clientes | B5: 8752333.2
A7: Histórico de Perdas Contabilizado
A8: - 5% do Saldo de Contas a Receber | B8: =-B5*5% -> -437616.66
A11: Perdas Conforme RIR e IN 1.515/14
A12: Até 07/10/2014 | B12: -317282.15
A13: A partir de 08/10/2014 | B13: -618815.95
A14: Total Perdas Conforme RIR e IN 1.515/14 | B14: =SUM(B12:B13) -> -936098.1 | D14: =B14-B8 -> -498481.44

Sheet Plan1

Sheet Plan2

Sheet Mod - Perdas - Apuração
A1: EMPRESA XYZ.
A2: CÁLCULO DO IRPJ E DA CSLL
A3: ELENCO DE RUBRICAS | C3: 2015
C4: IRPJ | D4: CSLL
A5: LUCRO LÍQUIDO ANTES DO IRPJ (RESULTADO CONTÁBIL) | C5: ='Mod - Perdas - Dados'!B3 -> 13282000 | D5: =C5 -> 13282000
A6: ADIÇÕES
A7: 2.3.04.01.0002 | B7: PERDAS NO RECEBIMENTO DE CRÉDITOS | C7: =-'Mod - Perdas - Dados'!B8 -> 437616.66 | D7: =C7 -> 437616.66
A8: EXCLUSÕES
A9: 3.2.01.03.0001 | B9: PERDAS NO RECEBIMENTO DE CRÉDITOS | C9: =-'Mod - Perdas - Dados'!B14 -> 936098.1 | D9: =C9 -> 936098.1 | F9: =C9-C7 -> 498481.44 | G9: >>> REDUÇÃO BC
A10: LUCRO REAL TRIBUTÁVEL (BASE PARA O IRPJ/CSLL) | C10: =C5+C7-C9 -> 12783519 | D10: =D5+D7-D9 -> 12783519
B11: Adicional | C11: 60000
A12: IRPJ (15%) / CSLL (9%) | C12: =IF(C10>0,ROUND(C10*15%,2),0) -> 1917527.8 | D12: =IF(D10>0,ROUND(D10*9%,2),0) -> 1150516.7
A13: IRPJ (adicional - 10%) | C13: =ROUND(IF(C10>C11,(C10-C11)*10%,0),2) -> 1272351.9
A14: TOTAL GERADO DE IRPJ/CSLL | C14: =SUM(C12:C13) -> 3189879.6 | D14: =D12 -> 1150516.7
