Workbook

Sheet inicio
B3: PLANILHA DE LUCRO REAL - IR e CS
C5: 1 | D5: Cadastro: | E5: Na aba de cadastro de tabelas com as alíquotas do lucro real (imposto de renda e contribuição social), lucro acumulado e compensações de impostos ;
C7: 2 | D7: Lançamentos: | E7: Na aba de lançamentos automáticos dos cálculos mensais dos impostos;
C9: 3 | D9: Resultados: | E9: Na aba de resultados consta o resumo do anual do impostos de renda, contribuição social e média;
C11: 4 | D11: Gráficos: | E11: Na aba de gráficos representa a evolução dos impostos por mês;
C13: 5 | D13: Impressão: | E13: Na aba de impressão dos relatórios do lucro real;
C15: 6 | D15: Sobre: | E15: Na aba sobre é destinado para publicação do site do desenvolvedor e formas de contato.

Sheet tab
B4: # | C4: Parâmetros | D4: % | E4: Jan | F4: Fev | G4: Mar | H4: Abr | I4: Mai | J4: Jun | K4: Jul | L4: Ago | M4: Set | N4: Out | O4: Nov | P4: Dez
B5: = | C5: Lucro Acumulado | E5: 1000 | F5: =E5+25000 -> 26000 | G5: =F5+25000 -> 51000 | H5: =G5+25000 -> 76000 | I5: =H5+25000 -> 101000 | J5: =I5+25000 -> 126000 | K5: =J5+25000 -> 151000 | L5: =K5+25000 -> 176000 | M5: =L5+25000 -> 201000 | ... P5: =O5+25000 -> 276000
B6: = | C6: Adições
B7: + | C7: Ajustes Devedores de Qualquer Natureza
B8: + | C8: Despesas de Variação Cambial
B9: + | C9: Despesas Particulares dos Sócios e Dirigentes;
B10: + | C10: Doações e Brindes; | E10: 100 | F10: 100 | G10: 100 | H10: 100 | I10: 100 | J10: 100 | K10: 100 | L10: 100 | M10: 100 | N10: 100 | O10: 100 | P10: 100
B11: + | C11: Impostos Não Pagos em Discussão Judicial;
B12: + | C12: Impostos Não Pagos por Iniciativa da Empresa;
B13: + | C13: Lucro Inflacionário apurado até 31/12/1995;
B14: + | C14: Multas Contratuais
B15: + | C15: Multas Punitivas (Transito, Imetro, Ibama, Multas sobre ação fiscal) | E15: 500 | F15: 500 | G15: 500 | H15: 500 | I15: 500 | J15: 500 | K15: 500 | L15: 500 | M15: 500 | N15: 500 | O15: 500 | P15: 500
B16: + | C16: Orçamentos, Pedidos e qualquer documento não idôneo;
B17: + | C17: Provisões Indedutíveis (perdas, frete, propaganda)
B18: + | C18: Recibos sem especificação da fonte recebedora;
B19: + | C19: Verbas Rescisórias em desacordo com a legislação trabalhista vigente
B20: = | C20: Exclusões
B21: - | C21: Ajustes credores de qualquer natureza
B22: - | C22: Decisão Favorável - Processos Judiciais Tributários
B23: - | C23: Despesas de Ágios
B24: - | C24: Distribuição de Lucros e Dividendos;
B25: - | C25: Dividendos Coligadas e Controladas
B26: - | C26: Pagamento de Impostos em Atraso por iniciativa da Empresa | E26: -1000 | F26: -1000 | G26: -1000 | H26: -1000 | I26: -1000 | J26: -1000 | K26: -1000 | L26: -1000 | M26: -1000 | N26: -1000 | O26: -1000 | P26: -1000
B27: - | C27: Pagamento de Impostos sobre discussão judicial,
B28: - | C28: Receita de Variação Cambial
B29: - | C29: Receitas Obtidas com Tributação Exclusiva ou Isenta de IR
B30: - | C30: Receitas que poderiam ser diferidas;
B31: - | C31: Resultado Positivo de Equivalência Patrimonial
B32: - | C32: Reversão de Provisões Indedutíveis
B33: - | C33: Vendas Não Expedidas do Período
B34: = | C34: Base de Cálculo
B35: = | C35: Saldo Prejuízo Fiscal | E35: 45000
B36: % | C36: Compensação de Prejuízo Fiscal | D36: 0.3
B37: % | C37: Adicional de Imposto de Renda | D37: 0.1
B38: % | C38: Imposto de Renda | D38: 0.15
B39: % | C39: Contribuição Social | D39: 0.09
B40: = | C40: Compensações
B41: - | C41: IR Base Negativa Exercícios Anteriores
B42: - | C42: IR s/ Aplicações Financeiras | E42: -100 | F42: -100 | G42: -100 | H42: -100 | I42: -100 | J42: -100 | K42: -100 | L42: -100 | M42: -100 | N42: -100 | O42: -100 | P42: -100
B43: - | C43: IR Retida s/ Notas Fiscais | E43: -2000 | F43: -2000 | G43: -2000 | H43: -2000 | I43: -2000 | J43: -2000 | K43: -2000 | L43: -2000 | M43: -2000 | N43: -2000 | O43: -2000 | P43: -2000
B44: - | C44: IR Pago no Exercício
B45: - | C45: CS Base Negativa Exercícios Anteriores
B46: - | C46: CS Retida s/ Notas Fiscais | E46: -1500 | F46: -1500 | G46: -1500 | H46: -1500 | I46: -1500 | J46: -1500 | K46: -1500 | L46: -1500 | M46: -1500 | N46: -1500 | O46: -1500 | P46: -1500
B47: - | C47: CS Pago no Exercício
B48: = | C48: Imposto de Renda a Pagar
B49: = | C49: Contribuição Social a Pagar

Sheet jan
B3: 2018
A4: 1 | B4: # | C4: Parâmetros | D4: % | E4: Jan | F4: Fev | G4: Mar | H4: Abr | I4: Mai | J4: Jun | K4: Jul | L4: Ago | M4: Set | N4: Out | O4: Nov | P4: Dez
A5: 2018 | B5: =tab!B5 -> = | C5: =tab!C5 -> Lucro Acumulado | E5: =HLOOKUP(E$4,tab!$E$4:$P$33,MATCH($C5,$C$4:$C$33,0),0) -> 1000
A6: 2019 | B6: =tab!B6 -> = | C6: =tab!C6 -> Adições | E6: =SUM(E7:E19) -> 600
A7: 2020 | B7: =tab!B7 -> + | C7: =tab!C7 -> Ajustes Devedores de Qualquer Natureza | E7: =HLOOKUP(E$4,tab!$E$4:$P$33,MATCH($C7,$C$4:$C$33,0),0) -> 0
A8: 2021 | B8: =tab!B8 -> + | C8: =tab!C8 -> Despesas de Variação Cambial | E8: =HLOOKUP(E$4,tab!$E$4:$P$33,MATCH($C8,$C$4:$C$33,0),0) -> 0
A9: 2022 | B9: =tab!B9 -> + | C9: =tab!C9 -> Despesas Particulares dos Sócios e Dirigentes; | E9: =HLOOKUP(E$4,tab!$E$4:$P$33,MATCH($C9,$C$4:$C$33,0),0) -> 0
A10: 2023 | B10: =tab!B10 -> + | C10: =tab!C10 -> Doações e Brindes; | E10: =HLOOKUP(E$4,tab!$E$4:$P$33,MATCH($C10,$C$4:$C$33,0),0) -> 100
A11: 2024 | B11: =tab!B11 -> + | C11: =tab!C11 -> Impostos Não Pagos em Discussão Judicial; | E11: =HLOOKUP(E$4,tab!$E$4:$P$33,MATCH($C11,$C$4:$C$33,0),0) -> 0
A12: 2025 | B12: =tab!B12 -> + | C12: =tab!C12 -> Impostos Não Pagos por Iniciativa da Empresa; | E12: =HLOOKUP(E$4,tab!$E$4:$P$33,MATCH($C12,$C$4:$C$33,0),0) -> 0
A13: 2026 | B13: =tab!B13 -> + | C13: =tab!C13 -> Lucro Inflacionário apurado até 31/12/1995; | E13: =HLOOKUP(E$4,tab!$E$4:$P$33,MATCH($C13,$C$4:$C$33,0),0) -> 0
A14: 2027 | B14: =tab!B14 -> + | C14: =tab!C14 -> Multas Contratuais | E14: =HLOOKUP(E$4,tab!$E$4:$P$33,MATCH($C14,$C$4:$C$33,0),0) -> 0
A15: 2028 | B15: =tab!B15 -> + | C15: =tab!C15 -> Multas Punitivas (Transito, Imetro, Ibama, Multas sobre ação fiscal) | E15: =HLOOKUP(E$4,tab!$E$4:$P$33,MATCH($C15,$C$4:$C$33,0),0) -> 500
A16: 2029 | B16: =tab!B16 -> + | C16: =tab!C16 -> Orçamentos, Pedidos e qualquer documento não idôneo; | E16: =HLOOKUP(E$4,tab!$E$4:$P$33,MATCH($C16,$C$4:$C$33,0),0) -> 0
A17: 2030 | B17: =tab!B17 -> + | C17: =tab!C17 -> Provisões Indedutíveis (perdas, frete, propaganda) | E17: =HLOOKUP(E$4,tab!$E$4:$P$33,MATCH($C17,$C$4:$C$33,0),0) -> 0
B18: =tab!B18 -> + | C18: =tab!C18 -> Recibos sem especificação da fonte recebedora; | E18: =HLOOKUP(E$4,tab!$E$4:$P$33,MATCH($C18,$C$4:$C$33,0),0) -> 0
B19: =tab!B19 -> + | C19: =tab!C19 -> Verbas Rescisórias em desacordo com a legislação trabalhista vigente | E19: =HLOOKUP(E$4,tab!$E$4:$P$33,MATCH($C19,$C$4:$C$33,0),0) -> 0
B20: =tab!B20 -> = | C20: =tab!C20 -> Exclusões | E20: =SUM(E21:E33) -> -1000
B21: =tab!B21 -> - | C21: =tab!C21 -> Ajustes credores de qualquer natureza | E21: =HLOOKUP(E$4,tab!$E$4:$P$33,MATCH($C21,$C$4:$C$33,0),0) -> 0
B22: =tab!B22 -> - | C22: =tab!C22 -> Decisão Favorável - Processos Judiciais Tributários | E22: =HLOOKUP(E$4,tab!$E$4:$P$33,MATCH($C22,$C$4:$C$33,0),0) -> 0
B23: =tab!B23 -> - | C23: =tab!C23 -> Despesas de Ágios | E23: =HLOOKUP(E$4,tab!$E$4:$P$33,MATCH($C23,$C$4:$C$33,0),0) -> 0
B24: =tab!B24 -> - | C24: =tab!C24 -> Distribuição de Lucros e Dividendos; | E24: =HLOOKUP(E$4,tab!$E$4:$P$33,MATCH($C24,$C$4:$C$33,0),0) -> 0
B25: =tab!B25 -> - | C25: =tab!C25 -> Dividendos Coligadas e Controladas | E25: =HLOOKUP(E$4,tab!$E$4:$P$33,MATCH($C25,$C$4:$C$33,0),0) -> 0
B26: =tab!B26 -> - | C26: =tab!C26 -> Pagamento de Impostos em Atraso por iniciativa da Empresa | E26: =HLOOKUP(E$4,tab!$E$4:$P$33,MATCH($C26,$C$4:$C$33,0),0) -> -1000
B27: =tab!B27 -> - | C27: =tab!C27 -> Pagamento de Impostos sobre discussão judicial, | E27: =HLOOKUP(E$4,tab!$E$4:$P$33,MATCH($C27,$C$4:$C$33,0),0) -> 0
B28: =tab!B28 -> - | C28: =tab!C28 -> Receita de Variação Cambial | E28: =HLOOKUP(E$4,tab!$E$4:$P$33,MATCH($C28,$C$4:$C$33,0),0) -> 0
B29: =tab!B29 -> - | C29: =tab!C29 -> Receitas Obtidas com Tributação Exclusiva ou Isenta de IR | E29: =HLOOKUP(E$4,tab!$E$4:$P$33,MATCH($C29,$C$4:$C$33,0),0) -> 0
B30: =tab!B30 -> - | C30: =tab!C30 -> Receitas que poderiam ser diferidas; | E30: =HLOOKUP(E$4,tab!$E$4:$P$33,MATCH($C30,$C$4:$C$33,0),0) -> 0
B31: =tab!B31 -> - | C31: =tab!C31 -> Resultado Positivo de Equivalência Patrimonial | E31: =HLOOKUP(E$4,tab!$E$4:$P$33,MATCH($C31,$C$4:$C$33,0),0) -> 0
B32: =tab!B32 -> - | C32: =tab!C32 -> Reversão de Provisões Indedutíveis | E32: =HLOOKUP(E$4,tab!$E$4:$P$33,MATCH($C32,$C$4:$C$33,0),0) -> 0
B33: =tab!B33 -> - | C33: =tab!C33 -> Vendas Não Expedidas do Período | E33: =HLOOKUP(E$4,tab!$E$4:$P$33,MATCH($C33,$C$4:$C$33,0),0) -> 0
B34: =tab!B34 -> = | C34: =tab!C34 -> Base de Cálculo | E34: =SUM(E5,E6,E20) -> 600
B35: =tab!B35 -> = | C35: =tab!C35 -> Saldo Prejuízo Fiscal | E35: =tab!E35 -> 45000
B36: =tab!B36 -> % | C36: =tab!C36 -> Compensação de Prejuízo Fiscal | D36: =tab!D36 -> 0.3 | E36: =-IF(AND(E35>0,E34*$D$36<E35),E34*$D$36,E35) -> -180
B37: =tab!B37 -> % | C37: =tab!C37 -> Adicional de Imposto de Renda | D37: =tab!D37 -> 0.1 | E37: =IF(SUM(E34,E36)>20000*$A$4,(SUM(E34,E36)-20000*$A$4)*$D$37,0) -> 0
B38: =tab!B38 -> % | C38: =tab!C38 -> Imposto de Renda | D38: =tab!D38 -> 0.15 | E38: =SUM(E34,E36)*$D$38 -> 63
B39: =tab!B39 -> % | C39: =tab!C39 -> Contribuição Social | D39: =tab!D39 -> 0.09 | E39: =SUM(E34,E36)*$D$39 -> 37.8
B40: =tab!B40 -> = | C40: =tab!C40 -> Compensações | E40: =SUM(E42:E47) -> -3600
B41: =tab!B41 -> - | C41: =tab!C41 -> IR Base Negativa Exercícios Anteriores | D41: =LEFT(C41,2) -> IR | E41: =HLOOKUP(E$4,tab!$E$4:$P$49,MATCH($C41,$C$4:$C$49,0),0) -> 0
B42: =tab!B42 -> - | C42: =tab!C42 -> IR s/ Aplicações Financeiras | D42: =LEFT(C42,2) -> IR | E42: =HLOOKUP(E$4,tab!$E$4:$P$49,MATCH($C42,$C$4:$C$49,0),0) -> -100
B43: =tab!B43 -> - | C43: =tab!C43 -> IR Retida s/ Notas Fiscais | D43: =LEFT(C43,2) -> IR | E43: =HLOOKUP(E$4,tab!$E$4:$P$49,MATCH($C43,$C$4:$C$49,0),0) -> -2000
B44: =tab!B44 -> - | C44: =tab!C44 -> IR Pago no Exercício | D44: =LEFT(C44,2) -> IR | E44: =HLOOKUP(E$4,tab!$E$4:$P$49,MATCH($C44,$C$4:$C$49,0),0) -> 0
B45: =tab!B45 -> - | C45: =tab!C45 -> CS Base Negativa Exercícios Anteriores | D45: =LEFT(C45,2) -> CS | E45: =HLOOKUP(E$4,tab!$E$4:$P$49,MATCH($C45,$C$4:$C$49,0),0) -> 0
B46: =tab!B46 -> - | C46: =tab!C46 -> CS Retida s/ Notas Fiscais | D46: =LEFT(C46,2) -> CS | E46: =HLOOKUP(E$4,tab!$E$4:$P$49,MATCH($C46,$C$4:$C$49,0),0) -> -1500
B47: =tab!B47 -> - | C47: =tab!C47 -> CS Pago no Exercício | D47: =LEFT(C47,2) -> CS | E47: =HLOOKUP(E$4,tab!$E$4:$P$49,MATCH($C47,$C$4:$C$49,0),0) -> 0
B48: =tab!B48 -> = | C48: =tab!C48 -> Imposto de Renda a Pagar | E48: =IF(SUM(E37,E38,SUMIF($D$41:E47,"IR",E$41:E$47))>0,SUM(E37,E38,SUMIF($D$41:E47,"IR",E$41:E$47)),0) -> 0
B49: =tab!B49 -> = | C49: =tab!C49 -> Contribuição Social a Pagar | E49: =IF(SUM(E39,SUMIF($D$41:E47,"CS",E$41:E$47))>0,SUM(E39,SUMIF($D$41:E47,"CS",E$41:E$47)),0) -> 0

Sheet fev
B3: 2018
A4: 2 | B4: # | C4: Parâmetros | D4: % | E4: Jan | F4: Fev | G4: Mar | H4: Abr | I4: Mai | J4: Jun | K4: Jul | L4: Ago | M4: Set | N4: Out | O4: Nov | P4: Dez
A5: 2018 | B5: =tab!B5 -> = | C5: =tab!C5 -> Lucro Acumulado | E5: =HLOOKUP(E$4,tab!$E$4:$P$33,MATCH($C5,$C$4:$C$33,0),0) -> 1000 | F5: =HLOOKUP(F$4,tab!$E$4:$P$33,MATCH($C5,$C$4:$C$33,0),0) -> 26000
A6: 2019 | B6: =tab!B6 -> = | C6: =tab!C6 -> Adições | E6: =SUM(E7:E19) -> 600 | F6: =SUM(F7:F19) -> 600
A7: 2020 | B7: =tab!B7 -> + | C7: =tab!C7 -> Ajustes Devedores de Qualquer Natureza | E7: =HLOOKUP(E$4,tab!$E$4:$P$49,MATCH($C7,$C$4:$C$49,0),0) -> 0 | F7: =HLOOKUP(F$4,tab!$E$4:$P$49,MATCH($C7,$C$4:$C$49,0),0) -> 0
A8: 2021 | B8: =tab!B8 -> + | C8: =tab!C8 -> Despesas de Variação Cambial | E8: =HLOOKUP(E$4,tab!$E$4:$P$49,MATCH($C8,$C$4:$C$49,0),0) -> 0 | F8: =HLOOKUP(F$4,tab!$E$4:$P$49,MATCH($C8,$C$4:$C$49,0),0) -> 0
A9: 2022 | B9: =tab!B9 -> + | C9: =tab!C9 -> Despesas Particulares dos Sócios e Dirigentes; | E9: =HLOOKUP(E$4,tab!$E$4:$P$49,MATCH($C9,$C$4:$C$49,0),0) -> 0 | F9: =HLOOKUP(F$4,tab!$E$4:$P$49,MATCH($C9,$C$4:$C$49,0),0) -> 0
A10: 2023 | B10: =tab!B10 -> + | C10: =tab!C10 -> Doações e Brindes; | E10: =HLOOKUP(E$4,tab!$E$4:$P$49,MATCH($C10,$C$4:$C$49,0),0) -> 100 | F10: =HLOOKUP(F$4,tab!$E$4:$P$49,MATCH($C10,$C$4:$C$49,0),0) -> 100
A11: 2024 | B11: =tab!B11 -> + | C11: =tab!C11 -> Impostos Não Pagos em Discussão Judicial; | E11: =HLOOKUP(E$4,tab!$E$4:$P$49,MATCH($C11,$C$4:$C$49,0),0) -> 0 | F11: =HLOOKUP(F$4,tab!$E$4:$P$49,MATCH($C11,$C$4:$C$49,0),0) -> 0
A12: 2025 | B12: =tab!B12 -> + | C12: =tab!C12 -> Impostos Não Pagos por Iniciativa da Empresa; | E12: =HLOOKUP(E$4,tab!$E$4:$P$49,MATCH($C12,$C$4:$C$49,0),0) -> 0 | F12: =HLOOKUP(F$4,tab!$E$4:$P$49,MATCH($C12,$C$4:$C$49,0),0) -> 0
A13: 2026 | B13: =tab!B13 -> + | C13: =tab!C13 -> Lucro Inflacionário apurado até 31/12/1995; | E13: =HLOOKUP(E$4,tab!$E$4:$P$49,MATCH($C13,$C$4:$C$49,0),0) -> 0 | F13: =HLOOKUP(F$4,tab!$E$4:$P$49,MATCH($C13,$C$4:$C$49,0),0) -> 0
A14: 2027 | B14: =tab!B14 -> + | C14: =tab!C14 -> Multas Contratuais | E14: =HLOOKUP(E$4,tab!$E$4:$P$49,MATCH($C14,$C$4:$C$49,0),0) -> 0 | F14: =HLOOKUP(F$4,tab!$E$4:$P$49,MATCH($C14,$C$4:$C$49,0),0) -> 0
A15: 2028 | B15: =tab!B15 -> + | C15: =tab!C15 -> Multas Punitivas (Transito, Imetro, Ibama, Multas sobre ação fiscal) | E15: =HLOOKUP(E$4,tab!$E$4:$P$49,MATCH($C15,$C$4:$C$49,0),0) -> 500 | F15: =HLOOKUP(F$4,tab!$E$4:$P$49,MATCH($C15,$C$4:$C$49,0),0) -> 500
A16: 2029 | B16: =tab!B16 -> + | C16: =tab!C16 -> Orçamentos, Pedidos e qualquer documento não idôneo; | E16: =HLOOKUP(E$4,tab!$E$4:$P$49,MATCH($C16,$C$4:$C$49,0),0) -> 0 | F16: =HLOOKUP(F$4,tab!$E$4:$P$49,MATCH($C16,$C$4:$C$49,0),0) -> 0
A17: 2030 | B17: =tab!B17 -> + | C17: =tab!C17 -> Provisões Indedutíveis (perdas, frete, propaganda) | E17: =HLOOKUP(E$4,tab!$E$4:$P$49,MATCH($C17,$C$4:$C$49,0),0) -> 0 | F17: =HLOOKUP(F$4,tab!$E$4:$P$49,MATCH($C17,$C$4:$C$49,0),0) -> 0
B18: =tab!B18 -> + | C18: =tab!C18 -> Recibos sem especificação da fonte recebedora; | E18: =HLOOKUP(E$4,tab!$E$4:$P$49,MATCH($C18,$C$4:$C$49,0),0) -> 0 | F18: =HLOOKUP(F$4,tab!$E$4:$P$49,MATCH($C18,$C$4:$C$49,0),0) -> 0
B19: =tab!B19 -> + | C19: =tab!C19 -> Verbas Rescisórias em desacordo com a legislação trabalhista vigente | E19: =HLOOKUP(E$4,tab!$E$4:$P$49,MATCH($C19,$C$4:$C$49,0),0) -> 0 | F19: =HLOOKUP(F$4,tab!$E$4:$P$49,MATCH($C19,$C$4:$C$49,0),0) -> 0
B20: =tab!B20 -> = | C20: =tab!C20 -> Exclusões | E20: =SUM(E21:E33) -> -1000 | F20: =SUM(F21:F33) -> -1000
B21: =tab!B21 -> - | C21: =tab!C21 -> Ajustes credores de qualquer natureza | E21: =HLOOKUP(E$4,tab!$E$4:$P$49,MATCH($C21,$C$4:$C$49,0),0) -> 0 | F21: =HLOOKUP(F$4,tab!$E$4:$P$49,MATCH($C21,$C$4:$C$49,0),0) -> 0
B22: =tab!B22 -> - | C22: =tab!C22 -> Decisão Favorável - Processos Judiciais Tributários | E22: =HLOOKUP(E$4,tab!$E$4:$P$49,MATCH($C22,$C$4:$C$49,0),0) -> 0 | F22: =HLOOKUP(F$4,tab!$E$4:$P$49,MATCH($C22,$C$4:$C$49,0),0) -> 0
B23: =tab!B23 -> - | C23: =tab!C23 -> Despesas de Ágios | E23: =HLOOKUP(E$4,tab!$E$4:$P$49,MATCH($C23,$C$4:$C$49,0),0) -> 0 | F23: =HLOOKUP(F$4,tab!$E$4:$P$49,MATCH($C23,$C$4:$C$49,0),0) -> 0
B24: =tab!B24 -> - | C24: =tab!C24 -> Distribuição de Lucros e Dividendos; | E24: =HLOOKUP(E$4,tab!$E$4:$P$49,MATCH($C24,$C$4:$C$49,0),0) -> 0 | F24: =HLOOKUP(F$4,tab!$E$4:$P$49,MATCH($C24,$C$4:$C$49,0),0) -> 0
B25: =tab!B25 -> - | C25: =tab!C25 -> Dividendos Coligadas e Controladas | E25: =HLOOKUP(E$4,tab!$E$4:$P$49,MATCH($C25,$C$4:$C$49,0),0) -> 0 | F25: =HLOOKUP(F$4,tab!$E$4:$P$49,MATCH($C25,$C$4:$C$49,0),0) -> 0
B26: =tab!B26 -> - | C26: =tab!C26 -> Pagamento de Impostos em Atraso por iniciativa da Empresa | E26: =HLOOKUP(E$4,tab!$E$4:$P$49,MATCH($C26,$C$4:$C$49,0),0) -> -1000 | F26: =HLOOKUP(F$4,tab!$E$4:$P$49,MATCH($C26,$C$4:$C$49,0),0) -> -1000
B27: =tab!B27 -> - | C27: =tab!C27 -> Pagamento de Impostos sobre discussão judicial, | E27: =HLOOKUP(E$4,tab!$E$4:$P$49,MATCH($C27,$C$4:$C$49,0),0) -> 0 | F27: =HLOOKUP(F$4,tab!$E$4:$P$49,MATCH($C27,$C$4:$C$49,0),0) -> 0
B28: =tab!B28 -> - | C28: =tab!C28 -> Receita de Variação Cambial | E28: =HLOOKUP(E$4,tab!$E$4:$P$49,MATCH($C28,$C$4:$C$49,0),0) -> 0 | F28: =HLOOKUP(F$4,tab!$E$4:$P$49,MATCH($C28,$C$4:$C$49,0),0) -> 0
B29: =tab!B29 -> - | C29: =tab!C29 -> Receitas Obtidas com Tributação Exclusiva ou Isenta de IR | E29: =HLOOKUP(E$4,tab!$E$4:$P$49,MATCH($C29,$C$4:$C$49,0),0) -> 0 | F29: =HLOOKUP(F$4,tab!$E$4:$P$49,MATCH($C29,$C$4:$C$49,0),0) -> 0
B30: =tab!B30 -> - | C30: =tab!C30 -> Receitas que poderiam ser diferidas; | E30: =HLOOKUP(E$4,tab!$E$4:$P$49,MATCH($C30,$C$4:$C$49,0),0) -> 0 | F30: =HLOOKUP(F$4,tab!$E$4:$P$49,MATCH($C30,$C$4:$C$49,0),0) -> 0
B31: =tab!B31 -> - | C31: =tab!C31 -> Resultado Positivo de Equivalência Patrimonial | E31: =HLOOKUP(E$4,tab!$E$4:$P$49,MATCH($C31,$C$4:$C$49,0),0) -> 0 | F31: =HLOOKUP(F$4,tab!$E$4:$P$49,MATCH($C31,$C$4:$C$49,0),0) -> 0
B32: =tab!B32 -> - | C32: =tab!C32 -> Reversão de Provisões Indedutíveis | E32: =HLOOKUP(E$4,tab!$E$4:$P$49,MATCH($C32,$C$4:$C$49,0),0) -> 0 | F32: =HLOOKUP(F$4,tab!$E$4:$P$49,MATCH($C32,$C$4:$C$49,0),0) -> 0
B33: =tab!B33 -> - | C33: =tab!C33 -> Vendas Não Expedidas do Período | E33: =HLOOKUP(E$4,tab!$E$4:$P$49,MATCH($C33,$C$4:$C$49,0),0) -> 0 | F33: =HLOOKUP(F$4,tab!$E$4:$P$49,MATCH($C33,$C$4:$C$49,0),0) -> 0
B34: =tab!B34 -> = | C34: =tab!C34 -> Base de Cálculo | E34: =SUM(E5,E6,E20) -> 600 | F34: =SUM(F5,F6,F20) -> 25600
B35: =tab!B35 -> = | C35: =tab!C35 -> Saldo Prejuízo Fiscal | E35: =tab!E35 -> 45000 | F35: =SUM(E35:E36) -> 44820
B36: =tab!B36 -> % | C36: =tab!C36 -> Compensação de Prejuízo Fiscal | D36: =tab!D36 -> 0.3 | E36: =-IF(AND(E35>0,E34*$D$36<E35),E34*$D$36,E35) -> -180 | F36: =-IF(AND(F35>0,F34*$D$36<F35),F34*$D$36,F35) -> -7680
B37: =tab!B37 -> % | C37: =tab!C37 -> Adicional de Imposto de Renda | D37: =tab!D37 -> 0.1 | E37: =HLOOKUP($E$4,INDIRECT($E$4&"!$E$4:$O$49"),MATCH(C37,INDIRECT($E$4&"!$C$4:$C$49"),0),0) -> 0 | F37: =IF(SUM(F34,F36)>20000*$A$4,(SUM(F34,F36)-20000*$A$4)*$D$37,0) -> 0
B38: =tab!B38 -> % | C38: =tab!C38 -> Imposto de Renda | D38: =tab!D38 -> 0.15 | E38: =SUM(E34,E36)*$D$38 -> 63 | F38: =SUM(F34,F36)*$D$38 -> 2688
B39: =tab!B39 -> % | C39: =tab!C39 -> Contribuição Social | D39: =tab!D39 -> 0.09 | E39: =SUM(E34,E36)*$D$39 -> 37.8 | F39: =SUM(F34,F36)*$D$39 -> 1612.8
B40: =tab!B40 -> = | C40: =tab!C40 -> Compensações | E40: =SUM(E42:E47) -> -3600 | F40: =SUM(F42:F47) -> -3600
B41: =tab!B41 -> - | C41: =tab!C41 -> IR Base Negativa Exercícios Anteriores | D41: =LEFT(C41,2) -> IR | E41: =HLOOKUP(E$4,tab!$E$4:$P$49,MATCH($C41,$C$4:$C$49,0),0) -> 0 | F41: =HLOOKUP(F$4,tab!$E$4:$P$49,MATCH($C41,$C$4:$C$49,0),0) -> 0
B42: =tab!B42 -> - | C42: =tab!C42 -> IR s/ Aplicações Financeiras | D42: =LEFT(C42,2) -> IR | E42: =HLOOKUP(E$4,tab!$E$4:$P$49,MATCH($C42,$C$4:$C$49,0),0) -> -100 | F42: =HLOOKUP(F$4,tab!$E$4:$P$49,MATCH($C42,$C$4:$C$49,0),0) -> -100
B43: =tab!B43 -> - | C43: =tab!C43 -> IR Retida s/ Notas Fiscais | D43: =LEFT(C43,2) -> IR | E43: =HLOOKUP(E$4,tab!$E$4:$P$49,MATCH($C43,$C$4:$C$49,0),0) -> -2000 | F43: =HLOOKUP(F$4,tab!$E$4:$P$49,MATCH($C43,$C$4:$C$49,0),0) -> -2000
B44: =tab!B44 -> - | C44: =tab!C44 -> IR Pago no Exercício | D44: =LEFT(C44,2) -> IR | E44: =HLOOKUP(E$4,tab!$E$4:$P$49,MATCH($C44,$C$4:$C$49,0),0) -> 0 | F44: =-E48 -> 0
B45: =tab!B45 -> - | C45: =tab!C45 -> CS Base Negativa Exercícios Anteriores | D45: =LEFT(C45,2) -> CS | E45: =HLOOKUP(E$4,tab!$E$4:$P$49,MATCH($C45,$C$4:$C$49,0),0) -> 0 | F45: =HLOOKUP(F$4,tab!$E$4:$P$49,MATCH($C45,$C$4:$C$49,0),0) -> 0
B46: =tab!B46 -> - | C46: =tab!C46 -> CS Retida s/ Notas Fiscais | D46: =LEFT(C46,2) -> CS | E46: =HLOOKUP(E$4,tab!$E$4:$P$49,MATCH($C46,$C$4:$C$49,0),0) -> -1500 | F46: =HLOOKUP(F$4,tab!$E$4:$P$49,MATCH($C46,$C$4:$C$49,0),0) -> -1500
B47: =tab!B47 -> - | C47: =tab!C47 -> CS Pago no Exercício | D47: =LEFT(C47,2) -> CS | E47: =HLOOKUP(E$4,tab!$E$4:$P$49,MATCH($C47,$C$4:$C$49,0),0) -> 0 | F47: =-E49 -> 0
B48: =tab!B48 -> = | C48: =tab!C48 -> Imposto de Renda a Pagar | E48: =IF(SUM(E37,E38,SUMIF($D$41:E47,"IR",E$41:E$47))>0,SUM(E37,E38,SUMIF($D$41:E47,"IR",E$41:E$47)),0) -> 0 | F48: =IF(SUM(F37,F38,SUMIF($D$41:F47,"IR",F$41:F$47))>0,SUM(F37,F38,SUMIF($D$41:F47,"IR",F$41:F$47)),0) -> 588
B49: =tab!B49 -> = | C49: =tab!C49 -> Contribuição Social a Pagar | E49: =IF(SUM(E39,SUMIF($D$41:E47,"CS",E$41:E$47))>0,SUM(E39,SUMIF($D$41:E47,"CS",E$41:E$47)),0) -> 0 | F49: =IF(SUM(F39,SUMIF($D$41:F47,"CS",F$41:F$47))>0,SUM(F39,SUMIF($D$41:F47,"CS",F$41:F$47)),0) -> 112.8

Sheet mar
B3: 2018
A4: 3 | B4: # | C4: Parâmetros | D4: % | E4: Jan | F4: Fev | G4: Mar | H4: Abr | I4: Mai | J4: Jun | K4: Jul | L4: Ago | M4: Set | N4: Out | O4: Nov | P4: Dez
A5: 2018 | B5: =tab!B5 -> = | C5: =tab!C5 -> Lucro Acumulado | E5: =HLOOKUP(E$4,tab!$E$4:$P$33,MATCH($C5,$C$4:$C$33,0),0) -> 1000 | F5: =HLOOKUP(F$4,tab!$E$4:$P$33,MATCH($C5,$C$4:$C$33,0),0) -> 26000 | G5: =HLOOKUP(G$4,tab!$E$4:$P$33,MATCH($C5,$C$4:$C$33,0),0) -> 51000
A6: 2019 | B6: =tab!B6 -> = | C6: =tab!C6 -> Adições | E6: =SUM(E7:E19) -> 600 | F6: =SUM(F7:F19) -> 600 | G6: =SUM(G7:G19) -> 600
A7: 2020 | B7: =tab!B7 -> + | C7: =tab!C7 -> Ajustes Devedores de Qualquer Natureza | E7: =HLOOKUP(E$4,tab!$E$4:$P$49,MATCH($C7,$C$4:$C$49,0),0) -> 0 | F7: =HLOOKUP(F$4,tab!$E$4:$P$49,MATCH($C7,$C$4:$C$49,0),0) -> 0 | G7: =HLOOKUP(G$4,tab!$E$4:$P$49,MATCH($C7,$C$4:$C$49,0),0) -> 0
A8: 2021 | B8: =tab!B8 -> + | C8: =tab!C8 -> Despesas de Variação Cambial | E8: =HLOOKUP(E$4,tab!$E$4:$P$49,MATCH($C8,$C$4:$C$49,0),0) -> 0 | F8: =HLOOKUP(F$4,tab!$E$4:$P$49,MATCH($C8,$C$4:$C$49,0),0) -> 0 | G8: =HLOOKUP(G$4,tab!$E$4:$P$49,MATCH($C8,$C$4:$C$49,0),0) -> 0
A9: 2022 | B9: =tab!B9 -> + | C9: =tab!C9 -> Despesas Particulares dos Sócios e Dirigentes; | E9: =HLOOKUP(E$4,tab!$E$4:$P$49,MATCH($C9,$C$4:$C$49,0),0) -> 0 | F9: =HLOOKUP(F$4,tab!$E$4:$P$49,MATCH($C9,$C$4:$C$49,0),0) -> 0 | G9: =HLOOKUP(G$4,tab!$E$4:$P$49,MATCH($C9,$C$4:$C$49,0),0) -> 0
A10: 2023 | B10: =tab!B10 -> + | C10: =tab!C10 -> Doações e Brindes; | E10: =HLOOKUP(E$4,tab!$E$4:$P$49,MATCH($C10,$C$4:$C$49,0),0) -> 100 | F10: =HLOOKUP(F$4,tab!$E$4:$P$49,MATCH($C10,$C$4:$C$49,0),0) -> 100 | G10: =HLOOKUP(G$4,tab!$E$4:$P$49,MATCH($C10,$C$4:$C$49,0),0) -> 100
A11: 2024 | B11: =tab!B11 -> + | C11: =tab!C11 -> Impostos Não Pagos em Discussão Judicial; | E11: =HLOOKUP(E$4,tab!$E$4:$P$49,MATCH($C11,$C$4:$C$49,0),0) -> 0 | F11: =HLOOKUP(F$4,tab!$E$4:$P$49,MATCH($C11,$C$4:$C$49,0),0) -> 0 | G11: =HLOOKUP(G$4,tab!$E$4:$P$49,MATCH($C11,$C$4:$C$49,0),0) -> 0
A12: 2025 | B12: =tab!B12 -> + | C12: =tab!C12 -> Impostos Não Pagos por Iniciativa da Empresa; | E12: =HLOOKUP(E$4,tab!$E$4:$P$49,MATCH($C12,$C$4:$C$49,0),0) -> 0 | F12: =HLOOKUP(F$4,tab!$E$4:$P$49,MATCH($C12,$C$4:$C$49,0),0) -> 0 | G12: =HLOOKUP(G$4,tab!$E$4:$P$49,MATCH($C12,$C$4:$C$49,0),0) -> 0
A13: 2026 | B13: =tab!B13 -> + | C13: =tab!C13 -> Lucro Inflacionário apurado até 31/12/1995; | E13: =HLOOKUP(E$4,tab!$E$4:$P$49,MATCH($C13,$C$4:$C$49,0),0) -> 0 | F13: =HLOOKUP(F$4,tab!$E$4:$P$49,MATCH($C13,$C$4:$C$49,0),0) -> 0 | G13: =HLOOKUP(G$4,tab!$E$4:$P$49,MATCH($C13,$C$4:$C$49,0),0) -> 0
A14: 2027 | B14: =tab!B14 -> + | C14: =tab!C14 -> Multas Contratuais | E14: =HLOOKUP(E$4,tab!$E$4:$P$49,MATCH($C14,$C$4:$C$49,0),0) -> 0 | F14: =HLOOKUP(F$4,tab!$E$4:$P$49,MATCH($C14,$C$4:$C$49,0),0) -> 0 | G14: =HLOOKUP(G$4,tab!$E$4:$P$49,MATCH($C14,$C$4:$C$49,0),0) -> 0
A15: 2028 | B15: =tab!B15 -> + | C15: =tab!C15 -> Multas Punitivas (Transito, Imetro, Ibama, Multas sobre ação fiscal) | E15: =HLOOKUP(E$4,tab!$E$4:$P$49,MATCH($C15,$C$4:$C$49,0),0) -> 500 | F15: =HLOOKUP(F$4,tab!$E$4:$P$49,MATCH($C15,$C$4:$C$49,0),0) -> 500 | G15: =HLOOKUP(G$4,tab!$E$4:$P$49,MATCH($C15,$C$4:$C$49,0),0) -> 500
A16: 2029 | B16: =tab!B16 -> + | C16: =tab!C16 -> Orçamentos, Pedidos e qualquer documento não idôneo; | E16: =HLOOKUP(E$4,tab!$E$4:$P$49,MATCH($C16,$C$4:$C$49,0),0) -> 0 | F16: =HLOOKUP(F$4,tab!$E$4:$P$49,MATCH($C16,$C$4:$C$49,0),0) -> 0 | G16: =HLOOKUP(G$4,tab!$E$4:$P$49,MATCH($C16,$C$4:$C$49,0),0) -> 0
A17: 2030 | B17: =tab!B17 -> + | C17: =tab!C17 -> Provisões Indedutíveis (perdas, frete, propaganda) | E17: =HLOOKUP(E$4,tab!$E$4:$P$49,MATCH($C17,$C$4:$C$49,0),0) -> 0 | F17: =HLOOKUP(F$4,tab!$E$4:$P$49,MATCH($C17,$C$4:$C$49,0),0) -> 0 | G17: =HLOOKUP(G$4,tab!$E$4:$P$49,MATCH($C17,$C$4:$C$49,0),0) -> 0
B18: =tab!B18 -> + | C18: =tab!C18 -> Recibos sem especificação da fonte recebedora; | E18: =HLOOKUP(E$4,tab!$E$4:$P$49,MATCH($C18,$C$4:$C$49,0),0) -> 0 | F18: =HLOOKUP(F$4,tab!$E$4:$P$49,MATCH($C18,$C$4:$C$49,0),0) -> 0 | G18: =HLOOKUP(G$4,tab!$E$4:$P$49,MATCH($C18,$C$4:$C$49,0),0) -> 0
B19: =tab!B19 -> + | C19: =tab!C19 -> Verbas Rescisórias em desacordo com a legislação trabalhista vigente | E19: =HLOOKUP(E$4,tab!$E$4:$P$49,MATCH($C19,$C$4:$C$49,0),0) -> 0 | F19: =HLOOKUP(F$4,tab!$E$4:$P$49,MATCH($C19,$C$4:$C$49,0),0) -> 0 | G19: =HLOOKUP(G$4,tab!$E$4:$P$49,MATCH($C19,$C$4:$C$49,0),0) -> 0
B20: =tab!B20 -> = | C20: =tab!C20 -> Exclusões | E20: =SUM(E21:E33) -> -1000 | F20: =SUM(F21:F33) -> -1000 | G20: =SUM(G21:G33) -> -1000
B21: =tab!B21 -> - | C21: =tab!C21 -> Ajustes credores de qualquer natureza | E21: =HLOOKUP(E$4,tab!$E$4:$P$49,MATCH($C21,$C$4:$C$49,0),0) -> 0 | F21: =HLOOKUP(F$4,tab!$E$4:$P$49,MATCH($C21,$C$4:$C$49,0),0) -> 0 | G21: =HLOOKUP(G$4,tab!$E$4:$P$49,MATCH($C21,$C$4:$C$49,0),0) -> 0
B22: =tab!B22 -> - | C22: =tab!C22 -> Decisão Favorável - Processos Judiciais Tributários | E22: =HLOOKUP(E$4,tab!$E$4:$P$49,MATCH($C22,$C$4:$C$49,0),0) -> 0 | F22: =HLOOKUP(F$4,tab!$E$4:$P$49,MATCH($C22,$C$4:$C$49,0),0) -> 0 | G22: =HLOOKUP(G$4,tab!$E$4:$P$49,MATCH($C22,$C$4:$C$49,0),0) -> 0
B23: =tab!B23 -> - | C23: =tab!C23 -> Despesas de Ágios | E23: =HLOOKUP(E$4,tab!$E$4:$P$49,MATCH($C23,$C$4:$C$49,0),0) -> 0 | F23: =HLOOKUP(F$4,tab!$E$4:$P$49,MATCH($C23,$C$4:$C$49,0),0) -> 0 | G23: =HLOOKUP(G$4,tab!$E$4:$P$49,MATCH($C23,$C$4:$C$49,0),0) -> 0
B24: =tab!B24 -> - | C24: =tab!C24 -> Distribuição de Lucros e Dividendos; | E24: =HLOOKUP(E$4,tab!$E$4:$P$49,MATCH($C24,$C$4:$C$49,0),0) -> 0 | F24: =HLOOKUP(F$4,tab!$E$4:$P$49,MATCH($C24,$C$4:$C$49,0),0) -> 0 | G24: =HLOOKUP(G$4,tab!$E$4:$P$49,MATCH($C24,$C$4:$C$49,0),0) -> 0
B25: =tab!B25 -> - | C25: =tab!C25 -> Dividendos Coligadas e Controladas | E25: =HLOOKUP(E$4,tab!$E$4:$P$49,MATCH($C25,$C$4:$C$49,0),0) -> 0 | F25: =HLOOKUP(F$4,tab!$E$4:$P$49,MATCH($C25,$C$4:$C$49,0),0) -> 0 | G25: =HLOOKUP(G$4,tab!$E$4:$P$49,MATCH($C25,$C$4:$C$49,0),0) -> 0
B26: =tab!B26 -> - | C26: =tab!C26 -> Pagamento de Impostos em Atraso por iniciativa da Empresa | E26: =HLOOKUP(E$4,tab!$E$4:$P$49,MATCH($C26,$C$4:$C$49,0),0) -> -1000 | F26: =HLOOKUP(F$4,tab!$E$4:$P$49,MATCH($C26,$C$4:$C$49,0),0) -> -1000 | G26: =HLOOKUP(G$4,tab!$E$4:$P$49,MATCH($C26,$C$4:$C$49,0),0) -> -1000
B27: =tab!B27 -> - | C27: =tab!C27 -> Pagamento de Impostos sobre discussão judicial, | E27: =HLOOKUP(E$4,tab!$E$4:$P$49,MATCH($C27,$C$4:$C$49,0),0) -> 0 | F27: =HLOOKUP(F$4,tab!$E$4:$P$49,MATCH($C27,$C$4:$C$49,0),0) -> 0 | G27: =HLOOKUP(G$4,tab!$E$4:$P$49,MATCH($C27,$C$4:$C$49,0),0) -> 0
B28: =tab!B28 -> - | C28: =tab!C28 -> Receita de Variação Cambial | E28: =HLOOKUP(E$4,tab!$E$4:$P$49,MATCH($C28,$C$4:$C$49,0),0) -> 0 | F28: =HLOOKUP(F$4,tab!$E$4:$P$49,MATCH($C28,$C$4:$C$49,0),0) -> 0 | G28: =HLOOKUP(G$4,tab!$E$4:$P$49,MATCH($C28,$C$4:$C$49,0),0) -> 0
B29: =tab!B29 -> - | C29: =tab!C29 -> Receitas Obtidas com Tributação Exclusiva ou Isenta de IR | E29: =HLOOKUP(E$4,tab!$E$4:$P$49,MATCH($C29,$C$4:$C$49,0),0) -> 0 | F29: =HLOOKUP(F$4,tab!$E$4:$P$49,MATCH($C29,$C$4:$C$49,0),0) -> 0 | G29: =HLOOKUP(G$4,tab!$E$4:$P$49,MATCH($C29,$C$4:$C$49,0),0) -> 0
B30: =tab!B30 -> - | C30: =tab!C30 -> Receitas que poderiam ser diferidas; | E30: =HLOOKUP(E$4,tab!$E$4:$P$49,MATCH($C30,$C$4:$C$49,0),0) -> 0 | F30: =HLOOKUP(F$4,tab!$E$4:$P$49,MATCH($C30,$C$4:$C$49,0),0) -> 0 | G30: =HLOOKUP(G$4,tab!$E$4:$P$49,MATCH($C30,$C$4:$C$49,0),0) -> 0
B31: =tab!B31 -> - | C31: =tab!C31 -> Resultado Positivo de Equivalência Patrimonial | E31: =HLOOKUP(E$4,tab!$E$4:$P$49,MATCH($C31,$C$4:$C$49,0),0) -> 0 | F31: =HLOOKUP(F$4,tab!$E$4:$P$49,MATCH($C31,$C$4:$C$49,0),0) -> 0 | G31: =HLOOKUP(G$4,tab!$E$4:$P$49,MATCH($C31,$C$4:$C$49,0),0) -> 0
B32: =tab!B32 -> - | C32: =tab!C32 -> Reversão de Provisões Indedutíveis | E32: =HLOOKUP(E$4,tab!$E$4:$P$49,MATCH($C32,$C$4:$C$49,0),0) -> 0 | F32: =HLOOKUP(F$4,tab!$E$4:$P$49,MATCH($C32,$C$4:$C$49,0),0) -> 0 | G32: =HLOOKUP(G$4,tab!$E$4:$P$49,MATCH($C32,$C$4:$C$49,0),0) -> 0
B33: =tab!B33 -> - | C33: =tab!C33 -> Vendas Não Expedidas do Período | E33: =HLOOKUP(E$4,tab!$E$4:$P$49,MATCH($C33,$C$4:$C$49,0),0) -> 0 | F33: =HLOOKUP(F$4,tab!$E$4:$P$49,MATCH($C33,$C$4:$C$49,0),0) -> 0 | G33: =HLOOKUP(G$4,tab!$E$4:$P$49,MATCH($C33,$C$4:$C$49,0),0) -> 0
B34: =tab!B34 -> = | C34: =tab!C34 -> Base de Cálculo | E34: =SUM(E5,E6,E20) -> 600 | F34: =SUM(F5,F6,F20) -> 25600 | G34: =SUM(G5,G6,G20) -> 50600
B35: =tab!B35 -> = | C35: =tab!C35 -> Saldo Prejuízo Fiscal | E35: =tab!E35 -> 45000 | F35: =SUM(E35:E36) -> 44820 | G35: =SUM(F35:F36) -> 37140
B36: =tab!B36 -> % | C36: =tab!C36 -> Compensação de Prejuízo Fiscal | D36: =tab!D36 -> 0.3 | E36: =-IF(AND(E35>0,E34*$D$36<E35),E34*$D$36,E35) -> -180 | F36: =-IF(AND(F35>0,F34*$D$36<F35),F34*$D$36,F35) -> -7680 | G36: =-IF(AND(G35>0,G34*$D$36<G35),G34*$D$36,G35) -> -15180
B37: =tab!B37 -> % | C37: =tab!C37 -> Adicional de Imposto de Renda | D37: =tab!D37 -> 0.1 | E37: =HLOOKUP($E$4,INDIRECT($E$4&"!$E$4:$O$49"),MATCH(C37,INDIRECT($E$4&"!$C$4:$C$49"),0),0) -> 0 | F37: =IF(SUM(F34,F36)>20000*$A$4,(SUM(F34,F36)-20000*$A$4)*$D$37,0) -> 0 | G37: =IF(SUM(G34,G36)>20000*$A$4,(SUM(G34,G36)-20000*$A$4)*$D$37,0) -> 0
B38: =tab!B38 -> % | C38: =tab!C38 -> Imposto de Renda | D38: =tab!D38 -> 0.15 | E38: =SUM(E34,E36)*$D$38 -> 63 | F38: =SUM(F34,F36)*$D$38 -> 2688 | G38: =SUM(G34,G36)*$D$38 -> 5313
B39: =tab!B39 -> % | C39: =tab!C39 -> Contribuição Social | D39: =tab!D39 -> 0.09 | E39: =SUM(E34,E36)*$D$39 -> 37.8 | F39: =SUM(F34,F36)*$D$39 -> 1612.8 | G39: =SUM(G34,G36)*$D$39 -> 3187.8
B40: =tab!B40 -> = | C40: =tab!C40 -> Compensações | E40: =SUM(E42:E47) -> -3600 | F40: =SUM(F42:F47) -> -3600 | G40: =SUM(G42:G47) -> -4300.8
B41: =tab!B41 -> - | C41: =tab!C41 -> IR Base Negativa Exercícios Anteriores | D41: =LEFT(C41,2) -> IR | E41: =HLOOKUP(E$4,tab!$E$4:$P$49,MATCH($C41,$C$4:$C$49,0),0) -> 0 | F41: =HLOOKUP(F$4,tab!$E$4:$P$49,MATCH($C41,$C$4:$C$49,0),0) -> 0 | G41: =HLOOKUP(G$4,tab!$E$4:$P$49,MATCH($C41,$C$4:$C$49,0),0) -> 0
B42: =tab!B42 -> - | C42: =tab!C42 -> IR s/ Aplicações Financeiras | D42: =LEFT(C42,2) -> IR | E42: =HLOOKUP(E$4,tab!$E$4:$P$49,MATCH($C42,$C$4:$C$49,0),0) -> -100 | F42: =HLOOKUP(F$4,tab!$E$4:$P$49,MATCH($C42,$C$4:$C$49,0),0) -> -100 | G42: =HLOOKUP(G$4,tab!$E$4:$P$49,MATCH($C42,$C$4:$C$49,0),0) -> -100
B43: =tab!B43 -> - | C43: =tab!C43 -> IR Retida s/ Notas Fiscais | D43: =LEFT(C43,2) -> IR | E43: =HLOOKUP(E$4,tab!$E$4:$P$49,MATCH($C43,$C$4:$C$49,0),0) -> -2000 | F43: =HLOOKUP(F$4,tab!$E$4:$P$49,MATCH($C43,$C$4:$C$49,0),0) -> -2000 | G43: =HLOOKUP(G$4,tab!$E$4:$P$49,MATCH($C43,$C$4:$C$49,0),0) -> -2000
B44: =tab!B44 -> - | C44: =tab!C44 -> IR Pago no Exercício | D44: =LEFT(C44,2) -> IR | E44: =HLOOKUP(E$4,tab!$E$4:$P$49,MATCH($C44,$C$4:$C$49,0),0) -> 0 | F44: =-E48 -> 0 | G44: =-SUM($E$48:F48) -> -588
B45: =tab!B45 -> - | C45: =tab!C45 -> CS Base Negativa Exercícios Anteriores | D45: =LEFT(C45,2) -> CS | E45: =HLOOKUP(E$4,tab!$E$4:$P$49,MATCH($C45,$C$4:$C$49,0),0) -> 0 | F45: =HLOOKUP(F$4,tab!$E$4:$P$49,MATCH($C45,$C$4:$C$49,0),0) -> 0 | G45: =HLOOKUP(G$4,tab!$E$4:$P$49,MATCH($C45,$C$4:$C$49,0),0) -> 0
B46: =tab!B46 -> - | C46: =tab!C46 -> CS Retida s/ Notas Fiscais | D46: =LEFT(C46,2) -> CS | E46: =HLOOKUP(E$4,tab!$E$4:$P$49,MATCH($C46,$C$4:$C$49,0),0) -> -1500 | F46: =HLOOKUP(F$4,tab!$E$4:$P$49,MATCH($C46,$C$4:$C$49,0),0) -> -1500 | G46: =HLOOKUP(G$4,tab!$E$4:$P$49,MATCH($C46,$C$4:$C$49,0),0) -> -1500
B47: =tab!B47 -> - | C47: =tab!C47 -> CS Pago no Exercício | D47: =LEFT(C47,2) -> CS | E47: =HLOOKUP(E$4,tab!$E$4:$P$49,MATCH($C47,$C$4:$C$49,0),0) -> 0 | F47: =-E49 -> 0 | G47: =-SUM($E$49:F49) -> -112.8
B48: =tab!B48 -> = | C48: =tab!C48 -> Imposto de Renda a Pagar | E48: =IF(SUM(E37,E38,SUMIF($D$41:E47,"IR",E$41:E$47))>0,SUM(E37,E38,SUMIF($D$41:E47,"IR",E$41:E$47)),0) -> 0 | F48: =IF(SUM(F37,F38,SUMIF($D$41:F47,"IR",F$41:F$47))>0,SUM(F37,F38,SUMIF($D$41:F47,"IR",F$41:F$47)),0) -> 588 | G48: =IF(SUM(G37,G38,SUMIF($D$41:G47,"IR",G$41:G$47))>0,SUM(G37,G38,SUMIF($D$41:G47,"IR",G$41:G$47)),0) -> 2625
B49: =tab!B49 -> = | C49: =tab!C49 -> Contribuição Social a Pagar | E49: =IF(SUM(E39,SUMIF($D$41:E47,"CS",E$41:E$47))>0,SUM(E39,SUMIF($D$41:E47,"CS",E$41:E$47)),0) -> 0 | F49: =IF(SUM(F39,SUMIF($D$41:F47,"CS",F$41:F$47))>0,SUM(F39,SUMIF($D$41:F47,"CS",F$41:F$47)),0) -> 112.8 | G49: =IF(SUM(G39,SUMIF($D$41:G47,"CS",G$41:G$47))>0,SUM(G39,SUMIF($D$41:G47,"CS",G$41:G$47)),0) -> 1575

Sheet abr
B3: 2018
A4: 4 | B4: # | C4: Parâmetros | D4: % | E4: Jan | F4: Fev | G4: Mar | H4: Abr | I4: Mai | J4: Jun | K4: Jul | L4: Ago | M4: Set | N4: Out | O4: Nov | P4: Dez
A5: 2018 | B5: =tab!B5 -> = | C5: =tab!C5 -> Lucro Acumulado | E5: =HLOOKUP(E$4,tab!$E$4:$P$33,MATCH($C5,$C$4:$C$33,0),0) -> 1000 | F5: =HLOOKUP(F$4,tab!$E$4:$P$33,MATCH($C5,$C$4:$C$33,0),0) -> 26000 | G5: =HLOOKUP(G$4,tab!$E$4:$P$33,MATCH($C5,$C$4:$C$33,0),0) -> 51000 | H5: =HLOOKUP(H$4,tab!$E$4:$P$33,MATCH($C5,$C$4:$C$33,0),0) -> 76000
A6: 2019 | B6: =tab!B6 -> = | C6: =tab!C6 -> Adições | E6: =SUM(E7:E19) -> 600 | F6: =SUM(F7:F19) -> 600 | G6: =SUM(G7:G19) -> 600 | H6: =SUM(H7:H19) -> 600
A7: 2020 | B7: =tab!B7 -> + | C7: =tab!C7 -> Ajustes Devedores de Qualquer Natureza | E7: =HLOOKUP(E$4,tab!$E$4:$P$49,MATCH($C7,$C$4:$C$49,0),0) -> 0 | F7: =HLOOKUP(F$4,tab!$E$4:$P$49,MATCH($C7,$C$4:$C$49,0),0) -> 0 | G7: =HLOOKUP(G$4,tab!$E$4:$P$49,MATCH($C7,$C$4:$C$49,0),0) -> 0 | H7: =HLOOKUP(H$4,tab!$E$4:$P$49,MATCH($C7,$C$4:$C$49,0),0) -> 0
A8: 2021 | B8: =tab!B8 -> + | C8: =tab!C8 -> Despesas de Variação Cambial | E8: =HLOOKUP(E$4,tab!$E$4:$P$49,MATCH($C8,$C$4:$C$49,0),0) -> 0 | F8: =HLOOKUP(F$4,tab!$E$4:$P$49,MATCH($C8,$C$4:$C$49,0),0) -> 0 | G8: =HLOOKUP(G$4,tab!$E$4:$P$49,MATCH($C8,$C$4:$C$49,0),0) -> 0 | H8: =HLOOKUP(H$4,tab!$E$4:$P$49,MATCH($C8,$C$4:$C$49,0),0) -> 0
A9: 2022 | B9: =tab!B9 -> + | C9: =tab!C9 -> Despesas Particulares dos Sócios e Dirigentes; | E9: =HLOOKUP(E$4,tab!$E$4:$P$49,MATCH($C9,$C$4:$C$49,0),0) -> 0 | F9: =HLOOKUP(F$4,tab!$E$4:$P$49,MATCH($C9,$C$4:$C$49,0),0) -> 0 | G9: =HLOOKUP(G$4,tab!$E$4:$P$49,MATCH($C9,$C$4:$C$49,0),0) -> 0 | H9: =HLOOKUP(H$4,tab!$E$4:$P$49,MATCH($C9,$C$4:$C$49,0),0) -> 0
A10: 2023 | B10: =tab!B10 -> + | C10: =tab!C10 -> Doações e Brindes; | E10: =HLOOKUP(E$4,tab!$E$4:$P$49,MATCH($C10,$C$4:$C$49,0),0) -> 100 | F10: =HLOOKUP(F$4,tab!$E$4:$P$49,MATCH($C10,$C$4:$C$49,0),0) -> 100 | G10: =HLOOKUP(G$4,tab!$E$4:$P$49,MATCH($C10,$C$4:$C$49,0),0) -> 100 | H10: =HLOOKUP(H$4,tab!$E$4:$P$49,MATCH($C10,$C$4:$C$49,0),0) -> 100
A11: 2024 | B11: =tab!B11 -> + | C11: =tab!C11 -> Impostos Não Pagos em Discussão Judicial; | E11: =HLOOKUP(E$4,tab!$E$4:$P$49,MATCH($C11,$C$4:$C$49,0),0) -> 0 | F11: =HLOOKUP(F$4,tab!$E$4:$P$49,MATCH($C11,$C$4:$C$49,0),0) -> 0 | G11: =HLOOKUP(G$4,tab!$E$4:$P$49,MATCH($C11,$C$4:$C$49,0),0) -> 0 | H11: =HLOOKUP(H$4,tab!$E$4:$P$49,MATCH($C11,$C$4:$C$49,0),0) -> 0
A12: 2025 | B12: =tab!B12 -> + | C12: =tab!C12 -> Impostos Não Pagos por Iniciativa da Empresa; | E12: =HLOOKUP(E$4,tab!$E$4:$P$49,MATCH($C12,$C$4:$C$49,0),0) -> 0 | F12: =HLOOKUP(F$4,tab!$E$4:$P$49,MATCH($C12,$C$4:$C$49,0),0) -> 0 | G12: =HLOOKUP(G$4,tab!$E$4:$P$49,MATCH($C12,$C$4:$C$49,0),0) -> 0 | H12: =HLOOKUP(H$4,tab!$E$4:$P$49,MATCH($C12,$C$4:$C$49,0),0) -> 0
A13: 2026 | B13: =tab!B13 -> + | C13: =tab!C13 -> Lucro Inflacionário apurado até 31/12/1995; | E13: =HLOOKUP(E$4,tab!$E$4:$P$49,MATCH($C13,$C$4:$C$49,0),0) -> 0 | F13: =HLOOKUP(F$4,tab!$E$4:$P$49,MATCH($C13,$C$4:$C$49,0),0) -> 0 | G13: =HLOOKUP(G$4,tab!$E$4:$P$49,MATCH($C13,$C$4:$C$49,0),0) -> 0 | H13: =HLOOKUP(H$4,tab!$E$4:$P$49,MATCH($C13,$C$4:$C$49,0),0) -> 0
A14: 2027 | B14: =tab!B14 -> + | C14: =tab!C14 -> Multas Contratuais | E14: =HLOOKUP(E$4,tab!$E$4:$P$49,MATCH($C14,$C$4:$C$49,0),0) -> 0 | F14: =HLOOKUP(F$4,tab!$E$4:$P$49,MATCH($C14,$C$4:$C$49,0),0) -> 0 | G14: =HLOOKUP(G$4,tab!$E$4:$P$49,MATCH($C14,$C$4:$C$49,0),0) -> 0 | H14: =HLOOKUP(H$4,tab!$E$4:$P$49,MATCH($C14,$C$4:$C$49,0),0) -> 0
A15: 2028 | B15: =tab!B15 -> + | C15: =tab!C15 -> Multas Punitivas (Transito, Imetro, Ibama, Multas sobre ação fiscal) | E15: =HLOOKUP(E$4,tab!$E$4:$P$49,MATCH($C15,$C$4:$C$49,0),0) -> 500 | F15: =HLOOKUP(F$4,tab!$E$4:$P$49,MATCH($C15,$C$4:$C$49,0),0) -> 500 | G15: =HLOOKUP(G$4,tab!$E$4:$P$49,MATCH($C15,$C$4:$C$49,0),0) -> 500 | H15: =HLOOKUP(H$4,tab!$E$4:$P$49,MATCH($C15,$C$4:$C$49,0),0) -> 500
A16: 2029 | B16: =tab!B16 -> + | C16: =tab!C16 -> Orçamentos, Pedidos e qualquer documento não idôneo; | E16: =HLOOKUP(E$4,tab!$E$4:$P$49,MATCH($C16,$C$4:$C$49,0),0) -> 0 | F16: =HLOOKUP(F$4,tab!$E$4:$P$49,MATCH($C16,$C$4:$C$49,0),0) -> 0 | G16: =HLOOKUP(G$4,tab!$E$4:$P$49,MATCH($C16,$C$4:$C$49,0),0) -> 0 | H16: =HLOOKUP(H$4,tab!$E$4:$P$49,MATCH($C16,$C$4:$C$49,0),0) -> 0
A17: 2030 | B17: =tab!B17 -> + | C17: =tab!C17 -> Provisões Indedutíveis (perdas, frete, propaganda) | E17: =HLOOKUP(E$4,tab!$E$4:$P$49,MATCH($C17,$C$4:$C$49,0),0) -> 0 | F17: =HLOOKUP(F$4,tab!$E$4:$P$49,MATCH($C17,$C$4:$C$49,0),0) -> 0 | G17: =HLOOKUP(G$4,tab!$E$4:$P$49,MATCH($C17,$C$4:$C$49,0),0) -> 0 | H17: =HLOOKUP(H$4,tab!$E$4:$P$49,MATCH($C17,$C$4:$C$49,0),0) -> 0
B18: =tab!B18 -> + | C18: =tab!C18 -> Recibos sem especificação da fonte recebedora; | E18: =HLOOKUP(E$4,tab!$E$4:$P$49,MATCH($C18,$C$4:$C$49,0),0) -> 0 | F18: =HLOOKUP(F$4,tab!$E$4:$P$49,MATCH($C18,$C$4:$C$49,0),0) -> 0 | G18: =HLOOKUP(G$4,tab!$E$4:$P$49,MATCH($C18,$C$4:$C$49,0),0) -> 0 | H18: =HLOOKUP(H$4,tab!$E$4:$P$49,MATCH($C18,$C$4:$C$49,0),0) -> 0
B19: =tab!B19 -> + | C19: =tab!C19 -> Verbas Rescisórias em desacordo com a legislação trabalhista vigente | E19: =HLOOKUP(E$4,tab!$E$4:$P$49,MATCH($C19,$C$4:$C$49,0),0) -> 0 | F19: =HLOOKUP(F$4,tab!$E$4:$P$49,MATCH($C19,$C$4:$C$49,0),0) -> 0 | G19: =HLOOKUP(G$4,tab!$E$4:$P$49,MATCH($C19,$C$4:$C$49,0),0) -> 0 | H19: =HLOOKUP(H$4,tab!$E$4:$P$49,MATCH($C19,$C$4:$C$49,0),0) -> 0
B20: =tab!B20 -> = | C20: =tab!C20 -> Exclusões | E20: =SUM(E21:E33) -> -1000 | F20: =SUM(F21:F33) -> -1000 | G20: =SUM(G21:G33) -> -1000 | H20: =SUM(H21:H33) -> -1000
B21: =tab!B21 -> - | C21: =tab!C21 -> Ajustes credores de qualquer natureza | E21: =HLOOKUP(E$4,tab!$E$4:$P$49,MATCH($C21,$C$4:$C$49,0),0) -> 0 | F21: =HLOOKUP(F$4,tab!$E$4:$P$49,MATCH($C21,$C$4:$C$49,0),0) -> 0 | G21: =HLOOKUP(G$4,tab!$E$4:$P$49,MATCH($C21,$C$4:$C$49,0),0) -> 0 | H21: =HLOOKUP(H$4,tab!$E$4:$P$49,MATCH($C21,$C$4:$C$49,0),0) -> 0
B22: =tab!B22 -> - | C22: =tab!C22 -> Decisão Favorável - Processos Judiciais Tributários | E22: =HLOOKUP(E$4,tab!$E$4:$P$49,MATCH($C22,$C$4:$C$49,0),0) -> 0 | F22: =HLOOKUP(F$4,tab!$E$4:$P$49,MATCH($C22,$C$4:$C$49,0),0) -> 0 | G22: =HLOOKUP(G$4,tab!$E$4:$P$49,MATCH($C22,$C$4:$C$49,0),0) -> 0 | H22: =HLOOKUP(H$4,tab!$E$4:$P$49,MATCH($C22,$C$4:$C$49,0),0) -> 0
B23: =tab!B23 -> - | C23: =tab!C23 -> Despesas de Ágios | E23: =HLOOKUP(E$4,tab!$E$4:$P$49,MATCH($C23,$C$4:$C$49,0),0) -> 0 | F23: =HLOOKUP(F$4,tab!$E$4:$P$49,MATCH($C23,$C$4:$C$49,0),0) -> 0 | G23: =HLOOKUP(G$4,tab!$E$4:$P$49,MATCH($C23,$C$4:$C$49,0),0) -> 0 | H23: =HLOOKUP(H$4,tab!$E$4:$P$49,MATCH($C23,$C$4:$C$49,0),0) -> 0
B24: =tab!B24 -> - | C24: =tab!C24 -> Distribuição de Lucros e Dividendos; | E24: =HLOOKUP(E$4,tab!$E$4:$P$49,MATCH($C24,$C$4:$C$49,0),0) -> 0 | F24: =HLOOKUP(F$4,tab!$E$4:$P$49,MATCH($C24,$C$4:$C$49,0),0) -> 0 | G24: =HLOOKUP(G$4,tab!$E$4:$P$49,MATCH($C24,$C$4:$C$49,0),0) -> 0 | H24: =HLOOKUP(H$4,tab!$E$4:$P$49,MATCH($C24,$C$4:$C$49,0),0) -> 0
B25: =tab!B25 -> - | C25: =tab!C25 -> Dividendos Coligadas e Controladas | E25: =HLOOKUP(E$4,tab!$E$4:$P$49,MATCH($C25,$C$4:$C$49,0),0) -> 0 | F25: =HLOOKUP(F$4,tab!$E$4:$P$49,MATCH($C25,$C$4:$C$49,0),0) -> 0 | G25: =HLOOKUP(G$4,tab!$E$4:$P$49,MATCH($C25,$C$4:$C$49,0),0) -> 0 | H25: =HLOOKUP(H$4,tab!$E$4:$P$49,MATCH($C25,$C$4:$C$49,0),0) -> 0
B26: =tab!B26 -> - | C26: =tab!C26 -> Pagamento de Impostos em Atraso por iniciativa da Empresa | E26: =HLOOKUP(E$4,tab!$E$4:$P$49,MATCH($C26,$C$4:$C$49,0),0) -> -1000 | F26: =HLOOKUP(F$4,tab!$E$4:$P$49,MATCH($C26,$C$4:$C$49,0),0) -> -1000 | G26: =HLOOKUP(G$4,tab!$E$4:$P$49,MATCH($C26,$C$4:$C$49,0),0) -> -1000 | H26: =HLOOKUP(H$4,tab!$E$4:$P$49,MATCH($C26,$C$4:$C$49,0),0) -> -1000
B27: =tab!B27 -> - | C27: =tab!C27 -> Pagamento de Impostos sobre discussão judicial, | E27: =HLOOKUP(E$4,tab!$E$4:$P$49,MATCH($C27,$C$4:$C$49,0),0) -> 0 | F27: =HLOOKUP(F$4,tab!$E$4:$P$49,MATCH($C27,$C$4:$C$49,0),0) -> 0 | G27: =HLOOKUP(G$4,tab!$E$4:$P$49,MATCH($C27,$C$4:$C$49,0),0) -> 0 | H27: =HLOOKUP(H$4,tab!$E$4:$P$49,MATCH($C27,$C$4:$C$49,0),0) -> 0
B28: =tab!B28 -> - | C28: =tab!C28 -> Receita de Variação Cambial | E28: =HLOOKUP(E$4,tab!$E$4:$P$49,MATCH($C28,$C$4:$C$49,0),0) -> 0 | F28: =HLOOKUP(F$4,tab!$E$4:$P$49,MATCH($C28,$C$4:$C$49,0),0) -> 0 | G28: =HLOOKUP(G$4,tab!$E$4:$P$49,MATCH($C28,$C$4:$C$49,0),0) -> 0 | H28: =HLOOKUP(H$4,tab!$E$4:$P$49,MATCH($C28,$C$4:$C$49,0),0) -> 0
B29: =tab!B29 -> - | C29: =tab!C29 -> Receitas Obtidas com Tributação Exclusiva ou Isenta de IR | E29: =HLOOKUP(E$4,tab!$E$4:$P$49,MATCH($C29,$C$4:$C$49,0),0) -> 0 | F29: =HLOOKUP(F$4,tab!$E$4:$P$49,MATCH($C29,$C$4:$C$49,0),0) -> 0 | G29: =HLOOKUP(G$4,tab!$E$4:$P$49,MATCH($C29,$C$4:$C$49,0),0) -> 0 | H29: =HLOOKUP(H$4,tab!$E$4:$P$49,MATCH($C29,$C$4:$C$49,0),0) -> 0
B30: =tab!B30 -> - | C30: =tab!C30 -> Receitas que poderiam ser diferidas; | E30: =HLOOKUP(E$4,tab!$E$4:$P$49,MATCH($C30,$C$4:$C$49,0),0) -> 0 | F30: =HLOOKUP(F$4,tab!$E$4:$P$49,MATCH($C30,$C$4:$C$49,0),0) -> 0 | G30: =HLOOKUP(G$4,tab!$E$4:$P$49,MATCH($C30,$C$4:$C$49,0),0) -> 0 | H30: =HLOOKUP(H$4,tab!$E$4:$P$49,MATCH($C30,$C$4:$C$49,0),0) -> 0
B31: =tab!B31 -> - | C31: =tab!C31 -> Resultado Positivo de Equivalência Patrimonial | E31: =HLOOKUP(E$4,tab!$E$4:$P$49,MATCH($C31,$C$4:$C$49,0),0) -> 0 | F31: =HLOOKUP(F$4,tab!$E$4:$P$49,MATCH($C31,$C$4:$C$49,0),0) -> 0 | G31: =HLOOKUP(G$4,tab!$E$4:$P$49,MATCH($C31,$C$4:$C$49,0),0) -> 0 | H31: =HLOOKUP(H$4,tab!$E$4:$P$49,MATCH($C31,$C$4:$C$49,0),0) -> 0
B32: =tab!B32 -> - | C32: =tab!C32 -> Reversão de Provisões Indedutíveis | E32: =HLOOKUP(E$4,tab!$E$4:$P$49,MATCH($C32,$C$4:$C$49,0),0) -> 0 | F32: =HLOOKUP(F$4,tab!$E$4:$P$49,MATCH($C32,$C$4:$C$49,0),0) -> 0 | G32: =HLOOKUP(G$4,tab!$E$4:$P$49,MATCH($C32,$C$4:$C$49,0),0) -> 0 | H32: =HLOOKUP(H$4,tab!$E$4:$P$49,MATCH($C32,$C$4:$C$49,0),0) -> 0
B33: =tab!B33 -> - | C33: =tab!C33 -> Vendas Não Expedidas do Período | E33: =HLOOKUP(E$4,tab!$E$4:$P$49,MATCH($C33,$C$4:$C$49,0),0) -> 0 | F33: =HLOOKUP(F$4,tab!$E$4:$P$49,MATCH($C33,$C$4:$C$49,0),0) -> 0 | G33: =HLOOKUP(G$4,tab!$E$4:$P$49,MATCH($C33,$C$4:$C$49,0),0) -> 0 | H33: =HLOOKUP(H$4,tab!$E$4:$P$49,MATCH($C33,$C$4:$C$49,0),0) -> 0
B34: =tab!B34 -> = | C34: =tab!C34 -> Base de Cálculo | E34: =SUM(E5,E6,E20) -> 600 | F34: =SUM(F5,F6,F20) -> 25600 | G34: =SUM(G5,G6,G20) -> 50600 | H34: =SUM(H5,H6,H20) -> 75600
B35: =tab!B35 -> = | C35: =tab!C35 -> Saldo Prejuízo Fiscal | E35: =tab!E35 -> 45000 | F35: =SUM(E35:E36) -> 44820 | G35: =SUM(F35:F36) -> 37140 | H35: =SUM(G35:G36) -> 21960
B36: =tab!B36 -> % | C36: =tab!C36 -> Compensação de Prejuízo Fiscal | D36: =tab!D36 -> 0.3 | E36: =-IF(AND(E35>0,E34*$D$36<E35),E34*$D$36,E35) -> -180 | F36: =-IF(AND(F35>0,F34*$D$36<F35),F34*$D$36,F35) -> -7680 | G36: =-IF(AND(G35>0,G34*$D$36<G35),G34*$D$36,G35) -> -15180 | H36: =-IF(AND(H35>0,H34*$D$36<H35),H34*$D$36,H35) -> -21960
B37: =tab!B37 -> % | C37: =tab!C37 -> Adicional de Imposto de Renda | D37: =tab!D37 -> 0.1 | E37: =HLOOKUP($E$4,INDIRECT($E$4&"!$E$4:$O$49"),MATCH(C37,INDIRECT($E$4&"!$C$4:$C$49"),0),0) -> 0 | F37: =IF(SUM(F34,F36)>20000*$A$4,(SUM(F34,F36)-20000*$A$4)*$D$37,0) -> 0 | G37: =IF(SUM(G34,G36)>20000*$A$4,(SUM(G34,G36)-20000*$A$4)*$D$37,0) -> 0 | H37: =IF(SUM(H34,H36)>20000*$A$4,(SUM(H34,H36)-20000*$A$4)*$D$37,0) -> 0
B38: =tab!B38 -> % | C38: =tab!C38 -> Imposto de Renda | D38: =tab!D38 -> 0.15 | E38: =SUM(E34,E36)*$D$38 -> 63 | F38: =SUM(F34,F36)*$D$38 -> 2688 | G38: =SUM(G34,G36)*$D$38 -> 5313 | H38: =SUM(H34,H36)*$D$38 -> 8046
B39: =tab!B39 -> % | C39: =tab!C39 -> Contribuição Social | D39: =tab!D39 -> 0.09 | E39: =SUM(E34,E36)*$D$39 -> 37.8 | F39: =SUM(F34,F36)*$D$39 -> 1612.8 | G39: =SUM(G34,G36)*$D$39 -> 3187.8 | H39: =SUM(H34,H36)*$D$39 -> 4827.6
B40: =tab!B40 -> = | C40: =tab!C40 -> Compensações | E40: =SUM(E42:E47) -> -3600 | F40: =SUM(F42:F47) -> -3600 | G40: =SUM(G42:G47) -> -4300.8 | H40: =SUM(H42:H47) -> -8500.8
B41: =tab!B41 -> - | C41: =tab!C41 -> IR Base Negativa Exercícios Anteriores | D41: =LEFT(C41,2) -> IR | E41: =HLOOKUP(E$4,tab!$E$4:$P$49,MATCH($C41,$C$4:$C$49,0),0) -> 0 | F41: =HLOOKUP(F$4,tab!$E$4:$P$49,MATCH($C41,$C$4:$C$49,0),0) -> 0 | G41: =HLOOKUP(G$4,tab!$E$4:$P$49,MATCH($C41,$C$4:$C$49,0),0) -> 0 | H41: =HLOOKUP(H$4,tab!$E$4:$P$49,MATCH($C41,$C$4:$C$49,0),0) -> 0
B42: =tab!B42 -> - | C42: =tab!C42 -> IR s/ Aplicações Financeiras | D42: =LEFT(C42,2) -> IR | E42: =HLOOKUP(E$4,tab!$E$4:$P$49,MATCH($C42,$C$4:$C$49,0),0) -> -100 | F42: =HLOOKUP(F$4,tab!$E$4:$P$49,MATCH($C42,$C$4:$C$49,0),0) -> -100 | G42: =HLOOKUP(G$4,tab!$E$4:$P$49,MATCH($C42,$C$4:$C$49,0),0) -> -100 | H42: =HLOOKUP(H$4,tab!$E$4:$P$49,MATCH($C42,$C$4:$C$49,0),0) -> -100
B43: =tab!B43 -> - | C43: =tab!C43 -> IR Retida s/ Notas Fiscais | D43: =LEFT(C43,2) -> IR | E43: =HLOOKUP(E$4,tab!$E$4:$P$49,MATCH($C43,$C$4:$C$49,0),0) -> -2000 | F43: =HLOOKUP(F$4,tab!$E$4:$P$49,MATCH($C43,$C$4:$C$49,0),0) -> -2000 | G43: =HLOOKUP(G$4,tab!$E$4:$P$49,MATCH($C43,$C$4:$C$49,0),0) -> -2000 | H43: =HLOOKUP(H$4,tab!$E$4:$P$49,MATCH($C43,$C$4:$C$49,0),0) -> -2000
B44: =tab!B44 -> - | C44: =tab!C44 -> IR Pago no Exercício | D44: =LEFT(C44,2) -> IR | E44: =HLOOKUP(E$4,tab!$E$4:$P$49,MATCH($C44,$C$4:$C$49,0),0) -> 0 | F44: =-E48 -> 0 | G44: =-SUM($E$48:F48) -> -588 | H44: =-SUM($E$48:G48) -> -3213
B45: =tab!B45 -> - | C45: =tab!C45 -> CS Base Negativa Exercícios Anteriores | D45: =LEFT(C45,2) -> CS | E45: =HLOOKUP(E$4,tab!$E$4:$P$49,MATCH($C45,$C$4:$C$49,0),0) -> 0 | F45: =HLOOKUP(F$4,tab!$E$4:$P$49,MATCH($C45,$C$4:$C$49,0),0) -> 0 | G45: =HLOOKUP(G$4,tab!$E$4:$P$49,MATCH($C45,$C$4:$C$49,0),0) -> 0 | H45: =HLOOKUP(H$4,tab!$E$4:$P$49,MATCH($C45,$C$4:$C$49,0),0) -> 0
B46: =tab!B46 -> - | C46: =tab!C46 -> CS Retida s/ Notas Fiscais | D46: =LEFT(C46,2) -> CS | E46: =HLOOKUP(E$4,tab!$E$4:$P$49,MATCH($C46,$C$4:$C$49,0),0) -> -1500 | F46: =HLOOKUP(F$4,tab!$E$4:$P$49,MATCH($C46,$C$4:$C$49,0),0) -> -1500 | G46: =HLOOKUP(G$4,tab!$E$4:$P$49,MATCH($C46,$C$4:$C$49,0),0) -> -1500 | H46: =HLOOKUP(H$4,tab!$E$4:$P$49,MATCH($C46,$C$4:$C$49,0),0) -> -1500
B47: =tab!B47 -> - | C47: =tab!C47 -> CS Pago no Exercício | D47: =LEFT(C47,2) -> CS | E47: =HLOOKUP(E$4,tab!$E$4:$P$49,MATCH($C47,$C$4:$C$49,0),0) -> 0 | F47: =-E49 -> 0 | G47: =-SUM($E$49:F49) -> -112.8 | H47: =-SUM($E$49:G49) -> -1687.8
B48: =tab!B48 -> = | C48: =tab!C48 -> Imposto de Renda a Pagar | E48: =IF(SUM(E37,E38,SUMIF($D$41:E47,"IR",E$41:E$47))>0,SUM(E37,E38,SUMIF($D$41:E47,"IR",E$41:E$47)),0) -> 0 | F48: =IF(SUM(F37,F38,SUMIF($D$41:F47,"IR",F$41:F$47))>0,SUM(F37,F38,SUMIF($D$41:F47,"IR",F$41:F$47)),0) -> 588 | G48: =IF(SUM(G37,G38,SUMIF($D$41:G47,"IR",G$41:G$47))>0,SUM(G37,G38,SUMIF($D$41:G47,"IR",G$41:G$47)),0) -> 2625 | H48: =IF(SUM(H37,H38,SUMIF($D$41:H47,"IR",H$41:H$47))>0,SUM(H37,H38,SUMIF($D$41:H47,"IR",H$41:H$47)),0) -> 2733
B49: =tab!B49 -> = | C49: =tab!C49 -> Contribuição Social a Pagar | E49: =IF(SUM(E39,SUMIF($D$41:E47,"CS",E$41:E$47))>0,SUM(E39,SUMIF($D$41:E47,"CS",E$41:E$47)),0) -> 0 | F49: =IF(SUM(F39,SUMIF($D$41:F47,"CS",F$41:F$47))>0,SUM(F39,SUMIF($D$41:F47,"CS",F$41:F$47)),0) -> 112.8 | G49: =IF(SUM(G39,SUMIF($D$41:G47,"CS",G$41:G$47))>0,SUM(G39,SUMIF($D$41:G47,"CS",G$41:G$47)),0) -> 1575 | H49: =IF(SUM(H39,SUMIF($D$41:H47,"CS",H$41:H$47))>0,SUM(H39,SUMIF($D$41:H47,"CS",H$41:H$47)),0) -> 1639.8

Sheet mai
B3: 2018
A4: 5 | B4: # | C4: Parâmetros | D4: % | E4: Jan | F4: Fev | G4: Mar | H4: Abr | I4: Mai | J4: Jun | K4: Jul | L4: Ago | M4: Set | N4: Out | O4: Nov | P4: Dez
A5: 2018 | B5: =tab!B5 -> = | C5: =tab!C5 -> Lucro Acumulado | E5: =HLOOKUP(E$4,tab!$E$4:$P$33,MATCH($C5,$C$4:$C$33,0),0) -> 1000 | F5: =HLOOKUP(F$4,tab!$E$4:$P$33,MATCH($C5,$C$4:$C$33,0),0) -> 26000 | G5: =HLOOKUP(G$4,tab!$E$4:$P$33,MATCH($C5,$C$4:$C$33,0),0) -> 51000 | H5: =HLOOKUP(H$4,tab!$E$4:$P$33,MATCH($C5,$C$4:$C$33,0),0) -> 76000 | I5: =HLOOKUP(I$4,tab!$E$4:$P$33,MATCH($C5,$C$4:$C$33,0),0) -> 101000
A6: 2019 | B6: =tab!B6 -> = | C6: =tab!C6 -> Adições | E6: =SUM(E7:E19) -> 600 | F6: =SUM(F7:F19) -> 600 | G6: =SUM(G7:G19) -> 600 | H6: =SUM(H7:H19) -> 600 | I6: =SUM(I7:I19) -> 600
A7: 2020 | B7: =tab!B7 -> + | C7: =tab!C7 -> Ajustes Devedores de Qualquer Natureza | E7: =HLOOKUP(E$4,tab!$E$4:$P$49,MATCH($C7,$C$4:$C$49,0),0) -> 0 | F7: =HLOOKUP(F$4,tab!$E$4:$P$49,MATCH($C7,$C$4:$C$49,0),0) -> 0 | G7: =HLOOKUP(G$4,tab!$E$4:$P$49,MATCH($C7,$C$4:$C$49,0),0) -> 0 | H7: =HLOOKUP(H$4,tab!$E$4:$P$49,MATCH($C7,$C$4:$C$49,0),0) -> 0 | I7: =HLOOKUP(I$4,tab!$E$4:$P$49,MATCH($C7,$C$4:$C$49,0),0) -> 0
A8: 2021 | B8: =tab!B8 -> + | C8: =tab!C8 -> Despesas de Variação Cambial | E8: =HLOOKUP(E$4,tab!$E$4:$P$49,MATCH($C8,$C$4:$C$49,0),0) -> 0 | F8: =HLOOKUP(F$4,tab!$E$4:$P$49,MATCH($C8,$C$4:$C$49,0),0) -> 0 | G8: =HLOOKUP(G$4,tab!$E$4:$P$49,MATCH($C8,$C$4:$C$49,0),0) -> 0 | H8: =HLOOKUP(H$4,tab!$E$4:$P$49,MATCH($C8,$C$4:$C$49,0),0) -> 0 | I8: =HLOOKUP(I$4,tab!$E$4:$P$49,MATCH($C8,$C$4:$C$49,0),0) -> 0
A9: 2022 | B9: =tab!B9 -> + | C9: =tab!C9 -> Despesas Particulares dos Sócios e Dirigentes; | E9: =HLOOKUP(E$4,tab!$E$4:$P$49,MATCH($C9,$C$4:$C$49,0),0) -> 0 | F9: =HLOOKUP(F$4,tab!$E$4:$P$49,MATCH($C9,$C$4:$C$49,0),0) -> 0 | G9: =HLOOKUP(G$4,tab!$E$4:$P$49,MATCH($C9,$C$4:$C$49,0),0) -> 0 | H9: =HLOOKUP(H$4,tab!$E$4:$P$49,MATCH($C9,$C$4:$C$49,0),0) -> 0 | I9: =HLOOKUP(I$4,tab!$E$4:$P$49,MATCH($C9,$C$4:$C$49,0),0) -> 0
A10: 2023 | B10: =tab!B10 -> + | C10: =tab!C10 -> Doações e Brindes; | E10: =HLOOKUP(E$4,tab!$E$4:$P$49,MATCH($C10,$C$4:$C$49,0),0) -> 100 | F10: =HLOOKUP(F$4,tab!$E$4:$P$49,MATCH($C10,$C$4:$C$49,0),0) -> 100 | G10: =HLOOKUP(G$4,tab!$E$4:$P$49,MATCH($C10,$C$4:$C$49,0),0) -> 100 | H10: =HLOOKUP(H$4,tab!$E$4:$P$49,MATCH($C10,$C$4:$C$49,0),0) -> 100 | I10: =HLOOKUP(I$4,tab!$E$4:$P$49,MATCH($C10,$C$4:$C$49,0),0) -> 100
A11: 2024 | B11: =tab!B11 -> + | C11: =tab!C11 -> Impostos Não Pagos em Discussão Judicial; | E11: =HLOOKUP(E$4,tab!$E$4:$P$49,MATCH($C11,$C$4:$C$49,0),0) -> 0 | F11: =HLOOKUP(F$4,tab!$E$4:$P$49,MATCH($C11,$C$4:$C$49,0),0) -> 0 | G11: =HLOOKUP(G$4,tab!$E$4:$P$49,MATCH($C11,$C$4:$C$49,0),0) -> 0 | H11: =HLOOKUP(H$4,tab!$E$4:$P$49,MATCH($C11,$C$4:$C$49,0),0) -> 0 | I11: =HLOOKUP(I$4,tab!$E$4:$P$49,MATCH($C11,$C$4:$C$49,0),0) -> 0
A12: 2025 | B12: =tab!B12 -> + | C12: =tab!C12 -> Impostos Não Pagos por Iniciativa da Empresa; | E12: =HLOOKUP(E$4,tab!$E$4:$P$49,MATCH($C12,$C$4:$C$49,0),0) -> 0 | F12: =HLOOKUP(F$4,tab!$E$4:$P$49,MATCH($C12,$C$4:$C$49,0),0) -> 0 | G12: =HLOOKUP(G$4,tab!$E$4:$P$49,MATCH($C12,$C$4:$C$49,0),0) -> 0 | H12: =HLOOKUP(H$4,tab!$E$4:$P$49,MATCH($C12,$C$4:$C$49,0),0) -> 0 | I12: =HLOOKUP(I$4,tab!$E$4:$P$49,MATCH($C12,$C$4:$C$49,0),0) -> 0
A13: 2026 | B13: =tab!B13 -> + | C13: =tab!C13 -> Lucro Inflacionário apurado até 31/12/1995; | E13: =HLOOKUP(E$4,tab!$E$4:$P$49,MATCH($C13,$C$4:$C$49,0),0) -> 0 | F13: =HLOOKUP(F$4,tab!$E$4:$P$49,MATCH($C13,$C$4:$C$49,0),0) -> 0 | G13: =HLOOKUP(G$4,tab!$E$4:$P$49,MATCH($C13,$C$4:$C$49,0),0) -> 0 | H13: =HLOOKUP(H$4,tab!$E$4:$P$49,MATCH($C13,$C$4:$C$49,0),0) -> 0 | I13: =HLOOKUP(I$4,tab!$E$4:$P$49,MATCH($C13,$C$4:$C$49,0),0) -> 0
A14: 2027 | B14: =tab!B14 -> + | C14: =tab!C14 -> Multas Contratuais | E14: =HLOOKUP(E$4,tab!$E$4:$P$49,MATCH($C14,$C$4:$C$49,0),0) -> 0 | F14: =HLOOKUP(F$4,tab!$E$4:$P$49,MATCH($C14,$C$4:$C$49,0),0) -> 0 | G14: =HLOOKUP(G$4,tab!$E$4:$P$49,MATCH($C14,$C$4:$C$49,0),0) -> 0 | H14: =HLOOKUP(H$4,tab!$E$4:$P$49,MATCH($C14,$C$4:$C$49,0),0) -> 0 | I14: =HLOOKUP(I$4,tab!$E$4:$P$49,MATCH($C14,$C$4:$C$49,0),0) -> 0
A15: 2028 | B15: =tab!B15 -> + | C15: =tab!C15 -> Multas Punitivas (Transito, Imetro, Ibama, Multas sobre ação fiscal) | E15: =HLOOKUP(E$4,tab!$E$4:$P$49,MATCH($C15,$C$4:$C$49,0),0) -> 500 | F15: =HLOOKUP(F$4,tab!$E$4:$P$49,MATCH($C15,$C$4:$C$49,0),0) -> 500 | G15: =HLOOKUP(G$4,tab!$E$4:$P$49,MATCH($C15,$C$4:$C$49,0),0) -> 500 | H15: =HLOOKUP(H$4,tab!$E$4:$P$49,MATCH($C15,$C$4:$C$49,0),0) -> 500 | I15: =HLOOKUP(I$4,tab!$E$4:$P$49,MATCH($C15,$C$4:$C$49,0),0) -> 500
A16: 2029 | B16: =tab!B16 -> + | C16: =tab!C16 -> Orçamentos, Pedidos e qualquer documento não idôneo; | E16: =HLOOKUP(E$4,tab!$E$4:$P$49,MATCH($C16,$C$4:$C$49,0),0) -> 0 | F16: =HLOOKUP(F$4,tab!$E$4:$P$49,MATCH($C16,$C$4:$C$49,0),0) -> 0 | G16: =HLOOKUP(G$4,tab!$E$4:$P$49,MATCH($C16,$C$4:$C$49,0),0) -> 0 | H16: =HLOOKUP(H$4,tab!$E$4:$P$49,MATCH($C16,$C$4:$C$49,0),0) -> 0 | I16: =HLOOKUP(I$4,tab!$E$4:$P$49,MATCH($C16,$C$4:$C$49,0),0) -> 0
A17: 2030 | B17: =tab!B17 -> + | C17: =tab!C17 -> Provisões Indedutíveis (perdas, frete, propaganda) | E17: =HLOOKUP(E$4,tab!$E$4:$P$49,MATCH($C17,$C$4:$C$49,0),0) -> 0 | F17: =HLOOKUP(F$4,tab!$E$4:$P$49,MATCH($C17,$C$4:$C$49,0),0) -> 0 | G17: =HLOOKUP(G$4,tab!$E$4:$P$49,MATCH($C17,$C$4:$C$49,0),0) -> 0 | H17: =HLOOKUP(H$4,tab!$E$4:$P$49,MATCH($C17,$C$4:$C$49,0),0) -> 0 | I17: =HLOOKUP(I$4,tab!$E$4:$P$49,MATCH($C17,$C$4:$C$49,0),0) -> 0
B18: =tab!B18 -> + | C18: =tab!C18 -> Recibos sem especificação da fonte recebedora; | E18: =HLOOKUP(E$4,tab!$E$4:$P$49,MATCH($C18,$C$4:$C$49,0),0) -> 0 | F18: =HLOOKUP(F$4,tab!$E$4:$P$49,MATCH($C18,$C$4:$C$49,0),0) -> 0 | G18: =HLOOKUP(G$4,tab!$E$4:$P$49,MATCH($C18,$C$4:$C$49,0),0) -> 0 | H18: =HLOOKUP(H$4,tab!$E$4:$P$49,MATCH($C18,$C$4:$C$49,0),0) -> 0 | I18: =HLOOKUP(I$4,tab!$E$4:$P$49,MATCH($C18,$C$4:$C$49,0),0) -> 0
B19: =tab!B19 -> + | C19: =tab!C19 -> Verbas Rescisórias em desacordo com a legislação trabalhista vigente | E19: =HLOOKUP(E$4,tab!$E$4:$P$49,MATCH($C19,$C$4:$C$49,0),0) -> 0 | F19: =HLOOKUP(F$4,tab!$E$4:$P$49,MATCH($C19,$C$4:$C$49,0),0) -> 0 | G19: =HLOOKUP(G$4,tab!$E$4:$P$49,MATCH($C19,$C$4:$C$49,0),0) -> 0 | H19: =HLOOKUP(H$4,tab!$E$4:$P$49,MATCH($C19,$C$4:$C$49,0),0) -> 0 | I19: =HLOOKUP(I$4,tab!$E$4:$P$49,MATCH($C19,$C$4:$C$49,0),0) -> 0
B20: =tab!B20 -> = | C20: =tab!C20 -> Exclusões | E20: =SUM(E21:E33) -> -1000 | F20: =SUM(F21:F33) -> -1000 | G20: =SUM(G21:G33) -> -1000 | H20: =SUM(H21:H33) -> -1000 | I20: =SUM(I21:I33) -> -1000
B21: =tab!B21 -> - | C21: =tab!C21 -> Ajustes credores de qualquer natureza | E21: =HLOOKUP(E$4,tab!$E$4:$P$49,MATCH($C21,$C$4:$C$49,0),0) -> 0 | F21: =HLOOKUP(F$4,tab!$E$4:$P$49,MATCH($C21,$C$4:$C$49,0),0) -> 0 | G21: =HLOOKUP(G$4,tab!$E$4:$P$49,MATCH($C21,$C$4:$C$49,0),0) -> 0 | H21: =HLOOKUP(H$4,tab!$E$4:$P$49,MATCH($C21,$C$4:$C$49,0),0) -> 0 | I21: =HLOOKUP(I$4,tab!$E$4:$P$49,MATCH($C21,$C$4:$C$49,0),0) -> 0
B22: =tab!B22 -> - | C22: =tab!C22 -> Decisão Favorável - Processos Judiciais Tributários | E22: =HLOOKUP(E$4,tab!$E$4:$P$49,MATCH($C22,$C$4:$C$49,0),0) -> 0 | F22: =HLOOKUP(F$4,tab!$E$4:$P$49,MATCH($C22,$C$4:$C$49,0),0) -> 0 | G22: =HLOOKUP(G$4,tab!$E$4:$P$49,MATCH($C22,$C$4:$C$49,0),0) -> 0 | H22: =HLOOKUP(H$4,tab!$E$4:$P$49,MATCH($C22,$C$4:$C$49,0),0) -> 0 | I22: =HLOOKUP(I$4,tab!$E$4:$P$49,MATCH($C22,$C$4:$C$49,0),0) -> 0
B23: =tab!B23 -> - | C23: =tab!C23 -> Despesas de Ágios | E23: =HLOOKUP(E$4,tab!$E$4:$P$49,MATCH($C23,$C$4:$C$49,0),0) -> 0 | F23: =HLOOKUP(F$4,tab!$E$4:$P$49,MATCH($C23,$C$4:$C$49,0),0) -> 0 | G23: =HLOOKUP(G$4,tab!$E$4:$P$49,MATCH($C23,$C$4:$C$49,0),0) -> 0 | H23: =HLOOKUP(H$4,tab!$E$4:$P$49,MATCH($C23,$C$4:$C$49,0),0) -> 0 | I23: =HLOOKUP(I$4,tab!$E$4:$P$49,MATCH($C23,$C$4:$C$49,0),0) -> 0
B24: =tab!B24 -> - | C24: =tab!C24 -> Distribuição de Lucros e Dividendos; | E24: =HLOOKUP(E$4,tab!$E$4:$P$49,MATCH($C24,$C$4:$C$49,0),0) -> 0 | F24: =HLOOKUP(F$4,tab!$E$4:$P$49,MATCH($C24,$C$4:$C$49,0),0) -> 0 | G24: =HLOOKUP(G$4,tab!$E$4:$P$49,MATCH($C24,$C$4:$C$49,0),0) -> 0 | H24: =HLOOKUP(H$4,tab!$E$4:$P$49,MATCH($C24,$C$4:$C$49,0),0) -> 0 | I24: =HLOOKUP(I$4,tab!$E$4:$P$49,MATCH($C24,$C$4:$C$49,0),0) -> 0
B25: =tab!B25 -> - | C25: =tab!C25 -> Dividendos Coligadas e Controladas | E25: =HLOOKUP(E$4,tab!$E$4:$P$49,MATCH($C25,$C$4:$C$49,0),0) -> 0 | F25: =HLOOKUP(F$4,tab!$E$4:$P$49,MATCH($C25,$C$4:$C$49,0),0) -> 0 | G25: =HLOOKUP(G$4,tab!$E$4:$P$49,MATCH($C25,$C$4:$C$49,0),0) -> 0 | H25: =HLOOKUP(H$4,tab!$E$4:$P$49,MATCH($C25,$C$4:$C$49,0),0) -> 0 | I25: =HLOOKUP(I$4,tab!$E$4:$P$49,MATCH($C25,$C$4:$C$49,0),0) -> 0
B26: =tab!B26 -> - | C26: =tab!C26 -> Pagamento de Impostos em Atraso por iniciativa da Empresa | E26: =HLOOKUP(E$4,tab!$E$4:$P$49,MATCH($C26,$C$4:$C$49,0),0) -> -1000 | F26: =HLOOKUP(F$4,tab!$E$4:$P$49,MATCH($C26,$C$4:$C$49,0),0) -> -1000 | G26: =HLOOKUP(G$4,tab!$E$4:$P$49,MATCH($C26,$C$4:$C$49,0),0) -> -1000 | H26: =HLOOKUP(H$4,tab!$E$4:$P$49,MATCH($C26,$C$4:$C$49,0),0) -> -1000 | I26: =HLOOKUP(I$4,tab!$E$4:$P$49,MATCH($C26,$C$4:$C$49,0),0) -> -1000
B27: =tab!B27 -> - | C27: =tab!C27 -> Pagamento de Impostos sobre discussão judicial, | E27: =HLOOKUP(E$4,tab!$E$4:$P$49,MATCH($C27,$C$4:$C$49,0),0) -> 0 | F27: =HLOOKUP(F$4,tab!$E$4:$P$49,MATCH($C27,$C$4:$C$49,0),0) -> 0 | G27: =HLOOKUP(G$4,tab!$E$4:$P$49,MATCH($C27,$C$4:$C$49,0),0) -> 0 | H27: =HLOOKUP(H$4,tab!$E$4:$P$49,MATCH($C27,$C$4:$C$49,0),0) -> 0 | I27: =HLOOKUP(I$4,tab!$E$4:$P$49,MATCH($C27,$C$4:$C$49,0),0) -> 0
B28: =tab!B28 -> - | C28: =tab!C28 -> Receita de Variação Cambial | E28: =HLOOKUP(E$4,tab!$E$4:$P$49,MATCH($C28,$C$4:$C$49,0),0) -> 0 | F28: =HLOOKUP(F$4,tab!$E$4:$P$49,MATCH($C28,$C$4:$C$49,0),0) -> 0 | G28: =HLOOKUP(G$4,tab!$E$4:$P$49,MATCH($C28,$C$4:$C$49,0),0) -> 0 | H28: =HLOOKUP(H$4,tab!$E$4:$P$49,MATCH($C28,$C$4:$C$49,0),0) -> 0 | I28: =HLOOKUP(I$4,tab!$E$4:$P$49,MATCH($C28,$C$4:$C$49,0),0) -> 0
B29: =tab!B29 -> - | C29: =tab!C29 -> Receitas Obtidas com Tributação Exclusiva ou Isenta de IR | E29: =HLOOKUP(E$4,tab!$E$4:$P$49,MATCH($C29,$C$4:$C$49,0),0) -> 0 | F29: =HLOOKUP(F$4,tab!$E$4:$P$49,MATCH($C29,$C$4:$C$49,0),0) -> 0 | G29: =HLOOKUP(G$4,tab!$E$4:$P$49,MATCH($C29,$C$4:$C$49,0),0) -> 0 | H29: =HLOOKUP(H$4,tab!$E$4:$P$49,MATCH($C29,$C$4:$C$49,0),0) -> 0 | I29: =HLOOKUP(I$4,tab!$E$4:$P$49,MATCH($C29,$C$4:$C$49,0),0) -> 0
B30: =tab!B30 -> - | C30: =tab!C30 -> Receitas que poderiam ser diferidas; | E30: =HLOOKUP(E$4,tab!$E$4:$P$49,MATCH($C30,$C$4:$C$49,0),0) -> 0 | F30: =HLOOKUP(F$4,tab!$E$4:$P$49,MATCH($C30,$C$4:$C$49,0),0) -> 0 | G30: =HLOOKUP(G$4,tab!$E$4:$P$49,MATCH($C30,$C$4:$C$49,0),0) -> 0 | H30: =HLOOKUP(H$4,tab!$E$4:$P$49,MATCH($C30,$C$4:$C$49,0),0) -> 0 | I30: =HLOOKUP(I$4,tab!$E$4:$P$49,MATCH($C30,$C$4:$C$49,0),0) -> 0
B31: =tab!B31 -> - | C31: =tab!C31 -> Resultado Positivo de Equivalência Patrimonial | E31: =HLOOKUP(E$4,tab!$E$4:$P$49,MATCH($C31,$C$4:$C$49,0),0) -> 0 | F31: =HLOOKUP(F$4,tab!$E$4:$P$49,MATCH($C31,$C$4:$C$49,0),0) -> 0 | G31: =HLOOKUP(G$4,tab!$E$4:$P$49,MATCH($C31,$C$4:$C$49,0),0) -> 0 | H31: =HLOOKUP(H$4,tab!$E$4:$P$49,MATCH($C31,$C$4:$C$49,0),0) -> 0 | I31: =HLOOKUP(I$4,tab!$E$4:$P$49,MATCH($C31,$C$4:$C$49,0),0) -> 0
B32: =tab!B32 -> - | C32: =tab!C32 -> Reversão de Provisões Indedutíveis | E32: =HLOOKUP(E$4,tab!$E$4:$P$49,MATCH($C32,$C$4:$C$49,0),0) -> 0 | F32: =HLOOKUP(F$4,tab!$E$4:$P$49,MATCH($C32,$C$4:$C$49,0),0) -> 0 | G32: =HLOOKUP(G$4,tab!$E$4:$P$49,MATCH($C32,$C$4:$C$49,0),0) -> 0 | H32: =HLOOKUP(H$4,tab!$E$4:$P$49,MATCH($C32,$C$4:$C$49,0),0) -> 0 | I32: =HLOOKUP(I$4,tab!$E$4:$P$49,MATCH($C32,$C$4:$C$49,0),0) -> 0
B33: =tab!B33 -> - | C33: =tab!C33 -> Vendas Não Expedidas do Período | E33: =HLOOKUP(E$4,tab!$E$4:$P$49,MATCH($C33,$C$4:$C$49,0),0) -> 0 | F33: =HLOOKUP(F$4,tab!$E$4:$P$49,MATCH($C33,$C$4:$C$49,0),0) -> 0 | G33: =HLOOKUP(G$4,tab!$E$4:$P$49,MATCH($C33,$C$4:$C$49,0),0) -> 0 | H33: =HLOOKUP(H$4,tab!$E$4:$P$49,MATCH($C33,$C$4:$C$49,0),0) -> 0 | I33: =HLOOKUP(I$4,tab!$E$4:$P$49,MATCH($C33,$C$4:$C$49,0),0) -> 0
B34: =tab!B34 -> = | C34: =tab!C34 -> Base de Cálculo | E34: =SUM(E5,E6,E20) -> 600 | F34: =SUM(F5,F6,F20) -> 25600 | G34: =SUM(G5,G6,G20) -> 50600 | H34: =SUM(H5,H6,H20) -> 75600 | I34: =SUM(I5,I6,I20) -> 100600
B35: =tab!B35 -> = | C35: =tab!C35 -> Saldo Prejuízo Fiscal | E35: =tab!E35 -> 45000 | F35: =SUM(E35:E36) -> 44820 | G35: =SUM(F35:F36) -> 37140 | H35: =SUM(G35:G36) -> 21960 | I35: =SUM(H35:H36) -> 0
B36: =tab!B36 -> % | C36: =tab!C36 -> Compensação de Prejuízo Fiscal | D36: =tab!D36 -> 0.3 | E36: =-IF(AND(E35>0,E34*$D$36<E35),E34*$D$36,E35) -> -180 | F36: =-IF(AND(F35>0,F34*$D$36<F35),F34*$D$36,F35) -> -7680 | G36: =-IF(AND(G35>0,G34*$D$36<G35),G34*$D$36,G35) -> -15180 | H36: =-IF(AND(H35>0,H34*$D$36<H35),H34*$D$36,H35) -> -21960 | I36: =-IF(AND(I35>0,I34*$D$36<I35),I34*$D$36,I35) -> 0
B37: =tab!B37 -> % | C37: =tab!C37 -> Adicional de Imposto de Renda | D37: =tab!D37 -> 0.1 | E37: =HLOOKUP($E$4,INDIRECT($E$4&"!$E$4:$O$49"),MATCH(C37,INDIRECT($E$4&"!$C$4:$C$49"),0),0) -> 0 | F37: =IF(SUM(F34,F36)>20000*$A$4,(SUM(F34,F36)-20000*$A$4)*$D$37,0) -> 0 | G37: =IF(SUM(G34,G36)>20000*$A$4,(SUM(G34,G36)-20000*$A$4)*$D$37,0) -> 0 | H37: =IF(SUM(H34,H36)>20000*$A$4,(SUM(H34,H36)-20000*$A$4)*$D$37,0) -> 0 | I37: =IF(SUM(I34,I36)>20000*$A$4,(SUM(I34,I36)-20000*$A$4)*$D$37,0) -> 60
B38: =tab!B38 -> % | C38: =tab!C38 -> Imposto de Renda | D38: =tab!D38 -> 0.15 | E38: =SUM(E34,E36)*$D$38 -> 63 | F38: =SUM(F34,F36)*$D$38 -> 2688 | G38: =SUM(G34,G36)*$D$38 -> 5313 | H38: =SUM(H34,H36)*$D$38 -> 8046 | I38: =SUM(I34,I36)*$D$38 -> 15090
B39: =tab!B39 -> % | C39: =tab!C39 -> Contribuição Social | D39: =tab!D39 -> 0.09 | E39: =SUM(E34,E36)*$D$39 -> 37.8 | F39: =SUM(F34,F36)*$D$39 -> 1612.8 | G39: =SUM(G34,G36)*$D$39 -> 3187.8 | H39: =SUM(H34,H36)*$D$39 -> 4827.6 | I39: =SUM(I34,I36)*$D$39 -> 9054
B40: =tab!B40 -> = | C40: =tab!C40 -> Compensações | E40: =SUM(E42:E47) -> -3600 | F40: =SUM(F42:F47) -> -3600 | G40: =SUM(G42:G47) -> -4300.8 | H40: =SUM(H42:H47) -> -8500.8 | I40: =SUM(I42:I47) -> -12873.6
B41: =tab!B41 -> - | C41: =tab!C41 -> IR Base Negativa Exercícios Anteriores | D41: =LEFT(C41,2) -> IR | E41: =HLOOKUP(E$4,tab!$E$4:$P$49,MATCH($C41,$C$4:$C$49,0),0) -> 0 | F41: =HLOOKUP(F$4,tab!$E$4:$P$49,MATCH($C41,$C$4:$C$49,0),0) -> 0 | G41: =HLOOKUP(G$4,tab!$E$4:$P$49,MATCH($C41,$C$4:$C$49,0),0) -> 0 | H41: =HLOOKUP(H$4,tab!$E$4:$P$49,MATCH($C41,$C$4:$C$49,0),0) -> 0 | I41: =HLOOKUP(I$4,tab!$E$4:$P$49,MATCH($C41,$C$4:$C$49,0),0) -> 0
B42: =tab!B42 -> - | C42: =tab!C42 -> IR s/ Aplicações Financeiras | D42: =LEFT(C42,2) -> IR | E42: =HLOOKUP(E$4,tab!$E$4:$P$49,MATCH($C42,$C$4:$C$49,0),0) -> -100 | F42: =HLOOKUP(F$4,tab!$E$4:$P$49,MATCH($C42,$C$4:$C$49,0),0) -> -100 | G42: =HLOOKUP(G$4,tab!$E$4:$P$49,MATCH($C42,$C$4:$C$49,0),0) -> -100 | H42: =HLOOKUP(H$4,tab!$E$4:$P$49,MATCH($C42,$C$4:$C$49,0),0) -> -100 | I42: =HLOOKUP(I$4,tab!$E$4:$P$49,MATCH($C42,$C$4:$C$49,0),0) -> -100
B43: =tab!B43 -> - | C43: =tab!C43 -> IR Retida s/ Notas Fiscais | D43: =LEFT(C43,2) -> IR | E43: =HLOOKUP(E$4,tab!$E$4:$P$49,MATCH($C43,$C$4:$C$49,0),0) -> -2000 | F43: =HLOOKUP(F$4,tab!$E$4:$P$49,MATCH($C43,$C$4:$C$49,0),0) -> -2000 | G43: =HLOOKUP(G$4,tab!$E$4:$P$49,MATCH($C43,$C$4:$C$49,0),0) -> -2000 | H43: =HLOOKUP(H$4,tab!$E$4:$P$49,MATCH($C43,$C$4:$C$49,0),0) -> -2000 | I43: =HLOOKUP(I$4,tab!$E$4:$P$49,MATCH($C43,$C$4:$C$49,0),0) -> -2000
B44: =tab!B44 -> - | C44: =tab!C44 -> IR Pago no Exercício | D44: =LEFT(C44,2) -> IR | E44: =HLOOKUP(E$4,tab!$E$4:$P$49,MATCH($C44,$C$4:$C$49,0),0) -> 0 | F44: =-E48 -> 0 | G44: =-SUM($E$48:F48) -> -588 | H44: =-SUM($E$48:G48) -> -3213 | I44: =-SUM($E$48:H48) -> -5946
B45: =tab!B45 -> - | C45: =tab!C45 -> CS Base Negativa Exercícios Anteriores | D45: =LEFT(C45,2) -> CS | E45: =HLOOKUP(E$4,tab!$E$4:$P$49,MATCH($C45,$C$4:$C$49,0),0) -> 0 | F45: =HLOOKUP(F$4,tab!$E$4:$P$49,MATCH($C45,$C$4:$C$49,0),0) -> 0 | G45: =HLOOKUP(G$4,tab!$E$4:$P$49,MATCH($C45,$C$4:$C$49,0),0) -> 0 | H45: =HLOOKUP(H$4,tab!$E$4:$P$49,MATCH($C45,$C$4:$C$49,0),0) -> 0 | I45: =HLOOKUP(I$4,tab!$E$4:$P$49,MATCH($C45,$C$4:$C$49,0),0) -> 0
B46: =tab!B46 -> - | C46: =tab!C46 -> CS Retida s/ Notas Fiscais | D46: =LEFT(C46,2) -> CS | E46: =HLOOKUP(E$4,tab!$E$4:$P$49,MATCH($C46,$C$4:$C$49,0),0) -> -1500 | F46: =HLOOKUP(F$4,tab!$E$4:$P$49,MATCH($C46,$C$4:$C$49,0),0) -> -1500 | G46: =HLOOKUP(G$4,tab!$E$4:$P$49,MATCH($C46,$C$4:$C$49,0),0) -> -1500 | H46: =HLOOKUP(H$4,tab!$E$4:$P$49,MATCH($C46,$C$4:$C$49,0),0) -> -1500 | I46: =HLOOKUP(I$4,tab!$E$4:$P$49,MATCH($C46,$C$4:$C$49,0),0) -> -1500
B47: =tab!B47 -> - | C47: =tab!C47 -> CS Pago no Exercício | D47: =LEFT(C47,2) -> CS | E47: =HLOOKUP(E$4,tab!$E$4:$P$49,MATCH($C47,$C$4:$C$49,0),0) -> 0 | F47: =-E49 -> 0 | G47: =-SUM($E$49:F49) -> -112.8 | H47: =-SUM($E$49:G49) -> -1687.8 | I47: =-SUM($E$49:H49) -> -3327.6
B48: =tab!B48 -> = | C48: =tab!C48 -> Imposto de Renda a Pagar | E48: =IF(SUM(E37,E38,SUMIF($D$41:E47,"IR",E$41:E$47))>0,SUM(E37,E38,SUMIF($D$41:E47,"IR",E$41:E$47)),0) -> 0 | F48: =IF(SUM(F37,F38,SUMIF($D$41:F47,"IR",F$41:F$47))>0,SUM(F37,F38,SUMIF($D$41:F47,"IR",F$41:F$47)),0) -> 588 | G48: =IF(SUM(G37,G38,SUMIF($D$41:G47,"IR",G$41:G$47))>0,SUM(G37,G38,SUMIF($D$41:G47,"IR",G$41:G$47)),0) -> 2625 | H48: =IF(SUM(H37,H38,SUMIF($D$41:H47,"IR",H$41:H$47))>0,SUM(H37,H38,SUMIF($D$41:H47,"IR",H$41:H$47)),0) -> 2733 | I48: =IF(SUM(I37,I38,SUMIF($D$41:I47,"IR",I$41:I$47))>0,SUM(I37,I38,SUMIF($D$41:I47,"IR",I$41:I$47)),0) -> 7104
B49: =tab!B49 -> = | C49: =tab!C49 -> Contribuição Social a Pagar | E49: =IF(SUM(E39,SUMIF($D$41:E47,"CS",E$41:E$47))>0,SUM(E39,SUMIF($D$41:E47,"CS",E$41:E$47)),0) -> 0 | F49: =IF(SUM(F39,SUMIF($D$41:F47,"CS",F$41:F$47))>0,SUM(F39,SUMIF($D$41:F47,"CS",F$41:F$47)),0) -> 112.8 | G49: =IF(SUM(G39,SUMIF($D$41:G47,"CS",G$41:G$47))>0,SUM(G39,SUMIF($D$41:G47,"CS",G$41:G$47)),0) -> 1575 | H49: =IF(SUM(H39,SUMIF($D$41:H47,"CS",H$41:H$47))>0,SUM(H39,SUMIF($D$41:H47,"CS",H$41:H$47)),0) -> 1639.8 | I49: =IF(SUM(I39,SUMIF($D$41:I47,"CS",I$41:I$47))>0,SUM(I39,SUMIF($D$41:I47,"CS",I$41:I$47)),0) -> 4226.4

Sheet jun
B3: 2018
A4: 6 | B4: # | C4: Parâmetros | D4: % | E4: Jan | F4: Fev | G4: Mar | H4: Abr | I4: Mai | J4: Jun | K4: Jul | L4: Ago | M4: Set | N4: Out | O4: Nov | P4: Dez
A5: 2018 | B5: =tab!B5 -> = | C5: =tab!C5 -> Lucro Acumulado | E5: =HLOOKUP(E$4,tab!$E$4:$P$33,MATCH($C5,$C$4:$C$33,0),0) -> 1000 | F5: =HLOOKUP(F$4,tab!$E$4:$P$33,MATCH($C5,$C$4:$C$33,0),0) -> 26000 | G5: =HLOOKUP(G$4,tab!$E$4:$P$33,MATCH($C5,$C$4:$C$33,0),0) -> 51000 | H5: =HLOOKUP(H$4,tab!$E$4:$P$33,MATCH($C5,$C$4:$C$33,0),0) -> 76000 | I5: =HLOOKUP(I$4,tab!$E$4:$P$33,MATCH($C5,$C$4:$C$33,0),0) -> 101000 | J5: =HLOOKUP(J$4,tab!$E$4:$P$33,MATCH($C5,$C$4:$C$33,0),0) -> 126000
A6: 2019 | B6: =tab!B6 -> = | C6: =tab!C6 -> Adições | E6: =SUM(E7:E19) -> 600 | F6: =SUM(F7:F19) -> 600 | G6: =SUM(G7:G19) -> 600 | H6: =SUM(H7:H19) -> 600 | I6: =SUM(I7:I19) -> 600 | J6: =SUM(J7:J19) -> 600
A7: 2020 | B7: =tab!B7 -> + | C7: =tab!C7 -> Ajustes Devedores de Qualquer Natureza | E7: =HLOOKUP(E$4,tab!$E$4:$P$49,MATCH($C7,$C$4:$C$49,0),0) -> 0 | F7: =HLOOKUP(F$4,tab!$E$4:$P$49,MATCH($C7,$C$4:$C$49,0),0) -> 0 | G7: =HLOOKUP(G$4,tab!$E$4:$P$49,MATCH($C7,$C$4:$C$49,0),0) -> 0 | H7: =HLOOKUP(H$4,tab!$E$4:$P$49,MATCH($C7,$C$4:$C$49,0),0) -> 0 | I7: =HLOOKUP(I$4,tab!$E$4:$P$49,MATCH($C7,$C$4:$C$49,0),0) -> 0 | J7: =HLOOKUP(J$4,tab!$E$4:$P$49,MATCH($C7,$C$4:$C$49,0),0) -> 0
A8: 2021 | B8: =tab!B8 -> + | C8: =tab!C8 -> Despesas de Variação Cambial | E8: =HLOOKUP(E$4,tab!$E$4:$P$49,MATCH($C8,$C$4:$C$49,0),0) -> 0 | F8: =HLOOKUP(F$4,tab!$E$4:$P$49,MATCH($C8,$C$4:$C$49,0),0) -> 0 | G8: =HLOOKUP(G$4,tab!$E$4:$P$49,MATCH($C8,$C$4:$C$49,0),0) -> 0 | H8: =HLOOKUP(H$4,tab!$E$4:$P$49,MATCH($C8,$C$4:$C$49,0),0) -> 0 | I8: =HLOOKUP(I$4,tab!$E$4:$P$49,MATCH($C8,$C$4:$C$49,0),0) -> 0 | J8: =HLOOKUP(J$4,tab!$E$4:$P$49,MATCH($C8,$C$4:$C$49,0),0) -> 0
A9: 2022 | B9: =tab!B9 -> + | C9: =tab!C9 -> Despesas Particulares dos Sócios e Dirigentes; | E9: =HLOOKUP(E$4,tab!$E$4:$P$49,MATCH($C9,$C$4:$C$49,0),0) -> 0 | F9: =HLOOKUP(F$4,tab!$E$4:$P$49,MATCH($C9,$C$4:$C$49,0),0) -> 0 | G9: =HLOOKUP(G$4,tab!$E$4:$P$49,MATCH($C9,$C$4:$C$49,0),0) -> 0 | H9: =HLOOKUP(H$4,tab!$E$4:$P$49,MATCH($C9,$C$4:$C$49,0),0) -> 0 | I9: =HLOOKUP(I$4,tab!$E$4:$P$49,MATCH($C9,$C$4:$C$49,0),0) -> 0 | J9: =HLOOKUP(J$4,tab!$E$4:$P$49,MATCH($C9,$C$4:$C$49,0),0) -> 0
A10: 2023 | B10: =tab!B10 -> + | C10: =tab!C10 -> Doações e Brindes; | E10: =HLOOKUP(E$4,tab!$E$4:$P$49,MATCH($C10,$C$4:$C$49,0),0) -> 100 | F10: =HLOOKUP(F$4,tab!$E$4:$P$49,MATCH($C10,$C$4:$C$49,0),0) -> 100 | G10: =HLOOKUP(G$4,tab!$E$4:$P$49,MATCH($C10,$C$4:$C$49,0),0) -> 100 | H10: =HLOOKUP(H$4,tab!$E$4:$P$49,MATCH($C10,$C$4:$C$49,0),0) -> 100 | I10: =HLOOKUP(I$4,tab!$E$4:$P$49,MATCH($C10,$C$4:$C$49,0),0) -> 100 | J10: =HLOOKUP(J$4,tab!$E$4:$P$49,MATCH($C10,$C$4:$C$49,0),0) -> 100
A11: 2024 | B11: =tab!B11 -> + | C11: =tab!C11 -> Impostos Não Pagos em Discussão Judicial; | E11: =HLOOKUP(E$4,tab!$E$4:$P$49,MATCH($C11,$C$4:$C$49,0),0) -> 0 | F11: =HLOOKUP(F$4,tab!$E$4:$P$49,MATCH($C11,$C$4:$C$49,0),0) -> 0 | G11: =HLOOKUP(G$4,tab!$E$4:$P$49,MATCH($C11,$C$4:$C$49,0),0) -> 0 | H11: =HLOOKUP(H$4,tab!$E$4:$P$49,MATCH($C11,$C$4:$C$49,0),0) -> 0 | I11: =HLOOKUP(I$4,tab!$E$4:$P$49,MATCH($C11,$C$4:$C$49,0),0) -> 0 | J11: =HLOOKUP(J$4,tab!$E$4:$P$49,MATCH($C11,$C$4:$C$49,0),0) -> 0
A12: 2025 | B12: =tab!B12 -> + | C12: =tab!C12 -> Impostos Não Pagos por Iniciativa da Empresa; | E12: =HLOOKUP(E$4,tab!$E$4:$P$49,MATCH($C12,$C$4:$C$49,0),0) -> 0 | F12: =HLOOKUP(F$4,tab!$E$4:$P$49,MATCH($C12,$C$4:$C$49,0),0) -> 0 | G12: =HLOOKUP(G$4,tab!$E$4:$P$49,MATCH($C12,$C$4:$C$49,0),0) -> 0 | H12: =HLOOKUP(H$4,tab!$E$4:$P$49,MATCH($C12,$C$4:$C$49,0),0) -> 0 | I12: =HLOOKUP(I$4,tab!$E$4:$P$49,MATCH($C12,$C$4:$C$49,0),0) -> 0 | J12: =HLOOKUP(J$4,tab!$E$4:$P$49,MATCH($C12,$C$4:$C$49,0),0) -> 0
A13: 2026 | B13: =tab!B13 -> + | C13: =tab!C13 -> Lucro Inflacionário apurado até 31/12/1995; | E13: =HLOOKUP(E$4,tab!$E$4:$P$49,MATCH($C13,$C$4:$C$49,0),0) -> 0 | F13: =HLOOKUP(F$4,tab!$E$4:$P$49,MATCH($C13,$C$4:$C$49,0),0) -> 0 | G13: =HLOOKUP(G$4,tab!$E$4:$P$49,MATCH($C13,$C$4:$C$49,0),0) -> 0 | H13: =HLOOKUP(H$4,tab!$E$4:$P$49,MATCH($C13,$C$4:$C$49,0),0) -> 0 | I13: =HLOOKUP(I$4,tab!$E$4:$P$49,MATCH($C13,$C$4:$C$49,0),0) -> 0 | J13: =HLOOKUP(J$4,tab!$E$4:$P$49,MATCH($C13,$C$4:$C$49,0),0) -> 0
A14: 2027 | B14: =tab!B14 -> + | C14: =tab!C14 -> Multas Contratuais | E14: =HLOOKUP(E$4,tab!$E$4:$P$49,MATCH($C14,$C$4:$C$49,0),0) -> 0 | F14: =HLOOKUP(F$4,tab!$E$4:$P$49,MATCH($C14,$C$4:$C$49,0),0) -> 0 | G14: =HLOOKUP(G$4,tab!$E$4:$P$49,MATCH($C14,$C$4:$C$49,0),0) -> 0 | H14: =HLOOKUP(H$4,tab!$E$4:$P$49,MATCH($C14,$C$4:$C$49,0),0) -> 0 | I14: =HLOOKUP(I$4,tab!$E$4:$P$49,MATCH($C14,$C$4:$C$49,0),0) -> 0 | J14: =HLOOKUP(J$4,tab!$E$4:$P$49,MATCH($C14,$C$4:$C$49,0),0) -> 0
A15: 2028 | B15: =tab!B15 -> + | C15: =tab!C15 -> Multas Punitivas (Transito, Imetro, Ibama, Multas sobre ação fiscal) | E15: =HLOOKUP(E$4,tab!$E$4:$P$49,MATCH($C15,$C$4:$C$49,0),0) -> 500 | F15: =HLOOKUP(F$4,tab!$E$4:$P$49,MATCH($C15,$C$4:$C$49,0),0) -> 500 | G15: =HLOOKUP(G$4,tab!$E$4:$P$49,MATCH($C15,$C$4:$C$49,0),0) -> 500 | H15: =HLOOKUP(H$4,tab!$E$4:$P$49,MATCH($C15,$C$4:$C$49,0),0) -> 500 | I15: =HLOOKUP(I$4,tab!$E$4:$P$49,MATCH($C15,$C$4:$C$49,0),0) -> 500 | J15: =HLOOKUP(J$4,tab!$E$4:$P$49,MATCH($C15,$C$4:$C$49,0),0) -> 500
A16: 2029 | B16: =tab!B16 -> + | C16: =tab!C16 -> Orçamentos, Pedidos e qualquer documento não idôneo; | E16: =HLOOKUP(E$4,tab!$E$4:$P$49,MATCH($C16,$C$4:$C$49,0),0) -> 0 | F16: =HLOOKUP(F$4,tab!$E$4:$P$49,MATCH($C16,$C$4:$C$49,0),0) -> 0 | G16: =HLOOKUP(G$4,tab!$E$4:$P$49,MATCH($C16,$C$4:$C$49,0),0) -> 0 | H16: =HLOOKUP(H$4,tab!$E$4:$P$49,MATCH($C16,$C$4:$C$49,0),0) -> 0 | I16: =HLOOKUP(I$4,tab!$E$4:$P$49,MATCH($C16,$C$4:$C$49,0),0) -> 0 | J16: =HLOOKUP(J$4,tab!$E$4:$P$49,MATCH($C16,$C$4:$C$49,0),0) -> 0
A17: 2030 | B17: =tab!B17 -> + | C17: =tab!C17 -> Provisões Indedutíveis (perdas, frete, propaganda) | E17: =HLOOKUP(E$4,tab!$E$4:$P$49,MATCH($C17,$C$4:$C$49,0),0) -> 0 | F17: =HLOOKUP(F$4,tab!$E$4:$P$49,MATCH($C17,$C$4:$C$49,0),0) -> 0 | G17: =HLOOKUP(G$4,tab!$E$4:$P$49,MATCH($C17,$C$4:$C$49,0),0) -> 0 | H17: =HLOOKUP(H$4,tab!$E$4:$P$49,MATCH($C17,$C$4:$C$49,0),0) -> 0 | I17: =HLOOKUP(I$4,tab!$E$4:$P$49,MATCH($C17,$C$4:$C$49,0),0) -> 0 | J17: =HLOOKUP(J$4,tab!$E$4:$P$49,MATCH($C17,$C$4:$C$49,0),0) -> 0
B18: =tab!B18 -> + | C18: =tab!C18 -> Recibos sem especificação da fonte recebedora; | E18: =HLOOKUP(E$4,tab!$E$4:$P$49,MATCH($C18,$C$4:$C$49,0),0) -> 0 | F18: =HLOOKUP(F$4,tab!$E$4:$P$49,MATCH($C18,$C$4:$C$49,0),0) -> 0 | G18: =HLOOKUP(G$4,tab!$E$4:$P$49,MATCH($C18,$C$4:$C$49,0),0) -> 0 | H18: =HLOOKUP(H$4,tab!$E$4:$P$49,MATCH($C18,$C$4:$C$49,0),0) -> 0 | I18: =HLOOKUP(I$4,tab!$E$4:$P$49,MATCH($C18,$C$4:$C$49,0),0) -> 0 | J18: =HLOOKUP(J$4,tab!$E$4:$P$49,MATCH($C18,$C$4:$C$49,0),0) -> 0
B19: =tab!B19 -> + | C19: =tab!C19 -> Verbas Rescisórias em desacordo com a legislação trabalhista vigente | E19: =HLOOKUP(E$4,tab!$E$4:$P$49,MATCH($C19,$C$4:$C$49,0),0) -> 0 | F19: =HLOOKUP(F$4,tab!$E$4:$P$49,MATCH($C19,$C$4:$C$49,0),0) -> 0 | G19: =HLOOKUP(G$4,tab!$E$4:$P$49,MATCH($C19,$C$4:$C$49,0),0) -> 0 | H19: =HLOOKUP(H$4,tab!$E$4:$P$49,MATCH($C19,$C$4:$C$49,0),0) -> 0 | I19: =HLOOKUP(I$4,tab!$E$4:$P$49,MATCH($C19,$C$4:$C$49,0),0) -> 0 | J19: =HLOOKUP(J$4,tab!$E$4:$P$49,MATCH($C19,$C$4:$C$49,0),0) -> 0
B20: =tab!B20 -> = | C20: =tab!C20 -> Exclusões | E20: =SUM(E21:E33) -> -1000 | F20: =SUM(F21:F33) -> -1000 | G20: =SUM(G21:G33) -> -1000 | H20: =SUM(H21:H33) -> -1000 | I20: =SUM(I21:I33) -> -1000 | J20: =SUM(J21:J33) -> -1000
B21: =tab!B21 -> - | C21: =tab!C21 -> Ajustes credores de qualquer natureza | E21: =HLOOKUP(E$4,tab!$E$4:$P$49,MATCH($C21,$C$4:$C$49,0),0) -> 0 | F21: =HLOOKUP(F$4,tab!$E$4:$P$49,MATCH($C21,$C$4:$C$49,0),0) -> 0 | G21: =HLOOKUP(G$4,tab!$E$4:$P$49,MATCH($C21,$C$4:$C$49,0),0) -> 0 | H21: =HLOOKUP(H$4,tab!$E$4:$P$49,MATCH($C21,$C$4:$C$49,0),0) -> 0 | I21: =HLOOKUP(I$4,tab!$E$4:$P$49,MATCH($C21,$C$4:$C$49,0),0) -> 0 | J21: =HLOOKUP(J$4,tab!$E$4:$P$49,MATCH($C21,$C$4:$C$49,0),0) -> 0
B22: =tab!B22 -> - | C22: =tab!C22 -> Decisão Favorável - Processos Judiciais Tributários | E22: =HLOOKUP(E$4,tab!$E$4:$P$49,MATCH($C22,$C$4:$C$49,0),0) -> 0 | F22: =HLOOKUP(F$4,tab!$E$4:$P$49,MATCH($C22,$C$4:$C$49,0),0) -> 0 | G22: =HLOOKUP(G$4,tab!$E$4:$P$49,MATCH($C22,$C$4:$C$49,0),0) -> 0 | H22: =HLOOKUP(H$4,tab!$E$4:$P$49,MATCH($C22,$C$4:$C$49,0),0) -> 0 | I22: =HLOOKUP(I$4,tab!$E$4:$P$49,MATCH($C22,$C$4:$C$49,0),0) -> 0 | J22: =HLOOKUP(J$4,tab!$E$4:$P$49,MATCH($C22,$C$4:$C$49,0),0) -> 0
B23: =tab!B23 -> - | C23: =tab!C23 -> Despesas de Ágios | E23: =HLOOKUP(E$4,tab!$E$4:$P$49,MATCH($C23,$C$4:$C$49,0),0) -> 0 | F23: =HLOOKUP(F$4,tab!$E$4:$P$49,MATCH($C23,$C$4:$C$49,0),0) -> 0 | G23: =HLOOKUP(G$4,tab!$E$4:$P$49,MATCH($C23,$C$4:$C$49,0),0) -> 0 | H23: =HLOOKUP(H$4,tab!$E$4:$P$49,MATCH($C23,$C$4:$C$49,0),0) -> 0 | I23: =HLOOKUP(I$4,tab!$E$4:$P$49,MATCH($C23,$C$4:$C$49,0),0) -> 0 | J23: =HLOOKUP(J$4,tab!$E$4:$P$49,MATCH($C23,$C$4:$C$49,0),0) -> 0
B24: =tab!B24 -> - | C24: =tab!C24 -> Distribuição de Lucros e Dividendos; | E24: =HLOOKUP(E$4,tab!$E$4:$P$49,MATCH($C24,$C$4:$C$49,0),0) -> 0 | F24: =HLOOKUP(F$4,tab!$E$4:$P$49,MATCH($C24,$C$4:$C$49,0),0) -> 0 | G24: =HLOOKUP(G$4,tab!$E$4:$P$49,MATCH($C24,$C$4:$C$49,0),0) -> 0 | H24: =HLOOKUP(H$4,tab!$E$4:$P$49,MATCH($C24,$C$4:$C$49,0),0) -> 0 | I24: =HLOOKUP(I$4,tab!$E$4:$P$49,MATCH($C24,$C$4:$C$49,0),0) -> 0 | J24: =HLOOKUP(J$4,tab!$E$4:$P$49,MATCH($C24,$C$4:$C$49,0),0) -> 0
B25: =tab!B25 -> - | C25: =tab!C25 -> Dividendos Coligadas e Controladas | E25: =HLOOKUP(E$4,tab!$E$4:$P$49,MATCH($C25,$C$4:$C$49,0),0) -> 0 | F25: =HLOOKUP(F$4,tab!$E$4:$P$49,MATCH($C25,$C$4:$C$49,0),0) -> 0 | G25: =HLOOKUP(G$4,tab!$E$4:$P$49,MATCH($C25,$C$4:$C$49,0),0) -> 0 | H25: =HLOOKUP(H$4,tab!$E$4:$P$49,MATCH($C25,$C$4:$C$49,0),0) -> 0 | I25: =HLOOKUP(I$4,tab!$E$4:$P$49,MATCH($C25,$C$4:$C$49,0),0) -> 0 | J25: =HLOOKUP(J$4,tab!$E$4:$P$49,MATCH($C25,$C$4:$C$49,0),0) -> 0
B26: =tab!B26 -> - | C26: =tab!C26 -> Pagamento de Impostos em Atraso por iniciativa da Empresa | E26: =HLOOKUP(E$4,tab!$E$4:$P$49,MATCH($C26,$C$4:$C$49,0),0) -> -1000 | F26: =HLOOKUP(F$4,tab!$E$4:$P$49,MATCH($C26,$C$4:$C$49,0),0) -> -1000 | G26: =HLOOKUP(G$4,tab!$E$4:$P$49,MATCH($C26,$C$4:$C$49,0),0) -> -1000 | H26: =HLOOKUP(H$4,tab!$E$4:$P$49,MATCH($C26,$C$4:$C$49,0),0) -> -1000 | I26: =HLOOKUP(I$4,tab!$E$4:$P$49,MATCH($C26,$C$4:$C$49,0),0) -> -1000 | J26: =HLOOKUP(J$4,tab!$E$4:$P$49,MATCH($C26,$C$4:$C$49,0),0) -> -1000
B27: =tab!B27 -> - | C27: =tab!C27 -> Pagamento de Impostos sobre discussão judicial, | E27: =HLOOKUP(E$4,tab!$E$4:$P$49,MATCH($C27,$C$4:$C$49,0),0) -> 0 | F27: =HLOOKUP(F$4,tab!$E$4:$P$49,MATCH($C27,$C$4:$C$49,0),0) -> 0 | G27: =HLOOKUP(G$4,tab!$E$4:$P$49,MATCH($C27,$C$4:$C$49,0),0) -> 0 | H27: =HLOOKUP(H$4,tab!$E$4:$P$49,MATCH($C27,$C$4:$C$49,0),0) -> 0 | I27: =HLOOKUP(I$4,tab!$E$4:$P$49,MATCH($C27,$C$4:$C$49,0),0) -> 0 | J27: =HLOOKUP(J$4,tab!$E$4:$P$49,MATCH($C27,$C$4:$C$49,0),0) -> 0
B28: =tab!B28 -> - | C28: =tab!C28 -> Receita de Variação Cambial | E28: =HLOOKUP(E$4,tab!$E$4:$P$49,MATCH($C28,$C$4:$C$49,0),0) -> 0 | F28: =HLOOKUP(F$4,tab!$E$4:$P$49,MATCH($C28,$C$4:$C$49,0),0) -> 0 | G28: =HLOOKUP(G$4,tab!$E$4:$P$49,MATCH($C28,$C$4:$C$49,0),0) -> 0 | H28: =HLOOKUP(H$4,tab!$E$4:$P$49,MATCH($C28,$C$4:$C$49,0),0) -> 0 | I28: =HLOOKUP(I$4,tab!$E$4:$P$49,MATCH($C28,$C$4:$C$49,0),0) -> 0 | J28: =HLOOKUP(J$4,tab!$E$4:$P$49,MATCH($C28,$C$4:$C$49,0),0) -> 0
B29: =tab!B29 -> - | C29: =tab!C29 -> Receitas Obtidas com Tributação Exclusiva ou Isenta de IR | E29: =HLOOKUP(E$4,tab!$E$4:$P$49,MATCH($C29,$C$4:$C$49,0),0) -> 0 | F29: =HLOOKUP(F$4,tab!$E$4:$P$49,MATCH($C29,$C$4:$C$49,0),0) -> 0 | G29: =HLOOKUP(G$4,tab!$E$4:$P$49,MATCH($C29,$C$4:$C$49,0),0) -> 0 | H29: =HLOOKUP(H$4,tab!$E$4:$P$49,MATCH($C29,$C$4:$C$49,0),0) -> 0 | I29: =HLOOKUP(I$4,tab!$E$4:$P$49,MATCH($C29,$C$4:$C$49,0),0) -> 0 | J29: =HLOOKUP(J$4,tab!$E$4:$P$49,MATCH($C29,$C$4:$C$49,0),0) -> 0
B30: =tab!B30 -> - | C30: =tab!C30 -> Receitas que poderiam ser diferidas; | E30: =HLOOKUP(E$4,tab!$E$4:$P$49,MATCH($C30,$C$4:$C$49,0),0) -> 0 | F30: =HLOOKUP(F$4,tab!$E$4:$P$49,MATCH($C30,$C$4:$C$49,0),0) -> 0 | G30: =HLOOKUP(G$4,tab!$E$4:$P$49,MATCH($C30,$C$4:$C$49,0),0) -> 0 | H30: =HLOOKUP(H$4,tab!$E$4:$P$49,MATCH($C30,$C$4:$C$49,0),0) -> 0 | I30: =HLOOKUP(I$4,tab!$E$4:$P$49,MATCH($C30,$C$4:$C$49,0),0) -> 0 | J30: =HLOOKUP(J$4,tab!$E$4:$P$49,MATCH($C30,$C$4:$C$49,0),0) -> 0
B31: =tab!B31 -> - | C31: =tab!C31 -> Resultado Positivo de Equivalência Patrimonial | E31: =HLOOKUP(E$4,tab!$E$4:$P$49,MATCH($C31,$C$4:$C$49,0),0) -> 0 | F31: =HLOOKUP(F$4,tab!$E$4:$P$49,MATCH($C31,$C$4:$C$49,0),0) -> 0 | G31: =HLOOKUP(G$4,tab!$E$4:$P$49,MATCH($C31,$C$4:$C$49,0),0) -> 0 | H31: =HLOOKUP(H$4,tab!$E$4:$P$49,MATCH($C31,$C$4:$C$49,0),0) -> 0 | I31: =HLOOKUP(I$4,tab!$E$4:$P$49,MATCH($C31,$C$4:$C$49,0),0) -> 0 | J31: =HLOOKUP(J$4,tab!$E$4:$P$49,MATCH($C31,$C$4:$C$49,0),0) -> 0
B32: =tab!B32 -> - | C32: =tab!C32 -> Reversão de Provisões Indedutíveis | E32: =HLOOKUP(E$4,tab!$E$4:$P$49,MATCH($C32,$C$4:$C$49,0),0) -> 0 | F32: =HLOOKUP(F$4,tab!$E$4:$P$49,MATCH($C32,$C$4:$C$49,0),0) -> 0 | G32: =HLOOKUP(G$4,tab!$E$4:$P$49,MATCH($C32,$C$4:$C$49,0),0) -> 0 | H32: =HLOOKUP(H$4,tab!$E$4:$P$49,MATCH($C32,$C$4:$C$49,0),0) -> 0 | I32: =HLOOKUP(I$4,tab!$E$4:$P$49,MATCH($C32,$C$4:$C$49,0),0) -> 0 | J32: =HLOOKUP(J$4,tab!$E$4:$P$49,MATCH($C32,$C$4:$C$49,0),0) -> 0
B33: =tab!B33 -> - | C33: =tab!C33 -> Vendas Não Expedidas do Período | E33: =HLOOKUP(E$4,tab!$E$4:$P$49,MATCH($C33,$C$4:$C$49,0),0) -> 0 | F33: =HLOOKUP(F$4,tab!$E$4:$P$49,MATCH($C33,$C$4:$C$49,0),0) -> 0 | G33: =HLOOKUP(G$4,tab!$E$4:$P$49,MATCH($C33,$C$4:$C$49,0),0) -> 0 | H33: =HLOOKUP(H$4,tab!$E$4:$P$49,MATCH($C33,$C$4:$C$49,0),0) -> 0 | I33: =HLOOKUP(I$4,tab!$E$4:$P$49,MATCH($C33,$C$4:$C$49,0),0) -> 0 | J33: =HLOOKUP(J$4,tab!$E$4:$P$49,MATCH($C33,$C$4:$C$49,0),0) -> 0
B34: =tab!B34 -> = | C34: =tab!C34 -> Base de Cálculo | E34: =SUM(E5,E6,E20) -> 600 | F34: =SUM(F5,F6,F20) -> 25600 | G34: =SUM(G5,G6,G20) -> 50600 | H34: =SUM(H5,H6,H20) -> 75600 | I34: =SUM(I5,I6,I20) -> 100600 | J34: =SUM(J5,J6,J20) -> 125600
B35: =tab!B35 -> = | C35: =tab!C35 -> Saldo Prejuízo Fiscal | E35: =tab!E35 -> 45000 | F35: =SUM(E35:E36) -> 44820 | G35: =SUM(F35:F36) -> 37140 | H35: =SUM(G35:G36) -> 21960 | I35: =SUM(H35:H36) -> 0 | J35: =SUM(I35:I36) -> 0
B36: =tab!B36 -> % | C36: =tab!C36 -> Compensação de Prejuízo Fiscal | D36: =tab!D36 -> 0.3 | E36: =-IF(AND(E35>0,E34*$D$36<E35),E34*$D$36,E35) -> -180 | F36: =-IF(AND(F35>0,F34*$D$36<F35),F34*$D$36,F35) -> -7680 | G36: =-IF(AND(G35>0,G34*$D$36<G35),G34*$D$36,G35) -> -15180 | H36: =-IF(AND(H35>0,H34*$D$36<H35),H34*$D$36,H35) -> -21960 | I36: =-IF(AND(I35>0,I34*$D$36<I35),I34*$D$36,I35) -> 0 | J36: =-IF(AND(J35>0,J34*$D$36<J35),J34*$D$36,J35) -> 0
B37: =tab!B37 -> % | C37: =tab!C37 -> Adicional de Imposto de Renda | D37: =tab!D37 -> 0.1 | E37: =HLOOKUP($E$4,INDIRECT($E$4&"!$E$4:$O$49"),MATCH(C37,INDIRECT($E$4&"!$C$4:$C$49"),0),0) -> 0 | F37: =IF(SUM(F34,F36)>20000*$A$4,(SUM(F34,F36)-20000*$A$4)*$D$37,0) -> 0 | G37: =IF(SUM(G34,G36)>20000*$A$4,(SUM(G34,G36)-20000*$A$4)*$D$37,0) -> 0 | H37: =IF(SUM(H34,H36)>20000*$A$4,(SUM(H34,H36)-20000*$A$4)*$D$37,0) -> 0 | I37: =IF(SUM(I34,I36)>20000*$A$4,(SUM(I34,I36)-20000*$A$4)*$D$37,0) -> 0 | J37: =IF(SUM(J34,J36)>20000*$A$4,(SUM(J34,J36)-20000*$A$4)*$D$37,0) -> 560
B38: =tab!B38 -> % | C38: =tab!C38 -> Imposto de Renda | D38: =tab!D38 -> 0.15 | E38: =SUM(E34,E36)*$D$38 -> 63 | F38: =SUM(F34,F36)*$D$38 -> 2688 | G38: =SUM(G34,G36)*$D$38 -> 5313 | H38: =SUM(H34,H36)*$D$38 -> 8046 | I38: =SUM(I34,I36)*$D$38 -> 15090 | J38: =SUM(J34,J36)*$D$38 -> 18840
B39: =tab!B39 -> % | C39: =tab!C39 -> Contribuição Social | D39: =tab!D39 -> 0.09 | E39: =SUM(E34,E36)*$D$39 -> 37.8 | F39: =SUM(F34,F36)*$D$39 -> 1612.8 | G39: =SUM(G34,G36)*$D$39 -> 3187.8 | H39: =SUM(H34,H36)*$D$39 -> 4827.6 | I39: =SUM(I34,I36)*$D$39 -> 9054 | J39: =SUM(J34,J36)*$D$39 -> 11304
B40: =tab!B40 -> = | C40: =tab!C40 -> Compensações | E40: =SUM(E42:E47) -> -3600 | F40: =SUM(F42:F47) -> -3600 | G40: =SUM(G42:G47) -> -4300.8 | H40: =SUM(H42:H47) -> -8500.8 | I40: =SUM(I42:I47) -> -12873.6 | J40: =SUM(J42:J47) -> -24144
B41: =tab!B41 -> - | C41: =tab!C41 -> IR Base Negativa Exercícios Anteriores | D41: =LEFT(C41,2) -> IR | E41: =HLOOKUP(E$4,tab!$E$4:$P$49,MATCH($C41,$C$4:$C$49,0),0) -> 0 | F41: =HLOOKUP(F$4,tab!$E$4:$P$49,MATCH($C41,$C$4:$C$49,0),0) -> 0 | G41: =HLOOKUP(G$4,tab!$E$4:$P$49,MATCH($C41,$C$4:$C$49,0),0) -> 0 | H41: =HLOOKUP(H$4,tab!$E$4:$P$49,MATCH($C41,$C$4:$C$49,0),0) -> 0 | I41: =HLOOKUP(I$4,tab!$E$4:$P$49,MATCH($C41,$C$4:$C$49,0),0) -> 0 | J41: =HLOOKUP(J$4,tab!$E$4:$P$49,MATCH($C41,$C$4:$C$49,0),0) -> 0
B42: =tab!B42 -> - | C42: =tab!C42 -> IR s/ Aplicações Financeiras | D42: =LEFT(C42,2) -> IR | E42: =HLOOKUP(E$4,tab!$E$4:$P$49,MATCH($C42,$C$4:$C$49,0),0) -> -100 | F42: =HLOOKUP(F$4,tab!$E$4:$P$49,MATCH($C42,$C$4:$C$49,0),0) -> -100 | G42: =HLOOKUP(G$4,tab!$E$4:$P$49,MATCH($C42,$C$4:$C$49,0),0) -> -100 | H42: =HLOOKUP(H$4,tab!$E$4:$P$49,MATCH($C42,$C$4:$C$49,0),0) -> -100 | I42: =HLOOKUP(I$4,tab!$E$4:$P$49,MATCH($C42,$C$4:$C$49,0),0) -> -100 | J42: =HLOOKUP(J$4,tab!$E$4:$P$49,MATCH($C42,$C$4:$C$49,0),0) -> -100
B43: =tab!B43 -> - | C43: =tab!C43 -> IR Retida s/ Notas Fiscais | D43: =LEFT(C43,2) -> IR | E43: =HLOOKUP(E$4,tab!$E$4:$P$49,MATCH($C43,$C$4:$C$49,0),0) -> -2000 | F43: =HLOOKUP(F$4,tab!$E$4:$P$49,MATCH($C43,$C$4:$C$49,0),0) -> -2000 | G43: =HLOOKUP(G$4,tab!$E$4:$P$49,MATCH($C43,$C$4:$C$49,0),0) -> -2000 | H43: =HLOOKUP(H$4,tab!$E$4:$P$49,MATCH($C43,$C$4:$C$49,0),0) -> -2000 | I43: =HLOOKUP(I$4,tab!$E$4:$P$49,MATCH($C43,$C$4:$C$49,0),0) -> -2000 | J43: =HLOOKUP(J$4,tab!$E$4:$P$49,MATCH($C43,$C$4:$C$49,0),0) -> -2000
B44: =tab!B44 -> - | C44: =tab!C44 -> IR Pago no Exercício | D44: =LEFT(C44,2) -> IR | E44: =HLOOKUP(E$4,tab!$E$4:$P$49,MATCH($C44,$C$4:$C$49,0),0) -> 0 | F44: =-E48 -> 0 | G44: =-SUM($E$48:F48) -> -588 | H44: =-SUM($E$48:G48) -> -3213 | I44: =-SUM($E$48:H48) -> -5946 | J44: =-SUM($E$48:I48) -> -12990
B45: =tab!B45 -> - | C45: =tab!C45 -> CS Base Negativa Exercícios Anteriores | D45: =LEFT(C45,2) -> CS | E45: =HLOOKUP(E$4,tab!$E$4:$P$49,MATCH($C45,$C$4:$C$49,0),0) -> 0 | F45: =HLOOKUP(F$4,tab!$E$4:$P$49,MATCH($C45,$C$4:$C$49,0),0) -> 0 | G45: =HLOOKUP(G$4,tab!$E$4:$P$49,MATCH($C45,$C$4:$C$49,0),0) -> 0 | H45: =HLOOKUP(H$4,tab!$E$4:$P$49,MATCH($C45,$C$4:$C$49,0),0) -> 0 | I45: =HLOOKUP(I$4,tab!$E$4:$P$49,MATCH($C45,$C$4:$C$49,0),0) -> 0 | J45: =HLOOKUP(J$4,tab!$E$4:$P$49,MATCH($C45,$C$4:$C$49,0),0) -> 0
B46: =tab!B46 -> - | C46: =tab!C46 -> CS Retida s/ Notas Fiscais | D46: =LEFT(C46,2) -> CS | E46: =HLOOKUP(E$4,tab!$E$4:$P$49,MATCH($C46,$C$4:$C$49,0),0) -> -1500 | F46: =HLOOKUP(F$4,tab!$E$4:$P$49,MATCH($C46,$C$4:$C$49,0),0) -> -1500 | G46: =HLOOKUP(G$4,tab!$E$4:$P$49,MATCH($C46,$C$4:$C$49,0),0) -> -1500 | H46: =HLOOKUP(H$4,tab!$E$4:$P$49,MATCH($C46,$C$4:$C$49,0),0) -> -1500 | I46: =HLOOKUP(I$4,tab!$E$4:$P$49,MATCH($C46,$C$4:$C$49,0),0) -> -1500 | J46: =HLOOKUP(J$4,tab!$E$4:$P$49,MATCH($C46,$C$4:$C$49,0),0) -> -1500
B47: =tab!B47 -> - | C47: =tab!C47 -> CS Pago no Exercício | D47: =LEFT(C47,2) -> CS | E47: =HLOOKUP(E$4,tab!$E$4:$P$49,MATCH($C47,$C$4:$C$49,0),0) -> 0 | F47: =-E49 -> 0 | G47: =-SUM($E$49:F49) -> -112.8 | H47: =-SUM($E$49:G49) -> -1687.8 | I47: =-SUM($E$49:H49) -> -3327.6 | J47: =-SUM($E$49:I49) -> -7554
B48: =tab!B48 -> = | C48: =tab!C48 -> Imposto de Renda a Pagar | E48: =IF(SUM(E37,E38,SUMIF($D$41:E47,"IR",E$41:E$47))>0,SUM(E37,E38,SUMIF($D$41:E47,"IR",E$41:E$47)),0) -> 0 | F48: =IF(SUM(F37,F38,SUMIF($D$41:F47,"IR",F$41:F$47))>0,SUM(F37,F38,SUMIF($D$41:F47,"IR",F$41:F$47)),0) -> 588 | G48: =IF(SUM(G37,G38,SUMIF($D$41:G47,"IR",G$41:G$47))>0,SUM(G37,G38,SUMIF($D$41:G47,"IR",G$41:G$47)),0) -> 2625 | H48: =IF(SUM(H37,H38,SUMIF($D$41:H47,"IR",H$41:H$47))>0,SUM(H37,H38,SUMIF($D$41:H47,"IR",H$41:H$47)),0) -> 2733 | I48: =IF(SUM(I37,I38,SUMIF($D$41:I47,"IR",I$41:I$47))>0,SUM(I37,I38,SUMIF($D$41:I47,"IR",I$41:I$47)),0) -> 7044 | J48: =IF(SUM(J37,J38,SUMIF($D$41:J47,"IR",J$41:J$47))>0,SUM(J37,J38,SUMIF($D$41:J47,"IR",J$41:J$47)),0) -> 4310
B49: =tab!B49 -> = | C49: =tab!C49 -> Contribuição Social a Pagar | E49: =IF(SUM(E39,SUMIF($D$41:E47,"CS",E$41:E$47))>0,SUM(E39,SUMIF($D$41:E47,"CS",E$41:E$47)),0) -> 0 | F49: =IF(SUM(F39,SUMIF($D$41:F47,"CS",F$41:F$47))>0,SUM(F39,SUMIF($D$41:F47,"CS",F$41:F$47)),0) -> 112.8 | G49: =IF(SUM(G39,SUMIF($D$41:G47,"CS",G$41:G$47))>0,SUM(G39,SUMIF($D$41:G47,"CS",G$41:G$47)),0) -> 1575 | H49: =IF(SUM(H39,SUMIF($D$41:H47,"CS",H$41:H$47))>0,SUM(H39,SUMIF($D$41:H47,"CS",H$41:H$47)),0) -> 1639.8 | I49: =IF(SUM(I39,SUMIF($D$41:I47,"CS",I$41:I$47))>0,SUM(I39,SUMIF($D$41:I47,"CS",I$41:I$47)),0) -> 4226.4 | J49: =IF(SUM(J39,SUMIF($D$41:J47,"CS",J$41:J$47))>0,SUM(J39,SUMIF($D$41:J47,"CS",J$41:J$47)),0) -> 2250

Sheet jul
B3: 2018
A4: 7 | B4: # | C4: Parâmetros | D4: % | E4: Jan | F4: Fev | G4: Mar | H4: Abr | I4: Mai | J4: Jun | K4: Jul | L4: Ago | M4: Set | N4: Out | O4: Nov | P4: Dez
A5: 2018 | B5: =tab!B5 -> = | C5: =tab!C5 -> Lucro Acumulado | E5: =HLOOKUP(E$4,tab!$E$4:$P$33,MATCH($C5,$C$4:$C$33,0),0) -> 1000 | F5: =HLOOKUP(F$4,tab!$E$4:$P$33,MATCH($C5,$C$4:$C$33,0),0) -> 26000 | G5: =HLOOKUP(G$4,tab!$E$4:$P$33,MATCH($C5,$C$4:$C$33,0),0) -> 51000 | H5: =HLOOKUP(H$4,tab!$E$4:$P$33,MATCH($C5,$C$4:$C$33,0),0) -> 76000 | I5: =HLOOKUP(I$4,tab!$E$4:$P$33,MATCH($C5,$C$4:$C$33,0),0) -> 101000 | J5: =HLOOKUP(J$4,tab!$E$4:$P$33,MATCH($C5,$C$4:$C$33,0),0) -> 126000 | K5: =HLOOKUP(K$4,tab!$E$4:$P$33,MATCH($C5,$C$4:$C$33,0),0) -> 151000
A6: 2019 | B6: =tab!B6 -> = | C6: =tab!C6 -> Adições | E6: =SUM(E7:E19) -> 600 | F6: =SUM(F7:F19) -> 600 | G6: =SUM(G7:G19) -> 600 | H6: =SUM(H7:H19) -> 600 | I6: =SUM(I7:I19) -> 600 | J6: =SUM(J7:J19) -> 600 | K6: =SUM(K7:K19) -> 600
A7: 2020 | B7: =tab!B7 -> + | C7: =tab!C7 -> Ajustes Devedores de Qualquer Natureza | E7: =HLOOKUP(E$4,tab!$E$4:$P$49,MATCH($C7,$C$4:$C$49,0),0) -> 0 | F7: =HLOOKUP(F$4,tab!$E$4:$P$49,MATCH($C7,$C$4:$C$49,0),0) -> 0 | G7: =HLOOKUP(G$4,tab!$E$4:$P$49,MATCH($C7,$C$4:$C$49,0),0) -> 0 | H7: =HLOOKUP(H$4,tab!$E$4:$P$49,MATCH($C7,$C$4:$C$49,0),0) -> 0 | I7: =HLOOKUP(I$4,tab!$E$4:$P$49,MATCH($C7,$C$4:$C$49,0),0) -> 0 | J7: =HLOOKUP(J$4,tab!$E$4:$P$49,MATCH($C7,$C$4:$C$49,0),0) -> 0 | K7: =HLOOKUP(K$4,tab!$E$4:$P$49,MATCH($C7,$C$4:$C$49,0),0) -> 0
A8: 2021 | B8: =tab!B8 -> + | C8: =tab!C8 -> Despesas de Variação Cambial | E8: =HLOOKUP(E$4,tab!$E$4:$P$49,MATCH($C8,$C$4:$C$49,0),0) -> 0 | F8: =HLOOKUP(F$4,tab!$E$4:$P$49,MATCH($C8,$C$4:$C$49,0),0) -> 0 | G8: =HLOOKUP(G$4,tab!$E$4:$P$49,MATCH($C8,$C$4:$C$49,0),0) -> 0 | H8: =HLOOKUP(H$4,tab!$E$4:$P$49,MATCH($C8,$C$4:$C$49,0),0) -> 0 | I8: =HLOOKUP(I$4,tab!$E$4:$P$49,MATCH($C8,$C$4:$C$49,0),0) -> 0 | J8: =HLOOKUP(J$4,tab!$E$4:$P$49,MATCH($C8,$C$4:$C$49,0),0) -> 0 | K8: =HLOOKUP(K$4,tab!$E$4:$P$49,MATCH($C8,$C$4:$C$49,0),0) -> 0
A9: 2022 | B9: =tab!B9 -> + | C9: =tab!C9 -> Despesas Particulares dos Sócios e Dirigentes; | E9: =HLOOKUP(E$4,tab!$E$4:$P$49,MATCH($C9,$C$4:$C$49,0),0) -> 0 | F9: =HLOOKUP(F$4,tab!$E$4:$P$49,MATCH($C9,$C$4:$C$49,0),0) -> 0 | G9: =HLOOKUP(G$4,tab!$E$4:$P$49,MATCH($C9,$C$4:$C$49,0),0) -> 0 | H9: =HLOOKUP(H$4,tab!$E$4:$P$49,MATCH($C9,$C$4:$C$49,0),0) -> 0 | I9: =HLOOKUP(I$4,tab!$E$4:$P$49,MATCH($C9,$C$4:$C$49,0),0) -> 0 | J9: =HLOOKUP(J$4,tab!$E$4:$P$49,MATCH($C9,$C$4:$C$49,0),0) -> 0 | K9: =HLOOKUP(K$4,tab!$E$4:$P$49,MATCH($C9,$C$4:$C$49,0),0) -> 0
A10: 2023 | B10: =tab!B10 -> + | C10: =tab!C10 -> Doações e Brindes; | E10: =HLOOKUP(E$4,tab!$E$4:$P$49,MATCH($C10,$C$4:$C$49,0),0) -> 100 | F10: =HLOOKUP(F$4,tab!$E$4:$P$49,MATCH($C10,$C$4:$C$49,0),0) -> 100 | G10: =HLOOKUP(G$4,tab!$E$4:$P$49,MATCH($C10,$C$4:$C$49,0),0) -> 100 | H10: =HLOOKUP(H$4,tab!$E$4:$P$49,MATCH($C10,$C$4:$C$49,0),0) -> 100 | I10: =HLOOKUP(I$4,tab!$E$4:$P$49,MATCH($C10,$C$4:$C$49,0),0) -> 100 | J10: =HLOOKUP(J$4,tab!$E$4:$P$49,MATCH($C10,$C$4:$C$49,0),0) -> 100 | K10: =HLOOKUP(K$4,tab!$E$4:$P$49,MATCH($C10,$C$4:$C$49,0),0) -> 100
A11: 2024 | B11: =tab!B11 -> + | C11: =tab!C11 -> Impostos Não Pagos em Discussão Judicial; | E11: =HLOOKUP(E$4,tab!$E$4:$P$49,MATCH($C11,$C$4:$C$49,0),0) -> 0 | F11: =HLOOKUP(F$4,tab!$E$4:$P$49,MATCH($C11,$C$4:$C$49,0),0) -> 0 | G11: =HLOOKUP(G$4,tab!$E$4:$P$49,MATCH($C11,$C$4:$C$49,0),0) -> 0 | H11: =HLOOKUP(H$4,tab!$E$4:$P$49,MATCH($C11,$C$4:$C$49,0),0) -> 0 | I11: =HLOOKUP(I$4,tab!$E$4:$P$49,MATCH($C11,$C$4:$C$49,0),0) -> 0 | J11: =HLOOKUP(J$4,tab!$E$4:$P$49,MATCH($C11,$C$4:$C$49,0),0) -> 0 | K11: =HLOOKUP(K$4,tab!$E$4:$P$49,MATCH($C11,$C$4:$C$49,0),0) -> 0
A12: 2025 | B12: =tab!B12 -> + | C12: =tab!C12 -> Impostos Não Pagos por Iniciativa da Empresa; | E12: =HLOOKUP(E$4,tab!$E$4:$P$49,MATCH($C12,$C$4:$C$49,0),0) -> 0 | F12: =HLOOKUP(F$4,tab!$E$4:$P$49,MATCH($C12,$C$4:$C$49,0),0) -> 0 | G12: =HLOOKUP(G$4,tab!$E$4:$P$49,MATCH($C12,$C$4:$C$49,0),0) -> 0 | H12: =HLOOKUP(H$4,tab!$E$4:$P$49,MATCH($C12,$C$4:$C$49,0),0) -> 0 | I12: =HLOOKUP(I$4,tab!$E$4:$P$49,MATCH($C12,$C$4:$C$49,0),0) -> 0 | J12: =HLOOKUP(J$4,tab!$E$4:$P$49,MATCH($C12,$C$4:$C$49,0),0) -> 0 | K12: =HLOOKUP(K$4,tab!$E$4:$P$49,MATCH($C12,$C$4:$C$49,0),0) -> 0
A13: 2026 | B13: =tab!B13 -> + | C13: =tab!C13 -> Lucro Inflacionário apurado até 31/12/1995; | E13: =HLOOKUP(E$4,tab!$E$4:$P$49,MATCH($C13,$C$4:$C$49,0),0) -> 0 | F13: =HLOOKUP(F$4,tab!$E$4:$P$49,MATCH($C13,$C$4:$C$49,0),0) -> 0 | G13: =HLOOKUP(G$4,tab!$E$4:$P$49,MATCH($C13,$C$4:$C$49,0),0) -> 0 | H13: =HLOOKUP(H$4,tab!$E$4:$P$49,MATCH($C13,$C$4:$C$49,0),0) -> 0 | I13: =HLOOKUP(I$4,tab!$E$4:$P$49,MATCH($C13,$C$4:$C$49,0),0) -> 0 | J13: =HLOOKUP(J$4,tab!$E$4:$P$49,MATCH($C13,$C$4:$C$49,0),0) -> 0 | K13: =HLOOKUP(K$4,tab!$E$4:$P$49,MATCH($C13,$C$4:$C$49,0),0) -> 0
A14: 2027 | B14: =tab!B14 -> + | C14: =tab!C14 -> Multas Contratuais | E14: =HLOOKUP(E$4,tab!$E$4:$P$49,MATCH($C14,$C$4:$C$49,0),0) -> 0 | F14: =HLOOKUP(F$4,tab!$E$4:$P$49,MATCH($C14,$C$4:$C$49,0),0) -> 0 | G14: =HLOOKUP(G$4,tab!$E$4:$P$49,MATCH($C14,$C$4:$C$49,0),0) -> 0 | H14: =HLOOKUP(H$4,tab!$E$4:$P$49,MATCH($C14,$C$4:$C$49,0),0) -> 0 | I14: =HLOOKUP(I$4,tab!$E$4:$P$49,MATCH($C14,$C$4:$C$49,0),0) -> 0 | J14: =HLOOKUP(J$4,tab!$E$4:$P$49,MATCH($C14,$C$4:$C$49,0),0) -> 0 | K14: =HLOOKUP(K$4,tab!$E$4:$P$49,MATCH($C14,$C$4:$C$49,0),0) -> 0
A15: 2028 | B15: =tab!B15 -> + | C15: =tab!C15 -> Multas Punitivas (Transito, Imetro, Ibama, Multas sobre ação fiscal) | E15: =HLOOKUP(E$4,tab!$E$4:$P$49,MATCH($C15,$C$4:$C$49,0),0) -> 500 | F15: =HLOOKUP(F$4,tab!$E$4:$P$49,MATCH($C15,$C$4:$C$49,0),0) -> 500 | G15: =HLOOKUP(G$4,tab!$E$4:$P$49,MATCH($C15,$C$4:$C$49,0),0) -> 500 | H15: =HLOOKUP(H$4,tab!$E$4:$P$49,MATCH($C15,$C$4:$C$49,0),0) -> 500 | I15: =HLOOKUP(I$4,tab!$E$4:$P$49,MATCH($C15,$C$4:$C$49,0),0) -> 500 | J15: =HLOOKUP(J$4,tab!$E$4:$P$49,MATCH($C15,$C$4:$C$49,0),0) -> 500 | K15: =HLOOKUP(K$4,tab!$E$4:$P$49,MATCH($C15,$C$4:$C$49,0),0) -> 500
A16: 2029 | B16: =tab!B16 -> + | C16: =tab!C16 -> Orçamentos, Pedidos e qualquer documento não idôneo; | E16: =HLOOKUP(E$4,tab!$E$4:$P$49,MATCH($C16,$C$4:$C$49,0),0) -> 0 | F16: =HLOOKUP(F$4,tab!$E$4:$P$49,MATCH($C16,$C$4:$C$49,0),0) -> 0 | G16: =HLOOKUP(G$4,tab!$E$4:$P$49,MATCH($C16,$C$4:$C$49,0),0) -> 0 | H16: =HLOOKUP(H$4,tab!$E$4:$P$49,MATCH($C16,$C$4:$C$49,0),0) -> 0 | I16: =HLOOKUP(I$4,tab!$E$4:$P$49,MATCH($C16,$C$4:$C$49,0),0) -> 0 | J16: =HLOOKUP(J$4,tab!$E$4:$P$49,MATCH($C16,$C$4:$C$49,0),0) -> 0 | K16: =HLOOKUP(K$4,tab!$E$4:$P$49,MATCH($C16,$C$4:$C$49,0),0) -> 0
A17: 2030 | B17: =tab!B17 -> + | C17: =tab!C17 -> Provisões Indedutíveis (perdas, frete, propaganda) | E17: =HLOOKUP(E$4,tab!$E$4:$P$49,MATCH($C17,$C$4:$C$49,0),0) -> 0 | F17: =HLOOKUP(F$4,tab!$E$4:$P$49,MATCH($C17,$C$4:$C$49,0),0) -> 0 | G17: =HLOOKUP(G$4,tab!$E$4:$P$49,MATCH($C17,$C$4:$C$49,0),0) -> 0 | H17: =HLOOKUP(H$4,tab!$E$4:$P$49,MATCH($C17,$C$4:$C$49,0),0) -> 0 | I17: =HLOOKUP(I$4,tab!$E$4:$P$49,MATCH($C17,$C$4:$C$49,0),0) -> 0 | J17: =HLOOKUP(J$4,tab!$E$4:$P$49,MATCH($C17,$C$4:$C$49,0),0) -> 0 | K17: =HLOOKUP(K$4,tab!$E$4:$P$49,MATCH($C17,$C$4:$C$49,0),0) -> 0
B18: =tab!B18 -> + | C18: =tab!C18 -> Recibos sem especificação da fonte recebedora; | E18: =HLOOKUP(E$4,tab!$E$4:$P$49,MATCH($C18,$C$4:$C$49,0),0) -> 0 | F18: =HLOOKUP(F$4,tab!$E$4:$P$49,MATCH($C18,$C$4:$C$49,0),0) -> 0 | G18: =HLOOKUP(G$4,tab!$E$4:$P$49,MATCH($C18,$C$4:$C$49,0),0) -> 0 | H18: =HLOOKUP(H$4,tab!$E$4:$P$49,MATCH($C18,$C$4:$C$49,0),0) -> 0 | I18: =HLOOKUP(I$4,tab!$E$4:$P$49,MATCH($C18,$C$4:$C$49,0),0) -> 0 | J18: =HLOOKUP(J$4,tab!$E$4:$P$49,MATCH($C18,$C$4:$C$49,0),0) -> 0 | K18: =HLOOKUP(K$4,tab!$E$4:$P$49,MATCH($C18,$C$4:$C$49,0),0) -> 0
B19: =tab!B19 -> + | C19: =tab!C19 -> Verbas Rescisórias em desacordo com a legislação trabalhista vigente | E19: =HLOOKUP(E$4,tab!$E$4:$P$49,MATCH($C19,$C$4:$C$49,0),0) -> 0 | F19: =HLOOKUP(F$4,tab!$E$4:$P$49,MATCH($C19,$C$4:$C$49,0),0) -> 0 | G19: =HLOOKUP(G$4,tab!$E$4:$P$49,MATCH($C19,$C$4:$C$49,0),0) -> 0 | H19: =HLOOKUP(H$4,tab!$E$4:$P$49,MATCH($C19,$C$4:$C$49,0),0) -> 0 | I19: =HLOOKUP(I$4,tab!$E$4:$P$49,MATCH($C19,$C$4:$C$49,0),0) -> 0 | J19: =HLOOKUP(J$4,tab!$E$4:$P$49,MATCH($C19,$C$4:$C$49,0),0) -> 0 | K19: =HLOOKUP(K$4,tab!$E$4:$P$49,MATCH($C19,$C$4:$C$49,0),0) -> 0
B20: =tab!B20 -> = | C20: =tab!C20 -> Exclusões | E20: =SUM(E21:E33) -> -1000 | F20: =SUM(F21:F33) -> -1000 | G20: =SUM(G21:G33) -> -1000 | H20: =SUM(H21:H33) -> -1000 | I20: =SUM(I21:I33) -> -1000 | J20: =SUM(J21:J33) -> -1000 | K20: =SUM(K21:K33) -> -1000
B21: =tab!B21 -> - | C21: =tab!C21 -> Ajustes credores de qualquer natureza | E21: =HLOOKUP(E$4,tab!$E$4:$P$49,MATCH($C21,$C$4:$C$49,0),0) -> 0 | F21: =HLOOKUP(F$4,tab!$E$4:$P$49,MATCH($C21,$C$4:$C$49,0),0) -> 0 | G21: =HLOOKUP(G$4,tab!$E$4:$P$49,MATCH($C21,$C$4:$C$49,0),0) -> 0 | H21: =HLOOKUP(H$4,tab!$E$4:$P$49,MATCH($C21,$C$4:$C$49,0),0) -> 0 | I21: =HLOOKUP(I$4,tab!$E$4:$P$49,MATCH($C21,$C$4:$C$49,0),0) -> 0 | J21: =HLOOKUP(J$4,tab!$E$4:$P$49,MATCH($C21,$C$4:$C$49,0),0) -> 0 | K21: =HLOOKUP(K$4,tab!$E$4:$P$49,MATCH($C21,$C$4:$C$49,0),0) -> 0
B22: =tab!B22 -> - | C22: =tab!C22 -> Decisão Favorável - Processos Judiciais Tributários | E22: =HLOOKUP(E$4,tab!$E$4:$P$49,MATCH($C22,$C$4:$C$49,0),0) -> 0 | F22: =HLOOKUP(F$4,tab!$E$4:$P$49,MATCH($C22,$C$4:$C$49,0),0) -> 0 | G22: =HLOOKUP(G$4,tab!$E$4:$P$49,MATCH($C22,$C$4:$C$49,0),0) -> 0 | H22: =HLOOKUP(H$4,tab!$E$4:$P$49,MATCH($C22,$C$4:$C$49,0),0) -> 0 | I22: =HLOOKUP(I$4,tab!$E$4:$P$49,MATCH($C22,$C$4:$C$49,0),0) -> 0 | J22: =HLOOKUP(J$4,tab!$E$4:$P$49,MATCH($C22,$C$4:$C$49,0),0) -> 0 | K22: =HLOOKUP(K$4,tab!$E$4:$P$49,MATCH($C22,$C$4:$C$49,0),0) -> 0
B23: =tab!B23 -> - | C23: =tab!C23 -> Despesas de Ágios | E23: =HLOOKUP(E$4,tab!$E$4:$P$49,MATCH($C23,$C$4:$C$49,0),0) -> 0 | F23: =HLOOKUP(F$4,tab!$E$4:$P$49,MATCH($C23,$C$4:$C$49,0),0) -> 0 | G23: =HLOOKUP(G$4,tab!$E$4:$P$49,MATCH($C23,$C$4:$C$49,0),0) -> 0 | H23: =HLOOKUP(H$4,tab!$E$4:$P$49,MATCH($C23,$C$4:$C$49,0),0) -> 0 | I23: =HLOOKUP(I$4,tab!$E$4:$P$49,MATCH($C23,$C$4:$C$49,0),0) -> 0 | J23: =HLOOKUP(J$4,tab!$E$4:$P$49,MATCH($C23,$C$4:$C$49,0),0) -> 0 | K23: =HLOOKUP(K$4,tab!$E$4:$P$49,MATCH($C23,$C$4:$C$49,0),0) -> 0
B24: =tab!B24 -> - | C24: =tab!C24 -> Distribuição de Lucros e Dividendos; | E24: =HLOOKUP(E$4,tab!$E$4:$P$49,MATCH($C24,$C$4:$C$49,0),0) -> 0 | F24: =HLOOKUP(F$4,tab!$E$4:$P$49,MATCH($C24,$C$4:$C$49,0),0) -> 0 | G24: =HLOOKUP(G$4,tab!$E$4:$P$49,MATCH($C24,$C$4:$C$49,0),0) -> 0 | H24: =HLOOKUP(H$4,tab!$E$4:$P$49,MATCH($C24,$C$4:$C$49,0),0) -> 0 | I24: =HLOOKUP(I$4,tab!$E$4:$P$49,MATCH($C24,$C$4:$C$49,0),0) -> 0 | J24: =HLOOKUP(J$4,tab!$E$4:$P$49,MATCH($C24,$C$4:$C$49,0),0) -> 0 | K24: =HLOOKUP(K$4,tab!$E$4:$P$49,MATCH($C24,$C$4:$C$49,0),0) -> 0
B25: =tab!B25 -> - | C25: =tab!C25 -> Dividendos Coligadas e Controladas | E25: =HLOOKUP(E$4,tab!$E$4:$P$49,MATCH($C25,$C$4:$C$49,0),0) -> 0 | F25: =HLOOKUP(F$4,tab!$E$4:$P$49,MATCH($C25,$C$4:$C$49,0),0) -> 0 | G25: =HLOOKUP(G$4,tab!$E$4:$P$49,MATCH($C25,$C$4:$C$49,0),0) -> 0 | H25: =HLOOKUP(H$4,tab!$E$4:$P$49,MATCH($C25,$C$4:$C$49,0),0) -> 0 | I25: =HLOOKUP(I$4,tab!$E$4:$P$49,MATCH($C25,$C$4:$C$49,0),0) -> 0 | J25: =HLOOKUP(J$4,tab!$E$4:$P$49,MATCH($C25,$C$4:$C$49,0),0) -> 0 | K25: =HLOOKUP(K$4,tab!$E$4:$P$49,MATCH($C25,$C$4:$C$49,0),0) -> 0
B26: =tab!B26 -> - | C26: =tab!C26 -> Pagamento de Impostos em Atraso por iniciativa da Empresa | E26: =HLOOKUP(E$4,tab!$E$4:$P$49,MATCH($C26,$C$4:$C$49,0),0) -> -1000 | F26: =HLOOKUP(F$4,tab!$E$4:$P$49,MATCH($C26,$C$4:$C$49,0),0) -> -1000 | G26: =HLOOKUP(G$4,tab!$E$4:$P$49,MATCH($C26,$C$4:$C$49,0),0) -> -1000 | H26: =HLOOKUP(H$4,tab!$E$4:$P$49,MATCH($C26,$C$4:$C$49,0),0) -> -1000 | I26: =HLOOKUP(I$4,tab!$E$4:$P$49,MATCH($C26,$C$4:$C$49,0),0) -> -1000 | J26: =HLOOKUP(J$4,tab!$E$4:$P$49,MATCH($C26,$C$4:$C$49,0),0) -> -1000 | K26: =HLOOKUP(K$4,tab!$E$4:$P$49,MATCH($C26,$C$4:$C$49,0),0) -> -1000
B27: =tab!B27 -> - | C27: =tab!C27 -> Pagamento de Impostos sobre discussão judicial, | E27: =HLOOKUP(E$4,tab!$E$4:$P$49,MATCH($C27,$C$4:$C$49,0),0) -> 0 | F27: =HLOOKUP(F$4,tab!$E$4:$P$49,MATCH($C27,$C$4:$C$49,0),0) -> 0 | G27: =HLOOKUP(G$4,tab!$E$4:$P$49,MATCH($C27,$C$4:$C$49,0),0) -> 0 | H27: =HLOOKUP(H$4,tab!$E$4:$P$49,MATCH($C27,$C$4:$C$49,0),0) -> 0 | I27: =HLOOKUP(I$4,tab!$E$4:$P$49,MATCH($C27,$C$4:$C$49,0),0) -> 0 | J27: =HLOOKUP(J$4,tab!$E$4:$P$49,MATCH($C27,$C$4:$C$49,0),0) -> 0 | K27: =HLOOKUP(K$4,tab!$E$4:$P$49,MATCH($C27,$C$4:$C$49,0),0) -> 0
B28: =tab!B28 -> - | C28: =tab!C28 -> Receita de Variação Cambial | E28: =HLOOKUP(E$4,tab!$E$4:$P$49,MATCH($C28,$C$4:$C$49,0),0) -> 0 | F28: =HLOOKUP(F$4,tab!$E$4:$P$49,MATCH($C28,$C$4:$C$49,0),0) -> 0 | G28: =HLOOKUP(G$4,tab!$E$4:$P$49,MATCH($C28,$C$4:$C$49,0),0) -> 0 | H28: =HLOOKUP(H$4,tab!$E$4:$P$49,MATCH($C28,$C$4:$C$49,0),0) -> 0 | I28: =HLOOKUP(I$4,tab!$E$4:$P$49,MATCH($C28,$C$4:$C$49,0),0) -> 0 | J28: =HLOOKUP(J$4,tab!$E$4:$P$49,MATCH($C28,$C$4:$C$49,0),0) -> 0 | K28: =HLOOKUP(K$4,tab!$E$4:$P$49,MATCH($C28,$C$4:$C$49,0),0) -> 0
B29: =tab!B29 -> - | C29: =tab!C29 -> Receitas Obtidas com Tributação Exclusiva ou Isenta de IR | E29: =HLOOKUP(E$4,tab!$E$4:$P$49,MATCH($C29,$C$4:$C$49,0),0) -> 0 | F29: =HLOOKUP(F$4,tab!$E$4:$P$49,MATCH($C29,$C$4:$C$49,0),0) -> 0 | G29: =HLOOKUP(G$4,tab!$E$4:$P$49,MATCH($C29,$C$4:$C$49,0),0) -> 0 | H29: =HLOOKUP(H$4,tab!$E$4:$P$49,MATCH($C29,$C$4:$C$49,0),0) -> 0 | I29: =HLOOKUP(I$4,tab!$E$4:$P$49,MATCH($C29,$C$4:$C$49,0),0) -> 0 | J29: =HLOOKUP(J$4,tab!$E$4:$P$49,MATCH($C29,$C$4:$C$49,0),0) -> 0 | K29: =HLOOKUP(K$4,tab!$E$4:$P$49,MATCH($C29,$C$4:$C$49,0),0) -> 0
B30: =tab!B30 -> - | C30: =tab!C30 -> Receitas que poderiam ser diferidas; | E30: =HLOOKUP(E$4,tab!$E$4:$P$49,MATCH($C30,$C$4:$C$49,0),0) -> 0 | F30: =HLOOKUP(F$4,tab!$E$4:$P$49,MATCH($C30,$C$4:$C$49,0),0) -> 0 | G30: =HLOOKUP(G$4,tab!$E$4:$P$49,MATCH($C30,$C$4:$C$49,0),0) -> 0 | H30: =HLOOKUP(H$4,tab!$E$4:$P$49,MATCH($C30,$C$4:$C$49,0),0) -> 0 | I30: =HLOOKUP(I$4,tab!$E$4:$P$49,MATCH($C30,$C$4:$C$49,0),0) -> 0 | J30: =HLOOKUP(J$4,tab!$E$4:$P$49,MATCH($C30,$C$4:$C$49,0),0) -> 0 | K30: =HLOOKUP(K$4,tab!$E$4:$P$49,MATCH($C30,$C$4:$C$49,0),0) -> 0
B31: =tab!B31 -> - | C31: =tab!C31 -> Resultado Positivo de Equivalência Patrimonial | E31: =HLOOKUP(E$4,tab!$E$4:$P$49,MATCH($C31,$C$4:$C$49,0),0) -> 0 | F31: =HLOOKUP(F$4,tab!$E$4:$P$49,MATCH($C31,$C$4:$C$49,0),0) -> 0 | G31: =HLOOKUP(G$4,tab!$E$4:$P$49,MATCH($C31,$C$4:$C$49,0),0) -> 0 | H31: =HLOOKUP(H$4,tab!$E$4:$P$49,MATCH($C31,$C$4:$C$49,0),0) -> 0 | I31: =HLOOKUP(I$4,tab!$E$4:$P$49,MATCH($C31,$C$4:$C$49,0),0) -> 0 | J31: =HLOOKUP(J$4,tab!$E$4:$P$49,MATCH($C31,$C$4:$C$49,0),0) -> 0 | K31: =HLOOKUP(K$4,tab!$E$4:$P$49,MATCH($C31,$C$4:$C$49,0),0) -> 0
B32: =tab!B32 -> - | C32: =tab!C32 -> Reversão de Provisões Indedutíveis | E32: =HLOOKUP(E$4,tab!$E$4:$P$49,MATCH($C32,$C$4:$C$49,0),0) -> 0 | F32: =HLOOKUP(F$4,tab!$E$4:$P$49,MATCH($C32,$C$4:$C$49,0),0) -> 0 | G32: =HLOOKUP(G$4,tab!$E$4:$P$49,MATCH($C32,$C$4:$C$49,0),0) -> 0 | H32: =HLOOKUP(H$4,tab!$E$4:$P$49,MATCH($C32,$C$4:$C$49,0),0) -> 0 | I32: =HLOOKUP(I$4,tab!$E$4:$P$49,MATCH($C32,$C$4:$C$49,0),0) -> 0 | J32: =HLOOKUP(J$4,tab!$E$4:$P$49,MATCH($C32,$C$4:$C$49,0),0) -> 0 | K32: =HLOOKUP(K$4,tab!$E$4:$P$49,MATCH($C32,$C$4:$C$49,0),0) -> 0
B33: =tab!B33 -> - | C33: =tab!C33 -> Vendas Não Expedidas do Período | E33: =HLOOKUP(E$4,tab!$E$4:$P$49,MATCH($C33,$C$4:$C$49,0),0) -> 0 | F33: =HLOOKUP(F$4,tab!$E$4:$P$49,MATCH($C33,$C$4:$C$49,0),0) -> 0 | G33: =HLOOKUP(G$4,tab!$E$4:$P$49,MATCH($C33,$C$4:$C$49,0),0) -> 0 | H33: =HLOOKUP(H$4,tab!$E$4:$P$49,MATCH($C33,$C$4:$C$49,0),0) -> 0 | I33: =HLOOKUP(I$4,tab!$E$4:$P$49,MATCH($C33,$C$4:$C$49,0),0) -> 0 | J33: =HLOOKUP(J$4,tab!$E$4:$P$49,MATCH($C33,$C$4:$C$49,0),0) -> 0 | K33: =HLOOKUP(K$4,tab!$E$4:$P$49,MATCH($C33,$C$4:$C$49,0),0) -> 0
B34: =tab!B34 -> = | C34: =tab!C34 -> Base de Cálculo | E34: =SUM(E5,E6,E20) -> 600 | F34: =SUM(F5,F6,F20) -> 25600 | G34: =SUM(G5,G6,G20) -> 50600 | H34: =SUM(H5,H6,H20) -> 75600 | I34: =SUM(I5,I6,I20) -> 100600 | J34: =SUM(J5,J6,J20) -> 125600 | K34: =SUM(K5,K6,K20) -> 150600
B35: =tab!B35 -> = | C35: =tab!C35 -> Saldo Prejuízo Fiscal | E35: =tab!E35 -> 45000 | F35: =SUM(E35:E36) -> 44820 | G35: =SUM(F35:F36) -> 37140 | H35: =SUM(G35:G36) -> 21960 | I35: =SUM(H35:H36) -> 0 | J35: =SUM(I35:I36) -> 0 | K35: =SUM(J35:J36) -> 0
B36: =tab!B36 -> % | C36: =tab!C36 -> Compensação de Prejuízo Fiscal | D36: =tab!D36 -> 0.3 | E36: =-IF(AND(E35>0,E34*$D$36<E35),E34*$D$36,E35) -> -180 | F36: =-IF(AND(F35>0,F34*$D$36<F35),F34*$D$36,F35) -> -7680 | G36: =-IF(AND(G35>0,G34*$D$36<G35),G34*$D$36,G35) -> -15180 | H36: =-IF(AND(H35>0,H34*$D$36<H35),H34*$D$36,H35) -> -21960 | I36: =-IF(AND(I35>0,I34*$D$36<I35),I34*$D$36,I35) -> 0 | J36: =-IF(AND(J35>0,J34*$D$36<J35),J34*$D$36,J35) -> 0 | K36: =-IF(AND(K35>0,K34*$D$36<K35),K34*$D$36,K35) -> 0
B37: =tab!B37 -> % | C37: =tab!C37 -> Adicional de Imposto de Renda | D37: =tab!D37 -> 0.1 | E37: =HLOOKUP($E$4,INDIRECT($E$4&"!$E$4:$O$49"),MATCH(C37,INDIRECT($E$4&"!$C$4:$C$49"),0),0) -> 0 | F37: =IF(SUM(F34,F36)>20000*$A$4,(SUM(F34,F36)-20000*$A$4)*$D$37,0) -> 0 | G37: =IF(SUM(G34,G36)>20000*$A$4,(SUM(G34,G36)-20000*$A$4)*$D$37,0) -> 0 | H37: =IF(SUM(H34,H36)>20000*$A$4,(SUM(H34,H36)-20000*$A$4)*$D$37,0) -> 0 | I37: =IF(SUM(I34,I36)>20000*$A$4,(SUM(I34,I36)-20000*$A$4)*$D$37,0) -> 0 | J37: =IF(SUM(J34,J36)>20000*$A$4,(SUM(J34,J36)-20000*$A$4)*$D$37,0) -> 0 | K37: =IF(SUM(K34,K36)>20000*$A$4,(SUM(K34,K36)-20000*$A$4)*$D$37,0) -> 1060
B38: =tab!B38 -> % | C38: =tab!C38 -> Imposto de Renda | D38: =tab!D38 -> 0.15 | E38: =SUM(E34,E36)*$D$38 -> 63 | F38: =SUM(F34,F36)*$D$38 -> 2688 | G38: =SUM(G34,G36)*$D$38 -> 5313 | H38: =SUM(H34,H36)*$D$38 -> 8046 | I38: =SUM(I34,I36)*$D$38 -> 15090 | J38: =SUM(J34,J36)*$D$38 -> 18840 | K38: =SUM(K34,K36)*$D$38 -> 22590
B39: =tab!B39 -> % | C39: =tab!C39 -> Contribuição Social | D39: =tab!D39 -> 0.09 | E39: =SUM(E34,E36)*$D$39 -> 37.8 | F39: =SUM(F34,F36)*$D$39 -> 1612.8 | G39: =SUM(G34,G36)*$D$39 -> 3187.8 | H39: =SUM(H34,H36)*$D$39 -> 4827.6 | I39: =SUM(I34,I36)*$D$39 -> 9054 | J39: =SUM(J34,J36)*$D$39 -> 11304 | K39: =SUM(K34,K36)*$D$39 -> 13554
B40: =tab!B40 -> = | C40: =tab!C40 -> Compensações | E40: =SUM(E42:E47) -> -3600 | F40: =SUM(F42:F47) -> -3600 | G40: =SUM(G42:G47) -> -4300.8 | H40: =SUM(H42:H47) -> -8500.8 | I40: =SUM(I42:I47) -> -12873.6 | J40: =SUM(J42:J47) -> -24144 | K40: =SUM(K42:K47) -> -30144
B41: =tab!B41 -> - | C41: =tab!C41 -> IR Base Negativa Exercícios Anteriores | D41: =LEFT(C41,2) -> IR | E41: =HLOOKUP(E$4,tab!$E$4:$P$49,MATCH($C41,$C$4:$C$49,0),0) -> 0 | F41: =HLOOKUP(F$4,tab!$E$4:$P$49,MATCH($C41,$C$4:$C$49,0),0) -> 0 | G41: =HLOOKUP(G$4,tab!$E$4:$P$49,MATCH($C41,$C$4:$C$49,0),0) -> 0 | H41: =HLOOKUP(H$4,tab!$E$4:$P$49,MATCH($C41,$C$4:$C$49,0),0) -> 0 | I41: =HLOOKUP(I$4,tab!$E$4:$P$49,MATCH($C41,$C$4:$C$49,0),0) -> 0 | J41: =HLOOKUP(J$4,tab!$E$4:$P$49,MATCH($C41,$C$4:$C$49,0),0) -> 0 | K41: =HLOOKUP(K$4,tab!$E$4:$P$49,MATCH($C41,$C$4:$C$49,0),0) -> 0
B42: =tab!B42 -> - | C42: =tab!C42 -> IR s/ Aplicações Financeiras | D42: =LEFT(C42,2) -> IR | E42: =HLOOKUP(E$4,tab!$E$4:$P$49,MATCH($C42,$C$4:$C$49,0),0) -> -100 | F42: =HLOOKUP(F$4,tab!$E$4:$P$49,MATCH($C42,$C$4:$C$49,0),0) -> -100 | G42: =HLOOKUP(G$4,tab!$E$4:$P$49,MATCH($C42,$C$4:$C$49,0),0) -> -100 | H42: =HLOOKUP(H$4,tab!$E$4:$P$49,MATCH($C42,$C$4:$C$49,0),0) -> -100 | I42: =HLOOKUP(I$4,tab!$E$4:$P$49,MATCH($C42,$C$4:$C$49,0),0) -> -100 | J42: =HLOOKUP(J$4,tab!$E$4:$P$49,MATCH($C42,$C$4:$C$49,0),0) -> -100 | K42: =HLOOKUP(K$4,tab!$E$4:$P$49,MATCH($C42,$C$4:$C$49,0),0) -> -100
B43: =tab!B43 -> - | C43: =tab!C43 -> IR Retida s/ Notas Fiscais | D43: =LEFT(C43,2) -> IR | E43: =HLOOKUP(E$4,tab!$E$4:$P$49,MATCH($C43,$C$4:$C$49,0),0) -> -2000 | F43: =HLOOKUP(F$4,tab!$E$4:$P$49,MATCH($C43,$C$4:$C$49,0),0) -> -2000 | G43: =HLOOKUP(G$4,tab!$E$4:$P$49,MATCH($C43,$C$4:$C$49,0),0) -> -2000 | H43: =HLOOKUP(H$4,tab!$E$4:$P$49,MATCH($C43,$C$4:$C$49,0),0) -> -2000 | I43: =HLOOKUP(I$4,tab!$E$4:$P$49,MATCH($C43,$C$4:$C$49,0),0) -> -2000 | J43: =HLOOKUP(J$4,tab!$E$4:$P$49,MATCH($C43,$C$4:$C$49,0),0) -> -2000 | K43: =HLOOKUP(K$4,tab!$E$4:$P$49,MATCH($C43,$C$4:$C$49,0),0) -> -2000
B44: =tab!B44 -> - | C44: =tab!C44 -> IR Pago no Exercício | D44: =LEFT(C44,2) -> IR | E44: =HLOOKUP(E$4,tab!$E$4:$P$49,MATCH($C44,$C$4:$C$49,0),0) -> 0 | F44: =-E48 -> 0 | G44: =-SUM($E$48:F48) -> -588 | H44: =-SUM($E$48:G48) -> -3213 | I44: =-SUM($E$48:H48) -> -5946 | J44: =-SUM($E$48:I48) -> -12990 | K44: =-SUM($E$48:J48) -> -16740
B45: =tab!B45 -> - | C45: =tab!C45 -> CS Base Negativa Exercícios Anteriores | D45: =LEFT(C45,2) -> CS | E45: =HLOOKUP(E$4,tab!$E$4:$P$49,MATCH($C45,$C$4:$C$49,0),0) -> 0 | F45: =HLOOKUP(F$4,tab!$E$4:$P$49,MATCH($C45,$C$4:$C$49,0),0) -> 0 | G45: =HLOOKUP(G$4,tab!$E$4:$P$49,MATCH($C45,$C$4:$C$49,0),0) -> 0 | H45: =HLOOKUP(H$4,tab!$E$4:$P$49,MATCH($C45,$C$4:$C$49,0),0) -> 0 | I45: =HLOOKUP(I$4,tab!$E$4:$P$49,MATCH($C45,$C$4:$C$49,0),0) -> 0 | J45: =HLOOKUP(J$4,tab!$E$4:$P$49,MATCH($C45,$C$4:$C$49,0),0) -> 0 | K45: =HLOOKUP(K$4,tab!$E$4:$P$49,MATCH($C45,$C$4:$C$49,0),0) -> 0
B46: =tab!B46 -> - | C46: =tab!C46 -> CS Retida s/ Notas Fiscais | D46: =LEFT(C46,2) -> CS | E46: =HLOOKUP(E$4,tab!$E$4:$P$49,MATCH($C46,$C$4:$C$49,0),0) -> -1500 | F46: =HLOOKUP(F$4,tab!$E$4:$P$49,MATCH($C46,$C$4:$C$49,0),0) -> -1500 | G46: =HLOOKUP(G$4,tab!$E$4:$P$49,MATCH($C46,$C$4:$C$49,0),0) -> -1500 | H46: =HLOOKUP(H$4,tab!$E$4:$P$49,MATCH($C46,$C$4:$C$49,0),0) -> -1500 | I46: =HLOOKUP(I$4,tab!$E$4:$P$49,MATCH($C46,$C$4:$C$49,0),0) -> -1500 | J46: =HLOOKUP(J$4,tab!$E$4:$P$49,MATCH($C46,$C$4:$C$49,0),0) -> -1500 | K46: =HLOOKUP(K$4,tab!$E$4:$P$49,MATCH($C46,$C$4:$C$49,0),0) -> -1500
B47: =tab!B47 -> - | C47: =tab!C47 -> CS Pago no Exercício | D47: =LEFT(C47,2) -> CS | E47: =HLOOKUP(E$4,tab!$E$4:$P$49,MATCH($C47,$C$4:$C$49,0),0) -> 0 | F47: =-E49 -> 0 | G47: =-SUM($E$49:F49) -> -112.8 | H47: =-SUM($E$49:G49) -> -1687.8 | I47: =-SUM($E$49:H49) -> -3327.6 | J47: =-SUM($E$49:I49) -> -7554 | K47: =-SUM($E$49:J49) -> -9804
B48: =tab!B48 -> = | C48: =tab!C48 -> Imposto de Renda a Pagar | E48: =IF(SUM(E37,E38,SUMIF($D$41:E47,"IR",E$41:E$47))>0,SUM(E37,E38,SUMIF($D$41:E47,"IR",E$41:E$47)),0) -> 0 | F48: =IF(SUM(F37,F38,SUMIF($D$41:F47,"IR",F$41:F$47))>0,SUM(F37,F38,SUMIF($D$41:F47,"IR",F$41:F$47)),0) -> 588 | G48: =IF(SUM(G37,G38,SUMIF($D$41:G47,"IR",G$41:G$47))>0,SUM(G37,G38,SUMIF($D$41:G47,"IR",G$41:G$47)),0) -> 2625 | H48: =IF(SUM(H37,H38,SUMIF($D$41:H47,"IR",H$41:H$47))>0,SUM(H37,H38,SUMIF($D$41:H47,"IR",H$41:H$47)),0) -> 2733 | I48: =IF(SUM(I37,I38,SUMIF($D$41:I47,"IR",I$41:I$47))>0,SUM(I37,I38,SUMIF($D$41:I47,"IR",I$41:I$47)),0) -> 7044 | J48: =IF(SUM(J37,J38,SUMIF($D$41:J47,"IR",J$41:J$47))>0,SUM(J37,J38,SUMIF($D$41:J47,"IR",J$41:J$47)),0) -> 3750 | K48: =IF(SUM(K37,K38,SUMIF($D$41:K47,"IR",K$41:K$47))>0,SUM(K37,K38,SUMIF($D$41:K47,"IR",K$41:K$47)),0) -> 4810
B49: =tab!B49 -> = | C49: =tab!C49 -> Contribuição Social a Pagar | E49: =IF(SUM(E39,SUMIF($D$41:E47,"CS",E$41:E$47))>0,SUM(E39,SUMIF($D$41:E47,"CS",E$41:E$47)),0) -> 0 | F49: =IF(SUM(F39,SUMIF($D$41:F47,"CS",F$41:F$47))>0,SUM(F39,SUMIF($D$41:F47,"CS",F$41:F$47)),0) -> 112.8 | G49: =IF(SUM(G39,SUMIF($D$41:G47,"CS",G$41:G$47))>0,SUM(G39,SUMIF($D$41:G47,"CS",G$41:G$47)),0) -> 1575 | H49: =IF(SUM(H39,SUMIF($D$41:H47,"CS",H$41:H$47))>0,SUM(H39,SUMIF($D$41:H47,"CS",H$41:H$47)),0) -> 1639.8 | I49: =IF(SUM(I39,SUMIF($D$41:I47,"CS",I$41:I$47))>0,SUM(I39,SUMIF($D$41:I47,"CS",I$41:I$47)),0) -> 4226.4 | J49: =IF(SUM(J39,SUMIF($D$41:J47,"CS",J$41:J$47))>0,SUM(J39,SUMIF($D$41:J47,"CS",J$41:J$47)),0) -> 2250 | K49: =IF(SUM(K39,SUMIF($D$41:K47,"CS",K$41:K$47))>0,SUM(K39,SUMIF($D$41:K47,"CS",K$41:K$47)),0) -> 2250

Sheet ago
B3: 2018
A4: 8 | B4: # | C4: Parâmetros | D4: % | E4: Jan | F4: Fev | G4: Mar | H4: Abr | I4: Mai | J4: Jun | K4: Jul | L4: Ago | M4: Set | N4: Out | O4: Nov | P4: Dez
A5: 2018 | B5: =tab!B5 -> = | C5: =tab!C5 -> Lucro Acumulado | E5: =HLOOKUP(E$4,tab!$E$4:$P$33,MATCH($C5,$C$4:$C$33,0),0) -> 1000 | F5: =HLOOKUP(F$4,tab!$E$4:$P$33,MATCH($C5,$C$4:$C$33,0),0) -> 26000 | G5: =HLOOKUP(G$4,tab!$E$4:$P$33,MATCH($C5,$C$4:$C$33,0),0) -> 51000 | H5: =HLOOKUP(H$4,tab!$E$4:$P$33,MATCH($C5,$C$4:$C$33,0),0) -> 76000 | I5: =HLOOKUP(I$4,tab!$E$4:$P$33,MATCH($C5,$C$4:$C$33,0),0) -> 101000 | J5: =HLOOKUP(J$4,tab!$E$4:$P$33,MATCH($C5,$C$4:$C$33,0),0) -> 126000 | K5: =HLOOKUP(K$4,tab!$E$4:$P$33,MATCH($C5,$C$4:$C$33,0),0) -> 151000 | L5: =HLOOKUP(L$4,tab!$E$4:$P$33,MATCH($C5,$C$4:$C$33,0),0) -> 176000
A6: 2019 | B6: =tab!B6 -> = | C6: =tab!C6 -> Adições | E6: =SUM(E7:E19) -> 600 | F6: =SUM(F7:F19) -> 600 | G6: =SUM(G7:G19) -> 600 | H6: =SUM(H7:H19) -> 600 | I6: =SUM(I7:I19) -> 600 | J6: =SUM(J7:J19) -> 600 | K6: =SUM(K7:K19) -> 600 | L6: =SUM(L7:L19) -> 600
A7: 2020 | B7: =tab!B7 -> + | C7: =tab!C7 -> Ajustes Devedores de Qualquer Natureza | E7: =HLOOKUP(E$4,tab!$E$4:$P$49,MATCH($C7,$C$4:$C$49,0),0) -> 0 | F7: =HLOOKUP(F$4,tab!$E$4:$P$49,MATCH($C7,$C$4:$C$49,0),0) -> 0 | G7: =HLOOKUP(G$4,tab!$E$4:$P$49,MATCH($C7,$C$4:$C$49,0),0) -> 0 | H7: =HLOOKUP(H$4,tab!$E$4:$P$49,MATCH($C7,$C$4:$C$49,0),0) -> 0 | I7: =HLOOKUP(I$4,tab!$E$4:$P$49,MATCH($C7,$C$4:$C$49,0),0) -> 0 | J7: =HLOOKUP(J$4,tab!$E$4:$P$49,MATCH($C7,$C$4:$C$49,0),0) -> 0 | K7: =HLOOKUP(K$4,tab!$E$4:$P$49,MATCH($C7,$C$4:$C$49,0),0) -> 0 | L7: =HLOOKUP(L$4,tab!$E$4:$P$49,MATCH($C7,$C$4:$C$49,0),0) -> 0
A8: 2021 | B8: =tab!B8 -> + | C8: =tab!C8 -> Despesas de Variação Cambial | E8: =HLOOKUP(E$4,tab!$E$4:$P$49,MATCH($C8,$C$4:$C$49,0),0) -> 0 | F8: =HLOOKUP(F$4,tab!$E$4:$P$49,MATCH($C8,$C$4:$C$49,0),0) -> 0 | G8: =HLOOKUP(G$4,tab!$E$4:$P$49,MATCH($C8,$C$4:$C$49,0),0) -> 0 | H8: =HLOOKUP(H$4,tab!$E$4:$P$49,MATCH($C8,$C$4:$C$49,0),0) -> 0 | I8: =HLOOKUP(I$4,tab!$E$4:$P$49,MATCH($C8,$C$4:$C$49,0),0) -> 0 | J8: =HLOOKUP(J$4,tab!$E$4:$P$49,MATCH($C8,$C$4:$C$49,0),0) -> 0 | K8: =HLOOKUP(K$4,tab!$E$4:$P$49,MATCH($C8,$C$4:$C$49,0),0) -> 0 | L8: =HLOOKUP(L$4,tab!$E$4:$P$49,MATCH($C8,$C$4:$C$49,0),0) -> 0
A9: 2022 | B9: =tab!B9 -> + | C9: =tab!C9 -> Despesas Particulares dos Sócios e Dirigentes; | E9: =HLOOKUP(E$4,tab!$E$4:$P$49,MATCH($C9,$C$4:$C$49,0),0) -> 0 | F9: =HLOOKUP(F$4,tab!$E$4:$P$49,MATCH($C9,$C$4:$C$49,0),0) -> 0 | G9: =HLOOKUP(G$4,tab!$E$4:$P$49,MATCH($C9,$C$4:$C$49,0),0) -> 0 | H9: =HLOOKUP(H$4,tab!$E$4:$P$49,MATCH($C9,$C$4:$C$49,0),0) -> 0 | I9: =HLOOKUP(I$4,tab!$E$4:$P$49,MATCH($C9,$C$4:$C$49,0),0) -> 0 | J9: =HLOOKUP(J$4,tab!$E$4:$P$49,MATCH($C9,$C$4:$C$49,0),0) -> 0 | K9: =HLOOKUP(K$4,tab!$E$4:$P$49,MATCH($C9,$C$4:$C$49,0),0) -> 0 | L9: =HLOOKUP(L$4,tab!$E$4:$P$49,MATCH($C9,$C$4:$C$49,0),0) -> 0
A10: 2023 | B10: =tab!B10 -> + | C10: =tab!C10 -> Doações e Brindes; | E10: =HLOOKUP(E$4,tab!$E$4:$P$49,MATCH($C10,$C$4:$C$49,0),0) -> 100 | F10: =HLOOKUP(F$4,tab!$E$4:$P$49,MATCH($C10,$C$4:$C$49,0),0) -> 100 | G10: =HLOOKUP(G$4,tab!$E$4:$P$49,MATCH($C10,$C$4:$C$49,0),0) -> 100 | H10: =HLOOKUP(H$4,tab!$E$4:$P$49,MATCH($C10,$C$4:$C$49,0),0) -> 100 | I10: =HLOOKUP(I$4,tab!$E$4:$P$49,MATCH($C10,$C$4:$C$49,0),0) -> 100 | J10: =HLOOKUP(J$4,tab!$E$4:$P$49,MATCH($C10,$C$4:$C$49,0),0) -> 100 | K10: =HLOOKUP(K$4,tab!$E$4:$P$49,MATCH($C10,$C$4:$C$49,0),0) -> 100 | L10: =HLOOKUP(L$4,tab!$E$4:$P$49,MATCH($C10,$C$4:$C$49,0),0) -> 100
A11: 2024 | B11: =tab!B11 -> + | C11: =tab!C11 -> Impostos Não Pagos em Discussão Judicial; | E11: =HLOOKUP(E$4,tab!$E$4:$P$49,MATCH($C11,$C$4:$C$49,0),0) -> 0 | F11: =HLOOKUP(F$4,tab!$E$4:$P$49,MATCH($C11,$C$4:$C$49,0),0) -> 0 | G11: =HLOOKUP(G$4,tab!$E$4:$P$49,MATCH($C11,$C$4:$C$49,0),0) -> 0 | H11: =HLOOKUP(H$4,tab!$E$4:$P$49,MATCH($C11,$C$4:$C$49,0),0) -> 0 | I11: =HLOOKUP(I$4,tab!$E$4:$P$49,MATCH($C11,$C$4:$C$49,0),0) -> 0 | J11: =HLOOKUP(J$4,tab!$E$4:$P$49,MATCH($C11,$C$4:$C$49,0),0) -> 0 | K11: =HLOOKUP(K$4,tab!$E$4:$P$49,MATCH($C11,$C$4:$C$49,0),0) -> 0 | L11: =HLOOKUP(L$4,tab!$E$4:$P$49,MATCH($C11,$C$4:$C$49,0),0) -> 0
A12: 2025 | B12: =tab!B12 -> + | C12: =tab!C12 -> Impostos Não Pagos por Iniciativa da Empresa; | E12: =HLOOKUP(E$4,tab!$E$4:$P$49,MATCH($C12,$C$4:$C$49,0),0) -> 0 | F12: =HLOOKUP(F$4,tab!$E$4:$P$49,MATCH($C12,$C$4:$C$49,0),0) -> 0 | G12: =HLOOKUP(G$4,tab!$E$4:$P$49,MATCH($C12,$C$4:$C$49,0),0) -> 0 | H12: =HLOOKUP(H$4,tab!$E$4:$P$49,MATCH($C12,$C$4:$C$49,0),0) -> 0 | I12: =HLOOKUP(I$4,tab!$E$4:$P$49,MATCH($C12,$C$4:$C$49,0),0) -> 0 | J12: =HLOOKUP(J$4,tab!$E$4:$P$49,MATCH($C12,$C$4:$C$49,0),0) -> 0 | K12: =HLOOKUP(K$4,tab!$E$4:$P$49,MATCH($C12,$C$4:$C$49,0),0) -> 0 | L12: =HLOOKUP(L$4,tab!$E$4:$P$49,MATCH($C12,$C$4:$C$49,0),0) -> 0
A13: 2026 | B13: =tab!B13 -> + | C13: =tab!C13 -> Lucro Inflacionário apurado até 31/12/1995; | E13: =HLOOKUP(E$4,tab!$E$4:$P$49,MATCH($C13,$C$4:$C$49,0),0) -> 0 | F13: =HLOOKUP(F$4,tab!$E$4:$P$49,MATCH($C13,$C$4:$C$49,0),0) -> 0 | G13: =HLOOKUP(G$4,tab!$E$4:$P$49,MATCH($C13,$C$4:$C$49,0),0) -> 0 | H13: =HLOOKUP(H$4,tab!$E$4:$P$49,MATCH($C13,$C$4:$C$49,0),0) -> 0 | I13: =HLOOKUP(I$4,tab!$E$4:$P$49,MATCH($C13,$C$4:$C$49,0),0) -> 0 | J13: =HLOOKUP(J$4,tab!$E$4:$P$49,MATCH($C13,$C$4:$C$49,0),0) -> 0 | K13: =HLOOKUP(K$4,tab!$E$4:$P$49,MATCH($C13,$C$4:$C$49,0),0) -> 0 | L13: =HLOOKUP(L$4,tab!$E$4:$P$49,MATCH($C13,$C$4:$C$49,0),0) -> 0
A14: 2027 | B14: =tab!B14 -> + | C14: =tab!C14 -> Multas Contratuais | E14: =HLOOKUP(E$4,tab!$E$4:$P$49,MATCH($C14,$C$4:$C$49,0),0) -> 0 | F14: =HLOOKUP(F$4,tab!$E$4:$P$49,MATCH($C14,$C$4:$C$49,0),0) -> 0 | G14: =HLOOKUP(G$4,tab!$E$4:$P$49,MATCH($C14,$C$4:$C$49,0),0) -> 0 | H14: =HLOOKUP(H$4,tab!$E$4:$P$49,MATCH($C14,$C$4:$C$49,0),0) -> 0 | I14: =HLOOKUP(I$4,tab!$E$4:$P$49,MATCH($C14,$C$4:$C$49,0),0) -> 0 | J14: =HLOOKUP(J$4,tab!$E$4:$P$49,MATCH($C14,$C$4:$C$49,0),0) -> 0 | K14: =HLOOKUP(K$4,tab!$E$4:$P$49,MATCH($C14,$C$4:$C$49,0),0) -> 0 | L14: =HLOOKUP(L$4,tab!$E$4:$P$49,MATCH($C14,$C$4:$C$49,0),0) -> 0
A15: 2028 | B15: =tab!B15 -> + | C15: =tab!C15 -> Multas Punitivas (Transito, Imetro, Ibama, Multas sobre ação fiscal) | E15: =HLOOKUP(E$4,tab!$E$4:$P$49,MATCH($C15,$C$4:$C$49,0),0) -> 500 | F15: =HLOOKUP(F$4,tab!$E$4:$P$49,MATCH($C15,$C$4:$C$49,0),0) -> 500 | G15: =HLOOKUP(G$4,tab!$E$4:$P$49,MATCH($C15,$C$4:$C$49,0),0) -> 500 | H15: =HLOOKUP(H$4,tab!$E$4:$P$49,MATCH($C15,$C$4:$C$49,0),0) -> 500 | I15: =HLOOKUP(I$4,tab!$E$4:$P$49,MATCH($C15,$C$4:$C$49,0),0) -> 500 | J15: =HLOOKUP(J$4,tab!$E$4:$P$49,MATCH($C15,$C$4:$C$49,0),0) -> 500 | K15: =HLOOKUP(K$4,tab!$E$4:$P$49,MATCH($C15,$C$4:$C$49,0),0) -> 500 | L15: =HLOOKUP(L$4,tab!$E$4:$P$49,MATCH($C15,$C$4:$C$49,0),0) -> 500
A16: 2029 | B16: =tab!B16 -> + | C16: =tab!C16 -> Orçamentos, Pedidos e qualquer documento não idôneo; | E16: =HLOOKUP(E$4,tab!$E$4:$P$49,MATCH($C16,$C$4:$C$49,0),0) -> 0 | F16: =HLOOKUP(F$4,tab!$E$4:$P$49,MATCH($C16,$C$4:$C$49,0),0) -> 0 | G16: =HLOOKUP(G$4,tab!$E$4:$P$49,MATCH($C16,$C$4:$C$49,0),0) -> 0 | H16: =HLOOKUP(H$4,tab!$E$4:$P$49,MATCH($C16,$C$4:$C$49,0),0) -> 0 | I16: =HLOOKUP(I$4,tab!$E$4:$P$49,MATCH($C16,$C$4:$C$49,0),0) -> 0 | J16: =HLOOKUP(J$4,tab!$E$4:$P$49,MATCH($C16,$C$4:$C$49,0),0) -> 0 | K16: =HLOOKUP(K$4,tab!$E$4:$P$49,MATCH($C16,$C$4:$C$49,0),0) -> 0 | L16: =HLOOKUP(L$4,tab!$E$4:$P$49,MATCH($C16,$C$4:$C$49,0),0) -> 0
A17: 2030 | B17: =tab!B17 -> + | C17: =tab!C17 -> Provisões Indedutíveis (perdas, frete, propaganda) | E17: =HLOOKUP(E$4,tab!$E$4:$P$49,MATCH($C17,$C$4:$C$49,0),0) -> 0 | F17: =HLOOKUP(F$4,tab!$E$4:$P$49,MATCH($C17,$C$4:$C$49,0),0) -> 0 | G17: =HLOOKUP(G$4,tab!$E$4:$P$49,MATCH($C17,$C$4:$C$49,0),0) -> 0 | H17: =HLOOKUP(H$4,tab!$E$4:$P$49,MATCH($C17,$C$4:$C$49,0),0) -> 0 | I17: =HLOOKUP(I$4,tab!$E$4:$P$49,MATCH($C17,$C$4:$C$49,0),0) -> 0 | J17: =HLOOKUP(J$4,tab!$E$4:$P$49,MATCH($C17,$C$4:$C$49,0),0) -> 0 | K17: =HLOOKUP(K$4,tab!$E$4:$P$49,MATCH($C17,$C$4:$C$49,0),0) -> 0 | L17: =HLOOKUP(L$4,tab!$E$4:$P$49,MATCH($C17,$C$4:$C$49,0),0) -> 0
B18: =tab!B18 -> + | C18: =tab!C18 -> Recibos sem especificação da fonte recebedora; | E18: =HLOOKUP(E$4,tab!$E$4:$P$49,MATCH($C18,$C$4:$C$49,0),0) -> 0 | F18: =HLOOKUP(F$4,tab!$E$4:$P$49,MATCH($C18,$C$4:$C$49,0),0) -> 0 | G18: =HLOOKUP(G$4,tab!$E$4:$P$49,MATCH($C18,$C$4:$C$49,0),0) -> 0 | H18: =HLOOKUP(H$4,tab!$E$4:$P$49,MATCH($C18,$C$4:$C$49,0),0) -> 0 | I18: =HLOOKUP(I$4,tab!$E$4:$P$49,MATCH($C18,$C$4:$C$49,0),0) -> 0 | J18: =HLOOKUP(J$4,tab!$E$4:$P$49,MATCH($C18,$C$4:$C$49,0),0) -> 0 | K18: =HLOOKUP(K$4,tab!$E$4:$P$49,MATCH($C18,$C$4:$C$49,0),0) -> 0 | L18: =HLOOKUP(L$4,tab!$E$4:$P$49,MATCH($C18,$C$4:$C$49,0),0) -> 0
B19: =tab!B19 -> + | C19: =tab!C19 -> Verbas Rescisórias em desacordo com a legislação trabalhista vigente | E19: =HLOOKUP(E$4,tab!$E$4:$P$49,MATCH($C19,$C$4:$C$49,0),0) -> 0 | F19: =HLOOKUP(F$4,tab!$E$4:$P$49,MATCH($C19,$C$4:$C$49,0),0) -> 0 | G19: =HLOOKUP(G$4,tab!$E$4:$P$49,MATCH($C19,$C$4:$C$49,0),0) -> 0 | H19: =HLOOKUP(H$4,tab!$E$4:$P$49,MATCH($C19,$C$4:$C$49,0),0) -> 0 | I19: =HLOOKUP(I$4,tab!$E$4:$P$49,MATCH($C19,$C$4:$C$49,0),0) -> 0 | J19: =HLOOKUP(J$4,tab!$E$4:$P$49,MATCH($C19,$C$4:$C$49,0),0) -> 0 | K19: =HLOOKUP(K$4,tab!$E$4:$P$49,MATCH($C19,$C$4:$C$49,0),0) -> 0 | L19: =HLOOKUP(L$4,tab!$E$4:$P$49,MATCH($C19,$C$4:$C$49,0),0) -> 0
B20: =tab!B20 -> = | C20: =tab!C20 -> Exclusões | E20: =SUM(E21:E33) -> -1000 | F20: =SUM(F21:F33) -> -1000 | G20: =SUM(G21:G33) -> -1000 | H20: =SUM(H21:H33) -> -1000 | I20: =SUM(I21:I33) -> -1000 | J20: =SUM(J21:J33) -> -1000 | K20: =SUM(K21:K33) -> -1000 | L20: =SUM(L21:L33) -> -1000
B21: =tab!B21 -> - | C21: =tab!C21 -> Ajustes credores de qualquer natureza | E21: =HLOOKUP(E$4,tab!$E$4:$P$49,MATCH($C21,$C$4:$C$49,0),0) -> 0 | F21: =HLOOKUP(F$4,tab!$E$4:$P$49,MATCH($C21,$C$4:$C$49,0),0) -> 0 | G21: =HLOOKUP(G$4,tab!$E$4:$P$49,MATCH($C21,$C$4:$C$49,0),0) -> 0 | H21: =HLOOKUP(H$4,tab!$E$4:$P$49,MATCH($C21,$C$4:$C$49,0),0) -> 0 | I21: =HLOOKUP(I$4,tab!$E$4:$P$49,MATCH($C21,$C$4:$C$49,0),0) -> 0 | J21: =HLOOKUP(J$4,tab!$E$4:$P$49,MATCH($C21,$C$4:$C$49,0),0) -> 0 | K21: =HLOOKUP(K$4,tab!$E$4:$P$49,MATCH($C21,$C$4:$C$49,0),0) -> 0 | L21: =HLOOKUP(L$4,tab!$E$4:$P$49,MATCH($C21,$C$4:$C$49,0),0) -> 0
B22: =tab!B22 -> - | C22: =tab!C22 -> Decisão Favorável - Processos Judiciais Tributários | E22: =HLOOKUP(E$4,tab!$E$4:$P$49,MATCH($C22,$C$4:$C$49,0),0) -> 0 | F22: =HLOOKUP(F$4,tab!$E$4:$P$49,MATCH($C22,$C$4:$C$49,0),0) -> 0 | G22: =HLOOKUP(G$4,tab!$E$4:$P$49,MATCH($C22,$C$4:$C$49,0),0) -> 0 | H22: =HLOOKUP(H$4,tab!$E$4:$P$49,MATCH($C22,$C$4:$C$49,0),0) -> 0 | I22: =HLOOKUP(I$4,tab!$E$4:$P$49,MATCH($C22,$C$4:$C$49,0),0) -> 0 | J22: =HLOOKUP(J$4,tab!$E$4:$P$49,MATCH($C22,$C$4:$C$49,0),0) -> 0 | K22: =HLOOKUP(K$4,tab!$E$4:$P$49,MATCH($C22,$C$4:$C$49,0),0) -> 0 | L22: =HLOOKUP(L$4,tab!$E$4:$P$49,MATCH($C22,$C$4:$C$49,0),0) -> 0
B23: =tab!B23 -> - | C23: =tab!C23 -> Despesas de Ágios | E23: =HLOOKUP(E$4,tab!$E$4:$P$49,MATCH($C23,$C$4:$C$49,0),0) -> 0 | F23: =HLOOKUP(F$4,tab!$E$4:$P$49,MATCH($C23,$C$4:$C$49,0),0) -> 0 | G23: =HLOOKUP(G$4,tab!$E$4:$P$49,MATCH($C23,$C$4:$C$49,0),0) -> 0 | H23: =HLOOKUP(H$4,tab!$E$4:$P$49,MATCH($C23,$C$4:$C$49,0),0) -> 0 | I23: =HLOOKUP(I$4,tab!$E$4:$P$49,MATCH($C23,$C$4:$C$49,0),0) -> 0 | J23: =HLOOKUP(J$4,tab!$E$4:$P$49,MATCH($C23,$C$4:$C$49,0),0) -> 0 | K23: =HLOOKUP(K$4,tab!$E$4:$P$49,MATCH($C23,$C$4:$C$49,0),0) -> 0 | L23: =HLOOKUP(L$4,tab!$E$4:$P$49,MATCH($C23,$C$4:$C$49,0),0) -> 0
B24: =tab!B24 -> - | C24: =tab!C24 -> Distribuição de Lucros e Dividendos; | E24: =HLOOKUP(E$4,tab!$E$4:$P$49,MATCH($C24,$C$4:$C$49,0),0) -> 0 | F24: =HLOOKUP(F$4,tab!$E$4:$P$49,MATCH($C24,$C$4:$C$49,0),0) -> 0 | G24: =HLOOKUP(G$4,tab!$E$4:$P$49,MATCH($C24,$C$4:$C$49,0),0) -> 0 | H24: =HLOOKUP(H$4,tab!$E$4:$P$49,MATCH($C24,$C$4:$C$49,0),0) -> 0 | I24: =HLOOKUP(I$4,tab!$E$4:$P$49,MATCH($C24,$C$4:$C$49,0),0) -> 0 | J24: =HLOOKUP(J$4,tab!$E$4:$P$49,MATCH($C24,$C$4:$C$49,0),0) -> 0 | K24: =HLOOKUP(K$4,tab!$E$4:$P$49,MATCH($C24,$C$4:$C$49,0),0) -> 0 | L24: =HLOOKUP(L$4,tab!$E$4:$P$49,MATCH($C24,$C$4:$C$49,0),0) -> 0
B25: =tab!B25 -> - | C25: =tab!C25 -> Dividendos Coligadas e Controladas | E25: =HLOOKUP(E$4,tab!$E$4:$P$49,MATCH($C25,$C$4:$C$49,0),0) -> 0 | F25: =HLOOKUP(F$4,tab!$E$4:$P$49,MATCH($C25,$C$4:$C$49,0),0) -> 0 | G25: =HLOOKUP(G$4,tab!$E$4:$P$49,MATCH($C25,$C$4:$C$49,0),0) -> 0 | H25: =HLOOKUP(H$4,tab!$E$4:$P$49,MATCH($C25,$C$4:$C$49,0),0) -> 0 | I25: =HLOOKUP(I$4,tab!$E$4:$P$49,MATCH($C25,$C$4:$C$49,0),0) -> 0 | J25: =HLOOKUP(J$4,tab!$E$4:$P$49,MATCH($C25,$C$4:$C$49,0),0) -> 0 | K25: =HLOOKUP(K$4,tab!$E$4:$P$49,MATCH($C25,$C$4:$C$49,0),0) -> 0 | L25: =HLOOKUP(L$4,tab!$E$4:$P$49,MATCH($C25,$C$4:$C$49,0),0) -> 0
B26: =tab!B26 -> - | C26: =tab!C26 -> Pagamento de Impostos em Atraso por iniciativa da Empresa | E26: =HLOOKUP(E$4,tab!$E$4:$P$49,MATCH($C26,$C$4:$C$49,0),0) -> -1000 | F26: =HLOOKUP(F$4,tab!$E$4:$P$49,MATCH($C26,$C$4:$C$49,0),0) -> -1000 | G26: =HLOOKUP(G$4,tab!$E$4:$P$49,MATCH($C26,$C$4:$C$49,0),0) -> -1000 | H26: =HLOOKUP(H$4,tab!$E$4:$P$49,MATCH($C26,$C$4:$C$49,0),0) -> -1000 | I26: =HLOOKUP(I$4,tab!$E$4:$P$49,MATCH($C26,$C$4:$C$49,0),0) -> -1000 | J26: =HLOOKUP(J$4,tab!$E$4:$P$49,MATCH($C26,$C$4:$C$49,0),0) -> -1000 | K26: =HLOOKUP(K$4,tab!$E$4:$P$49,MATCH($C26,$C$4:$C$49,0),0) -> -1000 | L26: =HLOOKUP(L$4,tab!$E$4:$P$49,MATCH($C26,$C$4:$C$49,0),0) -> -1000
B27: =tab!B27 -> - | C27: =tab!C27 -> Pagamento de Impostos sobre discussão judicial, | E27: =HLOOKUP(E$4,tab!$E$4:$P$49,MATCH($C27,$C$4:$C$49,0),0) -> 0 | F27: =HLOOKUP(F$4,tab!$E$4:$P$49,MATCH($C27,$C$4:$C$49,0),0) -> 0 | G27: =HLOOKUP(G$4,tab!$E$4:$P$49,MATCH($C27,$C$4:$C$49,0),0) -> 0 | H27: =HLOOKUP(H$4,tab!$E$4:$P$49,MATCH($C27,$C$4:$C$49,0),0) -> 0 | I27: =HLOOKUP(I$4,tab!$E$4:$P$49,MATCH($C27,$C$4:$C$49,0),0) -> 0 | J27: =HLOOKUP(J$4,tab!$E$4:$P$49,MATCH($C27,$C$4:$C$49,0),0) -> 0 | K27: =HLOOKUP(K$4,tab!$E$4:$P$49,MATCH($C27,$C$4:$C$49,0),0) -> 0 | L27: =HLOOKUP(L$4,tab!$E$4:$P$49,MATCH($C27,$C$4:$C$49,0),0) -> 0
B28: =tab!B28 -> - | C28: =tab!C28 -> Receita de Variação Cambial | E28: =HLOOKUP(E$4,tab!$E$4:$P$49,MATCH($C28,$C$4:$C$49,0),0) -> 0 | F28: =HLOOKUP(F$4,tab!$E$4:$P$49,MATCH($C28,$C$4:$C$49,0),0) -> 0 | G28: =HLOOKUP(G$4,tab!$E$4:$P$49,MATCH($C28,$C$4:$C$49,0),0) -> 0 | H28: =HLOOKUP(H$4,tab!$E$4:$P$49,MATCH($C28,$C$4:$C$49,0),0) -> 0 | I28: =HLOOKUP(I$4,tab!$E$4:$P$49,MATCH($C28,$C$4:$C$49,0),0) -> 0 | J28: =HLOOKUP(J$4,tab!$E$4:$P$49,MATCH($C28,$C$4:$C$49,0),0) -> 0 | K28: =HLOOKUP(K$4,tab!$E$4:$P$49,MATCH($C28,$C$4:$C$49,0),0) -> 0 | L28: =HLOOKUP(L$4,tab!$E$4:$P$49,MATCH($C28,$C$4:$C$49,0),0) -> 0
B29: =tab!B29 -> - | C29: =tab!C29 -> Receitas Obtidas com Tributação Exclusiva ou Isenta de IR | E29: =HLOOKUP(E$4,tab!$E$4:$P$49,MATCH($C29,$C$4:$C$49,0),0) -> 0 | F29: =HLOOKUP(F$4,tab!$E$4:$P$49,MATCH($C29,$C$4:$C$49,0),0) -> 0 | G29: =HLOOKUP(G$4,tab!$E$4:$P$49,MATCH($C29,$C$4:$C$49,0),0) -> 0 | H29: =HLOOKUP(H$4,tab!$E$4:$P$49,MATCH($C29,$C$4:$C$49,0),0) -> 0 | I29: =HLOOKUP(I$4,tab!$E$4:$P$49,MATCH($C29,$C$4:$C$49,0),0) -> 0 | J29: =HLOOKUP(J$4,tab!$E$4:$P$49,MATCH($C29,$C$4:$C$49,0),0) -> 0 | K29: =HLOOKUP(K$4,tab!$E$4:$P$49,MATCH($C29,$C$4:$C$49,0),0) -> 0 | L29: =HLOOKUP(L$4,tab!$E$4:$P$49,MATCH($C29,$C$4:$C$49,0),0) -> 0
B30: =tab!B30 -> - | C30: =tab!C30 -> Receitas que poderiam ser diferidas; | E30: =HLOOKUP(E$4,tab!$E$4:$P$49,MATCH($C30,$C$4:$C$49,0),0) -> 0 | F30: =HLOOKUP(F$4,tab!$E$4:$P$49,MATCH($C30,$C$4:$C$49,0),0) -> 0 | G30: =HLOOKUP(G$4,tab!$E$4:$P$49,MATCH($C30,$C$4:$C$49,0),0) -> 0 | H30: =HLOOKUP(H$4,tab!$E$4:$P$49,MATCH($C30,$C$4:$C$49,0),0) -> 0 | I30: =HLOOKUP(I$4,tab!$E$4:$P$49,MATCH($C30,$C$4:$C$49,0),0) -> 0 | J30: =HLOOKUP(J$4,tab!$E$4:$P$49,MATCH($C30,$C$4:$C$49,0),0) -> 0 | K30: =HLOOKUP(K$4,tab!$E$4:$P$49,MATCH($C30,$C$4:$C$49,0),0) -> 0 | L30: =HLOOKUP(L$4,tab!$E$4:$P$49,MATCH($C30,$C$4:$C$49,0),0) -> 0
B31: =tab!B31 -> - | C31: =tab!C31 -> Resultado Positivo de Equivalência Patrimonial | E31: =HLOOKUP(E$4,tab!$E$4:$P$49,MATCH($C31,$C$4:$C$49,0),0) -> 0 | F31: =HLOOKUP(F$4,tab!$E$4:$P$49,MATCH($C31,$C$4:$C$49,0),0) -> 0 | G31: =HLOOKUP(G$4,tab!$E$4:$P$49,MATCH($C31,$C$4:$C$49,0),0) -> 0 | H31: =HLOOKUP(H$4,tab!$E$4:$P$49,MATCH($C31,$C$4:$C$49,0),0) -> 0 | I31: =HLOOKUP(I$4,tab!$E$4:$P$49,MATCH($C31,$C$4:$C$49,0),0) -> 0 | J31: =HLOOKUP(J$4,tab!$E$4:$P$49,MATCH($C31,$C$4:$C$49,0),0) -> 0 | K31: =HLOOKUP(K$4,tab!$E$4:$P$49,MATCH($C31,$C$4:$C$49,0),0) -> 0 | L31: =HLOOKUP(L$4,tab!$E$4:$P$49,MATCH($C31,$C$4:$C$49,0),0) -> 0
B32: =tab!B32 -> - | C32: =tab!C32 -> Reversão de Provisões Indedutíveis | E32: =HLOOKUP(E$4,tab!$E$4:$P$49,MATCH($C32,$C$4:$C$49,0),0) -> 0 | F32: =HLOOKUP(F$4,tab!$E$4:$P$49,MATCH($C32,$C$4:$C$49,0),0) -> 0 | G32: =HLOOKUP(G$4,tab!$E$4:$P$49,MATCH($C32,$C$4:$C$49,0),0) -> 0 | H32: =HLOOKUP(H$4,tab!$E$4:$P$49,MATCH($C32,$C$4:$C$49,0),0) -> 0 | I32: =HLOOKUP(I$4,tab!$E$4:$P$49,MATCH($C32,$C$4:$C$49,0),0) -> 0 | J32: =HLOOKUP(J$4,tab!$E$4:$P$49,MATCH($C32,$C$4:$C$49,0),0) -> 0 | K32: =HLOOKUP(K$4,tab!$E$4:$P$49,MATCH($C32,$C$4:$C$49,0),0) -> 0 | L32: =HLOOKUP(L$4,tab!$E$4:$P$49,MATCH($C32,$C$4:$C$49,0),0) -> 0
B33: =tab!B33 -> - | C33: =tab!C33 -> Vendas Não Expedidas do Período | E33: =HLOOKUP(E$4,tab!$E$4:$P$49,MATCH($C33,$C$4:$C$49,0),0) -> 0 | F33: =HLOOKUP(F$4,tab!$E$4:$P$49,MATCH($C33,$C$4:$C$49,0),0) -> 0 | G33: =HLOOKUP(G$4,tab!$E$4:$P$49,MATCH($C33,$C$4:$C$49,0),0) -> 0 | H33: =HLOOKUP(H$4,tab!$E$4:$P$49,MATCH($C33,$C$4:$C$49,0),0) -> 0 | I33: =HLOOKUP(I$4,tab!$E$4:$P$49,MATCH($C33,$C$4:$C$49,0),0) -> 0 | J33: =HLOOKUP(J$4,tab!$E$4:$P$49,MATCH($C33,$C$4:$C$49,0),0) -> 0 | K33: =HLOOKUP(K$4,tab!$E$4:$P$49,MATCH($C33,$C$4:$C$49,0),0) -> 0 | L33: =HLOOKUP(L$4,tab!$E$4:$P$49,MATCH($C33,$C$4:$C$49,0),0) -> 0
B34: =tab!B34 -> = | C34: =tab!C34 -> Base de Cálculo | E34: =SUM(E5,E6,E20) -> 600 | F34: =SUM(F5,F6,F20) -> 25600 | G34: =SUM(G5,G6,G20) -> 50600 | H34: =SUM(H5,H6,H20) -> 75600 | I34: =SUM(I5,I6,I20) -> 100600 | J34: =SUM(J5,J6,J20) -> 125600 | K34: =SUM(K5,K6,K20) -> 150600 | L34: =SUM(L5,L6,L20) -> 175600
B35: =tab!B35 -> = | C35: =tab!C35 -> Saldo Prejuízo Fiscal | E35: =tab!E35 -> 45000 | F35: =SUM(E35:E36) -> 44820 | G35: =SUM(F35:F36) -> 37140 | H35: =SUM(G35:G36) -> 21960 | I35: =SUM(H35:H36) -> 0 | J35: =SUM(I35:I36) -> 0 | K35: =SUM(J35:J36) -> 0 | L35: =SUM(K35:K36) -> 0
B36: =tab!B36 -> % | C36: =tab!C36 -> Compensação de Prejuízo Fiscal | D36: =tab!D36 -> 0.3 | E36: =-IF(AND(E35>0,E34*$D$36<E35),E34*$D$36,E35) -> -180 | F36: =-IF(AND(F35>0,F34*$D$36<F35),F34*$D$36,F35) -> -7680 | G36: =-IF(AND(G35>0,G34*$D$36<G35),G34*$D$36,G35) -> -15180 | H36: =-IF(AND(H35>0,H34*$D$36<H35),H34*$D$36,H35) -> -21960 | I36: =-IF(AND(I35>0,I34*$D$36<I35),I34*$D$36,I35) -> 0 | J36: =-IF(AND(J35>0,J34*$D$36<J35),J34*$D$36,J35) -> 0 | K36: =-IF(AND(K35>0,K34*$D$36<K35),K34*$D$36,K35) -> 0 | L36: =-IF(AND(L35>0,L34*$D$36<L35),L34*$D$36,L35) -> 0
B37: =tab!B37 -> % | C37: =tab!C37 -> Adicional de Imposto de Renda | D37: =tab!D37 -> 0.1 | E37: =HLOOKUP($E$4,INDIRECT($E$4&"!$E$4:$O$49"),MATCH(C37,INDIRECT($E$4&"!$C$4:$C$49"),0),0) -> 0 | F37: =IF(SUM(F34,F36)>20000*$A$4,(SUM(F34,F36)-20000*$A$4)*$D$37,0) -> 0 | G37: =IF(SUM(G34,G36)>20000*$A$4,(SUM(G34,G36)-20000*$A$4)*$D$37,0) -> 0 | H37: =IF(SUM(H34,H36)>20000*$A$4,(SUM(H34,H36)-20000*$A$4)*$D$37,0) -> 0 | I37: =IF(SUM(I34,I36)>20000*$A$4,(SUM(I34,I36)-20000*$A$4)*$D$37,0) -> 0 | J37: =IF(SUM(J34,J36)>20000*$A$4,(SUM(J34,J36)-20000*$A$4)*$D$37,0) -> 0 | K37: =IF(SUM(K34,K36)>20000*$A$4,(SUM(K34,K36)-20000*$A$4)*$D$37,0) -> 0 | L37: =IF(SUM(L34,L36)>20000*$A$4,(SUM(L34,L36)-20000*$A$4)*$D$37,0) -> 1560
B38: =tab!B38 -> % | C38: =tab!C38 -> Imposto de Renda | D38: =tab!D38 -> 0.15 | E38: =SUM(E34,E36)*$D$38 -> 63 | F38: =SUM(F34,F36)*$D$38 -> 2688 | G38: =SUM(G34,G36)*$D$38 -> 5313 | H38: =SUM(H34,H36)*$D$38 -> 8046 | I38: =SUM(I34,I36)*$D$38 -> 15090 | J38: =SUM(J34,J36)*$D$38 -> 18840 | K38: =SUM(K34,K36)*$D$38 -> 22590 | L38: =SUM(L34,L36)*$D$38 -> 26340
B39: =tab!B39 -> % | C39: =tab!C39 -> Contribuição Social | D39: =tab!D39 -> 0.09 | E39: =SUM(E34,E36)*$D$39 -> 37.8 | F39: =SUM(F34,F36)*$D$39 -> 1612.8 | G39: =SUM(G34,G36)*$D$39 -> 3187.8 | H39: =SUM(H34,H36)*$D$39 -> 4827.6 | I39: =SUM(I34,I36)*$D$39 -> 9054 | J39: =SUM(J34,J36)*$D$39 -> 11304 | K39: =SUM(K34,K36)*$D$39 -> 13554 | L39: =SUM(L34,L36)*$D$39 -> 15804
B40: =tab!B40 -> = | C40: =tab!C40 -> Compensações | E40: =SUM(E42:E47) -> -3600 | F40: =SUM(F42:F47) -> -3600 | G40: =SUM(G42:G47) -> -4300.8 | H40: =SUM(H42:H47) -> -8500.8 | I40: =SUM(I42:I47) -> -12873.6 | J40: =SUM(J42:J47) -> -24144 | K40: =SUM(K42:K47) -> -30144 | L40: =SUM(L42:L47) -> -36144
B41: =tab!B41 -> - | C41: =tab!C41 -> IR Base Negativa Exercícios Anteriores | D41: =LEFT(C41,2) -> IR | E41: =HLOOKUP(E$4,tab!$E$4:$P$49,MATCH($C41,$C$4:$C$49,0),0) -> 0 | F41: =HLOOKUP(F$4,tab!$E$4:$P$49,MATCH($C41,$C$4:$C$49,0),0) -> 0 | G41: =HLOOKUP(G$4,tab!$E$4:$P$49,MATCH($C41,$C$4:$C$49,0),0) -> 0 | H41: =HLOOKUP(H$4,tab!$E$4:$P$49,MATCH($C41,$C$4:$C$49,0),0) -> 0 | I41: =HLOOKUP(I$4,tab!$E$4:$P$49,MATCH($C41,$C$4:$C$49,0),0) -> 0 | J41: =HLOOKUP(J$4,tab!$E$4:$P$49,MATCH($C41,$C$4:$C$49,0),0) -> 0 | K41: =HLOOKUP(K$4,tab!$E$4:$P$49,MATCH($C41,$C$4:$C$49,0),0) -> 0 | L41: =HLOOKUP(L$4,tab!$E$4:$P$49,MATCH($C41,$C$4:$C$49,0),0) -> 0
B42: =tab!B42 -> - | C42: =tab!C42 -> IR s/ Aplicações Financeiras | D42: =LEFT(C42,2) -> IR | E42: =HLOOKUP(E$4,tab!$E$4:$P$49,MATCH($C42,$C$4:$C$49,0),0) -> -100 | F42: =HLOOKUP(F$4,tab!$E$4:$P$49,MATCH($C42,$C$4:$C$49,0),0) -> -100 | G42: =HLOOKUP(G$4,tab!$E$4:$P$49,MATCH($C42,$C$4:$C$49,0),0) -> -100 | H42: =HLOOKUP(H$4,tab!$E$4:$P$49,MATCH($C42,$C$4:$C$49,0),0) -> -100 | I42: =HLOOKUP(I$4,tab!$E$4:$P$49,MATCH($C42,$C$4:$C$49,0),0) -> -100 | J42: =HLOOKUP(J$4,tab!$E$4:$P$49,MATCH($C42,$C$4:$C$49,0),0) -> -100 | K42: =HLOOKUP(K$4,tab!$E$4:$P$49,MATCH($C42,$C$4:$C$49,0),0) -> -100 | L42: =HLOOKUP(L$4,tab!$E$4:$P$49,MATCH($C42,$C$4:$C$49,0),0) -> -100
B43: =tab!B43 -> - | C43: =tab!C43 -> IR Retida s/ Notas Fiscais | D43: =LEFT(C43,2) -> IR | E43: =HLOOKUP(E$4,tab!$E$4:$P$49,MATCH($C43,$C$4:$C$49,0),0) -> -2000 | F43: =HLOOKUP(F$4,tab!$E$4:$P$49,MATCH($C43,$C$4:$C$49,0),0) -> -2000 | G43: =HLOOKUP(G$4,tab!$E$4:$P$49,MATCH($C43,$C$4:$C$49,0),0) -> -2000 | H43: =HLOOKUP(H$4,tab!$E$4:$P$49,MATCH($C43,$C$4:$C$49,0),0) -> -2000 | I43: =HLOOKUP(I$4,tab!$E$4:$P$49,MATCH($C43,$C$4:$C$49,0),0) -> -2000 | J43: =HLOOKUP(J$4,tab!$E$4:$P$49,MATCH($C43,$C$4:$C$49,0),0) -> -2000 | K43: =HLOOKUP(K$4,tab!$E$4:$P$49,MATCH($C43,$C$4:$C$49,0),0) -> -2000 | L43: =HLOOKUP(L$4,tab!$E$4:$P$49,MATCH($C43,$C$4:$C$49,0),0) -> -2000
B44: =tab!B44 -> - | C44: =tab!C44 -> IR Pago no Exercício | D44: =LEFT(C44,2) -> IR | E44: =HLOOKUP(E$4,tab!$E$4:$P$49,MATCH($C44,$C$4:$C$49,0),0) -> 0 | F44: =-E48 -> 0 | G44: =-SUM($E$48:F48) -> -588 | H44: =-SUM($E$48:G48) -> -3213 | I44: =-SUM($E$48:H48) -> -5946 | J44: =-SUM($E$48:I48) -> -12990 | K44: =-SUM($E$48:J48) -> -16740 | L44: =-SUM($E$48:K48) -> -20490
B45: =tab!B45 -> - | C45: =tab!C45 -> CS Base Negativa Exercícios Anteriores | D45: =LEFT(C45,2) -> CS | E45: =HLOOKUP(E$4,tab!$E$4:$P$49,MATCH($C45,$C$4:$C$49,0),0) -> 0 | F45: =HLOOKUP(F$4,tab!$E$4:$P$49,MATCH($C45,$C$4:$C$49,0),0) -> 0 | G45: =HLOOKUP(G$4,tab!$E$4:$P$49,MATCH($C45,$C$4:$C$49,0),0) -> 0 | H45: =HLOOKUP(H$4,tab!$E$4:$P$49,MATCH($C45,$C$4:$C$49,0),0) -> 0 | I45: =HLOOKUP(I$4,tab!$E$4:$P$49,MATCH($C45,$C$4:$C$49,0),0) -> 0 | J45: =HLOOKUP(J$4,tab!$E$4:$P$49,MATCH($C45,$C$4:$C$49,0),0) -> 0 | K45: =HLOOKUP(K$4,tab!$E$4:$P$49,MATCH($C45,$C$4:$C$49,0),0) -> 0 | L45: =HLOOKUP(L$4,tab!$E$4:$P$49,MATCH($C45,$C$4:$C$49,0),0) -> 0
B46: =tab!B46 -> - | C46: =tab!C46 -> CS Retida s/ Notas Fiscais | D46: =LEFT(C46,2) -> CS | E46: =HLOOKUP(E$4,tab!$E$4:$P$49,MATCH($C46,$C$4:$C$49,0),0) -> -1500 | F46: =HLOOKUP(F$4,tab!$E$4:$P$49,MATCH($C46,$C$4:$C$49,0),0) -> -1500 | G46: =HLOOKUP(G$4,tab!$E$4:$P$49,MATCH($C46,$C$4:$C$49,0),0) -> -1500 | H46: =HLOOKUP(H$4,tab!$E$4:$P$49,MATCH($C46,$C$4:$C$49,0),0) -> -1500 | I46: =HLOOKUP(I$4,tab!$E$4:$P$49,MATCH($C46,$C$4:$C$49,0),0) -> -1500 | J46: =HLOOKUP(J$4,tab!$E$4:$P$49,MATCH($C46,$C$4:$C$49,0),0) -> -1500 | K46: =HLOOKUP(K$4,tab!$E$4:$P$49,MATCH($C46,$C$4:$C$49,0),0) -> -1500 | L46: =HLOOKUP(L$4,tab!$E$4:$P$49,MATCH($C46,$C$4:$C$49,0),0) -> -1500
B47: =tab!B47 -> - | C47: =tab!C47 -> CS Pago no Exercício | D47: =LEFT(C47,2) -> CS | E47: =HLOOKUP(E$4,tab!$E$4:$P$49,MATCH($C47,$C$4:$C$49,0),0) -> 0 | F47: =-E49 -> 0 | G47: =-SUM($E$49:F49) -> -112.8 | H47: =-SUM($E$49:G49) -> -1687.8 | I47: =-SUM($E$49:H49) -> -3327.6 | J47: =-SUM($E$49:I49) -> -7554 | K47: =-SUM($E$49:J49) -> -9804 | L47: =-SUM($E$49:K49) -> -12054
B48: =tab!B48 -> = | C48: =tab!C48 -> Imposto de Renda a Pagar | E48: =IF(SUM(E37,E38,SUMIF($D$41:E47,"IR",E$41:E$47))>0,SUM(E37,E38,SUMIF($D$41:E47,"IR",E$41:E$47)),0) -> 0 | F48: =IF(SUM(F37,F38,SUMIF($D$41:F47,"IR",F$41:F$47))>0,SUM(F37,F38,SUMIF($D$41:F47,"IR",F$41:F$47)),0) -> 588 | G48: =IF(SUM(G37,G38,SUMIF($D$41:G47,"IR",G$41:G$47))>0,SUM(G37,G38,SUMIF($D$41:G47,"IR",G$41:G$47)),0) -> 2625 | H48: =IF(SUM(H37,H38,SUMIF($D$41:H47,"IR",H$41:H$47))>0,SUM(H37,H38,SUMIF($D$41:H47,"IR",H$41:H$47)),0) -> 2733 | I48: =IF(SUM(I37,I38,SUMIF($D$41:I47,"IR",I$41:I$47))>0,SUM(I37,I38,SUMIF($D$41:I47,"IR",I$41:I$47)),0) -> 7044 | J48: =IF(SUM(J37,J38,SUMIF($D$41:J47,"IR",J$41:J$47))>0,SUM(J37,J38,SUMIF($D$41:J47,"IR",J$41:J$47)),0) -> 3750 | K48: =IF(SUM(K37,K38,SUMIF($D$41:K47,"IR",K$41:K$47))>0,SUM(K37,K38,SUMIF($D$41:K47,"IR",K$41:K$47)),0) -> 3750 | L48: =IF(SUM(L37,L38,SUMIF($D$41:L47,"IR",L$41:L$47))>0,SUM(L37,L38,SUMIF($D$41:L47,"IR",L$41:L$47)),0) -> 5310
B49: =tab!B49 -> = | C49: =tab!C49 -> Contribuição Social a Pagar | E49: =IF(SUM(E39,SUMIF($D$41:E47,"CS",E$41:E$47))>0,SUM(E39,SUMIF($D$41:E47,"CS",E$41:E$47)),0) -> 0 | F49: =IF(SUM(F39,SUMIF($D$41:F47,"CS",F$41:F$47))>0,SUM(F39,SUMIF($D$41:F47,"CS",F$41:F$47)),0) -> 112.8 | G49: =IF(SUM(G39,SUMIF($D$41:G47,"CS",G$41:G$47))>0,SUM(G39,SUMIF($D$41:G47,"CS",G$41:G$47)),0) -> 1575 | H49: =IF(SUM(H39,SUMIF($D$41:H47,"CS",H$41:H$47))>0,SUM(H39,SUMIF($D$41:H47,"CS",H$41:H$47)),0) -> 1639.8 | I49: =IF(SUM(I39,SUMIF($D$41:I47,"CS",I$41:I$47))>0,SUM(I39,SUMIF($D$41:I47,"CS",I$41:I$47)),0) -> 4226.4 | J49: =IF(SUM(J39,SUMIF($D$41:J47,"CS",J$41:J$47))>0,SUM(J39,SUMIF($D$41:J47,"CS",J$41:J$47)),0) -> 2250 | K49: =IF(SUM(K39,SUMIF($D$41:K47,"CS",K$41:K$47))>0,SUM(K39,SUMIF($D$41:K47,"CS",K$41:K$47)),0) -> 2250 | L49: =IF(SUM(L39,SUMIF($D$41:L47,"CS",L$41:L$47))>0,SUM(L39,SUMIF($D$41:L47,"CS",L$41:L$47)),0) -> 2250

Sheet set
B3: 2018
A4: 9 | B4: # | C4: Parâmetros | D4: % | E4: Jan | F4: Fev | G4: Mar | H4: Abr | I4: Mai | J4: Jun | K4: Jul | L4: Ago | M4: Set | N4: Out | O4: Nov | P4: Dez
A5: 2018 | B5: =tab!B5 -> = | C5: =tab!C5 -> Lucro Acumulado | E5: =HLOOKUP(E$4,tab!$E$4:$P$33,MATCH($C5,$C$4:$C$33,0),0) -> 1000 | F5: =HLOOKUP(F$4,tab!$E$4:$P$33,MATCH($C5,$C$4:$C$33,0),0) -> 26000 | G5: =HLOOKUP(G$4,tab!$E$4:$P$33,MATCH($C5,$C$4:$C$33,0),0) -> 51000 | H5: =HLOOKUP(H$4,tab!$E$4:$P$33,MATCH($C5,$C$4:$C$33,0),0) -> 76000 | I5: =HLOOKUP(I$4,tab!$E$4:$P$33,MATCH($C5,$C$4:$C$33,0),0) -> 101000 | J5: =HLOOKUP(J$4,tab!$E$4:$P$33,MATCH($C5,$C$4:$C$33,0),0) -> 126000 | K5: =HLOOKUP(K$4,tab!$E$4:$P$33,MATCH($C5,$C$4:$C$33,0),0) -> 151000 | L5: =HLOOKUP(L$4,tab!$E$4:$P$33,MATCH($C5,$C$4:$C$33,0),0) -> 176000 | M5: =HLOOKUP(M$4,tab!$E$4:$P$33,MATCH($C5,$C$4:$C$33,0),0) -> 201000
A6: 2019 | B6: =tab!B6 -> = | C6: =tab!C6 -> Adições | E6: =SUM(E7:E19) -> 600 | F6: =SUM(F7:F19) -> 600 | G6: =SUM(G7:G19) -> 600 | H6: =SUM(H7:H19) -> 600 | I6: =SUM(I7:I19) -> 600 | J6: =SUM(J7:J19) -> 600 | K6: =SUM(K7:K19) -> 600 | L6: =SUM(L7:L19) -> 600 | M6: =SUM(M7:M19) -> 600
A7: 2020 | B7: =tab!B7 -> + | C7: =tab!C7 -> Ajustes Devedores de Qualquer Natureza | E7: =HLOOKUP(E$4,tab!$E$4:$P$49,MATCH($C7,$C$4:$C$49,0),0) -> 0 | F7: =HLOOKUP(F$4,tab!$E$4:$P$49,MATCH($C7,$C$4:$C$49,0),0) -> 0 | G7: =HLOOKUP(G$4,tab!$E$4:$P$49,MATCH($C7,$C$4:$C$49,0),0) -> 0 | H7: =HLOOKUP(H$4,tab!$E$4:$P$49,MATCH($C7,$C$4:$C$49,0),0) -> 0 | I7: =HLOOKUP(I$4,tab!$E$4:$P$49,MATCH($C7,$C$4:$C$49,0),0) -> 0 | J7: =HLOOKUP(J$4,tab!$E$4:$P$49,MATCH($C7,$C$4:$C$49,0),0) -> 0 | K7: =HLOOKUP(K$4,tab!$E$4:$P$49,MATCH($C7,$C$4:$C$49,0),0) -> 0 | L7: =HLOOKUP(L$4,tab!$E$4:$P$49,MATCH($C7,$C$4:$C$49,0),0) -> 0 | M7: =HLOOKUP(M$4,tab!$E$4:$P$49,MATCH($C7,$C$4:$C$49,0),0) -> 0
A8: 2021 | B8: =tab!B8 -> + | C8: =tab!C8 -> Despesas de Variação Cambial | E8: =HLOOKUP(E$4,tab!$E$4:$P$49,MATCH($C8,$C$4:$C$49,0),0) -> 0 | F8: =HLOOKUP(F$4,tab!$E$4:$P$49,MATCH($C8,$C$4:$C$49,0),0) -> 0 | G8: =HLOOKUP(G$4,tab!$E$4:$P$49,MATCH($C8,$C$4:$C$49,0),0) -> 0 | H8: =HLOOKUP(H$4,tab!$E$4:$P$49,MATCH($C8,$C$4:$C$49,0),0) -> 0 | I8: =HLOOKUP(I$4,tab!$E$4:$P$49,MATCH($C8,$C$4:$C$49,0),0) -> 0 | J8: =HLOOKUP(J$4,tab!$E$4:$P$49,MATCH($C8,$C$4:$C$49,0),0) -> 0 | K8: =HLOOKUP(K$4,tab!$E$4:$P$49,MATCH($C8,$C$4:$C$49,0),0) -> 0 | L8: =HLOOKUP(L$4,tab!$E$4:$P$49,MATCH($C8,$C$4:$C$49,0),0) -> 0 | M8: =HLOOKUP(M$4,tab!$E$4:$P$49,MATCH($C8,$C$4:$C$49,0),0) -> 0
A9: 2022 | B9: =tab!B9 -> + | C9: =tab!C9 -> Despesas Particulares dos Sócios e Dirigentes; | E9: =HLOOKUP(E$4,tab!$E$4:$P$49,MATCH($C9,$C$4:$C$49,0),0) -> 0 | F9: =HLOOKUP(F$4,tab!$E$4:$P$49,MATCH($C9,$C$4:$C$49,0),0) -> 0 | G9: =HLOOKUP(G$4,tab!$E$4:$P$49,MATCH($C9,$C$4:$C$49,0),0) -> 0 | H9: =HLOOKUP(H$4,tab!$E$4:$P$49,MATCH($C9,$C$4:$C$49,0),0) -> 0 | I9: =HLOOKUP(I$4,tab!$E$4:$P$49,MATCH($C9,$C$4:$C$49,0),0) -> 0 | J9: =HLOOKUP(J$4,tab!$E$4:$P$49,MATCH($C9,$C$4:$C$49,0),0) -> 0 | K9: =HLOOKUP(K$4,tab!$E$4:$P$49,MATCH($C9,$C$4:$C$49,0),0) -> 0 | L9: =HLOOKUP(L$4,tab!$E$4:$P$49,MATCH($C9,$C$4:$C$49,0),0) -> 0 | M9: =HLOOKUP(M$4,tab!$E$4:$P$49,MATCH($C9,$C$4:$C$49,0),0) -> 0
A10: 2023 | B10: =tab!B10 -> + | C10: =tab!C10 -> Doações e Brindes; | E10: =HLOOKUP(E$4,tab!$E$4:$P$49,MATCH($C10,$C$4:$C$49,0),0) -> 100 | F10: =HLOOKUP(F$4,tab!$E$4:$P$49,MATCH($C10,$C$4:$C$49,0),0) -> 100 | G10: =HLOOKUP(G$4,tab!$E$4:$P$49,MATCH($C10,$C$4:$C$49,0),0) -> 100 | H10: =HLOOKUP(H$4,tab!$E$4:$P$49,MATCH($C10,$C$4:$C$49,0),0) -> 100 | I10: =HLOOKUP(I$4,tab!$E$4:$P$49,MATCH($C10,$C$4:$C$49,0),0) -> 100 | J10: =HLOOKUP(J$4,tab!$E$4:$P$49,MATCH($C10,$C$4:$C$49,0),0) -> 100 | K10: =HLOOKUP(K$4,tab!$E$4:$P$49,MATCH($C10,$C$4:$C$49,0),0) -> 100 | L10: =HLOOKUP(L$4,tab!$E$4:$P$49,MATCH($C10,$C$4:$C$49,0),0) -> 100 | M10: =HLOOKUP(M$4,tab!$E$4:$P$49,MATCH($C10,$C$4:$C$49,0),0) -> 100
A11: 2024 | B11: =tab!B11 -> + | C11: =tab!C11 -> Impostos Não Pagos em Discussão Judicial; | E11: =HLOOKUP(E$4,tab!$E$4:$P$49,MATCH($C11,$C$4:$C$49,0),0) -> 0 | F11: =HLOOKUP(F$4,tab!$E$4:$P$49,MATCH($C11,$C$4:$C$49,0),0) -> 0 | G11: =HLOOKUP(G$4,tab!$E$4:$P$49,MATCH($C11,$C$4:$C$49,0),0) -> 0 | H11: =HLOOKUP(H$4,tab!$E$4:$P$49,MATCH($C11,$C$4:$C$49,0),0) -> 0 | I11: =HLOOKUP(I$4,tab!$E$4:$P$49,MATCH($C11,$C$4:$C$49,0),0) -> 0 | J11: =HLOOKUP(J$4,tab!$E$4:$P$49,MATCH($C11,$C$4:$C$49,0),0) -> 0 | K11: =HLOOKUP(K$4,tab!$E$4:$P$49,MATCH($C11,$C$4:$C$49,0),0) -> 0 | L11: =HLOOKUP(L$4,tab!$E$4:$P$49,MATCH($C11,$C$4:$C$49,0),0) -> 0 | M11: =HLOOKUP(M$4,tab!$E$4:$P$49,MATCH($C11,$C$4:$C$49,0),0) -> 0
A12: 2025 | B12: =tab!B12 -> + | C12: =tab!C12 -> Impostos Não Pagos por Iniciativa da Empresa; | E12: =HLOOKUP(E$4,tab!$E$4:$P$49,MATCH($C12,$C$4:$C$49,0),0) -> 0 | F12: =HLOOKUP(F$4,tab!$E$4:$P$49,MATCH($C12,$C$4:$C$49,0),0) -> 0 | G12: =HLOOKUP(G$4,tab!$E$4:$P$49,MATCH($C12,$C$4:$C$49,0),0) -> 0 | H12: =HLOOKUP(H$4,tab!$E$4:$P$49,MATCH($C12,$C$4:$C$49,0),0) -> 0 | I12: =HLOOKUP(I$4,tab!$E$4:$P$49,MATCH($C12,$C$4:$C$49,0),0) -> 0 | J12: =HLOOKUP(J$4,tab!$E$4:$P$49,MATCH($C12,$C$4:$C$49,0),0) -> 0 | K12: =HLOOKUP(K$4,tab!$E$4:$P$49,MATCH($C12,$C$4:$C$49,0),0) -> 0 | L12: =HLOOKUP(L$4,tab!$E$4:$P$49,MATCH($C12,$C$4:$C$49,0),0) -> 0 | M12: =HLOOKUP(M$4,tab!$E$4:$P$49,MATCH($C12,$C$4:$C$49,0),0) -> 0
A13: 2026 | B13: =tab!B13 -> + | C13: =tab!C13 -> Lucro Inflacionário apurado até 31/12/1995; | E13: =HLOOKUP(E$4,tab!$E$4:$P$49,MATCH($C13,$C$4:$C$49,0),0) -> 0 | F13: =HLOOKUP(F$4,tab!$E$4:$P$49,MATCH($C13,$C$4:$C$49,0),0) -> 0 | G13: =HLOOKUP(G$4,tab!$E$4:$P$49,MATCH($C13,$C$4:$C$49,0),0) -> 0 | H13: =HLOOKUP(H$4,tab!$E$4:$P$49,MATCH($C13,$C$4:$C$49,0),0) -> 0 | I13: =HLOOKUP(I$4,tab!$E$4:$P$49,MATCH($C13,$C$4:$C$49,0),0) -> 0 | J13: =HLOOKUP(J$4,tab!$E$4:$P$49,MATCH($C13,$C$4:$C$49,0),0) -> 0 | K13: =HLOOKUP(K$4,tab!$E$4:$P$49,MATCH($C13,$C$4:$C$49,0),0) -> 0 | L13: =HLOOKUP(L$4,tab!$E$4:$P$49,MATCH($C13,$C$4:$C$49,0),0) -> 0 | M13: =HLOOKUP(M$4,tab!$E$4:$P$49,MATCH($C13,$C$4:$C$49,0),0) -> 0
A14: 2027 | B14: =tab!B14 -> + | C14: =tab!C14 -> Multas Contratuais | E14: =HLOOKUP(E$4,tab!$E$4:$P$49,MATCH($C14,$C$4:$C$49,0),0) -> 0 | F14: =HLOOKUP(F$4,tab!$E$4:$P$49,MATCH($C14,$C$4:$C$49,0),0) -> 0 | G14: =HLOOKUP(G$4,tab!$E$4:$P$49,MATCH($C14,$C$4:$C$49,0),0) -> 0 | H14: =HLOOKUP(H$4,tab!$E$4:$P$49,MATCH($C14,$C$4:$C$49,0),0) -> 0 | I14: =HLOOKUP(I$4,tab!$E$4:$P$49,MATCH($C14,$C$4:$C$49,0),0) -> 0 | J14: =HLOOKUP(J$4,tab!$E$4:$P$49,MATCH($C14,$C$4:$C$49,0),0) -> 0 | K14: =HLOOKUP(K$4,tab!$E$4:$P$49,MATCH($C14,$C$4:$C$49,0),0) -> 0 | L14: =HLOOKUP(L$4,tab!$E$4:$P$49,MATCH($C14,$C$4:$C$49,0),0) -> 0 | M14: =HLOOKUP(M$4,tab!$E$4:$P$49,MATCH($C14,$C$4:$C$49,0),0) -> 0
A15: 2028 | B15: =tab!B15 -> + | C15: =tab!C15 -> Multas Punitivas (Transito, Imetro, Ibama, Multas sobre ação fiscal) | E15: =HLOOKUP(E$4,tab!$E$4:$P$49,MATCH($C15,$C$4:$C$49,0),0) -> 500 | F15: =HLOOKUP(F$4,tab!$E$4:$P$49,MATCH($C15,$C$4:$C$49,0),0) -> 500 | G15: =HLOOKUP(G$4,tab!$E$4:$P$49,MATCH($C15,$C$4:$C$49,0),0) -> 500 | H15: =HLOOKUP(H$4,tab!$E$4:$P$49,MATCH($C15,$C$4:$C$49,0),0) -> 500 | I15: =HLOOKUP(I$4,tab!$E$4:$P$49,MATCH($C15,$C$4:$C$49,0),0) -> 500 | J15: =HLOOKUP(J$4,tab!$E$4:$P$49,MATCH($C15,$C$4:$C$49,0),0) -> 500 | K15: =HLOOKUP(K$4,tab!$E$4:$P$49,MATCH($C15,$C$4:$C$49,0),0) -> 500 | L15: =HLOOKUP(L$4,tab!$E$4:$P$49,MATCH($C15,$C$4:$C$49,0),0) -> 500 | M15: =HLOOKUP(M$4,tab!$E$4:$P$49,MATCH($C15,$C$4:$C$49,0),0) -> 500
A16: 2029 | B16: =tab!B16 -> + | C16: =tab!C16 -> Orçamentos, Pedidos e qualquer documento não idôneo; | E16: =HLOOKUP(E$4,tab!$E$4:$P$49,MATCH($C16,$C$4:$C$49,0),0) -> 0 | F16: =HLOOKUP(F$4,tab!$E$4:$P$49,MATCH($C16,$C$4:$C$49,0),0) -> 0 | G16: =HLOOKUP(G$4,tab!$E$4:$P$49,MATCH($C16,$C$4:$C$49,0),0) -> 0 | H16: =HLOOKUP(H$4,tab!$E$4:$P$49,MATCH($C16,$C$4:$C$49,0),0) -> 0 | I16: =HLOOKUP(I$4,tab!$E$4:$P$49,MATCH($C16,$C$4:$C$49,0),0) -> 0 | J16: =HLOOKUP(J$4,tab!$E$4:$P$49,MATCH($C16,$C$4:$C$49,0),0) -> 0 | K16: =HLOOKUP(K$4,tab!$E$4:$P$49,MATCH($C16,$C$4:$C$49,0),0) -> 0 | L16: =HLOOKUP(L$4,tab!$E$4:$P$49,MATCH($C16,$C$4:$C$49,0),0) -> 0 | M16: =HLOOKUP(M$4,tab!$E$4:$P$49,MATCH($C16,$C$4:$C$49,0),0) -> 0
A17: 2030 | B17: =tab!B17 -> + | C17: =tab!C17 -> Provisões Indedutíveis (perdas, frete, propaganda) | E17: =HLOOKUP(E$4,tab!$E$4:$P$49,MATCH($C17,$C$4:$C$49,0),0) -> 0 | F17: =HLOOKUP(F$4,tab!$E$4:$P$49,MATCH($C17,$C$4:$C$49,0),0) -> 0 | G17: =HLOOKUP(G$4,tab!$E$4:$P$49,MATCH($C17,$C$4:$C$49,0),0) -> 0 | H17: =HLOOKUP(H$4,tab!$E$4:$P$49,MATCH($C17,$C$4:$C$49,0),0) -> 0 | I17: =HLOOKUP(I$4,tab!$E$4:$P$49,MATCH($C17,$C$4:$C$49,0),0) -> 0 | J17: =HLOOKUP(J$4,tab!$E$4:$P$49,MATCH($C17,$C$4:$C$49,0),0) -> 0 | K17: =HLOOKUP(K$4,tab!$E$4:$P$49,MATCH($C17,$C$4:$C$49,0),0) -> 0 | L17: =HLOOKUP(L$4,tab!$E$4:$P$49,MATCH($C17,$C$4:$C$49,0),0) -> 0 | M17: =HLOOKUP(M$4,tab!$E$4:$P$49,MATCH($C17,$C$4:$C$49,0),0) -> 0
B18: =tab!B18 -> + | C18: =tab!C18 -> Recibos sem especificação da fonte recebedora; | E18: =HLOOKUP(E$4,tab!$E$4:$P$49,MATCH($C18,$C$4:$C$49,0),0) -> 0 | F18: =HLOOKUP(F$4,tab!$E$4:$P$49,MATCH($C18,$C$4:$C$49,0),0) -> 0 | G18: =HLOOKUP(G$4,tab!$E$4:$P$49,MATCH($C18,$C$4:$C$49,0),0) -> 0 | H18: =HLOOKUP(H$4,tab!$E$4:$P$49,MATCH($C18,$C$4:$C$49,0),0) -> 0 | I18: =HLOOKUP(I$4,tab!$E$4:$P$49,MATCH($C18,$C$4:$C$49,0),0) -> 0 | J18: =HLOOKUP(J$4,tab!$E$4:$P$49,MATCH($C18,$C$4:$C$49,0),0) -> 0 | K18: =HLOOKUP(K$4,tab!$E$4:$P$49,MATCH($C18,$C$4:$C$49,0),0) -> 0 | L18: =HLOOKUP(L$4,tab!$E$4:$P$49,MATCH($C18,$C$4:$C$49,0),0) -> 0 | M18: =HLOOKUP(M$4,tab!$E$4:$P$49,MATCH($C18,$C$4:$C$49,0),0) -> 0
B19: =tab!B19 -> + | C19: =tab!C19 -> Verbas Rescisórias em desacordo com a legislação trabalhista vigente | E19: =HLOOKUP(E$4,tab!$E$4:$P$49,MATCH($C19,$C$4:$C$49,0),0) -> 0 | F19: =HLOOKUP(F$4,tab!$E$4:$P$49,MATCH($C19,$C$4:$C$49,0),0) -> 0 | G19: =HLOOKUP(G$4,tab!$E$4:$P$49,MATCH($C19,$C$4:$C$49,0),0) -> 0 | H19: =HLOOKUP(H$4,tab!$E$4:$P$49,MATCH($C19,$C$4:$C$49,0),0) -> 0 | I19: =HLOOKUP(I$4,tab!$E$4:$P$49,MATCH($C19,$C$4:$C$49,0),0) -> 0 | J19: =HLOOKUP(J$4,tab!$E$4:$P$49,MATCH($C19,$C$4:$C$49,0),0) -> 0 | K19: =HLOOKUP(K$4,tab!$E$4:$P$49,MATCH($C19,$C$4:$C$49,0),0) -> 0 | L19: =HLOOKUP(L$4,tab!$E$4:$P$49,MATCH($C19,$C$4:$C$49,0),0) -> 0 | M19: =HLOOKUP(M$4,tab!$E$4:$P$49,MATCH($C19,$C$4:$C$49,0),0) -> 0
B20: =tab!B20 -> = | C20: =tab!C20 -> Exclusões | E20: =SUM(E21:E33) -> -1000 | F20: =SUM(F21:F33) -> -1000 | G20: =SUM(G21:G33) -> -1000 | H20: =SUM(H21:H33) -> -1000 | I20: =SUM(I21:I33) -> -1000 | J20: =SUM(J21:J33) -> -1000 | K20: =SUM(K21:K33) -> -1000 | L20: =SUM(L21:L33) -> -1000 | M20: =SUM(M21:M33) -> -1000
B21: =tab!B21 -> - | C21: =tab!C21 -> Ajustes credores de qualquer natureza | E21: =HLOOKUP(E$4,tab!$E$4:$P$49,MATCH($C21,$C$4:$C$49,0),0) -> 0 | F21: =HLOOKUP(F$4,tab!$E$4:$P$49,MATCH($C21,$C$4:$C$49,0),0) -> 0 | G21: =HLOOKUP(G$4,tab!$E$4:$P$49,MATCH($C21,$C$4:$C$49,0),0) -> 0 | H21: =HLOOKUP(H$4,tab!$E$4:$P$49,MATCH($C21,$C$4:$C$49,0),0) -> 0 | I21: =HLOOKUP(I$4,tab!$E$4:$P$49,MATCH($C21,$C$4:$C$49,0),0) -> 0 | J21: =HLOOKUP(J$4,tab!$E$4:$P$49,MATCH($C21,$C$4:$C$49,0),0) -> 0 | K21: =HLOOKUP(K$4,tab!$E$4:$P$49,MATCH($C21,$C$4:$C$49,0),0) -> 0 | L21: =HLOOKUP(L$4,tab!$E$4:$P$49,MATCH($C21,$C$4:$C$49,0),0) -> 0 | M21: =HLOOKUP(M$4,tab!$E$4:$P$49,MATCH($C21,$C$4:$C$49,0),0) -> 0
B22: =tab!B22 -> - | C22: =tab!C22 -> Decisão Favorável - Processos Judiciais Tributários | E22: =HLOOKUP(E$4,tab!$E$4:$P$49,MATCH($C22,$C$4:$C$49,0),0) -> 0 | F22: =HLOOKUP(F$4,tab!$E$4:$P$49,MATCH($C22,$C$4:$C$49,0),0) -> 0 | G22: =HLOOKUP(G$4,tab!$E$4:$P$49,MATCH($C22,$C$4:$C$49,0),0) -> 0 | H22: =HLOOKUP(H$4,tab!$E$4:$P$49,MATCH($C22,$C$4:$C$49,0),0) -> 0 | I22: =HLOOKUP(I$4,tab!$E$4:$P$49,MATCH($C22,$C$4:$C$49,0),0) -> 0 | J22: =HLOOKUP(J$4,tab!$E$4:$P$49,MATCH($C22,$C$4:$C$49,0),0) -> 0 | K22: =HLOOKUP(K$4,tab!$E$4:$P$49,MATCH($C22,$C$4:$C$49,0),0) -> 0 | L22: =HLOOKUP(L$4,tab!$E$4:$P$49,MATCH($C22,$C$4:$C$49,0),0) -> 0 | M22: =HLOOKUP(M$4,tab!$E$4:$P$49,MATCH($C22,$C$4:$C$49,0),0) -> 0
B23: =tab!B23 -> - | C23: =tab!C23 -> Despesas de Ágios | E23: =HLOOKUP(E$4,tab!$E$4:$P$49,MATCH($C23,$C$4:$C$49,0),0) -> 0 | F23: =HLOOKUP(F$4,tab!$E$4:$P$49,MATCH($C23,$C$4:$C$49,0),0) -> 0 | G23: =HLOOKUP(G$4,tab!$E$4:$P$49,MATCH($C23,$C$4:$C$49,0),0) -> 0 | H23: =HLOOKUP(H$4,tab!$E$4:$P$49,MATCH($C23,$C$4:$C$49,0),0) -> 0 | I23: =HLOOKUP(I$4,tab!$E$4:$P$49,MATCH($C23,$C$4:$C$49,0),0) -> 0 | J23: =HLOOKUP(J$4,tab!$E$4:$P$49,MATCH($C23,$C$4:$C$49,0),0) -> 0 | K23: =HLOOKUP(K$4,tab!$E$4:$P$49,MATCH($C23,$C$4:$C$49,0),0) -> 0 | L23: =HLOOKUP(L$4,tab!$E$4:$P$49,MATCH($C23,$C$4:$C$49,0),0) -> 0 | M23: =HLOOKUP(M$4,tab!$E$4:$P$49,MATCH($C23,$C$4:$C$49,0),0) -> 0
B24: =tab!B24 -> - | C24: =tab!C24 -> Distribuição de Lucros e Dividendos; | E24: =HLOOKUP(E$4,tab!$E$4:$P$49,MATCH($C24,$C$4:$C$49,0),0) -> 0 | F24: =HLOOKUP(F$4,tab!$E$4:$P$49,MATCH($C24,$C$4:$C$49,0),0) -> 0 | G24: =HLOOKUP(G$4,tab!$E$4:$P$49,MATCH($C24,$C$4:$C$49,0),0) -> 0 | H24: =HLOOKUP(H$4,tab!$E$4:$P$49,MATCH($C24,$C$4:$C$49,0),0) -> 0 | I24: =HLOOKUP(I$4,tab!$E$4:$P$49,MATCH($C24,$C$4:$C$49,0),0) -> 0 | J24: =HLOOKUP(J$4,tab!$E$4:$P$49,MATCH($C24,$C$4:$C$49,0),0) -> 0 | K24: =HLOOKUP(K$4,tab!$E$4:$P$49,MATCH($C24,$C$4:$C$49,0),0) -> 0 | L24: =HLOOKUP(L$4,tab!$E$4:$P$49,MATCH($C24,$C$4:$C$49,0),0) -> 0 | M24: =HLOOKUP(M$4,tab!$E$4:$P$49,MATCH($C24,$C$4:$C$49,0),0) -> 0
B25: =tab!B25 -> - | C25: =tab!C25 -> Dividendos Coligadas e Controladas | E25: =HLOOKUP(E$4,tab!$E$4:$P$49,MATCH($C25,$C$4:$C$49,0),0) -> 0 | F25: =HLOOKUP(F$4,tab!$E$4:$P$49,MATCH($C25,$C$4:$C$49,0),0) -> 0 | G25: =HLOOKUP(G$4,tab!$E$4:$P$49,MATCH($C25,$C$4:$C$49,0),0) -> 0 | H25: =HLOOKUP(H$4,tab!$E$4:$P$49,MATCH($C25,$C$4:$C$49,0),0) -> 0 | I25: =HLOOKUP(I$4,tab!$E$4:$P$49,MATCH($C25,$C$4:$C$49,0),0) -> 0 | J25: =HLOOKUP(J$4,tab!$E$4:$P$49,MATCH($C25,$C$4:$C$49,0),0) -> 0 | K25: =HLOOKUP(K$4,tab!$E$4:$P$49,MATCH($C25,$C$4:$C$49,0),0) -> 0 | L25: =HLOOKUP(L$4,tab!$E$4:$P$49,MATCH($C25,$C$4:$C$49,0),0) -> 0 | M25: =HLOOKUP(M$4,tab!$E$4:$P$49,MATCH($C25,$C$4:$C$49,0),0) -> 0
B26: =tab!B26 -> - | C26: =tab!C26 -> Pagamento de Impostos em Atraso por iniciativa da Empresa | E26: =HLOOKUP(E$4,tab!$E$4:$P$49,MATCH($C26,$C$4:$C$49,0),0) -> -1000 | F26: =HLOOKUP(F$4,tab!$E$4:$P$49,MATCH($C26,$C$4:$C$49,0),0) -> -1000 | G26: =HLOOKUP(G$4,tab!$E$4:$P$49,MATCH($C26,$C$4:$C$49,0),0) -> -1000 | H26: =HLOOKUP(H$4,tab!$E$4:$P$49,MATCH($C26,$C$4:$C$49,0),0) -> -1000 | I26: =HLOOKUP(I$4,tab!$E$4:$P$49,MATCH($C26,$C$4:$C$49,0),0) -> -1000 | J26: =HLOOKUP(J$4,tab!$E$4:$P$49,MATCH($C26,$C$4:$C$49,0),0) -> -1000 | K26: =HLOOKUP(K$4,tab!$E$4:$P$49,MATCH($C26,$C$4:$C$49,0),0) -> -1000 | L26: =HLOOKUP(L$4,tab!$E$4:$P$49,MATCH($C26,$C$4:$C$49,0),0) -> -1000 | M26: =HLOOKUP(M$4,tab!$E$4:$P$49,MATCH($C26,$C$4:$C$49,0),0) -> -1000
B27: =tab!B27 -> - | C27: =tab!C27 -> Pagamento de Impostos sobre discussão judicial, | E27: =HLOOKUP(E$4,tab!$E$4:$P$49,MATCH($C27,$C$4:$C$49,0),0) -> 0 | F27: =HLOOKUP(F$4,tab!$E$4:$P$49,MATCH($C27,$C$4:$C$49,0),0) -> 0 | G27: =HLOOKUP(G$4,tab!$E$4:$P$49,MATCH($C27,$C$4:$C$49,0),0) -> 0 | H27: =HLOOKUP(H$4,tab!$E$4:$P$49,MATCH($C27,$C$4:$C$49,0),0) -> 0 | I27: =HLOOKUP(I$4,tab!$E$4:$P$49,MATCH($C27,$C$4:$C$49,0),0) -> 0 | J27: =HLOOKUP(J$4,tab!$E$4:$P$49,MATCH($C27,$C$4:$C$49,0),0) -> 0 | K27: =HLOOKUP(K$4,tab!$E$4:$P$49,MATCH($C27,$C$4:$C$49,0),0) -> 0 | L27: =HLOOKUP(L$4,tab!$E$4:$P$49,MATCH($C27,$C$4:$C$49,0),0) -> 0 | M27: =HLOOKUP(M$4,tab!$E$4:$P$49,MATCH($C27,$C$4:$C$49,0),0) -> 0
B28: =tab!B28 -> - | C28: =tab!C28 -> Receita de Variação Cambial | E28: =HLOOKUP(E$4,tab!$E$4:$P$49,MATCH($C28,$C$4:$C$49,0),0) -> 0 | F28: =HLOOKUP(F$4,tab!$E$4:$P$49,MATCH($C28,$C$4:$C$49,0),0) -> 0 | G28: =HLOOKUP(G$4,tab!$E$4:$P$49,MATCH($C28,$C$4:$C$49,0),0) -> 0 | H28: =HLOOKUP(H$4,tab!$E$4:$P$49,MATCH($C28,$C$4:$C$49,0),0) -> 0 | I28: =HLOOKUP(I$4,tab!$E$4:$P$49,MATCH($C28,$C$4:$C$49,0),0) -> 0 | J28: =HLOOKUP(J$4,tab!$E$4:$P$49,MATCH($C28,$C$4:$C$49,0),0) -> 0 | K28: =HLOOKUP(K$4,tab!$E$4:$P$49,MATCH($C28,$C$4:$C$49,0),0) -> 0 | L28: =HLOOKUP(L$4,tab!$E$4:$P$49,MATCH($C28,$C$4:$C$49,0),0) -> 0 | M28: =HLOOKUP(M$4,tab!$E$4:$P$49,MATCH($C28,$C$4:$C$49,0),0) -> 0
B29: =tab!B29 -> - | C29: =tab!C29 -> Receitas Obtidas com Tributação Exclusiva ou Isenta de IR | E29: =HLOOKUP(E$4,tab!$E$4:$P$49,MATCH($C29,$C$4:$C$49,0),0) -> 0 | F29: =HLOOKUP(F$4,tab!$E$4:$P$49,MATCH($C29,$C$4:$C$49,0),0) -> 0 | G29: =HLOOKUP(G$4,tab!$E$4:$P$49,MATCH($C29,$C$4:$C$49,0),0) -> 0 | H29: =HLOOKUP(H$4,tab!$E$4:$P$49,MATCH($C29,$C$4:$C$49,0),0) -> 0 | I29: =HLOOKUP(I$4,tab!$E$4:$P$49,MATCH($C29,$C$4:$C$49,0),0) -> 0 | J29: =HLOOKUP(J$4,tab!$E$4:$P$49,MATCH($C29,$C$4:$C$49,0),0) -> 0 | K29: =HLOOKUP(K$4,tab!$E$4:$P$49,MATCH($C29,$C$4:$C$49,0),0) -> 0 | L29: =HLOOKUP(L$4,tab!$E$4:$P$49,MATCH($C29,$C$4:$C$49,0),0) -> 0 | M29: =HLOOKUP(M$4,tab!$E$4:$P$49,MATCH($C29,$C$4:$C$49,0),0) -> 0
B30: =tab!B30 -> - | C30: =tab!C30 -> Receitas que poderiam ser diferidas; | E30: =HLOOKUP(E$4,tab!$E$4:$P$49,MATCH($C30,$C$4:$C$49,0),0) -> 0 | F30: =HLOOKUP(F$4,tab!$E$4:$P$49,MATCH($C30,$C$4:$C$49,0),0) -> 0 | G30: =HLOOKUP(G$4,tab!$E$4:$P$49,MATCH($C30,$C$4:$C$49,0),0) -> 0 | H30: =HLOOKUP(H$4,tab!$E$4:$P$49,MATCH($C30,$C$4:$C$49,0),0) -> 0 | I30: =HLOOKUP(I$4,tab!$E$4:$P$49,MATCH($C30,$C$4:$C$49,0),0) -> 0 | J30: =HLOOKUP(J$4,tab!$E$4:$P$49,MATCH($C30,$C$4:$C$49,0),0) -> 0 | K30: =HLOOKUP(K$4,tab!$E$4:$P$49,MATCH($C30,$C$4:$C$49,0),0) -> 0 | L30: =HLOOKUP(L$4,tab!$E$4:$P$49,MATCH($C30,$C$4:$C$49,0),0) -> 0 | M30: =HLOOKUP(M$4,tab!$E$4:$P$49,MATCH($C30,$C$4:$C$49,0),0) -> 0
B31: =tab!B31 -> - | C31: =tab!C31 -> Resultado Positivo de Equivalência Patrimonial | E31: =HLOOKUP(E$4,tab!$E$4:$P$49,MATCH($C31,$C$4:$C$49,0),0) -> 0 | F31: =HLOOKUP(F$4,tab!$E$4:$P$49,MATCH($C31,$C$4:$C$49,0),0) -> 0 | G31: =HLOOKUP(G$4,tab!$E$4:$P$49,MATCH($C31,$C$4:$C$49,0),0) -> 0 | H31: =HLOOKUP(H$4,tab!$E$4:$P$49,MATCH($C31,$C$4:$C$49,0),0) -> 0 | I31: =HLOOKUP(I$4,tab!$E$4:$P$49,MATCH($C31,$C$4:$C$49,0),0) -> 0 | J31: =HLOOKUP(J$4,tab!$E$4:$P$49,MATCH($C31,$C$4:$C$49,0),0) -> 0 | K31: =HLOOKUP(K$4,tab!$E$4:$P$49,MATCH($C31,$C$4:$C$49,0),0) -> 0 | L31: =HLOOKUP(L$4,tab!$E$4:$P$49,MATCH($C31,$C$4:$C$49,0),0) -> 0 | M31: =HLOOKUP(M$4,tab!$E$4:$P$49,MATCH($C31,$C$4:$C$49,0),0) -> 0
B32: =tab!B32 -> - | C32: =tab!C32 -> Reversão de Provisões Indedutíveis | E32: =HLOOKUP(E$4,tab!$E$4:$P$49,MATCH($C32,$C$4:$C$49,0),0) -> 0 | F32: =HLOOKUP(F$4,tab!$E$4:$P$49,MATCH($C32,$C$4:$C$49,0),0) -> 0 | G32: =HLOOKUP(G$4,tab!$E$4:$P$49,MATCH($C32,$C$4:$C$49,0),0) -> 0 | H32: =HLOOKUP(H$4,tab!$E$4:$P$49,MATCH($C32,$C$4:$C$49,0),0) -> 0 | I32: =HLOOKUP(I$4,tab!$E$4:$P$49,MATCH($C32,$C$4:$C$49,0),0) -> 0 | J32: =HLOOKUP(J$4,tab!$E$4:$P$49,MATCH($C32,$C$4:$C$49,0),0) -> 0 | K32: =HLOOKUP(K$4,tab!$E$4:$P$49,MATCH($C32,$C$4:$C$49,0),0) -> 0 | L32: =HLOOKUP(L$4,tab!$E$4:$P$49,MATCH($C32,$C$4:$C$49,0),0) -> 0 | M32: =HLOOKUP(M$4,tab!$E$4:$P$49,MATCH($C32,$C$4:$C$49,0),0) -> 0
B33: =tab!B33 -> - | C33: =tab!C33 -> Vendas Não Expedidas do Período | E33: =HLOOKUP(E$4,tab!$E$4:$P$49,MATCH($C33,$C$4:$C$49,0),0) -> 0 | F33: =HLOOKUP(F$4,tab!$E$4:$P$49,MATCH($C33,$C$4:$C$49,0),0) -> 0 | G33: =HLOOKUP(G$4,tab!$E$4:$P$49,MATCH($C33,$C$4:$C$49,0),0) -> 0 | H33: =HLOOKUP(H$4,tab!$E$4:$P$49,MATCH($C33,$C$4:$C$49,0),0) -> 0 | I33: =HLOOKUP(I$4,tab!$E$4:$P$49,MATCH($C33,$C$4:$C$49,0),0) -> 0 | J33: =HLOOKUP(J$4,tab!$E$4:$P$49,MATCH($C33,$C$4:$C$49,0),0) -> 0 | K33: =HLOOKUP(K$4,tab!$E$4:$P$49,MATCH($C33,$C$4:$C$49,0),0) -> 0 | L33: =HLOOKUP(L$4,tab!$E$4:$P$49,MATCH($C33,$C$4:$C$49,0),0) -> 0 | M33: =HLOOKUP(M$4,tab!$E$4:$P$49,MATCH($C33,$C$4:$C$49,0),0) -> 0
B34: =tab!B34 -> = | C34: =tab!C34 -> Base de Cálculo | E34: =SUM(E5,E6,E20) -> 600 | F34: =SUM(F5,F6,F20) -> 25600 | G34: =SUM(G5,G6,G20) -> 50600 | H34: =SUM(H5,H6,H20) -> 75600 | I34: =SUM(I5,I6,I20) -> 100600 | J34: =SUM(J5,J6,J20) -> 125600 | K34: =SUM(K5,K6,K20) -> 150600 | L34: =SUM(L5,L6,L20) -> 175600 | M34: =SUM(M5,M6,M20) -> 200600
B35: =tab!B35 -> = | C35: =tab!C35 -> Saldo Prejuízo Fiscal | E35: =tab!E35 -> 45000 | F35: =SUM(E35:E36) -> 44820 | G35: =SUM(F35:F36) -> 37140 | H35: =SUM(G35:G36) -> 21960 | I35: =SUM(H35:H36) -> 0 | J35: =SUM(I35:I36) -> 0 | K35: =SUM(J35:J36) -> 0 | L35: =SUM(K35:K36) -> 0 | M35: =SUM(L35:L36) -> 0
B36: =tab!B36 -> % | C36: =tab!C36 -> Compensação de Prejuízo Fiscal | D36: =tab!D36 -> 0.3 | E36: =-IF(AND(E35>0,E34*$D$36<E35),E34*$D$36,E35) -> -180 | F36: =-IF(AND(F35>0,F34*$D$36<F35),F34*$D$36,F35) -> -7680 | G36: =-IF(AND(G35>0,G34*$D$36<G35),G34*$D$36,G35) -> -15180 | H36: =-IF(AND(H35>0,H34*$D$36<H35),H34*$D$36,H35) -> -21960 | I36: =-IF(AND(I35>0,I34*$D$36<I35),I34*$D$36,I35) -> 0 | J36: =-IF(AND(J35>0,J34*$D$36<J35),J34*$D$36,J35) -> 0 | K36: =-IF(AND(K35>0,K34*$D$36<K35),K34*$D$36,K35) -> 0 | L36: =-IF(AND(L35>0,L34*$D$36<L35),L34*$D$36,L35) -> 0 | M36: =-IF(AND(M35>0,M34*$D$36<M35),M34*$D$36,M35) -> 0
B37: =tab!B37 -> % | C37: =tab!C37 -> Adicional de Imposto de Renda | D37: =tab!D37 -> 0.1 | E37: =HLOOKUP($E$4,INDIRECT($E$4&"!$E$4:$O$49"),MATCH(C37,INDIRECT($E$4&"!$C$4:$C$49"),0),0) -> 0 | F37: =IF(SUM(F34,F36)>20000*$A$4,(SUM(F34,F36)-20000*$A$4)*$D$37,0) -> 0 | G37: =IF(SUM(G34,G36)>20000*$A$4,(SUM(G34,G36)-20000*$A$4)*$D$37,0) -> 0 | H37: =IF(SUM(H34,H36)>20000*$A$4,(SUM(H34,H36)-20000*$A$4)*$D$37,0) -> 0 | I37: =IF(SUM(I34,I36)>20000*$A$4,(SUM(I34,I36)-20000*$A$4)*$D$37,0) -> 0 | J37: =IF(SUM(J34,J36)>20000*$A$4,(SUM(J34,J36)-20000*$A$4)*$D$37,0) -> 0 | K37: =IF(SUM(K34,K36)>20000*$A$4,(SUM(K34,K36)-20000*$A$4)*$D$37,0) -> 0 | L37: =IF(SUM(L34,L36)>20000*$A$4,(SUM(L34,L36)-20000*$A$4)*$D$37,0) -> 0 | M37: =IF(SUM(M34,M36)>20000*$A$4,(SUM(M34,M36)-20000*$A$4)*$D$37,0) -> 2060
B38: =tab!B38 -> % | C38: =tab!C38 -> Imposto de Renda | D38: =tab!D38 -> 0.15 | E38: =SUM(E34,E36)*$D$38 -> 63 | F38: =SUM(F34,F36)*$D$38 -> 2688 | G38: =SUM(G34,G36)*$D$38 -> 5313 | H38: =SUM(H34,H36)*$D$38 -> 8046 | I38: =SUM(I34,I36)*$D$38 -> 15090 | J38: =SUM(J34,J36)*$D$38 -> 18840 | K38: =SUM(K34,K36)*$D$38 -> 22590 | L38: =SUM(L34,L36)*$D$38 -> 26340 | M38: =SUM(M34,M36)*$D$38 -> 30090
B39: =tab!B39 -> % | C39: =tab!C39 -> Contribuição Social | D39: =tab!D39 -> 0.09 | E39: =SUM(E34,E36)*$D$39 -> 37.8 | F39: =SUM(F34,F36)*$D$39 -> 1612.8 | G39: =SUM(G34,G36)*$D$39 -> 3187.8 | H39: =SUM(H34,H36)*$D$39 -> 4827.6 | I39: =SUM(I34,I36)*$D$39 -> 9054 | J39: =SUM(J34,J36)*$D$39 -> 11304 | K39: =SUM(K34,K36)*$D$39 -> 13554 | L39: =SUM(L34,L36)*$D$39 -> 15804 | M39: =SUM(M34,M36)*$D$39 -> 18054
B40: =tab!B40 -> = | C40: =tab!C40 -> Compensações | E40: =SUM(E42:E47) -> -3600 | F40: =SUM(F42:F47) -> -3600 | G40: =SUM(G42:G47) -> -4300.8 | H40: =SUM(H42:H47) -> -8500.8 | I40: =SUM(I42:I47) -> -12873.6 | J40: =SUM(J42:J47) -> -24144 | K40: =SUM(K42:K47) -> -30144 | L40: =SUM(L42:L47) -> -36144 | M40: =SUM(M42:M47) -> -42144
B41: =tab!B41 -> - | C41: =tab!C41 -> IR Base Negativa Exercícios Anteriores | D41: =LEFT(C41,2) -> IR | E41: =HLOOKUP(E$4,tab!$E$4:$P$49,MATCH($C41,$C$4:$C$49,0),0) -> 0 | F41: =HLOOKUP(F$4,tab!$E$4:$P$49,MATCH($C41,$C$4:$C$49,0),0) -> 0 | G41: =HLOOKUP(G$4,tab!$E$4:$P$49,MATCH($C41,$C$4:$C$49,0),0) -> 0 | H41: =HLOOKUP(H$4,tab!$E$4:$P$49,MATCH($C41,$C$4:$C$49,0),0) -> 0 | I41: =HLOOKUP(I$4,tab!$E$4:$P$49,MATCH($C41,$C$4:$C$49,0),0) -> 0 | J41: =HLOOKUP(J$4,tab!$E$4:$P$49,MATCH($C41,$C$4:$C$49,0),0) -> 0 | K41: =HLOOKUP(K$4,tab!$E$4:$P$49,MATCH($C41,$C$4:$C$49,0),0) -> 0 | L41: =HLOOKUP(L$4,tab!$E$4:$P$49,MATCH($C41,$C$4:$C$49,0),0) -> 0 | M41: =HLOOKUP(M$4,tab!$E$4:$P$49,MATCH($C41,$C$4:$C$49,0),0) -> 0
B42: =tab!B42 -> - | C42: =tab!C42 -> IR s/ Aplicações Financeiras | D42: =LEFT(C42,2) -> IR | E42: =HLOOKUP(E$4,tab!$E$4:$P$49,MATCH($C42,$C$4:$C$49,0),0) -> -100 | F42: =HLOOKUP(F$4,tab!$E$4:$P$49,MATCH($C42,$C$4:$C$49,0),0) -> -100 | G42: =HLOOKUP(G$4,tab!$E$4:$P$49,MATCH($C42,$C$4:$C$49,0),0) -> -100 | H42: =HLOOKUP(H$4,tab!$E$4:$P$49,MATCH($C42,$C$4:$C$49,0),0) -> -100 | I42: =HLOOKUP(I$4,tab!$E$4:$P$49,MATCH($C42,$C$4:$C$49,0),0) -> -100 | J42: =HLOOKUP(J$4,tab!$E$4:$P$49,MATCH($C42,$C$4:$C$49,0),0) -> -100 | K42: =HLOOKUP(K$4,tab!$E$4:$P$49,MATCH($C42,$C$4:$C$49,0),0) -> -100 | L42: =HLOOKUP(L$4,tab!$E$4:$P$49,MATCH($C42,$C$4:$C$49,0),0) -> -100 | M42: =HLOOKUP(M$4,tab!$E$4:$P$49,MATCH($C42,$C$4:$C$49,0),0) -> -100
B43: =tab!B43 -> - | C43: =tab!C43 -> IR Retida s/ Notas Fiscais | D43: =LEFT(C43,2) -> IR | E43: =HLOOKUP(E$4,tab!$E$4:$P$49,MATCH($C43,$C$4:$C$49,0),0) -> -2000 | F43: =HLOOKUP(F$4,tab!$E$4:$P$49,MATCH($C43,$C$4:$C$49,0),0) -> -2000 | G43: =HLOOKUP(G$4,tab!$E$4:$P$49,MATCH($C43,$C$4:$C$49,0),0) -> -2000 | H43: =HLOOKUP(H$4,tab!$E$4:$P$49,MATCH($C43,$C$4:$C$49,0),0) -> -2000 | I43: =HLOOKUP(I$4,tab!$E$4:$P$49,MATCH($C43,$C$4:$C$49,0),0) -> -2000 | J43: =HLOOKUP(J$4,tab!$E$4:$P$49,MATCH($C43,$C$4:$C$49,0),0) -> -2000 | K43: =HLOOKUP(K$4,tab!$E$4:$P$49,MATCH($C43,$C$4:$C$49,0),0) -> -2000 | L43: =HLOOKUP(L$4,tab!$E$4:$P$49,MATCH($C43,$C$4:$C$49,0),0) -> -2000 | M43: =HLOOKUP(M$4,tab!$E$4:$P$49,MATCH($C43,$C$4:$C$49,0),0) -> -2000
B44: =tab!B44 -> - | C44: =tab!C44 -> IR Pago no Exercício | D44: =LEFT(C44,2) -> IR | E44: =HLOOKUP(E$4,tab!$E$4:$P$49,MATCH($C44,$C$4:$C$49,0),0) -> 0 | F44: =-E48 -> 0 | G44: =-SUM($E$48:F48) -> -588 | H44: =-SUM($E$48:G48) -> -3213 | I44: =-SUM($E$48:H48) -> -5946 | J44: =-SUM($E$48:I48) -> -12990 | K44: =-SUM($E$48:J48) -> -16740 | L44: =-SUM($E$48:K48) -> -20490 | M44: =-SUM($E$48:L48) -> -24240
B45: =tab!B45 -> - | C45: =tab!C45 -> CS Base Negativa Exercícios Anteriores | D45: =LEFT(C45,2) -> CS | E45: =HLOOKUP(E$4,tab!$E$4:$P$49,MATCH($C45,$C$4:$C$49,0),0) -> 0 | F45: =HLOOKUP(F$4,tab!$E$4:$P$49,MATCH($C45,$C$4:$C$49,0),0) -> 0 | G45: =HLOOKUP(G$4,tab!$E$4:$P$49,MATCH($C45,$C$4:$C$49,0),0) -> 0 | H45: =HLOOKUP(H$4,tab!$E$4:$P$49,MATCH($C45,$C$4:$C$49,0),0) -> 0 | I45: =HLOOKUP(I$4,tab!$E$4:$P$49,MATCH($C45,$C$4:$C$49,0),0) -> 0 | J45: =HLOOKUP(J$4,tab!$E$4:$P$49,MATCH($C45,$C$4:$C$49,0),0) -> 0 | K45: =HLOOKUP(K$4,tab!$E$4:$P$49,MATCH($C45,$C$4:$C$49,0),0) -> 0 | L45: =HLOOKUP(L$4,tab!$E$4:$P$49,MATCH($C45,$C$4:$C$49,0),0) -> 0 | M45: =HLOOKUP(M$4,tab!$E$4:$P$49,MATCH($C45,$C$4:$C$49,0),0) -> 0
B46: =tab!B46 -> - | C46: =tab!C46 -> CS Retida s/ Notas Fiscais | D46: =LEFT(C46,2) -> CS | E46: =HLOOKUP(E$4,tab!$E$4:$P$49,MATCH($C46,$C$4:$C$49,0),0) -> -1500 | F46: =HLOOKUP(F$4,tab!$E$4:$P$49,MATCH($C46,$C$4:$C$49,0),0) -> -1500 | G46: =HLOOKUP(G$4,tab!$E$4:$P$49,MATCH($C46,$C$4:$C$49,0),0) -> -1500 | H46: =HLOOKUP(H$4,tab!$E$4:$P$49,MATCH($C46,$C$4:$C$49,0),0) -> -1500 | I46: =HLOOKUP(I$4,tab!$E$4:$P$49,MATCH($C46,$C$4:$C$49,0),0) -> -1500 | J46: =HLOOKUP(J$4,tab!$E$4:$P$49,MATCH($C46,$C$4:$C$49,0),0) -> -1500 | K46: =HLOOKUP(K$4,tab!$E$4:$P$49,MATCH($C46,$C$4:$C$49,0),0) -> -1500 | L46: =HLOOKUP(L$4,tab!$E$4:$P$49,MATCH($C46,$C$4:$C$49,0),0) -> -1500 | M46: =HLOOKUP(M$4,tab!$E$4:$P$49,MATCH($C46,$C$4:$C$49,0),0) -> -1500
B47: =tab!B47 -> - | C47: =tab!C47 -> CS Pago no Exercício | D47: =LEFT(C47,2) -> CS | E47: =HLOOKUP(E$4,tab!$E$4:$P$49,MATCH($C47,$C$4:$C$49,0),0) -> 0 | F47: =-E49 -> 0 | G47: =-SUM($E$49:F49) -> -112.8 | H47: =-SUM($E$49:G49) -> -1687.8 | I47: =-SUM($E$49:H49) -> -3327.6 | J47: =-SUM($E$49:I49) -> -7554 | K47: =-SUM($E$49:J49) -> -9804 | L47: =-SUM($E$49:K49) -> -12054 | M47: =-SUM($E$49:L49) -> -14304
B48: =tab!B48 -> = | C48: =tab!C48 -> Imposto de Renda a Pagar | E48: =IF(SUM(E37,E38,SUMIF($D$41:E47,"IR",E$41:E$47))>0,SUM(E37,E38,SUMIF($D$41:E47,"IR",E$41:E$47)),0) -> 0 | F48: =IF(SUM(F37,F38,SUMIF($D$41:F47,"IR",F$41:F$47))>0,SUM(F37,F38,SUMIF($D$41:F47,"IR",F$41:F$47)),0) -> 588 | G48: =IF(SUM(G37,G38,SUMIF($D$41:G47,"IR",G$41:G$47))>0,SUM(G37,G38,SUMIF($D$41:G47,"IR",G$41:G$47)),0) -> 2625 | H48: =IF(SUM(H37,H38,SUMIF($D$41:H47,"IR",H$41:H$47))>0,SUM(H37,H38,SUMIF($D$41:H47,"IR",H$41:H$47)),0) -> 2733 | I48: =IF(SUM(I37,I38,SUMIF($D$41:I47,"IR",I$41:I$47))>0,SUM(I37,I38,SUMIF($D$41:I47,"IR",I$41:I$47)),0) -> 7044 | J48: =IF(SUM(J37,J38,SUMIF($D$41:J47,"IR",J$41:J$47))>0,SUM(J37,J38,SUMIF($D$41:J47,"IR",J$41:J$47)),0) -> 3750 | K48: =IF(SUM(K37,K38,SUMIF($D$41:K47,"IR",K$41:K$47))>0,SUM(K37,K38,SUMIF($D$41:K47,"IR",K$41:K$47)),0) -> 3750 | L48: =IF(SUM(L37,L38,SUMIF($D$41:L47,"IR",L$41:L$47))>0,SUM(L37,L38,SUMIF($D$41:L47,"IR",L$41:L$47)),0) -> 3750 | M48: =IF(SUM(M37,M38,SUMIF($D$41:M47,"IR",M$41:M$47))>0,SUM(M37,M38,SUMIF($D$41:M47,"IR",M$41:M$47)),0) -> 5810
B49: =tab!B49 -> = | C49: =tab!C49 -> Contribuição Social a Pagar | E49: =IF(SUM(E39,SUMIF($D$41:E47,"CS",E$41:E$47))>0,SUM(E39,SUMIF($D$41:E47,"CS",E$41:E$47)),0) -> 0 | F49: =IF(SUM(F39,SUMIF($D$41:F47,"CS",F$41:F$47))>0,SUM(F39,SUMIF($D$41:F47,"CS",F$41:F$47)),0) -> 112.8 | G49: =IF(SUM(G39,SUMIF($D$41:G47,"CS",G$41:G$47))>0,SUM(G39,SUMIF($D$41:G47,"CS",G$41:G$47)),0) -> 1575 | H49: =IF(SUM(H39,SUMIF($D$41:H47,"CS",H$41:H$47))>0,SUM(H39,SUMIF($D$41:H47,"CS",H$41:H$47)),0) -> 1639.8 | I49: =IF(SUM(I39,SUMIF($D$41:I47,"CS",I$41:I$47))>0,SUM(I39,SUMIF($D$41:I47,"CS",I$41:I$47)),0) -> 4226.4 | J49: =IF(SUM(J39,SUMIF($D$41:J47,"CS",J$41:J$47))>0,SUM(J39,SUMIF($D$41:J47,"CS",J$41:J$47)),0) -> 2250 | K49: =IF(SUM(K39,SUMIF($D$41:K47,"CS",K$41:K$47))>0,SUM(K39,SUMIF($D$41:K47,"CS",K$41:K$47)),0) -> 2250 | L49: =IF(SUM(L39,SUMIF($D$41:L47,"CS",L$41:L$47))>0,SUM(L39,SUMIF($D$41:L47,"CS",L$41:L$47)),0) -> 2250 | M49: =IF(SUM(M39,SUMIF($D$41:M47,"CS",M$41:M$47))>0,SUM(M39,SUMIF($D$41:M47,"CS",M$41:M$47)),0) -> 2250

Sheet out
B3: 2018
A4: 10 | B4: # | C4: Parâmetros | D4: % | E4: Jan | F4: Fev | G4: Mar | H4: Abr | I4: Mai | J4: Jun | K4: Jul | L4: Ago | M4: Set | N4: Out | O4: Nov | P4: Dez
A5: 2018 | B5: =tab!B5 -> = | C5: =tab!C5 -> Lucro Acumulado | E5: =HLOOKUP(E$4,tab!$E$4:$P$33,MATCH($C5,$C$4:$C$33,0),0) -> 1000 | F5: =HLOOKUP(F$4,tab!$E$4:$P$33,MATCH($C5,$C$4:$C$33,0),0) -> 26000 | G5: =HLOOKUP(G$4,tab!$E$4:$P$33,MATCH($C5,$C$4:$C$33,0),0) -> 51000 | H5: =HLOOKUP(H$4,tab!$E$4:$P$33,MATCH($C5,$C$4:$C$33,0),0) -> 76000 | I5: =HLOOKUP(I$4,tab!$E$4:$P$33,MATCH($C5,$C$4:$C$33,0),0) -> 101000 | J5: =HLOOKUP(J$4,tab!$E$4:$P$33,MATCH($C5,$C$4:$C$33,0),0) -> 126000 | K5: =HLOOKUP(K$4,tab!$E$4:$P$33,MATCH($C5,$C$4:$C$33,0),0) -> 151000 | L5: =HLOOKUP(L$4,tab!$E$4:$P$33,MATCH($C5,$C$4:$C$33,0),0) -> 176000 | ... N5: =HLOOKUP(N$4,tab!$E$4:$P$33,MATCH($C5,$C$4:$C$33,0),0) -> 226000
A6: 2019 | B6: =tab!B6 -> = | C6: =tab!C6 -> Adições | E6: =SUM(E7:E19) -> 600 | F6: =SUM(F7:F19) -> 600 | G6: =SUM(G7:G19) -> 600 | H6: =SUM(H7:H19) -> 600 | I6: =SUM(I7:I19) -> 600 | J6: =SUM(J7:J19) -> 600 | K6: =SUM(K7:K19) -> 600 | L6: =SUM(L7:L19) -> 600 | ... N6: =SUM(N7:N19) -> 600
A7: 2020 | B7: =tab!B7 -> + | C7: =tab!C7 -> Ajustes Devedores de Qualquer Natureza | E7: =HLOOKUP(E$4,tab!$E$4:$P$49,MATCH($C7,$C$4:$C$49,0),0) -> 0 | F7: =HLOOKUP(F$4,tab!$E$4:$P$49,MATCH($C7,$C$4:$C$49,0),0) -> 0 | G7: =HLOOKUP(G$4,tab!$E$4:$P$49,MATCH($C7,$C$4:$C$49,0),0) -> 0 | H7: =HLOOKUP(H$4,tab!$E$4:$P$49,MATCH($C7,$C$4:$C$49,0),0) -> 0 | I7: =HLOOKUP(I$4,tab!$E$4:$P$49,MATCH($C7,$C$4:$C$49,0),0) -> 0 | J7: =HLOOKUP(J$4,tab!$E$4:$P$49,MATCH($C7,$C$4:$C$49,0),0) -> 0 | K7: =HLOOKUP(K$4,tab!$E$4:$P$49,MATCH($C7,$C$4:$C$49,0),0) -> 0 | L7: =HLOOKUP(L$4,tab!$E$4:$P$49,MATCH($C7,$C$4:$C$49,0),0) -> 0 | ... N7: =HLOOKUP(N$4,tab!$E$4:$P$49,MATCH($C7,$C$4:$C$49,0),0) -> 0
A8: 2021 | B8: =tab!B8 -> + | C8: =tab!C8 -> Despesas de Variação Cambial | E8: =HLOOKUP(E$4,tab!$E$4:$P$49,MATCH($C8,$C$4:$C$49,0),0) -> 0 | F8: =HLOOKUP(F$4,tab!$E$4:$P$49,MATCH($C8,$C$4:$C$49,0),0) -> 0 | G8: =HLOOKUP(G$4,tab!$E$4:$P$49,MATCH($C8,$C$4:$C$49,0),0) -> 0 | H8: =HLOOKUP(H$4,tab!$E$4:$P$49,MATCH($C8,$C$4:$C$49,0),0) -> 0 | I8: =HLOOKUP(I$4,tab!$E$4:$P$49,MATCH($C8,$C$4:$C$49,0),0) -> 0 | J8: =HLOOKUP(J$4,tab!$E$4:$P$49,MATCH($C8,$C$4:$C$49,0),0) -> 0 | K8: =HLOOKUP(K$4,tab!$E$4:$P$49,MATCH($C8,$C$4:$C$49,0),0) -> 0 | L8: =HLOOKUP(L$4,tab!$E$4:$P$49,MATCH($C8,$C$4:$C$49,0),0) -> 0 | ... N8: =HLOOKUP(N$4,tab!$E$4:$P$49,MATCH($C8,$C$4:$C$49,0),0) -> 0
A9: 2022 | B9: =tab!B9 -> + | C9: =tab!C9 -> Despesas Particulares dos Sócios e Dirigentes; | E9: =HLOOKUP(E$4,tab!$E$4:$P$49,MATCH($C9,$C$4:$C$49,0),0) -> 0 | F9: =HLOOKUP(F$4,tab!$E$4:$P$49,MATCH($C9,$C$4:$C$49,0),0) -> 0 | G9: =HLOOKUP(G$4,tab!$E$4:$P$49,MATCH($C9,$C$4:$C$49,0),0) -> 0 | H9: =HLOOKUP(H$4,tab!$E$4:$P$49,MATCH($C9,$C$4:$C$49,0),0) -> 0 | I9: =HLOOKUP(I$4,tab!$E$4:$P$49,MATCH($C9,$C$4:$C$49,0),0) -> 0 | J9: =HLOOKUP(J$4,tab!$E$4:$P$49,MATCH($C9,$C$4:$C$49,0),0) -> 0 | K9: =HLOOKUP(K$4,tab!$E$4:$P$49,MATCH($C9,$C$4:$C$49,0),0) -> 0 | L9: =HLOOKUP(L$4,tab!$E$4:$P$49,MATCH($C9,$C$4:$C$49,0),0) -> 0 | ... N9: =HLOOKUP(N$4,tab!$E$4:$P$49,MATCH($C9,$C$4:$C$49,0),0) -> 0
A10: 2023 | B10: =tab!B10 -> + | C10: =tab!C10 -> Doações e Brindes; | E10: =HLOOKUP(E$4,tab!$E$4:$P$49,MATCH($C10,$C$4:$C$49,0),0) -> 100 | F10: =HLOOKUP(F$4,tab!$E$4:$P$49,MATCH($C10,$C$4:$C$49,0),0) -> 100 | G10: =HLOOKUP(G$4,tab!$E$4:$P$49,MATCH($C10,$C$4:$C$49,0),0) -> 100 | H10: =HLOOKUP(H$4,tab!$E$4:$P$49,MATCH($C10,$C$4:$C$49,0),0) -> 100 | I10: =HLOOKUP(I$4,tab!$E$4:$P$49,MATCH($C10,$C$4:$C$49,0),0) -> 100 | J10: =HLOOKUP(J$4,tab!$E$4:$P$49,MATCH($C10,$C$4:$C$49,0),0) -> 100 | K10: =HLOOKUP(K$4,tab!$E$4:$P$49,MATCH($C10,$C$4:$C$49,0),0) -> 100 | L10: =HLOOKUP(L$4,tab!$E$4:$P$49,MATCH($C10,$C$4:$C$49,0),0) -> 100 | ... N10: =HLOOKUP(N$4,tab!$E$4:$P$49,MATCH($C10,$C$4:$C$49,0),0) -> 100
A11: 2024 | B11: =tab!B11 -> + | C11: =tab!C11 -> Impostos Não Pagos em Discussão Judicial; | E11: =HLOOKUP(E$4,tab!$E$4:$P$49,MATCH($C11,$C$4:$C$49,0),0) -> 0 | F11: =HLOOKUP(F$4,tab!$E$4:$P$49,MATCH($C11,$C$4:$C$49,0),0) -> 0 | G11: =HLOOKUP(G$4,tab!$E$4:$P$49,MATCH($C11,$C$4:$C$49,0),0) -> 0 | H11: =HLOOKUP(H$4,tab!$E$4:$P$49,MATCH($C11,$C$4:$C$49,0),0) -> 0 | I11: =HLOOKUP(I$4,tab!$E$4:$P$49,MATCH($C11,$C$4:$C$49,0),0) -> 0 | J11: =HLOOKUP(J$4,tab!$E$4:$P$49,MATCH($C11,$C$4:$C$49,0),0) -> 0 | K11: =HLOOKUP(K$4,tab!$E$4:$P$49,MATCH($C11,$C$4:$C$49,0),0) -> 0 | L11: =HLOOKUP(L$4,tab!$E$4:$P$49,MATCH($C11,$C$4:$C$49,0),0) -> 0 | ... N11: =HLOOKUP(N$4,tab!$E$4:$P$49,MATCH($C11,$C$4:$C$49,0),0) -> 0
A12: 2025 | B12: =tab!B12 -> + | C12: =tab!C12 -> Impostos Não Pagos por Iniciativa da Empresa; | E12: =HLOOKUP(E$4,tab!$E$4:$P$49,MATCH($C12,$C$4:$C$49,0),0) -> 0 | F12: =HLOOKUP(F$4,tab!$E$4:$P$49,MATCH($C12,$C$4:$C$49,0),0) -> 0 | G12: =HLOOKUP(G$4,tab!$E$4:$P$49,MATCH($C12,$C$4:$C$49,0),0) -> 0 | H12: =HLOOKUP(H$4,tab!$E$4:$P$49,MATCH($C12,$C$4:$C$49,0),0) -> 0 | I12: =HLOOKUP(I$4,tab!$E$4:$P$49,MATCH($C12,$C$4:$C$49,0),0) -> 0 | J12: =HLOOKUP(J$4,tab!$E$4:$P$49,MATCH($C12,$C$4:$C$49,0),0) -> 0 | K12: =HLOOKUP(K$4,tab!$E$4:$P$49,MATCH($C12,$C$4:$C$49,0),0) -> 0 | L12: =HLOOKUP(L$4,tab!$E$4:$P$49,MATCH($C12,$C$4:$C$49,0),0) -> 0 | ... N12: =HLOOKUP(N$4,tab!$E$4:$P$49,MATCH($C12,$C$4:$C$49,0),0) -> 0
A13: 2026 | B13: =tab!B13 -> + | C13: =tab!C13 -> Lucro Inflacionário apurado até 31/12/1995; | E13: =HLOOKUP(E$4,tab!$E$4:$P$49,MATCH($C13,$C$4:$C$49,0),0) -> 0 | F13: =HLOOKUP(F$4,tab!$E$4:$P$49,MATCH($C13,$C$4:$C$49,0),0) -> 0 | G13: =HLOOKUP(G$4,tab!$E$4:$P$49,MATCH($C13,$C$4:$C$49,0),0) -> 0 | H13: =HLOOKUP(H$4,tab!$E$4:$P$49,MATCH($C13,$C$4:$C$49,0),0) -> 0 | I13: =HLOOKUP(I$4,tab!$E$4:$P$49,MATCH($C13,$C$4:$C$49,0),0) -> 0 | J13: =HLOOKUP(J$4,tab!$E$4:$P$49,MATCH($C13,$C$4:$C$49,0),0) -> 0 | K13: =HLOOKUP(K$4,tab!$E$4:$P$49,MATCH($C13,$C$4:$C$49,0),0) -> 0 | L13: =HLOOKUP(L$4,tab!$E$4:$P$49,MATCH($C13,$C$4:$C$49,0),0) -> 0 | ... N13: =HLOOKUP(N$4,tab!$E$4:$P$49,MATCH($C13,$C$4:$C$49,0),0) -> 0
A14: 2027 | B14: =tab!B14 -> + | C14: =tab!C14 -> Multas Contratuais | E14: =HLOOKUP(E$4,tab!$E$4:$P$49,MATCH($C14,$C$4:$C$49,0),0) -> 0 | F14: =HLOOKUP(F$4,tab!$E$4:$P$49,MATCH($C14,$C$4:$C$49,0),0) -> 0 | G14: =HLOOKUP(G$4,tab!$E$4:$P$49,MATCH($C14,$C$4:$C$49,0),0) -> 0 | H14: =HLOOKUP(H$4,tab!$E$4:$P$49,MATCH($C14,$C$4:$C$49,0),0) -> 0 | I14: =HLOOKUP(I$4,tab!$E$4:$P$49,MATCH($C14,$C$4:$C$49,0),0) -> 0 | J14: =HLOOKUP(J$4,tab!$E$4:$P$49,MATCH($C14,$C$4:$C$49,0),0) -> 0 | K14: =HLOOKUP(K$4,tab!$E$4:$P$49,MATCH($C14,$C$4:$C$49,0),0) -> 0 | L14: =HLOOKUP(L$4,tab!$E$4:$P$49,MATCH($C14,$C$4:$C$49,0),0) -> 0 | ... N14: =HLOOKUP(N$4,tab!$E$4:$P$49,MATCH($C14,$C$4:$C$49,0),0) -> 0
A15: 2028 | B15: =tab!B15 -> + | C15: =tab!C15 -> Multas Punitivas (Transito, Imetro, Ibama, Multas sobre ação fiscal) | E15: =HLOOKUP(E$4,tab!$E$4:$P$49,MATCH($C15,$C$4:$C$49,0),0) -> 500 | F15: =HLOOKUP(F$4,tab!$E$4:$P$49,MATCH($C15,$C$4:$C$49,0),0) -> 500 | G15: =HLOOKUP(G$4,tab!$E$4:$P$49,MATCH($C15,$C$4:$C$49,0),0) -> 500 | H15: =HLOOKUP(H$4,tab!$E$4:$P$49,MATCH($C15,$C$4:$C$49,0),0) -> 500 | I15: =HLOOKUP(I$4,tab!$E$4:$P$49,MATCH($C15,$C$4:$C$49,0),0) -> 500 | J15: =HLOOKUP(J$4,tab!$E$4:$P$49,MATCH($C15,$C$4:$C$49,0),0) -> 500 | K15: =HLOOKUP(K$4,tab!$E$4:$P$49,MATCH($C15,$C$4:$C$49,0),0) -> 500 | L15: =HLOOKUP(L$4,tab!$E$4:$P$49,MATCH($C15,$C$4:$C$49,0),0) -> 500 | ... N15: =HLOOKUP(N$4,tab!$E$4:$P$49,MATCH($C15,$C$4:$C$49,0),0) -> 500
A16: 2029 | B16: =tab!B16 -> + | C16: =tab!C16 -> Orçamentos, Pedidos e qualquer documento não idôneo; | E16: =HLOOKUP(E$4,tab!$E$4:$P$49,MATCH($C16,$C$4:$C$49,0),0) -> 0 | F16: =HLOOKUP(F$4,tab!$E$4:$P$49,MATCH($C16,$C$4:$C$49,0),0) -> 0 | G16: =HLOOKUP(G$4,tab!$E$4:$P$49,MATCH($C16,$C$4:$C$49,0),0) -> 0 | H16: =HLOOKUP(H$4,tab!$E$4:$P$49,MATCH($C16,$C$4:$C$49,0),0) -> 0 | I16: =HLOOKUP(I$4,tab!$E$4:$P$49,MATCH($C16,$C$4:$C$49,0),0) -> 0 | J16: =HLOOKUP(J$4,tab!$E$4:$P$49,MATCH($C16,$C$4:$C$49,0),0) -> 0 | K16: =HLOOKUP(K$4,tab!$E$4:$P$49,MATCH($C16,$C$4:$C$49,0),0) -> 0 | L16: =HLOOKUP(L$4,tab!$E$4:$P$49,MATCH($C16,$C$4:$C$49,0),0) -> 0 | ... N16: =HLOOKUP(N$4,tab!$E$4:$P$49,MATCH($C16,$C$4:$C$49,0),0) -> 0
A17: 2030 | B17: =tab!B17 -> + | C17: =tab!C17 -> Provisões Indedutíveis (perdas, frete, propaganda) | E17: =HLOOKUP(E$4,tab!$E$4:$P$49,MATCH($C17,$C$4:$C$49,0),0) -> 0 | F17: =HLOOKUP(F$4,tab!$E$4:$P$49,MATCH($C17,$C$4:$C$49,0),0) -> 0 | G17: =HLOOKUP(G$4,tab!$E$4:$P$49,MATCH($C17,$C$4:$C$49,0),0) -> 0 | H17: =HLOOKUP(H$4,tab!$E$4:$P$49,MATCH($C17,$C$4:$C$49,0),0) -> 0 | I17: =HLOOKUP(I$4,tab!$E$4:$P$49,MATCH($C17,$C$4:$C$49,0),0) -> 0 | J17: =HLOOKUP(J$4,tab!$E$4:$P$49,MATCH($C17,$C$4:$C$49,0),0) -> 0 | K17: =HLOOKUP(K$4,tab!$E$4:$P$49,MATCH($C17,$C$4:$C$49,0),0) -> 0 | L17: =HLOOKUP(L$4,tab!$E$4:$P$49,MATCH($C17,$C$4:$C$49,0),0) -> 0 | ... N17: =HLOOKUP(N$4,tab!$E$4:$P$49,MATCH($C17,$C$4:$C$49,0),0) -> 0
B18: =tab!B18 -> + | C18: =tab!C18 -> Recibos sem especificação da fonte recebedora; | E18: =HLOOKUP(E$4,tab!$E$4:$P$49,MATCH($C18,$C$4:$C$49,0),0) -> 0 | F18: =HLOOKUP(F$4,tab!$E$4:$P$49,MATCH($C18,$C$4:$C$49,0),0) -> 0 | G18: =HLOOKUP(G$4,tab!$E$4:$P$49,MATCH($C18,$C$4:$C$49,0),0) -> 0 | H18: =HLOOKUP(H$4,tab!$E$4:$P$49,MATCH($C18,$C$4:$C$49,0),0) -> 0 | I18: =HLOOKUP(I$4,tab!$E$4:$P$49,MATCH($C18,$C$4:$C$49,0),0) -> 0 | J18: =HLOOKUP(J$4,tab!$E$4:$P$49,MATCH($C18,$C$4:$C$49,0),0) -> 0 | K18: =HLOOKUP(K$4,tab!$E$4:$P$49,MATCH($C18,$C$4:$C$49,0),0) -> 0 | L18: =HLOOKUP(L$4,tab!$E$4:$P$49,MATCH($C18,$C$4:$C$49,0),0) -> 0 | ... N18: =HLOOKUP(N$4,tab!$E$4:$P$49,MATCH($C18,$C$4:$C$49,0),0) -> 0
B19: =tab!B19 -> + | C19: =tab!C19 -> Verbas Rescisórias em desacordo com a legislação trabalhista vigente | E19: =HLOOKUP(E$4,tab!$E$4:$P$49,MATCH($C19,$C$4:$C$49,0),0) -> 0 | F19: =HLOOKUP(F$4,tab!$E$4:$P$49,MATCH($C19,$C$4:$C$49,0),0) -> 0 | G19: =HLOOKUP(G$4,tab!$E$4:$P$49,MATCH($C19,$C$4:$C$49,0),0) -> 0 | H19: =HLOOKUP(H$4,tab!$E$4:$P$49,MATCH($C19,$C$4:$C$49,0),0) -> 0 | I19: =HLOOKUP(I$4,tab!$E$4:$P$49,MATCH($C19,$C$4:$C$49,0),0) -> 0 | J19: =HLOOKUP(J$4,tab!$E$4:$P$49,MATCH($C19,$C$4:$C$49,0),0) -> 0 | K19: =HLOOKUP(K$4,tab!$E$4:$P$49,MATCH($C19,$C$4:$C$49,0),0) -> 0 | L19: =HLOOKUP(L$4,tab!$E$4:$P$49,MATCH($C19,$C$4:$C$49,0),0) -> 0 | ... N19: =HLOOKUP(N$4,tab!$E$4:$P$49,MATCH($C19,$C$4:$C$49,0),0) -> 0
B20: =tab!B20 -> = | C20: =tab!C20 -> Exclusões | E20: =SUM(E21:E33) -> -1000 | F20: =SUM(F21:F33) -> -1000 | G20: =SUM(G21:G33) -> -1000 | H20: =SUM(H21:H33) -> -1000 | I20: =SUM(I21:I33) -> -1000 | J20: =SUM(J21:J33) -> -1000 | K20: =SUM(K21:K33) -> -1000 | L20: =SUM(L21:L33) -> -1000 | ... N20: =SUM(N21:N33) -> -1000
B21: =tab!B21 -> - | C21: =tab!C21 -> Ajustes credores de qualquer natureza | E21: =HLOOKUP(E$4,tab!$E$4:$P$49,MATCH($C21,$C$4:$C$49,0),0) -> 0 | F21: =HLOOKUP(F$4,tab!$E$4:$P$49,MATCH($C21,$C$4:$C$49,0),0) -> 0 | G21: =HLOOKUP(G$4,tab!$E$4:$P$49,MATCH($C21,$C$4:$C$49,0),0) -> 0 | H21: =HLOOKUP(H$4,tab!$E$4:$P$49,MATCH($C21,$C$4:$C$49,0),0) -> 0 | I21: =HLOOKUP(I$4,tab!$E$4:$P$49,MATCH($C21,$C$4:$C$49,0),0) -> 0 | J21: =HLOOKUP(J$4,tab!$E$4:$P$49,MATCH($C21,$C$4:$C$49,0),0) -> 0 | K21: =HLOOKUP(K$4,tab!$E$4:$P$49,MATCH($C21,$C$4:$C$49,0),0) -> 0 | L21: =HLOOKUP(L$4,tab!$E$4:$P$49,MATCH($C21,$C$4:$C$49,0),0) -> 0 | ... N21: =HLOOKUP(N$4,tab!$E$4:$P$49,MATCH($C21,$C$4:$C$49,0),0) -> 0
B22: =tab!B22 -> - | C22: =tab!C22 -> Decisão Favorável - Processos Judiciais Tributários | E22: =HLOOKUP(E$4,tab!$E$4:$P$49,MATCH($C22,$C$4:$C$49,0),0) -> 0 | F22: =HLOOKUP(F$4,tab!$E$4:$P$49,MATCH($C22,$C$4:$C$49,0),0) -> 0 | G22: =HLOOKUP(G$4,tab!$E$4:$P$49,MATCH($C22,$C$4:$C$49,0),0) -> 0 | H22: =HLOOKUP(H$4,tab!$E$4:$P$49,MATCH($C22,$C$4:$C$49,0),0) -> 0 | I22: =HLOOKUP(I$4,tab!$E$4:$P$49,MATCH($C22,$C$4:$C$49,0),0) -> 0 | J22: =HLOOKUP(J$4,tab!$E$4:$P$49,MATCH($C22,$C$4:$C$49,0),0) -> 0 | K22: =HLOOKUP(K$4,tab!$E$4:$P$49,MATCH($C22,$C$4:$C$49,0),0) -> 0 | L22: =HLOOKUP(L$4,tab!$E$4:$P$49,MATCH($C22,$C$4:$C$49,0),0) -> 0 | ... N22: =HLOOKUP(N$4,tab!$E$4:$P$49,MATCH($C22,$C$4:$C$49,0),0) -> 0
B23: =tab!B23 -> - | C23: =tab!C23 -> Despesas de Ágios | E23: =HLOOKUP(E$4,tab!$E$4:$P$49,MATCH($C23,$C$4:$C$49,0),0) -> 0 | F23: =HLOOKUP(F$4,tab!$E$4:$P$49,MATCH($C23,$C$4:$C$49,0),0) -> 0 | G23: =HLOOKUP(G$4,tab!$E$4:$P$49,MATCH($C23,$C$4:$C$49,0),0) -> 0 | H23: =HLOOKUP(H$4,tab!$E$4:$P$49,MATCH($C23,$C$4:$C$49,0),0) -> 0 | I23: =HLOOKUP(I$4,tab!$E$4:$P$49,MATCH($C23,$C$4:$C$49,0),0) -> 0 | J23: =HLOOKUP(J$4,tab!$E$4:$P$49,MATCH($C23,$C$4:$C$49,0),0) -> 0 | K23: =HLOOKUP(K$4,tab!$E$4:$P$49,MATCH($C23,$C$4:$C$49,0),0) -> 0 | L23: =HLOOKUP(L$4,tab!$E$4:$P$49,MATCH($C23,$C$4:$C$49,0),0) -> 0 | ... N23: =HLOOKUP(N$4,tab!$E$4:$P$49,MATCH($C23,$C$4:$C$49,0),0) -> 0
B24: =tab!B24 -> - | C24: =tab!C24 -> Distribuição de Lucros e Dividendos; | E24: =HLOOKUP(E$4,tab!$E$4:$P$49,MATCH($C24,$C$4:$C$49,0),0) -> 0 | F24: =HLOOKUP(F$4,tab!$E$4:$P$49,MATCH($C24,$C$4:$C$49,0),0) -> 0 | G24: =HLOOKUP(G$4,tab!$E$4:$P$49,MATCH($C24,$C$4:$C$49,0),0) -> 0 | H24: =HLOOKUP(H$4,tab!$E$4:$P$49,MATCH($C24,$C$4:$C$49,0),0) -> 0 | I24: =HLOOKUP(I$4,tab!$E$4:$P$49,MATCH($C24,$C$4:$C$49,0),0) -> 0 | J24: =HLOOKUP(J$4,tab!$E$4:$P$49,MATCH($C24,$C$4:$C$49,0),0) -> 0 | K24: =HLOOKUP(K$4,tab!$E$4:$P$49,MATCH($C24,$C$4:$C$49,0),0) -> 0 | L24: =HLOOKUP(L$4,tab!$E$4:$P$49,MATCH($C24,$C$4:$C$49,0),0) -> 0 | ... N24: =HLOOKUP(N$4,tab!$E$4:$P$49,MATCH($C24,$C$4:$C$49,0),0) -> 0
B25: =tab!B25 -> - | C25: =tab!C25 -> Dividendos Coligadas e Controladas | E25: =HLOOKUP(E$4,tab!$E$4:$P$49,MATCH($C25,$C$4:$C$49,0),0) -> 0 | F25: =HLOOKUP(F$4,tab!$E$4:$P$49,MATCH($C25,$C$4:$C$49,0),0) -> 0 | G25: =HLOOKUP(G$4,tab!$E$4:$P$49,MATCH($C25,$C$4:$C$49,0),0) -> 0 | H25: =HLOOKUP(H$4,tab!$E$4:$P$49,MATCH($C25,$C$4:$C$49,0),0) -> 0 | I25: =HLOOKUP(I$4,tab!$E$4:$P$49,MATCH($C25,$C$4:$C$49,0),0) -> 0 | J25: =HLOOKUP(J$4,tab!$E$4:$P$49,MATCH($C25,$C$4:$C$49,0),0) -> 0 | K25: =HLOOKUP(K$4,tab!$E$4:$P$49,MATCH($C25,$C$4:$C$49,0),0) -> 0 | L25: =HLOOKUP(L$4,tab!$E$4:$P$49,MATCH($C25,$C$4:$C$49,0),0) -> 0 | ... N25: =HLOOKUP(N$4,tab!$E$4:$P$49,MATCH($C25,$C$4:$C$49,0),0) -> 0
B26: =tab!B26 -> - | C26: =tab!C26 -> Pagamento de Impostos em Atraso por iniciativa da Empresa | E26: =HLOOKUP(E$4,tab!$E$4:$P$49,MATCH($C26,$C$4:$C$49,0),0) -> -1000 | F26: =HLOOKUP(F$4,tab!$E$4:$P$49,MATCH($C26,$C$4:$C$49,0),0) -> -1000 | G26: =HLOOKUP(G$4,tab!$E$4:$P$49,MATCH($C26,$C$4:$C$49,0),0) -> -1000 | H26: =HLOOKUP(H$4,tab!$E$4:$P$49,MATCH($C26,$C$4:$C$49,0),0) -> -1000 | I26: =HLOOKUP(I$4,tab!$E$4:$P$49,MATCH($C26,$C$4:$C$49,0),0) -> -1000 | J26: =HLOOKUP(J$4,tab!$E$4:$P$49,MATCH($C26,$C$4:$C$49,0),0) -> -1000 | K26: =HLOOKUP(K$4,tab!$E$4:$P$49,MATCH($C26,$C$4:$C$49,0),0) -> -1000 | L26: =HLOOKUP(L$4,tab!$E$4:$P$49,MATCH($C26,$C$4:$C$49,0),0) -> -1000 | ... N26: =HLOOKUP(N$4,tab!$E$4:$P$49,MATCH($C26,$C$4:$C$49,0),0) -> -1000
B27: =tab!B27 -> - | C27: =tab!C27 -> Pagamento de Impostos sobre discussão judicial, | E27: =HLOOKUP(E$4,tab!$E$4:$P$49,MATCH($C27,$C$4:$C$49,0),0) -> 0 | F27: =HLOOKUP(F$4,tab!$E$4:$P$49,MATCH($C27,$C$4:$C$49,0),0) -> 0 | G27: =HLOOKUP(G$4,tab!$E$4:$P$49,MATCH($C27,$C$4:$C$49,0),0) -> 0 | H27: =HLOOKUP(H$4,tab!$E$4:$P$49,MATCH($C27,$C$4:$C$49,0),0) -> 0 | I27: =HLOOKUP(I$4,tab!$E$4:$P$49,MATCH($C27,$C$4:$C$49,0),0) -> 0 | J27: =HLOOKUP(J$4,tab!$E$4:$P$49,MATCH($C27,$C$4:$C$49,0),0) -> 0 | K27: =HLOOKUP(K$4,tab!$E$4:$P$49,MATCH($C27,$C$4:$C$49,0),0) -> 0 | L27: =HLOOKUP(L$4,tab!$E$4:$P$49,MATCH($C27,$C$4:$C$49,0),0) -> 0 | ... N27: =HLOOKUP(N$4,tab!$E$4:$P$49,MATCH($C27,$C$4:$C$49,0),0) -> 0
B28: =tab!B28 -> - | C28: =tab!C28 -> Receita de Variação Cambial | E28: =HLOOKUP(E$4,tab!$E$4:$P$49,MATCH($C28,$C$4:$C$49,0),0) -> 0 | F28: =HLOOKUP(F$4,tab!$E$4:$P$49,MATCH($C28,$C$4:$C$49,0),0) -> 0 | G28: =HLOOKUP(G$4,tab!$E$4:$P$49,MATCH($C28,$C$4:$C$49,0),0) -> 0 | H28: =HLOOKUP(H$4,tab!$E$4:$P$49,MATCH($C28,$C$4:$C$49,0),0) -> 0 | I28: =HLOOKUP(I$4,tab!$E$4:$P$49,MATCH($C28,$C$4:$C$49,0),0) -> 0 | J28: =HLOOKUP(J$4,tab!$E$4:$P$49,MATCH($C28,$C$4:$C$49,0),0) -> 0 | K28: =HLOOKUP(K$4,tab!$E$4:$P$49,MATCH($C28,$C$4:$C$49,0),0) -> 0 | L28: =HLOOKUP(L$4,tab!$E$4:$P$49,MATCH($C28,$C$4:$C$49,0),0) -> 0 | ... N28: =HLOOKUP(N$4,tab!$E$4:$P$49,MATCH($C28,$C$4:$C$49,0),0) -> 0
B29: =tab!B29 -> - | C29: =tab!C29 -> Receitas Obtidas com Tributação Exclusiva ou Isenta de IR | E29: =HLOOKUP(E$4,tab!$E$4:$P$49,MATCH($C29,$C$4:$C$49,0),0) -> 0 | F29: =HLOOKUP(F$4,tab!$E$4:$P$49,MATCH($C29,$C$4:$C$49,0),0) -> 0 | G29: =HLOOKUP(G$4,tab!$E$4:$P$49,MATCH($C29,$C$4:$C$49,0),0) -> 0 | H29: =HLOOKUP(H$4,tab!$E$4:$P$49,MATCH($C29,$C$4:$C$49,0),0) -> 0 | I29: =HLOOKUP(I$4,tab!$E$4:$P$49,MATCH($C29,$C$4:$C$49,0),0) -> 0 | J29: =HLOOKUP(J$4,tab!$E$4:$P$49,MATCH($C29,$C$4:$C$49,0),0) -> 0 | K29: =HLOOKUP(K$4,tab!$E$4:$P$49,MATCH($C29,$C$4:$C$49,0),0) -> 0 | L29: =HLOOKUP(L$4,tab!$E$4:$P$49,MATCH($C29,$C$4:$C$49,0),0) -> 0 | ... N29: =HLOOKUP(N$4,tab!$E$4:$P$49,MATCH($C29,$C$4:$C$49,0),0) -> 0
B30: =tab!B30 -> - | C30: =tab!C30 -> Receitas que poderiam ser diferidas; | E30: =HLOOKUP(E$4,tab!$E$4:$P$49,MATCH($C30,$C$4:$C$49,0),0) -> 0 | F30: =HLOOKUP(F$4,tab!$E$4:$P$49,MATCH($C30,$C$4:$C$49,0),0) -> 0 | G30: =HLOOKUP(G$4,tab!$E$4:$P$49,MATCH($C30,$C$4:$C$49,0),0) -> 0 | H30: =HLOOKUP(H$4,tab!$E$4:$P$49,MATCH($C30,$C$4:$C$49,0),0) -> 0 | I30: =HLOOKUP(I$4,tab!$E$4:$P$49,MATCH($C30,$C$4:$C$49,0),0) -> 0 | J30: =HLOOKUP(J$4,tab!$E$4:$P$49,MATCH($C30,$C$4:$C$49,0),0) -> 0 | K30: =HLOOKUP(K$4,tab!$E$4:$P$49,MATCH($C30,$C$4:$C$49,0),0) -> 0 | L30: =HLOOKUP(L$4,tab!$E$4:$P$49,MATCH($C30,$C$4:$C$49,0),0) -> 0 | ... N30: =HLOOKUP(N$4,tab!$E$4:$P$49,MATCH($C30,$C$4:$C$49,0),0) -> 0
B31: =tab!B31 -> - | C31: =tab!C31 -> Resultado Positivo de Equivalência Patrimonial | E31: =HLOOKUP(E$4,tab!$E$4:$P$49,MATCH($C31,$C$4:$C$49,0),0) -> 0 | F31: =HLOOKUP(F$4,tab!$E$4:$P$49,MATCH($C31,$C$4:$C$49,0),0) -> 0 | G31: =HLOOKUP(G$4,tab!$E$4:$P$49,MATCH($C31,$C$4:$C$49,0),0) -> 0 | H31: =HLOOKUP(H$4,tab!$E$4:$P$49,MATCH($C31,$C$4:$C$49,0),0) -> 0 | I31: =HLOOKUP(I$4,tab!$E$4:$P$49,MATCH($C31,$C$4:$C$49,0),0) -> 0 | J31: =HLOOKUP(J$4,tab!$E$4:$P$49,MATCH($C31,$C$4:$C$49,0),0) -> 0 | K31: =HLOOKUP(K$4,tab!$E$4:$P$49,MATCH($C31,$C$4:$C$49,0),0) -> 0 | L31: =HLOOKUP(L$4,tab!$E$4:$P$49,MATCH($C31,$C$4:$C$49,0),0) -> 0 | ... N31: =HLOOKUP(N$4,tab!$E$4:$P$49,MATCH($C31,$C$4:$C$49,0),0) -> 0
B32: =tab!B32 -> - | C32: =tab!C32 -> Reversão de Provisões Indedutíveis | E32: =HLOOKUP(E$4,tab!$E$4:$P$49,MATCH($C32,$C$4:$C$49,0),0) -> 0 | F32: =HLOOKUP(F$4,tab!$E$4:$P$49,MATCH($C32,$C$4:$C$49,0),0) -> 0 | G32: =HLOOKUP(G$4,tab!$E$4:$P$49,MATCH($C32,$C$4:$C$49,0),0) -> 0 | H32: =HLOOKUP(H$4,tab!$E$4:$P$49,MATCH($C32,$C$4:$C$49,0),0) -> 0 | I32: =HLOOKUP(I$4,tab!$E$4:$P$49,MATCH($C32,$C$4:$C$49,0),0) -> 0 | J32: =HLOOKUP(J$4,tab!$E$4:$P$49,MATCH($C32,$C$4:$C$49,0),0) -> 0 | K32: =HLOOKUP(K$4,tab!$E$4:$P$49,MATCH($C32,$C$4:$C$49,0),0) -> 0 | L32: =HLOOKUP(L$4,tab!$E$4:$P$49,MATCH($C32,$C$4:$C$49,0),0) -> 0 | ... N32: =HLOOKUP(N$4,tab!$E$4:$P$49,MATCH($C32,$C$4:$C$49,0),0) -> 0
B33: =tab!B33 -> - | C33: =tab!C33 -> Vendas Não Expedidas do Período | E33: =HLOOKUP(E$4,tab!$E$4:$P$49,MATCH($C33,$C$4:$C$49,0),0) -> 0 | F33: =HLOOKUP(F$4,tab!$E$4:$P$49,MATCH($C33,$C$4:$C$49,0),0) -> 0 | G33: =HLOOKUP(G$4,tab!$E$4:$P$49,MATCH($C33,$C$4:$C$49,0),0) -> 0 | H33: =HLOOKUP(H$4,tab!$E$4:$P$49,MATCH($C33,$C$4:$C$49,0),0) -> 0 | I33: =HLOOKUP(I$4,tab!$E$4:$P$49,MATCH($C33,$C$4:$C$49,0),0) -> 0 | J33: =HLOOKUP(J$4,tab!$E$4:$P$49,MATCH($C33,$C$4:$C$49,0),0) -> 0 | K33: =HLOOKUP(K$4,tab!$E$4:$P$49,MATCH($C33,$C$4:$C$49,0),0) -> 0 | L33: =HLOOKUP(L$4,tab!$E$4:$P$49,MATCH($C33,$C$4:$C$49,0),0) -> 0 | ... N33: =HLOOKUP(N$4,tab!$E$4:$P$49,MATCH($C33,$C$4:$C$49,0),0) -> 0
B34: =tab!B34 -> = | C34: =tab!C34 -> Base de Cálculo | E34: =SUM(E5,E6,E20) -> 600 | F34: =SUM(F5,F6,F20) -> 25600 | G34: =SUM(G5,G6,G20) -> 50600 | H34: =SUM(H5,H6,H20) -> 75600 | I34: =SUM(I5,I6,I20) -> 100600 | J34: =SUM(J5,J6,J20) -> 125600 | K34: =SUM(K5,K6,K20) -> 150600 | L34: =SUM(L5,L6,L20) -> 175600 | ... N34: =SUM(N5,N6,N20) -> 225600
B35: =tab!B35 -> = | C35: =tab!C35 -> Saldo Prejuízo Fiscal | E35: =tab!E35 -> 45000 | F35: =SUM(E35:E36) -> 44820 | G35: =SUM(F35:F36) -> 37140 | H35: =SUM(G35:G36) -> 21960 | I35: =SUM(H35:H36) -> 0 | J35: =SUM(I35:I36) -> 0 | K35: =SUM(J35:J36) -> 0 | L35: =SUM(K35:K36) -> 0 | M35: =SUM(L35:L36) -> 0 | N35: =SUM(M35:M36) -> 0
B36: =tab!B36 -> % | C36: =tab!C36 -> Compensação de Prejuízo Fiscal | D36: =tab!D36 -> 0.3 | E36: =-IF(AND(E35>0,E34*$D$36<E35),E34*$D$36,E35) -> -180 | F36: =-IF(AND(F35>0,F34*$D$36<F35),F34*$D$36,F35) -> -7680 | G36: =-IF(AND(G35>0,G34*$D$36<G35),G34*$D$36,G35) -> -15180 | H36: =-IF(AND(H35>0,H34*$D$36<H35),H34*$D$36,H35) -> -21960 | I36: =-IF(AND(I35>0,I34*$D$36<I35),I34*$D$36,I35) -> 0 | J36: =-IF(AND(J35>0,J34*$D$36<J35),J34*$D$36,J35) -> 0 | K36: =-IF(AND(K35>0,K34*$D$36<K35),K34*$D$36,K35) -> 0 | L36: =-IF(AND(L35>0,L34*$D$36<L35),L34*$D$36,L35) -> 0 | ... N36: =-IF(AND(N35>0,N34*$D$36<N35),N34*$D$36,N35) -> 0
B37: =tab!B37 -> % | C37: =tab!C37 -> Adicional de Imposto de Renda | D37: =tab!D37 -> 0.1 | E37: =HLOOKUP($E$4,INDIRECT($E$4&"!$E$4:$O$49"),MATCH(C37,INDIRECT($E$4&"!$C$4:$C$49"),0),0) -> 0 | F37: =IF(SUM(F34,F36)>20000*$A$4,(SUM(F34,F36)-20000*$A$4)*$D$37,0) -> 0 | G37: =IF(SUM(G34,G36)>20000*$A$4,(SUM(G34,G36)-20000*$A$4)*$D$37,0) -> 0 | H37: =IF(SUM(H34,H36)>20000*$A$4,(SUM(H34,H36)-20000*$A$4)*$D$37,0) -> 0 | I37: =IF(SUM(I34,I36)>20000*$A$4,(SUM(I34,I36)-20000*$A$4)*$D$37,0) -> 0 | J37: =IF(SUM(J34,J36)>20000*$A$4,(SUM(J34,J36)-20000*$A$4)*$D$37,0) -> 0 | K37: =IF(SUM(K34,K36)>20000*$A$4,(SUM(K34,K36)-20000*$A$4)*$D$37,0) -> 0 | L37: =IF(SUM(L34,L36)>20000*$A$4,(SUM(L34,L36)-20000*$A$4)*$D$37,0) -> 0 | M37: =IF(SUM(M34,M36)>20000*$A$4,(SUM(M34,M36)-20000*$A$4)*$D$37,0) -> 60 | N37: =IF(SUM(N34,N36)>20000*$A$4,(SUM(N34,N36)-20000*$A$4)*$D$37,0) -> 2560
B38: =tab!B38 -> % | C38: =tab!C38 -> Imposto de Renda | D38: =tab!D38 -> 0.15 | E38: =SUM(E34,E36)*$D$38 -> 63 | F38: =SUM(F34,F36)*$D$38 -> 2688 | G38: =SUM(G34,G36)*$D$38 -> 5313 | H38: =SUM(H34,H36)*$D$38 -> 8046 | I38: =SUM(I34,I36)*$D$38 -> 15090 | J38: =SUM(J34,J36)*$D$38 -> 18840 | K38: =SUM(K34,K36)*$D$38 -> 22590 | L38: =SUM(L34,L36)*$D$38 -> 26340 | ... N38: =SUM(N34,N36)*$D$38 -> 33840
B39: =tab!B39 -> % | C39: =tab!C39 -> Contribuição Social | D39: =tab!D39 -> 0.09 | E39: =SUM(E34,E36)*$D$39 -> 37.8 | F39: =SUM(F34,F36)*$D$39 -> 1612.8 | G39: =SUM(G34,G36)*$D$39 -> 3187.8 | H39: =SUM(H34,H36)*$D$39 -> 4827.6 | I39: =SUM(I34,I36)*$D$39 -> 9054 | J39: =SUM(J34,J36)*$D$39 -> 11304 | K39: =SUM(K34,K36)*$D$39 -> 13554 | L39: =SUM(L34,L36)*$D$39 -> 15804 | ... N39: =SUM(N34,N36)*$D$39 -> 20304
B40: =tab!B40 -> = | C40: =tab!C40 -> Compensações | E40: =SUM(E42:E47) -> -3600 | F40: =SUM(F42:F47) -> -3600 | G40: =SUM(G42:G47) -> -4300.8 | H40: =SUM(H42:H47) -> -8500.8 | I40: =SUM(I42:I47) -> -12873.6 | J40: =SUM(J42:J47) -> -24144 | K40: =SUM(K42:K47) -> -30144 | L40: =SUM(L42:L47) -> -36144 | ... N40: =SUM(N42:N47) -> -48204
B41: =tab!B41 -> - | C41: =tab!C41 -> IR Base Negativa Exercícios Anteriores | D41: =LEFT(C41,2) -> IR | E41: =HLOOKUP(E$4,tab!$E$4:$P$49,MATCH($C41,$C$4:$C$49,0),0) -> 0 | F41: =HLOOKUP(F$4,tab!$E$4:$P$49,MATCH($C41,$C$4:$C$49,0),0) -> 0 | G41: =HLOOKUP(G$4,tab!$E$4:$P$49,MATCH($C41,$C$4:$C$49,0),0) -> 0 | H41: =HLOOKUP(H$4,tab!$E$4:$P$49,MATCH($C41,$C$4:$C$49,0),0) -> 0 | I41: =HLOOKUP(I$4,tab!$E$4:$P$49,MATCH($C41,$C$4:$C$49,0),0) -> 0 | J41: =HLOOKUP(J$4,tab!$E$4:$P$49,MATCH($C41,$C$4:$C$49,0),0) -> 0 | K41: =HLOOKUP(K$4,tab!$E$4:$P$49,MATCH($C41,$C$4:$C$49,0),0) -> 0 | L41: =HLOOKUP(L$4,tab!$E$4:$P$49,MATCH($C41,$C$4:$C$49,0),0) -> 0 | ... N41: =HLOOKUP(N$4,tab!$E$4:$P$49,MATCH($C41,$C$4:$C$49,0),0) -> 0
B42: =tab!B42 -> - | C42: =tab!C42 -> IR s/ Aplicações Financeiras | D42: =LEFT(C42,2) -> IR | E42: =HLOOKUP(E$4,tab!$E$4:$P$49,MATCH($C42,$C$4:$C$49,0),0) -> -100 | F42: =HLOOKUP(F$4,tab!$E$4:$P$49,MATCH($C42,$C$4:$C$49,0),0) -> -100 | G42: =HLOOKUP(G$4,tab!$E$4:$P$49,MATCH($C42,$C$4:$C$49,0),0) -> -100 | H42: =HLOOKUP(H$4,tab!$E$4:$P$49,MATCH($C42,$C$4:$C$49,0),0) -> -100 | I42: =HLOOKUP(I$4,tab!$E$4:$P$49,MATCH($C42,$C$4:$C$49,0),0) -> -100 | J42: =HLOOKUP(J$4,tab!$E$4:$P$49,MATCH($C42,$C$4:$C$49,0),0) -> -100 | K42: =HLOOKUP(K$4,tab!$E$4:$P$49,MATCH($C42,$C$4:$C$49,0),0) -> -100 | L42: =HLOOKUP(L$4,tab!$E$4:$P$49,MATCH($C42,$C$4:$C$49,0),0) -> -100 | ... N42: =HLOOKUP(N$4,tab!$E$4:$P$49,MATCH($C42,$C$4:$C$49,0),0) -> -100
B43: =tab!B43 -> - | C43: =tab!C43 -> IR Retida s/ Notas Fiscais | D43: =LEFT(C43,2) -> IR | E43: =HLOOKUP(E$4,tab!$E$4:$P$49,MATCH($C43,$C$4:$C$49,0),0) -> -2000 | F43: =HLOOKUP(F$4,tab!$E$4:$P$49,MATCH($C43,$C$4:$C$49,0),0) -> -2000 | G43: =HLOOKUP(G$4,tab!$E$4:$P$49,MATCH($C43,$C$4:$C$49,0),0) -> -2000 | H43: =HLOOKUP(H$4,tab!$E$4:$P$49,MATCH($C43,$C$4:$C$49,0),0) -> -2000 | I43: =HLOOKUP(I$4,tab!$E$4:$P$49,MATCH($C43,$C$4:$C$49,0),0) -> -2000 | J43: =HLOOKUP(J$4,tab!$E$4:$P$49,MATCH($C43,$C$4:$C$49,0),0) -> -2000 | K43: =HLOOKUP(K$4,tab!$E$4:$P$49,MATCH($C43,$C$4:$C$49,0),0) -> -2000 | L43: =HLOOKUP(L$4,tab!$E$4:$P$49,MATCH($C43,$C$4:$C$49,0),0) -> -2000 | ... N43: =HLOOKUP(N$4,tab!$E$4:$P$49,MATCH($C43,$C$4:$C$49,0),0) -> -2000
B44: =tab!B44 -> - | C44: =tab!C44 -> IR Pago no Exercício | D44: =LEFT(C44,2) -> IR | E44: =HLOOKUP(E$4,tab!$E$4:$P$49,MATCH($C44,$C$4:$C$49,0),0) -> 0 | F44: =-E48 -> 0 | G44: =-SUM($E$48:F48) -> -588 | H44: =-SUM($E$48:G48) -> -3213 | I44: =-SUM($E$48:H48) -> -5946 | J44: =-SUM($E$48:I48) -> -12990 | K44: =-SUM($E$48:J48) -> -16740 | L44: =-SUM($E$48:K48) -> -20490 | M44: =-SUM($E$48:L48) -> -24240 | N44: =-SUM($E$48:M48) -> -28050
B45: =tab!B45 -> - | C45: =tab!C45 -> CS Base Negativa Exercícios Anteriores | D45: =LEFT(C45,2) -> CS | E45: =HLOOKUP(E$4,tab!$E$4:$P$49,MATCH($C45,$C$4:$C$49,0),0) -> 0 | F45: =HLOOKUP(F$4,tab!$E$4:$P$49,MATCH($C45,$C$4:$C$49,0),0) -> 0 | G45: =HLOOKUP(G$4,tab!$E$4:$P$49,MATCH($C45,$C$4:$C$49,0),0) -> 0 | H45: =HLOOKUP(H$4,tab!$E$4:$P$49,MATCH($C45,$C$4:$C$49,0),0) -> 0 | I45: =HLOOKUP(I$4,tab!$E$4:$P$49,MATCH($C45,$C$4:$C$49,0),0) -> 0 | J45: =HLOOKUP(J$4,tab!$E$4:$P$49,MATCH($C45,$C$4:$C$49,0),0) -> 0 | K45: =HLOOKUP(K$4,tab!$E$4:$P$49,MATCH($C45,$C$4:$C$49,0),0) -> 0 | L45: =HLOOKUP(L$4,tab!$E$4:$P$49,MATCH($C45,$C$4:$C$49,0),0) -> 0 | ... N45: =HLOOKUP(N$4,tab!$E$4:$P$49,MATCH($C45,$C$4:$C$49,0),0) -> 0
B46: =tab!B46 -> - | C46: =tab!C46 -> CS Retida s/ Notas Fiscais | D46: =LEFT(C46,2) -> CS | E46: =HLOOKUP(E$4,tab!$E$4:$P$49,MATCH($C46,$C$4:$C$49,0),0) -> -1500 | F46: =HLOOKUP(F$4,tab!$E$4:$P$49,MATCH($C46,$C$4:$C$49,0),0) -> -1500 | G46: =HLOOKUP(G$4,tab!$E$4:$P$49,MATCH($C46,$C$4:$C$49,0),0) -> -1500 | H46: =HLOOKUP(H$4,tab!$E$4:$P$49,MATCH($C46,$C$4:$C$49,0),0) -> -1500 | I46: =HLOOKUP(I$4,tab!$E$4:$P$49,MATCH($C46,$C$4:$C$49,0),0) -> -1500 | J46: =HLOOKUP(J$4,tab!$E$4:$P$49,MATCH($C46,$C$4:$C$49,0),0) -> -1500 | K46: =HLOOKUP(K$4,tab!$E$4:$P$49,MATCH($C46,$C$4:$C$49,0),0) -> -1500 | L46: =HLOOKUP(L$4,tab!$E$4:$P$49,MATCH($C46,$C$4:$C$49,0),0) -> -1500 | ... N46: =HLOOKUP(N$4,tab!$E$4:$P$49,MATCH($C46,$C$4:$C$49,0),0) -> -1500
B47: =tab!B47 -> - | C47: =tab!C47 -> CS Pago no Exercício | D47: =LEFT(C47,2) -> CS | E47: =HLOOKUP(E$4,tab!$E$4:$P$49,MATCH($C47,$C$4:$C$49,0),0) -> 0 | F47: =-E49 -> 0 | G47: =-SUM($E$49:F49) -> -112.8 | H47: =-SUM($E$49:G49) -> -1687.8 | I47: =-SUM($E$49:H49) -> -3327.6 | J47: =-SUM($E$49:I49) -> -7554 | K47: =-SUM($E$49:J49) -> -9804 | L47: =-SUM($E$49:K49) -> -12054 | M47: =-SUM($E$49:L49) -> -14304 | N47: =-SUM($E$49:M49) -> -16554
B48: =tab!B48 -> = | C48: =tab!C48 -> Imposto de Renda a Pagar | E48: =IF(SUM(E37,E38,SUMIF($D$41:E47,"IR",E$41:E$47))>0,SUM(E37,E38,SUMIF($D$41:E47,"IR",E$41:E$47)),0) -> 0 | F48: =IF(SUM(F37,F38,SUMIF($D$41:F47,"IR",F$41:F$47))>0,SUM(F37,F38,SUMIF($D$41:F47,"IR",F$41:F$47)),0) -> 588 | G48: =IF(SUM(G37,G38,SUMIF($D$41:G47,"IR",G$41:G$47))>0,SUM(G37,G38,SUMIF($D$41:G47,"IR",G$41:G$47)),0) -> 2625 | H48: =IF(SUM(H37,H38,SUMIF($D$41:H47,"IR",H$41:H$47))>0,SUM(H37,H38,SUMIF($D$41:H47,"IR",H$41:H$47)),0) -> 2733 | I48: =IF(SUM(I37,I38,SUMIF($D$41:I47,"IR",I$41:I$47))>0,SUM(I37,I38,SUMIF($D$41:I47,"IR",I$41:I$47)),0) -> 7044 | J48: =IF(SUM(J37,J38,SUMIF($D$41:J47,"IR",J$41:J$47))>0,SUM(J37,J38,SUMIF($D$41:J47,"IR",J$41:J$47)),0) -> 3750 | K48: =IF(SUM(K37,K38,SUMIF($D$41:K47,"IR",K$41:K$47))>0,SUM(K37,K38,SUMIF($D$41:K47,"IR",K$41:K$47)),0) -> 3750 | L48: =IF(SUM(L37,L38,SUMIF($D$41:L47,"IR",L$41:L$47))>0,SUM(L37,L38,SUMIF($D$41:L47,"IR",L$41:L$47)),0) -> 3750 | ... N48: =IF(SUM(N37,N38,SUMIF($D$41:N47,"IR",N$41:N$47))>0,SUM(N37,N38,SUMIF($D$41:N47,"IR",N$41:N$47)),0) -> 6250
B49: =tab!B49 -> = | C49: =tab!C49 -> Contribuição Social a Pagar | E49: =IF(SUM(E39,SUMIF($D$41:E47,"CS",E$41:E$47))>0,SUM(E39,SUMIF($D$41:E47,"CS",E$41:E$47)),0) -> 0 | F49: =IF(SUM(F39,SUMIF($D$41:F47,"CS",F$41:F$47))>0,SUM(F39,SUMIF($D$41:F47,"CS",F$41:F$47)),0) -> 112.8 | G49: =IF(SUM(G39,SUMIF($D$41:G47,"CS",G$41:G$47))>0,SUM(G39,SUMIF($D$41:G47,"CS",G$41:G$47)),0) -> 1575 | H49: =IF(SUM(H39,SUMIF($D$41:H47,"CS",H$41:H$47))>0,SUM(H39,SUMIF($D$41:H47,"CS",H$41:H$47)),0) -> 1639.8 | I49: =IF(SUM(I39,SUMIF($D$41:I47,"CS",I$41:I$47))>0,SUM(I39,SUMIF($D$41:I47,"CS",I$41:I$47)),0) -> 4226.4 | J49: =IF(SUM(J39,SUMIF($D$41:J47,"CS",J$41:J$47))>0,SUM(J39,SUMIF($D$41:J47,"CS",J$41:J$47)),0) -> 2250 | K49: =IF(SUM(K39,SUMIF($D$41:K47,"CS",K$41:K$47))>0,SUM(K39,SUMIF($D$41:K47,"CS",K$41:K$47)),0) -> 2250 | L49: =IF(SUM(L39,SUMIF($D$41:L47,"CS",L$41:L$47))>0,SUM(L39,SUMIF($D$41:L47,"CS",L$41:L$47)),0) -> 2250 | ... N49: =IF(SUM(N39,SUMIF($D$41:N47,"CS",N$41:N$47))>0,SUM(N39,SUMIF($D$41:N47,"CS",N$41:N$47)),0) -> 2250

Sheet nov
B3: 2018
A4: 11 | B4: # | C4: Parâmetros | D4: % | E4: Jan | F4: Fev | G4: Mar | H4: Abr | I4: Mai | J4: Jun | K4: Jul | L4: Ago | M4: Set | N4: Out | O4: Nov | P4: Dez
A5: 2018 | B5: =tab!B5 -> = | C5: =tab!C5 -> Lucro Acumulado | E5: =HLOOKUP(E$4,tab!$E$4:$P$33,MATCH($C5,$C$4:$C$33,0),0) -> 1000 | F5: =HLOOKUP(F$4,tab!$E$4:$P$33,MATCH($C5,$C$4:$C$33,0),0) -> 26000 | G5: =HLOOKUP(G$4,tab!$E$4:$P$33,MATCH($C5,$C$4:$C$33,0),0) -> 51000 | H5: =HLOOKUP(H$4,tab!$E$4:$P$33,MATCH($C5,$C$4:$C$33,0),0) -> 76000 | I5: =HLOOKUP(I$4,tab!$E$4:$P$33,MATCH($C5,$C$4:$C$33,0),0) -> 101000 | J5: =HLOOKUP(J$4,tab!$E$4:$P$33,MATCH($C5,$C$4:$C$33,0),0) -> 126000 | K5: =HLOOKUP(K$4,tab!$E$4:$P$33,MATCH($C5,$C$4:$C$33,0),0) -> 151000 | L5: =HLOOKUP(L$4,tab!$E$4:$P$33,MATCH($C5,$C$4:$C$33,0),0) -> 176000 | ... O5: =HLOOKUP(O$4,tab!$E$4:$P$33,MATCH($C5,$C$4:$C$33,0),0) -> 251000
A6: 2019 | B6: =tab!B6 -> = | C6: =tab!C6 -> Adições | E6: =SUM(E7:E19) -> 600 | F6: =SUM(F7:F19) -> 600 | G6: =SUM(G7:G19) -> 600 | H6: =SUM(H7:H19) -> 600 | I6: =SUM(I7:I19) -> 600 | J6: =SUM(J7:J19) -> 600 | K6: =SUM(K7:K19) -> 600 | L6: =SUM(L7:L19) -> 600 | ... O6: =SUM(O7:O19) -> 600
A7: 2020 | B7: =tab!B7 -> + | C7: =tab!C7 -> Ajustes Devedores de Qualquer Natureza | E7: =HLOOKUP(E$4,tab!$E$4:$P$49,MATCH($C7,$C$4:$C$49,0),0) -> 0 | F7: =HLOOKUP(F$4,tab!$E$4:$P$49,MATCH($C7,$C$4:$C$49,0),0) -> 0 | G7: =HLOOKUP(G$4,tab!$E$4:$P$49,MATCH($C7,$C$4:$C$49,0),0) -> 0 | H7: =HLOOKUP(H$4,tab!$E$4:$P$49,MATCH($C7,$C$4:$C$49,0),0) -> 0 | I7: =HLOOKUP(I$4,tab!$E$4:$P$49,MATCH($C7,$C$4:$C$49,0),0) -> 0 | J7: =HLOOKUP(J$4,tab!$E$4:$P$49,MATCH($C7,$C$4:$C$49,0),0) -> 0 | K7: =HLOOKUP(K$4,tab!$E$4:$P$49,MATCH($C7,$C$4:$C$49,0),0) -> 0 | L7: =HLOOKUP(L$4,tab!$E$4:$P$49,MATCH($C7,$C$4:$C$49,0),0) -> 0 | ... O7: =HLOOKUP(O$4,tab!$E$4:$P$49,MATCH($C7,$C$4:$C$49,0),0) -> 0
A8: 2021 | B8: =tab!B8 -> + | C8: =tab!C8 -> Despesas de Variação Cambial | E8: =HLOOKUP(E$4,tab!$E$4:$P$49,MATCH($C8,$C$4:$C$49,0),0) -> 0 | F8: =HLOOKUP(F$4,tab!$E$4:$P$49,MATCH($C8,$C$4:$C$49,0),0) -> 0 | G8: =HLOOKUP(G$4,tab!$E$4:$P$49,MATCH($C8,$C$4:$C$49,0),0) -> 0 | H8: =HLOOKUP(H$4,tab!$E$4:$P$49,MATCH($C8,$C$4:$C$49,0),0) -> 0 | I8: =HLOOKUP(I$4,tab!$E$4:$P$49,MATCH($C8,$C$4:$C$49,0),0) -> 0 | J8: =HLOOKUP(J$4,tab!$E$4:$P$49,MATCH($C8,$C$4:$C$49,0),0) -> 0 | K8: =HLOOKUP(K$4,tab!$E$4:$P$49,MATCH($C8,$C$4:$C$49,0),0) -> 0 | L8: =HLOOKUP(L$4,tab!$E$4:$P$49,MATCH($C8,$C$4:$C$49,0),0) -> 0 | ... O8: =HLOOKUP(O$4,tab!$E$4:$P$49,MATCH($C8,$C$4:$C$49,0),0) -> 0
A9: 2022 | B9: =tab!B9 -> + | C9: =tab!C9 -> Despesas Particulares dos Sócios e Dirigentes; | E9: =HLOOKUP(E$4,tab!$E$4:$P$49,MATCH($C9,$C$4:$C$49,0),0) -> 0 | F9: =HLOOKUP(F$4,tab!$E$4:$P$49,MATCH($C9,$C$4:$C$49,0),0) -> 0 | G9: =HLOOKUP(G$4,tab!$E$4:$P$49,MATCH($C9,$C$4:$C$49,0),0) -> 0 | H9: =HLOOKUP(H$4,tab!$E$4:$P$49,MATCH($C9,$C$4:$C$49,0),0) -> 0 | I9: =HLOOKUP(I$4,tab!$E$4:$P$49,MATCH($C9,$C$4:$C$49,0),0) -> 0 | J9: =HLOOKUP(J$4,tab!$E$4:$P$49,MATCH($C9,$C$4:$C$49,0),0) -> 0 | K9: =HLOOKUP(K$4,tab!$E$4:$P$49,MATCH($C9,$C$4:$C$49,0),0) -> 0 | L9: =HLOOKUP(L$4,tab!$E$4:$P$49,MATCH($C9,$C$4:$C$49,0),0) -> 0 | ... O9: =HLOOKUP(O$4,tab!$E$4:$P$49,MATCH($C9,$C$4:$C$49,0),0) -> 0
