Workbook

Sheet DRE TRIMESTRAL
B3: Descrição | C3: Outubro | D3: Novembro | E3: Dezembro
B4: RECEITA BRUTA | C4: =C5+C6-C7 -> 921649.54 | D4: =D5+D6-D7 -> 1283250.7 | E4: =E5+E6-E7 -> 1001947.9
B5: VENDA DE MERCADORIAS | C5: 811710.14 | D5: 1148954.1 | E5: 838395
B6: SERVIÇOS PRESTADOS | C6: 127040.2 | D6: 166741.6 | E6: 190322.88
B7: DEVOLUÇÃO SOBRE VENDAS | C7: 17100.8 | D7: 32445 | E7: 26770
B9: IMPOSTOS | C9: =SUM(C10:C13) -> 239294.24 | D9: =SUM(D10:D13) -> 336850.68 | E9: =SUM(E10:E13) -> 255583.65
B10: PIS | C10: =(C5+C6)*1.65% -> 15489.381 | D10: =(D5+D6)*1.65% -> 21708.979 | E10: =(E5+E6)*1.65% -> 16973.845
B11: COFINS | C11: =(C5+C6)*7.6% -> 71345.026 | D11: =(D5+D6)*7.6% -> 99992.875 | E11: =(E5+E6)*7.6% -> 78182.559
B12: ICMS | C12: =C5*18% -> 146107.83 | D12: =D5*18% -> 206811.74 | E12: =E5*18% -> 150911.1
B13: ISS | C13: =C6*5% -> 6352.01 | D13: =D6*5% -> 8337.08 | E13: =E6*5% -> 9516.144
B15: RECEITA LÍQUIDA | C15: =C4-C9 -> 682355.3 | D15: =D4-D9 -> 946400.04 | E15: =E4-E9 -> 746364.23
B17: CUSTO DAS VENDAS | C17: =C23 -> 468762.07 | D17: =D23 -> 562413.02 | E17: =E23 -> 560624.41
B18: (+) COMPRAS MERCADORIAS | C18: 608782 | D18: 746820.15 | E18: 650618
B19: (+) FRETES | C19: =C5*1% -> 8117.1014 | D19: =D5*1% -> 11489.541 | E19: =E5*1% -> 8383.95
B20: ( - ) ICMS SOBRE COMPRAS E FRETES | C20: =C18*12% -> 73053.84 | D20: =D18*12% -> 89618.418 | E20: 20826
B21: ( - ) PIS SOBRE COMPRAS | C21: =C5*1.65% -> 13393.217 | D21: =D5*1.65% -> 18957.743 | E21: =E5*1.65% -> 13833.517
B22: ( - ) COFINS SOBRE COMPRAS | C22: =C5*7.6% -> 61689.971 | D22: =D5*7.6% -> 87320.513 | E22: =E5*7.6% -> 63718.02
B23: CUSTO DOS PRODUTOS VENDIDOS | C23: =C18+C19-C20-C21-C22 -> 468762.07 | D23: =D18+D19-D20-D21-D22 -> 562413.02 | E23: =E18+E19-E20-E21-E22 -> 560624.41
B25: LUCRO BRUTO | C25: =C15-C17 -> 213593.22 | D25: =D15-D17 -> 383987.03 | E25: =E15-E17 -> 185739.82
B27: DESPESAS FIXAS | C27: =SUM(C28:C36) -> 143218.04 | D27: =SUM(D28:D36) -> 145043.12 | E27: =SUM(E28:E36) -> 137941.71
B28: PRÓ-LABORE (Sócios) | C28: 1500 | D28: 1500 | E28: 1500
B29: SALÁRIOS | C29: 95890.1 | D29: 97125 | E29: 92320
B30: FGTS | C30: =C29*8% -> 7671.208 | D30: =D29*8% -> 7770 | E30: =E29*8% -> 7385.6
B31: INSS SOBRE FOLHA DE PAGAMENTO | C31: =C29*20% -> 19178.02 | D31: =D29*20% -> 19425 | E31: =E29*20% -> 18464
B32: TERCEIROS FOLHA PAGAMENTO | C32: =C29*6.8% -> 6520.5268 | D32: =D29*6.8% -> 6604.5 | E32: =E29*6.8% -> 6277.76
B33: PROVISÃO 13° SALÁRIO | C33: =C29/12 -> 7990.8417 | D33: =D29/12 -> 8093.75 | E33: =E29/12 -> 7693.3333
B34: ENCARGOS SOBRE 13° SALÁRIO | C34: =C33*34.8% -> 2780.8129 | D34: =D33*34.8% -> 2816.625 | E34: =E33*34.8% -> 2677.28
B35: PROVISÃO FÉRIAS E 1/3 DE FÉRIAS | C35: =((C29/12)*1.33)/12 -> 885.65162 | D35: =((D29/12)*1.33)/12 -> 897.05729 | E35: =((E29/12)*1.33)/12 -> 852.67778
B36: ENCARGOS SOBRE FÉRIAS E 1/3 FÉRIAS | C36: =C34*28.8% -> 800.87412 | D36: =D34*28.8% -> 811.188 | E36: =E34*28.8% -> 771.05664
B38: INFRA-ESTRUTURA | C38: =SUM(C39:C44) -> 22100 | D38: =SUM(D39:D44) -> 22323 | E38: =SUM(E39:E44) -> 22155
B39: AGUA E ESGOTO | C39: 900 | D39: 1058 | E39: 1258
B40: TELEFONE | C40: 470 | D40: 460 | E40: 425
B41: INTERNET | C41: 800 | D41: 800 | E41: 800
B42: ENERGIA | C42: 3180 | D42: 3255 | E42: 2922
B43: ALUGUEL A PAGAR | C43: 5500 | D43: 5500 | E43: 5500
B44: DEPRECIAÇÃO | C44: 11250 | D44: 11250 | E44: 11250
B46: OUTRAS DESPESAS | C46: =SUM(C47:C56) -> 73129 | D46: =SUM(D47:D56) -> 109176 | E46: =SUM(E47:E56) -> 94885
B47: COMBUSTÍVEIS | C47: 8125 | D47: 9958 | E47: 9045
B48: CONTABILIDADE | C48: 4400 | D48: 4400 | E48: 4400
B49: DOAÇÃO AMIGOS DA FLORESTA | C49: 15000 | D49: 15000 | E49: 15000
B50: OUTRAS CONSULTORIAS | C50: 1500 | D50: 1500 | E50: 1500
B51: MATERIAL DE ESCRITÓRIO | C51: 2385 | D51: 2958 | E51: 3125
B52: CURSOS E TREINAMENTOS | C52: 1200 | D52: 1200 | E52: 1200
B53: BRINDES P/ CLIENTES | C53: 0 | D53: 27850 | E53: 18500
B54: PRODUTOS DE LIMPEZA (USO E CONSUMO) | C54: 2455 | D54: 2110 | E54: 2585
B55: PLANO DE SAÚDE DIRETORIA | C55: 19950 | D55: 19950 | E55: 19950
B56: DESPESAS SÓCIOS | C56: 18114 | D56: 24250 | E56: 19580
B57: OUTRAS RECEITAS | C57: =C58 -> 0 | D57: =D58 -> 0 | E57: =E58 -> 0
B58: OUTRAS RECEITAS | C58: 0 | D58: 0 | E58: 0
B61: LUCRO ANTES DO IR e CSLL | C61: =(C25-C27-C38-C46+C57) -> -24853.81 | D61: =(D25-D27-D38-D46+D57) -> 107444.91 | E61: =(E25-E27-E38-E46+E57) -> -69241.888
D66: =C61+D61+E61 -> 13349.209

Sheet LALUR PARTE A
B1: PARTE A - REGISTRO DOS AJUSTES DO LUCRO LIQUIDO DO EXERCICIO
B2: DATA | C2: H I S T O R I C O | D2: OBSERVAÇÕES | E2: ADIÇÕES | F2: EXCLUSÕES
C3: NATUREZA DOS AJUSTES - OUTUBRO/2021
B4: 44476 | C4: ='DRE TRIMESTRAL'!B49 -> DOAÇÃO AMIGOS DA FLORESTA | E4: ='DRE TRIMESTRAL'!C49 -> 15000
C5: ='DRE TRIMESTRAL'!B53 -> BRINDES P/ CLIENTES | E5: ='DRE TRIMESTRAL'!C53 -> 0
B6: 44479 | C6: ='DRE TRIMESTRAL'!B55 -> PLANO DE SAÚDE DIRETORIA | E6: ='DRE TRIMESTRAL'!C55 -> 19950
B7: 44500 | C7: ='DRE TRIMESTRAL'!B56 -> DESPESAS SÓCIOS | E7: ='DRE TRIMESTRAL'!C56 -> 18114
E9: =SUM(E3:E8) -> 53064
C10: NATUREZA DOS AJUSTES - NOVEMBRO/2021
B11: 44505 | C11: ='DRE TRIMESTRAL'!B49 -> DOAÇÃO AMIGOS DA FLORESTA | E11: ='DRE TRIMESTRAL'!D49 -> 15000
B12: 44510 | C12: ='DRE TRIMESTRAL'!B53 -> BRINDES P/ CLIENTES | E12: ='DRE TRIMESTRAL'!D53 -> 27850
B13: 44515 | C13: ='DRE TRIMESTRAL'!B55 -> PLANO DE SAÚDE DIRETORIA | E13: ='DRE TRIMESTRAL'!D55 -> 19950
B14: 44528 | C14: ='DRE TRIMESTRAL'!B56 -> DESPESAS SÓCIOS | E14: ='DRE TRIMESTRAL'!D56 -> 24250
E15: =SUM(E10:E14) -> 87050
C16: NATUREZA DOS AJUSTES - DEZEMBRO/2021
B17: 44531 | C17: ='DRE TRIMESTRAL'!B49 -> DOAÇÃO AMIGOS DA FLORESTA | E17: ='DRE TRIMESTRAL'!E49 -> 15000
B18: 44540 | C18: ='DRE TRIMESTRAL'!B53 -> BRINDES P/ CLIENTES | E18: ='DRE TRIMESTRAL'!E53 -> 18500
B19: 44545 | C19: ='DRE TRIMESTRAL'!B55 -> PLANO DE SAÚDE DIRETORIA | E19: ='DRE TRIMESTRAL'!E55 -> 19950
B20: 44550 | C20: ='DRE TRIMESTRAL'!B56 -> DESPESAS SÓCIOS | E20: ='DRE TRIMESTRAL'!E56 -> 19580
E22: =SUM(E16:E21) -> 73030
C24: T O T A L A D I Ç Õ E S E E X C L U S Õ E S | E24: =SUM(E9,E15,E22) -> 213144 | F24: =SUM(F6:F22) -> 0
B26: 44561 | C26: DEMONSTRATIVO DO LUCRO REAL
C28: R E S U L T A D O D O P E R Í O D O | F28: ='DRE TRIMESTRAL'!C61+'DRE TRIMESTRAL'!D61+'DRE TRIMESTRAL'!E61 -> 13349.209
C29: A D I Ç Õ E S :
C30: Despesas Indedutíveis 10/2021 | E30: =E9 -> 53064 | F30: =E9 -> 53064
C31: Despesas Indedutíveis 11/2021 | E31: =E15 -> 87050 | F31: =E15 -> 87050
C32: Despesas Indedutíveis 12/2021 | E32: =E22 -> 73030 | F32: =E22 -> 73030
C33: T O T A L A D I Ç Õ E S | F33: =SUM(E30:E32) -> 213144
C35: E X C L U S Õ E S :
C38: T O T A L E X C L U S Õ E S | F38: =SUM(F36:F37) -> 0
C40: LUCRO REAL | F40: =F28+F33-F38 -> 226493.21
C43: PREJUÍZOS PERÍODOS ANTERIORES (LIMITADO A 30% DO LUCRO) | F43: =F40*30% -> 67947.963
D45: __________________________ | F45: =F40-F43 -> 158545.25
D47: Contador

Sheet LALUR PARTE B
A1: PARTE B - CONTROLE DE VALORES QUE CONSTITUIRÃO AJUSTE DO LUCRO LIQUIDO DE EXERCÍCIOS FUTUROS | I1: FOLHA 26
A3: CONTA : | B3: PREJUIZO FISCAL ANO CALENDÁRIO
C5: Para efeitos de Correção Monetária | G5: Controle de Valores
A6: DATA | B6: H I S T Ó R I C O | C6: Mês de | D6: Valor a | E6: Coef. | F6: Débito | G6: Crédito | H6: Valor Corrigido | I6: D/C
C7: Ref. | D7: Corrigir
A8: 4º TRI | B8: Prej. Fiscal apurado n/exercício | C8: 4º TRI 2020 | G8: 0 | H8: 457090
H14: =SUM(H8:H8) -> 457090
H16: ='LALUR PARTE A'!F43 -> 67947.963
H18: =H14-H16 -> 389142.04

Sheet APURAÇÃO LUCRO REAL
C5: PREJUÍZOS ACUMULADOS ANOS ANTERIORES
C6: Ano | D6: Prejuízo
C7: 2020-4 | D7: 457090
C12: TOTAL | D12: =SUM(D7:E11) -> 457090 | F12: =D12-E17 -> 457090 | G12: =F12-E18 -> 457090 | H12: =G12-E19 -> 457090
C15: LUCRO
C16: TRIMESTRE | D16: LUCRO
C17: 1° TRI | D17: 0 | E17: =IF($D$12>0,IF($D$12>(D17*30%),D17*30%,IF($D$12<(D17*30%),$D$12))) -> 0
C18: 2° TRI | D18: 0 | E18: =IF($F$12>0,IF($F$12>(D18*30%),D18*30%,IF($F$12<(D18*30%),$F$12))) -> 0
C19: 3° TRI | D19: 0
C20: 4° TRI | D20: ='DRE TRIMESTRAL'!D66 -> 13349.209 | E20: =IF($H$12>0,IF($H$12>(D20*30%),D20*30%,IF($H$12<(D20*30%),$H$12))) -> 4004.7626
B24: LUCRO REAL TRIMESTRAL - IR
B25: Mês / Ano | C25: 1° TRI | D25: 2° TRI | E25: 3° TRI | F25: 4° TRI
B26: LUCRO / PREJUÍZO | C26: =$D$17 -> 0 | D26: =D18 -> 0 | E26: =D19 -> 0 | F26: =D20 -> 13349.209
B27: ADIÇÕES | C27: 0 | F27: ='LALUR PARTE A'!E24 -> 213144
B28: PREJ. ANTERIORES | C28: =(C26+C27)*30% -> 0 | D28: 0 | E28: 0 | F28: ='LALUR PARTE B'!H16 -> 67947.963
B29: OUTRAS EXCLUSÕES | C29: 0
B30: LUCRO TRIBUTÁVEL | C30: =C26+C27-C28-C29 -> 0 | D30: =D26+D27-D28-D29 -> 0 | E30: =E26+E27-E28-E29 -> 0 | F30: =F26+F27-F28-F29 -> 158545.25
B31: IRPJ | C31: =C30*15% -> 0 | D31: =D30*15% -> 0 | E31: 0 | F31: =F30*15% -> 23781.787
B32: AD IRPJ | C32: =IF(C30>20000,((C30-60000)*10%),"0,00") -> 0,00 | D32: =IF(D30>40000,((D30-60000)*10%),"0,00") -> 0,00 | E32: =IF(E30>60000,((E30-60000)*10%),"0,00") -> 0,00 | F32: =IF(F30>80000,((F30-60000)*10%),"0,00") -> 9854.5246
B33: TOTAL IRPJ | C33: =C31+C32 -> 0 | D33: =D31+D32 -> 0 | E33: =E31+E32 -> 0 | F33: =F31+F32 -> 33636.311
B34: IR RETIDO | C34: 0
B35: IRPJ A RECOLHER | C35: =C33-C34 -> 0 | D35: =D33-D34 -> 0 | E35: =E33-E34 -> 0 | F35: =F33-F34 -> 33636.311
B37: LUCRO REAL TRIMESTRAL - CSLL
B38: Mês / Ano | C38: 1° TRI | D38: 2° TRI | E38: 3° TRI | F38: 4° TRI
B39: LUCRO / PREJUÍZO | C39: =$D$17 -> 0 | D39: =D18 -> 0 | E39: =D19 -> 0 | F39: =D20 -> 13349.209
B40: ADIÇÕES | C40: 0 | F40: ='LALUR PARTE A'!E24 -> 213144
B41: PREJ. ANTERIORES | C41: 0 | D41: 0 | E41: 0 | F41: ='LALUR PARTE B'!H16 -> 67947.963
B42: OUTRAS EXCLUSÕES | C42: 0
B43: LUCRO TRIBUTÁVEL | C43: =C39+C40-C41-C42 -> 0 | D43: =D39+D40-D41-D42 -> 0 | E43: =E39+E40-E41-E42 -> 0 | F43: =F39+F40-F41-F42 -> 158545.25
B44: TOTAL CSLL | C44: =C43*9% -> 0 | D44: =D43*9% -> 0 | E44: 0 | F44: =F43*9% -> 14269.072
B45: CSLL RETIDO
B46: CSLL A RECOLHER | C46: =C44-C45 -> 0 | D46: =D44-D45 -> 0 | E46: =E44-E45 -> 0 | F46: =F44-F45 -> 14269.072
C51: Mês / Ano | D51: IRPJ | E51: CSLL
C52: 1° TRI | D52: =C35 -> 0 | E52: =C46 -> 0
C53: 2° TRI | D53: =D35 -> 0 | E53: =D46 -> 0
C54: 3° TRI | D54: =E35 -> 0 | E54: =E46 -> 0
C55: 4° TRI | D55: =F35 -> 33636.311 | E55: =F46 -> 14269.072
C57: TOTAL | D57: =SUM(D52:D55) -> 33636.311 | E57: =SUM(E52:E55) -> 14269.072
C60: IRPJ | D60: CSLL
B61: DARF | C61: 3373 - Pessoas jurídicas não obrigadas, mas optante | D61: 6012 - Demais pessoas jurídicas
D66: 1

Sheet Apuração Lucro Real Anual
C6: PREJUÍZOS ACUMULADOS ANOS ANTERIORES
C7: Ano | D7: Prejuízo
D8: 0
D9: 0
D10: 0
D11: 0
D12: 0
C13: TOTAL | D13: =SUM(D8:E12) -> 0
C16: RECEITA BRUTA E LUCRO ANTES DO IR
C17: Mês / Ano | D17: Receita Bruta | E17: LUCRO ANTES IR
C18: 43831 | D18: 3400258 | E18: -143185
C19: 43862 | D19: 4250158 | E19: 310150 | F19: =E18+E19 -> 166965
C20: 43891 | D20: 3125000 | E20: 145000 | F20: =E18+E19+E20 -> 311965
C21: 43922 | D21: 4188050 | E21: -325000 | F21: =SUM(E18:E21) -> -13035
C22: 43952 | D22: 5485000 | E22: 378000 | F22: =SUM(E18:E22) -> 364965
C23: 43983 | D23: 3200000 | E23: -460000 | F23: =SUM(E18:E23) -> -95035
C24: 44013 | D24: 4185000 | E24: 650000 | F24: =SUM(E18:E24) -> 554965
C25: 44044 | D25: 2895150 | E25: 395000 | F25: =SUM(E18:E25) -> 949965
C26: 44075 | D26: 3777145 | E26: -725000
C27: 44105 | D27: 5975160 | E27: 925000
C28: 44136 | D28: 2855985 | E28: -845000
C29: 44166 | D29: 2458000 | E29: 980000
B35: ESTIMATIVA IRPJ
B36: Mês / Ano | C36: Receita Matriz e Filial | D36: Presunção | E36: IRPJ | F36: AD IR | G36: Total a Pagar
D37: 0.08 | E37: 0.15 | F37: 0.1
B38: 43831 | C38: =D18 -> 3400258 | D38: =C38*D37 -> 272020.64 | E38: =D38*E37 -> 40803.096 | F38: =(D38-20000)*10% -> 25202.064 | G38: =E38+F38 -> 66005.16
B39: 43862 | C39: =D19 -> 4250158 | D39: =C39*$D$37 -> 340012.64 | E39: =D39*$E$37 -> 51001.896 | F39: =(D39-20000)*10% -> 32001.264 | G39: =E39+F39 -> 83003.16
B40: 43891 | C40: =D20 -> 3125000 | D40: =C40*$D$37 -> 250000 | E40: =D40*$E$37 -> 37500 | F40: =(D40-20000)*10% -> 23000 | G40: =E40+F40 -> 60500
B41: 43922 | C41: =D21 -> 4188050 | D41: =C41*$D$37 -> 335044 | E41: =D41*$E$37 -> 50256.6 | F41: =(D41-20000)*10% -> 31504.4 | G41: =E41+F41 -> 81761
B42: 43952 | C42: =D22 -> 5485000 | D42: =C42*$D$37 -> 438800 | E42: =D42*$E$37 -> 65820 | F42: =(D42-20000)*10% -> 41880 | G42: =E42+F42 -> 107700
B43: 43983 | C43: =D23 -> 3200000 | D43: =C43*$D$37 -> 256000 | E43: =D43*$E$37 -> 38400 | F43: =(D43-20000)*10% -> 23600 | G43: =E43+F43 -> 62000
B44: 44013 | C44: =D24 -> 4185000 | D44: =C44*$D$37 -> 334800 | E44: =D44*$E$37 -> 50220 | F44: =(D44-20000)*10% -> 31480 | G44: =E44+F44 -> 81700
B45: 44044 | C45: =D25 -> 2895150 | D45: =C45*$D$37 -> 231612 | E45: =D45*$E$37 -> 34741.8 | F45: =(D45-20000)*10% -> 21161.2 | G45: =E45+F45 -> 55903
B46: 44075 | C46: =D26 -> 3777145 | D46: =C46*$D$37 -> 302171.6 | E46: =D46*$E$37 -> 45325.74 | F46: =(D46-20000)*10% -> 28217.16 | G46: =E46+F46 -> 73542.9
B47: 44105 | C47: =D27 -> 5975160 | D47: =C47*$D$37 -> 478012.8 | E47: =D47*$E$37 -> 71701.92 | F47: =(D47-20000)*10% -> 45801.28 | G47: =E47+F47 -> 117503.2
B48: 44136 | C48: =D28 -> 2855985 | D48: =C48*$D$37 -> 228478.8 | E48: =D48*$E$37 -> 34271.82 | F48: =(D48-20000)*10% -> 20847.88 | G48: =E48+F48 -> 55119.7
B49: 44166 | C49: =D29 -> 2458000 | D49: =C49*$D$37 -> 196640 | E49: =D49*$E$37 -> 29496 | F49: =(D49-20000)*10% -> 17664 | G49: =E49+F49 -> 47160
B53: ESTIMATIVA CSLL
B54: Mês / Ano | C54: Receita Matriz e Filial | D54: Presunção | E54: CSLL | F54: TOTAL A PAGAR
D55: 0.12 | E55: 0.09
B56: 43831 | C56: =D18 -> 3400258 | D56: =C56*$D$55 -> 408030.96 | E56: =D56*$E$55 -> 36722.786 | F56: =E56 -> 36722.786
B57: 43862 | C57: =D19 -> 4250158 | D57: =C57*$D$55 -> 510018.96 | E57: =D57*$E$55 -> 45901.706 | F57: =E57 -> 45901.706
B58: 43891 | C58: =D20 -> 3125000 | D58: =C58*$D$55 -> 375000 | E58: =D58*$E$55 -> 33750 | F58: =E58 -> 33750
B59: 43922 | C59: =D21 -> 4188050 | D59: =C59*$D$55 -> 502566 | E59: =D59*$E$55 -> 45230.94 | F59: =E59 -> 45230.94
B60: 43952 | C60: =D22 -> 5485000 | D60: =C60*$D$55 -> 658200 | E60: =D60*$E$55 -> 59238 | F60: =E60 -> 59238
B61: 43983 | C61: =D23 -> 3200000 | D61: =C61*$D$55 -> 384000 | E61: =D61*$E$55 -> 34560 | F61: =E61 -> 34560
B62: 44013 | C62: =D24 -> 4185000 | D62: =C62*$D$55 -> 502200 | E62: =D62*$E$55 -> 45198 | F62: =E62 -> 45198
B63: 44044 | C63: =D25 -> 2895150 | D63: =C63*$D$55 -> 347418 | E63: =D63*$E$55 -> 31267.62 | F63: =E63 -> 31267.62
B64: 44075 | C64: =D26 -> 3777145 | D64: =C64*$D$55 -> 453257.4 | E64: =D64*$E$55 -> 40793.166 | F64: =E64 -> 40793.166
B65: 44105 | C65: =D27 -> 5975160 | D65: =C65*$D$55 -> 717019.2 | E65: =D65*$E$55 -> 64531.728 | F65: =E65 -> 64531.728
B66: 44136 | C66: =D28 -> 2855985 | D66: =C66*$D$55 -> 342718.2 | E66: =D66*$E$55 -> 30844.638 | F66: =E66 -> 30844.638
B67: 44166 | C67: =D29 -> 2458000 | D67: =C67*$D$55 -> 294960 | E67: =D67*$E$55 -> 26546.4 | F67: =E67 -> 26546.4
B74: BALANCETE DE REDUÇÃO / SUSPENSÃO - IR (1º SEMESTRE)
B75: Mês / Ano | C75: JAN | D75: JAN à FEV | E75: JAN à MAR | F75: JAN à ABR | G75: JAN à MAI | H75: JAN à JUN
B76: EBTIDA | C76: =$E$18 -> -143185 | D76: =SUM($E$18:$E$19) -> 166965 | E76: =SUM($E$18:$E$20) -> 311965 | F76: =SUM($E$18:$E$21) -> -13035 | G76: =SUM($E$18:$E$22) -> 364965 | H76: =SUM($E$18:$E$23) -> -95035
B77: ADIÇÕES | C77: 0 | D77: 0 | E77: 0 | F77: 0 | G77: 0 | H77: 0
B78: PREJ. ANTERIORES | C78: 0 | D78: 0 | E78: 0 | F78: 0 | G78: 0 | H78: 0
B79: OUTRAS EXCLUSÕES | C79: 0 | D79: 0 | F79: 0 | G79: 0 | H79: 0
B80: LUCRO TRIBUTÁVEL | C80: =C76+C77-C78-C79 -> -143185 | D80: =D76+D77-D78-D79 -> 166965 | E80: =E76+E77-E78-E79 -> 311965 | F80: =F76+F77-F78-F79 -> -13035 | G80: =G76+G77-G78-G79 -> 364965 | H80: =H76+H77-H78-H79 -> -95035
B81: IRPJ | C81: =C80*15% -> -21477.75 | D81: =D80*15% -> 25044.75 | E81: =E80*15% -> 46794.75 | F81: =F80*15% -> -1955.25 | G81: =G80*15% -> 54744.75 | H81: =H80*15% -> -14255.25
B82: AD IRPJ | C82: =IF(C80>20000,((C80-20000)*10%),"0,00") -> 0,00 | D82: =IF(D80>40000,((D80-40000)*10%),"0,00") -> 12696.5 | E82: =IF(E80>60000,((E80-60000)*10%),"0,00") -> 25196.5 | F82: =IF(F80>80000,((F80-80000)*10%),"0,00") -> 0,00 | G82: =IF(G80>100000,((G80-100000)*10%),"0,00") -> 26496.5 | H82: =IF(H80>120000,((H80-120000)*10%),"0,00") -> 0,00
B83: TOTAL IRPJ | C83: =C81+C82 -> -21477.75 | D83: =D81+D82 -> 37741.25 | E83: =E81+E82 -> 71991.25 | F83: =F81+F82 -> -1955.25 | G83: =G81+G82 -> 81241.25 | H83: =H81+H82 -> -14255.25
B84: COMPENSAÇÃO IR ACUMULADO | D84: =D137 -> 0 | E84: =SUM($D$137:$D$138) -> 37741.25 | F84: =SUM($D$137:$D$139) -> 71991.25 | G84: =SUM($D$137:$D$140) -> 71991.25 | H84: =SUM($D$137:$D$141) -> 81241.25
B85: IR RETIDO
B86: IRPJ A RECOLHER | C86: =C83-C84-C85 -> -21477.75 | D86: =D83-D84-D85 -> 37741.25 | E86: =E83-E84-E85 -> 34250 | F86: =F83-F84-F85 -> -73946.5 | G86: =G83-G84-G85 -> 9250 | H86: =H83-H84-H85 -> -95496.5
B89: BALANCETE DE REDUÇÃO / SUSPENSÃO - IR (2º SEMESTRE)
B90: Mês / Ano | C90: JAN à JUL | D90: JAN à AGO | E90: JAN à SET | F90: JAN à OUT | G90: JAN à NOV | H90: JAN à DEZ
B91: EBTIDA | C91: =SUM($E$18:$E$24) -> 554965 | D91: =SUM($E$18:$E$25) -> 949965 | E91: =SUM($E$18:$E$26) -> 224965 | F91: =SUM($E$18:$E$27) -> 1149965 | G91: =SUM($E$18:$E$28) -> 304965 | H91: =SUM($E$18:$E$29) -> 1284965
B92: ADIÇÕES | C92: 0
B93: PREJ. ANTERIORES | C93: 0 | D93: 0 | E93: 0 | F93: 0 | G93: 0 | H93: 0
B94: OUTRAS EXCLUSÕES | C94: 0
B95: LUCRO TRIBUTÁVEL | C95: =C91+C92-C93-C94 -> 554965 | D95: =D91+D92-D93-D94 -> 949965 | E95: =E91+E92-E93-E94 -> 224965 | F95: =F91+F92-F93-F94 -> 1149965 | G95: =G91+G92-G93-G94 -> 304965 | H95: =H91+H92-H93-H94 -> 1284965
B96: IRPJ | C96: =C95*15% -> 83244.75 | D96: =D95*15% -> 142494.75 | E96: =E95*15% -> 33744.75 | F96: =F95*15% -> 172494.75 | G96: =G95*15% -> 45744.75 | H96: =H95*15% -> 192744.75
B97: AD IRPJ | C97: =IF(C95>140000,((C95-140000)*10%),"0,00") -> 41496.5 | D97: =IF(D95>160000,((D95-160000)*10%),"0,00") -> 78996.5 | E97: =IF(E95>180000,((E95-180000)*10%),"0,00") -> 4496.5 | F97: =IF(F95>200000,((F95-200000)*10%),"0,00") -> 94996.5 | G97: =IF(G95>220000,((G95-220000)*10%),"0,00") -> 8496.5 | H97: =IF(H95>240000,((H95-240000)*10%),"0,00") -> 104496.5
B98: TOTAL IRPJ | C98: =C96+C97 -> 124741.25 | D98: =D96+D97 -> 221491.25 | E98: =E96+E97 -> 38241.25 | F98: =F96+F97 -> 267491.25 | G98: =G96+G97 -> 54241.25 | H98: =H96+H97 -> 297241.25
B99: COMPENSAÇÃO IR ACUMULADO | C99: =SUM($D$137:$D$142) -> 81241.25 | D99: =SUM($D$137:$D$143) -> 124741.25 | E99: =SUM($D$137:$D$144) -> 180644.25 | F99: =SUM($D$137:$D$145) -> 180644.25 | G99: =SUM($D$137:$D$146) -> 267491.25 | H99: =SUM($D$137:$D$147) -> 267491.25
B100: IR RETIDO
B101: IRPJ A RECOLHER | C101: =C98-C99-C100 -> 43500 | D101: =D98-D99-D100 -> 96750 | E101: =E98-E99-E100 -> -142403 | F101: =F98-F99-F100 -> 86847 | G101: =G98-G99-G100 -> -213250 | H101: =H98-H99-H100 -> 29750
B108: BALANCETE DE REDUÇÃO / SUSPENSÃO - CSLL (1º SEMESTRE)
B109: Mês / Ano | C109: JAN | D109: JAN à FEV | E109: JAN à MAR | F109: JAN à ABR | G109: JAN à MAI | H109: JAN à JUN
B110: EBTIDA | C110: =$E$18 -> -143185 | D110: =SUM($E$18:$E$19) -> 166965 | E110: =SUM($E$18:$E$20) -> 311965 | F110: =SUM($E$18:$E$21) -> -13035 | G110: =SUM($E$18:$E$22) -> 364965 | H110: =SUM($E$18:$E$23) -> -95035
B111: ADIÇÕES | C111: 0
B112: PREJ. ANTERIORES | C112: 0 | D112: 0 | E112: 0 | F112: 0 | G112: 0 | H112: 0
B113: OUTRAS EXCLUSÕES | C113: 0 | D113: 0 | E113: 0 | F113: 0 | G113: 0 | H113: 0
B114: LUCRO TRIBUTÁVEL | C114: =C110+C111-C112-C113 -> -143185 | D114: =D110+D111-D112-D113 -> 166965 | E114: =E110+E111-E112-E113 -> 311965 | F114: =F110+F111-F112-F113 -> -13035 | G114: =G110+G111-G112-G113 -> 364965 | H114: =H110+H111-H112-H113 -> -95035
B115: TOTAL CSLL | C115: =C114*9% -> -12886.65 | D115: =D114*9% -> 15026.85 | E115: =E114*9% -> 28076.85 | F115: =F114*9% -> -1173.15 | G115: =G114*9% -> 32846.85 | H115: =H114*9% -> -8553.15
B116: COMPENSAÇÃO CSLL ACUMULADO | D116: =F137 -> 0 | E116: =SUM($F$137:$F$138) -> 15026.85 | F116: =SUM($F$137:$F$139) -> 28076.85 | G116: =SUM($F$137:$F$140) -> 28076.85 | H116: =SUM($F$137:$F$141) -> 32846.85
B117: CSLL RETIDO
B118: CSLL A RECOLHER | C118: =C115-C116-C117 -> -12886.65 | D118: =D115-D116-D117 -> 15026.85 | E118: =E115-E116-E117 -> 13050 | F118: =F115-F116-F117 -> -29250 | G118: =G115-G116-G117 -> 4770 | H118: =H115-H116-H117 -> -41400
B121: BALANCETE DE REDUÇÃO / SUSPENSÃO - CSLL (2º SEMESTRE)
B122: Mês / Ano | C122: JAN à JUL | D122: JAN à AGO | E122: JAN à SET | F122: JAN à OUT | G122: JAN à NOV | H122: JAN à DEZ
B123: EBTIDA | C123: =SUM($E$18:$E$24) -> 554965 | D123: =SUM($E$18:$E$25) -> 949965 | E123: =SUM($E$18:$E$26) -> 224965 | F123: =SUM($E$18:$E$27) -> 1149965 | G123: =SUM($E$18:$E$28) -> 304965 | H123: =SUM($E$18:$E$29) -> 1284965
B124: ADIÇÕES | C124: 0 | D124: 0 | E124: 0 | F124: 0 | G124: 0 | H124: 0
B125: PREJ. ANTERIORES | C125: 0 | D125: 0 | E125: 0 | F125: 0 | G125: 0 | H125: 0
B126: OUTRAS EXCLUSÕES | C126: 0 | D126: 0 | E126: 0 | F126: 0 | G126: 0 | H126: 0
B127: LUCRO TRIBUTÁVEL | C127: =C123+C124-C125-C126 -> 554965 | D127: =D123+D124-D125-D126 -> 949965 | E127: =E123+E124-E125-E126 -> 224965 | F127: =F123+F124-F125-F126 -> 1149965 | G127: =G123+G124-G125-G126 -> 304965 | H127: =H123+H124-H125-H126 -> 1284965
B128: TOTAL CSLL | C128: =C127*9% -> 49946.85 | D128: =D127*9% -> 85496.85 | E128: =E127*9% -> 20246.85 | F128: =F127*9% -> 103496.85 | G128: =G127*9% -> 27446.85 | H128: =H127*9% -> 115646.85
B129: COMPENSAÇÃO CSLL ACUMULADO | C129: =SUM($F$137:$F$142) -> 32846.85 | D129: =SUM($F$137:$F$143) -> 49946.85 | E129: =SUM($F$137:$F$144) -> 81214.47 | F129: =SUM($F$137:$F$145) -> 81214.47 | G129: =SUM($F$137:$F$146) -> 103496.85 | H129: =SUM($F$137:$F$147) -> 103496.85
B130: CSLL RETIDO
B131: CSLL A RECOLHER | C131: =C128-C129-C130 -> 17100 | D131: =D128-D129-D130 -> 35550 | E131: =E128-E129-E130 -> -60967.62 | F131: =F128-F129-F130 -> 22282.38 | G131: =G128-G129-G130 -> -76050 | H131: =H128-H129-H130 -> 12150
...
