Workbook

Sheet BP-DRE
B5: BALANÇO PATRIMONIAL
B6: ATIVO | G6: PASSIVO
D7: x1 | E7: x2 | J7: x1 | K7: x2
B8: Ativo circulante | H8: Ativo circulante
C9: Caixa e bancos | D9: =Lançamentos!D2 -> 100000 | E9: =Lançamentos!E26 -> 3001000 | I9: Empres. e Financiamnetos | J9: =Lançamentos!AH2 -> 0 | K9: =Lançamentos!AH26 -> -2270000
C10: Contas a receber | D10: =Lançamentos!G2 -> 650000 | E10: =Lançamentos!H26 -> 1492588 | I10: Fornecedores | J10: =Lançamentos!AK2 -> -180000 | K10: =Lançamentos!AK26 -> -1332700
C11: Partes relacionadas | D11: =Lançamentos!J2 -> 0 | E11: =Lançamentos!K26 -> 135000 | I11: Partes relacionadas | J11: =Lançamentos!AN2 -> 0 | K11: =Lançamentos!AN26 -> 0
C12: Estoques | D12: =Lançamentos!M2 -> 40000 | E12: =Lançamentos!N26 -> 290696 | I12: Salarios a pagar | J12: =Lançamentos!AQ2 -> 0 | K12: =Lançamentos!AQ26 -> -133400
C13: Outras contas Rec. | D13: =Lançamentos!P2 -> 0 | E13: =Lançamentos!Q26 -> 0 | I13: Outras contas pagar | J13: =Lançamentos!AT2 -> 0 | K13: =Lançamentos!AT26 -> -200000
C14: Adiantamentos | D14: =Lançamentos!S2 -> 0 | E14: =Lançamentos!T26 -> 0 | I14: Distribuição de dividendos | J14: =Lançamentos!AW2 -> 0 | K14: =Lançamentos!AW26 -> 0
B16: Ativo não circulante | H16: Passivo não circulante
C17: RLP | D17: =Lançamentos!V2 -> 0 | E17: =Lançamentos!W26 -> 0 | I17: ELP | J17: =Lançamentos!AZ2 -> -320000 | K17: =Lançamentos!AZ26 -> -320000
C19: Investimentos | D19: =Lançamentos!Y2 -> 60000 | E19: =Lançamentos!Z26 -> 60000
C20: Imobilizado | D20: =Lançamentos!AA2 -> 500000 | E20: =Lançamentos!AB26 -> 849450 | H20: Patrimonio Liquido
C21: Intangivel | D21: 0 | E21: 0 | I21: Capital social | J21: =Lançamentos!BC2 -> -600000 | K21: =Lançamentos!BC26 -> -600000
C22: Diferido | D22: =Lançamentos!AD2 -> 50000 | E22: =Lançamentos!AE26 -> 64800 | I22: Reserva de lucros | J22: =Lançamentos!BE2 -> -300000 | K22: =Lançamentos!BE26 -> -1037434
B25: TOTAL ATIVO | D25: =SUM(D8:D23) -> 1400000 | E25: =SUM(E8:E23) -> 5893534 | H25: TOTAL PASSIVO | J25: =SUM(J8:J23) -> -1400000 | K25: =SUM(K8:K23) -> -5893534
K27: =K25+E25 -> 0
B29: Demonstraçaõ do resultado do exercicio BR GAAP
J30: x1 | K30: x2
C31: Receitas liquidas de vendas | J31: =Lançamentos!BJ2 -> -700000 | K31: =Lançamentos!BJ26 -> -1815400
C33: CMV | J33: =Lançamentos!BL2 -> 195000 | K33: =Lançamentos!BM26 -> 640000
C35: Lucro operacional Liquido | J35: =J31+J33 -> -505000 | K35: =K31+K33 -> -1175400
C37: Despesas Administrativas | J37: =Lançamentos!BO2 -> 180000 | K37: =Lançamentos!BP26 -> 360966
C38: Despesas Comerciais | J38: =Lançamentos!BR2 -> 20000 | K38: =Lançamentos!BS26 -> 77000
C39: Resultado Financeiro, liquido | J39: =Lançamentos!BU2 -> 0 | K39: =Lançamentos!BV26 -> 0
C41: Resultado antes do IR e CSLL | J41: =J35+J37+J38+J39 -> -305000 | K41: =K35+K37+K38+K39 -> -737434
C43: Imposto de renda e Contribuição social | J43: =Lançamentos!BX2 -> 5000
C45: Resultado do Exercicio | J45: =J41+J43 -> -300000 | K45: =K41+K43 -> -737434

Sheet Lançamentos
B1: Lançamentos BR GAAP | D1: Caixa e bancos | G1: Contas a receber | J1: Partes relacionadas | M1: Estoques | P1: Outras contas a receber | S1: Adiantamentos | V1: RLP | Y1: Investimentos | AA1: Imobilizado | AD1: Diferido | AG1: Empres. E Fiananciamentos | AJ1: Fornecedores | AM1: Partes relacionadas | AP1: Salarios a pagar | AS1: Outras contas a pagar | AV1: Distrb. De Dividendos | AY1: ELP | BB1: Capital social | BE1: Reserva de lucros | BI1: Receitas vendas | BL1: CMV | BO1: Desp.Administrativas | BR1: Despesas Comerciais | BU1: Resultado Financeiro Loq | BX1: Impostos sobre fat. | CA1: ARE
B2: SALDO 31.12.2011 | D2: 100000 | G2: 650000 | J2: 0 | M2: 40000 | S2: 0 | Y2: 60000 | AA2: 500000 | AD2: 50000 | AH2: 0 | AK2: =-180000 -> -180000 | AN2: 0 | AO2: 0 | AQ2: 0 | AT2: 0 | AX2: 0 | AZ2: =-320000 -> -320000 | BA2: 0 | BC2: =-600000 -> -600000 | BE2: =-300000 -> -300000 | BI2: 0 | BJ2: =-700000 -> -700000 | BL2: 195000 | BO2: 180000 | BR2: 20000 | BX2: 5000 | CA2: 0 | CB2: 0
A3: Movimentação Mês | BE3: =CB3+CA3 -> 0 | CA3: =BI3+BL3+BO3+BR3+BU3+BX3 -> 0 | CB3: =BJ3+BM3+BP3+BS3+BV3+BY3 -> 0
B4: Vendas produtos a vista | D4: 800000 | N4: =-440000 -> -440000 | BE4: =CB4+CA4 -> -360000 | BJ4: =-800000 -> -800000 | BL4: 440000 | CA4: =BI4+BL4+BO4+BR4+BU4+BX4 -> 440000 | CB4: =BJ4+BM4+BP4+BS4+BV4+BY4 -> -800000
B5: Compras a prazo Estoques | M5: 750000 | AK5: =-750000 -> -750000 | BE5: =CB5+CA5 -> 0 | CA5: =BI5+BL5+BO5+BR5+BU5+BX5 -> 0 | CB5: =BJ5+BM5+BP5+BS5+BV5+BY5 -> 0
B6: Financiamento Banco do Brasil | D6: 2000000 | AH6: =-2000000 -> -2000000 | BE6: =CB6+CA6 -> 0 | CA6: =BI6+BL6+BO6+BR6+BU6+BX6 -> 0 | CB6: =BJ6+BM6+BP6+BS6+BV6+BY6 -> 0
B7: Vendas produtos a prazo-Parte relacionada | J7: 135000 | BE7: =CB7+CA7 -> -135000 | BJ7: =-135000 -> -135000 | CA7: =BI7+BL7+BO7+BR7+BU7+BX7 -> 0 | CB7: =BJ7+BM7+BP7+BS7+BV7+BY7 -> -135000
B8: Compra a prazo Ativo Imobilizado | AA8: 190500 | AK8: =-190500 -> -190500 | BE8: =CB8+CA8 -> 0 | CA8: =BI8+BL8+BO8+BR8+BU8+BX8 -> 0 | CB8: =BJ8+BM8+BP8+BS8+BV8+BY8 -> 0
B9: Aquisição de Leasing Financeiro | AA9: 220000 | AH9: -220000 | BE9: =CB9+CA9 -> 0 | CA9: =BI9+BL9+BO9+BR9+BU9+BX9 -> 0 | CB9: =BJ9+BM9+BP9+BS9+BV9+BY9 -> 0
B10: Compra de softawares a vista | E10: =-22000 -> -22000 | AD10: 22000 | BE10: =CB10+CA10 -> 0 | CA10: =BI10+BL10+BO10+BR10+BU10+BX10 -> 0 | CB10: =BJ10+BM10+BP10+BS10+BV10+BY10 -> 0
B11: Vendas produtos a prazo | G11: 530400 | BE11: =CB11+CA11 -> -530400 | BJ11: =-530400 -> -530400 | CA11: =BI11+BL11+BO11+BR11+BU11+BX11 -> 0 | CB11: =BJ11+BM11+BP11+BS11+BV11+BY11 -> -530400
B12: Compras a prazo estoques materia prima | M12: 175200 | AK12: =-175200 -> -175200 | BE12: =CB12+CA12 -> 0 | CA12: =BI12+BL12+BO12+BR12+BU12+BX12 -> 0 | CB12: =BJ12+BM12+BP12+BS12+BV12+BY12 -> 0
B13: Venda de estoque partes relaciondas | G13: 350000 | N13: =-200000 -> -200000 | BE13: =CB13+CA13 -> -150000 | BJ13: =-350000 -> -350000 | BL13: 200000 | CA13: =BI13+BL13+BO13+BR13+BU13+BX13 -> 200000 | CB13: =BJ13+BM13+BP13+BS13+BV13+BY13 -> -350000
B14: Recebimento de subvenções governamentais | D14: 200000 | AT14: =-200000 -> -200000 | BE14: =CB14+CA14 -> 0 | CA14: =BI14+BL14+BO14+BR14+BU14+BX14 -> 0 | CB14: =BJ14+BM14+BP14+BS14+BV14+BY14 -> 0
A15: Apropriações | BE15: =CB15+CA15 -> 0 | CA15: =BI15+BL15+BO15+BR15+BU15+BX15 -> 0 | CB15: =BJ15+BM15+BP15+BS15+BV15+BY15 -> 0
B16: Apropriação de PECLD- 3% Inadimplencia | H16: =-37812 -> -37812 | BE16: =CB16+CA16 -> 37812 | BO16: =H16*-1 -> 37812 | CA16: =BI16+BL16+BO16+BR16+BU16+BX16 -> 37812 | CB16: =BJ16+BM16+BP16+BS16+BV16+BY16 -> 0
B17: Constituição de provisão para perdas de estoques-2% | N17: =-34504 -> -34504 | BE17: =CB17+CA17 -> 34504 | BO17: =N17*-1 -> 34504 | CA17: =BI17+BL17+BO17+BR17+BU17+BX17 -> 34504 | CB17: =BJ17+BM17+BP17+BS17+BV17+BY17 -> 0
B18: Depreciação ativo imobilizado-10% | AB18: =-111050 -> -111050 | BE18: =CB18+CA18 -> 111050 | BO18: =AB18*-1 -> 111050 | CA18: =BI18+BL18+BO18+BR18+BU18+BX18 -> 111050 | CB18: =BJ18+BM18+BP18+BS18+BV18+BY18 -> 0
B19: Depreciação ativo Intangivel-10% | AE19: =(AD25*10%)*-1 -> -7200 | BE19: =CB19+CA19 -> 7200 | BO19: =AE19*-1 -> 7200 | CA19: =BI19+BL19+BO19+BR19+BU19+BX19 -> 7200 | CB19: =BJ19+BM19+BP19+BS19+BV19+BY19 -> 0
B20: Capitalização juros sobre financiamentos | AA20: 50000 | AH20: =-50000 -> -50000 | BE20: =CB20+CA20 -> 0 | CA20: =BI20+BL20+BO20+BR20+BU20+BX20 -> 0 | CB20: =BJ20+BM20+BP20+BS20+BV20+BY20 -> 0
B21: Apripriação Folha de pagamento | AQ21: =-133400 -> -133400 | BE21: =CB21+CA21 -> 133400 | BO21: 133400 | CA21: =BI21+BL21+BO21+BR21+BU21+BX21 -> 133400 | CB21: =BJ21+BM21+BP21+BS21+BV21+BY21 -> 0
B22: Gastos com energia eletrica | AK22: =-22000 -> -22000 | BE22: =CB22+CA22 -> 22000 | BO22: 22000 | CA22: =BI22+BL22+BO22+BR22+BU22+BX22 -> 22000 | CB22: =BJ22+BM22+BP22+BS22+BV22+BY22 -> 0
B23: Gastos com telefonia | AK23: =-15000 -> -15000 | BE23: =CB23+CA23 -> 15000 | BO23: 15000 | CA23: =BI23+BL23+BO23+BR23+BU23+BX23 -> 15000 | CB23: =BJ23+BM23+BP23+BS23+BV23+BY23 -> 0
B24: Gastos a vista com publicidade | E24: =-77000 -> -77000 | BE24: =CB24+CA24 -> 77000 | BR24: 77000 | CA24: =BI24+BL24+BO24+BR24+BU24+BX24 -> 77000 | CB24: =BJ24+BM24+BP24+BS24+BV24+BY24 -> 0
D25: =SUM(D2:D24) -> 3100000 | E25: =SUM(E2:E24) -> -99000 | G25: =SUM(G2:G24) -> 1530400 | H25: =SUM(H2:H24) -> -37812 | J25: =SUM(J2:J24) -> 135000 | K25: =SUM(K2:K24) -> 0 | M25: =SUM(M2:M24) -> 965200 | N25: =SUM(N2:N24) -> -674504 | P25: =SUM(P2:P24) -> 0 | Q25: =SUM(Q2:Q24) -> 0 | S25: =SUM(S2:S24) -> 0 | T25: =SUM(T2:T24) -> 0 | V25: =SUM(V2:V24) -> 0 | W25: =SUM(W2:W24) -> 0 | Y25: =SUM(Y2:Y24) -> 60000 | Z25: =SUM(Z2:Z24) -> 0 | AA25: =SUM(AA2:AA24) -> 960500 | AB25: =SUM(AB2:AB24) -> -111050 | AD25: =SUM(AD2:AD24) -> 72000 | AE25: =SUM(AE2:AE24) -> -7200 | AG25: =SUM(AG2:AG24) -> 0 | AH25: =SUM(AH2:AH24) -> -2270000 | AJ25: =SUM(AJ2:AJ24) -> 0 | AK25: =SUM(AK2:AK24) -> -1332700 | AM25: =SUM(AM2:AM24) -> 0 | AN25: =SUM(AN2:AN24) -> 0 | AP25: =SUM(AP2:AP24) -> 0 | AQ25: =SUM(AQ2:AQ24) -> -133400 | AS25: =SUM(AS2:AS24) -> 0 | AT25: =SUM(AT2:AT24) -> -200000 | AV25: =SUM(AV2:AV24) -> 0 | AW25: =SUM(AW2:AW24) -> 0 | AY25: =SUM(AY2:AY24) -> 0 | AZ25: =SUM(AZ2:AZ24) -> -320000 | BB25: =SUM(BB2:BB24) -> 0 | BC25: =SUM(BC2:BC24) -> -600000 | BE25: =SUM(BE2:BE24) -> -1037434 | BF25: =SUM(BF2:BF24) -> 0 | BI25: =SUM(BI3:BI24) -> 0 | BJ25: =SUM(BJ3:BJ24) -> -1815400 | BL25: =SUM(BL3:BL24) -> 640000 | BM25: =SUM(BM3:BM24) -> 0 | BO25: =SUM(BO3:BO24) -> 360966 | BP25: =SUM(BP3:BP24) -> 0 | BR25: =SUM(BR3:BR24) -> 77000 | BS25: =SUM(BS3:BS24) -> 0 | BU25: =SUM(BU3:BU24) -> 0 | BV25: =SUM(BV3:BV24) -> 0 | BX25: =SUM(BX3:BX24) -> 0 | BY25: =SUM(BY3:BY24) -> 0 | CA25: =SUM(CA3:CA24) -> 1077966 | CB25: =SUM(CB3:CB24) -> -1815400
E26: =D25+E25 -> 3001000 | H26: =G25+H25 -> 1492588 | K26: =J25+K25 -> 135000 | N26: =M25+N25 -> 290696 | Q26: =P25+Q25 -> 0 | T26: =S25+T25 -> 0 | W26: =V25+W25 -> 0 | Z26: =Y25+Z25 -> 60000 | AB26: =AA25+AB25 -> 849450 | AE26: =AD25+AE25 -> 64800 | AH26: =AG25+AH25 -> -2270000 | AK26: =AJ25+AK25 -> -1332700 | AN26: =AM25+AN25 -> 0 | AQ26: =AP25+AQ25 -> -133400 | AT26: =AS25+AT25 -> -200000 | AW26: =AV25+AW25 -> 0 | AZ26: =AY25+AZ25 -> -320000 | BC26: =BB25+BC25 -> -600000 | BE26: =BD25+BE25 -> -1037434 | BF26: =BE25+BF25 -> -1037434 | BJ26: =BI25+BJ25 -> -1815400 | BM26: =BL25+BM25 -> 640000 | BP26: =BO25+BP25 -> 360966 | BS26: =BR25+BS25 -> 77000 | BV26: =BU25+BV25 -> 0 | BY26: =BX25+BY25 -> 0 | CB26: =CA25+CB25 -> -737434
