Workbook

Sheet Apresentação
B8: Balanço Patrimonial + Indicadores Financeiros + Dashboard
B10: BALANÇO PATRIMONIAL
B12: Nesta tela você lança diretamente os valores apurados nas respectivas contas no Balanço Patrimonial
B14: KPI's
B16: Nesta tela será apurados os Indicadores Financeiros automaticamente
B18: DASHABOARD DE ANÁLISE
B20: Nesta tela com base nos dados lançados e apurados anteriormente, será gerado um Dashboard de Análise do Balanço com os Indicadores Financeiros
B22: ...

Sheet BP
B8: Digite Aqui o Nome Empresa
B11: Balanço Patrimonial em 31 de Dezembro de 20xx (em milhares de Reais)
B13: ATIVO | D13: PASSIVO
B14: Circulante
B15: Disponiblidades | C15: 104016 | D15: Fornecedores | E15: 127040
B16: Contas a Receber | C16: 45164 | D16: Financiamentos | E16: 28103.858
B17: Estoques | C17: 135687 | D17: Debentures | E17: 1400
B18: Impostos a Recuperar | C18: 25450 | D18: Salários e Contribuições Sociais | E18: 20953.353
B19: IR e Contr Social diferidos | C19: 8822.3563 | D19: Prov p/IR e Contr Social | E19: 10306.743
B20: Acordos Comerciais | C20: 33375.506 | D20: Financiamentos Compra Imóveis | E20: 4277.2879
B21: Fundos de Recebíveis | C21: 91953.883 | D21: Alugueis a pagar | E21: 4590
B22: Desp Antecipadas | C22: 15179.244 | D22: Dividendos e Jrs s/ Cap Próprio | E22: 6357.3549
B23: Outros | C23: 0 | D23: Outras Obrigações | E23: 22000
B24: TOTAL ATIVO CIRCULANTE | C24: =SUM(C15:C23) -> 459647.99 | D24: TOTAL PASSIVO CIRCULANTE | E24: =SUM(E15:E23) -> 225028.6
B26: Não Circulante
B27: Realizavel a Longo Prazo | D27: Exigível a Longo Prazo
B28: Contas a Receber | C28: 35026.32 | D28: Financiamentos | E28: 135987
B29: IR e Contr Social diferidos | C29: 96838.165 | D29: Quotas do fundo (FIDC) | E29: 87033.23
B30: Impostos a Recuperar | C30: 26540.652 | D30: Debentures | E30: 72729.696
B31: Partes Relacionadas | C31: 25849.79 | D31: Imp e Contr Recolher | E31: 18777.076
B32: Depositos Judiciais | C32: 26906.607 | D32: Prov p/Contingencias | E32: 134579.97
B33: TOTAL DO REAL LP | C33: =SUM(C28:C32) -> 211161.53 | D33: TOTAL EXIG LP | E33: =SUM(E28:E32) -> 449106.97
B35: Permanente | D35: Patrimônio Líquido
B36: Investimentos | C36: 10650.351 | D36: PL
B37: Ágio na aquisição de Investimentos | C37: 0 | D37: Capital Social | E37: 416137.28
B38: Outros | C38: 0 | D38: Reservas de Capital | E38: 53726.446
B39: Imobilizado | C39: 462017.97 | D39: Reservas de Lucros | E39: 53498
B40: Intangível | C40: 54019.565 | D40: Lucros Acumulados | E40: 0
B41: Outros | C41: 0
B42: TOTAL DO AT PERMANENTE | C42: =SUM(C36:C41) -> 526687.88 | D42: TOTAL PL | E42: =SUM(E36:E41) -> 523361.73
B44: TOTAL DO ATIVO | C44: =C24+C33+C42 -> 1197497.4 | D44: TOTAL PASSIVO+PL | E44: =E24+E33+E42 -> 1197497.3

Sheet Indicadores
B8: Digite Aqui o Nome Empresa
B11: Indicadores Financeiros
B14: ANÁLISE DA LIQUIDEZ
B15: CAPITAL CIRCULANTE LÍQUIDO | C15: =IFERROR(BP!C24-BP!E24,"") -> 234619.39 | D15: valor | F15: Ativo Circulante - Passivo Circulante
B16: LIQUIDEZ GERAL | C16: =IFERROR(BP!C44/BP!E24,"") -> 5.3215343 | D16: vezes | F16: Total do Ativo / Passivo Circulante
B17: LIQUIDEZ CORRENTE | C17: =IFERROR(BP!C24/BP!E24,"") -> 2.0426203 | D17: vezes | F17: Ativo Circulante / Passivo Circulante
B18: LIQUIDEZ SECA | C18: =IFERROR((BP!C24-BP!C17)/BP!E24,"") -> 1.4396436 | D18: vezes | F18: Ativo Circulante - Estoques / Passivo Circulante
B19: LIQUIDEZ IMEDIATA | C19: =IFERROR(BP!C15/BP!E24,"") -> 0.46223458 | D19: vezes | F19: Disponibilidades / Passivo Circulante
B21: ANÁLISE DO ENDIVIDAMENTO
B22: % ENDIVIDAMENTO | C22: =IFERROR((BP!E24+BP!E33)/BP!C44,"") -> 0.56295368 | D22: particip | F22: Obrigações / Total dos Ativos | N22: =C22 -> 0.56295368 | O22: =100%-N22 -> 0.43704632
B23: % EXIGIVEL LP S/ PL | C23: =IFERROR(BP!E33/BP!E42,"") -> 0.85811963 | D23: particip | F23: Exigivel a LP / PL | M23: =C23 -> 0.85811963 | N23: =100%-M23 -> 0.14188037

Sheet Auxiliar

Sheet Dashboard
D2: DASHBOARD DE ANÁLISE DE BALANÇO PATRIMONIAL E INDICADORES FINANCEIROS
D5: =X5 -> 1197497.4 | J5: =X6 -> 674135.57 | P5: =X7 -> 523361.73 | W5: TOTAL ATIVO | X5: =BP!C44 -> 1197497.4
W6: TOTAL PASSIVO | X6: =BP!E24+BP!E33 -> 674135.57
D7: TOTAL DO ATIVO | J7: TOTAL PASSIVO | P7: PATRIMÔNIO LIQUIDO | W7: TOTAL PL | X7: =BP!E42 -> 523361.73
W9: TOTAL RECEITAS | X9: =#REF! -> #REF!
D10: =Indicadores!B23 -> % EXIGIVEL LP S/ PL | J10: =Indicadores!B15 -> CAPITAL CIRCULANTE LÍQUIDO | P10: =Indicadores!B22 -> % ENDIVIDAMENTO | W10: TOTAL DESPESAS | X10: =SUM(#REF!-#REF!) -> #REF!
W11: LUCRO | X11: =X9-X10 -> #REF!
W12: INDICE
W13: INDICE
W14: INDICE
J20: =Indicadores!C15 -> 234619.39
