Workbook

Sheet CAMINHÃO BI TREM
A2: Planilha de Frete
A5: Custos da empresa | E5: Itens de custo fixo
A6: Salário do motorista (piso sindicato) | B6: $/ mês | C6: 1350 | E6: Depreciação | F6: ($/ mês) | G6: =(C28-C30)/C29 -> 1666.6667
A7: Salario (comissão) | B7: $/ mês | C7: =(G36*0.1)-C6 -> 1850 | E7: Comissão do frete | F7: ($/ mês) | G7: =(C7) -> 1850
A8: Horas de trabalho/ mês | B8: h.h./mês | C8: 240 | E8: Remuneração de capital | F8: ($/ mês) | G8: =C28*((1+C10)^(1/12)-1) -> 2573.612
A9: Encargos e benefícios do motorista | B9: $/ mês | C9: =(C6*0.4) -> 540 | E9: Salario + Encargos | F9: ($/ mês) | G9: =C6+C9 -> 1890
A10: Taxa de oportunidade (retorno) | B10: % a.a. | C10: 0.08 | E10: Seguros | F10: ($/ mês) | G10: =C37/12 -> 416.66667
A11: Financiamento Bancário | B11: mês | C11: 7700 | E11: Financiamento | F11: ($/ mês) | G11: =(C11) -> 7700
A12: Monitoramento via satélite | B12: mês | C12: 74 | E12: Monitoramento | F12: ($/ mês) | G12: =(C12) -> 74
A13: Custo indiretos (salario patrao + contador) | B13: $/ mês | C13: 300 | E13: IPVA | F13: ($/ mês) | G13: =C36/12 -> 83.333333
E14: Custo Fixo | F14: ($/ mês) | G14: =SUM(G6:G13) -> 16254.279
A15: Dados do veículo | E15: Custos Indireto | F15: ($/ mês) | G15: =C13 -> 300
A16: Consumo de combustível | B16: Km/ litro | C16: 2.1 | E16: Custo Fixo Total | F16: ($/ mês) | G16: =SUM(G14:G15) -> 16554.279
A17: Intervalo entre troca de óleo | B17: Km | C17: 10000
A18: Litros de óleo por troca | B18: litro | C18: 20 | E18: Itens de custo variável
A19: Número de pneus | C19: 22 | E19: Combustível | F19: ($/ Km) | G19: =C32/C16 -> 1
A20: Número de recapagens | C20: 2 | E20: Óleo | F20: ($/ Km) | G20: =C31*C18/(C17) -> 0.017
A21: Intervalo entre troca de pneu ou recapagens | B21: Km | C21: 70000 | E21: Pneu | F21: ($/ Km) | G21: =((C19*C33)+(C20*C34))/(C21) -> 0.388
A22: Manutencao mensal de auto eletrica + diversos | C22: 1000 | E22: Manutenção mensal | F22: ($/ Km) | G22: =(C22/C23) -> 0.05
A23: Intervalo da manutencao mensal | C23: 20000
A24: Custos de revisao | B24: $/ Km | C24: =(1200/15000) -> 0.08 | E24: Lubrificação | F24: ($/ Km) | G24: =C35/C25 -> 0.005
A25: Intervalo entre lubrificações | B25: Km | C25: 10000 | E25: Manutenção historica | F25: ($/ Km) | G25: =C24 -> 0.08
E26: Custo variável Total | F26: ($/ Km) | G26: =SUM(G19:G25)*G32 -> 16940 | H26: KM | I26: %
A27: Dados de mercado
A28: Valor de aquisição do veículo | B28: $ | C28: 400000 | E28: Custos fixos por km | G28: =(G16) -> 16554.279 | H28: =(G28/G32) -> 1.5049344 | I28: =(G28/G30)*100 -> 49.424198
A29: Vida útil do veículo | B29: meses | C29: 60 | E29: Custos variáveis ($/ Km) | G29: =G26 -> 16940 | H29: =(G29/G32) -> 1.54 | I29: =(G29/G30)*100 -> 50.575802
A30: Valor residual do veículo | B30: $ | C30: 300000 | E30: Custo total por km | G30: =SUM(G28:G29) -> 33494.279 | H30: =SUM(H28:H29) -> 3.0449344
A31: Preço do óleo de motor | B31: $/ litro | C31: 8.5
A32: Preço do combustível | B32: $/ litro | C32: 2.1 | E32: Km percorridos no mês | G32: 11000 | H32: quantidade de km
A33: Preço do pneu | B33: $ | C33: 1200
A34: Preço da recapagem | C34: 380 | I34: 50
A35: Preço da lavagem e lubrificação | B35: $ | C35: 50
A36: IPVA/Licenciamento | B36: $/ ano | C36: 1000 | E36: Receita de Frete no Mês | G36: 32000
A37: Seguro do veículo | B37: $/ ano | C37: 5000 | E37: Resultado do Mês | G37: =(G36-G30) -> -1494.2787

Sheet CAMINHÃO TRUCK
A2: Planilha de Frete
A5: Custos da empresa | E5: Itens de custo fixo
A6: Salário do motorista (piso sindicato) | B6: $/ mês | C6: 1500 | E6: Depreciação | F6: ($/ mês) | G6: =(C29-C31)/C30 -> 1500
A7: Salario (comissão) | B7: $/ mês | C7: =(G37*0.1)-C6 -> 2000 | E7: Comissão do frete | F7: ($/ mês) | G7: =(C7) -> 2000
A8: Horas de trabalho/ mês | B8: h.h./mês | C8: 240 | E8: Remuneração de capital | F8: ($/ mês) | G8: =C10*((1+C11)^(1/12)-1) -> 0
A9: Encargos e benefícios do motorista | B9: $/ mês | C9: =(C6*0.4) -> 600 | E9: Salario + Encargos | F9: ($/ mês) | G9: =C6+C9 -> 2100
A10: Valor do capital próprio do bem | B10: $/ mês | C10: 0
A11: Taxa de oportunidade (retorno) | B11: % a.a. | C11: 0.084 | E11: Seguros | F11: ($/ mês) | G11: =C38/12 -> 833.33333
A12: Financiamento Bancário | B12: mês | C12: 1500 | E12: Financiamento | F12: ($/ mês) | G12: =(C12) -> 1500
A13: Monitoramento via satélite | B13: mês | C13: 220 | E13: Monitoramento | F13: ($/ mês) | G13: =(C13) -> 220
A14: Custo indiretos (salario patrao + contador) | B14: $/ mês | C14: 550 | E14: IPVA | F14: ($/ mês) | G14: =C37/12 -> 166.66667
E15: Custo Fixo | F15: ($/ mês) | G15: =SUM(G6:G14) -> 8320
A16: Dados do veículo | E16: Custos Indireto | F16: ($/ mês) | G16: =C14 -> 550
A17: Consumo de combustível | B17: Km/ litro | C17: 2.29 | E17: Custo Fixo Total | F17: ($/ mês) | G17: =SUM(G15:G16) -> 8870
A18: Intervalo entre troca de óleo | B18: Km | C18: 20000
A19: Litros de óleo por troca | B19: litro | C19: 20 | E19: Itens de custo variável
A20: Número de pneus | C20: 22 | E20: Combustível | F20: ($/ Km) | G20: =C33/C17 -> 1.069869 | I20: =(G20/H31)*100 -> 46.159337
A21: Número de recapagens | C21: 0 | E21: Óleo | F21: ($/ Km) | G21: =C32*C19/(C18) -> 0.0085
A22: Intervalo entre troca de pneu ou recapagens | B22: Km | C22: 120000 | E22: Pneu | F22: ($/ Km) | G22: =((C20*C34)+(C21*C35))/(C22) -> 0.21083333
A23: Manutencao mensal de auto eletrica + diversos | C23: 500 | E23: Manutenção mensal | F23: ($/ Km) | G23: =(C23/C24) -> 0.025
A24: Intervalo da manutencao mensal | C24: 20000 | E24: Pedágio | F24: ($/ Km) | G24: =(G35/G33) -> 0.2
A25: Custos de revisao | B25: $/ Km | C25: =(3000)/C24 -> 0.15 | E25: Lubrificação | F25: ($/ Km) | G25: =C36/C26 -> 0.02
A26: Intervalo entre lubrificações | B26: Km | C26: 5000 | E26: Manutenção historica | F26: ($/ Km) | G26: =C25 -> 0.15
E27: Custo variável Total | F27: ($/ Km) | G27: =SUM(G20:G26)*G33 -> 23578.833 | H27: KM | I27: %
A28: Dados de mercado
A29: Valor de aquisição do veículo + furgao | B29: $ | C29: 450000 | E29: Custos fixos por km | G29: =(G17) -> 8870 | H29: =(G29/G33) -> 0.63357143 | I29: =(G29/G31)*100 -> 27.335344
A30: Vida útil do veículo | B30: meses | C30: 60 | E30: Custos variáveis ($/ Km) | G30: =G27 -> 23578.833 | H30: =(G30/G33) -> 1.6842023 | I30: =(G30/G31)*100 -> 72.664656
A31: Valor residual do veículo | B31: $ | C31: 360000 | E31: Custo total por km | G31: =SUM(G29:G30) -> 32448.833 | H31: =SUM(H29:H30) -> 2.3177738
A32: Preço do óleo de motor | B32: $/ litro | C32: 8.5
A33: Preço do combustível | B33: $/ litro | C33: 2.45 | E33: Km percorridos no mês | G33: 14000 | H33: quantidade de km
A34: Preço do pneu | B34: $ | C34: 1150
A35: Preço da recapagem | C35: 0 | E35: Pedágio mês | G35: 2800 | I35: 50
A36: Preço da lavagem e lubrificação | B36: $ | C36: 100
A37: IPVA/Licenciamento | B37: $/ ano | C37: 2000 | E37: Receita de Frete no Mês | G37: 35000
A38: Seguro do veículo | B38: $/ ano | C38: 10000 | E38: Resultado do Mês | G38: =(G37-G31) -> 2551.1674

Sheet SENSIBILIDADE.CAMINHÃO
B1: Análise de sensibilidade
A5: CF | C5: ($/ hora) | D5: =G15 -> 28.876161 | G5: Rota | H5: 1700 | I5: Km
A6: CV | C6: ($/ km) | D6: =G23 -> 1.49
A7: tempo de carga | C7: (h) | D7: 2 | F7: Itens de custo
A8: tempo de descarga | C8: (h) | D8: 2 | F8: Custos fixos | G8: ($/hora) | H8: ($/ rota) | I8: (% rota)
A9: velocidade média | C9: (Km/ h) | D9: 75 | F9: Depreciação | G9: ='CAMINHÃO BI TREM'!G6/'CAMINHÃO BI TREM'!$C$8 -> 6.9444444 | H9: =G9*SUM($D$7:$D$8)+$H$5/$D$9*G9 -> 185.18519 | I9: =H9/$I$25 -> 0.056065228
F10: Remuneração de Capital | G10: ='CAMINHÃO BI TREM'!G8/'CAMINHÃO BI TREM'!$C$8 -> 10.723384 | H10: =G10*SUM($D$7:$D$8)+$H$5/$D$9*G10 -> 285.95689 | I10: =H10/$I$25 -> 0.086574088
A11: Distância | B11: Custo | C11: Custo | F11: Mão de obra | G11: ='CAMINHÃO BI TREM'!G9/'CAMINHÃO BI TREM'!$C$8 -> 7.875 | H11: =G11*SUM($D$7:$D$8)+$H$5/$D$9*G11 -> 210 | I11: =H11/$I$25 -> 0.063577969
A12: (Km) | B12: ($) | C12: ($/ Km) | F12: Seguros | G12: ='CAMINHÃO BI TREM'!G10/'CAMINHÃO BI TREM'!$C$8 -> 1.7361111 | H12: =G12*SUM($D$7:$D$8)+$H$5/$D$9*G12 -> 46.296296 | I12: =H12/$I$25 -> 0.014016307
A13: 25 | B13: =SUM($D$7:$D$8)*$D$5+($D$5/$D$9+$D$6)*A13 -> 162.38003 | C13: =B13/A13 -> 6.4952013 | F13: IPVA | G13: ='CAMINHÃO BI TREM'!G13/'CAMINHÃO BI TREM'!$C$8 -> 0.34722222 | H13: =G13*SUM($D$7:$D$8)+$H$5/$D$9*G13 -> 9.2592593 | I13: =H13/$I$25 -> 0.0028032614
A14: 50 | B14: =SUM($D$7:$D$8)*$D$5+($D$5/$D$9+$D$6)*A14 -> 209.25542 | C14: =B14/A14 -> 4.1851084 | F14: Custo administrativo | G14: ='CAMINHÃO BI TREM'!G15/'CAMINHÃO BI TREM'!$C$8 -> 1.25 | H14: =G14*SUM($D$7:$D$8)+$H$5/$D$9*G14 -> 33.333333 | I14: =H14/$I$25 -> 0.010091741
A15: 75 | B15: =SUM($D$7:$D$8)*$D$5+($D$5/$D$9+$D$6)*A15 -> 256.13081 | C15: =B15/A15 -> 3.4150774 | G15: =SUM(G9:G14) -> 28.876161 | H15: =SUM(H9:H14) -> 770.03097 | I15: =SUM(I9:I14) -> 0.23312859
A16: 100 | B16: =SUM($D$7:$D$8)*$D$5+($D$5/$D$9+$D$6)*A16 -> 303.00619 | C16: =B16/A16 -> 3.0300619
A17: 150 | B17: =SUM($D$7:$D$8)*$D$5+($D$5/$D$9+$D$6)*A17 -> 396.75697 | C17: =B17/A17 -> 2.6450465 | F17: Custos variáveis | G17: ($/Km) | H17: ($/ rota) | I17: (% rota)
A18: 200 | B18: =SUM($D$7:$D$8)*$D$5+($D$5/$D$9+$D$6)*A18 -> 490.50774 | C18: =B18/A18 -> 2.4525387 | F18: Combustível | G18: ='CAMINHÃO BI TREM'!G19 -> 1 | H18: =G18*$H$5 -> 1700 | I18: =H18/$I$25 -> 0.5146788
A19: 250 | B19: =SUM($D$7:$D$8)*$D$5+($D$5/$D$9+$D$6)*A19 -> 584.25852 | C19: =B19/A19 -> 2.3370341 | F19: Óleo | G19: ='CAMINHÃO BI TREM'!G20 -> 0.017 | H19: =G19*$H$5 -> 28.9 | I19: =H19/$I$25 -> 0.0087495395
A20: 300 | B20: =SUM($D$7:$D$8)*$D$5+($D$5/$D$9+$D$6)*A20 -> 678.00929 | C20: =B20/A20 -> 2.260031 | F20: Pneu | G20: ='CAMINHÃO BI TREM'!G21 -> 0.388 | H20: =G20*$H$5 -> 659.6 | I20: =H20/$I$25 -> 0.19969537
A21: 400 | B21: =SUM($D$7:$D$8)*$D$5+($D$5/$D$9+$D$6)*A21 -> 865.51084 | C21: =B21/A21 -> 2.1637771 | F21: Lubrificação | G21: ='CAMINHÃO BI TREM'!G24 -> 0.005 | H21: =G21*$H$5 -> 8.5 | I21: =H21/$I$25 -> 0.002573394
A22: 500 | B22: =SUM($D$7:$D$8)*$D$5+($D$5/$D$9+$D$6)*A22 -> 1053.0124 | C22: =B22/A22 -> 2.1060248 | F22: Manutenção | G22: ='CAMINHÃO BI TREM'!G25 -> 0.08 | H22: =G22*$H$5 -> 136 | I22: =H22/$I$25 -> 0.041174304
A23: 700 | B23: =SUM($D$7:$D$8)*$D$5+($D$5/$D$9+$D$6)*A23 -> 1428.0155 | C23: =B23/A23 -> 2.0400221 | G23: =SUM(G18:G22) -> 1.49 | H23: =SUM(H18:H22) -> 2533 | I23: =SUM(I18:I22) -> 0.76687141
A24: 1000 | B24: =SUM($D$7:$D$8)*$D$5+($D$5/$D$9+$D$6)*A24 -> 1990.5201 | C24: =B24/A24 -> 1.9905201
A25: 1500 | B25: =SUM($D$7:$D$8)*$D$5+($D$5/$D$9+$D$6)*A25 -> 2928.0279 | C25: =B25/A25 -> 1.9520186 | F25: Custo Total da Rota de | G25: =H5 -> 1700 | H25: Km: | I25: =SUM(H9:H14,H18:H22) -> 3303.031
G26: VALOR DA CARGA: | I26: 35000
I27: =I25/I26 -> 0.094372313
