Workbook
Name Contratacoes: Contatacoes[CONTRATAÇÕES]
Name EIXO_CLIENTE: OFFSET(APOIO!$B$7,1,0,COUNTA(APOIO!$B:$B)-1,1)
Name Legenda_lucro: OFFSET(APOIO!$Y$7,1,0,COUNTA(APOIO!$B:$B)-1,1)
Name Legenda_receita: OFFSET(APOIO!$Q$7,1,0,COUNTA(APOIO!$B:$B),1)
Name Lucro: OFFSET(APOIO!$W$7,1,0,COUNTA(APOIO!$B:$B)-1,1)
Name RECEITA: OFFSET(APOIO!$O$7,1,0,COUNTA(APOIO!$B:$B)-1,1)
Name SegmentaçãodeDados_Ano: #N/A
Name SegmentaçãodeDados_ANO1: #N/A
Name SegmentaçãodeDados_CONTRATAÇÕES: #N/A
Name SegmentaçãodeDados_MÊS: #N/A
Name SegmentaçãodeDados_Mês_Abrev: #N/A

Sheet GERENCIAL

Sheet AUXILIARES
B4: CLIENTES | D4: CONTRATAÇÕES | F4: REGIÃO | H4: TIPO | J4: IMPOSTO
B5: LOBATO & ASSOCIADOS | D5: DILIGÊNCIAS | F5: CAPITAL | H5: CONTADOR | J5: 0.1125
B6: PEARTREE ADVOGADOS | D6: AUDIÊNCIAS | F6: GRANDE SP | H6: INTERNET
B7: GUMERCINDO LAW | D7: PROTOCOLO | F7: INTERIOR | H7: LUZ
F8: BRASIL | H8: UBER
H9: TARIFAS
H10: DELTA
H11: CELULAR
H12: GASOLINA
H13: JURIDICO CORRECT
H14: JURIS CORRESPONDENTE
H15: EMPRÉSTIMO
H16: SISTEMA
H17: CALENDÁRIOS
H18: JANTAR
H19: CONDUÇÕES
H20: SIMPLES
... H22: FUNCIONÁRIOS

Sheet BASE_CLIENTES
B5: DATA | C5: CLIENTE | D5: CONTRATAÇÕES | E5: REGIÃO | F5: QUANTIDADE | G5: CUSTO | H5: RECEITA | I5: CUSTO TOTAL | J5: RECEITA TOTAL | K5: LUCRO | L5: MÊS | M5: ANO
B6: 43831 | C6: LOBATO & ASSOCIADOS | D6: DILIGÊNCIAS | E6: CAPITAL | F6: 4 | G6: 25 | H6: 3685 | I6: =BASE_CLIENTES[[#This Row],[CUSTO]]*BASE_CLIENTES[[#This Row],[QUANTIDADE]] -> 100 | J6: =BASE_CLIENTES[[#This Row],[RECEITA]]*BASE_CLIENTES[[#This Row],[QUANTIDADE]] -> 14740 | K6: =BASE_CLIENTES[[#This Row],[QUANTIDADE]]*(BASE_CLIENTES[[#This Row],[RECEITA]]-BASE_CLIENTES[[#This Row],[CUSTO]]) -> 14640 | L6: =PROPER(TEXT(BASE_CLIENTES[[#This Row],[DATA]],"mmm")) -> Jan | M6: =TEXT(BASE_CLIENTES[[#This Row],[DATA]],"aaaa") -> 2020
B7: 43834 | C7: PEARTREE ADVOGADOS | D7: AUDIÊNCIAS | E7: INTERIOR | F7: 17 | G7: 26 | H7: 9987 | I7: =BASE_CLIENTES[[#This Row],[CUSTO]]*BASE_CLIENTES[[#This Row],[QUANTIDADE]] -> 442 | J7: =BASE_CLIENTES[[#This Row],[RECEITA]]*BASE_CLIENTES[[#This Row],[QUANTIDADE]] -> 169779 | K7: =BASE_CLIENTES[[#This Row],[QUANTIDADE]]*(BASE_CLIENTES[[#This Row],[RECEITA]]-BASE_CLIENTES[[#This Row],[CUSTO]]) -> 169337 | L7: =PROPER(TEXT(BASE_CLIENTES[[#This Row],[DATA]],"mmm")) -> Jan | M7: =TEXT(BASE_CLIENTES[[#This Row],[DATA]],"aaaa") -> 2020
B8: 43835 | C8: GUMERCINDO LAW | D8: PROTOCOLO | E8: INTERIOR | F8: 14 | G8: 26 | H8: 6252 | I8: =BASE_CLIENTES[[#This Row],[CUSTO]]*BASE_CLIENTES[[#This Row],[QUANTIDADE]] -> 364 | J8: =BASE_CLIENTES[[#This Row],[RECEITA]]*BASE_CLIENTES[[#This Row],[QUANTIDADE]] -> 87528 | K8: =BASE_CLIENTES[[#This Row],[QUANTIDADE]]*(BASE_CLIENTES[[#This Row],[RECEITA]]-BASE_CLIENTES[[#This Row],[CUSTO]]) -> 87164 | L8: =PROPER(TEXT(BASE_CLIENTES[[#This Row],[DATA]],"mmm")) -> Jan | M8: =TEXT(BASE_CLIENTES[[#This Row],[DATA]],"aaaa") -> 2020
B9: 43835 | C9: LOBATO & ASSOCIADOS | D9: DILIGÊNCIAS | E9: INTERIOR | F9: 6 | G9: 22 | H9: 3067 | I9: =BASE_CLIENTES[[#This Row],[CUSTO]]*BASE_CLIENTES[[#This Row],[QUANTIDADE]] -> 132 | J9: =BASE_CLIENTES[[#This Row],[RECEITA]]*BASE_CLIENTES[[#This Row],[QUANTIDADE]] -> 18402 | K9: =BASE_CLIENTES[[#This Row],[QUANTIDADE]]*(BASE_CLIENTES[[#This Row],[RECEITA]]-BASE_CLIENTES[[#This Row],[CUSTO]]) -> 18270 | L9: =PROPER(TEXT(BASE_CLIENTES[[#This Row],[DATA]],"mmm")) -> Jan | M9: =TEXT(BASE_CLIENTES[[#This Row],[DATA]],"aaaa") -> 2020
B10: 43843 | C10: LOBATO & ASSOCIADOS | D10: AUDIÊNCIAS | E10: INTERIOR | F10: 2 | G10: 21 | H10: 4711 | I10: =BASE_CLIENTES[[#This Row],[CUSTO]]*BASE_CLIENTES[[#This Row],[QUANTIDADE]] -> 42 | J10: =BASE_CLIENTES[[#This Row],[RECEITA]]*BASE_CLIENTES[[#This Row],[QUANTIDADE]] -> 9422 | K10: =BASE_CLIENTES[[#This Row],[QUANTIDADE]]*(BASE_CLIENTES[[#This Row],[RECEITA]]-BASE_CLIENTES[[#This Row],[CUSTO]]) -> 9380 | L10: =PROPER(TEXT(BASE_CLIENTES[[#This Row],[DATA]],"mmm")) -> Jan | M10: =TEXT(BASE_CLIENTES[[#This Row],[DATA]],"aaaa") -> 2020
B11: 43844 | C11: LOBATO & ASSOCIADOS | D11: PROTOCOLO | E11: CAPITAL | F11: 17 | G11: 24 | H11: 9786 | I11: =BASE_CLIENTES[[#This Row],[CUSTO]]*BASE_CLIENTES[[#This Row],[QUANTIDADE]] -> 408 | J11: =BASE_CLIENTES[[#This Row],[RECEITA]]*BASE_CLIENTES[[#This Row],[QUANTIDADE]] -> 166362 | K11: =BASE_CLIENTES[[#This Row],[QUANTIDADE]]*(BASE_CLIENTES[[#This Row],[RECEITA]]-BASE_CLIENTES[[#This Row],[CUSTO]]) -> 165954 | L11: =PROPER(TEXT(BASE_CLIENTES[[#This Row],[DATA]],"mmm")) -> Jan | M11: =TEXT(BASE_CLIENTES[[#This Row],[DATA]],"aaaa") -> 2020
B12: 43844 | C12: PEARTREE ADVOGADOS | D12: DILIGÊNCIAS | E12: GRANDE SP | F12: 7 | G12: 27 | H12: 9349 | I12: =BASE_CLIENTES[[#This Row],[CUSTO]]*BASE_CLIENTES[[#This Row],[QUANTIDADE]] -> 189 | J12: =BASE_CLIENTES[[#This Row],[RECEITA]]*BASE_CLIENTES[[#This Row],[QUANTIDADE]] -> 65443 | K12: =BASE_CLIENTES[[#This Row],[QUANTIDADE]]*(BASE_CLIENTES[[#This Row],[RECEITA]]-BASE_CLIENTES[[#This Row],[CUSTO]]) -> 65254 | L12: =PROPER(TEXT(BASE_CLIENTES[[#This Row],[DATA]],"mmm")) -> Jan | M12: =TEXT(BASE_CLIENTES[[#This Row],[DATA]],"aaaa") -> 2020
B13: 43845 | C13: GUMERCINDO LAW | D13: AUDIÊNCIAS | E13: CAPITAL | F13: 14 | G13: 26 | H13: 8364 | I13: =BASE_CLIENTES[[#This Row],[CUSTO]]*BASE_CLIENTES[[#This Row],[QUANTIDADE]] -> 364 | J13: =BASE_CLIENTES[[#This Row],[RECEITA]]*BASE_CLIENTES[[#This Row],[QUANTIDADE]] -> 117096 | K13: =BASE_CLIENTES[[#This Row],[QUANTIDADE]]*(BASE_CLIENTES[[#This Row],[RECEITA]]-BASE_CLIENTES[[#This Row],[CUSTO]]) -> 116732 | L13: =PROPER(TEXT(BASE_CLIENTES[[#This Row],[DATA]],"mmm")) -> Jan | M13: =TEXT(BASE_CLIENTES[[#This Row],[DATA]],"aaaa") -> 2020
B14: 43846 | C14: LOBATO & ASSOCIADOS | D14: PROTOCOLO | E14: BRASIL | F14: 18 | G14: 23 | H14: 7075 | I14: =BASE_CLIENTES[[#This Row],[CUSTO]]*BASE_CLIENTES[[#This Row],[QUANTIDADE]] -> 414 | J14: =BASE_CLIENTES[[#This Row],[RECEITA]]*BASE_CLIENTES[[#This Row],[QUANTIDADE]] -> 127350 | K14: =BASE_CLIENTES[[#This Row],[QUANTIDADE]]*(BASE_CLIENTES[[#This Row],[RECEITA]]-BASE_CLIENTES[[#This Row],[CUSTO]]) -> 126936 | L14: =PROPER(TEXT(BASE_CLIENTES[[#This Row],[DATA]],"mmm")) -> Jan | M14: =TEXT(BASE_CLIENTES[[#This Row],[DATA]],"aaaa") -> 2020
B15: 43848 | C15: LOBATO & ASSOCIADOS | D15: DILIGÊNCIAS | E15: INTERIOR | F15: 15 | G15: 29 | H15: 9952 | I15: =BASE_CLIENTES[[#This Row],[CUSTO]]*BASE_CLIENTES[[#This Row],[QUANTIDADE]] -> 435 | J15: =BASE_CLIENTES[[#This Row],[RECEITA]]*BASE_CLIENTES[[#This Row],[QUANTIDADE]] -> 149280 | K15: =BASE_CLIENTES[[#This Row],[QUANTIDADE]]*(BASE_CLIENTES[[#This Row],[RECEITA]]-BASE_CLIENTES[[#This Row],[CUSTO]]) -> 148845 | L15: =PROPER(TEXT(BASE_CLIENTES[[#This Row],[DATA]],"mmm")) -> Jan | M15: =TEXT(BASE_CLIENTES[[#This Row],[DATA]],"aaaa") -> 2020
B16: 43849 | C16: LOBATO & ASSOCIADOS | D16: AUDIÊNCIAS | E16: CAPITAL | F16: 15 | G16: 24 | H16: 8429 | I16: =BASE_CLIENTES[[#This Row],[CUSTO]]*BASE_CLIENTES[[#This Row],[QUANTIDADE]] -> 360 | J16: =BASE_CLIENTES[[#This Row],[RECEITA]]*BASE_CLIENTES[[#This Row],[QUANTIDADE]] -> 126435 | K16: =BASE_CLIENTES[[#This Row],[QUANTIDADE]]*(BASE_CLIENTES[[#This Row],[RECEITA]]-BASE_CLIENTES[[#This Row],[CUSTO]]) -> 126075 | L16: =PROPER(TEXT(BASE_CLIENTES[[#This Row],[DATA]],"mmm")) -> Jan | M16: =TEXT(BASE_CLIENTES[[#This Row],[DATA]],"aaaa") -> 2020
B17: 43849 | C17: PEARTREE ADVOGADOS | D17: PROTOCOLO | E17: GRANDE SP | F17: 20 | G17: 28 | H17: 9512 | I17: =BASE_CLIENTES[[#This Row],[CUSTO]]*BASE_CLIENTES[[#This Row],[QUANTIDADE]] -> 560 | J17: =BASE_CLIENTES[[#This Row],[RECEITA]]*BASE_CLIENTES[[#This Row],[QUANTIDADE]] -> 190240 | K17: =BASE_CLIENTES[[#This Row],[QUANTIDADE]]*(BASE_CLIENTES[[#This Row],[RECEITA]]-BASE_CLIENTES[[#This Row],[CUSTO]]) -> 189680 | L17: =PROPER(TEXT(BASE_CLIENTES[[#This Row],[DATA]],"mmm")) -> Jan | M17: =TEXT(BASE_CLIENTES[[#This Row],[DATA]],"aaaa") -> 2020
... B46: 43910 | C46: LOBATO & ASSOCIADOS | D46: AUDIÊNCIAS | E46: CAPITAL | F46: 18 | G46: 52 | H46: 3500 | I46: =BASE_CLIENTES[[#This Row],[CUSTO]]*BASE_CLIENTES[[#This Row],[QUANTIDADE]] -> 936 | J46: =BASE_CLIENTES[[#This Row],[RECEITA]]*BASE_CLIENTES[[#This Row],[QUANTIDADE]] -> 63000 | K46: =BASE_CLIENTES[[#This Row],[QUANTIDADE]]*(BASE_CLIENTES[[#This Row],[RECEITA]]-BASE_CLIENTES[[#This Row],[CUSTO]]) -> 62064 | L46: =PROPER(TEXT(BASE_CLIENTES[[#This Row],[DATA]],"mmm")) -> Mar | M46: =TEXT(BASE_CLIENTES[[#This Row],[DATA]],"aaaa") -> 2020

Sheet BASE_ESCRITÓRIO
B5: DATA | C5: TIPO | D5: VALOR | E5: OBSERVAÇÃO | F5: MÊS | G5: ANO
B6: 43831 | C6: CONTADOR | D6: 1657 | F6: =PROPER(TEXT(BASE_ESCRITÓRIO[[#This Row],[DATA]],"mmm")) -> Jan | G6: =TEXT(BASE_ESCRITÓRIO[[#This Row],[DATA]],"aaaa") -> 2020
B7: 43831 | C7: INTERNET | D7: 1344 | F7: =PROPER(TEXT(BASE_ESCRITÓRIO[[#This Row],[DATA]],"mmm")) -> Jan | G7: =TEXT(BASE_ESCRITÓRIO[[#This Row],[DATA]],"aaaa") -> 2020
B8: 43831 | C8: LUZ | D8: 1957 | F8: =PROPER(TEXT(BASE_ESCRITÓRIO[[#This Row],[DATA]],"mmm")) -> Jan | G8: =TEXT(BASE_ESCRITÓRIO[[#This Row],[DATA]],"aaaa") -> 2020
B9: 43831 | C9: UBER | D9: 1389 | F9: =PROPER(TEXT(BASE_ESCRITÓRIO[[#This Row],[DATA]],"mmm")) -> Jan | G9: =TEXT(BASE_ESCRITÓRIO[[#This Row],[DATA]],"aaaa") -> 2020
B10: 43831 | C10: TARIFAS | D10: 1244 | F10: =PROPER(TEXT(BASE_ESCRITÓRIO[[#This Row],[DATA]],"mmm")) -> Jan | G10: =TEXT(BASE_ESCRITÓRIO[[#This Row],[DATA]],"aaaa") -> 2020
B11: 43831 | C11: DELTA | D11: 1734 | F11: =PROPER(TEXT(BASE_ESCRITÓRIO[[#This Row],[DATA]],"mmm")) -> Jan | G11: =TEXT(BASE_ESCRITÓRIO[[#This Row],[DATA]],"aaaa") -> 2020
B12: 43831 | C12: CELULAR | D12: 1458 | F12: =PROPER(TEXT(BASE_ESCRITÓRIO[[#This Row],[DATA]],"mmm")) -> Jan | G12: =TEXT(BASE_ESCRITÓRIO[[#This Row],[DATA]],"aaaa") -> 2020
B13: 43831 | C13: GASOLINA | D13: 1488 | F13: =PROPER(TEXT(BASE_ESCRITÓRIO[[#This Row],[DATA]],"mmm")) -> Jan | G13: =TEXT(BASE_ESCRITÓRIO[[#This Row],[DATA]],"aaaa") -> 2020
B14: 43831 | C14: JURIDICO CORRECT | D14: 1254 | F14: =PROPER(TEXT(BASE_ESCRITÓRIO[[#This Row],[DATA]],"mmm")) -> Jan | G14: =TEXT(BASE_ESCRITÓRIO[[#This Row],[DATA]],"aaaa") -> 2020
B15: 43831 | C15: JURIS CORRESPONDENTE | D15: 1123 | F15: =PROPER(TEXT(BASE_ESCRITÓRIO[[#This Row],[DATA]],"mmm")) -> Jan | G15: =TEXT(BASE_ESCRITÓRIO[[#This Row],[DATA]],"aaaa") -> 2020
B16: 43831 | C16: EMPRÉSTIMO | D16: 1889 | F16: =PROPER(TEXT(BASE_ESCRITÓRIO[[#This Row],[DATA]],"mmm")) -> Jan | G16: =TEXT(BASE_ESCRITÓRIO[[#This Row],[DATA]],"aaaa") -> 2020
B17: 43831 | C17: SISTEMA | D17: 1412 | F17: =PROPER(TEXT(BASE_ESCRITÓRIO[[#This Row],[DATA]],"mmm")) -> Jan | G17: =TEXT(BASE_ESCRITÓRIO[[#This Row],[DATA]],"aaaa") -> 2020
... B58: 43891 | C58: INTERNET | D58: 1208 | F58: =PROPER(TEXT(BASE_ESCRITÓRIO[[#This Row],[DATA]],"mmm")) -> Mar | G58: =TEXT(BASE_ESCRITÓRIO[[#This Row],[DATA]],"aaaa") -> 2020
B59: 43891 | C59: FUNCIONÁRIOS | D59: 1539 | E59: Juliana | F59: =PROPER(TEXT(BASE_ESCRITÓRIO[[#This Row],[DATA]],"mmm")) -> Mar | G59: =TEXT(BASE_ESCRITÓRIO[[#This Row],[DATA]],"aaaa") -> 2020
B60: 43941 | C60: INTERNET | D60: 500 | E60: contrato novo net | F60: =PROPER(TEXT(BASE_ESCRITÓRIO[[#This Row],[DATA]],"mmm")) -> Abr | G60: =TEXT(BASE_ESCRITÓRIO[[#This Row],[DATA]],"aaaa") -> 2020

Sheet APOIO
AV2: DASHBOARD CLIENTE
Z3: Médias | AA3: RECEITA | AB3: =AVERAGE(O8:O30) -> 13646.333
AA4: % RECEITA | AB4: =AVERAGE(P8:P30) -> 0.33333333
C5: RECEITA | E5: CONTRATAÇÕES | H5: CUSTO VARIÁVEL | K5: CUSTO FUNCIONÁRIOS | AA5: LUCRO LÍQUIDO | AB5: =AVERAGE(W8:W30) -> 3588.6667 | AN5: TOTAL | AO5: =SUM(AN8:AN10) -> 7 | AZ5: Análise de contratações por cliente | BH5: Custos de contratações por regioão | BL5: Receita total de contratações por regioão
AA6: %LL | AB6: =AVERAGE(X8:X30) -> 0.28150049 | AD6: Análise de contratações por região | AJ6: Análise de tipos de contratações | AS6: Análise gastos
B7: Rótulos de Linha | C7: Soma de RECEITA | E7: Rótulos de Linha | F7: Contagem de CONTRATAÇÕES | H7: Rótulos de Linha | I7: Soma de CUSTO TOTAL | K7: Rótulos de Linha | L7: Soma de VALOR | N7: CLIENTES | O7: RECEITA | P7: % RECEITA | Q7: LEGENDA RECEITA | R7: CUSTO VARIÁVEL | S7: FUNCIONÁRIOS | T7: ESTRUTURAL | U7: IMPOSTO | V7: CUSTO TOTAL | W7: LUCRO LÍQUIDO | X7: %LL | Y7: LEGENDA LUCRO | Z7: total | AA7: FATURAMENTO | AB7: =SUM(O8:O30) -> 40939 | AD7: Rótulos de Linha | AE7: Contagem de CONTRATAÇÕES | AG7: Espelho para gráfico | AJ7: Rótulos de Linha | AK7: Contagem de CONTRATAÇÕES | AN7: QUANTIDADE | AO7: % | AP7: Complemento | AS7: Rótulos de Linha | AT7: Soma de VALOR | AV7: CONTRATAÇÕES | AW7: REGIÃO | AX7: Soma de QUANTIDADE | AZ7: CONTRATAÇÕES | BA7: Soma de QUANTIDADE | BB7: Soma de RECEITA | BE7: QUANTIDADE | BF7: RECEITA | BH7: CONTRATAÇÕES | BI7: REGIÃO | BJ7: Soma de CUSTO TOTAL | BL7: CONTRATAÇÕES | BM7: REGIÃO | BN7: Soma de RECEITA TOTAL
B8: LOBATO & ASSOCIADOS | C8: 25025 | E8: GUMERCINDO LAW | F8: 1 | H8: GUMERCINDO LAW | I8: 116 | K8: FUNCIONÁRIOS | L8: 1539 | N8: =B8 -> LOBATO & ASSOCIADOS | O8: =IFERROR(VLOOKUP(N8,B:C,2,0),"") -> 25025 | P8: =IFERROR(O8/$AB$7,"") -> 0.61127531 | Q8: =TEXT(O8,"R$0.000")&" | "&TEXT(P8,"0%") -> R$25.025 | 61% | R8: =IFERROR(VLOOKUP(N8,H:I,2,0),"") -> 2142 | S8: =IFERROR(P8*$L$8,"") -> 940.75271 | T8: =IFERROR(P8*$K$14,"") -> 16005.633 | U8: =IFERROR(AUXILIARES!$J$5*APOIO!O8,"") -> 2815.3125 | V8: =IFERROR(SUM(R8:U8),"") -> 21903.698 | W8: =IFERROR(O8-R8-S8-T8,"") -> 5936.6145 | X8: =IFERROR(W8/O8,"") -> 0.23722735 | Y8: =TEXT(W8,"R$0.000")&" | "&TEXT(X8,"0%") -> R$5.937 | 24% | AA8: CUSTO | AB8: =SUM(V8:V30) -> 34778.637 | AD8: BRASIL | AE8: 3 | AG8: CAPITAL | AH8: =IFERROR(VLOOKUP(AG8,$AD$7:$AE$13,2,0),"") -> 2 | AJ8: AUDIÊNCIAS | AK8: 3 | AM8: AUDIÊNCIAS | AN8: =IFERROR(VLOOKUP(AM8,$AJ$7:$AK$12,2,0),0) -> 3 | AO8: =AN8/$AO$5 -> 0.42857143 | AP8: =1-AO8 -> 0.57142857 | AS8: UBER | AT8: 1055 | AV8: AUDIÊNCIAS | AW8: BRASIL | AX8: 5 | AZ8: AUDIÊNCIAS | BA8: 23 | BB8: 16255 | BD8: AUDIÊNCIAS | BE8: =IFERROR(VLOOKUP(BD8,$AZ$7:$BB$11,2,0),0) -> 23 | BF8: =IFERROR(VLOOKUP(BD8,$AZ$7:$BB$11,3,0),0) -> 16255 | BH8: AUDIÊNCIAS | BI8: BRASIL | BJ8: 138 | BL8: AUDIÊNCIAS | BM8: BRASIL | BN8: 31706
B9: PEARTREE ADVOGADOS | C9: 9597 | E9: LOBATO & ASSOCIADOS | F9: 5 | H9: LOBATO & ASSOCIADOS | I9: 2142 | N9: =B9 -> PEARTREE ADVOGADOS | O9: =IFERROR(VLOOKUP(N9,B:C,2,0),"") -> 9597 | P9: =IFERROR(O9/$AB$7,"") -> 0.23442194 | Q9: =TEXT(O9,"R$0.000")&" | "&TEXT(P9,"0%") -> R$9.597 | 23% | R9: =IFERROR(VLOOKUP(N9,H:I,2,0),"") -> 192 | S9: =IFERROR(P9*$L$8,"") -> 360.77537 | T9: =IFERROR(P9*$K$14,"") -> 6138.1042 | U9: =IFERROR(AUXILIARES!$J$5*APOIO!O9,"") -> 1079.6625 | V9: =IFERROR(SUM(R9:U9),"") -> 7770.5421 | W9: =IFERROR(O9-R9-S9-T9,"") -> 2906.1204 | X9: =IFERROR(W9/O9,"") -> 0.30281551 | Y9: =TEXT(W9,"R$0.000")&" | "&TEXT(X9,"0%") -> R$2.906 | 30% | AA9: IMPOSTO | AB9: 10000 | AD9: CAPITAL | AE9: 2 | AG9: GRANDE SP | AH9: =IFERROR(VLOOKUP(AG9,$AD$7:$AE$13,2,0),"") | AJ9: DILIGÊNCIAS | AK9: 1 | AM9: DILIGÊNCIAS | AN9: =IFERROR(VLOOKUP(AM9,$AJ$7:$AK$12,2,0),0) -> 1 | AO9: =AN9/$AO$5 -> 0.14285714 | AP9: =1-AO9 -> 0.85714286 | AS9: EMPRÉSTIMO | AT9: 1096 | AV9: AUDIÊNCIAS | AW9: CAPITAL | AX9: 18 | AZ9: DILIGÊNCIAS | BA9: 8 | BB9: 9597 | BD9: DILIGÊNCIAS | BE9: =IFERROR(VLOOKUP(BD9,$AZ$7:$BB$11,2,0),0) -> 8 | BF9: =IFERROR(VLOOKUP(BD9,$AZ$7:$BB$11,3,0),0) -> 9597 | BH9: AUDIÊNCIAS | BI9: CAPITAL | BJ9: 936 | BL9: AUDIÊNCIAS | BM9: CAPITAL | BN9: 63000
B10: GUMERCINDO LAW | C10: 6317 | E10: PEARTREE ADVOGADOS | F10: 1 | H10: PEARTREE ADVOGADOS | I10: 192 | N10: =B10 -> GUMERCINDO LAW | O10: =IFERROR(VLOOKUP(N10,B:C,2,0),"") -> 6317 | P10: =IFERROR(O10/$AB$7,"") -> 0.15430274 | Q10: =TEXT(O10,"R$0.000")&" | "&TEXT(P10,"0%") -> R$6.317 | 15% | R10: =IFERROR(VLOOKUP(N10,H:I,2,0),"") -> 116 | S10: =IFERROR(P10*$L$8,"") -> 237.47192 | T10: =IFERROR(P10*$K$14,"") -> 4040.263 | U10: =IFERROR(AUXILIARES!$J$5*APOIO!O10,"") -> 710.6625 | V10: =IFERROR(SUM(R10:U10),"") -> 5104.3974 | W10: =IFERROR(O10-R10-S10-T10,"") -> 1923.2651 | X10: =IFERROR(W10/O10,"") -> 0.30445861 | Y10: =TEXT(W10,"R$0.000")&" | "&TEXT(X10,"0%") -> R$1.923 | 30% | AD10: INTERIOR | AE10: 2 | AG10: INTERIOR | AH10: =IFERROR(VLOOKUP(AG10,$AD$7:$AE$13,2,0),"") -> 2 | AJ10: PROTOCOLO | AK10: 3 | AM10: PROTOCOLO | AN10: =IFERROR(VLOOKUP(AM10,$AJ$7:$AK$12,2,0),0) -> 3 | AO10: =AN10/$AO$5 -> 0.42857143 | AP10: =1-AO10 -> 0.57142857 | AS10: LUZ | AT10: 1098 | AV10: DILIGÊNCIAS | AW10: CAPITAL | AX10: 8 | AZ10: PROTOCOLO | BA10: 52 | BB10: 15087 | BD10: PROTOCOLO | BE10: =IFERROR(VLOOKUP(BD10,$AZ$7:$BB$11,2,0),0) -> 52 | BF10: =IFERROR(VLOOKUP(BD10,$AZ$7:$BB$11,3,0),0) -> 15087 | BH10: DILIGÊNCIAS | BI10: CAPITAL | BJ10: 192 | BL10: DILIGÊNCIAS | BM10: CAPITAL | BN10: 76776
K11: CUSTO TOTAL | N11: =B11 -> 0 | O11: =IFERROR(VLOOKUP(N11,B:C,2,0),"") | P11: =IFERROR(O11/$AB$7,"") | Q11: =TEXT(O11,"R$0.000")&" | "&TEXT(P11,"0%") -> | | R11: =IFERROR(VLOOKUP(N11,H:I,2,0),"") | S11: =IFERROR(P11*$L$8,"") | T11: =IFERROR(P11*$K$14,"") | U11: =IFERROR(AUXILIARES!$J$5*APOIO!O11,"") | V11: =IFERROR(SUM(R11:U11),"") -> 0 | W11: =IFERROR(O11-R11-S11-T11,"") | X11: =IFERROR(W11/O11,"") | Y11: =TEXT(W11,"R$0.000")&" | "&TEXT(X11,"0%") -> | | AG11: BRASIL | AH11: =IFERROR(VLOOKUP(AG11,$AD$7:$AE$13,2,0),"") -> 3 | AS11: CELULAR | AT11: 1123 | AV11: PROTOCOLO | AW11: BRASIL | AX11: 12 | BH11: PROTOCOLO | BI11: BRASIL | BJ11: 276 | BL11: PROTOCOLO | BM11: BRASIL | BN11: 69816
N12: =B12 -> 0 | O12: =IFERROR(VLOOKUP(N12,B:C,2,0),"") | P12: =IFERROR(O12/$AB$7,"") | Q12: =TEXT(O12,"R$0.000")&" | "&TEXT(P12,"0%") -> | | R12: =IFERROR(VLOOKUP(N12,H:I,2,0),"") | S12: =IFERROR(P12*$L$8,"") | T12: =IFERROR(P12*$K$14,"") | U12: =IFERROR(AUXILIARES!$J$5*APOIO!O12,"") | V12: =IFERROR(SUM(R12:U12),"") -> 0 | W12: =IFERROR(O12-R12-S12-T12,"") | X12: =IFERROR(W12/O12,"") | Y12: =TEXT(W12,"R$0.000")&" | "&TEXT(X12,"0%") -> | | AS12: SISTEMA | AT12: 1263 | AV12: PROTOCOLO | AW12: INTERIOR | AX12: 40 | BH12: PROTOCOLO | BI12: INTERIOR | BJ12: 908 | BL12: PROTOCOLO | BM12: INTERIOR | BN12: 181111
K13: Soma de VALOR | N13: =B13 -> 0 | O13: =IFERROR(VLOOKUP(N13,B:C,2,0),"") | P13: =IFERROR(O13/$AB$7,"") | Q13: =TEXT(O13,"R$0.000")&" | "&TEXT(P13,"0%") -> | | R13: =IFERROR(VLOOKUP(N13,H:I,2,0),"") | S13: =IFERROR(P13*$L$8,"") | T13: =IFERROR(P13*$K$14,"") | U13: =IFERROR(AUXILIARES!$J$5*APOIO!O13,"") | V13: =IFERROR(SUM(R13:U13),"") -> 0 | W13: =IFERROR(O13-R13-S13-T13,"") | X13: =IFERROR(W13/O13,"") | Y13: =TEXT(W13,"R$0.000")&" | "&TEXT(X13,"0%") -> | | AS13: JURIDICO CORRECT | AT13: 1274
K14: 26184 | N14: =B14 -> 0 | O14: =IFERROR(VLOOKUP(N14,B:C,2,0),"") | P14: =IFERROR(O14/$AB$7,"") | Q14: =TEXT(O14,"R$0.000")&" | "&TEXT(P14,"0%") -> | | R14: =IFERROR(VLOOKUP(N14,H:I,2,0),"") | S14: =IFERROR(P14*$L$8,"") | T14: =IFERROR(P14*$K$14,"") | U14: =IFERROR(AUXILIARES!$J$5*APOIO!O14,"") | V14: =IFERROR(SUM(R14:U14),"") -> 0 | W14: =IFERROR(O14-R14-S14-T14,"") | X14: =IFERROR(W14/O14,"") | Y14: =TEXT(W14,"R$0.000")&" | "&TEXT(X14,"0%") -> | | AS14: GASOLINA | AT14: 1342
N15: =B15 -> 0 | O15: =IFERROR(VLOOKUP(N15,B:C,2,0),"") | P15: =IFERROR(O15/$AB$7,"") | Q15: =TEXT(O15,"R$0.000")&" | "&TEXT(P15,"0%") -> | | R15: =IFERROR(VLOOKUP(N15,H:I,2,0),"") | S15: =IFERROR(P15*$L$8,"") | T15: =IFERROR(P15*$K$14,"") | U15: =IFERROR(AUXILIARES!$J$5*APOIO!O15,"") | V15: =IFERROR(SUM(R15:U15),"") -> 0 | W15: =IFERROR(O15-R15-S15-T15,"") | X15: =IFERROR(W15/O15,"") | Y15: =TEXT(W15,"R$0.000")&" | "&TEXT(X15,"0%") -> | | AA15: FATURAMENTO | AB15: =AB7 -> 40939 | AS15: SIMPLES | AT15: 1342
N16: =B16 -> 0 | O16: =IFERROR(VLOOKUP(N16,B:C,2,0),"") | P16: =IFERROR(O16/$AB$7,"") | Q16: =TEXT(O16,"R$0.000")&" | "&TEXT(P16,"0%") -> | | R16: =IFERROR(VLOOKUP(N16,H:I,2,0),"") | S16: =IFERROR(P16*$L$8,"") | T16: =IFERROR(P16*$K$14,"") | U16: =IFERROR(AUXILIARES!$J$5*APOIO!O16,"") | V16: =IFERROR(SUM(R16:U16),"") -> 0 | W16: =IFERROR(O16-R16-S16-T16,"") | X16: =IFERROR(W16/O16,"") | Y16: =TEXT(W16,"R$0.000")&" | "&TEXT(X16,"0%") -> | | AA16: CUSTO VARIÁVEL | AB16: =SUM(R8:R30) -> 2450 | AS16: FUNCIONÁRIOS | AT16: 1539
N17: =B17 -> 0 | O17: =IFERROR(VLOOKUP(N17,B:C,2,0),"") | P17: =IFERROR(O17/$AB$7,"") | Q17: =TEXT(O17,"R$0.000")&" | "&TEXT(P17,"0%") -> | | R17: =IFERROR(VLOOKUP(N17,H:I,2,0),"") | S17: =IFERROR(P17*$L$8,"") | T17: =IFERROR(P17*$K$14,"") | U17: =IFERROR(AUXILIARES!$J$5*APOIO!O17,"") | V17: =IFERROR(SUM(R17:U17),"") -> 0 | W17: =IFERROR(O17-R17-S17-T17,"") | X17: =IFERROR(W17/O17,"") | Y17: =TEXT(W17,"R$0.000")&" | "&TEXT(X17,"0%") -> | | AA17: ESTRUTURA | AB17: =SUM(T8:T30) -> 26184 | AS17: CALENDÁRIOS | AT17: 1564
N18: =B18 -> 0 | O18: =IFERROR(VLOOKUP(N18,B:C,2,0),"") | P18: =IFERROR(O18/$AB$7,"") | Q18: =TEXT(O18,"R$0.000")&" | "&TEXT(P18,"0%") -> | | R18: =IFERROR(VLOOKUP(N18,H:I,2,0),"") | S18: =IFERROR(P18*$L$8,"") | T18: =IFERROR(P18*$K$14,"") | U18: =IFERROR(AUXILIARES!$J$5*APOIO!O18,"") | V18: =IFERROR(SUM(R18:U18),"") -> 0 | W18: =IFERROR(O18-R18-S18-T18,"") | X18: =IFERROR(W18/O18,"") | Y18: =TEXT(W18,"R$0.000")&" | "&TEXT(X18,"0%") -> | | AA18: IMPOSTO | AB18: =AB9 -> 10000 | AS18: CONDUÇÕES | AT18: 1658
N19: =B19 -> 0 | O19: =IFERROR(VLOOKUP(N19,B:C,2,0),"") | P19: =IFERROR(O19/$AB$7,"") | Q19: =TEXT(O19,"R$0.000")&" | "&TEXT(P19,"0%") -> | | R19: =IFERROR(VLOOKUP(N19,H:I,2,0),"") | S19: =IFERROR(P19*$L$8,"") | T19: =IFERROR(P19*$K$14,"") | U19: =IFERROR(AUXILIARES!$J$5*APOIO!O19,"") | V19: =IFERROR(SUM(R19:U19),"") -> 0 | W19: =IFERROR(O19-R19-S19-T19,"") | X19: =IFERROR(W19/O19,"") | Y19: =TEXT(W19,"R$0.000")&" | "&TEXT(X19,"0%") -> | | AA19: FUNCIONÁRIO | AB19: =SUM(S8:S30) -> 1539 | AS19: JURIS CORRESPONDENTE | AT19: 1668
N20: =B20 -> 0 | O20: =IFERROR(VLOOKUP(N20,B:C,2,0),"") | P20: =IFERROR(O20/$AB$7,"") | Q20: =TEXT(O20,"R$0.000")&" | "&TEXT(P20,"0%") -> | | R20: =IFERROR(VLOOKUP(N20,H:I,2,0),"") | S20: =IFERROR(P20*$L$8,"") | T20: =IFERROR(P20*$K$14,"") | U20: =IFERROR(AUXILIARES!$J$5*APOIO!O20,"") | V20: =IFERROR(SUM(R20:U20),"") -> 0 | W20: =IFERROR(O20-R20-S20-T20,"") | X20: =IFERROR(W20/O20,"") | Y20: =TEXT(W20,"R$0.000")&" | "&TEXT(X20,"0%") -> | | AA20: LUCRO LÍQUIDO | AB20: =SUM(W8:W30) -> 10766 | AS20: DELTA | AT20: 1698
N21: =B21 -> 0 | O21: =IFERROR(VLOOKUP(N21,B:C,2,0),"") | P21: =IFERROR(O21/$AB$7,"") | Q21: =TEXT(O21,"R$0.000")&" | "&TEXT(P21,"0%") -> | | R21: =IFERROR(VLOOKUP(N21,H:I,2,0),"") | S21: =IFERROR(P21*$L$8,"") | T21: =IFERROR(P21*$K$14,"") | U21: =IFERROR(AUXILIARES!$J$5*APOIO!O21,"") | V21: =IFERROR(SUM(R21:U21),"") -> 0 | W21: =IFERROR(O21-R21-S21-T21,"") | X21: =IFERROR(W21/O21,"") | Y21: =TEXT(W21,"R$0.000")&" | "&TEXT(X21,"0%") -> | | AS21: TARIFAS | AT21: 1726
N22: =B22 -> 0 | O22: =IFERROR(VLOOKUP(N22,B:C,2,0),"") | P22: =IFERROR(O22/$AB$7,"") | Q22: =TEXT(O22,"R$0.000")&" | "&TEXT(P22,"0%") -> | | R22: =IFERROR(VLOOKUP(N22,H:I,2,0),"") | S22: =IFERROR(P22*$L$8,"") | T22: =IFERROR(P22*$K$14,"") | U22: =IFERROR(AUXILIARES!$J$5*APOIO!O22,"") | V22: =IFERROR(SUM(R22:U22),"") -> 0 | W22: =IFERROR(O22-R22-S22-T22,"") | X22: =IFERROR(W22/O22,"") | Y22: =TEXT(W22,"R$0.000")&" | "&TEXT(X22,"0%") -> | | AA22: META | AB22: 25000 | AS22: CONTADOR | AT22: 1765
N23: =B23 -> 0 | O23: =IFERROR(VLOOKUP(N23,B:C,2,0),"") | P23: =IFERROR(O23/$AB$7,"") | Q23: =TEXT(O23,"R$0.000")&" | "&TEXT(P23,"0%") -> | | R23: =IFERROR(VLOOKUP(N23,H:I,2,0),"") | S23: =IFERROR(P23*$L$8,"") | T23: =IFERROR(P23*$K$14,"") | U23: =IFERROR(AUXILIARES!$J$5*APOIO!O23,"") | V23: =IFERROR(SUM(R23:U23),"") -> 0 | W23: =IFERROR(O23-R23-S23-T23,"") | X23: =IFERROR(W23/O23,"") | Y23: =TEXT(W23,"R$0.000")&" | "&TEXT(X23,"0%") -> | | AS23: JANTAR | AT23: 1989
N24: =B24 -> 0 | O24: =IFERROR(VLOOKUP(N24,B:C,2,0),"") | P24: =IFERROR(O24/$AB$7,"") | Q24: =TEXT(O24,"R$0.000")&" | "&TEXT(P24,"0%") -> | | R24: =IFERROR(VLOOKUP(N24,H:I,2,0),"") | S24: =IFERROR(P24*$L$8,"") | T24: =IFERROR(P24*$K$14,"") | U24: =IFERROR(AUXILIARES!$J$5*APOIO!O24,"") | V24: =IFERROR(SUM(R24:U24),"") -> 0 | W24: =IFERROR(O24-R24-S24-T24,"") | X24: =IFERROR(W24/O24,"") | Y24: =TEXT(W24,"R$0.000")&" | "&TEXT(X24,"0%") -> | | AS24: INTERNET | AT24: 2984
N25: =B25 -> 0 | O25: =IFERROR(VLOOKUP(N25,B:C,2,0),"") | P25: =IFERROR(O25/$AB$7,"") | Q25: =TEXT(O25,"R$0.000")&" | "&TEXT(P25,"0%") -> | | R25: =IFERROR(VLOOKUP(N25,H:I,2,0),"") | S25: =IFERROR(P25*$L$8,"") | T25: =IFERROR(P25*$K$14,"") | U25: =IFERROR(AUXILIARES!$J$5*APOIO!O25,"") | V25: =IFERROR(SUM(R25:U25),"") -> 0 | W25: =IFERROR(O25-R25-S25-T25,"") | X25: =IFERROR(W25/O25,"") | Y25: =TEXT(W25,"R$0.000")&" | "&TEXT(X25,"0%") -> |
N26: =B26 -> 0 | O26: =IFERROR(VLOOKUP(N26,B:C,2,0),"") | P26: =IFERROR(O26/$AB$7,"") | Q26: =TEXT(O26,"R$0.000")&" | "&TEXT(P26,"0%") -> | | R26: =IFERROR(VLOOKUP(N26,H:I,2,0),"") | S26: =IFERROR(P26*$L$8,"") | T26: =IFERROR(P26*$K$14,"") | U26: =IFERROR(AUXILIARES!$J$5*APOIO!O26,"") | V26: =IFERROR(SUM(R26:U26),"") -> 0 | W26: =IFERROR(O26-R26-S26-T26,"") | X26: =IFERROR(W26/O26,"") | Y26: =TEXT(W26,"R$0.000")&" | "&TEXT(X26,"0%") -> |
N27: =B27 -> 0 | O27: =IFERROR(VLOOKUP(N27,B:C,2,0),"") | P27: =IFERROR(O27/$AB$7,"") | Q27: =TEXT(O27,"R$0.000")&" | "&TEXT(P27,"0%") -> | | R27: =IFERROR(VLOOKUP(N27,H:I,2,0),"") | S27: =IFERROR(P27*$L$8,"") | T27: =IFERROR(P27*$K$14,"") | U27: =IFERROR(AUXILIARES!$J$5*APOIO!O27,"") | V27: =IFERROR(SUM(R27:U27),"") -> 0 | W27: =IFERROR(O27-R27-S27-T27,"") | X27: =IFERROR(W27/O27,"") | Y27: =TEXT(W27,"R$0.000")&" | "&TEXT(X27,"0%") -> |
N28: =B28 -> 0 | O28: =IFERROR(VLOOKUP(N28,B:C,2,0),"") | P28: =IFERROR(O28/$AB$7,"") | Q28: =TEXT(O28,"R$0.000")&" | "&TEXT(P28,"0%") -> | | R28: =IFERROR(VLOOKUP(N28,H:I,2,0),"") | S28: =IFERROR(P28*$L$8,"") | T28: =IFERROR(P28*$K$14,"") | U28: =IFERROR(AUXILIARES!$J$5*APOIO!O28,"") | V28: =IFERROR(SUM(R28:U28),"") -> 0 | W28: =IFERROR(O28-R28-S28-T28,"") | X28: =IFERROR(W28/O28,"") | Y28: =TEXT(W28,"R$0.000")&" | "&TEXT(X28,"0%") -> |
N29: =B29 -> 0 | O29: =IFERROR(VLOOKUP(N29,B:C,2,0),"") | P29: =IFERROR(O29/$AB$7,"") | Q29: =TEXT(O29,"R$0.000")&" | "&TEXT(P29,"0%") -> | | R29: =IFERROR(VLOOKUP(N29,H:I,2,0),"") | S29: =IFERROR(P29*$L$8,"") | T29: =IFERROR(P29*$K$14,"") | U29: =IFERROR(AUXILIARES!$J$5*APOIO!O29,"") | V29: =IFERROR(SUM(R29:U29),"") -> 0 | W29: =IFERROR(O29-R29-S29-T29,"") | X29: =IFERROR(W29/O29,"") | Y29: =TEXT(W29,"R$0.000")&" | "&TEXT(X29,"0%") -> |
N30: =B30 -> 0 | O30: =IFERROR(VLOOKUP(N30,B:C,2,0),"") | P30: =IFERROR(O30/$AB$7,"") | Q30: =TEXT(O30,"R$0.000")&" | "&TEXT(P30,"0%") -> | | R30: =IFERROR(VLOOKUP(N30,H:I,2,0),"") | S30: =IFERROR(P30*$L$8,"") | T30: =IFERROR(P30*$K$14,"") | U30: =IFERROR(AUXILIARES!$J$5*APOIO!O30,"") | V30: =IFERROR(SUM(R30:U30),"") -> 0 | W30: =IFERROR(O30-R30-S30-T30,"") | X30: =IFERROR(W30/O30,"") | Y30: =TEXT(W30,"R$0.000")&" | "&TEXT(X30,"0%") -> |

Sheet CLIENTES
