Workbook
Name area_impressao_ap: #REF!,#REF!
Name area_impressao_ap: #REF!,#REF!
Name area_impressao_ap: 'Listagem de Pagamentos Efet'!$A$1:$G$3,'Listagem de Pagamentos Efet'!#REF!
Name Bu: [1]INPUT!$B$10
Name DC: [1]INPUT!$B$8
Name EXHIBIT_01: #REF!
Name EXHIBIT_01: #REF!
Name EXHIBIT_01: #REF!
Name EXHIBIT_01: #REF!
Name EXHIBIT_01: #REF!
Name EXHIBIT_02: #REF!
Name EXHIBIT_02: #REF!
Name EXHIBIT_02: #REF!
Name EXHIBIT_02: #REF!
Name EXHIBIT_02: #REF!
Name EXHIBIT_05: #REF!
Name EXHIBIT_05: #REF!
Name EXHIBIT_05: #REF!
Name EXHIBIT_05: #REF!
Name EXHIBIT_05: #REF!
Name EXHIBIT_06: #REF!
Name EXHIBIT_06: #REF!
Name EXHIBIT_06: #REF!
Name EXHIBIT_06: #REF!
Name EXHIBIT_06: #REF!
Name EXHIBIT_07: #REF!
Name EXHIBIT_07: #REF!
Name EXHIBIT_07: #REF!
Name EXHIBIT_07: #REF!
Name EXHIBIT_07: #REF!
Name EXHIBIT_08: #REF!
Name EXHIBIT_08: #REF!
Name EXHIBIT_08: #REF!
Name EXHIBIT_08: #REF!
Name EXHIBIT_08: #REF!
Name new_proj: '[2]Novos Projectos'!$A$3:$A$57
Name Pm: [1]INPUT!$B$6
Name Rd: [1]INPUT!$B$4
Name t: [1]INPUT!$B$7
Name TD: [1]INPUT!$B$9
Name VARa: [1]INPUT!$B$12

Sheet Pressupostos 
D1: Empresa:
A4: Pressupostos Gerais
A7: Unidade monetária | B7: Moeda: Real BRL | C7: Saldo Inicial: | D7: =SUM(E13:E21) -> 1008.12
A9: Ano de Balisamento / Data para o Início dos trabalhos diários | B9: 2018 | C9: 43586 | D9: Atenção a mudança as fórmulas no dia a dia dos meses
A12: Contas Bancárias | B12: Agência | C12: Conta | D12: Tx. De Contrato | E12: Saldo Inicial
A13: BANCO DO BRASIL | E13: 730.01
A14: DAYCOVAL - | E14: -42.91
A15: DAYCOVAL - 01 | E15: -455.47
A16: HSBC - 01 | E16: 0
A17: BRADESCO - | E17: -158.86
A18: BRADESCO - 01 | E18: 1501
A19: HSBC - 01 | E19: 86.56
A20: BRADESCO - | E20: 0
A21: DAYCOVAL 02 | E21: -652.21
E22: =SUM(E13:E21) -> 1008.12

Sheet AUTORIZAÇÃO PAGAMENTO
F1: Empresa: | G1: =+'Pressupostos '!E1 -> 0
A3: AUTORIZAÇÃO DE PAGAMENTO
G5: x
A7: DT EMISSÃO | B7: DT. VENCIMENTO | C7: RUBRICA | D7: ORIGEM DA DESPESA | E7: FAVORECIDO | F7: NºDOC | G7: CPF/CNPJ | H7: CHEQUE nº | I7: DOC/TED | J7: VALOR | K7: ORÇAMENTO DISPONÍVEL
L8: =+IFERROR(VLOOKUP(#REF!,[3]DRE!B:N,12,FALSE),"")
A12: DT EMISSÃO | B12: DT. VENCIMENTO | C12: RUBRICA | D12: ORIGEM DA DESPESA | E12: FAVORECIDO | F12: NºDOC | G12: CPF/CNPJ | H12: CHEQUE nº | I12: DOC/TED | J12: VALOR | K12: ORÇAMENTO DISPONÍVEL
L13: =+IFERROR(VLOOKUP(#REF!,[3]DRE!B:N,12,FALSE),"")
L14: =+IFERROR(VLOOKUP(#REF!,DRE!B:N,12,FALSE),"")
K15: =+IFERROR(VLOOKUP(C15,DRE!B:N,12,FALSE),"") | L15: =+IFERROR(VLOOKUP(#REF!,DRE!B:N,12,FALSE),"")
K16: =+IFERROR(VLOOKUP(C16,DRE!B:N,12,FALSE),"")
K17: =+IFERROR(VLOOKUP(C17,DRE!B:N,12,FALSE),"")
K18: =+IFERROR(VLOOKUP(C18,DRE!B:N,12,FALSE),"")
K19: =+IFERROR(VLOOKUP(C19,DRE!B:N,12,FALSE),"")
K20: =+IFERROR(VLOOKUP(C20,DRE!B:N,12,FALSE),"")
K21: =+IFERROR(VLOOKUP(C21,DRE!B:N,12,FALSE),"")
K22: =+IFERROR(VLOOKUP(C22,DRE!B:N,12,FALSE),"")
K23: =+IFERROR(VLOOKUP(C23,DRE!B:N,12,FALSE),"")
K24: =+IFERROR(VLOOKUP(C24,DRE!B:N,12,FALSE),"")
K25: =+IFERROR(VLOOKUP(C25,DRE!B:N,12,FALSE),"")
K26: =+IFERROR(VLOOKUP(C26,DRE!B:N,12,FALSE),"")
K27: =+IFERROR(VLOOKUP(C27,DRE!B:N,12,FALSE),"")
... K55: =+IFERROR(VLOOKUP(C55,DRE!B:N,12,FALSE),"")
A57: SALDO BANCÁRIO | B57: =(FECHAMENTO!AH17+J57)*0+62425.73 -> 62425.73 | D57: SALDO APÓS AP | E57: =B57-J57 -> 62425.73 | I57: TOTAL DA AP | J57: =SUM(J15:J56) -> 0
C61: -60387
AA62: ----------------------------------------------------------------------------------
Z63: ALFA MIX | AA63: DINHEIRO (D+1)
Z64: CSN DISTRIBUIDORA | AA64: CHEQUE (D+1)
Z65: TAMOYO | AA65: DÉBITO (D+1)
Z66: FORTALEZA | AA66: CRÉDITO (D+1)
Z67: NATAL | AA67: BOLETO (D+1)
Z68: JOÃO PESSOA | AA68: OUTROS RECEBIMENTOS (D+1)
Z69: RECIFE | AA69: -------------------------------------------------------------------------------
Z70: CSN REPRESENTAÇÕES | AA70: --------------------------------------------------------------------------------
AA71: PIS
AA72: COFINS
AA73: ISS
AA74: ICMS (AJUSTADO)
AA75: --------------------------------------------------------------------------------
AA76: CARTÃO DÉBITO
AA77: CARTÃO CRÉDITO
AA78: BOLETO
AA79: --------------------------------------------------------------------------------
AA80: INADIMPLENCIA
AA81: DEVOLUÇÕES
AA82: ROUBOS E FURTOS
... AA170: ---------------------------------------------------------------------------------

Sheet Listagem de Pagamentos Efet
F1: EMPRESA:
A4: DT EMISSÃO | B4: VENCIMENTO | C4: RUBRICA | D4: ORIGEM DA DESPESA | E4: FAVORECIDO | F4: NºDOC | G4: CPF/CNPJ | J4: VALOR
A5: 43525 | B5: 43525 | C5: GÁS | E5: CIA DE GAS DO CEARA - CEGAS | F5: NF 189303 | J5: 10000 | K5: BANCOS
A6: 43525 | B6: 43525 | C6: CUSTO DE REPOSIÇÃO/PRESTAÇÃO DE SERVIÇOS | E6: POSTO ALTO ALEGRE LTDA | F6: NF 19433--19439 | J6: 30000 | K6: BANCOS
A7: 43525 | B7: 43525 | C7: VALE ALIMENTAÇÃO | E7: CV DISTRIBUIDORA DE ALIMENTOS EIRELE ME (CAMPO VERDE) | F7: NF 78519 | J7: 4000 | K7: BANCOS
A8: 43525 | B8: 43525 | C8: ICMS (AJUSTADO) | E8: DARE | J8: 100 | K8: BANCOS
J353: =SUM(J5:J352) -> 44100
J360: =2168.97+2205.49 -> 4374.46

Sheet FLUXO DE CAIXA
D3: =+WEEKDAY(D4,1) -> 3 | E3: =+WEEKDAY(E4,1) -> 4 | F3: =+WEEKDAY(F4,1) -> 5 | G3: =+WEEKDAY(G4,1) -> 6 | H3: =+WEEKDAY(H4,1) -> 7 | I3: =+WEEKDAY(I4,1) -> 1 | J3: =+WEEKDAY(J4,1) -> 2 | K3: =+WEEKDAY(K4,1) -> 3 | ... AE3: =+WEEKDAY(AE4,1) -> 2 | AI3: =+WEEKDAY(AI4,1) -> 5 | AJ3: =+WEEKDAY(AJ4,1) -> 6 | AK3: =+WEEKDAY(AK4,1) -> 7 | AL3: =+WEEKDAY(AL4,1) -> 1 | AM3: =+WEEKDAY(AM4,1) -> 2 | AN3: =+WEEKDAY(AN4,1) -> 3 | AO3: =+WEEKDAY(AO4,1) -> 4 | AP3: =+WEEKDAY(AP4,1) -> 5 | ... BM3: =+WEEKDAY(BM4,1) -> 7 | BO3: =+WEEKDAY(BO4,1) -> 1 | BP3: =+WEEKDAY(BP4,1) -> 2 | BQ3: =+WEEKDAY(BQ4,1) -> 3 | BR3: =+WEEKDAY(BR4,1) -> 4 | BS3: =+WEEKDAY(BS4,1) -> 5 | BT3: =+WEEKDAY(BT4,1) -> 6 | BU3: =+WEEKDAY(BU4,1) -> 7 | BV3: =+WEEKDAY(BV4,1) -> 1 | ... CR3: =+WEEKDAY(CR4,1) -> 2 | CT3: =+WEEKDAY(CT4,1) -> 3 | CU3: =+WEEKDAY(CU4,1) -> 4 | CV3: =+WEEKDAY(CV4,1) -> 5 | CW3: =+WEEKDAY(CW4,1) -> 6 | CX3: =+WEEKDAY(CX4,1) -> 7 | CY3: =+WEEKDAY(CY4,1) -> 1 | CZ3: =+WEEKDAY(CZ4,1) -> 2 | DA3: =+WEEKDAY(DA4,1) -> 3 | ... DX3: =+WEEKDAY(DX4,1) -> 5 | DZ3: =+WEEKDAY(DZ4,1) -> 6 | EA3: =+WEEKDAY(EA4,1) -> 7 | EB3: =+WEEKDAY(EB4,1) -> 1 | EC3: =+WEEKDAY(EC4,1) -> 2 | ED3: =+WEEKDAY(ED4,1) -> 3 | EE3: =+WEEKDAY(EE4,1) -> 4 | EF3: =+WEEKDAY(EF4,1) -> 5 | EG3: =+WEEKDAY(EG4,1) -> 6 | ... FC3: =+WEEKDAY(FC4,1) -> 7 | FE3: =+WEEKDAY(FE4,1) -> 1 | FF3: =+WEEKDAY(FF4,1) -> 2 | FG3: =+WEEKDAY(FG4,1) -> 3 | FH3: =+WEEKDAY(FH4,1) -> 4 | FI3: =+WEEKDAY(FI4,1) -> 5 | FJ3: =+WEEKDAY(FJ4,1) -> 6 | FK3: =+WEEKDAY(FK4,1) -> 7 | FL3: =+WEEKDAY(FL4,1) -> 1 | ... GI3: =+WEEKDAY(GI4,1) -> 3 | GK3: =+WEEKDAY(GK4,1) -> 4 | GL3: =+WEEKDAY(GL4,1) -> 5 | GM3: =+WEEKDAY(GM4,1) -> 6 | GN3: =+WEEKDAY(GN4,1) -> 7 | GO3: =+WEEKDAY(GO4,1) -> 1 | GP3: =+WEEKDAY(GP4,1) -> 2 | GQ3: =+WEEKDAY(GQ4,1) -> 3 | GR3: =+WEEKDAY(GR4,1) -> 4 | ... HO3: =+WEEKDAY(HO4,1) -> 6 | HQ3: =+WEEKDAY(HQ4,1) -> 7 | HR3: =+WEEKDAY(HR4,1) -> 1 | HS3: =+WEEKDAY(HS4,1) -> 2 | HT3: =+WEEKDAY(HT4,1) -> 3 | HU3: =+WEEKDAY(HU4,1) -> 4 | HV3: =+WEEKDAY(HV4,1) -> 5 | HW3: =+WEEKDAY(HW4,1) -> 6 | HX3: =+WEEKDAY(HX4,1) -> 7 | ... IT3: =+WEEKDAY(IT4,1) -> 1 | IV3: =+WEEKDAY(IV4,1) -> 2 | IW3: =+WEEKDAY(IW4,1) -> 3 | IX3: =+WEEKDAY(IX4,1) -> 4 | IY3: =+WEEKDAY(IY4,1) -> 5 | IZ3: =+WEEKDAY(IZ4,1) -> 6 | JA3: =+WEEKDAY(JA4,1) -> 7 | JB3: =+WEEKDAY(JB4,1) -> 1 | JC3: =+WEEKDAY(JC4,1) -> 2 | ... JZ3: =+WEEKDAY(JZ4,1) -> 4 | KB3: =+WEEKDAY(KB4,1) -> 5 | KC3: =+WEEKDAY(KC4,1) -> 6 | KD3: =+WEEKDAY(KD4,1) -> 7 | KE3: =+WEEKDAY(KE4,1) -> 1 | KF3: =+WEEKDAY(KF4,1) -> 2 | KG3: =+WEEKDAY(KG4,1) -> 3 | KH3: =+WEEKDAY(KH4,1) -> 4 | KI3: =+WEEKDAY(KI4,1) -> 5 | ... LE3: =+WEEKDAY(LE4,1) -> 6 | LG3: =+WEEKDAY(LG4,1) -> 7 | LH3: =+WEEKDAY(LH4,1) -> 1 | LI3: =+WEEKDAY(LI4,1) -> 2 | LJ3: =+WEEKDAY(LJ4,1) -> 3 | LK3: =+WEEKDAY(LK4,1) -> 4 | LL3: =+WEEKDAY(LL4,1) -> 5 | LM3: =+WEEKDAY(LM4,1) -> 6 | LN3: =+WEEKDAY(LN4,1) -> 7 | ... MK3: =+WEEKDAY(MK4,1) -> 2 | MM3: =+WEEKDAY(MM4,1) -> 3 | MN3: =+WEEKDAY(MN4,1) -> 4 | MO3: =+WEEKDAY(MO4,1) -> 5 | MP3: =+WEEKDAY(MP4,1) -> 6 | MQ3: =+WEEKDAY(MQ4,1) -> 7 | MR3: =+WEEKDAY(MR4,1) -> 1 | MS3: =+WEEKDAY(MS4,1) -> 2 | MT3: =+WEEKDAY(MT4,1) -> 3 | ... NQ3: =+WEEKDAY(NQ4,1) -> 5 | NS3: =+WEEKDAY(NS4,1) -> 6 | NT3: =+WEEKDAY(NT4,1) -> 7 | NU3: =+WEEKDAY(NU4,1) -> 1 | NV3: =+WEEKDAY(NV4,1) -> 2 | NW3: =+WEEKDAY(NW4,1) -> 3 | NX3: =+WEEKDAY(NX4,1) -> 4 | NY3: =+WEEKDAY(NY4,1) -> 5 | NZ3: =+WEEKDAY(NZ4,1) -> 6 | ... OT3: =+WEEKDAY(OT4,1) -> 5 | OV3: =+WEEKDAY(OV4,1) -> 6 | OW3: =+WEEKDAY(OW4,1) -> 7 | OX3: =+WEEKDAY(OX4,1) -> 1 | OY3: =+WEEKDAY(OY4,1) -> 2 | OZ3: =+WEEKDAY(OZ4,1) -> 3 | PA3: =+WEEKDAY(PA4,1) -> 4 | PB3: =+WEEKDAY(PB4,1) -> 5 | PC3: =+WEEKDAY(PC4,1) -> 6 | ... PZ3: =+WEEKDAY(PZ4,1) -> 1 | QB3: =+WEEKDAY(QB4,1) -> 2 | QC3: =+WEEKDAY(QC4,1) -> 3 | QD3: =+WEEKDAY(QD4,1) -> 4 | QE3: =+WEEKDAY(QE4,1) -> 5 | QF3: =+WEEKDAY(QF4,1) -> 6 | QG3: =+WEEKDAY(QG4,1) -> 7 | QH3: =+WEEKDAY(QH4,1) -> 1 | QI3: =+WEEKDAY(QI4,1) -> 2 | ... RE3: =+WEEKDAY(RE4,1) -> 3 | RG3: =+WEEKDAY(RG4,1) -> 4 | RH3: =+WEEKDAY(RH4,1) -> 5 | RI3: =+WEEKDAY(RI4,1) -> 6 | RJ3: =+WEEKDAY(RJ4,1) -> 7 | RK3: =+WEEKDAY(RK4,1) -> 1 | RL3: =+WEEKDAY(RL4,1) -> 2 | RM3: =+WEEKDAY(RM4,1) -> 3 | RN3: =+WEEKDAY(RN4,1) -> 4 | ... SK3: =+WEEKDAY(SK4,1) -> 6 | SM3: =+WEEKDAY(SM4,1) -> 7 | SN3: =+WEEKDAY(SN4,1) -> 1 | SO3: =+WEEKDAY(SO4,1) -> 2 | SP3: =+WEEKDAY(SP4,1) -> 3 | SQ3: =+WEEKDAY(SQ4,1) -> 4 | SR3: =+WEEKDAY(SR4,1) -> 5 | SS3: =+WEEKDAY(SS4,1) -> 6 | ST3: =+WEEKDAY(ST4,1) -> 7 | ... TP3: =+WEEKDAY(TP4,1) -> 1 | TR3: =+WEEKDAY(TR4,1) -> 2 | TS3: =+WEEKDAY(TS4,1) -> 3 | TT3: =+WEEKDAY(TT4,1) -> 4 | TU3: =+WEEKDAY(TU4,1) -> 5 | TV3: =+WEEKDAY(TV4,1) -> 6 | TW3: =+WEEKDAY(TW4,1) -> 7 | TX3: =+WEEKDAY(TX4,1) -> 1 | TY3: =+WEEKDAY(TY4,1) -> 2 | ... UV3: =+WEEKDAY(UV4,1) -> 4 | UX3: =+WEEKDAY(UX4,1) -> 5 | UY3: =+WEEKDAY(UY4,1) -> 6 | UZ3: =+WEEKDAY(UZ4,1) -> 7 | VA3: =+WEEKDAY(VA4,1) -> 1 | VB3: =+WEEKDAY(VB4,1) -> 2 | VC3: =+WEEKDAY(VC4,1) -> 3 | VD3: =+WEEKDAY(VD4,1) -> 4 | VE3: =+WEEKDAY(VE4,1) -> 5 | ... WB3: =+WEEKDAY(WB4,1) -> 7
B4: FLUXO DE CAIXA | C4: 42947 | D4: =+C4+1 -> 42948 | E4: =+D4+1 -> 42949 | F4: =+E4+1 -> 42950 | G4: =+F4+1 -> 42951 | H4: =+G4+1 -> 42952 | I4: =+H4+1 -> 42953 | J4: =+I4+1 -> 42954 | K4: =+J4+1 -> 42955 | ... AG4: =+AF4+1 -> 42977 | AH4: ABRIL | AI4: =+AG4+1 -> 42978 | AJ4: =+AI4+1 -> 42979 | AK4: =+AJ4+1 -> 42980 | AL4: =+AK4+1 -> 42981 | AM4: =+AL4+1 -> 42982 | AN4: =+AM4+1 -> 42983 | AO4: =+AN4+1 -> 42984 | AP4: =+AO4+1 -> 42985 | AQ4: =+AP4+1 -> 42986 | ... BM4: =+BL4+1 -> 43008 | BN4: MARÇO | BO4: =+BM4+1 -> 43009 | BP4: =+BO4+1 -> 43010 | BQ4: =+BP4+1 -> 43011 | BR4: =+BQ4+1 -> 43012 | BS4: =+BR4+1 -> 43013 | BT4: =+BS4+1 -> 43014 | BU4: =+BT4+1 -> 43015 | BV4: =+BU4+1 -> 43016 | BW4: =+BV4+1 -> 43017 | ... CR4: =+CQ4+1 -> 43038 | CS4: ABRIL | CT4: =+CR4+1 -> 43039 | CU4: =+CT4+1 -> 43040 | CV4: =+CU4+1 -> 43041 | CW4: =+CV4+1 -> 43042 | CX4: =+CW4+1 -> 43043 | CY4: =+CX4+1 -> 43044 | CZ4: =+CY4+1 -> 43045 | DA4: =+CZ4+1 -> 43046 | DB4: =+DA4+1 -> 43047 | ... DX4: =+DW4+1 -> 43069 | DY4: MAIO | DZ4: =+DX4+1 -> 43070 | EA4: =+DZ4+1 -> 43071 | EB4: =+EA4+1 -> 43072 | EC4: =+EB4+1 -> 43073 | ED4: =+EC4+1 -> 43074 | EE4: =+ED4+1 -> 43075 | EF4: =+EE4+1 -> 43076 | EG4: =+EF4+1 -> 43077 | EH4: =+EG4+1 -> 43078 | ... FC4: =+FB4+1 -> 43099 | FD4: JUNHO | FE4: =+FC4+1 -> 43100 | FF4: =+FE4+1 -> 43101 | FG4: =+FF4+1 -> 43102 | FH4: =+FG4+1 -> 43103 | FI4: =+FH4+1 -> 43104 | FJ4: =+FI4+1 -> 43105 | FK4: =+FJ4+1 -> 43106 | FL4: =+FK4+1 -> 43107 | FM4: =+FL4+1 -> 43108 | ... GI4: =+GH4+1 -> 43130 | GJ4: JULHO | GK4: =+GI4+1 -> 43131 | GL4: =+GK4+1 -> 43132 | GM4: =+GL4+1 -> 43133 | GN4: =+GM4+1 -> 43134 | GO4: =+GN4+1 -> 43135 | GP4: =+GO4+1 -> 43136 | GQ4: =+GP4+1 -> 43137 | GR4: =+GQ4+1 -> 43138 | GS4: =+GR4+1 -> 43139 | ... HO4: =+HN4+1 -> 43161 | HP4: AGOSTO | HQ4: =+HO4+1 -> 43162 | HR4: =+HQ4+1 -> 43163 | HS4: =+HR4+1 -> 43164 | HT4: =+HS4+1 -> 43165 | HU4: =+HT4+1 -> 43166 | HV4: =+HU4+1 -> 43167 | HW4: =+HV4+1 -> 43168 | HX4: =+HW4+1 -> 43169 | HY4: =+HX4+1 -> 43170 | ... IT4: =+IS4+1 -> 43191 | IU4: SETEMBRO | IV4: =+IT4+1 -> 43192 | IW4: =+IV4+1 -> 43193 | IX4: =+IW4+1 -> 43194 | IY4: =+IX4+1 -> 43195 | IZ4: =+IY4+1 -> 43196 | JA4: =+IZ4+1 -> 43197 | JB4: =+JA4+1 -> 43198 | JC4: =+JB4+1 -> 43199 | JD4: =+JC4+1 -> 43200 | ... JZ4: =+JY4+1 -> 43222 | KA4: OUTUBRO | KB4: =+JZ4+1 -> 43223 | KC4: =+KB4+1 -> 43224 | KD4: =+KC4+1 -> 43225 | KE4: =+KD4+1 -> 43226 | KF4: =+KE4+1 -> 43227 | KG4: =+KF4+1 -> 43228 | KH4: =+KG4+1 -> 43229 | KI4: =+KH4+1 -> 43230 | KJ4: =+KI4+1 -> 43231 | ... LE4: =+LD4+1 -> 43252 | LF4: NOVEMBRO | LG4: =+LE4+1 -> 43253 | LH4: =+LG4+1 -> 43254 | LI4: =+LH4+1 -> 43255 | LJ4: =+LI4+1 -> 43256 | LK4: =+LJ4+1 -> 43257 | LL4: =+LK4+1 -> 43258 | LM4: =+LL4+1 -> 43259 | LN4: =+LM4+1 -> 43260 | LO4: =+LN4+1 -> 43261 | ... MK4: =+MJ4+1 -> 43283 | ML4: DEZEMBRO | MM4: =+MK4+1 -> 43284 | MN4: =+MM4+1 -> 43285 | MO4: =+MN4+1 -> 43286 | MP4: =+MO4+1 -> 43287 | MQ4: =+MP4+1 -> 43288 | MR4: =+MQ4+1 -> 43289 | MS4: =+MR4+1 -> 43290 | MT4: =+MS4+1 -> 43291 | MU4: =+MT4+1 -> 43292 | ... NQ4: =+NP4+1 -> 43314 | NR4: JANEIRO | NS4: =+NQ4+1 -> 43315 | NT4: =+NS4+1 -> 43316 | NU4: =+NT4+1 -> 43317 | NV4: =+NU4+1 -> 43318 | NW4: =+NV4+1 -> 43319 | NX4: =+NW4+1 -> 43320 | NY4: =+NX4+1 -> 43321 | NZ4: =+NY4+1 -> 43322 | OA4: =+NZ4+1 -> 43323 | ... OT4: =+OS4+1 -> 43342 | OU4: FEVEREIRO | OV4: =+OT4+1 -> 43343 | OW4: =+OV4+1 -> 43344 | OX4: =+OW4+1 -> 43345 | OY4: =+OX4+1 -> 43346 | OZ4: =+OY4+1 -> 43347 | PA4: =+OZ4+1 -> 43348 | PB4: =+PA4+1 -> 43349 | PC4: =+PB4+1 -> 43350 | PD4: =+PC4+1 -> 43351 | ... PZ4: =+PY4+1 -> 43373 | QA4: MARÇO | QB4: =+PZ4+1 -> 43374 | QC4: =+QB4+1 -> 43375 | QD4: =+QC4+1 -> 43376 | QE4: =+QD4+1 -> 43377 | QF4: =+QE4+1 -> 43378 | QG4: =+QF4+1 -> 43379 | QH4: =+QG4+1 -> 43380 | QI4: =+QH4+1 -> 43381 | QJ4: =+QI4+1 -> 43382 | ... RE4: =+RD4+1 -> 43403 | RF4: ABRIL | RG4: =+RE4+1 -> 43404 | RH4: =+RG4+1 -> 43405 | RI4: =+RH4+1 -> 43406 | RJ4: =+RI4+1 -> 43407 | RK4: =+RJ4+1 -> 43408 | RL4: =+RK4+1 -> 43409 | RM4: =+RL4+1 -> 43410 | RN4: =+RM4+1 -> 43411 | RO4: =+RN4+1 -> 43412 | ... SK4: =+SJ4+1 -> 43434 | SL4: JUNHO | SM4: =+SK4+1 -> 43435 | SN4: =+SM4+1 -> 43436 | SO4: =+SN4+1 -> 43437 | SP4: =+SO4+1 -> 43438 | SQ4: =+SP4+1 -> 43439 | SR4: =+SQ4+1 -> 43440 | SS4: =+SR4+1 -> 43441 | ST4: =+SS4+1 -> 43442 | SU4: =+ST4+1 -> 43443 | ... TP4: =+TO4+1 -> 43464 | TQ4: JUNHO | TR4: =+TP4+1 -> 43465 | TS4: =+TR4+1 -> 43466 | TT4: =+TS4+1 -> 43467 | TU4: =+TT4+1 -> 43468 | TV4: =+TU4+1 -> 43469 | TW4: =+TV4+1 -> 43470 | TX4: =+TW4+1 -> 43471 | TY4: =+TX4+1 -> 43472 | TZ4: =+TY4+1 -> 43473 | ... UV4: =+UU4+1 -> 43495 | UW4: JULHO | UX4: =+UV4+1 -> 43496 | UY4: =+UX4+1 -> 43497 | UZ4: =+UY4+1 -> 43498 | VA4: =+UZ4+1 -> 43499 | VB4: =+VA4+1 -> 43500 | VC4: =+VB4+1 -> 43501 | VD4: =+VC4+1 -> 43502 | VE4: =+VD4+1 -> 43503 | VF4: =+VE4+1 -> 43504 | ... WB4: =+WA4+1 -> 43526 | WC4: AGOSTO
B5: PROJEÇÃO DO LVD (COMERCIAL) | D5: 93636.4 | E5: 0 | F5: 48940.172 | G5: 48940.172 | H5: 48940.172 | I5: 80606.825 | J5: 80606.825 | K5: 3636.4 | L5: 0 | M5: 48940.172 | N5: 48940.172 | O5: 48940.172 | P5: 80606.825 | Q5: 0 | R5: 0 | S5: 0 | T5: 48940.172 | U5: 48940.172 | V5: 48940.172 | W5: 80606.825 | X5: 0 | Y5: 3636.4 | Z5: 33637.105 | AA5: 48940.172 | AB5: 48940.172 | AC5: 48940.172 | AD5: 80606.825 | AE5: 80606.825 | AH5: =+SUM(D5:AE5) -> 1205469.3 | AI5: 0 | AJ5: 0 | AK5: =+F5 -> 48940.172 | AL5: =+G5 -> 48940.172 | AM5: =+H5 -> 48940.172 | AN5: =+I5 -> 80606.825 | AO5: =+J5 -> 80606.825 | AP5: =+K5 -> 3636.4 | AQ5: =+L5 -> 0 | AR5: =+M5 -> 48940.172 | ... BI5: =+AD5 -> 80606.825 | BJ5: =+J5 -> 80606.825 | BK5: =+K5 -> 3636.4 | BL5: =+L5 -> 0 | BM5: =+M5 -> 48940.172 | BN5: =+SUM(AI5:BM5) -> 1164409.5 | BO5: =+AL5 -> 48940.172 | BP5: =+AM5 -> 48940.172 | BQ5: =+AN5 -> 80606.825 | BR5: =+AO5 -> 80606.825 | BS5: =+AP5 -> 3636.4 | BT5: =+AQ5 -> 0 | BU5: =+AR5 -> 48940.172 | BV5: =+AS5 -> 48940.172 | ... CP5: =+BM5 -> 48940.172 | CQ5: =+CJ5 -> 48940.172 | CR5: =+CK5 -> 48940.172 | CS5: =SUM(BO5:CR5) -> 1213349.7 | CT5: =+BQ5 -> 80606.825 | CU5: =+BR5 -> 80606.825 | CV5: =+BS5 -> 3636.4 | CW5: =+BT5 -> 0 | CX5: =+BU5 -> 48940.172 | CY5: =+BV5 -> 48940.172 | CZ5: =+BW5 -> 48940.172 | DA5: =+BX5 -> 80606.825 | ... DT5: =+CQ5 -> 48940.172 | DU5: =+BW5 -> 48940.172 | DV5: =+BX5 -> 80606.825 | DW5: =+BY5 -> 0 | DX5: =+BZ5 -> 0 | DY5: =+SUM(CT5:DX5) -> 1196076.1 | DZ5: =+CW5 -> 0 | EA5: =+CX5 -> 48940.172 | EB5: =+CY5 -> 48940.172 | EC5: =+CZ5 -> 48940.172 | ED5: =+DA5 -> 80606.825 | EE5: =+DB5 -> 0 | EF5: =+DC5 -> 0 | EG5: =+DD5 -> 0 | ... EZ5: =+DW5 -> 0 | FA5: =+DC5 -> 0 | FB5: =+DD5 -> 0 | FC5: =+DE5 -> 48940.172 | FD5: =+SUM(DZ5:FC5) -> 1080166.3 | FE5: =+EC5 -> 48940.172 | FF5: =+ED5 -> 80606.825 | FG5: =+EE5 -> 0 | FH5: =+EF5 -> 0 | FI5: =+EG5 -> 0 | FJ5: =+EH5 -> 48940.172 | FK5: =+EI5 -> 48940.172 | FL5: =+EJ5 -> 48940.172 | ... GE5: =+FC5 -> 48940.172 | GF5: =+EI5 -> 48940.172 | GG5: =+EJ5 -> 48940.172 | GH5: =+EK5 -> 80606.825 | GI5: =+EL5 -> 0 | GJ5: =+SUM(FE5:GI5) -> 1160773.1 | GK5: =+FH5 -> 0 | GL5: =+FI5 -> 0 | GM5: =+FJ5 -> 48940.172 | GN5: =+FK5 -> 48940.172 | GO5: =+FL5 -> 48940.172 | GP5: =+FM5 -> 80606.825 | GQ5: =+FN5 -> 0 | GR5: =+FO5 -> 3636.4 | ... HK5: =+GH5 -> 80606.825 | HL5: =+FN5 -> 0 | HM5: =+FO5 -> 3636.4 | HN5: =+FP5 -> 33637.105 | HO5: =+FQ5 -> 48940.172 | HP5: =+SUM(GK5:HO5) -> 1117439.8 | HQ5: =+GN5 -> 48940.172 | HR5: =+GO5 -> 48940.172 | HS5: =+GP5 -> 80606.825 | HT5: =+GQ5 -> 0 | HU5: =+GR5 -> 3636.4 | HV5: =+GS5 -> 33637.105 | HW5: =+GT5 -> 48940.172 | HX5: =+GU5 -> 48940.172 | ... IQ5: =+HN5 -> 33637.105 | IR5: =+GT5 -> 48940.172 | IS5: =+GU5 -> 48940.172 | IT5: =+GV5 -> 48940.172 | IU5: =+SUM(HQ5:IT5) -> 1166379.9 | IV5: =+HT5 -> 0 | IW5: =+HU5 -> 3636.4 | IX5: =+HV5 -> 33637.105 | IY5: =+HW5 -> 48940.172 | IZ5: =+HX5 -> 48940.172 | JA5: =+HY5 -> 48940.172 | JB5: =+HZ5 -> 80606.825 | JC5: =+IA5 -> 80606.825 | ... JV5: =+IT5 -> 48940.172 | JW5: =+HZ5 -> 80606.825 | JX5: =+IA5 -> 80606.825 | JY5: =+IB5 -> 3636.4 | JZ5: =+IC5 -> 0 | KA5: =+SUM(IV5:JZ5) -> 1152742.8 | KB5: =+IY5 -> 48940.172 | KC5: =+IZ5 -> 48940.172 | KD5: =+JA5 -> 48940.172 | KE5: =+JB5 -> 80606.825 | KF5: =+JC5 -> 80606.825 | KG5: =+JD5 -> 3636.4 | KH5: =+JE5 -> 0 | KI5: =+JF5 -> 48940.172 | ... LB5: =+JY5 -> 3636.4 | LC5: =+JE5 -> 0 | LD5: =+JF5 -> 48940.172 | LE5: =+JG5 -> 48940.172 | LF5: =+SUM(KB5:LE5) -> 1213349.7 | LG5: =+KE5 -> 80606.825 | LH5: =+KF5 -> 80606.825 | LI5: =+KG5 -> 3636.4 | LJ5: =+KH5 -> 0 | LK5: =+KI5 -> 48940.172 | LL5: =+KJ5 -> 48940.172 | LM5: =+KK5 -> 48940.172 | LN5: =+KL5 -> 80606.825 | ... MG5: =+LE5 -> 48940.172 | MH5: =+KK5 -> 48940.172 | MI5: =+KL5 -> 80606.825 | MJ5: =+KM5 -> 0 | MK5: =+KN5 -> 0 | ML5: =+SUM(LG5:MK5) -> 1196076.1 | MM5: =+LJ5 -> 0 | MN5: =+LK5 -> 48940.172 | MO5: =+LL5 -> 48940.172 | MP5: =+LM5 -> 48940.172 | MQ5: =+LN5 -> 80606.825 | MR5: =+LO5 -> 0 | MS5: =+LP5 -> 0 | MT5: =+LQ5 -> 0 | ... NM5: =+MJ5 -> 0 | NN5: =+LP5 -> 0 | NO5: =+LQ5 -> 0 | NP5: =+LR5 -> 48940.172 | NQ5: =+LS5 -> 48940.172 | NR5: =+SUM(MM5:NQ5) -> 1129106.4 | NS5: =+MP5 -> 48940.172 | NT5: =+MQ5 -> 80606.825 | NU5: =+MR5 -> 0 | NV5: =+MS5 -> 0 | NW5: =+MT5 -> 0 | NX5: =+MU5 -> 48940.172 | NY5: =+MV5 -> 48940.172 | NZ5: =+MW5 -> 48940.172 | ... OS5: =+NP5 -> 48940.172 | OT5: =+MV5 -> 48940.172 | OU5: =+SUM(NS5:OT5) -> 1031226.1 | OV5: =+NV5 -> 0 | OW5: =+NW5 -> 0 | OX5: =+NX5 -> 48940.172 | OY5: =+NY5 -> 48940.172 | OZ5: =+NZ5 -> 48940.172 | PA5: =+OA5 -> 80606.825 | PB5: =+OB5 -> 0 | PC5: =+OC5 -> 3636.4 | ... PV5: =+OV5 -> 0 | PW5: =+OB5 -> 0 | PX5: =+OC5 -> 3636.4 | PY5: =+OD5 -> 33637.105 | PZ5: =+OE5 -> 48940.172 | QA5: =+SUM(OV5:PZ5) -> 2019118.9 | QB5: =+OY5 -> 48940.172 | QC5: =+OZ5 -> 48940.172 | QD5: =+PA5 -> 80606.825 | QE5: =+PB5 -> 0 | QF5: =+PC5 -> 3636.4 | QG5: =+PD5 -> 33637.105 | QH5: =+PE5 -> 48940.172 | QI5: =+PF5 -> 48940.172 | ... RB5: =+PY5 -> 33637.105 | RC5: =+PE5 -> 48940.172 | RD5: =+PF5 -> 48940.172 | RE5: =+PG5 -> 48940.172 | RF5: =+SUM(QB5:RE5) -> 2068059 | RG5: =+QE5 -> 0 | RH5: =+QF5 -> 3636.4 | RI5: =+QG5 -> 33637.105 | RJ5: =+QH5 -> 48940.172 | RK5: =+QI5 -> 48940.172 | RL5: =+QJ5 -> 48940.172 | RM5: =+QK5 -> 80606.825 | RN5: =+QL5 -> 80606.825 | ... SG5: =+RE5 -> 48940.172 | SH5: =+QK5 -> 80606.825 | SI5: =+QL5 -> 80606.825 | SJ5: =+QM5 -> 3636.4 | SK5: =+QN5 -> 0 | SL5: =+SUM(RG5:SK5) -> 2054421.9 | SM5: =+RJ5 -> 48940.172 | SN5: =+RK5 -> 48940.172 | SO5: =+RL5 -> 48940.172 | SP5: =+RM5 -> 80606.825 | SQ5: =+RN5 -> 80606.825 | SR5: =+RO5 -> 3636.4 | SS5: =+RP5 -> 0 | ST5: =+RQ5 -> 48940.172 | ... TM5: =+SJ5 -> 3636.4 | TN5: =+RP5 -> 0 | TO5: =+RQ5 -> 48940.172 | TP5: =+RR5 -> 48940.172 | TQ5: =+SUM(SM5:TP5) -> 2115028.8 | TR5: =+SP5 -> 80606.825 | TS5: =+SQ5 -> 80606.825 | TT5: =+SR5 -> 3636.4 | TU5: =+SS5 -> 0 | TV5: =+ST5 -> 48940.172 | TW5: =+SU5 -> 48940.172 | TX5: =+SV5 -> 48940.172 | TY5: =+SW5 -> 80606.825 | ... UR5: =+TP5 -> 48940.172 | US5: =+SV5 -> 48940.172 | UT5: =+SW5 -> 80606.825 | UU5: =+SX5 -> 0 | UV5: =+SY5 -> 0 | UW5: =+SUM(TR5:UV5) -> 2097755.2 | UX5: =+TU5 -> 0 | UY5: =+TV5 -> 48940.172 | UZ5: =+TW5 -> 48940.172 | VA5: =+TX5 -> 48940.172 | VB5: =+TY5 -> 80606.825 | VC5: =+TZ5 -> 0 | VD5: =+UA5 -> 0 | VE5: =+UB5 -> 0 | ... VX5: =+UU5 -> 0 | VY5: =+UA5 -> 0 | VZ5: =+UB5 -> 0 | WA5: =+UC5 -> 48940.172 | WB5: =+UD5 -> 48940.172 | WC5: =+SUM(UX5:WB5) -> 2030785.5
B6: RECEITA BRUTA PROJETADA | D6: 0 | E6: 0 | F6: =F5 -> 48940.172 | G6: =G5 -> 48940.172 | H6: =H5 -> 48940.172 | I6: =I5 -> 80606.825 | J6: =J5 -> 80606.825 | K6: =K5 -> 3636.4 | L6: =L5 -> 0 | M6: =M5 -> 48940.172 | ... AE6: =AE5 -> 80606.825 | AH6: =+SUM(D6:AE6) -> 1111832.9 | AI6: =AI5 -> 0 | AJ6: =AJ5 -> 0 | AK6: =AK5 -> 48940.172 | AL6: =AL5 -> 48940.172 | AM6: =AM5 -> 48940.172 | AN6: =AN5 -> 80606.825 | AO6: =AO5 -> 80606.825 | AP6: =AP5 -> 3636.4 | ... BM6: =BM5 -> 48940.172 | BN6: =+SUM(AI6:BM6) -> 1164409.5 | BO6: =BO5 -> 48940.172 | BP6: =BP5 -> 48940.172 | BQ6: =BQ5 -> 80606.825 | BR6: =BR5 -> 80606.825 | BS6: =BS5 -> 3636.4 | BT6: =BT5 -> 0 | BU6: =BU5 -> 48940.172 | BV6: =BV5 -> 48940.172 | ... CR6: =CR5 -> 48940.172 | CS6: =SUM(BO6:CR6) -> 1213349.7 | CT6: =CT5 -> 80606.825 | CU6: =CU5 -> 80606.825 | CV6: =CV5 -> 3636.4 | CW6: =CW5 -> 0 | CX6: =CX5 -> 48940.172 | CY6: =CY5 -> 48940.172 | CZ6: =CZ5 -> 48940.172 | DA6: =DA5 -> 80606.825 | ... DX6: =DX5 -> 0 | DY6: =+SUM(CT6:DX6) -> 1196076.1 | DZ6: =DZ5 -> 0 | EA6: =EA5 -> 48940.172 | EB6: =EB5 -> 48940.172 | EC6: =EC5 -> 48940.172 | ED6: =ED5 -> 80606.825 | EE6: =EE5 -> 0 | EF6: =EF5 -> 0 | EG6: =EG5 -> 0 | ... FC6: =FC5 -> 48940.172 | FD6: =+SUM(DZ6:FC6) -> 1080166.3 | FE6: =FE5 -> 48940.172 | FF6: =FF5 -> 80606.825 | FG6: =FG5 -> 0 | FH6: =FH5 -> 0 | FI6: =FI5 -> 0 | FJ6: =FJ5 -> 48940.172 | FK6: =FK5 -> 48940.172 | FL6: =FL5 -> 48940.172 | ... GI6: =GI5 -> 0 | GJ6: =+SUM(FE6:GI6) -> 1160773.1 | GK6: =GK5 -> 0 | GL6: =GL5 -> 0 | GM6: =GM5 -> 48940.172 | GN6: =GN5 -> 48940.172 | GO6: =GO5 -> 48940.172 | GP6: =GP5 -> 80606.825 | GQ6: =GQ5 -> 0 | GR6: =GR5 -> 3636.4 | ... HO6: =HO5 -> 48940.172 | HP6: =+SUM(GK6:HO6) -> 1117439.8 | HQ6: =HQ5 -> 48940.172 | HR6: =HR5 -> 48940.172 | HS6: =HS5 -> 80606.825 | HT6: =HT5 -> 0 | HU6: =HU5 -> 3636.4 | HV6: =HV5 -> 33637.105 | HW6: =HW5 -> 48940.172 | HX6: =HX5 -> 48940.172 | ... IT6: =IT5 -> 48940.172 | IU6: =+SUM(HQ6:IT6) -> 1166379.9 | IV6: =IV5 -> 0 | IW6: =IW5 -> 3636.4 | IX6: =IX5 -> 33637.105 | IY6: =IY5 -> 48940.172 | IZ6: =IZ5 -> 48940.172 | JA6: =JA5 -> 48940.172 | JB6: =JB5 -> 80606.825 | JC6: =JC5 -> 80606.825 | ... JZ6: =JZ5 -> 0 | KA6: =+SUM(IV6:JZ6) -> 1152742.8 | KB6: =KB5 -> 48940.172 | KC6: =KC5 -> 48940.172 | KD6: =KD5 -> 48940.172 | KE6: =KE5 -> 80606.825 | KF6: =KF5 -> 80606.825 | KG6: =KG5 -> 3636.4 | KH6: =KH5 -> 0 | KI6: =KI5 -> 48940.172 | ... LE6: =LE5 -> 48940.172 | LF6: =+SUM(KB6:LE6) -> 1213349.7 | LG6: =LG5 -> 80606.825 | LH6: =LH5 -> 80606.825 | LI6: =LI5 -> 3636.4 | LJ6: =LJ5 -> 0 | LK6: =LK5 -> 48940.172 | LL6: =LL5 -> 48940.172 | LM6: =LM5 -> 48940.172 | LN6: =LN5 -> 80606.825 | ... MK6: =MK5 -> 0 | ML6: =+SUM(LG6:MK6) -> 1196076.1 | MM6: =MM5 -> 0 | MN6: =MN5 -> 48940.172 | MO6: =MO5 -> 48940.172 | MP6: =MP5 -> 48940.172 | MQ6: =MQ5 -> 80606.825 | MR6: =MR5 -> 0 | MS6: =MS5 -> 0 | MT6: =MT5 -> 0 | ... NQ6: =NQ5 -> 48940.172 | NR6: =+SUM(MM6:NQ6) -> 1129106.4 | NS6: =NS5 -> 48940.172 | NT6: =NT5 -> 80606.825 | NU6: =NU5 -> 0 | NV6: =NV5 -> 0 | NW6: =NW5 -> 0 | NX6: =NX5 -> 48940.172 | NY6: =NY5 -> 48940.172 | NZ6: =NZ5 -> 48940.172 | ... OT6: =OT5 -> 48940.172 | OU6: =+SUM(NS6:OT6) -> 1031226.1 | OV6: =OV5 -> 0 | OW6: =OW5 -> 0 | OX6: =OX5 -> 48940.172 | OY6: =OY5 -> 48940.172 | OZ6: =OZ5 -> 48940.172 | PA6: =PA5 -> 80606.825 | PB6: =PB5 -> 0 | PC6: =PC5 -> 3636.4 | ... PZ6: =PZ5 -> 48940.172 | QA6: =+SUM(OV6:PZ6) -> 2019118.9 | QB6: =QB5 -> 48940.172 | QC6: =QC5 -> 48940.172 | QD6: =QD5 -> 80606.825 | QE6: =QE5 -> 0 | QF6: =QF5 -> 3636.4 | QG6: =QG5 -> 33637.105 | QH6: =QH5 -> 48940.172 | QI6: =QI5 -> 48940.172 | ... RE6: =RE5 -> 48940.172 | RF6: =+SUM(QB6:RE6) -> 2068059 | RG6: =RG5 -> 0 | RH6: =RH5 -> 3636.4 | RI6: =RI5 -> 33637.105 | RJ6: =RJ5 -> 48940.172 | RK6: =RK5 -> 48940.172 | RL6: =RL5 -> 48940.172 | RM6: =RM5 -> 80606.825 | RN6: =RN5 -> 80606.825 | ... SK6: =SK5 -> 0 | SL6: =+SUM(RG6:SK6) -> 2054421.9 | SM6: =SM5 -> 48940.172 | SN6: =SN5 -> 48940.172 | SO6: =SO5 -> 48940.172 | SP6: =SP5 -> 80606.825 | SQ6: =SQ5 -> 80606.825 | SR6: =SR5 -> 3636.4 | SS6: =SS5 -> 0 | ST6: =ST5 -> 48940.172 | ... TP6: =TP5 -> 48940.172 | TQ6: =+SUM(SM6:TP6) -> 2115028.8 | TR6: =TR5 -> 80606.825 | TS6: =TS5 -> 80606.825 | TT6: =TT5 -> 3636.4 | TU6: =TU5 -> 0 | TV6: =TV5 -> 48940.172 | TW6: =TW5 -> 48940.172 | TX6: =TX5 -> 48940.172 | TY6: =TY5 -> 80606.825 | ... UV6: =UV5 -> 0 | UW6: =+SUM(TR6:UV6) -> 2097755.2 | UX6: =UX5 -> 0 | UY6: =UY5 -> 48940.172 | UZ6: =UZ5 -> 48940.172 | VA6: =VA5 -> 48940.172 | VB6: =VB5 -> 80606.825 | VC6: =VC5 -> 0 | VD6: =VD5 -> 0 | VE6: =VE5 -> 0 | ... WB6: =WB5 -> 48940.172 | WC6: =+SUM(UX6:WB6) -> 2030785.5
B7: DINHEIRO (D+1) | C7: =+[4]DRE!AC8 -> 0.38580871 | D7: =+D$6*$C7 -> 0 | E7: =+E$6*$C7 -> 0 | F7: =+F$6*$C7 -> 18881.544 | G7: =+G$6*$C7 -> 18881.544 | H7: =+H$6*$C7 -> 18881.544 | I7: =+I$6*$C7 -> 31098.815 | J7: =+J$6*$C7 -> 31098.815 | K7: =+K$6*$C7 -> 1402.9548 | ... AE7: =+AE$6*$C7 -> 31098.815 | AH7: =+SUM(D7:AE7) -> 428954.82 | AI7: =+AI$6*$C7 -> 0 | AJ7: =+AJ$6*$C7 -> 0 | AK7: =+AK$6*$C7 -> 18881.544 | AL7: =+AL$6*$C7 -> 18881.544 | AM7: =+AM$6*$C7 -> 18881.544 | AN7: =+AN$6*$C7 -> 31098.815 | AO7: =+AO$6*$C7 -> 31098.815 | AP7: =+AP$6*$C7 -> 1402.9548 | ... AS7: =+AS$6*$C7 -> 18881.544 | AT7: 0 | AU7: =+AU$6*$C7 -> 31098.815 | AV7: =+AV$6*$C7 -> 0 | AW7: =+AW$6*$C7 -> 0 | AX7: =+AX$6*$C7 -> 0 | AY7: =+AY$6*$C7 -> 18881.544 | AZ7: =+AZ$6*$C7 -> 18881.544 | BA7: 0 | BB7: =+BB$6*$C7 -> 31098.815 | BC7: =+BC$6*$C7 -> 0 | BD7: =+BD$6*$C7 -> 1402.9548 | BE7: =+BE$6*$C7 -> 12977.488 | BF7: =+BF$6*$C7 -> 18881.544 | BG7: =+BG$6*$C7 -> 18881.544 | BH7: 0 | BI7: =+BI$6*$C7 -> 31098.815 | BJ7: =+BJ$6*$C7 -> 31098.815 | BK7: =+BK$6*$C7 -> 1402.9548 | BL7: =+BL$6*$C7 -> 0 | BM7: =+BM$6*$C7 -> 18881.544 | BN7: =+SUM(AI7:BM7) -> 392594.69 | BO7: =+BO$6*$C7 -> 18881.544 | BP7: 0 | BQ7: =+BQ$6*$C7 -> 31098.815 | BR7: =+BR$6*$C7 -> 31098.815 | BS7: =+BS$6*$C7 -> 1402.9548 | BT7: =+BT$6*$C7 -> 0 | BU7: =+BU$6*$C7 -> 18881.544 | BV7: =+BV$6*$C7 -> 18881.544 | BW7: 0 | BX7: =+BX$6*$C7 -> 31098.815 | BY7: =+BY$6*$C7 -> 0 | BZ7: =+BZ$6*$C7 -> 0 | CA7: =+CA$6*$C7 -> 0 | CB7: =+CB$6*$C7 -> 18881.544 | CC7: =+CC$6*$C7 -> 18881.544 | CD7: 0 | CE7: =+CE$6*$C7 -> 31098.815 | CF7: =+CF$6*$C7 -> 0 | CG7: =+CG$6*$C7 -> 1402.9548 | CH7: =+CH$6*$C7 -> 12977.488 | CI7: =+CI$6*$C7 -> 18881.544 | CJ7: =+CJ$6*$C7 -> 18881.544 | CK7: 0 | CL7: =+CL$6*$C7 -> 31098.815 | CM7: =+CM$6*$C7 -> 31098.815 | CN7: =+CN$6*$C7 -> 1402.9548 | CO7: =+CO$6*$C7 -> 0 | CP7: =+CP$6*$C7 -> 18881.544 | CQ7: =+CQ$6*$C7 -> 18881.544 | CR7: 0 | CS7: =SUM(BO7:CR7) -> 373713.14 | CT7: =+CT$6*$C7 -> 31098.815 | CU7: =+CU$6*$C7 -> 31098.815 | CV7: =+CV$6*$C7 -> 1402.9548 | CW7: =+CW$6*$C7 -> 0 | CX7: =+CX$6*$C7 -> 18881.544 | CY7: =+CY$6*$C7 -> 18881.544 | CZ7: =+CZ$6*$C7 -> 18881.544 | DA7: =+DA$6*$C7 -> 31098.815 | ... DD7: =+DD$6*$C7 -> 0 | DE7: 0 | DF7: =+DF$6*$C7 -> 18881.544 | DG7: =+DG$6*$C7 -> 18881.544 | DH7: =+DH$6*$C7 -> 31098.815 | DI7: =+DI$6*$C7 -> 0 | DJ7: =+DJ$6*$C7 -> 1402.9548 | DK7: =+DK$6*$C7 -> 12977.488 | DL7: 0 | DM7: =+DM$6*$C7 -> 18881.544 | DN7: =+DN$6*$C7 -> 18881.544 | DO7: =+DO$6*$C7 -> 31098.815 | DP7: =+DP$6*$C7 -> 31098.815 | DQ7: =+DQ$6*$C7 -> 1402.9548 | DR7: =+DR$6*$C7 -> 0 | DS7: 0 | DT7: =+DT$6*$C7 -> 18881.544 | DU7: =+DU$6*$C7 -> 18881.544 | DV7: =+DV$6*$C7 -> 31098.815 | DW7: =+DW$6*$C7 -> 0 | DX7: =+DX$6*$C7 -> 0 | DY7: =+SUM(CT7:DX7) -> 404811.96 | DZ7: =+DZ$6*$C7 -> 0 | EA7: =+EA$6*$C7 -> 18881.544 | EB7: =+EB$6*$C7 -> 18881.544 | EC7: =+EC$6*$C7 -> 18881.544 | ED7: =+ED$6*$C7 -> 31098.815 | EE7: =+EE$6*$C7 -> 0 | EF7: =+EF$6*$C7 -> 0 | EG7: =+EG$6*$C7 -> 0 | ... EJ7: =+EJ$6*$C7 -> 18881.544 | EK7: 0 | EL7: =+EL$6*$C7 -> 0 | EM7: =+EM$6*$C7 -> 1402.9548 | EN7: =+EN$6*$C7 -> 12977.488 | EO7: =+EO$6*$C7 -> 18881.544 | EP7: =+EP$6*$C7 -> 18881.544 | EQ7: =+EQ$6*$C7 -> 18881.544 | ER7: 0 | ES7: =+ES$6*$C7 -> 31098.815 | ET7: =+ET$6*$C7 -> 1402.9548 | EU7: =+EU$6*$C7 -> 0 | EV7: =+EV$6*$C7 -> 18881.544 | EW7: =+EW$6*$C7 -> 18881.544 | EX7: =+EX$6*$C7 -> 18881.544 | EY7: 0 | EZ7: =+EZ$6*$C7 -> 0 | FA7: =+FA$6*$C7 -> 0 | FB7: =+FB$6*$C7 -> 0 | FC7: =+FC$6*$C7 -> 18881.544 | FD7: =+SUM(DZ7:FC7) -> 323441.11 | FE7: =+FE$6*$C7 -> 18881.544 | FF7: =+FF$6*$C7 -> 31098.815 | FG7: =+FG$6*$C7 -> 0 | FH7: =+FH$6*$C7 -> 0 | FI7: =+FI$6*$C7 -> 0 | FJ7: =+FJ$6*$C7 -> 18881.544 | FK7: =+FK$6*$C7 -> 18881.544 | FL7: =+FL$6*$C7 -> 18881.544 | ... FO7: =+FO$6*$C7 -> 1402.9548 | FP7: 0 | FQ7: =+FQ$6*$C7 -> 18881.544 | FR7: =+FR$6*$C7 -> 18881.544 | FS7: =+FS$6*$C7 -> 18881.544 | FT7: =+FT$6*$C7 -> 31098.815 | FU7: =+FU$6*$C7 -> 31098.815 | FV7: =+FV$6*$C7 -> 1402.9548 | FW7: 0 | FX7: =+FX$6*$C7 -> 18881.544 | FY7: =+FY$6*$C7 -> 18881.544 | FZ7: =+FZ$6*$C7 -> 18881.544 | GA7: =+GA$6*$C7 -> 31098.815 | GB7: =+GB$6*$C7 -> 0 | GC7: =+GC$6*$C7 -> 0 | GD7: 0 | GE7: =+GE$6*$C7 -> 18881.544 | GF7: =+GF$6*$C7 -> 18881.544 | GG7: =+GG$6*$C7 -> 18881.544 | GH7: =+GH$6*$C7 -> 31098.815 | GI7: =+GI$6*$C7 -> 0 | GJ7: =+SUM(FE7:GI7) -> 434858.88 | GK7: =+GK$6*$C7 -> 0 | GL7: =+GL$6*$C7 -> 0 | GM7: =+GM$6*$C7 -> 18881.544 | GN7: =+GN$6*$C7 -> 18881.544 | GO7: =+GO$6*$C7 -> 18881.544 | GP7: =+GP$6*$C7 -> 31098.815 | GQ7: =+GQ$6*$C7 -> 0 | GR7: =+GR$6*$C7 -> 1402.9548 | ... GU7: =+GU$6*$C7 -> 18881.544 | GV7: 0 | GW7: =+GW$6*$C7 -> 31098.815 | GX7: =+GX$6*$C7 -> 31098.815 | GY7: =+GY$6*$C7 -> 1402.9548 | GZ7: =+GZ$6*$C7 -> 0 | HA7: =+HA$6*$C7 -> 18881.544 | HB7: =+HB$6*$C7 -> 18881.544 | HC7: 0 | HD7: =+HD$6*$C7 -> 31098.815 | HE7: =+HE$6*$C7 -> 0 | HF7: =+HF$6*$C7 -> 0 | HG7: =+HG$6*$C7 -> 0 | HH7: =+HH$6*$C7 -> 18881.544 | HI7: =+HI$6*$C7 -> 18881.544 | HJ7: 0 | HK7: =+HK$6*$C7 -> 31098.815 | HL7: =+HL$6*$C7 -> 0 | HM7: =+HM$6*$C7 -> 1402.9548 | HN7: =+HN$6*$C7 -> 12977.488 | HO7: =+HO$6*$C7 -> 18881.544 | HP7: =+SUM(GK7:HO7) -> 374473.36 | HQ7: =+HQ$6*$C7 -> 18881.544 | HR7: =+HR$6*$C7 -> 18881.544 | HS7: =+HS$6*$C7 -> 31098.815 | HT7: =+HT$6*$C7 -> 0 | HU7: =+HU$6*$C7 -> 1402.9548 | HV7: =+HV$6*$C7 -> 12977.488 | HW7: =+HW$6*$C7 -> 18881.544 | HX7: =+HX$6*$C7 -> 18881.544 | ... IA7: =+IA$6*$C7 -> 31098.815 | IB7: 0 | IC7: =+IC$6*$C7 -> 0 | ID7: =+ID$6*$C7 -> 18881.544 | IE7: =+IE$6*$C7 -> 18881.544 | IF7: =+IF$6*$C7 -> 18881.544 | IG7: =+IG$6*$C7 -> 31098.815 | IH7: =+IH$6*$C7 -> 0 | II7: 0 | IJ7: =+IJ$6*$C7 -> 0 | IK7: =+IK$6*$C7 -> 18881.544 | IL7: =+IL$6*$C7 -> 18881.544 | IM7: =+IM$6*$C7 -> 18881.544 | IN7: =+IN$6*$C7 -> 31098.815 | IO7: =+IO$6*$C7 -> 0 | IP7: 0 | IQ7: =+IQ$6*$C7 -> 12977.488 | IR7: =+IR$6*$C7 -> 18881.544 | IS7: =+IS$6*$C7 -> 18881.544 | IT7: =+IT$6*$C7 -> 18881.544 | IU7: =+SUM(HQ7:IT7) -> 447193.63 | IV7: =+IV$6*$C7 -> 0 | IW7: =+IW$6*$C7 -> 1402.9548 | IX7: =+IX$6*$C7 -> 12977.488 | IY7: =+IY$6*$C7 -> 18881.544 | IZ7: =+IZ$6*$C7 -> 18881.544 | JA7: =+JA$6*$C7 -> 18881.544 | JB7: =+JB$6*$C7 -> 31098.815 | JC7: =+JC$6*$C7 -> 31098.815 | ... JF7: =+JF$6*$C7 -> 18881.544 | JG7: 0 | JH7: =+JH$6*$C7 -> 18881.544 | JI7: =+JI$6*$C7 -> 31098.815 | JJ7: =+JJ$6*$C7 -> 0 | JK7: =+JK$6*$C7 -> 0 | JL7: =+JL$6*$C7 -> 0 | JM7: =+JM$6*$C7 -> 18881.544 | JN7: 0 | JO7: =+JO$6*$C7 -> 18881.544 | JP7: =+JP$6*$C7 -> 31098.815 | JQ7: =+JQ$6*$C7 -> 0 | JR7: =+JR$6*$C7 -> 1402.9548 | JS7: =+JS$6*$C7 -> 12977.488 | JT7: =+JT$6*$C7 -> 18881.544 | JU7: 0 | JV7: =+JV$6*$C7 -> 18881.544 | JW7: =+JW$6*$C7 -> 31098.815 | JX7: =+JX$6*$C7 -> 31098.815 | JY7: =+JY$6*$C7 -> 1402.9548 | JZ7: =+JZ$6*$C7 -> 0 | KA7: =+SUM(IV7:JZ7) -> 388093.59 | KB7: =+KB$6*$C7 -> 18881.544 | KC7: =+KC$6*$C7 -> 18881.544 | KD7: =+KD$6*$C7 -> 18881.544 | KE7: =+KE$6*$C7 -> 31098.815 | KF7: =+KF$6*$C7 -> 31098.815 | KG7: =+KG$6*$C7 -> 1402.9548 | KH7: =+KH$6*$C7 -> 0 | KI7: =+KI$6*$C7 -> 18881.544 | ... KL7: =+KL$6*$C7 -> 31098.815 | KM7: 0 | KN7: =+KN$6*$C7 -> 0 | KO7: =+KO$6*$C7 -> 0 | KP7: =+KP$6*$C7 -> 18881.544 | KQ7: =+KQ$6*$C7 -> 18881.544 | KR7: =+KR$6*$C7 -> 18881.544 | KS7: =+KS$6*$C7 -> 31098.815 | KT7: 0 | KU7: =+KU$6*$C7 -> 1402.9548 | KV7: =+KV$6*$C7 -> 12977.488 | KW7: =+KW$6*$C7 -> 18881.544 | KX7: =+KX$6*$C7 -> 18881.544 | KY7: =+KY$6*$C7 -> 18881.544 | KZ7: =+KZ$6*$C7 -> 31098.815 | LA7: 0 | LB7: =+LB$6*$C7 -> 1402.9548 | LC7: =+LC$6*$C7 -> 0 | LD7: =+LD$6*$C7 -> 18881.544 | LE7: =+LE$6*$C7 -> 18881.544 | LF7: =+SUM(KB7:LE7) -> 437022.05 | LG7: =+LG$6*$C7 -> 31098.815 | LH7: =+LH$6*$C7 -> 31098.815 | LI7: =+LI$6*$C7 -> 1402.9548 | LJ7: =+LJ$6*$C7 -> 0 | LK7: =+LK$6*$C7 -> 18881.544 | LL7: =+LL$6*$C7 -> 18881.544 | LM7: =+LM$6*$C7 -> 18881.544 | LN7: =+LN$6*$C7 -> 31098.815 | ... LQ7: =+LQ$6*$C7 -> 0 | LR7: 0 | LS7: =+LS$6*$C7 -> 18881.544 | LT7: =+LT$6*$C7 -> 18881.544 | LU7: =+LU$6*$C7 -> 31098.815 | LV7: =+LV$6*$C7 -> 0 | LW7: =+LW$6*$C7 -> 1402.9548 | LX7: =+LX$6*$C7 -> 12977.488 | LY7: 0 | LZ7: =+LZ$6*$C7 -> 18881.544 | MA7: =+MA$6*$C7 -> 18881.544 | MB7: =+MB$6*$C7 -> 31098.815 | MC7: =+MC$6*$C7 -> 31098.815 | MD7: =+MD$6*$C7 -> 1402.9548 | ME7: =+ME$6*$C7 -> 0 | MF7: 0 | MG7: =+MG$6*$C7 -> 18881.544 | MH7: =+MH$6*$C7 -> 18881.544 | MI7: =+MI$6*$C7 -> 31098.815 | MJ7: =+MJ$6*$C7 -> 0 | MK7: =+MK$6*$C7 -> 0 | ML7: =+SUM(LG7:MK7) -> 404811.96 | MM7: =+MM$6*$C7 -> 0 | MN7: =+MN$6*$C7 -> 18881.544 | MO7: =+MO$6*$C7 -> 18881.544 | MP7: =+MP$6*$C7 -> 18881.544 | MQ7: =+MQ$6*$C7 -> 31098.815 | MR7: =+MR$6*$C7 -> 0 | MS7: =+MS$6*$C7 -> 0 | MT7: =+MT$6*$C7 -> 0 | ... MW7: =+MW$6*$C7 -> 18881.544 | MX7: 0 | MY7: =+MY$6*$C7 -> 0 | MZ7: =+MZ$6*$C7 -> 1402.9548 | NA7: =+NA$6*$C7 -> 12977.488 | NB7: =+NB$6*$C7 -> 18881.544 | NC7: =+NC$6*$C7 -> 18881.544 | ND7: =+ND$6*$C7 -> 18881.544 | NE7: 0 | NF7: =+NF$6*$C7 -> 31098.815 | NG7: =+NG$6*$C7 -> 1402.9548 | NH7: =+NH$6*$C7 -> 0 | NI7: =+NI$6*$C7 -> 18881.544 | NJ7: =+NJ$6*$C7 -> 18881.544 | NK7: =+NK$6*$C7 -> 18881.544 | NL7: 0 | NM7: =+NM$6*$C7 -> 0 | NN7: =+NN$6*$C7 -> 0 | NO7: =+NO$6*$C7 -> 0 | NP7: =+NP$6*$C7 -> 18881.544 | NQ7: =+NQ$6*$C7 -> 18881.544 | NR7: =+SUM(MM7:NQ7) -> 342322.65 | NS7: =+NS$6*$C7 -> 18881.544 | NT7: =+NT$6*$C7 -> 31098.815 | NU7: =+NU$6*$C7 -> 0 | NV7: =+NV$6*$C7 -> 0 | NW7: =+NW$6*$C7 -> 0 | NX7: =+NX$6*$C7 -> 18881.544 | NY7: =+NY$6*$C7 -> 18881.544 | NZ7: =+NZ$6*$C7 -> 18881.544 | ... OC7: =+OC$6*$C7 -> 1402.9548 | OD7: 0 | OE7: =+OE$6*$C7 -> 18881.544 | OF7: =+OF$6*$C7 -> 18881.544 | OG7: =+OG$6*$C7 -> 18881.544 | OH7: =+OH$6*$C7 -> 31098.815 | OI7: =+OI$6*$C7 -> 31098.815 | OJ7: =+OJ$6*$C7 -> 1402.9548 | OK7: 0 | OL7: =+OL$6*$C7 -> 18881.544 | OM7: =+OM$6*$C7 -> 18881.544 | ON7: =+ON$6*$C7 -> 18881.544 | OO7: =+OO$6*$C7 -> 31098.815 | OP7: =+OP$6*$C7 -> 0 | OQ7: =+OQ$6*$C7 -> 0 | OR7: 0 | OS7: =+OS$6*$C7 -> 18881.544 | OT7: =+OT$6*$C7 -> 18881.544 | OU7: =+SUM(NS7:OT7) -> 384878.52 | OV7: =+OV$6*$C7 -> 0 | OW7: =+OW$6*$C7 -> 0 | OX7: =+OX$6*$C7 -> 18881.544 | OY7: =+OY$6*$C7 -> 18881.544 | OZ7: =+OZ$6*$C7 -> 18881.544 | PA7: =+PA$6*$C7 -> 31098.815 | PB7: =+PB$6*$C7 -> 0 | PC7: =+PC$6*$C7 -> 1402.9548 | ... PF7: =+PF$6*$C7 -> 18881.544 | PG7: 0 | PH7: =+PH$6*$C7 -> 31098.815 | PI7: =+PI$6*$C7 -> 31098.815 | PJ7: =+PJ$6*$C7 -> 1402.9548 | PK7: =+PK$6*$C7 -> 0 | PL7: =+PL$6*$C7 -> 18881.544 | PM7: =+PM$6*$C7 -> 18881.544 | PN7: 0 | PO7: =+PO$6*$C7 -> 31098.815 | PP7: =+PP$6*$C7 -> 0 | PQ7: =+PQ$6*$C7 -> 0 | PR7: =+PR$6*$C7 -> 0 | PS7: =+PS$6*$C7 -> 18881.544 | PT7: =+PT$6*$C7 -> 18881.544 | PU7: 0 | PV7: =+PV$6*$C7 -> 0 | PW7: =+PW$6*$C7 -> 0 | PX7: =+PX$6*$C7 -> 1402.9548 | PY7: =+PY$6*$C7 -> 12977.488 | PZ7: =+PZ$6*$C7 -> 18881.544 | QA7: =+SUM(OV7:PZ7) -> 343374.55 | QB7: =+QB$6*$C7 -> 18881.544 | QC7: =+QC$6*$C7 -> 18881.544 | QD7: =+QD$6*$C7 -> 31098.815 | QE7: =+QE$6*$C7 -> 0 | QF7: =+QF$6*$C7 -> 1402.9548 | QG7: =+QG$6*$C7 -> 12977.488 | QH7: =+QH$6*$C7 -> 18881.544 | QI7: =+QI$6*$C7 -> 18881.544 | ... QL7: =+QL$6*$C7 -> 31098.815 | QM7: 0 | QN7: =+QN$6*$C7 -> 0 | QO7: =+QO$6*$C7 -> 18881.544 | QP7: =+QP$6*$C7 -> 18881.544 | QQ7: =+QQ$6*$C7 -> 18881.544 | QR7: =+QR$6*$C7 -> 31098.815 | QS7: =+QS$6*$C7 -> 0 | QT7: 0 | QU7: =+QU$6*$C7 -> 0 | QV7: =+QV$6*$C7 -> 18881.544 | QW7: =+QW$6*$C7 -> 18881.544 | QX7: =+QX$6*$C7 -> 397856.01 | QY7: =+QY$6*$C7 -> 0 | QZ7: =+QZ$6*$C7 -> 0 | RA7: 0 | RB7: =+RB$6*$C7 -> 12977.488 | RC7: =+RC$6*$C7 -> 18881.544 | RD7: =+RD$6*$C7 -> 18881.544 | RE7: =+RE$6*$C7 -> 18881.544 | RF7: =+SUM(QB7:RE7) -> 795069.28 | RG7: =+RG$6*$C7 -> 0 | RH7: =+RH$6*$C7 -> 1402.9548 | RI7: =+RI$6*$C7 -> 12977.488 | RJ7: =+RJ$6*$C7 -> 18881.544 | RK7: =+RK$6*$C7 -> 18881.544 | RL7: =+RL$6*$C7 -> 18881.544 | RM7: =+RM$6*$C7 -> 31098.815 | RN7: =+RN$6*$C7 -> 31098.815 | ... RQ7: =+RQ$6*$C7 -> 18881.544 | RR7: 0 | RS7: =+RS$6*$C7 -> 18881.544 | RT7: =+RT$6*$C7 -> 31098.815 | RU7: =+RU$6*$C7 -> 0 | RV7: =+RV$6*$C7 -> 0 | RW7: =+RW$6*$C7 -> 0 | RX7: =+RX$6*$C7 -> 18881.544 | RY7: 0 | RZ7: =+RZ$6*$C7 -> 397856.01 | SA7: =+SA$6*$C7 -> 0 | SB7: =+SB$6*$C7 -> 0 | SC7: =+SC$6*$C7 -> 1402.9548 | SD7: =+SD$6*$C7 -> 12977.488 | SE7: =+SE$6*$C7 -> 18881.544 | SF7: 0 | SG7: =+SG$6*$C7 -> 18881.544 | SH7: =+SH$6*$C7 -> 31098.815 | SI7: =+SI$6*$C7 -> 31098.815 | SJ7: =+SJ$6*$C7 -> 1402.9548 | SK7: =+SK$6*$C7 -> 0 | SL7: =+SUM(RG7:SK7) -> 735969.23 | SM7: =+SM$6*$C7 -> 18881.544 | SN7: =+SN$6*$C7 -> 18881.544 | SO7: =+SO$6*$C7 -> 18881.544 | SP7: =+SP$6*$C7 -> 31098.815 | SQ7: =+SQ$6*$C7 -> 31098.815 | SR7: =+SR$6*$C7 -> 1402.9548 | SS7: =+SS$6*$C7 -> 0 | ST7: =+ST$6*$C7 -> 18881.544 | ... SW7: =+SW$6*$C7 -> 31098.815 | SX7: 0 | SY7: =+SY$6*$C7 -> 0 | SZ7: =+SZ$6*$C7 -> 0 | TA7: =+TA$6*$C7 -> 18881.544 | TB7: =+TB$6*$C7 -> 18881.544 | TC7: =+TC$6*$C7 -> 397856.01 | TD7: =+TD$6*$C7 -> 0 | TE7: 0 | TF7: =+TF$6*$C7 -> 1402.9548 | TG7: =+TG$6*$C7 -> 12977.488 | TH7: =+TH$6*$C7 -> 18881.544 | TI7: =+TI$6*$C7 -> 18881.544 | TJ7: =+TJ$6*$C7 -> 18881.544 | TK7: =+TK$6*$C7 -> 31098.815 | TL7: 0 | TM7: =+TM$6*$C7 -> 1402.9548 | TN7: =+TN$6*$C7 -> 0 | TO7: =+TO$6*$C7 -> 18881.544 | TP7: =+TP$6*$C7 -> 18881.544 | TQ7: =+SUM(SM7:TP7) -> 784897.7 | TR7: =+TR$6*$C7 -> 31098.815 | TS7: =+TS$6*$C7 -> 31098.815 | TT7: =+TT$6*$C7 -> 1402.9548 | TU7: =+TU$6*$C7 -> 0 | TV7: =+TV$6*$C7 -> 18881.544 | TW7: =+TW$6*$C7 -> 18881.544 | TX7: =+TX$6*$C7 -> 18881.544 | TY7: =+TY$6*$C7 -> 31098.815 | ... UB7: =+UB$6*$C7 -> 0 | UC7: 0 | UD7: =+UD$6*$C7 -> 18881.544 | UE7: =+UE$6*$C7 -> 397856.01 | UF7: =+UF$6*$C7 -> 0 | UG7: =+UG$6*$C7 -> 0 | UH7: =+UH$6*$C7 -> 1402.9548 | UI7: =+UI$6*$C7 -> 12977.488 | UJ7: 0 | UK7: =+UK$6*$C7 -> 18881.544 | UL7: =+UL$6*$C7 -> 18881.544 | UM7: =+UM$6*$C7 -> 31098.815 | UN7: =+UN$6*$C7 -> 31098.815 | UO7: =+UO$6*$C7 -> 1402.9548 | UP7: =+UP$6*$C7 -> 0 | UQ7: 0 | UR7: =+UR$6*$C7 -> 18881.544 | US7: =+US$6*$C7 -> 18881.544 | UT7: =+UT$6*$C7 -> 31098.815 | UU7: =+UU$6*$C7 -> 0 | UV7: =+UV$6*$C7 -> 0 | UW7: =+SUM(TR7:UV7) -> 752687.61 | UX7: =+UX$6*$C7 -> 0 | UY7: =+UY$6*$C7 -> 18881.544 | UZ7: =+UZ$6*$C7 -> 18881.544 | VA7: =+VA$6*$C7 -> 18881.544 | VB7: =+VB$6*$C7 -> 31098.815 | VC7: =+VC$6*$C7 -> 0 | VD7: =+VD$6*$C7 -> 0 | VE7: =+VE$6*$C7 -> 0 | ... VH7: =+VH$6*$C7 -> 397856.01 | VI7: 0 | VJ7: =+VJ$6*$C7 -> 0 | VK7: =+VK$6*$C7 -> 1402.9548 | VL7: =+VL$6*$C7 -> 12977.488 | VM7: =+VM$6*$C7 -> 18881.544 | VN7: =+VN$6*$C7 -> 18881.544 | VO7: =+VO$6*$C7 -> 18881.544 | VP7: 0 | VQ7: =+VQ$6*$C7 -> 31098.815 | VR7: =+VR$6*$C7 -> 1402.9548 | VS7: =+VS$6*$C7 -> 0 | VT7: =+VT$6*$C7 -> 18881.544 | VU7: =+VU$6*$C7 -> 18881.544 | VV7: =+VV$6*$C7 -> 18881.544 | VW7: 0 | VX7: =+VX$6*$C7 -> 0 | VY7: =+VY$6*$C7 -> 0 | VZ7: =+VZ$6*$C7 -> 0 | WA7: =+WA$6*$C7 -> 18881.544 | WB7: =+WB$6*$C7 -> 18881.544 | WC7: =+SUM(UX7:WB7) -> 721297.11
B8: CHEQUE (D+1) | C8: =+[4]DRE!AC9 -> 0.055007171 | D8: =+D$6*$C8 -> 0 | E8: =+E$6*$C8 -> 0 | F8: =+F$6*$C8 -> 2692.0604 | G8: =+G$6*$C8 -> 2692.0604 | H8: =+H$6*$C8 -> 2692.0604 | I8: =+I$6*$C8 -> 4433.9534 | J8: =+J$6*$C8 -> 4433.9534 | K8: =+K$6*$C8 -> 200.02808 | ... AE8: =+AE$6*$C8 -> 4433.9534 | AH8: =+SUM(D8:AE8) -> 61158.783 | AI8: =+AI$6*$C8 -> 0 | AJ8: =+AJ$6*$C8 -> 0 | AK8: =+AK$6*$C8 -> 2692.0604 | AL8: =+AL$6*$C8 -> 2692.0604 | AM8: =+AM$6*$C8 -> 2692.0604 | AN8: =+AN$6*$C8 -> 4433.9534 | AO8: =+AO$6*$C8 -> 4433.9534 | AP8: =+AP$6*$C8 -> 200.02808 | ... AS8: =+AS$6*$C8 -> 2692.0604 | AT8: 0 | AU8: =+AU$6*$C8 -> 4433.9534 | AV8: =+AV$6*$C8 -> 0 | AW8: =+AW$6*$C8 -> 0 | AX8: =+AX$6*$C8 -> 0 | AY8: =+AY$6*$C8 -> 2692.0604 | AZ8: =+AZ$6*$C8 -> 2692.0604 | BA8: 0 | BB8: =+BB$6*$C8 -> 4433.9534 | BC8: =+BC$6*$C8 -> 0 | BD8: =+BD$6*$C8 -> 200.02808 | BE8: =+BE$6*$C8 -> 1850.282 | BF8: =+BF$6*$C8 -> 2692.0604 | BG8: =+BG$6*$C8 -> 2692.0604 | BH8: 0 | BI8: =+BI$6*$C8 -> 4433.9534 | BJ8: =+BJ$6*$C8 -> 4433.9534 | BK8: =+BK$6*$C8 -> 200.02808 | BL8: =+BL$6*$C8 -> 0 | BM8: =+BM$6*$C8 -> 2692.0604 | BN8: =+SUM(AI8:BM8) -> 55974.69 | BO8: =+BO$6*$C8 -> 2692.0604 | BP8: 0 | BQ8: =+BQ$6*$C8 -> 4433.9534 | BR8: =+BR$6*$C8 -> 4433.9534 | BS8: =+BS$6*$C8 -> 200.02808 | BT8: =+BT$6*$C8 -> 0 | BU8: =+BU$6*$C8 -> 2692.0604 | BV8: =+BV$6*$C8 -> 2692.0604 | BW8: 0 | BX8: =+BX$6*$C8 -> 4433.9534 | BY8: =+BY$6*$C8 -> 0 | BZ8: =+BZ$6*$C8 -> 0 | CA8: =+CA$6*$C8 -> 0 | CB8: =+CB$6*$C8 -> 2692.0604 | CC8: =+CC$6*$C8 -> 2692.0604 | CD8: 0 | CE8: =+CE$6*$C8 -> 4433.9534 | CF8: =+CF$6*$C8 -> 0 | CG8: =+CG$6*$C8 -> 200.02808 | CH8: =+CH$6*$C8 -> 1850.282 | CI8: =+CI$6*$C8 -> 2692.0604 | CJ8: =+CJ$6*$C8 -> 2692.0604 | CK8: 0 | CL8: =+CL$6*$C8 -> 4433.9534 | CM8: =+CM$6*$C8 -> 4433.9534 | CN8: =+CN$6*$C8 -> 200.02808 | CO8: =+CO$6*$C8 -> 0 | CP8: =+CP$6*$C8 -> 2692.0604 | CQ8: =+CQ$6*$C8 -> 2692.0604 | CR8: 0 | CS8: =SUM(BO8:CR8) -> 53282.63 | CT8: =+CT$6*$C8 -> 4433.9534 | CU8: =+CU$6*$C8 -> 4433.9534 | CV8: =+CV$6*$C8 -> 200.02808 | CW8: =+CW$6*$C8 -> 0 | CX8: =+CX$6*$C8 -> 2692.0604 | CY8: =+CY$6*$C8 -> 2692.0604 | CZ8: =+CZ$6*$C8 -> 2692.0604 | DA8: =+DA$6*$C8 -> 4433.9534 | ... DD8: =+DD$6*$C8 -> 0 | DE8: 0 | DF8: =+DF$6*$C8 -> 2692.0604 | DG8: =+DG$6*$C8 -> 2692.0604 | DH8: =+DH$6*$C8 -> 4433.9534 | DI8: =+DI$6*$C8 -> 0 | DJ8: =+DJ$6*$C8 -> 200.02808 | DK8: =+DK$6*$C8 -> 1850.282 | DL8: 0 | DM8: =+DM$6*$C8 -> 2692.0604 | DN8: =+DN$6*$C8 -> 2692.0604 | DO8: =+DO$6*$C8 -> 4433.9534 | DP8: =+DP$6*$C8 -> 4433.9534 | DQ8: =+DQ$6*$C8 -> 200.02808 | DR8: =+DR$6*$C8 -> 0 | DS8: 0 | DT8: =+DT$6*$C8 -> 2692.0604 | DU8: =+DU$6*$C8 -> 2692.0604 | DV8: =+DV$6*$C8 -> 4433.9534 | DW8: =+DW$6*$C8 -> 0 | DX8: =+DX$6*$C8 -> 0 | DY8: =+SUM(CT8:DX8) -> 57716.583 | DZ8: =+DZ$6*$C8 -> 0 | EA8: =+EA$6*$C8 -> 2692.0604 | EB8: =+EB$6*$C8 -> 2692.0604 | EC8: =+EC$6*$C8 -> 2692.0604 | ED8: =+ED$6*$C8 -> 4433.9534 | EE8: =+EE$6*$C8 -> 0 | EF8: =+EF$6*$C8 -> 0 | EG8: =+EG$6*$C8 -> 0 | ... EJ8: =+EJ$6*$C8 -> 2692.0604 | EK8: 0 | EL8: =+EL$6*$C8 -> 0 | EM8: =+EM$6*$C8 -> 200.02808 | EN8: =+EN$6*$C8 -> 1850.282 | EO8: =+EO$6*$C8 -> 2692.0604 | EP8: =+EP$6*$C8 -> 2692.0604 | EQ8: =+EQ$6*$C8 -> 2692.0604 | ER8: 0 | ES8: =+ES$6*$C8 -> 4433.9534 | ET8: =+ET$6*$C8 -> 200.02808 | EU8: =+EU$6*$C8 -> 0 | EV8: =+EV$6*$C8 -> 2692.0604 | EW8: =+EW$6*$C8 -> 2692.0604 | EX8: =+EX$6*$C8 -> 2692.0604 | EY8: 0 | EZ8: =+EZ$6*$C8 -> 0 | FA8: =+FA$6*$C8 -> 0 | FB8: =+FB$6*$C8 -> 0 | FC8: =+FC$6*$C8 -> 2692.0604 | FD8: =+SUM(DZ8:FC8) -> 46115.03 | FE8: =+FE$6*$C8 -> 2692.0604 | FF8: =+FF$6*$C8 -> 4433.9534 | FG8: =+FG$6*$C8 -> 0 | FH8: =+FH$6*$C8 -> 0 | FI8: =+FI$6*$C8 -> 0 | FJ8: =+FJ$6*$C8 -> 2692.0604 | FK8: =+FK$6*$C8 -> 2692.0604 | FL8: =+FL$6*$C8 -> 2692.0604 | ... FO8: =+FO$6*$C8 -> 200.02808 | FP8: 0 | FQ8: =+FQ$6*$C8 -> 2692.0604 | FR8: =+FR$6*$C8 -> 2692.0604 | FS8: =+FS$6*$C8 -> 2692.0604 | FT8: =+FT$6*$C8 -> 4433.9534 | FU8: =+FU$6*$C8 -> 4433.9534 | FV8: =+FV$6*$C8 -> 200.02808 | FW8: 0 | FX8: =+FX$6*$C8 -> 2692.0604 | FY8: =+FY$6*$C8 -> 2692.0604 | FZ8: =+FZ$6*$C8 -> 2692.0604 | GA8: =+GA$6*$C8 -> 4433.9534 | GB8: =+GB$6*$C8 -> 0 | GC8: =+GC$6*$C8 -> 0 | GD8: 0 | GE8: =+GE$6*$C8 -> 2692.0604 | GF8: =+GF$6*$C8 -> 2692.0604 | GG8: =+GG$6*$C8 -> 2692.0604 | GH8: =+GH$6*$C8 -> 4433.9534 | GI8: =+GI$6*$C8 -> 0 | GJ8: =+SUM(FE8:GI8) -> 62000.561 | GK8: =+GK$6*$C8 -> 0 | GL8: =+GL$6*$C8 -> 0 | GM8: =+GM$6*$C8 -> 2692.0604 | GN8: =+GN$6*$C8 -> 2692.0604 | GO8: =+GO$6*$C8 -> 2692.0604 | GP8: =+GP$6*$C8 -> 4433.9534 | GQ8: =+GQ$6*$C8 -> 0 | GR8: =+GR$6*$C8 -> 200.02808 | ... GU8: =+GU$6*$C8 -> 2692.0604 | GV8: 0 | GW8: =+GW$6*$C8 -> 4433.9534 | GX8: =+GX$6*$C8 -> 4433.9534 | GY8: =+GY$6*$C8 -> 200.02808 | GZ8: =+GZ$6*$C8 -> 0 | HA8: =+HA$6*$C8 -> 2692.0604 | HB8: =+HB$6*$C8 -> 2692.0604 | HC8: 0 | HD8: =+HD$6*$C8 -> 4433.9534 | HE8: =+HE$6*$C8 -> 0 | HF8: =+HF$6*$C8 -> 0 | HG8: =+HG$6*$C8 -> 0 | HH8: =+HH$6*$C8 -> 2692.0604 | HI8: =+HI$6*$C8 -> 2692.0604 | HJ8: 0 | HK8: =+HK$6*$C8 -> 4433.9534 | HL8: =+HL$6*$C8 -> 0 | HM8: =+HM$6*$C8 -> 200.02808 | HN8: =+HN$6*$C8 -> 1850.282 | HO8: =+HO$6*$C8 -> 2692.0604 | HP8: =+SUM(GK8:HO8) -> 53391.019 | HQ8: =+HQ$6*$C8 -> 2692.0604 | HR8: =+HR$6*$C8 -> 2692.0604 | HS8: =+HS$6*$C8 -> 4433.9534 | HT8: =+HT$6*$C8 -> 0 | HU8: =+HU$6*$C8 -> 200.02808 | HV8: =+HV$6*$C8 -> 1850.282 | HW8: =+HW$6*$C8 -> 2692.0604 | HX8: =+HX$6*$C8 -> 2692.0604 | ... IA8: =+IA$6*$C8 -> 4433.9534 | IB8: 0 | IC8: =+IC$6*$C8 -> 0 | ID8: =+ID$6*$C8 -> 2692.0604 | IE8: =+IE$6*$C8 -> 2692.0604 | IF8: =+IF$6*$C8 -> 2692.0604 | IG8: =+IG$6*$C8 -> 4433.9534 | IH8: =+IH$6*$C8 -> 0 | II8: 0 | IJ8: =+IJ$6*$C8 -> 0 | IK8: =+IK$6*$C8 -> 2692.0604 | IL8: =+IL$6*$C8 -> 2692.0604 | IM8: =+IM$6*$C8 -> 2692.0604 | IN8: =+IN$6*$C8 -> 4433.9534 | IO8: =+IO$6*$C8 -> 0 | IP8: 0 | IQ8: =+IQ$6*$C8 -> 1850.282 | IR8: =+IR$6*$C8 -> 2692.0604 | IS8: =+IS$6*$C8 -> 2692.0604 | IT8: =+IT$6*$C8 -> 2692.0604 | IU8: =+SUM(HQ8:IT8) -> 63759.204 | IV8: =+IV$6*$C8 -> 0 | IW8: =+IW$6*$C8 -> 200.02808 | IX8: =+IX$6*$C8 -> 1850.282 | IY8: =+IY$6*$C8 -> 2692.0604 | IZ8: =+IZ$6*$C8 -> 2692.0604 | JA8: =+JA$6*$C8 -> 2692.0604 | JB8: =+JB$6*$C8 -> 4433.9534 | JC8: =+JC$6*$C8 -> 4433.9534 | ... JF8: =+JF$6*$C8 -> 2692.0604 | JG8: 0 | JH8: =+JH$6*$C8 -> 2692.0604 | JI8: =+JI$6*$C8 -> 4433.9534 | JJ8: =+JJ$6*$C8 -> 0 | JK8: =+JK$6*$C8 -> 0 | JL8: =+JL$6*$C8 -> 0 | JM8: =+JM$6*$C8 -> 2692.0604 | JN8: 0 | JO8: =+JO$6*$C8 -> 2692.0604 | JP8: =+JP$6*$C8 -> 4433.9534 | JQ8: =+JQ$6*$C8 -> 0 | JR8: =+JR$6*$C8 -> 200.02808 | JS8: =+JS$6*$C8 -> 1850.282 | JT8: =+JT$6*$C8 -> 2692.0604 | JU8: 0 | JV8: =+JV$6*$C8 -> 2692.0604 | JW8: =+JW$6*$C8 -> 4433.9534 | JX8: =+JX$6*$C8 -> 4433.9534 | JY8: =+JY$6*$C8 -> 200.02808 | JZ8: =+JZ$6*$C8 -> 0 | KA8: =+SUM(IV8:JZ8) -> 55332.94 | KB8: =+KB$6*$C8 -> 2692.0604 | KC8: =+KC$6*$C8 -> 2692.0604 | KD8: =+KD$6*$C8 -> 2692.0604 | KE8: =+KE$6*$C8 -> 4433.9534 | KF8: =+KF$6*$C8 -> 4433.9534 | KG8: =+KG$6*$C8 -> 200.02808 | KH8: =+KH$6*$C8 -> 0 | KI8: =+KI$6*$C8 -> 2692.0604 | ... KL8: =+KL$6*$C8 -> 4433.9534 | KM8: 0 | KN8: =+KN$6*$C8 -> 0 | KO8: =+KO$6*$C8 -> 0 | KP8: =+KP$6*$C8 -> 2692.0604 | KQ8: =+KQ$6*$C8 -> 2692.0604 | KR8: =+KR$6*$C8 -> 2692.0604 | KS8: =+KS$6*$C8 -> 4433.9534 | KT8: 0 | KU8: =+KU$6*$C8 -> 200.02808 | KV8: =+KV$6*$C8 -> 1850.282 | KW8: =+KW$6*$C8 -> 2692.0604 | KX8: =+KX$6*$C8 -> 2692.0604 | KY8: =+KY$6*$C8 -> 2692.0604 | KZ8: =+KZ$6*$C8 -> 4433.9534 | LA8: 0 | LB8: =+LB$6*$C8 -> 200.02808 | LC8: =+LC$6*$C8 -> 0 | LD8: =+LD$6*$C8 -> 2692.0604 | LE8: =+LE$6*$C8 -> 2692.0604 | LF8: =+SUM(KB8:LE8) -> 62308.979 | LG8: =+LG$6*$C8 -> 4433.9534 | LH8: =+LH$6*$C8 -> 4433.9534 | LI8: =+LI$6*$C8 -> 200.02808 | LJ8: =+LJ$6*$C8 -> 0 | LK8: =+LK$6*$C8 -> 2692.0604 | LL8: =+LL$6*$C8 -> 2692.0604 | LM8: =+LM$6*$C8 -> 2692.0604 | LN8: =+LN$6*$C8 -> 4433.9534 | ... LQ8: =+LQ$6*$C8 -> 0 | LR8: 0 | LS8: =+LS$6*$C8 -> 2692.0604 | LT8: =+LT$6*$C8 -> 2692.0604 | LU8: =+LU$6*$C8 -> 4433.9534 | LV8: =+LV$6*$C8 -> 0 | LW8: =+LW$6*$C8 -> 200.02808 | LX8: =+LX$6*$C8 -> 1850.282 | LY8: 0 | LZ8: =+LZ$6*$C8 -> 2692.0604 | MA8: =+MA$6*$C8 -> 2692.0604 | MB8: =+MB$6*$C8 -> 4433.9534 | MC8: =+MC$6*$C8 -> 4433.9534 | MD8: =+MD$6*$C8 -> 200.02808 | ME8: =+ME$6*$C8 -> 0 | MF8: 0 | MG8: =+MG$6*$C8 -> 2692.0604 | MH8: =+MH$6*$C8 -> 2692.0604 | MI8: =+MI$6*$C8 -> 4433.9534 | MJ8: =+MJ$6*$C8 -> 0 | MK8: =+MK$6*$C8 -> 0 | ML8: =+SUM(LG8:MK8) -> 57716.583 | MM8: =+MM$6*$C8 -> 0 | MN8: =+MN$6*$C8 -> 2692.0604 | MO8: =+MO$6*$C8 -> 2692.0604 | MP8: =+MP$6*$C8 -> 2692.0604 | MQ8: =+MQ$6*$C8 -> 4433.9534 | MR8: =+MR$6*$C8 -> 0 | MS8: =+MS$6*$C8 -> 0 | MT8: =+MT$6*$C8 -> 0 | ... MW8: =+MW$6*$C8 -> 2692.0604 | MX8: 0 | MY8: =+MY$6*$C8 -> 0 | MZ8: =+MZ$6*$C8 -> 200.02808 | NA8: =+NA$6*$C8 -> 1850.282 | NB8: =+NB$6*$C8 -> 2692.0604 | NC8: =+NC$6*$C8 -> 2692.0604 | ND8: =+ND$6*$C8 -> 2692.0604 | NE8: 0 | NF8: =+NF$6*$C8 -> 4433.9534 | NG8: =+NG$6*$C8 -> 200.02808 | NH8: =+NH$6*$C8 -> 0 | NI8: =+NI$6*$C8 -> 2692.0604 | NJ8: =+NJ$6*$C8 -> 2692.0604 | NK8: =+NK$6*$C8 -> 2692.0604 | NL8: 0 | NM8: =+NM$6*$C8 -> 0 | NN8: =+NN$6*$C8 -> 0 | NO8: =+NO$6*$C8 -> 0 | NP8: =+NP$6*$C8 -> 2692.0604 | NQ8: =+NQ$6*$C8 -> 2692.0604 | NR8: =+SUM(MM8:NQ8) -> 48807.09 | NS8: =+NS$6*$C8 -> 2692.0604 | NT8: =+NT$6*$C8 -> 4433.9534 | NU8: =+NU$6*$C8 -> 0 | NV8: =+NV$6*$C8 -> 0 | NW8: =+NW$6*$C8 -> 0 | NX8: =+NX$6*$C8 -> 2692.0604 | NY8: =+NY$6*$C8 -> 2692.0604 | NZ8: =+NZ$6*$C8 -> 2692.0604 | ... OC8: =+OC$6*$C8 -> 200.02808 | OD8: 0 | OE8: =+OE$6*$C8 -> 2692.0604 | OF8: =+OF$6*$C8 -> 2692.0604 | OG8: =+OG$6*$C8 -> 2692.0604 | OH8: =+OH$6*$C8 -> 4433.9534 | OI8: =+OI$6*$C8 -> 4433.9534 | OJ8: =+OJ$6*$C8 -> 200.02808 | OK8: 0 | OL8: =+OL$6*$C8 -> 2692.0604 | OM8: =+OM$6*$C8 -> 2692.0604 | ON8: =+ON$6*$C8 -> 2692.0604 | OO8: =+OO$6*$C8 -> 4433.9534 | OP8: =+OP$6*$C8 -> 0 | OQ8: =+OQ$6*$C8 -> 0 | OR8: 0 | OS8: =+OS$6*$C8 -> 2692.0604 | OT8: =+OT$6*$C8 -> 2692.0604 | OU8: =+SUM(NS8:OT8) -> 54874.548 | OV8: =+OV$6*$C8 -> 0 | OW8: =+OW$6*$C8 -> 0 | OX8: =+OX$6*$C8 -> 2692.0604 | OY8: =+OY$6*$C8 -> 2692.0604 | OZ8: =+OZ$6*$C8 -> 2692.0604 | PA8: =+PA$6*$C8 -> 4433.9534 | PB8: =+PB$6*$C8 -> 0 | PC8: =+PC$6*$C8 -> 200.02808 | ... PF8: =+PF$6*$C8 -> 2692.0604 | PG8: 0 | PH8: =+PH$6*$C8 -> 4433.9534 | PI8: =+PI$6*$C8 -> 4433.9534 | PJ8: =+PJ$6*$C8 -> 200.02808 | PK8: =+PK$6*$C8 -> 0 | PL8: =+PL$6*$C8 -> 2692.0604 | PM8: =+PM$6*$C8 -> 2692.0604 | PN8: 0 | PO8: =+PO$6*$C8 -> 4433.9534 | PP8: =+PP$6*$C8 -> 0 | PQ8: =+PQ$6*$C8 -> 0 | PR8: =+PR$6*$C8 -> 0 | PS8: =+PS$6*$C8 -> 2692.0604 | PT8: =+PT$6*$C8 -> 2692.0604 | PU8: 0 | PV8: =+PV$6*$C8 -> 0 | PW8: =+PW$6*$C8 -> 0 | PX8: =+PX$6*$C8 -> 200.02808 | PY8: =+PY$6*$C8 -> 1850.282 | PZ8: =+PZ$6*$C8 -> 2692.0604 | QA8: =+SUM(OV8:PZ8) -> 48957.066 | QB8: =+QB$6*$C8 -> 2692.0604 | QC8: =+QC$6*$C8 -> 2692.0604 | QD8: =+QD$6*$C8 -> 4433.9534 | QE8: =+QE$6*$C8 -> 0 | QF8: =+QF$6*$C8 -> 200.02808 | QG8: =+QG$6*$C8 -> 1850.282 | QH8: =+QH$6*$C8 -> 2692.0604 | QI8: =+QI$6*$C8 -> 2692.0604 | ... QL8: =+QL$6*$C8 -> 4433.9534 | QM8: 0 | QN8: =+QN$6*$C8 -> 0 | QO8: =+QO$6*$C8 -> 2692.0604 | QP8: =+QP$6*$C8 -> 2692.0604 | QQ8: =+QQ$6*$C8 -> 2692.0604 | QR8: =+QR$6*$C8 -> 4433.9534 | QS8: =+QS$6*$C8 -> 0 | QT8: 0 | QU8: =+QU$6*$C8 -> 0 | QV8: =+QV$6*$C8 -> 2692.0604 | QW8: =+QW$6*$C8 -> 2692.0604 | QX8: =+QX$6*$C8 -> 56724.83 | QY8: =+QY$6*$C8 -> 0 | QZ8: =+QZ$6*$C8 -> 0 | RA8: 0 | RB8: =+RB$6*$C8 -> 1850.282 | RC8: =+RC$6*$C8 -> 2692.0604 | RD8: =+RD$6*$C8 -> 2692.0604 | RE8: =+RE$6*$C8 -> 2692.0604 | RF8: =+SUM(QB8:RE8) -> 113358.02 | RG8: =+RG$6*$C8 -> 0 | RH8: =+RH$6*$C8 -> 200.02808 | RI8: =+RI$6*$C8 -> 1850.282 | RJ8: =+RJ$6*$C8 -> 2692.0604 | RK8: =+RK$6*$C8 -> 2692.0604 | RL8: =+RL$6*$C8 -> 2692.0604 | RM8: =+RM$6*$C8 -> 4433.9534 | RN8: =+RN$6*$C8 -> 4433.9534 | ... RQ8: =+RQ$6*$C8 -> 2692.0604 | RR8: 0 | RS8: =+RS$6*$C8 -> 2692.0604 | RT8: =+RT$6*$C8 -> 4433.9534 | RU8: =+RU$6*$C8 -> 0 | RV8: =+RV$6*$C8 -> 0 | RW8: =+RW$6*$C8 -> 0 | RX8: =+RX$6*$C8 -> 2692.0604 | RY8: 0 | RZ8: =+RZ$6*$C8 -> 56724.83 | SA8: =+SA$6*$C8 -> 0 | SB8: =+SB$6*$C8 -> 0 | SC8: =+SC$6*$C8 -> 200.02808 | SD8: =+SD$6*$C8 -> 1850.282 | SE8: =+SE$6*$C8 -> 2692.0604 | SF8: 0 | SG8: =+SG$6*$C8 -> 2692.0604 | SH8: =+SH$6*$C8 -> 4433.9534 | SI8: =+SI$6*$C8 -> 4433.9534 | SJ8: =+SJ$6*$C8 -> 200.02808 | SK8: =+SK$6*$C8 -> 0 | SL8: =+SUM(RG8:SK8) -> 104931.76 | SM8: =+SM$6*$C8 -> 2692.0604 | SN8: =+SN$6*$C8 -> 2692.0604 | SO8: =+SO$6*$C8 -> 2692.0604 | SP8: =+SP$6*$C8 -> 4433.9534 | SQ8: =+SQ$6*$C8 -> 4433.9534 | SR8: =+SR$6*$C8 -> 200.02808 | SS8: =+SS$6*$C8 -> 0 | ST8: =+ST$6*$C8 -> 2692.0604 | ... SW8: =+SW$6*$C8 -> 4433.9534 | SX8: 0 | SY8: =+SY$6*$C8 -> 0 | SZ8: =+SZ$6*$C8 -> 0 | TA8: =+TA$6*$C8 -> 2692.0604 | TB8: =+TB$6*$C8 -> 2692.0604 | TC8: =+TC$6*$C8 -> 56724.83 | TD8: =+TD$6*$C8 -> 0 | TE8: 0 | TF8: =+TF$6*$C8 -> 200.02808 | TG8: =+TG$6*$C8 -> 1850.282 | TH8: =+TH$6*$C8 -> 2692.0604 | TI8: =+TI$6*$C8 -> 2692.0604 | TJ8: =+TJ$6*$C8 -> 2692.0604 | TK8: =+TK$6*$C8 -> 4433.9534 | TL8: 0 | TM8: =+TM$6*$C8 -> 200.02808 | TN8: =+TN$6*$C8 -> 0 | TO8: =+TO$6*$C8 -> 2692.0604 | TP8: =+TP$6*$C8 -> 2692.0604 | TQ8: =+SUM(SM8:TP8) -> 111907.79 | TR8: =+TR$6*$C8 -> 4433.9534 | TS8: =+TS$6*$C8 -> 4433.9534 | TT8: =+TT$6*$C8 -> 200.02808 | TU8: =+TU$6*$C8 -> 0 | TV8: =+TV$6*$C8 -> 2692.0604 | TW8: =+TW$6*$C8 -> 2692.0604 | TX8: =+TX$6*$C8 -> 2692.0604 | TY8: =+TY$6*$C8 -> 4433.9534 | ... UB8: =+UB$6*$C8 -> 0 | UC8: 0 | UD8: =+UD$6*$C8 -> 2692.0604 | UE8: =+UE$6*$C8 -> 56724.83 | UF8: =+UF$6*$C8 -> 0 | UG8: =+UG$6*$C8 -> 0 | UH8: =+UH$6*$C8 -> 200.02808 | UI8: =+UI$6*$C8 -> 1850.282 | UJ8: 0 | UK8: =+UK$6*$C8 -> 2692.0604 | UL8: =+UL$6*$C8 -> 2692.0604 | UM8: =+UM$6*$C8 -> 4433.9534 | UN8: =+UN$6*$C8 -> 4433.9534 | UO8: =+UO$6*$C8 -> 200.02808 | UP8: =+UP$6*$C8 -> 0 | UQ8: 0 | UR8: =+UR$6*$C8 -> 2692.0604 | US8: =+US$6*$C8 -> 2692.0604 | UT8: =+UT$6*$C8 -> 4433.9534 | UU8: =+UU$6*$C8 -> 0 | UV8: =+UV$6*$C8 -> 0 | UW8: =+SUM(TR8:UV8) -> 107315.4 | UX8: =+UX$6*$C8 -> 0 | UY8: =+UY$6*$C8 -> 2692.0604 | UZ8: =+UZ$6*$C8 -> 2692.0604 | VA8: =+VA$6*$C8 -> 2692.0604 | VB8: =+VB$6*$C8 -> 4433.9534 | VC8: =+VC$6*$C8 -> 0 | VD8: =+VD$6*$C8 -> 0 | VE8: =+VE$6*$C8 -> 0 | ... VH8: =+VH$6*$C8 -> 56724.83 | VI8: 0 | VJ8: =+VJ$6*$C8 -> 0 | VK8: =+VK$6*$C8 -> 200.02808 | VL8: =+VL$6*$C8 -> 1850.282 | VM8: =+VM$6*$C8 -> 2692.0604 | VN8: =+VN$6*$C8 -> 2692.0604 | VO8: =+VO$6*$C8 -> 2692.0604 | VP8: 0 | VQ8: =+VQ$6*$C8 -> 4433.9534 | VR8: =+VR$6*$C8 -> 200.02808 | VS8: =+VS$6*$C8 -> 0 | VT8: =+VT$6*$C8 -> 2692.0604 | VU8: =+VU$6*$C8 -> 2692.0604 | VV8: =+VV$6*$C8 -> 2692.0604 | VW8: 0 | VX8: =+VX$6*$C8 -> 0 | VY8: =+VY$6*$C8 -> 0 | VZ8: =+VZ$6*$C8 -> 0 | WA8: =+WA$6*$C8 -> 2692.0604 | WB8: =+WB$6*$C8 -> 2692.0604 | WC8: =+SUM(UX8:WB8) -> 102839.86
B9: DÉBITO (D+1) | C9: =+[4]DRE!AC10 -> 0.0059505625 | D9: =+D$6*$C9 -> 0 | E9: =+E$6*$C9 -> 0 | F9: =+F$6*$C9 -> 291.22155 | G9: =+G$6*$C9 -> 291.22155 | H9: =+H$6*$C9 -> 291.22155 | I9: =+I$6*$C9 -> 479.65595 | J9: =+J$6*$C9 -> 479.65595 | K9: =+K$6*$C9 -> 21.638626 | ... AE9: =+AE$6*$C9 -> 479.65595 | AH9: =+SUM(D9:AE9) -> 6616.0313 | AI9: =+AI$6*$C9 -> 0 | AJ9: =+AJ$6*$C9 -> 0 | AK9: =+AK$6*$C9 -> 291.22155 | AL9: =+AL$6*$C9 -> 291.22155 | AM9: =+AM$6*$C9 -> 291.22155 | AN9: =+AN$6*$C9 -> 479.65595 | AO9: =+AO$6*$C9 -> 479.65595 | AP9: =+AP$6*$C9 -> 21.638626 | ... AS9: =+AS$6*$C9 -> 291.22155 | AT9: 0 | AU9: =+AU$6*$C9 -> 479.65595 | AV9: =+AV$6*$C9 -> 0 | AW9: =+AW$6*$C9 -> 0 | AX9: =+AX$6*$C9 -> 0 | AY9: =+AY$6*$C9 -> 291.22155 | AZ9: =+AZ$6*$C9 -> 291.22155 | BA9: 0 | BB9: =+BB$6*$C9 -> 479.65595 | BC9: =+BC$6*$C9 -> 0 | BD9: =+BD$6*$C9 -> 21.638626 | BE9: =+BE$6*$C9 -> 200.1597 | BF9: =+BF$6*$C9 -> 291.22155 | BG9: =+BG$6*$C9 -> 291.22155 | BH9: 0 | BI9: =+BI$6*$C9 -> 479.65595 | BJ9: =+BJ$6*$C9 -> 479.65595 | BK9: =+BK$6*$C9 -> 21.638626 | BL9: =+BL$6*$C9 -> 0 | BM9: =+BM$6*$C9 -> 291.22155 | BN9: =+SUM(AI9:BM9) -> 6055.2268 | BO9: =+BO$6*$C9 -> 291.22155 | BP9: 0 | BQ9: =+BQ$6*$C9 -> 479.65595 | BR9: =+BR$6*$C9 -> 479.65595 | BS9: =+BS$6*$C9 -> 21.638626 | BT9: =+BT$6*$C9 -> 0 | BU9: =+BU$6*$C9 -> 291.22155 | BV9: =+BV$6*$C9 -> 291.22155 | BW9: 0 | BX9: =+BX$6*$C9 -> 479.65595 | BY9: =+BY$6*$C9 -> 0 | BZ9: =+BZ$6*$C9 -> 0 | CA9: =+CA$6*$C9 -> 0 | CB9: =+CB$6*$C9 -> 291.22155 | CC9: =+CC$6*$C9 -> 291.22155 | CD9: 0 | CE9: =+CE$6*$C9 -> 479.65595 | CF9: =+CF$6*$C9 -> 0 | CG9: =+CG$6*$C9 -> 21.638626 | CH9: =+CH$6*$C9 -> 200.1597 | CI9: =+CI$6*$C9 -> 291.22155 | CJ9: =+CJ$6*$C9 -> 291.22155 | CK9: 0 | CL9: =+CL$6*$C9 -> 479.65595 | CM9: =+CM$6*$C9 -> 479.65595 | CN9: =+CN$6*$C9 -> 21.638626 | CO9: =+CO$6*$C9 -> 0 | CP9: =+CP$6*$C9 -> 291.22155 | CQ9: =+CQ$6*$C9 -> 291.22155 | CR9: 0 | CS9: =SUM(BO9:CR9) -> 5764.0053 | CT9: =+CT$6*$C9 -> 479.65595 | CU9: =+CU$6*$C9 -> 479.65595 | CV9: =+CV$6*$C9 -> 21.638626 | CW9: =+CW$6*$C9 -> 0 | CX9: =+CX$6*$C9 -> 291.22155 | CY9: =+CY$6*$C9 -> 291.22155 | CZ9: =+CZ$6*$C9 -> 291.22155 | DA9: =+DA$6*$C9 -> 479.65595 | ... DD9: =+DD$6*$C9 -> 0 | DE9: 0 | DF9: =+DF$6*$C9 -> 291.22155 | DG9: =+DG$6*$C9 -> 291.22155 | DH9: =+DH$6*$C9 -> 479.65595 | DI9: =+DI$6*$C9 -> 0 | DJ9: =+DJ$6*$C9 -> 21.638626 | DK9: =+DK$6*$C9 -> 200.1597 | DL9: 0 | DM9: =+DM$6*$C9 -> 291.22155 | DN9: =+DN$6*$C9 -> 291.22155 | DO9: =+DO$6*$C9 -> 479.65595 | DP9: =+DP$6*$C9 -> 479.65595 | DQ9: =+DQ$6*$C9 -> 21.638626 | DR9: =+DR$6*$C9 -> 0 | DS9: 0 | DT9: =+DT$6*$C9 -> 291.22155 | DU9: =+DU$6*$C9 -> 291.22155 | DV9: =+DV$6*$C9 -> 479.65595 | DW9: =+DW$6*$C9 -> 0 | DX9: =+DX$6*$C9 -> 0 | DY9: =+SUM(CT9:DX9) -> 6243.6612 | DZ9: =+DZ$6*$C9 -> 0 | EA9: =+EA$6*$C9 -> 291.22155 | EB9: =+EB$6*$C9 -> 291.22155 | EC9: =+EC$6*$C9 -> 291.22155 | ED9: =+ED$6*$C9 -> 479.65595 | EE9: =+EE$6*$C9 -> 0 | EF9: =+EF$6*$C9 -> 0 | EG9: =+EG$6*$C9 -> 0 | ... EJ9: =+EJ$6*$C9 -> 291.22155 | EK9: 0 | EL9: =+EL$6*$C9 -> 0 | EM9: =+EM$6*$C9 -> 21.638626 | EN9: =+EN$6*$C9 -> 200.1597 | EO9: =+EO$6*$C9 -> 291.22155 | EP9: =+EP$6*$C9 -> 291.22155 | EQ9: =+EQ$6*$C9 -> 291.22155 | ER9: 0 | ES9: =+ES$6*$C9 -> 479.65595 | ET9: =+ET$6*$C9 -> 21.638626 | EU9: =+EU$6*$C9 -> 0 | EV9: =+EV$6*$C9 -> 291.22155 | EW9: =+EW$6*$C9 -> 291.22155 | EX9: =+EX$6*$C9 -> 291.22155 | EY9: 0 | EZ9: =+EZ$6*$C9 -> 0 | FA9: =+FA$6*$C9 -> 0 | FB9: =+FB$6*$C9 -> 0 | FC9: =+FC$6*$C9 -> 291.22155 | FD9: =+SUM(DZ9:FC9) -> 4988.629 | FE9: =+FE$6*$C9 -> 291.22155 | FF9: =+FF$6*$C9 -> 479.65595 | FG9: =+FG$6*$C9 -> 0 | FH9: =+FH$6*$C9 -> 0 | FI9: =+FI$6*$C9 -> 0 | FJ9: =+FJ$6*$C9 -> 291.22155 | FK9: =+FK$6*$C9 -> 291.22155 | FL9: =+FL$6*$C9 -> 291.22155 | ... FO9: =+FO$6*$C9 -> 21.638626 | FP9: 0 | FQ9: =+FQ$6*$C9 -> 291.22155 | FR9: =+FR$6*$C9 -> 291.22155 | FS9: =+FS$6*$C9 -> 291.22155 | FT9: =+FT$6*$C9 -> 479.65595 | FU9: =+FU$6*$C9 -> 479.65595 | FV9: =+FV$6*$C9 -> 21.638626 | FW9: 0 | FX9: =+FX$6*$C9 -> 291.22155 | FY9: =+FY$6*$C9 -> 291.22155 | FZ9: =+FZ$6*$C9 -> 291.22155 | GA9: =+GA$6*$C9 -> 479.65595 | GB9: =+GB$6*$C9 -> 0 | GC9: =+GC$6*$C9 -> 0 | GD9: 0 | GE9: =+GE$6*$C9 -> 291.22155 | GF9: =+GF$6*$C9 -> 291.22155 | GG9: =+GG$6*$C9 -> 291.22155 | GH9: =+GH$6*$C9 -> 479.65595 | GI9: =+GI$6*$C9 -> 0 | GJ9: =+SUM(FE9:GI9) -> 6707.0932 | GK9: =+GK$6*$C9 -> 0 | GL9: =+GL$6*$C9 -> 0 | GM9: =+GM$6*$C9 -> 291.22155 | GN9: =+GN$6*$C9 -> 291.22155 | GO9: =+GO$6*$C9 -> 291.22155 | GP9: =+GP$6*$C9 -> 479.65595 | GQ9: =+GQ$6*$C9 -> 0 | GR9: =+GR$6*$C9 -> 21.638626 | ... GU9: =+GU$6*$C9 -> 291.22155 | GV9: 0 | GW9: =+GW$6*$C9 -> 479.65595 | GX9: =+GX$6*$C9 -> 479.65595 | GY9: =+GY$6*$C9 -> 21.638626 | GZ9: =+GZ$6*$C9 -> 0 | HA9: =+HA$6*$C9 -> 291.22155 | HB9: =+HB$6*$C9 -> 291.22155 | HC9: 0 | HD9: =+HD$6*$C9 -> 479.65595 | HE9: =+HE$6*$C9 -> 0 | HF9: =+HF$6*$C9 -> 0 | HG9: =+HG$6*$C9 -> 0 | HH9: =+HH$6*$C9 -> 291.22155 | HI9: =+HI$6*$C9 -> 291.22155 | HJ9: 0 | HK9: =+HK$6*$C9 -> 479.65595 | HL9: =+HL$6*$C9 -> 0 | HM9: =+HM$6*$C9 -> 21.638626 | HN9: =+HN$6*$C9 -> 200.1597 | HO9: =+HO$6*$C9 -> 291.22155 | HP9: =+SUM(GK9:HO9) -> 5775.7306 | HQ9: =+HQ$6*$C9 -> 291.22155 | HR9: =+HR$6*$C9 -> 291.22155 | HS9: =+HS$6*$C9 -> 479.65595 | HT9: =+HT$6*$C9 -> 0 | HU9: =+HU$6*$C9 -> 21.638626 | HV9: =+HV$6*$C9 -> 200.1597 | HW9: =+HW$6*$C9 -> 291.22155 | HX9: =+HX$6*$C9 -> 291.22155 | ... IA9: =+IA$6*$C9 -> 479.65595 | IB9: 0 | IC9: =+IC$6*$C9 -> 0 | ID9: =+ID$6*$C9 -> 291.22155 | IE9: =+IE$6*$C9 -> 291.22155 | IF9: =+IF$6*$C9 -> 291.22155 | IG9: =+IG$6*$C9 -> 479.65595 | IH9: =+IH$6*$C9 -> 0 | II9: 0 | IJ9: =+IJ$6*$C9 -> 0 | IK9: =+IK$6*$C9 -> 291.22155 | IL9: =+IL$6*$C9 -> 291.22155 | IM9: =+IM$6*$C9 -> 291.22155 | IN9: =+IN$6*$C9 -> 479.65595 | IO9: =+IO$6*$C9 -> 0 | IP9: 0 | IQ9: =+IQ$6*$C9 -> 200.1597 | IR9: =+IR$6*$C9 -> 291.22155 | IS9: =+IS$6*$C9 -> 291.22155 | IT9: =+IT$6*$C9 -> 291.22155 | IU9: =+SUM(HQ9:IT9) -> 6897.3395 | IV9: =+IV$6*$C9 -> 0 | IW9: =+IW$6*$C9 -> 21.638626 | IX9: =+IX$6*$C9 -> 200.1597 | IY9: =+IY$6*$C9 -> 291.22155 | IZ9: =+IZ$6*$C9 -> 291.22155 | JA9: =+JA$6*$C9 -> 291.22155 | JB9: =+JB$6*$C9 -> 479.65595 | JC9: =+JC$6*$C9 -> 479.65595 | ... JF9: =+JF$6*$C9 -> 291.22155 | JG9: 0 | JH9: =+JH$6*$C9 -> 291.22155 | JI9: =+JI$6*$C9 -> 479.65595 | JJ9: =+JJ$6*$C9 -> 0 | JK9: =+JK$6*$C9 -> 0 | JL9: =+JL$6*$C9 -> 0 | JM9: =+JM$6*$C9 -> 291.22155 | JN9: 0 | JO9: =+JO$6*$C9 -> 291.22155 | JP9: =+JP$6*$C9 -> 479.65595 | JQ9: =+JQ$6*$C9 -> 0 | JR9: =+JR$6*$C9 -> 21.638626 | JS9: =+JS$6*$C9 -> 200.1597 | JT9: =+JT$6*$C9 -> 291.22155 | JU9: 0 | JV9: =+JV$6*$C9 -> 291.22155 | JW9: =+JW$6*$C9 -> 479.65595 | JX9: =+JX$6*$C9 -> 479.65595 | JY9: =+JY$6*$C9 -> 21.638626 | JZ9: =+JZ$6*$C9 -> 0 | KA9: =+SUM(IV9:JZ9) -> 5985.8036 | KB9: =+KB$6*$C9 -> 291.22155 | KC9: =+KC$6*$C9 -> 291.22155 | KD9: =+KD$6*$C9 -> 291.22155 | KE9: =+KE$6*$C9 -> 479.65595 | KF9: =+KF$6*$C9 -> 479.65595 | KG9: =+KG$6*$C9 -> 21.638626 | KH9: =+KH$6*$C9 -> 0 | KI9: =+KI$6*$C9 -> 291.22155 | ... KL9: =+KL$6*$C9 -> 479.65595 | KM9: 0 | KN9: =+KN$6*$C9 -> 0 | KO9: =+KO$6*$C9 -> 0 | KP9: =+KP$6*$C9 -> 291.22155 | KQ9: =+KQ$6*$C9 -> 291.22155 | KR9: =+KR$6*$C9 -> 291.22155 | KS9: =+KS$6*$C9 -> 479.65595 | KT9: 0 | KU9: =+KU$6*$C9 -> 21.638626 | KV9: =+KV$6*$C9 -> 200.1597 | KW9: =+KW$6*$C9 -> 291.22155 | KX9: =+KX$6*$C9 -> 291.22155 | KY9: =+KY$6*$C9 -> 291.22155 | KZ9: =+KZ$6*$C9 -> 479.65595 | LA9: 0 | LB9: =+LB$6*$C9 -> 21.638626 | LC9: =+LC$6*$C9 -> 0 | LD9: =+LD$6*$C9 -> 291.22155 | LE9: =+LE$6*$C9 -> 291.22155 | LF9: =+SUM(KB9:LE9) -> 6740.4571 | LG9: =+LG$6*$C9 -> 479.65595 | LH9: =+LH$6*$C9 -> 479.65595 | LI9: =+LI$6*$C9 -> 21.638626 | LJ9: =+LJ$6*$C9 -> 0 | LK9: =+LK$6*$C9 -> 291.22155 | LL9: =+LL$6*$C9 -> 291.22155 | LM9: =+LM$6*$C9 -> 291.22155 | LN9: =+LN$6*$C9 -> 479.65595 | ... LQ9: =+LQ$6*$C9 -> 0 | LR9: 0 | LS9: =+LS$6*$C9 -> 291.22155 | LT9: =+LT$6*$C9 -> 291.22155 | LU9: =+LU$6*$C9 -> 479.65595 | LV9: =+LV$6*$C9 -> 0 | LW9: =+LW$6*$C9 -> 21.638626 | LX9: =+LX$6*$C9 -> 200.1597 | LY9: 0 | LZ9: =+LZ$6*$C9 -> 291.22155 | MA9: =+MA$6*$C9 -> 291.22155 | MB9: =+MB$6*$C9 -> 479.65595 | MC9: =+MC$6*$C9 -> 479.65595 | MD9: =+MD$6*$C9 -> 21.638626 | ME9: =+ME$6*$C9 -> 0 | MF9: 0 | MG9: =+MG$6*$C9 -> 291.22155 | MH9: =+MH$6*$C9 -> 291.22155 | MI9: =+MI$6*$C9 -> 479.65595 | MJ9: =+MJ$6*$C9 -> 0 | MK9: =+MK$6*$C9 -> 0 | ML9: =+SUM(LG9:MK9) -> 6243.6612 | MM9: =+MM$6*$C9 -> 0 | MN9: =+MN$6*$C9 -> 291.22155 | MO9: =+MO$6*$C9 -> 291.22155 | MP9: =+MP$6*$C9 -> 291.22155 | MQ9: =+MQ$6*$C9 -> 479.65595 | MR9: =+MR$6*$C9 -> 0 | MS9: =+MS$6*$C9 -> 0 | MT9: =+MT$6*$C9 -> 0 | ... MW9: =+MW$6*$C9 -> 291.22155 | MX9: 0 | MY9: =+MY$6*$C9 -> 0 | MZ9: =+MZ$6*$C9 -> 21.638626 | NA9: =+NA$6*$C9 -> 200.1597 | NB9: =+NB$6*$C9 -> 291.22155 | NC9: =+NC$6*$C9 -> 291.22155 | ND9: =+ND$6*$C9 -> 291.22155 | NE9: 0 | NF9: =+NF$6*$C9 -> 479.65595 | NG9: =+NG$6*$C9 -> 21.638626 | NH9: =+NH$6*$C9 -> 0 | NI9: =+NI$6*$C9 -> 291.22155 | NJ9: =+NJ$6*$C9 -> 291.22155 | NK9: =+NK$6*$C9 -> 291.22155 | NL9: 0 | NM9: =+NM$6*$C9 -> 0 | NN9: =+NN$6*$C9 -> 0 | NO9: =+NO$6*$C9 -> 0 | NP9: =+NP$6*$C9 -> 291.22155 | NQ9: =+NQ$6*$C9 -> 291.22155 | NR9: =+SUM(MM9:NQ9) -> 5279.8506 | NS9: =+NS$6*$C9 -> 291.22155 | NT9: =+NT$6*$C9 -> 479.65595 | NU9: =+NU$6*$C9 -> 0 | NV9: =+NV$6*$C9 -> 0 | NW9: =+NW$6*$C9 -> 0 | NX9: =+NX$6*$C9 -> 291.22155 | NY9: =+NY$6*$C9 -> 291.22155 | NZ9: =+NZ$6*$C9 -> 291.22155 | ... OC9: =+OC$6*$C9 -> 21.638626 | OD9: 0 | OE9: =+OE$6*$C9 -> 291.22155 | OF9: =+OF$6*$C9 -> 291.22155 | OG9: =+OG$6*$C9 -> 291.22155 | OH9: =+OH$6*$C9 -> 479.65595 | OI9: =+OI$6*$C9 -> 479.65595 | OJ9: =+OJ$6*$C9 -> 21.638626 | OK9: 0 | OL9: =+OL$6*$C9 -> 291.22155 | OM9: =+OM$6*$C9 -> 291.22155 | ON9: =+ON$6*$C9 -> 291.22155 | OO9: =+OO$6*$C9 -> 479.65595 | OP9: =+OP$6*$C9 -> 0 | OQ9: =+OQ$6*$C9 -> 0 | OR9: 0 | OS9: =+OS$6*$C9 -> 291.22155 | OT9: =+OT$6*$C9 -> 291.22155 | OU9: =+SUM(NS9:OT9) -> 5936.2156 | OV9: =+OV$6*$C9 -> 0 | OW9: =+OW$6*$C9 -> 0 | OX9: =+OX$6*$C9 -> 291.22155 | OY9: =+OY$6*$C9 -> 291.22155 | OZ9: =+OZ$6*$C9 -> 291.22155 | PA9: =+PA$6*$C9 -> 479.65595 | PB9: =+PB$6*$C9 -> 0 | PC9: =+PC$6*$C9 -> 21.638626 | ... PF9: =+PF$6*$C9 -> 291.22155 | PG9: 0 | PH9: =+PH$6*$C9 -> 479.65595 | PI9: =+PI$6*$C9 -> 479.65595 | PJ9: =+PJ$6*$C9 -> 21.638626 | PK9: =+PK$6*$C9 -> 0 | PL9: =+PL$6*$C9 -> 291.22155 | PM9: =+PM$6*$C9 -> 291.22155 | PN9: 0 | PO9: =+PO$6*$C9 -> 479.65595 | PP9: =+PP$6*$C9 -> 0 | PQ9: =+PQ$6*$C9 -> 0 | PR9: =+PR$6*$C9 -> 0 | PS9: =+PS$6*$C9 -> 291.22155 | PT9: =+PT$6*$C9 -> 291.22155 | PU9: 0 | PV9: =+PV$6*$C9 -> 0 | PW9: =+PW$6*$C9 -> 0 | PX9: =+PX$6*$C9 -> 21.638626 | PY9: =+PY$6*$C9 -> 200.1597 | PZ9: =+PZ$6*$C9 -> 291.22155 | QA9: =+SUM(OV9:PZ9) -> 5296.0746 | QB9: =+QB$6*$C9 -> 291.22155 | QC9: =+QC$6*$C9 -> 291.22155 | QD9: =+QD$6*$C9 -> 479.65595 | QE9: =+QE$6*$C9 -> 0 | QF9: =+QF$6*$C9 -> 21.638626 | QG9: =+QG$6*$C9 -> 200.1597 | QH9: =+QH$6*$C9 -> 291.22155 | QI9: =+QI$6*$C9 -> 291.22155 | ... QL9: =+QL$6*$C9 -> 479.65595 | QM9: 0 | QN9: =+QN$6*$C9 -> 0 | QO9: =+QO$6*$C9 -> 291.22155 | QP9: =+QP$6*$C9 -> 291.22155 | QQ9: =+QQ$6*$C9 -> 291.22155 | QR9: =+QR$6*$C9 -> 479.65595 | QS9: =+QS$6*$C9 -> 0 | QT9: 0 | QU9: =+QU$6*$C9 -> 0 | QV9: =+QV$6*$C9 -> 291.22155 | QW9: =+QW$6*$C9 -> 291.22155 | QX9: =+QX$6*$C9 -> 6136.3753 | QY9: =+QY$6*$C9 -> 0 | QZ9: =+QZ$6*$C9 -> 0 | RA9: 0 | RB9: =+RB$6*$C9 -> 200.1597 | RC9: =+RC$6*$C9 -> 291.22155 | RD9: =+RD$6*$C9 -> 291.22155 | RE9: =+RE$6*$C9 -> 291.22155 | RF9: =+SUM(QB9:RE9) -> 12262.837 | RG9: =+RG$6*$C9 -> 0 | RH9: =+RH$6*$C9 -> 21.638626 | RI9: =+RI$6*$C9 -> 200.1597 | RJ9: =+RJ$6*$C9 -> 291.22155 | RK9: =+RK$6*$C9 -> 291.22155 | RL9: =+RL$6*$C9 -> 291.22155 | RM9: =+RM$6*$C9 -> 479.65595 | RN9: =+RN$6*$C9 -> 479.65595 | ... RQ9: =+RQ$6*$C9 -> 291.22155 | RR9: 0 | RS9: =+RS$6*$C9 -> 291.22155 | RT9: =+RT$6*$C9 -> 479.65595 | RU9: =+RU$6*$C9 -> 0 | RV9: =+RV$6*$C9 -> 0 | RW9: =+RW$6*$C9 -> 0 | RX9: =+RX$6*$C9 -> 291.22155 | RY9: 0 | RZ9: =+RZ$6*$C9 -> 6136.3753 | SA9: =+SA$6*$C9 -> 0 | SB9: =+SB$6*$C9 -> 0 | SC9: =+SC$6*$C9 -> 21.638626 | SD9: =+SD$6*$C9 -> 200.1597 | SE9: =+SE$6*$C9 -> 291.22155 | SF9: 0 | SG9: =+SG$6*$C9 -> 291.22155 | SH9: =+SH$6*$C9 -> 479.65595 | SI9: =+SI$6*$C9 -> 479.65595 | SJ9: =+SJ$6*$C9 -> 21.638626 | SK9: =+SK$6*$C9 -> 0 | SL9: =+SUM(RG9:SK9) -> 11351.301 | SM9: =+SM$6*$C9 -> 291.22155 | SN9: =+SN$6*$C9 -> 291.22155 | SO9: =+SO$6*$C9 -> 291.22155 | SP9: =+SP$6*$C9 -> 479.65595 | SQ9: =+SQ$6*$C9 -> 479.65595 | SR9: =+SR$6*$C9 -> 21.638626 | SS9: =+SS$6*$C9 -> 0 | ST9: =+ST$6*$C9 -> 291.22155 | ... SW9: =+SW$6*$C9 -> 479.65595 | SX9: 0 | SY9: =+SY$6*$C9 -> 0 | SZ9: =+SZ$6*$C9 -> 0 | TA9: =+TA$6*$C9 -> 291.22155 | TB9: =+TB$6*$C9 -> 291.22155 | TC9: =+TC$6*$C9 -> 6136.3753 | TD9: =+TD$6*$C9 -> 0 | TE9: 0 | TF9: =+TF$6*$C9 -> 21.638626 | TG9: =+TG$6*$C9 -> 200.1597 | TH9: =+TH$6*$C9 -> 291.22155 | TI9: =+TI$6*$C9 -> 291.22155 | TJ9: =+TJ$6*$C9 -> 291.22155 | TK9: =+TK$6*$C9 -> 479.65595 | TL9: 0 | TM9: =+TM$6*$C9 -> 21.638626 | TN9: =+TN$6*$C9 -> 0 | TO9: =+TO$6*$C9 -> 291.22155 | TP9: =+TP$6*$C9 -> 291.22155 | TQ9: =+SUM(SM9:TP9) -> 12105.955 | TR9: =+TR$6*$C9 -> 479.65595 | TS9: =+TS$6*$C9 -> 479.65595 | TT9: =+TT$6*$C9 -> 21.638626 | TU9: =+TU$6*$C9 -> 0 | TV9: =+TV$6*$C9 -> 291.22155 | TW9: =+TW$6*$C9 -> 291.22155 | TX9: =+TX$6*$C9 -> 291.22155 | TY9: =+TY$6*$C9 -> 479.65595 | ... UB9: =+UB$6*$C9 -> 0 | UC9: 0 | UD9: =+UD$6*$C9 -> 291.22155 | UE9: =+UE$6*$C9 -> 6136.3753 | UF9: =+UF$6*$C9 -> 0 | UG9: =+UG$6*$C9 -> 0 | UH9: =+UH$6*$C9 -> 21.638626 | UI9: =+UI$6*$C9 -> 200.1597 | UJ9: 0 | UK9: =+UK$6*$C9 -> 291.22155 | UL9: =+UL$6*$C9 -> 291.22155 | UM9: =+UM$6*$C9 -> 479.65595 | UN9: =+UN$6*$C9 -> 479.65595 | UO9: =+UO$6*$C9 -> 21.638626 | UP9: =+UP$6*$C9 -> 0 | UQ9: 0 | UR9: =+UR$6*$C9 -> 291.22155 | US9: =+US$6*$C9 -> 291.22155 | UT9: =+UT$6*$C9 -> 479.65595 | UU9: =+UU$6*$C9 -> 0 | UV9: =+UV$6*$C9 -> 0 | UW9: =+SUM(TR9:UV9) -> 11609.159 | UX9: =+UX$6*$C9 -> 0 | UY9: =+UY$6*$C9 -> 291.22155 | UZ9: =+UZ$6*$C9 -> 291.22155 | VA9: =+VA$6*$C9 -> 291.22155 | VB9: =+VB$6*$C9 -> 479.65595 | VC9: =+VC$6*$C9 -> 0 | VD9: =+VD$6*$C9 -> 0 | VE9: =+VE$6*$C9 -> 0 | ... VH9: =+VH$6*$C9 -> 6136.3753 | VI9: 0 | VJ9: =+VJ$6*$C9 -> 0 | VK9: =+VK$6*$C9 -> 21.638626 | VL9: =+VL$6*$C9 -> 200.1597 | VM9: =+VM$6*$C9 -> 291.22155 | VN9: =+VN$6*$C9 -> 291.22155 | VO9: =+VO$6*$C9 -> 291.22155 | VP9: 0 | VQ9: =+VQ$6*$C9 -> 479.65595 | VR9: =+VR$6*$C9 -> 21.638626 | VS9: =+VS$6*$C9 -> 0 | VT9: =+VT$6*$C9 -> 291.22155 | VU9: =+VU$6*$C9 -> 291.22155 | VV9: =+VV$6*$C9 -> 291.22155 | VW9: 0 | VX9: =+VX$6*$C9 -> 0 | VY9: =+VY$6*$C9 -> 0 | VZ9: =+VZ$6*$C9 -> 0 | WA9: =+WA$6*$C9 -> 291.22155 | WB9: =+WB$6*$C9 -> 291.22155 | WC9: =+SUM(UX9:WB9) -> 11125.004
B10: CRÉDITO (D+1) | C10: =+[4]DRE!AC11 -> 0.0047880208 | D10: =+D$6*$C10 -> 0 | E10: =+E$6*$C10 -> 0 | F10: =+F$6*$C10 -> 234.32656 | G10: =+G$6*$C10 -> 234.32656 | H10: =+H$6*$C10 -> 234.32656 | I10: =+I$6*$C10 -> 385.94715 | J10: =+J$6*$C10 -> 385.94715 | K10: =+K$6*$C10 -> 17.411159 | ... AE10: =+AE$6*$C10 -> 385.94715 | AH10: =+SUM(D10:AE10) -> 5323.4791 | AI10: =+AI$6*$C10 -> 0 | AJ10: =+AJ$6*$C10 -> 0 | AK10: =+AK$6*$C10 -> 234.32656 | AL10: =+AL$6*$C10 -> 234.32656 | AM10: =+AM$6*$C10 -> 234.32656 | AN10: =+AN$6*$C10 -> 385.94715 | AO10: =+AO$6*$C10 -> 385.94715 | AP10: =+AP$6*$C10 -> 17.411159 | ... AS10: =+AS$6*$C10 -> 234.32656 | AT10: 0 | AU10: =+AU$6*$C10 -> 385.94715 | AV10: =+AV$6*$C10 -> 0 | AW10: =+AW$6*$C10 -> 0 | AX10: =+AX$6*$C10 -> 0 | AY10: =+AY$6*$C10 -> 234.32656 | AZ10: =+AZ$6*$C10 -> 234.32656 | BA10: 0 | BB10: =+BB$6*$C10 -> 385.94715 | BC10: =+BC$6*$C10 -> 0 | BD10: =+BD$6*$C10 -> 17.411159 | BE10: =+BE$6*$C10 -> 161.05516 | BF10: =+BF$6*$C10 -> 234.32656 | BG10: =+BG$6*$C10 -> 234.32656 | BH10: 0 | BI10: =+BI$6*$C10 -> 385.94715 | BJ10: =+BJ$6*$C10 -> 385.94715 | BK10: =+BK$6*$C10 -> 17.411159 | BL10: =+BL$6*$C10 -> 0 | BM10: =+BM$6*$C10 -> 234.32656 | BN10: =+SUM(AI10:BM10) -> 4872.2372 | BO10: =+BO$6*$C10 -> 234.32656 | BP10: 0 | BQ10: =+BQ$6*$C10 -> 385.94715 | BR10: =+BR$6*$C10 -> 385.94715 | BS10: =+BS$6*$C10 -> 17.411159 | BT10: =+BT$6*$C10 -> 0 | BU10: =+BU$6*$C10 -> 234.32656 | BV10: =+BV$6*$C10 -> 234.32656 | BW10: 0 | BX10: =+BX$6*$C10 -> 385.94715 | BY10: =+BY$6*$C10 -> 0 | BZ10: =+BZ$6*$C10 -> 0 | CA10: =+CA$6*$C10 -> 0 | CB10: =+CB$6*$C10 -> 234.32656 | CC10: =+CC$6*$C10 -> 234.32656 | CD10: 0 | CE10: =+CE$6*$C10 -> 385.94715 | CF10: =+CF$6*$C10 -> 0 | CG10: =+CG$6*$C10 -> 17.411159 | CH10: =+CH$6*$C10 -> 161.05516 | CI10: =+CI$6*$C10 -> 234.32656 | CJ10: =+CJ$6*$C10 -> 234.32656 | CK10: 0 | CL10: =+CL$6*$C10 -> 385.94715 | CM10: =+CM$6*$C10 -> 385.94715 | CN10: =+CN$6*$C10 -> 17.411159 | CO10: =+CO$6*$C10 -> 0 | CP10: =+CP$6*$C10 -> 234.32656 | CQ10: =+CQ$6*$C10 -> 234.32656 | CR10: 0 | CS10: =SUM(BO10:CR10) -> 4637.9106 | CT10: =+CT$6*$C10 -> 385.94715 | CU10: =+CU$6*$C10 -> 385.94715 | CV10: =+CV$6*$C10 -> 17.411159 | CW10: =+CW$6*$C10 -> 0 | CX10: =+CX$6*$C10 -> 234.32656 | CY10: =+CY$6*$C10 -> 234.32656 | CZ10: =+CZ$6*$C10 -> 234.32656 | DA10: =+DA$6*$C10 -> 385.94715 | ... DD10: =+DD$6*$C10 -> 0 | DE10: 0 | DF10: =+DF$6*$C10 -> 234.32656 | DG10: =+DG$6*$C10 -> 234.32656 | DH10: =+DH$6*$C10 -> 385.94715 | DI10: =+DI$6*$C10 -> 0 | DJ10: =+DJ$6*$C10 -> 17.411159 | DK10: =+DK$6*$C10 -> 161.05516 | DL10: 0 | DM10: =+DM$6*$C10 -> 234.32656 | DN10: =+DN$6*$C10 -> 234.32656 | DO10: =+DO$6*$C10 -> 385.94715 | DP10: =+DP$6*$C10 -> 385.94715 | DQ10: =+DQ$6*$C10 -> 17.411159 | DR10: =+DR$6*$C10 -> 0 | DS10: 0 | DT10: =+DT$6*$C10 -> 234.32656 | DU10: =+DU$6*$C10 -> 234.32656 | DV10: =+DV$6*$C10 -> 385.94715 | DW10: =+DW$6*$C10 -> 0 | DX10: =+DX$6*$C10 -> 0 | DY10: =+SUM(CT10:DX10) -> 5023.8578 | DZ10: =+DZ$6*$C10 -> 0 | EA10: =+EA$6*$C10 -> 234.32656 | EB10: =+EB$6*$C10 -> 234.32656 | EC10: =+EC$6*$C10 -> 234.32656 | ED10: =+ED$6*$C10 -> 385.94715 | EE10: =+EE$6*$C10 -> 0 | EF10: =+EF$6*$C10 -> 0 | EG10: =+EG$6*$C10 -> 0 | ... EJ10: =+EJ$6*$C10 -> 234.32656 | EK10: 0 | EL10: =+EL$6*$C10 -> 0 | EM10: =+EM$6*$C10 -> 17.411159 | EN10: =+EN$6*$C10 -> 161.05516 | EO10: =+EO$6*$C10 -> 234.32656 | EP10: =+EP$6*$C10 -> 234.32656 | EQ10: =+EQ$6*$C10 -> 234.32656 | ER10: 0 | ES10: =+ES$6*$C10 -> 385.94715 | ET10: =+ET$6*$C10 -> 17.411159 | EU10: =+EU$6*$C10 -> 0 | EV10: =+EV$6*$C10 -> 234.32656 | EW10: =+EW$6*$C10 -> 234.32656 | EX10: =+EX$6*$C10 -> 234.32656 | EY10: 0 | EZ10: =+EZ$6*$C10 -> 0 | FA10: =+FA$6*$C10 -> 0 | FB10: =+FB$6*$C10 -> 0 | FC10: =+FC$6*$C10 -> 234.32656 | FD10: =+SUM(DZ10:FC10) -> 4014.0171 | FE10: =+FE$6*$C10 -> 234.32656 | FF10: =+FF$6*$C10 -> 385.94715 | FG10: =+FG$6*$C10 -> 0 | FH10: =+FH$6*$C10 -> 0 | FI10: =+FI$6*$C10 -> 0 | FJ10: =+FJ$6*$C10 -> 234.32656 | FK10: =+FK$6*$C10 -> 234.32656 | FL10: =+FL$6*$C10 -> 234.32656 | ... FO10: =+FO$6*$C10 -> 17.411159 | FP10: 0 | FQ10: =+FQ$6*$C10 -> 234.32656 | FR10: =+FR$6*$C10 -> 234.32656 | FS10: =+FS$6*$C10 -> 234.32656 | FT10: =+FT$6*$C10 -> 385.94715 | FU10: =+FU$6*$C10 -> 385.94715 | FV10: =+FV$6*$C10 -> 17.411159 | FW10: 0 | FX10: =+FX$6*$C10 -> 234.32656 | FY10: =+FY$6*$C10 -> 234.32656 | FZ10: =+FZ$6*$C10 -> 234.32656 | GA10: =+GA$6*$C10 -> 385.94715 | GB10: =+GB$6*$C10 -> 0 | GC10: =+GC$6*$C10 -> 0 | GD10: 0 | GE10: =+GE$6*$C10 -> 234.32656 | GF10: =+GF$6*$C10 -> 234.32656 | GG10: =+GG$6*$C10 -> 234.32656 | GH10: =+GH$6*$C10 -> 385.94715 | GI10: =+GI$6*$C10 -> 0 | GJ10: =+SUM(FE10:GI10) -> 5396.7505 | GK10: =+GK$6*$C10 -> 0 | GL10: =+GL$6*$C10 -> 0 | GM10: =+GM$6*$C10 -> 234.32656 | GN10: =+GN$6*$C10 -> 234.32656 | GO10: =+GO$6*$C10 -> 234.32656 | GP10: =+GP$6*$C10 -> 385.94715 | GQ10: =+GQ$6*$C10 -> 0 | GR10: =+GR$6*$C10 -> 17.411159 | ... GU10: =+GU$6*$C10 -> 234.32656 | GV10: 0 | GW10: =+GW$6*$C10 -> 385.94715 | GX10: =+GX$6*$C10 -> 385.94715 | GY10: =+GY$6*$C10 -> 17.411159 | GZ10: =+GZ$6*$C10 -> 0 | HA10: =+HA$6*$C10 -> 234.32656 | HB10: =+HB$6*$C10 -> 234.32656 | HC10: 0 | HD10: =+HD$6*$C10 -> 385.94715 | HE10: =+HE$6*$C10 -> 0 | HF10: =+HF$6*$C10 -> 0 | HG10: =+HG$6*$C10 -> 0 | HH10: =+HH$6*$C10 -> 234.32656 | HI10: =+HI$6*$C10 -> 234.32656 | HJ10: 0 | HK10: =+HK$6*$C10 -> 385.94715 | HL10: =+HL$6*$C10 -> 0 | HM10: =+HM$6*$C10 -> 17.411159 | HN10: =+HN$6*$C10 -> 161.05516 | HO10: =+HO$6*$C10 -> 234.32656 | HP10: =+SUM(GK10:HO10) -> 4647.3452 | HQ10: =+HQ$6*$C10 -> 234.32656 | HR10: =+HR$6*$C10 -> 234.32656 | HS10: =+HS$6*$C10 -> 385.94715 | HT10: =+HT$6*$C10 -> 0 | HU10: =+HU$6*$C10 -> 17.411159 | HV10: =+HV$6*$C10 -> 161.05516 | HW10: =+HW$6*$C10 -> 234.32656 | HX10: =+HX$6*$C10 -> 234.32656 | ... IA10: =+IA$6*$C10 -> 385.94715 | IB10: 0 | IC10: =+IC$6*$C10 -> 0 | ID10: =+ID$6*$C10 -> 234.32656 | IE10: =+IE$6*$C10 -> 234.32656 | IF10: =+IF$6*$C10 -> 234.32656 | IG10: =+IG$6*$C10 -> 385.94715 | IH10: =+IH$6*$C10 -> 0 | II10: 0 | IJ10: =+IJ$6*$C10 -> 0 | IK10: =+IK$6*$C10 -> 234.32656 | IL10: =+IL$6*$C10 -> 234.32656 | IM10: =+IM$6*$C10 -> 234.32656 | IN10: =+IN$6*$C10 -> 385.94715 | IO10: =+IO$6*$C10 -> 0 | IP10: 0 | IQ10: =+IQ$6*$C10 -> 161.05516 | IR10: =+IR$6*$C10 -> 234.32656 | IS10: =+IS$6*$C10 -> 234.32656 | IT10: =+IT$6*$C10 -> 234.32656 | IU10: =+SUM(HQ10:IT10) -> 5549.8291 | IV10: =+IV$6*$C10 -> 0 | IW10: =+IW$6*$C10 -> 17.411159 | IX10: =+IX$6*$C10 -> 161.05516 | IY10: =+IY$6*$C10 -> 234.32656 | IZ10: =+IZ$6*$C10 -> 234.32656 | JA10: =+JA$6*$C10 -> 234.32656 | JB10: =+JB$6*$C10 -> 385.94715 | JC10: =+JC$6*$C10 -> 385.94715 | ... JF10: =+JF$6*$C10 -> 234.32656 | JG10: 0 | JH10: =+JH$6*$C10 -> 234.32656 | JI10: =+JI$6*$C10 -> 385.94715 | JJ10: =+JJ$6*$C10 -> 0 | JK10: =+JK$6*$C10 -> 0 | JL10: =+JL$6*$C10 -> 0 | JM10: =+JM$6*$C10 -> 234.32656 | JN10: 0 | JO10: =+JO$6*$C10 -> 234.32656 | JP10: =+JP$6*$C10 -> 385.94715 | JQ10: =+JQ$6*$C10 -> 0 | JR10: =+JR$6*$C10 -> 17.411159 | JS10: =+JS$6*$C10 -> 161.05516 | JT10: =+JT$6*$C10 -> 234.32656 | JU10: 0 | JV10: =+JV$6*$C10 -> 234.32656 | JW10: =+JW$6*$C10 -> 385.94715 | JX10: =+JX$6*$C10 -> 385.94715 | JY10: =+JY$6*$C10 -> 17.411159 | JZ10: =+JZ$6*$C10 -> 0 | KA10: =+SUM(IV10:JZ10) -> 4816.3769 | KB10: =+KB$6*$C10 -> 234.32656 | KC10: =+KC$6*$C10 -> 234.32656 | KD10: =+KD$6*$C10 -> 234.32656 | KE10: =+KE$6*$C10 -> 385.94715 | KF10: =+KF$6*$C10 -> 385.94715 | KG10: =+KG$6*$C10 -> 17.411159 | KH10: =+KH$6*$C10 -> 0 | KI10: =+KI$6*$C10 -> 234.32656 | ... KL10: =+KL$6*$C10 -> 385.94715 | KM10: 0 | KN10: =+KN$6*$C10 -> 0 | KO10: =+KO$6*$C10 -> 0 | KP10: =+KP$6*$C10 -> 234.32656 | KQ10: =+KQ$6*$C10 -> 234.32656 | KR10: =+KR$6*$C10 -> 234.32656 | KS10: =+KS$6*$C10 -> 385.94715 | KT10: 0 | KU10: =+KU$6*$C10 -> 17.411159 | KV10: =+KV$6*$C10 -> 161.05516 | KW10: =+KW$6*$C10 -> 234.32656 | KX10: =+KX$6*$C10 -> 234.32656 | KY10: =+KY$6*$C10 -> 234.32656 | KZ10: =+KZ$6*$C10 -> 385.94715 | LA10: 0 | LB10: =+LB$6*$C10 -> 17.411159 | LC10: =+LC$6*$C10 -> 0 | LD10: =+LD$6*$C10 -> 234.32656 | LE10: =+LE$6*$C10 -> 234.32656 | LF10: =+SUM(KB10:LE10) -> 5423.5963 | LG10: =+LG$6*$C10 -> 385.94715 | LH10: =+LH$6*$C10 -> 385.94715 | LI10: =+LI$6*$C10 -> 17.411159 | LJ10: =+LJ$6*$C10 -> 0 | LK10: =+LK$6*$C10 -> 234.32656 | LL10: =+LL$6*$C10 -> 234.32656 | LM10: =+LM$6*$C10 -> 234.32656 | LN10: =+LN$6*$C10 -> 385.94715 | ... LQ10: =+LQ$6*$C10 -> 0 | LR10: 0 | LS10: =+LS$6*$C10 -> 234.32656 | LT10: =+LT$6*$C10 -> 234.32656 | LU10: =+LU$6*$C10 -> 385.94715 | LV10: =+LV$6*$C10 -> 0 | LW10: =+LW$6*$C10 -> 17.411159 | LX10: =+LX$6*$C10 -> 161.05516 | LY10: 0 | LZ10: =+LZ$6*$C10 -> 234.32656 | MA10: =+MA$6*$C10 -> 234.32656 | MB10: =+MB$6*$C10 -> 385.94715 | MC10: =+MC$6*$C10 -> 385.94715 | MD10: =+MD$6*$C10 -> 17.411159 | ME10: =+ME$6*$C10 -> 0 | MF10: 0 | MG10: =+MG$6*$C10 -> 234.32656 | MH10: =+MH$6*$C10 -> 234.32656 | MI10: =+MI$6*$C10 -> 385.94715 | MJ10: =+MJ$6*$C10 -> 0 | MK10: =+MK$6*$C10 -> 0 | ML10: =+SUM(LG10:MK10) -> 5023.8578 | MM10: =+MM$6*$C10 -> 0 | MN10: =+MN$6*$C10 -> 234.32656 | MO10: =+MO$6*$C10 -> 234.32656 | MP10: =+MP$6*$C10 -> 234.32656 | MQ10: =+MQ$6*$C10 -> 385.94715 | MR10: =+MR$6*$C10 -> 0 | MS10: =+MS$6*$C10 -> 0 | MT10: =+MT$6*$C10 -> 0 | ... MW10: =+MW$6*$C10 -> 234.32656 | MX10: 0 | MY10: =+MY$6*$C10 -> 0 | MZ10: =+MZ$6*$C10 -> 17.411159 | NA10: =+NA$6*$C10 -> 161.05516 | NB10: =+NB$6*$C10 -> 234.32656 | NC10: =+NC$6*$C10 -> 234.32656 | ND10: =+ND$6*$C10 -> 234.32656 | NE10: 0 | NF10: =+NF$6*$C10 -> 385.94715 | NG10: =+NG$6*$C10 -> 17.411159 | NH10: =+NH$6*$C10 -> 0 | NI10: =+NI$6*$C10 -> 234.32656 | NJ10: =+NJ$6*$C10 -> 234.32656 | NK10: =+NK$6*$C10 -> 234.32656 | NL10: 0 | NM10: =+NM$6*$C10 -> 0 | NN10: =+NN$6*$C10 -> 0 | NO10: =+NO$6*$C10 -> 0 | NP10: =+NP$6*$C10 -> 234.32656 | NQ10: =+NQ$6*$C10 -> 234.32656 | NR10: =+SUM(MM10:NQ10) -> 4248.3436 | NS10: =+NS$6*$C10 -> 234.32656 | NT10: =+NT$6*$C10 -> 385.94715 | NU10: =+NU$6*$C10 -> 0 | NV10: =+NV$6*$C10 -> 0 | NW10: =+NW$6*$C10 -> 0 | NX10: =+NX$6*$C10 -> 234.32656 | NY10: =+NY$6*$C10 -> 234.32656 | NZ10: =+NZ$6*$C10 -> 234.32656 | ... OC10: =+OC$6*$C10 -> 17.411159 | OD10: 0 | OE10: =+OE$6*$C10 -> 234.32656 | OF10: =+OF$6*$C10 -> 234.32656 | OG10: =+OG$6*$C10 -> 234.32656 | OH10: =+OH$6*$C10 -> 385.94715 | OI10: =+OI$6*$C10 -> 385.94715 | OJ10: =+OJ$6*$C10 -> 17.411159 | OK10: 0 | OL10: =+OL$6*$C10 -> 234.32656 | OM10: =+OM$6*$C10 -> 234.32656 | ON10: =+ON$6*$C10 -> 234.32656 | OO10: =+OO$6*$C10 -> 385.94715 | OP10: =+OP$6*$C10 -> 0 | OQ10: =+OQ$6*$C10 -> 0 | OR10: 0 | OS10: =+OS$6*$C10 -> 234.32656 | OT10: =+OT$6*$C10 -> 234.32656 | OU10: =+SUM(NS10:OT10) -> 4776.4768 | OV10: =+OV$6*$C10 -> 0 | OW10: =+OW$6*$C10 -> 0 | OX10: =+OX$6*$C10 -> 234.32656 | OY10: =+OY$6*$C10 -> 234.32656 | OZ10: =+OZ$6*$C10 -> 234.32656 | PA10: =+PA$6*$C10 -> 385.94715 | PB10: =+PB$6*$C10 -> 0 | PC10: =+PC$6*$C10 -> 17.411159 | ... PF10: =+PF$6*$C10 -> 234.32656 | PG10: 0 | PH10: =+PH$6*$C10 -> 385.94715 | PI10: =+PI$6*$C10 -> 385.94715 | PJ10: =+PJ$6*$C10 -> 17.411159 | PK10: =+PK$6*$C10 -> 0 | PL10: =+PL$6*$C10 -> 234.32656 | PM10: =+PM$6*$C10 -> 234.32656 | PN10: 0 | PO10: =+PO$6*$C10 -> 385.94715 | PP10: =+PP$6*$C10 -> 0 | PQ10: =+PQ$6*$C10 -> 0 | PR10: =+PR$6*$C10 -> 0 | PS10: =+PS$6*$C10 -> 234.32656 | PT10: =+PT$6*$C10 -> 234.32656 | PU10: 0 | PV10: =+PV$6*$C10 -> 0 | PW10: =+PW$6*$C10 -> 0 | PX10: =+PX$6*$C10 -> 17.411159 | PY10: =+PY$6*$C10 -> 161.05516 | PZ10: =+PZ$6*$C10 -> 234.32656 | QA10: =+SUM(OV10:PZ10) -> 4261.398 | QB10: =+QB$6*$C10 -> 234.32656 | QC10: =+QC$6*$C10 -> 234.32656 | QD10: =+QD$6*$C10 -> 385.94715 | QE10: =+QE$6*$C10 -> 0 | QF10: =+QF$6*$C10 -> 17.411159 | QG10: =+QG$6*$C10 -> 161.05516 | QH10: =+QH$6*$C10 -> 234.32656 | QI10: =+QI$6*$C10 -> 234.32656 | ... QL10: =+QL$6*$C10 -> 385.94715 | QM10: 0 | QN10: =+QN$6*$C10 -> 0 | QO10: =+QO$6*$C10 -> 234.32656 | QP10: =+QP$6*$C10 -> 234.32656 | QQ10: =+QQ$6*$C10 -> 234.32656 | QR10: =+QR$6*$C10 -> 385.94715 | QS10: =+QS$6*$C10 -> 0 | QT10: 0 | QU10: =+QU$6*$C10 -> 0 | QV10: =+QV$6*$C10 -> 234.32656 | QW10: =+QW$6*$C10 -> 234.32656 | QX10: =+QX$6*$C10 -> 4937.532 | QY10: =+QY$6*$C10 -> 0 | QZ10: =+QZ$6*$C10 -> 0 | RA10: 0 | RB10: =+RB$6*$C10 -> 161.05516 | RC10: =+RC$6*$C10 -> 234.32656 | RD10: =+RD$6*$C10 -> 234.32656 | RE10: =+RE$6*$C10 -> 234.32656 | RF10: =+SUM(QB10:RE10) -> 9867.0874 | RG10: =+RG$6*$C10 -> 0 | RH10: =+RH$6*$C10 -> 17.411159 | RI10: =+RI$6*$C10 -> 161.05516 | RJ10: =+RJ$6*$C10 -> 234.32656 | RK10: =+RK$6*$C10 -> 234.32656 | RL10: =+RL$6*$C10 -> 234.32656 | RM10: =+RM$6*$C10 -> 385.94715 | RN10: =+RN$6*$C10 -> 385.94715 | ... RQ10: =+RQ$6*$C10 -> 234.32656 | RR10: 0 | RS10: =+RS$6*$C10 -> 234.32656 | RT10: =+RT$6*$C10 -> 385.94715 | RU10: =+RU$6*$C10 -> 0 | RV10: =+RV$6*$C10 -> 0 | RW10: =+RW$6*$C10 -> 0 | RX10: =+RX$6*$C10 -> 234.32656 | RY10: 0 | RZ10: =+RZ$6*$C10 -> 4937.532 | SA10: =+SA$6*$C10 -> 0 | SB10: =+SB$6*$C10 -> 0 | SC10: =+SC$6*$C10 -> 17.411159 | SD10: =+SD$6*$C10 -> 161.05516 | SE10: =+SE$6*$C10 -> 234.32656 | SF10: 0 | SG10: =+SG$6*$C10 -> 234.32656 | SH10: =+SH$6*$C10 -> 385.94715 | SI10: =+SI$6*$C10 -> 385.94715 | SJ10: =+SJ$6*$C10 -> 17.411159 | SK10: =+SK$6*$C10 -> 0 | SL10: =+SUM(RG10:SK10) -> 9133.6352 | SM10: =+SM$6*$C10 -> 234.32656 | SN10: =+SN$6*$C10 -> 234.32656 | SO10: =+SO$6*$C10 -> 234.32656 | SP10: =+SP$6*$C10 -> 385.94715 | SQ10: =+SQ$6*$C10 -> 385.94715 | SR10: =+SR$6*$C10 -> 17.411159 | SS10: =+SS$6*$C10 -> 0 | ST10: =+ST$6*$C10 -> 234.32656 | ... SW10: =+SW$6*$C10 -> 385.94715 | SX10: 0 | SY10: =+SY$6*$C10 -> 0 | SZ10: =+SZ$6*$C10 -> 0 | TA10: =+TA$6*$C10 -> 234.32656 | TB10: =+TB$6*$C10 -> 234.32656 | TC10: =+TC$6*$C10 -> 4937.532 | TD10: =+TD$6*$C10 -> 0 | TE10: 0 | TF10: =+TF$6*$C10 -> 17.411159 | TG10: =+TG$6*$C10 -> 161.05516 | TH10: =+TH$6*$C10 -> 234.32656 | TI10: =+TI$6*$C10 -> 234.32656 | TJ10: =+TJ$6*$C10 -> 234.32656 | TK10: =+TK$6*$C10 -> 385.94715 | TL10: 0 | TM10: =+TM$6*$C10 -> 17.411159 | TN10: =+TN$6*$C10 -> 0 | TO10: =+TO$6*$C10 -> 234.32656 | TP10: =+TP$6*$C10 -> 234.32656 | TQ10: =+SUM(SM10:TP10) -> 9740.8545 | TR10: =+TR$6*$C10 -> 385.94715 | TS10: =+TS$6*$C10 -> 385.94715 | TT10: =+TT$6*$C10 -> 17.411159 | TU10: =+TU$6*$C10 -> 0 | TV10: =+TV$6*$C10 -> 234.32656 | TW10: =+TW$6*$C10 -> 234.32656 | TX10: =+TX$6*$C10 -> 234.32656 | TY10: =+TY$6*$C10 -> 385.94715 | ... UB10: =+UB$6*$C10 -> 0 | UC10: 0 | UD10: =+UD$6*$C10 -> 234.32656 | UE10: =+UE$6*$C10 -> 4937.532 | UF10: =+UF$6*$C10 -> 0 | UG10: =+UG$6*$C10 -> 0 | UH10: =+UH$6*$C10 -> 17.411159 | UI10: =+UI$6*$C10 -> 161.05516 | UJ10: 0 | UK10: =+UK$6*$C10 -> 234.32656 | UL10: =+UL$6*$C10 -> 234.32656 | UM10: =+UM$6*$C10 -> 385.94715 | UN10: =+UN$6*$C10 -> 385.94715 | UO10: =+UO$6*$C10 -> 17.411159 | UP10: =+UP$6*$C10 -> 0 | UQ10: 0 | UR10: =+UR$6*$C10 -> 234.32656 | US10: =+US$6*$C10 -> 234.32656 | UT10: =+UT$6*$C10 -> 385.94715 | UU10: =+UU$6*$C10 -> 0 | UV10: =+UV$6*$C10 -> 0 | UW10: =+SUM(TR10:UV10) -> 9341.116 | UX10: =+UX$6*$C10 -> 0 | UY10: =+UY$6*$C10 -> 234.32656 | UZ10: =+UZ$6*$C10 -> 234.32656 | VA10: =+VA$6*$C10 -> 234.32656 | VB10: =+VB$6*$C10 -> 385.94715 | VC10: =+VC$6*$C10 -> 0 | VD10: =+VD$6*$C10 -> 0 | VE10: =+VE$6*$C10 -> 0 | ... VH10: =+VH$6*$C10 -> 4937.532 | VI10: 0 | VJ10: =+VJ$6*$C10 -> 0 | VK10: =+VK$6*$C10 -> 17.411159 | VL10: =+VL$6*$C10 -> 161.05516 | VM10: =+VM$6*$C10 -> 234.32656 | VN10: =+VN$6*$C10 -> 234.32656 | VO10: =+VO$6*$C10 -> 234.32656 | VP10: 0 | VQ10: =+VQ$6*$C10 -> 385.94715 | VR10: =+VR$6*$C10 -> 17.411159 | VS10: =+VS$6*$C10 -> 0 | VT10: =+VT$6*$C10 -> 234.32656 | VU10: =+VU$6*$C10 -> 234.32656 | VV10: =+VV$6*$C10 -> 234.32656 | VW10: 0 | VX10: =+VX$6*$C10 -> 0 | VY10: =+VY$6*$C10 -> 0 | VZ10: =+VZ$6*$C10 -> 0 | WA10: =+WA$6*$C10 -> 234.32656 | WB10: =+WB$6*$C10 -> 234.32656 | WC10: =+SUM(UX10:WB10) -> 8951.5491
B11: BOLETO (D+1) | C11: =+[4]DRE!AC12 -> 0.4734325 | D11: =+D$6*$C11 -> 0 | E11: =+E$6*$C11 -> 0 | F11: =+F$6*$C11 -> 23169.868 | G11: =+G$6*$C11 -> 23169.868 | H11: =+H$6*$C11 -> 23169.868 | I11: =+I$6*$C11 -> 38161.891 | J11: =+J$6*$C11 -> 38161.891 | K11: =+K$6*$C11 -> 1721.5899 | ... AE11: =+AE$6*$C11 -> 38161.891 | AH11: =+SUM(D11:AE11) -> 526377.84 | AI11: =+AI$6*$C11 -> 0 | AJ11: =+AJ$6*$C11 -> 0 | AK11: =+AK$6*$C11 -> 23169.868 | AL11: =+AL$6*$C11 -> 23169.868 | AM11: =+AM$6*$C11 -> 23169.868 | AN11: =+AN$6*$C11 -> 38161.891 | AO11: =+AO$6*$C11 -> 38161.891 | AP11: =+AP$6*$C11 -> 1721.5899 | ... AS11: =+AS$6*$C11 -> 23169.868 | AT11: 0 | AU11: =+AU$6*$C11 -> 38161.891 | AV11: =+AV$6*$C11 -> 0 | AW11: =+AW$6*$C11 -> 0 | AX11: =+AX$6*$C11 -> 0 | AY11: =+AY$6*$C11 -> 23169.868 | AZ11: =+AZ$6*$C11 -> 23169.868 | BA11: 0 | BB11: =+BB$6*$C11 -> 38161.891 | BC11: =+BC$6*$C11 -> 0 | BD11: =+BD$6*$C11 -> 1721.5899 | BE11: =+BE$6*$C11 -> 15924.899 | BF11: =+BF$6*$C11 -> 23169.868 | BG11: =+BG$6*$C11 -> 23169.868 | BH11: 0 | BI11: =+BI$6*$C11 -> 38161.891 | BJ11: =+BJ$6*$C11 -> 38161.891 | BK11: =+BK$6*$C11 -> 1721.5899 | BL11: =+BL$6*$C11 -> 0 | BM11: =+BM$6*$C11 -> 23169.868 | BN11: =+SUM(AI11:BM11) -> 481759.69 | BO11: =+BO$6*$C11 -> 23169.868 | BP11: 0 | BQ11: =+BQ$6*$C11 -> 38161.891 | BR11: =+BR$6*$C11 -> 38161.891 | BS11: =+BS$6*$C11 -> 1721.5899 | BT11: =+BT$6*$C11 -> 0 | BU11: =+BU$6*$C11 -> 23169.868 | BV11: =+BV$6*$C11 -> 23169.868 | BW11: 0 | BX11: =+BX$6*$C11 -> 38161.891 | BY11: =+BY$6*$C11 -> 0 | BZ11: =+BZ$6*$C11 -> 0 | CA11: =+CA$6*$C11 -> 0 | CB11: =+CB$6*$C11 -> 23169.868 | CC11: =+CC$6*$C11 -> 23169.868 | CD11: 0 | CE11: =+CE$6*$C11 -> 38161.891 | CF11: =+CF$6*$C11 -> 0 | CG11: =+CG$6*$C11 -> 1721.5899 | CH11: =+CH$6*$C11 -> 15924.899 | CI11: =+CI$6*$C11 -> 23169.868 | CJ11: =+CJ$6*$C11 -> 23169.868 | CK11: 0 | CL11: =+CL$6*$C11 -> 38161.891 | CM11: =+CM$6*$C11 -> 38161.891 | CN11: =+CN$6*$C11 -> 1721.5899 | CO11: =+CO$6*$C11 -> 0 | CP11: =+CP$6*$C11 -> 23169.868 | CQ11: =+CQ$6*$C11 -> 23169.868 | CR11: 0 | CS11: =SUM(BO11:CR11) -> 458589.82 | CT11: =+CT$6*$C11 -> 38161.891 | CU11: =+CU$6*$C11 -> 38161.891 | CV11: =+CV$6*$C11 -> 1721.5899 | CW11: =+CW$6*$C11 -> 0 | CX11: =+CX$6*$C11 -> 23169.868 | CY11: =+CY$6*$C11 -> 23169.868 | CZ11: =+CZ$6*$C11 -> 23169.868 | DA11: =+DA$6*$C11 -> 38161.891 | ... DD11: =+DD$6*$C11 -> 0 | DE11: 0 | DF11: =+DF$6*$C11 -> 23169.868 | DG11: =+DG$6*$C11 -> 23169.868 | DH11: =+DH$6*$C11 -> 38161.891 | DI11: =+DI$6*$C11 -> 0 | DJ11: =+DJ$6*$C11 -> 1721.5899 | DK11: =+DK$6*$C11 -> 15924.899 | DL11: 0 | DM11: =+DM$6*$C11 -> 23169.868 | DN11: =+DN$6*$C11 -> 23169.868 | DO11: =+DO$6*$C11 -> 38161.891 | DP11: =+DP$6*$C11 -> 38161.891 | DQ11: =+DQ$6*$C11 -> 1721.5899 | DR11: =+DR$6*$C11 -> 0 | DS11: 0 | DT11: =+DT$6*$C11 -> 23169.868 | DU11: =+DU$6*$C11 -> 23169.868 | DV11: =+DV$6*$C11 -> 38161.891 | DW11: =+DW$6*$C11 -> 0 | DX11: =+DX$6*$C11 -> 0 | DY11: =+SUM(CT11:DX11) -> 496751.71 | DZ11: =+DZ$6*$C11 -> 0 | EA11: =+EA$6*$C11 -> 23169.868 | EB11: =+EB$6*$C11 -> 23169.868 | EC11: =+EC$6*$C11 -> 23169.868 | ED11: =+ED$6*$C11 -> 38161.891 | EE11: =+EE$6*$C11 -> 0 | EF11: =+EF$6*$C11 -> 0 | EG11: =+EG$6*$C11 -> 0 | ... EJ11: =+EJ$6*$C11 -> 23169.868 | EK11: 0 | EL11: =+EL$6*$C11 -> 0 | EM11: =+EM$6*$C11 -> 1721.5899 | EN11: =+EN$6*$C11 -> 15924.899 | EO11: =+EO$6*$C11 -> 23169.868 | EP11: =+EP$6*$C11 -> 23169.868 | EQ11: =+EQ$6*$C11 -> 23169.868 | ER11: 0 | ES11: =+ES$6*$C11 -> 38161.891 | ET11: =+ET$6*$C11 -> 1721.5899 | EU11: =+EU$6*$C11 -> 0 | EV11: =+EV$6*$C11 -> 23169.868 | EW11: =+EW$6*$C11 -> 23169.868 | EX11: =+EX$6*$C11 -> 23169.868 | EY11: 0 | EZ11: =+EZ$6*$C11 -> 0 | FA11: =+FA$6*$C11 -> 0 | FB11: =+FB$6*$C11 -> 0 | FC11: =+FC$6*$C11 -> 23169.868 | FD11: =+SUM(DZ11:FC11) -> 396900.14 | FE11: =+FE$6*$C11 -> 23169.868 | FF11: =+FF$6*$C11 -> 38161.891 | FG11: =+FG$6*$C11 -> 0 | FH11: =+FH$6*$C11 -> 0 | FI11: =+FI$6*$C11 -> 0 | FJ11: =+FJ$6*$C11 -> 23169.868 | FK11: =+FK$6*$C11 -> 23169.868 | FL11: =+FL$6*$C11 -> 23169.868 | ... FO11: =+FO$6*$C11 -> 1721.5899 | FP11: 0 | FQ11: =+FQ$6*$C11 -> 23169.868 | FR11: =+FR$6*$C11 -> 23169.868 | FS11: =+FS$6*$C11 -> 23169.868 | FT11: =+FT$6*$C11 -> 38161.891 | FU11: =+FU$6*$C11 -> 38161.891 | FV11: =+FV$6*$C11 -> 1721.5899 | FW11: 0 | FX11: =+FX$6*$C11 -> 23169.868 | FY11: =+FY$6*$C11 -> 23169.868 | FZ11: =+FZ$6*$C11 -> 23169.868 | GA11: =+GA$6*$C11 -> 38161.891 | GB11: =+GB$6*$C11 -> 0 | GC11: =+GC$6*$C11 -> 0 | GD11: 0 | GE11: =+GE$6*$C11 -> 23169.868 | GF11: =+GF$6*$C11 -> 23169.868 | GG11: =+GG$6*$C11 -> 23169.868 | GH11: =+GH$6*$C11 -> 38161.891 | GI11: =+GI$6*$C11 -> 0 | GJ11: =+SUM(FE11:GI11) -> 533622.8 | GK11: =+GK$6*$C11 -> 0 | GL11: =+GL$6*$C11 -> 0 | GM11: =+GM$6*$C11 -> 23169.868 | GN11: =+GN$6*$C11 -> 23169.868 | GO11: =+GO$6*$C11 -> 23169.868 | GP11: =+GP$6*$C11 -> 38161.891 | GQ11: =+GQ$6*$C11 -> 0 | GR11: =+GR$6*$C11 -> 1721.5899 | ... GU11: =+GU$6*$C11 -> 23169.868 | GV11: 0 | GW11: =+GW$6*$C11 -> 38161.891 | GX11: =+GX$6*$C11 -> 38161.891 | GY11: =+GY$6*$C11 -> 1721.5899 | GZ11: =+GZ$6*$C11 -> 0 | HA11: =+HA$6*$C11 -> 23169.868 | HB11: =+HB$6*$C11 -> 23169.868 | HC11: 0 | HD11: =+HD$6*$C11 -> 38161.891 | HE11: =+HE$6*$C11 -> 0 | HF11: =+HF$6*$C11 -> 0 | HG11: =+HG$6*$C11 -> 0 | HH11: =+HH$6*$C11 -> 23169.868 | HI11: =+HI$6*$C11 -> 23169.868 | HJ11: 0 | HK11: =+HK$6*$C11 -> 38161.891 | HL11: =+HL$6*$C11 -> 0 | HM11: =+HM$6*$C11 -> 1721.5899 | HN11: =+HN$6*$C11 -> 15924.899 | HO11: =+HO$6*$C11 -> 23169.868 | HP11: =+SUM(GK11:HO11) -> 459522.7 | HQ11: =+HQ$6*$C11 -> 23169.868 | HR11: =+HR$6*$C11 -> 23169.868 | HS11: =+HS$6*$C11 -> 38161.891 | HT11: =+HT$6*$C11 -> 0 | HU11: =+HU$6*$C11 -> 1721.5899 | HV11: =+HV$6*$C11 -> 15924.899 | HW11: =+HW$6*$C11 -> 23169.868 | HX11: =+HX$6*$C11 -> 23169.868 | ... IA11: =+IA$6*$C11 -> 38161.891 | IB11: 0 | IC11: =+IC$6*$C11 -> 0 | ID11: =+ID$6*$C11 -> 23169.868 | IE11: =+IE$6*$C11 -> 23169.868 | IF11: =+IF$6*$C11 -> 23169.868 | IG11: =+IG$6*$C11 -> 38161.891 | IH11: =+IH$6*$C11 -> 0 | II11: 0 | IJ11: =+IJ$6*$C11 -> 0 | IK11: =+IK$6*$C11 -> 23169.868 | IL11: =+IL$6*$C11 -> 23169.868 | IM11: =+IM$6*$C11 -> 23169.868 | IN11: =+IN$6*$C11 -> 38161.891 | IO11: =+IO$6*$C11 -> 0 | IP11: 0 | IQ11: =+IQ$6*$C11 -> 15924.899 | IR11: =+IR$6*$C11 -> 23169.868 | IS11: =+IS$6*$C11 -> 23169.868 | IT11: =+IT$6*$C11 -> 23169.868 | IU11: =+SUM(HQ11:IT11) -> 548758.99 | IV11: =+IV$6*$C11 -> 0 | IW11: =+IW$6*$C11 -> 1721.5899 | IX11: =+IX$6*$C11 -> 15924.899 | IY11: =+IY$6*$C11 -> 23169.868 | IZ11: =+IZ$6*$C11 -> 23169.868 | JA11: =+JA$6*$C11 -> 23169.868 | JB11: =+JB$6*$C11 -> 38161.891 | JC11: =+JC$6*$C11 -> 38161.891 | ... JF11: =+JF$6*$C11 -> 23169.868 | JG11: 0 | JH11: =+JH$6*$C11 -> 23169.868 | JI11: =+JI$6*$C11 -> 38161.891 | JJ11: =+JJ$6*$C11 -> 0 | JK11: =+JK$6*$C11 -> 0 | JL11: =+JL$6*$C11 -> 0 | JM11: =+JM$6*$C11 -> 23169.868 | JN11: 0 | JO11: =+JO$6*$C11 -> 23169.868 | JP11: =+JP$6*$C11 -> 38161.891 | JQ11: =+JQ$6*$C11 -> 0 | JR11: =+JR$6*$C11 -> 1721.5899 | JS11: =+JS$6*$C11 -> 15924.899 | JT11: =+JT$6*$C11 -> 23169.868 | JU11: 0 | JV11: =+JV$6*$C11 -> 23169.868 | JW11: =+JW$6*$C11 -> 38161.891 | JX11: =+JX$6*$C11 -> 38161.891 | JY11: =+JY$6*$C11 -> 1721.5899 | JZ11: =+JZ$6*$C11 -> 0 | KA11: =+SUM(IV11:JZ11) -> 476236.31 | KB11: =+KB$6*$C11 -> 23169.868 | KC11: =+KC$6*$C11 -> 23169.868 | KD11: =+KD$6*$C11 -> 23169.868 | KE11: =+KE$6*$C11 -> 38161.891 | KF11: =+KF$6*$C11 -> 38161.891 | KG11: =+KG$6*$C11 -> 1721.5899 | KH11: =+KH$6*$C11 -> 0 | KI11: =+KI$6*$C11 -> 23169.868 | ... KL11: =+KL$6*$C11 -> 38161.891 | KM11: 0 | KN11: =+KN$6*$C11 -> 0 | KO11: =+KO$6*$C11 -> 0 | KP11: =+KP$6*$C11 -> 23169.868 | KQ11: =+KQ$6*$C11 -> 23169.868 | KR11: =+KR$6*$C11 -> 23169.868 | KS11: =+KS$6*$C11 -> 38161.891 | KT11: 0 | KU11: =+KU$6*$C11 -> 1721.5899 | KV11: =+KV$6*$C11 -> 15924.899 | KW11: =+KW$6*$C11 -> 23169.868 | KX11: =+KX$6*$C11 -> 23169.868 | KY11: =+KY$6*$C11 -> 23169.868 | KZ11: =+KZ$6*$C11 -> 38161.891 | LA11: 0 | LB11: =+LB$6*$C11 -> 1721.5899 | LC11: =+LC$6*$C11 -> 0 | LD11: =+LD$6*$C11 -> 23169.868 | LE11: =+LE$6*$C11 -> 23169.868 | LF11: =+SUM(KB11:LE11) -> 536277.27 | LG11: =+LG$6*$C11 -> 38161.891 | LH11: =+LH$6*$C11 -> 38161.891 | LI11: =+LI$6*$C11 -> 1721.5899 | LJ11: =+LJ$6*$C11 -> 0 | LK11: =+LK$6*$C11 -> 23169.868 | LL11: =+LL$6*$C11 -> 23169.868 | LM11: =+LM$6*$C11 -> 23169.868 | LN11: =+LN$6*$C11 -> 38161.891 | ... LQ11: =+LQ$6*$C11 -> 0 | LR11: 0 | LS11: =+LS$6*$C11 -> 23169.868 | LT11: =+LT$6*$C11 -> 23169.868 | LU11: =+LU$6*$C11 -> 38161.891 | LV11: =+LV$6*$C11 -> 0 | LW11: =+LW$6*$C11 -> 1721.5899 | LX11: =+LX$6*$C11 -> 15924.899 | LY11: 0 | LZ11: =+LZ$6*$C11 -> 23169.868 | MA11: =+MA$6*$C11 -> 23169.868 | MB11: =+MB$6*$C11 -> 38161.891 | MC11: =+MC$6*$C11 -> 38161.891 | MD11: =+MD$6*$C11 -> 1721.5899 | ME11: =+ME$6*$C11 -> 0 | MF11: 0 | MG11: =+MG$6*$C11 -> 23169.868 | MH11: =+MH$6*$C11 -> 23169.868 | MI11: =+MI$6*$C11 -> 38161.891 | MJ11: =+MJ$6*$C11 -> 0 | MK11: =+MK$6*$C11 -> 0 | ML11: =+SUM(LG11:MK11) -> 496751.71 | MM11: =+MM$6*$C11 -> 0 | MN11: =+MN$6*$C11 -> 23169.868 | MO11: =+MO$6*$C11 -> 23169.868 | MP11: =+MP$6*$C11 -> 23169.868 | MQ11: =+MQ$6*$C11 -> 38161.891 | MR11: =+MR$6*$C11 -> 0 | MS11: =+MS$6*$C11 -> 0 | MT11: =+MT$6*$C11 -> 0 | ... MW11: =+MW$6*$C11 -> 23169.868 | MX11: 0 | MY11: =+MY$6*$C11 -> 0 | MZ11: =+MZ$6*$C11 -> 1721.5899 | NA11: =+NA$6*$C11 -> 15924.899 | NB11: =+NB$6*$C11 -> 23169.868 | NC11: =+NC$6*$C11 -> 23169.868 | ND11: =+ND$6*$C11 -> 23169.868 | NE11: 0 | NF11: =+NF$6*$C11 -> 38161.891 | NG11: =+NG$6*$C11 -> 1721.5899 | NH11: =+NH$6*$C11 -> 0 | NI11: =+NI$6*$C11 -> 23169.868 | NJ11: =+NJ$6*$C11 -> 23169.868 | NK11: =+NK$6*$C11 -> 23169.868 | NL11: 0 | NM11: =+NM$6*$C11 -> 0 | NN11: =+NN$6*$C11 -> 0 | NO11: =+NO$6*$C11 -> 0 | NP11: =+NP$6*$C11 -> 23169.868 | NQ11: =+NQ$6*$C11 -> 23169.868 | NR11: =+SUM(MM11:NQ11) -> 420070.01 | NS11: =+NS$6*$C11 -> 23169.868 | NT11: =+NT$6*$C11 -> 38161.891 | NU11: =+NU$6*$C11 -> 0 | NV11: =+NV$6*$C11 -> 0 | NW11: =+NW$6*$C11 -> 0 | NX11: =+NX$6*$C11 -> 23169.868 | NY11: =+NY$6*$C11 -> 23169.868 | NZ11: =+NZ$6*$C11 -> 23169.868 | ... OC11: =+OC$6*$C11 -> 1721.5899 | OD11: 0 | OE11: =+OE$6*$C11 -> 23169.868 | OF11: =+OF$6*$C11 -> 23169.868 | OG11: =+OG$6*$C11 -> 23169.868 | OH11: =+OH$6*$C11 -> 38161.891 | OI11: =+OI$6*$C11 -> 38161.891 | OJ11: =+OJ$6*$C11 -> 1721.5899 | OK11: 0 | OL11: =+OL$6*$C11 -> 23169.868 | OM11: =+OM$6*$C11 -> 23169.868 | ON11: =+ON$6*$C11 -> 23169.868 | OO11: =+OO$6*$C11 -> 38161.891 | OP11: =+OP$6*$C11 -> 0 | OQ11: =+OQ$6*$C11 -> 0 | OR11: 0 | OS11: =+OS$6*$C11 -> 23169.868 | OT11: =+OT$6*$C11 -> 23169.868 | OU11: =+SUM(NS11:OT11) -> 472291.05 | OV11: =+OV$6*$C11 -> 0 | OW11: =+OW$6*$C11 -> 0 | OX11: =+OX$6*$C11 -> 23169.868 | OY11: =+OY$6*$C11 -> 23169.868 | OZ11: =+OZ$6*$C11 -> 23169.868 | PA11: =+PA$6*$C11 -> 38161.891 | PB11: =+PB$6*$C11 -> 0 | PC11: =+PC$6*$C11 -> 1721.5899 | ... PF11: =+PF$6*$C11 -> 23169.868 | PG11: 0 | PH11: =+PH$6*$C11 -> 38161.891 | PI11: =+PI$6*$C11 -> 38161.891 | PJ11: =+PJ$6*$C11 -> 1721.5899 | PK11: =+PK$6*$C11 -> 0 | PL11: =+PL$6*$C11 -> 23169.868 | PM11: =+PM$6*$C11 -> 23169.868 | PN11: 0 | PO11: =+PO$6*$C11 -> 38161.891 | PP11: =+PP$6*$C11 -> 0 | PQ11: =+PQ$6*$C11 -> 0 | PR11: =+PR$6*$C11 -> 0 | PS11: =+PS$6*$C11 -> 23169.868 | PT11: =+PT$6*$C11 -> 23169.868 | PU11: 0 | PV11: =+PV$6*$C11 -> 0 | PW11: =+PW$6*$C11 -> 0 | PX11: =+PX$6*$C11 -> 1721.5899 | PY11: =+PY$6*$C11 -> 15924.899 | PZ11: =+PZ$6*$C11 -> 23169.868 | QA11: =+SUM(OV11:PZ11) -> 421360.81 | QB11: =+QB$6*$C11 -> 23169.868 | QC11: =+QC$6*$C11 -> 23169.868 | QD11: =+QD$6*$C11 -> 38161.891 | QE11: =+QE$6*$C11 -> 0 | QF11: =+QF$6*$C11 -> 1721.5899 | QG11: =+QG$6*$C11 -> 15924.899 | QH11: =+QH$6*$C11 -> 23169.868 | QI11: =+QI$6*$C11 -> 23169.868 | ... QL11: =+QL$6*$C11 -> 38161.891 | QM11: 0 | QN11: =+QN$6*$C11 -> 0 | QO11: =+QO$6*$C11 -> 23169.868 | QP11: =+QP$6*$C11 -> 23169.868 | QQ11: =+QQ$6*$C11 -> 23169.868 | QR11: =+QR$6*$C11 -> 38161.891 | QS11: =+QS$6*$C11 -> 0 | QT11: 0 | QU11: =+QU$6*$C11 -> 0 | QV11: =+QV$6*$C11 -> 23169.868 | QW11: =+QW$6*$C11 -> 23169.868 | QX11: =+QX$6*$C11 -> 488215.94 | QY11: =+QY$6*$C11 -> 0 | QZ11: =+QZ$6*$C11 -> 0 | RA11: 0 | RB11: =+RB$6*$C11 -> 15924.899 | RC11: =+RC$6*$C11 -> 23169.868 | RD11: =+RD$6*$C11 -> 23169.868 | RE11: =+RE$6*$C11 -> 23169.868 | RF11: =+SUM(QB11:RE11) -> 975643.18 | RG11: =+RG$6*$C11 -> 0 | RH11: =+RH$6*$C11 -> 1721.5899 | RI11: =+RI$6*$C11 -> 15924.899 | RJ11: =+RJ$6*$C11 -> 23169.868 | RK11: =+RK$6*$C11 -> 23169.868 | RL11: =+RL$6*$C11 -> 23169.868 | RM11: =+RM$6*$C11 -> 38161.891 | RN11: =+RN$6*$C11 -> 38161.891 | ... RQ11: =+RQ$6*$C11 -> 23169.868 | RR11: 0 | RS11: =+RS$6*$C11 -> 23169.868 | RT11: =+RT$6*$C11 -> 38161.891 | RU11: =+RU$6*$C11 -> 0 | RV11: =+RV$6*$C11 -> 0 | RW11: =+RW$6*$C11 -> 0 | RX11: =+RX$6*$C11 -> 23169.868 | RY11: 0 | RZ11: =+RZ$6*$C11 -> 488215.94 | SA11: =+SA$6*$C11 -> 0 | SB11: =+SB$6*$C11 -> 0 | SC11: =+SC$6*$C11 -> 1721.5899 | SD11: =+SD$6*$C11 -> 15924.899 | SE11: =+SE$6*$C11 -> 23169.868 | SF11: 0 | SG11: =+SG$6*$C11 -> 23169.868 | SH11: =+SH$6*$C11 -> 38161.891 | SI11: =+SI$6*$C11 -> 38161.891 | SJ11: =+SJ$6*$C11 -> 1721.5899 | SK11: =+SK$6*$C11 -> 0 | SL11: =+SUM(RG11:SK11) -> 903120.5 | SM11: =+SM$6*$C11 -> 23169.868 | SN11: =+SN$6*$C11 -> 23169.868 | SO11: =+SO$6*$C11 -> 23169.868 | SP11: =+SP$6*$C11 -> 38161.891 | SQ11: =+SQ$6*$C11 -> 38161.891 | SR11: =+SR$6*$C11 -> 1721.5899 | SS11: =+SS$6*$C11 -> 0 | ST11: =+ST$6*$C11 -> 23169.868 | ... SW11: =+SW$6*$C11 -> 38161.891 | SX11: 0 | SY11: =+SY$6*$C11 -> 0 | SZ11: =+SZ$6*$C11 -> 0 | TA11: =+TA$6*$C11 -> 23169.868 | TB11: =+TB$6*$C11 -> 23169.868 | TC11: =+TC$6*$C11 -> 488215.94 | TD11: =+TD$6*$C11 -> 0 | TE11: 0 | TF11: =+TF$6*$C11 -> 1721.5899 | TG11: =+TG$6*$C11 -> 15924.899 | TH11: =+TH$6*$C11 -> 23169.868 | TI11: =+TI$6*$C11 -> 23169.868 | TJ11: =+TJ$6*$C11 -> 23169.868 | TK11: =+TK$6*$C11 -> 38161.891 | TL11: 0 | TM11: =+TM$6*$C11 -> 1721.5899 | TN11: =+TN$6*$C11 -> 0 | TO11: =+TO$6*$C11 -> 23169.868 | TP11: =+TP$6*$C11 -> 23169.868 | TQ11: =+SUM(SM11:TP11) -> 963161.46 | TR11: =+TR$6*$C11 -> 38161.891 | TS11: =+TS$6*$C11 -> 38161.891 | TT11: =+TT$6*$C11 -> 1721.5899 | TU11: =+TU$6*$C11 -> 0 | TV11: =+TV$6*$C11 -> 23169.868 | TW11: =+TW$6*$C11 -> 23169.868 | TX11: =+TX$6*$C11 -> 23169.868 | TY11: =+TY$6*$C11 -> 38161.891 | ... UB11: =+UB$6*$C11 -> 0 | UC11: 0 | UD11: =+UD$6*$C11 -> 23169.868 | UE11: =+UE$6*$C11 -> 488215.94 | UF11: =+UF$6*$C11 -> 0 | UG11: =+UG$6*$C11 -> 0 | UH11: =+UH$6*$C11 -> 1721.5899 | UI11: =+UI$6*$C11 -> 15924.899 | UJ11: 0 | UK11: =+UK$6*$C11 -> 23169.868 | UL11: =+UL$6*$C11 -> 23169.868 | UM11: =+UM$6*$C11 -> 38161.891 | UN11: =+UN$6*$C11 -> 38161.891 | UO11: =+UO$6*$C11 -> 1721.5899 | UP11: =+UP$6*$C11 -> 0 | UQ11: 0 | UR11: =+UR$6*$C11 -> 23169.868 | US11: =+US$6*$C11 -> 23169.868 | UT11: =+UT$6*$C11 -> 38161.891 | UU11: =+UU$6*$C11 -> 0 | UV11: =+UV$6*$C11 -> 0 | UW11: =+SUM(TR11:UV11) -> 923635.9 | UX11: =+UX$6*$C11 -> 0 | UY11: =+UY$6*$C11 -> 23169.868 | UZ11: =+UZ$6*$C11 -> 23169.868 | VA11: =+VA$6*$C11 -> 23169.868 | VB11: =+VB$6*$C11 -> 38161.891 | VC11: =+VC$6*$C11 -> 0 | VD11: =+VD$6*$C11 -> 0 | VE11: =+VE$6*$C11 -> 0 | ... VH11: =+VH$6*$C11 -> 488215.94 | VI11: 0 | VJ11: =+VJ$6*$C11 -> 0 | VK11: =+VK$6*$C11 -> 1721.5899 | VL11: =+VL$6*$C11 -> 15924.899 | VM11: =+VM$6*$C11 -> 23169.868 | VN11: =+VN$6*$C11 -> 23169.868 | VO11: =+VO$6*$C11 -> 23169.868 | VP11: 0 | VQ11: =+VQ$6*$C11 -> 38161.891 | VR11: =+VR$6*$C11 -> 1721.5899 | VS11: =+VS$6*$C11 -> 0 | VT11: =+VT$6*$C11 -> 23169.868 | VU11: =+VU$6*$C11 -> 23169.868 | VV11: =+VV$6*$C11 -> 23169.868 | VW11: 0 | VX11: =+VX$6*$C11 -> 0 | VY11: =+VY$6*$C11 -> 0 | VZ11: =+VZ$6*$C11 -> 0 | WA11: =+WA$6*$C11 -> 23169.868 | WB11: =+WB$6*$C11 -> 23169.868 | WC11: =+SUM(UX11:WB11) -> 885116.09
B12: OUTROS RECEBIMENTOS (D+1) | C12: =+[4]DRE!AC13 -> 0.075013039 | D12: =+D$6*$C12 -> 0 | E12: =+E$6*$C12 -> 0 | F12: =+F$6*$C12 -> 3671.151 | G12: =+G$6*$C12 -> 3671.151 | H12: =+H$6*$C12 -> 3671.151 | I12: =+I$6*$C12 -> 6046.5629 | J12: =+J$6*$C12 -> 6046.5629 | K12: =+K$6*$C12 -> 272.77741 | ... AE12: =+AE$6*$C12 -> 6046.5629 | AH12: =+SUM(D12:AE12) -> 83401.966 | AI12: =+AI$6*$C12 -> 0 | AJ12: =+AJ$6*$C12 -> 0 | AK12: =+AK$6*$C12 -> 3671.151 | AL12: =+AL$6*$C12 -> 3671.151 | AM12: =+AM$6*$C12 -> 3671.151 | AN12: =+AN$6*$C12 -> 6046.5629 | AO12: =+AO$6*$C12 -> 6046.5629 | AP12: =+AP$6*$C12 -> 272.77741 | ... AS12: =+AS$6*$C12 -> 3671.151 | AT12: 0 | AU12: =+AU$6*$C12 -> 6046.5629 | AV12: =+AV$6*$C12 -> 0 | AW12: =+AW$6*$C12 -> 0 | AX12: =+AX$6*$C12 -> 0 | AY12: =+AY$6*$C12 -> 3671.151 | AZ12: =+AZ$6*$C12 -> 3671.151 | BA12: 0 | BB12: =+BB$6*$C12 -> 6046.5629 | BC12: =+BC$6*$C12 -> 0 | BD12: =+BD$6*$C12 -> 272.77741 | BE12: =+BE$6*$C12 -> 2523.2215 | BF12: =+BF$6*$C12 -> 3671.151 | BG12: =+BG$6*$C12 -> 3671.151 | BH12: 0 | BI12: =+BI$6*$C12 -> 6046.5629 | BJ12: =+BJ$6*$C12 -> 6046.5629 | BK12: =+BK$6*$C12 -> 272.77741 | BL12: =+BL$6*$C12 -> 0 | BM12: =+BM$6*$C12 -> 3671.151 | BN12: =+SUM(AI12:BM12) -> 76332.441 | BO12: =+BO$6*$C12 -> 3671.151 | BP12: 0 | BQ12: =+BQ$6*$C12 -> 6046.5629 | BR12: =+BR$6*$C12 -> 6046.5629 | BS12: =+BS$6*$C12 -> 272.77741 | BT12: =+BT$6*$C12 -> 0 | BU12: =+BU$6*$C12 -> 3671.151 | BV12: =+BV$6*$C12 -> 3671.151 | BW12: 0 | BX12: =+BX$6*$C12 -> 6046.5629 | BY12: =+BY$6*$C12 -> 0 | BZ12: =+BZ$6*$C12 -> 0 | CA12: =+CA$6*$C12 -> 0 | CB12: =+CB$6*$C12 -> 3671.151 | CC12: =+CC$6*$C12 -> 3671.151 | CD12: 0 | CE12: =+CE$6*$C12 -> 6046.5629 | CF12: =+CF$6*$C12 -> 0 | CG12: =+CG$6*$C12 -> 272.77741 | CH12: =+CH$6*$C12 -> 2523.2215 | CI12: =+CI$6*$C12 -> 3671.151 | CJ12: =+CJ$6*$C12 -> 3671.151 | CK12: 0 | CL12: =+CL$6*$C12 -> 6046.5629 | CM12: =+CM$6*$C12 -> 6046.5629 | CN12: =+CN$6*$C12 -> 272.77741 | CO12: =+CO$6*$C12 -> 0 | CP12: =+CP$6*$C12 -> 3671.151 | CQ12: =+CQ$6*$C12 -> 3671.151 | CR12: 0 | CS12: =SUM(BO12:CR12) -> 72661.29 | CT12: =+CT$6*$C12 -> 6046.5629 | CU12: =+CU$6*$C12 -> 6046.5629 | CV12: =+CV$6*$C12 -> 272.77741 | CW12: =+CW$6*$C12 -> 0 | CX12: =+CX$6*$C12 -> 3671.151 | CY12: =+CY$6*$C12 -> 3671.151 | CZ12: =+CZ$6*$C12 -> 3671.151 | DA12: =+DA$6*$C12 -> 6046.5629 | ... DD12: =+DD$6*$C12 -> 0 | DE12: 0 | DF12: =+DF$6*$C12 -> 3671.151 | DG12: =+DG$6*$C12 -> 3671.151 | DH12: =+DH$6*$C12 -> 6046.5629 | DI12: =+DI$6*$C12 -> 0 | DJ12: =+DJ$6*$C12 -> 272.77741 | DK12: =+DK$6*$C12 -> 2523.2215 | DL12: 0 | DM12: =+DM$6*$C12 -> 3671.151 | DN12: =+DN$6*$C12 -> 3671.151 | DO12: =+DO$6*$C12 -> 6046.5629 | DP12: =+DP$6*$C12 -> 6046.5629 | DQ12: =+DQ$6*$C12 -> 272.77741 | DR12: =+DR$6*$C12 -> 0 | DS12: 0 | DT12: =+DT$6*$C12 -> 3671.151 | DU12: =+DU$6*$C12 -> 3671.151 | DV12: =+DV$6*$C12 -> 6046.5629 | DW12: =+DW$6*$C12 -> 0 | DX12: =+DX$6*$C12 -> 0 | DY12: =+SUM(CT12:DX12) -> 78707.853 | DZ12: =+DZ$6*$C12 -> 0 | EA12: =+EA$6*$C12 -> 3671.151 | EB12: =+EB$6*$C12 -> 3671.151 | EC12: =+EC$6*$C12 -> 3671.151 | ED12: =+ED$6*$C12 -> 6046.5629 | EE12: =+EE$6*$C12 -> 0 | EF12: =+EF$6*$C12 -> 0 | EG12: =+EG$6*$C12 -> 0 | ... EJ12: =+EJ$6*$C12 -> 3671.151 | EK12: 0 | EL12: =+EL$6*$C12 -> 0 | EM12: =+EM$6*$C12 -> 272.77741 | EN12: =+EN$6*$C12 -> 2523.2215 | EO12: =+EO$6*$C12 -> 3671.151 | EP12: =+EP$6*$C12 -> 3671.151 | EQ12: =+EQ$6*$C12 -> 3671.151 | ER12: 0 | ES12: =+ES$6*$C12 -> 6046.5629 | ET12: =+ET$6*$C12 -> 272.77741 | EU12: =+EU$6*$C12 -> 0 | EV12: =+EV$6*$C12 -> 3671.151 | EW12: =+EW$6*$C12 -> 3671.151 | EX12: =+EX$6*$C12 -> 3671.151 | EY12: 0 | EZ12: =+EZ$6*$C12 -> 0 | FA12: =+FA$6*$C12 -> 0 | FB12: =+FB$6*$C12 -> 0 | FC12: =+FC$6*$C12 -> 3671.151 | FD12: =+SUM(DZ12:FC12) -> 62886.865 | FE12: =+FE$6*$C12 -> 3671.151 | FF12: =+FF$6*$C12 -> 6046.5629 | FG12: =+FG$6*$C12 -> 0 | FH12: =+FH$6*$C12 -> 0 | FI12: =+FI$6*$C12 -> 0 | FJ12: =+FJ$6*$C12 -> 3671.151 | FK12: =+FK$6*$C12 -> 3671.151 | FL12: =+FL$6*$C12 -> 3671.151 | ... FO12: =+FO$6*$C12 -> 272.77741 | FP12: 0 | FQ12: =+FQ$6*$C12 -> 3671.151 | FR12: =+FR$6*$C12 -> 3671.151 | FS12: =+FS$6*$C12 -> 3671.151 | FT12: =+FT$6*$C12 -> 6046.5629 | FU12: =+FU$6*$C12 -> 6046.5629 | FV12: =+FV$6*$C12 -> 272.77741 | FW12: 0 | FX12: =+FX$6*$C12 -> 3671.151 | FY12: =+FY$6*$C12 -> 3671.151 | FZ12: =+FZ$6*$C12 -> 3671.151 | GA12: =+GA$6*$C12 -> 6046.5629 | GB12: =+GB$6*$C12 -> 0 | GC12: =+GC$6*$C12 -> 0 | GD12: 0 | GE12: =+GE$6*$C12 -> 3671.151 | GF12: =+GF$6*$C12 -> 3671.151 | GG12: =+GG$6*$C12 -> 3671.151 | GH12: =+GH$6*$C12 -> 6046.5629 | GI12: =+GI$6*$C12 -> 0 | GJ12: =+SUM(FE12:GI12) -> 84549.895 | GK12: =+GK$6*$C12 -> 0 | GL12: =+GL$6*$C12 -> 0 | GM12: =+GM$6*$C12 -> 3671.151 | GN12: =+GN$6*$C12 -> 3671.151 | GO12: =+GO$6*$C12 -> 3671.151 | GP12: =+GP$6*$C12 -> 6046.5629 | GQ12: =+GQ$6*$C12 -> 0 | GR12: =+GR$6*$C12 -> 272.77741 | ... GU12: =+GU$6*$C12 -> 3671.151 | GV12: 0 | GW12: =+GW$6*$C12 -> 6046.5629 | GX12: =+GX$6*$C12 -> 6046.5629 | GY12: =+GY$6*$C12 -> 272.77741 | GZ12: =+GZ$6*$C12 -> 0 | HA12: =+HA$6*$C12 -> 3671.151 | HB12: =+HB$6*$C12 -> 3671.151 | HC12: 0 | HD12: =+HD$6*$C12 -> 6046.5629 | HE12: =+HE$6*$C12 -> 0 | HF12: =+HF$6*$C12 -> 0 | HG12: =+HG$6*$C12 -> 0 | HH12: =+HH$6*$C12 -> 3671.151 | HI12: =+HI$6*$C12 -> 3671.151 | HJ12: 0 | HK12: =+HK$6*$C12 -> 6046.5629 | HL12: =+HL$6*$C12 -> 0 | HM12: =+HM$6*$C12 -> 272.77741 | HN12: =+HN$6*$C12 -> 2523.2215 | HO12: =+HO$6*$C12 -> 3671.151 | HP12: =+SUM(GK12:HO12) -> 72809.1 | HQ12: =+HQ$6*$C12 -> 3671.151 | HR12: =+HR$6*$C12 -> 3671.151 | HS12: =+HS$6*$C12 -> 6046.5629 | HT12: =+HT$6*$C12 -> 0 | HU12: =+HU$6*$C12 -> 272.77741 | HV12: =+HV$6*$C12 -> 2523.2215 | HW12: =+HW$6*$C12 -> 3671.151 | HX12: =+HX$6*$C12 -> 3671.151 | ... IA12: =+IA$6*$C12 -> 6046.5629 | IB12: 0 | IC12: =+IC$6*$C12 -> 0 | ID12: =+ID$6*$C12 -> 3671.151 | IE12: =+IE$6*$C12 -> 3671.151 | IF12: =+IF$6*$C12 -> 3671.151 | IG12: =+IG$6*$C12 -> 6046.5629 | IH12: =+IH$6*$C12 -> 0 | II12: 0 | IJ12: =+IJ$6*$C12 -> 0 | IK12: =+IK$6*$C12 -> 3671.151 | IL12: =+IL$6*$C12 -> 3671.151 | IM12: =+IM$6*$C12 -> 3671.151 | IN12: =+IN$6*$C12 -> 6046.5629 | IO12: =+IO$6*$C12 -> 0 | IP12: 0 | IQ12: =+IQ$6*$C12 -> 2523.2215 | IR12: =+IR$6*$C12 -> 3671.151 | IS12: =+IS$6*$C12 -> 3671.151 | IT12: =+IT$6*$C12 -> 3671.151 | IU12: =+SUM(HQ12:IT12) -> 86948.149 | IV12: =+IV$6*$C12 -> 0 | IW12: =+IW$6*$C12 -> 272.77741 | IX12: =+IX$6*$C12 -> 2523.2215 | IY12: =+IY$6*$C12 -> 3671.151 | IZ12: =+IZ$6*$C12 -> 3671.151 | JA12: =+JA$6*$C12 -> 3671.151 | JB12: =+JB$6*$C12 -> 6046.5629 | JC12: =+JC$6*$C12 -> 6046.5629 | ... JF12: =+JF$6*$C12 -> 3671.151 | JG12: 0 | JH12: =+JH$6*$C12 -> 3671.151 | JI12: =+JI$6*$C12 -> 6046.5629 | JJ12: =+JJ$6*$C12 -> 0 | JK12: =+JK$6*$C12 -> 0 | JL12: =+JL$6*$C12 -> 0 | JM12: =+JM$6*$C12 -> 3671.151 | JN12: 0 | JO12: =+JO$6*$C12 -> 3671.151 | JP12: =+JP$6*$C12 -> 6046.5629 | JQ12: =+JQ$6*$C12 -> 0 | JR12: =+JR$6*$C12 -> 272.77741 | JS12: =+JS$6*$C12 -> 2523.2215 | JT12: =+JT$6*$C12 -> 3671.151 | JU12: 0 | JV12: =+JV$6*$C12 -> 3671.151 | JW12: =+JW$6*$C12 -> 6046.5629 | JX12: =+JX$6*$C12 -> 6046.5629 | JY12: =+JY$6*$C12 -> 272.77741 | JZ12: =+JZ$6*$C12 -> 0 | KA12: =+SUM(IV12:JZ12) -> 75457.289 | KB12: =+KB$6*$C12 -> 3671.151 | KC12: =+KC$6*$C12 -> 3671.151 | KD12: =+KD$6*$C12 -> 3671.151 | KE12: =+KE$6*$C12 -> 6046.5629 | KF12: =+KF$6*$C12 -> 6046.5629 | KG12: =+KG$6*$C12 -> 272.77741 | KH12: =+KH$6*$C12 -> 0 | KI12: =+KI$6*$C12 -> 3671.151 | ... KL12: =+KL$6*$C12 -> 6046.5629 | KM12: 0 | KN12: =+KN$6*$C12 -> 0 | KO12: =+KO$6*$C12 -> 0 | KP12: =+KP$6*$C12 -> 3671.151 | KQ12: =+KQ$6*$C12 -> 3671.151 | KR12: =+KR$6*$C12 -> 3671.151 | KS12: =+KS$6*$C12 -> 6046.5629 | KT12: 0 | KU12: =+KU$6*$C12 -> 272.77741 | KV12: =+KV$6*$C12 -> 2523.2215 | KW12: =+KW$6*$C12 -> 3671.151 | KX12: =+KX$6*$C12 -> 3671.151 | KY12: =+KY$6*$C12 -> 3671.151 | KZ12: =+KZ$6*$C12 -> 6046.5629 | LA12: 0 | LB12: =+LB$6*$C12 -> 272.77741 | LC12: =+LC$6*$C12 -> 0 | LD12: =+LD$6*$C12 -> 3671.151 | LE12: =+LE$6*$C12 -> 3671.151 | LF12: =+SUM(KB12:LE12) -> 84970.482 | LG12: =+LG$6*$C12 -> 6046.5629 | LH12: =+LH$6*$C12 -> 6046.5629 | LI12: =+LI$6*$C12 -> 272.77741 | LJ12: =+LJ$6*$C12 -> 0 | LK12: =+LK$6*$C12 -> 3671.151 | LL12: =+LL$6*$C12 -> 3671.151 | LM12: =+LM$6*$C12 -> 3671.151 | LN12: =+LN$6*$C12 -> 6046.5629 | ... LQ12: =+LQ$6*$C12 -> 0 | LR12: 0 | LS12: =+LS$6*$C12 -> 3671.151 | LT12: =+LT$6*$C12 -> 3671.151 | LU12: =+LU$6*$C12 -> 6046.5629 | LV12: =+LV$6*$C12 -> 0 | LW12: =+LW$6*$C12 -> 272.77741 | LX12: =+LX$6*$C12 -> 2523.2215 | LY12: 0 | LZ12: =+LZ$6*$C12 -> 3671.151 | MA12: =+MA$6*$C12 -> 3671.151 | MB12: =+MB$6*$C12 -> 6046.5629 | MC12: =+MC$6*$C12 -> 6046.5629 | MD12: =+MD$6*$C12 -> 272.77741 | ME12: =+ME$6*$C12 -> 0 | MF12: 0 | MG12: =+MG$6*$C12 -> 3671.151 | MH12: =+MH$6*$C12 -> 3671.151 | MI12: =+MI$6*$C12 -> 6046.5629 | MJ12: =+MJ$6*$C12 -> 0 | MK12: =+MK$6*$C12 -> 0 | ML12: =+SUM(LG12:MK12) -> 78707.853 | MM12: =+MM$6*$C12 -> 0 | MN12: =+MN$6*$C12 -> 3671.151 | MO12: =+MO$6*$C12 -> 3671.151 | MP12: =+MP$6*$C12 -> 3671.151 | MQ12: =+MQ$6*$C12 -> 6046.5629 | MR12: =+MR$6*$C12 -> 0 | MS12: =+MS$6*$C12 -> 0 | MT12: =+MT$6*$C12 -> 0 | ... MW12: =+MW$6*$C12 -> 3671.151 | MX12: 0 | MY12: =+MY$6*$C12 -> 0 | MZ12: =+MZ$6*$C12 -> 272.77741 | NA12: =+NA$6*$C12 -> 2523.2215 | NB12: =+NB$6*$C12 -> 3671.151 | NC12: =+NC$6*$C12 -> 3671.151 | ND12: =+ND$6*$C12 -> 3671.151 | NE12: 0 | NF12: =+NF$6*$C12 -> 6046.5629 | NG12: =+NG$6*$C12 -> 272.77741 | NH12: =+NH$6*$C12 -> 0 | NI12: =+NI$6*$C12 -> 3671.151 | NJ12: =+NJ$6*$C12 -> 3671.151 | NK12: =+NK$6*$C12 -> 3671.151 | NL12: 0 | NM12: =+NM$6*$C12 -> 0 | NN12: =+NN$6*$C12 -> 0 | NO12: =+NO$6*$C12 -> 0 | NP12: =+NP$6*$C12 -> 3671.151 | NQ12: =+NQ$6*$C12 -> 3671.151 | NR12: =+SUM(MM12:NQ12) -> 66558.016 | NS12: =+NS$6*$C12 -> 3671.151 | NT12: =+NT$6*$C12 -> 6046.5629 | NU12: =+NU$6*$C12 -> 0 | NV12: =+NV$6*$C12 -> 0 | NW12: =+NW$6*$C12 -> 0 | NX12: =+NX$6*$C12 -> 3671.151 | NY12: =+NY$6*$C12 -> 3671.151 | NZ12: =+NZ$6*$C12 -> 3671.151 | ... OC12: =+OC$6*$C12 -> 272.77741 | OD12: 0 | OE12: =+OE$6*$C12 -> 3671.151 | OF12: =+OF$6*$C12 -> 3671.151 | OG12: =+OG$6*$C12 -> 3671.151 | OH12: =+OH$6*$C12 -> 6046.5629 | OI12: =+OI$6*$C12 -> 6046.5629 | OJ12: =+OJ$6*$C12 -> 272.77741 | OK12: 0 | OL12: =+OL$6*$C12 -> 3671.151 | OM12: =+OM$6*$C12 -> 3671.151 | ON12: =+ON$6*$C12 -> 3671.151 | OO12: =+OO$6*$C12 -> 6046.5629 | OP12: =+OP$6*$C12 -> 0 | OQ12: =+OQ$6*$C12 -> 0 | OR12: 0 | OS12: =+OS$6*$C12 -> 3671.151 | OT12: =+OT$6*$C12 -> 3671.151 | OU12: =+SUM(NS12:OT12) -> 74832.181 | OV12: =+OV$6*$C12 -> 0 | OW12: =+OW$6*$C12 -> 0 | OX12: =+OX$6*$C12 -> 3671.151 | OY12: =+OY$6*$C12 -> 3671.151 | OZ12: =+OZ$6*$C12 -> 3671.151 | PA12: =+PA$6*$C12 -> 6046.5629 | PB12: =+PB$6*$C12 -> 0 | PC12: =+PC$6*$C12 -> 272.77741 | ... PF12: =+PF$6*$C12 -> 3671.151 | PG12: 0 | PH12: =+PH$6*$C12 -> 6046.5629 | PI12: =+PI$6*$C12 -> 6046.5629 | PJ12: =+PJ$6*$C12 -> 272.77741 | PK12: =+PK$6*$C12 -> 0 | PL12: =+PL$6*$C12 -> 3671.151 | PM12: =+PM$6*$C12 -> 3671.151 | PN12: 0 | PO12: =+PO$6*$C12 -> 6046.5629 | PP12: =+PP$6*$C12 -> 0 | PQ12: =+PQ$6*$C12 -> 0 | PR12: =+PR$6*$C12 -> 0 | PS12: =+PS$6*$C12 -> 3671.151 | PT12: =+PT$6*$C12 -> 3671.151 | PU12: 0 | PV12: =+PV$6*$C12 -> 0 | PW12: =+PW$6*$C12 -> 0 | PX12: =+PX$6*$C12 -> 272.77741 | PY12: =+PY$6*$C12 -> 2523.2215 | PZ12: =+PZ$6*$C12 -> 3671.151 | QA12: =+SUM(OV12:PZ12) -> 66762.537 | QB12: =+QB$6*$C12 -> 3671.151 | QC12: =+QC$6*$C12 -> 3671.151 | QD12: =+QD$6*$C12 -> 6046.5629 | QE12: =+QE$6*$C12 -> 0 | QF12: =+QF$6*$C12 -> 272.77741 | QG12: =+QG$6*$C12 -> 2523.2215 | QH12: =+QH$6*$C12 -> 3671.151 | QI12: =+QI$6*$C12 -> 3671.151 | ... QL12: =+QL$6*$C12 -> 6046.5629 | QM12: 0 | QN12: =+QN$6*$C12 -> 0 | QO12: =+QO$6*$C12 -> 3671.151 | QP12: =+QP$6*$C12 -> 3671.151 | QQ12: =+QQ$6*$C12 -> 3671.151 | QR12: =+QR$6*$C12 -> 6046.5629 | QS12: =+QS$6*$C12 -> 0 | QT12: 0 | QU12: =+QU$6*$C12 -> 0 | QV12: =+QV$6*$C12 -> 3671.151 | QW12: =+QW$6*$C12 -> 3671.151 | QX12: =+QX$6*$C12 -> 77355.403 | QY12: =+QY$6*$C12 -> 0 | QZ12: =+QZ$6*$C12 -> 0 | RA12: 0 | RB12: =+RB$6*$C12 -> 2523.2215 | RC12: =+RC$6*$C12 -> 3671.151 | RD12: =+RD$6*$C12 -> 3671.151 | RE12: =+RE$6*$C12 -> 3671.151 | RF12: =+SUM(QB12:RE12) -> 154585.84 | RG12: =+RG$6*$C12 -> 0 | RH12: =+RH$6*$C12 -> 272.77741 | RI12: =+RI$6*$C12 -> 2523.2215 | RJ12: =+RJ$6*$C12 -> 3671.151 | RK12: =+RK$6*$C12 -> 3671.151 | RL12: =+RL$6*$C12 -> 3671.151 | RM12: =+RM$6*$C12 -> 6046.5629 | RN12: =+RN$6*$C12 -> 6046.5629 | ... RQ12: =+RQ$6*$C12 -> 3671.151 | RR12: 0 | RS12: =+RS$6*$C12 -> 3671.151 | RT12: =+RT$6*$C12 -> 6046.5629 | RU12: =+RU$6*$C12 -> 0 | RV12: =+RV$6*$C12 -> 0 | RW12: =+RW$6*$C12 -> 0 | RX12: =+RX$6*$C12 -> 3671.151 | RY12: 0 | RZ12: =+RZ$6*$C12 -> 77355.403 | SA12: =+SA$6*$C12 -> 0 | SB12: =+SB$6*$C12 -> 0 | SC12: =+SC$6*$C12 -> 272.77741 | SD12: =+SD$6*$C12 -> 2523.2215 | SE12: =+SE$6*$C12 -> 3671.151 | SF12: 0 | SG12: =+SG$6*$C12 -> 3671.151 | SH12: =+SH$6*$C12 -> 6046.5629 | SI12: =+SI$6*$C12 -> 6046.5629 | SJ12: =+SJ$6*$C12 -> 272.77741 | SK12: =+SK$6*$C12 -> 0 | SL12: =+SUM(RG12:SK12) -> 143094.98 | SM12: =+SM$6*$C12 -> 3671.151 | SN12: =+SN$6*$C12 -> 3671.151 | SO12: =+SO$6*$C12 -> 3671.151 | SP12: =+SP$6*$C12 -> 6046.5629 | SQ12: =+SQ$6*$C12 -> 6046.5629 | SR12: =+SR$6*$C12 -> 272.77741 | SS12: =+SS$6*$C12 -> 0 | ST12: =+ST$6*$C12 -> 3671.151 | ... SW12: =+SW$6*$C12 -> 6046.5629 | SX12: 0 | SY12: =+SY$6*$C12 -> 0 | SZ12: =+SZ$6*$C12 -> 0 | TA12: =+TA$6*$C12 -> 3671.151 | TB12: =+TB$6*$C12 -> 3671.151 | TC12: =+TC$6*$C12 -> 77355.403 | TD12: =+TD$6*$C12 -> 0 | TE12: 0 | TF12: =+TF$6*$C12 -> 272.77741 | TG12: =+TG$6*$C12 -> 2523.2215 | TH12: =+TH$6*$C12 -> 3671.151 | TI12: =+TI$6*$C12 -> 3671.151 | TJ12: =+TJ$6*$C12 -> 3671.151 | TK12: =+TK$6*$C12 -> 6046.5629 | TL12: 0 | TM12: =+TM$6*$C12 -> 272.77741 | TN12: =+TN$6*$C12 -> 0 | TO12: =+TO$6*$C12 -> 3671.151 | TP12: =+TP$6*$C12 -> 3671.151 | TQ12: =+SUM(SM12:TP12) -> 152608.17 | TR12: =+TR$6*$C12 -> 6046.5629 | TS12: =+TS$6*$C12 -> 6046.5629 | TT12: =+TT$6*$C12 -> 272.77741 | TU12: =+TU$6*$C12 -> 0 | TV12: =+TV$6*$C12 -> 3671.151 | TW12: =+TW$6*$C12 -> 3671.151 | TX12: =+TX$6*$C12 -> 3671.151 | TY12: =+TY$6*$C12 -> 6046.5629 | ... UB12: =+UB$6*$C12 -> 0 | UC12: 0 | UD12: =+UD$6*$C12 -> 3671.151 | UE12: =+UE$6*$C12 -> 77355.403 | UF12: =+UF$6*$C12 -> 0 | UG12: =+UG$6*$C12 -> 0 | UH12: =+UH$6*$C12 -> 272.77741 | UI12: =+UI$6*$C12 -> 2523.2215 | UJ12: 0 | UK12: =+UK$6*$C12 -> 3671.151 | UL12: =+UL$6*$C12 -> 3671.151 | UM12: =+UM$6*$C12 -> 6046.5629 | UN12: =+UN$6*$C12 -> 6046.5629 | UO12: =+UO$6*$C12 -> 272.77741 | UP12: =+UP$6*$C12 -> 0 | UQ12: 0 | UR12: =+UR$6*$C12 -> 3671.151 | US12: =+US$6*$C12 -> 3671.151 | UT12: =+UT$6*$C12 -> 6046.5629 | UU12: =+UU$6*$C12 -> 0 | UV12: =+UV$6*$C12 -> 0 | UW12: =+SUM(TR12:UV12) -> 146345.54 | UX12: =+UX$6*$C12 -> 0 | UY12: =+UY$6*$C12 -> 3671.151 | UZ12: =+UZ$6*$C12 -> 3671.151 | VA12: =+VA$6*$C12 -> 3671.151 | VB12: =+VB$6*$C12 -> 6046.5629 | VC12: =+VC$6*$C12 -> 0 | VD12: =+VD$6*$C12 -> 0 | VE12: =+VE$6*$C12 -> 0 | ... VH12: =+VH$6*$C12 -> 77355.403 | VI12: 0 | VJ12: =+VJ$6*$C12 -> 0 | VK12: =+VK$6*$C12 -> 272.77741 | VL12: =+VL$6*$C12 -> 2523.2215 | VM12: =+VM$6*$C12 -> 3671.151 | VN12: =+VN$6*$C12 -> 3671.151 | VO12: =+VO$6*$C12 -> 3671.151 | VP12: 0 | VQ12: =+VQ$6*$C12 -> 6046.5629 | VR12: =+VR$6*$C12 -> 272.77741 | VS12: =+VS$6*$C12 -> 0 | VT12: =+VT$6*$C12 -> 3671.151 | VU12: =+VU$6*$C12 -> 3671.151 | VV12: =+VV$6*$C12 -> 3671.151 | VW12: 0 | VX12: =+VX$6*$C12 -> 0 | VY12: =+VY$6*$C12 -> 0 | VZ12: =+VZ$6*$C12 -> 0 | WA12: =+WA$6*$C12 -> 3671.151 | WB12: =+WB$6*$C12 -> 3671.151 | WC12: =+SUM(UX12:WB12) -> 140242.27
B13: RECEITAS BRUTAS REALIZADAS NO MÊS | D13: =SUM(D14:D19) -> 0 | E13: =SUM(E14:E19) -> 0 | F13: =SUM(F14:F19) -> #REF! | G13: =SUM(G14:G19) -> 0 | H13: =SUM(H14:H19) -> 0 | I13: =SUM(I14:I19) -> 0 | J13: =SUM(J14:J19) -> 0 | K13: =SUM(K14:K19) -> 0 | ... AE13: =SUM(AE14:AE19) -> #REF! | AH13: =+SUM(D13:AE13) -> #REF! | AI13: =SUM(AI14:AI19) -> 0 | AJ13: =SUM(AJ14:AJ19) -> 0 | AK13: =SUM(AK14:AK19) -> 0 | AL13: =SUM(AL14:AL19) -> 0 | AM13: =SUM(AM14:AM19) -> 0 | AN13: =SUM(AN14:AN19) -> 0 | AO13: =SUM(AO14:AO19) -> 0 | AP13: =SUM(AP14:AP19) -> 0 | ... BM13: =SUM(BM14:BM19) -> 0 | BN13: =+SUM(AI13:BM13) -> 0 | BO13: =SUM(BO14:BO19) -> 0 | BP13: =SUM(BP14:BP19) -> 0 | BQ13: =SUM(BQ14:BQ19) -> 97880.344 | BR13: =SUM(BR14:BR19) -> 49508.01 | BS13: =SUM(BS14:BS19) -> 80606.825 | BT13: =SUM(BT14:BT19) -> 33332.26 | BU13: =SUM(BU14:BU19) -> 1402.9548 | BV13: =SUM(BV14:BV19) -> 0 | ... CR13: =SUM(CR14:CR19) -> 0 | CS13: =SUM(BO13:CR13) -> 857633.69 | CT13: =SUM(CT14:CT19) -> 91542.835 | CU13: =SUM(CU14:CU19) -> 49508.01 | CV13: =SUM(CV14:CV19) -> 111705.64 | CW13: =SUM(CW14:CW19) -> 0 | CX13: =SUM(CX14:CX19) -> 0 | CY13: =SUM(CY14:CY19) -> 3636.4 | CZ13: =SUM(CZ14:CZ19) -> 30058.627 | DA13: =SUM(DA14:DA19) -> 48940.172 | ... DX13: =SUM(DX14:DX19) -> 31098.815 | DY13: =+SUM(CT13:DX13) -> 1091858.3 | DZ13: =SUM(DZ14:DZ19) -> 78707.853 | EA13: =SUM(EA14:EA19) -> 0 | EB13: =SUM(EB14:EB19) -> 48940.172 | EC13: =SUM(EC14:EC19) -> 0 | ED13: =SUM(ED14:ED19) -> 0 | EE13: =SUM(EE14:EE19) -> 97880.344 | EF13: =SUM(EF14:EF19) -> 0 | EG13: =SUM(EG14:EG19) -> 0 | ... FC13: =SUM(FC14:FC19) -> 0 | FD13: =+SUM(DZ13:FC13) -> 787506.64 | FE13: =SUM(FE14:FE19) -> 108155.89 | FF13: =SUM(FF14:FF19) -> 48940.172 | FG13: =SUM(FG14:FG19) -> 99488.369 | FH13: =SUM(FH14:FH19) -> 0 | FI13: =SUM(FI14:FI19) -> 0 | FJ13: =SUM(FJ14:FJ19) -> 0 | FK13: =SUM(FK14:FK19) -> 30058.627 | FL13: =SUM(FL14:FL19) -> 48940.172 | ... GI13: =SUM(GI14:GI19) -> 99488.369 | GJ13: =+SUM(FE13:GI13) -> 1254173.4 | GK13: =SUM(GK14:GK19) -> 115648.71 | GL13: =SUM(GL14:GL19) -> 0 | GM13: =SUM(GM14:GM19) -> 0 | GN13: =SUM(GN14:GN19) -> 0 | GO13: =SUM(GO14:GO19) -> 0 | GP13: =SUM(GP14:GP19) -> 97880.344 | GQ13: =SUM(GQ14:GQ19) -> 49508.01 | GR13: =SUM(GR14:GR19) -> 31098.815 | ... HO13: =SUM(HO14:HO19) -> 35040.06 | HP13: =+SUM(GK13:HO13) -> 988387.62 | HQ13: =SUM(HQ14:HQ19) -> 112174.06 | HR13: =SUM(HR14:HR19) -> 48940.172 | HS13: =SUM(HS14:HS19) -> 67821.716 | HT13: =SUM(HT14:HT19) -> 0 | HU13: =SUM(HU14:HU19) -> 0 | HV13: =SUM(HV14:HV19) -> 80606.825 | HW13: =SUM(HW14:HW19) -> 20659.617 | HX13: =SUM(HX14:HX19) -> 43036.115 | ... IT13: =SUM(IT14:IT19) -> 48940.172 | IU13: =+SUM(HQ13:IT13) -> 1218704.6 | IV13: =SUM(IV14:IV19) -> 105829.69 | IW13: =SUM(IW14:IW19) -> 0 | IX13: =SUM(IX14:IX19) -> 3636.4 | IY13: =SUM(IY14:IY19) -> 0 | IZ13: =SUM(IZ14:IZ19) -> 0 | JA13: =SUM(JA14:JA19) -> 82577.277 | JB13: =SUM(JB14:JB19) -> 30058.627 | JC13: =SUM(JC14:JC19) -> 68389.554 | ... JZ13: =SUM(JZ14:JZ19) -> 34735.215 | KA13: =+SUM(IV13:JZ13) -> 1062811.8 | KB13: =SUM(KB14:KB19) -> 76860.244 | KC13: =SUM(KC14:KC19) -> 30058.627 | KD13: =SUM(KD14:KD19) -> 67821.716 | KE13: =SUM(KE14:KE19) -> 0 | KF13: =SUM(KF14:KF19) -> 0 | KG13: =SUM(KG14:KG19) -> 129547 | KH13: =SUM(KH14:KH19) -> 2233.4452 | KI13: =SUM(KI14:KI19) -> 1402.9548 | ... LE13: =SUM(LE14:LE19) -> 30058.627 | LF13: =+SUM(KB13:LE13) -> 1061174.5 | LG13: =SUM(LG14:LG19) -> 103852.03 | LH13: =SUM(LH14:LH19) -> 49508.01 | LI13: =SUM(LI14:LI19) -> 111705.64 | LJ13: =SUM(LJ14:LJ19) -> 0 | LK13: =SUM(LK14:LK19) -> 0 | LL13: =SUM(LL14:LL19) -> 3636.4 | LM13: =SUM(LM14:LM19) -> 30058.627 | LN13: =SUM(LN14:LN19) -> 48940.172 | ... MK13: =SUM(MK14:MK19) -> 31098.815 | ML13: =+SUM(LG13:MK13) -> 1104167.5 | MM13: =SUM(MM14:MM19) -> 78707.853 | MN13: =SUM(MN14:MN19) -> 0 | MO13: =SUM(MO14:MO19) -> 48940.172 | MP13: =SUM(MP14:MP19) -> 0 | MQ13: =SUM(MQ14:MQ19) -> 0 | MR13: =SUM(MR14:MR19) -> 97880.344 | MS13: =SUM(MS14:MS19) -> 0 | MT13: =SUM(MT14:MT19) -> 0 | ... NQ13: =SUM(NQ14:NQ19) -> 48940.172 | NR13: =+SUM(MM13:NQ13) -> 836446.82 | NS13: =SUM(NS14:NS19) -> 111827.04 | NT13: =SUM(NT14:NT19) -> 48940.172 | NU13: =SUM(NU14:NU19) -> 99488.369 | NV13: =SUM(NV14:NV19) -> 0 | NW13: =SUM(NW14:NW19) -> 0 | NX13: =SUM(NX14:NX19) -> 0 | NY13: =SUM(NY14:NY19) -> 30058.627 | NZ13: =SUM(NZ14:NZ19) -> 48940.172 | ... OT13: =SUM(OT14:OT19) -> 30058.627 | OU13: =+SUM(NS13:OT13) -> 1060475.9 | OV13: =SUM(OV14:OV19) -> 74832.181 | OW13: =SUM(OW14:OW19) -> 0 | OX13: =SUM(OX14:OX19) -> 0 | OY13: =SUM(OY14:OY19) -> 0 | OZ13: =SUM(OZ14:OZ19) -> 0 | PA13: =SUM(PA14:PA19) -> 97880.344 | PB13: =SUM(PB14:PB19) -> 49508.01 | PC13: =SUM(PC14:PC19) -> 31098.815 | ... PZ13: =SUM(PZ14:PZ19) -> 35040.06 | QA13: =+SUM(OV13:PZ13) -> 866964.27 | QB13: =SUM(QB14:QB19) -> 39364.964 | QC13: =SUM(QC14:QC19) -> 48940.172 | QD13: =SUM(QD14:QD19) -> 67821.716 | QE13: =SUM(QE14:QE19) -> 0 | QF13: =SUM(QF14:QF19) -> 0 | QG13: =SUM(QG14:QG19) -> 80606.825 | QH13: =SUM(QH14:QH19) -> 20659.617 | QI13: =SUM(QI14:QI19) -> 43036.115 | ... RE13: =SUM(RE14:RE19) -> 48940.172 | RF13: =+SUM(QB13:RE13) -> 997466.99 | RG13: =SUM(RG14:RG19) -> 0 | RH13: =SUM(RH14:RH19) -> 0 | RI13: =SUM(RI14:RI19) -> 3636.4 | RJ13: =SUM(RJ14:RJ19) -> 0 | RK13: =SUM(RK14:RK19) -> 0 | RL13: =SUM(RL14:RL19) -> 82577.277 | RM13: =SUM(RM14:RM19) -> 30058.627 | RN13: =SUM(RN14:RN19) -> 68389.554 | ... SK13: =SUM(SK14:SK19) -> 34735.215 | SL13: =+SUM(RG13:SK13) -> 827435.14 | SM13: =SUM(SM14:SM19) -> 144497.93 | SN13: =SUM(SN14:SN19) -> 30058.627 | SO13: =SUM(SO14:SO19) -> 67821.716 | SP13: =SUM(SP14:SP19) -> 0 | SQ13: =SUM(SQ14:SQ19) -> 0 | SR13: =SUM(SR14:SR19) -> 129547 | SS13: =SUM(SS14:SS19) -> 2233.4452 | ST13: =SUM(ST14:ST19) -> 1402.9548 | ... TP13: =SUM(TP14:TP19) -> 30058.627 | TQ13: =+SUM(SM13:TP13) -> 2030491.3 | TR13: =SUM(TR14:TR19) -> #REF! | TS13: =SUM(TS14:TS19) -> #REF! | TT13: =SUM(TT14:TT19) -> 111705.64 | TU13: =SUM(TU14:TU19) -> 0 | TV13: =SUM(TV14:TV19) -> 0 | TW13: =SUM(TW14:TW19) -> 3636.4 | TX13: =SUM(TX14:TX19) -> 30058.627 | TY13: =SUM(TY14:TY19) -> 48940.172 | ... UV13: =SUM(UV14:UV19) -> 31098.815 | UW13: =+SUM(TR13:UV13) -> #REF! | UX13: =SUM(UX14:UX19) -> 146345.54 | UY13: =SUM(UY14:UY19) -> 0 | UZ13: =SUM(UZ14:UZ19) -> 48940.172 | VA13: =SUM(VA14:VA19) -> 0 | VB13: =SUM(VB14:VB19) -> 0 | VC13: =SUM(VC14:VC19) -> 97880.344 | VD13: =SUM(VD14:VD19) -> 0 | VE13: =SUM(VE14:VE19) -> 0 | ... WB13: =SUM(WB14:WB19) -> 48940.172 | WC13: =+SUM(UX13:WB13) -> 1886370.4
A14: OK | B14: DINHEIRO (D+1) | D14: =DRE!Q7 -> 0 | E14: =DRE!R7 -> 0 | F14: =DRE!#REF! -> #REF! | G14: =DRE!S7 -> 0 | H14: =DRE!T7 -> 0 | I14: =DRE!U7 -> 0 | J14: =DRE!V7 -> 0 | K14: =DRE!W7 -> 0 | L14: =DRE!X7 -> 0 | M14: =DRE!Y7 -> 0 | N14: =DRE!Z7 -> 0 | ... W14: =DRE!AI7 -> 0 | X14: =DRE!AQ7 -> 0 | Y14: =DRE!AK7 -> 0 | Z14: =DRE!AL7 -> 0 | AA14: =DRE!AM7 -> 0 | AB14: =DRE!AN7 -> 0 | AC14: =DRE!AO7 -> 0 | AD14: =DRE!AP7 -> 0 | AE14: =DRE!#REF! -> #REF! | AF14: =DRE!AR7 -> 0 | AG14: =DRE!AS7 -> 0 | AH14: =+SUM(D14:AE14) -> #REF! | BN14: =+SUM(AI14:BM14) -> 0 | BQ14: =+BM7+BO7 -> 37763.089 | BS14: =+BQ7 -> 31098.815 | BT14: =+BR7 -> 31098.815 | BU14: =+BS7+BT7 -> 1402.9548 | BX14: =+BU7+BV7 -> 37763.089 | BZ14: =+BX7 -> 31098.815 | CA14: =+BY7 -> 0 | CB14: =+BZ7+CA7 -> 0 | CE14: =+CB7+CC7 -> 37763.089 | CG14: =+CE7 -> 31098.815 | CH14: =+CF7 -> 0 | CI14: =+CG7+CH7 -> 14380.443 | CL14: =+CI7+CJ7 -> 37763.089 | CN14: =+CL7 -> 31098.815 | CO14: =+CM7 -> 31098.815 | CP14: =+CN7+CO7 -> 1402.9548 | CS14: =SUM(BO14:CR14) -> 354831.6 | CT14: =+CQ7 -> 18881.544 | CU14: =+CR7 -> 0 | CV14: =+CT7+CU7 -> 62197.63 | CY14: =+CV7+CW7 -> 1402.9548 | DA14: =+CY7 -> 18881.544 | DB14: =+CZ7 -> 18881.544 | DC14: =+DA7+DB7 -> 31098.815 | DF14: =+DC7+DD7 -> 0 | DH14: =+DF7 -> 18881.544 | DI14: =+DG7 -> 18881.544 | DJ14: =+DH7+DI7 -> 31098.815 | DM14: =+DJ7+DK7 -> 14380.443 | DO14: =+DM7 -> 18881.544 | DP14: =+DN7 -> 18881.544 | DQ14: =+DO7+DP7 -> 62197.63 | DT14: =+DQ7+DR7 -> 1402.9548 | DV14: =+DT7 -> 18881.544 | DW14: =+DU7 -> 18881.544 | DX14: =+DV7+DW7 -> 31098.815 | DY14: =+SUM(CT14:DX14) -> 404811.96 | DZ14: =+DW7 -> 0 | EA14: =+DX7 -> 0 | EB14: =+DZ7+EA7 -> 18881.544 | EE14: =+EB7+EC7 -> 37763.089 | EG14: =+EE7 -> 0 | EH14: =+EF7 -> 0 | EI14: =+EG7+EH7 -> 18881.544 | EL14: =+EI7+EJ7 -> 37763.089 | EN14: =+EL7 -> 0 | EO14: =+EM7 -> 1402.9548 | EP14: =+EN7+EO7 -> 31859.033 | ES14: =+EP7+EQ7 -> 37763.089 | EU14: =+ES7 -> 31098.815 | EV14: =+ET7 -> 1402.9548 | EW14: =+EU7+EV7 -> 18881.544 | EZ14: =+EW7+EX7 -> 37763.089 | FB14: =+EZ7 -> 0 | FC14: =+FA7 -> 0 | FD14: =+SUM(DZ14:FC14) -> 273460.75 | FE14: =+FC7 -> 18881.544 | FF14: =FC7 -> 18881.544 | FG14: =+FE7+FF7 -> 49980.36 | FJ14: =+FG7+FH7 -> 0 | FL14: =+FJ7 -> 18881.544 | FM14: =+FK7 -> 18881.544 | FN14: =+FL7+FM7 -> 49980.36 | FQ14: =+FN7+FO7 -> 1402.9548 | FS14: =+FQ7 -> 18881.544 | FT14: =+FR7 -> 18881.544 | FU14: =+FS7+FT7 -> 49980.36 | FX14: =+FU7+FV7 -> 32501.77 | FZ14: =+FX7 -> 18881.544 | GA14: =+FY7 -> 18881.544 | GB14: =+FZ7+GA7 -> 49980.36 | GE14: =+GB7+GC7 -> 0 | GG14: =+GE7 -> 18881.544 | GH14: =+GF7 -> 18881.544 | GI14: =+GG7+GH7 -> 49980.36 | GJ14: =+SUM(FE14:GI14) -> 472621.97 | GK14: =+GH7 -> 31098.815 | GL14: =+GI7 -> 0 | GM14: =+GK7+GL7 -> 0 | GP14: =+GM7+GN7 -> 37763.089 | GR14: =+GP7 -> 31098.815 | GS14: =+GQ7 -> 0 | GT14: =+GR7+GS7 -> 14380.443 | GW14: =+GT7+GU7 -> 37763.089 | GY14: =+GW7 -> 31098.815 | GZ14: =+GX7 -> 31098.815 | HA14: =+GY7+GZ7 -> 1402.9548 | HD14: =+HA7+HB7 -> 37763.089 | HF14: =+HD7 -> 31098.815 | HG14: =+HE7 -> 0 | HH14: =+HF7+HG7 -> 0 | HK14: =+HH7+HI7 -> 37763.089 | HM14: =+HK7 -> 31098.815 | HN14: =+HL7 -> 0 | HO14: =+HM7+HN7 -> 14380.443 | HP14: =+SUM(GK14:HO14) -> 367809.09 | HQ14: =+HN7 -> 12977.488 | HR14: =+HO7 -> 18881.544 | HS14: =+HQ7+HR7 -> 37763.089 | HV14: =+HS7+HT7 -> 31098.815 | HX14: =+HV7 -> 12977.488 | HY14: =+HW7 -> 18881.544 | HZ14: =+HX7+HY7 -> 37763.089 | IC14: =+HZ7+IA7 -> 62197.63 | IE14: =+IC7 -> 0 | IF14: =+ID7 -> 18881.544 | IG14: =+IE7+IF7 -> 37763.089 | IJ14: =+IG7+IH7 -> 31098.815 | IL14: =+IJ7 -> 0 | IM14: =+IK7 -> 18881.544 | IN14: =+IL7+IM7 -> 37763.089 | IQ14: =+IN7+IO7 -> 31098.815 | IS14: =+IQ7 -> 12977.488 | IT14: =+IR7 -> 18881.544 | IU14: =+SUM(HQ14:IT14) -> 439886.62 | IV14: =+IT7 -> 18881.544 | IW14: 0 | IX14: =+IV7+IW7 -> 1402.9548 | JA14: =+IX7+IY7 -> 31859.033 | JC14: =+JA7 -> 18881.544 | JD14: =+JB7 -> 31098.815 | JE14: =+JC7+JD7 -> 32501.77 | JH14: =+JE7+JF7 -> 18881.544 | JJ14: =+JH7 -> 18881.544 | JK14: =+JI7 -> 31098.815 | JL14: =+JJ7+JK7 -> 0 | JO14: =+JL7+JM7 -> 18881.544 | JQ14: =+JO7 -> 18881.544 | JR14: =+JP7 -> 31098.815 | JS14: =+JQ7+JR7 -> 1402.9548 | JV14: =+JS7+JT7 -> 31859.033 | JX14: =+JV7 -> 18881.544 | JY14: =+JW7 -> 31098.815 | JZ14: =+JX7+JY7 -> 32501.77 | KA14: =+SUM(IV14:JZ14) -> 388093.59 | KB14: =+JY7 -> 1402.9548 | KC14: =+JZ7 -> 0 | KD14: =+KB7+KC7 -> 37763.089 | KG14: =+KD7+KE7 -> 49980.36 | KI14: =+KG7 -> 1402.9548 | KJ14: =+KH7 -> 0 | KK14: =+KI7+KJ7 -> 37763.089 | KN14: =+KK7+KL7 -> 49980.36 | KP14: =+KN7 -> 0 | KQ14: =+KO7 -> 0 | KR14: =+KP7+KQ7 -> 37763.089 | KU14: =+KR7+KS7 -> 49980.36 | KW14: =+KU7 -> 1402.9548 | KX14: =+KV7 -> 12977.488 | KY14: =+KW7+KX7 -> 37763.089 | LB14: =+KY7+KZ7 -> 49980.36 | LD14: =+LB7 -> 1402.9548 | LE14: =+LC7 -> 0 | LF14: =+SUM(KB14:LE14) -> 369563.1 | LG14: =+LE7 -> 18881.544 | LH14: 0 | LI14: =+LG7+LH7 -> 62197.63 | LL14: =+LI7+LJ7 -> 1402.9548 | LN14: =+LL7 -> 18881.544 | LO14: =+LM7 -> 18881.544 | LP14: =+LN7+LO7 -> 31098.815 | LS14: =+LP7+LQ7 -> 0 | LU14: =+LS7 -> 18881.544 | LV14: =+LT7 -> 18881.544 | LW14: =+LU7+LV7 -> 31098.815 | LZ14: =+LW7+LX7 -> 14380.443 | MB14: =+LZ7 -> 18881.544 | MC14: =+MA7 -> 18881.544 | MD14: =+MB7+MC7 -> 62197.63 | MG14: =+MD7+ME7 -> 1402.9548 | MI14: =+MG7 -> 18881.544 | MJ14: =+MH7 -> 18881.544 | MK14: =+MI7+MJ7 -> 31098.815 | ML14: =+SUM(LG14:MK14) -> 404811.96 | MM14: =+MJ7 -> 0 | MN14: =+MK7 -> 0 | MO14: =+MM7+MN7 -> 18881.544 | MR14: =+MO7+MP7 -> 37763.089 | MT14: =+MR7 -> 0 | MU14: =+MS7 -> 0 | MV14: =+MT7+MU7 -> 18881.544 | MY14: =+MV7+MW7 -> 37763.089 | NA14: =+MY7 -> 0 | NB14: =+MZ7 -> 1402.9548 | NC14: =+NA7+NB7 -> 31859.033 | NF14: =+NC7+ND7 -> 37763.089 | NH14: =+NF7 -> 31098.815 | NI14: =+NG7 -> 1402.9548 | NJ14: =+NH7+NI7 -> 18881.544 | NM14: =+NJ7+NK7 -> 37763.089 | NO14: =+NM7 -> 0 | NP14: =+NN7 -> 0 | NQ14: =+NO7+NP7 -> 18881.544 | NR14: =+SUM(MM14:NQ14) -> 292342.29 | NS14: =+NP7 -> 18881.544 | NT14: =+NQ7 -> 18881.544 | NU14: =+NS7+NT7 -> 49980.36 | NX14: =+NU7+NV7 -> 0 | NZ14: =+NX7 -> 18881.544 | OA14: =+NY7 -> 18881.544 | OB14: =+NZ7+OA7 -> 49980.36 | OE14: =+OB7+OC7 -> 1402.9548 | OG14: =+OE7 -> 18881.544 | OH14: =+OF7 -> 18881.544 | OI14: =+OG7+OH7 -> 49980.36 | OL14: =+OI7+OJ7 -> 32501.77 | ON14: =+OL7 -> 18881.544 | OO14: =+OM7 -> 18881.544 | OP14: =+ON7+OO7 -> 49980.36 | OS14: =+OP7+OQ7 -> 0 | OU14: =+SUM(NS14:OT14) -> 384878.52 | OV14: 0 | OW14: 0 | OX14: =+OV7+OW7 -> 0 | PA14: =+OX7+OY7 -> 37763.089 | PC14: =+PA7 -> 31098.815 | PD14: =+PB7 -> 0 | PE14: =+PC7+PD7 -> 14380.443 | PH14: =+PE7+PF7 -> 37763.089 | PJ14: =+PH7 -> 31098.815 | PK14: =+PI7 -> 31098.815 | PL14: =+PJ7+PK7 -> 1402.9548 | PO14: =+PL7+PM7 -> 37763.089 | PQ14: =+PO7 -> 31098.815 | PR14: =+PP7 -> 0 | PS14: =+PQ7+PR7 -> 0 | PV14: =+PS7+PT7 -> 37763.089 | PW14: 0 | PX14: 0 | PY14: =+PW7 -> 0 | PZ14: =+PX7+PY7 -> 14380.443 | QA14: =+SUM(OV14:PZ14) -> 305611.46 | QB14: =+PY7 -> 12977.488 | QC14: =+PZ7 -> 18881.544 | QD14: =+QB7+QC7 -> 37763.089 | QG14: =+QD7+QE7 -> 31098.815 | QI14: =+QG7 -> 12977.488 | QJ14: =+QH7 -> 18881.544 | QK14: =+QI7+QJ7 -> 37763.089 | QN14: =+QK7+QL7 -> 62197.63 | QP14: =+QN7 -> 0 | QQ14: =+QO7 -> 18881.544 | QR14: =+QP7+QQ7 -> 37763.089 | QU14: =+QR7+QS7 -> 31098.815 | QW14: =+QU7 -> 0 | QX14: =+QV7 -> 18881.544 | QY14: 0 | RB14: 0 | RD14: =+RB7 -> 12977.488 | RE14: =+RC7 -> 18881.544 | RF14: =+SUM(QB14:RE14) -> 371024.71 | RG14: 0 | RH14: 0 | RI14: =+RG7+RH7 -> 1402.9548 | RL14: =+RI7+RJ7 -> 31859.033 | RN14: =+RL7 -> 18881.544 | RO14: =+RM7 -> 31098.815 | RP14: =+RN7+RO7 -> 32501.77 | RS14: =+RP7+RQ7 -> 18881.544 | RU14: =+RS7 -> 18881.544 | RV14: =+RT7 -> 31098.815 | RW14: =+RU7+RV7 -> 0 | RZ14: =+RW7+RX7 -> 18881.544 | SA14: 0 | SB14: 0 | SC14: =+SA7 -> 0 | SD14: =+SB7+SC7 -> 1402.9548 | SG14: =+SD7+SE7 -> 31859.033 | SI14: =+SG7 -> 18881.544 | SJ14: =+SH7 -> 31098.815 | SK14: =+SI7+SJ7 -> 32501.77 | SL14: =+SUM(RG14:SK14) -> 319231.68 | SM14: =+SJ7 -> 1402.9548 | SN14: =+SK7 -> 0 | SO14: =+SM7+SN7 -> 37763.089 | SR14: =+SO7+SP7 -> 49980.36 | ST14: =+SR7 -> 1402.9548 | SU14: =+SS7 -> 0 | SV14: =+ST7+SU7 -> 37763.089 | SY14: =+SV7+SW7 -> 49980.36 | TA14: =+SY7 -> 0 | TB14: =+SZ7 -> 0 | TC14: =+TA7+TB7 -> 37763.089 | TF14: =+TC7+TD7 -> 397856.01 | TH14: =+TF7 -> 1402.9548 | TI14: =+TG7 -> 12977.488 | TJ14: =+TH7+TI7 -> 37763.089 | TM14: =+TJ7+TK7 -> 49980.36 | TO14: =+TM7 -> 1402.9548 | TP14: =+TN7 -> 0 | TQ14: =+SUM(SM14:TP14) -> 717438.75 | TR14: =+TP7 -> 18881.544 | TS14: =+#REF! -> #REF! | TT14: =+TR7+TS7 -> 62197.63 | TW14: =+TT7+TU7 -> 1402.9548 | TY14: =+TW7 -> 18881.544 | TZ14: =+TX7 -> 18881.544 | UA14: =+TY7+TZ7 -> 31098.815 | UD14: =+UA7+UB7 -> 0 | UF14: =+UD7 -> 18881.544 | UG14: =+UE7 -> 397856.01 | UH14: =+UF7+UG7 -> 0 | UK14: =+UH7+UI7 -> 14380.443 | UM14: =+UK7 -> 18881.544 | UN14: =+UL7 -> 18881.544 | UO14: =+UM7+UN7 -> 62197.63 | UR14: =+UO7+UP7 -> 1402.9548 | UT14: =+UR7 -> 18881.544 | UU14: =+US7 -> 18881.544 | UV14: =+UT7+UU7 -> 31098.815 | UW14: =+SUM(TR14:UV14) -> #REF! | UX14: =+UU7 -> 0 | UY14: =+UV7 -> 0 | UZ14: =+UX7+UY7 -> 18881.544 | VC14: =+UZ7+VA7 -> 37763.089 | VE14: =+VC7 -> 0 | VF14: =+VD7 -> 0 | VG14: =+VE7+VF7 -> 18881.544 | VJ14: =+VG7+VH7 -> 416737.55 | VL14: =+VJ7 -> 0 | VM14: =+VK7 -> 1402.9548 | VN14: =+VL7+VM7 -> 31859.033 | VQ14: =+VN7+VO7 -> 37763.089 | VS14: =+VQ7 -> 31098.815 | VT14: =+VR7 -> 1402.9548 | VU14: =+VS7+VT7 -> 18881.544 | VX14: =+VU7+VV7 -> 37763.089 | VZ14: =+VX7 -> 0 | WA14: =+VY7 -> 0 | WB14: =+VZ7+WA7 -> 18881.544 | WC14: =+SUM(UX14:WB14) -> 671316.75
A15: OK | B15: CHEQUE (D+1) | AH15: =+SUM(D15:AE15) -> 0 | BN15: =+SUM(AI15:BM15) -> 0 | BQ15: =+BM8+BO8 -> 5384.1208 | BR15: =+BQ8 -> 4433.9534 | BS15: =+BR8 -> 4433.9534 | BT15: =+BS8 -> 200.02808 | BU15: =+BT8 -> 0 | BX15: =+BU8+BV8 -> 5384.1208 | BY15: =+BX8 -> 4433.9534 | BZ15: =+BY8 -> 0 | CA15: =+BZ8 -> 0 | CB15: =+CA8 -> 0 | CE15: =+CB8+CC8 -> 5384.1208 | CF15: =+CE8 -> 4433.9534 | CG15: =+CF8 -> 0 | CH15: =+CG8 -> 200.02808 | CI15: =+CH8 -> 1850.282 | CL15: =+CI8+CJ8 -> 5384.1208 | CM15: =+CL8 -> 4433.9534 | CN15: =+CM8 -> 4433.9534 | CO15: =+CN8 -> 200.02808 | CP15: =+CO8 -> 0 | CS15: =SUM(BO15:CR15) -> 50590.57 | CT15: =+CR8 -> 0 | CU15: =+CT8 -> 4433.9534 | CV15: =+CU8 -> 4433.9534 | CY15: =+CV8+CW8 -> 200.02808 | CZ15: =+CY8 -> 2692.0604 | DA15: =+CZ8 -> 2692.0604 | DB15: =+DA8 -> 4433.9534 | DC15: =+DB8 -> 0 | DF15: =+DC8+DD8 -> 0 | DG15: =+DF8 -> 2692.0604 | DH15: =+DG8 -> 2692.0604 | DI15: =+DH8 -> 4433.9534 | DJ15: =+DI8 -> 0 | DM15: =+DJ8+DK8 -> 2050.3101 | DN15: =+DM8 -> 2692.0604 | DO15: =+DN8 -> 2692.0604 | DP15: =+DO8 -> 4433.9534 | DQ15: =+DP8 -> 4433.9534 | DT15: =+DQ8+DR8 -> 200.02808 | DU15: =+DT8 -> 2692.0604 | DV15: =+DU8 -> 2692.0604 | DW15: =+DV8 -> 4433.9534 | DX15: =+DW8 -> 0 | DY15: =+SUM(CT15:DX15) -> 55024.523 | DZ15: =+DX8 -> 0 | EA15: =+DZ8 -> 0 | EB15: =+EA8 -> 2692.0604 | EE15: =+EB8+EC8 -> 5384.1208 | EF15: =+EE8 -> 0 | EG15: =+EF8 -> 0 | EH15: =+EG8 -> 0 | EI15: =+EH8 -> 2692.0604 | EL15: =+EI8+EJ8 -> 5384.1208 | EM15: =+EL8 -> 0 | EN15: =+EM8 -> 200.02808 | EO15: =+EN8 -> 1850.282 | EP15: =+EO8 -> 2692.0604 | ES15: =+EP8+EQ8 -> 5384.1208 | ET15: =+ES8 -> 4433.9534 | EU15: =+ET8 -> 200.02808 | EV15: =+EU8 -> 0 | EW15: =+EV8 -> 2692.0604 | EZ15: =+EW8+EX8 -> 5384.1208 | FA15: =+EZ8 -> 0 | FB15: =+FA8 -> 0 | FC15: =+FB8 -> 0 | FD15: =+SUM(DZ15:FC15) -> 38989.016 | FE15: =FC8 -> 2692.0604 | FF15: =+FE8 -> 2692.0604 | FG15: =+FF8 -> 4433.9534 | FJ15: =+FG8+FH8 -> 0 | FK15: =+FJ8 -> 2692.0604 | FL15: =+FK8 -> 2692.0604 | FM15: =+FL8 -> 2692.0604 | FN15: =+FM8 -> 4433.9534 | FQ15: =+FN8+FO8 -> 200.02808 | FR15: =+FQ8 -> 2692.0604 | FS15: =+FR8 -> 2692.0604 | FT15: =+FS8 -> 2692.0604 | FU15: =+FT8 -> 4433.9534 | FX15: =+FU8+FV8 -> 4633.9815 | FY15: =+FX8 -> 2692.0604 | FZ15: =+FY8 -> 2692.0604 | GA15: =+FZ8 -> 2692.0604 | GB15: =+GA8 -> 4433.9534 | GE15: =+GB8+GC8 -> 0 | GF15: =+GE8 -> 2692.0604 | GG15: =+GF8 -> 2692.0604 | GH15: =+GG8 -> 2692.0604 | GI15: =+GH8 -> 4433.9534 | GJ15: =+SUM(FE15:GI15) -> 64692.622 | GK15: =+GI8 -> 0 | GL15: =+GK8 -> 0 | GM15: =+GL8 -> 0 | GP15: =+GM8+GN8 -> 5384.1208 | GQ15: =+GP8 -> 4433.9534 | GR15: =+GQ8 -> 0 | GS15: =+GR8 -> 200.02808 | GT15: =+GS8 -> 1850.282 | GW15: =+GT8+GU8 -> 5384.1208 | GX15: =+GW8 -> 4433.9534 | GY15: =+GX8 -> 4433.9534 | GZ15: =+GY8 -> 200.02808 | HA15: =+GZ8 -> 0 | HD15: =+HA8+HB8 -> 5384.1208 | HE15: =+HD8 -> 4433.9534 | HF15: =+HE8 -> 0 | HG15: =+HF8 -> 0 | HH15: =+HG8 -> 0 | HK15: =+HH8+HI8 -> 5384.1208 | HL15: =+HK8 -> 4433.9534 | HM15: =+HL8 -> 0 | HN15: =+HM8 -> 200.02808 | HO15: =+HN8 -> 1850.282 | HP15: =+SUM(GK15:HO15) -> 48006.898 | HQ15: =+HO8 -> 2692.0604 | HR15: =+HQ8 -> 2692.0604 | HS15: =+HR8 -> 2692.0604 | HV15: =+HS8+HT8 -> 4433.9534 | HW15: =+HV8 -> 1850.282 | HX15: =+HW8 -> 2692.0604 | HY15: =+HX8 -> 2692.0604 | HZ15: =+HY8 -> 2692.0604 | IC15: =+HZ8+IA8 -> 8867.9068 | ID15: =+IC8 -> 0 | IE15: =+ID8 -> 2692.0604 | IF15: =+IE8 -> 2692.0604 | IG15: =+IF8 -> 2692.0604 | IJ15: =+IG8+IH8 -> 4433.9534 | IK15: =+IJ8 -> 0 | IL15: =+IK8 -> 2692.0604 | IM15: =+IL8 -> 2692.0604 | IN15: =+IM8 -> 2692.0604 | IQ15: =+IN8+IO8 -> 4433.9534 | IR15: =+IQ8 -> 1850.282 | IS15: =+IR8 -> 2692.0604 | IT15: =+IS8 -> 2692.0604 | IU15: =+SUM(HQ15:IT15) -> 63559.176 | IV15: 0 | IW15: =+IV8 -> 0 | IX15: =+IW8 -> 200.02808 | JA15: =+IX8+IY8 -> 4542.3424 | JB15: =+JA8 -> 2692.0604 | JC15: =+JB8 -> 4433.9534 | JD15: =+JC8 -> 4433.9534 | JE15: =+JD8 -> 200.02808 | JH15: =+JE8+JF8 -> 2692.0604 | JI15: =+JH8 -> 2692.0604 | JJ15: =+JI8 -> 4433.9534 | JK15: =+JJ8 -> 0 | JL15: =+JK8 -> 0 | JO15: =+JL8+JM8 -> 2692.0604 | JP15: =+JO8 -> 2692.0604 | JQ15: =+JP8 -> 4433.9534 | JR15: =+JQ8 -> 0 | JS15: =+JR8 -> 200.02808 | JV15: =+JS8+JT8 -> 4542.3424 | JW15: =+JV8 -> 2692.0604 | JX15: =+JW8 -> 4433.9534 | JY15: =+JX8 -> 4433.9534 | JZ15: =+JY8 -> 200.02808 | KA15: =+SUM(IV15:JZ15) -> 52640.88 | KB15: =+JZ8 -> 0 | KC15: =+KB8 -> 2692.0604 | KD15: =+KC8 -> 2692.0604 | KG15: =+KD8+KE8 -> 7126.0138 | KH15: =+KG8 -> 200.02808 | KI15: =+KH8 -> 0 | KJ15: =+KI8 -> 2692.0604 | KK15: =+KJ8 -> 2692.0604 | KN15: =+KK8+KL8 -> 7126.0138 | KO15: =+KN8 -> 0 | KP15: =+KO8 -> 0 | KQ15: =+KP8 -> 2692.0604 | KR15: =+KQ8 -> 2692.0604 | KU15: =+KR8+KS8 -> 7126.0138 | KV15: =+KU8 -> 200.02808 | KW15: =+KV8 -> 1850.282 | KX15: =+KW8 -> 2692.0604 | KY15: =+KX8 -> 2692.0604 | LB15: =+KY8+KZ8 -> 7126.0138 | LC15: =+LB8 -> 200.02808 | LD15: =+LC8 -> 0 | LE15: =+LD8 -> 2692.0604 | LF15: =+SUM(KB15:LE15) -> 55182.965 | LG15: 0 | LH15: =+LG8 -> 4433.9534 | LI15: =+LH8 -> 4433.9534 | LL15: =+LI8+LJ8 -> 200.02808 | LM15: =+LL8 -> 2692.0604 | LN15: =+LM8 -> 2692.0604 | LO15: =+LN8 -> 4433.9534 | LP15: =+LO8 -> 0 | LS15: =+LP8+LQ8 -> 0 | LT15: =+LS8 -> 2692.0604 | LU15: =+LT8 -> 2692.0604 | LV15: =+LU8 -> 4433.9534 | LW15: =+LV8 -> 0 | LZ15: =+LW8+LX8 -> 2050.3101 | MA15: =+LZ8 -> 2692.0604 | MB15: =+MA8 -> 2692.0604 | MC15: =+MB8 -> 4433.9534 | MD15: =+MC8 -> 4433.9534 | MG15: =+MD8+ME8 -> 200.02808 | MH15: =+MG8 -> 2692.0604 | MI15: =+MH8 -> 2692.0604 | MJ15: =+MI8 -> 4433.9534 | MK15: =+MJ8 -> 0 | ML15: =+SUM(LG15:MK15) -> 55024.523 | MM15: =+MK8 -> 0 | MN15: =+MM8 -> 0 | MO15: =+MN8 -> 2692.0604 | MR15: =+MO8+MP8 -> 5384.1208 | MS15: =+MR8 -> 0 | MT15: =+MS8 -> 0 | MU15: =+MT8 -> 0 | MV15: =+MU8 -> 2692.0604 | MY15: =+MV8+MW8 -> 5384.1208 | MZ15: =+MY8 -> 0 | NA15: =+MZ8 -> 200.02808 | NB15: =+NA8 -> 1850.282 | NC15: =+NB8 -> 2692.0604 | NF15: =+NC8+ND8 -> 5384.1208 | NG15: =+NF8 -> 4433.9534 | NH15: =+NG8 -> 200.02808 | NI15: =+NH8 -> 0 | NJ15: =+NI8 -> 2692.0604 | NM15: =+NJ8+NK8 -> 5384.1208 | NN15: =+NM8 -> 0 | NO15: =+NN8 -> 0 | NP15: =+NO8 -> 0 | NQ15: =+NP8 -> 2692.0604 | NR15: =+SUM(MM15:NQ15) -> 41681.077 | NS15: =+NQ8 -> 2692.0604 | NT15: =+NS8 -> 2692.0604 | NU15: =+NT8 -> 4433.9534 | NX15: =+NU8+NV8 -> 0 | NY15: =+NX8 -> 2692.0604 | NZ15: =+NY8 -> 2692.0604 | OA15: =+NZ8 -> 2692.0604 | OB15: =+OA8 -> 4433.9534 | OE15: =+OB8+OC8 -> 200.02808 | OF15: =+OE8 -> 2692.0604 | OG15: =+OF8 -> 2692.0604 | OH15: =+OG8 -> 2692.0604 | OI15: =+OH8 -> 4433.9534 | OL15: =+OI8+OJ8 -> 4633.9815 | OM15: =+OL8 -> 2692.0604 | ON15: =+OM8 -> 2692.0604 | OO15: =+ON8 -> 2692.0604 | OP15: =+OO8 -> 4433.9534 | OS15: =+OP8+OQ8 -> 0 | OT15: =+OS8 -> 2692.0604 | OU15: =+SUM(NS15:OT15) -> 54874.548 | OV15: 0 | OW15: =+OV8 -> 0 | OX15: =+OW8 -> 0 | PA15: =+OX8+OY8 -> 5384.1208 | PB15: =+PA8 -> 4433.9534 | PC15: =+PB8 -> 0 | PD15: =+PC8 -> 200.02808 | PE15: =+PD8 -> 1850.282 | PH15: =+PE8+PF8 -> 5384.1208 | PI15: =+PH8 -> 4433.9534 | PJ15: =+PI8 -> 4433.9534 | PK15: =+PJ8 -> 200.02808 | PL15: =+PK8 -> 0 | PO15: =+PL8+PM8 -> 5384.1208 | PP15: =+PO8 -> 4433.9534 | PQ15: =+PP8 -> 0 | PR15: =+PQ8 -> 0 | PS15: =+PR8 -> 0 | PV15: =+PS8+PT8 -> 5384.1208 | PW15: 0 | PX15: =+PW8 -> 0 | PY15: =+PX8 -> 200.02808 | PZ15: =+PY8 -> 1850.282 | QA15: =+SUM(OV15:PZ15) -> 43572.945 | QB15: =+PZ8 -> 2692.0604 | QC15: =+QB8 -> 2692.0604 | QD15: =+QC8 -> 2692.0604 | QG15: =+QD8+QE8 -> 4433.9534 | QH15: =+QG8 -> 1850.282 | QI15: =+QH8 -> 2692.0604 | QJ15: =+QI8 -> 2692.0604 | QK15: =+QJ8 -> 2692.0604 | QN15: =+QK8+QL8 -> 8867.9068 | QO15: =+QN8 -> 0 | QP15: =+QO8 -> 2692.0604 | QQ15: =+QP8 -> 2692.0604 | QR15: =+QQ8 -> 2692.0604 | QU15: =+QR8+QS8 -> 4433.9534 | QV15: =+QU8 -> 0 | QW15: =+QV8 -> 2692.0604 | QX15: =+QW8 -> 2692.0604 | QY15: 0 | RB15: 0 | RC15: =+RB8 -> 1850.282 | RD15: =+RC8 -> 2692.0604 | RE15: =+RD8 -> 2692.0604 | RF15: =+SUM(QB15:RE15) -> 56433.163 | RG15: 0 | RH15: =+RG8 -> 0 | RI15: =+RH8 -> 200.02808 | RL15: =+RI8+RJ8 -> 4542.3424 | RM15: =+RL8 -> 2692.0604 | RN15: =+RM8 -> 4433.9534 | RO15: =+RN8 -> 4433.9534 | RP15: =+RO8 -> 200.02808 | RS15: =+RP8+RQ8 -> 2692.0604 | RT15: =+RS8 -> 2692.0604 | RU15: =+RT8 -> 4433.9534 | RV15: =+RU8 -> 0 | RW15: =+RV8 -> 0 | RZ15: =+RW8+RX8 -> 2692.0604 | SA15: 0 | SB15: 0 | SC15: =+SB8 -> 0 | SD15: =+SC8 -> 200.02808 | SG15: =+SD8+SE8 -> 4542.3424 | SH15: =+SG8 -> 2692.0604 | SI15: =+SH8 -> 4433.9534 | SJ15: =+SI8 -> 4433.9534 | SK15: =+SJ8 -> 200.02808 | SL15: =+SUM(RG15:SK15) -> 45514.866 | SM15: =+SK8 -> 0 | SN15: =+SM8 -> 2692.0604 | SO15: =+SN8 -> 2692.0604 | SR15: =+SO8+SP8 -> 7126.0138 | SS15: =+SR8 -> 200.02808 | ST15: =+SS8 -> 0 | SU15: =+ST8 -> 2692.0604 | SV15: =+SU8 -> 2692.0604 | SY15: =+SV8+SW8 -> 7126.0138 | SZ15: =+SY8 -> 0 | TA15: =+SZ8 -> 0 | TB15: =+TA8 -> 2692.0604 | TC15: =+TB8 -> 2692.0604 | TF15: =+TC8+TD8 -> 56724.83 | TG15: =+TF8 -> 200.02808 | TH15: =+TG8 -> 1850.282 | TI15: =+TH8 -> 2692.0604 | TJ15: =+TI8 -> 2692.0604 | TM15: =+TJ8+TK8 -> 7126.0138 | TN15: =+TM8 -> 200.02808 | TO15: =+TN8 -> 0 | TP15: =+TO8 -> 2692.0604 | TQ15: =+SUM(SM15:TP15) -> 104781.78 | TR15: =+#REF! -> #REF! | TS15: =+TR8 -> 4433.9534 | TT15: =+TS8 -> 4433.9534 | TW15: =+TT8+TU8 -> 200.02808 | TX15: =+TW8 -> 2692.0604 | TY15: =+TX8 -> 2692.0604 | TZ15: =+TY8 -> 4433.9534 | UA15: =+TZ8 -> 0 | UD15: =+UA8+UB8 -> 0 | UE15: =+UD8 -> 2692.0604 | UF15: =+UE8 -> 56724.83 | UG15: =+UF8 -> 0 | UH15: =+UG8 -> 0 | UK15: =+UH8+UI8 -> 2050.3101 | UL15: =+UK8 -> 2692.0604 | UM15: =+UL8 -> 2692.0604 | UN15: =+UM8 -> 4433.9534 | UO15: =+UN8 -> 4433.9534 | UR15: =+UO8+UP8 -> 200.02808 | US15: =+UR8 -> 2692.0604 | UT15: =+US8 -> 2692.0604 | UU15: =+UT8 -> 4433.9534 | UV15: =+UU8 -> 0 | UW15: =+SUM(TR15:UV15) -> #REF! | UX15: =+UV8 -> 0 | UY15: =+UX8 -> 0 | UZ15: =+UY8 -> 2692.0604 | VC15: =+UZ8+VA8 -> 5384.1208 | VD15: =+VC8 -> 0 | VE15: =+VD8 -> 0 | VF15: =+VE8 -> 0 | VG15: =+VF8 -> 2692.0604 | VJ15: =+VG8+VH8 -> 59416.89 | VK15: =+VJ8 -> 0 | VL15: =+VK8 -> 200.02808 | VM15: =+VL8 -> 1850.282 | VN15: =+VM8 -> 2692.0604 | VQ15: =+VN8+VO8 -> 5384.1208 | VR15: =+VQ8 -> 4433.9534 | VS15: =+VR8 -> 200.02808 | VT15: =+VS8 -> 0 | VU15: =+VT8 -> 2692.0604 | VX15: =+VU8+VV8 -> 5384.1208 | VY15: =+VX8 -> 0 | VZ15: =+VY8 -> 0 | WA15: =+VZ8 -> 0 | WB15: =+WA8 -> 2692.0604 | WC15: =+SUM(UX15:WB15) -> 95713.846
A16: OK | B16: DÉBITO (D+1) | AH16: =+SUM(D16:AE16) -> 0 | BN16: =+SUM(AI16:BM16) -> 0 | BQ16: =+BM9+BO9 -> 582.44311 | BR16: =+BQ9 -> 479.65595 | BS16: =+BR9 -> 479.65595 | BT16: =+BS9 -> 21.638626 | BU16: =+BT9 -> 0 | BX16: =+BU9+BV9 -> 582.44311 | BY16: =+BX9 -> 479.65595 | BZ16: =+BY9 -> 0 | CA16: =+BZ9 -> 0 | CB16: =+CA9 -> 0 | CE16: =+CB9+CC9 -> 582.44311 | CF16: =+CE9 -> 479.65595 | CG16: =+CF9 -> 0 | CH16: =+CG9 -> 21.638626 | CI16: =+CH9 -> 200.1597 | CL16: =+CI9+CJ9 -> 582.44311 | CM16: =+CL9 -> 479.65595 | CN16: =+CM9 -> 479.65595 | CO16: =+CN9 -> 21.638626 | CP16: =+CO9 -> 0 | CS16: =SUM(BO16:CR16) -> 5472.7837 | CT16: =+CR9 -> 0 | CU16: =+CT9 -> 479.65595 | CV16: =+CU9 -> 479.65595 | CY16: =+CV9+CW9 -> 21.638626 | CZ16: =+CY9 -> 291.22155 | DA16: =+CZ9 -> 291.22155 | DB16: =+DA9 -> 479.65595 | DC16: =+DB9 -> 0 | DF16: =+DC9+DD9 -> 0 | DG16: =+DF9 -> 291.22155 | DH16: =+DG9 -> 291.22155 | DI16: =+DH9 -> 479.65595 | DJ16: =+DI9 -> 0 | DM16: =+DJ9+DK9 -> 221.79832 | DN16: =+DM9 -> 291.22155 | DO16: =+DN9 -> 291.22155 | DP16: =+DO9 -> 479.65595 | DQ16: =+DP9 -> 479.65595 | DT16: =+DQ9+DR9 -> 21.638626 | DU16: =+DT9 -> 291.22155 | DV16: =+DU9 -> 291.22155 | DW16: =+DV9 -> 479.65595 | DX16: =+DW9 -> 0 | DY16: =+SUM(CT16:DX16) -> 5952.4397 | DZ16: =+DX9 -> 0 | EA16: =+DZ9 -> 0 | EB16: =+EA9 -> 291.22155 | EE16: =+EB9+EC9 -> 582.44311 | EF16: =+EE9 -> 0 | EG16: =+EF9 -> 0 | EH16: =+EG9 -> 0 | EI16: =+EH9 -> 291.22155 | EL16: =+EI9+EJ9 -> 582.44311 | EM16: =+EL9 -> 0 | EN16: =+EM9 -> 21.638626 | EO16: =+EN9 -> 200.1597 | EP16: =+EO9 -> 291.22155 | ES16: =+EP9+EQ9 -> 582.44311 | ET16: =+ES9 -> 479.65595 | EU16: =+ET9 -> 21.638626 | EV16: =+EU9 -> 0 | EW16: =+EV9 -> 291.22155 | EZ16: =+EW9+EX9 -> 582.44311 | FA16: =+EZ9 -> 0 | FB16: =+FA9 -> 0 | FC16: =+FB9 -> 0 | FD16: =+SUM(DZ16:FC16) -> 4217.7515 | FE16: =FC9 -> 291.22155 | FF16: =+FE9 -> 291.22155 | FG16: =+FF9 -> 479.65595 | FJ16: =+FG9+FH9 -> 0 | FK16: =+FJ9 -> 291.22155 | FL16: =+FK9 -> 291.22155 | FM16: =+FL9 -> 291.22155 | FN16: =+FM9 -> 479.65595 | FQ16: =+FN9+FO9 -> 21.638626 | FR16: =+FQ9 -> 291.22155 | FS16: =+FR9 -> 291.22155 | FT16: =+FS9 -> 291.22155 | FU16: =+FT9 -> 479.65595 | FX16: =+FU9+FV9 -> 501.29458 | FY16: =+FX9 -> 291.22155 | FZ16: =+FY9 -> 291.22155 | GA16: =+FZ9 -> 291.22155 | GB16: =+GA9 -> 479.65595 | GE16: =+GB9+GC9 -> 0 | GF16: =+GE9 -> 291.22155 | GG16: =+GF9 -> 291.22155 | GH16: =+GG9 -> 291.22155 | GI16: =+GH9 -> 479.65595 | GJ16: =+SUM(FE16:GI16) -> 6998.3147 | GK16: =+GI9 -> 0 | GL16: =+GK9 -> 0 | GM16: =+GL9 -> 0 | GP16: =+GM9+GN9 -> 582.44311 | GQ16: =+GP9 -> 479.65595 | GR16: =+GQ9 -> 0 | GS16: =+GR9 -> 21.638626 | GT16: =+GS9 -> 200.1597 | GW16: =+GT9+GU9 -> 582.44311 | GX16: =+GW9 -> 479.65595 | GY16: =+GX9 -> 479.65595 | GZ16: =+GY9 -> 21.638626 | HA16: =+GZ9 -> 0 | HD16: =+HA9+HB9 -> 582.44311 | HE16: =+HD9 -> 479.65595 | HF16: =+HE9 -> 0 | HG16: =+HF9 -> 0 | HH16: =+HG9 -> 0 | HK16: =+HH9+HI9 -> 582.44311 | HL16: =+HK9 -> 479.65595 | HM16: =+HL9 -> 0 | HN16: =+HM9 -> 21.638626 | HO16: =+HN9 -> 200.1597 | HP16: =+SUM(GK16:HO16) -> 5193.2875 | HQ16: =+HO9 -> 291.22155 | HR16: =+HQ9 -> 291.22155 | HS16: =+HR9 -> 291.22155 | HV16: =+HS9+HT9 -> 479.65595 | HW16: =+HV9 -> 200.1597 | HX16: =+HW9 -> 291.22155 | HY16: =+HX9 -> 291.22155 | HZ16: =+HY9 -> 291.22155 | IC16: =+HZ9+IA9 -> 959.31191 | ID16: =+IC9 -> 0 | IE16: =+ID9 -> 291.22155 | IF16: =+IE9 -> 291.22155 | IG16: =+IF9 -> 291.22155 | IJ16: =+IG9+IH9 -> 479.65595 | IK16: =+IJ9 -> 0 | IL16: =+IK9 -> 291.22155 | IM16: =+IL9 -> 291.22155 | IN16: =+IM9 -> 291.22155 | IQ16: =+IN9+IO9 -> 479.65595 | IR16: =+IQ9 -> 200.1597 | IS16: =+IR9 -> 291.22155 | IT16: =+IS9 -> 291.22155 | IU16: =+SUM(HQ16:IT16) -> 6875.7009 | IV16: 0 | IW16: =+IV9 -> 0 | IX16: =+IW9 -> 21.638626 | JA16: =+IX9+IY9 -> 491.38125 | JB16: =+JA9 -> 291.22155 | JC16: =+JB9 -> 479.65595 | JD16: =+JC9 -> 479.65595 | JE16: =+JD9 -> 21.638626 | JH16: =+JE9+JF9 -> 291.22155 | JI16: =+JH9 -> 291.22155 | JJ16: =+JI9 -> 479.65595 | JK16: =+JJ9 -> 0 | JL16: =+JK9 -> 0 | JO16: =+JL9+JM9 -> 291.22155 | JP16: =+JO9 -> 291.22155 | JQ16: =+JP9 -> 479.65595 | JR16: =+JQ9 -> 0 | JS16: =+JR9 -> 21.638626 | JV16: =+JS9+JT9 -> 491.38125 | JW16: =+JV9 -> 291.22155 | JX16: =+JW9 -> 479.65595 | JY16: =+JX9 -> 479.65595 | JZ16: =+JY9 -> 21.638626 | KA16: =+SUM(IV16:JZ16) -> 5694.582 | KB16: =+JZ9 -> 0 | KC16: =+KB9 -> 291.22155 | KD16: =+KC9 -> 291.22155 | KG16: =+KD9+KE9 -> 770.87751 | KH16: =+KG9 -> 21.638626 | KI16: =+KH9 -> 0 | KJ16: =+KI9 -> 291.22155 | KK16: =+KJ9 -> 291.22155 | KN16: =+KK9+KL9 -> 770.87751 | KO16: =+KN9 -> 0 | KP16: =+KO9 -> 0 | KQ16: =+KP9 -> 291.22155 | KR16: =+KQ9 -> 291.22155 | KU16: =+KR9+KS9 -> 770.87751 | KV16: =+KU9 -> 21.638626 | KW16: =+KV9 -> 200.1597 | KX16: =+KW9 -> 291.22155 | KY16: =+KX9 -> 291.22155 | LB16: =+KY9+KZ9 -> 770.87751 | LC16: =+LB9 -> 21.638626 | LD16: =+LC9 -> 0 | LE16: =+LD9 -> 291.22155 | LF16: =+SUM(KB16:LE16) -> 5969.5796 | LG16: 0 | LH16: =+LG9 -> 479.65595 | LI16: =+LH9 -> 479.65595 | LL16: =+LI9+LJ9 -> 21.638626 | LM16: =+LL9 -> 291.22155 | LN16: =+LM9 -> 291.22155 | LO16: =+LN9 -> 479.65595 | LP16: =+LO9 -> 0 | LS16: =+LP9+LQ9 -> 0 | LT16: =+LS9 -> 291.22155 | LU16: =+LT9 -> 291.22155 | LV16: =+LU9 -> 479.65595 | LW16: =+LV9 -> 0 | LZ16: =+LW9+LX9 -> 221.79832 | MA16: =+LZ9 -> 291.22155 | MB16: =+MA9 -> 291.22155 | MC16: =+MB9 -> 479.65595 | MD16: =+MC9 -> 479.65595 | MG16: =+MD9+ME9 -> 21.638626 | MH16: =+MG9 -> 291.22155 | MI16: =+MH9 -> 291.22155 | MJ16: =+MI9 -> 479.65595 | MK16: =+MJ9 -> 0 | ML16: =+SUM(LG16:MK16) -> 5952.4397 | MM16: =+MK9 -> 0 | MN16: =+MM9 -> 0 | MO16: =+MN9 -> 291.22155 | MR16: =+MO9+MP9 -> 582.44311 | MS16: =+MR9 -> 0 | MT16: =+MS9 -> 0 | MU16: =+MT9 -> 0 | MV16: =+MU9 -> 291.22155 | MY16: =+MV9+MW9 -> 582.44311 | MZ16: =+MY9 -> 0 | NA16: =+MZ9 -> 21.638626 | NB16: =+NA9 -> 200.1597 | NC16: =+NB9 -> 291.22155 | NF16: =+NC9+ND9 -> 582.44311 | NG16: =+NF9 -> 479.65595 | NH16: =+NG9 -> 21.638626 | NI16: =+NH9 -> 0 | NJ16: =+NI9 -> 291.22155 | NM16: =+NJ9+NK9 -> 582.44311 | NN16: =+NM9 -> 0 | NO16: =+NN9 -> 0 | NP16: =+NO9 -> 0 | NQ16: =+NP9 -> 291.22155 | NR16: =+SUM(MM16:NQ16) -> 4508.9731 | NS16: =+NQ9 -> 291.22155 | NT16: =+NS9 -> 291.22155 | NU16: =+NT9 -> 479.65595 | NX16: =+NU9+NV9 -> 0 | NY16: =+NX9 -> 291.22155 | NZ16: =+NY9 -> 291.22155 | OA16: =+NZ9 -> 291.22155 | OB16: =+OA9 -> 479.65595 | OE16: =+OB9+OC9 -> 21.638626 | OF16: =+OE9 -> 291.22155 | OG16: =+OF9 -> 291.22155 | OH16: =+OG9 -> 291.22155 | OI16: =+OH9 -> 479.65595 | OL16: =+OI9+OJ9 -> 501.29458 | OM16: =+OL9 -> 291.22155 | ON16: =+OM9 -> 291.22155 | OO16: =+ON9 -> 291.22155 | OP16: =+OO9 -> 479.65595 | OS16: =+OP9+OQ9 -> 0 | OT16: =+OS9 -> 291.22155 | OU16: =+SUM(NS16:OT16) -> 5936.2156 | OV16: 0 | OW16: =+OV9 -> 0 | OX16: =+OW9 -> 0 | PA16: =+OX9+OY9 -> 582.44311 | PB16: =+PA9 -> 479.65595 | PC16: =+PB9 -> 0 | PD16: =+PC9 -> 21.638626 | PE16: =+PD9 -> 200.1597 | PH16: =+PE9+PF9 -> 582.44311 | PI16: =+PH9 -> 479.65595 | PJ16: =+PI9 -> 479.65595 | PK16: =+PJ9 -> 21.638626 | PL16: =+PK9 -> 0 | PO16: =+PL9+PM9 -> 582.44311 | PP16: =+PO9 -> 479.65595 | PQ16: =+PP9 -> 0 | PR16: =+PQ9 -> 0 | PS16: =+PR9 -> 0 | PV16: =+PS9+PT9 -> 582.44311 | PW16: 0 | PX16: =+PW9 -> 0 | PY16: =+PX9 -> 21.638626 | PZ16: =+PY9 -> 200.1597 | QA16: =+SUM(OV16:PZ16) -> 4713.6315 | QB16: =+PZ9 -> 291.22155 | QC16: =+QB9 -> 291.22155 | QD16: =+QC9 -> 291.22155 | QG16: =+QD9+QE9 -> 479.65595 | QH16: =+QG9 -> 200.1597 | QI16: =+QH9 -> 291.22155 | QJ16: =+QI9 -> 291.22155 | QK16: =+QJ9 -> 291.22155 | QN16: =+QK9+QL9 -> 959.31191 | QO16: =+QN9 -> 0 | QP16: =+QO9 -> 291.22155 | QQ16: =+QP9 -> 291.22155 | QR16: =+QQ9 -> 291.22155 | QU16: =+QR9+QS9 -> 479.65595 | QV16: =+QU9 -> 0 | QW16: =+QV9 -> 291.22155 | QX16: =+QW9 -> 291.22155 | QY16: 0 | RB16: 0 | RC16: =+RB9 -> 200.1597 | RD16: =+RC9 -> 291.22155 | RE16: =+RD9 -> 291.22155 | RF16: =+SUM(QB16:RE16) -> 6104.8234 | RG16: 0 | RH16: =+RG9 -> 0 | RI16: =+RH9 -> 21.638626 | RL16: =+RI9+RJ9 -> 491.38125 | RM16: =+RL9 -> 291.22155 | RN16: =+RM9 -> 479.65595 | RO16: =+RN9 -> 479.65595 | RP16: =+RO9 -> 21.638626 | RS16: =+RP9+RQ9 -> 291.22155 | RT16: =+RS9 -> 291.22155 | RU16: =+RT9 -> 479.65595 | RV16: =+RU9 -> 0 | RW16: =+RV9 -> 0 | RZ16: =+RW9+RX9 -> 291.22155 | SA16: 0 | SB16: 0 | SC16: =+SB9 -> 0 | SD16: =+SC9 -> 21.638626 | SG16: =+SD9+SE9 -> 491.38125 | SH16: =+SG9 -> 291.22155 | SI16: =+SH9 -> 479.65595 | SJ16: =+SI9 -> 479.65595 | SK16: =+SJ9 -> 21.638626 | SL16: =+SUM(RG16:SK16) -> 4923.7045 | SM16: =+SK9 -> 0 | SN16: =+SM9 -> 291.22155 | SO16: =+SN9 -> 291.22155 | SR16: =+SO9+SP9 -> 770.87751 | SS16: =+SR9 -> 21.638626 | ST16: =+SS9 -> 0 | SU16: =+ST9 -> 291.22155 | SV16: =+SU9 -> 291.22155 | SY16: =+SV9+SW9 -> 770.87751 | SZ16: =+SY9 -> 0 | TA16: =+SZ9 -> 0 | TB16: =+TA9 -> 291.22155 | TC16: =+TB9 -> 291.22155 | TF16: =+TC9+TD9 -> 6136.3753 | TG16: =+TF9 -> 21.638626 | TH16: =+TG9 -> 200.1597 | TI16: =+TH9 -> 291.22155 | TJ16: =+TI9 -> 291.22155 | TM16: =+TJ9+TK9 -> 770.87751 | TN16: =+TM9 -> 21.638626 | TO16: =+TN9 -> 0 | TP16: =+TO9 -> 291.22155 | TQ16: =+SUM(SM16:TP16) -> 11335.077 | TR16: =+#REF! -> #REF! | TS16: =+TR9 -> 479.65595 | TT16: =+TS9 -> 479.65595 | TW16: =+TT9+TU9 -> 21.638626 | TX16: =+TW9 -> 291.22155 | TY16: =+TX9 -> 291.22155 | TZ16: =+TY9 -> 479.65595 | UA16: =+TZ9 -> 0 | UD16: =+UA9+UB9 -> 0 | UE16: =+UD9 -> 291.22155 | UF16: =+UE9 -> 6136.3753 | UG16: =+UF9 -> 0 | UH16: =+UG9 -> 0 | UK16: =+UH9+UI9 -> 221.79832 | UL16: =+UK9 -> 291.22155 | UM16: =+UL9 -> 291.22155 | UN16: =+UM9 -> 479.65595 | UO16: =+UN9 -> 479.65595 | UR16: =+UO9+UP9 -> 21.638626 | US16: =+UR9 -> 291.22155 | UT16: =+US9 -> 291.22155 | UU16: =+UT9 -> 479.65595 | UV16: =+UU9 -> 0 | UW16: =+SUM(TR16:UV16) -> #REF! | UX16: =+UV9 -> 0 | UY16: =+UX9 -> 0 | UZ16: =+UY9 -> 291.22155 | VC16: =+UZ9+VA9 -> 582.44311 | VD16: =+VC9 -> 0 | VE16: =+VD9 -> 0 | VF16: =+VE9 -> 0 | VG16: =+VF9 -> 291.22155 | VJ16: =+VG9+VH9 -> 6427.5969 | VK16: =+VJ9 -> 0 | VL16: =+VK9 -> 21.638626 | VM16: =+VL9 -> 200.1597 | VN16: =+VM9 -> 291.22155 | VQ16: =+VN9+VO9 -> 582.44311 | VR16: =+VQ9 -> 479.65595 | VS16: =+VR9 -> 21.638626 | VT16: =+VS9 -> 0 | VU16: =+VT9 -> 291.22155 | VX16: =+VU9+VV9 -> 582.44311 | VY16: =+VX9 -> 0 | VZ16: =+VY9 -> 0 | WA16: =+VZ9 -> 0 | WB16: =+WA9 -> 291.22155 | WC16: =+SUM(UX16:WB16) -> 10354.127
A17: OK | B17: CRÉDITO (D+1) | AH17: =+SUM(D17:AE17) -> 0 | BN17: =+SUM(AI17:BM17) -> 0 | BQ17: =+BM10+BO10 -> 468.65312 | BR17: =+BQ10 -> 385.94715 | BS17: =+BR10 -> 385.94715 | BT17: =+BS10 -> 17.411159 | BU17: =+BT10 -> 0 | BX17: =+BU10+BV10 -> 468.65312 | BY17: =+BX10 -> 385.94715 | BZ17: =+BY10 -> 0 | CA17: =+BZ10 -> 0 | CB17: =+CA10 -> 0 | CE17: =+CB10+CC10 -> 468.65312 | CF17: =+CE10 -> 385.94715 | CG17: =+CF10 -> 0 | CH17: =+CG10 -> 17.411159 | CI17: =+CH10 -> 161.05516 | CL17: =+CI10+CJ10 -> 468.65312 | CM17: =+CL10 -> 385.94715 | CN17: =+CM10 -> 385.94715 | CO17: =+CN10 -> 17.411159 | CP17: =+CO10 -> 0 | CS17: =SUM(BO17:CR17) -> 4403.584 | CT17: =+CR10 -> 0 | CU17: =+CT10 -> 385.94715 | CV17: =+CU10 -> 385.94715 | CY17: =+CV10+CW10 -> 17.411159 | CZ17: =+CY10 -> 234.32656 | DA17: =+CZ10 -> 234.32656 | DB17: =+DA10 -> 385.94715 | DC17: =+DB10 -> 0 | DF17: =+DC10+DD10 -> 0 | DG17: =+DF10 -> 234.32656 | DH17: =+DG10 -> 234.32656 | DI17: =+DH10 -> 385.94715 | DJ17: =+DI10 -> 0 | DM17: =+DJ10+DK10 -> 178.46632 | DN17: =+DM10 -> 234.32656 | DO17: =+DN10 -> 234.32656 | DP17: =+DO10 -> 385.94715 | DQ17: =+DP10 -> 385.94715 | DT17: =+DQ10+DR10 -> 17.411159 | DU17: =+DT10 -> 234.32656 | DV17: =+DU10 -> 234.32656 | DW17: =+DV10 -> 385.94715 | DX17: =+DW10 -> 0 | DY17: =+SUM(CT17:DX17) -> 4789.5312 | DZ17: =+DX10 -> 0 | EA17: =+DZ10 -> 0 | EB17: =+EA10 -> 234.32656 | EE17: =+EB10+EC10 -> 468.65312 | EF17: =+EE10 -> 0 | EG17: =+EF10 -> 0 | EH17: =+EG10 -> 0 | EI17: =+EH10 -> 234.32656 | EL17: =+EI10+EJ10 -> 468.65312 | EM17: =+EL10 -> 0 | EN17: =+EM10 -> 17.411159 | EO17: =+EN10 -> 161.05516 | EP17: =+EO10 -> 234.32656 | ES17: =+EP10+EQ10 -> 468.65312 | ET17: =+ES10 -> 385.94715 | EU17: =+ET10 -> 17.411159 | EV17: =+EU10 -> 0 | EW17: =+EV10 -> 234.32656 | EZ17: =+EW10+EX10 -> 468.65312 | FA17: =+EZ10 -> 0 | FB17: =+FA10 -> 0 | FC17: =+FB10 -> 0 | FD17: =+SUM(DZ17:FC17) -> 3393.7434 | FE17: =FC10 -> 234.32656 | FF17: =+FE10 -> 234.32656 | FG17: =+FF10 -> 385.94715 | FJ17: =+FG10+FH10 -> 0 | FK17: =+FJ10 -> 234.32656 | FL17: =+FK10 -> 234.32656 | FM17: =+FL10 -> 234.32656 | FN17: =+FM10 -> 385.94715 | FQ17: =+FN10+FO10 -> 17.411159 | FR17: =+FQ10 -> 234.32656 | FS17: =+FR10 -> 234.32656 | FT17: =+FS10 -> 234.32656 | FU17: =+FT10 -> 385.94715 | FX17: =+FU10+FV10 -> 403.35831 | FY17: =+FX10 -> 234.32656 | FZ17: =+FY10 -> 234.32656 | GA17: =+FZ10 -> 234.32656 | GB17: =+GA10 -> 385.94715 | GE17: =+GB10+GC10 -> 0 | GF17: =+GE10 -> 234.32656 | GG17: =+GF10 -> 234.32656 | GH17: =+GG10 -> 234.32656 | GI17: =+GH10 -> 385.94715 | GJ17: =+SUM(FE17:GI17) -> 5631.0771 | GK17: =+GI10 -> 0 | GL17: =+GK10 -> 0 | GM17: =+GL10 -> 0 | GP17: =+GM10+GN10 -> 468.65312 | GQ17: =+GP10 -> 385.94715 | GR17: =+GQ10 -> 0 | GS17: =+GR10 -> 17.411159 | GT17: =+GS10 -> 161.05516 | GW17: =+GT10+GU10 -> 468.65312 | GX17: =+GW10 -> 385.94715 | GY17: =+GX10 -> 385.94715 | GZ17: =+GY10 -> 17.411159 | HA17: =+GZ10 -> 0 | HD17: =+HA10+HB10 -> 468.65312 | HE17: =+HD10 -> 385.94715 | HF17: =+HE10 -> 0 | HG17: =+HF10 -> 0 | HH17: =+HG10 -> 0 | HK17: =+HH10+HI10 -> 468.65312 | HL17: =+HK10 -> 385.94715 | HM17: =+HL10 -> 0 | HN17: =+HM10 -> 17.411159 | HO17: =+HN10 -> 161.05516 | HP17: =+SUM(GK17:HO17) -> 4178.6921 | HQ17: =+HO10 -> 234.32656 | HR17: =+HQ10 -> 234.32656 | HS17: =+HR10 -> 234.32656 | HV17: =+HS10+HT10 -> 385.94715 | HW17: =+HV10 -> 161.05516 | HX17: =+HW10 -> 234.32656 | HY17: =+HX10 -> 234.32656 | HZ17: =+HY10 -> 234.32656 | IC17: =+HZ10+IA10 -> 771.89431 | ID17: =+IC10 -> 0 | IE17: =+ID10 -> 234.32656 | IF17: =+IE10 -> 234.32656 | IG17: =+IF10 -> 234.32656 | IJ17: =+IG10+IH10 -> 385.94715 | IK17: =+IJ10 -> 0 | IL17: =+IK10 -> 234.32656 | IM17: =+IL10 -> 234.32656 | IN17: =+IM10 -> 234.32656 | IQ17: =+IN10+IO10 -> 385.94715 | IR17: =+IQ10 -> 161.05516 | IS17: =+IR10 -> 234.32656 | IT17: =+IS10 -> 234.32656 | IU17: =+SUM(HQ17:IT17) -> 5532.4179 | IV17: 0 | IW17: =+IV10 -> 0 | IX17: =+IW10 -> 17.411159 | JA17: =+IX10+IY10 -> 395.38172 | JB17: =+JA10 -> 234.32656 | JC17: =+JB10 -> 385.94715 | JD17: =+JC10 -> 385.94715 | JE17: =+JD10 -> 17.411159 | JH17: =+JE10+JF10 -> 234.32656 | JI17: =+JH10 -> 234.32656 | JJ17: =+JI10 -> 385.94715 | JK17: =+JJ10 -> 0 | JL17: =+JK10 -> 0 | JO17: =+JL10+JM10 -> 234.32656 | JP17: =+JO10 -> 234.32656 | JQ17: =+JP10 -> 385.94715 | JR17: =+JQ10 -> 0 | JS17: =+JR10 -> 17.411159 | JV17: =+JS10+JT10 -> 395.38172 | JW17: =+JV10 -> 234.32656 | JX17: =+JW10 -> 385.94715 | JY17: =+JX10 -> 385.94715 | JZ17: =+JY10 -> 17.411159 | KA17: =+SUM(IV17:JZ17) -> 4582.0504 | KB17: =+JZ10 -> 0 | KC17: =+KB10 -> 234.32656 | KD17: =+KC10 -> 234.32656 | KG17: =+KD10+KE10 -> 620.27372 | KH17: =+KG10 -> 17.411159 | KI17: =+KH10 -> 0 | KJ17: =+KI10 -> 234.32656 | KK17: =+KJ10 -> 234.32656 | KN17: =+KK10+KL10 -> 620.27372 | KO17: =+KN10 -> 0 | KP17: =+KO10 -> 0 | KQ17: =+KP10 -> 234.32656 | KR17: =+KQ10 -> 234.32656 | KU17: =+KR10+KS10 -> 620.27372 | KV17: =+KU10 -> 17.411159 | KW17: =+KV10 -> 161.05516 | KX17: =+KW10 -> 234.32656 | KY17: =+KX10 -> 234.32656 | LB17: =+KY10+KZ10 -> 620.27372 | LC17: =+LB10 -> 17.411159 | LD17: =+LC10 -> 0 | LE17: =+LD10 -> 234.32656 | LF17: =+SUM(KB17:LE17) -> 4803.3225 | LG17: 0 | LH17: =+LG10 -> 385.94715 | LI17: =+LH10 -> 385.94715 | LL17: =+LI10+LJ10 -> 17.411159 | LM17: =+LL10 -> 234.32656 | LN17: =+LM10 -> 234.32656 | LO17: =+LN10 -> 385.94715 | LP17: =+LO10 -> 0 | LS17: =+LP10+LQ10 -> 0 | LT17: =+LS10 -> 234.32656 | LU17: =+LT10 -> 234.32656 | LV17: =+LU10 -> 385.94715 | LW17: =+LV10 -> 0 | LZ17: =+LW10+LX10 -> 178.46632 | MA17: =+LZ10 -> 234.32656 | MB17: =+MA10 -> 234.32656 | MC17: =+MB10 -> 385.94715 | MD17: =+MC10 -> 385.94715 | MG17: =+MD10+ME10 -> 17.411159 | MH17: =+MG10 -> 234.32656 | MI17: =+MH10 -> 234.32656 | MJ17: =+MI10 -> 385.94715 | MK17: =+MJ10 -> 0 | ML17: =+SUM(LG17:MK17) -> 4789.5312 | MM17: =+MK10 -> 0 | MN17: =+MM10 -> 0 | MO17: =+MN10 -> 234.32656 | MR17: =+MO10+MP10 -> 468.65312 | MS17: =+MR10 -> 0 | MT17: =+MS10 -> 0 | MU17: =+MT10 -> 0 | MV17: =+MU10 -> 234.32656 | MY17: =+MV10+MW10 -> 468.65312 | MZ17: =+MY10 -> 0 | NA17: =+MZ10 -> 17.411159 | NB17: =+NA10 -> 161.05516 | NC17: =+NB10 -> 234.32656 | NF17: =+NC10+ND10 -> 468.65312 | NG17: =+NF10 -> 385.94715 | NH17: =+NG10 -> 17.411159 | NI17: =+NH10 -> 0 | NJ17: =+NI10 -> 234.32656 | NM17: =+NJ10+NK10 -> 468.65312 | NN17: =+NM10 -> 0 | NO17: =+NN10 -> 0 | NP17: =+NO10 -> 0 | NQ17: =+NP10 -> 234.32656 | NR17: =+SUM(MM17:NQ17) -> 3628.0699 | NS17: =+NQ10 -> 234.32656 | NT17: =+NS10 -> 234.32656 | NU17: =+NT10 -> 385.94715 | NX17: =+NU10+NV10 -> 0 | NY17: =+NX10 -> 234.32656 | NZ17: =+NY10 -> 234.32656 | OA17: =+NZ10 -> 234.32656 | OB17: =+OA10 -> 385.94715 | OE17: =+OB10+OC10 -> 17.411159 | OF17: =+OE10 -> 234.32656 | OG17: =+OF10 -> 234.32656 | OH17: =+OG10 -> 234.32656 | OI17: =+OH10 -> 385.94715 | OL17: =+OI10+OJ10 -> 403.35831 | OM17: =+OL10 -> 234.32656 | ON17: =+OM10 -> 234.32656 | OO17: =+ON10 -> 234.32656 | OP17: =+OO10 -> 385.94715 | OS17: =+OP10+OQ10 -> 0 | OT17: =+OS10 -> 234.32656 | OU17: =+SUM(NS17:OT17) -> 4776.4768 | OV17: 0 | OW17: =+OV10 -> 0 | OX17: =+OW10 -> 0 | PA17: =+OX10+OY10 -> 468.65312 | PB17: =+PA10 -> 385.94715 | PC17: =+PB10 -> 0 | PD17: =+PC10 -> 17.411159 | PE17: =+PD10 -> 161.05516 | PH17: =+PE10+PF10 -> 468.65312 | PI17: =+PH10 -> 385.94715 | PJ17: =+PI10 -> 385.94715 | PK17: =+PJ10 -> 17.411159 | PL17: =+PK10 -> 0 | PO17: =+PL10+PM10 -> 468.65312 | PP17: =+PO10 -> 385.94715 | PQ17: =+PP10 -> 0 | PR17: =+PQ10 -> 0 | PS17: =+PR10 -> 0 | PV17: =+PS10+PT10 -> 468.65312 | PW17: 0 | PX17: =+PW10 -> 0 | PY17: =+PX10 -> 17.411159 | PZ17: =+PY10 -> 161.05516 | QA17: =+SUM(OV17:PZ17) -> 3792.7449 | QB17: =+PZ10 -> 234.32656 | QC17: =+QB10 -> 234.32656 | QD17: =+QC10 -> 234.32656 | QG17: =+QD10+QE10 -> 385.94715 | QH17: =+QG10 -> 161.05516 | QI17: =+QH10 -> 234.32656 | QJ17: =+QI10 -> 234.32656 | QK17: =+QJ10 -> 234.32656 | QN17: =+QK10+QL10 -> 771.89431 | QO17: =+QN10 -> 0 | QP17: =+QO10 -> 234.32656 | QQ17: =+QP10 -> 234.32656 | QR17: =+QQ10 -> 234.32656 | QU17: =+QR10+QS10 -> 385.94715 | QV17: =+QU10 -> 0 | QW17: =+QV10 -> 234.32656 | QX17: =+QW10 -> 234.32656 | QY17: 0 | RB17: 0 | RC17: =+RB10 -> 161.05516 | RD17: =+RC10 -> 234.32656 | RE17: =+RD10 -> 234.32656 | RF17: =+SUM(QB17:RE17) -> 4912.1442 | RG17: 0 | RH17: =+RG10 -> 0 | RI17: =+RH10 -> 17.411159 | RL17: =+RI10+RJ10 -> 395.38172 | RM17: =+RL10 -> 234.32656 | RN17: =+RM10 -> 385.94715 | RO17: =+RN10 -> 385.94715 | RP17: =+RO10 -> 17.411159 | RS17: =+RP10+RQ10 -> 234.32656 | RT17: =+RS10 -> 234.32656 | RU17: =+RT10 -> 385.94715 | RV17: =+RU10 -> 0 | RW17: =+RV10 -> 0 | RZ17: =+RW10+RX10 -> 234.32656 | SA17: 0 | SB17: 0 | SC17: =+SB10 -> 0 | SD17: =+SC10 -> 17.411159 | SG17: =+SD10+SE10 -> 395.38172 | SH17: =+SG10 -> 234.32656 | SI17: =+SH10 -> 385.94715 | SJ17: =+SI10 -> 385.94715 | SK17: =+SJ10 -> 17.411159 | SL17: =+SUM(RG17:SK17) -> 3961.7767 | SM17: =+SK10 -> 0 | SN17: =+SM10 -> 234.32656 | SO17: =+SN10 -> 234.32656 | SR17: =+SO10+SP10 -> 620.27372 | SS17: =+SR10 -> 17.411159 | ST17: =+SS10 -> 0 | SU17: =+ST10 -> 234.32656 | SV17: =+SU10 -> 234.32656 | SY17: =+SV10+SW10 -> 620.27372 | SZ17: =+SY10 -> 0 | TA17: =+SZ10 -> 0 | TB17: =+TA10 -> 234.32656 | TC17: =+TB10 -> 234.32656 | TF17: =+TC10+TD10 -> 4937.532 | TG17: =+TF10 -> 17.411159 | TH17: =+TG10 -> 161.05516 | TI17: =+TH10 -> 234.32656 | TJ17: =+TI10 -> 234.32656 | TM17: =+TJ10+TK10 -> 620.27372 | TN17: =+TM10 -> 17.411159 | TO17: =+TN10 -> 0 | TP17: =+TO10 -> 234.32656 | TQ17: =+SUM(SM17:TP17) -> 9120.5808 | TR17: =+#REF! -> #REF! | TS17: =+TR10 -> 385.94715 | TT17: =+TS10 -> 385.94715 | TW17: =+TT10+TU10 -> 17.411159 | TX17: =+TW10 -> 234.32656 | TY17: =+TX10 -> 234.32656 | TZ17: =+TY10 -> 385.94715 | UA17: =+TZ10 -> 0 | UD17: =+UA10+UB10 -> 0 | UE17: =+UD10 -> 234.32656 | UF17: =+UE10 -> 4937.532 | UG17: =+UF10 -> 0 | UH17: =+UG10 -> 0 | UK17: =+UH10+UI10 -> 178.46632 | UL17: =+UK10 -> 234.32656 | UM17: =+UL10 -> 234.32656 | UN17: =+UM10 -> 385.94715 | UO17: =+UN10 -> 385.94715 | UR17: =+UO10+UP10 -> 17.411159 | US17: =+UR10 -> 234.32656 | UT17: =+US10 -> 234.32656 | UU17: =+UT10 -> 385.94715 | UV17: =+UU10 -> 0 | UW17: =+SUM(TR17:UV17) -> #REF! | UX17: =+UV10 -> 0 | UY17: =+UX10 -> 0 | UZ17: =+UY10 -> 234.32656 | VC17: =+UZ10+VA10 -> 468.65312 | VD17: =+VC10 -> 0 | VE17: =+VD10 -> 0 | VF17: =+VE10 -> 0 | VG17: =+VF10 -> 234.32656 | VJ17: =+VG10+VH10 -> 5171.8585 | VK17: =+VJ10 -> 0 | VL17: =+VK10 -> 17.411159 | VM17: =+VL10 -> 161.05516 | VN17: =+VM10 -> 234.32656 | VQ17: =+VN10+VO10 -> 468.65312 | VR17: =+VQ10 -> 385.94715 | VS17: =+VR10 -> 17.411159 | VT17: =+VS10 -> 0 | VU17: =+VT10 -> 234.32656 | VX17: =+VU10+VV10 -> 468.65312 | VY17: =+VX10 -> 0 | VZ17: =+VY10 -> 0 | WA17: =+VZ10 -> 0 | WB17: =+WA10 -> 234.32656 | WC17: =+SUM(UX17:WB17) -> 8331.2753
A18: OK | B18: BOLETO (D+1) | AH18: =+SUM(D18:AE18) -> 0 | BN18: =+SUM(AI18:BM18) -> 0 | BQ18: =+BM11+BO11 -> 46339.736 | BR18: =+BQ11 -> 38161.891 | BS18: =+BR11 -> 38161.891 | BT18: =+BS11 -> 1721.5899 | BU18: =+BT11 -> 0 | BX18: =+BT11+BV11 -> 23169.868 | BY18: =+BX11 -> 38161.891 | BZ18: =+BY11 -> 0 | CA18: =+BZ11 -> 0 | CB18: =+CA11 -> 0 | CE18: =+CA11+CC11 -> 23169.868 | CF18: =+CE11 -> 38161.891 | CG18: =+CF11 -> 0 | CH18: =+CG11 -> 1721.5899 | CI18: =+CH11 -> 15924.899 | CL18: =+CH11+CJ11 -> 39094.766 | CM18: =+CL11 -> 38161.891 | CN18: =+CM11 -> 38161.891 | CO18: =+CN11 -> 1721.5899 | CP18: =+CO11 -> 0 | CS18: =SUM(BO18:CR18) -> 381835.25 | CT18: =+CR11 -> 0 | CU18: =+CT11 -> 38161.891 | CV18: =+CU11 -> 38161.891 | CY18: =+CV11+CW11 -> 1721.5899 | CZ18: =+CY11 -> 23169.868 | DA18: =+CZ11 -> 23169.868 | DB18: =+DA11 -> 38161.891 | DC18: =+DB11 -> 0 | DF18: =+DC11+DD11 -> 0 | DG18: =+DF11 -> 23169.868 | DH18: =+DG11 -> 23169.868 | DI18: =+DH11 -> 38161.891 | DJ18: =+DI11 -> 0 | DM18: =+DJ11+DK11 -> 17646.489 | DN18: =+DM11 -> 23169.868 | DO18: =+DN11 -> 23169.868 | DP18: =+DO11 -> 38161.891 | DQ18: =+DP11 -> 38161.891 | DT18: =+DQ11+DR11 -> 1721.5899 | DU18: =+DT11 -> 23169.868 | DV18: =+DU11 -> 23169.868 | DW18: =+DV11 -> 38161.891 | DX18: =+DW11 -> 0 | DY18: =+SUM(CT18:DX18) -> 473581.84 | DZ18: =+DX11 -> 0 | EA18: =+DZ11 -> 0 | EB18: =+EA11 -> 23169.868 | EE18: =+EB11+EC11 -> 46339.736 | EF18: =+EE11 -> 0 | EG18: =+EF11 -> 0 | EH18: =+EG11 -> 0 | EI18: =+EH11 -> 23169.868 | EL18: =+EI11+EJ11 -> 46339.736 | EM18: =+EL11 -> 0 | EN18: =+EM11 -> 1721.5899 | EO18: =+EN11 -> 15924.899 | EP18: =+EO11 -> 23169.868 | ES18: =+EP11+EQ11 -> 46339.736 | ET18: =+ES11 -> 38161.891 | EU18: =+ET11 -> 1721.5899 | EV18: =+EU11 -> 0 | EW18: =+EV11 -> 23169.868 | EZ18: =+EW11+EX11 -> 46339.736 | FA18: =+EZ11 -> 0 | FB18: =+FA11 -> 0 | FC18: =+FB11 -> 0 | FD18: =+SUM(DZ18:FC18) -> 335568.38 | FE18: =FC11 -> 23169.868 | FF18: =+FE11 -> 23169.868 | FG18: =+FF11 -> 38161.891 | FJ18: =+FG11+FH11 -> 0 | FK18: =+FJ11 -> 23169.868 | FL18: =+FK11 -> 23169.868 | FM18: =+FL11 -> 23169.868 | FN18: =+FM11 -> 38161.891 | FQ18: =+FN11+FO11 -> 1721.5899 | FR18: =+FQ11 -> 23169.868 | FS18: =+FR11 -> 23169.868 | FT18: =+FS11 -> 23169.868 | FU18: =+FT11 -> 38161.891 | FX18: =+FU11+FV11 -> 39883.48 | FY18: =+FX11 -> 23169.868 | FZ18: =+FY11 -> 23169.868 | GA18: =+FZ11 -> 23169.868 | GB18: =+GA11 -> 38161.891 | GE18: =+GB11+GC11 -> 0 | GF18: =+GE11 -> 23169.868 | GG18: =+GF11 -> 23169.868 | GH18: =+GG11 -> 23169.868 | GI18: =+GH11 -> 38161.891 | GJ18: =+SUM(FE18:GI18) -> 556792.67 | GK18: =+GI11 -> 0 | GL18: =+GK11 -> 0 | GM18: =+GL11 -> 0 | GP18: =+GM11+GN11 -> 46339.736 | GQ18: =+GP11 -> 38161.891 | GR18: =+GQ11 -> 0 | GS18: =+GR11 -> 1721.5899 | GT18: =+GS11 -> 15924.899 | GW18: =+GT11+GU11 -> 46339.736 | GX18: =+GW11 -> 38161.891 | GY18: =+GX11 -> 38161.891 | GZ18: =+GY11 -> 1721.5899 | HA18: =+GZ11 -> 0 | HD18: =+HA11+HB11 -> 46339.736 | HE18: =+HD11 -> 38161.891 | HF18: =+HE11 -> 0 | HG18: =+HF11 -> 0 | HH18: =+HG11 -> 0 | HK18: =+HH11+HI11 -> 46339.736 | HL18: =+HK11 -> 38161.891 | HM18: =+HL11 -> 0 | HN18: =+HM11 -> 1721.5899 | HO18: =+HN11 -> 15924.899 | HP18: =+SUM(GK18:HO18) -> 413182.96 | HQ18: =+HO11 -> 23169.868 | HR18: =+HQ11 -> 23169.868 | HS18: =+HR11 -> 23169.868 | HV18: =+HS11+HT11 -> 38161.891 | HW18: =+HV11 -> 15924.899 | HX18: =+HW11 -> 23169.868 | HY18: =+HX11 -> 23169.868 | HZ18: =+HY11 -> 23169.868 | IC18: =+HZ11+IA11 -> 76323.781 | ID18: =+IC11 -> 0 | IE18: =+ID11 -> 23169.868 | IF18: =+IE11 -> 23169.868 | IG18: =+IF11 -> 23169.868 | IJ18: =+IG11+IH11 -> 38161.891 | IK18: =+IJ11 -> 0 | IL18: =+IK11 -> 23169.868 | IM18: =+IL11 -> 23169.868 | IN18: =+IM11 -> 23169.868 | IQ18: =+IN11+IO11 -> 38161.891 | IR18: =+IQ11 -> 15924.899 | IS18: =+IR11 -> 23169.868 | IT18: =+IS11 -> 23169.868 | IU18: =+SUM(HQ18:IT18) -> 547037.4 | IV18: 0 | IW18: =+IV11 -> 0 | IX18: =+IW11 -> 1721.5899 | JA18: =+IX11+IY11 -> 39094.766 | JB18: =+JA11 -> 23169.868 | JC18: =+JB11 -> 38161.891 | JD18: =+JC11 -> 38161.891 | JE18: =+JD11 -> 1721.5899 | JH18: =+JE11+JF11 -> 23169.868 | JI18: =+JH11 -> 23169.868 | JJ18: =+JI11 -> 38161.891 | JK18: =+JJ11 -> 0 | JL18: =+JK11 -> 0 | JO18: =+JL11+JM11 -> 23169.868 | JP18: =+JO11 -> 23169.868 | JQ18: =+JP11 -> 38161.891 | JR18: =+JQ11 -> 0 | JS18: =+JR11 -> 1721.5899 | JV18: =+JS11+JT11 -> 39094.766 | JW18: =+JV11 -> 23169.868 | JX18: =+JW11 -> 38161.891 | JY18: =+JX11 -> 38161.891 | JZ18: =+JY11 -> 1721.5899 | KA18: =+SUM(IV18:JZ18) -> 453066.44 | KB18: =+JZ11 -> 0 | KC18: =+KB11 -> 23169.868 | KD18: =+KC11 -> 23169.868 | KG18: =+KD11+KE11 -> 61331.758 | KH18: =+KG11 -> 1721.5899 | KI18: =+KH11 -> 0 | KJ18: =+KI11 -> 23169.868 | KK18: =+KJ11 -> 23169.868 | KN18: =+KK11+KL11 -> 61331.758 | KO18: =+KN11 -> 0 | KP18: =+KO11 -> 0 | KQ18: =+KP11 -> 23169.868 | KR18: =+KQ11 -> 23169.868 | KU18: =+KR11+KS11 -> 61331.758 | KV18: =+KU11 -> 1721.5899 | KW18: =+KV11 -> 15924.899 | KX18: =+KW11 -> 23169.868 | KY18: =+KX11 -> 23169.868 | LB18: =+KY11+KZ11 -> 61331.758 | LC18: =+LB11 -> 1721.5899 | LD18: =+LC11 -> 0 | LE18: =+LD11 -> 23169.868 | LF18: =+SUM(KB18:LE18) -> 474945.51 | LG18: 0 | LH18: =+LG11 -> 38161.891 | LI18: =+LH11 -> 38161.891 | LL18: =+LI11+LJ11 -> 1721.5899 | LM18: =+LL11 -> 23169.868 | LN18: =+LM11 -> 23169.868 | LO18: =+LN11 -> 38161.891 | LP18: =+LO11 -> 0 | LS18: =+LP11+LQ11 -> 0 | LT18: =+LS11 -> 23169.868 | LU18: =+LT11 -> 23169.868 | LV18: =+LU11 -> 38161.891 | LW18: =+LV11 -> 0 | LZ18: =+LW11+LX11 -> 17646.489 | MA18: =+LZ11 -> 23169.868 | MB18: =+MA11 -> 23169.868 | MC18: =+MB11 -> 38161.891 | MD18: =+MC11 -> 38161.891 | MG18: =+MD11+ME11 -> 1721.5899 | MH18: =+MG11 -> 23169.868 | MI18: =+MH11 -> 23169.868 | MJ18: =+MI11 -> 38161.891 | MK18: =+MJ11 -> 0 | ML18: =+SUM(LG18:MK18) -> 473581.84 | MM18: =+MK11 -> 0 | MN18: =+MM11 -> 0 | MO18: =+MN11 -> 23169.868 | MR18: =+MO11+MP11 -> 46339.736 | MS18: =+MR11 -> 0 | MT18: =+MS11 -> 0 | MU18: =+MT11 -> 0 | MV18: =+MU11 -> 23169.868 | MY18: =+MV11+MW11 -> 46339.736 | MZ18: =+MY11 -> 0 | NA18: =+MZ11 -> 1721.5899 | NB18: =+NA11 -> 15924.899 | NC18: =+NB11 -> 23169.868 | NF18: =+NC11+ND11 -> 46339.736 | NG18: =+NF11 -> 38161.891 | NH18: =+NG11 -> 1721.5899 | NI18: =+NH11 -> 0 | NJ18: =+NI11 -> 23169.868 | NM18: =+NJ11+NK11 -> 46339.736 | NN18: =+NM11 -> 0 | NO18: =+NN11 -> 0 | NP18: =+NO11 -> 0 | NQ18: =+NP11 -> 23169.868 | NR18: =+SUM(MM18:NQ18) -> 358738.25 | NS18: =+NQ11 -> 23169.868 | NT18: =+NS11 -> 23169.868 | NU18: =+NT11 -> 38161.891 | NX18: =+NU11+NV11 -> 0 | NY18: =+NX11 -> 23169.868 | NZ18: =+NY11 -> 23169.868 | OA18: =+NZ11 -> 23169.868 | OB18: =+OA11 -> 38161.891 | OE18: =+OB11+OC11 -> 1721.5899 | OF18: =+OE11 -> 23169.868 | OG18: =+OF11 -> 23169.868 | OH18: =+OG11 -> 23169.868 | OI18: =+OH11 -> 38161.891 | OL18: =+OI11+OJ11 -> 39883.48 | OM18: =+OL11 -> 23169.868 | ON18: =+OM11 -> 23169.868 | OO18: =+ON11 -> 23169.868 | OP18: =+OO11 -> 38161.891 | OS18: =+OP11+OQ11 -> 0 | OT18: =+OS11 -> 23169.868 | OU18: =+SUM(NS18:OT18) -> 472291.05 | OV18: 0 | OW18: 0 | OX18: =+OW11 -> 0 | PA18: =+OX11+OY11 -> 46339.736 | PB18: =+PA11 -> 38161.891 | PC18: =+PB11 -> 0 | PD18: =+PC11 -> 1721.5899 | PE18: =+PD11 -> 15924.899 | PH18: =+PE11+PF11 -> 46339.736 | PI18: =+PH11 -> 38161.891 | PJ18: =+PI11 -> 38161.891 | PK18: =+PJ11 -> 1721.5899 | PL18: =+PK11 -> 0 | PO18: =+PL11+PM11 -> 46339.736 | PP18: =+PO11 -> 38161.891 | PQ18: =+PP11 -> 0 | PR18: =+PQ11 -> 0 | PS18: =+PR11 -> 0 | PV18: =+PS11+PT11 -> 46339.736 | PW18: 0 | PX18: =+PW11 -> 0 | PY18: =+PX11 -> 1721.5899 | PZ18: =+PY11 -> 15924.899 | QA18: =+SUM(OV18:PZ18) -> 375021.07 | QB18: =+PZ11 -> 23169.868 | QC18: =+QB11 -> 23169.868 | QD18: =+QC11 -> 23169.868 | QG18: =+QD11+QE11 -> 38161.891 | QH18: =+QG11 -> 15924.899 | QI18: =+QH11 -> 23169.868 | QJ18: =+QI11 -> 23169.868 | QK18: =+QJ11 -> 23169.868 | QN18: =+QK11+QL11 -> 76323.781 | QO18: =+QN11 -> 0 | QP18: =+QO11 -> 23169.868 | QQ18: =+QP11 -> 23169.868 | QR18: =+QQ11 -> 23169.868 | QU18: =+QR11+QS11 -> 38161.891 | QV18: =+QU11 -> 0 | QW18: =+QV11 -> 23169.868 | QX18: =+QW11 -> 23169.868 | QY18: 0 | RB18: 0 | RC18: =+RB11 -> 15924.899 | RD18: =+RC11 -> 23169.868 | RE18: =+RD11 -> 23169.868 | RF18: =+SUM(QB18:RE18) -> 485705.64 | RG18: 0 | RH18: =+RG11 -> 0 | RI18: =+RH11 -> 1721.5899 | RL18: =+RI11+RJ11 -> 39094.766 | RM18: =+RL11 -> 23169.868 | RN18: =+RM11 -> 38161.891 | RO18: =+RN11 -> 38161.891 | RP18: =+RO11 -> 1721.5899 | RS18: =+RP11+RQ11 -> 23169.868 | RT18: =+RS11 -> 23169.868 | RU18: =+RT11 -> 38161.891 | RV18: =+RU11 -> 0 | RW18: =+RV11 -> 0 | RZ18: =+RW11+RX11 -> 23169.868 | SA18: 0 | SB18: 0 | SC18: =+SB11 -> 0 | SD18: =+SC11 -> 1721.5899 | SG18: =+SD11+SE11 -> 39094.766 | SH18: =+SG11 -> 23169.868 | SI18: =+SH11 -> 38161.891 | SJ18: =+SI11 -> 38161.891 | SK18: =+SJ11 -> 1721.5899 | SL18: =+SUM(RG18:SK18) -> 391734.68 | SM18: =+SK11 -> 0 | SN18: =+SM11 -> 23169.868 | SO18: =+SN11 -> 23169.868 | SR18: =+SO11+SP11 -> 61331.758 | SS18: =+SR11 -> 1721.5899 | ST18: =+SS11 -> 0 | SU18: =+ST11 -> 23169.868 | SV18: =+SU11 -> 23169.868 | SY18: =+SV11+SW11 -> 61331.758 | SZ18: =+SY11 -> 0 | TA18: =+SZ11 -> 0 | TB18: =+TA11 -> 23169.868 | TC18: =+TB11 -> 23169.868 | TF18: =+TC11+TD11 -> 488215.94 | TG18: =+TF11 -> 1721.5899 | TH18: =+TG11 -> 15924.899 | TI18: =+TH11 -> 23169.868 | TJ18: =+TI11 -> 23169.868 | TM18: =+TJ11+TK11 -> 61331.758 | TN18: =+TM11 -> 1721.5899 | TO18: =+TN11 -> 0 | TP18: =+TO11 -> 23169.868 | TQ18: =+SUM(SM18:TP18) -> 901829.7 | TR18: =+#REF! -> #REF! | TS18: =+TR11 -> 38161.891 | TT18: =+TS11 -> 38161.891 | TW18: =+TT11+TU11 -> 1721.5899 | TX18: =+TW11 -> 23169.868 | TY18: =+TX11 -> 23169.868 | TZ18: =+TY11 -> 38161.891 | UA18: =+TZ11 -> 0 | UD18: =+UA11+UB11 -> 0 | UE18: =+UD11 -> 23169.868 | UF18: =+UE11 -> 488215.94 | UG18: =+UF11 -> 0 | UH18: =+UG11 -> 0 | UK18: =+UH11+UI11 -> 17646.489 | UL18: =+UK11 -> 23169.868 | UM18: =+UL11 -> 23169.868 | UN18: =+UM11 -> 38161.891 | UO18: =+UN11 -> 38161.891 | UR18: =+UO11+UP11 -> 1721.5899 | US18: =+UR11 -> 23169.868 | UT18: =+US11 -> 23169.868 | UU18: =+UT11 -> 38161.891 | UV18: =+UU11 -> 0 | UW18: =+SUM(TR18:UV18) -> #REF! | UX18: =+UV11 -> 0 | UY18: =+UX11 -> 0 | UZ18: =+UY11 -> 23169.868 | VC18: =+UZ11+VA11 -> 46339.736 | VD18: =+VC11 -> 0 | VE18: =+VD11 -> 0 | VF18: =+VE11 -> 0 | VG18: =+VF11 -> 23169.868 | VJ18: =+VG11+VH11 -> 511385.81 | VK18: =+VJ11 -> 0 | VL18: =+VK11 -> 1721.5899 | VM18: =+VL11 -> 15924.899 | VN18: =+VM11 -> 23169.868 | VQ18: =+VN11+VO11 -> 46339.736 | VR18: =+VQ11 -> 38161.891 | VS18: =+VR11 -> 1721.5899 | VT18: =+VS11 -> 0 | VU18: =+VT11 -> 23169.868 | VX18: =+VU11+VV11 -> 46339.736 | VY18: =+VX11 -> 0 | VZ18: =+VY11 -> 0 | WA18: =+VZ11 -> 0 | WB18: =+WA11 -> 23169.868 | WC18: =+SUM(UX18:WB18) -> 823784.33
A19: OK | B19: OUTROS RECEBIMENTOS (D+1) | AH19: =+SUM(D19:AE19) -> 0 | BN19: =+SUM(AI19:BM19) -> 0 | BQ19: =+BM12+BO12 -> 7342.302 | BR19: =+BQ12 -> 6046.5629 | BS19: =+BR12 -> 6046.5629 | BT19: =+BS12 -> 272.77741 | BU19: =+BT12 -> 0 | BX19: =+BT12+BV12 -> 3671.151 | BY19: =+BX12 -> 6046.5629 | BZ19: =+BY12 -> 0 | CA19: =+BZ12 -> 0 | CB19: =+CA12 -> 0 | CE19: =+CA12+CC12 -> 3671.151 | CF19: =+CE12 -> 6046.5629 | CG19: =+CF12 -> 0 | CH19: =+CG12 -> 272.77741 | CI19: =+CH12 -> 2523.2215 | CL19: =+CH12+CJ12 -> 6194.3725 | CM19: =+CL12 -> 6046.5629 | CN19: =+CM12 -> 6046.5629 | CO19: =+CN12 -> 272.77741 | CP19: =+CO12 -> 0 | CS19: =SUM(BO19:CR19) -> 60499.908 | CT19: =+CS12 -> 72661.29 | CU19: =+CT12 -> 6046.5629 | CV19: =+CU12 -> 6046.5629 | CY19: =+CV12+CW12 -> 272.77741 | CZ19: =+CY12 -> 3671.151 | DA19: =+CZ12 -> 3671.151 | DB19: =+DA12 -> 6046.5629 | DC19: =+DB12 -> 0 | DF19: =+DC12+DD12 -> 0 | DG19: =+DF12 -> 3671.151 | DH19: =+DG12 -> 3671.151 | DI19: =+DH12 -> 6046.5629 | DJ19: =+DI12 -> 0 | DM19: =+DJ12+DK12 -> 2795.9989 | DN19: =+DM12 -> 3671.151 | DO19: =+DN12 -> 3671.151 | DP19: =+DO12 -> 6046.5629 | DQ19: =+DP12 -> 6046.5629 | DT19: =+DQ12+DR12 -> 272.77741 | DU19: =+DT12 -> 3671.151 | DV19: =+DU12 -> 3671.151 | DW19: =+DV12 -> 6046.5629 | DX19: =+DW12 -> 0 | DY19: =+SUM(CT19:DX19) -> 147697.99 | DZ19: =+DY12 -> 78707.853 | EA19: =+DZ12 -> 0 | EB19: =+EA12 -> 3671.151 | EE19: =+EB12+EC12 -> 7342.302 | EF19: =+EE12 -> 0 | EG19: =+EF12 -> 0 | EH19: =+EG12 -> 0 | EI19: =+EH12 -> 3671.151 | EL19: =+EI12+EJ12 -> 7342.302 | EM19: =+EL12 -> 0 | EN19: =+EM12 -> 272.77741 | EO19: =+EN12 -> 2523.2215 | EP19: =+EO12 -> 3671.151 | ES19: =+EP12+EQ12 -> 7342.302 | ET19: =+ES12 -> 6046.5629 | EU19: =+ET12 -> 272.77741 | EV19: =+EU12 -> 0 | EW19: =+EV12 -> 3671.151 | EZ19: =+EW12+EX12 -> 7342.302 | FA19: =+EZ12 -> 0 | FB19: =+FA12 -> 0 | FC19: =+FB12 -> 0 | FD19: =+SUM(DZ19:FC19) -> 131877 | FE19: =+FD12 -> 62886.865 | FF19: =+FE12 -> 3671.151 | FG19: =+FF12 -> 6046.5629 | FJ19: =+FG12+FH12 -> 0 | FK19: =+FJ12 -> 3671.151 | FL19: =+FK12 -> 3671.151 | FM19: =+FL12 -> 3671.151 | FN19: =+FM12 -> 6046.5629 | FQ19: =+FN12+FO12 -> 272.77741 | FR19: =+FQ12 -> 3671.151 | FS19: =+FR12 -> 3671.151 | FT19: =+FS12 -> 3671.151 | FU19: =+FT12 -> 6046.5629 | FX19: =+FU12+FV12 -> 6319.3403 | FY19: =+FX12 -> 3671.151 | FZ19: =+FY12 -> 3671.151 | GA19: =+FZ12 -> 3671.151 | GB19: =+GA12 -> 6046.5629 | GE19: =+GB12+GC12 -> 0 | GF19: =+GE12 -> 3671.151 | GG19: =+GF12 -> 3671.151 | GH19: =+GG12 -> 3671.151 | GI19: =+GH12 -> 6046.5629 | GJ19: =+SUM(FE19:GI19) -> 147436.76 | GK19: =+GJ12 -> 84549.895 | GL19: =+GK12 -> 0 | GM19: =+GL12 -> 0 | GP19: =+GM12+GN12 -> 7342.302 | GQ19: =+GP12 -> 6046.5629 | GR19: =+GQ12 -> 0 | GS19: =+GR12 -> 272.77741 | GT19: =+GS12 -> 2523.2215 | GW19: =+GT12+GU12 -> 7342.302 | GX19: =+GW12 -> 6046.5629 | GY19: =+GX12 -> 6046.5629 | GZ19: =+GY12 -> 272.77741 | HA19: =+GZ12 -> 0 | HD19: =+HA12+HB12 -> 7342.302 | HE19: =+HD12 -> 6046.5629 | HF19: =+HE12 -> 0 | HG19: =+HF12 -> 0 | HH19: =+HG12 -> 0 | HK19: =+HH12+HI12 -> 7342.302 | HL19: =+HK12 -> 6046.5629 | HM19: =+HL12 -> 0 | HN19: =+HM12 -> 272.77741 | HO19: =+HN12 -> 2523.2215 | HP19: =+SUM(GK19:HO19) -> 150016.69 | HQ19: =+HP12 -> 72809.1 | HR19: =+HQ12 -> 3671.151 | HS19: =+HR12 -> 3671.151 | HV19: =+HS12+HT12 -> 6046.5629 | HW19: =+HV12 -> 2523.2215 | HX19: =+HW12 -> 3671.151 | HY19: =+HX12 -> 3671.151 | HZ19: =+HY12 -> 3671.151 | IC19: =+HZ12+IA12 -> 12093.126 | ID19: =+IC12 -> 0 | IE19: =+ID12 -> 3671.151 | IF19: =+IE12 -> 3671.151 | IG19: =+IF12 -> 3671.151 | IJ19: =+IG12+IH12 -> 6046.5629 | IK19: =+IJ12 -> 0 | IL19: =+IK12 -> 3671.151 | IM19: =+IL12 -> 3671.151 | IN19: =+IM12 -> 3671.151 | IQ19: =+IN12+IO12 -> 6046.5629 | IR19: =+IQ12 -> 2523.2215 | IS19: =+IR12 -> 3671.151 | IT19: =+IS12 -> 3671.151 | IU19: =+SUM(HQ19:IT19) -> 155813.32 | IV19: =+IU12 -> 86948.149 | IW19: =+IV12 -> 0 | IX19: =+IW12 -> 272.77741 | JA19: =+IX12+IY12 -> 6194.3725 | JB19: =+JA12 -> 3671.151 | JC19: =+JB12 -> 6046.5629 | JD19: =+JC12 -> 6046.5629 | JE19: =+JD12 -> 272.77741 | JH19: =+JE12+JF12 -> 3671.151 | JI19: =+JH12 -> 3671.151 | JJ19: =+JI12 -> 6046.5629 | JK19: =+JJ12 -> 0 | JL19: =+JK12 -> 0 | JO19: =+JL12+JM12 -> 3671.151 | JP19: =+JO12 -> 3671.151 | JQ19: =+JP12 -> 6046.5629 | JR19: =+JQ12 -> 0 | JS19: =+JR12 -> 272.77741 | JV19: =+JS12+JT12 -> 6194.3725 | JW19: =+JV12 -> 3671.151 | JX19: =+JW12 -> 6046.5629 | JY19: =+JX12 -> 6046.5629 | JZ19: =+JY12 -> 272.77741 | KA19: =+SUM(IV19:JZ19) -> 158734.29 | KB19: =+KA12 -> 75457.289 | KC19: =+KB12 -> 3671.151 | KD19: =+KC12 -> 3671.151 | KG19: =+KD12+KE12 -> 9717.7139 | KH19: =+KG12 -> 272.77741 | KI19: =+KH12 -> 0 | KJ19: =+KI12 -> 3671.151 | KK19: =+KJ12 -> 3671.151 | KN19: =+KK12+KL12 -> 9717.7139 | KO19: =+KN12 -> 0 | KP19: =+KO12 -> 0 | KQ19: =+KP12 -> 3671.151 | KR19: =+KQ12 -> 3671.151 | KU19: =+KR12+KS12 -> 9717.7139 | KV19: =+KU12 -> 272.77741 | KW19: =+KV12 -> 2523.2215 | KX19: =+KW12 -> 3671.151 | KY19: =+KX12 -> 3671.151 | LB19: =+KY12+KZ12 -> 9717.7139 | LC19: =+LB12 -> 272.77741 | LD19: =+LC12 -> 0 | LE19: =+LD12 -> 3671.151 | LF19: =+SUM(KB19:LE19) -> 150710.06 | LG19: =+LF12 -> 84970.482 | LH19: =+LG12 -> 6046.5629 | LI19: =+LH12 -> 6046.5629 | LL19: =+LI12+LJ12 -> 272.77741 | LM19: =+LL12 -> 3671.151 | LN19: =+LM12 -> 3671.151 | LO19: =+LN12 -> 6046.5629 | LP19: =+LO12 -> 0 | LS19: =+LP12+LQ12 -> 0 | LT19: =+LS12 -> 3671.151 | LU19: =+LT12 -> 3671.151 | LV19: =+LU12 -> 6046.5629 | LW19: =+LV12 -> 0 | LZ19: =+LW12+LX12 -> 2795.9989 | MA19: =+LZ12 -> 3671.151 | MB19: =+MA12 -> 3671.151 | MC19: =+MB12 -> 6046.5629 | MD19: =+MC12 -> 6046.5629 | MG19: =+MD12+ME12 -> 272.77741 | MH19: =+MG12 -> 3671.151 | MI19: =+MH12 -> 3671.151 | MJ19: =+MI12 -> 6046.5629 | MK19: =+MJ12 -> 0 | ML19: =+SUM(LG19:MK19) -> 160007.18 | MM19: =+ML12 -> 78707.853 | MN19: =+MM12 -> 0 | MO19: =+MN12 -> 3671.151 | MR19: =+MO12+MP12 -> 7342.302 | MS19: =+MR12 -> 0 | MT19: =+MS12 -> 0 | MU19: =+MT12 -> 0 | MV19: =+MU12 -> 3671.151 | MY19: =+MV12+MW12 -> 7342.302 | MZ19: =+MY12 -> 0 | NA19: =+MZ12 -> 272.77741 | NB19: =+NA12 -> 2523.2215 | NC19: =+NB12 -> 3671.151 | NF19: =+NC12+ND12 -> 7342.302 | NG19: =+NF12 -> 6046.5629 | NH19: =+NG12 -> 272.77741 | NI19: =+NH12 -> 0 | NJ19: =+NI12 -> 3671.151 | NM19: =+NJ12+NK12 -> 7342.302 | NN19: =+NM12 -> 0 | NO19: =+NN12 -> 0 | NP19: =+NO12 -> 0 | NQ19: =+NP12 -> 3671.151 | NR19: =+SUM(MM19:NQ19) -> 135548.16 | NS19: =+NR12 -> 66558.016 | NT19: =+NS12 -> 3671.151 | NU19: =+NT12 -> 6046.5629 | NX19: =+NU12+NV12 -> 0 | NY19: =+NX12 -> 3671.151 | NZ19: =+NY12 -> 3671.151 | OA19: =+NZ12 -> 3671.151 | OB19: =+OA12 -> 6046.5629 | OE19: =+OB12+OC12 -> 272.77741 | OF19: =+OE12 -> 3671.151 | OG19: =+OF12 -> 3671.151 | OH19: =+OG12 -> 3671.151 | OI19: =+OH12 -> 6046.5629 | OL19: =+OI12+OJ12 -> 6319.3403 | OM19: =+OL12 -> 3671.151 | ON19: =+OM12 -> 3671.151 | OO19: =+ON12 -> 3671.151 | OP19: =+OO12 -> 6046.5629 | OS19: =+OP12+OQ12 -> 0 | OT19: =+OS12 -> 3671.151 | OU19: =+SUM(NS19:OT19) -> 137719.05 | OV19: =+OU12 -> 74832.181 | OW19: =+OV12 -> 0 | OX19: =+OW12 -> 0 | PA19: =+OX12+OY12 -> 7342.302 | PB19: =+PA12 -> 6046.5629 | PC19: =+PB12 -> 0 | PD19: =+PC12 -> 272.77741 | PE19: =+PD12 -> 2523.2215 | PH19: =+PE12+PF12 -> 7342.302 | PI19: =+PH12 -> 6046.5629 | PJ19: =+PI12 -> 6046.5629 | PK19: =+PJ12 -> 272.77741 | PL19: =+PK12 -> 0 | PO19: =+PL12+PM12 -> 7342.302 | PP19: =+PO12 -> 6046.5629 | PQ19: =+PP12 -> 0 | PR19: =+PQ12 -> 0 | PS19: =+PR12 -> 0 | PV19: =+PS12+PT12 -> 7342.302 | PW19: 0 | PX19: =+PW12 -> 0 | PY19: =+PX12 -> 272.77741 | PZ19: =+PY12 -> 2523.2215 | QA19: =+SUM(OV19:PZ19) -> 134252.42 | QB19: 0 | QC19: =+QB12 -> 3671.151 | QD19: =+QC12 -> 3671.151 | QG19: =+QD12+QE12 -> 6046.5629 | QH19: =+QG12 -> 2523.2215 | QI19: =+QH12 -> 3671.151 | QJ19: =+QI12 -> 3671.151 | QK19: =+QJ12 -> 3671.151 | QN19: =+QK12+QL12 -> 12093.126 | QO19: =+QN12 -> 0 | QP19: =+QO12 -> 3671.151 | QQ19: =+QP12 -> 3671.151 | QR19: =+QQ12 -> 3671.151 | QU19: =+QR12+QS12 -> 6046.5629 | QV19: =+QU12 -> 0 | QW19: =+QV12 -> 3671.151 | QX19: =+QW12 -> 3671.151 | QY19: 0 | RB19: 0 | RC19: =+RB12 -> 2523.2215 | RD19: =+RC12 -> 3671.151 | RE19: =+RD12 -> 3671.151 | RF19: =+SUM(QB19:RE19) -> 73286.507 | RG19: 0 | RH19: =+RG12 -> 0 | RI19: =+RH12 -> 272.77741 | RL19: =+RI12+RJ12 -> 6194.3725 | RM19: =+RL12 -> 3671.151 | RN19: =+RM12 -> 6046.5629 | RO19: =+RN12 -> 6046.5629 | RP19: =+RO12 -> 272.77741 | RS19: =+RP12+RQ12 -> 3671.151 | RT19: =+RS12 -> 3671.151 | RU19: =+RT12 -> 6046.5629 | RV19: =+RU12 -> 0 | RW19: =+RV12 -> 0 | RZ19: =+RW12+RX12 -> 3671.151 | SA19: 0 | SB19: 0 | SC19: =+SB12 -> 0 | SD19: =+SC12 -> 272.77741 | SG19: =+SD12+SE12 -> 6194.3725 | SH19: =+SG12 -> 3671.151 | SI19: =+SH12 -> 6046.5629 | SJ19: =+SI12 -> 6046.5629 | SK19: =+SJ12 -> 272.77741 | SL19: =+SUM(RG19:SK19) -> 62068.424 | SM19: =+SL12 -> 143094.98 | SN19: =+SM12 -> 3671.151 | SO19: =+SN12 -> 3671.151 | SR19: =+SO12+SP12 -> 9717.7139 | SS19: =+SR12 -> 272.77741 | ST19: =+SS12 -> 0 | SU19: =+ST12 -> 3671.151 | SV19: =+SU12 -> 3671.151 | SY19: =+SV12+SW12 -> 9717.7139 | SZ19: =+SY12 -> 0 | TA19: =+SZ12 -> 0 | TB19: =+TA12 -> 3671.151 | TC19: =+TB12 -> 3671.151 | TF19: =+TC12+TD12 -> 77355.403 | TG19: =+TF12 -> 272.77741 | TH19: =+TG12 -> 2523.2215 | TI19: =+TH12 -> 3671.151 | TJ19: =+TI12 -> 3671.151 | TM19: =+TJ12+TK12 -> 9717.7139 | TN19: =+TM12 -> 272.77741 | TO19: =+TN12 -> 0 | TP19: =+TO12 -> 3671.151 | TQ19: =+SUM(SM19:TP19) -> 285985.44 | TR19: =+TQ12 -> 152608.17 | TS19: =+TR12 -> 6046.5629 | TT19: =+TS12 -> 6046.5629 | TW19: =+TT12+TU12 -> 272.77741 | TX19: =+TW12 -> 3671.151 | TY19: =+TX12 -> 3671.151 | TZ19: =+TY12 -> 6046.5629 | UA19: =+TZ12 -> 0 | UD19: =+UA12+UB12 -> 0 | UE19: =+UD12 -> 3671.151 | UF19: =+UE12 -> 77355.403 | UG19: =+UF12 -> 0 | UH19: =+UG12 -> 0 | UK19: =+UH12+UI12 -> 2795.9989 | UL19: =+UK12 -> 3671.151 | UM19: =+UL12 -> 3671.151 | UN19: =+UM12 -> 6046.5629 | UO19: =+UN12 -> 6046.5629 | UR19: =+UO12+UP12 -> 272.77741 | US19: =+UR12 -> 3671.151 | UT19: =+US12 -> 3671.151 | UU19: =+UT12 -> 6046.5629 | UV19: =+UU12 -> 0 | UW19: =+SUM(TR19:UV19) -> 295282.56 | UX19: =+UW12 -> 146345.54 | UY19: =+UX12 -> 0 | UZ19: =+UY12 -> 3671.151 | VC19: =+UZ12+VA12 -> 7342.302 | VD19: =+VC12 -> 0 | VE19: =+VD12 -> 0 | VF19: =+VE12 -> 0 | VG19: =+VF12 -> 3671.151 | VJ19: =+VG12+VH12 -> 81026.554 | VK19: =+VJ12 -> 0 | VL19: =+VK12 -> 272.77741 | VM19: =+VL12 -> 2523.2215 | VN19: =+VM12 -> 3671.151 | VQ19: =+VN12+VO12 -> 7342.302 | VR19: =+VQ12 -> 6046.5629 | VS19: =+VR12 -> 272.77741 | VT19: =+VS12 -> 0 | VU19: =+VT12 -> 3671.151 | VX19: =+VU12+VV12 -> 7342.302 | VY19: =+VX12 -> 0 | VZ19: =+VY12 -> 0 | WA19: =+VZ12 -> 0 | WB19: =+WA12 -> 3671.151 | WC19: =+SUM(UX19:WB19) -> 276870.1
B20: RECEITAS PARA O FLUXO DE CAIXA | D20: =+SUM(D14:D19) -> 0 | E20: =+SUM(E14:E19) -> 0 | F20: =+SUM(F14:F19) -> #REF! | G20: =+SUM(G14:G19) -> 0 | H20: =+SUM(H14:H19) -> 0 | I20: =+SUM(I14:I19) -> 0 | J20: =+SUM(J14:J19) -> 0 | K20: =+SUM(K14:K19) -> 0 | ... N20: =+SUM(N14:N19) -> 0 | O20: =+SUM(O14:O19)+C122 -> 4644.51 | P20: =+SUM(P14:P19) -> 0 | Q20: =+SUM(Q14:Q19) -> 0 | R20: =+SUM(R14:R19) -> 0 | S20: =+SUM(S14:S19) -> 0 | T20: =+SUM(T14:T19) -> 0 | U20: =+SUM(U14:U19) -> 0 | V20: =+SUM(V14:V19) -> 0 | W20: =+SUM(W14:W19) -> 0 | ... AE20: =+SUM(AE14:AE19) -> #REF! | AH20: =+SUM(D20:AE20) -> #REF! | AI20: =+SUM(AI14:AI19) -> 0 | AJ20: =+SUM(AJ14:AJ19) -> 0 | AK20: =+SUM(AK14:AK19) -> 0 | AL20: =+SUM(AL14:AL19) -> 0 | AM20: =+SUM(AM14:AM19) -> 0 | AN20: =+SUM(AN14:AN19) -> 0 | AO20: =+SUM(AO14:AO19) -> 0 | AP20: =+SUM(AP14:AP19) -> 0 | ... BM20: =+SUM(BM14:BM19) -> 0 | BN20: =+SUM(AI20:BM20) -> 0 | BO20: =+SUM(BO14:BO19) -> 0 | BP20: =+SUM(BP14:BP19) -> 0 | BQ20: =+SUM(BQ14:BQ19) -> 97880.344 | BR20: =+SUM(BR14:BR19) -> 49508.01 | BS20: =+SUM(BS14:BS19) -> 80606.825 | BT20: =+SUM(BT14:BT19) -> 33332.26 | BU20: =+SUM(BU14:BU19) -> 1402.9548 | BV20: =+SUM(BV14:BV19) -> 0 | ... CR20: =+SUM(CR14:CR19) -> 0 | CS20: =SUM(BO20:CR20) -> 857633.69 | CT20: =+SUM(CT14:CT19) -> 91542.835 | CU20: =+SUM(CU14:CU19) -> 49508.01 | CV20: =+SUM(CV14:CV19) -> 111705.64 | CW20: =+SUM(CW14:CW19) -> 0 | CX20: =+SUM(CX14:CX19) -> 0 | CY20: =+SUM(CY14:CY19) -> 3636.4 | CZ20: =+SUM(CZ14:CZ19) -> 30058.627 | DA20: =+SUM(DA14:DA19) -> 48940.172 | ... DX20: =+SUM(DX14:DX19) -> 31098.815 | DY20: =+SUM(CT20:DX20) -> 1091858.3 | DZ20: =+SUM(DZ14:DZ19) -> 78707.853 | EA20: =+SUM(EA14:EA19) -> 0 | EB20: =+SUM(EB14:EB19) -> 48940.172 | EC20: =+SUM(EC14:EC19) -> 0 | ED20: =+SUM(ED14:ED19) -> 0 | EE20: =+SUM(EE14:EE19) -> 97880.344 | EF20: =+SUM(EF14:EF19) -> 0 | EG20: =+SUM(EG14:EG19) -> 0 | ... FC20: =+SUM(FC14:FC19) -> 0 | FD20: =+SUM(DZ20:FC20) -> 787506.64 | FE20: =+SUM(FE14:FE19) -> 108155.89 | FF20: =+SUM(FF14:FF19) -> 48940.172 | FG20: =+SUM(FG14:FG19) -> 99488.369 | FH20: =+SUM(FH14:FH19) -> 0 | FI20: =+SUM(FI14:FI19) -> 0 | FJ20: =+SUM(FJ14:FJ19) -> 0 | FK20: =+SUM(FK14:FK19) -> 30058.627 | FL20: =+SUM(FL14:FL19) -> 48940.172 | ... GI20: =+SUM(GI14:GI19) -> 99488.369 | GJ20: =+SUM(FE20:GI20) -> 1254173.4 | GK20: =+SUM(GK14:GK19) -> 115648.71 | GL20: =+SUM(GL14:GL19) -> 0 | GM20: =+SUM(GM14:GM19) -> 0 | GN20: =+SUM(GN14:GN19) -> 0 | GO20: =+SUM(GO14:GO19) -> 0 | GP20: =+SUM(GP14:GP19) -> 97880.344 | GQ20: =+SUM(GQ14:GQ19) -> 49508.01 | GR20: =+SUM(GR14:GR19) -> 31098.815 | ... HO20: =+SUM(HO14:HO19) -> 35040.06 | HP20: =+SUM(GK20:HO20) -> 988387.62 | HQ20: =+SUM(HQ14:HQ19) -> 112174.06 | HR20: =+SUM(HR14:HR19) -> 48940.172 | HS20: =+SUM(HS14:HS19) -> 67821.716 | HT20: =+SUM(HT14:HT19) -> 0 | HU20: =+SUM(HU14:HU19) -> 0 | HV20: =+SUM(HV14:HV19) -> 80606.825 | HW20: =+SUM(HW14:HW19) -> 20659.617 | HX20: =+SUM(HX14:HX19) -> 43036.115 | ... IT20: =+SUM(IT14:IT19) -> 48940.172 | IU20: =+SUM(HQ20:IT20) -> 1218704.6 | IV20: =+SUM(IV14:IV19) -> 105829.69 | IW20: =+SUM(IW14:IW19) -> 0 | IX20: =+SUM(IX14:IX19) -> 3636.4 | IY20: =+SUM(IY14:IY19) -> 0 | IZ20: =+SUM(IZ14:IZ19) -> 0 | JA20: =+SUM(JA14:JA19) -> 82577.277 | JB20: =+SUM(JB14:JB19) -> 30058.627 | JC20: =+SUM(JC14:JC19) -> 68389.554 | ... JZ20: =+SUM(JZ14:JZ19) -> 34735.215 | KA20: =+SUM(IV20:JZ20) -> 1062811.8 | KB20: =+SUM(KB14:KB19) -> 76860.244 | KC20: =+SUM(KC14:KC19) -> 30058.627 | KD20: =+SUM(KD14:KD19) -> 67821.716 | KE20: =+SUM(KE14:KE19) -> 0 | KF20: =+SUM(KF14:KF19) -> 0 | KG20: =+SUM(KG14:KG19) -> 129547 | KH20: =+SUM(KH14:KH19) -> 2233.4452 | KI20: =+SUM(KI14:KI19) -> 1402.9548 | ... LE20: =+SUM(LE14:LE19) -> 30058.627 | LF20: =+SUM(KB20:LE20) -> 1061174.5 | LG20: =+SUM(LG14:LG19) -> 103852.03 | LH20: =+SUM(LH14:LH19) -> 49508.01 | LI20: =+SUM(LI14:LI19) -> 111705.64 | LJ20: =+SUM(LJ14:LJ19) -> 0 | LK20: =+SUM(LK14:LK19) -> 0 | LL20: =+SUM(LL14:LL19) -> 3636.4 | LM20: =+SUM(LM14:LM19) -> 30058.627 | LN20: =+SUM(LN14:LN19) -> 48940.172 | ... MK20: =+SUM(MK14:MK19) -> 31098.815 | ML20: =+SUM(LG20:MK20) -> 1104167.5 | MM20: =+SUM(MM14:MM19) -> 78707.853 | MN20: =+SUM(MN14:MN19) -> 0 | MO20: =+SUM(MO14:MO19) -> 48940.172 | MP20: =+SUM(MP14:MP19) -> 0 | MQ20: =+SUM(MQ14:MQ19) -> 0 | MR20: =+SUM(MR14:MR19) -> 97880.344 | MS20: =+SUM(MS14:MS19) -> 0 | MT20: =+SUM(MT14:MT19) -> 0 | ... NQ20: =+SUM(NQ14:NQ19) -> 48940.172 | NR20: =+SUM(MM20:NQ20) -> 836446.82 | NS20: =+SUM(NS14:NS19) -> 111827.04 | NT20: =+SUM(NT14:NT19) -> 48940.172 | NU20: =+SUM(NU14:NU19) -> 99488.369 | NV20: =+SUM(NV14:NV19) -> 0 | NW20: =+SUM(NW14:NW19) -> 0 | NX20: =+SUM(NX14:NX19) -> 0 | NY20: =+SUM(NY14:NY19) -> 30058.627 | NZ20: =+SUM(NZ14:NZ19) -> 48940.172 | ... OT20: =+SUM(OT14:OT19) -> 30058.627 | OU20: =+SUM(NS20:OT20) -> 1060475.9 | OV20: =+SUM(OV14:OV19) -> 74832.181 | OW20: =+SUM(OW14:OW19) -> 0 | OX20: =+SUM(OX14:OX19) -> 0 | OY20: =+SUM(OY14:OY19) -> 0 | OZ20: =+SUM(OZ14:OZ19) -> 0 | PA20: =+SUM(PA14:PA19) -> 97880.344 | PB20: =+SUM(PB14:PB19) -> 49508.01 | PC20: =+SUM(PC14:PC19) -> 31098.815 | ... PZ20: =+SUM(PZ14:PZ19) -> 35040.06 | QA20: =+SUM(OV20:PZ20) -> 866964.27 | QB20: =+SUM(QB14:QB19) -> 39364.964 | QC20: =+SUM(QC14:QC19) -> 48940.172 | QD20: =+SUM(QD14:QD19) -> 67821.716 | QE20: =+SUM(QE14:QE19) -> 0 | QF20: =+SUM(QF14:QF19) -> 0 | QG20: =+SUM(QG14:QG19) -> 80606.825 | QH20: =+SUM(QH14:QH19) -> 20659.617 | QI20: =+SUM(QI14:QI19) -> 43036.115 | ... RE20: =+SUM(RE14:RE19) -> 48940.172 | RF20: =+SUM(QB20:RE20) -> 997466.99 | RG20: =+SUM(RG14:RG19) -> 0 | RH20: =+SUM(RH14:RH19) -> 0 | RI20: =+SUM(RI14:RI19) -> 3636.4 | RJ20: =+SUM(RJ14:RJ19) -> 0 | RK20: =+SUM(RK14:RK19) -> 0 | RL20: =+SUM(RL14:RL19) -> 82577.277 | RM20: =+SUM(RM14:RM19) -> 30058.627 | RN20: =+SUM(RN14:RN19) -> 68389.554 | ... SK20: =+SUM(SK14:SK19) -> 34735.215 | SL20: =+SUM(RG20:SK20) -> 827435.14 | SM20: =+SUM(SM14:SM19) -> 144497.93 | SN20: =+SUM(SN14:SN19) -> 30058.627 | SO20: =+SUM(SO14:SO19) -> 67821.716 | SP20: =+SUM(SP14:SP19) -> 0 | SQ20: =+SUM(SQ14:SQ19) -> 0 | SR20: =+SUM(SR14:SR19) -> 129547 | SS20: =+SUM(SS14:SS19) -> 2233.4452 | ST20: =+SUM(ST14:ST19) -> 1402.9548 | ... TP20: =+SUM(TP14:TP19) -> 30058.627 | TQ20: =+SUM(SM20:TP20) -> 2030491.3 | TR20: =+SUM(TR14:TR19) -> #REF! | TS20: =+SUM(TS14:TS19) -> #REF! | TT20: =+SUM(TT14:TT19) -> 111705.64 | TU20: =+SUM(TU14:TU19) -> 0 | TV20: =+SUM(TV14:TV19) -> 0 | TW20: =+SUM(TW14:TW19) -> 3636.4 | TX20: =+SUM(TX14:TX19) -> 30058.627 | TY20: =+SUM(TY14:TY19) -> 48940.172 | ... UV20: =+SUM(UV14:UV19) -> 31098.815 | UW20: =+SUM(TR20:UV20) -> #REF! | UX20: =+SUM(UX14:UX19) -> 146345.54 | UY20: =+SUM(UY14:UY19) -> 0 | UZ20: =+SUM(UZ14:UZ19) -> 48940.172 | VA20: =+SUM(VA14:VA19) -> 0 | VB20: =+SUM(VB14:VB19) -> 0 | VC20: =+SUM(VC14:VC19) -> 97880.344 | VD20: =+SUM(VD14:VD19) -> 0 | VE20: =+SUM(VE14:VE19) -> 0 | ... WB20: =+SUM(WB14:WB19) -> 48940.172 | WC20: =+SUM(UX20:WB20) -> 1886370.4
