Workbook

Sheet Dados
B2: BALANÇO PATRIMONIAL (R$ MIL) - ANO 2014
B3: Ativo | E3: Passivo
B5: Ativo Circulante | C5: =SUM(C6:C13) -> 1900 | E5: Passivo Circulante | F5: =SUM(F6:F13) -> 1600
B7: Disponível | C7: 450 | E7: Fornecedores | F7: 250
B8: Duplicatas a receber | C8: 950 | E8: Impostos, taxas e contribuições | F8: 450
B9: Estoques | C9: 350 | E9: Obrigações trabalhistas | F9: 250
B10: Impostos a recuperar | C10: 100 | E10: Obrigações administrativas | F10: 350
B11: Outros | C11: 50 | E11: Empréstimos e financiamentos | F11: 150
E12: Provisões | F12: 150
B14: Ativo Não Circulante | C14: =C15+SUM(C21:C23) -> 1950 | E14: Passivo Não Circulante | F14: =F15+F20 -> 2250
B15: Realizavel a Longo Prazo | C15: =SUM(C16:C19) -> 450 | E15: Exigivel a Longo Prazo | F15: =SUM(F16:F19) -> 400
B16: Duplicatas a receber LP | C16: 0 | E16: Fornecedores a longo prazo | F16: 150
B17: Créditos com atividades ligadas | C17: 450 | E17: Empréstimos e financiamentos | F17: 150
E18: Outras contas a pagar | F18: 100
E20: Patrimônio Líquido | F20: =SUM(F21:F24) -> 1850
B21: Investimentos | C21: 300 | E21: Capital Social | F21: 1000
B22: Imobilizado | C22: 800 | E22: Lucros / Prejuizos | F22: =C49 -> 350
B23: Diferido | C23: 400 | E23: Reservas | F23: 500
B25: Total | C25: =C5+C14 -> 3850 | F25: =F5+F14 -> 3850
B27: DEMONSTRAÇÃO DE RESULTADO DO EXERCÍCIO (R$ MIL) - ANO 2014
B29: Receita Operacional Bruta | C29: 10000
B31: (-) Deduções | C31: =-C29*37.5% -> -3750
B33: (=) Receita Operacional Liquida | C33: =C29+C31 -> 6250
B35: (-) Custo das mercadorias vendidas | C35: -4500
B37: (=) Lucro Bruto | C37: =C33+C35 -> 1750
B39: (-) Despesas Operacionais | C39: -1241
B41: (=) Lucro Operacional | C41: =C37+C39 -> 509
B43: (+/-) Receitas/Despesas não operac | C43: 72
B45: (=) Lucro antes do IR e CSLL | C45: =C41+C43 -> 581
B47: (-) Provisão para IR e CSLL | C47: -231
B49: (=) Lucro Liquido | C49: =C45+C47 -> 350

Sheet Estrutura de Capital
B3: Endividamento Geral
B5: PC + PELP | C5: x 100 | D5: = | E5: =Dados!F5 -> 1600 | F5: + | G5: =Dados!F15 -> 400 | H5: = | I5: =E5+G5 -> 2000 | J5: = | K5: =I5/I6 -> 0.51948052 | L5: x 100 | M5: = | N5: =K5*100 -> 51.948052 | O5: -100
B6: Passivo Total | E6: =Dados!F25 -> 3850 | I6: =E6 -> 3850
B8: Composição do Endividamento
B10: PC | C10: x 100 | D10: = | E10: =Dados!F5 -> 1600 | H10: = | I10: =E10+G10 -> 1600 | J10: = | K10: =I10/I11 -> 0.8 | L10: x 100 | M10: = | N10: =K10*100 -> 80 | O10: -100
B11: PC + PELP | E11: =Dados!F5 -> 1600 | F11: + | G11: =Dados!F15 -> 400 | I11: =E11+G11 -> 2000
B13: Imobilização do patrimônio líquido
B15: AP | C15: x 100 | D15: = | E15: =Dados!C20 -> 0 | H15: = | I15: =E15+G15 -> 0 | J15: = | K15: =I15/I16 -> 0 | L15: x 100 | M15: = | N15: =K15*100 -> 0 | O15: -100
B16: PL | E16: =Dados!F20 -> 1850 | I16: =E16+G16 -> 1850
B18: Imobilização de recursos não recorrentes
B20: AP | C20: x 100 | D20: = | E20: =Dados!C20 -> 0 | H20: = | I20: =E20+G20 -> 0 | J20: = | K20: =I20/I21 -> 0 | L20: x 100 | M20: = | N20: =K20*100 -> 0 | O20: -100
B21: PL + PELP | E21: =Dados!F20 -> 1850 | F21: + | G21: =Dados!F15 -> 400 | I21: =E21+G21 -> 2250
B23: Passivo oneroso sobre o ativo
B25: PC + PELP | C25: x 100 | D25: = | E25: =Dados!F11 -> 150 | F25: + | G25: =Dados!F16 -> 150 | H25: = | I25: =E25+G25 -> 300 | J25: = | K25: =I25/I26 -> 0.077922078 | L25: x 100 | M25: = | N25: =K25*100 -> 7.7922078 | O25: -100
B26: ATIVO | E26: =Dados!C25 -> 3850 | I26: =E26+G26 -> 3850

Sheet Liquidez
B3: Liquidez imediata
B5: Disponível | C5: = | D5: =Dados!C7 -> 450 | E5: = | F5: =D5/D6 -> 0.28125
B6: PC | D6: =Dados!F5 -> 1600
B8: Liquidez Corrente
B10: AC | C10: = | D10: =Dados!C5 -> 1900 | E10: = | F10: =D10/D11 -> 1.1875
B11: PC | D11: =Dados!F5 -> 1600
B13: Liquidez Seca
B15: AC - Estoque | C15: = | D15: =Dados!C5 -> 1900 | E15: - | F15: =Dados!C9 -> 350 | G15: = | H15: =D15-F15 -> 1550 | I15: = | J15: =H15/H16 -> 0.96875
B16: PC | D16: =Dados!F5 -> 1600 | H16: =D16+F16 -> 1600
B18: Liquidez Geral
B20: AC + ARLP | C20: = | D20: =Dados!C5 -> 1900 | E20: + | F20: =Dados!C15 -> 450 | G20: = | H20: =D20+F20 -> 2350 | I20: = | J20: =H20/H21 -> 1.175
B21: PC + PELP | D21: =Dados!F5 -> 1600 | E21: + | F21: =Dados!F15 -> 400 | H21: =D21+F21 -> 2000

Sheet Rentabilidade
B3: Rentabilidade do Patrimonio
B5: Lucro Liquido | C5: x 100 | D5: = | E5: =Dados!C49 -> 350 | F5: = | G5: =E5/E6 -> 0.18918919 | H5: x 100 | I5: = | J5: =G5*100 -> 18.918919
B6: Patrimônio Liquido | E6: =Dados!F20 -> 1850
B8: Rentabilidade dos ativos
J9: 100
B10: Lucro Liquido | C10: x 100 | D10: = | E10: =Dados!C49 -> 350 | F10: = | G10: =E10/E11 -> 0.090909091 | H10: x 100 | I10: = | J10: =G10*100 -> 9.0909091
B11: Ativo Total | E11: =Dados!C25 -> 3850 | J11: =J9/J10 -> 11
B13: Giro do ativo
B15: Vendas Líquidas | D15: = | E15: =Dados!C33 -> 6250 | F15: = | G15: =E15/E16 -> 1.6233766
B16: Ativo Total | E16: =Dados!C25 -> 3850
B18: Margem bruta
B20: Lucro Bruto | C20: x 100 | D20: = | E20: =Dados!C37 -> 1750 | F20: = | G20: =E20/E21 -> 0.28 | H20: x 100 | I20: = | J20: =G20*100 -> 28
B21: Receita Operacional Liquida | E21: =Dados!C33 -> 6250
B23: Margem Operacional
B25: Lucro Operacional | C25: x 100 | D25: = | E25: =Dados!C41 -> 509 | F25: = | G25: =E25/E26 -> 0.08144 | H25: x 100 | I25: = | J25: =G25*100 -> 8.144
B26: Receita Operacional Liquida | E26: =Dados!C33 -> 6250
B28: Margem Líquida
B30: Lucro Líquido | C30: x 100 | D30: = | E30: =Dados!C49 -> 350 | F30: = | G30: =E30/E31 -> 0.056 | H30: x 100 | I30: = | J30: =G30*100 -> 5.6
B31: Receita Operacional Liquida | E31: =Dados!C33 -> 6250

Sheet Prazos Médios
B1: ANO 2014
B3: Prazo médio de compra
B5: MC = CMV + Estoque Final - Estoque Inicial | E5: =-Dados!C35 -> 4500 | G5: =Dados!C9 -> 350 | H5: -720 | I5: = | J5: =SUM(E5:H5) -> 4130
B7: Fornecedores | C7: x 360 | D7: = | E7: =Dados!F7+Dados!F16 -> 400 | F7: x | G7: 360
B8: Montante de compras | E8: =J5 -> 4130
E10: =E7/E8 -> 0.0968523 | F10: x | G10: 360 | I10: = | J10: =E10*G10 -> 34.866828
B12: Prazo médio de estoques
B14: Estoques | C14: x 360 | D14: = | E14: =Dados!C9 -> 350 | F14: x | G14: 360 | I14: =
B15: Custo da mercadoria vendida | E15: =-Dados!C35 -> 4500
E17: =E14/E15 -> 0.077777778 | F17: x | G17: 360 | I17: = | J17: =E17*G17 -> 28
B19: Prazo médio de recebimentos
B21: Clientes | C21: x 360 | D21: = | E21: =Dados!C8+Dados!C16 -> 950 | F21: x | G21: 360 | I21: =
B22: Receita Operacional Bruta | E22: =Dados!C29 -> 10000
E24: =E21/E22 -> 0.095 | F24: x | G24: 360 | I24: = | J24: =E24*G24 -> 34.2
N25: Compra | Q25: Vende | S25: Recebe
B26: Ciclo operacional
B28: CO = PME + PMR | E28: =J17 -> 28 | F28: + | G28: =J24 -> 34.2 | I28: = | J28: =E28+G28 -> 62.2
N29: 0 | O29: 30 | P29: 60 | Q29: 90 | R29: 120 | S29: 150 | T29: 180
B30: Ciclo Financeiro
B32: CF = CO - PMC | E32: =J28 -> 62.2 | F32: - | G32: =J10 -> 34.866828 | I32: = | J32: =E32-G32 -> 27.333172
