Workbook

Sheet Dados
B2: BALANÇO PATRIMONIAL (R$ MIL)
B3: Ativo | E3: Passivo
B5: Ativo Circulante | C5: =SUM(C6:C13) -> 5800 | E5: Passivo Circulante | F5: =SUM(F6:F13) -> 5100
B7: Disponível | C7: 1800 | E7: Fornecedores | F7: 2000
B8: Clientes | C8: 1000 | E8: Impostos, taxas e contribuições | F8: 1600
B9: Estoques | C9: 1000 | E9: Obrigações trabalhistas | F9: 300
B10: Impostos a recuperar | C10: 1500 | E10: Obrigações administrativas | F10: 400
B11: Outros contas a receber | C11: 500 | E11: Empréstimos e financiamentos | F11: 600
E12: Provisões | F12: 200
B14: Ativo Não Circulante | C14: =C15+SUM(C20:C22) -> 4650 | E14: Passivo Não Circulante | F14: =F15+SUM(F20:F22) -> 5350
B15: Realizavel a Longo Prazo | C15: =SUM(C16:C18) -> 500 | E15: Exigivel a Longo Prazo | F15: =SUM(F16:F18) -> 400
B16: Clientes a longo prazo | C16: 500 | E16: Empréstimos e financiamentos | F16: 200
E17: Fornecedores LP | F17: 200
E19: Patrimônio Líquido | F19: =SUM(F20:F23) -> 4950
B20: Investimentos | C20: 850 | E20: Capital Social | F20: 790
B21: Imobilizado | C21: 3200 | E21: Lucros / Prejuizos | F21: =C55 -> 3870
B22: Intangível | C22: 100 | E22: Reservas | F22: 290
B24: Total | C24: =C5+C14 -> 10450 | F24: =F5+F14 -> 10450 | G24: =C24-F24 -> 0
B26: DEMONSTRAÇÃO DE RESULTADO DO EXERCÍCIO (R$ MIL)
B28: Receita Operacional Bruta | C28: 12000
B30: (-) Deduções | C30: -2000
B32: (=) Receita Operacional Liquida | C32: =C28+C30 -> 10000
B34: (-) Custo das mercadorias vendidas | C34: -3500
B36: (=) Lucro Bruto | C36: =C32+C34 -> 6500
B38: (-) Despesas Operacionais | C38: =SUM(C39:C42) -> -2500
B39: Administrativas | C39: -1000
B40: Comercial | C40: -1000
B41: Logistica | C41: -500
B42: Marketing | C42: 0
B44: (=) Lucro Operacional | C44: =C36+C38 -> 4000
B46: (+/-) Receitas/Despesas não operac | C46: =SUM(C47:C49) -> 100
B47: Receitas Financeiras | C47: 1700
B48: Juros Ativos | C48: 2000
B49: Juros Passivos | C49: -3600
B51: (=) Lucro antes do IR e CSLL | C51: =C44+C46 -> 4100
B53: (-) Provisão para IR e CSLL | C53: -230
B55: (=) Lucro Liquido | C55: =C51+C53 -> 3870

Sheet Estrutura de Capital
B3: Endividamento Geral
B5: PC + PELP | C5: x 100 | D5: = | E5: =Dados!F5 -> 5100 | F5: + | G5: =Dados!F15 -> 400 | H5: = | I5: =E5+G5 -> 5500 | J5: = | K5: =I5/I6 -> 0.52631579 | L5: x 100 | M5: = | N5: =K5*100 -> 52.631579 | O5: -100
B6: Passivo Total | E6: =Dados!F24 -> 10450 | I6: =E6 -> 10450
B8: Composição do Endividamento
B10: PC | C10: x 100 | D10: = | E10: =Dados!F5 -> 5100 | H10: = | I10: =E10+G10 -> 5100 | J10: = | K10: =I10/I11 -> 0.92727273 | L10: x 100 | M10: = | N10: =K10*100 -> 92.727273 | O10: -100
B11: PC + PELP | E11: =Dados!F5 -> 5100 | F11: + | G11: =Dados!F15 -> 400 | I11: =E11+G11 -> 5500
B13: Imobilização do patrimônio líquido
B15: AP | C15: x 100 | D15: = | E15: =Dados!C19 -> 0 | H15: = | I15: =E15+G15 -> 0 | J15: = | K15: =I15/I16 -> 0 | L15: x 100 | M15: = | N15: =K15*100 -> 0 | O15: -100
B16: PL | E16: =Dados!F19 -> 4950 | I16: =E16+G16 -> 4950
B18: Imobilização de recursos não recorrentes
B20: AP | C20: x 100 | D20: = | E20: =Dados!C19 -> 0 | H20: = | I20: =E20+G20 -> 0 | J20: = | K20: =I20/I21 -> 0 | L20: x 100 | M20: = | N20: =K20*100 -> 0 | O20: -100
B21: PL + PELP | E21: =Dados!F19 -> 4950 | F21: + | G21: =Dados!F15 -> 400 | I21: =E21+G21 -> 5350
B23: Passivo oneroso sobre o ativo
B25: PC + PELP | C25: x 100 | D25: = | E25: =Dados!F11 -> 600 | F25: + | G25: =Dados!F16 -> 200 | H25: = | I25: =E25+G25 -> 800 | J25: = | K25: =I25/I26 -> 0.076555024 | L25: x 100 | M25: = | N25: =K25*100 -> 7.6555024 | O25: -100
B26: ATIVO | E26: =Dados!C24 -> 10450 | I26: =E26+G26 -> 10450

Sheet Liquidez
B3: Liquidez imediata
B5: Disponível | C5: = | D5: =Dados!C7 -> 1800 | E5: = | F5: =D5/D6 -> 0.35294118
B6: PC | D6: =Dados!F5 -> 5100
B8: Liquidez Corrente
B10: AC | C10: = | D10: =Dados!C5 -> 5800 | E10: = | F10: =D10/D11 -> 1.1372549
B11: PC | D11: =Dados!F5 -> 5100
B13: Liquidez Seca
B15: AC - Estoque | C15: = | D15: =Dados!C5 -> 5800 | E15: - | F15: =Dados!C9 -> 1000 | G15: = | H15: =D15-F15 -> 4800 | I15: = | J15: =H15/H16 -> 0.94117647
B16: PC | D16: =Dados!F5 -> 5100 | H16: =D16+F16 -> 5100
B18: Liquidez Geral
B20: AC + ARLP | C20: = | D20: =Dados!C5 -> 5800 | E20: + | F20: =Dados!C15 -> 500 | G20: = | H20: =D20+F20 -> 6300 | I20: = | J20: =H20/H21 -> 1.1454545
B21: PC + PELP | D21: =Dados!F5 -> 5100 | E21: + | F21: =Dados!F15 -> 400 | H21: =D21+F21 -> 5500

Sheet Rentabilidade
B3: Rentabilidade do Patrimonio
B5: Lucro Liquido | C5: x 100 | D5: = | E5: =Dados!C55 -> 3870 | F5: = | G5: =E5/E6 -> 0.78181818 | H5: x 100 | I5: = | J5: =G5*100 -> 78.181818
B6: Patrimônio Liquido | E6: =Dados!F19 -> 4950
B8: Rentabilidade dos ativos
J9: 100
B10: Lucro Liquido | C10: x 100 | D10: = | E10: =Dados!C55 -> 3870 | F10: = | G10: =E10/E11 -> 0.37033493 | H10: x 100 | I10: = | J10: =G10*100 -> 37.033493
B11: Ativo Total | E11: =Dados!C24 -> 10450 | J11: =J9/J10 -> 2.7002584
B13: Giro do ativo
B15: Vendas Líquidas | D15: = | E15: =Dados!C32 -> 10000 | F15: = | G15: =E15/E16 -> 0.9569378
B16: Ativo Total | E16: =Dados!C24 -> 10450
B18: Margem bruta
B20: Lucro Bruto | C20: x 100 | D20: = | E20: =Dados!C36 -> 6500 | F20: = | G20: =E20/E21 -> 0.65 | H20: x 100 | I20: = | J20: =G20*100 -> 65
B21: Receita Operacional Liquida | E21: =Dados!C32 -> 10000
B23: Margem Operacional
B25: Lucro Operacional | C25: x 100 | D25: = | E25: =Dados!C44 -> 4000 | F25: = | G25: =E25/E26 -> 0.4 | H25: x 100 | I25: = | J25: =G25*100 -> 40
B26: Receita Operacional Liquida | E26: =Dados!C32 -> 10000
B28: Margem Líquida
B30: Lucro Líquido | C30: x 100 | D30: = | E30: =Dados!C55 -> 3870 | F30: = | G30: =E30/E31 -> 0.387 | H30: x 100 | I30: = | J30: =G30*100 -> 38.7
B31: Receita Operacional Liquida | E31: =Dados!C32 -> 10000

Sheet Prazo
B3: Prazo médio de compra
B5: MC = CMV + Estoque Inicial - Estoque Final | E5: =-Dados!C34 -> 3500 | G5: =Dados!C9 -> 1000 | H5: -50 | I5: = | J5: =SUM(E5:H5) -> 4450
B7: Fornecedores | C7: x 360 | D7: = | E7: =Dados!F7 -> 2000 | F7: x | G7: 360
B8: Montante de compras | E8: =J5 -> 4450
E10: =E7/E8 -> 0.4494382 | F10: x | G10: 360 | I10: = | J10: =E10*G10 -> 161.79775
B12: Prazo médio de estoques
B14: Estoques | C14: x 360 | D14: = | E14: =Dados!C9 -> 1000 | F14: x | G14: 360 | I14: =
B15: Custo da mercadoria vendida | E15: =-Dados!C34 -> 3500
E17: =E14/E15 -> 0.28571429 | F17: x | G17: 360 | I17: = | J17: =E17*G17 -> 102.85714
B19: Prazo médio de recebimentos
B21: Clientes | C21: x 360 | D21: = | E21: =Dados!C8+Dados!C16 -> 1500 | F21: x | G21: 360 | I21: =
B22: Receita Operacional Bruta | E22: =Dados!C28 -> 12000
E24: =E21/E22 -> 0.125 | F24: x | G24: 360 | I24: = | J24: =E24*G24 -> 45
B26: Ciclo operacional
B28: CO = PME + PMR | E28: =J17 -> 102.85714 | F28: + | G28: =J24 -> 45 | I28: = | J28: =E28+G28 -> 147.85714
B30: Ciclo Financeiro
B32: CF = CO - PMC | E32: =J28 -> 147.85714 | F32: - | G32: =J10 -> 161.79775 | I32: = | J32: =E32-G32 -> -13.94061
