Workbook
Name B17I: #REF!
Name B3I: #REF!
Name cadastro: #REF!
Name entrada: #REF!
Name estoque: ' '!$AY$1
Name item: 'Controle Detalhado'!#REF!
Name numitem: #REF!
Name preco: #REF!
Name saida: Saidas!#REF!
Name saldo: 'Controle Detalhado'!#REF!
Name Tabela75: #REF!
Name tudoexcel: 'Controle Detalhado'!#REF!,'Controle Detalhado'!#REF!

Sheet APRESENTAÇÃO
B3: Bem-vindo à Planilha de Controle de Almoxarifado do Sienge Esse modelo de Planilha de Controle de Almoxarifado permite gerenciar seu estoque a partir do registro de cada Entrada e Saída de insumos ou equipamentos, verificando facilmente os custos, quantidade e principais informações do item. Acesse um dos botões do menu abaixo: | F3: Apareceu uma barra rosa no topo do arquivo dizendo que a planilha não é segura? Basta clicar em "Obter mais detalhes" e posteriormente clicar no botão “Editar mesmo assim”.
B5: Caso você precise fazer algum tipo de edição, fique tranquilo, pois esse arquivo é desbloqueado e permite a adaptação para sua empresa. E não esqueça, se as planilhas não permitirem mais o desempenho desejado para sua empresa e você quiser uma gestão mais madura, sem retrabalho e que permita fácil acesso a informações gerenciais, você precisa de um ERP, um Software de Gestão de Obras. Quem sabe não é a hora de conhecer o Sienge? Acesse: www.sienge.com.br ou assista a palestra Gestão de Estoque do Sienge clicando no banner.
A7: Faça a gestão completa de sua obra com o Sienge, saiba mais em www.sienge.com.br ou (48) 3027 8110.

Sheet Como Utilizar
B3: 1º | C3: Somente as células brancas devem ser preenchidas; | F3: Apareceu uma barra rosa no topo do arquivo dizendo que a planilha não é segura? Basta clicar em "Obter mais detalhes" e posteriormente clicar no botão “Editar mesmo assim”.
B4: 2º | C4: Todas as células verdes estão devidamente configuradas para alimentar automaticamente seu Controle de Almoxarifado;
B5: 3º | C5: A Planilha Controle de Almoxarifado é um modelo gratuito, totalmente aberto a edição, que permite adequações para o processo de sua empresa;
B6: 4º | C6: Essa planilha permite que você tenha dois controles, ficando a escolha a seu critérios;
B7: 5º | C7: As duas opções de controle permitem o registro de entradas, saídas e alertam quanto a necessidade de compra;
B8: 6º | C8: Controle Simplificado - Trabalhe em uma única aba, com controle diário de entradas e saídas; Veja como funciona:
B10: 7º | C10: Controle Detalhado - Trabalhe com controle individual de entradas e saídas e ainda tenha um relatório para controlar seu almoxarifado. É fácil e fornece mais informações: registre as informações o item, seja ele insumo ou equipamento, em detalhes uma única vez na aba Entradas; alimente a aba Saídas com todas as entregas de itens e também com as devoluções, caso ocorram; insira na aba Controle Detalhado o código do item e a quantidade mínima necessária. Pronto seu almoxarifado da obra estará sob controle!
B13: 8º | C13: Informações Padrão - Nessa aba você encontra informações pré-definidas como padrão para o preenchimento do seu Controle de Almoxarifado. Como a planilha é aberta a edição você pode incluir e excluir informações tranquilamente, porém isso implicará nas opções de preenchimento das demais abas. Orientamos que, sempre que houver inclusão de novas linhas de informação na aba ‘Informações Padrão’ você teste se as opções de resposta permanecem ok, principalmente na aba Entradas. Caso a nova informação padrão não apareça como opção de resposta faça o seguinte: Clique na célula onde a resposta deverá aparecer > Menu > DADOS > VALIDAÇÃO DE DADOS ; abrirá uma janela de CONFIGURAÇÕES onde você deverá indicar no campo FONTE informações quais as opções de resposta devem aparecer.
B17: 9º | C17: Se você preferir um controle que integre o almoxarifado ao setores de Suprimentos, Compras e até Planejamento de obra acesse www.sienge.com.br e conheça do software de gestão Sienge!
A19: Faça a gestão completa de sua obra com o Sienge, saiba mais em www.sienge.com.br ou (48) 3027 8110.

Sheet Controle Simplificado
A3: Código | B3: Descrição do Item | C3: Categoria | D3: Und. Medida | E3: Preço Unitário | F3: Centro de custo | G3: Saldo Minimo | H3: Saldo Atual | I3: Preço Total | J3: Situação | K3: Saldo Inicial | L3: 42675 | M3: 42676 | N3: 42677 | O3: 42678 | P3: 42679 | Q3: 42680 | R3: 42681 | S3: 42682 | T3: 42683 | U3: 42684 | V3: 42685 | W3: 42686 | X3: 42687 | Y3: 42688 | Z3: 42689 | AA3: 42690 | AB3: 42691 | AC3: 42692 | AD3: 42693 | AE3: 42694 | AF3: 42695 | AG3: 42696 | AH3: 42697 | AI3: 42698 | AJ3: 42699 | AK3: 42700 | AL3: 42701 | AM3: 42702 | AN3: 42703 | AO3: 42704 | AP3: 42705 | AQ3: 42706 | AR3: 42707 | AS3: 42708 | AT3: 42709 | AU3: 42710 | AV3: 42711 | AW3: 42712 | AX3: 42713 | AY3: 42714 | AZ3: 42715 | BA3: 42716 | BB3: 42717 | BC3: 42718 | BD3: 42719 | BE3: 42720 | BF3: 42721 | BG3: 42722 | BH3: 42723 | BI3: 42724 | BJ3: 42725 | BK3: 42726 | BL3: 42727 | BM3: 42728 | BN3: 42729 | BO3: 42730 | BP3: 42731 | BQ3: 42732 | BR3: 42733 | BS3: 42734 | BT3: 42735 | BU3: 42736 | BV3: 42737 | BW3: 42738 | BX3: 42739 | BY3: 42740 | BZ3: 42741 | CA3: 42742 | CB3: 42743 | CC3: 42744 | CD3: 42745 | CE3: 42746 | CF3: 42747 | CG3: 42748 | CH3: 42749 | CI3: 42750 | CJ3: 42751 | CK3: 42752 | CL3: 42753 | CM3: 42754 | CN3: 42755 | CO3: 42756 | CP3: 42757 | CQ3: 42758 | CR3: 42759 | CS3: 42760 | CT3: 42761 | CU3: 42762 | CV3: 42763 | CW3: 42764 | CX3: 42765 | CY3: 42766 | CZ3: 42767 | DA3: 42768 | DB3: 42769 | DC3: 42770 | DD3: 42771 | DE3: 42772 | DF3: 42773 | DG3: 42774 | DH3: 42775 | DI3: 42776 | DJ3: 42777 | DK3: 42778 | DL3: 42779 | DM3: 42780 | DN3: 42781 | DO3: 42782 | DP3: 42783 | DQ3: 42784 | DR3: 42785 | DS3: 42786 | DT3: 42787 | DU3: 42788 | DV3: 42789 | DW3: 42790 | DX3: 42791 | DY3: 42792 | DZ3: 42793 | EA3: 42794 | EB3: 42795 | EC3: 42796 | ED3: 42797 | EE3: 42798 | EF3: 42799 | EG3: 42800 | EH3: 42801 | EI3: 42802 | EJ3: 42803 | EK3: 42804 | EL3: 42805 | EM3: 42806 | EN3: 42807 | EO3: 42808 | EP3: 42809 | EQ3: 42810 | ER3: 42811 | ES3: 42812 | ET3: 42813 | EU3: 42814 | EV3: 42815 | EW3: 42816 | EX3: 42817 | EY3: 42818 | EZ3: 42819 | FA3: 42820 | FB3: 42821 | FC3: 42822 | FD3: 42823 | FE3: 42824 | FF3: 42825 | FG3: 42826 | FH3: 42827 | FI3: 42828 | FJ3: 42829 | FK3: 42830 | FL3: 42831 | FM3: 42832 | FN3: 42833 | FO3: 42834 | FP3: 42835 | FQ3: 42836 | FR3: 42837 | FS3: 42838 | FT3: 42839 | FU3: 42840 | FV3: 42841 | FW3: 42842 | FX3: 42843 | FY3: 42844 | FZ3: 42845 | GA3: 42846 | GB3: 42847 | GC3: 42848 | GD3: 42849 | GE3: 42850 | GF3: 42851 | GG3: 42852 | GH3: 42853 | GI3: 42854 | GJ3: 42855 | GK3: 42856 | GL3: 42857 | GM3: 42858 | GN3: 42859 | GO3: 42860 | GP3: 42861 | GQ3: 42862 | GR3: 42863 | GS3: 42864 | GT3: 42865 | GU3: 42866 | GV3: 42867 | GW3: 42868 | GX3: 42869 | GY3: 42870 | GZ3: 42871 | HA3: 42872 | HB3: 42873 | HC3: 42874 | HD3: 42875 | HE3: 42876 | HF3: 42877 | HG3: 42878 | HH3: 42879 | HI3: 42880 | HJ3: 42881 | HK3: 42882 | HL3: 42883 | HM3: 42884 | HN3: 42885 | HO3: 42886 | HP3: 42887 | HQ3: 42888 | HR3: 42889 | HS3: 42890 | HT3: 42891 | HU3: 42892 | HV3: 42893 | HW3: 42894 | HX3: 42895 | HY3: 42896 | HZ3: 42897 | IA3: 42898 | IB3: 42899 | IC3: 42900 | ID3: 42901 | IE3: 42902 | IF3: 42903 | IG3: 42904 | IH3: 42905 | II3: 42906 | IJ3: 42907 | IK3: 42908 | IL3: 42909 | IM3: 42910 | IN3: 42911 | IO3: 42912 | IP3: 42913 | IQ3: 42914 | IR3: 42915 | IS3: 42916 | IT3: 42917 | IU3: 42918 | IV3: 42919 | IW3: 42920 | IX3: 42921 | IY3: 42922 | IZ3: 42923 | JA3: 42924 | JB3: 42925 | JC3: 42926 | JD3: 42927 | JE3: 42928 | JF3: 42929 | JG3: 42930 | JH3: 42931 | JI3: 42932 | JJ3: 42933 | JK3: 42934 | JL3: 42935 | JM3: 42936 | JN3: 42937 | JO3: 42938 | JP3: 42939 | JQ3: 42940 | JR3: 42941 | JS3: 42942 | JT3: 42943 | JU3: 42944 | JV3: 42945 | JW3: 42946 | JX3: 42947 | JY3: 42948 | JZ3: 42949 | KA3: 42950 | KB3: 42951 | KC3: 42952 | KD3: 42953 | KE3: 42954 | KF3: 42955 | KG3: 42956 | KH3: 42957 | KI3: 42958 | KJ3: 42959 | KK3: 42960 | KL3: 42961 | KM3: 42962 | KN3: 42963 | KO3: 42964 | KP3: 42965 | KQ3: 42966 | KR3: 42967 | KS3: 42968 | KT3: 42969 | KU3: 42970 | KV3: 42971 | KW3: 42972 | KX3: 42973 | KY3: 42974 | KZ3: 42975 | LA3: 42976 | LB3: 42977 | LC3: 42978 | LD3: 42979 | LE3: 42980 | LF3: 42981 | LG3: 42982 | LH3: 42983 | LI3: 42984 | LJ3: 42985 | LK3: 42986 | LL3: 42987 | LM3: 42988 | LN3: 42989 | LO3: 42990 | LP3: 42991 | LQ3: 42992 | LR3: 42993 | LS3: 42994 | LT3: 42995 | LU3: 42996 | LV3: 42997 | LW3: 42998 | LX3: 42999 | LY3: 43000 | LZ3: 43001 | MA3: 43002 | MB3: 43003 | MC3: 43004 | MD3: 43005 | ME3: 43006 | MF3: 43007 | MG3: 43008 | MH3: 43009 | MI3: 43010 | MJ3: 43011 | MK3: 43012 | ML3: 43013 | MM3: 43014 | MN3: 43015 | MO3: 43016 | MP3: 43017 | MQ3: 43018 | MR3: 43019 | MS3: 43020 | MT3: 43021 | MU3: 43022 | MV3: 43023 | MW3: 43024 | MX3: 43025 | MY3: 43026 | MZ3: 43027 | NA3: 43028 | NB3: 43029 | NC3: 43030 | ND3: 43031 | NE3: 43032 | NF3: 43033 | NG3: 43034 | NH3: 43035 | NI3: 43036 | NJ3: 43037 | NK3: 43038 | NL3: 43039 | NM3: 43040 | NN3: 43041 | NO3: 43042 | NP3: 43043 | NQ3: 43044 | NR3: 43045 | NS3: 43046 | NT3: 43047 | NU3: 43048 | NV3: 43049 | NW3: 43050 | NX3: 43051 | NY3: 43052 | NZ3: 43053 | OA3: 43054 | OB3: 43055 | OC3: 43056 | OD3: 43057 | OE3: 43058 | OF3: 43059 | OG3: 43060 | OH3: 43061 | OI3: 43062 | OJ3: 43063 | OK3: 43064 | OL3: 43065 | OM3: 43066 | ON3: 43067 | OO3: 43068 | OP3: 43069 | OQ3: 43070 | OR3: 43071 | OS3: 43072 | OT3: 43073 | OU3: 43074 | OV3: 43075 | OW3: 43076 | OX3: 43077 | OY3: 43078 | OZ3: 43079 | PA3: 43080 | PB3: 43081 | PC3: 43082 | PD3: 43083 | PE3: 43084 | PF3: 43085 | PG3: 43086 | PH3: 43087 | PI3: 43088 | PJ3: 43089 | PK3: 43090 | PL3: 43091 | PM3: 43092 | PN3: 43093 | PO3: 43094 | PP3: 43095 | PQ3: 43096 | PR3: 43097 | PS3: 43098 | PT3: 43099 | PU3: 43100
H4: =SUM(K4:PU4) -> 0 | I4: =H4*E4 -> 0 | J4: =IF(H4<G4,"Comprar Urgente!",IF(H4<=(G4*1.2),"Atenção!","")) -> Atenção!
H5: =SUM(K5:PU5) -> 0 | I5: =H5*E5 -> 0 | J5: =IF(H5<G5,"Comprar Urgente!",IF(H5<=G5,"Atenção!","")) -> Atenção!
H6: =SUM(K6:PU6) -> 0 | I6: =H6*E6 -> 0 | J6: =IF(H6<G6,"Comprar Urgente!",IF(H6<=G6,"Atenção!","")) -> Atenção!
H7: =SUM(K7:PU7) -> 0 | I7: =H7*E7 -> 0 | J7: =IF(H7<G7,"Comprar Urgente!",IF(H7<=G7,"Atenção!","")) -> Atenção!
H8: =SUM(K8:PU8) -> 0 | I8: =H8*E8 -> 0 | J8: =IF(H8<G8,"Comprar Urgente!",IF(H8<=G8,"Atenção!","")) -> Atenção!
H9: =SUM(K9:PU9) -> 0 | I9: =H9*E9 -> 0 | J9: =IF(H9<G9,"Comprar Urgente!",IF(H9<=G9,"Atenção!","")) -> Atenção!
H10: =SUM(K10:PU10) -> 0 | I10: =H10*E10 -> 0 | J10: =IF(H10<G10,"Comprar Urgente!",IF(H10<=G10,"Atenção!","")) -> Atenção!
H11: =SUM(K11:PU11) -> 0 | I11: =H11*E11 -> 0 | J11: =IF(H11<G11,"Comprar Urgente!",IF(H11<=G11,"Atenção!","")) -> Atenção!
H12: =SUM(K12:PU12) -> 0 | I12: =H12*E12 -> 0 | J12: =IF(H12<G12,"Comprar Urgente!",IF(H12<=G12,"Atenção!","")) -> Atenção!
H13: =SUM(K13:PU13) -> 0 | I13: =H13*E13 -> 0 | J13: =IF(H13<G13,"Comprar Urgente!",IF(H13<=G13,"Atenção!","")) -> Atenção!
H14: =SUM(K14:PU14) -> 0 | I14: =H14*E14 -> 0 | J14: =IF(H14<G14,"Comprar Urgente!",IF(H14<=G14,"Atenção!","")) -> Atenção!
H15: =SUM(K15:PU15) -> 0 | I15: =H15*E15 -> 0 | J15: =IF(H15<G15,"Comprar Urgente!",IF(H15<=G15,"Atenção!","")) -> Atenção!
H16: =SUM(K16:PU16) -> 0 | I16: =H16*E16 -> 0 | J16: =IF(H16<G16,"Comprar Urgente!",IF(H16<=G16,"Atenção!","")) -> Atenção!
... H1199: =SUM(K1199:PU1199) -> 0 | I1199: =H1199*E1199 -> 0 | J1199: =IF(H1199<G1199,"Comprar Urgente!",IF(H1199<=G1199,"Atenção!","")) -> Atenção!

Sheet Controle Detalhado
A3: Código | B3: Descrição do Item | C3: Categoria | D3: Und. Medida | E3: Preço Unitário | F3: Centro de custo | G3: Saldo Minimo | H3: Entradas | I3: Saídas | J3: Saldo Atual | K3: Preço Total | L3: Situação
A4: 1 | B4: =LOOKUP(A4,Entradas!$B$4:$B$1048576,Entradas!$C$4:$C$1048576) -> #N/A | C4: =LOOKUP(A4,Entradas!$B$4:$B$1048576,Entradas!$D$4:$D$1048576) -> #N/A | D4: =LOOKUP(A4,Entradas!$B$4:$B$1048576,Entradas!$G$4:$G$1048576) -> #N/A | E4: =LOOKUP(A4,Entradas!$B$4:$B$1048576,Entradas!$H$4:$H$1048576) -> #N/A | F4: =LOOKUP(A4,Entradas!$B$4:$B$1048576,Entradas!$J$4:$J$1048576) -> #N/A | H4: =SUMIFS(Entradas!F:F,Entradas!B:B,'Controle Detalhado'!A4) -> 0 | I4: =SUMIFS(Saidas!$H:$H,Saidas!$C:$C,'Controle Detalhado'!A4) -> 0 | J4: =H4-I4 -> 0 | K4: =J4*E4 -> #N/A | L4: =IF(J4<=G4,"Comprar Urgente!",IF(J4<=(G4*1.2),"Atenção!","")) -> Comprar Urgente!
B5: =LOOKUP(A5,Entradas!$B$4:$B$1048576,Entradas!$C$4:$C$1048576) -> #N/A | C5: =LOOKUP(A5,Entradas!$B$4:$B$1048576,Entradas!$D$4:$D$1048576) -> #N/A | D5: =LOOKUP(A5,Entradas!$B$4:$B$1048576,Entradas!$G$4:$G$1048576) -> #N/A | E5: =LOOKUP(A5,Entradas!$B$4:$B$1048576,Entradas!$H$4:$H$1048576) -> #N/A | F5: =LOOKUP(A5,Entradas!$B$4:$B$1048576,Entradas!$J$4:$J$1048576) -> #N/A | H5: =SUMIFS(Entradas!F:F,Entradas!B:B,'Controle Detalhado'!A5) -> 0 | I5: =SUMIFS(Saidas!$H:$H,Saidas!$C:$C,'Controle Detalhado'!A5) -> 0 | J5: =H5-I5 -> 0 | K5: =J5*E5 -> #N/A | L5: =IF(J5<=G5,"Comprar Urgente!",IF(J5<=(G5*1.2),"Atenção!","")) -> Comprar Urgente!
B6: =LOOKUP(A6,Entradas!$B$4:$B$1048576,Entradas!$C$4:$C$1048576) -> #N/A | C6: =LOOKUP(A6,Entradas!$B$4:$B$1048576,Entradas!$D$4:$D$1048576) -> #N/A | D6: =LOOKUP(A6,Entradas!$B$4:$B$1048576,Entradas!$G$4:$G$1048576) -> #N/A | E6: =LOOKUP(A6,Entradas!$B$4:$B$1048576,Entradas!$H$4:$H$1048576) -> #N/A | F6: =LOOKUP(A6,Entradas!$B$4:$B$1048576,Entradas!$J$4:$J$1048576) -> #N/A | H6: =SUMIFS(Entradas!F:F,Entradas!B:B,'Controle Detalhado'!A6) -> 0 | I6: =SUMIFS(Saidas!$H:$H,Saidas!$C:$C,'Controle Detalhado'!A6) -> 0 | J6: =H6-I6 -> 0 | K6: =J6*E6 -> #N/A | L6: =IF(J6<=G6,"Comprar Urgente!",IF(J6<=(G6*1.2),"Atenção!","")) -> Comprar Urgente!
B7: =LOOKUP(A7,Entradas!$B$4:$B$1048576,Entradas!$C$4:$C$1048576) -> #N/A | C7: =LOOKUP(A7,Entradas!$B$4:$B$1048576,Entradas!$D$4:$D$1048576) -> #N/A | D7: =LOOKUP(A7,Entradas!$B$4:$B$1048576,Entradas!$G$4:$G$1048576) -> #N/A | E7: =LOOKUP(A7,Entradas!$B$4:$B$1048576,Entradas!$H$4:$H$1048576) -> #N/A | F7: =LOOKUP(A7,Entradas!$B$4:$B$1048576,Entradas!$J$4:$J$1048576) -> #N/A | H7: =SUMIFS(Entradas!F:F,Entradas!B:B,'Controle Detalhado'!A7) -> 0 | I7: =SUMIFS(Saidas!$H:$H,Saidas!$C:$C,'Controle Detalhado'!A7) -> 0 | J7: =H7-I7 -> 0 | K7: =J7*E7 -> #N/A | L7: =IF(J7<=G7,"Comprar Urgente!",IF(J7<=(G7*1.2),"Atenção!","")) -> Comprar Urgente!
B8: =LOOKUP(A8,Entradas!$B$4:$B$1048576,Entradas!$C$4:$C$1048576) -> #N/A | C8: =LOOKUP(A8,Entradas!$B$4:$B$1048576,Entradas!$D$4:$D$1048576) -> #N/A | D8: =LOOKUP(A8,Entradas!$B$4:$B$1048576,Entradas!$G$4:$G$1048576) -> #N/A | E8: =LOOKUP(A8,Entradas!$B$4:$B$1048576,Entradas!$H$4:$H$1048576) -> #N/A | F8: =LOOKUP(A8,Entradas!$B$4:$B$1048576,Entradas!$J$4:$J$1048576) -> #N/A | H8: =SUMIFS(Entradas!F:F,Entradas!B:B,'Controle Detalhado'!A8) -> 0 | I8: =SUMIFS(Saidas!$H:$H,Saidas!$C:$C,'Controle Detalhado'!A8) -> 0 | J8: =H8-I8 -> 0 | K8: =J8*E8 -> #N/A | L8: =IF(J8<=G8,"Comprar Urgente!",IF(J8<=(G8*1.2),"Atenção!","")) -> Comprar Urgente!
B9: =LOOKUP(A9,Entradas!$B$4:$B$1048576,Entradas!$C$4:$C$1048576) -> #N/A | C9: =LOOKUP(A9,Entradas!$B$4:$B$1048576,Entradas!$D$4:$D$1048576) -> #N/A | D9: =LOOKUP(A9,Entradas!$B$4:$B$1048576,Entradas!$G$4:$G$1048576) -> #N/A | E9: =LOOKUP(A9,Entradas!$B$4:$B$1048576,Entradas!$H$4:$H$1048576) -> #N/A | F9: =LOOKUP(A9,Entradas!$B$4:$B$1048576,Entradas!$J$4:$J$1048576) -> #N/A | H9: =SUMIFS(Entradas!F:F,Entradas!B:B,'Controle Detalhado'!A9) -> 0 | I9: =SUMIFS(Saidas!$H:$H,Saidas!$C:$C,'Controle Detalhado'!A9) -> 0 | J9: =H9-I9 -> 0 | K9: =J9*E9 -> #N/A | L9: =IF(J9<=G9,"Comprar Urgente!",IF(J9<=(G9*1.2),"Atenção!","")) -> Comprar Urgente!
B10: =LOOKUP(A10,Entradas!$B$4:$B$1048576,Entradas!$C$4:$C$1048576) -> #N/A | C10: =LOOKUP(A10,Entradas!$B$4:$B$1048576,Entradas!$D$4:$D$1048576) -> #N/A | D10: =LOOKUP(A10,Entradas!$B$4:$B$1048576,Entradas!$G$4:$G$1048576) -> #N/A | E10: =LOOKUP(A10,Entradas!$B$4:$B$1048576,Entradas!$H$4:$H$1048576) -> #N/A | F10: =LOOKUP(A10,Entradas!$B$4:$B$1048576,Entradas!$J$4:$J$1048576) -> #N/A | H10: =SUMIFS(Entradas!F:F,Entradas!B:B,'Controle Detalhado'!A10) -> 0 | I10: =SUMIFS(Saidas!$H:$H,Saidas!$C:$C,'Controle Detalhado'!A10) -> 0 | J10: =H10-I10 -> 0 | K10: =J10*E10 -> #N/A | L10: =IF(J10<=G10,"Comprar Urgente!",IF(J10<=(G10*1.2),"Atenção!","")) -> Comprar Urgente!
B11: =LOOKUP(A11,Entradas!$B$4:$B$1048576,Entradas!$C$4:$C$1048576) -> #N/A | C11: =LOOKUP(A11,Entradas!$B$4:$B$1048576,Entradas!$D$4:$D$1048576) -> #N/A | D11: =LOOKUP(A11,Entradas!$B$4:$B$1048576,Entradas!$G$4:$G$1048576) -> #N/A | E11: =LOOKUP(A11,Entradas!$B$4:$B$1048576,Entradas!$H$4:$H$1048576) -> #N/A | F11: =LOOKUP(A11,Entradas!$B$4:$B$1048576,Entradas!$J$4:$J$1048576) -> #N/A | H11: =SUMIFS(Entradas!F:F,Entradas!B:B,'Controle Detalhado'!A11) -> 0 | I11: =SUMIFS(Saidas!$H:$H,Saidas!$C:$C,'Controle Detalhado'!A11) -> 0 | J11: =H11-I11 -> 0 | K11: =J11*E11 -> #N/A | L11: =IF(J11<=G11,"Comprar Urgente!",IF(J11<=(G11*1.2),"Atenção!","")) -> Comprar Urgente!
B12: =LOOKUP(A12,Entradas!$B$4:$B$1048576,Entradas!$C$4:$C$1048576) -> #N/A | C12: =LOOKUP(A12,Entradas!$B$4:$B$1048576,Entradas!$D$4:$D$1048576) -> #N/A | D12: =LOOKUP(A12,Entradas!$B$4:$B$1048576,Entradas!$G$4:$G$1048576) -> #N/A | E12: =LOOKUP(A12,Entradas!$B$4:$B$1048576,Entradas!$H$4:$H$1048576) -> #N/A | F12: =LOOKUP(A12,Entradas!$B$4:$B$1048576,Entradas!$J$4:$J$1048576) -> #N/A | H12: =SUMIFS(Entradas!F:F,Entradas!B:B,'Controle Detalhado'!A12) -> 0 | I12: =SUMIFS(Saidas!$H:$H,Saidas!$C:$C,'Controle Detalhado'!A12) -> 0 | J12: =H12-I12 -> 0 | K12: =J12*E12 -> #N/A | L12: =IF(J12<=G12,"Comprar Urgente!",IF(J12<=(G12*1.2),"Atenção!","")) -> Comprar Urgente!
B13: =LOOKUP(A13,Entradas!$B$4:$B$1048576,Entradas!$C$4:$C$1048576) -> #N/A | C13: =LOOKUP(A13,Entradas!$B$4:$B$1048576,Entradas!$D$4:$D$1048576) -> #N/A | D13: =LOOKUP(A13,Entradas!$B$4:$B$1048576,Entradas!$G$4:$G$1048576) -> #N/A | E13: =LOOKUP(A13,Entradas!$B$4:$B$1048576,Entradas!$H$4:$H$1048576) -> #N/A | F13: =LOOKUP(A13,Entradas!$B$4:$B$1048576,Entradas!$J$4:$J$1048576) -> #N/A | H13: =SUMIFS(Entradas!F:F,Entradas!B:B,'Controle Detalhado'!A13) -> 0 | I13: =SUMIFS(Saidas!$H:$H,Saidas!$C:$C,'Controle Detalhado'!A13) -> 0 | J13: =H13-I13 -> 0 | K13: =J13*E13 -> #N/A | L13: =IF(J13<=G13,"Comprar Urgente!",IF(J13<=(G13*1.2),"Atenção!","")) -> Comprar Urgente!
B14: =LOOKUP(A14,Entradas!$B$4:$B$1048576,Entradas!$C$4:$C$1048576) -> #N/A | C14: =LOOKUP(A14,Entradas!$B$4:$B$1048576,Entradas!$D$4:$D$1048576) -> #N/A | D14: =LOOKUP(A14,Entradas!$B$4:$B$1048576,Entradas!$G$4:$G$1048576) -> #N/A | E14: =LOOKUP(A14,Entradas!$B$4:$B$1048576,Entradas!$H$4:$H$1048576) -> #N/A | F14: =LOOKUP(A14,Entradas!$B$4:$B$1048576,Entradas!$J$4:$J$1048576) -> #N/A | H14: =SUMIFS(Entradas!F:F,Entradas!B:B,'Controle Detalhado'!A14) -> 0 | I14: =SUMIFS(Saidas!$H:$H,Saidas!$C:$C,'Controle Detalhado'!A14) -> 0 | J14: =H14-I14 -> 0 | K14: =J14*E14 -> #N/A | L14: =IF(J14<=G14,"Comprar Urgente!",IF(J14<=(G14*1.2),"Atenção!","")) -> Comprar Urgente!
B15: =LOOKUP(A15,Entradas!$B$4:$B$1048576,Entradas!$C$4:$C$1048576) -> #N/A | C15: =LOOKUP(A15,Entradas!$B$4:$B$1048576,Entradas!$D$4:$D$1048576) -> #N/A | D15: =LOOKUP(A15,Entradas!$B$4:$B$1048576,Entradas!$G$4:$G$1048576) -> #N/A | E15: =LOOKUP(A15,Entradas!$B$4:$B$1048576,Entradas!$H$4:$H$1048576) -> #N/A | F15: =LOOKUP(A15,Entradas!$B$4:$B$1048576,Entradas!$J$4:$J$1048576) -> #N/A | H15: =SUMIFS(Entradas!F:F,Entradas!B:B,'Controle Detalhado'!A15) -> 0 | I15: =SUMIFS(Saidas!$H:$H,Saidas!$C:$C,'Controle Detalhado'!A15) -> 0 | J15: =H15-I15 -> 0 | K15: =J15*E15 -> #N/A | L15: =IF(J15<=G15,"Comprar Urgente!",IF(J15<=(G15*1.2),"Atenção!","")) -> Comprar Urgente!
B16: =LOOKUP(A16,Entradas!$B$4:$B$1048576,Entradas!$C$4:$C$1048576) -> #N/A | C16: =LOOKUP(A16,Entradas!$B$4:$B$1048576,Entradas!$D$4:$D$1048576) -> #N/A | D16: =LOOKUP(A16,Entradas!$B$4:$B$1048576,Entradas!$G$4:$G$1048576) -> #N/A | E16: =LOOKUP(A16,Entradas!$B$4:$B$1048576,Entradas!$H$4:$H$1048576) -> #N/A | F16: =LOOKUP(A16,Entradas!$B$4:$B$1048576,Entradas!$J$4:$J$1048576) -> #N/A | H16: =SUMIFS(Entradas!F:F,Entradas!B:B,'Controle Detalhado'!A16) -> 0 | I16: =SUMIFS(Saidas!$H:$H,Saidas!$C:$C,'Controle Detalhado'!A16) -> 0 | J16: =H16-I16 -> 0 | K16: =J16*E16 -> #N/A | L16: =IF(J16<=G16,"Comprar Urgente!",IF(J16<=(G16*1.2),"Atenção!","")) -> Comprar Urgente!
... B1197: =LOOKUP(A1197,Entradas!$B$4:$B$1048576,Entradas!$C$4:$C$1048576) -> #N/A | C1197: =LOOKUP(A1197,Entradas!$B$4:$B$1048576,Entradas!$D$4:$D$1048576) -> #N/A | D1197: =LOOKUP(A1197,Entradas!$B$4:$B$1048576,Entradas!$G$4:$G$1048576) -> #N/A | E1197: =LOOKUP(A1197,Entradas!$B$4:$B$1048576,Entradas!$H$4:$H$1048576) -> #N/A | F1197: =LOOKUP(A1197,Entradas!$B$4:$B$1048576,Entradas!$J$4:$J$1048576) -> #N/A | H1197: =SUMIFS(Entradas!F:F,Entradas!B:B,'Controle Detalhado'!A1197) -> 0 | I1197: =SUMIFS(Saidas!$H:$H,Saidas!$C:$C,'Controle Detalhado'!A1197) -> 0 | J1197: =H1197-I1197 -> 0 | K1197: =J1197*E1197 -> #N/A | L1197: =IF(J1197<=G1197,"Comprar Urgente!",IF(J1197<=(G1197*1.2),"Atenção!","")) -> Comprar Urgente!

Sheet Entradas
A3: Data | B3: Código | C3: Descrição do Item | D3: Categoria | E3: Marca | F3: Qtd | G3: Und. Medida | H3: Preço Unitário | I3: Preço Total | J3: Centro de custo | K3: Fornecedor | L3: Validade | M3: Nº Nota Fiscal | N3: Responsável Recebimento
I4: =Tabela1023[[#This Row],[Qtd]]*Tabela1023[[#This Row],[Preço Unitário]] -> 0
I5: =Tabela1023[[#This Row],[Qtd]]*Tabela1023[[#This Row],[Preço Unitário]] -> 0
I6: =Tabela1023[[#This Row],[Qtd]]*Tabela1023[[#This Row],[Preço Unitário]] -> 0
I7: =Tabela1023[[#This Row],[Qtd]]*Tabela1023[[#This Row],[Preço Unitário]] -> 0
I8: =Tabela1023[[#This Row],[Qtd]]*Tabela1023[[#This Row],[Preço Unitário]] -> 0
I9: =Tabela1023[[#This Row],[Qtd]]*Tabela1023[[#This Row],[Preço Unitário]] -> 0
I10: =Tabela1023[[#This Row],[Qtd]]*Tabela1023[[#This Row],[Preço Unitário]] -> 0
I11: =Tabela1023[[#This Row],[Qtd]]*Tabela1023[[#This Row],[Preço Unitário]] -> 0
I12: =Tabela1023[[#This Row],[Qtd]]*Tabela1023[[#This Row],[Preço Unitário]] -> 0
I13: =Tabela1023[[#This Row],[Qtd]]*Tabela1023[[#This Row],[Preço Unitário]] -> 0
I14: =Tabela1023[[#This Row],[Qtd]]*Tabela1023[[#This Row],[Preço Unitário]] -> 0
I15: =Tabela1023[[#This Row],[Qtd]]*Tabela1023[[#This Row],[Preço Unitário]] -> 0
... I23: =Tabela1023[[#This Row],[Qtd]]*Tabela1023[[#This Row],[Preço Unitário]] -> 0

Sheet Saidas
A3: Data | B3: Movimentação | C3: Código | D3: Descrição do Item | E3: Categoria | F3: Und. Medida | G3: Preço Unitário | H3: Qtd | I3: Preço Total | J3: Centro de custo origem | K3: Centro de custo destino | L3: Nº Documento de Retidada | M3: Autorizado por | N3: Retirado por
D4: =LOOKUP(Tabela10[[#This Row],[Código]],Entradas!$B$4:$B$1048576,Entradas!$C$4:$C$1048576) -> #N/A | E4: =LOOKUP(Tabela10[[#This Row],[Código]],Entradas!$B$4:$B$1048576,Entradas!$D$4:$D$1048576) -> #N/A | F4: =LOOKUP(Tabela10[[#This Row],[Código]],Entradas!$B$4:$B$1048576,Entradas!$G$4:$G$1048576) -> #N/A | G4: =LOOKUP(Tabela10[[#This Row],[Código]],Entradas!$B$4:$B$1048576,Entradas!$H$4:$H$1048576) -> #N/A | I4: =Tabela10[[#This Row],[Qtd]]*Tabela10[[#This Row],[Preço Unitário]] -> #N/A | J4: =LOOKUP(Tabela10[[#This Row],[Código]],Entradas!$B$4:$B$1048576,Entradas!$J$4:$J$1048576) -> #N/A
D5: =LOOKUP(Tabela10[[#This Row],[Código]],Entradas!$B$4:$B$1048576,Entradas!$C$4:$C$1048576) -> #N/A | E5: =LOOKUP(Tabela10[[#This Row],[Código]],Entradas!$B$4:$B$1048576,Entradas!$D$4:$D$1048576) -> #N/A | F5: =LOOKUP(Tabela10[[#This Row],[Código]],Entradas!$B$4:$B$1048576,Entradas!$G$4:$G$1048576) -> #N/A | G5: =LOOKUP(Tabela10[[#This Row],[Código]],Entradas!$B$4:$B$1048576,Entradas!$H$4:$H$1048576) -> #N/A | I5: =Tabela10[[#This Row],[Qtd]]*Tabela10[[#This Row],[Preço Unitário]] -> #N/A | J5: =LOOKUP(Tabela10[[#This Row],[Código]],Entradas!$B$4:$B$1048576,Entradas!$J$4:$J$1048576) -> #N/A
D6: =LOOKUP(Tabela10[[#This Row],[Código]],Entradas!$B$4:$B$1048576,Entradas!$C$4:$C$1048576) -> #N/A | E6: =LOOKUP(Tabela10[[#This Row],[Código]],Entradas!$B$4:$B$1048576,Entradas!$D$4:$D$1048576) -> #N/A | F6: =LOOKUP(Tabela10[[#This Row],[Código]],Entradas!$B$4:$B$1048576,Entradas!$G$4:$G$1048576) -> #N/A | G6: =LOOKUP(Tabela10[[#This Row],[Código]],Entradas!$B$4:$B$1048576,Entradas!$H$4:$H$1048576) -> #N/A | I6: =Tabela10[[#This Row],[Qtd]]*Tabela10[[#This Row],[Preço Unitário]] -> #N/A | J6: =LOOKUP(Tabela10[[#This Row],[Código]],Entradas!$B$4:$B$1048576,Entradas!$J$4:$J$1048576) -> #N/A
D7: =LOOKUP(Tabela10[[#This Row],[Código]],Entradas!$B$4:$B$1048576,Entradas!$C$4:$C$1048576) -> #N/A | E7: =LOOKUP(Tabela10[[#This Row],[Código]],Entradas!$B$4:$B$1048576,Entradas!$D$4:$D$1048576) -> #N/A | F7: =LOOKUP(Tabela10[[#This Row],[Código]],Entradas!$B$4:$B$1048576,Entradas!$G$4:$G$1048576) -> #N/A | G7: =LOOKUP(Tabela10[[#This Row],[Código]],Entradas!$B$4:$B$1048576,Entradas!$H$4:$H$1048576) -> #N/A | I7: =Tabela10[[#This Row],[Qtd]]*Tabela10[[#This Row],[Preço Unitário]] -> #N/A | J7: =LOOKUP(Tabela10[[#This Row],[Código]],Entradas!$B$4:$B$1048576,Entradas!$J$4:$J$1048576) -> #N/A
D8: =LOOKUP(Tabela10[[#This Row],[Código]],Entradas!$B$4:$B$1048576,Entradas!$C$4:$C$1048576) -> #N/A | E8: =LOOKUP(Tabela10[[#This Row],[Código]],Entradas!$B$4:$B$1048576,Entradas!$D$4:$D$1048576) -> #N/A | F8: =LOOKUP(Tabela10[[#This Row],[Código]],Entradas!$B$4:$B$1048576,Entradas!$G$4:$G$1048576) -> #N/A | G8: =LOOKUP(Tabela10[[#This Row],[Código]],Entradas!$B$4:$B$1048576,Entradas!$H$4:$H$1048576) -> #N/A | I8: =Tabela10[[#This Row],[Qtd]]*Tabela10[[#This Row],[Preço Unitário]] -> #N/A | J8: =LOOKUP(Tabela10[[#This Row],[Código]],Entradas!$B$4:$B$1048576,Entradas!$J$4:$J$1048576) -> #N/A
D9: =LOOKUP(Tabela10[[#This Row],[Código]],Entradas!$B$4:$B$1048576,Entradas!$C$4:$C$1048576) -> #N/A | E9: =LOOKUP(Tabela10[[#This Row],[Código]],Entradas!$B$4:$B$1048576,Entradas!$D$4:$D$1048576) -> #N/A | F9: =LOOKUP(Tabela10[[#This Row],[Código]],Entradas!$B$4:$B$1048576,Entradas!$G$4:$G$1048576) -> #N/A | G9: =LOOKUP(Tabela10[[#This Row],[Código]],Entradas!$B$4:$B$1048576,Entradas!$H$4:$H$1048576) -> #N/A | I9: =Tabela10[[#This Row],[Qtd]]*Tabela10[[#This Row],[Preço Unitário]] -> #N/A | J9: =LOOKUP(Tabela10[[#This Row],[Código]],Entradas!$B$4:$B$1048576,Entradas!$J$4:$J$1048576) -> #N/A
D10: =LOOKUP(Tabela10[[#This Row],[Código]],Entradas!$B$4:$B$1048576,Entradas!$C$4:$C$1048576) -> #N/A | E10: =LOOKUP(Tabela10[[#This Row],[Código]],Entradas!$B$4:$B$1048576,Entradas!$D$4:$D$1048576) -> #N/A | F10: =LOOKUP(Tabela10[[#This Row],[Código]],Entradas!$B$4:$B$1048576,Entradas!$G$4:$G$1048576) -> #N/A | G10: =LOOKUP(Tabela10[[#This Row],[Código]],Entradas!$B$4:$B$1048576,Entradas!$H$4:$H$1048576) -> #N/A | I10: =Tabela10[[#This Row],[Qtd]]*Tabela10[[#This Row],[Preço Unitário]] -> #N/A | J10: =LOOKUP(Tabela10[[#This Row],[Código]],Entradas!$B$4:$B$1048576,Entradas!$J$4:$J$1048576) -> #N/A
D11: =LOOKUP(Tabela10[[#This Row],[Código]],Entradas!$B$4:$B$1048576,Entradas!$C$4:$C$1048576) -> #N/A | E11: =LOOKUP(Tabela10[[#This Row],[Código]],Entradas!$B$4:$B$1048576,Entradas!$D$4:$D$1048576) -> #N/A | F11: =LOOKUP(Tabela10[[#This Row],[Código]],Entradas!$B$4:$B$1048576,Entradas!$G$4:$G$1048576) -> #N/A | G11: =LOOKUP(Tabela10[[#This Row],[Código]],Entradas!$B$4:$B$1048576,Entradas!$H$4:$H$1048576) -> #N/A | I11: =Tabela10[[#This Row],[Qtd]]*Tabela10[[#This Row],[Preço Unitário]] -> #N/A | J11: =LOOKUP(Tabela10[[#This Row],[Código]],Entradas!$B$4:$B$1048576,Entradas!$J$4:$J$1048576) -> #N/A
D12: =LOOKUP(Tabela10[[#This Row],[Código]],Entradas!$B$4:$B$1048576,Entradas!$C$4:$C$1048576) -> #N/A | E12: =LOOKUP(Tabela10[[#This Row],[Código]],Entradas!$B$4:$B$1048576,Entradas!$D$4:$D$1048576) -> #N/A | F12: =LOOKUP(Tabela10[[#This Row],[Código]],Entradas!$B$4:$B$1048576,Entradas!$G$4:$G$1048576) -> #N/A | G12: =LOOKUP(Tabela10[[#This Row],[Código]],Entradas!$B$4:$B$1048576,Entradas!$H$4:$H$1048576) -> #N/A | I12: =Tabela10[[#This Row],[Qtd]]*Tabela10[[#This Row],[Preço Unitário]] -> #N/A | J12: =LOOKUP(Tabela10[[#This Row],[Código]],Entradas!$B$4:$B$1048576,Entradas!$J$4:$J$1048576) -> #N/A
D13: =LOOKUP(Tabela10[[#This Row],[Código]],Entradas!$B$4:$B$1048576,Entradas!$C$4:$C$1048576) -> #N/A | E13: =LOOKUP(Tabela10[[#This Row],[Código]],Entradas!$B$4:$B$1048576,Entradas!$D$4:$D$1048576) -> #N/A | F13: =LOOKUP(Tabela10[[#This Row],[Código]],Entradas!$B$4:$B$1048576,Entradas!$G$4:$G$1048576) -> #N/A | G13: =LOOKUP(Tabela10[[#This Row],[Código]],Entradas!$B$4:$B$1048576,Entradas!$H$4:$H$1048576) -> #N/A | I13: =Tabela10[[#This Row],[Qtd]]*Tabela10[[#This Row],[Preço Unitário]] -> #N/A | J13: =LOOKUP(Tabela10[[#This Row],[Código]],Entradas!$B$4:$B$1048576,Entradas!$J$4:$J$1048576) -> #N/A
D14: =LOOKUP(Tabela10[[#This Row],[Código]],Entradas!$B$4:$B$1048576,Entradas!$C$4:$C$1048576) -> #N/A | E14: =LOOKUP(Tabela10[[#This Row],[Código]],Entradas!$B$4:$B$1048576,Entradas!$D$4:$D$1048576) -> #N/A | F14: =LOOKUP(Tabela10[[#This Row],[Código]],Entradas!$B$4:$B$1048576,Entradas!$G$4:$G$1048576) -> #N/A | G14: =LOOKUP(Tabela10[[#This Row],[Código]],Entradas!$B$4:$B$1048576,Entradas!$H$4:$H$1048576) -> #N/A | I14: =Tabela10[[#This Row],[Qtd]]*Tabela10[[#This Row],[Preço Unitário]] -> #N/A | J14: =LOOKUP(Tabela10[[#This Row],[Código]],Entradas!$B$4:$B$1048576,Entradas!$J$4:$J$1048576) -> #N/A
D15: =LOOKUP(Tabela10[[#This Row],[Código]],Entradas!$B$4:$B$1048576,Entradas!$C$4:$C$1048576) -> #N/A | E15: =LOOKUP(Tabela10[[#This Row],[Código]],Entradas!$B$4:$B$1048576,Entradas!$D$4:$D$1048576) -> #N/A | F15: =LOOKUP(Tabela10[[#This Row],[Código]],Entradas!$B$4:$B$1048576,Entradas!$G$4:$G$1048576) -> #N/A | G15: =LOOKUP(Tabela10[[#This Row],[Código]],Entradas!$B$4:$B$1048576,Entradas!$H$4:$H$1048576) -> #N/A | I15: =Tabela10[[#This Row],[Qtd]]*Tabela10[[#This Row],[Preço Unitário]] -> #N/A | J15: =LOOKUP(Tabela10[[#This Row],[Código]],Entradas!$B$4:$B$1048576,Entradas!$J$4:$J$1048576) -> #N/A
... D21: =LOOKUP(Tabela10[[#This Row],[Código]],Entradas!$B$4:$B$1048576,Entradas!$C$4:$C$1048576) -> #N/A | E21: =LOOKUP(Tabela10[[#This Row],[Código]],Entradas!$B$4:$B$1048576,Entradas!$D$4:$D$1048576) -> #N/A | F21: =LOOKUP(Tabela10[[#This Row],[Código]],Entradas!$B$4:$B$1048576,Entradas!$G$4:$G$1048576) -> #N/A | G21: =LOOKUP(Tabela10[[#This Row],[Código]],Entradas!$B$4:$B$1048576,Entradas!$H$4:$H$1048576) -> #N/A | I21: =Tabela10[[#This Row],[Qtd]]*Tabela10[[#This Row],[Preço Unitário]] -> #N/A | J21: =LOOKUP(Tabela10[[#This Row],[Código]],Entradas!$B$4:$B$1048576,Entradas!$J$4:$J$1048576) -> #N/A

Sheet Informações Padrão
B3: Und. Medida | E3: Centros de Custo | H3: Categoria | J3: Movimentação
B5: CX | C5: Caixa | E5: 1 | F5: Obra | H5: Eletrico | J5: Retirada
B6: CM | C6: Centimetro | E6: 2 | F6: Escritório | H6: Estrutural | J6: (Devolução)
B7: KG | C7: Kilograma | E7: 3 | F7: Almoxarifado central | H7: Hidraulica
B8: L | C8: Litro | H8: Louças e Metais
B9: M³ | C9: Metro cubico | H9: Pintura
B10: M² | C10: Metro quadrado
B11: PÇ | C11: Peça
A27: Faça a gestão completa de sua obra com o Sienge, saiba mais em www.sienge.com.br ou (48) 3027 8110.

Sheet  
AY1: www.guiadecompra.com
