Workbook

Sheet ANUAL
L2: INFORME O ANO DO ORÇAMENTO | P2: 2010
A4: <--- ÁREA DE IMPRESSÃO INICIA NA PRÓXIMA LINHA --->
A5: >> | B5: =P$2 -> 2010
C9: SALDO MENSAL POR CONTA
C11: CONTA | D11: DESCRIÇÃO | E11: SALDO
E12: Janeiro | F12: Fevereiro | G12: Março | H12: Abril | I12: Maio | J12: Junho | K12: Julho | L12: Agosto | M12: Setembro | N12: Outubro | O12: Novembro | P12: Dezembro
A13: 1 | D13: CONTA CORRENTE BANCO 1 | E13: =INDIRECT("M"&COLUMN()-4&"!G"&ROW()-4) -> 0 | F13: =INDIRECT("M"&COLUMN()-4&"!G"&ROW()-4) -> 0 | G13: =INDIRECT("M"&COLUMN()-4&"!G"&ROW()-4) -> 0 | H13: =INDIRECT("M"&COLUMN()-4&"!G"&ROW()-4) -> 0 | I13: =INDIRECT("M"&COLUMN()-4&"!G"&ROW()-4) -> 0 | J13: =INDIRECT("M"&COLUMN()-4&"!G"&ROW()-4) -> 0 | K13: =INDIRECT("M"&COLUMN()-4&"!G"&ROW()-4) -> 0 | L13: =INDIRECT("M"&COLUMN()-4&"!G"&ROW()-4) -> 0 | ... P13: =INDIRECT("M"&COLUMN()-4&"!G"&ROW()-4) -> 0
A14: =A13+1 -> 2 | C14: INV1 | D14: POUPANÇA BANCO 1 | E14: =INDIRECT("M"&COLUMN()-4&"!G"&ROW()-4) -> 0 | F14: =INDIRECT("M"&COLUMN()-4&"!G"&ROW()-4) -> 0 | G14: =INDIRECT("M"&COLUMN()-4&"!G"&ROW()-4) -> 0 | H14: =INDIRECT("M"&COLUMN()-4&"!G"&ROW()-4) -> 0 | I14: =INDIRECT("M"&COLUMN()-4&"!G"&ROW()-4) -> 0 | J14: =INDIRECT("M"&COLUMN()-4&"!G"&ROW()-4) -> 0 | K14: =INDIRECT("M"&COLUMN()-4&"!G"&ROW()-4) -> 0 | L14: =INDIRECT("M"&COLUMN()-4&"!G"&ROW()-4) -> 0 | ... P14: =INDIRECT("M"&COLUMN()-4&"!G"&ROW()-4) -> 0
A15: =A14+1 -> 3 | C15: DINH1 | D15: EM ESPÉCIE | E15: =INDIRECT("M"&COLUMN()-4&"!G"&ROW()-4) -> 0 | F15: =INDIRECT("M"&COLUMN()-4&"!G"&ROW()-4) -> 0 | G15: =INDIRECT("M"&COLUMN()-4&"!G"&ROW()-4) -> 0 | H15: =INDIRECT("M"&COLUMN()-4&"!G"&ROW()-4) -> 0 | I15: =INDIRECT("M"&COLUMN()-4&"!G"&ROW()-4) -> 0 | J15: =INDIRECT("M"&COLUMN()-4&"!G"&ROW()-4) -> 0 | K15: =INDIRECT("M"&COLUMN()-4&"!G"&ROW()-4) -> 0 | L15: =INDIRECT("M"&COLUMN()-4&"!G"&ROW()-4) -> 0 | ... P15: =INDIRECT("M"&COLUMN()-4&"!G"&ROW()-4) -> 0
A16: =A15+1 -> 4 | C16: CRED1 | D16: CARTÃO DE CRÉDITO 1 | E16: =INDIRECT("M"&COLUMN()-4&"!G"&ROW()-4) -> 0 | F16: =INDIRECT("M"&COLUMN()-4&"!G"&ROW()-4) -> 0 | G16: =INDIRECT("M"&COLUMN()-4&"!G"&ROW()-4) -> 0 | H16: =INDIRECT("M"&COLUMN()-4&"!G"&ROW()-4) -> 0 | I16: =INDIRECT("M"&COLUMN()-4&"!G"&ROW()-4) -> 0 | J16: =INDIRECT("M"&COLUMN()-4&"!G"&ROW()-4) -> 0 | K16: =INDIRECT("M"&COLUMN()-4&"!G"&ROW()-4) -> 0 | L16: =INDIRECT("M"&COLUMN()-4&"!G"&ROW()-4) -> 0 | ... P16: =INDIRECT("M"&COLUMN()-4&"!G"&ROW()-4) -> 0
A17: =A16+1 -> 5 | C17: --- | E17: =INDIRECT("M"&COLUMN()-4&"!G"&ROW()-4) -> 0 | F17: =INDIRECT("M"&COLUMN()-4&"!G"&ROW()-4) -> 0 | G17: =INDIRECT("M"&COLUMN()-4&"!G"&ROW()-4) -> 0 | H17: =INDIRECT("M"&COLUMN()-4&"!G"&ROW()-4) -> 0 | I17: =INDIRECT("M"&COLUMN()-4&"!G"&ROW()-4) -> 0 | J17: =INDIRECT("M"&COLUMN()-4&"!G"&ROW()-4) -> 0 | K17: =INDIRECT("M"&COLUMN()-4&"!G"&ROW()-4) -> 0 | L17: =INDIRECT("M"&COLUMN()-4&"!G"&ROW()-4) -> 0 | ... P17: =INDIRECT("M"&COLUMN()-4&"!G"&ROW()-4) -> 0
A18: =A17+1 -> 6 | C18: --- | E18: =INDIRECT("M"&COLUMN()-4&"!G"&ROW()-4) -> 0 | F18: =INDIRECT("M"&COLUMN()-4&"!G"&ROW()-4) -> 0 | G18: =INDIRECT("M"&COLUMN()-4&"!G"&ROW()-4) -> 0 | H18: =INDIRECT("M"&COLUMN()-4&"!G"&ROW()-4) -> 0 | I18: =INDIRECT("M"&COLUMN()-4&"!G"&ROW()-4) -> 0 | J18: =INDIRECT("M"&COLUMN()-4&"!G"&ROW()-4) -> 0 | K18: =INDIRECT("M"&COLUMN()-4&"!G"&ROW()-4) -> 0 | L18: =INDIRECT("M"&COLUMN()-4&"!G"&ROW()-4) -> 0 | ... P18: =INDIRECT("M"&COLUMN()-4&"!G"&ROW()-4) -> 0
A19: =A18+1 -> 7 | C19: --- | E19: =INDIRECT("M"&COLUMN()-4&"!G"&ROW()-4) -> 0 | F19: =INDIRECT("M"&COLUMN()-4&"!G"&ROW()-4) -> 0 | G19: =INDIRECT("M"&COLUMN()-4&"!G"&ROW()-4) -> 0 | H19: =INDIRECT("M"&COLUMN()-4&"!G"&ROW()-4) -> 0 | I19: =INDIRECT("M"&COLUMN()-4&"!G"&ROW()-4) -> 0 | J19: =INDIRECT("M"&COLUMN()-4&"!G"&ROW()-4) -> 0 | K19: =INDIRECT("M"&COLUMN()-4&"!G"&ROW()-4) -> 0 | L19: =INDIRECT("M"&COLUMN()-4&"!G"&ROW()-4) -> 0 | ... P19: =INDIRECT("M"&COLUMN()-4&"!G"&ROW()-4) -> 0
A20: =A19+1 -> 8 | C20: --- | E20: =INDIRECT("M"&COLUMN()-4&"!G"&ROW()-4) -> 0 | F20: =INDIRECT("M"&COLUMN()-4&"!G"&ROW()-4) -> 0 | G20: =INDIRECT("M"&COLUMN()-4&"!G"&ROW()-4) -> 0 | H20: =INDIRECT("M"&COLUMN()-4&"!G"&ROW()-4) -> 0 | I20: =INDIRECT("M"&COLUMN()-4&"!G"&ROW()-4) -> 0 | J20: =INDIRECT("M"&COLUMN()-4&"!G"&ROW()-4) -> 0 | K20: =INDIRECT("M"&COLUMN()-4&"!G"&ROW()-4) -> 0 | L20: =INDIRECT("M"&COLUMN()-4&"!G"&ROW()-4) -> 0 | ... P20: =INDIRECT("M"&COLUMN()-4&"!G"&ROW()-4) -> 0
A21: =A20+1 -> 9 | C21: --- | E21: =INDIRECT("M"&COLUMN()-4&"!G"&ROW()-4) -> 0 | F21: =INDIRECT("M"&COLUMN()-4&"!G"&ROW()-4) -> 0 | G21: =INDIRECT("M"&COLUMN()-4&"!G"&ROW()-4) -> 0 | H21: =INDIRECT("M"&COLUMN()-4&"!G"&ROW()-4) -> 0 | I21: =INDIRECT("M"&COLUMN()-4&"!G"&ROW()-4) -> 0 | J21: =INDIRECT("M"&COLUMN()-4&"!G"&ROW()-4) -> 0 | K21: =INDIRECT("M"&COLUMN()-4&"!G"&ROW()-4) -> 0 | L21: =INDIRECT("M"&COLUMN()-4&"!G"&ROW()-4) -> 0 | ... P21: =INDIRECT("M"&COLUMN()-4&"!G"&ROW()-4) -> 0
A22: =A21+1 -> 10 | C22: --- | E22: =INDIRECT("M"&COLUMN()-4&"!G"&ROW()-4) -> 0 | F22: =INDIRECT("M"&COLUMN()-4&"!G"&ROW()-4) -> 0 | G22: =INDIRECT("M"&COLUMN()-4&"!G"&ROW()-4) -> 0 | H22: =INDIRECT("M"&COLUMN()-4&"!G"&ROW()-4) -> 0 | I22: =INDIRECT("M"&COLUMN()-4&"!G"&ROW()-4) -> 0 | J22: =INDIRECT("M"&COLUMN()-4&"!G"&ROW()-4) -> 0 | K22: =INDIRECT("M"&COLUMN()-4&"!G"&ROW()-4) -> 0 | L22: =INDIRECT("M"&COLUMN()-4&"!G"&ROW()-4) -> 0 | ... P22: =INDIRECT("M"&COLUMN()-4&"!G"&ROW()-4) -> 0
A23: =A22+1 -> 11 | C23: --- | E23: =INDIRECT("M"&COLUMN()-4&"!G"&ROW()-4) -> 0 | F23: =INDIRECT("M"&COLUMN()-4&"!G"&ROW()-4) -> 0 | G23: =INDIRECT("M"&COLUMN()-4&"!G"&ROW()-4) -> 0 | H23: =INDIRECT("M"&COLUMN()-4&"!G"&ROW()-4) -> 0 | I23: =INDIRECT("M"&COLUMN()-4&"!G"&ROW()-4) -> 0 | J23: =INDIRECT("M"&COLUMN()-4&"!G"&ROW()-4) -> 0 | K23: =INDIRECT("M"&COLUMN()-4&"!G"&ROW()-4) -> 0 | L23: =INDIRECT("M"&COLUMN()-4&"!G"&ROW()-4) -> 0 | ... P23: =INDIRECT("M"&COLUMN()-4&"!G"&ROW()-4) -> 0
A24: =A23+1 -> 12 | C24: --- | E24: =INDIRECT("M"&COLUMN()-4&"!G"&ROW()-4) -> 0 | F24: =INDIRECT("M"&COLUMN()-4&"!G"&ROW()-4) -> 0 | G24: =INDIRECT("M"&COLUMN()-4&"!G"&ROW()-4) -> 0 | H24: =INDIRECT("M"&COLUMN()-4&"!G"&ROW()-4) -> 0 | I24: =INDIRECT("M"&COLUMN()-4&"!G"&ROW()-4) -> 0 | J24: =INDIRECT("M"&COLUMN()-4&"!G"&ROW()-4) -> 0 | K24: =INDIRECT("M"&COLUMN()-4&"!G"&ROW()-4) -> 0 | L24: =INDIRECT("M"&COLUMN()-4&"!G"&ROW()-4) -> 0 | ... P24: =INDIRECT("M"&COLUMN()-4&"!G"&ROW()-4) -> 0
B26: =IF($D$13<>"",$D$13&" ("&$C$13&")",$C$13) -> CONTA CORRENTE BANCO 1 () | F26: =IF($D$14<>"",$D$14&" ("&$C$14&")",$C$14) -> POUPANÇA BANCO 1 (INV1) | L26: =IF($D$15<>"",$D$15&" ("&$C$15&")",$C$15) -> EM ESPÉCIE (DINH1)
B46: =IF($D$16<>"",$D$16&" ("&$C$16&")",$C$16) -> CARTÃO DE CRÉDITO 1 (CRED1) | F46: =IF($D$17<>"",$D$17&" ("&$C$17&")",$C$17) -> --- | L46: =IF($D$18<>"",$D$18&" ("&$C$18&")",$C$18) -> ---
B67: =IF($D$19<>"",$D$19&" ("&$C$19&")",$C$19) -> --- | F67: =IF($D$20<>"",$D$20&" ("&$C$20&")",$C$20) -> --- | L67: =IF($D$21<>"",$D$21&" ("&$C$21&")",$C$21) -> ---
B88: =IF($D$22<>"",$D$22&" ("&$C$22&")",$C$22) -> --- | F88: =IF($D$23<>"",$D$23&" ("&$C$23&")",$C$23) -> --- | L88: =IF($D$24<>"",$D$24&" ("&$C$24&")",$C$24) -> ---
C111: HISTÓRICO DE SALDOS POR GRUPO
C113: GRUPO | D113: DESCRIÇÃO | E113: SALDO
E114: Janeiro | F114: Fevereiro | G114: Março | H114: Abril | I114: Maio | J114: Junho | K114: Julho | L114: Agosto | M114: Setembro | N114: Outubro | O114: Novembro | P114: Dezembro
A115: 1 | C115: CC | D115: CONTA CORRENTE | E115: =INDIRECT("M"&COLUMN()-4&"!G"&47+$A115-1) -> 0 | F115: =INDIRECT("M"&COLUMN()-4&"!G"&47+$A115-1) -> 0 | G115: =INDIRECT("M"&COLUMN()-4&"!G"&47+$A115-1) -> 0 | H115: =INDIRECT("M"&COLUMN()-4&"!G"&47+$A115-1) -> 0 | I115: =INDIRECT("M"&COLUMN()-4&"!G"&47+$A115-1) -> 0 | J115: =INDIRECT("M"&COLUMN()-4&"!G"&47+$A115-1) -> 0 | K115: =INDIRECT("M"&COLUMN()-4&"!G"&47+$A115-1) -> 0 | L115: =INDIRECT("M"&COLUMN()-4&"!G"&47+$A115-1) -> 0 | ... P115: =INDIRECT("M"&COLUMN()-4&"!G"&47+$A115-1) -> 0
A116: =A115+1 -> 2 | C116: INV | D116: APLICAÇÕES DE INVESTIMENTO | E116: =INDIRECT("M"&COLUMN()-4&"!G"&47+$A116-1) -> 0 | F116: =INDIRECT("M"&COLUMN()-4&"!G"&47+$A116-1) -> 0 | G116: =INDIRECT("M"&COLUMN()-4&"!G"&47+$A116-1) -> 0 | H116: =INDIRECT("M"&COLUMN()-4&"!G"&47+$A116-1) -> 0 | I116: =INDIRECT("M"&COLUMN()-4&"!G"&47+$A116-1) -> 0 | J116: =INDIRECT("M"&COLUMN()-4&"!G"&47+$A116-1) -> 0 | K116: =INDIRECT("M"&COLUMN()-4&"!G"&47+$A116-1) -> 0 | L116: =INDIRECT("M"&COLUMN()-4&"!G"&47+$A116-1) -> 0 | ... P116: =INDIRECT("M"&COLUMN()-4&"!G"&47+$A116-1) -> 0
A117: =A116+1 -> 3 | C117: DINH | D117: EM ESPÉCIE | E117: =INDIRECT("M"&COLUMN()-4&"!G"&47+$A117-1) -> 0 | F117: =INDIRECT("M"&COLUMN()-4&"!G"&47+$A117-1) -> 0 | G117: =INDIRECT("M"&COLUMN()-4&"!G"&47+$A117-1) -> 0 | H117: =INDIRECT("M"&COLUMN()-4&"!G"&47+$A117-1) -> 0 | I117: =INDIRECT("M"&COLUMN()-4&"!G"&47+$A117-1) -> 0 | J117: =INDIRECT("M"&COLUMN()-4&"!G"&47+$A117-1) -> 0 | K117: =INDIRECT("M"&COLUMN()-4&"!G"&47+$A117-1) -> 0 | L117: =INDIRECT("M"&COLUMN()-4&"!G"&47+$A117-1) -> 0 | ... P117: =INDIRECT("M"&COLUMN()-4&"!G"&47+$A117-1) -> 0
B119: =IF($D$115<>"",$D$115&" ("&$C$115&")",$C$115) -> CONTA CORRENTE (CC) | F119: =IF($D$116<>"",$D$116&" ("&$C$116&")",$C$116) -> APLICAÇÕES DE INVESTIMENTO (INV) | L119: =IF($D$117<>"",$D$117&" ("&$C$117&")",$C$117) -> EM ESPÉCIE (DINH)
A133: >> | B133: =P$2 -> 2010
C137: ACOMPANHAMENTO DE DESPESAS
C139: CÓDIGO | D139: DESCRIÇÃO | E139: 1º TRIMESTRE | H139: 2º TRIMESTRE | K139: 3º TRIMESTRE | N139: 4º TRIMESTRE
E140: Janeiro | F140: Fevereiro | G140: Março | H140: Abril | I140: Maio | J140: Junho | K140: Julho | L140: Agosto | M140: Setembro | N140: Outubro | O140: Novembro | P140: Dezembro
A141: 1 | C141: M01 | D141: MORADIA – CONDOMÍNIO | E141: =INDIRECT("M"&COLUMN()-4&"!G"&ROW('M1'!$G57)) -> 0 | F141: =INDIRECT("M"&COLUMN()-4&"!G"&ROW('M1'!$G57)) -> 0 | G141: =INDIRECT("M"&COLUMN()-4&"!G"&ROW('M1'!$G57)) -> 0 | H141: =INDIRECT("M"&COLUMN()-4&"!G"&ROW('M1'!$G57)) -> 0 | I141: =INDIRECT("M"&COLUMN()-4&"!G"&ROW('M1'!$G57)) -> 0 | J141: =INDIRECT("M"&COLUMN()-4&"!G"&ROW('M1'!$G57)) -> 0 | K141: =INDIRECT("M"&COLUMN()-4&"!G"&ROW('M1'!$G57)) -> 0 | L141: =INDIRECT("M"&COLUMN()-4&"!G"&ROW('M1'!$G57)) -> 0 | ... P141: =INDIRECT("M"&COLUMN()-4&"!G"&ROW('M1'!$G57)) -> 0 | R141: =SUM(E141:P141) -> 0
A142: 2 | C142: M02 | D142: MORADIA – IPTU | E142: =INDIRECT("M"&COLUMN()-4&"!G"&ROW('M1'!$G58)) -> 0 | F142: =INDIRECT("M"&COLUMN()-4&"!G"&ROW('M1'!$G58)) -> 0 | G142: =INDIRECT("M"&COLUMN()-4&"!G"&ROW('M1'!$G58)) -> 0 | H142: =INDIRECT("M"&COLUMN()-4&"!G"&ROW('M1'!$G58)) -> 0 | I142: =INDIRECT("M"&COLUMN()-4&"!G"&ROW('M1'!$G58)) -> 0 | J142: =INDIRECT("M"&COLUMN()-4&"!G"&ROW('M1'!$G58)) -> 0 | K142: =INDIRECT("M"&COLUMN()-4&"!G"&ROW('M1'!$G58)) -> 0 | L142: =INDIRECT("M"&COLUMN()-4&"!G"&ROW('M1'!$G58)) -> 0 | ... P142: =INDIRECT("M"&COLUMN()-4&"!G"&ROW('M1'!$G58)) -> 0 | R142: =SUM(E142:P142) -> 0
A143: 3 | C143: M03 | D143: MORADIA – ALUGUEL | E143: =INDIRECT("M"&COLUMN()-4&"!G"&ROW('M1'!$G59)) -> 0 | F143: =INDIRECT("M"&COLUMN()-4&"!G"&ROW('M1'!$G59)) -> 0 | G143: =INDIRECT("M"&COLUMN()-4&"!G"&ROW('M1'!$G59)) -> 0 | H143: =INDIRECT("M"&COLUMN()-4&"!G"&ROW('M1'!$G59)) -> 0 | I143: =INDIRECT("M"&COLUMN()-4&"!G"&ROW('M1'!$G59)) -> 0 | J143: =INDIRECT("M"&COLUMN()-4&"!G"&ROW('M1'!$G59)) -> 0 | K143: =INDIRECT("M"&COLUMN()-4&"!G"&ROW('M1'!$G59)) -> 0 | L143: =INDIRECT("M"&COLUMN()-4&"!G"&ROW('M1'!$G59)) -> 0 | ... P143: =INDIRECT("M"&COLUMN()-4&"!G"&ROW('M1'!$G59)) -> 0 | R143: =SUM(E143:P143) -> 0
A144: 4 | C144: M04 | D144: MORADIA – REFORMA | E144: =INDIRECT("M"&COLUMN()-4&"!G"&ROW('M1'!$G60)) -> 0 | F144: =INDIRECT("M"&COLUMN()-4&"!G"&ROW('M1'!$G60)) -> 0 | G144: =INDIRECT("M"&COLUMN()-4&"!G"&ROW('M1'!$G60)) -> 0 | H144: =INDIRECT("M"&COLUMN()-4&"!G"&ROW('M1'!$G60)) -> 0 | I144: =INDIRECT("M"&COLUMN()-4&"!G"&ROW('M1'!$G60)) -> 0 | J144: =INDIRECT("M"&COLUMN()-4&"!G"&ROW('M1'!$G60)) -> 0 | K144: =INDIRECT("M"&COLUMN()-4&"!G"&ROW('M1'!$G60)) -> 0 | L144: =INDIRECT("M"&COLUMN()-4&"!G"&ROW('M1'!$G60)) -> 0 | ... P144: =INDIRECT("M"&COLUMN()-4&"!G"&ROW('M1'!$G60)) -> 0 | R144: =SUM(E144:P144) -> 0
A145: 5 | C145: U01 | D145: UTILITIES – ENERGIA ELÉTRICA | E145: =INDIRECT("M"&COLUMN()-4&"!G"&ROW('M1'!$G61)) -> 0 | F145: =INDIRECT("M"&COLUMN()-4&"!G"&ROW('M1'!$G61)) -> 0 | G145: =INDIRECT("M"&COLUMN()-4&"!G"&ROW('M1'!$G61)) -> 0 | H145: =INDIRECT("M"&COLUMN()-4&"!G"&ROW('M1'!$G61)) -> 0 | I145: =INDIRECT("M"&COLUMN()-4&"!G"&ROW('M1'!$G61)) -> 0 | J145: =INDIRECT("M"&COLUMN()-4&"!G"&ROW('M1'!$G61)) -> 0 | K145: =INDIRECT("M"&COLUMN()-4&"!G"&ROW('M1'!$G61)) -> 0 | L145: =INDIRECT("M"&COLUMN()-4&"!G"&ROW('M1'!$G61)) -> 0 | ... P145: =INDIRECT("M"&COLUMN()-4&"!G"&ROW('M1'!$G61)) -> 0 | R145: =SUM(E145:P145) -> 0
A146: 6 | C146: U02 | D146: UTILITIES – ÁGUA POTÁVEL | E146: =INDIRECT("M"&COLUMN()-4&"!G"&ROW('M1'!$G62)) -> 0 | F146: =INDIRECT("M"&COLUMN()-4&"!G"&ROW('M1'!$G62)) -> 0 | G146: =INDIRECT("M"&COLUMN()-4&"!G"&ROW('M1'!$G62)) -> 0 | H146: =INDIRECT("M"&COLUMN()-4&"!G"&ROW('M1'!$G62)) -> 0 | I146: =INDIRECT("M"&COLUMN()-4&"!G"&ROW('M1'!$G62)) -> 0 | J146: =INDIRECT("M"&COLUMN()-4&"!G"&ROW('M1'!$G62)) -> 0 | K146: =INDIRECT("M"&COLUMN()-4&"!G"&ROW('M1'!$G62)) -> 0 | L146: =INDIRECT("M"&COLUMN()-4&"!G"&ROW('M1'!$G62)) -> 0 | ... P146: =INDIRECT("M"&COLUMN()-4&"!G"&ROW('M1'!$G62)) -> 0 | R146: =SUM(E146:P146) -> 0
A147: 7 | C147: U03 | D147: UTILITIES – DIVERSOS (ÁGUA, GÁS, SERV. GERAIS) | E147: =INDIRECT("M"&COLUMN()-4&"!G"&ROW('M1'!$G63)) -> 0 | F147: =INDIRECT("M"&COLUMN()-4&"!G"&ROW('M1'!$G63)) -> 0 | G147: =INDIRECT("M"&COLUMN()-4&"!G"&ROW('M1'!$G63)) -> 0 | H147: =INDIRECT("M"&COLUMN()-4&"!G"&ROW('M1'!$G63)) -> 0 | I147: =INDIRECT("M"&COLUMN()-4&"!G"&ROW('M1'!$G63)) -> 0 | J147: =INDIRECT("M"&COLUMN()-4&"!G"&ROW('M1'!$G63)) -> 0 | K147: =INDIRECT("M"&COLUMN()-4&"!G"&ROW('M1'!$G63)) -> 0 | L147: =INDIRECT("M"&COLUMN()-4&"!G"&ROW('M1'!$G63)) -> 0 | ... P147: =INDIRECT("M"&COLUMN()-4&"!G"&ROW('M1'!$G63)) -> 0 | R147: =SUM(E147:P147) -> 0
A148: 8 | C148: S01 | D148: SAÚDE – PLANO DE SAÚDE | E148: =INDIRECT("M"&COLUMN()-4&"!G"&ROW('M1'!$G64)) -> 0 | F148: =INDIRECT("M"&COLUMN()-4&"!G"&ROW('M1'!$G64)) -> 0 | G148: =INDIRECT("M"&COLUMN()-4&"!G"&ROW('M1'!$G64)) -> 0 | H148: =INDIRECT("M"&COLUMN()-4&"!G"&ROW('M1'!$G64)) -> 0 | I148: =INDIRECT("M"&COLUMN()-4&"!G"&ROW('M1'!$G64)) -> 0 | J148: =INDIRECT("M"&COLUMN()-4&"!G"&ROW('M1'!$G64)) -> 0 | K148: =INDIRECT("M"&COLUMN()-4&"!G"&ROW('M1'!$G64)) -> 0 | L148: =INDIRECT("M"&COLUMN()-4&"!G"&ROW('M1'!$G64)) -> 0 | ... P148: =INDIRECT("M"&COLUMN()-4&"!G"&ROW('M1'!$G64)) -> 0 | R148: =SUM(E148:P148) -> 0
A149: 9 | C149: S02 | D149: SAÚDE – REMÉDIOS | E149: =INDIRECT("M"&COLUMN()-4&"!G"&ROW('M1'!$G65)) -> 0 | F149: =INDIRECT("M"&COLUMN()-4&"!G"&ROW('M1'!$G65)) -> 0 | G149: =INDIRECT("M"&COLUMN()-4&"!G"&ROW('M1'!$G65)) -> 0 | H149: =INDIRECT("M"&COLUMN()-4&"!G"&ROW('M1'!$G65)) -> 0 | I149: =INDIRECT("M"&COLUMN()-4&"!G"&ROW('M1'!$G65)) -> 0 | J149: =INDIRECT("M"&COLUMN()-4&"!G"&ROW('M1'!$G65)) -> 0 | K149: =INDIRECT("M"&COLUMN()-4&"!G"&ROW('M1'!$G65)) -> 0 | L149: =INDIRECT("M"&COLUMN()-4&"!G"&ROW('M1'!$G65)) -> 0 | ... P149: =INDIRECT("M"&COLUMN()-4&"!G"&ROW('M1'!$G65)) -> 0 | R149: =SUM(E149:P149) -> 0
A150: 10 | C150: S03 | D150: SAÚDE – ACADEMIA | E150: =INDIRECT("M"&COLUMN()-4&"!G"&ROW('M1'!$G66)) -> 0 | F150: =INDIRECT("M"&COLUMN()-4&"!G"&ROW('M1'!$G66)) -> 0 | G150: =INDIRECT("M"&COLUMN()-4&"!G"&ROW('M1'!$G66)) -> 0 | H150: =INDIRECT("M"&COLUMN()-4&"!G"&ROW('M1'!$G66)) -> 0 | I150: =INDIRECT("M"&COLUMN()-4&"!G"&ROW('M1'!$G66)) -> 0 | J150: =INDIRECT("M"&COLUMN()-4&"!G"&ROW('M1'!$G66)) -> 0 | K150: =INDIRECT("M"&COLUMN()-4&"!G"&ROW('M1'!$G66)) -> 0 | L150: =INDIRECT("M"&COLUMN()-4&"!G"&ROW('M1'!$G66)) -> 0 | ... P150: =INDIRECT("M"&COLUMN()-4&"!G"&ROW('M1'!$G66)) -> 0 | R150: =SUM(E150:P150) -> 0
A151: 11 | C151: C01 | D151: COMPRAS | E151: =INDIRECT("M"&COLUMN()-4&"!G"&ROW('M1'!$G67)) -> 0 | F151: =INDIRECT("M"&COLUMN()-4&"!G"&ROW('M1'!$G67)) -> 0 | G151: =INDIRECT("M"&COLUMN()-4&"!G"&ROW('M1'!$G67)) -> 0 | H151: =INDIRECT("M"&COLUMN()-4&"!G"&ROW('M1'!$G67)) -> 0 | I151: =INDIRECT("M"&COLUMN()-4&"!G"&ROW('M1'!$G67)) -> 0 | J151: =INDIRECT("M"&COLUMN()-4&"!G"&ROW('M1'!$G67)) -> 0 | K151: =INDIRECT("M"&COLUMN()-4&"!G"&ROW('M1'!$G67)) -> 0 | L151: =INDIRECT("M"&COLUMN()-4&"!G"&ROW('M1'!$G67)) -> 0 | ... P151: =INDIRECT("M"&COLUMN()-4&"!G"&ROW('M1'!$G67)) -> 0 | R151: =SUM(E151:P151) -> 0
A152: 12 | C152: L01 | D152: LAZER | E152: =INDIRECT("M"&COLUMN()-4&"!G"&ROW('M1'!$G68)) -> 0 | F152: =INDIRECT("M"&COLUMN()-4&"!G"&ROW('M1'!$G68)) -> 0 | G152: =INDIRECT("M"&COLUMN()-4&"!G"&ROW('M1'!$G68)) -> 0 | H152: =INDIRECT("M"&COLUMN()-4&"!G"&ROW('M1'!$G68)) -> 0 | I152: =INDIRECT("M"&COLUMN()-4&"!G"&ROW('M1'!$G68)) -> 0 | J152: =INDIRECT("M"&COLUMN()-4&"!G"&ROW('M1'!$G68)) -> 0 | K152: =INDIRECT("M"&COLUMN()-4&"!G"&ROW('M1'!$G68)) -> 0 | L152: =INDIRECT("M"&COLUMN()-4&"!G"&ROW('M1'!$G68)) -> 0 | ... P152: =INDIRECT("M"&COLUMN()-4&"!G"&ROW('M1'!$G68)) -> 0 | R152: =SUM(E152:P152) -> 0
... A172: 32 | C172: --- | D172: --- | E172: =INDIRECT("M"&COLUMN()-4&"!G"&ROW('M1'!$G88)) -> 0 | F172: =INDIRECT("M"&COLUMN()-4&"!G"&ROW('M1'!$G88)) -> 0 | G172: =INDIRECT("M"&COLUMN()-4&"!G"&ROW('M1'!$G88)) -> 0 | H172: =INDIRECT("M"&COLUMN()-4&"!G"&ROW('M1'!$G88)) -> 0 | I172: =INDIRECT("M"&COLUMN()-4&"!G"&ROW('M1'!$G88)) -> 0 | J172: =INDIRECT("M"&COLUMN()-4&"!G"&ROW('M1'!$G88)) -> 0 | K172: =INDIRECT("M"&COLUMN()-4&"!G"&ROW('M1'!$G88)) -> 0 | L172: =INDIRECT("M"&COLUMN()-4&"!G"&ROW('M1'!$G88)) -> 0 | ... P172: =INDIRECT("M"&COLUMN()-4&"!G"&ROW('M1'!$G88)) -> 0 | R172: =SUM(E172:P172) -> 0
A259: >> | B259: =P$2 -> 2010
C263: HISTÓRICO DE MOVIMENTAÇÕES (ENTRADAS)
C265: CONTA | D265: DESCRIÇÃO | E265: ENTRADA
E266: Janeiro | F266: Fevereiro | G266: Março | H266: Abril | I266: Maio | J266: Junho | K266: Julho | L266: Agosto | M266: Setembro | N266: Outubro | O266: Novembro | P266: Dezembro
A267: 1 | C267: =C13 -> 0 | D267: =D13 -> CONTA CORRENTE BANCO 1 | E267: =INDIRECT("M"&COLUMN()-4&"!E"&28+$A267-1) -> 0 | F267: =INDIRECT("M"&COLUMN()-4&"!E"&28+$A267-1) -> 0 | G267: =INDIRECT("M"&COLUMN()-4&"!E"&28+$A267-1) -> 0 | H267: =INDIRECT("M"&COLUMN()-4&"!E"&28+$A267-1) -> 0 | I267: =INDIRECT("M"&COLUMN()-4&"!E"&28+$A267-1) -> 0 | J267: =INDIRECT("M"&COLUMN()-4&"!E"&28+$A267-1) -> 0 | K267: =INDIRECT("M"&COLUMN()-4&"!E"&28+$A267-1) -> 0 | L267: =INDIRECT("M"&COLUMN()-4&"!E"&28+$A267-1) -> 0 | ... P267: =INDIRECT("M"&COLUMN()-4&"!E"&28+$A267-1) -> 0
A268: 2 | C268: =C14 -> INV1 | D268: =D14 -> POUPANÇA BANCO 1 | E268: =INDIRECT("M"&COLUMN()-4&"!E"&28+$A268-1) -> 0 | F268: =INDIRECT("M"&COLUMN()-4&"!E"&28+$A268-1) -> 0 | G268: =INDIRECT("M"&COLUMN()-4&"!E"&28+$A268-1) -> 0 | H268: =INDIRECT("M"&COLUMN()-4&"!E"&28+$A268-1) -> 0 | I268: =INDIRECT("M"&COLUMN()-4&"!E"&28+$A268-1) -> 0 | J268: =INDIRECT("M"&COLUMN()-4&"!E"&28+$A268-1) -> 0 | K268: =INDIRECT("M"&COLUMN()-4&"!E"&28+$A268-1) -> 0 | L268: =INDIRECT("M"&COLUMN()-4&"!E"&28+$A268-1) -> 0 | ... P268: =INDIRECT("M"&COLUMN()-4&"!E"&28+$A268-1) -> 0
A269: 3 | C269: =C15 -> DINH1 | D269: =D15 -> EM ESPÉCIE | E269: =INDIRECT("M"&COLUMN()-4&"!E"&28+$A269-1) -> 0 | F269: =INDIRECT("M"&COLUMN()-4&"!E"&28+$A269-1) -> 0 | G269: =INDIRECT("M"&COLUMN()-4&"!E"&28+$A269-1) -> 0 | H269: =INDIRECT("M"&COLUMN()-4&"!E"&28+$A269-1) -> 0 | I269: =INDIRECT("M"&COLUMN()-4&"!E"&28+$A269-1) -> 0 | J269: =INDIRECT("M"&COLUMN()-4&"!E"&28+$A269-1) -> 0 | K269: =INDIRECT("M"&COLUMN()-4&"!E"&28+$A269-1) -> 0 | L269: =INDIRECT("M"&COLUMN()-4&"!E"&28+$A269-1) -> 0 | ... P269: =INDIRECT("M"&COLUMN()-4&"!E"&28+$A269-1) -> 0
A270: 4 | C270: =C16 -> CRED1 | D270: =D16 -> CARTÃO DE CRÉDITO 1 | E270: =INDIRECT("M"&COLUMN()-4&"!E"&28+$A270-1) -> 0 | F270: =INDIRECT("M"&COLUMN()-4&"!E"&28+$A270-1) -> 0 | G270: =INDIRECT("M"&COLUMN()-4&"!E"&28+$A270-1) -> 0 | H270: =INDIRECT("M"&COLUMN()-4&"!E"&28+$A270-1) -> 0 | I270: =INDIRECT("M"&COLUMN()-4&"!E"&28+$A270-1) -> 0 | J270: =INDIRECT("M"&COLUMN()-4&"!E"&28+$A270-1) -> 0 | K270: =INDIRECT("M"&COLUMN()-4&"!E"&28+$A270-1) -> 0 | L270: =INDIRECT("M"&COLUMN()-4&"!E"&28+$A270-1) -> 0 | ... P270: =INDIRECT("M"&COLUMN()-4&"!E"&28+$A270-1) -> 0
A271: 5 | C271: =C17 -> --- | D271: =D17 -> 0 | E271: =INDIRECT("M"&COLUMN()-4&"!E"&28+$A271-1) -> 0 | F271: =INDIRECT("M"&COLUMN()-4&"!E"&28+$A271-1) -> 0 | G271: =INDIRECT("M"&COLUMN()-4&"!E"&28+$A271-1) -> 0 | H271: =INDIRECT("M"&COLUMN()-4&"!E"&28+$A271-1) -> 0 | I271: =INDIRECT("M"&COLUMN()-4&"!E"&28+$A271-1) -> 0 | J271: =INDIRECT("M"&COLUMN()-4&"!E"&28+$A271-1) -> 0 | K271: =INDIRECT("M"&COLUMN()-4&"!E"&28+$A271-1) -> 0 | L271: =INDIRECT("M"&COLUMN()-4&"!E"&28+$A271-1) -> 0 | ... P271: =INDIRECT("M"&COLUMN()-4&"!E"&28+$A271-1) -> 0
A272: 6 | C272: =C18 -> --- | D272: =D18 -> 0 | E272: =INDIRECT("M"&COLUMN()-4&"!E"&28+$A272-1) -> 0 | F272: =INDIRECT("M"&COLUMN()-4&"!E"&28+$A272-1) -> 0 | G272: =INDIRECT("M"&COLUMN()-4&"!E"&28+$A272-1) -> 0 | H272: =INDIRECT("M"&COLUMN()-4&"!E"&28+$A272-1) -> 0 | I272: =INDIRECT("M"&COLUMN()-4&"!E"&28+$A272-1) -> 0 | J272: =INDIRECT("M"&COLUMN()-4&"!E"&28+$A272-1) -> 0 | K272: =INDIRECT("M"&COLUMN()-4&"!E"&28+$A272-1) -> 0 | L272: =INDIRECT("M"&COLUMN()-4&"!E"&28+$A272-1) -> 0 | ... P272: =INDIRECT("M"&COLUMN()-4&"!E"&28+$A272-1) -> 0
A273: 7 | C273: =C19 -> --- | D273: =D19 -> 0 | E273: =INDIRECT("M"&COLUMN()-4&"!E"&28+$A273-1) -> 0 | F273: =INDIRECT("M"&COLUMN()-4&"!E"&28+$A273-1) -> 0 | G273: =INDIRECT("M"&COLUMN()-4&"!E"&28+$A273-1) -> 0 | H273: =INDIRECT("M"&COLUMN()-4&"!E"&28+$A273-1) -> 0 | I273: =INDIRECT("M"&COLUMN()-4&"!E"&28+$A273-1) -> 0 | J273: =INDIRECT("M"&COLUMN()-4&"!E"&28+$A273-1) -> 0 | K273: =INDIRECT("M"&COLUMN()-4&"!E"&28+$A273-1) -> 0 | L273: =INDIRECT("M"&COLUMN()-4&"!E"&28+$A273-1) -> 0 | ... P273: =INDIRECT("M"&COLUMN()-4&"!E"&28+$A273-1) -> 0
A274: 8 | C274: =C20 -> --- | D274: =D20 -> 0 | E274: =INDIRECT("M"&COLUMN()-4&"!E"&28+$A274-1) -> 0 | F274: =INDIRECT("M"&COLUMN()-4&"!E"&28+$A274-1) -> 0 | G274: =INDIRECT("M"&COLUMN()-4&"!E"&28+$A274-1) -> 0 | H274: =INDIRECT("M"&COLUMN()-4&"!E"&28+$A274-1) -> 0 | I274: =INDIRECT("M"&COLUMN()-4&"!E"&28+$A274-1) -> 0 | J274: =INDIRECT("M"&COLUMN()-4&"!E"&28+$A274-1) -> 0 | K274: =INDIRECT("M"&COLUMN()-4&"!E"&28+$A274-1) -> 0 | L274: =INDIRECT("M"&COLUMN()-4&"!E"&28+$A274-1) -> 0 | ... P274: =INDIRECT("M"&COLUMN()-4&"!E"&28+$A274-1) -> 0
A275: 9 | C275: =C21 -> --- | D275: =D21 -> 0 | E275: =INDIRECT("M"&COLUMN()-4&"!E"&28+$A275-1) -> 0 | F275: =INDIRECT("M"&COLUMN()-4&"!E"&28+$A275-1) -> 0 | G275: =INDIRECT("M"&COLUMN()-4&"!E"&28+$A275-1) -> 0 | H275: =INDIRECT("M"&COLUMN()-4&"!E"&28+$A275-1) -> 0 | I275: =INDIRECT("M"&COLUMN()-4&"!E"&28+$A275-1) -> 0 | J275: =INDIRECT("M"&COLUMN()-4&"!E"&28+$A275-1) -> 0 | K275: =INDIRECT("M"&COLUMN()-4&"!E"&28+$A275-1) -> 0 | L275: =INDIRECT("M"&COLUMN()-4&"!E"&28+$A275-1) -> 0 | ... P275: =INDIRECT("M"&COLUMN()-4&"!E"&28+$A275-1) -> 0
A276: 10 | C276: =C22 -> --- | D276: =D22 -> 0 | E276: =INDIRECT("M"&COLUMN()-4&"!E"&28+$A276-1) -> 0 | F276: =INDIRECT("M"&COLUMN()-4&"!E"&28+$A276-1) -> 0 | G276: =INDIRECT("M"&COLUMN()-4&"!E"&28+$A276-1) -> 0 | H276: =INDIRECT("M"&COLUMN()-4&"!E"&28+$A276-1) -> 0 | I276: =INDIRECT("M"&COLUMN()-4&"!E"&28+$A276-1) -> 0 | J276: =INDIRECT("M"&COLUMN()-4&"!E"&28+$A276-1) -> 0 | K276: =INDIRECT("M"&COLUMN()-4&"!E"&28+$A276-1) -> 0 | L276: =INDIRECT("M"&COLUMN()-4&"!E"&28+$A276-1) -> 0 | ... P276: =INDIRECT("M"&COLUMN()-4&"!E"&28+$A276-1) -> 0
A277: 11 | C277: =C23 -> --- | D277: =D23 -> 0 | E277: =INDIRECT("M"&COLUMN()-4&"!E"&28+$A277-1) -> 0 | F277: =INDIRECT("M"&COLUMN()-4&"!E"&28+$A277-1) -> 0 | G277: =INDIRECT("M"&COLUMN()-4&"!E"&28+$A277-1) -> 0 | H277: =INDIRECT("M"&COLUMN()-4&"!E"&28+$A277-1) -> 0 | I277: =INDIRECT("M"&COLUMN()-4&"!E"&28+$A277-1) -> 0 | J277: =INDIRECT("M"&COLUMN()-4&"!E"&28+$A277-1) -> 0 | K277: =INDIRECT("M"&COLUMN()-4&"!E"&28+$A277-1) -> 0 | L277: =INDIRECT("M"&COLUMN()-4&"!E"&28+$A277-1) -> 0 | ... P277: =INDIRECT("M"&COLUMN()-4&"!E"&28+$A277-1) -> 0
A278: 12 | C278: =C24 -> --- | D278: =D24 -> 0 | E278: =INDIRECT("M"&COLUMN()-4&"!E"&28+$A278-1) -> 0 | F278: =INDIRECT("M"&COLUMN()-4&"!E"&28+$A278-1) -> 0 | G278: =INDIRECT("M"&COLUMN()-4&"!E"&28+$A278-1) -> 0 | H278: =INDIRECT("M"&COLUMN()-4&"!E"&28+$A278-1) -> 0 | I278: =INDIRECT("M"&COLUMN()-4&"!E"&28+$A278-1) -> 0 | J278: =INDIRECT("M"&COLUMN()-4&"!E"&28+$A278-1) -> 0 | K278: =INDIRECT("M"&COLUMN()-4&"!E"&28+$A278-1) -> 0 | L278: =INDIRECT("M"&COLUMN()-4&"!E"&28+$A278-1) -> 0 | ... P278: =INDIRECT("M"&COLUMN()-4&"!E"&28+$A278-1) -> 0
C304: HISTÓRICO DE MOVIMENTAÇÕES (SAÍDAS)
C306: CONTA | D306: DESCRIÇÃO | E306: SAÍDA
E307: Janeiro | F307: Fevereiro | G307: Março | H307: Abril | I307: Maio | J307: Junho | K307: Julho | L307: Agosto | M307: Setembro | N307: Outubro | O307: Novembro | P307: Dezembro
A308: 1 | C308: =C267 -> 0 | D308: =D267 -> CONTA CORRENTE BANCO 1 | E308: =-INDIRECT("M"&COLUMN()-4&"!F"&28+$A308-1) -> 0 | F308: =-INDIRECT("M"&COLUMN()-4&"!F"&28+$A308-1) -> 0 | G308: =-INDIRECT("M"&COLUMN()-4&"!F"&28+$A308-1) -> 0 | H308: =-INDIRECT("M"&COLUMN()-4&"!F"&28+$A308-1) -> 0 | I308: =-INDIRECT("M"&COLUMN()-4&"!F"&28+$A308-1) -> 0 | J308: =-INDIRECT("M"&COLUMN()-4&"!F"&28+$A308-1) -> 0 | K308: =-INDIRECT("M"&COLUMN()-4&"!F"&28+$A308-1) -> 0 | L308: =-INDIRECT("M"&COLUMN()-4&"!F"&28+$A308-1) -> 0 | ... P308: =-INDIRECT("M"&COLUMN()-4&"!F"&28+$A308-1) -> 0
A309: 2 | C309: =C268 -> INV1 | D309: =D268 -> POUPANÇA BANCO 1 | E309: =-INDIRECT("M"&COLUMN()-4&"!F"&28+$A309-1) -> 0 | F309: =-INDIRECT("M"&COLUMN()-4&"!F"&28+$A309-1) -> 0 | G309: =-INDIRECT("M"&COLUMN()-4&"!F"&28+$A309-1) -> 0 | H309: =-INDIRECT("M"&COLUMN()-4&"!F"&28+$A309-1) -> 0 | I309: =-INDIRECT("M"&COLUMN()-4&"!F"&28+$A309-1) -> 0 | J309: =-INDIRECT("M"&COLUMN()-4&"!F"&28+$A309-1) -> 0 | K309: =-INDIRECT("M"&COLUMN()-4&"!F"&28+$A309-1) -> 0 | L309: =-INDIRECT("M"&COLUMN()-4&"!F"&28+$A309-1) -> 0 | ... P309: =-INDIRECT("M"&COLUMN()-4&"!F"&28+$A309-1) -> 0
A310: 3 | C310: =C269 -> DINH1 | D310: =D269 -> EM ESPÉCIE | E310: =-INDIRECT("M"&COLUMN()-4&"!F"&28+$A310-1) -> 0 | F310: =-INDIRECT("M"&COLUMN()-4&"!F"&28+$A310-1) -> 0 | G310: =-INDIRECT("M"&COLUMN()-4&"!F"&28+$A310-1) -> 0 | H310: =-INDIRECT("M"&COLUMN()-4&"!F"&28+$A310-1) -> 0 | I310: =-INDIRECT("M"&COLUMN()-4&"!F"&28+$A310-1) -> 0 | J310: =-INDIRECT("M"&COLUMN()-4&"!F"&28+$A310-1) -> 0 | K310: =-INDIRECT("M"&COLUMN()-4&"!F"&28+$A310-1) -> 0 | L310: =-INDIRECT("M"&COLUMN()-4&"!F"&28+$A310-1) -> 0 | ... P310: =-INDIRECT("M"&COLUMN()-4&"!F"&28+$A310-1) -> 0
A311: 4 | C311: =C270 -> CRED1 | D311: =D270 -> CARTÃO DE CRÉDITO 1 | E311: =-INDIRECT("M"&COLUMN()-4&"!F"&28+$A311-1) -> 0 | F311: =-INDIRECT("M"&COLUMN()-4&"!F"&28+$A311-1) -> 0 | G311: =-INDIRECT("M"&COLUMN()-4&"!F"&28+$A311-1) -> 0 | H311: =-INDIRECT("M"&COLUMN()-4&"!F"&28+$A311-1) -> 0 | I311: =-INDIRECT("M"&COLUMN()-4&"!F"&28+$A311-1) -> 0 | J311: =-INDIRECT("M"&COLUMN()-4&"!F"&28+$A311-1) -> 0 | K311: =-INDIRECT("M"&COLUMN()-4&"!F"&28+$A311-1) -> 0 | L311: =-INDIRECT("M"&COLUMN()-4&"!F"&28+$A311-1) -> 0 | ... P311: =-INDIRECT("M"&COLUMN()-4&"!F"&28+$A311-1) -> 0
A312: 5 | C312: =C271 -> --- | D312: =D271 -> 0 | E312: =-INDIRECT("M"&COLUMN()-4&"!F"&28+$A312-1) -> 0 | F312: =-INDIRECT("M"&COLUMN()-4&"!F"&28+$A312-1) -> 0 | G312: =-INDIRECT("M"&COLUMN()-4&"!F"&28+$A312-1) -> 0 | H312: =-INDIRECT("M"&COLUMN()-4&"!F"&28+$A312-1) -> 0 | I312: =-INDIRECT("M"&COLUMN()-4&"!F"&28+$A312-1) -> 0 | J312: =-INDIRECT("M"&COLUMN()-4&"!F"&28+$A312-1) -> 0 | K312: =-INDIRECT("M"&COLUMN()-4&"!F"&28+$A312-1) -> 0 | L312: =-INDIRECT("M"&COLUMN()-4&"!F"&28+$A312-1) -> 0 | ... P312: =-INDIRECT("M"&COLUMN()-4&"!F"&28+$A312-1) -> 0
A313: 6 | C313: =C272 -> --- | D313: =D272 -> 0 | E313: =-INDIRECT("M"&COLUMN()-4&"!F"&28+$A313-1) -> 0 | F313: =-INDIRECT("M"&COLUMN()-4&"!F"&28+$A313-1) -> 0 | G313: =-INDIRECT("M"&COLUMN()-4&"!F"&28+$A313-1) -> 0 | H313: =-INDIRECT("M"&COLUMN()-4&"!F"&28+$A313-1) -> 0 | I313: =-INDIRECT("M"&COLUMN()-4&"!F"&28+$A313-1) -> 0 | J313: =-INDIRECT("M"&COLUMN()-4&"!F"&28+$A313-1) -> 0 | K313: =-INDIRECT("M"&COLUMN()-4&"!F"&28+$A313-1) -> 0 | L313: =-INDIRECT("M"&COLUMN()-4&"!F"&28+$A313-1) -> 0 | ... P313: =-INDIRECT("M"&COLUMN()-4&"!F"&28+$A313-1) -> 0
A314: 7 | C314: =C273 -> --- | D314: =D273 -> 0 | E314: =-INDIRECT("M"&COLUMN()-4&"!F"&28+$A314-1) -> 0 | F314: =-INDIRECT("M"&COLUMN()-4&"!F"&28+$A314-1) -> 0 | G314: =-INDIRECT("M"&COLUMN()-4&"!F"&28+$A314-1) -> 0 | H314: =-INDIRECT("M"&COLUMN()-4&"!F"&28+$A314-1) -> 0 | I314: =-INDIRECT("M"&COLUMN()-4&"!F"&28+$A314-1) -> 0 | J314: =-INDIRECT("M"&COLUMN()-4&"!F"&28+$A314-1) -> 0 | K314: =-INDIRECT("M"&COLUMN()-4&"!F"&28+$A314-1) -> 0 | L314: =-INDIRECT("M"&COLUMN()-4&"!F"&28+$A314-1) -> 0 | ... P314: =-INDIRECT("M"&COLUMN()-4&"!F"&28+$A314-1) -> 0
A315: 8 | C315: =C274 -> --- | D315: =D274 -> 0 | E315: =-INDIRECT("M"&COLUMN()-4&"!F"&28+$A315-1) -> 0 | F315: =-INDIRECT("M"&COLUMN()-4&"!F"&28+$A315-1) -> 0 | G315: =-INDIRECT("M"&COLUMN()-4&"!F"&28+$A315-1) -> 0 | H315: =-INDIRECT("M"&COLUMN()-4&"!F"&28+$A315-1) -> 0 | I315: =-INDIRECT("M"&COLUMN()-4&"!F"&28+$A315-1) -> 0 | J315: =-INDIRECT("M"&COLUMN()-4&"!F"&28+$A315-1) -> 0 | K315: =-INDIRECT("M"&COLUMN()-4&"!F"&28+$A315-1) -> 0 | L315: =-INDIRECT("M"&COLUMN()-4&"!F"&28+$A315-1) -> 0 | ... P315: =-INDIRECT("M"&COLUMN()-4&"!F"&28+$A315-1) -> 0
A316: 9 | C316: =C275 -> --- | D316: =D275 -> 0 | E316: =-INDIRECT("M"&COLUMN()-4&"!F"&28+$A316-1) -> 0 | F316: =-INDIRECT("M"&COLUMN()-4&"!F"&28+$A316-1) -> 0 | G316: =-INDIRECT("M"&COLUMN()-4&"!F"&28+$A316-1) -> 0 | H316: =-INDIRECT("M"&COLUMN()-4&"!F"&28+$A316-1) -> 0 | I316: =-INDIRECT("M"&COLUMN()-4&"!F"&28+$A316-1) -> 0 | J316: =-INDIRECT("M"&COLUMN()-4&"!F"&28+$A316-1) -> 0 | K316: =-INDIRECT("M"&COLUMN()-4&"!F"&28+$A316-1) -> 0 | L316: =-INDIRECT("M"&COLUMN()-4&"!F"&28+$A316-1) -> 0 | ... P316: =-INDIRECT("M"&COLUMN()-4&"!F"&28+$A316-1) -> 0
A317: 10 | C317: =C276 -> --- | D317: =D276 -> 0 | E317: =-INDIRECT("M"&COLUMN()-4&"!F"&28+$A317-1) -> 0 | F317: =-INDIRECT("M"&COLUMN()-4&"!F"&28+$A317-1) -> 0 | G317: =-INDIRECT("M"&COLUMN()-4&"!F"&28+$A317-1) -> 0 | H317: =-INDIRECT("M"&COLUMN()-4&"!F"&28+$A317-1) -> 0 | I317: =-INDIRECT("M"&COLUMN()-4&"!F"&28+$A317-1) -> 0 | J317: =-INDIRECT("M"&COLUMN()-4&"!F"&28+$A317-1) -> 0 | K317: =-INDIRECT("M"&COLUMN()-4&"!F"&28+$A317-1) -> 0 | L317: =-INDIRECT("M"&COLUMN()-4&"!F"&28+$A317-1) -> 0 | ... P317: =-INDIRECT("M"&COLUMN()-4&"!F"&28+$A317-1) -> 0
A318: 11 | C318: =C277 -> --- | D318: =D277 -> 0 | E318: =-INDIRECT("M"&COLUMN()-4&"!F"&28+$A318-1) -> 0 | F318: =-INDIRECT("M"&COLUMN()-4&"!F"&28+$A318-1) -> 0 | G318: =-INDIRECT("M"&COLUMN()-4&"!F"&28+$A318-1) -> 0 | H318: =-INDIRECT("M"&COLUMN()-4&"!F"&28+$A318-1) -> 0 | I318: =-INDIRECT("M"&COLUMN()-4&"!F"&28+$A318-1) -> 0 | J318: =-INDIRECT("M"&COLUMN()-4&"!F"&28+$A318-1) -> 0 | K318: =-INDIRECT("M"&COLUMN()-4&"!F"&28+$A318-1) -> 0 | L318: =-INDIRECT("M"&COLUMN()-4&"!F"&28+$A318-1) -> 0 | ... P318: =-INDIRECT("M"&COLUMN()-4&"!F"&28+$A318-1) -> 0
A319: 12 | C319: =C278 -> --- | D319: =D278 -> 0 | E319: =-INDIRECT("M"&COLUMN()-4&"!F"&28+$A319-1) -> 0 | F319: =-INDIRECT("M"&COLUMN()-4&"!F"&28+$A319-1) -> 0 | G319: =-INDIRECT("M"&COLUMN()-4&"!F"&28+$A319-1) -> 0 | H319: =-INDIRECT("M"&COLUMN()-4&"!F"&28+$A319-1) -> 0 | I319: =-INDIRECT("M"&COLUMN()-4&"!F"&28+$A319-1) -> 0 | J319: =-INDIRECT("M"&COLUMN()-4&"!F"&28+$A319-1) -> 0 | K319: =-INDIRECT("M"&COLUMN()-4&"!F"&28+$A319-1) -> 0 | L319: =-INDIRECT("M"&COLUMN()-4&"!F"&28+$A319-1) -> 0 | ... P319: =-INDIRECT("M"&COLUMN()-4&"!F"&28+$A319-1) -> 0
C345: HISTÓRICO DE MOVIMENTAÇÕES (VARIAÇÕES)
C347: CONTA | D347: DESCRIÇÃO | E347: SAÍDA
E348: Janeiro | F348: Fevereiro | G348: Março | H348: Abril | I348: Maio | J348: Junho | K348: Julho | L348: Agosto | M348: Setembro | N348: Outubro | O348: Novembro | P348: Dezembro
A349: 1 | C349: =C308 -> 0 | D349: =D308 -> CONTA CORRENTE BANCO 1 | E349: =INDIRECT("M"&COLUMN()-4&"!G"&28+$A349-1) -> 0 | F349: =INDIRECT("M"&COLUMN()-4&"!G"&28+$A349-1) -> 0 | G349: =INDIRECT("M"&COLUMN()-4&"!G"&28+$A349-1) -> 0 | H349: =INDIRECT("M"&COLUMN()-4&"!G"&28+$A349-1) -> 0 | I349: =INDIRECT("M"&COLUMN()-4&"!G"&28+$A349-1) -> 0 | J349: =INDIRECT("M"&COLUMN()-4&"!G"&28+$A349-1) -> 0 | K349: =INDIRECT("M"&COLUMN()-4&"!G"&28+$A349-1) -> 0 | L349: =INDIRECT("M"&COLUMN()-4&"!G"&28+$A349-1) -> 0 | ... P349: =INDIRECT("M"&COLUMN()-4&"!G"&28+$A349-1) -> 0
A350: 2 | C350: =C309 -> INV1 | D350: =D309 -> POUPANÇA BANCO 1 | E350: =INDIRECT("M"&COLUMN()-4&"!G"&28+$A350-1) -> 0 | F350: =INDIRECT("M"&COLUMN()-4&"!G"&28+$A350-1) -> 0 | G350: =INDIRECT("M"&COLUMN()-4&"!G"&28+$A350-1) -> 0 | H350: =INDIRECT("M"&COLUMN()-4&"!G"&28+$A350-1) -> 0 | I350: =INDIRECT("M"&COLUMN()-4&"!G"&28+$A350-1) -> 0 | J350: =INDIRECT("M"&COLUMN()-4&"!G"&28+$A350-1) -> 0 | K350: =INDIRECT("M"&COLUMN()-4&"!G"&28+$A350-1) -> 0 | L350: =INDIRECT("M"&COLUMN()-4&"!G"&28+$A350-1) -> 0 | ... P350: =INDIRECT("M"&COLUMN()-4&"!G"&28+$A350-1) -> 0
A351: 3 | C351: =C310 -> DINH1 | D351: =D310 -> EM ESPÉCIE | E351: =INDIRECT("M"&COLUMN()-4&"!G"&28+$A351-1) -> 0 | F351: =INDIRECT("M"&COLUMN()-4&"!G"&28+$A351-1) -> 0 | G351: =INDIRECT("M"&COLUMN()-4&"!G"&28+$A351-1) -> 0 | H351: =INDIRECT("M"&COLUMN()-4&"!G"&28+$A351-1) -> 0 | I351: =INDIRECT("M"&COLUMN()-4&"!G"&28+$A351-1) -> 0 | J351: =INDIRECT("M"&COLUMN()-4&"!G"&28+$A351-1) -> 0 | K351: =INDIRECT("M"&COLUMN()-4&"!G"&28+$A351-1) -> 0 | L351: =INDIRECT("M"&COLUMN()-4&"!G"&28+$A351-1) -> 0 | ... P351: =INDIRECT("M"&COLUMN()-4&"!G"&28+$A351-1) -> 0
A352: 4 | C352: =C311 -> CRED1 | D352: =D311 -> CARTÃO DE CRÉDITO 1 | E352: =INDIRECT("M"&COLUMN()-4&"!G"&28+$A352-1) -> 0 | F352: =INDIRECT("M"&COLUMN()-4&"!G"&28+$A352-1) -> 0 | G352: =INDIRECT("M"&COLUMN()-4&"!G"&28+$A352-1) -> 0 | H352: =INDIRECT("M"&COLUMN()-4&"!G"&28+$A352-1) -> 0 | I352: =INDIRECT("M"&COLUMN()-4&"!G"&28+$A352-1) -> 0 | J352: =INDIRECT("M"&COLUMN()-4&"!G"&28+$A352-1) -> 0 | K352: =INDIRECT("M"&COLUMN()-4&"!G"&28+$A352-1) -> 0 | L352: =INDIRECT("M"&COLUMN()-4&"!G"&28+$A352-1) -> 0 | ... P352: =INDIRECT("M"&COLUMN()-4&"!G"&28+$A352-1) -> 0
A353: 5 | C353: =C312 -> --- | D353: =D312 -> 0 | E353: =INDIRECT("M"&COLUMN()-4&"!G"&28+$A353-1) -> 0 | F353: =INDIRECT("M"&COLUMN()-4&"!G"&28+$A353-1) -> 0 | G353: =INDIRECT("M"&COLUMN()-4&"!G"&28+$A353-1) -> 0 | H353: =INDIRECT("M"&COLUMN()-4&"!G"&28+$A353-1) -> 0 | I353: =INDIRECT("M"&COLUMN()-4&"!G"&28+$A353-1) -> 0 | J353: =INDIRECT("M"&COLUMN()-4&"!G"&28+$A353-1) -> 0 | K353: =INDIRECT("M"&COLUMN()-4&"!G"&28+$A353-1) -> 0 | L353: =INDIRECT("M"&COLUMN()-4&"!G"&28+$A353-1) -> 0 | ... P353: =INDIRECT("M"&COLUMN()-4&"!G"&28+$A353-1) -> 0
A354: 6 | C354: =C313 -> --- | D354: =D313 -> 0 | E354: =INDIRECT("M"&COLUMN()-4&"!G"&28+$A354-1) -> 0 | F354: =INDIRECT("M"&COLUMN()-4&"!G"&28+$A354-1) -> 0 | G354: =INDIRECT("M"&COLUMN()-4&"!G"&28+$A354-1) -> 0 | H354: =INDIRECT("M"&COLUMN()-4&"!G"&28+$A354-1) -> 0 | I354: =INDIRECT("M"&COLUMN()-4&"!G"&28+$A354-1) -> 0 | J354: =INDIRECT("M"&COLUMN()-4&"!G"&28+$A354-1) -> 0 | K354: =INDIRECT("M"&COLUMN()-4&"!G"&28+$A354-1) -> 0 | L354: =INDIRECT("M"&COLUMN()-4&"!G"&28+$A354-1) -> 0 | ... P354: =INDIRECT("M"&COLUMN()-4&"!G"&28+$A354-1) -> 0
A355: 7 | C355: =C314 -> --- | D355: =D314 -> 0 | E355: =INDIRECT("M"&COLUMN()-4&"!G"&28+$A355-1) -> 0 | F355: =INDIRECT("M"&COLUMN()-4&"!G"&28+$A355-1) -> 0 | G355: =INDIRECT("M"&COLUMN()-4&"!G"&28+$A355-1) -> 0 | H355: =INDIRECT("M"&COLUMN()-4&"!G"&28+$A355-1) -> 0 | I355: =INDIRECT("M"&COLUMN()-4&"!G"&28+$A355-1) -> 0 | J355: =INDIRECT("M"&COLUMN()-4&"!G"&28+$A355-1) -> 0 | K355: =INDIRECT("M"&COLUMN()-4&"!G"&28+$A355-1) -> 0 | L355: =INDIRECT("M"&COLUMN()-4&"!G"&28+$A355-1) -> 0 | ... P355: =INDIRECT("M"&COLUMN()-4&"!G"&28+$A355-1) -> 0
A356: 8 | C356: =C315 -> --- | D356: =D315 -> 0 | E356: =INDIRECT("M"&COLUMN()-4&"!G"&28+$A356-1) -> 0 | F356: =INDIRECT("M"&COLUMN()-4&"!G"&28+$A356-1) -> 0 | G356: =INDIRECT("M"&COLUMN()-4&"!G"&28+$A356-1) -> 0 | H356: =INDIRECT("M"&COLUMN()-4&"!G"&28+$A356-1) -> 0 | I356: =INDIRECT("M"&COLUMN()-4&"!G"&28+$A356-1) -> 0 | J356: =INDIRECT("M"&COLUMN()-4&"!G"&28+$A356-1) -> 0 | K356: =INDIRECT("M"&COLUMN()-4&"!G"&28+$A356-1) -> 0 | L356: =INDIRECT("M"&COLUMN()-4&"!G"&28+$A356-1) -> 0 | ... P356: =INDIRECT("M"&COLUMN()-4&"!G"&28+$A356-1) -> 0
A357: 9 | C357: =C316 -> --- | D357: =D316 -> 0 | E357: =INDIRECT("M"&COLUMN()-4&"!G"&28+$A357-1) -> 0 | F357: =INDIRECT("M"&COLUMN()-4&"!G"&28+$A357-1) -> 0 | G357: =INDIRECT("M"&COLUMN()-4&"!G"&28+$A357-1) -> 0 | H357: =INDIRECT("M"&COLUMN()-4&"!G"&28+$A357-1) -> 0 | I357: =INDIRECT("M"&COLUMN()-4&"!G"&28+$A357-1) -> 0 | J357: =INDIRECT("M"&COLUMN()-4&"!G"&28+$A357-1) -> 0 | K357: =INDIRECT("M"&COLUMN()-4&"!G"&28+$A357-1) -> 0 | L357: =INDIRECT("M"&COLUMN()-4&"!G"&28+$A357-1) -> 0 | ... P357: =INDIRECT("M"&COLUMN()-4&"!G"&28+$A357-1) -> 0
A358: 10 | C358: =C317 -> --- | D358: =D317 -> 0 | E358: =INDIRECT("M"&COLUMN()-4&"!G"&28+$A358-1) -> 0 | F358: =INDIRECT("M"&COLUMN()-4&"!G"&28+$A358-1) -> 0 | G358: =INDIRECT("M"&COLUMN()-4&"!G"&28+$A358-1) -> 0 | H358: =INDIRECT("M"&COLUMN()-4&"!G"&28+$A358-1) -> 0 | I358: =INDIRECT("M"&COLUMN()-4&"!G"&28+$A358-1) -> 0 | J358: =INDIRECT("M"&COLUMN()-4&"!G"&28+$A358-1) -> 0 | K358: =INDIRECT("M"&COLUMN()-4&"!G"&28+$A358-1) -> 0 | L358: =INDIRECT("M"&COLUMN()-4&"!G"&28+$A358-1) -> 0 | ... P358: =INDIRECT("M"&COLUMN()-4&"!G"&28+$A358-1) -> 0
A359: 11 | C359: =C318 -> --- | D359: =D318 -> 0 | E359: =INDIRECT("M"&COLUMN()-4&"!G"&28+$A359-1) -> 0 | F359: =INDIRECT("M"&COLUMN()-4&"!G"&28+$A359-1) -> 0 | G359: =INDIRECT("M"&COLUMN()-4&"!G"&28+$A359-1) -> 0 | H359: =INDIRECT("M"&COLUMN()-4&"!G"&28+$A359-1) -> 0 | I359: =INDIRECT("M"&COLUMN()-4&"!G"&28+$A359-1) -> 0 | J359: =INDIRECT("M"&COLUMN()-4&"!G"&28+$A359-1) -> 0 | K359: =INDIRECT("M"&COLUMN()-4&"!G"&28+$A359-1) -> 0 | L359: =INDIRECT("M"&COLUMN()-4&"!G"&28+$A359-1) -> 0 | ... P359: =INDIRECT("M"&COLUMN()-4&"!G"&28+$A359-1) -> 0
A360: 12 | C360: =C319 -> --- | D360: =D319 -> 0 | E360: =INDIRECT("M"&COLUMN()-4&"!G"&28+$A360-1) -> 0 | F360: =INDIRECT("M"&COLUMN()-4&"!G"&28+$A360-1) -> 0 | G360: =INDIRECT("M"&COLUMN()-4&"!G"&28+$A360-1) -> 0 | H360: =INDIRECT("M"&COLUMN()-4&"!G"&28+$A360-1) -> 0 | I360: =INDIRECT("M"&COLUMN()-4&"!G"&28+$A360-1) -> 0 | J360: =INDIRECT("M"&COLUMN()-4&"!G"&28+$A360-1) -> 0 | K360: =INDIRECT("M"&COLUMN()-4&"!G"&28+$A360-1) -> 0 | L360: =INDIRECT("M"&COLUMN()-4&"!G"&28+$A360-1) -> 0 | ... P360: =INDIRECT("M"&COLUMN()-4&"!G"&28+$A360-1) -> 0
A387: >> | B387: =P$2 -> 2010
C391: SALDO MENSAL DAS CONTAS
C393: CONTA | D393: DESCRIÇÃO | E393: SALDO
E394: Janeiro | F394: Fevereiro | G394: Março | H394: Abril | I394: Maio | J394: Junho | K394: Julho | L394: Agosto | M394: Setembro | N394: Outubro | O394: Novembro | P394: Dezembro
A395: 1 | C395: =C13 -> 0 | D395: =D13 -> CONTA CORRENTE BANCO 1 | E395: =E13 -> 0 | F395: =F13 -> 0 | G395: =G13 -> 0 | H395: =H13 -> 0 | I395: =I13 -> 0 | J395: =J13 -> 0 | ... P395: =P13 -> 0
A396: 2 | C396: =C14 -> INV1 | D396: =D14 -> POUPANÇA BANCO 1 | E396: =E14 -> 0 | F396: =F14 -> 0 | G396: =G14 -> 0 | H396: =H14 -> 0 | I396: =I14 -> 0 | J396: =J14 -> 0 | ... P396: =P14 -> 0
A397: 3 | C397: =C15 -> DINH1 | D397: =D15 -> EM ESPÉCIE | E397: =E15 -> 0 | F397: =F15 -> 0 | G397: =G15 -> 0 | H397: =H15 -> 0 | I397: =I15 -> 0 | J397: =J15 -> 0 | ... P397: =P15 -> 0
A398: 4 | C398: =C16 -> CRED1 | D398: =D16 -> CARTÃO DE CRÉDITO 1 | E398: =E16 -> 0 | F398: =F16 -> 0 | G398: =G16 -> 0 | H398: =H16 -> 0 | I398: =I16 -> 0 | J398: =J16 -> 0 | ... P398: =P16 -> 0
...

Sheet M1
B1: =DATE(ANUAL!B5,B2,8) -> 40186 | I1: >> | M1: << | W1: >> | AL1: <<
B2: 1
C5: LISTA DE CONTAS | P5: MOVIMENTAÇÕES DO MÊS
C7: CONTA | D7: DESCRIÇÃO | E7: SALDO | P7: DATA | Q7: DESCRIÇÃO | R7: TRANFERÊNCIAS | T7: VALOR | U7: CODIGO
E8: ANTERIOR | F8: ATUAL | G8: PREVISTO | P8: DATA | Q8: DESCRIÇÃO | R8: SAÍDA | S8: ENTRADA | T8: VALOR | U8: TIPO | X8: ATUAL | Z8: =$C$9 | AA8: =$C$10 -> INV1 | AB8: =$C$11 -> DINH1 | AC8: =$C$12 -> CRED1 | AD8: =$C$13 -> --- | AE8: =$C$14 -> --- | AF8: =$C$15 -> --- | AG8: =$C$16 -> --- | AH8: =$C$17 -> --- | AI8: =$C$18 -> --- | AJ8: =$C$19 -> --- | AK8: =$C$20 -> ---
A9: 1 | C9: =TRIM(ANUAL!C13) | D9: =TRIM(ANUAL!D13) -> CONTA CORRENTE BANCO 1 | E9: 0 | F9: =E9+SUMIF(X$9:X$88,1,OFFSET($Z$9:$Z$88,0,A9-1)) -> 0 | G9: =E9+SUM(OFFSET($Z$9:$Z$88,0,A9-1)) -> 0 | J9: =NOT(ISERR(SEARCH(J$27,$C9))) -> FALSE | K9: =NOT(ISERR(SEARCH(K$27,$C9))) -> FALSE | L9: =NOT(ISERR(SEARCH(L$27,$C9))) -> FALSE | N9: 1 | X9: =IF(P9<NOW(),1,0) -> 1 | Z9: =IF(Z$8=$R9,-$T9,0)+IF(Z$8=$S9,$T9,0) -> 0 | AA9: =IF(AA$8=$R9,-$T9,0)+IF(AA$8=$S9,$T9,0) -> 0 | AB9: =IF(AB$8=$R9,-$T9,0)+IF(AB$8=$S9,$T9,0) -> 0 | AC9: =IF(AC$8=$R9,-$T9,0)+IF(AC$8=$S9,$T9,0) -> 0 | AD9: =IF(AD$8=$R9,-$T9,0)+IF(AD$8=$S9,$T9,0) -> 0 | AE9: =IF(AE$8=$R9,-$T9,0)+IF(AE$8=$S9,$T9,0) -> 0 | AF9: =IF(AF$8=$R9,-$T9,0)+IF(AF$8=$S9,$T9,0) -> 0 | AG9: =IF(AG$8=$R9,-$T9,0)+IF(AG$8=$S9,$T9,0) -> 0 | ... AK9: =IF(AK$8=$R9,-$T9,0)+IF(AK$8=$S9,$T9,0) -> 0
A10: 2 | C10: =TRIM(ANUAL!C14) -> INV1 | D10: =TRIM(ANUAL!D14) -> POUPANÇA BANCO 1 | E10: 0 | F10: =E10+SUMIF(X$9:X$88,1,OFFSET($Z$9:$Z$88,0,A10-1)) -> 0 | G10: =E10+SUM(OFFSET($Z$9:$Z$88,0,A10-1)) -> 0 | J10: =NOT(ISERR(SEARCH(J$27,$C10))) -> FALSE | K10: =NOT(ISERR(SEARCH(K$27,$C10))) -> TRUE | L10: =NOT(ISERR(SEARCH(L$27,$C10))) -> FALSE | N10: 2 | X10: =IF(P10<NOW(),1,0) -> 1 | Z10: =IF(Z$8=$R10,-$T10,0)+IF(Z$8=$S10,$T10,0) -> 0 | AA10: =IF(AA$8=$R10,-$T10,0)+IF(AA$8=$S10,$T10,0) -> 0 | AB10: =IF(AB$8=$R10,-$T10,0)+IF(AB$8=$S10,$T10,0) -> 0 | AC10: =IF(AC$8=$R10,-$T10,0)+IF(AC$8=$S10,$T10,0) -> 0 | AD10: =IF(AD$8=$R10,-$T10,0)+IF(AD$8=$S10,$T10,0) -> 0 | AE10: =IF(AE$8=$R10,-$T10,0)+IF(AE$8=$S10,$T10,0) -> 0 | AF10: =IF(AF$8=$R10,-$T10,0)+IF(AF$8=$S10,$T10,0) -> 0 | AG10: =IF(AG$8=$R10,-$T10,0)+IF(AG$8=$S10,$T10,0) -> 0 | ... AK10: =IF(AK$8=$R10,-$T10,0)+IF(AK$8=$S10,$T10,0) -> 0
A11: 3 | C11: =TRIM(ANUAL!C15) -> DINH1 | D11: =TRIM(ANUAL!D15) -> EM ESPÉCIE | E11: 0 | F11: =E11+SUMIF(X$9:X$88,1,OFFSET($Z$9:$Z$88,0,A11-1)) -> 0 | G11: =E11+SUM(OFFSET($Z$9:$Z$88,0,A11-1)) -> 0 | J11: =NOT(ISERR(SEARCH(J$27,$C11))) -> FALSE | K11: =NOT(ISERR(SEARCH(K$27,$C11))) -> FALSE | L11: =NOT(ISERR(SEARCH(L$27,$C11))) -> TRUE | N11: 3 | X11: =IF(P11<NOW(),1,0) -> 1 | Z11: =IF(Z$8=$R11,-$T11,0)+IF(Z$8=$S11,$T11,0) -> 0 | AA11: =IF(AA$8=$R11,-$T11,0)+IF(AA$8=$S11,$T11,0) -> 0 | AB11: =IF(AB$8=$R11,-$T11,0)+IF(AB$8=$S11,$T11,0) -> 0 | AC11: =IF(AC$8=$R11,-$T11,0)+IF(AC$8=$S11,$T11,0) -> 0 | AD11: =IF(AD$8=$R11,-$T11,0)+IF(AD$8=$S11,$T11,0) -> 0 | AE11: =IF(AE$8=$R11,-$T11,0)+IF(AE$8=$S11,$T11,0) -> 0 | AF11: =IF(AF$8=$R11,-$T11,0)+IF(AF$8=$S11,$T11,0) -> 0 | AG11: =IF(AG$8=$R11,-$T11,0)+IF(AG$8=$S11,$T11,0) -> 0 | ... AK11: =IF(AK$8=$R11,-$T11,0)+IF(AK$8=$S11,$T11,0) -> 0
A12: 4 | C12: =TRIM(ANUAL!C16) -> CRED1 | D12: =TRIM(ANUAL!D16) -> CARTÃO DE CRÉDITO 1 | E12: 0 | F12: =E12+SUMIF(X$9:X$88,1,OFFSET($Z$9:$Z$88,0,A12-1)) -> 0 | G12: =E12+SUM(OFFSET($Z$9:$Z$88,0,A12-1)) -> 0 | J12: =NOT(ISERR(SEARCH(J$27,$C12))) -> FALSE | K12: =NOT(ISERR(SEARCH(K$27,$C12))) -> FALSE | L12: =NOT(ISERR(SEARCH(L$27,$C12))) -> FALSE | N12: 4 | X12: =IF(P12<NOW(),1,0) -> 1 | Z12: =IF(Z$8=$R12,-$T12,0)+IF(Z$8=$S12,$T12,0) -> 0 | AA12: =IF(AA$8=$R12,-$T12,0)+IF(AA$8=$S12,$T12,0) -> 0 | AB12: =IF(AB$8=$R12,-$T12,0)+IF(AB$8=$S12,$T12,0) -> 0 | AC12: =IF(AC$8=$R12,-$T12,0)+IF(AC$8=$S12,$T12,0) -> 0 | AD12: =IF(AD$8=$R12,-$T12,0)+IF(AD$8=$S12,$T12,0) -> 0 | AE12: =IF(AE$8=$R12,-$T12,0)+IF(AE$8=$S12,$T12,0) -> 0 | AF12: =IF(AF$8=$R12,-$T12,0)+IF(AF$8=$S12,$T12,0) -> 0 | AG12: =IF(AG$8=$R12,-$T12,0)+IF(AG$8=$S12,$T12,0) -> 0 | ... AK12: =IF(AK$8=$R12,-$T12,0)+IF(AK$8=$S12,$T12,0) -> 0
A13: 5 | C13: =TRIM(ANUAL!C17) -> --- | D13: =TRIM(ANUAL!D17) | E13: 0 | F13: =E13+SUMIF(X$9:X$88,1,OFFSET($Z$9:$Z$88,0,A13-1)) -> 0 | G13: =E13+SUM(OFFSET($Z$9:$Z$88,0,A13-1)) -> 0 | J13: =NOT(ISERR(SEARCH(J$27,$C13))) -> FALSE | K13: =NOT(ISERR(SEARCH(K$27,$C13))) -> FALSE | L13: =NOT(ISERR(SEARCH(L$27,$C13))) -> FALSE | N13: 5 | X13: =IF(P13<NOW(),1,0) -> 1 | Z13: =IF(Z$8=$R13,-$T13,0)+IF(Z$8=$S13,$T13,0) -> 0 | AA13: =IF(AA$8=$R13,-$T13,0)+IF(AA$8=$S13,$T13,0) -> 0 | AB13: =IF(AB$8=$R13,-$T13,0)+IF(AB$8=$S13,$T13,0) -> 0 | AC13: =IF(AC$8=$R13,-$T13,0)+IF(AC$8=$S13,$T13,0) -> 0 | AD13: =IF(AD$8=$R13,-$T13,0)+IF(AD$8=$S13,$T13,0) -> 0 | AE13: =IF(AE$8=$R13,-$T13,0)+IF(AE$8=$S13,$T13,0) -> 0 | AF13: =IF(AF$8=$R13,-$T13,0)+IF(AF$8=$S13,$T13,0) -> 0 | AG13: =IF(AG$8=$R13,-$T13,0)+IF(AG$8=$S13,$T13,0) -> 0 | ... AK13: =IF(AK$8=$R13,-$T13,0)+IF(AK$8=$S13,$T13,0) -> 0
A14: 6 | C14: =TRIM(ANUAL!C18) -> --- | D14: =TRIM(ANUAL!D18) | E14: 0 | F14: =E14+SUMIF(X$9:X$88,1,OFFSET($Z$9:$Z$88,0,A14-1)) -> 0 | G14: =E14+SUM(OFFSET($Z$9:$Z$88,0,A14-1)) -> 0 | J14: =NOT(ISERR(SEARCH(J$27,$C14))) -> FALSE | K14: =NOT(ISERR(SEARCH(K$27,$C14))) -> FALSE | L14: =NOT(ISERR(SEARCH(L$27,$C14))) -> FALSE | N14: 6 | X14: =IF(P14<NOW(),1,0) -> 1 | Z14: =IF(Z$8=$R14,-$T14,0)+IF(Z$8=$S14,$T14,0) -> 0 | AA14: =IF(AA$8=$R14,-$T14,0)+IF(AA$8=$S14,$T14,0) -> 0 | AB14: =IF(AB$8=$R14,-$T14,0)+IF(AB$8=$S14,$T14,0) -> 0 | AC14: =IF(AC$8=$R14,-$T14,0)+IF(AC$8=$S14,$T14,0) -> 0 | AD14: =IF(AD$8=$R14,-$T14,0)+IF(AD$8=$S14,$T14,0) -> 0 | AE14: =IF(AE$8=$R14,-$T14,0)+IF(AE$8=$S14,$T14,0) -> 0 | AF14: =IF(AF$8=$R14,-$T14,0)+IF(AF$8=$S14,$T14,0) -> 0 | AG14: =IF(AG$8=$R14,-$T14,0)+IF(AG$8=$S14,$T14,0) -> 0 | ... AK14: =IF(AK$8=$R14,-$T14,0)+IF(AK$8=$S14,$T14,0) -> 0
A15: 7 | C15: =TRIM(ANUAL!C19) -> --- | D15: =TRIM(ANUAL!D19) | E15: 0 | F15: =E15+SUMIF(X$9:X$88,1,OFFSET($Z$9:$Z$88,0,A15-1)) -> 0 | G15: =E15+SUM(OFFSET($Z$9:$Z$88,0,A15-1)) -> 0 | J15: =NOT(ISERR(SEARCH(J$27,$C15))) -> FALSE | K15: =NOT(ISERR(SEARCH(K$27,$C15))) -> FALSE | L15: =NOT(ISERR(SEARCH(L$27,$C15))) -> FALSE | N15: 7 | X15: =IF(P15<NOW(),1,0) -> 1 | Z15: =IF(Z$8=$R15,-$T15,0)+IF(Z$8=$S15,$T15,0) -> 0 | AA15: =IF(AA$8=$R15,-$T15,0)+IF(AA$8=$S15,$T15,0) -> 0 | AB15: =IF(AB$8=$R15,-$T15,0)+IF(AB$8=$S15,$T15,0) -> 0 | AC15: =IF(AC$8=$R15,-$T15,0)+IF(AC$8=$S15,$T15,0) -> 0 | AD15: =IF(AD$8=$R15,-$T15,0)+IF(AD$8=$S15,$T15,0) -> 0 | AE15: =IF(AE$8=$R15,-$T15,0)+IF(AE$8=$S15,$T15,0) -> 0 | AF15: =IF(AF$8=$R15,-$T15,0)+IF(AF$8=$S15,$T15,0) -> 0 | AG15: =IF(AG$8=$R15,-$T15,0)+IF(AG$8=$S15,$T15,0) -> 0 | ... AK15: =IF(AK$8=$R15,-$T15,0)+IF(AK$8=$S15,$T15,0) -> 0
A16: 8 | C16: =TRIM(ANUAL!C20) -> --- | D16: =TRIM(ANUAL!D20) | E16: 0 | F16: =E16+SUMIF(X$9:X$88,1,OFFSET($Z$9:$Z$88,0,A16-1)) -> 0 | G16: =E16+SUM(OFFSET($Z$9:$Z$88,0,A16-1)) -> 0 | J16: =NOT(ISERR(SEARCH(J$27,$C16))) -> FALSE | K16: =NOT(ISERR(SEARCH(K$27,$C16))) -> FALSE | L16: =NOT(ISERR(SEARCH(L$27,$C16))) -> FALSE | N16: 8 | X16: =IF(P16<NOW(),1,0) -> 1 | Z16: =IF(Z$8=$R16,-$T16,0)+IF(Z$8=$S16,$T16,0) -> 0 | AA16: =IF(AA$8=$R16,-$T16,0)+IF(AA$8=$S16,$T16,0) -> 0 | AB16: =IF(AB$8=$R16,-$T16,0)+IF(AB$8=$S16,$T16,0) -> 0 | AC16: =IF(AC$8=$R16,-$T16,0)+IF(AC$8=$S16,$T16,0) -> 0 | AD16: =IF(AD$8=$R16,-$T16,0)+IF(AD$8=$S16,$T16,0) -> 0 | AE16: =IF(AE$8=$R16,-$T16,0)+IF(AE$8=$S16,$T16,0) -> 0 | AF16: =IF(AF$8=$R16,-$T16,0)+IF(AF$8=$S16,$T16,0) -> 0 | AG16: =IF(AG$8=$R16,-$T16,0)+IF(AG$8=$S16,$T16,0) -> 0 | ... AK16: =IF(AK$8=$R16,-$T16,0)+IF(AK$8=$S16,$T16,0) -> 0
A17: 9 | C17: =TRIM(ANUAL!C21) -> --- | D17: =TRIM(ANUAL!D21) | E17: 0 | F17: =E17+SUMIF(X$9:X$88,1,OFFSET($Z$9:$Z$88,0,A17-1)) -> 0 | G17: =E17+SUM(OFFSET($Z$9:$Z$88,0,A17-1)) -> 0 | J17: =NOT(ISERR(SEARCH(J$27,$C17))) -> FALSE | K17: =NOT(ISERR(SEARCH(K$27,$C17))) -> FALSE | L17: =NOT(ISERR(SEARCH(L$27,$C17))) -> FALSE | N17: 9 | X17: =IF(P17<NOW(),1,0) -> 1 | Z17: =IF(Z$8=$R17,-$T17,0)+IF(Z$8=$S17,$T17,0) -> 0 | AA17: =IF(AA$8=$R17,-$T17,0)+IF(AA$8=$S17,$T17,0) -> 0 | AB17: =IF(AB$8=$R17,-$T17,0)+IF(AB$8=$S17,$T17,0) -> 0 | AC17: =IF(AC$8=$R17,-$T17,0)+IF(AC$8=$S17,$T17,0) -> 0 | AD17: =IF(AD$8=$R17,-$T17,0)+IF(AD$8=$S17,$T17,0) -> 0 | AE17: =IF(AE$8=$R17,-$T17,0)+IF(AE$8=$S17,$T17,0) -> 0 | AF17: =IF(AF$8=$R17,-$T17,0)+IF(AF$8=$S17,$T17,0) -> 0 | AG17: =IF(AG$8=$R17,-$T17,0)+IF(AG$8=$S17,$T17,0) -> 0 | ... AK17: =IF(AK$8=$R17,-$T17,0)+IF(AK$8=$S17,$T17,0) -> 0
A18: 10 | C18: =TRIM(ANUAL!C22) -> --- | D18: =TRIM(ANUAL!D22) | E18: 0 | F18: =E18+SUMIF(X$9:X$88,1,OFFSET($Z$9:$Z$88,0,A18-1)) -> 0 | G18: =E18+SUM(OFFSET($Z$9:$Z$88,0,A18-1)) -> 0 | J18: =NOT(ISERR(SEARCH(J$27,$C18))) -> FALSE | K18: =NOT(ISERR(SEARCH(K$27,$C18))) -> FALSE | L18: =NOT(ISERR(SEARCH(L$27,$C18))) -> FALSE | N18: 10 | X18: =IF(P18<NOW(),1,0) -> 1 | Z18: =IF(Z$8=$R18,-$T18,0)+IF(Z$8=$S18,$T18,0) -> 0 | AA18: =IF(AA$8=$R18,-$T18,0)+IF(AA$8=$S18,$T18,0) -> 0 | AB18: =IF(AB$8=$R18,-$T18,0)+IF(AB$8=$S18,$T18,0) -> 0 | AC18: =IF(AC$8=$R18,-$T18,0)+IF(AC$8=$S18,$T18,0) -> 0 | AD18: =IF(AD$8=$R18,-$T18,0)+IF(AD$8=$S18,$T18,0) -> 0 | AE18: =IF(AE$8=$R18,-$T18,0)+IF(AE$8=$S18,$T18,0) -> 0 | AF18: =IF(AF$8=$R18,-$T18,0)+IF(AF$8=$S18,$T18,0) -> 0 | AG18: =IF(AG$8=$R18,-$T18,0)+IF(AG$8=$S18,$T18,0) -> 0 | ... AK18: =IF(AK$8=$R18,-$T18,0)+IF(AK$8=$S18,$T18,0) -> 0
A19: 11 | C19: =TRIM(ANUAL!C23) -> --- | D19: =TRIM(ANUAL!D23) | E19: 0 | F19: =E19+SUMIF(X$9:X$88,1,OFFSET($Z$9:$Z$88,0,A19-1)) -> 0 | G19: =E19+SUM(OFFSET($Z$9:$Z$88,0,A19-1)) -> 0 | J19: =NOT(ISERR(SEARCH(J$27,$C19))) -> FALSE | K19: =NOT(ISERR(SEARCH(K$27,$C19))) -> FALSE | L19: =NOT(ISERR(SEARCH(L$27,$C19))) -> FALSE | N19: 11 | X19: =IF(P19<NOW(),1,0) -> 1 | Z19: =IF(Z$8=$R19,-$T19,0)+IF(Z$8=$S19,$T19,0) -> 0 | AA19: =IF(AA$8=$R19,-$T19,0)+IF(AA$8=$S19,$T19,0) -> 0 | AB19: =IF(AB$8=$R19,-$T19,0)+IF(AB$8=$S19,$T19,0) -> 0 | AC19: =IF(AC$8=$R19,-$T19,0)+IF(AC$8=$S19,$T19,0) -> 0 | AD19: =IF(AD$8=$R19,-$T19,0)+IF(AD$8=$S19,$T19,0) -> 0 | AE19: =IF(AE$8=$R19,-$T19,0)+IF(AE$8=$S19,$T19,0) -> 0 | AF19: =IF(AF$8=$R19,-$T19,0)+IF(AF$8=$S19,$T19,0) -> 0 | AG19: =IF(AG$8=$R19,-$T19,0)+IF(AG$8=$S19,$T19,0) -> 0 | ... AK19: =IF(AK$8=$R19,-$T19,0)+IF(AK$8=$S19,$T19,0) -> 0
A20: 12 | C20: =TRIM(ANUAL!C24) -> --- | D20: =TRIM(ANUAL!D24) | E20: 0 | F20: =E20+SUMIF(X$9:X$88,1,OFFSET($Z$9:$Z$88,0,A20-1)) -> 0 | G20: =E20+SUM(OFFSET($Z$9:$Z$88,0,A20-1)) -> 0 | J20: =NOT(ISERR(SEARCH(J$27,$C20))) -> FALSE | K20: =NOT(ISERR(SEARCH(K$27,$C20))) -> FALSE | L20: =NOT(ISERR(SEARCH(L$27,$C20))) -> FALSE | N20: 12 | X20: =IF(P20<NOW(),1,0) -> 1 | Z20: =IF(Z$8=$R20,-$T20,0)+IF(Z$8=$S20,$T20,0) -> 0 | AA20: =IF(AA$8=$R20,-$T20,0)+IF(AA$8=$S20,$T20,0) -> 0 | AB20: =IF(AB$8=$R20,-$T20,0)+IF(AB$8=$S20,$T20,0) -> 0 | AC20: =IF(AC$8=$R20,-$T20,0)+IF(AC$8=$S20,$T20,0) -> 0 | AD20: =IF(AD$8=$R20,-$T20,0)+IF(AD$8=$S20,$T20,0) -> 0 | AE20: =IF(AE$8=$R20,-$T20,0)+IF(AE$8=$S20,$T20,0) -> 0 | AF20: =IF(AF$8=$R20,-$T20,0)+IF(AF$8=$S20,$T20,0) -> 0 | AG20: =IF(AG$8=$R20,-$T20,0)+IF(AG$8=$S20,$T20,0) -> 0 | ... AK20: =IF(AK$8=$R20,-$T20,0)+IF(AK$8=$S20,$T20,0) -> 0
N21: 13 | X21: =IF(P21<NOW(),1,0) -> 1 | Z21: =IF(Z$8=$R21,-$T21,0)+IF(Z$8=$S21,$T21,0) -> 0 | AA21: =IF(AA$8=$R21,-$T21,0)+IF(AA$8=$S21,$T21,0) -> 0 | AB21: =IF(AB$8=$R21,-$T21,0)+IF(AB$8=$S21,$T21,0) -> 0 | AC21: =IF(AC$8=$R21,-$T21,0)+IF(AC$8=$S21,$T21,0) -> 0 | AD21: =IF(AD$8=$R21,-$T21,0)+IF(AD$8=$S21,$T21,0) -> 0 | AE21: =IF(AE$8=$R21,-$T21,0)+IF(AE$8=$S21,$T21,0) -> 0 | AF21: =IF(AF$8=$R21,-$T21,0)+IF(AF$8=$S21,$T21,0) -> 0 | AG21: =IF(AG$8=$R21,-$T21,0)+IF(AG$8=$S21,$T21,0) -> 0 | ... AK21: =IF(AK$8=$R21,-$T21,0)+IF(AK$8=$S21,$T21,0) -> 0
N22: 14 | X22: =IF(P22<NOW(),1,0) -> 1 | Z22: =IF(Z$8=$R22,-$T22,0)+IF(Z$8=$S22,$T22,0) -> 0 | AA22: =IF(AA$8=$R22,-$T22,0)+IF(AA$8=$S22,$T22,0) -> 0 | AB22: =IF(AB$8=$R22,-$T22,0)+IF(AB$8=$S22,$T22,0) -> 0 | AC22: =IF(AC$8=$R22,-$T22,0)+IF(AC$8=$S22,$T22,0) -> 0 | AD22: =IF(AD$8=$R22,-$T22,0)+IF(AD$8=$S22,$T22,0) -> 0 | AE22: =IF(AE$8=$R22,-$T22,0)+IF(AE$8=$S22,$T22,0) -> 0 | AF22: =IF(AF$8=$R22,-$T22,0)+IF(AF$8=$S22,$T22,0) -> 0 | AG22: =IF(AG$8=$R22,-$T22,0)+IF(AG$8=$S22,$T22,0) -> 0 | ... AK22: =IF(AK$8=$R22,-$T22,0)+IF(AK$8=$S22,$T22,0) -> 0
N23: 15 | X23: =IF(P23<NOW(),1,0) -> 1 | Z23: =IF(Z$8=$R23,-$T23,0)+IF(Z$8=$S23,$T23,0) -> 0 | AA23: =IF(AA$8=$R23,-$T23,0)+IF(AA$8=$S23,$T23,0) -> 0 | AB23: =IF(AB$8=$R23,-$T23,0)+IF(AB$8=$S23,$T23,0) -> 0 | AC23: =IF(AC$8=$R23,-$T23,0)+IF(AC$8=$S23,$T23,0) -> 0 | AD23: =IF(AD$8=$R23,-$T23,0)+IF(AD$8=$S23,$T23,0) -> 0 | AE23: =IF(AE$8=$R23,-$T23,0)+IF(AE$8=$S23,$T23,0) -> 0 | AF23: =IF(AF$8=$R23,-$T23,0)+IF(AF$8=$S23,$T23,0) -> 0 | AG23: =IF(AG$8=$R23,-$T23,0)+IF(AG$8=$S23,$T23,0) -> 0 | ... AK23: =IF(AK$8=$R23,-$T23,0)+IF(AK$8=$S23,$T23,0) -> 0
C24: VARIAÇÃO MENSAL POR CONTA | N24: 16 | X24: =IF(P24<NOW(),1,0) -> 1 | Z24: =IF(Z$8=$R24,-$T24,0)+IF(Z$8=$S24,$T24,0) -> 0 | AA24: =IF(AA$8=$R24,-$T24,0)+IF(AA$8=$S24,$T24,0) -> 0 | AB24: =IF(AB$8=$R24,-$T24,0)+IF(AB$8=$S24,$T24,0) -> 0 | AC24: =IF(AC$8=$R24,-$T24,0)+IF(AC$8=$S24,$T24,0) -> 0 | AD24: =IF(AD$8=$R24,-$T24,0)+IF(AD$8=$S24,$T24,0) -> 0 | AE24: =IF(AE$8=$R24,-$T24,0)+IF(AE$8=$S24,$T24,0) -> 0 | AF24: =IF(AF$8=$R24,-$T24,0)+IF(AF$8=$S24,$T24,0) -> 0 | AG24: =IF(AG$8=$R24,-$T24,0)+IF(AG$8=$S24,$T24,0) -> 0 | ... AK24: =IF(AK$8=$R24,-$T24,0)+IF(AK$8=$S24,$T24,0) -> 0
N25: 17 | X25: =IF(P25<NOW(),1,0) -> 1 | Z25: =IF(Z$8=$R25,-$T25,0)+IF(Z$8=$S25,$T25,0) -> 0 | AA25: =IF(AA$8=$R25,-$T25,0)+IF(AA$8=$S25,$T25,0) -> 0 | AB25: =IF(AB$8=$R25,-$T25,0)+IF(AB$8=$S25,$T25,0) -> 0 | AC25: =IF(AC$8=$R25,-$T25,0)+IF(AC$8=$S25,$T25,0) -> 0 | AD25: =IF(AD$8=$R25,-$T25,0)+IF(AD$8=$S25,$T25,0) -> 0 | AE25: =IF(AE$8=$R25,-$T25,0)+IF(AE$8=$S25,$T25,0) -> 0 | AF25: =IF(AF$8=$R25,-$T25,0)+IF(AF$8=$S25,$T25,0) -> 0 | AG25: =IF(AG$8=$R25,-$T25,0)+IF(AG$8=$S25,$T25,0) -> 0 | ... AK25: =IF(AK$8=$R25,-$T25,0)+IF(AK$8=$S25,$T25,0) -> 0
C26: CONTA | D26: DESCRIÇÃO | E26: TRANSFERÊNCIAS | F26: SAÍDA | G26: SALDO | N26: 18 | X26: =IF(P26<NOW(),1,0) -> 1 | Z26: =IF(Z$8=$R26,-$T26,0)+IF(Z$8=$S26,$T26,0) -> 0 | AA26: =IF(AA$8=$R26,-$T26,0)+IF(AA$8=$S26,$T26,0) -> 0 | AB26: =IF(AB$8=$R26,-$T26,0)+IF(AB$8=$S26,$T26,0) -> 0 | AC26: =IF(AC$8=$R26,-$T26,0)+IF(AC$8=$S26,$T26,0) -> 0 | AD26: =IF(AD$8=$R26,-$T26,0)+IF(AD$8=$S26,$T26,0) -> 0 | AE26: =IF(AE$8=$R26,-$T26,0)+IF(AE$8=$S26,$T26,0) -> 0 | AF26: =IF(AF$8=$R26,-$T26,0)+IF(AF$8=$S26,$T26,0) -> 0 | AG26: =IF(AG$8=$R26,-$T26,0)+IF(AG$8=$S26,$T26,0) -> 0 | ... AK26: =IF(AK$8=$R26,-$T26,0)+IF(AK$8=$S26,$T26,0) -> 0
E27: ENTRADA | F27: SAÍDA | G27: VARIAÇÃO | J27: =ANUAL!C115 -> CC | K27: =ANUAL!C116 -> INV | L27: =ANUAL!C117 -> DINH | N27: 19 | X27: =IF(P27<NOW(),1,0) -> 1 | Z27: =IF(Z$8=$R27,-$T27,0)+IF(Z$8=$S27,$T27,0) -> 0 | AA27: =IF(AA$8=$R27,-$T27,0)+IF(AA$8=$S27,$T27,0) -> 0 | AB27: =IF(AB$8=$R27,-$T27,0)+IF(AB$8=$S27,$T27,0) -> 0 | AC27: =IF(AC$8=$R27,-$T27,0)+IF(AC$8=$S27,$T27,0) -> 0 | AD27: =IF(AD$8=$R27,-$T27,0)+IF(AD$8=$S27,$T27,0) -> 0 | AE27: =IF(AE$8=$R27,-$T27,0)+IF(AE$8=$S27,$T27,0) -> 0 | AF27: =IF(AF$8=$R27,-$T27,0)+IF(AF$8=$S27,$T27,0) -> 0 | AG27: =IF(AG$8=$R27,-$T27,0)+IF(AG$8=$S27,$T27,0) -> 0 | ... AK27: =IF(AK$8=$R27,-$T27,0)+IF(AK$8=$S27,$T27,0) -> 0
A28: 1 | C28: =C9 | D28: =D9 -> CONTA CORRENTE BANCO 1 | E28: =SUMIF(OFFSET($Z$9:$Z$88,0,A28-1),">0") -> 0 | F28: =SUMIF(OFFSET($Z$9:$Z$88,0,A28-1),"<0") -> 0 | G28: =SUM(E28:F28) -> 0 | J28: =NOT(ISERR(SEARCH(J$27,$C28))) -> FALSE | K28: =NOT(ISERR(SEARCH(K$27,$C28))) -> FALSE | L28: =NOT(ISERR(SEARCH(L$27,$C28))) -> FALSE | N28: 20 | X28: =IF(P28<NOW(),1,0) -> 1 | Z28: =IF(Z$8=$R28,-$T28,0)+IF(Z$8=$S28,$T28,0) -> 0 | AA28: =IF(AA$8=$R28,-$T28,0)+IF(AA$8=$S28,$T28,0) -> 0 | AB28: =IF(AB$8=$R28,-$T28,0)+IF(AB$8=$S28,$T28,0) -> 0 | AC28: =IF(AC$8=$R28,-$T28,0)+IF(AC$8=$S28,$T28,0) -> 0 | AD28: =IF(AD$8=$R28,-$T28,0)+IF(AD$8=$S28,$T28,0) -> 0 | AE28: =IF(AE$8=$R28,-$T28,0)+IF(AE$8=$S28,$T28,0) -> 0 | AF28: =IF(AF$8=$R28,-$T28,0)+IF(AF$8=$S28,$T28,0) -> 0 | AG28: =IF(AG$8=$R28,-$T28,0)+IF(AG$8=$S28,$T28,0) -> 0 | ... AK28: =IF(AK$8=$R28,-$T28,0)+IF(AK$8=$S28,$T28,0) -> 0
A29: 2 | C29: =C10 -> INV1 | D29: =D10 -> POUPANÇA BANCO 1 | E29: =SUMIF(OFFSET($Z$9:$Z$88,0,A29-1),">0") -> 0 | F29: =SUMIF(OFFSET($Z$9:$Z$88,0,A29-1),"<0") -> 0 | G29: =SUM(E29:F29) -> 0 | J29: =NOT(ISERR(SEARCH(J$27,$C29))) -> FALSE | K29: =NOT(ISERR(SEARCH(K$27,$C29))) -> TRUE | L29: =NOT(ISERR(SEARCH(L$27,$C29))) -> FALSE | N29: 21 | X29: =IF(P29<NOW(),1,0) -> 1 | Z29: =IF(Z$8=$R29,-$T29,0)+IF(Z$8=$S29,$T29,0) -> 0 | AA29: =IF(AA$8=$R29,-$T29,0)+IF(AA$8=$S29,$T29,0) -> 0 | AB29: =IF(AB$8=$R29,-$T29,0)+IF(AB$8=$S29,$T29,0) -> 0 | AC29: =IF(AC$8=$R29,-$T29,0)+IF(AC$8=$S29,$T29,0) -> 0 | AD29: =IF(AD$8=$R29,-$T29,0)+IF(AD$8=$S29,$T29,0) -> 0 | AE29: =IF(AE$8=$R29,-$T29,0)+IF(AE$8=$S29,$T29,0) -> 0 | AF29: =IF(AF$8=$R29,-$T29,0)+IF(AF$8=$S29,$T29,0) -> 0 | AG29: =IF(AG$8=$R29,-$T29,0)+IF(AG$8=$S29,$T29,0) -> 0 | ... AK29: =IF(AK$8=$R29,-$T29,0)+IF(AK$8=$S29,$T29,0) -> 0
A30: 3 | C30: =C11 -> DINH1 | D30: =D11 -> EM ESPÉCIE | E30: =SUMIF(OFFSET($Z$9:$Z$88,0,A30-1),">0") -> 0 | F30: =SUMIF(OFFSET($Z$9:$Z$88,0,A30-1),"<0") -> 0 | G30: =SUM(E30:F30) -> 0 | J30: =NOT(ISERR(SEARCH(J$27,$C30))) -> FALSE | K30: =NOT(ISERR(SEARCH(K$27,$C30))) -> FALSE | L30: =NOT(ISERR(SEARCH(L$27,$C30))) -> TRUE | N30: 22 | X30: =IF(P30<NOW(),1,0) -> 1 | Z30: =IF(Z$8=$R30,-$T30,0)+IF(Z$8=$S30,$T30,0) -> 0 | AA30: =IF(AA$8=$R30,-$T30,0)+IF(AA$8=$S30,$T30,0) -> 0 | AB30: =IF(AB$8=$R30,-$T30,0)+IF(AB$8=$S30,$T30,0) -> 0 | AC30: =IF(AC$8=$R30,-$T30,0)+IF(AC$8=$S30,$T30,0) -> 0 | AD30: =IF(AD$8=$R30,-$T30,0)+IF(AD$8=$S30,$T30,0) -> 0 | AE30: =IF(AE$8=$R30,-$T30,0)+IF(AE$8=$S30,$T30,0) -> 0 | AF30: =IF(AF$8=$R30,-$T30,0)+IF(AF$8=$S30,$T30,0) -> 0 | AG30: =IF(AG$8=$R30,-$T30,0)+IF(AG$8=$S30,$T30,0) -> 0 | ... AK30: =IF(AK$8=$R30,-$T30,0)+IF(AK$8=$S30,$T30,0) -> 0
A31: 4 | C31: =C12 -> CRED1 | D31: =D12 -> CARTÃO DE CRÉDITO 1 | E31: =SUMIF(OFFSET($Z$9:$Z$88,0,A31-1),">0") -> 0 | F31: =SUMIF(OFFSET($Z$9:$Z$88,0,A31-1),"<0") -> 0 | G31: =SUM(E31:F31) -> 0 | J31: =NOT(ISERR(SEARCH(J$27,$C31))) -> FALSE | K31: =NOT(ISERR(SEARCH(K$27,$C31))) -> FALSE | L31: =NOT(ISERR(SEARCH(L$27,$C31))) -> FALSE | N31: 23 | X31: =IF(P31<NOW(),1,0) -> 1 | Z31: =IF(Z$8=$R31,-$T31,0)+IF(Z$8=$S31,$T31,0) -> 0 | AA31: =IF(AA$8=$R31,-$T31,0)+IF(AA$8=$S31,$T31,0) -> 0 | AB31: =IF(AB$8=$R31,-$T31,0)+IF(AB$8=$S31,$T31,0) -> 0 | AC31: =IF(AC$8=$R31,-$T31,0)+IF(AC$8=$S31,$T31,0) -> 0 | AD31: =IF(AD$8=$R31,-$T31,0)+IF(AD$8=$S31,$T31,0) -> 0 | AE31: =IF(AE$8=$R31,-$T31,0)+IF(AE$8=$S31,$T31,0) -> 0 | AF31: =IF(AF$8=$R31,-$T31,0)+IF(AF$8=$S31,$T31,0) -> 0 | AG31: =IF(AG$8=$R31,-$T31,0)+IF(AG$8=$S31,$T31,0) -> 0 | ... AK31: =IF(AK$8=$R31,-$T31,0)+IF(AK$8=$S31,$T31,0) -> 0
A32: 5 | C32: =C13 -> --- | D32: =D13 | E32: =SUMIF(OFFSET($Z$9:$Z$88,0,A32-1),">0") -> 0 | F32: =SUMIF(OFFSET($Z$9:$Z$88,0,A32-1),"<0") -> 0 | G32: =SUM(E32:F32) -> 0 | J32: =NOT(ISERR(SEARCH(J$27,$C32))) -> FALSE | K32: =NOT(ISERR(SEARCH(K$27,$C32))) -> FALSE | L32: =NOT(ISERR(SEARCH(L$27,$C32))) -> FALSE | N32: 24 | X32: =IF(P32<NOW(),1,0) -> 1 | Z32: =IF(Z$8=$R32,-$T32,0)+IF(Z$8=$S32,$T32,0) -> 0 | AA32: =IF(AA$8=$R32,-$T32,0)+IF(AA$8=$S32,$T32,0) -> 0 | AB32: =IF(AB$8=$R32,-$T32,0)+IF(AB$8=$S32,$T32,0) -> 0 | AC32: =IF(AC$8=$R32,-$T32,0)+IF(AC$8=$S32,$T32,0) -> 0 | AD32: =IF(AD$8=$R32,-$T32,0)+IF(AD$8=$S32,$T32,0) -> 0 | AE32: =IF(AE$8=$R32,-$T32,0)+IF(AE$8=$S32,$T32,0) -> 0 | AF32: =IF(AF$8=$R32,-$T32,0)+IF(AF$8=$S32,$T32,0) -> 0 | AG32: =IF(AG$8=$R32,-$T32,0)+IF(AG$8=$S32,$T32,0) -> 0 | ... AK32: =IF(AK$8=$R32,-$T32,0)+IF(AK$8=$S32,$T32,0) -> 0
A33: 6 | C33: =C14 -> --- | D33: =D14 | E33: =SUMIF(OFFSET($Z$9:$Z$88,0,A33-1),">0") -> 0 | F33: =SUMIF(OFFSET($Z$9:$Z$88,0,A33-1),"<0") -> 0 | G33: =SUM(E33:F33) -> 0 | J33: =NOT(ISERR(SEARCH(J$27,$C33))) -> FALSE | K33: =NOT(ISERR(SEARCH(K$27,$C33))) -> FALSE | L33: =NOT(ISERR(SEARCH(L$27,$C33))) -> FALSE | N33: 25 | X33: =IF(P33<NOW(),1,0) -> 1 | Z33: =IF(Z$8=$R33,-$T33,0)+IF(Z$8=$S33,$T33,0) -> 0 | AA33: =IF(AA$8=$R33,-$T33,0)+IF(AA$8=$S33,$T33,0) -> 0 | AB33: =IF(AB$8=$R33,-$T33,0)+IF(AB$8=$S33,$T33,0) -> 0 | AC33: =IF(AC$8=$R33,-$T33,0)+IF(AC$8=$S33,$T33,0) -> 0 | AD33: =IF(AD$8=$R33,-$T33,0)+IF(AD$8=$S33,$T33,0) -> 0 | AE33: =IF(AE$8=$R33,-$T33,0)+IF(AE$8=$S33,$T33,0) -> 0 | AF33: =IF(AF$8=$R33,-$T33,0)+IF(AF$8=$S33,$T33,0) -> 0 | AG33: =IF(AG$8=$R33,-$T33,0)+IF(AG$8=$S33,$T33,0) -> 0 | ... AK33: =IF(AK$8=$R33,-$T33,0)+IF(AK$8=$S33,$T33,0) -> 0
A34: 7 | C34: =C15 -> --- | D34: =D15 | E34: =SUMIF(OFFSET($Z$9:$Z$88,0,A34-1),">0") -> 0 | F34: =SUMIF(OFFSET($Z$9:$Z$88,0,A34-1),"<0") -> 0 | G34: =SUM(E34:F34) -> 0 | J34: =NOT(ISERR(SEARCH(J$27,$C34))) -> FALSE | K34: =NOT(ISERR(SEARCH(K$27,$C34))) -> FALSE | L34: =NOT(ISERR(SEARCH(L$27,$C34))) -> FALSE | N34: 26 | X34: =IF(P34<NOW(),1,0) -> 1 | Z34: =IF(Z$8=$R34,-$T34,0)+IF(Z$8=$S34,$T34,0) -> 0 | AA34: =IF(AA$8=$R34,-$T34,0)+IF(AA$8=$S34,$T34,0) -> 0 | AB34: =IF(AB$8=$R34,-$T34,0)+IF(AB$8=$S34,$T34,0) -> 0 | AC34: =IF(AC$8=$R34,-$T34,0)+IF(AC$8=$S34,$T34,0) -> 0 | AD34: =IF(AD$8=$R34,-$T34,0)+IF(AD$8=$S34,$T34,0) -> 0 | AE34: =IF(AE$8=$R34,-$T34,0)+IF(AE$8=$S34,$T34,0) -> 0 | AF34: =IF(AF$8=$R34,-$T34,0)+IF(AF$8=$S34,$T34,0) -> 0 | AG34: =IF(AG$8=$R34,-$T34,0)+IF(AG$8=$S34,$T34,0) -> 0 | ... AK34: =IF(AK$8=$R34,-$T34,0)+IF(AK$8=$S34,$T34,0) -> 0
A35: 8 | C35: =C16 -> --- | D35: =D16 | E35: =SUMIF(OFFSET($Z$9:$Z$88,0,A35-1),">0") -> 0 | F35: =SUMIF(OFFSET($Z$9:$Z$88,0,A35-1),"<0") -> 0 | G35: =SUM(E35:F35) -> 0 | J35: =NOT(ISERR(SEARCH(J$27,$C35))) -> FALSE | K35: =NOT(ISERR(SEARCH(K$27,$C35))) -> FALSE | L35: =NOT(ISERR(SEARCH(L$27,$C35))) -> FALSE | N35: 27 | X35: =IF(P35<NOW(),1,0) -> 1 | Z35: =IF(Z$8=$R35,-$T35,0)+IF(Z$8=$S35,$T35,0) -> 0 | AA35: =IF(AA$8=$R35,-$T35,0)+IF(AA$8=$S35,$T35,0) -> 0 | AB35: =IF(AB$8=$R35,-$T35,0)+IF(AB$8=$S35,$T35,0) -> 0 | AC35: =IF(AC$8=$R35,-$T35,0)+IF(AC$8=$S35,$T35,0) -> 0 | AD35: =IF(AD$8=$R35,-$T35,0)+IF(AD$8=$S35,$T35,0) -> 0 | AE35: =IF(AE$8=$R35,-$T35,0)+IF(AE$8=$S35,$T35,0) -> 0 | AF35: =IF(AF$8=$R35,-$T35,0)+IF(AF$8=$S35,$T35,0) -> 0 | AG35: =IF(AG$8=$R35,-$T35,0)+IF(AG$8=$S35,$T35,0) -> 0 | ... AK35: =IF(AK$8=$R35,-$T35,0)+IF(AK$8=$S35,$T35,0) -> 0
A36: 9 | C36: =C17 -> --- | D36: =D17 | E36: =SUMIF(OFFSET($Z$9:$Z$88,0,A36-1),">0") -> 0 | F36: =SUMIF(OFFSET($Z$9:$Z$88,0,A36-1),"<0") -> 0 | G36: =SUM(E36:F36) -> 0 | J36: =NOT(ISERR(SEARCH(J$27,$C36))) -> FALSE | K36: =NOT(ISERR(SEARCH(K$27,$C36))) -> FALSE | L36: =NOT(ISERR(SEARCH(L$27,$C36))) -> FALSE | N36: 28 | X36: =IF(P36<NOW(),1,0) -> 1 | Z36: =IF(Z$8=$R36,-$T36,0)+IF(Z$8=$S36,$T36,0) -> 0 | AA36: =IF(AA$8=$R36,-$T36,0)+IF(AA$8=$S36,$T36,0) -> 0 | AB36: =IF(AB$8=$R36,-$T36,0)+IF(AB$8=$S36,$T36,0) -> 0 | AC36: =IF(AC$8=$R36,-$T36,0)+IF(AC$8=$S36,$T36,0) -> 0 | AD36: =IF(AD$8=$R36,-$T36,0)+IF(AD$8=$S36,$T36,0) -> 0 | AE36: =IF(AE$8=$R36,-$T36,0)+IF(AE$8=$S36,$T36,0) -> 0 | AF36: =IF(AF$8=$R36,-$T36,0)+IF(AF$8=$S36,$T36,0) -> 0 | AG36: =IF(AG$8=$R36,-$T36,0)+IF(AG$8=$S36,$T36,0) -> 0 | ... AK36: =IF(AK$8=$R36,-$T36,0)+IF(AK$8=$S36,$T36,0) -> 0
A37: 10 | C37: =C18 -> --- | D37: =D18 | E37: =SUMIF(OFFSET($Z$9:$Z$88,0,A37-1),">0") -> 0 | F37: =SUMIF(OFFSET($Z$9:$Z$88,0,A37-1),"<0") -> 0 | G37: =SUM(E37:F37) -> 0 | J37: =NOT(ISERR(SEARCH(J$27,$C37))) -> FALSE | K37: =NOT(ISERR(SEARCH(K$27,$C37))) -> FALSE | L37: =NOT(ISERR(SEARCH(L$27,$C37))) -> FALSE | N37: 29 | X37: =IF(P37<NOW(),1,0) -> 1 | Z37: =IF(Z$8=$R37,-$T37,0)+IF(Z$8=$S37,$T37,0) -> 0 | AA37: =IF(AA$8=$R37,-$T37,0)+IF(AA$8=$S37,$T37,0) -> 0 | AB37: =IF(AB$8=$R37,-$T37,0)+IF(AB$8=$S37,$T37,0) -> 0 | AC37: =IF(AC$8=$R37,-$T37,0)+IF(AC$8=$S37,$T37,0) -> 0 | AD37: =IF(AD$8=$R37,-$T37,0)+IF(AD$8=$S37,$T37,0) -> 0 | AE37: =IF(AE$8=$R37,-$T37,0)+IF(AE$8=$S37,$T37,0) -> 0 | AF37: =IF(AF$8=$R37,-$T37,0)+IF(AF$8=$S37,$T37,0) -> 0 | AG37: =IF(AG$8=$R37,-$T37,0)+IF(AG$8=$S37,$T37,0) -> 0 | ... AK37: =IF(AK$8=$R37,-$T37,0)+IF(AK$8=$S37,$T37,0) -> 0
A38: 11 | C38: =C19 -> --- | D38: =D19 | E38: =SUMIF(OFFSET($Z$9:$Z$88,0,A38-1),">0") -> 0 | F38: =SUMIF(OFFSET($Z$9:$Z$88,0,A38-1),"<0") -> 0 | G38: =SUM(E38:F38) -> 0 | J38: =NOT(ISERR(SEARCH(J$27,$C38))) -> FALSE | K38: =NOT(ISERR(SEARCH(K$27,$C38))) -> FALSE | L38: =NOT(ISERR(SEARCH(L$27,$C38))) -> FALSE | N38: 30 | X38: =IF(P38<NOW(),1,0) -> 1 | Z38: =IF(Z$8=$R38,-$T38,0)+IF(Z$8=$S38,$T38,0) -> 0 | AA38: =IF(AA$8=$R38,-$T38,0)+IF(AA$8=$S38,$T38,0) -> 0 | AB38: =IF(AB$8=$R38,-$T38,0)+IF(AB$8=$S38,$T38,0) -> 0 | AC38: =IF(AC$8=$R38,-$T38,0)+IF(AC$8=$S38,$T38,0) -> 0 | AD38: =IF(AD$8=$R38,-$T38,0)+IF(AD$8=$S38,$T38,0) -> 0 | AE38: =IF(AE$8=$R38,-$T38,0)+IF(AE$8=$S38,$T38,0) -> 0 | AF38: =IF(AF$8=$R38,-$T38,0)+IF(AF$8=$S38,$T38,0) -> 0 | AG38: =IF(AG$8=$R38,-$T38,0)+IF(AG$8=$S38,$T38,0) -> 0 | ... AK38: =IF(AK$8=$R38,-$T38,0)+IF(AK$8=$S38,$T38,0) -> 0
A39: 12 | C39: =C20 -> --- | D39: =D20 | E39: =SUMIF(OFFSET($Z$9:$Z$88,0,A39-1),">0") -> 0 | F39: =SUMIF(OFFSET($Z$9:$Z$88,0,A39-1),"<0") -> 0 | G39: =SUM(E39:F39) -> 0 | J39: =NOT(ISERR(SEARCH(J$27,$C39))) -> FALSE | K39: =NOT(ISERR(SEARCH(K$27,$C39))) -> FALSE | L39: =NOT(ISERR(SEARCH(L$27,$C39))) -> FALSE | N39: 31 | X39: =IF(P39<NOW(),1,0) -> 1 | Z39: =IF(Z$8=$R39,-$T39,0)+IF(Z$8=$S39,$T39,0) -> 0 | AA39: =IF(AA$8=$R39,-$T39,0)+IF(AA$8=$S39,$T39,0) -> 0 | AB39: =IF(AB$8=$R39,-$T39,0)+IF(AB$8=$S39,$T39,0) -> 0 | AC39: =IF(AC$8=$R39,-$T39,0)+IF(AC$8=$S39,$T39,0) -> 0 | AD39: =IF(AD$8=$R39,-$T39,0)+IF(AD$8=$S39,$T39,0) -> 0 | AE39: =IF(AE$8=$R39,-$T39,0)+IF(AE$8=$S39,$T39,0) -> 0 | AF39: =IF(AF$8=$R39,-$T39,0)+IF(AF$8=$S39,$T39,0) -> 0 | AG39: =IF(AG$8=$R39,-$T39,0)+IF(AG$8=$S39,$T39,0) -> 0 | ... AK39: =IF(AK$8=$R39,-$T39,0)+IF(AK$8=$S39,$T39,0) -> 0
N40: 32 | X40: =IF(P40<NOW(),1,0) -> 1 | Z40: =IF(Z$8=$R40,-$T40,0)+IF(Z$8=$S40,$T40,0) -> 0 | AA40: =IF(AA$8=$R40,-$T40,0)+IF(AA$8=$S40,$T40,0) -> 0 | AB40: =IF(AB$8=$R40,-$T40,0)+IF(AB$8=$S40,$T40,0) -> 0 | AC40: =IF(AC$8=$R40,-$T40,0)+IF(AC$8=$S40,$T40,0) -> 0 | AD40: =IF(AD$8=$R40,-$T40,0)+IF(AD$8=$S40,$T40,0) -> 0 | AE40: =IF(AE$8=$R40,-$T40,0)+IF(AE$8=$S40,$T40,0) -> 0 | AF40: =IF(AF$8=$R40,-$T40,0)+IF(AF$8=$S40,$T40,0) -> 0 | AG40: =IF(AG$8=$R40,-$T40,0)+IF(AG$8=$S40,$T40,0) -> 0 | ... AK40: =IF(AK$8=$R40,-$T40,0)+IF(AK$8=$S40,$T40,0) -> 0
N41: 33 | X41: =IF(P41<NOW(),1,0) -> 1 | Z41: =IF(Z$8=$R41,-$T41,0)+IF(Z$8=$S41,$T41,0) -> 0 | AA41: =IF(AA$8=$R41,-$T41,0)+IF(AA$8=$S41,$T41,0) -> 0 | AB41: =IF(AB$8=$R41,-$T41,0)+IF(AB$8=$S41,$T41,0) -> 0 | AC41: =IF(AC$8=$R41,-$T41,0)+IF(AC$8=$S41,$T41,0) -> 0 | AD41: =IF(AD$8=$R41,-$T41,0)+IF(AD$8=$S41,$T41,0) -> 0 | AE41: =IF(AE$8=$R41,-$T41,0)+IF(AE$8=$S41,$T41,0) -> 0 | AF41: =IF(AF$8=$R41,-$T41,0)+IF(AF$8=$S41,$T41,0) -> 0 | AG41: =IF(AG$8=$R41,-$T41,0)+IF(AG$8=$S41,$T41,0) -> 0 | ... AK41: =IF(AK$8=$R41,-$T41,0)+IF(AK$8=$S41,$T41,0) -> 0
N42: 34 | X42: =IF(P42<NOW(),1,0) -> 1 | Z42: =IF(Z$8=$R42,-$T42,0)+IF(Z$8=$S42,$T42,0) -> 0 | AA42: =IF(AA$8=$R42,-$T42,0)+IF(AA$8=$S42,$T42,0) -> 0 | AB42: =IF(AB$8=$R42,-$T42,0)+IF(AB$8=$S42,$T42,0) -> 0 | AC42: =IF(AC$8=$R42,-$T42,0)+IF(AC$8=$S42,$T42,0) -> 0 | AD42: =IF(AD$8=$R42,-$T42,0)+IF(AD$8=$S42,$T42,0) -> 0 | AE42: =IF(AE$8=$R42,-$T42,0)+IF(AE$8=$S42,$T42,0) -> 0 | AF42: =IF(AF$8=$R42,-$T42,0)+IF(AF$8=$S42,$T42,0) -> 0 | AG42: =IF(AG$8=$R42,-$T42,0)+IF(AG$8=$S42,$T42,0) -> 0 | ... AK42: =IF(AK$8=$R42,-$T42,0)+IF(AK$8=$S42,$T42,0) -> 0
C43: MOVIMENTAÇÕES DO MÊS POR GRUPO DE CONTAS | N43: 35 | X43: =IF(P43<NOW(),1,0) -> 1 | Z43: =IF(Z$8=$R43,-$T43,0)+IF(Z$8=$S43,$T43,0) -> 0 | AA43: =IF(AA$8=$R43,-$T43,0)+IF(AA$8=$S43,$T43,0) -> 0 | AB43: =IF(AB$8=$R43,-$T43,0)+IF(AB$8=$S43,$T43,0) -> 0 | AC43: =IF(AC$8=$R43,-$T43,0)+IF(AC$8=$S43,$T43,0) -> 0 | AD43: =IF(AD$8=$R43,-$T43,0)+IF(AD$8=$S43,$T43,0) -> 0 | AE43: =IF(AE$8=$R43,-$T43,0)+IF(AE$8=$S43,$T43,0) -> 0 | AF43: =IF(AF$8=$R43,-$T43,0)+IF(AF$8=$S43,$T43,0) -> 0 | AG43: =IF(AG$8=$R43,-$T43,0)+IF(AG$8=$S43,$T43,0) -> 0 | ... AK43: =IF(AK$8=$R43,-$T43,0)+IF(AK$8=$S43,$T43,0) -> 0
N44: 36 | X44: =IF(P44<NOW(),1,0) -> 1 | Z44: =IF(Z$8=$R44,-$T44,0)+IF(Z$8=$S44,$T44,0) -> 0 | AA44: =IF(AA$8=$R44,-$T44,0)+IF(AA$8=$S44,$T44,0) -> 0 | AB44: =IF(AB$8=$R44,-$T44,0)+IF(AB$8=$S44,$T44,0) -> 0 | AC44: =IF(AC$8=$R44,-$T44,0)+IF(AC$8=$S44,$T44,0) -> 0 | AD44: =IF(AD$8=$R44,-$T44,0)+IF(AD$8=$S44,$T44,0) -> 0 | AE44: =IF(AE$8=$R44,-$T44,0)+IF(AE$8=$S44,$T44,0) -> 0 | AF44: =IF(AF$8=$R44,-$T44,0)+IF(AF$8=$S44,$T44,0) -> 0 | AG44: =IF(AG$8=$R44,-$T44,0)+IF(AG$8=$S44,$T44,0) -> 0 | ... AK44: =IF(AK$8=$R44,-$T44,0)+IF(AK$8=$S44,$T44,0) -> 0
C45: GRUPO | D45: DESCRIÇÃO | E45: TRANSFERÊNCIAS | F45: SAÍDA | G45: SALDO | N45: 37 | X45: =IF(P45<NOW(),1,0) -> 1 | Z45: =IF(Z$8=$R45,-$T45,0)+IF(Z$8=$S45,$T45,0) -> 0 | AA45: =IF(AA$8=$R45,-$T45,0)+IF(AA$8=$S45,$T45,0) -> 0 | AB45: =IF(AB$8=$R45,-$T45,0)+IF(AB$8=$S45,$T45,0) -> 0 | AC45: =IF(AC$8=$R45,-$T45,0)+IF(AC$8=$S45,$T45,0) -> 0 | AD45: =IF(AD$8=$R45,-$T45,0)+IF(AD$8=$S45,$T45,0) -> 0 | AE45: =IF(AE$8=$R45,-$T45,0)+IF(AE$8=$S45,$T45,0) -> 0 | AF45: =IF(AF$8=$R45,-$T45,0)+IF(AF$8=$S45,$T45,0) -> 0 | AG45: =IF(AG$8=$R45,-$T45,0)+IF(AG$8=$S45,$T45,0) -> 0 | ... AK45: =IF(AK$8=$R45,-$T45,0)+IF(AK$8=$S45,$T45,0) -> 0
E46: ENTRADA | F46: SAÍDA | G46: SALDO | N46: 38 | X46: =IF(P46<NOW(),1,0) -> 1 | Z46: =IF(Z$8=$R46,-$T46,0)+IF(Z$8=$S46,$T46,0) -> 0 | AA46: =IF(AA$8=$R46,-$T46,0)+IF(AA$8=$S46,$T46,0) -> 0 | AB46: =IF(AB$8=$R46,-$T46,0)+IF(AB$8=$S46,$T46,0) -> 0 | AC46: =IF(AC$8=$R46,-$T46,0)+IF(AC$8=$S46,$T46,0) -> 0 | AD46: =IF(AD$8=$R46,-$T46,0)+IF(AD$8=$S46,$T46,0) -> 0 | AE46: =IF(AE$8=$R46,-$T46,0)+IF(AE$8=$S46,$T46,0) -> 0 | AF46: =IF(AF$8=$R46,-$T46,0)+IF(AF$8=$S46,$T46,0) -> 0 | AG46: =IF(AG$8=$R46,-$T46,0)+IF(AG$8=$S46,$T46,0) -> 0 | ... AK46: =IF(AK$8=$R46,-$T46,0)+IF(AK$8=$S46,$T46,0) -> 0
A47: 1 | C47: =ANUAL!$C115 -> CC | D47: =ANUAL!$D115 -> CONTA CORRENTE | E47: =SUMIF($J$28:$J$39,TRUE,E$28:E$39) -> 0 | F47: =SUMIF($J$28:$J$39,TRUE,F$28:F$39) -> 0 | G47: =SUMIF($J$28:$J$39,TRUE,G$28:G$39)+SUMIF($J$9:$J$20,TRUE,E$9:E$20) -> 0 | N47: 39 | X47: =IF(P47<NOW(),1,0) -> 1 | Z47: =IF(Z$8=$R47,-$T47,0)+IF(Z$8=$S47,$T47,0) -> 0 | AA47: =IF(AA$8=$R47,-$T47,0)+IF(AA$8=$S47,$T47,0) -> 0 | AB47: =IF(AB$8=$R47,-$T47,0)+IF(AB$8=$S47,$T47,0) -> 0 | AC47: =IF(AC$8=$R47,-$T47,0)+IF(AC$8=$S47,$T47,0) -> 0 | AD47: =IF(AD$8=$R47,-$T47,0)+IF(AD$8=$S47,$T47,0) -> 0 | AE47: =IF(AE$8=$R47,-$T47,0)+IF(AE$8=$S47,$T47,0) -> 0 | AF47: =IF(AF$8=$R47,-$T47,0)+IF(AF$8=$S47,$T47,0) -> 0 | AG47: =IF(AG$8=$R47,-$T47,0)+IF(AG$8=$S47,$T47,0) -> 0 | ... AK47: =IF(AK$8=$R47,-$T47,0)+IF(AK$8=$S47,$T47,0) -> 0
A48: 2 | C48: =ANUAL!$C116 -> INV | D48: =ANUAL!$D116 -> APLICAÇÕES DE INVESTIMENTO | E48: =SUMIF($K$28:$K$39,TRUE,E$28:E$39) -> 0 | F48: =SUMIF($K$28:$K$39,TRUE,F$28:F$39) -> 0 | G48: =SUMIF($K$28:$K$39,TRUE,G$28:G$39)+SUMIF($K$9:$K$20,TRUE,E$9:E$20) -> 0 | N48: 40 | X48: =IF(P48<NOW(),1,0) -> 1 | Z48: =IF(Z$8=$R48,-$T48,0)+IF(Z$8=$S48,$T48,0) -> 0 | AA48: =IF(AA$8=$R48,-$T48,0)+IF(AA$8=$S48,$T48,0) -> 0 | AB48: =IF(AB$8=$R48,-$T48,0)+IF(AB$8=$S48,$T48,0) -> 0 | AC48: =IF(AC$8=$R48,-$T48,0)+IF(AC$8=$S48,$T48,0) -> 0 | AD48: =IF(AD$8=$R48,-$T48,0)+IF(AD$8=$S48,$T48,0) -> 0 | AE48: =IF(AE$8=$R48,-$T48,0)+IF(AE$8=$S48,$T48,0) -> 0 | AF48: =IF(AF$8=$R48,-$T48,0)+IF(AF$8=$S48,$T48,0) -> 0 | AG48: =IF(AG$8=$R48,-$T48,0)+IF(AG$8=$S48,$T48,0) -> 0 | ... AK48: =IF(AK$8=$R48,-$T48,0)+IF(AK$8=$S48,$T48,0) -> 0
A49: 3 | C49: =ANUAL!$C117 -> DINH | D49: =ANUAL!$D117 -> EM ESPÉCIE | E49: =SUMIF($L$28:$L$39,TRUE,E$28:E$39) -> 0 | F49: =SUMIF($L$28:$L$39,TRUE,F$28:F$39) -> 0 | G49: =SUMIF($L$28:$L$39,TRUE,G$28:G$39)+SUMIF($L$9:$L$20,TRUE,E$9:E$20) -> 0 | N49: 41 | X49: =IF(P49<NOW(),1,0) -> 1 | Z49: =IF(Z$8=$R49,-$T49,0)+IF(Z$8=$S49,$T49,0) -> 0 | AA49: =IF(AA$8=$R49,-$T49,0)+IF(AA$8=$S49,$T49,0) -> 0 | AB49: =IF(AB$8=$R49,-$T49,0)+IF(AB$8=$S49,$T49,0) -> 0 | AC49: =IF(AC$8=$R49,-$T49,0)+IF(AC$8=$S49,$T49,0) -> 0 | AD49: =IF(AD$8=$R49,-$T49,0)+IF(AD$8=$S49,$T49,0) -> 0 | AE49: =IF(AE$8=$R49,-$T49,0)+IF(AE$8=$S49,$T49,0) -> 0 | AF49: =IF(AF$8=$R49,-$T49,0)+IF(AF$8=$S49,$T49,0) -> 0 | AG49: =IF(AG$8=$R49,-$T49,0)+IF(AG$8=$S49,$T49,0) -> 0 | ... AK49: =IF(AK$8=$R49,-$T49,0)+IF(AK$8=$S49,$T49,0) -> 0
N50: 42 | X50: =IF(P50<NOW(),1,0) -> 1 | Z50: =IF(Z$8=$R50,-$T50,0)+IF(Z$8=$S50,$T50,0) -> 0 | AA50: =IF(AA$8=$R50,-$T50,0)+IF(AA$8=$S50,$T50,0) -> 0 | AB50: =IF(AB$8=$R50,-$T50,0)+IF(AB$8=$S50,$T50,0) -> 0 | AC50: =IF(AC$8=$R50,-$T50,0)+IF(AC$8=$S50,$T50,0) -> 0 | AD50: =IF(AD$8=$R50,-$T50,0)+IF(AD$8=$S50,$T50,0) -> 0 | AE50: =IF(AE$8=$R50,-$T50,0)+IF(AE$8=$S50,$T50,0) -> 0 | AF50: =IF(AF$8=$R50,-$T50,0)+IF(AF$8=$S50,$T50,0) -> 0 | AG50: =IF(AG$8=$R50,-$T50,0)+IF(AG$8=$S50,$T50,0) -> 0 | ... AK50: =IF(AK$8=$R50,-$T50,0)+IF(AK$8=$S50,$T50,0) -> 0
N51: 43 | X51: =IF(P51<NOW(),1,0) -> 1 | Z51: =IF(Z$8=$R51,-$T51,0)+IF(Z$8=$S51,$T51,0) -> 0 | AA51: =IF(AA$8=$R51,-$T51,0)+IF(AA$8=$S51,$T51,0) -> 0 | AB51: =IF(AB$8=$R51,-$T51,0)+IF(AB$8=$S51,$T51,0) -> 0 | AC51: =IF(AC$8=$R51,-$T51,0)+IF(AC$8=$S51,$T51,0) -> 0 | AD51: =IF(AD$8=$R51,-$T51,0)+IF(AD$8=$S51,$T51,0) -> 0 | AE51: =IF(AE$8=$R51,-$T51,0)+IF(AE$8=$S51,$T51,0) -> 0 | AF51: =IF(AF$8=$R51,-$T51,0)+IF(AF$8=$S51,$T51,0) -> 0 | AG51: =IF(AG$8=$R51,-$T51,0)+IF(AG$8=$S51,$T51,0) -> 0 | ... AK51: =IF(AK$8=$R51,-$T51,0)+IF(AK$8=$S51,$T51,0) -> 0
N52: 44 | X52: =IF(P52<NOW(),1,0) -> 1 | Z52: =IF(Z$8=$R52,-$T52,0)+IF(Z$8=$S52,$T52,0) -> 0 | AA52: =IF(AA$8=$R52,-$T52,0)+IF(AA$8=$S52,$T52,0) -> 0 | AB52: =IF(AB$8=$R52,-$T52,0)+IF(AB$8=$S52,$T52,0) -> 0 | AC52: =IF(AC$8=$R52,-$T52,0)+IF(AC$8=$S52,$T52,0) -> 0 | AD52: =IF(AD$8=$R52,-$T52,0)+IF(AD$8=$S52,$T52,0) -> 0 | AE52: =IF(AE$8=$R52,-$T52,0)+IF(AE$8=$S52,$T52,0) -> 0 | AF52: =IF(AF$8=$R52,-$T52,0)+IF(AF$8=$S52,$T52,0) -> 0 | AG52: =IF(AG$8=$R52,-$T52,0)+IF(AG$8=$S52,$T52,0) -> 0 | ... AK52: =IF(AK$8=$R52,-$T52,0)+IF(AK$8=$S52,$T52,0) -> 0
C53: ACOMPANHAMENTO DE DESPESAS | N53: 45 | X53: =IF(P53<NOW(),1,0) -> 1 | Z53: =IF(Z$8=$R53,-$T53,0)+IF(Z$8=$S53,$T53,0) -> 0 | AA53: =IF(AA$8=$R53,-$T53,0)+IF(AA$8=$S53,$T53,0) -> 0 | AB53: =IF(AB$8=$R53,-$T53,0)+IF(AB$8=$S53,$T53,0) -> 0 | AC53: =IF(AC$8=$R53,-$T53,0)+IF(AC$8=$S53,$T53,0) -> 0 | AD53: =IF(AD$8=$R53,-$T53,0)+IF(AD$8=$S53,$T53,0) -> 0 | AE53: =IF(AE$8=$R53,-$T53,0)+IF(AE$8=$S53,$T53,0) -> 0 | AF53: =IF(AF$8=$R53,-$T53,0)+IF(AF$8=$S53,$T53,0) -> 0 | AG53: =IF(AG$8=$R53,-$T53,0)+IF(AG$8=$S53,$T53,0) -> 0 | ... AK53: =IF(AK$8=$R53,-$T53,0)+IF(AK$8=$S53,$T53,0) -> 0
N54: 46 | X54: =IF(P54<NOW(),1,0) -> 1 | Z54: =IF(Z$8=$R54,-$T54,0)+IF(Z$8=$S54,$T54,0) -> 0 | AA54: =IF(AA$8=$R54,-$T54,0)+IF(AA$8=$S54,$T54,0) -> 0 | AB54: =IF(AB$8=$R54,-$T54,0)+IF(AB$8=$S54,$T54,0) -> 0 | AC54: =IF(AC$8=$R54,-$T54,0)+IF(AC$8=$S54,$T54,0) -> 0 | AD54: =IF(AD$8=$R54,-$T54,0)+IF(AD$8=$S54,$T54,0) -> 0 | AE54: =IF(AE$8=$R54,-$T54,0)+IF(AE$8=$S54,$T54,0) -> 0 | AF54: =IF(AF$8=$R54,-$T54,0)+IF(AF$8=$S54,$T54,0) -> 0 | AG54: =IF(AG$8=$R54,-$T54,0)+IF(AG$8=$S54,$T54,0) -> 0 | ... AK54: =IF(AK$8=$R54,-$T54,0)+IF(AK$8=$S54,$T54,0) -> 0
C55: CODIGO | D55: DESCRIÇÃO | G55: VALOR | N55: 47 | X55: =IF(P55<NOW(),1,0) -> 1 | Z55: =IF(Z$8=$R55,-$T55,0)+IF(Z$8=$S55,$T55,0) -> 0 | AA55: =IF(AA$8=$R55,-$T55,0)+IF(AA$8=$S55,$T55,0) -> 0 | AB55: =IF(AB$8=$R55,-$T55,0)+IF(AB$8=$S55,$T55,0) -> 0 | AC55: =IF(AC$8=$R55,-$T55,0)+IF(AC$8=$S55,$T55,0) -> 0 | AD55: =IF(AD$8=$R55,-$T55,0)+IF(AD$8=$S55,$T55,0) -> 0 | AE55: =IF(AE$8=$R55,-$T55,0)+IF(AE$8=$S55,$T55,0) -> 0 | AF55: =IF(AF$8=$R55,-$T55,0)+IF(AF$8=$S55,$T55,0) -> 0 | AG55: =IF(AG$8=$R55,-$T55,0)+IF(AG$8=$S55,$T55,0) -> 0 | ... AK55: =IF(AK$8=$R55,-$T55,0)+IF(AK$8=$S55,$T55,0) -> 0
N56: 48 | X56: =IF(P56<NOW(),1,0) -> 1 | Z56: =IF(Z$8=$R56,-$T56,0)+IF(Z$8=$S56,$T56,0) -> 0 | AA56: =IF(AA$8=$R56,-$T56,0)+IF(AA$8=$S56,$T56,0) -> 0 | AB56: =IF(AB$8=$R56,-$T56,0)+IF(AB$8=$S56,$T56,0) -> 0 | AC56: =IF(AC$8=$R56,-$T56,0)+IF(AC$8=$S56,$T56,0) -> 0 | AD56: =IF(AD$8=$R56,-$T56,0)+IF(AD$8=$S56,$T56,0) -> 0 | AE56: =IF(AE$8=$R56,-$T56,0)+IF(AE$8=$S56,$T56,0) -> 0 | AF56: =IF(AF$8=$R56,-$T56,0)+IF(AF$8=$S56,$T56,0) -> 0 | AG56: =IF(AG$8=$R56,-$T56,0)+IF(AG$8=$S56,$T56,0) -> 0 | ... AK56: =IF(AK$8=$R56,-$T56,0)+IF(AK$8=$S56,$T56,0) -> 0
A57: 1 | C57: =ANUAL!$C141 -> M01 | D57: =ANUAL!$D141 -> MORADIA – CONDOMÍNIO | G57: =SUMIF(U$9:U$88,ANUAL!C141,T$9:T$88) -> 0 | N57: 49 | X57: =IF(P57<NOW(),1,0) -> 1 | Z57: =IF(Z$8=$R57,-$T57,0)+IF(Z$8=$S57,$T57,0) -> 0 | AA57: =IF(AA$8=$R57,-$T57,0)+IF(AA$8=$S57,$T57,0) -> 0 | AB57: =IF(AB$8=$R57,-$T57,0)+IF(AB$8=$S57,$T57,0) -> 0 | AC57: =IF(AC$8=$R57,-$T57,0)+IF(AC$8=$S57,$T57,0) -> 0 | AD57: =IF(AD$8=$R57,-$T57,0)+IF(AD$8=$S57,$T57,0) -> 0 | AE57: =IF(AE$8=$R57,-$T57,0)+IF(AE$8=$S57,$T57,0) -> 0 | AF57: =IF(AF$8=$R57,-$T57,0)+IF(AF$8=$S57,$T57,0) -> 0 | AG57: =IF(AG$8=$R57,-$T57,0)+IF(AG$8=$S57,$T57,0) -> 0 | ... AK57: =IF(AK$8=$R57,-$T57,0)+IF(AK$8=$S57,$T57,0) -> 0
A58: 2 | C58: =ANUAL!$C142 -> M02 | D58: =ANUAL!$D142 -> MORADIA – IPTU | G58: =SUMIF(U$9:U$88,ANUAL!C142,T$9:T$88) -> 0 | N58: 50 | X58: =IF(P58<NOW(),1,0) -> 1 | Z58: =IF(Z$8=$R58,-$T58,0)+IF(Z$8=$S58,$T58,0) -> 0 | AA58: =IF(AA$8=$R58,-$T58,0)+IF(AA$8=$S58,$T58,0) -> 0 | AB58: =IF(AB$8=$R58,-$T58,0)+IF(AB$8=$S58,$T58,0) -> 0 | AC58: =IF(AC$8=$R58,-$T58,0)+IF(AC$8=$S58,$T58,0) -> 0 | AD58: =IF(AD$8=$R58,-$T58,0)+IF(AD$8=$S58,$T58,0) -> 0 | AE58: =IF(AE$8=$R58,-$T58,0)+IF(AE$8=$S58,$T58,0) -> 0 | AF58: =IF(AF$8=$R58,-$T58,0)+IF(AF$8=$S58,$T58,0) -> 0 | AG58: =IF(AG$8=$R58,-$T58,0)+IF(AG$8=$S58,$T58,0) -> 0 | ... AK58: =IF(AK$8=$R58,-$T58,0)+IF(AK$8=$S58,$T58,0) -> 0
A59: 3 | C59: =ANUAL!$C143 -> M03 | D59: =ANUAL!$D143 -> MORADIA – ALUGUEL | G59: =SUMIF(U$9:U$88,ANUAL!C143,T$9:T$88) -> 0 | N59: 51 | X59: =IF(P59<NOW(),1,0) -> 1 | Z59: =IF(Z$8=$R59,-$T59,0)+IF(Z$8=$S59,$T59,0) -> 0 | AA59: =IF(AA$8=$R59,-$T59,0)+IF(AA$8=$S59,$T59,0) -> 0 | AB59: =IF(AB$8=$R59,-$T59,0)+IF(AB$8=$S59,$T59,0) -> 0 | AC59: =IF(AC$8=$R59,-$T59,0)+IF(AC$8=$S59,$T59,0) -> 0 | AD59: =IF(AD$8=$R59,-$T59,0)+IF(AD$8=$S59,$T59,0) -> 0 | AE59: =IF(AE$8=$R59,-$T59,0)+IF(AE$8=$S59,$T59,0) -> 0 | AF59: =IF(AF$8=$R59,-$T59,0)+IF(AF$8=$S59,$T59,0) -> 0 | AG59: =IF(AG$8=$R59,-$T59,0)+IF(AG$8=$S59,$T59,0) -> 0 | ... AK59: =IF(AK$8=$R59,-$T59,0)+IF(AK$8=$S59,$T59,0) -> 0
A60: 4 | C60: =ANUAL!$C144 -> M04 | D60: =ANUAL!$D144 -> MORADIA – REFORMA | G60: =SUMIF(U$9:U$88,ANUAL!C144,T$9:T$88) -> 0 | N60: 52 | X60: =IF(P60<NOW(),1,0) -> 1 | Z60: =IF(Z$8=$R60,-$T60,0)+IF(Z$8=$S60,$T60,0) -> 0 | AA60: =IF(AA$8=$R60,-$T60,0)+IF(AA$8=$S60,$T60,0) -> 0 | AB60: =IF(AB$8=$R60,-$T60,0)+IF(AB$8=$S60,$T60,0) -> 0 | AC60: =IF(AC$8=$R60,-$T60,0)+IF(AC$8=$S60,$T60,0) -> 0 | AD60: =IF(AD$8=$R60,-$T60,0)+IF(AD$8=$S60,$T60,0) -> 0 | AE60: =IF(AE$8=$R60,-$T60,0)+IF(AE$8=$S60,$T60,0) -> 0 | AF60: =IF(AF$8=$R60,-$T60,0)+IF(AF$8=$S60,$T60,0) -> 0 | AG60: =IF(AG$8=$R60,-$T60,0)+IF(AG$8=$S60,$T60,0) -> 0 | ... AK60: =IF(AK$8=$R60,-$T60,0)+IF(AK$8=$S60,$T60,0) -> 0
A61: 5 | C61: =ANUAL!$C145 -> U01 | D61: =ANUAL!$D145 -> UTILITIES – ENERGIA ELÉTRICA | G61: =SUMIF(U$9:U$88,ANUAL!C145,T$9:T$88) -> 0 | N61: 53 | X61: =IF(P61<NOW(),1,0) -> 1 | Z61: =IF(Z$8=$R61,-$T61,0)+IF(Z$8=$S61,$T61,0) -> 0 | AA61: =IF(AA$8=$R61,-$T61,0)+IF(AA$8=$S61,$T61,0) -> 0 | AB61: =IF(AB$8=$R61,-$T61,0)+IF(AB$8=$S61,$T61,0) -> 0 | AC61: =IF(AC$8=$R61,-$T61,0)+IF(AC$8=$S61,$T61,0) -> 0 | AD61: =IF(AD$8=$R61,-$T61,0)+IF(AD$8=$S61,$T61,0) -> 0 | AE61: =IF(AE$8=$R61,-$T61,0)+IF(AE$8=$S61,$T61,0) -> 0 | AF61: =IF(AF$8=$R61,-$T61,0)+IF(AF$8=$S61,$T61,0) -> 0 | AG61: =IF(AG$8=$R61,-$T61,0)+IF(AG$8=$S61,$T61,0) -> 0 | ... AK61: =IF(AK$8=$R61,-$T61,0)+IF(AK$8=$S61,$T61,0) -> 0
A62: 6 | C62: =ANUAL!$C146 -> U02 | D62: =ANUAL!$D146 -> UTILITIES – ÁGUA POTÁVEL | G62: =SUMIF(U$9:U$88,ANUAL!C146,T$9:T$88) -> 0 | N62: 54 | X62: =IF(P62<NOW(),1,0) -> 1 | Z62: =IF(Z$8=$R62,-$T62,0)+IF(Z$8=$S62,$T62,0) -> 0 | AA62: =IF(AA$8=$R62,-$T62,0)+IF(AA$8=$S62,$T62,0) -> 0 | AB62: =IF(AB$8=$R62,-$T62,0)+IF(AB$8=$S62,$T62,0) -> 0 | AC62: =IF(AC$8=$R62,-$T62,0)+IF(AC$8=$S62,$T62,0) -> 0 | AD62: =IF(AD$8=$R62,-$T62,0)+IF(AD$8=$S62,$T62,0) -> 0 | AE62: =IF(AE$8=$R62,-$T62,0)+IF(AE$8=$S62,$T62,0) -> 0 | AF62: =IF(AF$8=$R62,-$T62,0)+IF(AF$8=$S62,$T62,0) -> 0 | AG62: =IF(AG$8=$R62,-$T62,0)+IF(AG$8=$S62,$T62,0) -> 0 | ... AK62: =IF(AK$8=$R62,-$T62,0)+IF(AK$8=$S62,$T62,0) -> 0
A63: 7 | C63: =ANUAL!$C147 -> U03 | D63: =ANUAL!$D147 -> UTILITIES – DIVERSOS (ÁGUA, GÁS, SERV. GERAIS) | G63: =SUMIF(U$9:U$88,ANUAL!C147,T$9:T$88) -> 0 | N63: 55 | X63: =IF(P63<NOW(),1,0) -> 1 | Z63: =IF(Z$8=$R63,-$T63,0)+IF(Z$8=$S63,$T63,0) -> 0 | AA63: =IF(AA$8=$R63,-$T63,0)+IF(AA$8=$S63,$T63,0) -> 0 | AB63: =IF(AB$8=$R63,-$T63,0)+IF(AB$8=$S63,$T63,0) -> 0 | AC63: =IF(AC$8=$R63,-$T63,0)+IF(AC$8=$S63,$T63,0) -> 0 | AD63: =IF(AD$8=$R63,-$T63,0)+IF(AD$8=$S63,$T63,0) -> 0 | AE63: =IF(AE$8=$R63,-$T63,0)+IF(AE$8=$S63,$T63,0) -> 0 | AF63: =IF(AF$8=$R63,-$T63,0)+IF(AF$8=$S63,$T63,0) -> 0 | AG63: =IF(AG$8=$R63,-$T63,0)+IF(AG$8=$S63,$T63,0) -> 0 | ... AK63: =IF(AK$8=$R63,-$T63,0)+IF(AK$8=$S63,$T63,0) -> 0
A64: 8 | C64: =ANUAL!$C148 -> S01 | D64: =ANUAL!$D148 -> SAÚDE – PLANO DE SAÚDE | G64: =SUMIF(U$9:U$88,ANUAL!C148,T$9:T$88) -> 0 | N64: 56 | X64: =IF(P64<NOW(),1,0) -> 1 | Z64: =IF(Z$8=$R64,-$T64,0)+IF(Z$8=$S64,$T64,0) -> 0 | AA64: =IF(AA$8=$R64,-$T64,0)+IF(AA$8=$S64,$T64,0) -> 0 | AB64: =IF(AB$8=$R64,-$T64,0)+IF(AB$8=$S64,$T64,0) -> 0 | AC64: =IF(AC$8=$R64,-$T64,0)+IF(AC$8=$S64,$T64,0) -> 0 | AD64: =IF(AD$8=$R64,-$T64,0)+IF(AD$8=$S64,$T64,0) -> 0 | AE64: =IF(AE$8=$R64,-$T64,0)+IF(AE$8=$S64,$T64,0) -> 0 | AF64: =IF(AF$8=$R64,-$T64,0)+IF(AF$8=$S64,$T64,0) -> 0 | AG64: =IF(AG$8=$R64,-$T64,0)+IF(AG$8=$S64,$T64,0) -> 0 | ... AK64: =IF(AK$8=$R64,-$T64,0)+IF(AK$8=$S64,$T64,0) -> 0
A65: 9 | C65: =ANUAL!$C149 -> S02 | D65: =ANUAL!$D149 -> SAÚDE – REMÉDIOS | G65: =SUMIF(U$9:U$88,ANUAL!C149,T$9:T$88) -> 0 | N65: 57 | X65: =IF(P65<NOW(),1,0) -> 1 | Z65: =IF(Z$8=$R65,-$T65,0)+IF(Z$8=$S65,$T65,0) -> 0 | AA65: =IF(AA$8=$R65,-$T65,0)+IF(AA$8=$S65,$T65,0) -> 0 | AB65: =IF(AB$8=$R65,-$T65,0)+IF(AB$8=$S65,$T65,0) -> 0 | AC65: =IF(AC$8=$R65,-$T65,0)+IF(AC$8=$S65,$T65,0) -> 0 | AD65: =IF(AD$8=$R65,-$T65,0)+IF(AD$8=$S65,$T65,0) -> 0 | AE65: =IF(AE$8=$R65,-$T65,0)+IF(AE$8=$S65,$T65,0) -> 0 | AF65: =IF(AF$8=$R65,-$T65,0)+IF(AF$8=$S65,$T65,0) -> 0 | AG65: =IF(AG$8=$R65,-$T65,0)+IF(AG$8=$S65,$T65,0) -> 0 | ... AK65: =IF(AK$8=$R65,-$T65,0)+IF(AK$8=$S65,$T65,0) -> 0
A66: 10 | C66: =ANUAL!$C150 -> S03 | D66: =ANUAL!$D150 -> SAÚDE – ACADEMIA | G66: =SUMIF(U$9:U$88,ANUAL!C150,T$9:T$88) -> 0 | N66: 58 | X66: =IF(P66<NOW(),1,0) -> 1 | Z66: =IF(Z$8=$R66,-$T66,0)+IF(Z$8=$S66,$T66,0) -> 0 | AA66: =IF(AA$8=$R66,-$T66,0)+IF(AA$8=$S66,$T66,0) -> 0 | AB66: =IF(AB$8=$R66,-$T66,0)+IF(AB$8=$S66,$T66,0) -> 0 | AC66: =IF(AC$8=$R66,-$T66,0)+IF(AC$8=$S66,$T66,0) -> 0 | AD66: =IF(AD$8=$R66,-$T66,0)+IF(AD$8=$S66,$T66,0) -> 0 | AE66: =IF(AE$8=$R66,-$T66,0)+IF(AE$8=$S66,$T66,0) -> 0 | AF66: =IF(AF$8=$R66,-$T66,0)+IF(AF$8=$S66,$T66,0) -> 0 | AG66: =IF(AG$8=$R66,-$T66,0)+IF(AG$8=$S66,$T66,0) -> 0 | ... AK66: =IF(AK$8=$R66,-$T66,0)+IF(AK$8=$S66,$T66,0) -> 0
A67: 11 | C67: =ANUAL!$C151 -> C01 | D67: =ANUAL!$D151 -> COMPRAS | G67: =SUMIF(U$9:U$88,ANUAL!C151,T$9:T$88) -> 0 | N67: 59 | X67: =IF(P67<NOW(),1,0) -> 1 | Z67: =IF(Z$8=$R67,-$T67,0)+IF(Z$8=$S67,$T67,0) -> 0 | AA67: =IF(AA$8=$R67,-$T67,0)+IF(AA$8=$S67,$T67,0) -> 0 | AB67: =IF(AB$8=$R67,-$T67,0)+IF(AB$8=$S67,$T67,0) -> 0 | AC67: =IF(AC$8=$R67,-$T67,0)+IF(AC$8=$S67,$T67,0) -> 0 | AD67: =IF(AD$8=$R67,-$T67,0)+IF(AD$8=$S67,$T67,0) -> 0 | AE67: =IF(AE$8=$R67,-$T67,0)+IF(AE$8=$S67,$T67,0) -> 0 | AF67: =IF(AF$8=$R67,-$T67,0)+IF(AF$8=$S67,$T67,0) -> 0 | AG67: =IF(AG$8=$R67,-$T67,0)+IF(AG$8=$S67,$T67,0) -> 0 | ... AK67: =IF(AK$8=$R67,-$T67,0)+IF(AK$8=$S67,$T67,0) -> 0
A68: 12 | C68: =ANUAL!$C152 -> L01 | D68: =ANUAL!$D152 -> LAZER | G68: =SUMIF(U$9:U$88,ANUAL!C152,T$9:T$88) -> 0 | N68: 60 | X68: =IF(P68<NOW(),1,0) -> 1 | Z68: =IF(Z$8=$R68,-$T68,0)+IF(Z$8=$S68,$T68,0) -> 0 | AA68: =IF(AA$8=$R68,-$T68,0)+IF(AA$8=$S68,$T68,0) -> 0 | AB68: =IF(AB$8=$R68,-$T68,0)+IF(AB$8=$S68,$T68,0) -> 0 | AC68: =IF(AC$8=$R68,-$T68,0)+IF(AC$8=$S68,$T68,0) -> 0 | AD68: =IF(AD$8=$R68,-$T68,0)+IF(AD$8=$S68,$T68,0) -> 0 | AE68: =IF(AE$8=$R68,-$T68,0)+IF(AE$8=$S68,$T68,0) -> 0 | AF68: =IF(AF$8=$R68,-$T68,0)+IF(AF$8=$S68,$T68,0) -> 0 | AG68: =IF(AG$8=$R68,-$T68,0)+IF(AG$8=$S68,$T68,0) -> 0 | ... AK68: =IF(AK$8=$R68,-$T68,0)+IF(AK$8=$S68,$T68,0) -> 0
... A88: 32 | C88: =ANUAL!$C172 -> --- | D88: =ANUAL!$D172 -> --- | G88: =SUMIF(U$9:U$88,ANUAL!C172,T$9:T$88) -> 0 | N88: 80 | X88: =IF(P88<NOW(),1,0) -> 1 | Z88: =IF(Z$8=$R88,-$T88,0)+IF(Z$8=$S88,$T88,0) -> 0 | AA88: =IF(AA$8=$R88,-$T88,0)+IF(AA$8=$S88,$T88,0) -> 0 | AB88: =IF(AB$8=$R88,-$T88,0)+IF(AB$8=$S88,$T88,0) -> 0 | AC88: =IF(AC$8=$R88,-$T88,0)+IF(AC$8=$S88,$T88,0) -> 0 | AD88: =IF(AD$8=$R88,-$T88,0)+IF(AD$8=$S88,$T88,0) -> 0 | AE88: =IF(AE$8=$R88,-$T88,0)+IF(AE$8=$S88,$T88,0) -> 0 | AF88: =IF(AF$8=$R88,-$T88,0)+IF(AF$8=$S88,$T88,0) -> 0 | AG88: =IF(AG$8=$R88,-$T88,0)+IF(AG$8=$S88,$T88,0) -> 0 | ... AK88: =IF(AK$8=$R88,-$T88,0)+IF(AK$8=$S88,$T88,0) -> 0

Sheet M2
B1: =DATE(ANUAL!B5,B2,8) -> 40217 | I1: >> | M1: << | W1: >> | AL1: <<
B2: ='M1'!B2+1 -> 2
C5: LISTA DE CONTAS | P5: MOVIMENTAÇÕES DO MÊS
C7: CONTA | D7: DESCRIÇÃO | E7: SALDO | P7: DATA | Q7: DESCRIÇÃO | R7: TRANFERÊNCIAS | T7: VALOR | U7: CODIGO
E8: ANTERIOR | F8: ATUAL | G8: PREVISTO | P8: DATA | Q8: DESCRIÇÃO | R8: SAÍDA | S8: ENTRADA | T8: VALOR | X8: ATUAL | Z8: =$C$9 | AA8: =$C$10 -> INV1 | AB8: =$C$11 -> DINH1 | AC8: =$C$12 -> CRED1 | AD8: =$C$13 -> --- | AE8: =$C$14 -> --- | AF8: =$C$15 -> --- | AG8: =$C$16 -> --- | AH8: =$C$17 -> --- | AI8: =$C$18 -> --- | AJ8: =$C$19 -> --- | AK8: =$C$20 -> ---
A9: 1 | C9: =TRIM(ANUAL!C13) | D9: =TRIM(ANUAL!D13) -> CONTA CORRENTE BANCO 1 | E9: =INDIRECT("M"&B$2-1&"!G"&A9+ROW(A$8)) -> 0 | F9: =E9+SUMIF(X$9:X$88,1,OFFSET($Z$9:$Z$88,0,A9-1)) -> 0 | G9: =E9+SUM(OFFSET($Z$9:$Z$88,0,A9-1)) -> 0 | J9: =NOT(ISERR(SEARCH(J$27,$C9))) -> FALSE | K9: =NOT(ISERR(SEARCH(K$27,$C9))) -> FALSE | L9: =NOT(ISERR(SEARCH(L$27,$C9))) -> FALSE | N9: 1 | X9: =IF(P9<NOW(),1,0) -> 1 | Z9: =IF(Z$8=$R9,-$T9,0)+IF(Z$8=$S9,$T9,0) -> 0 | AA9: =IF(AA$8=$R9,-$T9,0)+IF(AA$8=$S9,$T9,0) -> 0 | AB9: =IF(AB$8=$R9,-$T9,0)+IF(AB$8=$S9,$T9,0) -> 0 | AC9: =IF(AC$8=$R9,-$T9,0)+IF(AC$8=$S9,$T9,0) -> 0 | AD9: =IF(AD$8=$R9,-$T9,0)+IF(AD$8=$S9,$T9,0) -> 0 | AE9: =IF(AE$8=$R9,-$T9,0)+IF(AE$8=$S9,$T9,0) -> 0 | AF9: =IF(AF$8=$R9,-$T9,0)+IF(AF$8=$S9,$T9,0) -> 0 | AG9: =IF(AG$8=$R9,-$T9,0)+IF(AG$8=$S9,$T9,0) -> 0 | ... AK9: =IF(AK$8=$R9,-$T9,0)+IF(AK$8=$S9,$T9,0) -> 0
A10: 2 | C10: =TRIM(ANUAL!C14) -> INV1 | D10: =TRIM(ANUAL!D14) -> POUPANÇA BANCO 1 | E10: =INDIRECT("M"&B$2-1&"!G"&A10+ROW(A$8)) -> 0 | F10: =E10+SUMIF(X$9:X$88,1,OFFSET($Z$9:$Z$88,0,A10-1)) -> 0 | G10: =E10+SUM(OFFSET($Z$9:$Z$88,0,A10-1)) -> 0 | J10: =NOT(ISERR(SEARCH(J$27,$C10))) -> FALSE | K10: =NOT(ISERR(SEARCH(K$27,$C10))) -> TRUE | L10: =NOT(ISERR(SEARCH(L$27,$C10))) -> FALSE | N10: 2 | X10: =IF(P10<NOW(),1,0) -> 1 | Z10: =IF(Z$8=$R10,-$T10,0)+IF(Z$8=$S10,$T10,0) -> 0 | AA10: =IF(AA$8=$R10,-$T10,0)+IF(AA$8=$S10,$T10,0) -> 0 | AB10: =IF(AB$8=$R10,-$T10,0)+IF(AB$8=$S10,$T10,0) -> 0 | AC10: =IF(AC$8=$R10,-$T10,0)+IF(AC$8=$S10,$T10,0) -> 0 | AD10: =IF(AD$8=$R10,-$T10,0)+IF(AD$8=$S10,$T10,0) -> 0 | AE10: =IF(AE$8=$R10,-$T10,0)+IF(AE$8=$S10,$T10,0) -> 0 | AF10: =IF(AF$8=$R10,-$T10,0)+IF(AF$8=$S10,$T10,0) -> 0 | AG10: =IF(AG$8=$R10,-$T10,0)+IF(AG$8=$S10,$T10,0) -> 0 | ... AK10: =IF(AK$8=$R10,-$T10,0)+IF(AK$8=$S10,$T10,0) -> 0
A11: 3 | C11: =TRIM(ANUAL!C15) -> DINH1 | D11: =TRIM(ANUAL!D15) -> EM ESPÉCIE | E11: =INDIRECT("M"&B$2-1&"!G"&A11+ROW(A$8)) -> 0 | F11: =E11+SUMIF(X$9:X$88,1,OFFSET($Z$9:$Z$88,0,A11-1)) -> 0 | G11: =E11+SUM(OFFSET($Z$9:$Z$88,0,A11-1)) -> 0 | J11: =NOT(ISERR(SEARCH(J$27,$C11))) -> FALSE | K11: =NOT(ISERR(SEARCH(K$27,$C11))) -> FALSE | L11: =NOT(ISERR(SEARCH(L$27,$C11))) -> TRUE | N11: 3 | X11: =IF(P11<NOW(),1,0) -> 1 | Z11: =IF(Z$8=$R11,-$T11,0)+IF(Z$8=$S11,$T11,0) -> 0 | AA11: =IF(AA$8=$R11,-$T11,0)+IF(AA$8=$S11,$T11,0) -> 0 | AB11: =IF(AB$8=$R11,-$T11,0)+IF(AB$8=$S11,$T11,0) -> 0 | AC11: =IF(AC$8=$R11,-$T11,0)+IF(AC$8=$S11,$T11,0) -> 0 | AD11: =IF(AD$8=$R11,-$T11,0)+IF(AD$8=$S11,$T11,0) -> 0 | AE11: =IF(AE$8=$R11,-$T11,0)+IF(AE$8=$S11,$T11,0) -> 0 | AF11: =IF(AF$8=$R11,-$T11,0)+IF(AF$8=$S11,$T11,0) -> 0 | AG11: =IF(AG$8=$R11,-$T11,0)+IF(AG$8=$S11,$T11,0) -> 0 | ... AK11: =IF(AK$8=$R11,-$T11,0)+IF(AK$8=$S11,$T11,0) -> 0
A12: 4 | C12: =TRIM(ANUAL!C16) -> CRED1 | D12: =TRIM(ANUAL!D16) -> CARTÃO DE CRÉDITO 1 | E12: =INDIRECT("M"&B$2-1&"!G"&A12+ROW(A$8)) -> 0 | F12: =E12+SUMIF(X$9:X$88,1,OFFSET($Z$9:$Z$88,0,A12-1)) -> 0 | G12: =E12+SUM(OFFSET($Z$9:$Z$88,0,A12-1)) -> 0 | J12: =NOT(ISERR(SEARCH(J$27,$C12))) -> FALSE | K12: =NOT(ISERR(SEARCH(K$27,$C12))) -> FALSE | L12: =NOT(ISERR(SEARCH(L$27,$C12))) -> FALSE | N12: 4 | X12: =IF(P12<NOW(),1,0) -> 1 | Z12: =IF(Z$8=$R12,-$T12,0)+IF(Z$8=$S12,$T12,0) -> 0 | AA12: =IF(AA$8=$R12,-$T12,0)+IF(AA$8=$S12,$T12,0) -> 0 | AB12: =IF(AB$8=$R12,-$T12,0)+IF(AB$8=$S12,$T12,0) -> 0 | AC12: =IF(AC$8=$R12,-$T12,0)+IF(AC$8=$S12,$T12,0) -> 0 | AD12: =IF(AD$8=$R12,-$T12,0)+IF(AD$8=$S12,$T12,0) -> 0 | AE12: =IF(AE$8=$R12,-$T12,0)+IF(AE$8=$S12,$T12,0) -> 0 | AF12: =IF(AF$8=$R12,-$T12,0)+IF(AF$8=$S12,$T12,0) -> 0 | AG12: =IF(AG$8=$R12,-$T12,0)+IF(AG$8=$S12,$T12,0) -> 0 | ... AK12: =IF(AK$8=$R12,-$T12,0)+IF(AK$8=$S12,$T12,0) -> 0
A13: 5 | C13: =TRIM(ANUAL!C17) -> --- | D13: =TRIM(ANUAL!D17) | E13: =INDIRECT("M"&B$2-1&"!G"&A13+ROW(A$8)) -> 0 | F13: =E13+SUMIF(X$9:X$88,1,OFFSET($Z$9:$Z$88,0,A13-1)) -> 0 | G13: =E13+SUM(OFFSET($Z$9:$Z$88,0,A13-1)) -> 0 | J13: =NOT(ISERR(SEARCH(J$27,$C13))) -> FALSE | K13: =NOT(ISERR(SEARCH(K$27,$C13))) -> FALSE | L13: =NOT(ISERR(SEARCH(L$27,$C13))) -> FALSE | N13: 5 | X13: =IF(P13<NOW(),1,0) -> 1 | Z13: =IF(Z$8=$R13,-$T13,0)+IF(Z$8=$S13,$T13,0) -> 0 | AA13: =IF(AA$8=$R13,-$T13,0)+IF(AA$8=$S13,$T13,0) -> 0 | AB13: =IF(AB$8=$R13,-$T13,0)+IF(AB$8=$S13,$T13,0) -> 0 | AC13: =IF(AC$8=$R13,-$T13,0)+IF(AC$8=$S13,$T13,0) -> 0 | AD13: =IF(AD$8=$R13,-$T13,0)+IF(AD$8=$S13,$T13,0) -> 0 | AE13: =IF(AE$8=$R13,-$T13,0)+IF(AE$8=$S13,$T13,0) -> 0 | AF13: =IF(AF$8=$R13,-$T13,0)+IF(AF$8=$S13,$T13,0) -> 0 | AG13: =IF(AG$8=$R13,-$T13,0)+IF(AG$8=$S13,$T13,0) -> 0 | ... AK13: =IF(AK$8=$R13,-$T13,0)+IF(AK$8=$S13,$T13,0) -> 0
A14: 6 | C14: =TRIM(ANUAL!C18) -> --- | D14: =TRIM(ANUAL!D18) | E14: =INDIRECT("M"&B$2-1&"!G"&A14+ROW(A$8)) -> 0 | F14: =E14+SUMIF(X$9:X$88,1,OFFSET($Z$9:$Z$88,0,A14-1)) -> 0 | G14: =E14+SUM(OFFSET($Z$9:$Z$88,0,A14-1)) -> 0 | J14: =NOT(ISERR(SEARCH(J$27,$C14))) -> FALSE | K14: =NOT(ISERR(SEARCH(K$27,$C14))) -> FALSE | L14: =NOT(ISERR(SEARCH(L$27,$C14))) -> FALSE | N14: 6 | X14: =IF(P14<NOW(),1,0) -> 1 | Z14: =IF(Z$8=$R14,-$T14,0)+IF(Z$8=$S14,$T14,0) -> 0 | AA14: =IF(AA$8=$R14,-$T14,0)+IF(AA$8=$S14,$T14,0) -> 0 | AB14: =IF(AB$8=$R14,-$T14,0)+IF(AB$8=$S14,$T14,0) -> 0 | AC14: =IF(AC$8=$R14,-$T14,0)+IF(AC$8=$S14,$T14,0) -> 0 | AD14: =IF(AD$8=$R14,-$T14,0)+IF(AD$8=$S14,$T14,0) -> 0 | AE14: =IF(AE$8=$R14,-$T14,0)+IF(AE$8=$S14,$T14,0) -> 0 | AF14: =IF(AF$8=$R14,-$T14,0)+IF(AF$8=$S14,$T14,0) -> 0 | AG14: =IF(AG$8=$R14,-$T14,0)+IF(AG$8=$S14,$T14,0) -> 0 | ... AK14: =IF(AK$8=$R14,-$T14,0)+IF(AK$8=$S14,$T14,0) -> 0
A15: 7 | C15: =TRIM(ANUAL!C19) -> --- | D15: =TRIM(ANUAL!D19) | E15: =INDIRECT("M"&B$2-1&"!G"&A15+ROW(A$8)) -> 0 | F15: =E15+SUMIF(X$9:X$88,1,OFFSET($Z$9:$Z$88,0,A15-1)) -> 0 | G15: =E15+SUM(OFFSET($Z$9:$Z$88,0,A15-1)) -> 0 | J15: =NOT(ISERR(SEARCH(J$27,$C15))) -> FALSE | K15: =NOT(ISERR(SEARCH(K$27,$C15))) -> FALSE | L15: =NOT(ISERR(SEARCH(L$27,$C15))) -> FALSE | N15: 7 | X15: =IF(P15<NOW(),1,0) -> 1 | Z15: =IF(Z$8=$R15,-$T15,0)+IF(Z$8=$S15,$T15,0) -> 0 | AA15: =IF(AA$8=$R15,-$T15,0)+IF(AA$8=$S15,$T15,0) -> 0 | AB15: =IF(AB$8=$R15,-$T15,0)+IF(AB$8=$S15,$T15,0) -> 0 | AC15: =IF(AC$8=$R15,-$T15,0)+IF(AC$8=$S15,$T15,0) -> 0 | AD15: =IF(AD$8=$R15,-$T15,0)+IF(AD$8=$S15,$T15,0) -> 0 | AE15: =IF(AE$8=$R15,-$T15,0)+IF(AE$8=$S15,$T15,0) -> 0 | AF15: =IF(AF$8=$R15,-$T15,0)+IF(AF$8=$S15,$T15,0) -> 0 | AG15: =IF(AG$8=$R15,-$T15,0)+IF(AG$8=$S15,$T15,0) -> 0 | ... AK15: =IF(AK$8=$R15,-$T15,0)+IF(AK$8=$S15,$T15,0) -> 0
A16: 8 | C16: =TRIM(ANUAL!C20) -> --- | D16: =TRIM(ANUAL!D20) | E16: =INDIRECT("M"&B$2-1&"!G"&A16+ROW(A$8)) -> 0 | F16: =E16+SUMIF(X$9:X$88,1,OFFSET($Z$9:$Z$88,0,A16-1)) -> 0 | G16: =E16+SUM(OFFSET($Z$9:$Z$88,0,A16-1)) -> 0 | J16: =NOT(ISERR(SEARCH(J$27,$C16))) -> FALSE | K16: =NOT(ISERR(SEARCH(K$27,$C16))) -> FALSE | L16: =NOT(ISERR(SEARCH(L$27,$C16))) -> FALSE | N16: 8 | X16: =IF(P16<NOW(),1,0) -> 1 | Z16: =IF(Z$8=$R16,-$T16,0)+IF(Z$8=$S16,$T16,0) -> 0 | AA16: =IF(AA$8=$R16,-$T16,0)+IF(AA$8=$S16,$T16,0) -> 0 | AB16: =IF(AB$8=$R16,-$T16,0)+IF(AB$8=$S16,$T16,0) -> 0 | AC16: =IF(AC$8=$R16,-$T16,0)+IF(AC$8=$S16,$T16,0) -> 0 | AD16: =IF(AD$8=$R16,-$T16,0)+IF(AD$8=$S16,$T16,0) -> 0 | AE16: =IF(AE$8=$R16,-$T16,0)+IF(AE$8=$S16,$T16,0) -> 0 | AF16: =IF(AF$8=$R16,-$T16,0)+IF(AF$8=$S16,$T16,0) -> 0 | AG16: =IF(AG$8=$R16,-$T16,0)+IF(AG$8=$S16,$T16,0) -> 0 | ... AK16: =IF(AK$8=$R16,-$T16,0)+IF(AK$8=$S16,$T16,0) -> 0
A17: 9 | C17: =TRIM(ANUAL!C21) -> --- | D17: =TRIM(ANUAL!D21) | E17: =INDIRECT("M"&B$2-1&"!G"&A17+ROW(A$8)) -> 0 | F17: =E17+SUMIF(X$9:X$88,1,OFFSET($Z$9:$Z$88,0,A17-1)) -> 0 | G17: =E17+SUM(OFFSET($Z$9:$Z$88,0,A17-1)) -> 0 | J17: =NOT(ISERR(SEARCH(J$27,$C17))) -> FALSE | K17: =NOT(ISERR(SEARCH(K$27,$C17))) -> FALSE | L17: =NOT(ISERR(SEARCH(L$27,$C17))) -> FALSE | N17: 9 | X17: =IF(P17<NOW(),1,0) -> 1 | Z17: =IF(Z$8=$R17,-$T17,0)+IF(Z$8=$S17,$T17,0) -> 0 | AA17: =IF(AA$8=$R17,-$T17,0)+IF(AA$8=$S17,$T17,0) -> 0 | AB17: =IF(AB$8=$R17,-$T17,0)+IF(AB$8=$S17,$T17,0) -> 0 | AC17: =IF(AC$8=$R17,-$T17,0)+IF(AC$8=$S17,$T17,0) -> 0 | AD17: =IF(AD$8=$R17,-$T17,0)+IF(AD$8=$S17,$T17,0) -> 0 | AE17: =IF(AE$8=$R17,-$T17,0)+IF(AE$8=$S17,$T17,0) -> 0 | AF17: =IF(AF$8=$R17,-$T17,0)+IF(AF$8=$S17,$T17,0) -> 0 | AG17: =IF(AG$8=$R17,-$T17,0)+IF(AG$8=$S17,$T17,0) -> 0 | ... AK17: =IF(AK$8=$R17,-$T17,0)+IF(AK$8=$S17,$T17,0) -> 0
A18: 10 | C18: =TRIM(ANUAL!C22) -> --- | D18: =TRIM(ANUAL!D22) | E18: =INDIRECT("M"&B$2-1&"!G"&A18+ROW(A$8)) -> 0 | F18: =E18+SUMIF(X$9:X$88,1,OFFSET($Z$9:$Z$88,0,A18-1)) -> 0 | G18: =E18+SUM(OFFSET($Z$9:$Z$88,0,A18-1)) -> 0 | J18: =NOT(ISERR(SEARCH(J$27,$C18))) -> FALSE | K18: =NOT(ISERR(SEARCH(K$27,$C18))) -> FALSE | L18: =NOT(ISERR(SEARCH(L$27,$C18))) -> FALSE | N18: 10 | X18: =IF(P18<NOW(),1,0) -> 1 | Z18: =IF(Z$8=$R18,-$T18,0)+IF(Z$8=$S18,$T18,0) -> 0 | AA18: =IF(AA$8=$R18,-$T18,0)+IF(AA$8=$S18,$T18,0) -> 0 | AB18: =IF(AB$8=$R18,-$T18,0)+IF(AB$8=$S18,$T18,0) -> 0 | AC18: =IF(AC$8=$R18,-$T18,0)+IF(AC$8=$S18,$T18,0) -> 0 | AD18: =IF(AD$8=$R18,-$T18,0)+IF(AD$8=$S18,$T18,0) -> 0 | AE18: =IF(AE$8=$R18,-$T18,0)+IF(AE$8=$S18,$T18,0) -> 0 | AF18: =IF(AF$8=$R18,-$T18,0)+IF(AF$8=$S18,$T18,0) -> 0 | AG18: =IF(AG$8=$R18,-$T18,0)+IF(AG$8=$S18,$T18,0) -> 0 | ... AK18: =IF(AK$8=$R18,-$T18,0)+IF(AK$8=$S18,$T18,0) -> 0
A19: 11 | C19: =TRIM(ANUAL!C23) -> --- | D19: =TRIM(ANUAL!D23) | E19: =INDIRECT("M"&B$2-1&"!G"&A19+ROW(A$8)) -> 0 | F19: =E19+SUMIF(X$9:X$88,1,OFFSET($Z$9:$Z$88,0,A19-1)) -> 0 | G19: =E19+SUM(OFFSET($Z$9:$Z$88,0,A19-1)) -> 0 | J19: =NOT(ISERR(SEARCH(J$27,$C19))) -> FALSE | K19: =NOT(ISERR(SEARCH(K$27,$C19))) -> FALSE | L19: =NOT(ISERR(SEARCH(L$27,$C19))) -> FALSE | N19: 11 | X19: =IF(P19<NOW(),1,0) -> 1 | Z19: =IF(Z$8=$R19,-$T19,0)+IF(Z$8=$S19,$T19,0) -> 0 | AA19: =IF(AA$8=$R19,-$T19,0)+IF(AA$8=$S19,$T19,0) -> 0 | AB19: =IF(AB$8=$R19,-$T19,0)+IF(AB$8=$S19,$T19,0) -> 0 | AC19: =IF(AC$8=$R19,-$T19,0)+IF(AC$8=$S19,$T19,0) -> 0 | AD19: =IF(AD$8=$R19,-$T19,0)+IF(AD$8=$S19,$T19,0) -> 0 | AE19: =IF(AE$8=$R19,-$T19,0)+IF(AE$8=$S19,$T19,0) -> 0 | AF19: =IF(AF$8=$R19,-$T19,0)+IF(AF$8=$S19,$T19,0) -> 0 | AG19: =IF(AG$8=$R19,-$T19,0)+IF(AG$8=$S19,$T19,0) -> 0 | ... AK19: =IF(AK$8=$R19,-$T19,0)+IF(AK$8=$S19,$T19,0) -> 0
A20: 12 | C20: =TRIM(ANUAL!C24) -> --- | D20: =TRIM(ANUAL!D24) | E20: =INDIRECT("M"&B$2-1&"!G"&A20+ROW(A$8)) -> 0 | F20: =E20+SUMIF(X$9:X$88,1,OFFSET($Z$9:$Z$88,0,A20-1)) -> 0 | G20: =E20+SUM(OFFSET($Z$9:$Z$88,0,A20-1)) -> 0 | J20: =NOT(ISERR(SEARCH(J$27,$C20))) -> FALSE | K20: =NOT(ISERR(SEARCH(K$27,$C20))) -> FALSE | L20: =NOT(ISERR(SEARCH(L$27,$C20))) -> FALSE | N20: 12 | X20: =IF(P20<NOW(),1,0) -> 1 | Z20: =IF(Z$8=$R20,-$T20,0)+IF(Z$8=$S20,$T20,0) -> 0 | AA20: =IF(AA$8=$R20,-$T20,0)+IF(AA$8=$S20,$T20,0) -> 0 | AB20: =IF(AB$8=$R20,-$T20,0)+IF(AB$8=$S20,$T20,0) -> 0 | AC20: =IF(AC$8=$R20,-$T20,0)+IF(AC$8=$S20,$T20,0) -> 0 | AD20: =IF(AD$8=$R20,-$T20,0)+IF(AD$8=$S20,$T20,0) -> 0 | AE20: =IF(AE$8=$R20,-$T20,0)+IF(AE$8=$S20,$T20,0) -> 0 | AF20: =IF(AF$8=$R20,-$T20,0)+IF(AF$8=$S20,$T20,0) -> 0 | AG20: =IF(AG$8=$R20,-$T20,0)+IF(AG$8=$S20,$T20,0) -> 0 | ... AK20: =IF(AK$8=$R20,-$T20,0)+IF(AK$8=$S20,$T20,0) -> 0
N21: 13 | X21: =IF(P21<NOW(),1,0) -> 1 | Z21: =IF(Z$8=$R21,-$T21,0)+IF(Z$8=$S21,$T21,0) -> 0 | AA21: =IF(AA$8=$R21,-$T21,0)+IF(AA$8=$S21,$T21,0) -> 0 | AB21: =IF(AB$8=$R21,-$T21,0)+IF(AB$8=$S21,$T21,0) -> 0 | AC21: =IF(AC$8=$R21,-$T21,0)+IF(AC$8=$S21,$T21,0) -> 0 | AD21: =IF(AD$8=$R21,-$T21,0)+IF(AD$8=$S21,$T21,0) -> 0 | AE21: =IF(AE$8=$R21,-$T21,0)+IF(AE$8=$S21,$T21,0) -> 0 | AF21: =IF(AF$8=$R21,-$T21,0)+IF(AF$8=$S21,$T21,0) -> 0 | AG21: =IF(AG$8=$R21,-$T21,0)+IF(AG$8=$S21,$T21,0) -> 0 | ... AK21: =IF(AK$8=$R21,-$T21,0)+IF(AK$8=$S21,$T21,0) -> 0
N22: 14 | X22: =IF(P22<NOW(),1,0) -> 1 | Z22: =IF(Z$8=$R22,-$T22,0)+IF(Z$8=$S22,$T22,0) -> 0 | AA22: =IF(AA$8=$R22,-$T22,0)+IF(AA$8=$S22,$T22,0) -> 0 | AB22: =IF(AB$8=$R22,-$T22,0)+IF(AB$8=$S22,$T22,0) -> 0 | AC22: =IF(AC$8=$R22,-$T22,0)+IF(AC$8=$S22,$T22,0) -> 0 | AD22: =IF(AD$8=$R22,-$T22,0)+IF(AD$8=$S22,$T22,0) -> 0 | AE22: =IF(AE$8=$R22,-$T22,0)+IF(AE$8=$S22,$T22,0) -> 0 | AF22: =IF(AF$8=$R22,-$T22,0)+IF(AF$8=$S22,$T22,0) -> 0 | AG22: =IF(AG$8=$R22,-$T22,0)+IF(AG$8=$S22,$T22,0) -> 0 | ... AK22: =IF(AK$8=$R22,-$T22,0)+IF(AK$8=$S22,$T22,0) -> 0
N23: 15 | X23: =IF(P23<NOW(),1,0) -> 1 | Z23: =IF(Z$8=$R23,-$T23,0)+IF(Z$8=$S23,$T23,0) -> 0 | AA23: =IF(AA$8=$R23,-$T23,0)+IF(AA$8=$S23,$T23,0) -> 0 | AB23: =IF(AB$8=$R23,-$T23,0)+IF(AB$8=$S23,$T23,0) -> 0 | AC23: =IF(AC$8=$R23,-$T23,0)+IF(AC$8=$S23,$T23,0) -> 0 | AD23: =IF(AD$8=$R23,-$T23,0)+IF(AD$8=$S23,$T23,0) -> 0 | AE23: =IF(AE$8=$R23,-$T23,0)+IF(AE$8=$S23,$T23,0) -> 0 | AF23: =IF(AF$8=$R23,-$T23,0)+IF(AF$8=$S23,$T23,0) -> 0 | AG23: =IF(AG$8=$R23,-$T23,0)+IF(AG$8=$S23,$T23,0) -> 0 | ... AK23: =IF(AK$8=$R23,-$T23,0)+IF(AK$8=$S23,$T23,0) -> 0
C24: VARIAÇÃO MENSAL POR CONTA | N24: 16 | X24: =IF(P24<NOW(),1,0) -> 1 | Z24: =IF(Z$8=$R24,-$T24,0)+IF(Z$8=$S24,$T24,0) -> 0 | AA24: =IF(AA$8=$R24,-$T24,0)+IF(AA$8=$S24,$T24,0) -> 0 | AB24: =IF(AB$8=$R24,-$T24,0)+IF(AB$8=$S24,$T24,0) -> 0 | AC24: =IF(AC$8=$R24,-$T24,0)+IF(AC$8=$S24,$T24,0) -> 0 | AD24: =IF(AD$8=$R24,-$T24,0)+IF(AD$8=$S24,$T24,0) -> 0 | AE24: =IF(AE$8=$R24,-$T24,0)+IF(AE$8=$S24,$T24,0) -> 0 | AF24: =IF(AF$8=$R24,-$T24,0)+IF(AF$8=$S24,$T24,0) -> 0 | AG24: =IF(AG$8=$R24,-$T24,0)+IF(AG$8=$S24,$T24,0) -> 0 | ... AK24: =IF(AK$8=$R24,-$T24,0)+IF(AK$8=$S24,$T24,0) -> 0
N25: 17 | X25: =IF(P25<NOW(),1,0) -> 1 | Z25: =IF(Z$8=$R25,-$T25,0)+IF(Z$8=$S25,$T25,0) -> 0 | AA25: =IF(AA$8=$R25,-$T25,0)+IF(AA$8=$S25,$T25,0) -> 0 | AB25: =IF(AB$8=$R25,-$T25,0)+IF(AB$8=$S25,$T25,0) -> 0 | AC25: =IF(AC$8=$R25,-$T25,0)+IF(AC$8=$S25,$T25,0) -> 0 | AD25: =IF(AD$8=$R25,-$T25,0)+IF(AD$8=$S25,$T25,0) -> 0 | AE25: =IF(AE$8=$R25,-$T25,0)+IF(AE$8=$S25,$T25,0) -> 0 | AF25: =IF(AF$8=$R25,-$T25,0)+IF(AF$8=$S25,$T25,0) -> 0 | AG25: =IF(AG$8=$R25,-$T25,0)+IF(AG$8=$S25,$T25,0) -> 0 | ... AK25: =IF(AK$8=$R25,-$T25,0)+IF(AK$8=$S25,$T25,0) -> 0
C26: CONTA | D26: DESCRIÇÃO | E26: TRANSFERÊNCIAS | F26: SAÍDA | G26: SALDO | N26: 18 | X26: =IF(P26<NOW(),1,0) -> 1 | Z26: =IF(Z$8=$R26,-$T26,0)+IF(Z$8=$S26,$T26,0) -> 0 | AA26: =IF(AA$8=$R26,-$T26,0)+IF(AA$8=$S26,$T26,0) -> 0 | AB26: =IF(AB$8=$R26,-$T26,0)+IF(AB$8=$S26,$T26,0) -> 0 | AC26: =IF(AC$8=$R26,-$T26,0)+IF(AC$8=$S26,$T26,0) -> 0 | AD26: =IF(AD$8=$R26,-$T26,0)+IF(AD$8=$S26,$T26,0) -> 0 | AE26: =IF(AE$8=$R26,-$T26,0)+IF(AE$8=$S26,$T26,0) -> 0 | AF26: =IF(AF$8=$R26,-$T26,0)+IF(AF$8=$S26,$T26,0) -> 0 | AG26: =IF(AG$8=$R26,-$T26,0)+IF(AG$8=$S26,$T26,0) -> 0 | ... AK26: =IF(AK$8=$R26,-$T26,0)+IF(AK$8=$S26,$T26,0) -> 0
E27: ENTRADA | F27: SAÍDA | G27: VARIAÇÃO | J27: =ANUAL!C115 -> CC | K27: =ANUAL!C116 -> INV | L27: =ANUAL!C117 -> DINH | N27: 19 | X27: =IF(P27<NOW(),1,0) -> 1 | Z27: =IF(Z$8=$R27,-$T27,0)+IF(Z$8=$S27,$T27,0) -> 0 | AA27: =IF(AA$8=$R27,-$T27,0)+IF(AA$8=$S27,$T27,0) -> 0 | AB27: =IF(AB$8=$R27,-$T27,0)+IF(AB$8=$S27,$T27,0) -> 0 | AC27: =IF(AC$8=$R27,-$T27,0)+IF(AC$8=$S27,$T27,0) -> 0 | AD27: =IF(AD$8=$R27,-$T27,0)+IF(AD$8=$S27,$T27,0) -> 0 | AE27: =IF(AE$8=$R27,-$T27,0)+IF(AE$8=$S27,$T27,0) -> 0 | AF27: =IF(AF$8=$R27,-$T27,0)+IF(AF$8=$S27,$T27,0) -> 0 | AG27: =IF(AG$8=$R27,-$T27,0)+IF(AG$8=$S27,$T27,0) -> 0 | ... AK27: =IF(AK$8=$R27,-$T27,0)+IF(AK$8=$S27,$T27,0) -> 0
A28: 1 | C28: =C9 | D28: =D9 -> CONTA CORRENTE BANCO 1 | E28: =SUMIF(OFFSET($Z$9:$Z$88,0,A28-1),">0") -> 0 | F28: =SUMIF(OFFSET($Z$9:$Z$88,0,A28-1),"<0") -> 0 | G28: =SUM(E28:F28) -> 0 | J28: =NOT(ISERR(SEARCH(J$27,$C28))) -> FALSE | K28: =NOT(ISERR(SEARCH(K$27,$C28))) -> FALSE | L28: =NOT(ISERR(SEARCH(L$27,$C28))) -> FALSE | N28: 20 | X28: =IF(P28<NOW(),1,0) -> 1 | Z28: =IF(Z$8=$R28,-$T28,0)+IF(Z$8=$S28,$T28,0) -> 0 | AA28: =IF(AA$8=$R28,-$T28,0)+IF(AA$8=$S28,$T28,0) -> 0 | AB28: =IF(AB$8=$R28,-$T28,0)+IF(AB$8=$S28,$T28,0) -> 0 | AC28: =IF(AC$8=$R28,-$T28,0)+IF(AC$8=$S28,$T28,0) -> 0 | AD28: =IF(AD$8=$R28,-$T28,0)+IF(AD$8=$S28,$T28,0) -> 0 | AE28: =IF(AE$8=$R28,-$T28,0)+IF(AE$8=$S28,$T28,0) -> 0 | AF28: =IF(AF$8=$R28,-$T28,0)+IF(AF$8=$S28,$T28,0) -> 0 | AG28: =IF(AG$8=$R28,-$T28,0)+IF(AG$8=$S28,$T28,0) -> 0 | ... AK28: =IF(AK$8=$R28,-$T28,0)+IF(AK$8=$S28,$T28,0) -> 0
A29: 2 | C29: =C10 -> INV1 | D29: =D10 -> POUPANÇA BANCO 1 | E29: =SUMIF(OFFSET($Z$9:$Z$88,0,A29-1),">0") -> 0 | F29: =SUMIF(OFFSET($Z$9:$Z$88,0,A29-1),"<0") -> 0 | G29: =SUM(E29:F29) -> 0 | J29: =NOT(ISERR(SEARCH(J$27,$C29))) -> FALSE | K29: =NOT(ISERR(SEARCH(K$27,$C29))) -> TRUE | L29: =NOT(ISERR(SEARCH(L$27,$C29))) -> FALSE | N29: 21 | X29: =IF(P29<NOW(),1,0) -> 1 | Z29: =IF(Z$8=$R29,-$T29,0)+IF(Z$8=$S29,$T29,0) -> 0 | AA29: =IF(AA$8=$R29,-$T29,0)+IF(AA$8=$S29,$T29,0) -> 0 | AB29: =IF(AB$8=$R29,-$T29,0)+IF(AB$8=$S29,$T29,0) -> 0 | AC29: =IF(AC$8=$R29,-$T29,0)+IF(AC$8=$S29,$T29,0) -> 0 | AD29: =IF(AD$8=$R29,-$T29,0)+IF(AD$8=$S29,$T29,0) -> 0 | AE29: =IF(AE$8=$R29,-$T29,0)+IF(AE$8=$S29,$T29,0) -> 0 | AF29: =IF(AF$8=$R29,-$T29,0)+IF(AF$8=$S29,$T29,0) -> 0 | AG29: =IF(AG$8=$R29,-$T29,0)+IF(AG$8=$S29,$T29,0) -> 0 | ... AK29: =IF(AK$8=$R29,-$T29,0)+IF(AK$8=$S29,$T29,0) -> 0
A30: 3 | C30: =C11 -> DINH1 | D30: =D11 -> EM ESPÉCIE | E30: =SUMIF(OFFSET($Z$9:$Z$88,0,A30-1),">0") -> 0 | F30: =SUMIF(OFFSET($Z$9:$Z$88,0,A30-1),"<0") -> 0 | G30: =SUM(E30:F30) -> 0 | J30: =NOT(ISERR(SEARCH(J$27,$C30))) -> FALSE | K30: =NOT(ISERR(SEARCH(K$27,$C30))) -> FALSE | L30: =NOT(ISERR(SEARCH(L$27,$C30))) -> TRUE | N30: 22 | X30: =IF(P30<NOW(),1,0) -> 1 | Z30: =IF(Z$8=$R30,-$T30,0)+IF(Z$8=$S30,$T30,0) -> 0 | AA30: =IF(AA$8=$R30,-$T30,0)+IF(AA$8=$S30,$T30,0) -> 0 | AB30: =IF(AB$8=$R30,-$T30,0)+IF(AB$8=$S30,$T30,0) -> 0 | AC30: =IF(AC$8=$R30,-$T30,0)+IF(AC$8=$S30,$T30,0) -> 0 | AD30: =IF(AD$8=$R30,-$T30,0)+IF(AD$8=$S30,$T30,0) -> 0 | AE30: =IF(AE$8=$R30,-$T30,0)+IF(AE$8=$S30,$T30,0) -> 0 | AF30: =IF(AF$8=$R30,-$T30,0)+IF(AF$8=$S30,$T30,0) -> 0 | AG30: =IF(AG$8=$R30,-$T30,0)+IF(AG$8=$S30,$T30,0) -> 0 | ... AK30: =IF(AK$8=$R30,-$T30,0)+IF(AK$8=$S30,$T30,0) -> 0
A31: 4 | C31: =C12 -> CRED1 | D31: =D12 -> CARTÃO DE CRÉDITO 1 | E31: =SUMIF(OFFSET($Z$9:$Z$88,0,A31-1),">0") -> 0 | F31: =SUMIF(OFFSET($Z$9:$Z$88,0,A31-1),"<0") -> 0 | G31: =SUM(E31:F31) -> 0 | J31: =NOT(ISERR(SEARCH(J$27,$C31))) -> FALSE | K31: =NOT(ISERR(SEARCH(K$27,$C31))) -> FALSE | L31: =NOT(ISERR(SEARCH(L$27,$C31))) -> FALSE | N31: 23 | X31: =IF(P31<NOW(),1,0) -> 1 | Z31: =IF(Z$8=$R31,-$T31,0)+IF(Z$8=$S31,$T31,0) -> 0 | AA31: =IF(AA$8=$R31,-$T31,0)+IF(AA$8=$S31,$T31,0) -> 0 | AB31: =IF(AB$8=$R31,-$T31,0)+IF(AB$8=$S31,$T31,0) -> 0 | AC31: =IF(AC$8=$R31,-$T31,0)+IF(AC$8=$S31,$T31,0) -> 0 | AD31: =IF(AD$8=$R31,-$T31,0)+IF(AD$8=$S31,$T31,0) -> 0 | AE31: =IF(AE$8=$R31,-$T31,0)+IF(AE$8=$S31,$T31,0) -> 0 | AF31: =IF(AF$8=$R31,-$T31,0)+IF(AF$8=$S31,$T31,0) -> 0 | AG31: =IF(AG$8=$R31,-$T31,0)+IF(AG$8=$S31,$T31,0) -> 0 | ... AK31: =IF(AK$8=$R31,-$T31,0)+IF(AK$8=$S31,$T31,0) -> 0
A32: 5 | C32: =C13 -> --- | D32: =D13 | E32: =SUMIF(OFFSET($Z$9:$Z$88,0,A32-1),">0") -> 0 | F32: =SUMIF(OFFSET($Z$9:$Z$88,0,A32-1),"<0") -> 0 | G32: =SUM(E32:F32) -> 0 | J32: =NOT(ISERR(SEARCH(J$27,$C32))) -> FALSE | K32: =NOT(ISERR(SEARCH(K$27,$C32))) -> FALSE | L32: =NOT(ISERR(SEARCH(L$27,$C32))) -> FALSE | N32: 24 | X32: =IF(P32<NOW(),1,0) -> 1 | Z32: =IF(Z$8=$R32,-$T32,0)+IF(Z$8=$S32,$T32,0) -> 0 | AA32: =IF(AA$8=$R32,-$T32,0)+IF(AA$8=$S32,$T32,0) -> 0 | AB32: =IF(AB$8=$R32,-$T32,0)+IF(AB$8=$S32,$T32,0) -> 0 | AC32: =IF(AC$8=$R32,-$T32,0)+IF(AC$8=$S32,$T32,0) -> 0 | AD32: =IF(AD$8=$R32,-$T32,0)+IF(AD$8=$S32,$T32,0) -> 0 | AE32: =IF(AE$8=$R32,-$T32,0)+IF(AE$8=$S32,$T32,0) -> 0 | AF32: =IF(AF$8=$R32,-$T32,0)+IF(AF$8=$S32,$T32,0) -> 0 | AG32: =IF(AG$8=$R32,-$T32,0)+IF(AG$8=$S32,$T32,0) -> 0 | ... AK32: =IF(AK$8=$R32,-$T32,0)+IF(AK$8=$S32,$T32,0) -> 0
A33: 6 | C33: =C14 -> --- | D33: =D14 | E33: =SUMIF(OFFSET($Z$9:$Z$88,0,A33-1),">0") -> 0 | F33: =SUMIF(OFFSET($Z$9:$Z$88,0,A33-1),"<0") -> 0 | G33: =SUM(E33:F33) -> 0 | J33: =NOT(ISERR(SEARCH(J$27,$C33))) -> FALSE | K33: =NOT(ISERR(SEARCH(K$27,$C33))) -> FALSE | L33: =NOT(ISERR(SEARCH(L$27,$C33))) -> FALSE | N33: 25 | X33: =IF(P33<NOW(),1,0) -> 1 | Z33: =IF(Z$8=$R33,-$T33,0)+IF(Z$8=$S33,$T33,0) -> 0 | AA33: =IF(AA$8=$R33,-$T33,0)+IF(AA$8=$S33,$T33,0) -> 0 | AB33: =IF(AB$8=$R33,-$T33,0)+IF(AB$8=$S33,$T33,0) -> 0 | AC33: =IF(AC$8=$R33,-$T33,0)+IF(AC$8=$S33,$T33,0) -> 0 | AD33: =IF(AD$8=$R33,-$T33,0)+IF(AD$8=$S33,$T33,0) -> 0 | AE33: =IF(AE$8=$R33,-$T33,0)+IF(AE$8=$S33,$T33,0) -> 0 | AF33: =IF(AF$8=$R33,-$T33,0)+IF(AF$8=$S33,$T33,0) -> 0 | AG33: =IF(AG$8=$R33,-$T33,0)+IF(AG$8=$S33,$T33,0) -> 0 | ... AK33: =IF(AK$8=$R33,-$T33,0)+IF(AK$8=$S33,$T33,0) -> 0
A34: 7 | C34: =C15 -> --- | D34: =D15 | E34: =SUMIF(OFFSET($Z$9:$Z$88,0,A34-1),">0") -> 0 | F34: =SUMIF(OFFSET($Z$9:$Z$88,0,A34-1),"<0") -> 0 | G34: =SUM(E34:F34) -> 0 | J34: =NOT(ISERR(SEARCH(J$27,$C34))) -> FALSE | K34: =NOT(ISERR(SEARCH(K$27,$C34))) -> FALSE | L34: =NOT(ISERR(SEARCH(L$27,$C34))) -> FALSE | N34: 26 | X34: =IF(P34<NOW(),1,0) -> 1 | Z34: =IF(Z$8=$R34,-$T34,0)+IF(Z$8=$S34,$T34,0) -> 0 | AA34: =IF(AA$8=$R34,-$T34,0)+IF(AA$8=$S34,$T34,0) -> 0 | AB34: =IF(AB$8=$R34,-$T34,0)+IF(AB$8=$S34,$T34,0) -> 0 | AC34: =IF(AC$8=$R34,-$T34,0)+IF(AC$8=$S34,$T34,0) -> 0 | AD34: =IF(AD$8=$R34,-$T34,0)+IF(AD$8=$S34,$T34,0) -> 0 | AE34: =IF(AE$8=$R34,-$T34,0)+IF(AE$8=$S34,$T34,0) -> 0 | AF34: =IF(AF$8=$R34,-$T34,0)+IF(AF$8=$S34,$T34,0) -> 0 | AG34: =IF(AG$8=$R34,-$T34,0)+IF(AG$8=$S34,$T34,0) -> 0 | ... AK34: =IF(AK$8=$R34,-$T34,0)+IF(AK$8=$S34,$T34,0) -> 0
A35: 8 | C35: =C16 -> --- | D35: =D16 | E35: =SUMIF(OFFSET($Z$9:$Z$88,0,A35-1),">0") -> 0 | F35: =SUMIF(OFFSET($Z$9:$Z$88,0,A35-1),"<0") -> 0 | G35: =SUM(E35:F35) -> 0 | J35: =NOT(ISERR(SEARCH(J$27,$C35))) -> FALSE | K35: =NOT(ISERR(SEARCH(K$27,$C35))) -> FALSE | L35: =NOT(ISERR(SEARCH(L$27,$C35))) -> FALSE | N35: 27 | X35: =IF(P35<NOW(),1,0) -> 1 | Z35: =IF(Z$8=$R35,-$T35,0)+IF(Z$8=$S35,$T35,0) -> 0 | AA35: =IF(AA$8=$R35,-$T35,0)+IF(AA$8=$S35,$T35,0) -> 0 | AB35: =IF(AB$8=$R35,-$T35,0)+IF(AB$8=$S35,$T35,0) -> 0 | AC35: =IF(AC$8=$R35,-$T35,0)+IF(AC$8=$S35,$T35,0) -> 0 | AD35: =IF(AD$8=$R35,-$T35,0)+IF(AD$8=$S35,$T35,0) -> 0 | AE35: =IF(AE$8=$R35,-$T35,0)+IF(AE$8=$S35,$T35,0) -> 0 | AF35: =IF(AF$8=$R35,-$T35,0)+IF(AF$8=$S35,$T35,0) -> 0 | AG35: =IF(AG$8=$R35,-$T35,0)+IF(AG$8=$S35,$T35,0) -> 0 | ... AK35: =IF(AK$8=$R35,-$T35,0)+IF(AK$8=$S35,$T35,0) -> 0
A36: 9 | C36: =C17 -> --- | D36: =D17 | E36: =SUMIF(OFFSET($Z$9:$Z$88,0,A36-1),">0") -> 0 | F36: =SUMIF(OFFSET($Z$9:$Z$88,0,A36-1),"<0") -> 0 | G36: =SUM(E36:F36) -> 0 | J36: =NOT(ISERR(SEARCH(J$27,$C36))) -> FALSE | K36: =NOT(ISERR(SEARCH(K$27,$C36))) -> FALSE | L36: =NOT(ISERR(SEARCH(L$27,$C36))) -> FALSE | N36: 28 | X36: =IF(P36<NOW(),1,0) -> 1 | Z36: =IF(Z$8=$R36,-$T36,0)+IF(Z$8=$S36,$T36,0) -> 0 | AA36: =IF(AA$8=$R36,-$T36,0)+IF(AA$8=$S36,$T36,0) -> 0 | AB36: =IF(AB$8=$R36,-$T36,0)+IF(AB$8=$S36,$T36,0) -> 0 | AC36: =IF(AC$8=$R36,-$T36,0)+IF(AC$8=$S36,$T36,0) -> 0 | AD36: =IF(AD$8=$R36,-$T36,0)+IF(AD$8=$S36,$T36,0) -> 0 | AE36: =IF(AE$8=$R36,-$T36,0)+IF(AE$8=$S36,$T36,0) -> 0 | AF36: =IF(AF$8=$R36,-$T36,0)+IF(AF$8=$S36,$T36,0) -> 0 | AG36: =IF(AG$8=$R36,-$T36,0)+IF(AG$8=$S36,$T36,0) -> 0 | ... AK36: =IF(AK$8=$R36,-$T36,0)+IF(AK$8=$S36,$T36,0) -> 0
A37: 10 | C37: =C18 -> --- | D37: =D18 | E37: =SUMIF(OFFSET($Z$9:$Z$88,0,A37-1),">0") -> 0 | F37: =SUMIF(OFFSET($Z$9:$Z$88,0,A37-1),"<0") -> 0 | G37: =SUM(E37:F37) -> 0 | J37: =NOT(ISERR(SEARCH(J$27,$C37))) -> FALSE | K37: =NOT(ISERR(SEARCH(K$27,$C37))) -> FALSE | L37: =NOT(ISERR(SEARCH(L$27,$C37))) -> FALSE | N37: 29 | X37: =IF(P37<NOW(),1,0) -> 1 | Z37: =IF(Z$8=$R37,-$T37,0)+IF(Z$8=$S37,$T37,0) -> 0 | AA37: =IF(AA$8=$R37,-$T37,0)+IF(AA$8=$S37,$T37,0) -> 0 | AB37: =IF(AB$8=$R37,-$T37,0)+IF(AB$8=$S37,$T37,0) -> 0 | AC37: =IF(AC$8=$R37,-$T37,0)+IF(AC$8=$S37,$T37,0) -> 0 | AD37: =IF(AD$8=$R37,-$T37,0)+IF(AD$8=$S37,$T37,0) -> 0 | AE37: =IF(AE$8=$R37,-$T37,0)+IF(AE$8=$S37,$T37,0) -> 0 | AF37: =IF(AF$8=$R37,-$T37,0)+IF(AF$8=$S37,$T37,0) -> 0 | AG37: =IF(AG$8=$R37,-$T37,0)+IF(AG$8=$S37,$T37,0) -> 0 | ... AK37: =IF(AK$8=$R37,-$T37,0)+IF(AK$8=$S37,$T37,0) -> 0
A38: 11 | C38: =C19 -> --- | D38: =D19 | E38: =SUMIF(OFFSET($Z$9:$Z$88,0,A38-1),">0") -> 0 | F38: =SUMIF(OFFSET($Z$9:$Z$88,0,A38-1),"<0") -> 0 | G38: =SUM(E38:F38) -> 0 | J38: =NOT(ISERR(SEARCH(J$27,$C38))) -> FALSE | K38: =NOT(ISERR(SEARCH(K$27,$C38))) -> FALSE | L38: =NOT(ISERR(SEARCH(L$27,$C38))) -> FALSE | N38: 30 | X38: =IF(P38<NOW(),1,0) -> 1 | Z38: =IF(Z$8=$R38,-$T38,0)+IF(Z$8=$S38,$T38,0) -> 0 | AA38: =IF(AA$8=$R38,-$T38,0)+IF(AA$8=$S38,$T38,0) -> 0 | AB38: =IF(AB$8=$R38,-$T38,0)+IF(AB$8=$S38,$T38,0) -> 0 | AC38: =IF(AC$8=$R38,-$T38,0)+IF(AC$8=$S38,$T38,0) -> 0 | AD38: =IF(AD$8=$R38,-$T38,0)+IF(AD$8=$S38,$T38,0) -> 0 | AE38: =IF(AE$8=$R38,-$T38,0)+IF(AE$8=$S38,$T38,0) -> 0 | AF38: =IF(AF$8=$R38,-$T38,0)+IF(AF$8=$S38,$T38,0) -> 0 | AG38: =IF(AG$8=$R38,-$T38,0)+IF(AG$8=$S38,$T38,0) -> 0 | ... AK38: =IF(AK$8=$R38,-$T38,0)+IF(AK$8=$S38,$T38,0) -> 0
A39: 12 | C39: =C20 -> --- | D39: =D20 | E39: =SUMIF(OFFSET($Z$9:$Z$88,0,A39-1),">0") -> 0 | F39: =SUMIF(OFFSET($Z$9:$Z$88,0,A39-1),"<0") -> 0 | G39: =SUM(E39:F39) -> 0 | J39: =NOT(ISERR(SEARCH(J$27,$C39))) -> FALSE | K39: =NOT(ISERR(SEARCH(K$27,$C39))) -> FALSE | L39: =NOT(ISERR(SEARCH(L$27,$C39))) -> FALSE | N39: 31 | X39: =IF(P39<NOW(),1,0) -> 1 | Z39: =IF(Z$8=$R39,-$T39,0)+IF(Z$8=$S39,$T39,0) -> 0 | AA39: =IF(AA$8=$R39,-$T39,0)+IF(AA$8=$S39,$T39,0) -> 0 | AB39: =IF(AB$8=$R39,-$T39,0)+IF(AB$8=$S39,$T39,0) -> 0 | AC39: =IF(AC$8=$R39,-$T39,0)+IF(AC$8=$S39,$T39,0) -> 0 | AD39: =IF(AD$8=$R39,-$T39,0)+IF(AD$8=$S39,$T39,0) -> 0 | AE39: =IF(AE$8=$R39,-$T39,0)+IF(AE$8=$S39,$T39,0) -> 0 | AF39: =IF(AF$8=$R39,-$T39,0)+IF(AF$8=$S39,$T39,0) -> 0 | AG39: =IF(AG$8=$R39,-$T39,0)+IF(AG$8=$S39,$T39,0) -> 0 | ... AK39: =IF(AK$8=$R39,-$T39,0)+IF(AK$8=$S39,$T39,0) -> 0
N40: 32 | X40: =IF(P40<NOW(),1,0) -> 1 | Z40: =IF(Z$8=$R40,-$T40,0)+IF(Z$8=$S40,$T40,0) -> 0 | AA40: =IF(AA$8=$R40,-$T40,0)+IF(AA$8=$S40,$T40,0) -> 0 | AB40: =IF(AB$8=$R40,-$T40,0)+IF(AB$8=$S40,$T40,0) -> 0 | AC40: =IF(AC$8=$R40,-$T40,0)+IF(AC$8=$S40,$T40,0) -> 0 | AD40: =IF(AD$8=$R40,-$T40,0)+IF(AD$8=$S40,$T40,0) -> 0 | AE40: =IF(AE$8=$R40,-$T40,0)+IF(AE$8=$S40,$T40,0) -> 0 | AF40: =IF(AF$8=$R40,-$T40,0)+IF(AF$8=$S40,$T40,0) -> 0 | AG40: =IF(AG$8=$R40,-$T40,0)+IF(AG$8=$S40,$T40,0) -> 0 | ... AK40: =IF(AK$8=$R40,-$T40,0)+IF(AK$8=$S40,$T40,0) -> 0
N41: 33 | X41: =IF(P41<NOW(),1,0) -> 1 | Z41: =IF(Z$8=$R41,-$T41,0)+IF(Z$8=$S41,$T41,0) -> 0 | AA41: =IF(AA$8=$R41,-$T41,0)+IF(AA$8=$S41,$T41,0) -> 0 | AB41: =IF(AB$8=$R41,-$T41,0)+IF(AB$8=$S41,$T41,0) -> 0 | AC41: =IF(AC$8=$R41,-$T41,0)+IF(AC$8=$S41,$T41,0) -> 0 | AD41: =IF(AD$8=$R41,-$T41,0)+IF(AD$8=$S41,$T41,0) -> 0 | AE41: =IF(AE$8=$R41,-$T41,0)+IF(AE$8=$S41,$T41,0) -> 0 | AF41: =IF(AF$8=$R41,-$T41,0)+IF(AF$8=$S41,$T41,0) -> 0 | AG41: =IF(AG$8=$R41,-$T41,0)+IF(AG$8=$S41,$T41,0) -> 0 | ... AK41: =IF(AK$8=$R41,-$T41,0)+IF(AK$8=$S41,$T41,0) -> 0
N42: 34 | X42: =IF(P42<NOW(),1,0) -> 1 | Z42: =IF(Z$8=$R42,-$T42,0)+IF(Z$8=$S42,$T42,0) -> 0 | AA42: =IF(AA$8=$R42,-$T42,0)+IF(AA$8=$S42,$T42,0) -> 0 | AB42: =IF(AB$8=$R42,-$T42,0)+IF(AB$8=$S42,$T42,0) -> 0 | AC42: =IF(AC$8=$R42,-$T42,0)+IF(AC$8=$S42,$T42,0) -> 0 | AD42: =IF(AD$8=$R42,-$T42,0)+IF(AD$8=$S42,$T42,0) -> 0 | AE42: =IF(AE$8=$R42,-$T42,0)+IF(AE$8=$S42,$T42,0) -> 0 | AF42: =IF(AF$8=$R42,-$T42,0)+IF(AF$8=$S42,$T42,0) -> 0 | AG42: =IF(AG$8=$R42,-$T42,0)+IF(AG$8=$S42,$T42,0) -> 0 | ... AK42: =IF(AK$8=$R42,-$T42,0)+IF(AK$8=$S42,$T42,0) -> 0
C43: MOVIMENTAÇÕES DO MÊS POR GRUPO DE CONTAS | N43: 35 | X43: =IF(P43<NOW(),1,0) -> 1 | Z43: =IF(Z$8=$R43,-$T43,0)+IF(Z$8=$S43,$T43,0) -> 0 | AA43: =IF(AA$8=$R43,-$T43,0)+IF(AA$8=$S43,$T43,0) -> 0 | AB43: =IF(AB$8=$R43,-$T43,0)+IF(AB$8=$S43,$T43,0) -> 0 | AC43: =IF(AC$8=$R43,-$T43,0)+IF(AC$8=$S43,$T43,0) -> 0 | AD43: =IF(AD$8=$R43,-$T43,0)+IF(AD$8=$S43,$T43,0) -> 0 | AE43: =IF(AE$8=$R43,-$T43,0)+IF(AE$8=$S43,$T43,0) -> 0 | AF43: =IF(AF$8=$R43,-$T43,0)+IF(AF$8=$S43,$T43,0) -> 0 | AG43: =IF(AG$8=$R43,-$T43,0)+IF(AG$8=$S43,$T43,0) -> 0 | ... AK43: =IF(AK$8=$R43,-$T43,0)+IF(AK$8=$S43,$T43,0) -> 0
N44: 36 | X44: =IF(P44<NOW(),1,0) -> 1 | Z44: =IF(Z$8=$R44,-$T44,0)+IF(Z$8=$S44,$T44,0) -> 0 | AA44: =IF(AA$8=$R44,-$T44,0)+IF(AA$8=$S44,$T44,0) -> 0 | AB44: =IF(AB$8=$R44,-$T44,0)+IF(AB$8=$S44,$T44,0) -> 0 | AC44: =IF(AC$8=$R44,-$T44,0)+IF(AC$8=$S44,$T44,0) -> 0 | AD44: =IF(AD$8=$R44,-$T44,0)+IF(AD$8=$S44,$T44,0) -> 0 | AE44: =IF(AE$8=$R44,-$T44,0)+IF(AE$8=$S44,$T44,0) -> 0 | AF44: =IF(AF$8=$R44,-$T44,0)+IF(AF$8=$S44,$T44,0) -> 0 | AG44: =IF(AG$8=$R44,-$T44,0)+IF(AG$8=$S44,$T44,0) -> 0 | ... AK44: =IF(AK$8=$R44,-$T44,0)+IF(AK$8=$S44,$T44,0) -> 0
C45: GRUPO | D45: DESCRIÇÃO | E45: TRANSFERÊNCIAS | F45: SAÍDA | G45: SALDO | N45: 37 | X45: =IF(P45<NOW(),1,0) -> 1 | Z45: =IF(Z$8=$R45,-$T45,0)+IF(Z$8=$S45,$T45,0) -> 0 | AA45: =IF(AA$8=$R45,-$T45,0)+IF(AA$8=$S45,$T45,0) -> 0 | AB45: =IF(AB$8=$R45,-$T45,0)+IF(AB$8=$S45,$T45,0) -> 0 | AC45: =IF(AC$8=$R45,-$T45,0)+IF(AC$8=$S45,$T45,0) -> 0 | AD45: =IF(AD$8=$R45,-$T45,0)+IF(AD$8=$S45,$T45,0) -> 0 | AE45: =IF(AE$8=$R45,-$T45,0)+IF(AE$8=$S45,$T45,0) -> 0 | AF45: =IF(AF$8=$R45,-$T45,0)+IF(AF$8=$S45,$T45,0) -> 0 | AG45: =IF(AG$8=$R45,-$T45,0)+IF(AG$8=$S45,$T45,0) -> 0 | ... AK45: =IF(AK$8=$R45,-$T45,0)+IF(AK$8=$S45,$T45,0) -> 0
E46: ENTRADA | F46: SAÍDA | G46: SALDO | N46: 38 | X46: =IF(P46<NOW(),1,0) -> 1 | Z46: =IF(Z$8=$R46,-$T46,0)+IF(Z$8=$S46,$T46,0) -> 0 | AA46: =IF(AA$8=$R46,-$T46,0)+IF(AA$8=$S46,$T46,0) -> 0 | AB46: =IF(AB$8=$R46,-$T46,0)+IF(AB$8=$S46,$T46,0) -> 0 | AC46: =IF(AC$8=$R46,-$T46,0)+IF(AC$8=$S46,$T46,0) -> 0 | AD46: =IF(AD$8=$R46,-$T46,0)+IF(AD$8=$S46,$T46,0) -> 0 | AE46: =IF(AE$8=$R46,-$T46,0)+IF(AE$8=$S46,$T46,0) -> 0 | AF46: =IF(AF$8=$R46,-$T46,0)+IF(AF$8=$S46,$T46,0) -> 0 | AG46: =IF(AG$8=$R46,-$T46,0)+IF(AG$8=$S46,$T46,0) -> 0 | ... AK46: =IF(AK$8=$R46,-$T46,0)+IF(AK$8=$S46,$T46,0) -> 0
A47: 1 | C47: =ANUAL!$C115 -> CC | D47: =ANUAL!$D115 -> CONTA CORRENTE | E47: =SUMIF($J$28:$J$39,TRUE,E$28:E$39) -> 0 | F47: =SUMIF($J$28:$J$39,TRUE,F$28:F$39) -> 0 | G47: =SUMIF($J$28:$J$39,TRUE,G$28:G$39)+SUMIF($J$9:$J$20,TRUE,E$9:E$20) -> 0 | N47: 39 | X47: =IF(P47<NOW(),1,0) -> 1 | Z47: =IF(Z$8=$R47,-$T47,0)+IF(Z$8=$S47,$T47,0) -> 0 | AA47: =IF(AA$8=$R47,-$T47,0)+IF(AA$8=$S47,$T47,0) -> 0 | AB47: =IF(AB$8=$R47,-$T47,0)+IF(AB$8=$S47,$T47,0) -> 0 | AC47: =IF(AC$8=$R47,-$T47,0)+IF(AC$8=$S47,$T47,0) -> 0 | AD47: =IF(AD$8=$R47,-$T47,0)+IF(AD$8=$S47,$T47,0) -> 0 | AE47: =IF(AE$8=$R47,-$T47,0)+IF(AE$8=$S47,$T47,0) -> 0 | AF47: =IF(AF$8=$R47,-$T47,0)+IF(AF$8=$S47,$T47,0) -> 0 | AG47: =IF(AG$8=$R47,-$T47,0)+IF(AG$8=$S47,$T47,0) -> 0 | ... AK47: =IF(AK$8=$R47,-$T47,0)+IF(AK$8=$S47,$T47,0) -> 0
A48: 2 | C48: =ANUAL!$C116 -> INV | D48: =ANUAL!$D116 -> APLICAÇÕES DE INVESTIMENTO | E48: =SUMIF($K$28:$K$39,TRUE,E$28:E$39) -> 0 | F48: =SUMIF($K$28:$K$39,TRUE,F$28:F$39) -> 0 | G48: =SUMIF($K$28:$K$39,TRUE,G$28:G$39)+SUMIF($K$9:$K$20,TRUE,E$9:E$20) -> 0 | N48: 40 | X48: =IF(P48<NOW(),1,0) -> 1 | Z48: =IF(Z$8=$R48,-$T48,0)+IF(Z$8=$S48,$T48,0) -> 0 | AA48: =IF(AA$8=$R48,-$T48,0)+IF(AA$8=$S48,$T48,0) -> 0 | AB48: =IF(AB$8=$R48,-$T48,0)+IF(AB$8=$S48,$T48,0) -> 0 | AC48: =IF(AC$8=$R48,-$T48,0)+IF(AC$8=$S48,$T48,0) -> 0 | AD48: =IF(AD$8=$R48,-$T48,0)+IF(AD$8=$S48,$T48,0) -> 0 | AE48: =IF(AE$8=$R48,-$T48,0)+IF(AE$8=$S48,$T48,0) -> 0 | AF48: =IF(AF$8=$R48,-$T48,0)+IF(AF$8=$S48,$T48,0) -> 0 | AG48: =IF(AG$8=$R48,-$T48,0)+IF(AG$8=$S48,$T48,0) -> 0 | ... AK48: =IF(AK$8=$R48,-$T48,0)+IF(AK$8=$S48,$T48,0) -> 0
A49: 3 | C49: =ANUAL!$C117 -> DINH | D49: =ANUAL!$D117 -> EM ESPÉCIE | E49: =SUMIF($L$28:$L$39,TRUE,E$28:E$39) -> 0 | F49: =SUMIF($L$28:$L$39,TRUE,F$28:F$39) -> 0 | G49: =SUMIF($L$28:$L$39,TRUE,G$28:G$39)+SUMIF($L$9:$L$20,TRUE,E$9:E$20) -> 0 | N49: 41 | X49: =IF(P49<NOW(),1,0) -> 1 | Z49: =IF(Z$8=$R49,-$T49,0)+IF(Z$8=$S49,$T49,0) -> 0 | AA49: =IF(AA$8=$R49,-$T49,0)+IF(AA$8=$S49,$T49,0) -> 0 | AB49: =IF(AB$8=$R49,-$T49,0)+IF(AB$8=$S49,$T49,0) -> 0 | AC49: =IF(AC$8=$R49,-$T49,0)+IF(AC$8=$S49,$T49,0) -> 0 | AD49: =IF(AD$8=$R49,-$T49,0)+IF(AD$8=$S49,$T49,0) -> 0 | AE49: =IF(AE$8=$R49,-$T49,0)+IF(AE$8=$S49,$T49,0) -> 0 | AF49: =IF(AF$8=$R49,-$T49,0)+IF(AF$8=$S49,$T49,0) -> 0 | AG49: =IF(AG$8=$R49,-$T49,0)+IF(AG$8=$S49,$T49,0) -> 0 | ... AK49: =IF(AK$8=$R49,-$T49,0)+IF(AK$8=$S49,$T49,0) -> 0
N50: 42 | X50: =IF(P50<NOW(),1,0) -> 1 | Z50: =IF(Z$8=$R50,-$T50,0)+IF(Z$8=$S50,$T50,0) -> 0 | AA50: =IF(AA$8=$R50,-$T50,0)+IF(AA$8=$S50,$T50,0) -> 0 | AB50: =IF(AB$8=$R50,-$T50,0)+IF(AB$8=$S50,$T50,0) -> 0 | AC50: =IF(AC$8=$R50,-$T50,0)+IF(AC$8=$S50,$T50,0) -> 0 | AD50: =IF(AD$8=$R50,-$T50,0)+IF(AD$8=$S50,$T50,0) -> 0 | AE50: =IF(AE$8=$R50,-$T50,0)+IF(AE$8=$S50,$T50,0) -> 0 | AF50: =IF(AF$8=$R50,-$T50,0)+IF(AF$8=$S50,$T50,0) -> 0 | AG50: =IF(AG$8=$R50,-$T50,0)+IF(AG$8=$S50,$T50,0) -> 0 | ... AK50: =IF(AK$8=$R50,-$T50,0)+IF(AK$8=$S50,$T50,0) -> 0
N51: 43 | X51: =IF(P51<NOW(),1,0) -> 1 | Z51: =IF(Z$8=$R51,-$T51,0)+IF(Z$8=$S51,$T51,0) -> 0 | AA51: =IF(AA$8=$R51,-$T51,0)+IF(AA$8=$S51,$T51,0) -> 0 | AB51: =IF(AB$8=$R51,-$T51,0)+IF(AB$8=$S51,$T51,0) -> 0 | AC51: =IF(AC$8=$R51,-$T51,0)+IF(AC$8=$S51,$T51,0) -> 0 | AD51: =IF(AD$8=$R51,-$T51,0)+IF(AD$8=$S51,$T51,0) -> 0 | AE51: =IF(AE$8=$R51,-$T51,0)+IF(AE$8=$S51,$T51,0) -> 0 | AF51: =IF(AF$8=$R51,-$T51,0)+IF(AF$8=$S51,$T51,0) -> 0 | AG51: =IF(AG$8=$R51,-$T51,0)+IF(AG$8=$S51,$T51,0) -> 0 | ... AK51: =IF(AK$8=$R51,-$T51,0)+IF(AK$8=$S51,$T51,0) -> 0
N52: 44 | X52: =IF(P52<NOW(),1,0) -> 1 | Z52: =IF(Z$8=$R52,-$T52,0)+IF(Z$8=$S52,$T52,0) -> 0 | AA52: =IF(AA$8=$R52,-$T52,0)+IF(AA$8=$S52,$T52,0) -> 0 | AB52: =IF(AB$8=$R52,-$T52,0)+IF(AB$8=$S52,$T52,0) -> 0 | AC52: =IF(AC$8=$R52,-$T52,0)+IF(AC$8=$S52,$T52,0) -> 0 | AD52: =IF(AD$8=$R52,-$T52,0)+IF(AD$8=$S52,$T52,0) -> 0 | AE52: =IF(AE$8=$R52,-$T52,0)+IF(AE$8=$S52,$T52,0) -> 0 | AF52: =IF(AF$8=$R52,-$T52,0)+IF(AF$8=$S52,$T52,0) -> 0 | AG52: =IF(AG$8=$R52,-$T52,0)+IF(AG$8=$S52,$T52,0) -> 0 | ... AK52: =IF(AK$8=$R52,-$T52,0)+IF(AK$8=$S52,$T52,0) -> 0
C53: ACOMPANHAMENTO DE DESPESAS | N53: 45 | X53: =IF(P53<NOW(),1,0) -> 1 | Z53: =IF(Z$8=$R53,-$T53,0)+IF(Z$8=$S53,$T53,0) -> 0 | AA53: =IF(AA$8=$R53,-$T53,0)+IF(AA$8=$S53,$T53,0) -> 0 | AB53: =IF(AB$8=$R53,-$T53,0)+IF(AB$8=$S53,$T53,0) -> 0 | AC53: =IF(AC$8=$R53,-$T53,0)+IF(AC$8=$S53,$T53,0) -> 0 | AD53: =IF(AD$8=$R53,-$T53,0)+IF(AD$8=$S53,$T53,0) -> 0 | AE53: =IF(AE$8=$R53,-$T53,0)+IF(AE$8=$S53,$T53,0) -> 0 | AF53: =IF(AF$8=$R53,-$T53,0)+IF(AF$8=$S53,$T53,0) -> 0 | AG53: =IF(AG$8=$R53,-$T53,0)+IF(AG$8=$S53,$T53,0) -> 0 | ... AK53: =IF(AK$8=$R53,-$T53,0)+IF(AK$8=$S53,$T53,0) -> 0
N54: 46 | X54: =IF(P54<NOW(),1,0) -> 1 | Z54: =IF(Z$8=$R54,-$T54,0)+IF(Z$8=$S54,$T54,0) -> 0 | AA54: =IF(AA$8=$R54,-$T54,0)+IF(AA$8=$S54,$T54,0) -> 0 | AB54: =IF(AB$8=$R54,-$T54,0)+IF(AB$8=$S54,$T54,0) -> 0 | AC54: =IF(AC$8=$R54,-$T54,0)+IF(AC$8=$S54,$T54,0) -> 0 | AD54: =IF(AD$8=$R54,-$T54,0)+IF(AD$8=$S54,$T54,0) -> 0 | AE54: =IF(AE$8=$R54,-$T54,0)+IF(AE$8=$S54,$T54,0) -> 0 | AF54: =IF(AF$8=$R54,-$T54,0)+IF(AF$8=$S54,$T54,0) -> 0 | AG54: =IF(AG$8=$R54,-$T54,0)+IF(AG$8=$S54,$T54,0) -> 0 | ... AK54: =IF(AK$8=$R54,-$T54,0)+IF(AK$8=$S54,$T54,0) -> 0
C55: CONTAS | D55: DESCRIÇÃO | G55: VALOR | N55: 47 | X55: =IF(P55<NOW(),1,0) -> 1 | Z55: =IF(Z$8=$R55,-$T55,0)+IF(Z$8=$S55,$T55,0) -> 0 | AA55: =IF(AA$8=$R55,-$T55,0)+IF(AA$8=$S55,$T55,0) -> 0 | AB55: =IF(AB$8=$R55,-$T55,0)+IF(AB$8=$S55,$T55,0) -> 0 | AC55: =IF(AC$8=$R55,-$T55,0)+IF(AC$8=$S55,$T55,0) -> 0 | AD55: =IF(AD$8=$R55,-$T55,0)+IF(AD$8=$S55,$T55,0) -> 0 | AE55: =IF(AE$8=$R55,-$T55,0)+IF(AE$8=$S55,$T55,0) -> 0 | AF55: =IF(AF$8=$R55,-$T55,0)+IF(AF$8=$S55,$T55,0) -> 0 | AG55: =IF(AG$8=$R55,-$T55,0)+IF(AG$8=$S55,$T55,0) -> 0 | ... AK55: =IF(AK$8=$R55,-$T55,0)+IF(AK$8=$S55,$T55,0) -> 0
N56: 48 | X56: =IF(P56<NOW(),1,0) -> 1 | Z56: =IF(Z$8=$R56,-$T56,0)+IF(Z$8=$S56,$T56,0) -> 0 | AA56: =IF(AA$8=$R56,-$T56,0)+IF(AA$8=$S56,$T56,0) -> 0 | AB56: =IF(AB$8=$R56,-$T56,0)+IF(AB$8=$S56,$T56,0) -> 0 | AC56: =IF(AC$8=$R56,-$T56,0)+IF(AC$8=$S56,$T56,0) -> 0 | AD56: =IF(AD$8=$R56,-$T56,0)+IF(AD$8=$S56,$T56,0) -> 0 | AE56: =IF(AE$8=$R56,-$T56,0)+IF(AE$8=$S56,$T56,0) -> 0 | AF56: =IF(AF$8=$R56,-$T56,0)+IF(AF$8=$S56,$T56,0) -> 0 | AG56: =IF(AG$8=$R56,-$T56,0)+IF(AG$8=$S56,$T56,0) -> 0 | ... AK56: =IF(AK$8=$R56,-$T56,0)+IF(AK$8=$S56,$T56,0) -> 0
A57: 1 | C57: =ANUAL!$C141 -> M01 | D57: =ANUAL!$D141 -> MORADIA – CONDOMÍNIO | G57: =SUMIF(U$9:U$88,C57,T$9:T$88) -> 0 | N57: 49 | X57: =IF(P57<NOW(),1,0) -> 1 | Z57: =IF(Z$8=$R57,-$T57,0)+IF(Z$8=$S57,$T57,0) -> 0 | AA57: =IF(AA$8=$R57,-$T57,0)+IF(AA$8=$S57,$T57,0) -> 0 | AB57: =IF(AB$8=$R57,-$T57,0)+IF(AB$8=$S57,$T57,0) -> 0 | AC57: =IF(AC$8=$R57,-$T57,0)+IF(AC$8=$S57,$T57,0) -> 0 | AD57: =IF(AD$8=$R57,-$T57,0)+IF(AD$8=$S57,$T57,0) -> 0 | AE57: =IF(AE$8=$R57,-$T57,0)+IF(AE$8=$S57,$T57,0) -> 0 | AF57: =IF(AF$8=$R57,-$T57,0)+IF(AF$8=$S57,$T57,0) -> 0 | AG57: =IF(AG$8=$R57,-$T57,0)+IF(AG$8=$S57,$T57,0) -> 0 | ... AK57: =IF(AK$8=$R57,-$T57,0)+IF(AK$8=$S57,$T57,0) -> 0
A58: 2 | C58: =ANUAL!$C142 -> M02 | D58: =ANUAL!$D142 -> MORADIA – IPTU | G58: =SUMIF(U$9:U$88,C58,T$9:T$88) -> 0 | N58: 50 | X58: =IF(P58<NOW(),1,0) -> 1 | Z58: =IF(Z$8=$R58,-$T58,0)+IF(Z$8=$S58,$T58,0) -> 0 | AA58: =IF(AA$8=$R58,-$T58,0)+IF(AA$8=$S58,$T58,0) -> 0 | AB58: =IF(AB$8=$R58,-$T58,0)+IF(AB$8=$S58,$T58,0) -> 0 | AC58: =IF(AC$8=$R58,-$T58,0)+IF(AC$8=$S58,$T58,0) -> 0 | AD58: =IF(AD$8=$R58,-$T58,0)+IF(AD$8=$S58,$T58,0) -> 0 | AE58: =IF(AE$8=$R58,-$T58,0)+IF(AE$8=$S58,$T58,0) -> 0 | AF58: =IF(AF$8=$R58,-$T58,0)+IF(AF$8=$S58,$T58,0) -> 0 | AG58: =IF(AG$8=$R58,-$T58,0)+IF(AG$8=$S58,$T58,0) -> 0 | ... AK58: =IF(AK$8=$R58,-$T58,0)+IF(AK$8=$S58,$T58,0) -> 0
A59: 3 | C59: =ANUAL!$C143 -> M03 | D59: =ANUAL!$D143 -> MORADIA – ALUGUEL | G59: =SUMIF(U$9:U$88,C59,T$9:T$88) -> 0 | N59: 51 | X59: =IF(P59<NOW(),1,0) -> 1 | Z59: =IF(Z$8=$R59,-$T59,0)+IF(Z$8=$S59,$T59,0) -> 0 | AA59: =IF(AA$8=$R59,-$T59,0)+IF(AA$8=$S59,$T59,0) -> 0 | AB59: =IF(AB$8=$R59,-$T59,0)+IF(AB$8=$S59,$T59,0) -> 0 | AC59: =IF(AC$8=$R59,-$T59,0)+IF(AC$8=$S59,$T59,0) -> 0 | AD59: =IF(AD$8=$R59,-$T59,0)+IF(AD$8=$S59,$T59,0) -> 0 | AE59: =IF(AE$8=$R59,-$T59,0)+IF(AE$8=$S59,$T59,0) -> 0 | AF59: =IF(AF$8=$R59,-$T59,0)+IF(AF$8=$S59,$T59,0) -> 0 | AG59: =IF(AG$8=$R59,-$T59,0)+IF(AG$8=$S59,$T59,0) -> 0 | ... AK59: =IF(AK$8=$R59,-$T59,0)+IF(AK$8=$S59,$T59,0) -> 0
A60: 4 | C60: =ANUAL!$C144 -> M04 | D60: =ANUAL!$D144 -> MORADIA – REFORMA | G60: =SUMIF(U$9:U$88,C60,T$9:T$88) -> 0 | N60: 52 | X60: =IF(P60<NOW(),1,0) -> 1 | Z60: =IF(Z$8=$R60,-$T60,0)+IF(Z$8=$S60,$T60,0) -> 0 | AA60: =IF(AA$8=$R60,-$T60,0)+IF(AA$8=$S60,$T60,0) -> 0 | AB60: =IF(AB$8=$R60,-$T60,0)+IF(AB$8=$S60,$T60,0) -> 0 | AC60: =IF(AC$8=$R60,-$T60,0)+IF(AC$8=$S60,$T60,0) -> 0 | AD60: =IF(AD$8=$R60,-$T60,0)+IF(AD$8=$S60,$T60,0) -> 0 | AE60: =IF(AE$8=$R60,-$T60,0)+IF(AE$8=$S60,$T60,0) -> 0 | AF60: =IF(AF$8=$R60,-$T60,0)+IF(AF$8=$S60,$T60,0) -> 0 | AG60: =IF(AG$8=$R60,-$T60,0)+IF(AG$8=$S60,$T60,0) -> 0 | ... AK60: =IF(AK$8=$R60,-$T60,0)+IF(AK$8=$S60,$T60,0) -> 0
A61: 5 | C61: =ANUAL!$C145 -> U01 | D61: =ANUAL!$D145 -> UTILITIES – ENERGIA ELÉTRICA | G61: =SUMIF(U$9:U$88,C61,T$9:T$88) -> 0 | N61: 53 | X61: =IF(P61<NOW(),1,0) -> 1 | Z61: =IF(Z$8=$R61,-$T61,0)+IF(Z$8=$S61,$T61,0) -> 0 | AA61: =IF(AA$8=$R61,-$T61,0)+IF(AA$8=$S61,$T61,0) -> 0 | AB61: =IF(AB$8=$R61,-$T61,0)+IF(AB$8=$S61,$T61,0) -> 0 | AC61: =IF(AC$8=$R61,-$T61,0)+IF(AC$8=$S61,$T61,0) -> 0 | AD61: =IF(AD$8=$R61,-$T61,0)+IF(AD$8=$S61,$T61,0) -> 0 | AE61: =IF(AE$8=$R61,-$T61,0)+IF(AE$8=$S61,$T61,0) -> 0 | AF61: =IF(AF$8=$R61,-$T61,0)+IF(AF$8=$S61,$T61,0) -> 0 | AG61: =IF(AG$8=$R61,-$T61,0)+IF(AG$8=$S61,$T61,0) -> 0 | ... AK61: =IF(AK$8=$R61,-$T61,0)+IF(AK$8=$S61,$T61,0) -> 0
A62: 6 | C62: =ANUAL!$C146 -> U02 | D62: =ANUAL!$D146 -> UTILITIES – ÁGUA POTÁVEL | G62: =SUMIF(U$9:U$88,C62,T$9:T$88) -> 0 | N62: 54 | X62: =IF(P62<NOW(),1,0) -> 1 | Z62: =IF(Z$8=$R62,-$T62,0)+IF(Z$8=$S62,$T62,0) -> 0 | AA62: =IF(AA$8=$R62,-$T62,0)+IF(AA$8=$S62,$T62,0) -> 0 | AB62: =IF(AB$8=$R62,-$T62,0)+IF(AB$8=$S62,$T62,0) -> 0 | AC62: =IF(AC$8=$R62,-$T62,0)+IF(AC$8=$S62,$T62,0) -> 0 | AD62: =IF(AD$8=$R62,-$T62,0)+IF(AD$8=$S62,$T62,0) -> 0 | AE62: =IF(AE$8=$R62,-$T62,0)+IF(AE$8=$S62,$T62,0) -> 0 | AF62: =IF(AF$8=$R62,-$T62,0)+IF(AF$8=$S62,$T62,0) -> 0 | AG62: =IF(AG$8=$R62,-$T62,0)+IF(AG$8=$S62,$T62,0) -> 0 | ... AK62: =IF(AK$8=$R62,-$T62,0)+IF(AK$8=$S62,$T62,0) -> 0
A63: 7 | C63: =ANUAL!$C147 -> U03 | D63: =ANUAL!$D147 -> UTILITIES – DIVERSOS (ÁGUA, GÁS, SERV. GERAIS) | G63: =SUMIF(U$9:U$88,C63,T$9:T$88) -> 0 | N63: 55 | X63: =IF(P63<NOW(),1,0) -> 1 | Z63: =IF(Z$8=$R63,-$T63,0)+IF(Z$8=$S63,$T63,0) -> 0 | AA63: =IF(AA$8=$R63,-$T63,0)+IF(AA$8=$S63,$T63,0) -> 0 | AB63: =IF(AB$8=$R63,-$T63,0)+IF(AB$8=$S63,$T63,0) -> 0 | AC63: =IF(AC$8=$R63,-$T63,0)+IF(AC$8=$S63,$T63,0) -> 0 | AD63: =IF(AD$8=$R63,-$T63,0)+IF(AD$8=$S63,$T63,0) -> 0 | AE63: =IF(AE$8=$R63,-$T63,0)+IF(AE$8=$S63,$T63,0) -> 0 | AF63: =IF(AF$8=$R63,-$T63,0)+IF(AF$8=$S63,$T63,0) -> 0 | AG63: =IF(AG$8=$R63,-$T63,0)+IF(AG$8=$S63,$T63,0) -> 0 | ... AK63: =IF(AK$8=$R63,-$T63,0)+IF(AK$8=$S63,$T63,0) -> 0
A64: 8 | C64: =ANUAL!$C148 -> S01 | D64: =ANUAL!$D148 -> SAÚDE – PLANO DE SAÚDE | G64: =SUMIF(U$9:U$88,C64,T$9:T$88) -> 0 | N64: 56 | X64: =IF(P64<NOW(),1,0) -> 1 | Z64: =IF(Z$8=$R64,-$T64,0)+IF(Z$8=$S64,$T64,0) -> 0 | AA64: =IF(AA$8=$R64,-$T64,0)+IF(AA$8=$S64,$T64,0) -> 0 | AB64: =IF(AB$8=$R64,-$T64,0)+IF(AB$8=$S64,$T64,0) -> 0 | AC64: =IF(AC$8=$R64,-$T64,0)+IF(AC$8=$S64,$T64,0) -> 0 | AD64: =IF(AD$8=$R64,-$T64,0)+IF(AD$8=$S64,$T64,0) -> 0 | AE64: =IF(AE$8=$R64,-$T64,0)+IF(AE$8=$S64,$T64,0) -> 0 | AF64: =IF(AF$8=$R64,-$T64,0)+IF(AF$8=$S64,$T64,0) -> 0 | AG64: =IF(AG$8=$R64,-$T64,0)+IF(AG$8=$S64,$T64,0) -> 0 | ... AK64: =IF(AK$8=$R64,-$T64,0)+IF(AK$8=$S64,$T64,0) -> 0
A65: 9 | C65: =ANUAL!$C149 -> S02 | D65: =ANUAL!$D149 -> SAÚDE – REMÉDIOS | G65: =SUMIF(U$9:U$88,C65,T$9:T$88) -> 0 | N65: 57 | X65: =IF(P65<NOW(),1,0) -> 1 | Z65: =IF(Z$8=$R65,-$T65,0)+IF(Z$8=$S65,$T65,0) -> 0 | AA65: =IF(AA$8=$R65,-$T65,0)+IF(AA$8=$S65,$T65,0) -> 0 | AB65: =IF(AB$8=$R65,-$T65,0)+IF(AB$8=$S65,$T65,0) -> 0 | AC65: =IF(AC$8=$R65,-$T65,0)+IF(AC$8=$S65,$T65,0) -> 0 | AD65: =IF(AD$8=$R65,-$T65,0)+IF(AD$8=$S65,$T65,0) -> 0 | AE65: =IF(AE$8=$R65,-$T65,0)+IF(AE$8=$S65,$T65,0) -> 0 | AF65: =IF(AF$8=$R65,-$T65,0)+IF(AF$8=$S65,$T65,0) -> 0 | AG65: =IF(AG$8=$R65,-$T65,0)+IF(AG$8=$S65,$T65,0) -> 0 | ... AK65: =IF(AK$8=$R65,-$T65,0)+IF(AK$8=$S65,$T65,0) -> 0
A66: 10 | C66: =ANUAL!$C150 -> S03 | D66: =ANUAL!$D150 -> SAÚDE – ACADEMIA | G66: =SUMIF(U$9:U$88,C66,T$9:T$88) -> 0 | N66: 58 | X66: =IF(P66<NOW(),1,0) -> 1 | Z66: =IF(Z$8=$R66,-$T66,0)+IF(Z$8=$S66,$T66,0) -> 0 | AA66: =IF(AA$8=$R66,-$T66,0)+IF(AA$8=$S66,$T66,0) -> 0 | AB66: =IF(AB$8=$R66,-$T66,0)+IF(AB$8=$S66,$T66,0) -> 0 | AC66: =IF(AC$8=$R66,-$T66,0)+IF(AC$8=$S66,$T66,0) -> 0 | AD66: =IF(AD$8=$R66,-$T66,0)+IF(AD$8=$S66,$T66,0) -> 0 | AE66: =IF(AE$8=$R66,-$T66,0)+IF(AE$8=$S66,$T66,0) -> 0 | AF66: =IF(AF$8=$R66,-$T66,0)+IF(AF$8=$S66,$T66,0) -> 0 | AG66: =IF(AG$8=$R66,-$T66,0)+IF(AG$8=$S66,$T66,0) -> 0 | ... AK66: =IF(AK$8=$R66,-$T66,0)+IF(AK$8=$S66,$T66,0) -> 0
A67: 11 | C67: =ANUAL!$C151 -> C01 | D67: =ANUAL!$D151 -> COMPRAS | G67: =SUMIF(U$9:U$88,C67,T$9:T$88) -> 0 | N67: 59 | X67: =IF(P67<NOW(),1,0) -> 1 | Z67: =IF(Z$8=$R67,-$T67,0)+IF(Z$8=$S67,$T67,0) -> 0 | AA67: =IF(AA$8=$R67,-$T67,0)+IF(AA$8=$S67,$T67,0) -> 0 | AB67: =IF(AB$8=$R67,-$T67,0)+IF(AB$8=$S67,$T67,0) -> 0 | AC67: =IF(AC$8=$R67,-$T67,0)+IF(AC$8=$S67,$T67,0) -> 0 | AD67: =IF(AD$8=$R67,-$T67,0)+IF(AD$8=$S67,$T67,0) -> 0 | AE67: =IF(AE$8=$R67,-$T67,0)+IF(AE$8=$S67,$T67,0) -> 0 | AF67: =IF(AF$8=$R67,-$T67,0)+IF(AF$8=$S67,$T67,0) -> 0 | AG67: =IF(AG$8=$R67,-$T67,0)+IF(AG$8=$S67,$T67,0) -> 0 | ... AK67: =IF(AK$8=$R67,-$T67,0)+IF(AK$8=$S67,$T67,0) -> 0
A68: 12 | C68: =ANUAL!$C152 -> L01 | D68: =ANUAL!$D152 -> LAZER | G68: =SUMIF(U$9:U$88,C68,T$9:T$88) -> 0 | N68: 60 | X68: =IF(P68<NOW(),1,0) -> 1 | Z68: =IF(Z$8=$R68,-$T68,0)+IF(Z$8=$S68,$T68,0) -> 0 | AA68: =IF(AA$8=$R68,-$T68,0)+IF(AA$8=$S68,$T68,0) -> 0 | AB68: =IF(AB$8=$R68,-$T68,0)+IF(AB$8=$S68,$T68,0) -> 0 | AC68: =IF(AC$8=$R68,-$T68,0)+IF(AC$8=$S68,$T68,0) -> 0 | AD68: =IF(AD$8=$R68,-$T68,0)+IF(AD$8=$S68,$T68,0) -> 0 | AE68: =IF(AE$8=$R68,-$T68,0)+IF(AE$8=$S68,$T68,0) -> 0 | AF68: =IF(AF$8=$R68,-$T68,0)+IF(AF$8=$S68,$T68,0) -> 0 | AG68: =IF(AG$8=$R68,-$T68,0)+IF(AG$8=$S68,$T68,0) -> 0 | ... AK68: =IF(AK$8=$R68,-$T68,0)+IF(AK$8=$S68,$T68,0) -> 0
... A88: 32 | C88: =ANUAL!$C172 -> --- | D88: =ANUAL!$D172 -> --- | G88: =SUMIF(U$9:U$88,C88,T$9:T$88) -> 0 | N88: 80 | X88: =IF(P88<NOW(),1,0) -> 1 | Z88: =IF(Z$8=$R88,-$T88,0)+IF(Z$8=$S88,$T88,0) -> 0 | AA88: =IF(AA$8=$R88,-$T88,0)+IF(AA$8=$S88,$T88,0) -> 0 | AB88: =IF(AB$8=$R88,-$T88,0)+IF(AB$8=$S88,$T88,0) -> 0 | AC88: =IF(AC$8=$R88,-$T88,0)+IF(AC$8=$S88,$T88,0) -> 0 | AD88: =IF(AD$8=$R88,-$T88,0)+IF(AD$8=$S88,$T88,0) -> 0 | AE88: =IF(AE$8=$R88,-$T88,0)+IF(AE$8=$S88,$T88,0) -> 0 | AF88: =IF(AF$8=$R88,-$T88,0)+IF(AF$8=$S88,$T88,0) -> 0 | AG88: =IF(AG$8=$R88,-$T88,0)+IF(AG$8=$S88,$T88,0) -> 0 | ... AK88: =IF(AK$8=$R88,-$T88,0)+IF(AK$8=$S88,$T88,0) -> 0

Sheet M3
B1: =DATE(ANUAL!B5,B2,8) -> 40245 | I1: >> | M1: << | W1: >> | AL1: <<
B2: ='M2'!B2+1 -> 3
C5: LISTA DE CONTAS | P5: MOVIMENTAÇÕES DO MÊS
C7: CONTA | D7: DESCRIÇÃO | E7: SALDO | P7: DATA | Q7: DESCRIÇÃO | R7: TRANFERÊNCIAS | T7: VALOR | U7: CODIGO
E8: ANTERIOR | F8: ATUAL | G8: PREVISTO | P8: DATA | Q8: DESCRIÇÃO | R8: SAÍDA | S8: ENTRADA | T8: VALOR | X8: ATUAL | Z8: =$C$9 | AA8: =$C$10 -> INV1 | AB8: =$C$11 -> DINH1 | AC8: =$C$12 -> CRED1 | AD8: =$C$13 -> --- | AE8: =$C$14 -> --- | AF8: =$C$15 -> --- | AG8: =$C$16 -> --- | AH8: =$C$17 -> --- | AI8: =$C$18 -> --- | AJ8: =$C$19 -> --- | AK8: =$C$20 -> ---
A9: 1 | C9: =TRIM(ANUAL!C13) | D9: =TRIM(ANUAL!D13) -> CONTA CORRENTE BANCO 1 | E9: =INDIRECT("M"&B$2-1&"!G"&A9+ROW(A$8)) -> 0 | F9: =E9+SUMIF(X$9:X$88,1,OFFSET($Z$9:$Z$88,0,A9-1)) -> 0 | G9: =E9+SUM(OFFSET($Z$9:$Z$88,0,A9-1)) -> 0 | J9: =NOT(ISERR(SEARCH(J$27,$C9))) -> FALSE | K9: =NOT(ISERR(SEARCH(K$27,$C9))) -> FALSE | L9: =NOT(ISERR(SEARCH(L$27,$C9))) -> FALSE | N9: 1 | X9: =IF(P9<NOW(),1,0) -> 1 | Z9: =IF(Z$8=$R9,-$T9,0)+IF(Z$8=$S9,$T9,0) -> 0 | AA9: =IF(AA$8=$R9,-$T9,0)+IF(AA$8=$S9,$T9,0) -> 0 | AB9: =IF(AB$8=$R9,-$T9,0)+IF(AB$8=$S9,$T9,0) -> 0 | AC9: =IF(AC$8=$R9,-$T9,0)+IF(AC$8=$S9,$T9,0) -> 0 | AD9: =IF(AD$8=$R9,-$T9,0)+IF(AD$8=$S9,$T9,0) -> 0 | AE9: =IF(AE$8=$R9,-$T9,0)+IF(AE$8=$S9,$T9,0) -> 0 | AF9: =IF(AF$8=$R9,-$T9,0)+IF(AF$8=$S9,$T9,0) -> 0 | AG9: =IF(AG$8=$R9,-$T9,0)+IF(AG$8=$S9,$T9,0) -> 0 | ... AK9: =IF(AK$8=$R9,-$T9,0)+IF(AK$8=$S9,$T9,0) -> 0
A10: 2 | C10: =TRIM(ANUAL!C14) -> INV1 | D10: =TRIM(ANUAL!D14) -> POUPANÇA BANCO 1 | E10: =INDIRECT("M"&B$2-1&"!G"&A10+ROW(A$8)) -> 0 | F10: =E10+SUMIF(X$9:X$88,1,OFFSET($Z$9:$Z$88,0,A10-1)) -> 0 | G10: =E10+SUM(OFFSET($Z$9:$Z$88,0,A10-1)) -> 0 | J10: =NOT(ISERR(SEARCH(J$27,$C10))) -> FALSE | K10: =NOT(ISERR(SEARCH(K$27,$C10))) -> TRUE | L10: =NOT(ISERR(SEARCH(L$27,$C10))) -> FALSE | N10: 2 | X10: =IF(P10<NOW(),1,0) -> 1 | Z10: =IF(Z$8=$R10,-$T10,0)+IF(Z$8=$S10,$T10,0) -> 0 | AA10: =IF(AA$8=$R10,-$T10,0)+IF(AA$8=$S10,$T10,0) -> 0 | AB10: =IF(AB$8=$R10,-$T10,0)+IF(AB$8=$S10,$T10,0) -> 0 | AC10: =IF(AC$8=$R10,-$T10,0)+IF(AC$8=$S10,$T10,0) -> 0 | AD10: =IF(AD$8=$R10,-$T10,0)+IF(AD$8=$S10,$T10,0) -> 0 | AE10: =IF(AE$8=$R10,-$T10,0)+IF(AE$8=$S10,$T10,0) -> 0 | AF10: =IF(AF$8=$R10,-$T10,0)+IF(AF$8=$S10,$T10,0) -> 0 | AG10: =IF(AG$8=$R10,-$T10,0)+IF(AG$8=$S10,$T10,0) -> 0 | ... AK10: =IF(AK$8=$R10,-$T10,0)+IF(AK$8=$S10,$T10,0) -> 0
A11: 3 | C11: =TRIM(ANUAL!C15) -> DINH1 | D11: =TRIM(ANUAL!D15) -> EM ESPÉCIE | E11: =INDIRECT("M"&B$2-1&"!G"&A11+ROW(A$8)) -> 0 | F11: =E11+SUMIF(X$9:X$88,1,OFFSET($Z$9:$Z$88,0,A11-1)) -> 0 | G11: =E11+SUM(OFFSET($Z$9:$Z$88,0,A11-1)) -> 0 | J11: =NOT(ISERR(SEARCH(J$27,$C11))) -> FALSE | K11: =NOT(ISERR(SEARCH(K$27,$C11))) -> FALSE | L11: =NOT(ISERR(SEARCH(L$27,$C11))) -> TRUE | N11: 3 | X11: =IF(P11<NOW(),1,0) -> 1 | Z11: =IF(Z$8=$R11,-$T11,0)+IF(Z$8=$S11,$T11,0) -> 0 | AA11: =IF(AA$8=$R11,-$T11,0)+IF(AA$8=$S11,$T11,0) -> 0 | AB11: =IF(AB$8=$R11,-$T11,0)+IF(AB$8=$S11,$T11,0) -> 0 | AC11: =IF(AC$8=$R11,-$T11,0)+IF(AC$8=$S11,$T11,0) -> 0 | AD11: =IF(AD$8=$R11,-$T11,0)+IF(AD$8=$S11,$T11,0) -> 0 | AE11: =IF(AE$8=$R11,-$T11,0)+IF(AE$8=$S11,$T11,0) -> 0 | AF11: =IF(AF$8=$R11,-$T11,0)+IF(AF$8=$S11,$T11,0) -> 0 | AG11: =IF(AG$8=$R11,-$T11,0)+IF(AG$8=$S11,$T11,0) -> 0 | ... AK11: =IF(AK$8=$R11,-$T11,0)+IF(AK$8=$S11,$T11,0) -> 0
A12: 4 | C12: =TRIM(ANUAL!C16) -> CRED1 | D12: =TRIM(ANUAL!D16) -> CARTÃO DE CRÉDITO 1 | E12: =INDIRECT("M"&B$2-1&"!G"&A12+ROW(A$8)) -> 0 | F12: =E12+SUMIF(X$9:X$88,1,OFFSET($Z$9:$Z$88,0,A12-1)) -> 0 | G12: =E12+SUM(OFFSET($Z$9:$Z$88,0,A12-1)) -> 0 | J12: =NOT(ISERR(SEARCH(J$27,$C12))) -> FALSE | K12: =NOT(ISERR(SEARCH(K$27,$C12))) -> FALSE | L12: =NOT(ISERR(SEARCH(L$27,$C12))) -> FALSE | N12: 4 | X12: =IF(P12<NOW(),1,0) -> 1 | Z12: =IF(Z$8=$R12,-$T12,0)+IF(Z$8=$S12,$T12,0) -> 0 | AA12: =IF(AA$8=$R12,-$T12,0)+IF(AA$8=$S12,$T12,0) -> 0 | AB12: =IF(AB$8=$R12,-$T12,0)+IF(AB$8=$S12,$T12,0) -> 0 | AC12: =IF(AC$8=$R12,-$T12,0)+IF(AC$8=$S12,$T12,0) -> 0 | AD12: =IF(AD$8=$R12,-$T12,0)+IF(AD$8=$S12,$T12,0) -> 0 | AE12: =IF(AE$8=$R12,-$T12,0)+IF(AE$8=$S12,$T12,0) -> 0 | AF12: =IF(AF$8=$R12,-$T12,0)+IF(AF$8=$S12,$T12,0) -> 0 | AG12: =IF(AG$8=$R12,-$T12,0)+IF(AG$8=$S12,$T12,0) -> 0 | ... AK12: =IF(AK$8=$R12,-$T12,0)+IF(AK$8=$S12,$T12,0) -> 0
A13: 5 | C13: =TRIM(ANUAL!C17) -> --- | D13: =TRIM(ANUAL!D17) | E13: =INDIRECT("M"&B$2-1&"!G"&A13+ROW(A$8)) -> 0 | F13: =E13+SUMIF(X$9:X$88,1,OFFSET($Z$9:$Z$88,0,A13-1)) -> 0 | G13: =E13+SUM(OFFSET($Z$9:$Z$88,0,A13-1)) -> 0 | J13: =NOT(ISERR(SEARCH(J$27,$C13))) -> FALSE | K13: =NOT(ISERR(SEARCH(K$27,$C13))) -> FALSE | L13: =NOT(ISERR(SEARCH(L$27,$C13))) -> FALSE | N13: 5 | X13: =IF(P13<NOW(),1,0) -> 1 | Z13: =IF(Z$8=$R13,-$T13,0)+IF(Z$8=$S13,$T13,0) -> 0 | AA13: =IF(AA$8=$R13,-$T13,0)+IF(AA$8=$S13,$T13,0) -> 0 | AB13: =IF(AB$8=$R13,-$T13,0)+IF(AB$8=$S13,$T13,0) -> 0 | AC13: =IF(AC$8=$R13,-$T13,0)+IF(AC$8=$S13,$T13,0) -> 0 | AD13: =IF(AD$8=$R13,-$T13,0)+IF(AD$8=$S13,$T13,0) -> 0 | AE13: =IF(AE$8=$R13,-$T13,0)+IF(AE$8=$S13,$T13,0) -> 0 | AF13: =IF(AF$8=$R13,-$T13,0)+IF(AF$8=$S13,$T13,0) -> 0 | AG13: =IF(AG$8=$R13,-$T13,0)+IF(AG$8=$S13,$T13,0) -> 0 | ... AK13: =IF(AK$8=$R13,-$T13,0)+IF(AK$8=$S13,$T13,0) -> 0
A14: 6 | C14: =TRIM(ANUAL!C18) -> --- | D14: =TRIM(ANUAL!D18) | E14: =INDIRECT("M"&B$2-1&"!G"&A14+ROW(A$8)) -> 0 | F14: =E14+SUMIF(X$9:X$88,1,OFFSET($Z$9:$Z$88,0,A14-1)) -> 0 | G14: =E14+SUM(OFFSET($Z$9:$Z$88,0,A14-1)) -> 0 | J14: =NOT(ISERR(SEARCH(J$27,$C14))) -> FALSE | K14: =NOT(ISERR(SEARCH(K$27,$C14))) -> FALSE | L14: =NOT(ISERR(SEARCH(L$27,$C14))) -> FALSE | N14: 6 | X14: =IF(P14<NOW(),1,0) -> 1 | Z14: =IF(Z$8=$R14,-$T14,0)+IF(Z$8=$S14,$T14,0) -> 0 | AA14: =IF(AA$8=$R14,-$T14,0)+IF(AA$8=$S14,$T14,0) -> 0 | AB14: =IF(AB$8=$R14,-$T14,0)+IF(AB$8=$S14,$T14,0) -> 0 | AC14: =IF(AC$8=$R14,-$T14,0)+IF(AC$8=$S14,$T14,0) -> 0 | AD14: =IF(AD$8=$R14,-$T14,0)+IF(AD$8=$S14,$T14,0) -> 0 | AE14: =IF(AE$8=$R14,-$T14,0)+IF(AE$8=$S14,$T14,0) -> 0 | AF14: =IF(AF$8=$R14,-$T14,0)+IF(AF$8=$S14,$T14,0) -> 0 | AG14: =IF(AG$8=$R14,-$T14,0)+IF(AG$8=$S14,$T14,0) -> 0 | ... AK14: =IF(AK$8=$R14,-$T14,0)+IF(AK$8=$S14,$T14,0) -> 0
A15: 7 | C15: =TRIM(ANUAL!C19) -> --- | D15: =TRIM(ANUAL!D19) | E15: =INDIRECT("M"&B$2-1&"!G"&A15+ROW(A$8)) -> 0 | F15: =E15+SUMIF(X$9:X$88,1,OFFSET($Z$9:$Z$88,0,A15-1)) -> 0 | G15: =E15+SUM(OFFSET($Z$9:$Z$88,0,A15-1)) -> 0 | J15: =NOT(ISERR(SEARCH(J$27,$C15))) -> FALSE | K15: =NOT(ISERR(SEARCH(K$27,$C15))) -> FALSE | L15: =NOT(ISERR(SEARCH(L$27,$C15))) -> FALSE | N15: 7 | X15: =IF(P15<NOW(),1,0) -> 1 | Z15: =IF(Z$8=$R15,-$T15,0)+IF(Z$8=$S15,$T15,0) -> 0 | AA15: =IF(AA$8=$R15,-$T15,0)+IF(AA$8=$S15,$T15,0) -> 0 | AB15: =IF(AB$8=$R15,-$T15,0)+IF(AB$8=$S15,$T15,0) -> 0 | AC15: =IF(AC$8=$R15,-$T15,0)+IF(AC$8=$S15,$T15,0) -> 0 | AD15: =IF(AD$8=$R15,-$T15,0)+IF(AD$8=$S15,$T15,0) -> 0 | AE15: =IF(AE$8=$R15,-$T15,0)+IF(AE$8=$S15,$T15,0) -> 0 | AF15: =IF(AF$8=$R15,-$T15,0)+IF(AF$8=$S15,$T15,0) -> 0 | AG15: =IF(AG$8=$R15,-$T15,0)+IF(AG$8=$S15,$T15,0) -> 0 | ... AK15: =IF(AK$8=$R15,-$T15,0)+IF(AK$8=$S15,$T15,0) -> 0
A16: 8 | C16: =TRIM(ANUAL!C20) -> --- | D16: =TRIM(ANUAL!D20) | E16: =INDIRECT("M"&B$2-1&"!G"&A16+ROW(A$8)) -> 0 | F16: =E16+SUMIF(X$9:X$88,1,OFFSET($Z$9:$Z$88,0,A16-1)) -> 0 | G16: =E16+SUM(OFFSET($Z$9:$Z$88,0,A16-1)) -> 0 | J16: =NOT(ISERR(SEARCH(J$27,$C16))) -> FALSE | K16: =NOT(ISERR(SEARCH(K$27,$C16))) -> FALSE | L16: =NOT(ISERR(SEARCH(L$27,$C16))) -> FALSE | N16: 8 | X16: =IF(P16<NOW(),1,0) -> 1 | Z16: =IF(Z$8=$R16,-$T16,0)+IF(Z$8=$S16,$T16,0) -> 0 | AA16: =IF(AA$8=$R16,-$T16,0)+IF(AA$8=$S16,$T16,0) -> 0 | AB16: =IF(AB$8=$R16,-$T16,0)+IF(AB$8=$S16,$T16,0) -> 0 | AC16: =IF(AC$8=$R16,-$T16,0)+IF(AC$8=$S16,$T16,0) -> 0 | AD16: =IF(AD$8=$R16,-$T16,0)+IF(AD$8=$S16,$T16,0) -> 0 | AE16: =IF(AE$8=$R16,-$T16,0)+IF(AE$8=$S16,$T16,0) -> 0 | AF16: =IF(AF$8=$R16,-$T16,0)+IF(AF$8=$S16,$T16,0) -> 0 | AG16: =IF(AG$8=$R16,-$T16,0)+IF(AG$8=$S16,$T16,0) -> 0 | ... AK16: =IF(AK$8=$R16,-$T16,0)+IF(AK$8=$S16,$T16,0) -> 0
A17: 9 | C17: =TRIM(ANUAL!C21) -> --- | D17: =TRIM(ANUAL!D21) | E17: =INDIRECT("M"&B$2-1&"!G"&A17+ROW(A$8)) -> 0 | F17: =E17+SUMIF(X$9:X$88,1,OFFSET($Z$9:$Z$88,0,A17-1)) -> 0 | G17: =E17+SUM(OFFSET($Z$9:$Z$88,0,A17-1)) -> 0 | J17: =NOT(ISERR(SEARCH(J$27,$C17))) -> FALSE | K17: =NOT(ISERR(SEARCH(K$27,$C17))) -> FALSE | L17: =NOT(ISERR(SEARCH(L$27,$C17))) -> FALSE | N17: 9 | X17: =IF(P17<NOW(),1,0) -> 1 | Z17: =IF(Z$8=$R17,-$T17,0)+IF(Z$8=$S17,$T17,0) -> 0 | AA17: =IF(AA$8=$R17,-$T17,0)+IF(AA$8=$S17,$T17,0) -> 0 | AB17: =IF(AB$8=$R17,-$T17,0)+IF(AB$8=$S17,$T17,0) -> 0 | AC17: =IF(AC$8=$R17,-$T17,0)+IF(AC$8=$S17,$T17,0) -> 0 | AD17: =IF(AD$8=$R17,-$T17,0)+IF(AD$8=$S17,$T17,0) -> 0 | AE17: =IF(AE$8=$R17,-$T17,0)+IF(AE$8=$S17,$T17,0) -> 0 | AF17: =IF(AF$8=$R17,-$T17,0)+IF(AF$8=$S17,$T17,0) -> 0 | AG17: =IF(AG$8=$R17,-$T17,0)+IF(AG$8=$S17,$T17,0) -> 0 | ... AK17: =IF(AK$8=$R17,-$T17,0)+IF(AK$8=$S17,$T17,0) -> 0
A18: 10 | C18: =TRIM(ANUAL!C22) -> --- | D18: =TRIM(ANUAL!D22) | E18: =INDIRECT("M"&B$2-1&"!G"&A18+ROW(A$8)) -> 0 | F18: =E18+SUMIF(X$9:X$88,1,OFFSET($Z$9:$Z$88,0,A18-1)) -> 0 | G18: =E18+SUM(OFFSET($Z$9:$Z$88,0,A18-1)) -> 0 | J18: =NOT(ISERR(SEARCH(J$27,$C18))) -> FALSE | K18: =NOT(ISERR(SEARCH(K$27,$C18))) -> FALSE | L18: =NOT(ISERR(SEARCH(L$27,$C18))) -> FALSE | N18: 10 | X18: =IF(P18<NOW(),1,0) -> 1 | Z18: =IF(Z$8=$R18,-$T18,0)+IF(Z$8=$S18,$T18,0) -> 0 | AA18: =IF(AA$8=$R18,-$T18,0)+IF(AA$8=$S18,$T18,0) -> 0 | AB18: =IF(AB$8=$R18,-$T18,0)+IF(AB$8=$S18,$T18,0) -> 0 | AC18: =IF(AC$8=$R18,-$T18,0)+IF(AC$8=$S18,$T18,0) -> 0 | AD18: =IF(AD$8=$R18,-$T18,0)+IF(AD$8=$S18,$T18,0) -> 0 | AE18: =IF(AE$8=$R18,-$T18,0)+IF(AE$8=$S18,$T18,0) -> 0 | AF18: =IF(AF$8=$R18,-$T18,0)+IF(AF$8=$S18,$T18,0) -> 0 | AG18: =IF(AG$8=$R18,-$T18,0)+IF(AG$8=$S18,$T18,0) -> 0 | ... AK18: =IF(AK$8=$R18,-$T18,0)+IF(AK$8=$S18,$T18,0) -> 0
A19: 11 | C19: =TRIM(ANUAL!C23) -> --- | D19: =TRIM(ANUAL!D23) | E19: =INDIRECT("M"&B$2-1&"!G"&A19+ROW(A$8)) -> 0 | F19: =E19+SUMIF(X$9:X$88,1,OFFSET($Z$9:$Z$88,0,A19-1)) -> 0 | G19: =E19+SUM(OFFSET($Z$9:$Z$88,0,A19-1)) -> 0 | J19: =NOT(ISERR(SEARCH(J$27,$C19))) -> FALSE | K19: =NOT(ISERR(SEARCH(K$27,$C19))) -> FALSE | L19: =NOT(ISERR(SEARCH(L$27,$C19))) -> FALSE | N19: 11 | X19: =IF(P19<NOW(),1,0) -> 1 | Z19: =IF(Z$8=$R19,-$T19,0)+IF(Z$8=$S19,$T19,0) -> 0 | AA19: =IF(AA$8=$R19,-$T19,0)+IF(AA$8=$S19,$T19,0) -> 0 | AB19: =IF(AB$8=$R19,-$T19,0)+IF(AB$8=$S19,$T19,0) -> 0 | AC19: =IF(AC$8=$R19,-$T19,0)+IF(AC$8=$S19,$T19,0) -> 0 | AD19: =IF(AD$8=$R19,-$T19,0)+IF(AD$8=$S19,$T19,0) -> 0 | AE19: =IF(AE$8=$R19,-$T19,0)+IF(AE$8=$S19,$T19,0) -> 0 | AF19: =IF(AF$8=$R19,-$T19,0)+IF(AF$8=$S19,$T19,0) -> 0 | AG19: =IF(AG$8=$R19,-$T19,0)+IF(AG$8=$S19,$T19,0) -> 0 | ... AK19: =IF(AK$8=$R19,-$T19,0)+IF(AK$8=$S19,$T19,0) -> 0
A20: 12 | C20: =TRIM(ANUAL!C24) -> --- | D20: =TRIM(ANUAL!D24) | E20: =INDIRECT("M"&B$2-1&"!G"&A20+ROW(A$8)) -> 0 | F20: =E20+SUMIF(X$9:X$88,1,OFFSET($Z$9:$Z$88,0,A20-1)) -> 0 | G20: =E20+SUM(OFFSET($Z$9:$Z$88,0,A20-1)) -> 0 | J20: =NOT(ISERR(SEARCH(J$27,$C20))) -> FALSE | K20: =NOT(ISERR(SEARCH(K$27,$C20))) -> FALSE | L20: =NOT(ISERR(SEARCH(L$27,$C20))) -> FALSE | N20: 12 | X20: =IF(P20<NOW(),1,0) -> 1 | Z20: =IF(Z$8=$R20,-$T20,0)+IF(Z$8=$S20,$T20,0) -> 0 | AA20: =IF(AA$8=$R20,-$T20,0)+IF(AA$8=$S20,$T20,0) -> 0 | AB20: =IF(AB$8=$R20,-$T20,0)+IF(AB$8=$S20,$T20,0) -> 0 | AC20: =IF(AC$8=$R20,-$T20,0)+IF(AC$8=$S20,$T20,0) -> 0 | AD20: =IF(AD$8=$R20,-$T20,0)+IF(AD$8=$S20,$T20,0) -> 0 | AE20: =IF(AE$8=$R20,-$T20,0)+IF(AE$8=$S20,$T20,0) -> 0 | AF20: =IF(AF$8=$R20,-$T20,0)+IF(AF$8=$S20,$T20,0) -> 0 | AG20: =IF(AG$8=$R20,-$T20,0)+IF(AG$8=$S20,$T20,0) -> 0 | ... AK20: =IF(AK$8=$R20,-$T20,0)+IF(AK$8=$S20,$T20,0) -> 0
N21: 13 | X21: =IF(P21<NOW(),1,0) -> 1 | Z21: =IF(Z$8=$R21,-$T21,0)+IF(Z$8=$S21,$T21,0) -> 0 | AA21: =IF(AA$8=$R21,-$T21,0)+IF(AA$8=$S21,$T21,0) -> 0 | AB21: =IF(AB$8=$R21,-$T21,0)+IF(AB$8=$S21,$T21,0) -> 0 | AC21: =IF(AC$8=$R21,-$T21,0)+IF(AC$8=$S21,$T21,0) -> 0 | AD21: =IF(AD$8=$R21,-$T21,0)+IF(AD$8=$S21,$T21,0) -> 0 | AE21: =IF(AE$8=$R21,-$T21,0)+IF(AE$8=$S21,$T21,0) -> 0 | AF21: =IF(AF$8=$R21,-$T21,0)+IF(AF$8=$S21,$T21,0) -> 0 | AG21: =IF(AG$8=$R21,-$T21,0)+IF(AG$8=$S21,$T21,0) -> 0 | ... AK21: =IF(AK$8=$R21,-$T21,0)+IF(AK$8=$S21,$T21,0) -> 0
N22: 14 | X22: =IF(P22<NOW(),1,0) -> 1 | Z22: =IF(Z$8=$R22,-$T22,0)+IF(Z$8=$S22,$T22,0) -> 0 | AA22: =IF(AA$8=$R22,-$T22,0)+IF(AA$8=$S22,$T22,0) -> 0 | AB22: =IF(AB$8=$R22,-$T22,0)+IF(AB$8=$S22,$T22,0) -> 0 | AC22: =IF(AC$8=$R22,-$T22,0)+IF(AC$8=$S22,$T22,0) -> 0 | AD22: =IF(AD$8=$R22,-$T22,0)+IF(AD$8=$S22,$T22,0) -> 0 | AE22: =IF(AE$8=$R22,-$T22,0)+IF(AE$8=$S22,$T22,0) -> 0 | AF22: =IF(AF$8=$R22,-$T22,0)+IF(AF$8=$S22,$T22,0) -> 0 | AG22: =IF(AG$8=$R22,-$T22,0)+IF(AG$8=$S22,$T22,0) -> 0 | ... AK22: =IF(AK$8=$R22,-$T22,0)+IF(AK$8=$S22,$T22,0) -> 0
N23: 15 | X23: =IF(P23<NOW(),1,0) -> 1 | Z23: =IF(Z$8=$R23,-$T23,0)+IF(Z$8=$S23,$T23,0) -> 0 | AA23: =IF(AA$8=$R23,-$T23,0)+IF(AA$8=$S23,$T23,0) -> 0 | AB23: =IF(AB$8=$R23,-$T23,0)+IF(AB$8=$S23,$T23,0) -> 0 | AC23: =IF(AC$8=$R23,-$T23,0)+IF(AC$8=$S23,$T23,0) -> 0 | AD23: =IF(AD$8=$R23,-$T23,0)+IF(AD$8=$S23,$T23,0) -> 0 | AE23: =IF(AE$8=$R23,-$T23,0)+IF(AE$8=$S23,$T23,0) -> 0 | AF23: =IF(AF$8=$R23,-$T23,0)+IF(AF$8=$S23,$T23,0) -> 0 | AG23: =IF(AG$8=$R23,-$T23,0)+IF(AG$8=$S23,$T23,0) -> 0 | ... AK23: =IF(AK$8=$R23,-$T23,0)+IF(AK$8=$S23,$T23,0) -> 0
C24: VARIAÇÃO MENSAL POR CONTA | N24: 16 | X24: =IF(P24<NOW(),1,0) -> 1 | Z24: =IF(Z$8=$R24,-$T24,0)+IF(Z$8=$S24,$T24,0) -> 0 | AA24: =IF(AA$8=$R24,-$T24,0)+IF(AA$8=$S24,$T24,0) -> 0 | AB24: =IF(AB$8=$R24,-$T24,0)+IF(AB$8=$S24,$T24,0) -> 0 | AC24: =IF(AC$8=$R24,-$T24,0)+IF(AC$8=$S24,$T24,0) -> 0 | AD24: =IF(AD$8=$R24,-$T24,0)+IF(AD$8=$S24,$T24,0) -> 0 | AE24: =IF(AE$8=$R24,-$T24,0)+IF(AE$8=$S24,$T24,0) -> 0 | AF24: =IF(AF$8=$R24,-$T24,0)+IF(AF$8=$S24,$T24,0) -> 0 | AG24: =IF(AG$8=$R24,-$T24,0)+IF(AG$8=$S24,$T24,0) -> 0 | ... AK24: =IF(AK$8=$R24,-$T24,0)+IF(AK$8=$S24,$T24,0) -> 0
N25: 17 | X25: =IF(P25<NOW(),1,0) -> 1 | Z25: =IF(Z$8=$R25,-$T25,0)+IF(Z$8=$S25,$T25,0) -> 0 | AA25: =IF(AA$8=$R25,-$T25,0)+IF(AA$8=$S25,$T25,0) -> 0 | AB25: =IF(AB$8=$R25,-$T25,0)+IF(AB$8=$S25,$T25,0) -> 0 | AC25: =IF(AC$8=$R25,-$T25,0)+IF(AC$8=$S25,$T25,0) -> 0 | AD25: =IF(AD$8=$R25,-$T25,0)+IF(AD$8=$S25,$T25,0) -> 0 | AE25: =IF(AE$8=$R25,-$T25,0)+IF(AE$8=$S25,$T25,0) -> 0 | AF25: =IF(AF$8=$R25,-$T25,0)+IF(AF$8=$S25,$T25,0) -> 0 | AG25: =IF(AG$8=$R25,-$T25,0)+IF(AG$8=$S25,$T25,0) -> 0 | ... AK25: =IF(AK$8=$R25,-$T25,0)+IF(AK$8=$S25,$T25,0) -> 0
C26: CONTA | D26: DESCRIÇÃO | E26: TRANSFERÊNCIAS | F26: SAÍDA | G26: SALDO | N26: 18 | X26: =IF(P26<NOW(),1,0) -> 1 | Z26: =IF(Z$8=$R26,-$T26,0)+IF(Z$8=$S26,$T26,0) -> 0 | AA26: =IF(AA$8=$R26,-$T26,0)+IF(AA$8=$S26,$T26,0) -> 0 | AB26: =IF(AB$8=$R26,-$T26,0)+IF(AB$8=$S26,$T26,0) -> 0 | AC26: =IF(AC$8=$R26,-$T26,0)+IF(AC$8=$S26,$T26,0) -> 0 | AD26: =IF(AD$8=$R26,-$T26,0)+IF(AD$8=$S26,$T26,0) -> 0 | AE26: =IF(AE$8=$R26,-$T26,0)+IF(AE$8=$S26,$T26,0) -> 0 | AF26: =IF(AF$8=$R26,-$T26,0)+IF(AF$8=$S26,$T26,0) -> 0 | AG26: =IF(AG$8=$R26,-$T26,0)+IF(AG$8=$S26,$T26,0) -> 0 | ... AK26: =IF(AK$8=$R26,-$T26,0)+IF(AK$8=$S26,$T26,0) -> 0
E27: ENTRADA | F27: SAÍDA | G27: VARIAÇÃO | J27: =ANUAL!C115 -> CC | K27: =ANUAL!C116 -> INV | L27: =ANUAL!C117 -> DINH | N27: 19 | X27: =IF(P27<NOW(),1,0) -> 1 | Z27: =IF(Z$8=$R27,-$T27,0)+IF(Z$8=$S27,$T27,0) -> 0 | AA27: =IF(AA$8=$R27,-$T27,0)+IF(AA$8=$S27,$T27,0) -> 0 | AB27: =IF(AB$8=$R27,-$T27,0)+IF(AB$8=$S27,$T27,0) -> 0 | AC27: =IF(AC$8=$R27,-$T27,0)+IF(AC$8=$S27,$T27,0) -> 0 | AD27: =IF(AD$8=$R27,-$T27,0)+IF(AD$8=$S27,$T27,0) -> 0 | AE27: =IF(AE$8=$R27,-$T27,0)+IF(AE$8=$S27,$T27,0) -> 0 | AF27: =IF(AF$8=$R27,-$T27,0)+IF(AF$8=$S27,$T27,0) -> 0 | AG27: =IF(AG$8=$R27,-$T27,0)+IF(AG$8=$S27,$T27,0) -> 0 | ... AK27: =IF(AK$8=$R27,-$T27,0)+IF(AK$8=$S27,$T27,0) -> 0
A28: 1 | C28: =C9 | D28: =D9 -> CONTA CORRENTE BANCO 1 | E28: =SUMIF(OFFSET($Z$9:$Z$88,0,A28-1),">0") -> 0 | F28: =SUMIF(OFFSET($Z$9:$Z$88,0,A28-1),"<0") -> 0 | G28: =SUM(E28:F28) -> 0 | J28: =NOT(ISERR(SEARCH(J$27,$C28))) -> FALSE | K28: =NOT(ISERR(SEARCH(K$27,$C28))) -> FALSE | L28: =NOT(ISERR(SEARCH(L$27,$C28))) -> FALSE | N28: 20 | X28: =IF(P28<NOW(),1,0) -> 1 | Z28: =IF(Z$8=$R28,-$T28,0)+IF(Z$8=$S28,$T28,0) -> 0 | AA28: =IF(AA$8=$R28,-$T28,0)+IF(AA$8=$S28,$T28,0) -> 0 | AB28: =IF(AB$8=$R28,-$T28,0)+IF(AB$8=$S28,$T28,0) -> 0 | AC28: =IF(AC$8=$R28,-$T28,0)+IF(AC$8=$S28,$T28,0) -> 0 | AD28: =IF(AD$8=$R28,-$T28,0)+IF(AD$8=$S28,$T28,0) -> 0 | AE28: =IF(AE$8=$R28,-$T28,0)+IF(AE$8=$S28,$T28,0) -> 0 | AF28: =IF(AF$8=$R28,-$T28,0)+IF(AF$8=$S28,$T28,0) -> 0 | AG28: =IF(AG$8=$R28,-$T28,0)+IF(AG$8=$S28,$T28,0) -> 0 | ... AK28: =IF(AK$8=$R28,-$T28,0)+IF(AK$8=$S28,$T28,0) -> 0
A29: 2 | C29: =C10 -> INV1 | D29: =D10 -> POUPANÇA BANCO 1 | E29: =SUMIF(OFFSET($Z$9:$Z$88,0,A29-1),">0") -> 0 | F29: =SUMIF(OFFSET($Z$9:$Z$88,0,A29-1),"<0") -> 0 | G29: =SUM(E29:F29) -> 0 | J29: =NOT(ISERR(SEARCH(J$27,$C29))) -> FALSE | K29: =NOT(ISERR(SEARCH(K$27,$C29))) -> TRUE | L29: =NOT(ISERR(SEARCH(L$27,$C29))) -> FALSE | N29: 21 | X29: =IF(P29<NOW(),1,0) -> 1 | Z29: =IF(Z$8=$R29,-$T29,0)+IF(Z$8=$S29,$T29,0) -> 0 | AA29: =IF(AA$8=$R29,-$T29,0)+IF(AA$8=$S29,$T29,0) -> 0 | AB29: =IF(AB$8=$R29,-$T29,0)+IF(AB$8=$S29,$T29,0) -> 0 | AC29: =IF(AC$8=$R29,-$T29,0)+IF(AC$8=$S29,$T29,0) -> 0 | AD29: =IF(AD$8=$R29,-$T29,0)+IF(AD$8=$S29,$T29,0) -> 0 | AE29: =IF(AE$8=$R29,-$T29,0)+IF(AE$8=$S29,$T29,0) -> 0 | AF29: =IF(AF$8=$R29,-$T29,0)+IF(AF$8=$S29,$T29,0) -> 0 | AG29: =IF(AG$8=$R29,-$T29,0)+IF(AG$8=$S29,$T29,0) -> 0 | ... AK29: =IF(AK$8=$R29,-$T29,0)+IF(AK$8=$S29,$T29,0) -> 0
A30: 3 | C30: =C11 -> DINH1 | D30: =D11 -> EM ESPÉCIE | E30: =SUMIF(OFFSET($Z$9:$Z$88,0,A30-1),">0") -> 0 | F30: =SUMIF(OFFSET($Z$9:$Z$88,0,A30-1),"<0") -> 0 | G30: =SUM(E30:F30) -> 0 | J30: =NOT(ISERR(SEARCH(J$27,$C30))) -> FALSE | K30: =NOT(ISERR(SEARCH(K$27,$C30))) -> FALSE | L30: =NOT(ISERR(SEARCH(L$27,$C30))) -> TRUE | N30: 22 | X30: =IF(P30<NOW(),1,0) -> 1 | Z30: =IF(Z$8=$R30,-$T30,0)+IF(Z$8=$S30,$T30,0) -> 0 | AA30: =IF(AA$8=$R30,-$T30,0)+IF(AA$8=$S30,$T30,0) -> 0 | AB30: =IF(AB$8=$R30,-$T30,0)+IF(AB$8=$S30,$T30,0) -> 0 | AC30: =IF(AC$8=$R30,-$T30,0)+IF(AC$8=$S30,$T30,0) -> 0 | AD30: =IF(AD$8=$R30,-$T30,0)+IF(AD$8=$S30,$T30,0) -> 0 | AE30: =IF(AE$8=$R30,-$T30,0)+IF(AE$8=$S30,$T30,0) -> 0 | AF30: =IF(AF$8=$R30,-$T30,0)+IF(AF$8=$S30,$T30,0) -> 0 | AG30: =IF(AG$8=$R30,-$T30,0)+IF(AG$8=$S30,$T30,0) -> 0 | ... AK30: =IF(AK$8=$R30,-$T30,0)+IF(AK$8=$S30,$T30,0) -> 0
A31: 4 | C31: =C12 -> CRED1 | D31: =D12 -> CARTÃO DE CRÉDITO 1 | E31: =SUMIF(OFFSET($Z$9:$Z$88,0,A31-1),">0") -> 0 | F31: =SUMIF(OFFSET($Z$9:$Z$88,0,A31-1),"<0") -> 0 | G31: =SUM(E31:F31) -> 0 | J31: =NOT(ISERR(SEARCH(J$27,$C31))) -> FALSE | K31: =NOT(ISERR(SEARCH(K$27,$C31))) -> FALSE | L31: =NOT(ISERR(SEARCH(L$27,$C31))) -> FALSE | N31: 23 | X31: =IF(P31<NOW(),1,0) -> 1 | Z31: =IF(Z$8=$R31,-$T31,0)+IF(Z$8=$S31,$T31,0) -> 0 | AA31: =IF(AA$8=$R31,-$T31,0)+IF(AA$8=$S31,$T31,0) -> 0 | AB31: =IF(AB$8=$R31,-$T31,0)+IF(AB$8=$S31,$T31,0) -> 0 | AC31: =IF(AC$8=$R31,-$T31,0)+IF(AC$8=$S31,$T31,0) -> 0 | AD31: =IF(AD$8=$R31,-$T31,0)+IF(AD$8=$S31,$T31,0) -> 0 | AE31: =IF(AE$8=$R31,-$T31,0)+IF(AE$8=$S31,$T31,0) -> 0 | AF31: =IF(AF$8=$R31,-$T31,0)+IF(AF$8=$S31,$T31,0) -> 0 | AG31: =IF(AG$8=$R31,-$T31,0)+IF(AG$8=$S31,$T31,0) -> 0 | ... AK31: =IF(AK$8=$R31,-$T31,0)+IF(AK$8=$S31,$T31,0) -> 0
A32: 5 | C32: =C13 -> --- | D32: =D13 | E32: =SUMIF(OFFSET($Z$9:$Z$88,0,A32-1),">0") -> 0 | F32: =SUMIF(OFFSET($Z$9:$Z$88,0,A32-1),"<0") -> 0 | G32: =SUM(E32:F32) -> 0 | J32: =NOT(ISERR(SEARCH(J$27,$C32))) -> FALSE | K32: =NOT(ISERR(SEARCH(K$27,$C32))) -> FALSE | L32: =NOT(ISERR(SEARCH(L$27,$C32))) -> FALSE | N32: 24 | X32: =IF(P32<NOW(),1,0) -> 1 | Z32: =IF(Z$8=$R32,-$T32,0)+IF(Z$8=$S32,$T32,0) -> 0 | AA32: =IF(AA$8=$R32,-$T32,0)+IF(AA$8=$S32,$T32,0) -> 0 | AB32: =IF(AB$8=$R32,-$T32,0)+IF(AB$8=$S32,$T32,0) -> 0 | AC32: =IF(AC$8=$R32,-$T32,0)+IF(AC$8=$S32,$T32,0) -> 0 | AD32: =IF(AD$8=$R32,-$T32,0)+IF(AD$8=$S32,$T32,0) -> 0 | AE32: =IF(AE$8=$R32,-$T32,0)+IF(AE$8=$S32,$T32,0) -> 0 | AF32: =IF(AF$8=$R32,-$T32,0)+IF(AF$8=$S32,$T32,0) -> 0 | AG32: =IF(AG$8=$R32,-$T32,0)+IF(AG$8=$S32,$T32,0) -> 0 | ... AK32: =IF(AK$8=$R32,-$T32,0)+IF(AK$8=$S32,$T32,0) -> 0
A33: 6 | C33: =C14 -> --- | D33: =D14 | E33: =SUMIF(OFFSET($Z$9:$Z$88,0,A33-1),">0") -> 0 | F33: =SUMIF(OFFSET($Z$9:$Z$88,0,A33-1),"<0") -> 0 | G33: =SUM(E33:F33) -> 0 | J33: =NOT(ISERR(SEARCH(J$27,$C33))) -> FALSE | K33: =NOT(ISERR(SEARCH(K$27,$C33))) -> FALSE | L33: =NOT(ISERR(SEARCH(L$27,$C33))) -> FALSE | N33: 25 | X33: =IF(P33<NOW(),1,0) -> 1 | Z33: =IF(Z$8=$R33,-$T33,0)+IF(Z$8=$S33,$T33,0) -> 0 | AA33: =IF(AA$8=$R33,-$T33,0)+IF(AA$8=$S33,$T33,0) -> 0 | AB33: =IF(AB$8=$R33,-$T33,0)+IF(AB$8=$S33,$T33,0) -> 0 | AC33: =IF(AC$8=$R33,-$T33,0)+IF(AC$8=$S33,$T33,0) -> 0 | AD33: =IF(AD$8=$R33,-$T33,0)+IF(AD$8=$S33,$T33,0) -> 0 | AE33: =IF(AE$8=$R33,-$T33,0)+IF(AE$8=$S33,$T33,0) -> 0 | AF33: =IF(AF$8=$R33,-$T33,0)+IF(AF$8=$S33,$T33,0) -> 0 | AG33: =IF(AG$8=$R33,-$T33,0)+IF(AG$8=$S33,$T33,0) -> 0 | ... AK33: =IF(AK$8=$R33,-$T33,0)+IF(AK$8=$S33,$T33,0) -> 0
A34: 7 | C34: =C15 -> --- | D34: =D15 | E34: =SUMIF(OFFSET($Z$9:$Z$88,0,A34-1),">0") -> 0 | F34: =SUMIF(OFFSET($Z$9:$Z$88,0,A34-1),"<0") -> 0 | G34: =SUM(E34:F34) -> 0 | J34: =NOT(ISERR(SEARCH(J$27,$C34))) -> FALSE | K34: =NOT(ISERR(SEARCH(K$27,$C34))) -> FALSE | L34: =NOT(ISERR(SEARCH(L$27,$C34))) -> FALSE | N34: 26 | X34: =IF(P34<NOW(),1,0) -> 1 | Z34: =IF(Z$8=$R34,-$T34,0)+IF(Z$8=$S34,$T34,0) -> 0 | AA34: =IF(AA$8=$R34,-$T34,0)+IF(AA$8=$S34,$T34,0) -> 0 | AB34: =IF(AB$8=$R34,-$T34,0)+IF(AB$8=$S34,$T34,0) -> 0 | AC34: =IF(AC$8=$R34,-$T34,0)+IF(AC$8=$S34,$T34,0) -> 0 | AD34: =IF(AD$8=$R34,-$T34,0)+IF(AD$8=$S34,$T34,0) -> 0 | AE34: =IF(AE$8=$R34,-$T34,0)+IF(AE$8=$S34,$T34,0) -> 0 | AF34: =IF(AF$8=$R34,-$T34,0)+IF(AF$8=$S34,$T34,0) -> 0 | AG34: =IF(AG$8=$R34,-$T34,0)+IF(AG$8=$S34,$T34,0) -> 0 | ... AK34: =IF(AK$8=$R34,-$T34,0)+IF(AK$8=$S34,$T34,0) -> 0
A35: 8 | C35: =C16 -> --- | D35: =D16 | E35: =SUMIF(OFFSET($Z$9:$Z$88,0,A35-1),">0") -> 0 | F35: =SUMIF(OFFSET($Z$9:$Z$88,0,A35-1),"<0") -> 0 | G35: =SUM(E35:F35) -> 0 | J35: =NOT(ISERR(SEARCH(J$27,$C35))) -> FALSE | K35: =NOT(ISERR(SEARCH(K$27,$C35))) -> FALSE | L35: =NOT(ISERR(SEARCH(L$27,$C35))) -> FALSE | N35: 27 | X35: =IF(P35<NOW(),1,0) -> 1 | Z35: =IF(Z$8=$R35,-$T35,0)+IF(Z$8=$S35,$T35,0) -> 0 | AA35: =IF(AA$8=$R35,-$T35,0)+IF(AA$8=$S35,$T35,0) -> 0 | AB35: =IF(AB$8=$R35,-$T35,0)+IF(AB$8=$S35,$T35,0) -> 0 | AC35: =IF(AC$8=$R35,-$T35,0)+IF(AC$8=$S35,$T35,0) -> 0 | AD35: =IF(AD$8=$R35,-$T35,0)+IF(AD$8=$S35,$T35,0) -> 0 | AE35: =IF(AE$8=$R35,-$T35,0)+IF(AE$8=$S35,$T35,0) -> 0 | AF35: =IF(AF$8=$R35,-$T35,0)+IF(AF$8=$S35,$T35,0) -> 0 | AG35: =IF(AG$8=$R35,-$T35,0)+IF(AG$8=$S35,$T35,0) -> 0 | ... AK35: =IF(AK$8=$R35,-$T35,0)+IF(AK$8=$S35,$T35,0) -> 0
A36: 9 | C36: =C17 -> --- | D36: =D17 | E36: =SUMIF(OFFSET($Z$9:$Z$88,0,A36-1),">0") -> 0 | F36: =SUMIF(OFFSET($Z$9:$Z$88,0,A36-1),"<0") -> 0 | G36: =SUM(E36:F36) -> 0 | J36: =NOT(ISERR(SEARCH(J$27,$C36))) -> FALSE | K36: =NOT(ISERR(SEARCH(K$27,$C36))) -> FALSE | L36: =NOT(ISERR(SEARCH(L$27,$C36))) -> FALSE | N36: 28 | X36: =IF(P36<NOW(),1,0) -> 1 | Z36: =IF(Z$8=$R36,-$T36,0)+IF(Z$8=$S36,$T36,0) -> 0 | AA36: =IF(AA$8=$R36,-$T36,0)+IF(AA$8=$S36,$T36,0) -> 0 | AB36: =IF(AB$8=$R36,-$T36,0)+IF(AB$8=$S36,$T36,0) -> 0 | AC36: =IF(AC$8=$R36,-$T36,0)+IF(AC$8=$S36,$T36,0) -> 0 | AD36: =IF(AD$8=$R36,-$T36,0)+IF(AD$8=$S36,$T36,0) -> 0 | AE36: =IF(AE$8=$R36,-$T36,0)+IF(AE$8=$S36,$T36,0) -> 0 | AF36: =IF(AF$8=$R36,-$T36,0)+IF(AF$8=$S36,$T36,0) -> 0 | AG36: =IF(AG$8=$R36,-$T36,0)+IF(AG$8=$S36,$T36,0) -> 0 | ... AK36: =IF(AK$8=$R36,-$T36,0)+IF(AK$8=$S36,$T36,0) -> 0
A37: 10 | C37: =C18 -> --- | D37: =D18 | E37: =SUMIF(OFFSET($Z$9:$Z$88,0,A37-1),">0") -> 0 | F37: =SUMIF(OFFSET($Z$9:$Z$88,0,A37-1),"<0") -> 0 | G37: =SUM(E37:F37) -> 0 | J37: =NOT(ISERR(SEARCH(J$27,$C37))) -> FALSE | K37: =NOT(ISERR(SEARCH(K$27,$C37))) -> FALSE | L37: =NOT(ISERR(SEARCH(L$27,$C37))) -> FALSE | N37: 29 | X37: =IF(P37<NOW(),1,0) -> 1 | Z37: =IF(Z$8=$R37,-$T37,0)+IF(Z$8=$S37,$T37,0) -> 0 | AA37: =IF(AA$8=$R37,-$T37,0)+IF(AA$8=$S37,$T37,0) -> 0 | AB37: =IF(AB$8=$R37,-$T37,0)+IF(AB$8=$S37,$T37,0) -> 0 | AC37: =IF(AC$8=$R37,-$T37,0)+IF(AC$8=$S37,$T37,0) -> 0 | AD37: =IF(AD$8=$R37,-$T37,0)+IF(AD$8=$S37,$T37,0) -> 0 | AE37: =IF(AE$8=$R37,-$T37,0)+IF(AE$8=$S37,$T37,0) -> 0 | AF37: =IF(AF$8=$R37,-$T37,0)+IF(AF$8=$S37,$T37,0) -> 0 | AG37: =IF(AG$8=$R37,-$T37,0)+IF(AG$8=$S37,$T37,0) -> 0 | ... AK37: =IF(AK$8=$R37,-$T37,0)+IF(AK$8=$S37,$T37,0) -> 0
A38: 11 | C38: =C19 -> --- | D38: =D19 | E38: =SUMIF(OFFSET($Z$9:$Z$88,0,A38-1),">0") -> 0 | F38: =SUMIF(OFFSET($Z$9:$Z$88,0,A38-1),"<0") -> 0 | G38: =SUM(E38:F38) -> 0 | J38: =NOT(ISERR(SEARCH(J$27,$C38))) -> FALSE | K38: =NOT(ISERR(SEARCH(K$27,$C38))) -> FALSE | L38: =NOT(ISERR(SEARCH(L$27,$C38))) -> FALSE | N38: 30 | X38: =IF(P38<NOW(),1,0) -> 1 | Z38: =IF(Z$8=$R38,-$T38,0)+IF(Z$8=$S38,$T38,0) -> 0 | AA38: =IF(AA$8=$R38,-$T38,0)+IF(AA$8=$S38,$T38,0) -> 0 | AB38: =IF(AB$8=$R38,-$T38,0)+IF(AB$8=$S38,$T38,0) -> 0 | AC38: =IF(AC$8=$R38,-$T38,0)+IF(AC$8=$S38,$T38,0) -> 0 | AD38: =IF(AD$8=$R38,-$T38,0)+IF(AD$8=$S38,$T38,0) -> 0 | AE38: =IF(AE$8=$R38,-$T38,0)+IF(AE$8=$S38,$T38,0) -> 0 | AF38: =IF(AF$8=$R38,-$T38,0)+IF(AF$8=$S38,$T38,0) -> 0 | AG38: =IF(AG$8=$R38,-$T38,0)+IF(AG$8=$S38,$T38,0) -> 0 | ... AK38: =IF(AK$8=$R38,-$T38,0)+IF(AK$8=$S38,$T38,0) -> 0
A39: 12 | C39: =C20 -> --- | D39: =D20 | E39: =SUMIF(OFFSET($Z$9:$Z$88,0,A39-1),">0") -> 0 | F39: =SUMIF(OFFSET($Z$9:$Z$88,0,A39-1),"<0") -> 0 | G39: =SUM(E39:F39) -> 0 | J39: =NOT(ISERR(SEARCH(J$27,$C39))) -> FALSE | K39: =NOT(ISERR(SEARCH(K$27,$C39))) -> FALSE | L39: =NOT(ISERR(SEARCH(L$27,$C39))) -> FALSE | N39: 31 | X39: =IF(P39<NOW(),1,0) -> 1 | Z39: =IF(Z$8=$R39,-$T39,0)+IF(Z$8=$S39,$T39,0) -> 0 | AA39: =IF(AA$8=$R39,-$T39,0)+IF(AA$8=$S39,$T39,0) -> 0 | AB39: =IF(AB$8=$R39,-$T39,0)+IF(AB$8=$S39,$T39,0) -> 0 | AC39: =IF(AC$8=$R39,-$T39,0)+IF(AC$8=$S39,$T39,0) -> 0 | AD39: =IF(AD$8=$R39,-$T39,0)+IF(AD$8=$S39,$T39,0) -> 0 | AE39: =IF(AE$8=$R39,-$T39,0)+IF(AE$8=$S39,$T39,0) -> 0 | AF39: =IF(AF$8=$R39,-$T39,0)+IF(AF$8=$S39,$T39,0) -> 0 | AG39: =IF(AG$8=$R39,-$T39,0)+IF(AG$8=$S39,$T39,0) -> 0 | ... AK39: =IF(AK$8=$R39,-$T39,0)+IF(AK$8=$S39,$T39,0) -> 0
N40: 32 | X40: =IF(P40<NOW(),1,0) -> 1 | Z40: =IF(Z$8=$R40,-$T40,0)+IF(Z$8=$S40,$T40,0) -> 0 | AA40: =IF(AA$8=$R40,-$T40,0)+IF(AA$8=$S40,$T40,0) -> 0 | AB40: =IF(AB$8=$R40,-$T40,0)+IF(AB$8=$S40,$T40,0) -> 0 | AC40: =IF(AC$8=$R40,-$T40,0)+IF(AC$8=$S40,$T40,0) -> 0 | AD40: =IF(AD$8=$R40,-$T40,0)+IF(AD$8=$S40,$T40,0) -> 0 | AE40: =IF(AE$8=$R40,-$T40,0)+IF(AE$8=$S40,$T40,0) -> 0 | AF40: =IF(AF$8=$R40,-$T40,0)+IF(AF$8=$S40,$T40,0) -> 0 | AG40: =IF(AG$8=$R40,-$T40,0)+IF(AG$8=$S40,$T40,0) -> 0 | ... AK40: =IF(AK$8=$R40,-$T40,0)+IF(AK$8=$S40,$T40,0) -> 0
N41: 33 | X41: =IF(P41<NOW(),1,0) -> 1 | Z41: =IF(Z$8=$R41,-$T41,0)+IF(Z$8=$S41,$T41,0) -> 0 | AA41: =IF(AA$8=$R41,-$T41,0)+IF(AA$8=$S41,$T41,0) -> 0 | AB41: =IF(AB$8=$R41,-$T41,0)+IF(AB$8=$S41,$T41,0) -> 0 | AC41: =IF(AC$8=$R41,-$T41,0)+IF(AC$8=$S41,$T41,0) -> 0 | AD41: =IF(AD$8=$R41,-$T41,0)+IF(AD$8=$S41,$T41,0) -> 0 | AE41: =IF(AE$8=$R41,-$T41,0)+IF(AE$8=$S41,$T41,0) -> 0 | AF41: =IF(AF$8=$R41,-$T41,0)+IF(AF$8=$S41,$T41,0) -> 0 | AG41: =IF(AG$8=$R41,-$T41,0)+IF(AG$8=$S41,$T41,0) -> 0 | ... AK41: =IF(AK$8=$R41,-$T41,0)+IF(AK$8=$S41,$T41,0) -> 0
N42: 34 | X42: =IF(P42<NOW(),1,0) -> 1 | Z42: =IF(Z$8=$R42,-$T42,0)+IF(Z$8=$S42,$T42,0) -> 0 | AA42: =IF(AA$8=$R42,-$T42,0)+IF(AA$8=$S42,$T42,0) -> 0 | AB42: =IF(AB$8=$R42,-$T42,0)+IF(AB$8=$S42,$T42,0) -> 0 | AC42: =IF(AC$8=$R42,-$T42,0)+IF(AC$8=$S42,$T42,0) -> 0 | AD42: =IF(AD$8=$R42,-$T42,0)+IF(AD$8=$S42,$T42,0) -> 0 | AE42: =IF(AE$8=$R42,-$T42,0)+IF(AE$8=$S42,$T42,0) -> 0 | AF42: =IF(AF$8=$R42,-$T42,0)+IF(AF$8=$S42,$T42,0) -> 0 | AG42: =IF(AG$8=$R42,-$T42,0)+IF(AG$8=$S42,$T42,0) -> 0 | ... AK42: =IF(AK$8=$R42,-$T42,0)+IF(AK$8=$S42,$T42,0) -> 0
C43: MOVIMENTAÇÕES DO MÊS POR GRUPO DE CONTAS | N43: 35 | X43: =IF(P43<NOW(),1,0) -> 1 | Z43: =IF(Z$8=$R43,-$T43,0)+IF(Z$8=$S43,$T43,0) -> 0 | AA43: =IF(AA$8=$R43,-$T43,0)+IF(AA$8=$S43,$T43,0) -> 0 | AB43: =IF(AB$8=$R43,-$T43,0)+IF(AB$8=$S43,$T43,0) -> 0 | AC43: =IF(AC$8=$R43,-$T43,0)+IF(AC$8=$S43,$T43,0) -> 0 | AD43: =IF(AD$8=$R43,-$T43,0)+IF(AD$8=$S43,$T43,0) -> 0 | AE43: =IF(AE$8=$R43,-$T43,0)+IF(AE$8=$S43,$T43,0) -> 0 | AF43: =IF(AF$8=$R43,-$T43,0)+IF(AF$8=$S43,$T43,0) -> 0 | AG43: =IF(AG$8=$R43,-$T43,0)+IF(AG$8=$S43,$T43,0) -> 0 | ... AK43: =IF(AK$8=$R43,-$T43,0)+IF(AK$8=$S43,$T43,0) -> 0
N44: 36 | X44: =IF(P44<NOW(),1,0) -> 1 | Z44: =IF(Z$8=$R44,-$T44,0)+IF(Z$8=$S44,$T44,0) -> 0 | AA44: =IF(AA$8=$R44,-$T44,0)+IF(AA$8=$S44,$T44,0) -> 0 | AB44: =IF(AB$8=$R44,-$T44,0)+IF(AB$8=$S44,$T44,0) -> 0 | AC44: =IF(AC$8=$R44,-$T44,0)+IF(AC$8=$S44,$T44,0) -> 0 | AD44: =IF(AD$8=$R44,-$T44,0)+IF(AD$8=$S44,$T44,0) -> 0 | AE44: =IF(AE$8=$R44,-$T44,0)+IF(AE$8=$S44,$T44,0) -> 0 | AF44: =IF(AF$8=$R44,-$T44,0)+IF(AF$8=$S44,$T44,0) -> 0 | AG44: =IF(AG$8=$R44,-$T44,0)+IF(AG$8=$S44,$T44,0) -> 0 | ... AK44: =IF(AK$8=$R44,-$T44,0)+IF(AK$8=$S44,$T44,0) -> 0
C45: GRUPO | D45: DESCRIÇÃO | E45: TRANSFERÊNCIAS | F45: SAÍDA | G45: SALDO | N45: 37 | X45: =IF(P45<NOW(),1,0) -> 1 | Z45: =IF(Z$8=$R45,-$T45,0)+IF(Z$8=$S45,$T45,0) -> 0 | AA45: =IF(AA$8=$R45,-$T45,0)+IF(AA$8=$S45,$T45,0) -> 0 | AB45: =IF(AB$8=$R45,-$T45,0)+IF(AB$8=$S45,$T45,0) -> 0 | AC45: =IF(AC$8=$R45,-$T45,0)+IF(AC$8=$S45,$T45,0) -> 0 | AD45: =IF(AD$8=$R45,-$T45,0)+IF(AD$8=$S45,$T45,0) -> 0 | AE45: =IF(AE$8=$R45,-$T45,0)+IF(AE$8=$S45,$T45,0) -> 0 | AF45: =IF(AF$8=$R45,-$T45,0)+IF(AF$8=$S45,$T45,0) -> 0 | AG45: =IF(AG$8=$R45,-$T45,0)+IF(AG$8=$S45,$T45,0) -> 0 | ... AK45: =IF(AK$8=$R45,-$T45,0)+IF(AK$8=$S45,$T45,0) -> 0
E46: ENTRADA | F46: SAÍDA | G46: SALDO | N46: 38 | X46: =IF(P46<NOW(),1,0) -> 1 | Z46: =IF(Z$8=$R46,-$T46,0)+IF(Z$8=$S46,$T46,0) -> 0 | AA46: =IF(AA$8=$R46,-$T46,0)+IF(AA$8=$S46,$T46,0) -> 0 | AB46: =IF(AB$8=$R46,-$T46,0)+IF(AB$8=$S46,$T46,0) -> 0 | AC46: =IF(AC$8=$R46,-$T46,0)+IF(AC$8=$S46,$T46,0) -> 0 | AD46: =IF(AD$8=$R46,-$T46,0)+IF(AD$8=$S46,$T46,0) -> 0 | AE46: =IF(AE$8=$R46,-$T46,0)+IF(AE$8=$S46,$T46,0) -> 0 | AF46: =IF(AF$8=$R46,-$T46,0)+IF(AF$8=$S46,$T46,0) -> 0 | AG46: =IF(AG$8=$R46,-$T46,0)+IF(AG$8=$S46,$T46,0) -> 0 | ... AK46: =IF(AK$8=$R46,-$T46,0)+IF(AK$8=$S46,$T46,0) -> 0
A47: 1 | C47: =ANUAL!$C115 -> CC | D47: =ANUAL!$D115 -> CONTA CORRENTE | E47: =SUMIF($J$28:$J$39,TRUE,E$28:E$39) -> 0 | F47: =SUMIF($J$28:$J$39,TRUE,F$28:F$39) -> 0 | G47: =SUMIF($J$28:$J$39,TRUE,G$28:G$39)+SUMIF($J$9:$J$20,TRUE,E$9:E$20) -> 0 | N47: 39 | X47: =IF(P47<NOW(),1,0) -> 1 | Z47: =IF(Z$8=$R47,-$T47,0)+IF(Z$8=$S47,$T47,0) -> 0 | AA47: =IF(AA$8=$R47,-$T47,0)+IF(AA$8=$S47,$T47,0) -> 0 | AB47: =IF(AB$8=$R47,-$T47,0)+IF(AB$8=$S47,$T47,0) -> 0 | AC47: =IF(AC$8=$R47,-$T47,0)+IF(AC$8=$S47,$T47,0) -> 0 | AD47: =IF(AD$8=$R47,-$T47,0)+IF(AD$8=$S47,$T47,0) -> 0 | AE47: =IF(AE$8=$R47,-$T47,0)+IF(AE$8=$S47,$T47,0) -> 0 | AF47: =IF(AF$8=$R47,-$T47,0)+IF(AF$8=$S47,$T47,0) -> 0 | AG47: =IF(AG$8=$R47,-$T47,0)+IF(AG$8=$S47,$T47,0) -> 0 | ... AK47: =IF(AK$8=$R47,-$T47,0)+IF(AK$8=$S47,$T47,0) -> 0
A48: 2 | C48: =ANUAL!$C116 -> INV | D48: =ANUAL!$D116 -> APLICAÇÕES DE INVESTIMENTO | E48: =SUMIF($K$28:$K$39,TRUE,E$28:E$39) -> 0 | F48: =SUMIF($K$28:$K$39,TRUE,F$28:F$39) -> 0 | G48: =SUMIF($K$28:$K$39,TRUE,G$28:G$39)+SUMIF($K$9:$K$20,TRUE,E$9:E$20) -> 0 | N48: 40 | X48: =IF(P48<NOW(),1,0) -> 1 | Z48: =IF(Z$8=$R48,-$T48,0)+IF(Z$8=$S48,$T48,0) -> 0 | AA48: =IF(AA$8=$R48,-$T48,0)+IF(AA$8=$S48,$T48,0) -> 0 | AB48: =IF(AB$8=$R48,-$T48,0)+IF(AB$8=$S48,$T48,0) -> 0 | AC48: =IF(AC$8=$R48,-$T48,0)+IF(AC$8=$S48,$T48,0) -> 0 | AD48: =IF(AD$8=$R48,-$T48,0)+IF(AD$8=$S48,$T48,0) -> 0 | AE48: =IF(AE$8=$R48,-$T48,0)+IF(AE$8=$S48,$T48,0) -> 0 | AF48: =IF(AF$8=$R48,-$T48,0)+IF(AF$8=$S48,$T48,0) -> 0 | AG48: =IF(AG$8=$R48,-$T48,0)+IF(AG$8=$S48,$T48,0) -> 0 | ... AK48: =IF(AK$8=$R48,-$T48,0)+IF(AK$8=$S48,$T48,0) -> 0
A49: 3 | C49: =ANUAL!$C117 -> DINH | D49: =ANUAL!$D117 -> EM ESPÉCIE | E49: =SUMIF($L$28:$L$39,TRUE,E$28:E$39) -> 0 | F49: =SUMIF($L$28:$L$39,TRUE,F$28:F$39) -> 0 | G49: =SUMIF($L$28:$L$39,TRUE,G$28:G$39)+SUMIF($L$9:$L$20,TRUE,E$9:E$20) -> 0 | N49: 41 | X49: =IF(P49<NOW(),1,0) -> 1 | Z49: =IF(Z$8=$R49,-$T49,0)+IF(Z$8=$S49,$T49,0) -> 0 | AA49: =IF(AA$8=$R49,-$T49,0)+IF(AA$8=$S49,$T49,0) -> 0 | AB49: =IF(AB$8=$R49,-$T49,0)+IF(AB$8=$S49,$T49,0) -> 0 | AC49: =IF(AC$8=$R49,-$T49,0)+IF(AC$8=$S49,$T49,0) -> 0 | AD49: =IF(AD$8=$R49,-$T49,0)+IF(AD$8=$S49,$T49,0) -> 0 | AE49: =IF(AE$8=$R49,-$T49,0)+IF(AE$8=$S49,$T49,0) -> 0 | AF49: =IF(AF$8=$R49,-$T49,0)+IF(AF$8=$S49,$T49,0) -> 0 | AG49: =IF(AG$8=$R49,-$T49,0)+IF(AG$8=$S49,$T49,0) -> 0 | ... AK49: =IF(AK$8=$R49,-$T49,0)+IF(AK$8=$S49,$T49,0) -> 0
N50: 42 | X50: =IF(P50<NOW(),1,0) -> 1 | Z50: =IF(Z$8=$R50,-$T50,0)+IF(Z$8=$S50,$T50,0) -> 0 | AA50: =IF(AA$8=$R50,-$T50,0)+IF(AA$8=$S50,$T50,0) -> 0 | AB50: =IF(AB$8=$R50,-$T50,0)+IF(AB$8=$S50,$T50,0) -> 0 | AC50: =IF(AC$8=$R50,-$T50,0)+IF(AC$8=$S50,$T50,0) -> 0 | AD50: =IF(AD$8=$R50,-$T50,0)+IF(AD$8=$S50,$T50,0) -> 0 | AE50: =IF(AE$8=$R50,-$T50,0)+IF(AE$8=$S50,$T50,0) -> 0 | AF50: =IF(AF$8=$R50,-$T50,0)+IF(AF$8=$S50,$T50,0) -> 0 | AG50: =IF(AG$8=$R50,-$T50,0)+IF(AG$8=$S50,$T50,0) -> 0 | ... AK50: =IF(AK$8=$R50,-$T50,0)+IF(AK$8=$S50,$T50,0) -> 0
N51: 43 | X51: =IF(P51<NOW(),1,0) -> 1 | Z51: =IF(Z$8=$R51,-$T51,0)+IF(Z$8=$S51,$T51,0) -> 0 | AA51: =IF(AA$8=$R51,-$T51,0)+IF(AA$8=$S51,$T51,0) -> 0 | AB51: =IF(AB$8=$R51,-$T51,0)+IF(AB$8=$S51,$T51,0) -> 0 | AC51: =IF(AC$8=$R51,-$T51,0)+IF(AC$8=$S51,$T51,0) -> 0 | AD51: =IF(AD$8=$R51,-$T51,0)+IF(AD$8=$S51,$T51,0) -> 0 | AE51: =IF(AE$8=$R51,-$T51,0)+IF(AE$8=$S51,$T51,0) -> 0 | AF51: =IF(AF$8=$R51,-$T51,0)+IF(AF$8=$S51,$T51,0) -> 0 | AG51: =IF(AG$8=$R51,-$T51,0)+IF(AG$8=$S51,$T51,0) -> 0 | ... AK51: =IF(AK$8=$R51,-$T51,0)+IF(AK$8=$S51,$T51,0) -> 0
N52: 44 | X52: =IF(P52<NOW(),1,0) -> 1 | Z52: =IF(Z$8=$R52,-$T52,0)+IF(Z$8=$S52,$T52,0) -> 0 | AA52: =IF(AA$8=$R52,-$T52,0)+IF(AA$8=$S52,$T52,0) -> 0 | AB52: =IF(AB$8=$R52,-$T52,0)+IF(AB$8=$S52,$T52,0) -> 0 | AC52: =IF(AC$8=$R52,-$T52,0)+IF(AC$8=$S52,$T52,0) -> 0 | AD52: =IF(AD$8=$R52,-$T52,0)+IF(AD$8=$S52,$T52,0) -> 0 | AE52: =IF(AE$8=$R52,-$T52,0)+IF(AE$8=$S52,$T52,0) -> 0 | AF52: =IF(AF$8=$R52,-$T52,0)+IF(AF$8=$S52,$T52,0) -> 0 | AG52: =IF(AG$8=$R52,-$T52,0)+IF(AG$8=$S52,$T52,0) -> 0 | ... AK52: =IF(AK$8=$R52,-$T52,0)+IF(AK$8=$S52,$T52,0) -> 0
C53: ACOMPANHAMENTO DE DESPESAS | N53: 45 | X53: =IF(P53<NOW(),1,0) -> 1 | Z53: =IF(Z$8=$R53,-$T53,0)+IF(Z$8=$S53,$T53,0) -> 0 | AA53: =IF(AA$8=$R53,-$T53,0)+IF(AA$8=$S53,$T53,0) -> 0 | AB53: =IF(AB$8=$R53,-$T53,0)+IF(AB$8=$S53,$T53,0) -> 0 | AC53: =IF(AC$8=$R53,-$T53,0)+IF(AC$8=$S53,$T53,0) -> 0 | AD53: =IF(AD$8=$R53,-$T53,0)+IF(AD$8=$S53,$T53,0) -> 0 | AE53: =IF(AE$8=$R53,-$T53,0)+IF(AE$8=$S53,$T53,0) -> 0 | AF53: =IF(AF$8=$R53,-$T53,0)+IF(AF$8=$S53,$T53,0) -> 0 | AG53: =IF(AG$8=$R53,-$T53,0)+IF(AG$8=$S53,$T53,0) -> 0 | ... AK53: =IF(AK$8=$R53,-$T53,0)+IF(AK$8=$S53,$T53,0) -> 0
N54: 46 | X54: =IF(P54<NOW(),1,0) -> 1 | Z54: =IF(Z$8=$R54,-$T54,0)+IF(Z$8=$S54,$T54,0) -> 0 | AA54: =IF(AA$8=$R54,-$T54,0)+IF(AA$8=$S54,$T54,0) -> 0 | AB54: =IF(AB$8=$R54,-$T54,0)+IF(AB$8=$S54,$T54,0) -> 0 | AC54: =IF(AC$8=$R54,-$T54,0)+IF(AC$8=$S54,$T54,0) -> 0 | AD54: =IF(AD$8=$R54,-$T54,0)+IF(AD$8=$S54,$T54,0) -> 0 | AE54: =IF(AE$8=$R54,-$T54,0)+IF(AE$8=$S54,$T54,0) -> 0 | AF54: =IF(AF$8=$R54,-$T54,0)+IF(AF$8=$S54,$T54,0) -> 0 | AG54: =IF(AG$8=$R54,-$T54,0)+IF(AG$8=$S54,$T54,0) -> 0 | ... AK54: =IF(AK$8=$R54,-$T54,0)+IF(AK$8=$S54,$T54,0) -> 0
C55: CONTAS | D55: DESCRIÇÃO | G55: VALOR | N55: 47 | X55: =IF(P55<NOW(),1,0) -> 1 | Z55: =IF(Z$8=$R55,-$T55,0)+IF(Z$8=$S55,$T55,0) -> 0 | AA55: =IF(AA$8=$R55,-$T55,0)+IF(AA$8=$S55,$T55,0) -> 0 | AB55: =IF(AB$8=$R55,-$T55,0)+IF(AB$8=$S55,$T55,0) -> 0 | AC55: =IF(AC$8=$R55,-$T55,0)+IF(AC$8=$S55,$T55,0) -> 0 | AD55: =IF(AD$8=$R55,-$T55,0)+IF(AD$8=$S55,$T55,0) -> 0 | AE55: =IF(AE$8=$R55,-$T55,0)+IF(AE$8=$S55,$T55,0) -> 0 | AF55: =IF(AF$8=$R55,-$T55,0)+IF(AF$8=$S55,$T55,0) -> 0 | AG55: =IF(AG$8=$R55,-$T55,0)+IF(AG$8=$S55,$T55,0) -> 0 | ... AK55: =IF(AK$8=$R55,-$T55,0)+IF(AK$8=$S55,$T55,0) -> 0
N56: 48 | X56: =IF(P56<NOW(),1,0) -> 1 | Z56: =IF(Z$8=$R56,-$T56,0)+IF(Z$8=$S56,$T56,0) -> 0 | AA56: =IF(AA$8=$R56,-$T56,0)+IF(AA$8=$S56,$T56,0) -> 0 | AB56: =IF(AB$8=$R56,-$T56,0)+IF(AB$8=$S56,$T56,0) -> 0 | AC56: =IF(AC$8=$R56,-$T56,0)+IF(AC$8=$S56,$T56,0) -> 0 | AD56: =IF(AD$8=$R56,-$T56,0)+IF(AD$8=$S56,$T56,0) -> 0 | AE56: =IF(AE$8=$R56,-$T56,0)+IF(AE$8=$S56,$T56,0) -> 0 | AF56: =IF(AF$8=$R56,-$T56,0)+IF(AF$8=$S56,$T56,0) -> 0 | AG56: =IF(AG$8=$R56,-$T56,0)+IF(AG$8=$S56,$T56,0) -> 0 | ... AK56: =IF(AK$8=$R56,-$T56,0)+IF(AK$8=$S56,$T56,0) -> 0
A57: 1 | C57: =ANUAL!$C141 -> M01 | D57: =ANUAL!$D141 -> MORADIA – CONDOMÍNIO | G57: =SUMIF(U$9:U$88,C57,T$9:T$88) -> 0 | N57: 49 | X57: =IF(P57<NOW(),1,0) -> 1 | Z57: =IF(Z$8=$R57,-$T57,0)+IF(Z$8=$S57,$T57,0) -> 0 | AA57: =IF(AA$8=$R57,-$T57,0)+IF(AA$8=$S57,$T57,0) -> 0 | AB57: =IF(AB$8=$R57,-$T57,0)+IF(AB$8=$S57,$T57,0) -> 0 | AC57: =IF(AC$8=$R57,-$T57,0)+IF(AC$8=$S57,$T57,0) -> 0 | AD57: =IF(AD$8=$R57,-$T57,0)+IF(AD$8=$S57,$T57,0) -> 0 | AE57: =IF(AE$8=$R57,-$T57,0)+IF(AE$8=$S57,$T57,0) -> 0 | AF57: =IF(AF$8=$R57,-$T57,0)+IF(AF$8=$S57,$T57,0) -> 0 | AG57: =IF(AG$8=$R57,-$T57,0)+IF(AG$8=$S57,$T57,0) -> 0 | ... AK57: =IF(AK$8=$R57,-$T57,0)+IF(AK$8=$S57,$T57,0) -> 0
A58: 2 | C58: =ANUAL!$C142 -> M02 | D58: =ANUAL!$D142 -> MORADIA – IPTU | G58: =SUMIF(U$9:U$88,C58,T$9:T$88) -> 0 | N58: 50 | X58: =IF(P58<NOW(),1,0) -> 1 | Z58: =IF(Z$8=$R58,-$T58,0)+IF(Z$8=$S58,$T58,0) -> 0 | AA58: =IF(AA$8=$R58,-$T58,0)+IF(AA$8=$S58,$T58,0) -> 0 | AB58: =IF(AB$8=$R58,-$T58,0)+IF(AB$8=$S58,$T58,0) -> 0 | AC58: =IF(AC$8=$R58,-$T58,0)+IF(AC$8=$S58,$T58,0) -> 0 | AD58: =IF(AD$8=$R58,-$T58,0)+IF(AD$8=$S58,$T58,0) -> 0 | AE58: =IF(AE$8=$R58,-$T58,0)+IF(AE$8=$S58,$T58,0) -> 0 | AF58: =IF(AF$8=$R58,-$T58,0)+IF(AF$8=$S58,$T58,0) -> 0 | AG58: =IF(AG$8=$R58,-$T58,0)+IF(AG$8=$S58,$T58,0) -> 0 | ... AK58: =IF(AK$8=$R58,-$T58,0)+IF(AK$8=$S58,$T58,0) -> 0
A59: 3 | C59: =ANUAL!$C143 -> M03 | D59: =ANUAL!$D143 -> MORADIA – ALUGUEL | G59: =SUMIF(U$9:U$88,C59,T$9:T$88) -> 0 | N59: 51 | X59: =IF(P59<NOW(),1,0) -> 1 | Z59: =IF(Z$8=$R59,-$T59,0)+IF(Z$8=$S59,$T59,0) -> 0 | AA59: =IF(AA$8=$R59,-$T59,0)+IF(AA$8=$S59,$T59,0) -> 0 | AB59: =IF(AB$8=$R59,-$T59,0)+IF(AB$8=$S59,$T59,0) -> 0 | AC59: =IF(AC$8=$R59,-$T59,0)+IF(AC$8=$S59,$T59,0) -> 0 | AD59: =IF(AD$8=$R59,-$T59,0)+IF(AD$8=$S59,$T59,0) -> 0 | AE59: =IF(AE$8=$R59,-$T59,0)+IF(AE$8=$S59,$T59,0) -> 0 | AF59: =IF(AF$8=$R59,-$T59,0)+IF(AF$8=$S59,$T59,0) -> 0 | AG59: =IF(AG$8=$R59,-$T59,0)+IF(AG$8=$S59,$T59,0) -> 0 | ... AK59: =IF(AK$8=$R59,-$T59,0)+IF(AK$8=$S59,$T59,0) -> 0
A60: 4 | C60: =ANUAL!$C144 -> M04 | D60: =ANUAL!$D144 -> MORADIA – REFORMA | G60: =SUMIF(U$9:U$88,C60,T$9:T$88) -> 0 | N60: 52 | X60: =IF(P60<NOW(),1,0) -> 1 | Z60: =IF(Z$8=$R60,-$T60,0)+IF(Z$8=$S60,$T60,0) -> 0 | AA60: =IF(AA$8=$R60,-$T60,0)+IF(AA$8=$S60,$T60,0) -> 0 | AB60: =IF(AB$8=$R60,-$T60,0)+IF(AB$8=$S60,$T60,0) -> 0 | AC60: =IF(AC$8=$R60,-$T60,0)+IF(AC$8=$S60,$T60,0) -> 0 | AD60: =IF(AD$8=$R60,-$T60,0)+IF(AD$8=$S60,$T60,0) -> 0 | AE60: =IF(AE$8=$R60,-$T60,0)+IF(AE$8=$S60,$T60,0) -> 0 | AF60: =IF(AF$8=$R60,-$T60,0)+IF(AF$8=$S60,$T60,0) -> 0 | AG60: =IF(AG$8=$R60,-$T60,0)+IF(AG$8=$S60,$T60,0) -> 0 | ... AK60: =IF(AK$8=$R60,-$T60,0)+IF(AK$8=$S60,$T60,0) -> 0
A61: 5 | C61: =ANUAL!$C145 -> U01 | D61: =ANUAL!$D145 -> UTILITIES – ENERGIA ELÉTRICA | G61: =SUMIF(U$9:U$88,C61,T$9:T$88) -> 0 | N61: 53 | X61: =IF(P61<NOW(),1,0) -> 1 | Z61: =IF(Z$8=$R61,-$T61,0)+IF(Z$8=$S61,$T61,0) -> 0 | AA61: =IF(AA$8=$R61,-$T61,0)+IF(AA$8=$S61,$T61,0) -> 0 | AB61: =IF(AB$8=$R61,-$T61,0)+IF(AB$8=$S61,$T61,0) -> 0 | AC61: =IF(AC$8=$R61,-$T61,0)+IF(AC$8=$S61,$T61,0) -> 0 | AD61: =IF(AD$8=$R61,-$T61,0)+IF(AD$8=$S61,$T61,0) -> 0 | AE61: =IF(AE$8=$R61,-$T61,0)+IF(AE$8=$S61,$T61,0) -> 0 | AF61: =IF(AF$8=$R61,-$T61,0)+IF(AF$8=$S61,$T61,0) -> 0 | AG61: =IF(AG$8=$R61,-$T61,0)+IF(AG$8=$S61,$T61,0) -> 0 | ... AK61: =IF(AK$8=$R61,-$T61,0)+IF(AK$8=$S61,$T61,0) -> 0
A62: 6 | C62: =ANUAL!$C146 -> U02 | D62: =ANUAL!$D146 -> UTILITIES – ÁGUA POTÁVEL | G62: =SUMIF(U$9:U$88,C62,T$9:T$88) -> 0 | N62: 54 | X62: =IF(P62<NOW(),1,0) -> 1 | Z62: =IF(Z$8=$R62,-$T62,0)+IF(Z$8=$S62,$T62,0) -> 0 | AA62: =IF(AA$8=$R62,-$T62,0)+IF(AA$8=$S62,$T62,0) -> 0 | AB62: =IF(AB$8=$R62,-$T62,0)+IF(AB$8=$S62,$T62,0) -> 0 | AC62: =IF(AC$8=$R62,-$T62,0)+IF(AC$8=$S62,$T62,0) -> 0 | AD62: =IF(AD$8=$R62,-$T62,0)+IF(AD$8=$S62,$T62,0) -> 0 | AE62: =IF(AE$8=$R62,-$T62,0)+IF(AE$8=$S62,$T62,0) -> 0 | AF62: =IF(AF$8=$R62,-$T62,0)+IF(AF$8=$S62,$T62,0) -> 0 | AG62: =IF(AG$8=$R62,-$T62,0)+IF(AG$8=$S62,$T62,0) -> 0 | ... AK62: =IF(AK$8=$R62,-$T62,0)+IF(AK$8=$S62,$T62,0) -> 0
A63: 7 | C63: =ANUAL!$C147 -> U03 | D63: =ANUAL!$D147 -> UTILITIES – DIVERSOS (ÁGUA, GÁS, SERV. GERAIS) | G63: =SUMIF(U$9:U$88,C63,T$9:T$88) -> 0 | N63: 55 | X63: =IF(P63<NOW(),1,0) -> 1 | Z63: =IF(Z$8=$R63,-$T63,0)+IF(Z$8=$S63,$T63,0) -> 0 | AA63: =IF(AA$8=$R63,-$T63,0)+IF(AA$8=$S63,$T63,0) -> 0 | AB63: =IF(AB$8=$R63,-$T63,0)+IF(AB$8=$S63,$T63,0) -> 0 | AC63: =IF(AC$8=$R63,-$T63,0)+IF(AC$8=$S63,$T63,0) -> 0 | AD63: =IF(AD$8=$R63,-$T63,0)+IF(AD$8=$S63,$T63,0) -> 0 | AE63: =IF(AE$8=$R63,-$T63,0)+IF(AE$8=$S63,$T63,0) -> 0 | AF63: =IF(AF$8=$R63,-$T63,0)+IF(AF$8=$S63,$T63,0) -> 0 | AG63: =IF(AG$8=$R63,-$T63,0)+IF(AG$8=$S63,$T63,0) -> 0 | ... AK63: =IF(AK$8=$R63,-$T63,0)+IF(AK$8=$S63,$T63,0) -> 0
A64: 8 | C64: =ANUAL!$C148 -> S01 | D64: =ANUAL!$D148 -> SAÚDE – PLANO DE SAÚDE | G64: =SUMIF(U$9:U$88,C64,T$9:T$88) -> 0 | N64: 56 | X64: =IF(P64<NOW(),1,0) -> 1 | Z64: =IF(Z$8=$R64,-$T64,0)+IF(Z$8=$S64,$T64,0) -> 0 | AA64: =IF(AA$8=$R64,-$T64,0)+IF(AA$8=$S64,$T64,0) -> 0 | AB64: =IF(AB$8=$R64,-$T64,0)+IF(AB$8=$S64,$T64,0) -> 0 | AC64: =IF(AC$8=$R64,-$T64,0)+IF(AC$8=$S64,$T64,0) -> 0 | AD64: =IF(AD$8=$R64,-$T64,0)+IF(AD$8=$S64,$T64,0) -> 0 | AE64: =IF(AE$8=$R64,-$T64,0)+IF(AE$8=$S64,$T64,0) -> 0 | AF64: =IF(AF$8=$R64,-$T64,0)+IF(AF$8=$S64,$T64,0) -> 0 | AG64: =IF(AG$8=$R64,-$T64,0)+IF(AG$8=$S64,$T64,0) -> 0 | ... AK64: =IF(AK$8=$R64,-$T64,0)+IF(AK$8=$S64,$T64,0) -> 0
A65: 9 | C65: =ANUAL!$C149 -> S02 | D65: =ANUAL!$D149 -> SAÚDE – REMÉDIOS | G65: =SUMIF(U$9:U$88,C65,T$9:T$88) -> 0 | N65: 57 | X65: =IF(P65<NOW(),1,0) -> 1 | Z65: =IF(Z$8=$R65,-$T65,0)+IF(Z$8=$S65,$T65,0) -> 0 | AA65: =IF(AA$8=$R65,-$T65,0)+IF(AA$8=$S65,$T65,0) -> 0 | AB65: =IF(AB$8=$R65,-$T65,0)+IF(AB$8=$S65,$T65,0) -> 0 | AC65: =IF(AC$8=$R65,-$T65,0)+IF(AC$8=$S65,$T65,0) -> 0 | AD65: =IF(AD$8=$R65,-$T65,0)+IF(AD$8=$S65,$T65,0) -> 0 | AE65: =IF(AE$8=$R65,-$T65,0)+IF(AE$8=$S65,$T65,0) -> 0 | AF65: =IF(AF$8=$R65,-$T65,0)+IF(AF$8=$S65,$T65,0) -> 0 | AG65: =IF(AG$8=$R65,-$T65,0)+IF(AG$8=$S65,$T65,0) -> 0 | ... AK65: =IF(AK$8=$R65,-$T65,0)+IF(AK$8=$S65,$T65,0) -> 0
A66: 10 | C66: =ANUAL!$C150 -> S03 | D66: =ANUAL!$D150 -> SAÚDE – ACADEMIA | G66: =SUMIF(U$9:U$88,C66,T$9:T$88) -> 0 | N66: 58 | X66: =IF(P66<NOW(),1,0) -> 1 | Z66: =IF(Z$8=$R66,-$T66,0)+IF(Z$8=$S66,$T66,0) -> 0 | AA66: =IF(AA$8=$R66,-$T66,0)+IF(AA$8=$S66,$T66,0) -> 0 | AB66: =IF(AB$8=$R66,-$T66,0)+IF(AB$8=$S66,$T66,0) -> 0 | AC66: =IF(AC$8=$R66,-$T66,0)+IF(AC$8=$S66,$T66,0) -> 0 | AD66: =IF(AD$8=$R66,-$T66,0)+IF(AD$8=$S66,$T66,0) -> 0 | AE66: =IF(AE$8=$R66,-$T66,0)+IF(AE$8=$S66,$T66,0) -> 0 | AF66: =IF(AF$8=$R66,-$T66,0)+IF(AF$8=$S66,$T66,0) -> 0 | AG66: =IF(AG$8=$R66,-$T66,0)+IF(AG$8=$S66,$T66,0) -> 0 | ... AK66: =IF(AK$8=$R66,-$T66,0)+IF(AK$8=$S66,$T66,0) -> 0
A67: 11 | C67: =ANUAL!$C151 -> C01 | D67: =ANUAL!$D151 -> COMPRAS | G67: =SUMIF(U$9:U$88,C67,T$9:T$88) -> 0 | N67: 59 | X67: =IF(P67<NOW(),1,0) -> 1 | Z67: =IF(Z$8=$R67,-$T67,0)+IF(Z$8=$S67,$T67,0) -> 0 | AA67: =IF(AA$8=$R67,-$T67,0)+IF(AA$8=$S67,$T67,0) -> 0 | AB67: =IF(AB$8=$R67,-$T67,0)+IF(AB$8=$S67,$T67,0) -> 0 | AC67: =IF(AC$8=$R67,-$T67,0)+IF(AC$8=$S67,$T67,0) -> 0 | AD67: =IF(AD$8=$R67,-$T67,0)+IF(AD$8=$S67,$T67,0) -> 0 | AE67: =IF(AE$8=$R67,-$T67,0)+IF(AE$8=$S67,$T67,0) -> 0 | AF67: =IF(AF$8=$R67,-$T67,0)+IF(AF$8=$S67,$T67,0) -> 0 | AG67: =IF(AG$8=$R67,-$T67,0)+IF(AG$8=$S67,$T67,0) -> 0 | ... AK67: =IF(AK$8=$R67,-$T67,0)+IF(AK$8=$S67,$T67,0) -> 0
A68: 12 | C68: =ANUAL!$C152 -> L01 | D68: =ANUAL!$D152 -> LAZER | G68: =SUMIF(U$9:U$88,C68,T$9:T$88) -> 0 | N68: 60 | X68: =IF(P68<NOW(),1,0) -> 1 | Z68: =IF(Z$8=$R68,-$T68,0)+IF(Z$8=$S68,$T68,0) -> 0 | AA68: =IF(AA$8=$R68,-$T68,0)+IF(AA$8=$S68,$T68,0) -> 0 | AB68: =IF(AB$8=$R68,-$T68,0)+IF(AB$8=$S68,$T68,0) -> 0 | AC68: =IF(AC$8=$R68,-$T68,0)+IF(AC$8=$S68,$T68,0) -> 0 | AD68: =IF(AD$8=$R68,-$T68,0)+IF(AD$8=$S68,$T68,0) -> 0 | AE68: =IF(AE$8=$R68,-$T68,0)+IF(AE$8=$S68,$T68,0) -> 0 | AF68: =IF(AF$8=$R68,-$T68,0)+IF(AF$8=$S68,$T68,0) -> 0 | AG68: =IF(AG$8=$R68,-$T68,0)+IF(AG$8=$S68,$T68,0) -> 0 | ... AK68: =IF(AK$8=$R68,-$T68,0)+IF(AK$8=$S68,$T68,0) -> 0
... A88: 32 | C88: =ANUAL!$C172 -> --- | D88: =ANUAL!$D172 -> --- | G88: =SUMIF(U$9:U$88,C88,T$9:T$88) -> 0 | N88: 80 | X88: =IF(P88<NOW(),1,0) -> 1 | Z88: =IF(Z$8=$R88,-$T88,0)+IF(Z$8=$S88,$T88,0) -> 0 | AA88: =IF(AA$8=$R88,-$T88,0)+IF(AA$8=$S88,$T88,0) -> 0 | AB88: =IF(AB$8=$R88,-$T88,0)+IF(AB$8=$S88,$T88,0) -> 0 | AC88: =IF(AC$8=$R88,-$T88,0)+IF(AC$8=$S88,$T88,0) -> 0 | AD88: =IF(AD$8=$R88,-$T88,0)+IF(AD$8=$S88,$T88,0) -> 0 | AE88: =IF(AE$8=$R88,-$T88,0)+IF(AE$8=$S88,$T88,0) -> 0 | AF88: =IF(AF$8=$R88,-$T88,0)+IF(AF$8=$S88,$T88,0) -> 0 | AG88: =IF(AG$8=$R88,-$T88,0)+IF(AG$8=$S88,$T88,0) -> 0 | ... AK88: =IF(AK$8=$R88,-$T88,0)+IF(AK$8=$S88,$T88,0) -> 0

Sheet M4
B1: =DATE(ANUAL!B5,B2,8) -> 40276 | I1: >> | M1: << | W1: >> | AL1: <<
B2: ='M3'!B2+1 -> 4
C5: LISTA DE CONTAS | P5: MOVIMENTAÇÕES DO MÊS
C7: CONTA | D7: DESCRIÇÃO | E7: SALDO | P7: DATA | Q7: DESCRIÇÃO | R7: TRANFERÊNCIAS | T7: VALOR | U7: CODIGO
E8: ANTERIOR | F8: ATUAL | G8: PREVISTO | P8: DATA | Q8: DESCRIÇÃO | R8: SAÍDA | S8: ENTRADA | T8: VALOR | X8: ATUAL | Z8: =$C$9 | AA8: =$C$10 -> INV1 | AB8: =$C$11 -> DINH1 | AC8: =$C$12 -> CRED1 | AD8: =$C$13 -> --- | AE8: =$C$14 -> --- | AF8: =$C$15 -> --- | AG8: =$C$16 -> --- | AH8: =$C$17 -> --- | AI8: =$C$18 -> --- | AJ8: =$C$19 -> --- | AK8: =$C$20 -> ---
A9: 1 | C9: =TRIM(ANUAL!C13) | D9: =TRIM(ANUAL!D13) -> CONTA CORRENTE BANCO 1 | E9: =INDIRECT("M"&B$2-1&"!G"&A9+ROW(A$8)) -> 0 | F9: =E9+SUMIF(X$9:X$88,1,OFFSET($Z$9:$Z$88,0,A9-1)) -> 0 | G9: =E9+SUM(OFFSET($Z$9:$Z$88,0,A9-1)) -> 0 | J9: =NOT(ISERR(SEARCH(J$27,$C9))) -> FALSE | K9: =NOT(ISERR(SEARCH(K$27,$C9))) -> FALSE | L9: =NOT(ISERR(SEARCH(L$27,$C9))) -> FALSE | N9: 1 | X9: =IF(P9<NOW(),1,0) -> 1 | Z9: =IF(Z$8=$R9,-$T9,0)+IF(Z$8=$S9,$T9,0) -> 0 | AA9: =IF(AA$8=$R9,-$T9,0)+IF(AA$8=$S9,$T9,0) -> 0 | AB9: =IF(AB$8=$R9,-$T9,0)+IF(AB$8=$S9,$T9,0) -> 0 | AC9: =IF(AC$8=$R9,-$T9,0)+IF(AC$8=$S9,$T9,0) -> 0 | AD9: =IF(AD$8=$R9,-$T9,0)+IF(AD$8=$S9,$T9,0) -> 0 | AE9: =IF(AE$8=$R9,-$T9,0)+IF(AE$8=$S9,$T9,0) -> 0 | AF9: =IF(AF$8=$R9,-$T9,0)+IF(AF$8=$S9,$T9,0) -> 0 | AG9: =IF(AG$8=$R9,-$T9,0)+IF(AG$8=$S9,$T9,0) -> 0 | ... AK9: =IF(AK$8=$R9,-$T9,0)+IF(AK$8=$S9,$T9,0) -> 0
A10: 2 | C10: =TRIM(ANUAL!C14) -> INV1 | D10: =TRIM(ANUAL!D14) -> POUPANÇA BANCO 1 | E10: =INDIRECT("M"&B$2-1&"!G"&A10+ROW(A$8)) -> 0 | F10: =E10+SUMIF(X$9:X$88,1,OFFSET($Z$9:$Z$88,0,A10-1)) -> 0 | G10: =E10+SUM(OFFSET($Z$9:$Z$88,0,A10-1)) -> 0 | J10: =NOT(ISERR(SEARCH(J$27,$C10))) -> FALSE | K10: =NOT(ISERR(SEARCH(K$27,$C10))) -> TRUE | L10: =NOT(ISERR(SEARCH(L$27,$C10))) -> FALSE | N10: 2 | X10: =IF(P10<NOW(),1,0) -> 1 | Z10: =IF(Z$8=$R10,-$T10,0)+IF(Z$8=$S10,$T10,0) -> 0 | AA10: =IF(AA$8=$R10,-$T10,0)+IF(AA$8=$S10,$T10,0) -> 0 | AB10: =IF(AB$8=$R10,-$T10,0)+IF(AB$8=$S10,$T10,0) -> 0 | AC10: =IF(AC$8=$R10,-$T10,0)+IF(AC$8=$S10,$T10,0) -> 0 | AD10: =IF(AD$8=$R10,-$T10,0)+IF(AD$8=$S10,$T10,0) -> 0 | AE10: =IF(AE$8=$R10,-$T10,0)+IF(AE$8=$S10,$T10,0) -> 0 | AF10: =IF(AF$8=$R10,-$T10,0)+IF(AF$8=$S10,$T10,0) -> 0 | AG10: =IF(AG$8=$R10,-$T10,0)+IF(AG$8=$S10,$T10,0) -> 0 | ... AK10: =IF(AK$8=$R10,-$T10,0)+IF(AK$8=$S10,$T10,0) -> 0
A11: 3 | C11: =TRIM(ANUAL!C15) -> DINH1 | D11: =TRIM(ANUAL!D15) -> EM ESPÉCIE | E11: =INDIRECT("M"&B$2-1&"!G"&A11+ROW(A$8)) -> 0 | F11: =E11+SUMIF(X$9:X$88,1,OFFSET($Z$9:$Z$88,0,A11-1)) -> 0 | G11: =E11+SUM(OFFSET($Z$9:$Z$88,0,A11-1)) -> 0 | J11: =NOT(ISERR(SEARCH(J$27,$C11))) -> FALSE | K11: =NOT(ISERR(SEARCH(K$27,$C11))) -> FALSE | L11: =NOT(ISERR(SEARCH(L$27,$C11))) -> TRUE | N11: 3 | X11: =IF(P11<NOW(),1,0) -> 1 | Z11: =IF(Z$8=$R11,-$T11,0)+IF(Z$8=$S11,$T11,0) -> 0 | AA11: =IF(AA$8=$R11,-$T11,0)+IF(AA$8=$S11,$T11,0) -> 0 | AB11: =IF(AB$8=$R11,-$T11,0)+IF(AB$8=$S11,$T11,0) -> 0 | AC11: =IF(AC$8=$R11,-$T11,0)+IF(AC$8=$S11,$T11,0) -> 0 | AD11: =IF(AD$8=$R11,-$T11,0)+IF(AD$8=$S11,$T11,0) -> 0 | AE11: =IF(AE$8=$R11,-$T11,0)+IF(AE$8=$S11,$T11,0) -> 0 | AF11: =IF(AF$8=$R11,-$T11,0)+IF(AF$8=$S11,$T11,0) -> 0 | AG11: =IF(AG$8=$R11,-$T11,0)+IF(AG$8=$S11,$T11,0) -> 0 | ... AK11: =IF(AK$8=$R11,-$T11,0)+IF(AK$8=$S11,$T11,0) -> 0
A12: 4 | C12: =TRIM(ANUAL!C16) -> CRED1 | D12: =TRIM(ANUAL!D16) -> CARTÃO DE CRÉDITO 1 | E12: =INDIRECT("M"&B$2-1&"!G"&A12+ROW(A$8)) -> 0 | F12: =E12+SUMIF(X$9:X$88,1,OFFSET($Z$9:$Z$88,0,A12-1)) -> 0 | G12: =E12+SUM(OFFSET($Z$9:$Z$88,0,A12-1)) -> 0 | J12: =NOT(ISERR(SEARCH(J$27,$C12))) -> FALSE | K12: =NOT(ISERR(SEARCH(K$27,$C12))) -> FALSE | L12: =NOT(ISERR(SEARCH(L$27,$C12))) -> FALSE | N12: 4 | X12: =IF(P12<NOW(),1,0) -> 1 | Z12: =IF(Z$8=$R12,-$T12,0)+IF(Z$8=$S12,$T12,0) -> 0 | AA12: =IF(AA$8=$R12,-$T12,0)+IF(AA$8=$S12,$T12,0) -> 0 | AB12: =IF(AB$8=$R12,-$T12,0)+IF(AB$8=$S12,$T12,0) -> 0 | AC12: =IF(AC$8=$R12,-$T12,0)+IF(AC$8=$S12,$T12,0) -> 0 | AD12: =IF(AD$8=$R12,-$T12,0)+IF(AD$8=$S12,$T12,0) -> 0 | AE12: =IF(AE$8=$R12,-$T12,0)+IF(AE$8=$S12,$T12,0) -> 0 | AF12: =IF(AF$8=$R12,-$T12,0)+IF(AF$8=$S12,$T12,0) -> 0 | AG12: =IF(AG$8=$R12,-$T12,0)+IF(AG$8=$S12,$T12,0) -> 0 | ... AK12: =IF(AK$8=$R12,-$T12,0)+IF(AK$8=$S12,$T12,0) -> 0
A13: 5 | C13: =TRIM(ANUAL!C17) -> --- | D13: =TRIM(ANUAL!D17) | E13: =INDIRECT("M"&B$2-1&"!G"&A13+ROW(A$8)) -> 0 | F13: =E13+SUMIF(X$9:X$88,1,OFFSET($Z$9:$Z$88,0,A13-1)) -> 0 | G13: =E13+SUM(OFFSET($Z$9:$Z$88,0,A13-1)) -> 0 | J13: =NOT(ISERR(SEARCH(J$27,$C13))) -> FALSE | K13: =NOT(ISERR(SEARCH(K$27,$C13))) -> FALSE | L13: =NOT(ISERR(SEARCH(L$27,$C13))) -> FALSE | N13: 5 | X13: =IF(P13<NOW(),1,0) -> 1 | Z13: =IF(Z$8=$R13,-$T13,0)+IF(Z$8=$S13,$T13,0) -> 0 | AA13: =IF(AA$8=$R13,-$T13,0)+IF(AA$8=$S13,$T13,0) -> 0 | AB13: =IF(AB$8=$R13,-$T13,0)+IF(AB$8=$S13,$T13,0) -> 0 | AC13: =IF(AC$8=$R13,-$T13,0)+IF(AC$8=$S13,$T13,0) -> 0 | AD13: =IF(AD$8=$R13,-$T13,0)+IF(AD$8=$S13,$T13,0) -> 0 | AE13: =IF(AE$8=$R13,-$T13,0)+IF(AE$8=$S13,$T13,0) -> 0 | AF13: =IF(AF$8=$R13,-$T13,0)+IF(AF$8=$S13,$T13,0) -> 0 | AG13: =IF(AG$8=$R13,-$T13,0)+IF(AG$8=$S13,$T13,0) -> 0 | ... AK13: =IF(AK$8=$R13,-$T13,0)+IF(AK$8=$S13,$T13,0) -> 0
A14: 6 | C14: =TRIM(ANUAL!C18) -> --- | D14: =TRIM(ANUAL!D18) | E14: =INDIRECT("M"&B$2-1&"!G"&A14+ROW(A$8)) -> 0 | F14: =E14+SUMIF(X$9:X$88,1,OFFSET($Z$9:$Z$88,0,A14-1)) -> 0 | G14: =E14+SUM(OFFSET($Z$9:$Z$88,0,A14-1)) -> 0 | J14: =NOT(ISERR(SEARCH(J$27,$C14))) -> FALSE | K14: =NOT(ISERR(SEARCH(K$27,$C14))) -> FALSE | L14: =NOT(ISERR(SEARCH(L$27,$C14))) -> FALSE | N14: 6 | X14: =IF(P14<NOW(),1,0) -> 1 | Z14: =IF(Z$8=$R14,-$T14,0)+IF(Z$8=$S14,$T14,0) -> 0 | AA14: =IF(AA$8=$R14,-$T14,0)+IF(AA$8=$S14,$T14,0) -> 0 | AB14: =IF(AB$8=$R14,-$T14,0)+IF(AB$8=$S14,$T14,0) -> 0 | AC14: =IF(AC$8=$R14,-$T14,0)+IF(AC$8=$S14,$T14,0) -> 0 | AD14: =IF(AD$8=$R14,-$T14,0)+IF(AD$8=$S14,$T14,0) -> 0 | AE14: =IF(AE$8=$R14,-$T14,0)+IF(AE$8=$S14,$T14,0) -> 0 | AF14: =IF(AF$8=$R14,-$T14,0)+IF(AF$8=$S14,$T14,0) -> 0 | AG14: =IF(AG$8=$R14,-$T14,0)+IF(AG$8=$S14,$T14,0) -> 0 | ... AK14: =IF(AK$8=$R14,-$T14,0)+IF(AK$8=$S14,$T14,0) -> 0
A15: 7 | C15: =TRIM(ANUAL!C19) -> --- | D15: =TRIM(ANUAL!D19) | E15: =INDIRECT("M"&B$2-1&"!G"&A15+ROW(A$8)) -> 0 | F15: =E15+SUMIF(X$9:X$88,1,OFFSET($Z$9:$Z$88,0,A15-1)) -> 0 | G15: =E15+SUM(OFFSET($Z$9:$Z$88,0,A15-1)) -> 0 | J15: =NOT(ISERR(SEARCH(J$27,$C15))) -> FALSE | K15: =NOT(ISERR(SEARCH(K$27,$C15))) -> FALSE | L15: =NOT(ISERR(SEARCH(L$27,$C15))) -> FALSE | N15: 7 | X15: =IF(P15<NOW(),1,0) -> 1 | Z15: =IF(Z$8=$R15,-$T15,0)+IF(Z$8=$S15,$T15,0) -> 0 | AA15: =IF(AA$8=$R15,-$T15,0)+IF(AA$8=$S15,$T15,0) -> 0 | AB15: =IF(AB$8=$R15,-$T15,0)+IF(AB$8=$S15,$T15,0) -> 0 | AC15: =IF(AC$8=$R15,-$T15,0)+IF(AC$8=$S15,$T15,0) -> 0 | AD15: =IF(AD$8=$R15,-$T15,0)+IF(AD$8=$S15,$T15,0) -> 0 | AE15: =IF(AE$8=$R15,-$T15,0)+IF(AE$8=$S15,$T15,0) -> 0 | AF15: =IF(AF$8=$R15,-$T15,0)+IF(AF$8=$S15,$T15,0) -> 0 | AG15: =IF(AG$8=$R15,-$T15,0)+IF(AG$8=$S15,$T15,0) -> 0 | ... AK15: =IF(AK$8=$R15,-$T15,0)+IF(AK$8=$S15,$T15,0) -> 0
A16: 8 | C16: =TRIM(ANUAL!C20) -> --- | D16: =TRIM(ANUAL!D20) | E16: =INDIRECT("M"&B$2-1&"!G"&A16+ROW(A$8)) -> 0 | F16: =E16+SUMIF(X$9:X$88,1,OFFSET($Z$9:$Z$88,0,A16-1)) -> 0 | G16: =E16+SUM(OFFSET($Z$9:$Z$88,0,A16-1)) -> 0 | J16: =NOT(ISERR(SEARCH(J$27,$C16))) -> FALSE | K16: =NOT(ISERR(SEARCH(K$27,$C16))) -> FALSE | L16: =NOT(ISERR(SEARCH(L$27,$C16))) -> FALSE | N16: 8 | X16: =IF(P16<NOW(),1,0) -> 1 | Z16: =IF(Z$8=$R16,-$T16,0)+IF(Z$8=$S16,$T16,0) -> 0 | AA16: =IF(AA$8=$R16,-$T16,0)+IF(AA$8=$S16,$T16,0) -> 0 | AB16: =IF(AB$8=$R16,-$T16,0)+IF(AB$8=$S16,$T16,0) -> 0 | AC16: =IF(AC$8=$R16,-$T16,0)+IF(AC$8=$S16,$T16,0) -> 0 | AD16: =IF(AD$8=$R16,-$T16,0)+IF(AD$8=$S16,$T16,0) -> 0 | AE16: =IF(AE$8=$R16,-$T16,0)+IF(AE$8=$S16,$T16,0) -> 0 | AF16: =IF(AF$8=$R16,-$T16,0)+IF(AF$8=$S16,$T16,0) -> 0 | AG16: =IF(AG$8=$R16,-$T16,0)+IF(AG$8=$S16,$T16,0) -> 0 | ... AK16: =IF(AK$8=$R16,-$T16,0)+IF(AK$8=$S16,$T16,0) -> 0
A17: 9 | C17: =TRIM(ANUAL!C21) -> --- | D17: =TRIM(ANUAL!D21) | E17: =INDIRECT("M"&B$2-1&"!G"&A17+ROW(A$8)) -> 0 | F17: =E17+SUMIF(X$9:X$88,1,OFFSET($Z$9:$Z$88,0,A17-1)) -> 0 | G17: =E17+SUM(OFFSET($Z$9:$Z$88,0,A17-1)) -> 0 | J17: =NOT(ISERR(SEARCH(J$27,$C17))) -> FALSE | K17: =NOT(ISERR(SEARCH(K$27,$C17))) -> FALSE | L17: =NOT(ISERR(SEARCH(L$27,$C17))) -> FALSE | N17: 9 | X17: =IF(P17<NOW(),1,0) -> 1 | Z17: =IF(Z$8=$R17,-$T17,0)+IF(Z$8=$S17,$T17,0) -> 0 | AA17: =IF(AA$8=$R17,-$T17,0)+IF(AA$8=$S17,$T17,0) -> 0 | AB17: =IF(AB$8=$R17,-$T17,0)+IF(AB$8=$S17,$T17,0) -> 0 | AC17: =IF(AC$8=$R17,-$T17,0)+IF(AC$8=$S17,$T17,0) -> 0 | AD17: =IF(AD$8=$R17,-$T17,0)+IF(AD$8=$S17,$T17,0) -> 0 | AE17: =IF(AE$8=$R17,-$T17,0)+IF(AE$8=$S17,$T17,0) -> 0 | AF17: =IF(AF$8=$R17,-$T17,0)+IF(AF$8=$S17,$T17,0) -> 0 | AG17: =IF(AG$8=$R17,-$T17,0)+IF(AG$8=$S17,$T17,0) -> 0 | ... AK17: =IF(AK$8=$R17,-$T17,0)+IF(AK$8=$S17,$T17,0) -> 0
A18: 10 | C18: =TRIM(ANUAL!C22) -> --- | D18: =TRIM(ANUAL!D22) | E18: =INDIRECT("M"&B$2-1&"!G"&A18+ROW(A$8)) -> 0 | F18: =E18+SUMIF(X$9:X$88,1,OFFSET($Z$9:$Z$88,0,A18-1)) -> 0 | G18: =E18+SUM(OFFSET($Z$9:$Z$88,0,A18-1)) -> 0 | J18: =NOT(ISERR(SEARCH(J$27,$C18))) -> FALSE | K18: =NOT(ISERR(SEARCH(K$27,$C18))) -> FALSE | L18: =NOT(ISERR(SEARCH(L$27,$C18))) -> FALSE | N18: 10 | X18: =IF(P18<NOW(),1,0) -> 1 | Z18: =IF(Z$8=$R18,-$T18,0)+IF(Z$8=$S18,$T18,0) -> 0 | AA18: =IF(AA$8=$R18,-$T18,0)+IF(AA$8=$S18,$T18,0) -> 0 | AB18: =IF(AB$8=$R18,-$T18,0)+IF(AB$8=$S18,$T18,0) -> 0 | AC18: =IF(AC$8=$R18,-$T18,0)+IF(AC$8=$S18,$T18,0) -> 0 | AD18: =IF(AD$8=$R18,-$T18,0)+IF(AD$8=$S18,$T18,0) -> 0 | AE18: =IF(AE$8=$R18,-$T18,0)+IF(AE$8=$S18,$T18,0) -> 0 | AF18: =IF(AF$8=$R18,-$T18,0)+IF(AF$8=$S18,$T18,0) -> 0 | AG18: =IF(AG$8=$R18,-$T18,0)+IF(AG$8=$S18,$T18,0) -> 0 | ... AK18: =IF(AK$8=$R18,-$T18,0)+IF(AK$8=$S18,$T18,0) -> 0
A19: 11 | C19: =TRIM(ANUAL!C23) -> --- | D19: =TRIM(ANUAL!D23) | E19: =INDIRECT("M"&B$2-1&"!G"&A19+ROW(A$8)) -> 0 | F19: =E19+SUMIF(X$9:X$88,1,OFFSET($Z$9:$Z$88,0,A19-1)) -> 0 | G19: =E19+SUM(OFFSET($Z$9:$Z$88,0,A19-1)) -> 0 | J19: =NOT(ISERR(SEARCH(J$27,$C19))) -> FALSE | K19: =NOT(ISERR(SEARCH(K$27,$C19))) -> FALSE | L19: =NOT(ISERR(SEARCH(L$27,$C19))) -> FALSE | N19: 11 | X19: =IF(P19<NOW(),1,0) -> 1 | Z19: =IF(Z$8=$R19,-$T19,0)+IF(Z$8=$S19,$T19,0) -> 0 | AA19: =IF(AA$8=$R19,-$T19,0)+IF(AA$8=$S19,$T19,0) -> 0 | AB19: =IF(AB$8=$R19,-$T19,0)+IF(AB$8=$S19,$T19,0) -> 0 | AC19: =IF(AC$8=$R19,-$T19,0)+IF(AC$8=$S19,$T19,0) -> 0 | AD19: =IF(AD$8=$R19,-$T19,0)+IF(AD$8=$S19,$T19,0) -> 0 | AE19: =IF(AE$8=$R19,-$T19,0)+IF(AE$8=$S19,$T19,0) -> 0 | AF19: =IF(AF$8=$R19,-$T19,0)+IF(AF$8=$S19,$T19,0) -> 0 | AG19: =IF(AG$8=$R19,-$T19,0)+IF(AG$8=$S19,$T19,0) -> 0 | ... AK19: =IF(AK$8=$R19,-$T19,0)+IF(AK$8=$S19,$T19,0) -> 0
A20: 12 | C20: =TRIM(ANUAL!C24) -> --- | D20: =TRIM(ANUAL!D24) | E20: =INDIRECT("M"&B$2-1&"!G"&A20+ROW(A$8)) -> 0 | F20: =E20+SUMIF(X$9:X$88,1,OFFSET($Z$9:$Z$88,0,A20-1)) -> 0 | G20: =E20+SUM(OFFSET($Z$9:$Z$88,0,A20-1)) -> 0 | J20: =NOT(ISERR(SEARCH(J$27,$C20))) -> FALSE | K20: =NOT(ISERR(SEARCH(K$27,$C20))) -> FALSE | L20: =NOT(ISERR(SEARCH(L$27,$C20))) -> FALSE | N20: 12 | X20: =IF(P20<NOW(),1,0) -> 1 | Z20: =IF(Z$8=$R20,-$T20,0)+IF(Z$8=$S20,$T20,0) -> 0 | AA20: =IF(AA$8=$R20,-$T20,0)+IF(AA$8=$S20,$T20,0) -> 0 | AB20: =IF(AB$8=$R20,-$T20,0)+IF(AB$8=$S20,$T20,0) -> 0 | AC20: =IF(AC$8=$R20,-$T20,0)+IF(AC$8=$S20,$T20,0) -> 0 | AD20: =IF(AD$8=$R20,-$T20,0)+IF(AD$8=$S20,$T20,0) -> 0 | AE20: =IF(AE$8=$R20,-$T20,0)+IF(AE$8=$S20,$T20,0) -> 0 | AF20: =IF(AF$8=$R20,-$T20,0)+IF(AF$8=$S20,$T20,0) -> 0 | AG20: =IF(AG$8=$R20,-$T20,0)+IF(AG$8=$S20,$T20,0) -> 0 | ... AK20: =IF(AK$8=$R20,-$T20,0)+IF(AK$8=$S20,$T20,0) -> 0
N21: 13 | X21: =IF(P21<NOW(),1,0) -> 1 | Z21: =IF(Z$8=$R21,-$T21,0)+IF(Z$8=$S21,$T21,0) -> 0 | AA21: =IF(AA$8=$R21,-$T21,0)+IF(AA$8=$S21,$T21,0) -> 0 | AB21: =IF(AB$8=$R21,-$T21,0)+IF(AB$8=$S21,$T21,0) -> 0 | AC21: =IF(AC$8=$R21,-$T21,0)+IF(AC$8=$S21,$T21,0) -> 0 | AD21: =IF(AD$8=$R21,-$T21,0)+IF(AD$8=$S21,$T21,0) -> 0 | AE21: =IF(AE$8=$R21,-$T21,0)+IF(AE$8=$S21,$T21,0) -> 0 | AF21: =IF(AF$8=$R21,-$T21,0)+IF(AF$8=$S21,$T21,0) -> 0 | AG21: =IF(AG$8=$R21,-$T21,0)+IF(AG$8=$S21,$T21,0) -> 0 | ... AK21: =IF(AK$8=$R21,-$T21,0)+IF(AK$8=$S21,$T21,0) -> 0
N22: 14 | X22: =IF(P22<NOW(),1,0) -> 1 | Z22: =IF(Z$8=$R22,-$T22,0)+IF(Z$8=$S22,$T22,0) -> 0 | AA22: =IF(AA$8=$R22,-$T22,0)+IF(AA$8=$S22,$T22,0) -> 0 | AB22: =IF(AB$8=$R22,-$T22,0)+IF(AB$8=$S22,$T22,0) -> 0 | AC22: =IF(AC$8=$R22,-$T22,0)+IF(AC$8=$S22,$T22,0) -> 0 | AD22: =IF(AD$8=$R22,-$T22,0)+IF(AD$8=$S22,$T22,0) -> 0 | AE22: =IF(AE$8=$R22,-$T22,0)+IF(AE$8=$S22,$T22,0) -> 0 | AF22: =IF(AF$8=$R22,-$T22,0)+IF(AF$8=$S22,$T22,0) -> 0 | AG22: =IF(AG$8=$R22,-$T22,0)+IF(AG$8=$S22,$T22,0) -> 0 | ... AK22: =IF(AK$8=$R22,-$T22,0)+IF(AK$8=$S22,$T22,0) -> 0
N23: 15 | X23: =IF(P23<NOW(),1,0) -> 1 | Z23: =IF(Z$8=$R23,-$T23,0)+IF(Z$8=$S23,$T23,0) -> 0 | AA23: =IF(AA$8=$R23,-$T23,0)+IF(AA$8=$S23,$T23,0) -> 0 | AB23: =IF(AB$8=$R23,-$T23,0)+IF(AB$8=$S23,$T23,0) -> 0 | AC23: =IF(AC$8=$R23,-$T23,0)+IF(AC$8=$S23,$T23,0) -> 0 | AD23: =IF(AD$8=$R23,-$T23,0)+IF(AD$8=$S23,$T23,0) -> 0 | AE23: =IF(AE$8=$R23,-$T23,0)+IF(AE$8=$S23,$T23,0) -> 0 | AF23: =IF(AF$8=$R23,-$T23,0)+IF(AF$8=$S23,$T23,0) -> 0 | AG23: =IF(AG$8=$R23,-$T23,0)+IF(AG$8=$S23,$T23,0) -> 0 | ... AK23: =IF(AK$8=$R23,-$T23,0)+IF(AK$8=$S23,$T23,0) -> 0
C24: VARIAÇÃO MENSAL POR CONTA | N24: 16 | X24: =IF(P24<NOW(),1,0) -> 1 | Z24: =IF(Z$8=$R24,-$T24,0)+IF(Z$8=$S24,$T24,0) -> 0 | AA24: =IF(AA$8=$R24,-$T24,0)+IF(AA$8=$S24,$T24,0) -> 0 | AB24: =IF(AB$8=$R24,-$T24,0)+IF(AB$8=$S24,$T24,0) -> 0 | AC24: =IF(AC$8=$R24,-$T24,0)+IF(AC$8=$S24,$T24,0) -> 0 | AD24: =IF(AD$8=$R24,-$T24,0)+IF(AD$8=$S24,$T24,0) -> 0 | AE24: =IF(AE$8=$R24,-$T24,0)+IF(AE$8=$S24,$T24,0) -> 0 | AF24: =IF(AF$8=$R24,-$T24,0)+IF(AF$8=$S24,$T24,0) -> 0 | AG24: =IF(AG$8=$R24,-$T24,0)+IF(AG$8=$S24,$T24,0) -> 0 | ... AK24: =IF(AK$8=$R24,-$T24,0)+IF(AK$8=$S24,$T24,0) -> 0
N25: 17 | X25: =IF(P25<NOW(),1,0) -> 1 | Z25: =IF(Z$8=$R25,-$T25,0)+IF(Z$8=$S25,$T25,0) -> 0 | AA25: =IF(AA$8=$R25,-$T25,0)+IF(AA$8=$S25,$T25,0) -> 0 | AB25: =IF(AB$8=$R25,-$T25,0)+IF(AB$8=$S25,$T25,0) -> 0 | AC25: =IF(AC$8=$R25,-$T25,0)+IF(AC$8=$S25,$T25,0) -> 0 | AD25: =IF(AD$8=$R25,-$T25,0)+IF(AD$8=$S25,$T25,0) -> 0 | AE25: =IF(AE$8=$R25,-$T25,0)+IF(AE$8=$S25,$T25,0) -> 0 | AF25: =IF(AF$8=$R25,-$T25,0)+IF(AF$8=$S25,$T25,0) -> 0 | AG25: =IF(AG$8=$R25,-$T25,0)+IF(AG$8=$S25,$T25,0) -> 0 | ... AK25: =IF(AK$8=$R25,-$T25,0)+IF(AK$8=$S25,$T25,0) -> 0
C26: CONTA | D26: DESCRIÇÃO | E26: TRANSFERÊNCIAS | F26: SAÍDA | G26: SALDO | N26: 18 | X26: =IF(P26<NOW(),1,0) -> 1 | Z26: =IF(Z$8=$R26,-$T26,0)+IF(Z$8=$S26,$T26,0) -> 0 | AA26: =IF(AA$8=$R26,-$T26,0)+IF(AA$8=$S26,$T26,0) -> 0 | AB26: =IF(AB$8=$R26,-$T26,0)+IF(AB$8=$S26,$T26,0) -> 0 | AC26: =IF(AC$8=$R26,-$T26,0)+IF(AC$8=$S26,$T26,0) -> 0 | AD26: =IF(AD$8=$R26,-$T26,0)+IF(AD$8=$S26,$T26,0) -> 0 | AE26: =IF(AE$8=$R26,-$T26,0)+IF(AE$8=$S26,$T26,0) -> 0 | AF26: =IF(AF$8=$R26,-$T26,0)+IF(AF$8=$S26,$T26,0) -> 0 | AG26: =IF(AG$8=$R26,-$T26,0)+IF(AG$8=$S26,$T26,0) -> 0 | ... AK26: =IF(AK$8=$R26,-$T26,0)+IF(AK$8=$S26,$T26,0) -> 0
E27: ENTRADA | F27: SAÍDA | G27: VARIAÇÃO | J27: =ANUAL!C115 -> CC | K27: =ANUAL!C116 -> INV | L27: =ANUAL!C117 -> DINH | N27: 19 | X27: =IF(P27<NOW(),1,0) -> 1 | Z27: =IF(Z$8=$R27,-$T27,0)+IF(Z$8=$S27,$T27,0) -> 0 | AA27: =IF(AA$8=$R27,-$T27,0)+IF(AA$8=$S27,$T27,0) -> 0 | AB27: =IF(AB$8=$R27,-$T27,0)+IF(AB$8=$S27,$T27,0) -> 0 | AC27: =IF(AC$8=$R27,-$T27,0)+IF(AC$8=$S27,$T27,0) -> 0 | AD27: =IF(AD$8=$R27,-$T27,0)+IF(AD$8=$S27,$T27,0) -> 0 | AE27: =IF(AE$8=$R27,-$T27,0)+IF(AE$8=$S27,$T27,0) -> 0 | AF27: =IF(AF$8=$R27,-$T27,0)+IF(AF$8=$S27,$T27,0) -> 0 | AG27: =IF(AG$8=$R27,-$T27,0)+IF(AG$8=$S27,$T27,0) -> 0 | ... AK27: =IF(AK$8=$R27,-$T27,0)+IF(AK$8=$S27,$T27,0) -> 0
A28: 1 | C28: =C9 | D28: =D9 -> CONTA CORRENTE BANCO 1 | E28: =SUMIF(OFFSET($Z$9:$Z$88,0,A28-1),">0") -> 0 | F28: =SUMIF(OFFSET($Z$9:$Z$88,0,A28-1),"<0") -> 0 | G28: =SUM(E28:F28) -> 0 | J28: =NOT(ISERR(SEARCH(J$27,$C28))) -> FALSE | K28: =NOT(ISERR(SEARCH(K$27,$C28))) -> FALSE | L28: =NOT(ISERR(SEARCH(L$27,$C28))) -> FALSE | N28: 20 | X28: =IF(P28<NOW(),1,0) -> 1 | Z28: =IF(Z$8=$R28,-$T28,0)+IF(Z$8=$S28,$T28,0) -> 0 | AA28: =IF(AA$8=$R28,-$T28,0)+IF(AA$8=$S28,$T28,0) -> 0 | AB28: =IF(AB$8=$R28,-$T28,0)+IF(AB$8=$S28,$T28,0) -> 0 | AC28: =IF(AC$8=$R28,-$T28,0)+IF(AC$8=$S28,$T28,0) -> 0 | AD28: =IF(AD$8=$R28,-$T28,0)+IF(AD$8=$S28,$T28,0) -> 0 | AE28: =IF(AE$8=$R28,-$T28,0)+IF(AE$8=$S28,$T28,0) -> 0 | AF28: =IF(AF$8=$R28,-$T28,0)+IF(AF$8=$S28,$T28,0) -> 0 | AG28: =IF(AG$8=$R28,-$T28,0)+IF(AG$8=$S28,$T28,0) -> 0 | ... AK28: =IF(AK$8=$R28,-$T28,0)+IF(AK$8=$S28,$T28,0) -> 0
A29: 2 | C29: =C10 -> INV1 | D29: =D10 -> POUPANÇA BANCO 1 | E29: =SUMIF(OFFSET($Z$9:$Z$88,0,A29-1),">0") -> 0 | F29: =SUMIF(OFFSET($Z$9:$Z$88,0,A29-1),"<0") -> 0 | G29: =SUM(E29:F29) -> 0 | J29: =NOT(ISERR(SEARCH(J$27,$C29))) -> FALSE | K29: =NOT(ISERR(SEARCH(K$27,$C29))) -> TRUE | L29: =NOT(ISERR(SEARCH(L$27,$C29))) -> FALSE | N29: 21 | X29: =IF(P29<NOW(),1,0) -> 1 | Z29: =IF(Z$8=$R29,-$T29,0)+IF(Z$8=$S29,$T29,0) -> 0 | AA29: =IF(AA$8=$R29,-$T29,0)+IF(AA$8=$S29,$T29,0) -> 0 | AB29: =IF(AB$8=$R29,-$T29,0)+IF(AB$8=$S29,$T29,0) -> 0 | AC29: =IF(AC$8=$R29,-$T29,0)+IF(AC$8=$S29,$T29,0) -> 0 | AD29: =IF(AD$8=$R29,-$T29,0)+IF(AD$8=$S29,$T29,0) -> 0 | AE29: =IF(AE$8=$R29,-$T29,0)+IF(AE$8=$S29,$T29,0) -> 0 | AF29: =IF(AF$8=$R29,-$T29,0)+IF(AF$8=$S29,$T29,0) -> 0 | AG29: =IF(AG$8=$R29,-$T29,0)+IF(AG$8=$S29,$T29,0) -> 0 | ... AK29: =IF(AK$8=$R29,-$T29,0)+IF(AK$8=$S29,$T29,0) -> 0
A30: 3 | C30: =C11 -> DINH1 | D30: =D11 -> EM ESPÉCIE | E30: =SUMIF(OFFSET($Z$9:$Z$88,0,A30-1),">0") -> 0 | F30: =SUMIF(OFFSET($Z$9:$Z$88,0,A30-1),"<0") -> 0 | G30: =SUM(E30:F30) -> 0 | J30: =NOT(ISERR(SEARCH(J$27,$C30))) -> FALSE | K30: =NOT(ISERR(SEARCH(K$27,$C30))) -> FALSE | L30: =NOT(ISERR(SEARCH(L$27,$C30))) -> TRUE | N30: 22 | X30: =IF(P30<NOW(),1,0) -> 1 | Z30: =IF(Z$8=$R30,-$T30,0)+IF(Z$8=$S30,$T30,0) -> 0 | AA30: =IF(AA$8=$R30,-$T30,0)+IF(AA$8=$S30,$T30,0) -> 0 | AB30: =IF(AB$8=$R30,-$T30,0)+IF(AB$8=$S30,$T30,0) -> 0 | AC30: =IF(AC$8=$R30,-$T30,0)+IF(AC$8=$S30,$T30,0) -> 0 | AD30: =IF(AD$8=$R30,-$T30,0)+IF(AD$8=$S30,$T30,0) -> 0 | AE30: =IF(AE$8=$R30,-$T30,0)+IF(AE$8=$S30,$T30,0) -> 0 | AF30: =IF(AF$8=$R30,-$T30,0)+IF(AF$8=$S30,$T30,0) -> 0 | AG30: =IF(AG$8=$R30,-$T30,0)+IF(AG$8=$S30,$T30,0) -> 0 | ... AK30: =IF(AK$8=$R30,-$T30,0)+IF(AK$8=$S30,$T30,0) -> 0
A31: 4 | C31: =C12 -> CRED1 | D31: =D12 -> CARTÃO DE CRÉDITO 1 | E31: =SUMIF(OFFSET($Z$9:$Z$88,0,A31-1),">0") -> 0 | F31: =SUMIF(OFFSET($Z$9:$Z$88,0,A31-1),"<0") -> 0 | G31: =SUM(E31:F31) -> 0 | J31: =NOT(ISERR(SEARCH(J$27,$C31))) -> FALSE | K31: =NOT(ISERR(SEARCH(K$27,$C31))) -> FALSE | L31: =NOT(ISERR(SEARCH(L$27,$C31))) -> FALSE | N31: 23 | X31: =IF(P31<NOW(),1,0) -> 1 | Z31: =IF(Z$8=$R31,-$T31,0)+IF(Z$8=$S31,$T31,0) -> 0 | AA31: =IF(AA$8=$R31,-$T31,0)+IF(AA$8=$S31,$T31,0) -> 0 | AB31: =IF(AB$8=$R31,-$T31,0)+IF(AB$8=$S31,$T31,0) -> 0 | AC31: =IF(AC$8=$R31,-$T31,0)+IF(AC$8=$S31,$T31,0) -> 0 | AD31: =IF(AD$8=$R31,-$T31,0)+IF(AD$8=$S31,$T31,0) -> 0 | AE31: =IF(AE$8=$R31,-$T31,0)+IF(AE$8=$S31,$T31,0) -> 0 | AF31: =IF(AF$8=$R31,-$T31,0)+IF(AF$8=$S31,$T31,0) -> 0 | AG31: =IF(AG$8=$R31,-$T31,0)+IF(AG$8=$S31,$T31,0) -> 0 | ... AK31: =IF(AK$8=$R31,-$T31,0)+IF(AK$8=$S31,$T31,0) -> 0
A32: 5 | C32: =C13 -> --- | D32: =D13 | E32: =SUMIF(OFFSET($Z$9:$Z$88,0,A32-1),">0") -> 0 | F32: =SUMIF(OFFSET($Z$9:$Z$88,0,A32-1),"<0") -> 0 | G32: =SUM(E32:F32) -> 0 | J32: =NOT(ISERR(SEARCH(J$27,$C32))) -> FALSE | K32: =NOT(ISERR(SEARCH(K$27,$C32))) -> FALSE | L32: =NOT(ISERR(SEARCH(L$27,$C32))) -> FALSE | N32: 24 | X32: =IF(P32<NOW(),1,0) -> 1 | Z32: =IF(Z$8=$R32,-$T32,0)+IF(Z$8=$S32,$T32,0) -> 0 | AA32: =IF(AA$8=$R32,-$T32,0)+IF(AA$8=$S32,$T32,0) -> 0 | AB32: =IF(AB$8=$R32,-$T32,0)+IF(AB$8=$S32,$T32,0) -> 0 | AC32: =IF(AC$8=$R32,-$T32,0)+IF(AC$8=$S32,$T32,0) -> 0 | AD32: =IF(AD$8=$R32,-$T32,0)+IF(AD$8=$S32,$T32,0) -> 0 | AE32: =IF(AE$8=$R32,-$T32,0)+IF(AE$8=$S32,$T32,0) -> 0 | AF32: =IF(AF$8=$R32,-$T32,0)+IF(AF$8=$S32,$T32,0) -> 0 | AG32: =IF(AG$8=$R32,-$T32,0)+IF(AG$8=$S32,$T32,0) -> 0 | ... AK32: =IF(AK$8=$R32,-$T32,0)+IF(AK$8=$S32,$T32,0) -> 0
A33: 6 | C33: =C14 -> --- | D33: =D14 | E33: =SUMIF(OFFSET($Z$9:$Z$88,0,A33-1),">0") -> 0 | F33: =SUMIF(OFFSET($Z$9:$Z$88,0,A33-1),"<0") -> 0 | G33: =SUM(E33:F33) -> 0 | J33: =NOT(ISERR(SEARCH(J$27,$C33))) -> FALSE | K33: =NOT(ISERR(SEARCH(K$27,$C33))) -> FALSE | L33: =NOT(ISERR(SEARCH(L$27,$C33))) -> FALSE | N33: 25 | X33: =IF(P33<NOW(),1,0) -> 1 | Z33: =IF(Z$8=$R33,-$T33,0)+IF(Z$8=$S33,$T33,0) -> 0 | AA33: =IF(AA$8=$R33,-$T33,0)+IF(AA$8=$S33,$T33,0) -> 0 | AB33: =IF(AB$8=$R33,-$T33,0)+IF(AB$8=$S33,$T33,0) -> 0 | AC33: =IF(AC$8=$R33,-$T33,0)+IF(AC$8=$S33,$T33,0) -> 0 | AD33: =IF(AD$8=$R33,-$T33,0)+IF(AD$8=$S33,$T33,0) -> 0 | AE33: =IF(AE$8=$R33,-$T33,0)+IF(AE$8=$S33,$T33,0) -> 0 | AF33: =IF(AF$8=$R33,-$T33,0)+IF(AF$8=$S33,$T33,0) -> 0 | AG33: =IF(AG$8=$R33,-$T33,0)+IF(AG$8=$S33,$T33,0) -> 0 | ... AK33: =IF(AK$8=$R33,-$T33,0)+IF(AK$8=$S33,$T33,0) -> 0
A34: 7 | C34: =C15 -> --- | D34: =D15 | E34: =SUMIF(OFFSET($Z$9:$Z$88,0,A34-1),">0") -> 0 | F34: =SUMIF(OFFSET($Z$9:$Z$88,0,A34-1),"<0") -> 0 | G34: =SUM(E34:F34) -> 0 | J34: =NOT(ISERR(SEARCH(J$27,$C34))) -> FALSE | K34: =NOT(ISERR(SEARCH(K$27,$C34))) -> FALSE | L34: =NOT(ISERR(SEARCH(L$27,$C34))) -> FALSE | N34: 26 | X34: =IF(P34<NOW(),1,0) -> 1 | Z34: =IF(Z$8=$R34,-$T34,0)+IF(Z$8=$S34,$T34,0) -> 0 | AA34: =IF(AA$8=$R34,-$T34,0)+IF(AA$8=$S34,$T34,0) -> 0 | AB34: =IF(AB$8=$R34,-$T34,0)+IF(AB$8=$S34,$T34,0) -> 0 | AC34: =IF(AC$8=$R34,-$T34,0)+IF(AC$8=$S34,$T34,0) -> 0 | AD34: =IF(AD$8=$R34,-$T34,0)+IF(AD$8=$S34,$T34,0) -> 0 | AE34: =IF(AE$8=$R34,-$T34,0)+IF(AE$8=$S34,$T34,0) -> 0 | AF34: =IF(AF$8=$R34,-$T34,0)+IF(AF$8=$S34,$T34,0) -> 0 | AG34: =IF(AG$8=$R34,-$T34,0)+IF(AG$8=$S34,$T34,0) -> 0 | ... AK34: =IF(AK$8=$R34,-$T34,0)+IF(AK$8=$S34,$T34,0) -> 0
A35: 8 | C35: =C16 -> --- | D35: =D16 | E35: =SUMIF(OFFSET($Z$9:$Z$88,0,A35-1),">0") -> 0 | F35: =SUMIF(OFFSET($Z$9:$Z$88,0,A35-1),"<0") -> 0 | G35: =SUM(E35:F35) -> 0 | J35: =NOT(ISERR(SEARCH(J$27,$C35))) -> FALSE | K35: =NOT(ISERR(SEARCH(K$27,$C35))) -> FALSE | L35: =NOT(ISERR(SEARCH(L$27,$C35))) -> FALSE | N35: 27 | X35: =IF(P35<NOW(),1,0) -> 1 | Z35: =IF(Z$8=$R35,-$T35,0)+IF(Z$8=$S35,$T35,0) -> 0 | AA35: =IF(AA$8=$R35,-$T35,0)+IF(AA$8=$S35,$T35,0) -> 0 | AB35: =IF(AB$8=$R35,-$T35,0)+IF(AB$8=$S35,$T35,0) -> 0 | AC35: =IF(AC$8=$R35,-$T35,0)+IF(AC$8=$S35,$T35,0) -> 0 | AD35: =IF(AD$8=$R35,-$T35,0)+IF(AD$8=$S35,$T35,0) -> 0 | AE35: =IF(AE$8=$R35,-$T35,0)+IF(AE$8=$S35,$T35,0) -> 0 | AF35: =IF(AF$8=$R35,-$T35,0)+IF(AF$8=$S35,$T35,0) -> 0 | AG35: =IF(AG$8=$R35,-$T35,0)+IF(AG$8=$S35,$T35,0) -> 0 | ... AK35: =IF(AK$8=$R35,-$T35,0)+IF(AK$8=$S35,$T35,0) -> 0
A36: 9 | C36: =C17 -> --- | D36: =D17 | E36: =SUMIF(OFFSET($Z$9:$Z$88,0,A36-1),">0") -> 0 | F36: =SUMIF(OFFSET($Z$9:$Z$88,0,A36-1),"<0") -> 0 | G36: =SUM(E36:F36) -> 0 | J36: =NOT(ISERR(SEARCH(J$27,$C36))) -> FALSE | K36: =NOT(ISERR(SEARCH(K$27,$C36))) -> FALSE | L36: =NOT(ISERR(SEARCH(L$27,$C36))) -> FALSE | N36: 28 | X36: =IF(P36<NOW(),1,0) -> 1 | Z36: =IF(Z$8=$R36,-$T36,0)+IF(Z$8=$S36,$T36,0) -> 0 | AA36: =IF(AA$8=$R36,-$T36,0)+IF(AA$8=$S36,$T36,0) -> 0 | AB36: =IF(AB$8=$R36,-$T36,0)+IF(AB$8=$S36,$T36,0) -> 0 | AC36: =IF(AC$8=$R36,-$T36,0)+IF(AC$8=$S36,$T36,0) -> 0 | AD36: =IF(AD$8=$R36,-$T36,0)+IF(AD$8=$S36,$T36,0) -> 0 | AE36: =IF(AE$8=$R36,-$T36,0)+IF(AE$8=$S36,$T36,0) -> 0 | AF36: =IF(AF$8=$R36,-$T36,0)+IF(AF$8=$S36,$T36,0) -> 0 | AG36: =IF(AG$8=$R36,-$T36,0)+IF(AG$8=$S36,$T36,0) -> 0 | ... AK36: =IF(AK$8=$R36,-$T36,0)+IF(AK$8=$S36,$T36,0) -> 0
A37: 10 | C37: =C18 -> --- | D37: =D18 | E37: =SUMIF(OFFSET($Z$9:$Z$88,0,A37-1),">0") -> 0 | F37: =SUMIF(OFFSET($Z$9:$Z$88,0,A37-1),"<0") -> 0 | G37: =SUM(E37:F37) -> 0 | J37: =NOT(ISERR(SEARCH(J$27,$C37))) -> FALSE | K37: =NOT(ISERR(SEARCH(K$27,$C37))) -> FALSE | L37: =NOT(ISERR(SEARCH(L$27,$C37))) -> FALSE | N37: 29 | X37: =IF(P37<NOW(),1,0) -> 1 | Z37: =IF(Z$8=$R37,-$T37,0)+IF(Z$8=$S37,$T37,0) -> 0 | AA37: =IF(AA$8=$R37,-$T37,0)+IF(AA$8=$S37,$T37,0) -> 0 | AB37: =IF(AB$8=$R37,-$T37,0)+IF(AB$8=$S37,$T37,0) -> 0 | AC37: =IF(AC$8=$R37,-$T37,0)+IF(AC$8=$S37,$T37,0) -> 0 | AD37: =IF(AD$8=$R37,-$T37,0)+IF(AD$8=$S37,$T37,0) -> 0 | AE37: =IF(AE$8=$R37,-$T37,0)+IF(AE$8=$S37,$T37,0) -> 0 | AF37: =IF(AF$8=$R37,-$T37,0)+IF(AF$8=$S37,$T37,0) -> 0 | AG37: =IF(AG$8=$R37,-$T37,0)+IF(AG$8=$S37,$T37,0) -> 0 | ... AK37: =IF(AK$8=$R37,-$T37,0)+IF(AK$8=$S37,$T37,0) -> 0
