Workbook

Sheet CONTROLE CONCILIAÇÃO 
A1: Planilha de Controle de Responsabilidades e Conciliação Contábil | K1: Balancetes Mensais
A4: Cod Conta | B4: Desc Moeda 1 | C4: Classe Conta | D4: Cond Normal | E4: Natureza Contábil | F4: Backup Responsável | G4: Responsável | H4: OK | I4: Data Limite da Conciliação | J4: DESCRIÇÃO | K4: JAN/2017 | L4: Concilição | M4: FEV/2017 | N4: Concilição | O4: MAR/2017 | P4: Concilição | Q4: ABR/2017 | R4: Concilição | S4: MAI/2017 | T4: Concilição | U4: JUN/2017 | V4: Concilição | W4: JUL/2017 | X4: Concilição | Y4: AGO/2017 | Z4: Concilição | AA4: SET/2017 | AB4: Concilição | AC4: OUT/2017 | AD4: Concilição | AE4: NOV/2017 | AF4: Concilição | AG4: DEZ/2017 | AH4: Concilição
A5: 1 | B5: ATIVO | C5: Sintetica | D5: Devedora | J5: ATIVO
A6: 10 | B6: CIRCULANTE | C6: Sintetica | D6: Devedora | J6: CIRCULANTE
A7: 100 | B7: DISPONIVEL | C7: Sintetica | D7: Devedora | J7: DISPONIVEL
A8: 1000 | B8: CAIXA | C8: Sintetica | D8: Devedora | J8: CAIXA
A9: 100001 | B9: CAIXA | C9: Analitica | D9: Devedora | J9: CAIXA
A10: 100002 | B10: VALORES EM TRANSITO | C10: Analitica | D10: Devedora | J10: VALORES EM TRANSITO
A11: 1001 | B11: BANCOS CONTA CORRENTE | C11: Sintetica | D11: Devedora | J11: BANCOS CONTA CORRENTE
A12: 100101 | B12: BANCO ITAU S.A. | C12: Analitica | D12: Devedora | J12: BANCO ITAU S.A. | L12: OK | N12: OK
A13: 100102 | B13: BANCO BRADESCO S.A. | C13: Analitica | D13: Devedora | J13: BANCO BRADESCO S.A. | L13: OK | N13: OK
A14: 100103 | B14: BANCO SANTANDER S.A. | C14: Analitica | D14: Devedora | J14: BANCO SANTANDER S.A. | L14: OK | N14: OK
A15: 100105 | B15: CAIXA ECONOMICA FEDERAL | C15: Analitica | D15: Devedora | J15: CAIXA ECONOMICA FEDERAL | L15: OK | N15: OK
A16: 100106 | B16: BANCO DO BRASIL S.A. | C16: Analitica | D16: Devedora | J16: BANCO DO BRASIL S.A. | L16: OK | N16: OK
A17: 100107 | B17: BANRISUL | C17: Analitica | D17: Devedora | J17: BANRISUL | L17: OK | N17: OK
A18: 1002 | B18: APLICACOES FINANCEIRAS | C18: Sintetica | D18: Devedora | J18: APLICACOES FINANCEIRAS | N18: OK
A19: 100201 | B19: BANCO ITAU S.A. | C19: Analitica | D19: Devedora | J19: BANCO ITAU S.A. | L19: OK | N19: OK
A20: 100202 | B20: BANCO BRADESCO S.A. | C20: Analitica | D20: Devedora | J20: BANCO BRADESCO S.A. | L20: OK | N20: OK
A21: 100203 | B21: BANCO SANTANDER S.A. | C21: Analitica | D21: Devedora | J21: BANCO SANTANDER S.A. | L21: OK | N21: OK
A22: 1003 | B22: BANCOS CONTA VINCULADA | C22: Sintetica | D22: Devedora | J22: BANCOS CONTA VINCULADA
A23: 100301 | B23: BANCO ITAU | C23: Analitica | D23: Devedora | J23: BANCO ITAU | L23: OK | N23: OK
A24: 103 | B24: CONTAS A RECEBER-CLIENTES | C24: Sintetica | D24: Devedora | J24: CONTAS A RECEBER-CLIENTES
A25: 1030 | B25: CONTAS A RECEBER-CLIENTES | C25: Sintetica | D25: Devedora | J25: CONTAS A RECEBER-CLIENTES
A26: 103003 | B26: CHEQUES A RECEBER | C26: Analitica | D26: Devedora | J26: CHEQUES A RECEBER
A27: 103005 | B27: CONTAS RECEBER | C27: Analitica | D27: Devedora | J27: CONTAS RECEBER
A28: 103006 | B28: PROVISAO DEVEDORES DUVIDOSO | C28: Analitica | D28: Credora | J28: PROVISAO DEVEDORES DUVIDOSO
A29: 104 | B29: VALORES A RECEBER | C29: Sintetica | D29: Devedora | J29: VALORES A RECEBER
A30: 1040 | B30: VALORES A RECEBER | C30: Sintetica | D30: Devedora | J30: VALORES A RECEBER
A31: 104001 | B31: ADIANTAMENTO DE SALARIO | C31: Analitica | D31: Devedora | J31: ADIANTAMENTO DE SALARIO
A32: 104002 | B32: ADIANTAMENTO 13* SALARIO | C32: Analitica | D32: Devedora | J32: ADIANTAMENTO 13* SALARIO
A33: 104003 | B33: ADIANTAMENTO FERIAS | C33: Analitica | D33: Devedora | J33: ADIANTAMENTO FERIAS
A34: 104004 | B34: INDENIZACOES A RECEBER | C34: Analitica | D34: Devedora | J34: INDENIZACOES A RECEBER
A35: 104005 | B35: VALORES A RECEBER | C35: Analitica | D35: Devedora | J35: VALORES A RECEBER
... A91: 1310 | B91: BENS DO ATIVO IMOBILIZADO | C91: Sintetica | D91: Devedora | J91: BENS DO ATIVO IMOBILIZADO
A92: 131001 | B92: VEICULOS | C92: Analitica | D92: Devedora | J92: VEICULOS | L92: OK | N92: OK
A93: 131002 | B93: EQUIPAMENTOS DE INFORMATICA | C93: Analitica | D93: Devedora | J93: EQUIPAMENTOS DE INFORMATICA | L93: OK | N93: OK
A94: 131003 | B94: MOVEIS E UTENSILIOS | C94: Analitica | D94: Devedora | J94: MOVEIS E UTENSILIOS | L94: OK | N94: OK
A95: 131004 | B95: EQUIPAMENTOS E INSTALACOES OPERACIONAIS | C95: Analitica | D95: Devedora | J95: EQUIPAMENTOS E INSTALACOES OPERACIONAIS | L95: OK | N95: OK
A96: 131005 | B96: INSTALACOES | C96: Analitica | D96: Devedora | J96: INSTALACOES | L96: OK | N96: OK
A97: 131006 | B97: DIREITO DE USO DE SOFTWARE | C97: Analitica | D97: Devedora | J97: DIREITO DE USO DE SOFTWARE | L97: OK | N97: OK
A98: 131007 | B98: VEICULOS RTT LEASING | C98: Analitica | D98: Devedora | J98: VEICULOS RTT LEASING | L98: OK | N98: OK
A99: 131008 | B99: EQUIPAMENTOS DE INFORMATICA RTT LEASING | C99: Analitica | D99: Devedora | J99: EQUIPAMENTOS DE INFORMATICA RTT LEASING | L99: OK | N99: OK
A100: 131010 | B100: EQUIPAMENTOS E INSTAL.OPER.RTT LEASING | C100: Analitica | D100: Devedora | J100: EQUIPAMENTOS E INSTAL.OPER.RTT LEASING | L100: OK | N100: OK
A101: 131012 | B101: DIREITO DE USO DE SOFTWARE RTT LEASING | C101: Analitica | D101: Devedora | J101: DIREITO DE USO DE SOFTWARE RTT LEASING | L101: OK | N101: OK
A102: 131013 | B102: VEICULOS 8704 | C102: Analitica | D102: Devedora | J102: VEICULOS 8704 | L102: OK | N102: OK
A103: 1311 | B103: DEPRECIACAO ACUMULADA | C103: Sintetica | D103: Credora | J103: DEPRECIACAO ACUMULADA | L103: OK | N103: OK
... A118: 132 | B118: DIFERIDO | C118: Sintetica | D118: Devedora | J118: DIFERIDO | L118: OK | N118: OK
A119: 1321 | B119: BENFEITORIAS EM BENS DE TERCEIROS | C119: Sintetica | D119: Devedora | J119: BENFEITORIAS EM BENS DE TERCEIROS | L119: OK
A120: 132101 | B120: BENFEITORIAS EM BENS DE TERCEIROS | C120: Analitica | D120: Devedora | J120: BENFEITORIAS EM BENS DE TERCEIROS | L120: OK
A121: 1322 | B121: AMORTIZACAO ACUMULADA | C121: Sintetica | D121: Credora | J121: AMORTIZACAO ACUMULADA | L121: OK
A122: 132201 | B122: AMORTIZACAO ACUMULADA | C122: Analitica | D122: Credora | J122: AMORTIZACAO ACUMULADA | L122: OK
A123: 1323 | B123: IMOBILIZADO EM ANDAMENTO | C123: Sintetica | D123: Devedora | J123: IMOBILIZADO EM ANDAMENTO | L123: OK
A124: 132301 | B124: IMOBILIZADO EM ANDAMENTO | C124: Analitica | D124: Devedora | J124: IMOBILIZADO EM ANDAMENTO | L124: OK
A125: 2 | B125: PASSIVO | C125: Sintetica | D125: Credora | J125: PASSIVO
A126: 20 | B126: CIRCULANTE | C126: Sintetica | D126: Devedora | J126: CIRCULANTE
A127: 200 | B127: CIRCULANTE | C127: Sintetica | D127: Devedora | J127: CIRCULANTE
A128: 2000 | B128: CONTAS A PAGAR | C128: Sintetica | D128: Credora | J128: CONTAS A PAGAR
A129: 200001 | B129: FORNECEDORES | C129: Analitica | D129: Credora | J129: FORNECEDORES
A130: 200002 | B130: ALUGUEL | C130: Analitica | D130: Credora | J130: ALUGUEL
A131: 200003 | B131: SEGUROS A PAGAR | C131: Analitica | D131: Credora | J131: SEGUROS A PAGAR
A132: 200004 | B132: SEGURO DE VIDA A PAGAR | C132: Analitica | D132: Credora | J132: SEGURO DE VIDA A PAGAR
A133: 200006 | B133: CARRETEIROS EVENTUAIS | C133: Analitica | D133: Credora | J133: CARRETEIROS EVENTUAIS
A134: 200007 | B134: CARRETEIROS AGREGADOS | C134: Analitica | D134: Credora | J134: CARRETEIROS AGREGADOS
A135: 200008 | B135: SUBCONTRATADOS A PAGAR | C135: Analitica | D135: Credora | J135: SUBCONTRATADOS A PAGAR
A136: 200009 | B136: INDENIZACOES COM COBRANCA DE SEGUROS | C136: Analitica | D136: Credora | J136: INDENIZACOES COM COBRANCA DE SEGUROS
... A532: 770007 | B532: AMORTIZACOES | C532: Analitica | D532: Devedora | J532: AMORTIZACOES

Sheet STATUS CONCILIAÇÃO_012020
B2: CONCILIAÇÕES MENSAIS POR CONTA x RESPONSÁVEL 2020 | K2: % de Evolução | M2: =COUNTIF(L14:L33,"Concluída")/COUNTA(L14:L33) -> 0.5
F4: Analitico
F5: Concluída | G5: =COUNTIF($L$14:$L$175,F5)+G171 -> 44 | H5: =G5/$G$9 -> #REF!
F6: A iniciar | G6: =COUNTIF($L$14:$L$175,F6)+G177 -> 0 | H6: =G6/$G$9 -> #REF!
B7: Escopo: | D7: CONCILIAÇÃO CONTAS 2020 - EMPRESA XXXXXXXXX BASE JANEIRO | F7: Em andamento | G7: =COUNTIF($L$14:$L$175,F7)+G153 -> 0 | H7: =G7/$G$9 -> #REF!
F8: Atrasada | G8: =COUNTIF($L$14:$L$175,F8)+#REF! -> #REF! | H8: =G8/$G$9 -> #REF!
G9: =SUM(G5:G8) -> #REF!
B12: Atividades | F12: Quem | H12: Prazo Previsto | J12: Realizado | L12: Status | N12: RESULTADO DA AÇÃO | O12: PONTOS PROBLEMÁTICOS | P12: PROPOSIÇÕES FUTURAS
B13: NO. | C13: CONTA | D13: Prioridade | E13: DESCRIÇÃO | F13: Respons. | G13: Executor | H13: INÍCIO | I13: TÉRMINO | J13: INÍCIO | K13: TÉRMINO | L13: Status | M13: Farol
B14: 1 | C14: 100001 | D14: Alta | E14: =VLOOKUP(C14,'CONTROLE CONCILIAÇÃO '!A:C,2,FALSE) -> CAIXA | H14: 42767 | I14: 42793 | L14: =IF(H14="","",IF(K14<>"","Concluída",IF(TODAY()>I14,"Atrasada",IF(J14<>"","Em andamento",IF(AND(J14="",TODAY()>H14),"Atrasada","A iniciar"))))) -> Atrasada | M14: =IF(L14<>"","n","") -> n
B15: 2 | C15: 100002 | D15: Alta | E15: =VLOOKUP(C15,'CONTROLE CONCILIAÇÃO '!A:C,2,FALSE) -> VALORES EM TRANSITO | H15: 42767 | I15: 42793 | L15: =IF(H15="","",IF(K15<>"","Concluída",IF(TODAY()>I15,"Atrasada",IF(J15<>"","Em andamento",IF(AND(J15="",TODAY()>H15),"Atrasada","A iniciar"))))) -> Atrasada | M15: =IF(L15<>"","n","") -> n
B16: 3 | C16: 100101 | D16: Alta | E16: =VLOOKUP(C16,'CONTROLE CONCILIAÇÃO '!A:C,2,FALSE) -> BANCO ITAU S.A. | H16: 42767 | I16: 42793 | J16: 42767 | K16: 42767 | L16: =IF(H16="","",IF(K16<>"","Concluída",IF(TODAY()>I16,"Atrasada",IF(J16<>"","Em andamento",IF(AND(J16="",TODAY()>H16),"Atrasada","A iniciar"))))) -> Concluída | M16: =IF(L16<>"","n","") -> n
B17: 4 | C17: 100102 | D17: Alta | E17: =VLOOKUP(C17,'CONTROLE CONCILIAÇÃO '!A:C,2,FALSE) -> BANCO BRADESCO S.A. | H17: 42767 | I17: 42793 | J17: 42767 | K17: 42767 | L17: =IF(H17="","",IF(K17<>"","Concluída",IF(TODAY()>I17,"Atrasada",IF(J17<>"","Em andamento",IF(AND(J17="",TODAY()>H17),"Atrasada","A iniciar"))))) -> Concluída | M17: =IF(L17<>"","n","") -> n
B18: 5 | C18: 100103 | D18: Alta | E18: =VLOOKUP(C18,'CONTROLE CONCILIAÇÃO '!A:C,2,FALSE) -> BANCO SANTANDER S.A. | H18: 42767 | I18: 42793 | J18: 42767 | K18: 42767 | L18: =IF(H18="","",IF(K18<>"","Concluída",IF(TODAY()>I18,"Atrasada",IF(J18<>"","Em andamento",IF(AND(J18="",TODAY()>H18),"Atrasada","A iniciar"))))) -> Concluída | M18: =IF(L18<>"","n","") -> n
B19: 6 | C19: 100105 | D19: Alta | E19: =VLOOKUP(C19,'CONTROLE CONCILIAÇÃO '!A:C,2,FALSE) -> CAIXA ECONOMICA FEDERAL | H19: 42767 | I19: 42793 | J19: 42767 | K19: 42767 | L19: =IF(H19="","",IF(K19<>"","Concluída",IF(TODAY()>I19,"Atrasada",IF(J19<>"","Em andamento",IF(AND(J19="",TODAY()>H19),"Atrasada","A iniciar"))))) -> Concluída | M19: =IF(L19<>"","n","") -> n
B20: 7 | C20: 100106 | D20: Alta | E20: =VLOOKUP(C20,'CONTROLE CONCILIAÇÃO '!A:C,2,FALSE) -> BANCO DO BRASIL S.A. | H20: 42767 | I20: 42793 | J20: 42767 | K20: 42767 | L20: =IF(H20="","",IF(K20<>"","Concluída",IF(TODAY()>I20,"Atrasada",IF(J20<>"","Em andamento",IF(AND(J20="",TODAY()>H20),"Atrasada","A iniciar"))))) -> Concluída | M20: =IF(L20<>"","n","") -> n
B21: 8 | C21: 100107 | D21: Alta | E21: =VLOOKUP(C21,'CONTROLE CONCILIAÇÃO '!A:C,2,FALSE) -> BANRISUL | H21: 42767 | I21: 42793 | J21: 42767 | K21: 42767 | L21: =IF(H21="","",IF(K21<>"","Concluída",IF(TODAY()>I21,"Atrasada",IF(J21<>"","Em andamento",IF(AND(J21="",TODAY()>H21),"Atrasada","A iniciar"))))) -> Concluída | M21: =IF(L21<>"","n","") -> n
B22: 9 | C22: 100201 | D22: Alta | E22: =VLOOKUP(C22,'CONTROLE CONCILIAÇÃO '!A:C,2,FALSE) -> BANCO ITAU S.A. | H22: 42767 | I22: 42793 | J22: 42767 | K22: 42767 | L22: =IF(H22="","",IF(K22<>"","Concluída",IF(TODAY()>I22,"Atrasada",IF(J22<>"","Em andamento",IF(AND(J22="",TODAY()>H22),"Atrasada","A iniciar"))))) -> Concluída | M22: =IF(L22<>"","n","") -> n
B23: 10 | C23: 100202 | D23: Alta | E23: =VLOOKUP(C23,'CONTROLE CONCILIAÇÃO '!A:C,2,FALSE) -> BANCO BRADESCO S.A. | H23: 42767 | I23: 42793 | J23: 42767 | K23: 42767 | L23: =IF(H23="","",IF(K23<>"","Concluída",IF(TODAY()>I23,"Atrasada",IF(J23<>"","Em andamento",IF(AND(J23="",TODAY()>H23),"Atrasada","A iniciar"))))) -> Concluída | M23: =IF(L23<>"","n","") -> n
B24: 11 | C24: 100203 | D24: Alta | E24: =VLOOKUP(C24,'CONTROLE CONCILIAÇÃO '!A:C,2,FALSE) -> BANCO SANTANDER S.A. | H24: 42767 | I24: 42793 | J24: 42767 | K24: 42767 | L24: =IF(H24="","",IF(K24<>"","Concluída",IF(TODAY()>I24,"Atrasada",IF(J24<>"","Em andamento",IF(AND(J24="",TODAY()>H24),"Atrasada","A iniciar"))))) -> Concluída | M24: =IF(L24<>"","n","") -> n
B25: 12 | C25: 100301 | D25: Alta | E25: =VLOOKUP(C25,'CONTROLE CONCILIAÇÃO '!A:C,2,FALSE) -> BANCO ITAU | H25: 42767 | I25: 42793 | J25: 42767 | K25: 42767 | L25: =IF(H25="","",IF(K25<>"","Concluída",IF(TODAY()>I25,"Atrasada",IF(J25<>"","Em andamento",IF(AND(J25="",TODAY()>H25),"Atrasada","A iniciar"))))) -> Concluída | M25: =IF(L25<>"","n","") -> n
B26: 13 | C26: 103003 | D26: Alta | E26: =VLOOKUP(C26,'CONTROLE CONCILIAÇÃO '!A:C,2,FALSE) -> CHEQUES A RECEBER | H26: 42767 | I26: 42793 | L26: =IF(H26="","",IF(K26<>"","Concluída",IF(TODAY()>I26,"Atrasada",IF(J26<>"","Em andamento",IF(AND(J26="",TODAY()>H26),"Atrasada","A iniciar"))))) -> Atrasada | M26: =IF(L26<>"","n","") -> n
B27: 14 | C27: 103005 | D27: Alta | E27: =VLOOKUP(C27,'CONTROLE CONCILIAÇÃO '!A:C,2,FALSE) -> CONTAS RECEBER | H27: 42767 | I27: 42793 | L27: =IF(H27="","",IF(K27<>"","Concluída",IF(TODAY()>I27,"Atrasada",IF(J27<>"","Em andamento",IF(AND(J27="",TODAY()>H27),"Atrasada","A iniciar"))))) -> Atrasada | M27: =IF(L27<>"","n","") -> n
B28: 15 | C28: 103006 | D28: Alta | E28: =VLOOKUP(C28,'CONTROLE CONCILIAÇÃO '!A:C,2,FALSE) -> PROVISAO DEVEDORES DUVIDOSO | H28: 42767 | I28: 42793 | L28: =IF(H28="","",IF(K28<>"","Concluída",IF(TODAY()>I28,"Atrasada",IF(J28<>"","Em andamento",IF(AND(J28="",TODAY()>H28),"Atrasada","A iniciar"))))) -> Atrasada | M28: =IF(L28<>"","n","") -> n
B29: 16 | C29: 104001 | D29: Alta | E29: =VLOOKUP(C29,'CONTROLE CONCILIAÇÃO '!A:C,2,FALSE) -> ADIANTAMENTO DE SALARIO | H29: 42767 | I29: 42793 | L29: =IF(H29="","",IF(K29<>"","Concluída",IF(TODAY()>I29,"Atrasada",IF(J29<>"","Em andamento",IF(AND(J29="",TODAY()>H29),"Atrasada","A iniciar"))))) -> Atrasada | M29: =IF(L29<>"","n","") -> n
B30: 17 | C30: 104002 | D30: Alta | E30: =VLOOKUP(C30,'CONTROLE CONCILIAÇÃO '!A:C,2,FALSE) -> ADIANTAMENTO 13* SALARIO | H30: 42767 | I30: 42793 | L30: =IF(H30="","",IF(K30<>"","Concluída",IF(TODAY()>I30,"Atrasada",IF(J30<>"","Em andamento",IF(AND(J30="",TODAY()>H30),"Atrasada","A iniciar"))))) -> Atrasada | M30: =IF(L30<>"","n","") -> n
B31: 18 | C31: 104003 | D31: Alta | E31: =VLOOKUP(C31,'CONTROLE CONCILIAÇÃO '!A:C,2,FALSE) -> ADIANTAMENTO FERIAS | H31: 42767 | I31: 42793 | L31: =IF(H31="","",IF(K31<>"","Concluída",IF(TODAY()>I31,"Atrasada",IF(J31<>"","Em andamento",IF(AND(J31="",TODAY()>H31),"Atrasada","A iniciar"))))) -> Atrasada | M31: =IF(L31<>"","n","") -> n
B32: 19 | C32: 104004 | D32: Alta | E32: =VLOOKUP(C32,'CONTROLE CONCILIAÇÃO '!A:C,2,FALSE) -> INDENIZACOES A RECEBER | H32: 42767 | I32: 42793 | L32: =IF(H32="","",IF(K32<>"","Concluída",IF(TODAY()>I32,"Atrasada",IF(J32<>"","Em andamento",IF(AND(J32="",TODAY()>H32),"Atrasada","A iniciar"))))) -> Atrasada | M32: =IF(L32<>"","n","") -> n
B33: 20 | C33: 104005 | D33: Alta | E33: =VLOOKUP(C33,'CONTROLE CONCILIAÇÃO '!A:C,2,FALSE) -> VALORES A RECEBER | H33: 42767 | I33: 42793 | L33: =IF(H33="","",IF(K33<>"","Concluída",IF(TODAY()>I33,"Atrasada",IF(J33<>"","Em andamento",IF(AND(J33="",TODAY()>H33),"Atrasada","A iniciar"))))) -> Atrasada | M33: =IF(L33<>"","n","") -> n
B34: 21 | C34: 104006 | D34: Alta | E34: =VLOOKUP(C34,'CONTROLE CONCILIAÇÃO '!A:C,2,FALSE) -> ABASTECIMENTOS A AGREGADOS | H34: 42767 | I34: 42793 | L34: =IF(H34="","",IF(K34<>"","Concluída",IF(TODAY()>I34,"Atrasada",IF(J34<>"","Em andamento",IF(AND(J34="",TODAY()>H34),"Atrasada","A iniciar"))))) -> Atrasada | M34: =IF(L34<>"","n","") -> n
B35: 22 | C35: 104007 | D35: Alta | E35: =VLOOKUP(C35,'CONTROLE CONCILIAÇÃO '!A:C,2,FALSE) -> ADIANTAMENTO A CARRETEIROS | H35: 42767 | I35: 42793 | L35: =IF(H35="","",IF(K35<>"","Concluída",IF(TODAY()>I35,"Atrasada",IF(J35<>"","Em andamento",IF(AND(J35="",TODAY()>H35),"Atrasada","A iniciar"))))) -> Atrasada | M35: =IF(L35<>"","n","") -> n
B36: 23 | C36: 104008 | D36: Alta | E36: =VLOOKUP(C36,'CONTROLE CONCILIAÇÃO '!A:C,2,FALSE) -> ADIANTAMENTO CAV | H36: 42767 | I36: 42793 | L36: =IF(H36="","",IF(K36<>"","Concluída",IF(TODAY()>I36,"Atrasada",IF(J36<>"","Em andamento",IF(AND(J36="",TODAY()>H36),"Atrasada","A iniciar"))))) -> Atrasada | M36: =IF(L36<>"","n","") -> n
B37: 24 | C37: 105001 | D37: Alta | E37: =VLOOKUP(C37,'CONTROLE CONCILIAÇÃO '!A:C,2,FALSE) -> PREMIO DE SEGURO | H37: 42767 | I37: 42793 | L37: =IF(H37="","",IF(K37<>"","Concluída",IF(TODAY()>I37,"Atrasada",IF(J37<>"","Em andamento",IF(AND(J37="",TODAY()>H37),"Atrasada","A iniciar"))))) -> Atrasada | M37: =IF(L37<>"","n","") -> n
... B70: 60 | C70: 110601 | D70: Alta | E70: =VLOOKUP(C70,'CONTROLE CONCILIAÇÃO '!A:C,2,FALSE) -> JUROS A APROPRIAR - LONGO PRAZO | H70: 42767 | I70: 42793 | L70: =IF(H70="","",IF(K70<>"","Concluída",IF(TODAY()>I70,"Atrasada",IF(J70<>"","Em andamento",IF(AND(J70="",TODAY()>H70),"Atrasada","A iniciar"))))) -> Atrasada | M70: =IF(L70<>"","n","") -> n
B71: 61 | C71: 131001 | D71: Alta | E71: =VLOOKUP(C71,'CONTROLE CONCILIAÇÃO '!A:C,2,FALSE) -> VEICULOS | H71: 42767 | I71: 42793 | J71: 42766 | K71: 42766 | L71: =IF(H71="","",IF(K71<>"","Concluída",IF(TODAY()>I71,"Atrasada",IF(J71<>"","Em andamento",IF(AND(J71="",TODAY()>H71),"Atrasada","A iniciar"))))) -> Concluída | M71: =IF(L71<>"","n","") -> n
B72: 62 | C72: 131002 | D72: Alta | E72: =VLOOKUP(C72,'CONTROLE CONCILIAÇÃO '!A:C,2,FALSE) -> EQUIPAMENTOS DE INFORMATICA | H72: 42767 | I72: 42793 | J72: 42766 | K72: 42766 | L72: =IF(H72="","",IF(K72<>"","Concluída",IF(TODAY()>I72,"Atrasada",IF(J72<>"","Em andamento",IF(AND(J72="",TODAY()>H72),"Atrasada","A iniciar"))))) -> Concluída | M72: =IF(L72<>"","n","") -> n
B73: 63 | C73: 131003 | D73: Alta | E73: =VLOOKUP(C73,'CONTROLE CONCILIAÇÃO '!A:C,2,FALSE) -> MOVEIS E UTENSILIOS | H73: 42767 | I73: 42793 | J73: 42766 | K73: 42766 | L73: =IF(H73="","",IF(K73<>"","Concluída",IF(TODAY()>I73,"Atrasada",IF(J73<>"","Em andamento",IF(AND(J73="",TODAY()>H73),"Atrasada","A iniciar"))))) -> Concluída | M73: =IF(L73<>"","n","") -> n
B74: 64 | C74: 131004 | D74: Alta | E74: =VLOOKUP(C74,'CONTROLE CONCILIAÇÃO '!A:C,2,FALSE) -> EQUIPAMENTOS E INSTALACOES OPERACIONAIS | H74: 42767 | I74: 42793 | J74: 42766 | K74: 42766 | L74: =IF(H74="","",IF(K74<>"","Concluída",IF(TODAY()>I74,"Atrasada",IF(J74<>"","Em andamento",IF(AND(J74="",TODAY()>H74),"Atrasada","A iniciar"))))) -> Concluída | M74: =IF(L74<>"","n","") -> n
B75: 65 | C75: 131005 | D75: Alta | E75: =VLOOKUP(C75,'CONTROLE CONCILIAÇÃO '!A:C,2,FALSE) -> INSTALACOES | H75: 42767 | I75: 42793 | J75: 42766 | K75: 42766 | L75: =IF(H75="","",IF(K75<>"","Concluída",IF(TODAY()>I75,"Atrasada",IF(J75<>"","Em andamento",IF(AND(J75="",TODAY()>H75),"Atrasada","A iniciar"))))) -> Concluída | M75: =IF(L75<>"","n","") -> n
B76: 66 | C76: 131006 | D76: Alta | E76: =VLOOKUP(C76,'CONTROLE CONCILIAÇÃO '!A:C,2,FALSE) -> DIREITO DE USO DE SOFTWARE | H76: 42767 | I76: 42793 | J76: 42766 | K76: 42766 | L76: =IF(H76="","",IF(K76<>"","Concluída",IF(TODAY()>I76,"Atrasada",IF(J76<>"","Em andamento",IF(AND(J76="",TODAY()>H76),"Atrasada","A iniciar"))))) -> Concluída | M76: =IF(L76<>"","n","") -> n
B77: 67 | C77: 131007 | D77: Alta | E77: =VLOOKUP(C77,'CONTROLE CONCILIAÇÃO '!A:C,2,FALSE) -> VEICULOS RTT LEASING | H77: 42767 | I77: 42793 | J77: 42766 | K77: 42766 | L77: =IF(H77="","",IF(K77<>"","Concluída",IF(TODAY()>I77,"Atrasada",IF(J77<>"","Em andamento",IF(AND(J77="",TODAY()>H77),"Atrasada","A iniciar"))))) -> Concluída | M77: =IF(L77<>"","n","") -> n
B78: 68 | C78: 131008 | D78: Alta | E78: =VLOOKUP(C78,'CONTROLE CONCILIAÇÃO '!A:C,2,FALSE) -> EQUIPAMENTOS DE INFORMATICA RTT LEASING | H78: 42767 | I78: 42793 | J78: 42766 | K78: 42766 | L78: =IF(H78="","",IF(K78<>"","Concluída",IF(TODAY()>I78,"Atrasada",IF(J78<>"","Em andamento",IF(AND(J78="",TODAY()>H78),"Atrasada","A iniciar"))))) -> Concluída | M78: =IF(L78<>"","n","") -> n
B79: 69 | C79: 131010 | D79: Alta | E79: =VLOOKUP(C79,'CONTROLE CONCILIAÇÃO '!A:C,2,FALSE) -> EQUIPAMENTOS E INSTAL.OPER.RTT LEASING | H79: 42767 | I79: 42793 | J79: 42766 | K79: 42766 | L79: =IF(H79="","",IF(K79<>"","Concluída",IF(TODAY()>I79,"Atrasada",IF(J79<>"","Em andamento",IF(AND(J79="",TODAY()>H79),"Atrasada","A iniciar"))))) -> Concluída | M79: =IF(L79<>"","n","") -> n
B80: 70 | C80: 131012 | D80: Alta | E80: =VLOOKUP(C80,'CONTROLE CONCILIAÇÃO '!A:C,2,FALSE) -> DIREITO DE USO DE SOFTWARE RTT LEASING | H80: 42767 | I80: 42793 | J80: 42766 | K80: 42766 | L80: =IF(H80="","",IF(K80<>"","Concluída",IF(TODAY()>I80,"Atrasada",IF(J80<>"","Em andamento",IF(AND(J80="",TODAY()>H80),"Atrasada","A iniciar"))))) -> Concluída | M80: =IF(L80<>"","n","") -> n
B81: 71 | C81: 131013 | D81: Alta | E81: =VLOOKUP(C81,'CONTROLE CONCILIAÇÃO '!A:C,2,FALSE) -> VEICULOS 8704 | H81: 42767 | I81: 42793 | J81: 42766 | K81: 42766 | L81: =IF(H81="","",IF(K81<>"","Concluída",IF(TODAY()>I81,"Atrasada",IF(J81<>"","Em andamento",IF(AND(J81="",TODAY()>H81),"Atrasada","A iniciar"))))) -> Concluída | M81: =IF(L81<>"","n","") -> n
B82: 72 | C82: 131101 | D82: Alta | E82: =VLOOKUP(C82,'CONTROLE CONCILIAÇÃO '!A:C,2,FALSE) -> DEPRECIACAO ACUMULADA VEICULOS | H82: 42767 | I82: 42793 | J82: 42766 | K82: 42766 | L82: =IF(H82="","",IF(K82<>"","Concluída",IF(TODAY()>I82,"Atrasada",IF(J82<>"","Em andamento",IF(AND(J82="",TODAY()>H82),"Atrasada","A iniciar"))))) -> Concluída | M82: =IF(L82<>"","n","") -> n
... B97: 87 | C97: 132301 | D97: Alta | E97: =VLOOKUP(C97,'CONTROLE CONCILIAÇÃO '!A:C,2,FALSE) -> IMOBILIZADO EM ANDAMENTO | H97: 42767 | I97: 42793 | J97: 42766 | K97: 42766 | L97: =IF(H97="","",IF(K97<>"","Concluída",IF(TODAY()>I97,"Atrasada",IF(J97<>"","Em andamento",IF(AND(J97="",TODAY()>H97),"Atrasada","A iniciar"))))) -> Concluída | M97: =IF(L97<>"","n","") -> n
B98: 88 | C98: 200001 | D98: Alta | E98: =VLOOKUP(C98,'CONTROLE CONCILIAÇÃO '!A:C,2,FALSE) -> FORNECEDORES | H98: 42767 | I98: 42793 | L98: =IF(H98="","",IF(K98<>"","Concluída",IF(TODAY()>I98,"Atrasada",IF(J98<>"","Em andamento",IF(AND(J98="",TODAY()>H98),"Atrasada","A iniciar"))))) -> Atrasada | M98: =IF(L98<>"","n","") -> n
B99: 89 | C99: 200002 | D99: Alta | E99: =VLOOKUP(C99,'CONTROLE CONCILIAÇÃO '!A:C,2,FALSE) -> ALUGUEL | H99: 42767 | I99: 42793 | L99: =IF(H99="","",IF(K99<>"","Concluída",IF(TODAY()>I99,"Atrasada",IF(J99<>"","Em andamento",IF(AND(J99="",TODAY()>H99),"Atrasada","A iniciar"))))) -> Atrasada | M99: =IF(L99<>"","n","") -> n
B100: 90 | C100: 200003 | D100: Alta | E100: =VLOOKUP(C100,'CONTROLE CONCILIAÇÃO '!A:C,2,FALSE) -> SEGUROS A PAGAR | H100: 42767 | I100: 42793 | L100: =IF(H100="","",IF(K100<>"","Concluída",IF(TODAY()>I100,"Atrasada",IF(J100<>"","Em andamento",IF(AND(J100="",TODAY()>H100),"Atrasada","A iniciar"))))) -> Atrasada | M100: =IF(L100<>"","n","") -> n
B101: 91 | C101: 200004 | D101: Alta | E101: =VLOOKUP(C101,'CONTROLE CONCILIAÇÃO '!A:C,2,FALSE) -> SEGURO DE VIDA A PAGAR | H101: 42767 | I101: 42793 | L101: =IF(H101="","",IF(K101<>"","Concluída",IF(TODAY()>I101,"Atrasada",IF(J101<>"","Em andamento",IF(AND(J101="",TODAY()>H101),"Atrasada","A iniciar"))))) -> Atrasada | M101: =IF(L101<>"","n","") -> n
B102: 92 | C102: 200006 | D102: Alta | E102: =VLOOKUP(C102,'CONTROLE CONCILIAÇÃO '!A:C,2,FALSE) -> CARRETEIROS EVENTUAIS | H102: 42767 | I102: 42793 | L102: =IF(H102="","",IF(K102<>"","Concluída",IF(TODAY()>I102,"Atrasada",IF(J102<>"","Em andamento",IF(AND(J102="",TODAY()>H102),"Atrasada","A iniciar"))))) -> Atrasada | M102: =IF(L102<>"","n","") -> n
B103: 93 | C103: 200007 | D103: Alta | E103: =VLOOKUP(C103,'CONTROLE CONCILIAÇÃO '!A:C,2,FALSE) -> CARRETEIROS AGREGADOS | H103: 42767 | I103: 42793 | J103: 42766 | K103: 42766 | L103: =IF(H103="","",IF(K103<>"","Concluída",IF(TODAY()>I103,"Atrasada",IF(J103<>"","Em andamento",IF(AND(J103="",TODAY()>H103),"Atrasada","A iniciar"))))) -> Concluída | M103: =IF(L103<>"","n","") -> n
B104: 94 | C104: 200008 | D104: Alta | E104: =VLOOKUP(C104,'CONTROLE CONCILIAÇÃO '!A:C,2,FALSE) -> SUBCONTRATADOS A PAGAR | H104: 42767 | I104: 42793 | L104: =IF(H104="","",IF(K104<>"","Concluída",IF(TODAY()>I104,"Atrasada",IF(J104<>"","Em andamento",IF(AND(J104="",TODAY()>H104),"Atrasada","A iniciar"))))) -> Atrasada | M104: =IF(L104<>"","n","") -> n
B105: 95 | C105: 200009 | D105: Alta | E105: =VLOOKUP(C105,'CONTROLE CONCILIAÇÃO '!A:C,2,FALSE) -> INDENIZACOES COM COBRANCA DE SEGUROS | H105: 42767 | I105: 42793 | L105: =IF(H105="","",IF(K105<>"","Concluída",IF(TODAY()>I105,"Atrasada",IF(J105<>"","Em andamento",IF(AND(J105="",TODAY()>H105),"Atrasada","A iniciar"))))) -> Atrasada | M105: =IF(L105<>"","n","") -> n
B106: 96 | C106: 200010 | D106: Alta | E106: =VLOOKUP(C106,'CONTROLE CONCILIAÇÃO '!A:C,2,FALSE) -> DPVAT SEGURO OBRIGATORIO | H106: 42767 | I106: 42793 | L106: =IF(H106="","",IF(K106<>"","Concluída",IF(TODAY()>I106,"Atrasada",IF(J106<>"","Em andamento",IF(AND(J106="",TODAY()>H106),"Atrasada","A iniciar"))))) -> Atrasada | M106: =IF(L106<>"","n","") -> n
B107: 97 | C107: 200011 | D107: Alta | E107: =VLOOKUP(C107,'CONTROLE CONCILIAÇÃO '!A:C,2,FALSE) -> ACORDO TRABALHISTA | H107: 42767 | I107: 42793 | L107: =IF(H107="","",IF(K107<>"","Concluída",IF(TODAY()>I107,"Atrasada",IF(J107<>"","Em andamento",IF(AND(J107="",TODAY()>H107),"Atrasada","A iniciar"))))) -> Atrasada | M107: =IF(L107<>"","n","") -> n
B108: 98 | C108: 200012 | D108: Alta | E108: =VLOOKUP(C108,'CONTROLE CONCILIAÇÃO '!A:C,2,FALSE) -> CONTAS A PAGAR DIVERSAS | H108: 42767 | I108: 42793 | L108: =IF(H108="","",IF(K108<>"","Concluída",IF(TODAY()>I108,"Atrasada",IF(J108<>"","Em andamento",IF(AND(J108="",TODAY()>H108),"Atrasada","A iniciar"))))) -> Atrasada | M108: =IF(L108<>"","n","") -> n
B109: 99 | C109: 200013 | D109: Alta | E109: =VLOOKUP(C109,'CONTROLE CONCILIAÇÃO '!A:C,2,FALSE) -> CONTROLADA | H109: 42767 | I109: 42793 | L109: =IF(H109="","",IF(K109<>"","Concluída",IF(TODAY()>I109,"Atrasada",IF(J109<>"","Em andamento",IF(AND(J109="",TODAY()>H109),"Atrasada","A iniciar"))))) -> Atrasada | M109: =IF(L109<>"","n","") -> n
B110: 104 | C110: 200020 | D110: Alta | E110: =VLOOKUP(C110,'CONTROLE CONCILIAÇÃO '!A:C,2,FALSE) -> TRANSPORTES AEREOS | H110: 42767 | I110: 42793 | L110: =IF(H110="","",IF(K110<>"","Concluída",IF(TODAY()>I110,"Atrasada",IF(J110<>"","Em andamento",IF(AND(J110="",TODAY()>H110),"Atrasada","A iniciar"))))) -> Atrasada | M110: =IF(L110<>"","n","") -> n
B111: 105 | C111: 201101 | D111: Alta | E111: =VLOOKUP(C111,'CONTROLE CONCILIAÇÃO '!A:C,2,FALSE) -> SALARIOS E ORDENADOS A PAGAR | H111: 42767 | I111: 42793 | L111: =IF(H111="","",IF(K111<>"","Concluída",IF(TODAY()>I111,"Atrasada",IF(J111<>"","Em andamento",IF(AND(J111="",TODAY()>H111),"Atrasada","A iniciar"))))) -> Atrasada | M111: =IF(L111<>"","n","") -> n
B112: 106 | C112: 201103 | D112: Alta | E112: =VLOOKUP(C112,'CONTROLE CONCILIAÇÃO '!A:C,2,FALSE) -> PENSAO ALIMENTICIA | H112: 42767 | I112: 42793 | L112: =IF(H112="","",IF(K112<>"","Concluída",IF(TODAY()>I112,"Atrasada",IF(J112<>"","Em andamento",IF(AND(J112="",TODAY()>H112),"Atrasada","A iniciar"))))) -> Atrasada | M112: =IF(L112<>"","n","") -> n
B113: 107 | C113: 201104 | D113: Alta | E113: =VLOOKUP(C113,'CONTROLE CONCILIAÇÃO '!A:C,2,FALSE) -> CONVENIO FARMACIA | H113: 42767 | I113: 42793 | L113: =IF(H113="","",IF(K113<>"","Concluída",IF(TODAY()>I113,"Atrasada",IF(J113<>"","Em andamento",IF(AND(J113="",TODAY()>H113),"Atrasada","A iniciar"))))) -> Atrasada | M113: =IF(L113<>"","n","") -> n
B114: 108 | C114: 201105 | D114: Alta | E114: =VLOOKUP(C114,'CONTROLE CONCILIAÇÃO '!A:C,2,FALSE) -> CONTRIBUICAO SINDICAL ASSISTENCIAL | H114: 42767 | I114: 42793 | L114: =IF(H114="","",IF(K114<>"","Concluída",IF(TODAY()>I114,"Atrasada",IF(J114<>"","Em andamento",IF(AND(J114="",TODAY()>H114),"Atrasada","A iniciar"))))) -> Atrasada | M114: =IF(L114<>"","n","") -> n
B115: 109 | C115: 201106 | D115: Alta | E115: =VLOOKUP(C115,'CONTROLE CONCILIAÇÃO '!A:C,2,FALSE) -> EMPRESTIMOS DECRETO 4840 | H115: 42767 | I115: 42793 | L115: =IF(H115="","",IF(K115<>"","Concluída",IF(TODAY()>I115,"Atrasada",IF(J115<>"","Em andamento",IF(AND(J115="",TODAY()>H115),"Atrasada","A iniciar"))))) -> Atrasada | M115: =IF(L115<>"","n","") -> n
... B150: 145 | C150: 212006 | D150: Alta | E150: =VLOOKUP(C150,'CONTROLE CONCILIAÇÃO '!A:C,2,FALSE) -> CONTINGENCIA DEMANDA FISCAL | H150: 42767 | I150: 42793 | L150: =IF(H150="","",IF(K150<>"","Concluída",IF(TODAY()>I150,"Atrasada",IF(J150<>"","Em andamento",IF(AND(J150="",TODAY()>H150),"Atrasada","A iniciar"))))) -> Atrasada | M150: =IF(L150<>"","n","") -> n
B151: 146 | C151: 212007 | D151: Alta | E151: =VLOOKUP(C151,'CONTROLE CONCILIAÇÃO '!A:C,2,FALSE) -> PROVISOES | H151: 42767 | I151: 42793 | J151: 42766 | K151: 42766 | L151: =IF(H151="","",IF(K151<>"","Concluída",IF(TODAY()>I151,"Atrasada",IF(J151<>"","Em andamento",IF(AND(J151="",TODAY()>H151),"Atrasada","A iniciar"))))) -> Concluída | M151: =IF(L151<>"","n","") -> n
B152: 147 | C152: 213001 | D152: Alta | E152: =VLOOKUP(C152,'CONTROLE CONCILIAÇÃO '!A:C,2,FALSE) -> IMPOSTO DIFERIDO PDD | H152: 42767 | I152: 42793 | K152: 42766 | L152: =IF(H152="","",IF(K152<>"","Concluída",IF(TODAY()>I152,"Atrasada",IF(J152<>"","Em andamento",IF(AND(J152="",TODAY()>H152),"Atrasada","A iniciar"))))) -> Concluída | M152: =IF(L152<>"","n","") -> n
B153: 148 | C153: 270001 | D153: Alta | E153: =VLOOKUP(C153,'CONTROLE CONCILIAÇÃO '!A:C,2,FALSE) -> CAPITAL SOCIAL | H153: 42767 | I153: 42793 | K153: 42766 | L153: =IF(H153="","",IF(K153<>"","Concluída",IF(TODAY()>I153,"Atrasada",IF(J153<>"","Em andamento",IF(AND(J153="",TODAY()>H153),"Atrasada","A iniciar"))))) -> Concluída | M153: =IF(L153<>"","n","") -> n
B154: 150 | C154: 271001 | D154: Alta | E154: =VLOOKUP(C154,'CONTROLE CONCILIAÇÃO '!A:C,2,FALSE) -> AJUSTE CONF.LEI 11638/7 | H154: 42767 | I154: 42793 | L154: =IF(H154="","",IF(K154<>"","Concluída",IF(TODAY()>I154,"Atrasada",IF(J154<>"","Em andamento",IF(AND(J154="",TODAY()>H154),"Atrasada","A iniciar"))))) -> Atrasada | M154: =IF(L154<>"","n","") -> n
B155: 151 | C155: 272008 | D155: Alta | E155: =VLOOKUP(C155,'CONTROLE CONCILIAÇÃO '!A:C,2,FALSE) -> RESULTADO DO EXERCICIO 2013 | H155: 42767 | I155: 42793 | L155: =IF(H155="","",IF(K155<>"","Concluída",IF(TODAY()>I155,"Atrasada",IF(J155<>"","Em andamento",IF(AND(J155="",TODAY()>H155),"Atrasada","A iniciar"))))) -> Atrasada | M155: =IF(L155<>"","n","") -> n
B156: 152 | C156: 272009 | D156: Alta | E156: =VLOOKUP(C156,'CONTROLE CONCILIAÇÃO '!A:C,2,FALSE) -> RESULTADO DO EXERCICIO 2014 | H156: 42767 | I156: 42793 | L156: =IF(H156="","",IF(K156<>"","Concluída",IF(TODAY()>I156,"Atrasada",IF(J156<>"","Em andamento",IF(AND(J156="",TODAY()>H156),"Atrasada","A iniciar"))))) -> Atrasada | M156: =IF(L156<>"","n","") -> n
B157: 153 | C157: 272010 | D157: Alta | E157: =VLOOKUP(C157,'CONTROLE CONCILIAÇÃO '!A:C,2,FALSE) -> RESULTADO DO EXERCICIO 2015 | H157: 42767 | I157: 42793 | L157: =IF(H157="","",IF(K157<>"","Concluída",IF(TODAY()>I157,"Atrasada",IF(J157<>"","Em andamento",IF(AND(J157="",TODAY()>H157),"Atrasada","A iniciar"))))) -> Atrasada | M157: =IF(L157<>"","n","") -> n
B158: 154 | C158: 273001 | D158: Alta | E158: =VLOOKUP(C158,'CONTROLE CONCILIAÇÃO '!A:C,2,FALSE) -> ANTECIPACAO LUCROS | H158: 42767 | I158: 42793 | L158: =IF(H158="","",IF(K158<>"","Concluída",IF(TODAY()>I158,"Atrasada",IF(J158<>"","Em andamento",IF(AND(J158="",TODAY()>H158),"Atrasada","A iniciar"))))) -> Atrasada | M158: =IF(L158<>"","n","") -> n
B159: 155 | C159: 273002 | D159: Alta | E159: =VLOOKUP(C159,'CONTROLE CONCILIAÇÃO '!A:C,2,FALSE) -> ANTECIPACAO DE LUCROS (AJUSTES) | H159: 42767 | I159: 42793 | L159: =IF(H159="","",IF(K159<>"","Concluída",IF(TODAY()>I159,"Atrasada",IF(J159<>"","Em andamento",IF(AND(J159="",TODAY()>H159),"Atrasada","A iniciar"))))) -> Atrasada | M159: =IF(L159<>"","n","") -> n
B160: 156 | C160: 502001 | D160: Alta | E160: =VLOOKUP(C160,'CONTROLE CONCILIAÇÃO '!A:C,2,FALSE) -> INSS A RECUPERAR | H160: 42767 | I160: 42793 | L160: =IF(H160="","",IF(K160<>"","Concluída",IF(TODAY()>I160,"Atrasada",IF(J160<>"","Em andamento",IF(AND(J160="",TODAY()>H160),"Atrasada","A iniciar"))))) -> Atrasada | M160: =IF(L160<>"","n","") -> n
B161: 157 | C161: 510301 | D161: Alta | E161: =VLOOKUP(C161,'CONTROLE CONCILIAÇÃO '!A:C,2,FALSE) -> VALORES A RECEBER | H161: 42767 | I161: 42793 | L161: =IF(H161="","",IF(K161<>"","Concluída",IF(TODAY()>I161,"Atrasada",IF(J161<>"","Em andamento",IF(AND(J161="",TODAY()>H161),"Atrasada","A iniciar"))))) -> Atrasada | M161: =IF(L161<>"","n","") -> n
B162: 160 | C162: 510399 | D162: Alta | E162: =VLOOKUP(C162,'CONTROLE CONCILIAÇÃO '!A:C,2,FALSE) -> MUTUO PF | H162: 42767 | I162: 42793 | L162: =IF(H162="","",IF(K162<>"","Concluída",IF(TODAY()>I162,"Atrasada",IF(J162<>"","Em andamento",IF(AND(J162="",TODAY()>H162),"Atrasada","A iniciar"))))) -> Atrasada | M162: =IF(L162<>"","n","") -> n
B163: 161 | C163: 510401 | D163: Alta | E163: =VLOOKUP(C163,'CONTROLE CONCILIAÇÃO '!A:C,2,FALSE) -> IMPOSTO DIFERIDO CONTINGENCIA | H163: 42767 | I163: 42793 | L163: =IF(H163="","",IF(K163<>"","Concluída",IF(TODAY()>I163,"Atrasada",IF(J163<>"","Em andamento",IF(AND(J163="",TODAY()>H163),"Atrasada","A iniciar"))))) -> Atrasada | M163: =IF(L163<>"","n","") -> n
B164: 162 | C164: 531101 | D164: Alta | E164: =VLOOKUP(C164,'CONTROLE CONCILIAÇÃO '!A:C,2,FALSE) -> DEPRECIACAO ACUMULADA VEICULOS | H164: 42767 | I164: 42793 | J164: 42766 | K164: 42766 | L164: =IF(H164="","",IF(K164<>"","Concluída",IF(TODAY()>I164,"Atrasada",IF(J164<>"","Em andamento",IF(AND(J164="",TODAY()>H164),"Atrasada","A iniciar"))))) -> Concluída | M164: =IF(L164<>"","n","") -> n
B165: 163 | C165: 532101 | D165: Alta | E165: =VLOOKUP(C165,'CONTROLE CONCILIAÇÃO '!A:C,2,FALSE) -> BENFEITORIA EM BENS DE TERCEIROS | H165: 42767 | I165: 42793 | J165: 42766 | K165: 42766 | L165: =IF(H165="","",IF(K165<>"","Concluída",IF(TODAY()>I165,"Atrasada",IF(J165<>"","Em andamento",IF(AND(J165="",TODAY()>H165),"Atrasada","A iniciar"))))) -> Concluída | M165: =IF(L165<>"","n","") -> n
B166: 164 | C166: 532201 | D166: Alta | E166: =VLOOKUP(C166,'CONTROLE CONCILIAÇÃO '!A:C,2,FALSE) -> AMORTIZACAO BENF ACUMULADA | H166: 42767 | I166: 42793 | J166: 42766 | K166: 42766 | L166: =IF(H166="","",IF(K166<>"","Concluída",IF(TODAY()>I166,"Atrasada",IF(J166<>"","Em andamento",IF(AND(J166="",TODAY()>H166),"Atrasada","A iniciar"))))) -> Concluída | M166: =IF(L166<>"","n","") -> n
B167: 165 | C167: 600001 | D167: Alta | E167: =VLOOKUP(C167,'CONTROLE CONCILIAÇÃO '!A:C,2,FALSE) -> FORNECEDORES | H167: 42767 | I167: 42793 | L167: =IF(H167="","",IF(K167<>"","Concluída",IF(TODAY()>I167,"Atrasada",IF(J167<>"","Em andamento",IF(AND(J167="",TODAY()>H167),"Atrasada","A iniciar"))))) -> Atrasada | M167: =IF(L167<>"","n","") -> n
B168: 169 | C168: 601101 | D168: Alta | E168: =VLOOKUP(C168,'CONTROLE CONCILIAÇÃO '!A:C,2,FALSE) -> SALARIOS E ORDENADOS A PAGAR | H168: 42767 | I168: 42793 | L168: =IF(H168="","",IF(K168<>"","Concluída",IF(TODAY()>I168,"Atrasada",IF(J168<>"","Em andamento",IF(AND(J168="",TODAY()>H168),"Atrasada","A iniciar"))))) -> Atrasada | M168: =IF(L168<>"","n","") -> n
B169: 170 | C169: 601108 | D169: Alta | E169: =VLOOKUP(C169,'CONTROLE CONCILIAÇÃO '!A:C,2,FALSE) -> INSS FOLHA | H169: 42767 | I169: 42793 | L169: =IF(H169="","",IF(K169<>"","Concluída",IF(TODAY()>I169,"Atrasada",IF(J169<>"","Em andamento",IF(AND(J169="",TODAY()>H169),"Atrasada","A iniciar"))))) -> Atrasada | M169: =IF(L169<>"","n","") -> n
B170: 171 | C170: 603100 | D170: Alta | E170: =VLOOKUP(C170,'CONTROLE CONCILIAÇÃO '!A:C,2,FALSE) -> PROVISAO PARA 13 SALARIO E ENCARGOS | H170: 42767 | I170: 42793 | L170: =IF(H170="","",IF(K170<>"","Concluída",IF(TODAY()>I170,"Atrasada",IF(J170<>"","Em andamento",IF(AND(J170="",TODAY()>H170),"Atrasada","A iniciar"))))) -> Atrasada | M170: =IF(L170<>"","n","") -> n
B171: 172 | C171: 603101 | D171: Alta | E171: =VLOOKUP(C171,'CONTROLE CONCILIAÇÃO '!A:C,2,FALSE) -> PROVISAO PARA FERIAS E ENCARGOS | H171: 42767 | I171: 42793 | L171: =IF(H171="","",IF(K171<>"","Concluída",IF(TODAY()>I171,"Atrasada",IF(J171<>"","Em andamento",IF(AND(J171="",TODAY()>H171),"Atrasada","A iniciar"))))) -> Atrasada | M171: =IF(L171<>"","n","") -> n
B172: 173 | C172: 603102 | D172: Alta | E172: =VLOOKUP(C172,'CONTROLE CONCILIAÇÃO '!A:C,2,FALSE) -> ACORDO SANTANDER | H172: 42767 | I172: 42793 | L172: =IF(H172="","",IF(K172<>"","Concluída",IF(TODAY()>I172,"Atrasada",IF(J172<>"","Em andamento",IF(AND(J172="",TODAY()>H172),"Atrasada","A iniciar"))))) -> Atrasada | M172: =IF(L172<>"","n","") -> n
B173: 174 | C173: 612001 | D173: Alta | E173: =VLOOKUP(C173,'CONTROLE CONCILIAÇÃO '!A:C,2,FALSE) -> CONTINGENCIA FRETE AGREGADOS | H173: 42767 | I173: 42793 | L173: =IF(H173="","",IF(K173<>"","Concluída",IF(TODAY()>I173,"Atrasada",IF(J173<>"","Em andamento",IF(AND(J173="",TODAY()>H173),"Atrasada","A iniciar"))))) -> Atrasada | M173: =IF(L173<>"","n","") -> n
B174: 175 | C174: 613001 | D174: Alta | E174: =VLOOKUP(C174,'CONTROLE CONCILIAÇÃO '!A:C,2,FALSE) -> IMPOSTO DIFERIDO ATIVO FIXO | H174: 42767 | I174: 42793 | L174: =IF(H174="","",IF(K174<>"","Concluída",IF(TODAY()>I174,"Atrasada",IF(J174<>"","Em andamento",IF(AND(J174="",TODAY()>H174),"Atrasada","A iniciar"))))) -> Atrasada | M174: =IF(L174<>"","n","") -> n
B175: 176 | C175: 673001 | D175: Alta | E175: =VLOOKUP(C175,'CONTROLE CONCILIAÇÃO '!A:C,2,FALSE) -> ANTECIPACAO DE LUCROS | H175: 42767 | I175: 42793 | L175: =IF(H175="","",IF(K175<>"","Concluída",IF(TODAY()>I175,"Atrasada",IF(J175<>"","Em andamento",IF(AND(J175="",TODAY()>H175),"Atrasada","A iniciar"))))) -> Atrasada | M175: =IF(L175<>"","n","") -> n
