Workbook
Name _1_2: #REF!
Name _1_2: #REF!
Name _2: #REF!
Name _2: #REF!
Name _GoBack: Configurações!#REF!
Name CotacoesTodosAtivos_3: #REF!
Name CotacoesTodosAtivos_3: #REF!
Name default_2: #REF!
Name default_2: #REF!

Sheet Operações Normais
B2: Período de Apuração | G2: Operação Normal: Operação com compra e venda em dias diferentes
B3: Mês: | C3: 6 | D3: Ano: | E3: 2020
B5: Operações Normais Ações e Opções | X5: ISS | AB5: Taxas compra | AI5: Taxas Venda
B6: Tipo | C6: Data Compra | D6: Código Ativo | E6: Quantidade | F6: Preço Compra | G6: PM Compra com custos inclusos? | H6: Movimento Compra | I6: Data Venda | J6: Preço Venda | K6: PM Venda com custos inclusos? | L6: Movimento Total | M6: Movimento Venda | N6: Taxa Negociação | O6: Taxa Liquidação | P6: Taxa Registro | Q6: Corretagem Compra | R6: Corretagem Venda | S6: Outras despesas | T6: Resultado | U6: IRRF s/ Operações | V6: % | W6: Dias | X6: (AJUSTAR) | AB6: Taxa Negociação | AC6: Taxa Liquidação | AD6: Taxa Registro | AE6: Corretagem | AF6: ISS | AG6: Total | AI6: Taxa Negociação | AJ6: Taxa Liquidação | AK6: Taxa Registro | AL6: Corretagem | AM6: ISS | AN6: Total
X7: 0.1068
B8: ACAO | G8: NÃO | H8: =E8*F8 -> 0 | K8: NÃO | L8: =SUM(H8,M8) -> 0 | M8: =E8*J8 -> 0 | N8: =ROUNDDOWN(IF(OR(B8="ACAO",B8="DIR",B8="ETF",B8="EXERCICIO"),L8*Configurações!$B$9,IF(B8="EXERC. LC",H8*Configurações!$B$9+M8*Configurações!$B$37,IF(B8="OPCAO",L8*Configurações!$B$23))),2) -> 0 | O8: =ROUNDDOWN(IF(OR(B8="ACAO",B8="DIR",B8="ETF",B8="EXERCICIO"),L8*Configurações!$C$9,IF(B8="EXERC. LC",H8*Configurações!$C$9+M8*Configurações!$C$37,IF(B8="OPCAO",L8*Configurações!$C$23))),2) -> 0 | P8: =ROUNDDOWN(IF(OR(B8="ACAO",B8="DIR",B8="ETF",B8="EXERCICIO"),L8*Configurações!$D$9,IF(B8="EXERC. LC",H8*Configurações!$D$9+M8*Configurações!$D$37,IF(B8="OPCAO",L8*Configurações!$D$23))),2) -> 0 | T8: =IF(AND(G8="SIM",K8="NÃO"),-H8+M8-P8-Q8-R8-X8-S8-O8-N8+AG8,IF(AND(K8="SIM",G8="NÃO"),-H8+M8-P8-Q8-R8-X8-S8-O8-N8+AN8,IF(AND(K8="SIM",G8="SIM"),-H8+M8-P8-Q8-R8-X8-S8-O8-N8+AN8+AG8,IF(AND(K8="NÃO",G8="NÃO"),-H8+M8-P8-Q8-R8-X8-S8-O8-N8,0)))) -> 0 | V8: =IF(D8="","-",T8/H8) -> - | W8: =DAYS360(C8,I8) -> 0 | X8: =(Q8+R8)*$X$7 -> 0 | AB8: =ROUNDDOWN(IF(OR(B8="ACAO",B8="DIR",B8="ETF",B8="EXERCICIO"),H8*Configurações!$B$9,IF(B8="EXERC. LC",H8*Configurações!$B$9,IF(B8="OPCAO",H8*Configurações!$B$23))),2) -> 0 | AC8: =ROUNDDOWN(IF(OR(B8="ACAO",B8="DIR",B8="ETF",B8="EXERCICIO"),H8*Configurações!$C$9,IF(B8="EXERC. LC",H8*Configurações!$C$9,IF(B8="OPCAO",H8*Configurações!$C$23))),2) -> 0 | AD8: =ROUNDDOWN(IF(OR(B8="ACAO",B8="DIR",B8="ETF",B8="EXERCICIO"),H8*Configurações!$D$9,IF(B8="EXERC. LC",H8*Configurações!$D$9,IF(B8="OPCAO",H8*Configurações!$D$23))),2) -> 0 | AE8: =Q8 -> 0 | AF8: =AE8*$X$7 -> 0 | AG8: =SUM(AB8:AF8) -> 0 | AI8: =ROUNDDOWN(IF(OR(B8="ACAO",B8="DIR",B8="ETF",B8="EXERCICIO"),M8*Configurações!$B$9,IF(B8="EXERC. LC",M8*Configurações!$B$37,IF(B8="OPCAO",M8*Configurações!$B$23))),2) -> 0 | AJ8: =ROUNDDOWN(IF(OR(B8="ACAO",B8="DIR",B8="ETF",B8="EXERCICIO"),M8*Configurações!$C$9,IF(B8="EXERC. LC",M8*Configurações!$C$37,IF(B8="OPCAO",M8*Configurações!$C$23))),2) -> 0 | AK8: =ROUNDDOWN(IF(OR(B8="ACAO",B8="DIR",B8="ETF",B8="EXERCICIO"),M8*Configurações!$D$9,IF(B8="EXERC. LC",M8*Configurações!$D$37,IF(B8="OPCAO",M8*Configurações!$D$23))),2) -> 0 | AL8: =R8 -> 0 | AM8: =AL8*$X$7 -> 0 | AN8: =SUM(AI8:AM8) -> 0
B9: ACAO | G9: NÃO | H9: =E9*F9 -> 0 | K9: NÃO | L9: =SUM(H9,M9) -> 0 | M9: =E9*J9 -> 0 | N9: =ROUNDDOWN(IF(OR(B9="ACAO",B9="DIR",B9="ETF",B9="EXERCICIO"),L9*Configurações!$B$9,IF(B9="EXERC. LC",H9*Configurações!$B$9+M9*Configurações!$B$37,IF(B9="OPCAO",L9*Configurações!$B$23))),2) -> 0 | O9: =ROUNDDOWN(IF(OR(B9="ACAO",B9="DIR",B9="ETF",B9="EXERCICIO"),L9*Configurações!$C$9,IF(B9="EXERC. LC",H9*Configurações!$C$9+M9*Configurações!$C$37,IF(B9="OPCAO",L9*Configurações!$C$23))),2) -> 0 | P9: =ROUNDDOWN(IF(OR(B9="ACAO",B9="DIR",B9="ETF",B9="EXERCICIO"),L9*Configurações!$D$9,IF(B9="EXERC. LC",H9*Configurações!$D$9+M9*Configurações!$D$37,IF(B9="OPCAO",L9*Configurações!$D$23))),2) -> 0 | T9: =IF(AND(G9="SIM",K9="NÃO"),-H9+M9-P9-Q9-R9-X9-S9-O9-N9+AG9,IF(AND(K9="SIM",G9="NÃO"),-H9+M9-P9-Q9-R9-X9-S9-O9-N9+AN9,IF(AND(K9="SIM",G9="SIM"),-H9+M9-P9-Q9-R9-X9-S9-O9-N9+AN9+AG9,IF(AND(K9="NÃO",G9="NÃO"),-H9+M9-P9-Q9-R9-X9-S9-O9-N9,0)))) -> 0 | V9: =IF(D9="","-",T9/H9) -> - | W9: =DAYS360(C9,I9) -> 0 | X9: =(Q9+R9)*$X$7 -> 0 | AB9: =ROUNDDOWN(IF(OR(B9="ACAO",B9="DIR",B9="ETF",B9="EXERCICIO"),H9*Configurações!$B$9,IF(B9="EXERC. LC",H9*Configurações!$B$9,IF(B9="OPCAO",H9*Configurações!$B$23))),2) -> 0 | AC9: =ROUNDDOWN(IF(OR(B9="ACAO",B9="DIR",B9="ETF",B9="EXERCICIO"),H9*Configurações!$C$9,IF(B9="EXERC. LC",H9*Configurações!$C$9,IF(B9="OPCAO",H9*Configurações!$C$23))),2) -> 0 | AD9: =ROUNDDOWN(IF(OR(B9="ACAO",B9="DIR",B9="ETF",B9="EXERCICIO"),H9*Configurações!$D$9,IF(B9="EXERC. LC",H9*Configurações!$D$9,IF(B9="OPCAO",H9*Configurações!$D$23))),2) -> 0 | AE9: =Q9 -> 0 | AF9: =AE9*$X$7 -> 0 | AG9: =SUM(AB9:AF9) -> 0 | AI9: =ROUNDDOWN(IF(OR(B9="ACAO",B9="DIR",B9="ETF",B9="EXERCICIO"),M9*Configurações!$B$9,IF(B9="EXERC. LC",M9*Configurações!$B$37,IF(B9="OPCAO",M9*Configurações!$B$23))),2) -> 0 | AJ9: =ROUNDDOWN(IF(OR(B9="ACAO",B9="DIR",B9="ETF",B9="EXERCICIO"),M9*Configurações!$C$9,IF(B9="EXERC. LC",M9*Configurações!$C$37,IF(B9="OPCAO",M9*Configurações!$C$23))),2) -> 0 | AK9: =ROUNDDOWN(IF(OR(B9="ACAO",B9="DIR",B9="ETF",B9="EXERCICIO"),M9*Configurações!$D$9,IF(B9="EXERC. LC",M9*Configurações!$D$37,IF(B9="OPCAO",M9*Configurações!$D$23))),2) -> 0 | AL9: =R9 -> 0 | AM9: =AL9*$X$7 -> 0 | AN9: =SUM(AI9:AM9) -> 0
B10: ACAO | G10: NÃO | H10: =E10*F10 -> 0 | K10: NÃO | L10: =SUM(H10,M10) -> 0 | M10: =E10*J10 -> 0 | N10: =ROUNDDOWN(IF(OR(B10="ACAO",B10="DIR",B10="ETF",B10="EXERCICIO"),L10*Configurações!$B$9,IF(B10="EXERC. LC",H10*Configurações!$B$9+M10*Configurações!$B$37,IF(B10="OPCAO",L10*Configurações!$B$23))),2) -> 0 | O10: =ROUNDDOWN(IF(OR(B10="ACAO",B10="DIR",B10="ETF",B10="EXERCICIO"),L10*Configurações!$C$9,IF(B10="EXERC. LC",H10*Configurações!$C$9+M10*Configurações!$C$37,IF(B10="OPCAO",L10*Configurações!$C$23))),2) -> 0 | P10: =ROUNDDOWN(IF(OR(B10="ACAO",B10="DIR",B10="ETF",B10="EXERCICIO"),L10*Configurações!$D$9,IF(B10="EXERC. LC",H10*Configurações!$D$9+M10*Configurações!$D$37,IF(B10="OPCAO",L10*Configurações!$D$23))),2) -> 0 | T10: =IF(AND(G10="SIM",K10="NÃO"),-H10+M10-P10-Q10-R10-X10-S10-O10-N10+AG10,IF(AND(K10="SIM",G10="NÃO"),-H10+M10-P10-Q10-R10-X10-S10-O10-N10+AN10,IF(AND(K10="SIM",G10="SIM"),-H10+M10-P10-Q10-R10-X10-S10-O10-N10+AN10+AG10,IF(AND(K10="NÃO",G10="NÃO"),-H10+M10-P10-Q10-R10-X10-S10-O10-N10,0)))) -> 0 | V10: =IF(D10="","-",T10/H10) -> - | W10: =DAYS360(C10,I10) -> 0 | X10: =(Q10+R10)*$X$7 -> 0 | AB10: =ROUNDDOWN(IF(OR(B10="ACAO",B10="DIR",B10="ETF",B10="EXERCICIO"),H10*Configurações!$B$9,IF(B10="EXERC. LC",H10*Configurações!$B$9,IF(B10="OPCAO",H10*Configurações!$B$23))),2) -> 0 | AC10: =ROUNDDOWN(IF(OR(B10="ACAO",B10="DIR",B10="ETF",B10="EXERCICIO"),H10*Configurações!$C$9,IF(B10="EXERC. LC",H10*Configurações!$C$9,IF(B10="OPCAO",H10*Configurações!$C$23))),2) -> 0 | AD10: =ROUNDDOWN(IF(OR(B10="ACAO",B10="DIR",B10="ETF",B10="EXERCICIO"),H10*Configurações!$D$9,IF(B10="EXERC. LC",H10*Configurações!$D$9,IF(B10="OPCAO",H10*Configurações!$D$23))),2) -> 0 | AE10: =Q10 -> 0 | AF10: =AE10*$X$7 -> 0 | AG10: =SUM(AB10:AF10) -> 0 | AI10: =ROUNDDOWN(IF(OR(B10="ACAO",B10="DIR",B10="ETF",B10="EXERCICIO"),M10*Configurações!$B$9,IF(B10="EXERC. LC",M10*Configurações!$B$37,IF(B10="OPCAO",M10*Configurações!$B$23))),2) -> 0 | AJ10: =ROUNDDOWN(IF(OR(B10="ACAO",B10="DIR",B10="ETF",B10="EXERCICIO"),M10*Configurações!$C$9,IF(B10="EXERC. LC",M10*Configurações!$C$37,IF(B10="OPCAO",M10*Configurações!$C$23))),2) -> 0 | AK10: =ROUNDDOWN(IF(OR(B10="ACAO",B10="DIR",B10="ETF",B10="EXERCICIO"),M10*Configurações!$D$9,IF(B10="EXERC. LC",M10*Configurações!$D$37,IF(B10="OPCAO",M10*Configurações!$D$23))),2) -> 0 | AL10: =R10 -> 0 | AM10: =AL10*$X$7 -> 0 | AN10: =SUM(AI10:AM10) -> 0 | AP10: SIM
B11: ACAO | G11: NÃO | H11: =E11*F11 -> 0 | K11: NÃO | L11: =SUM(H11,M11) -> 0 | M11: =E11*J11 -> 0 | N11: =ROUNDDOWN(IF(OR(B11="ACAO",B11="DIR",B11="ETF",B11="EXERCICIO"),L11*Configurações!$B$9,IF(B11="EXERC. LC",H11*Configurações!$B$9+M11*Configurações!$B$37,IF(B11="OPCAO",L11*Configurações!$B$23))),2) -> 0 | O11: =ROUNDDOWN(IF(OR(B11="ACAO",B11="DIR",B11="ETF",B11="EXERCICIO"),L11*Configurações!$C$9,IF(B11="EXERC. LC",H11*Configurações!$C$9+M11*Configurações!$C$37,IF(B11="OPCAO",L11*Configurações!$C$23))),2) -> 0 | P11: =ROUNDDOWN(IF(OR(B11="ACAO",B11="DIR",B11="ETF",B11="EXERCICIO"),L11*Configurações!$D$9,IF(B11="EXERC. LC",H11*Configurações!$D$9+M11*Configurações!$D$37,IF(B11="OPCAO",L11*Configurações!$D$23))),2) -> 0 | T11: =IF(AND(G11="SIM",K11="NÃO"),-H11+M11-P11-Q11-R11-X11-S11-O11-N11+AG11,IF(AND(K11="SIM",G11="NÃO"),-H11+M11-P11-Q11-R11-X11-S11-O11-N11+AN11,IF(AND(K11="SIM",G11="SIM"),-H11+M11-P11-Q11-R11-X11-S11-O11-N11+AN11+AG11,IF(AND(K11="NÃO",G11="NÃO"),-H11+M11-P11-Q11-R11-X11-S11-O11-N11,0)))) -> 0 | V11: =IF(D11="","-",T11/H11) -> - | W11: =DAYS360(C11,I11) -> 0 | X11: =(Q11+R11)*$X$7 -> 0 | AB11: =ROUNDDOWN(IF(OR(B11="ACAO",B11="DIR",B11="ETF",B11="EXERCICIO"),H11*Configurações!$B$9,IF(B11="EXERC. LC",H11*Configurações!$B$9,IF(B11="OPCAO",H11*Configurações!$B$23))),2) -> 0 | AC11: =ROUNDDOWN(IF(OR(B11="ACAO",B11="DIR",B11="ETF",B11="EXERCICIO"),H11*Configurações!$C$9,IF(B11="EXERC. LC",H11*Configurações!$C$9,IF(B11="OPCAO",H11*Configurações!$C$23))),2) -> 0 | AD11: =ROUNDDOWN(IF(OR(B11="ACAO",B11="DIR",B11="ETF",B11="EXERCICIO"),H11*Configurações!$D$9,IF(B11="EXERC. LC",H11*Configurações!$D$9,IF(B11="OPCAO",H11*Configurações!$D$23))),2) -> 0 | AE11: =Q11 -> 0 | AF11: =AE11*$X$7 -> 0 | AG11: =SUM(AB11:AF11) -> 0 | AI11: =ROUNDDOWN(IF(OR(B11="ACAO",B11="DIR",B11="ETF",B11="EXERCICIO"),M11*Configurações!$B$9,IF(B11="EXERC. LC",M11*Configurações!$B$37,IF(B11="OPCAO",M11*Configurações!$B$23))),2) -> 0 | AJ11: =ROUNDDOWN(IF(OR(B11="ACAO",B11="DIR",B11="ETF",B11="EXERCICIO"),M11*Configurações!$C$9,IF(B11="EXERC. LC",M11*Configurações!$C$37,IF(B11="OPCAO",M11*Configurações!$C$23))),2) -> 0 | AK11: =ROUNDDOWN(IF(OR(B11="ACAO",B11="DIR",B11="ETF",B11="EXERCICIO"),M11*Configurações!$D$9,IF(B11="EXERC. LC",M11*Configurações!$D$37,IF(B11="OPCAO",M11*Configurações!$D$23))),2) -> 0 | AL11: =R11 -> 0 | AM11: =AL11*$X$7 -> 0 | AN11: =SUM(AI11:AM11) -> 0 | AP11: NÃO
B12: ACAO | G12: NÃO | H12: =E12*F12 -> 0 | K12: NÃO | L12: =SUM(H12,M12) -> 0 | M12: =E12*J12 -> 0 | N12: =ROUNDDOWN(IF(OR(B12="ACAO",B12="DIR",B12="ETF",B12="EXERCICIO"),L12*Configurações!$B$9,IF(B12="EXERC. LC",H12*Configurações!$B$9+M12*Configurações!$B$37,IF(B12="OPCAO",L12*Configurações!$B$23))),2) -> 0 | O12: =ROUNDDOWN(IF(OR(B12="ACAO",B12="DIR",B12="ETF",B12="EXERCICIO"),L12*Configurações!$C$9,IF(B12="EXERC. LC",H12*Configurações!$C$9+M12*Configurações!$C$37,IF(B12="OPCAO",L12*Configurações!$C$23))),2) -> 0 | P12: =ROUNDDOWN(IF(OR(B12="ACAO",B12="DIR",B12="ETF",B12="EXERCICIO"),L12*Configurações!$D$9,IF(B12="EXERC. LC",H12*Configurações!$D$9+M12*Configurações!$D$37,IF(B12="OPCAO",L12*Configurações!$D$23))),2) -> 0 | T12: =IF(AND(G12="SIM",K12="NÃO"),-H12+M12-P12-Q12-R12-X12-S12-O12-N12+AG12,IF(AND(K12="SIM",G12="NÃO"),-H12+M12-P12-Q12-R12-X12-S12-O12-N12+AN12,IF(AND(K12="SIM",G12="SIM"),-H12+M12-P12-Q12-R12-X12-S12-O12-N12+AN12+AG12,IF(AND(K12="NÃO",G12="NÃO"),-H12+M12-P12-Q12-R12-X12-S12-O12-N12,0)))) -> 0 | V12: =IF(D12="","-",T12/H12) -> - | W12: =DAYS360(C12,I12) -> 0 | X12: =(Q12+R12)*$X$7 -> 0 | AB12: =ROUNDDOWN(IF(OR(B12="ACAO",B12="DIR",B12="ETF",B12="EXERCICIO"),H12*Configurações!$B$9,IF(B12="EXERC. LC",H12*Configurações!$B$9,IF(B12="OPCAO",H12*Configurações!$B$23))),2) -> 0 | AC12: =ROUNDDOWN(IF(OR(B12="ACAO",B12="DIR",B12="ETF",B12="EXERCICIO"),H12*Configurações!$C$9,IF(B12="EXERC. LC",H12*Configurações!$C$9,IF(B12="OPCAO",H12*Configurações!$C$23))),2) -> 0 | AD12: =ROUNDDOWN(IF(OR(B12="ACAO",B12="DIR",B12="ETF",B12="EXERCICIO"),H12*Configurações!$D$9,IF(B12="EXERC. LC",H12*Configurações!$D$9,IF(B12="OPCAO",H12*Configurações!$D$23))),2) -> 0 | AE12: =Q12 -> 0 | AF12: =AE12*$X$7 -> 0 | AG12: =SUM(AB12:AF12) -> 0 | AI12: =ROUNDDOWN(IF(OR(B12="ACAO",B12="DIR",B12="ETF",B12="EXERCICIO"),M12*Configurações!$B$9,IF(B12="EXERC. LC",M12*Configurações!$B$37,IF(B12="OPCAO",M12*Configurações!$B$23))),2) -> 0 | AJ12: =ROUNDDOWN(IF(OR(B12="ACAO",B12="DIR",B12="ETF",B12="EXERCICIO"),M12*Configurações!$C$9,IF(B12="EXERC. LC",M12*Configurações!$C$37,IF(B12="OPCAO",M12*Configurações!$C$23))),2) -> 0 | AK12: =ROUNDDOWN(IF(OR(B12="ACAO",B12="DIR",B12="ETF",B12="EXERCICIO"),M12*Configurações!$D$9,IF(B12="EXERC. LC",M12*Configurações!$D$37,IF(B12="OPCAO",M12*Configurações!$D$23))),2) -> 0 | AL12: =R12 -> 0 | AM12: =AL12*$X$7 -> 0 | AN12: =SUM(AI12:AM12) -> 0
B13: ACAO | G13: NÃO | H13: =E13*F13 -> 0 | K13: NÃO | L13: =SUM(H13,M13) -> 0 | M13: =E13*J13 -> 0 | N13: =ROUNDDOWN(IF(OR(B13="ACAO",B13="DIR",B13="ETF",B13="EXERCICIO"),L13*Configurações!$B$9,IF(B13="EXERC. LC",H13*Configurações!$B$9+M13*Configurações!$B$37,IF(B13="OPCAO",L13*Configurações!$B$23))),2) -> 0 | O13: =ROUNDDOWN(IF(OR(B13="ACAO",B13="DIR",B13="ETF",B13="EXERCICIO"),L13*Configurações!$C$9,IF(B13="EXERC. LC",H13*Configurações!$C$9+M13*Configurações!$C$37,IF(B13="OPCAO",L13*Configurações!$C$23))),2) -> 0 | P13: =ROUNDDOWN(IF(OR(B13="ACAO",B13="DIR",B13="ETF",B13="EXERCICIO"),L13*Configurações!$D$9,IF(B13="EXERC. LC",H13*Configurações!$D$9+M13*Configurações!$D$37,IF(B13="OPCAO",L13*Configurações!$D$23))),2) -> 0 | T13: =IF(AND(G13="SIM",K13="NÃO"),-H13+M13-P13-Q13-R13-X13-S13-O13-N13+AG13,IF(AND(K13="SIM",G13="NÃO"),-H13+M13-P13-Q13-R13-X13-S13-O13-N13+AN13,IF(AND(K13="SIM",G13="SIM"),-H13+M13-P13-Q13-R13-X13-S13-O13-N13+AN13+AG13,IF(AND(K13="NÃO",G13="NÃO"),-H13+M13-P13-Q13-R13-X13-S13-O13-N13,0)))) -> 0 | V13: =IF(D13="","-",T13/H13) -> - | W13: =DAYS360(C13,I13) -> 0 | X13: =(Q13+R13)*$X$7 -> 0 | AB13: =ROUNDDOWN(IF(OR(B13="ACAO",B13="DIR",B13="ETF",B13="EXERCICIO"),H13*Configurações!$B$9,IF(B13="EXERC. LC",H13*Configurações!$B$9,IF(B13="OPCAO",H13*Configurações!$B$23))),2) -> 0 | AC13: =ROUNDDOWN(IF(OR(B13="ACAO",B13="DIR",B13="ETF",B13="EXERCICIO"),H13*Configurações!$C$9,IF(B13="EXERC. LC",H13*Configurações!$C$9,IF(B13="OPCAO",H13*Configurações!$C$23))),2) -> 0 | AD13: =ROUNDDOWN(IF(OR(B13="ACAO",B13="DIR",B13="ETF",B13="EXERCICIO"),H13*Configurações!$D$9,IF(B13="EXERC. LC",H13*Configurações!$D$9,IF(B13="OPCAO",H13*Configurações!$D$23))),2) -> 0 | AE13: =Q13 -> 0 | AF13: =AE13*$X$7 -> 0 | AG13: =SUM(AB13:AF13) -> 0 | AI13: =ROUNDDOWN(IF(OR(B13="ACAO",B13="DIR",B13="ETF",B13="EXERCICIO"),M13*Configurações!$B$9,IF(B13="EXERC. LC",M13*Configurações!$B$37,IF(B13="OPCAO",M13*Configurações!$B$23))),2) -> 0 | AJ13: =ROUNDDOWN(IF(OR(B13="ACAO",B13="DIR",B13="ETF",B13="EXERCICIO"),M13*Configurações!$C$9,IF(B13="EXERC. LC",M13*Configurações!$C$37,IF(B13="OPCAO",M13*Configurações!$C$23))),2) -> 0 | AK13: =ROUNDDOWN(IF(OR(B13="ACAO",B13="DIR",B13="ETF",B13="EXERCICIO"),M13*Configurações!$D$9,IF(B13="EXERC. LC",M13*Configurações!$D$37,IF(B13="OPCAO",M13*Configurações!$D$23))),2) -> 0 | AL13: =R13 -> 0 | AM13: =AL13*$X$7 -> 0 | AN13: =SUM(AI13:AM13) -> 0
B14: ACAO | G14: NÃO | H14: =E14*F14 -> 0 | K14: NÃO | L14: =SUM(H14,M14) -> 0 | M14: =E14*J14 -> 0 | N14: =ROUNDDOWN(IF(OR(B14="ACAO",B14="DIR",B14="ETF",B14="EXERCICIO"),L14*Configurações!$B$9,IF(B14="EXERC. LC",H14*Configurações!$B$9+M14*Configurações!$B$37,IF(B14="OPCAO",L14*Configurações!$B$23))),2) -> 0 | O14: =ROUNDDOWN(IF(OR(B14="ACAO",B14="DIR",B14="ETF",B14="EXERCICIO"),L14*Configurações!$C$9,IF(B14="EXERC. LC",H14*Configurações!$C$9+M14*Configurações!$C$37,IF(B14="OPCAO",L14*Configurações!$C$23))),2) -> 0 | P14: =ROUNDDOWN(IF(OR(B14="ACAO",B14="DIR",B14="ETF",B14="EXERCICIO"),L14*Configurações!$D$9,IF(B14="EXERC. LC",H14*Configurações!$D$9+M14*Configurações!$D$37,IF(B14="OPCAO",L14*Configurações!$D$23))),2) -> 0 | T14: =IF(AND(G14="SIM",K14="NÃO"),-H14+M14-P14-Q14-R14-X14-S14-O14-N14+AG14,IF(AND(K14="SIM",G14="NÃO"),-H14+M14-P14-Q14-R14-X14-S14-O14-N14+AN14,IF(AND(K14="SIM",G14="SIM"),-H14+M14-P14-Q14-R14-X14-S14-O14-N14+AN14+AG14,IF(AND(K14="NÃO",G14="NÃO"),-H14+M14-P14-Q14-R14-X14-S14-O14-N14,0)))) -> 0 | V14: =IF(D14="","-",T14/H14) -> - | W14: =DAYS360(C14,I14) -> 0 | X14: =(Q14+R14)*$X$7 -> 0 | AB14: =ROUNDDOWN(IF(OR(B14="ACAO",B14="DIR",B14="ETF",B14="EXERCICIO"),H14*Configurações!$B$9,IF(B14="EXERC. LC",H14*Configurações!$B$9,IF(B14="OPCAO",H14*Configurações!$B$23))),2) -> 0 | AC14: =ROUNDDOWN(IF(OR(B14="ACAO",B14="DIR",B14="ETF",B14="EXERCICIO"),H14*Configurações!$C$9,IF(B14="EXERC. LC",H14*Configurações!$C$9,IF(B14="OPCAO",H14*Configurações!$C$23))),2) -> 0 | AD14: =ROUNDDOWN(IF(OR(B14="ACAO",B14="DIR",B14="ETF",B14="EXERCICIO"),H14*Configurações!$D$9,IF(B14="EXERC. LC",H14*Configurações!$D$9,IF(B14="OPCAO",H14*Configurações!$D$23))),2) -> 0 | AE14: =Q14 -> 0 | AF14: =AE14*$X$7 -> 0 | AG14: =SUM(AB14:AF14) -> 0 | AI14: =ROUNDDOWN(IF(OR(B14="ACAO",B14="DIR",B14="ETF",B14="EXERCICIO"),M14*Configurações!$B$9,IF(B14="EXERC. LC",M14*Configurações!$B$37,IF(B14="OPCAO",M14*Configurações!$B$23))),2) -> 0 | AJ14: =ROUNDDOWN(IF(OR(B14="ACAO",B14="DIR",B14="ETF",B14="EXERCICIO"),M14*Configurações!$C$9,IF(B14="EXERC. LC",M14*Configurações!$C$37,IF(B14="OPCAO",M14*Configurações!$C$23))),2) -> 0 | AK14: =ROUNDDOWN(IF(OR(B14="ACAO",B14="DIR",B14="ETF",B14="EXERCICIO"),M14*Configurações!$D$9,IF(B14="EXERC. LC",M14*Configurações!$D$37,IF(B14="OPCAO",M14*Configurações!$D$23))),2) -> 0 | AL14: =R14 -> 0 | AM14: =AL14*$X$7 -> 0 | AN14: =SUM(AI14:AM14) -> 0
B15: ACAO | G15: NÃO | H15: =E15*F15 -> 0 | K15: NÃO | L15: =SUM(H15,M15) -> 0 | M15: =E15*J15 -> 0 | N15: =ROUNDDOWN(IF(OR(B15="ACAO",B15="DIR",B15="ETF",B15="EXERCICIO"),L15*Configurações!$B$9,IF(B15="EXERC. LC",H15*Configurações!$B$9+M15*Configurações!$B$37,IF(B15="OPCAO",L15*Configurações!$B$23))),2) -> 0 | O15: =ROUNDDOWN(IF(OR(B15="ACAO",B15="DIR",B15="ETF",B15="EXERCICIO"),L15*Configurações!$C$9,IF(B15="EXERC. LC",H15*Configurações!$C$9+M15*Configurações!$C$37,IF(B15="OPCAO",L15*Configurações!$C$23))),2) -> 0 | P15: =ROUNDDOWN(IF(OR(B15="ACAO",B15="DIR",B15="ETF",B15="EXERCICIO"),L15*Configurações!$D$9,IF(B15="EXERC. LC",H15*Configurações!$D$9+M15*Configurações!$D$37,IF(B15="OPCAO",L15*Configurações!$D$23))),2) -> 0 | T15: =IF(AND(G15="SIM",K15="NÃO"),-H15+M15-P15-Q15-R15-X15-S15-O15-N15+AG15,IF(AND(K15="SIM",G15="NÃO"),-H15+M15-P15-Q15-R15-X15-S15-O15-N15+AN15,IF(AND(K15="SIM",G15="SIM"),-H15+M15-P15-Q15-R15-X15-S15-O15-N15+AN15+AG15,IF(AND(K15="NÃO",G15="NÃO"),-H15+M15-P15-Q15-R15-X15-S15-O15-N15,0)))) -> 0 | V15: =IF(D15="","-",T15/H15) -> - | W15: =DAYS360(C15,I15) -> 0 | X15: =(Q15+R15)*$X$7 -> 0 | AB15: =ROUNDDOWN(IF(OR(B15="ACAO",B15="DIR",B15="ETF",B15="EXERCICIO"),H15*Configurações!$B$9,IF(B15="EXERC. LC",H15*Configurações!$B$9,IF(B15="OPCAO",H15*Configurações!$B$23))),2) -> 0 | AC15: =ROUNDDOWN(IF(OR(B15="ACAO",B15="DIR",B15="ETF",B15="EXERCICIO"),H15*Configurações!$C$9,IF(B15="EXERC. LC",H15*Configurações!$C$9,IF(B15="OPCAO",H15*Configurações!$C$23))),2) -> 0 | AD15: =ROUNDDOWN(IF(OR(B15="ACAO",B15="DIR",B15="ETF",B15="EXERCICIO"),H15*Configurações!$D$9,IF(B15="EXERC. LC",H15*Configurações!$D$9,IF(B15="OPCAO",H15*Configurações!$D$23))),2) -> 0 | AE15: =Q15 -> 0 | AF15: =AE15*$X$7 -> 0 | AG15: =SUM(AB15:AF15) -> 0 | AI15: =ROUNDDOWN(IF(OR(B15="ACAO",B15="DIR",B15="ETF",B15="EXERCICIO"),M15*Configurações!$B$9,IF(B15="EXERC. LC",M15*Configurações!$B$37,IF(B15="OPCAO",M15*Configurações!$B$23))),2) -> 0 | AJ15: =ROUNDDOWN(IF(OR(B15="ACAO",B15="DIR",B15="ETF",B15="EXERCICIO"),M15*Configurações!$C$9,IF(B15="EXERC. LC",M15*Configurações!$C$37,IF(B15="OPCAO",M15*Configurações!$C$23))),2) -> 0 | AK15: =ROUNDDOWN(IF(OR(B15="ACAO",B15="DIR",B15="ETF",B15="EXERCICIO"),M15*Configurações!$D$9,IF(B15="EXERC. LC",M15*Configurações!$D$37,IF(B15="OPCAO",M15*Configurações!$D$23))),2) -> 0 | AL15: =R15 -> 0 | AM15: =AL15*$X$7 -> 0 | AN15: =SUM(AI15:AM15) -> 0
B16: ACAO | G16: NÃO | H16: =E16*F16 -> 0 | K16: NÃO | L16: =SUM(H16,M16) -> 0 | M16: =E16*J16 -> 0 | N16: =ROUNDDOWN(IF(OR(B16="ACAO",B16="DIR",B16="ETF",B16="EXERCICIO"),L16*Configurações!$B$9,IF(B16="EXERC. LC",H16*Configurações!$B$9+M16*Configurações!$B$37,IF(B16="OPCAO",L16*Configurações!$B$23))),2) -> 0 | O16: =ROUNDDOWN(IF(OR(B16="ACAO",B16="DIR",B16="ETF",B16="EXERCICIO"),L16*Configurações!$C$9,IF(B16="EXERC. LC",H16*Configurações!$C$9+M16*Configurações!$C$37,IF(B16="OPCAO",L16*Configurações!$C$23))),2) -> 0 | P16: =ROUNDDOWN(IF(OR(B16="ACAO",B16="DIR",B16="ETF",B16="EXERCICIO"),L16*Configurações!$D$9,IF(B16="EXERC. LC",H16*Configurações!$D$9+M16*Configurações!$D$37,IF(B16="OPCAO",L16*Configurações!$D$23))),2) -> 0 | T16: =IF(AND(G16="SIM",K16="NÃO"),-H16+M16-P16-Q16-R16-X16-S16-O16-N16+AG16,IF(AND(K16="SIM",G16="NÃO"),-H16+M16-P16-Q16-R16-X16-S16-O16-N16+AN16,IF(AND(K16="SIM",G16="SIM"),-H16+M16-P16-Q16-R16-X16-S16-O16-N16+AN16+AG16,IF(AND(K16="NÃO",G16="NÃO"),-H16+M16-P16-Q16-R16-X16-S16-O16-N16,0)))) -> 0 | V16: =IF(D16="","-",T16/H16) -> - | W16: =DAYS360(C16,I16) -> 0 | X16: =(Q16+R16)*$X$7 -> 0 | AB16: =ROUNDDOWN(IF(OR(B16="ACAO",B16="DIR",B16="ETF",B16="EXERCICIO"),H16*Configurações!$B$9,IF(B16="EXERC. LC",H16*Configurações!$B$9,IF(B16="OPCAO",H16*Configurações!$B$23))),2) -> 0 | AC16: =ROUNDDOWN(IF(OR(B16="ACAO",B16="DIR",B16="ETF",B16="EXERCICIO"),H16*Configurações!$C$9,IF(B16="EXERC. LC",H16*Configurações!$C$9,IF(B16="OPCAO",H16*Configurações!$C$23))),2) -> 0 | AD16: =ROUNDDOWN(IF(OR(B16="ACAO",B16="DIR",B16="ETF",B16="EXERCICIO"),H16*Configurações!$D$9,IF(B16="EXERC. LC",H16*Configurações!$D$9,IF(B16="OPCAO",H16*Configurações!$D$23))),2) -> 0 | AE16: =Q16 -> 0 | AF16: =AE16*$X$7 -> 0 | AG16: =SUM(AB16:AF16) -> 0 | AI16: =ROUNDDOWN(IF(OR(B16="ACAO",B16="DIR",B16="ETF",B16="EXERCICIO"),M16*Configurações!$B$9,IF(B16="EXERC. LC",M16*Configurações!$B$37,IF(B16="OPCAO",M16*Configurações!$B$23))),2) -> 0 | AJ16: =ROUNDDOWN(IF(OR(B16="ACAO",B16="DIR",B16="ETF",B16="EXERCICIO"),M16*Configurações!$C$9,IF(B16="EXERC. LC",M16*Configurações!$C$37,IF(B16="OPCAO",M16*Configurações!$C$23))),2) -> 0 | AK16: =ROUNDDOWN(IF(OR(B16="ACAO",B16="DIR",B16="ETF",B16="EXERCICIO"),M16*Configurações!$D$9,IF(B16="EXERC. LC",M16*Configurações!$D$37,IF(B16="OPCAO",M16*Configurações!$D$23))),2) -> 0 | AL16: =R16 -> 0 | AM16: =AL16*$X$7 -> 0 | AN16: =SUM(AI16:AM16) -> 0
B17: ACAO | G17: NÃO | H17: =E17*F17 -> 0 | K17: NÃO | L17: =SUM(H17,M17) -> 0 | M17: =E17*J17 -> 0 | N17: =ROUNDDOWN(IF(OR(B17="ACAO",B17="DIR",B17="ETF",B17="EXERCICIO"),L17*Configurações!$B$9,IF(B17="EXERC. LC",H17*Configurações!$B$9+M17*Configurações!$B$37,IF(B17="OPCAO",L17*Configurações!$B$23))),2) -> 0 | O17: =ROUNDDOWN(IF(OR(B17="ACAO",B17="DIR",B17="ETF",B17="EXERCICIO"),L17*Configurações!$C$9,IF(B17="EXERC. LC",H17*Configurações!$C$9+M17*Configurações!$C$37,IF(B17="OPCAO",L17*Configurações!$C$23))),2) -> 0 | P17: =ROUNDDOWN(IF(OR(B17="ACAO",B17="DIR",B17="ETF",B17="EXERCICIO"),L17*Configurações!$D$9,IF(B17="EXERC. LC",H17*Configurações!$D$9+M17*Configurações!$D$37,IF(B17="OPCAO",L17*Configurações!$D$23))),2) -> 0 | T17: =IF(AND(G17="SIM",K17="NÃO"),-H17+M17-P17-Q17-R17-X17-S17-O17-N17+AG17,IF(AND(K17="SIM",G17="NÃO"),-H17+M17-P17-Q17-R17-X17-S17-O17-N17+AN17,IF(AND(K17="SIM",G17="SIM"),-H17+M17-P17-Q17-R17-X17-S17-O17-N17+AN17+AG17,IF(AND(K17="NÃO",G17="NÃO"),-H17+M17-P17-Q17-R17-X17-S17-O17-N17,0)))) -> 0 | V17: =IF(D17="","-",T17/H17) -> - | W17: =DAYS360(C17,I17) -> 0 | X17: =(Q17+R17)*$X$7 -> 0 | AB17: =ROUNDDOWN(IF(OR(B17="ACAO",B17="DIR",B17="ETF",B17="EXERCICIO"),H17*Configurações!$B$9,IF(B17="EXERC. LC",H17*Configurações!$B$9,IF(B17="OPCAO",H17*Configurações!$B$23))),2) -> 0 | AC17: =ROUNDDOWN(IF(OR(B17="ACAO",B17="DIR",B17="ETF",B17="EXERCICIO"),H17*Configurações!$C$9,IF(B17="EXERC. LC",H17*Configurações!$C$9,IF(B17="OPCAO",H17*Configurações!$C$23))),2) -> 0 | AD17: =ROUNDDOWN(IF(OR(B17="ACAO",B17="DIR",B17="ETF",B17="EXERCICIO"),H17*Configurações!$D$9,IF(B17="EXERC. LC",H17*Configurações!$D$9,IF(B17="OPCAO",H17*Configurações!$D$23))),2) -> 0 | AE17: =Q17 -> 0 | AF17: =AE17*$X$7 -> 0 | AG17: =SUM(AB17:AF17) -> 0 | AI17: =ROUNDDOWN(IF(OR(B17="ACAO",B17="DIR",B17="ETF",B17="EXERCICIO"),M17*Configurações!$B$9,IF(B17="EXERC. LC",M17*Configurações!$B$37,IF(B17="OPCAO",M17*Configurações!$B$23))),2) -> 0 | AJ17: =ROUNDDOWN(IF(OR(B17="ACAO",B17="DIR",B17="ETF",B17="EXERCICIO"),M17*Configurações!$C$9,IF(B17="EXERC. LC",M17*Configurações!$C$37,IF(B17="OPCAO",M17*Configurações!$C$23))),2) -> 0 | AK17: =ROUNDDOWN(IF(OR(B17="ACAO",B17="DIR",B17="ETF",B17="EXERCICIO"),M17*Configurações!$D$9,IF(B17="EXERC. LC",M17*Configurações!$D$37,IF(B17="OPCAO",M17*Configurações!$D$23))),2) -> 0 | AL17: =R17 -> 0 | AM17: =AL17*$X$7 -> 0 | AN17: =SUM(AI17:AM17) -> 0
B18: ACAO | G18: NÃO | H18: =E18*F18 -> 0 | K18: NÃO | L18: =SUM(H18,M18) -> 0 | M18: =E18*J18 -> 0 | N18: =ROUNDDOWN(IF(OR(B18="ACAO",B18="DIR",B18="ETF",B18="EXERCICIO"),L18*Configurações!$B$9,IF(B18="EXERC. LC",H18*Configurações!$B$9+M18*Configurações!$B$37,IF(B18="OPCAO",L18*Configurações!$B$23))),2) -> 0 | O18: =ROUNDDOWN(IF(OR(B18="ACAO",B18="DIR",B18="ETF",B18="EXERCICIO"),L18*Configurações!$C$9,IF(B18="EXERC. LC",H18*Configurações!$C$9+M18*Configurações!$C$37,IF(B18="OPCAO",L18*Configurações!$C$23))),2) -> 0 | P18: =ROUNDDOWN(IF(OR(B18="ACAO",B18="DIR",B18="ETF",B18="EXERCICIO"),L18*Configurações!$D$9,IF(B18="EXERC. LC",H18*Configurações!$D$9+M18*Configurações!$D$37,IF(B18="OPCAO",L18*Configurações!$D$23))),2) -> 0 | T18: =IF(AND(G18="SIM",K18="NÃO"),-H18+M18-P18-Q18-R18-X18-S18-O18-N18+AG18,IF(AND(K18="SIM",G18="NÃO"),-H18+M18-P18-Q18-R18-X18-S18-O18-N18+AN18,IF(AND(K18="SIM",G18="SIM"),-H18+M18-P18-Q18-R18-X18-S18-O18-N18+AN18+AG18,IF(AND(K18="NÃO",G18="NÃO"),-H18+M18-P18-Q18-R18-X18-S18-O18-N18,0)))) -> 0 | V18: =IF(D18="","-",T18/H18) -> - | W18: =DAYS360(C18,I18) -> 0 | X18: =(Q18+R18)*$X$7 -> 0 | AB18: =ROUNDDOWN(IF(OR(B18="ACAO",B18="DIR",B18="ETF",B18="EXERCICIO"),H18*Configurações!$B$9,IF(B18="EXERC. LC",H18*Configurações!$B$9,IF(B18="OPCAO",H18*Configurações!$B$23))),2) -> 0 | AC18: =ROUNDDOWN(IF(OR(B18="ACAO",B18="DIR",B18="ETF",B18="EXERCICIO"),H18*Configurações!$C$9,IF(B18="EXERC. LC",H18*Configurações!$C$9,IF(B18="OPCAO",H18*Configurações!$C$23))),2) -> 0 | AD18: =ROUNDDOWN(IF(OR(B18="ACAO",B18="DIR",B18="ETF",B18="EXERCICIO"),H18*Configurações!$D$9,IF(B18="EXERC. LC",H18*Configurações!$D$9,IF(B18="OPCAO",H18*Configurações!$D$23))),2) -> 0 | AE18: =Q18 -> 0 | AF18: =AE18*$X$7 -> 0 | AG18: =SUM(AB18:AF18) -> 0 | AI18: =ROUNDDOWN(IF(OR(B18="ACAO",B18="DIR",B18="ETF",B18="EXERCICIO"),M18*Configurações!$B$9,IF(B18="EXERC. LC",M18*Configurações!$B$37,IF(B18="OPCAO",M18*Configurações!$B$23))),2) -> 0 | AJ18: =ROUNDDOWN(IF(OR(B18="ACAO",B18="DIR",B18="ETF",B18="EXERCICIO"),M18*Configurações!$C$9,IF(B18="EXERC. LC",M18*Configurações!$C$37,IF(B18="OPCAO",M18*Configurações!$C$23))),2) -> 0 | AK18: =ROUNDDOWN(IF(OR(B18="ACAO",B18="DIR",B18="ETF",B18="EXERCICIO"),M18*Configurações!$D$9,IF(B18="EXERC. LC",M18*Configurações!$D$37,IF(B18="OPCAO",M18*Configurações!$D$23))),2) -> 0 | AL18: =R18 -> 0 | AM18: =AL18*$X$7 -> 0 | AN18: =SUM(AI18:AM18) -> 0
B19: ACAO | G19: NÃO | H19: =E19*F19 -> 0 | K19: NÃO | L19: =SUM(H19,M19) -> 0 | M19: =E19*J19 -> 0 | N19: =ROUNDDOWN(IF(OR(B19="ACAO",B19="DIR",B19="ETF",B19="EXERCICIO"),L19*Configurações!$B$9,IF(B19="EXERC. LC",H19*Configurações!$B$9+M19*Configurações!$B$37,IF(B19="OPCAO",L19*Configurações!$B$23))),2) -> 0 | O19: =ROUNDDOWN(IF(OR(B19="ACAO",B19="DIR",B19="ETF",B19="EXERCICIO"),L19*Configurações!$C$9,IF(B19="EXERC. LC",H19*Configurações!$C$9+M19*Configurações!$C$37,IF(B19="OPCAO",L19*Configurações!$C$23))),2) -> 0 | P19: =ROUNDDOWN(IF(OR(B19="ACAO",B19="DIR",B19="ETF",B19="EXERCICIO"),L19*Configurações!$D$9,IF(B19="EXERC. LC",H19*Configurações!$D$9+M19*Configurações!$D$37,IF(B19="OPCAO",L19*Configurações!$D$23))),2) -> 0 | T19: =IF(AND(G19="SIM",K19="NÃO"),-H19+M19-P19-Q19-R19-X19-S19-O19-N19+AG19,IF(AND(K19="SIM",G19="NÃO"),-H19+M19-P19-Q19-R19-X19-S19-O19-N19+AN19,IF(AND(K19="SIM",G19="SIM"),-H19+M19-P19-Q19-R19-X19-S19-O19-N19+AN19+AG19,IF(AND(K19="NÃO",G19="NÃO"),-H19+M19-P19-Q19-R19-X19-S19-O19-N19,0)))) -> 0 | V19: =IF(D19="","-",T19/H19) -> - | W19: =DAYS360(C19,I19) -> 0 | X19: =(Q19+R19)*$X$7 -> 0 | AB19: =ROUNDDOWN(IF(OR(B19="ACAO",B19="DIR",B19="ETF",B19="EXERCICIO"),H19*Configurações!$B$9,IF(B19="EXERC. LC",H19*Configurações!$B$9,IF(B19="OPCAO",H19*Configurações!$B$23))),2) -> 0 | AC19: =ROUNDDOWN(IF(OR(B19="ACAO",B19="DIR",B19="ETF",B19="EXERCICIO"),H19*Configurações!$C$9,IF(B19="EXERC. LC",H19*Configurações!$C$9,IF(B19="OPCAO",H19*Configurações!$C$23))),2) -> 0 | AD19: =ROUNDDOWN(IF(OR(B19="ACAO",B19="DIR",B19="ETF",B19="EXERCICIO"),H19*Configurações!$D$9,IF(B19="EXERC. LC",H19*Configurações!$D$9,IF(B19="OPCAO",H19*Configurações!$D$23))),2) -> 0 | AE19: =Q19 -> 0 | AF19: =AE19*$X$7 -> 0 | AG19: =SUM(AB19:AF19) -> 0 | AI19: =ROUNDDOWN(IF(OR(B19="ACAO",B19="DIR",B19="ETF",B19="EXERCICIO"),M19*Configurações!$B$9,IF(B19="EXERC. LC",M19*Configurações!$B$37,IF(B19="OPCAO",M19*Configurações!$B$23))),2) -> 0 | AJ19: =ROUNDDOWN(IF(OR(B19="ACAO",B19="DIR",B19="ETF",B19="EXERCICIO"),M19*Configurações!$C$9,IF(B19="EXERC. LC",M19*Configurações!$C$37,IF(B19="OPCAO",M19*Configurações!$C$23))),2) -> 0 | AK19: =ROUNDDOWN(IF(OR(B19="ACAO",B19="DIR",B19="ETF",B19="EXERCICIO"),M19*Configurações!$D$9,IF(B19="EXERC. LC",M19*Configurações!$D$37,IF(B19="OPCAO",M19*Configurações!$D$23))),2) -> 0 | AL19: =R19 -> 0 | AM19: =AL19*$X$7 -> 0 | AN19: =SUM(AI19:AM19) -> 0
B20: ACAO | G20: NÃO | H20: =E20*F20 -> 0 | K20: NÃO | L20: =SUM(H20,M20) -> 0 | M20: =E20*J20 -> 0 | N20: =ROUNDDOWN(IF(OR(B20="ACAO",B20="DIR",B20="ETF",B20="EXERCICIO"),L20*Configurações!$B$9,IF(B20="EXERC. LC",H20*Configurações!$B$9+M20*Configurações!$B$37,IF(B20="OPCAO",L20*Configurações!$B$23))),2) -> 0 | O20: =ROUNDDOWN(IF(OR(B20="ACAO",B20="DIR",B20="ETF",B20="EXERCICIO"),L20*Configurações!$C$9,IF(B20="EXERC. LC",H20*Configurações!$C$9+M20*Configurações!$C$37,IF(B20="OPCAO",L20*Configurações!$C$23))),2) -> 0 | P20: =ROUNDDOWN(IF(OR(B20="ACAO",B20="DIR",B20="ETF",B20="EXERCICIO"),L20*Configurações!$D$9,IF(B20="EXERC. LC",H20*Configurações!$D$9+M20*Configurações!$D$37,IF(B20="OPCAO",L20*Configurações!$D$23))),2) -> 0 | T20: =IF(AND(G20="SIM",K20="NÃO"),-H20+M20-P20-Q20-R20-X20-S20-O20-N20+AG20,IF(AND(K20="SIM",G20="NÃO"),-H20+M20-P20-Q20-R20-X20-S20-O20-N20+AN20,IF(AND(K20="SIM",G20="SIM"),-H20+M20-P20-Q20-R20-X20-S20-O20-N20+AN20+AG20,IF(AND(K20="NÃO",G20="NÃO"),-H20+M20-P20-Q20-R20-X20-S20-O20-N20,0)))) -> 0 | V20: =IF(D20="","-",T20/H20) -> - | W20: =DAYS360(C20,I20) -> 0 | X20: =(Q20+R20)*$X$7 -> 0 | AB20: =ROUNDDOWN(IF(OR(B20="ACAO",B20="DIR",B20="ETF",B20="EXERCICIO"),H20*Configurações!$B$9,IF(B20="EXERC. LC",H20*Configurações!$B$9,IF(B20="OPCAO",H20*Configurações!$B$23))),2) -> 0 | AC20: =ROUNDDOWN(IF(OR(B20="ACAO",B20="DIR",B20="ETF",B20="EXERCICIO"),H20*Configurações!$C$9,IF(B20="EXERC. LC",H20*Configurações!$C$9,IF(B20="OPCAO",H20*Configurações!$C$23))),2) -> 0 | AD20: =ROUNDDOWN(IF(OR(B20="ACAO",B20="DIR",B20="ETF",B20="EXERCICIO"),H20*Configurações!$D$9,IF(B20="EXERC. LC",H20*Configurações!$D$9,IF(B20="OPCAO",H20*Configurações!$D$23))),2) -> 0 | AE20: =Q20 -> 0 | AF20: =AE20*$X$7 -> 0 | AG20: =SUM(AB20:AF20) -> 0 | AI20: =ROUNDDOWN(IF(OR(B20="ACAO",B20="DIR",B20="ETF",B20="EXERCICIO"),M20*Configurações!$B$9,IF(B20="EXERC. LC",M20*Configurações!$B$37,IF(B20="OPCAO",M20*Configurações!$B$23))),2) -> 0 | AJ20: =ROUNDDOWN(IF(OR(B20="ACAO",B20="DIR",B20="ETF",B20="EXERCICIO"),M20*Configurações!$C$9,IF(B20="EXERC. LC",M20*Configurações!$C$37,IF(B20="OPCAO",M20*Configurações!$C$23))),2) -> 0 | AK20: =ROUNDDOWN(IF(OR(B20="ACAO",B20="DIR",B20="ETF",B20="EXERCICIO"),M20*Configurações!$D$9,IF(B20="EXERC. LC",M20*Configurações!$D$37,IF(B20="OPCAO",M20*Configurações!$D$23))),2) -> 0 | AL20: =R20 -> 0 | AM20: =AL20*$X$7 -> 0 | AN20: =SUM(AI20:AM20) -> 0
B21: ACAO | G21: NÃO | H21: =E21*F21 -> 0 | K21: NÃO | L21: =SUM(H21,M21) -> 0 | M21: =E21*J21 -> 0 | N21: =ROUNDDOWN(IF(OR(B21="ACAO",B21="DIR",B21="ETF",B21="EXERCICIO"),L21*Configurações!$B$9,IF(B21="EXERC. LC",H21*Configurações!$B$9+M21*Configurações!$B$37,IF(B21="OPCAO",L21*Configurações!$B$23))),2) -> 0 | O21: =ROUNDDOWN(IF(OR(B21="ACAO",B21="DIR",B21="ETF",B21="EXERCICIO"),L21*Configurações!$C$9,IF(B21="EXERC. LC",H21*Configurações!$C$9+M21*Configurações!$C$37,IF(B21="OPCAO",L21*Configurações!$C$23))),2) -> 0 | P21: =ROUNDDOWN(IF(OR(B21="ACAO",B21="DIR",B21="ETF",B21="EXERCICIO"),L21*Configurações!$D$9,IF(B21="EXERC. LC",H21*Configurações!$D$9+M21*Configurações!$D$37,IF(B21="OPCAO",L21*Configurações!$D$23))),2) -> 0 | T21: =IF(AND(G21="SIM",K21="NÃO"),-H21+M21-P21-Q21-R21-X21-S21-O21-N21+AG21,IF(AND(K21="SIM",G21="NÃO"),-H21+M21-P21-Q21-R21-X21-S21-O21-N21+AN21,IF(AND(K21="SIM",G21="SIM"),-H21+M21-P21-Q21-R21-X21-S21-O21-N21+AN21+AG21,IF(AND(K21="NÃO",G21="NÃO"),-H21+M21-P21-Q21-R21-X21-S21-O21-N21,0)))) -> 0 | V21: =IF(D21="","-",T21/H21) -> - | W21: =DAYS360(C21,I21) -> 0 | X21: =(Q21+R21)*$X$7 -> 0 | AB21: =ROUNDDOWN(IF(OR(B21="ACAO",B21="DIR",B21="ETF",B21="EXERCICIO"),H21*Configurações!$B$9,IF(B21="EXERC. LC",H21*Configurações!$B$9,IF(B21="OPCAO",H21*Configurações!$B$23))),2) -> 0 | AC21: =ROUNDDOWN(IF(OR(B21="ACAO",B21="DIR",B21="ETF",B21="EXERCICIO"),H21*Configurações!$C$9,IF(B21="EXERC. LC",H21*Configurações!$C$9,IF(B21="OPCAO",H21*Configurações!$C$23))),2) -> 0 | AD21: =ROUNDDOWN(IF(OR(B21="ACAO",B21="DIR",B21="ETF",B21="EXERCICIO"),H21*Configurações!$D$9,IF(B21="EXERC. LC",H21*Configurações!$D$9,IF(B21="OPCAO",H21*Configurações!$D$23))),2) -> 0 | AE21: =Q21 -> 0 | AF21: =AE21*$X$7 -> 0 | AG21: =SUM(AB21:AF21) -> 0 | AI21: =ROUNDDOWN(IF(OR(B21="ACAO",B21="DIR",B21="ETF",B21="EXERCICIO"),M21*Configurações!$B$9,IF(B21="EXERC. LC",M21*Configurações!$B$37,IF(B21="OPCAO",M21*Configurações!$B$23))),2) -> 0 | AJ21: =ROUNDDOWN(IF(OR(B21="ACAO",B21="DIR",B21="ETF",B21="EXERCICIO"),M21*Configurações!$C$9,IF(B21="EXERC. LC",M21*Configurações!$C$37,IF(B21="OPCAO",M21*Configurações!$C$23))),2) -> 0 | AK21: =ROUNDDOWN(IF(OR(B21="ACAO",B21="DIR",B21="ETF",B21="EXERCICIO"),M21*Configurações!$D$9,IF(B21="EXERC. LC",M21*Configurações!$D$37,IF(B21="OPCAO",M21*Configurações!$D$23))),2) -> 0 | AL21: =R21 -> 0 | AM21: =AL21*$X$7 -> 0 | AN21: =SUM(AI21:AM21) -> 0
B22: ACAO | G22: NÃO | H22: =E22*F22 -> 0 | K22: NÃO | L22: =SUM(H22,M22) -> 0 | M22: =E22*J22 -> 0 | N22: =ROUNDDOWN(IF(OR(B22="ACAO",B22="DIR",B22="ETF",B22="EXERCICIO"),L22*Configurações!$B$9,IF(B22="EXERC. LC",H22*Configurações!$B$9+M22*Configurações!$B$37,IF(B22="OPCAO",L22*Configurações!$B$23))),2) -> 0 | O22: =ROUNDDOWN(IF(OR(B22="ACAO",B22="DIR",B22="ETF",B22="EXERCICIO"),L22*Configurações!$C$9,IF(B22="EXERC. LC",H22*Configurações!$C$9+M22*Configurações!$C$37,IF(B22="OPCAO",L22*Configurações!$C$23))),2) -> 0 | P22: =ROUNDDOWN(IF(OR(B22="ACAO",B22="DIR",B22="ETF",B22="EXERCICIO"),L22*Configurações!$D$9,IF(B22="EXERC. LC",H22*Configurações!$D$9+M22*Configurações!$D$37,IF(B22="OPCAO",L22*Configurações!$D$23))),2) -> 0 | T22: =IF(AND(G22="SIM",K22="NÃO"),-H22+M22-P22-Q22-R22-X22-S22-O22-N22+AG22,IF(AND(K22="SIM",G22="NÃO"),-H22+M22-P22-Q22-R22-X22-S22-O22-N22+AN22,IF(AND(K22="SIM",G22="SIM"),-H22+M22-P22-Q22-R22-X22-S22-O22-N22+AN22+AG22,IF(AND(K22="NÃO",G22="NÃO"),-H22+M22-P22-Q22-R22-X22-S22-O22-N22,0)))) -> 0 | V22: =IF(D22="","-",T22/H22) -> - | W22: =DAYS360(C22,I22) -> 0 | X22: =(Q22+R22)*$X$7 -> 0 | AB22: =ROUNDDOWN(IF(OR(B22="ACAO",B22="DIR",B22="ETF",B22="EXERCICIO"),H22*Configurações!$B$9,IF(B22="EXERC. LC",H22*Configurações!$B$9,IF(B22="OPCAO",H22*Configurações!$B$23))),2) -> 0 | AC22: =ROUNDDOWN(IF(OR(B22="ACAO",B22="DIR",B22="ETF",B22="EXERCICIO"),H22*Configurações!$C$9,IF(B22="EXERC. LC",H22*Configurações!$C$9,IF(B22="OPCAO",H22*Configurações!$C$23))),2) -> 0 | AD22: =ROUNDDOWN(IF(OR(B22="ACAO",B22="DIR",B22="ETF",B22="EXERCICIO"),H22*Configurações!$D$9,IF(B22="EXERC. LC",H22*Configurações!$D$9,IF(B22="OPCAO",H22*Configurações!$D$23))),2) -> 0 | AE22: =Q22 -> 0 | AF22: =AE22*$X$7 -> 0 | AG22: =SUM(AB22:AF22) -> 0 | AI22: =ROUNDDOWN(IF(OR(B22="ACAO",B22="DIR",B22="ETF",B22="EXERCICIO"),M22*Configurações!$B$9,IF(B22="EXERC. LC",M22*Configurações!$B$37,IF(B22="OPCAO",M22*Configurações!$B$23))),2) -> 0 | AJ22: =ROUNDDOWN(IF(OR(B22="ACAO",B22="DIR",B22="ETF",B22="EXERCICIO"),M22*Configurações!$C$9,IF(B22="EXERC. LC",M22*Configurações!$C$37,IF(B22="OPCAO",M22*Configurações!$C$23))),2) -> 0 | AK22: =ROUNDDOWN(IF(OR(B22="ACAO",B22="DIR",B22="ETF",B22="EXERCICIO"),M22*Configurações!$D$9,IF(B22="EXERC. LC",M22*Configurações!$D$37,IF(B22="OPCAO",M22*Configurações!$D$23))),2) -> 0 | AL22: =R22 -> 0 | AM22: =AL22*$X$7 -> 0 | AN22: =SUM(AI22:AM22) -> 0
B23: ACAO | G23: NÃO | H23: =E23*F23 -> 0 | K23: NÃO | L23: =SUM(H23,M23) -> 0 | M23: =E23*J23 -> 0 | N23: =ROUNDDOWN(IF(OR(B23="ACAO",B23="DIR",B23="ETF",B23="EXERCICIO"),L23*Configurações!$B$9,IF(B23="EXERC. LC",H23*Configurações!$B$9+M23*Configurações!$B$37,IF(B23="OPCAO",L23*Configurações!$B$23))),2) -> 0 | O23: =ROUNDDOWN(IF(OR(B23="ACAO",B23="DIR",B23="ETF",B23="EXERCICIO"),L23*Configurações!$C$9,IF(B23="EXERC. LC",H23*Configurações!$C$9+M23*Configurações!$C$37,IF(B23="OPCAO",L23*Configurações!$C$23))),2) -> 0 | P23: =ROUNDDOWN(IF(OR(B23="ACAO",B23="DIR",B23="ETF",B23="EXERCICIO"),L23*Configurações!$D$9,IF(B23="EXERC. LC",H23*Configurações!$D$9+M23*Configurações!$D$37,IF(B23="OPCAO",L23*Configurações!$D$23))),2) -> 0 | T23: =IF(AND(G23="SIM",K23="NÃO"),-H23+M23-P23-Q23-R23-X23-S23-O23-N23+AG23,IF(AND(K23="SIM",G23="NÃO"),-H23+M23-P23-Q23-R23-X23-S23-O23-N23+AN23,IF(AND(K23="SIM",G23="SIM"),-H23+M23-P23-Q23-R23-X23-S23-O23-N23+AN23+AG23,IF(AND(K23="NÃO",G23="NÃO"),-H23+M23-P23-Q23-R23-X23-S23-O23-N23,0)))) -> 0 | V23: =IF(D23="","-",T23/H23) -> - | W23: =DAYS360(C23,I23) -> 0 | X23: =(Q23+R23)*$X$7 -> 0 | AB23: =ROUNDDOWN(IF(OR(B23="ACAO",B23="DIR",B23="ETF",B23="EXERCICIO"),H23*Configurações!$B$9,IF(B23="EXERC. LC",H23*Configurações!$B$9,IF(B23="OPCAO",H23*Configurações!$B$23))),2) -> 0 | AC23: =ROUNDDOWN(IF(OR(B23="ACAO",B23="DIR",B23="ETF",B23="EXERCICIO"),H23*Configurações!$C$9,IF(B23="EXERC. LC",H23*Configurações!$C$9,IF(B23="OPCAO",H23*Configurações!$C$23))),2) -> 0 | AD23: =ROUNDDOWN(IF(OR(B23="ACAO",B23="DIR",B23="ETF",B23="EXERCICIO"),H23*Configurações!$D$9,IF(B23="EXERC. LC",H23*Configurações!$D$9,IF(B23="OPCAO",H23*Configurações!$D$23))),2) -> 0 | AE23: =Q23 -> 0 | AF23: =AE23*$X$7 -> 0 | AG23: =SUM(AB23:AF23) -> 0 | AI23: =ROUNDDOWN(IF(OR(B23="ACAO",B23="DIR",B23="ETF",B23="EXERCICIO"),M23*Configurações!$B$9,IF(B23="EXERC. LC",M23*Configurações!$B$37,IF(B23="OPCAO",M23*Configurações!$B$23))),2) -> 0 | AJ23: =ROUNDDOWN(IF(OR(B23="ACAO",B23="DIR",B23="ETF",B23="EXERCICIO"),M23*Configurações!$C$9,IF(B23="EXERC. LC",M23*Configurações!$C$37,IF(B23="OPCAO",M23*Configurações!$C$23))),2) -> 0 | AK23: =ROUNDDOWN(IF(OR(B23="ACAO",B23="DIR",B23="ETF",B23="EXERCICIO"),M23*Configurações!$D$9,IF(B23="EXERC. LC",M23*Configurações!$D$37,IF(B23="OPCAO",M23*Configurações!$D$23))),2) -> 0 | AL23: =R23 -> 0 | AM23: =AL23*$X$7 -> 0 | AN23: =SUM(AI23:AM23) -> 0
... B48: ACAO | G48: NÃO | H48: =E48*F48 -> 0 | K48: NÃO | L48: =SUM(H48,M48) -> 0 | M48: =E48*J48 -> 0 | N48: =ROUNDDOWN(IF(OR(B48="ACAO",B48="DIR",B48="ETF",B48="EXERCICIO"),L48*Configurações!$B$9,IF(B48="EXERC. LC",H48*Configurações!$B$9+M48*Configurações!$B$37,IF(B48="OPCAO",L48*Configurações!$B$23))),2) -> 0 | O48: =ROUNDDOWN(IF(OR(B48="ACAO",B48="DIR",B48="ETF",B48="EXERCICIO"),L48*Configurações!$C$9,IF(B48="EXERC. LC",H48*Configurações!$C$9+M48*Configurações!$C$37,IF(B48="OPCAO",L48*Configurações!$C$23))),2) -> 0 | P48: =ROUNDDOWN(IF(OR(B48="ACAO",B48="DIR",B48="ETF",B48="EXERCICIO"),L48*Configurações!$D$9,IF(B48="EXERC. LC",H48*Configurações!$D$9+M48*Configurações!$D$37,IF(B48="OPCAO",L48*Configurações!$D$23))),2) -> 0 | T48: =IF(AND(G48="SIM",K48="NÃO"),-H48+M48-P48-Q48-R48-X48-S48-O48-N48+AG48,IF(AND(K48="SIM",G48="NÃO"),-H48+M48-P48-Q48-R48-X48-S48-O48-N48+AN48,IF(AND(K48="SIM",G48="SIM"),-H48+M48-P48-Q48-R48-X48-S48-O48-N48+AN48+AG48,IF(AND(K48="NÃO",G48="NÃO"),-H48+M48-P48-Q48-R48-X48-S48-O48-N48,0)))) -> 0 | V48: =IF(D48="","-",T48/H48) -> - | W48: =DAYS360(C48,I48) -> 0 | X48: =(Q48+R48)*$X$7 -> 0 | AB48: =ROUNDDOWN(IF(OR(B48="ACAO",B48="DIR",B48="ETF",B48="EXERCICIO"),H48*Configurações!$B$9,IF(B48="EXERC. LC",H48*Configurações!$B$9,IF(B48="OPCAO",H48*Configurações!$B$23))),2) -> 0 | AC48: =ROUNDDOWN(IF(OR(B48="ACAO",B48="DIR",B48="ETF",B48="EXERCICIO"),H48*Configurações!$C$9,IF(B48="EXERC. LC",H48*Configurações!$C$9,IF(B48="OPCAO",H48*Configurações!$C$23))),2) -> 0 | AD48: =ROUNDDOWN(IF(OR(B48="ACAO",B48="DIR",B48="ETF",B48="EXERCICIO"),H48*Configurações!$D$9,IF(B48="EXERC. LC",H48*Configurações!$D$9,IF(B48="OPCAO",H48*Configurações!$D$23))),2) -> 0 | AE48: =Q48 -> 0 | AF48: =AE48*$X$7 -> 0 | AG48: =SUM(AB48:AF48) -> 0 | AI48: =ROUNDDOWN(IF(OR(B48="ACAO",B48="DIR",B48="ETF",B48="EXERCICIO"),M48*Configurações!$B$9,IF(B48="EXERC. LC",M48*Configurações!$B$37,IF(B48="OPCAO",M48*Configurações!$B$23))),2) -> 0 | AJ48: =ROUNDDOWN(IF(OR(B48="ACAO",B48="DIR",B48="ETF",B48="EXERCICIO"),M48*Configurações!$C$9,IF(B48="EXERC. LC",M48*Configurações!$C$37,IF(B48="OPCAO",M48*Configurações!$C$23))),2) -> 0 | AK48: =ROUNDDOWN(IF(OR(B48="ACAO",B48="DIR",B48="ETF",B48="EXERCICIO"),M48*Configurações!$D$9,IF(B48="EXERC. LC",M48*Configurações!$D$37,IF(B48="OPCAO",M48*Configurações!$D$23))),2) -> 0 | AL48: =R48 -> 0 | AM48: =AL48*$X$7 -> 0 | AN48: =SUM(AI48:AM48) -> 0
M49: =SUM(M8:M48) -> 0 | U49: =IF(SUM(U8:U48)>1,SUM(U8:U48),0) -> 0
E52: OPERAÇÕES NORMAIS
E54: Ações | I54: ETFs | M54: Direitos de Subscrição | Q54: Opções
C57: Resultado | E57: =SUMIF(B8:B48,"ACAO",T8:T48) -> 0 | I57: =SUMIF(B8:B48,"ETF",T8:T48) -> 0 | M57: =SUMIF(B8:B48,"DIR",T8:T48) -> 0 | Q57: =SUMIF(B8:B48,"OPCAO",T8:T48)+SUMIF(B8:B48,"EXERCICIO",T8:T48)+SUMIF(B8:B48,"EXERC. LC",T8:T48) -> 0
C60: Volume Vendas | E60: =SUMIF(B8:B48,"ACAO",M8:M48) -> 0
C63: Emolumentos/Taxas | E63: =SUMIF(B8:B48,"ACAO",N8:N48)+SUMIF(B8:B48,"ACAO",O8:O48)+SUMIF(B8:B48,"ACAO",P8:P48) -> 0 | I63: =SUMIF(B8:B48,"ETF",N8:N48)+SUMIF(B8:B48,"ETF",O8:O48)+SUMIF(B8:B48,"ETF",P8:P48) -> 0 | M63: =SUMIF(B8:B48,"DIR",N8:N48)+SUMIF(B8:B48,"DIR",O8:O48)+SUMIF(B8:B48,"DIR",P8:P48) -> 0 | Q63: =SUMIF(B8:B48,"OPCAO",N8:N48)+SUMIF(B8:B48,"OPCAO",O8:O48)+SUMIF(B8:B48,"OPCAO",P8:P48)+SUMIF(B8:B48,"EXERCICIO",N8:N48)+SUMIF(B8:B48,"EXERCICIO",O8:O48)+SUMIF(B8:B48,"EXERCICIO",P8:P48)+SUMIF(B8:B48,"EXERC. LC",N8:N48)+SUMIF(B8:B48,"EXERC. LC",O8:O48)+SUMIF(B8:B48,"EXERC. LC",P8:P48) -> 0
C66: Corretagens | E66: =SUMIF(B8:B48,"ACAO",Q8:Q48)+SUMIF(B8:B48,"ACAO",R8:R48) -> 0 | I66: =SUMIF(B8:B48,"ETF",Q8:Q48)+SUMIF(B8:B48,"ETF",R8:R48) -> 0 | M66: =SUMIF(B8:B48,"DIR",Q8:Q48)+SUMIF(B8:B48,"DIR",R8:R48) -> 0 | Q66: =SUMIF(B8:B48,"OPCAO",Q8:Q48)+SUMIF(B8:B48,"OPCAO",R8:R48)+SUMIF(B8:B48,"EXERCICIO",Q8:Q48)+SUMIF(B8:B48,"EXERCICIO",R8:R48)+SUMIF(B8:B48,"EXERC. LC",Q8:Q48)+SUMIF(B8:B48,"EXERC. LC",R8:R48) -> 0
E70: Resultado Ações | H70: + | I70: Resultado ETFs, DIR, Opções | L70: = | M70: Resultado Geral
E73: =E57 -> 0 | I73: =I57+M57+Q57 -> 0 | M73: =I73+E73 -> 0
B83: ACAO
B84: OPCAO
B85: ETF
B86: DIR
B87: EXERCICIO
B88: EXERC. LC

Sheet Operações Day Trade
B2: Período de Apuração | G2: Operação Day Trade: Operação com Compra e Venda no mesmo dia
B3: Mês: | C3: ='Operações Normais'!C3 -> 6 | D3: Ano: | E3: ='Operações Normais'!E3 -> 2020
B5: Operações Day Trade Ações e Opções | V5: ISS
B6: Tipo | C6: Data Compra | D6: Código Ativo | E6: Quantidade | F6: Preço Compra | G6: Movimento Compra | H6: Data Venda | I6: Preço Venda | J6: Movimento Total | K6: Movimento Venda | L6: Taxa Negociação | M6: Taxa Liquidação | N6: Taxa Registro | O6: Corretagem Compra | P6: Corretagem Venda | Q6: Outras despesas | R6: Resultado | S6: IRRF Day-Trade | T6: % | U6: Dias | V6: ='Operações Normais'!X7 -> 0.1068
B8: ACAO | G8: =E8*F8 -> 0 | H8: =C8 -> 0 | J8: =SUM(G8,K8) -> 0 | K8: =E8*I8 -> 0 | L8: =ROUNDDOWN(IF(OR(B8="ACAO",B8="DIR",B8="ETF"),J8*Configurações!$B$16,IF(B8="OPCAO",J8*Configurações!$B$30)),2) -> 0 | M8: =ROUNDDOWN(IF(OR(B8="ACAO",B8="DIR",B8="ETF"),J8*Configurações!$C$16,IF(B8="OPCAO",J8*Configurações!$C$30)),2) -> 0 | N8: =ROUNDDOWN(IF(OR(B8="ACAO",B8="DIR",B8="ETF"),J8*Configurações!$D$16,IF(B8="OPCAO",J8*Configurações!$D$30)),2) -> 0 | O8: 0 | P8: 0 | R8: =-G8+K8-N8-O8-P8-V8-Q8-M8-L8 -> 0 | T8: =IF(D8="","-",R8/G8) -> - | U8: =DAYS360(C8,H8) -> 0 | V8: =(O8+P8)*$V$6 -> 0
B9: ACAO | G9: =E9*F9 -> 0 | H9: =C9 -> 0 | J9: =SUM(G9,K9) -> 0 | K9: =E9*I9 -> 0 | L9: =ROUNDDOWN(IF(OR(B9="ACAO",B9="DIR",B9="ETF"),J9*Configurações!$B$16,IF(B9="OPCAO",J9*Configurações!$B$30)),2) -> 0 | M9: =ROUNDDOWN(IF(OR(B9="ACAO",B9="DIR",B9="ETF"),J9*Configurações!$C$16,IF(B9="OPCAO",J9*Configurações!$C$30)),2) -> 0 | N9: =ROUNDDOWN(IF(OR(B9="ACAO",B9="DIR",B9="ETF"),J9*Configurações!$D$16,IF(B9="OPCAO",J9*Configurações!$D$30)),2) -> 0 | O9: 0 | P9: 0 | R9: =-G9+K9-N9-O9-P9-V9-Q9-M9-L9 -> 0 | T9: =IF(D9="","-",R9/G9) -> - | U9: =DAYS360(C9,H9) -> 0 | V9: =(O9+P9)*$V$6 -> 0
B10: ACAO | G10: =E10*F10 -> 0 | H10: =C10 -> 0 | J10: =SUM(G10,K10) -> 0 | K10: =E10*I10 -> 0 | L10: =ROUNDDOWN(IF(OR(B10="ACAO",B10="DIR",B10="ETF"),J10*Configurações!$B$16,IF(B10="OPCAO",J10*Configurações!$B$30)),2) -> 0 | M10: =ROUNDDOWN(IF(OR(B10="ACAO",B10="DIR",B10="ETF"),J10*Configurações!$C$16,IF(B10="OPCAO",J10*Configurações!$C$30)),2) -> 0 | N10: =ROUNDDOWN(IF(OR(B10="ACAO",B10="DIR",B10="ETF"),J10*Configurações!$D$16,IF(B10="OPCAO",J10*Configurações!$D$30)),2) -> 0 | O10: 0 | P10: 0 | R10: =-G10+K10-N10-O10-P10-V10-Q10-M10-L10 -> 0 | T10: =IF(D10="","-",R10/G10) -> - | U10: =DAYS360(C10,H10) -> 0 | V10: =(O10+P10)*$V$6 -> 0
B11: ACAO | G11: =E11*F11 -> 0 | H11: =C11 -> 0 | J11: =SUM(G11,K11) -> 0 | K11: =E11*I11 -> 0 | L11: =ROUNDDOWN(IF(OR(B11="ACAO",B11="DIR",B11="ETF"),J11*Configurações!$B$16,IF(B11="OPCAO",J11*Configurações!$B$30)),2) -> 0 | M11: =ROUNDDOWN(IF(OR(B11="ACAO",B11="DIR",B11="ETF"),J11*Configurações!$C$16,IF(B11="OPCAO",J11*Configurações!$C$30)),2) -> 0 | N11: =ROUNDDOWN(IF(OR(B11="ACAO",B11="DIR",B11="ETF"),J11*Configurações!$D$16,IF(B11="OPCAO",J11*Configurações!$D$30)),2) -> 0 | R11: =-G11+K11-N11-O11-P11-V11-Q11-M11-L11 -> 0 | T11: =IF(D11="","-",R11/G11) -> - | U11: =DAYS360(C11,H11) -> 0 | V11: =(O11+P11)*$V$6 -> 0
B12: ACAO | G12: =E12*F12 -> 0 | H12: =C12 -> 0 | J12: =SUM(G12,K12) -> 0 | K12: =E12*I12 -> 0 | L12: =ROUNDDOWN(IF(OR(B12="ACAO",B12="DIR",B12="ETF"),J12*Configurações!$B$16,IF(B12="OPCAO",J12*Configurações!$B$30)),2) -> 0 | M12: =ROUNDDOWN(IF(OR(B12="ACAO",B12="DIR",B12="ETF"),J12*Configurações!$C$16,IF(B12="OPCAO",J12*Configurações!$C$30)),2) -> 0 | N12: =ROUNDDOWN(IF(OR(B12="ACAO",B12="DIR",B12="ETF"),J12*Configurações!$D$16,IF(B12="OPCAO",J12*Configurações!$D$30)),2) -> 0 | R12: =-G12+K12-N12-O12-P12-V12-Q12-M12-L12 -> 0 | T12: =IF(D12="","-",R12/G12) -> - | U12: =DAYS360(C12,H12) -> 0 | V12: =(O12+P12)*$V$6 -> 0
B13: ACAO | G13: =E13*F13 -> 0 | H13: =C13 -> 0 | J13: =SUM(G13,K13) -> 0 | K13: =E13*I13 -> 0 | L13: =ROUNDDOWN(IF(OR(B13="ACAO",B13="DIR",B13="ETF"),J13*Configurações!$B$16,IF(B13="OPCAO",J13*Configurações!$B$30)),2) -> 0 | M13: =ROUNDDOWN(IF(OR(B13="ACAO",B13="DIR",B13="ETF"),J13*Configurações!$C$16,IF(B13="OPCAO",J13*Configurações!$C$30)),2) -> 0 | N13: =ROUNDDOWN(IF(OR(B13="ACAO",B13="DIR",B13="ETF"),J13*Configurações!$D$16,IF(B13="OPCAO",J13*Configurações!$D$30)),2) -> 0 | R13: =-G13+K13-N13-O13-P13-V13-Q13-M13-L13 -> 0 | T13: =IF(D13="","-",R13/G13) -> - | U13: =DAYS360(C13,H13) -> 0 | V13: =(O13+P13)*$V$6 -> 0
B14: ACAO | G14: =E14*F14 -> 0 | H14: =C14 -> 0 | J14: =SUM(G14,K14) -> 0 | K14: =E14*I14 -> 0 | L14: =ROUNDDOWN(IF(OR(B14="ACAO",B14="DIR",B14="ETF"),J14*Configurações!$B$16,IF(B14="OPCAO",J14*Configurações!$B$30)),2) -> 0 | M14: =ROUNDDOWN(IF(OR(B14="ACAO",B14="DIR",B14="ETF"),J14*Configurações!$C$16,IF(B14="OPCAO",J14*Configurações!$C$30)),2) -> 0 | N14: =ROUNDDOWN(IF(OR(B14="ACAO",B14="DIR",B14="ETF"),J14*Configurações!$D$16,IF(B14="OPCAO",J14*Configurações!$D$30)),2) -> 0 | R14: =-G14+K14-N14-O14-P14-V14-Q14-M14-L14 -> 0 | T14: =IF(D14="","-",R14/G14) -> - | U14: =DAYS360(C14,H14) -> 0 | V14: =(O14+P14)*$V$6 -> 0
B15: ACAO | G15: =E15*F15 -> 0 | H15: =C15 -> 0 | J15: =SUM(G15,K15) -> 0 | K15: =E15*I15 -> 0 | L15: =ROUNDDOWN(IF(OR(B15="ACAO",B15="DIR",B15="ETF"),J15*Configurações!$B$16,IF(B15="OPCAO",J15*Configurações!$B$30)),2) -> 0 | M15: =ROUNDDOWN(IF(OR(B15="ACAO",B15="DIR",B15="ETF"),J15*Configurações!$C$16,IF(B15="OPCAO",J15*Configurações!$C$30)),2) -> 0 | N15: =ROUNDDOWN(IF(OR(B15="ACAO",B15="DIR",B15="ETF"),J15*Configurações!$D$16,IF(B15="OPCAO",J15*Configurações!$D$30)),2) -> 0 | R15: =-G15+K15-N15-O15-P15-V15-Q15-M15-L15 -> 0 | T15: =IF(D15="","-",R15/G15) -> - | U15: =DAYS360(C15,H15) -> 0 | V15: =(O15+P15)*$V$6 -> 0
B16: ACAO | G16: =E16*F16 -> 0 | H16: =C16 -> 0 | J16: =SUM(G16,K16) -> 0 | K16: =E16*I16 -> 0 | L16: =ROUNDDOWN(IF(OR(B16="ACAO",B16="DIR",B16="ETF"),J16*Configurações!$B$16,IF(B16="OPCAO",J16*Configurações!$B$30)),2) -> 0 | M16: =ROUNDDOWN(IF(OR(B16="ACAO",B16="DIR",B16="ETF"),J16*Configurações!$C$16,IF(B16="OPCAO",J16*Configurações!$C$30)),2) -> 0 | N16: =ROUNDDOWN(IF(OR(B16="ACAO",B16="DIR",B16="ETF"),J16*Configurações!$D$16,IF(B16="OPCAO",J16*Configurações!$D$30)),2) -> 0 | R16: =-G16+K16-N16-O16-P16-V16-Q16-M16-L16 -> 0 | T16: =IF(D16="","-",R16/G16) -> - | U16: =DAYS360(C16,H16) -> 0 | V16: =(O16+P16)*$V$6 -> 0
B17: ACAO | G17: =E17*F17 -> 0 | H17: =C17 -> 0 | J17: =SUM(G17,K17) -> 0 | K17: =E17*I17 -> 0 | L17: =ROUNDDOWN(IF(OR(B17="ACAO",B17="DIR",B17="ETF"),J17*Configurações!$B$16,IF(B17="OPCAO",J17*Configurações!$B$30)),2) -> 0 | M17: =ROUNDDOWN(IF(OR(B17="ACAO",B17="DIR",B17="ETF"),J17*Configurações!$C$16,IF(B17="OPCAO",J17*Configurações!$C$30)),2) -> 0 | N17: =ROUNDDOWN(IF(OR(B17="ACAO",B17="DIR",B17="ETF"),J17*Configurações!$D$16,IF(B17="OPCAO",J17*Configurações!$D$30)),2) -> 0 | R17: =-G17+K17-N17-O17-P17-V17-Q17-M17-L17 -> 0 | T17: =IF(D17="","-",R17/G17) -> - | U17: =DAYS360(C17,H17) -> 0 | V17: =(O17+P17)*$V$6 -> 0
B18: ACAO | G18: =E18*F18 -> 0 | H18: =C18 -> 0 | J18: =SUM(G18,K18) -> 0 | K18: =E18*I18 -> 0 | L18: =ROUNDDOWN(IF(OR(B18="ACAO",B18="DIR",B18="ETF"),J18*Configurações!$B$16,IF(B18="OPCAO",J18*Configurações!$B$30)),2) -> 0 | M18: =ROUNDDOWN(IF(OR(B18="ACAO",B18="DIR",B18="ETF"),J18*Configurações!$C$16,IF(B18="OPCAO",J18*Configurações!$C$30)),2) -> 0 | N18: =ROUNDDOWN(IF(OR(B18="ACAO",B18="DIR",B18="ETF"),J18*Configurações!$D$16,IF(B18="OPCAO",J18*Configurações!$D$30)),2) -> 0 | R18: =-G18+K18-N18-O18-P18-V18-Q18-M18-L18 -> 0 | T18: =IF(D18="","-",R18/G18) -> - | U18: =DAYS360(C18,H18) -> 0 | V18: =(O18+P18)*$V$6 -> 0
B19: ACAO | G19: =E19*F19 -> 0 | H19: =C19 -> 0 | J19: =SUM(G19,K19) -> 0 | K19: =E19*I19 -> 0 | L19: =ROUNDDOWN(IF(OR(B19="ACAO",B19="DIR",B19="ETF"),J19*Configurações!$B$16,IF(B19="OPCAO",J19*Configurações!$B$30)),2) -> 0 | M19: =ROUNDDOWN(IF(OR(B19="ACAO",B19="DIR",B19="ETF"),J19*Configurações!$C$16,IF(B19="OPCAO",J19*Configurações!$C$30)),2) -> 0 | N19: =ROUNDDOWN(IF(OR(B19="ACAO",B19="DIR",B19="ETF"),J19*Configurações!$D$16,IF(B19="OPCAO",J19*Configurações!$D$30)),2) -> 0 | R19: =-G19+K19-N19-O19-P19-V19-Q19-M19-L19 -> 0 | T19: =IF(D19="","-",R19/G19) -> - | U19: =DAYS360(C19,H19) -> 0 | V19: =(O19+P19)*$V$6 -> 0
B20: ACAO | G20: =E20*F20 -> 0 | H20: =C20 -> 0 | J20: =SUM(G20,K20) -> 0 | K20: =E20*I20 -> 0 | L20: =ROUNDDOWN(IF(OR(B20="ACAO",B20="DIR",B20="ETF"),J20*Configurações!$B$16,IF(B20="OPCAO",J20*Configurações!$B$30)),2) -> 0 | M20: =ROUNDDOWN(IF(OR(B20="ACAO",B20="DIR",B20="ETF"),J20*Configurações!$C$16,IF(B20="OPCAO",J20*Configurações!$C$30)),2) -> 0 | N20: =ROUNDDOWN(IF(OR(B20="ACAO",B20="DIR",B20="ETF"),J20*Configurações!$D$16,IF(B20="OPCAO",J20*Configurações!$D$30)),2) -> 0 | R20: =-G20+K20-N20-O20-P20-V20-Q20-M20-L20 -> 0 | T20: =IF(D20="","-",R20/G20) -> - | U20: =DAYS360(C20,H20) -> 0 | V20: =(O20+P20)*$V$6 -> 0
B21: ACAO | G21: =E21*F21 -> 0 | H21: =C21 -> 0 | J21: =SUM(G21,K21) -> 0 | K21: =E21*I21 -> 0 | L21: =ROUNDDOWN(IF(OR(B21="ACAO",B21="DIR",B21="ETF"),J21*Configurações!$B$16,IF(B21="OPCAO",J21*Configurações!$B$30)),2) -> 0 | M21: =ROUNDDOWN(IF(OR(B21="ACAO",B21="DIR",B21="ETF"),J21*Configurações!$C$16,IF(B21="OPCAO",J21*Configurações!$C$30)),2) -> 0 | N21: =ROUNDDOWN(IF(OR(B21="ACAO",B21="DIR",B21="ETF"),J21*Configurações!$D$16,IF(B21="OPCAO",J21*Configurações!$D$30)),2) -> 0 | R21: =-G21+K21-N21-O21-P21-V21-Q21-M21-L21 -> 0 | T21: =IF(D21="","-",R21/G21) -> - | U21: =DAYS360(C21,H21) -> 0 | V21: =(O21+P21)*$V$6 -> 0
B22: ACAO | G22: =E22*F22 -> 0 | H22: =C22 -> 0 | J22: =SUM(G22,K22) -> 0 | K22: =E22*I22 -> 0 | L22: =ROUNDDOWN(IF(OR(B22="ACAO",B22="DIR",B22="ETF"),J22*Configurações!$B$16,IF(B22="OPCAO",J22*Configurações!$B$30)),2) -> 0 | M22: =ROUNDDOWN(IF(OR(B22="ACAO",B22="DIR",B22="ETF"),J22*Configurações!$C$16,IF(B22="OPCAO",J22*Configurações!$C$30)),2) -> 0 | N22: =ROUNDDOWN(IF(OR(B22="ACAO",B22="DIR",B22="ETF"),J22*Configurações!$D$16,IF(B22="OPCAO",J22*Configurações!$D$30)),2) -> 0 | R22: =-G22+K22-N22-O22-P22-V22-Q22-M22-L22 -> 0 | T22: =IF(D22="","-",R22/G22) -> - | U22: =DAYS360(C22,H22) -> 0 | V22: =(O22+P22)*$V$6 -> 0
... B48: ACAO | G48: =E48*F48 -> 0 | H48: =C48 -> 0 | J48: =SUM(G48,K48) -> 0 | K48: =E48*I48 -> 0 | L48: =ROUNDDOWN(IF(OR(B48="ACAO",B48="DIR",B48="ETF"),J48*Configurações!$B$16,IF(B48="OPCAO",J48*Configurações!$B$30)),2) -> 0 | M48: =ROUNDDOWN(IF(OR(B48="ACAO",B48="DIR",B48="ETF"),J48*Configurações!$C$16,IF(B48="OPCAO",J48*Configurações!$C$30)),2) -> 0 | N48: =ROUNDDOWN(IF(OR(B48="ACAO",B48="DIR",B48="ETF"),J48*Configurações!$D$16,IF(B48="OPCAO",J48*Configurações!$D$30)),2) -> 0 | R48: =-G48+K48-N48-O48-P48-V48-Q48-M48-L48 -> 0 | T48: =IF(D48="","-",R48/G48) -> - | U48: =DAYS360(C48,H48) -> 0 | V48: =(O48+P48)*$V$6 -> 0
K49: =SUM(K8:K48) -> 0 | S49: =SUM(S8:S48) -> 0
E52: OPERAÇÕES DAY TRADE
E54: Ações | I54: ETFs | M54: Direitos de Subscrição | Q54: Opções
C57: Resultado | E57: =SUMIF(B8:B48,"ACAO",R8:R48) -> 0 | I57: =SUMIF(B8:B48,"ETF",R8:R48) -> 0 | M57: =SUMIF(B8:B48,"DIR",R8:R48) -> 0 | Q57: =SUMIF(B8:B48,"OPCAO",R8:R48) -> 0
C60: Volume Vendas | E60: =SUMIF(B8:B48,"ACAO",K8:K48) -> 0
C63: Emolumentos/Taxas | E63: =SUMIF(B8:B48,"ACAO",L8:L48)+SUMIF(B8:B48,"ACAO",M8:M48)+SUMIF(B8:B48,"ACAO",N8:N48) -> 0 | I63: =SUMIF(B8:B48,"ETF",L8:L48)+SUMIF(B8:B48,"ETF",M8:M48)+SUMIF(B8:B48,"ETF",N8:N48) -> 0 | M63: =SUMIF(B8:B48,"DIR",L8:L48)+SUMIF(B8:B48,"DIR",M8:M48)+SUMIF(B8:B48,"DIR",N8:N48) -> 0 | Q63: =SUMIF(B8:B48,"OPCAO",L8:L48)+SUMIF(B8:B48,"OPCAO",M8:M48)+SUMIF(B8:B48,"OPCAO",N8:N48) -> 0
C66: Corretagens | E66: =SUMIF(B8:B48,"ACAO",O8:O48)+SUMIF(B8:B48,"ACAO",P8:P48) -> 0 | I66: =SUMIF(B8:B48,"ETF",O8:O48)+SUMIF(B8:B48,"ETF",P8:P48) -> 0 | M66: =SUMIF(B8:B48,"DIR",O8:O48)+SUMIF(B8:B48,"DIR",P8:P48) -> 0 | Q66: =SUMIF(B8:B48,"OPCAO",O8:O48)+SUMIF(B8:B48,"OPCAO",P8:P48) -> 0
E70: Resultado Ações | H70: + | I70: Resultado ETFs, DIR, Opções | L70: = | M70: Resultado Geral
E73: =E57 -> 0 | I73: =I57+M57+Q57 -> 0 | M73: =E73+I73+A73 -> 0
B85: ACAO
B86: OPCAO
B87: ETF
B88: DIR

Sheet Normais Índice e Dólar
B3: CONTROLE DE IR OPERAÇÕES NORMAIS COM CONTRATOS FUTUROS DE ÍNDICE E DÓLAR
B7: Período de Apuração
B8: Mês: | C8: ='Operações Normais'!C3 -> 6 | D8: Ano: | E8: ='Operações Normais'!E3 -> 2020
B10: Como Preencher?
B12: 1) Selecionar um Tipo Contrato, WDO para Míni Dólar, DOL para Dólar Cheio, WIN para Mini Índice ou IND para Índice Cheio
B13: 2) Na coluna "Negócio foi encerrado?" Selecione SIM caso esteja encerrado, caso contrário selecione NÃO. Esta coluna servirá para a planilha considerar
B14: apenas os negócios encerrados no mês na base de cálculo de IR.
B15: 3) Negócio não encerrado deve ser copiado para a tabela do mês seguinte.
B16: 4) Lance o preço de compra e preço de venda, em pontos (índice) ou em milhares de reais (dólar).
B17: 5) Verifique exemplo de preenchimento no PDF de instruções da planilha.
D19: Dados da Compra | F19: Dados da Venda | H19: Taxas Operacionais (Verificar Nota de Corretagem) | N19: IRRF | O19: Resultado Bruto | P19: Resultado Descontadas as Taxas Operacionais | Q19: Negócio foi encerrado?
B22: Tipo Contrato | C22: Quantidade | D22: Data Compra | E22: Preço Compra | F22: Data Venda | G22: Preço Venda | H22: Corretagens | I22: ISS | J22: Taxas BM&F | K22: Taxa de Permanência | L22: Taxa Registro BM&F | M22: Outras Despesas
I24: ='Operações Normais'!X7 -> 0.1068
B25: WDO | I25: =H25*$I$24 -> 0 | O25: =IF(B25="WDO",(G25-E25)*C25*10,IF(B25="WIN",(G25-E25)*C25*0.2,IF(B25="IND",(G25-E25)*C25,IF(B25="DOL",(G25-E25)*C25*50,0)))) -> 0 | P25: =O25-H25-I25-J25-M25-K25-L25 -> 0 | Q25: SIM
I26: =H26*$I$24 -> 0 | O26: =IF(B26="WDO",(G26-E26)*C26*10,IF(B26="WIN",(G26-E26)*C26*0.2,IF(B26="IND",(G26-E26)*C26,IF(B26="DOL",(G26-E26)*C26*50,0)))) -> 0 | P26: =O26-H26-I26-J26-M26-K26-L26 -> 0 | Q26: SIM
I27: =H27*$I$24 -> 0 | O27: =IF(B27="WDO",(G27-E27)*C27*10,IF(B27="WIN",(G27-E27)*C27*0.2,IF(B27="IND",(G27-E27)*C27,IF(B27="DOL",(G27-E27)*C27*50,0)))) -> 0 | P27: =O27-H27-I27-J27-M27-K27-L27 -> 0
I28: =H28*$I$24 -> 0 | O28: =IF(B28="WDO",(G28-E28)*C28*10,IF(B28="WIN",(G28-E28)*C28*0.2,IF(B28="IND",(G28-E28)*C28,IF(B28="DOL",(G28-E28)*C28*50,0)))) -> 0 | P28: =O28-H28-I28-J28-M28-K28-L28 -> 0
I29: =H29*$I$24 -> 0 | O29: =IF(B29="WDO",(G29-E29)*C29*10,IF(B29="WIN",(G29-E29)*C29*0.2,IF(B29="IND",(G29-E29)*C29,IF(B29="DOL",(G29-E29)*C29*50,0)))) -> 0 | P29: =O29-H29-I29-J29-M29-K29-L29 -> 0
I30: =H30*$I$24 -> 0 | O30: =IF(B30="WDO",(G30-E30)*C30*10,IF(B30="WIN",(G30-E30)*C30*0.2,IF(B30="IND",(G30-E30)*C30,IF(B30="DOL",(G30-E30)*C30*50,0)))) -> 0 | P30: =O30-H30-I30-J30-M30-K30-L30 -> 0
I31: =H31*$I$24 -> 0 | O31: =IF(B31="WDO",(G31-E31)*C31*10,IF(B31="WIN",(G31-E31)*C31*0.2,IF(B31="IND",(G31-E31)*C31,IF(B31="DOL",(G31-E31)*C31*50,0)))) -> 0 | P31: =O31-H31-I31-J31-M31-K31-L31 -> 0
I32: =H32*$I$24 -> 0 | O32: =IF(B32="WDO",(G32-E32)*C32*10,IF(B32="WIN",(G32-E32)*C32*0.2,IF(B32="IND",(G32-E32)*C32,IF(B32="DOL",(G32-E32)*C32*50,0)))) -> 0 | P32: =O32-H32-I32-J32-M32-K32-L32 -> 0
I33: =H33*$I$24 -> 0 | O33: =IF(B33="WDO",(G33-E33)*C33*10,IF(B33="WIN",(G33-E33)*C33*0.2,IF(B33="IND",(G33-E33)*C33,IF(B33="DOL",(G33-E33)*C33*50,0)))) -> 0 | P33: =O33-H33-I33-J33-M33-K33-L33 -> 0
I34: =H34*$I$24 -> 0 | O34: =IF(B34="WDO",(G34-E34)*C34*10,IF(B34="WIN",(G34-E34)*C34*0.2,IF(B34="IND",(G34-E34)*C34,IF(B34="DOL",(G34-E34)*C34*50,0)))) -> 0 | P34: =O34-H34-I34-J34-M34-K34-L34 -> 0
I35: =H35*$I$24 -> 0 | O35: =IF(B35="WDO",(G35-E35)*C35*10,IF(B35="WIN",(G35-E35)*C35*0.2,IF(B35="IND",(G35-E35)*C35,IF(B35="DOL",(G35-E35)*C35*50,0)))) -> 0 | P35: =O35-H35-I35-J35-M35-K35-L35 -> 0
I36: =H36*$I$24 -> 0 | O36: =IF(B36="WDO",(G36-E36)*C36*10,IF(B36="WIN",(G36-E36)*C36*0.2,IF(B36="IND",(G36-E36)*C36,IF(B36="DOL",(G36-E36)*C36*50,0)))) -> 0 | P36: =O36-H36-I36-J36-M36-K36-L36 -> 0
I37: =H37*$I$24 -> 0 | O37: =IF(B37="WDO",(G37-E37)*C37*10,IF(B37="WIN",(G37-E37)*C37*0.2,IF(B37="IND",(G37-E37)*C37,IF(B37="DOL",(G37-E37)*C37*50,0)))) -> 0 | P37: =O37-H37-I37-J37-M37-K37-L37 -> 0
I38: =H38*$I$24 -> 0 | O38: =IF(B38="WDO",(G38-E38)*C38*10,IF(B38="WIN",(G38-E38)*C38*0.2,IF(B38="IND",(G38-E38)*C38,IF(B38="DOL",(G38-E38)*C38*50,0)))) -> 0 | P38: =O38-H38-I38-J38-M38-K38-L38 -> 0
... I51: =H51*$I$24 -> 0 | O51: =IF(B51="WDO",(G51-E51)*C51*10,IF(B51="WIN",(G51-E51)*C51*0.2,IF(B51="IND",(G51-E51)*C51,IF(B51="DOL",(G51-E51)*C51*50,0)))) -> 0 | P51: =O51-H51-I51-J51-M51-K51-L51 -> 0
B53: RESUMO
B55: Lucro / Prejuízo Mês | E55: =SUMIF(Q25:Q51,"SIM",P25:P51) -> 0
B57: Total Taxas Pagas | E57: =SUMIF(Q25:Q51,"SIM",H25:M51) -> 0
B59: Total Imposto Retido | E59: =SUM(N25:N51) -> 0 | H59: (ESTE NÃO É O IR A PAGAR. VERIFIQUE A ABA RESUMO IMPOSTO)
B62: Resultado Mercado Futuro - Dólar dos EUA | E62: =SUMIFS(P25:P51,B25:B51,"WDO",Q25:Q51,"SIM")+SUMIFS(P25:P51,B25:B51,"DOL",Q25:Q51,"SIM") -> 0
B64: Resultado Mercado Futuro - Índices | E64: =SUMIFS(P25:P51,B25:B51,"WIN",Q25:Q51,"SIM")+SUMIFS(P25:P51,B25:B51,"IND",Q25:Q51,"SIM") -> 0
E71: SIM
E72: NÃO
B75: WIN
B76: WDO
B77: IND
B78: DOL

Sheet Day Trade Índice e Dólar
B3: CONTROLE DE IR OPERAÇÕES DAY-TRADE EM CONTRATOS FUTUROS DE ÍNDICE E DÓLAR
B7: Período de Apuração
B8: Mês: | C8: ='Operações Normais'!C3 -> 6 | D8: Ano: | E8: ='Operações Normais'!E3 -> 2020
B10: Como Preencher?
B12: 1) Selecionar um Tipo Contrato, WDO para Míni Dólar, DOL para Dólar Cheio, WIN para Mini Índice ou IND para Índice Cheio
B13: 2) Lance o preço de compra e preço de venda em pontos (índice) ou em milhares de reais (dólar).
B14: 3) Verifique os exemplos no PDF de instruções da planilha
G16: Taxas Operacionais (Verificar Nota de Corretagem) | L16: IRRF Day-Trade | M16: Ajuste day trade | N16: Resultado Descontadas as Taxas Operacionais
B19: Tipo Contrato | C19: Quantidade | D19: Dia do Negócio | E19: Preço Compra | F19: Preço Venda | G19: Corretagens | H19: ISS | I19: Taxas BM&F | J19: Taxa Registro BM&F | K19: Outras despesas
H21: ='Operações Normais'!X7 -> 0.1068
B22: WIN | H22: =G22*$H$21 -> 0 | M22: =IF(B22="WDO",(F22-E22)*C22*10,IF(B22="WIN",(F22-E22)*C22*0.2,IF(B22="IND",(F22-E22)*C22,IF(B22="DOL",(F22-E22)*C22*50,0)))) -> 0 | N22: =M22-G22-H22-I22-K22-J22 -> 0
H23: =G23*$H$21 -> 0 | M23: =IF(B23="WDO",(F23-E23)*C23*10,IF(B23="WIN",(F23-E23)*C23*0.2,IF(B23="IND",(F23-E23)*C23,IF(B23="DOL",(F23-E23)*C23*50,0)))) -> 0 | N23: =M23-G23-H23-I23-K23-J23 -> 0
H24: =G24*$H$21 -> 0 | M24: =IF(B24="WDO",(F24-E24)*C24*10,IF(B24="WIN",(F24-E24)*C24*0.2,IF(B24="IND",(F24-E24)*C24,IF(B24="DOL",(F24-E24)*C24*50,0)))) -> 0 | N24: =M24-G24-H24-I24-K24-J24 -> 0
H25: =G25*$H$21 -> 0 | M25: =IF(B25="WDO",(F25-E25)*C25*10,IF(B25="WIN",(F25-E25)*C25*0.2,IF(B25="IND",(F25-E25)*C25,IF(B25="DOL",(F25-E25)*C25*50,0)))) -> 0 | N25: =M25-G25-H25-I25-K25-J25 -> 0
H26: =G26*$H$21 -> 0 | M26: =IF(B26="WDO",(F26-E26)*C26*10,IF(B26="WIN",(F26-E26)*C26*0.2,IF(B26="IND",(F26-E26)*C26,IF(B26="DOL",(F26-E26)*C26*50,0)))) -> 0 | N26: =M26-G26-H26-I26-K26-J26 -> 0
H27: =G27*$H$21 -> 0 | M27: =IF(B27="WDO",(F27-E27)*C27*10,IF(B27="WIN",(F27-E27)*C27*0.2,IF(B27="IND",(F27-E27)*C27,IF(B27="DOL",(F27-E27)*C27*50,0)))) -> 0 | N27: =M27-G27-H27-I27-K27-J27 -> 0
H28: =G28*$H$21 -> 0 | M28: =IF(B28="WDO",(F28-E28)*C28*10,IF(B28="WIN",(F28-E28)*C28*0.2,IF(B28="IND",(F28-E28)*C28,IF(B28="DOL",(F28-E28)*C28*50,0)))) -> 0 | N28: =M28-G28-H28-I28-K28-J28 -> 0
H29: =G29*$H$21 -> 0 | M29: =IF(B29="WDO",(F29-E29)*C29*10,IF(B29="WIN",(F29-E29)*C29*0.2,IF(B29="IND",(F29-E29)*C29,IF(B29="DOL",(F29-E29)*C29*50,0)))) -> 0 | N29: =M29-G29-H29-I29-K29-J29 -> 0
H30: =G30*$H$21 -> 0 | M30: =IF(B30="WDO",(F30-E30)*C30*10,IF(B30="WIN",(F30-E30)*C30*0.2,IF(B30="IND",(F30-E30)*C30,IF(B30="DOL",(F30-E30)*C30*50,0)))) -> 0 | N30: =M30-G30-H30-I30-K30-J30 -> 0
H31: =G31*$H$21 -> 0 | M31: =IF(B31="WDO",(F31-E31)*C31*10,IF(B31="WIN",(F31-E31)*C31*0.2,IF(B31="IND",(F31-E31)*C31,IF(B31="DOL",(F31-E31)*C31*50,0)))) -> 0 | N31: =M31-G31-H31-I31-K31-J31 -> 0
H32: =G32*$H$21 -> 0 | M32: =IF(B32="WDO",(F32-E32)*C32*10,IF(B32="WIN",(F32-E32)*C32*0.2,IF(B32="IND",(F32-E32)*C32,IF(B32="DOL",(F32-E32)*C32*50,0)))) -> 0 | N32: =M32-G32-H32-I32-K32-J32 -> 0
H33: =G33*$H$21 -> 0 | M33: =IF(B33="WDO",(F33-E33)*C33*10,IF(B33="WIN",(F33-E33)*C33*0.2,IF(B33="IND",(F33-E33)*C33,IF(B33="DOL",(F33-E33)*C33*50,0)))) -> 0 | N33: =M33-G33-H33-I33-K33-J33 -> 0
H34: =G34*$H$21 -> 0 | M34: =IF(B34="WDO",(F34-E34)*C34*10,IF(B34="WIN",(F34-E34)*C34*0.2,IF(B34="IND",(F34-E34)*C34,IF(B34="DOL",(F34-E34)*C34*50,0)))) -> 0 | N34: =M34-G34-H34-I34-K34-J34 -> 0
... H66: =G66*$H$21 -> 0 | M66: =IF(B66="WDO",(F66-E66)*C66*10,IF(B66="WIN",(F66-E66)*C66*0.2,IF(B66="IND",(F66-E66)*C66,IF(B66="DOL",(F66-E66)*C66*50,0)))) -> 0 | N66: =M66-G66-H66-I66-K66-J66 -> 0
B68: RESUMO
B70: Lucro / Prejuízo Mês | E70: =SUM(N22:N66) -> 0
B72: Total Taxas Pagas | E72: =SUM(G22:K66) -> 0
B74: Total Imposto Retido | E74: =SUM(L22:L66) -> 0 | G74: (ESTE NÃO É O IR A PAGAR. VERIFIQUE A ABA RESUMO IMPOSTO)
B77: Resultado Mercado Futuro - Dólar dos EUA | E77: =SUMIF(B22:B66,"WDO",N22:N66)+SUMIF(B22:B66,"DOL",N22:N66) -> 0
B79: Resultado Mercado Futuro - Índices | E79: =SUMIF(B22:B66,"WIN",N22:N66)+SUMIF(B22:B66,"IND",N22:N66) -> 0
B91: WIN
B92: WDO
B93: IND
B94: DOL

Sheet Resumo Imposto
B2: Período de Apuração | G2: Resumo do Imposto referente ao mês de apuração
B3: Mês: | C3: ='Operações Normais'!C3 -> 6 | D3: Ano: | E3: ='Operações Normais'!E3 -> 2020
F6: PREJUÍZOS ACUMULADOS NOS MESES ANTERIORES (SE HOUVER) | J6: LUCRO / PREJUÍZO NO MÊS DE APURAÇÃO | N6: SALDO DE PREJUÍZO A COMPENSAR (PARA PRÓXIMOS MESES)
B9: OPERAÇÕES NORMAIS | J9: =SUM('Operações Normais'!E57:H59,'Operações Normais'!I73:K75,'Normais Índice e Dólar'!E55) -> 0 | N9: =IF(AND(F24="SIM",(J9-F9)<0),J9-F9,IF(AND(F24="NÃO",'Operações Normais'!E57>=0,('Operações Normais'!I73+'Normais Índice e Dólar'!E55-F9)<0),'Operações Normais'!I73+'Normais Índice e Dólar'!E55-F9,IF(AND('Operações Normais'!E57<0,(J9-F9)<0),J9-F9,0))) -> 0
B12: OPERAÇÕES DAY TRADE | J12: =SUM('Operações Day Trade'!E57:H59,'Operações Day Trade'!I73:K75,'Day Trade Índice e Dólar'!E70:F71) -> 0 | N12: =IF((J12-F12)<0,J12-F12,0) -> 0
F17: IRRF ACUMULADO MESES ANTERIORES (SE HOUVER) | J17: IRRF GERADO NO MÊS DE APURAÇÃO | N17: IRRF ACUMULADO (PARA PRÓXIMOS MESES)
B20: IMPOSTO RETIDO NA FONTE | J20: =SUM('Operações Day Trade'!S49,'Operações Normais'!U49,'Day Trade Índice e Dólar'!E74:F75,'Normais Índice e Dólar'!E59:G60) -> 0 | N20: =IF((F28+F31-F20-J20)=0,F20+J20,IF(F28+F31-F20-J20<0,F20+J20-F28-F31,0)) -> 0
B24: VENDEU MAIS DE R$ 20.000,00 EM AÇÕES NO MÊS? | F24: NÃO | J24: LUCRO ISENTO (OPERAÇÕES NORMAIS COM AÇÕES) NO MÊS | N24: =IF(AND(F24="NÃO",'Operações Normais'!E57>0),'Operações Normais'!E57,0) -> 0
B28: IMPOSTO OPERAÇÕES NORMAIS | F28: =IF(AND(F24="SIM",(J9-F9)>0),(J9-F9)*0.15,IF(AND(F24="NÃO",('Operações Normais'!I73+'Normais Índice e Dólar'!E55-F9)>0,'Operações Normais'!E57>=0),(J9-'Operações Normais'!E57-F9)*0.15,IF(AND('Operações Normais'!E57<0,(J9-F9)>0),(J9-F9)*0.15,0))) -> 0 | J28: Este não é o valor final a ser pago
B31: IMPOSTO OPERAÇÕES DT | F31: =IF((J12-F12)>0,(J12-F12)*0.2,0) -> 0 | J31: Este não é o valor final a ser pago
B35: IMPOSTO A PAGAR | F35: =IF((F28+F31-F20-J20)>0,F28+F31-F20-J20+F43,IF((F28+F31-F20-J20)<=0,F43,0)) -> 0 | J35: O código da DARF para pagamento do IR de renda variável é 6015. A DARF deve ser paga até o último dia útil do mês subseqüente ao da apuração.
B38: Não é possível pagar o Darf se o valor do imposto de renda devido for inferior a R$ 10,00 (dez reais). Nesse caso, o valor deve ser somado ao imposto dos meses de apuração seguintes até que alcance o mínimo de R$ 10,00, quando, então, deve ser pago no prazo estabelecido na legislação referente ao último mês de apuração.
B41: Caso o valor de IMPOSTO A PAGAR fique menor que R$ 10, lance o valor no campo abaixo da tabela de apuração do mês seguinte
B43: IR NÃO PAGO (DARF < R$ 10) DE MESES ANTERIORES
B49: Resultados do Mês
F50: Comum | H50: Day Trade
B51: Mercado à vista - ações | F51: ='Operações Normais'!E57+'Operações Normais'!I57+'Operações Normais'!M57-N24 -> 0 | H51: ='Operações Day Trade'!E57+'Operações Day Trade'!I57+'Operações Day Trade'!M57 -> 0
B52: Lucro isento - ações | F52: =N24 -> 0
B53: Mercado opções - ações | F53: ='Operações Normais'!Q57 -> 0 | H53: ='Operações Day Trade'!Q57 -> 0
B54: Mercado futuro - dólar dos EUA | F54: ='Normais Índice e Dólar'!E62 -> 0 | H54: ='Day Trade Índice e Dólar'!E77 -> 0
B55: Mercado futuro - Índices | F55: ='Normais Índice e Dólar'!E64 -> 0 | H55: ='Day Trade Índice e Dólar'!E79 -> 0
B59: SIM
B60: NÃO

Sheet Posições Abertas
B2: POSIÇÕES ABERTAS - ACOMPANHAMENTO DE PREÇO MÉDIO
B4: Quadro das Operações COMPRADAS (abertas) | N4: ISS | P4: ATIVO | Q4: =AA6 -> 0 | R4: CALCULADORA PREÇO MÉDIO | Y4: CÁLCULO DE PREÇO MÉDIO
B5: Tipo | C5: Data Compra | D5: Código Ativo | E5: Quantidade | F5: Preço Compra | G5: Movimento Compra | H5: Taxa Negociação | I5: Taxa Liquidação | J5: Taxa Registro | K5: Corretagens de Compra | L5: Outras despesas | M5: Total investido | N5: ='Operações Normais'!X7 -> 0.1068 | P5: Quantidade | Q5: Total | R5: Quantidade atual | S5: Preço médio atual | T5: Investimento atual | U5: Custos | V5: Investimento atual com custos embutidos | W5: Preço médio atual com custos
Y6: INSIRA O CÓDIGO DO ATIVO >
B7: ACAO | G7: =E7*F7 -> 0 | H7: =ROUNDDOWN(IF(OR(B7="ACAO",B7="DIR",B7="ETF"),G7*Configurações!$B$9,IF(B7="OPCAO",G7*Configurações!$B$23,0)),2) -> 0 | I7: =ROUNDDOWN(IF(OR(B7="ACAO",B7="ETF",B7="DIR"),G7*Configurações!$C$9,IF(B7="OPCAO",G7*Configurações!$C$23,0)),2) -> 0 | J7: =ROUNDDOWN(IF(OR(B7="ACAO",B7="ETF",B7="DIR"),G7*Configurações!$D$9,IF(B7="OPCAO",G7*Configurações!$D$23,0)),2) -> 0 | M7: =G7+J7+K7+N7+L7+I7+H7 -> 0 | N7: =K7*$N$5 -> 0 | P7: =IF(D:D=$Q$4,E7,0) -> 0 | Q7: =IF(D:D=$Q$4,G7,0) -> 0 | R7: =P7 -> 0 | S7: =Q7/R7 -> #DIV/0! | T7: =IF(R7=0,0,R7*S7) -> 0 | U7: =IF(D:D=$Q$4,H7+I7+J7+K7+L7+N7,0) -> 0 | V7: =SUM(T7,U7) -> 0 | W7: =V7/R7 -> #DIV/0!
B8: ACAO | G8: =E8*F8 -> 0 | H8: =ROUNDDOWN(IF(OR(B8="ACAO",B8="DIR",B8="ETF"),G8*Configurações!$B$9,IF(B8="OPCAO",G8*Configurações!$B$23,0)),2) -> 0 | I8: =ROUNDDOWN(IF(OR(B8="ACAO",B8="ETF",B8="DIR"),G8*Configurações!$C$9,IF(B8="OPCAO",G8*Configurações!$C$23,0)),2) -> 0 | J8: =ROUNDDOWN(IF(OR(B8="ACAO",B8="ETF",B8="DIR"),G8*Configurações!$D$9,IF(B8="OPCAO",G8*Configurações!$D$23,0)),2) -> 0 | M8: =G8+J8+K8+N8+L8+I8+H8 -> 0 | N8: =K8*$N$5 -> 0 | P8: =IF(D:D=$Q$4,E8,0) -> 0 | Q8: =IF(D:D=$Q$4,G8,0) -> 0 | R8: =R7+P8 -> 0 | S8: =IF(P8<=0,S7,IF(P8>0,((T7+Q8)/R8))) -> #DIV/0! | T8: =IF(R8=0,0,R8*S8) -> 0 | U8: =IF(D:D=$Q$4,H8+I8+J8+K8+L8+N8,0) -> 0 | V8: =IF(P8>0,SUM(T8,$U$7:U8),IF(P8=0,V7,IF(P8<0,V7+(P8*W8)))) -> 0 | W8: =IF(P8<=0,W7,IF(P8>0,V8/R8)) -> #DIV/0! | Y8: Quantidade | AA8: =R81 -> 0 | AC8: CAMPO AUTOMÁTICO
B9: ACAO | G9: =E9*F9 -> 0 | H9: =ROUNDDOWN(IF(OR(B9="ACAO",B9="DIR",B9="ETF"),G9*Configurações!$B$9,IF(B9="OPCAO",G9*Configurações!$B$23,0)),2) -> 0 | I9: =ROUNDDOWN(IF(OR(B9="ACAO",B9="ETF",B9="DIR"),G9*Configurações!$C$9,IF(B9="OPCAO",G9*Configurações!$C$23,0)),2) -> 0 | J9: =ROUNDDOWN(IF(OR(B9="ACAO",B9="ETF",B9="DIR"),G9*Configurações!$D$9,IF(B9="OPCAO",G9*Configurações!$D$23,0)),2) -> 0 | M9: =G9+J9+K9+N9+L9+I9+H9 -> 0 | N9: =K9*$N$5 -> 0 | P9: =IF(D:D=$Q$4,E9,0) -> 0 | Q9: =IF(D:D=$Q$4,G9,0) -> 0 | R9: =R8+P9 -> 0 | S9: =IF(P9<=0,S8,IF(P9>0,((T8+Q9)/R9))) -> #DIV/0! | T9: =IF(R9=0,0,R9*S9) -> 0 | U9: =IF(D:D=$Q$4,H9+I9+J9+K9+L9+N9,0) -> 0 | V9: =IF(P9>0,SUM(T9,$U$7:U9),IF(P9=0,V8,IF(P9<0,V8+(P9*W9)))) -> 0 | W9: =IF(P9<=0,W8,IF(P9>0,V9/R9)) -> #DIV/0!
B10: ACAO | G10: =E10*F10 -> 0 | H10: =ROUNDDOWN(IF(OR(B10="ACAO",B10="DIR",B10="ETF"),G10*Configurações!$B$9,IF(B10="OPCAO",G10*Configurações!$B$23,0)),2) -> 0 | I10: =ROUNDDOWN(IF(OR(B10="ACAO",B10="ETF",B10="DIR"),G10*Configurações!$C$9,IF(B10="OPCAO",G10*Configurações!$C$23,0)),2) -> 0 | J10: =ROUNDDOWN(IF(OR(B10="ACAO",B10="ETF",B10="DIR"),G10*Configurações!$D$9,IF(B10="OPCAO",G10*Configurações!$D$23,0)),2) -> 0 | M10: =G10+J10+K10+N10+L10+I10+H10 -> 0 | N10: =K10*$N$5 -> 0 | P10: =IF(D:D=$Q$4,E10,0) -> 0 | Q10: =IF(D:D=$Q$4,G10,0) -> 0 | R10: =R9+P10 -> 0 | S10: =IF(P10<=0,S9,IF(P10>0,(T9+Q10)/R10)) -> #DIV/0! | T10: =IF(R10=0,0,R10*S10) -> 0 | U10: =IF(D:D=$Q$4,H10+I10+J10+K10+L10+N10,0) -> 0 | V10: =IF(P10>0,SUM(T10,$U$7:U10),IF(P10=0,V9,IF(P10<0,V9+(P10*W10)))) -> 0 | W10: =IF(P10<=0,W9,IF(P10>0,V10/R10)) -> #DIV/0!
B11: ACAO | G11: =E11*F11 -> 0 | H11: =ROUNDDOWN(IF(OR(B11="ACAO",B11="DIR",B11="ETF"),G11*Configurações!$B$9,IF(B11="OPCAO",G11*Configurações!$B$23,0)),2) -> 0 | I11: =ROUNDDOWN(IF(OR(B11="ACAO",B11="ETF",B11="DIR"),G11*Configurações!$C$9,IF(B11="OPCAO",G11*Configurações!$C$23,0)),2) -> 0 | J11: =ROUNDDOWN(IF(OR(B11="ACAO",B11="ETF",B11="DIR"),G11*Configurações!$D$9,IF(B11="OPCAO",G11*Configurações!$D$23,0)),2) -> 0 | M11: =G11+J11+K11+N11+L11+I11+H11 -> 0 | N11: =K11*$N$5 -> 0 | P11: =IF(D:D=$Q$4,E11,0) -> 0 | Q11: =IF(D:D=$Q$4,G11,0) -> 0 | R11: =R10+P11 -> 0 | S11: =IF(P11<=0,S10,IF(P11>0,((T10+Q11)/R11))) -> #DIV/0! | T11: =IF(R11=0,0,R11*S11) -> 0 | U11: =IF(D:D=$Q$4,H11+I11+J11+K11+L11+N11,0) -> 0 | V11: =IF(P11>0,SUM(T11,$U$7:U11),IF(P11=0,V10,IF(P11<0,V10+(P11*W11)))) -> 0 | W11: =IF(P11<=0,W10,IF(P11>0,V11/R11)) -> #DIV/0! | Y11: Preço médio sem custos (taxas) | AA11: =IF(AA6="","-",S81) -> - | AC11: CAMPO AUTOMÁTICO
B12: ACAO | G12: =E12*F12 -> 0 | H12: =ROUNDDOWN(IF(OR(B12="ACAO",B12="DIR",B12="ETF"),G12*Configurações!$B$9,IF(B12="OPCAO",G12*Configurações!$B$23,0)),2) -> 0 | I12: =ROUNDDOWN(IF(OR(B12="ACAO",B12="ETF",B12="DIR"),G12*Configurações!$C$9,IF(B12="OPCAO",G12*Configurações!$C$23,0)),2) -> 0 | J12: =ROUNDDOWN(IF(OR(B12="ACAO",B12="ETF",B12="DIR"),G12*Configurações!$D$9,IF(B12="OPCAO",G12*Configurações!$D$23,0)),2) -> 0 | M12: =G12+J12+K12+N12+L12+I12+H12 -> 0 | N12: =K12*$N$5 -> 0 | P12: =IF(D:D=$Q$4,E12,0) -> 0 | Q12: =IF(D:D=$Q$4,G12,0) -> 0 | R12: =R11+P12 -> 0 | S12: =IF(P12<=0,S11,IF(P12>0,((T11+Q12)/R12))) -> #DIV/0! | T12: =IF(R12=0,0,R12*S12) -> 0 | U12: =IF(D:D=$Q$4,H12+I12+J12+K12+L12+N12,0) -> 0 | V12: =IF(P12>0,SUM(T12,$U$7:U12),IF(P12=0,V11,IF(P12<0,V11+(P12*W12)))) -> 0 | W12: =IF(P12<=0,W11,IF(P12>0,V12/R12)) -> #DIV/0!
B13: ACAO | G13: =E13*F13 -> 0 | H13: =ROUNDDOWN(IF(OR(B13="ACAO",B13="DIR",B13="ETF"),G13*Configurações!$B$9,IF(B13="OPCAO",G13*Configurações!$B$23,0)),2) -> 0 | I13: =ROUNDDOWN(IF(OR(B13="ACAO",B13="ETF",B13="DIR"),G13*Configurações!$C$9,IF(B13="OPCAO",G13*Configurações!$C$23,0)),2) -> 0 | J13: =ROUNDDOWN(IF(OR(B13="ACAO",B13="ETF",B13="DIR"),G13*Configurações!$D$9,IF(B13="OPCAO",G13*Configurações!$D$23,0)),2) -> 0 | M13: =G13+J13+K13+N13+L13+I13+H13 -> 0 | N13: =K13*$N$5 -> 0 | P13: =IF(D:D=$Q$4,E13,0) -> 0 | Q13: =IF(D:D=$Q$4,G13,0) -> 0 | R13: =R12+P13 -> 0 | S13: =IF(P13<=0,S12,IF(P13>0,((T12+Q13)/R13))) -> #DIV/0! | T13: =IF(R13=0,0,R13*S13) -> 0 | U13: =IF(D:D=$Q$4,H13+I13+J13+K13+L13+N13,0) -> 0 | V13: =IF(P13>0,SUM(T13,$U$7:U13),IF(P13=0,V12,IF(P13<0,V12+(P13*W13)))) -> 0 | W13: =IF(P13<=0,W12,IF(P13>0,V13/R13)) -> #DIV/0!
B14: ACAO | G14: =E14*F14 -> 0 | H14: =ROUNDDOWN(IF(OR(B14="ACAO",B14="DIR",B14="ETF"),G14*Configurações!$B$9,IF(B14="OPCAO",G14*Configurações!$B$23,0)),2) -> 0 | I14: =ROUNDDOWN(IF(OR(B14="ACAO",B14="ETF",B14="DIR"),G14*Configurações!$C$9,IF(B14="OPCAO",G14*Configurações!$C$23,0)),2) -> 0 | J14: =ROUNDDOWN(IF(OR(B14="ACAO",B14="ETF",B14="DIR"),G14*Configurações!$D$9,IF(B14="OPCAO",G14*Configurações!$D$23,0)),2) -> 0 | M14: =G14+J14+K14+N14+L14+I14+H14 -> 0 | N14: =K14*$N$5 -> 0 | P14: =IF(D:D=$Q$4,E14,0) -> 0 | Q14: =IF(D:D=$Q$4,G14,0) -> 0 | R14: =R13+P14 -> 0 | S14: =IF(P14<=0,S13,IF(P14>0,((T13+Q14)/R14))) -> #DIV/0! | T14: =IF(R14=0,0,R14*S14) -> 0 | U14: =IF(D:D=$Q$4,H14+I14+J14+K14+L14+N14,0) -> 0 | V14: =IF(P14>0,SUM(T14,$U$7:U14),IF(P14=0,V13,IF(P14<0,V13+(P14*W14)))) -> 0 | W14: =IF(P14<=0,W13,IF(P14>0,V14/R14)) -> #DIV/0! | Y14: Preço médio com custos (taxas) | AA14: =IF(AA6="","-",W81) -> - | AC14: CAMPO AUTOMÁTICO
B15: ACAO | G15: =E15*F15 -> 0 | H15: =ROUNDDOWN(IF(OR(B15="ACAO",B15="DIR",B15="ETF"),G15*Configurações!$B$9,IF(B15="OPCAO",G15*Configurações!$B$23,0)),2) -> 0 | I15: =ROUNDDOWN(IF(OR(B15="ACAO",B15="ETF",B15="DIR"),G15*Configurações!$C$9,IF(B15="OPCAO",G15*Configurações!$C$23,0)),2) -> 0 | J15: =ROUNDDOWN(IF(OR(B15="ACAO",B15="ETF",B15="DIR"),G15*Configurações!$D$9,IF(B15="OPCAO",G15*Configurações!$D$23,0)),2) -> 0 | M15: =G15+J15+K15+N15+L15+I15+H15 -> 0 | N15: =K15*$N$5 -> 0 | P15: =IF(D:D=$Q$4,E15,0) -> 0 | Q15: =IF(D:D=$Q$4,G15,0) -> 0 | R15: =R14+P15 -> 0 | S15: =IF(P15<=0,S14,IF(P15>0,((T14+Q15)/R15))) -> #DIV/0! | T15: =IF(R15=0,0,R15*S15) -> 0 | U15: =IF(D:D=$Q$4,H15+I15+J15+K15+L15+N15,0) -> 0 | V15: =IF(P15>0,SUM(T15,$U$7:U15),IF(P15=0,V14,IF(P15<0,V14+(P15*W15)))) -> 0 | W15: =IF(P15<=0,W14,IF(P15>0,V15/R15)) -> #DIV/0!
B16: ACAO | G16: =E16*F16 -> 0 | H16: =ROUNDDOWN(IF(OR(B16="ACAO",B16="DIR",B16="ETF"),G16*Configurações!$B$9,IF(B16="OPCAO",G16*Configurações!$B$23,0)),2) -> 0 | I16: =ROUNDDOWN(IF(OR(B16="ACAO",B16="ETF",B16="DIR"),G16*Configurações!$C$9,IF(B16="OPCAO",G16*Configurações!$C$23,0)),2) -> 0 | J16: =ROUNDDOWN(IF(OR(B16="ACAO",B16="ETF",B16="DIR"),G16*Configurações!$D$9,IF(B16="OPCAO",G16*Configurações!$D$23,0)),2) -> 0 | M16: =G16+J16+K16+N16+L16+I16+H16 -> 0 | N16: =K16*$N$5 -> 0 | P16: =IF(D:D=$Q$4,E16,0) -> 0 | Q16: =IF(D:D=$Q$4,G16,0) -> 0 | R16: =R15+P16 -> 0 | S16: =IF(P16<=0,S15,IF(P16>0,((T15+Q16)/R16))) -> #DIV/0! | T16: =IF(R16=0,0,R16*S16) -> 0 | U16: =IF(D:D=$Q$4,H16+I16+J16+K16+L16+N16,0) -> 0 | V16: =IF(P16>0,SUM(T16,$U$7:U16),IF(P16=0,V15,IF(P16<0,V15+(P16*W16)))) -> 0 | W16: =IF(P16<=0,W15,IF(P16>0,V16/R16)) -> #DIV/0!
B17: ACAO | G17: =E17*F17 -> 0 | H17: =ROUNDDOWN(IF(OR(B17="ACAO",B17="DIR",B17="ETF"),G17*Configurações!$B$9,IF(B17="OPCAO",G17*Configurações!$B$23,0)),2) -> 0 | I17: =ROUNDDOWN(IF(OR(B17="ACAO",B17="ETF",B17="DIR"),G17*Configurações!$C$9,IF(B17="OPCAO",G17*Configurações!$C$23,0)),2) -> 0 | J17: =ROUNDDOWN(IF(OR(B17="ACAO",B17="ETF",B17="DIR"),G17*Configurações!$D$9,IF(B17="OPCAO",G17*Configurações!$D$23,0)),2) -> 0 | M17: =G17+J17+K17+N17+L17+I17+H17 -> 0 | N17: =K17*$N$5 -> 0 | P17: =IF(D:D=$Q$4,E17,0) -> 0 | Q17: =IF(D:D=$Q$4,G17,0) -> 0 | R17: =R16+P17 -> 0 | S17: =IF(P17<=0,S16,IF(P17>0,((T16+Q17)/R17))) -> #DIV/0! | T17: =IF(R17=0,0,R17*S17) -> 0 | U17: =IF(D:D=$Q$4,H17+I17+J17+K17+L17+N17,0) -> 0 | V17: =IF(P17>0,SUM(T17,$U$7:U17),IF(P17=0,V16,IF(P17<0,V16+(P17*W17)))) -> 0 | W17: =IF(P17<=0,W16,IF(P17>0,V17/R17)) -> #DIV/0!
B18: ACAO | G18: =E18*F18 -> 0 | H18: =ROUNDDOWN(IF(OR(B18="ACAO",B18="DIR",B18="ETF"),G18*Configurações!$B$9,IF(B18="OPCAO",G18*Configurações!$B$23,0)),2) -> 0 | I18: =ROUNDDOWN(IF(OR(B18="ACAO",B18="ETF",B18="DIR"),G18*Configurações!$C$9,IF(B18="OPCAO",G18*Configurações!$C$23,0)),2) -> 0 | J18: =ROUNDDOWN(IF(OR(B18="ACAO",B18="ETF",B18="DIR"),G18*Configurações!$D$9,IF(B18="OPCAO",G18*Configurações!$D$23,0)),2) -> 0 | M18: =G18+J18+K18+N18+L18+I18+H18 -> 0 | N18: =K18*$N$5 -> 0 | P18: =IF(D:D=$Q$4,E18,0) -> 0 | Q18: =IF(D:D=$Q$4,G18,0) -> 0 | R18: =R17+P18 -> 0 | S18: =IF(P18<=0,S17,IF(P18>0,((T17+Q18)/R18))) -> #DIV/0! | T18: =IF(R18=0,0,R18*S18) -> 0 | U18: =IF(D:D=$Q$4,H18+I18+J18+K18+L18+N18,0) -> 0 | V18: =IF(P18>0,SUM(T18,$U$7:U18),IF(P18=0,V17,IF(P18<0,V17+(P18*W18)))) -> 0 | W18: =IF(P18<=0,W17,IF(P18>0,V18/R18)) -> #DIV/0! | Y18: SIMULAÇÃO DE RESULTADO E STOP
B19: ACAO | G19: =E19*F19 -> 0 | H19: =ROUNDDOWN(IF(OR(B19="ACAO",B19="DIR",B19="ETF"),G19*Configurações!$B$9,IF(B19="OPCAO",G19*Configurações!$B$23,0)),2) -> 0 | I19: =ROUNDDOWN(IF(OR(B19="ACAO",B19="ETF",B19="DIR"),G19*Configurações!$C$9,IF(B19="OPCAO",G19*Configurações!$C$23,0)),2) -> 0 | J19: =ROUNDDOWN(IF(OR(B19="ACAO",B19="ETF",B19="DIR"),G19*Configurações!$D$9,IF(B19="OPCAO",G19*Configurações!$D$23,0)),2) -> 0 | M19: =G19+J19+K19+N19+L19+I19+H19 -> 0 | N19: =K19*$N$5 -> 0 | P19: =IF(D:D=$Q$4,E19,0) -> 0 | Q19: =IF(D:D=$Q$4,G19,0) -> 0 | R19: =R18+P19 -> 0 | S19: =IF(P19<=0,S18,IF(P19>0,((T18+Q19)/R19))) -> #DIV/0! | T19: =IF(R19=0,0,R19*S19) -> 0 | U19: =IF(D:D=$Q$4,H19+I19+J19+K19+L19+N19,0) -> 0 | V19: =IF(P19>0,SUM(T19,$U$7:U19),IF(P19=0,V18,IF(P19<0,V18+(P19*W19)))) -> 0 | W19: =IF(P19<=0,W18,IF(P19>0,V19/R19)) -> #DIV/0!
B20: ACAO | G20: =E20*F20 -> 0 | H20: =ROUNDDOWN(IF(OR(B20="ACAO",B20="DIR",B20="ETF"),G20*Configurações!$B$9,IF(B20="OPCAO",G20*Configurações!$B$23,0)),2) -> 0 | I20: =ROUNDDOWN(IF(OR(B20="ACAO",B20="ETF",B20="DIR"),G20*Configurações!$C$9,IF(B20="OPCAO",G20*Configurações!$C$23,0)),2) -> 0 | J20: =ROUNDDOWN(IF(OR(B20="ACAO",B20="ETF",B20="DIR"),G20*Configurações!$D$9,IF(B20="OPCAO",G20*Configurações!$D$23,0)),2) -> 0 | M20: =G20+J20+K20+N20+L20+I20+H20 -> 0 | N20: =K20*$N$5 -> 0 | P20: =IF(D:D=$Q$4,E20,0) -> 0 | Q20: =IF(D:D=$Q$4,G20,0) -> 0 | R20: =R19+P20 -> 0 | S20: =IF(P20<=0,S19,IF(P20>0,((T19+Q20)/R20))) -> #DIV/0! | T20: =IF(R20=0,0,R20*S20) -> 0 | U20: =IF(D:D=$Q$4,H20+I20+J20+K20+L20+N20,0) -> 0 | V20: =IF(P20>0,SUM(T20,$U$7:U20),IF(P20=0,V19,IF(P20<0,V19+(P20*W20)))) -> 0 | W20: =IF(P20<=0,W19,IF(P20>0,V20/R20)) -> #DIV/0!
B21: ACAO | G21: =E21*F21 -> 0 | H21: =ROUNDDOWN(IF(OR(B21="ACAO",B21="DIR",B21="ETF"),G21*Configurações!$B$9,IF(B21="OPCAO",G21*Configurações!$B$23,0)),2) -> 0 | I21: =ROUNDDOWN(IF(OR(B21="ACAO",B21="ETF",B21="DIR"),G21*Configurações!$C$9,IF(B21="OPCAO",G21*Configurações!$C$23,0)),2) -> 0 | J21: =ROUNDDOWN(IF(OR(B21="ACAO",B21="ETF",B21="DIR"),G21*Configurações!$D$9,IF(B21="OPCAO",G21*Configurações!$D$23,0)),2) -> 0 | M21: =G21+J21+K21+N21+L21+I21+H21 -> 0 | N21: =K21*$N$5 -> 0 | P21: =IF(D:D=$Q$4,E21,0) -> 0 | Q21: =IF(D:D=$Q$4,G21,0) -> 0 | R21: =R20+P21 -> 0 | S21: =IF(P21<=0,S20,IF(P21>0,((T20+Q21)/R21))) -> #DIV/0! | T21: =IF(R21=0,0,R21*S21) -> 0 | U21: =IF(D:D=$Q$4,H21+I21+J21+K21+L21+N21,0) -> 0 | V21: =IF(P21>0,SUM(T21,$U$7:U21),IF(P21=0,V20,IF(P21<0,V20+(P21*W21)))) -> 0 | W21: =IF(P21<=0,W20,IF(P21>0,V21/R21)) -> #DIV/0! | Y21: Cotação atual do ativo >
B22: ACAO | G22: =E22*F22 -> 0 | H22: =ROUNDDOWN(IF(OR(B22="ACAO",B22="DIR",B22="ETF"),G22*Configurações!$B$9,IF(B22="OPCAO",G22*Configurações!$B$23,0)),2) -> 0 | I22: =ROUNDDOWN(IF(OR(B22="ACAO",B22="ETF",B22="DIR"),G22*Configurações!$C$9,IF(B22="OPCAO",G22*Configurações!$C$23,0)),2) -> 0 | J22: =ROUNDDOWN(IF(OR(B22="ACAO",B22="ETF",B22="DIR"),G22*Configurações!$D$9,IF(B22="OPCAO",G22*Configurações!$D$23,0)),2) -> 0 | M22: =G22+J22+K22+N22+L22+I22+H22 -> 0 | N22: =K22*$N$5 -> 0 | P22: =IF(D:D=$Q$4,E22,0) -> 0 | Q22: =IF(D:D=$Q$4,G22,0) -> 0 | R22: =R21+P22 -> 0 | S22: =IF(P22<=0,S21,IF(P22>0,((T21+Q22)/R22))) -> #DIV/0! | T22: =IF(R22=0,0,R22*S22) -> 0 | U22: =IF(D:D=$Q$4,H22+I22+J22+K22+L22+N22,0) -> 0 | V22: =IF(P22>0,SUM(T22,$U$7:U22),IF(P22=0,V21,IF(P22<0,V21+(P22*W22)))) -> 0 | W22: =IF(P22<=0,W21,IF(P22>0,V22/R22)) -> #DIV/0!
B23: ACAO | G23: =E23*F23 -> 0 | H23: =ROUNDDOWN(IF(OR(B23="ACAO",B23="DIR",B23="ETF"),G23*Configurações!$B$9,IF(B23="OPCAO",G23*Configurações!$B$23,0)),2) -> 0 | I23: =ROUNDDOWN(IF(OR(B23="ACAO",B23="ETF",B23="DIR"),G23*Configurações!$C$9,IF(B23="OPCAO",G23*Configurações!$C$23,0)),2) -> 0 | J23: =ROUNDDOWN(IF(OR(B23="ACAO",B23="ETF",B23="DIR"),G23*Configurações!$D$9,IF(B23="OPCAO",G23*Configurações!$D$23,0)),2) -> 0 | M23: =G23+J23+K23+N23+L23+I23+H23 -> 0 | N23: =K23*$N$5 -> 0 | P23: =IF(D:D=$Q$4,E23,0) -> 0 | Q23: =IF(D:D=$Q$4,G23,0) -> 0 | R23: =R22+P23 -> 0 | S23: =IF(P23<=0,S22,IF(P23>0,((T22+Q23)/R23))) -> #DIV/0! | T23: =IF(R23=0,0,R23*S23) -> 0 | U23: =IF(D:D=$Q$4,H23+I23+J23+K23+L23+N23,0) -> 0 | V23: =IF(P23>0,SUM(T23,$U$7:U23),IF(P23=0,V22,IF(P23<0,V22+(P23*W23)))) -> 0 | W23: =IF(P23<=0,W22,IF(P23>0,V23/R23)) -> #DIV/0!
B24: ACAO | G24: =E24*F24 -> 0 | H24: =ROUNDDOWN(IF(OR(B24="ACAO",B24="DIR",B24="ETF"),G24*Configurações!$B$9,IF(B24="OPCAO",G24*Configurações!$B$23,0)),2) -> 0 | I24: =ROUNDDOWN(IF(OR(B24="ACAO",B24="ETF",B24="DIR"),G24*Configurações!$C$9,IF(B24="OPCAO",G24*Configurações!$C$23,0)),2) -> 0 | J24: =ROUNDDOWN(IF(OR(B24="ACAO",B24="ETF",B24="DIR"),G24*Configurações!$D$9,IF(B24="OPCAO",G24*Configurações!$D$23,0)),2) -> 0 | M24: =G24+J24+K24+N24+L24+I24+H24 -> 0 | N24: =K24*$N$5 -> 0 | P24: =IF(D:D=$Q$4,E24,0) -> 0 | Q24: =IF(D:D=$Q$4,G24,0) -> 0 | R24: =R23+P24 -> 0 | S24: =IF(P24<=0,S23,IF(P24>0,((T23+Q24)/R24))) -> #DIV/0! | T24: =IF(R24=0,0,R24*S24) -> 0 | U24: =IF(D:D=$Q$4,H24+I24+J24+K24+L24+N24,0) -> 0 | V24: =IF(P24>0,SUM(T24,$U$7:U24),IF(P24=0,V23,IF(P24<0,V23+(P24*W24)))) -> 0 | W24: =IF(P24<=0,W23,IF(P24>0,V24/R24)) -> #DIV/0! | Y24: Resultado atual da operação ( R$ ) | AA24: =IF(AA6="","-",(AA21-AA14)*AA8) -> - | AC24: CAMPO AUTOMÁTICO
B25: ACAO | G25: =E25*F25 -> 0 | H25: =ROUNDDOWN(IF(OR(B25="ACAO",B25="DIR",B25="ETF"),G25*Configurações!$B$9,IF(B25="OPCAO",G25*Configurações!$B$23,0)),2) -> 0 | I25: =ROUNDDOWN(IF(OR(B25="ACAO",B25="ETF",B25="DIR"),G25*Configurações!$C$9,IF(B25="OPCAO",G25*Configurações!$C$23,0)),2) -> 0 | J25: =ROUNDDOWN(IF(OR(B25="ACAO",B25="ETF",B25="DIR"),G25*Configurações!$D$9,IF(B25="OPCAO",G25*Configurações!$D$23,0)),2) -> 0 | M25: =G25+J25+K25+N25+L25+I25+H25 -> 0 | N25: =K25*$N$5 -> 0 | P25: =IF(D:D=$Q$4,E25,0) -> 0 | Q25: =IF(D:D=$Q$4,G25,0) -> 0 | R25: =R24+P25 -> 0 | S25: =IF(P25<=0,S24,IF(P25>0,((T24+Q25)/R25))) -> #DIV/0! | T25: =IF(R25=0,0,R25*S25) -> 0 | U25: =IF(D:D=$Q$4,H25+I25+J25+K25+L25+N25,0) -> 0 | V25: =IF(P25>0,SUM(T25,$U$7:U25),IF(P25=0,V24,IF(P25<0,V24+(P25*W25)))) -> 0 | W25: =IF(P25<=0,W24,IF(P25>0,V25/R25)) -> #DIV/0!
B26: ACAO | G26: =E26*F26 -> 0 | H26: =ROUNDDOWN(IF(OR(B26="ACAO",B26="DIR",B26="ETF"),G26*Configurações!$B$9,IF(B26="OPCAO",G26*Configurações!$B$23,0)),2) -> 0 | I26: =ROUNDDOWN(IF(OR(B26="ACAO",B26="ETF",B26="DIR"),G26*Configurações!$C$9,IF(B26="OPCAO",G26*Configurações!$C$23,0)),2) -> 0 | J26: =ROUNDDOWN(IF(OR(B26="ACAO",B26="ETF",B26="DIR"),G26*Configurações!$D$9,IF(B26="OPCAO",G26*Configurações!$D$23,0)),2) -> 0 | M26: =G26+J26+K26+N26+L26+I26+H26 -> 0 | N26: =K26*$N$5 -> 0 | P26: =IF(D:D=$Q$4,E26,0) -> 0 | Q26: =IF(D:D=$Q$4,G26,0) -> 0 | R26: =R25+P26 -> 0 | S26: =IF(P26<=0,S25,IF(P26>0,((T25+Q26)/R26))) -> #DIV/0! | T26: =IF(R26=0,0,R26*S26) -> 0 | U26: =IF(D:D=$Q$4,H26+I26+J26+K26+L26+N26,0) -> 0 | V26: =IF(P26>0,SUM(T26,$U$7:U26),IF(P26=0,V25,IF(P26<0,V25+(P26*W26)))) -> 0 | W26: =IF(P26<=0,W25,IF(P26>0,V26/R26)) -> #DIV/0!
B27: ACAO | G27: =E27*F27 -> 0 | H27: =ROUNDDOWN(IF(OR(B27="ACAO",B27="DIR",B27="ETF"),G27*Configurações!$B$9,IF(B27="OPCAO",G27*Configurações!$B$23,0)),2) -> 0 | I27: =ROUNDDOWN(IF(OR(B27="ACAO",B27="ETF",B27="DIR"),G27*Configurações!$C$9,IF(B27="OPCAO",G27*Configurações!$C$23,0)),2) -> 0 | J27: =ROUNDDOWN(IF(OR(B27="ACAO",B27="ETF",B27="DIR"),G27*Configurações!$D$9,IF(B27="OPCAO",G27*Configurações!$D$23,0)),2) -> 0 | M27: =G27+J27+K27+N27+L27+I27+H27 -> 0 | N27: =K27*$N$5 -> 0 | P27: =IF(D:D=$Q$4,E27,0) -> 0 | Q27: =IF(D:D=$Q$4,G27,0) -> 0 | R27: =R26+P27 -> 0 | S27: =IF(P27<=0,S26,IF(P27>0,((T26+Q27)/R27))) -> #DIV/0! | T27: =IF(R27=0,0,R27*S27) -> 0 | U27: =IF(D:D=$Q$4,H27+I27+J27+K27+L27+N27,0) -> 0 | V27: =IF(P27>0,SUM(T27,$U$7:U27),IF(P27=0,V26,IF(P27<0,V26+(P27*W27)))) -> 0 | W27: =IF(P27<=0,W26,IF(P27>0,V27/R27)) -> #DIV/0! | Y27: Resultado atual da operação ( % ) | AA27: =IF(AA6="","-",(AA21-AA14)/AA14) -> - | AC27: CAMPO AUTOMÁTICO
B28: ACAO | G28: =E28*F28 -> 0 | H28: =ROUNDDOWN(IF(OR(B28="ACAO",B28="DIR",B28="ETF"),G28*Configurações!$B$9,IF(B28="OPCAO",G28*Configurações!$B$23,0)),2) -> 0 | I28: =ROUNDDOWN(IF(OR(B28="ACAO",B28="ETF",B28="DIR"),G28*Configurações!$C$9,IF(B28="OPCAO",G28*Configurações!$C$23,0)),2) -> 0 | J28: =ROUNDDOWN(IF(OR(B28="ACAO",B28="ETF",B28="DIR"),G28*Configurações!$D$9,IF(B28="OPCAO",G28*Configurações!$D$23,0)),2) -> 0 | M28: =G28+J28+K28+N28+L28+I28+H28 -> 0 | N28: =K28*$N$5 -> 0 | P28: =IF(D:D=$Q$4,E28,0) -> 0 | Q28: =IF(D:D=$Q$4,G28,0) -> 0 | R28: =R27+P28 -> 0 | S28: =IF(P28<=0,S27,IF(P28>0,((T27+Q28)/R28))) -> #DIV/0! | T28: =IF(R28=0,0,R28*S28) -> 0 | U28: =IF(D:D=$Q$4,H28+I28+J28+K28+L28+N28,0) -> 0 | V28: =IF(P28>0,SUM(T28,$U$7:U28),IF(P28=0,V27,IF(P28<0,V27+(P28*W28)))) -> 0 | W28: =IF(P28<=0,W27,IF(P28>0,V28/R28)) -> #DIV/0!
B29: ACAO | G29: =E29*F29 -> 0 | H29: =ROUNDDOWN(IF(OR(B29="ACAO",B29="DIR",B29="ETF"),G29*Configurações!$B$9,IF(B29="OPCAO",G29*Configurações!$B$23,0)),2) -> 0 | I29: =ROUNDDOWN(IF(OR(B29="ACAO",B29="ETF",B29="DIR"),G29*Configurações!$C$9,IF(B29="OPCAO",G29*Configurações!$C$23,0)),2) -> 0 | J29: =ROUNDDOWN(IF(OR(B29="ACAO",B29="ETF",B29="DIR"),G29*Configurações!$D$9,IF(B29="OPCAO",G29*Configurações!$D$23,0)),2) -> 0 | M29: =G29+J29+K29+N29+L29+I29+H29 -> 0 | N29: =K29*$N$5 -> 0 | P29: =IF(D:D=$Q$4,E29,0) -> 0 | Q29: =IF(D:D=$Q$4,G29,0) -> 0 | R29: =R28+P29 -> 0 | S29: =IF(P29<=0,S28,IF(P29>0,((T28+Q29)/R29))) -> #DIV/0! | T29: =IF(R29=0,0,R29*S29) -> 0 | U29: =IF(D:D=$Q$4,H29+I29+J29+K29+L29+N29,0) -> 0 | V29: =IF(P29>0,SUM(T29,$U$7:U29),IF(P29=0,V28,IF(P29<0,V28+(P29*W29)))) -> 0 | W29: =IF(P29<=0,W28,IF(P29>0,V29/R29)) -> #DIV/0!
B30: ACAO | G30: =E30*F30 -> 0 | H30: =ROUNDDOWN(IF(OR(B30="ACAO",B30="DIR",B30="ETF"),G30*Configurações!$B$9,IF(B30="OPCAO",G30*Configurações!$B$23,0)),2) -> 0 | I30: =ROUNDDOWN(IF(OR(B30="ACAO",B30="ETF",B30="DIR"),G30*Configurações!$C$9,IF(B30="OPCAO",G30*Configurações!$C$23,0)),2) -> 0 | J30: =ROUNDDOWN(IF(OR(B30="ACAO",B30="ETF",B30="DIR"),G30*Configurações!$D$9,IF(B30="OPCAO",G30*Configurações!$D$23,0)),2) -> 0 | M30: =G30+J30+K30+N30+L30+I30+H30 -> 0 | N30: =K30*$N$5 -> 0 | P30: =IF(D:D=$Q$4,E30,0) -> 0 | Q30: =IF(D:D=$Q$4,G30,0) -> 0 | R30: =R29+P30 -> 0 | S30: =IF(P30<=0,S29,IF(P30>0,((T29+Q30)/R30))) -> #DIV/0! | T30: =IF(R30=0,0,R30*S30) -> 0 | U30: =IF(D:D=$Q$4,H30+I30+J30+K30+L30+N30,0) -> 0 | V30: =IF(P30>0,SUM(T30,$U$7:U30),IF(P30=0,V29,IF(P30<0,V29+(P30*W30)))) -> 0 | W30: =IF(P30<=0,W29,IF(P30>0,V30/R30)) -> #DIV/0! | Y30: Stop >
B31: ACAO | G31: =E31*F31 -> 0 | H31: =ROUNDDOWN(IF(OR(B31="ACAO",B31="DIR",B31="ETF"),G31*Configurações!$B$9,IF(B31="OPCAO",G31*Configurações!$B$23,0)),2) -> 0 | I31: =ROUNDDOWN(IF(OR(B31="ACAO",B31="ETF",B31="DIR"),G31*Configurações!$C$9,IF(B31="OPCAO",G31*Configurações!$C$23,0)),2) -> 0 | J31: =ROUNDDOWN(IF(OR(B31="ACAO",B31="ETF",B31="DIR"),G31*Configurações!$D$9,IF(B31="OPCAO",G31*Configurações!$D$23,0)),2) -> 0 | M31: =G31+J31+K31+N31+L31+I31+H31 -> 0 | N31: =K31*$N$5 -> 0 | P31: =IF(D:D=$Q$4,E31,0) -> 0 | Q31: =IF(D:D=$Q$4,G31,0) -> 0 | R31: =R30+P31 -> 0 | S31: =IF(P31<=0,S30,IF(P31>0,((T30+Q31)/R31))) -> #DIV/0! | T31: =IF(R31=0,0,R31*S31) -> 0 | U31: =IF(D:D=$Q$4,H31+I31+J31+K31+L31+N31,0) -> 0 | V31: =IF(P31>0,SUM(T31,$U$7:U31),IF(P31=0,V30,IF(P31<0,V30+(P31*W31)))) -> 0 | W31: =IF(P31<=0,W30,IF(P31>0,V31/R31)) -> #DIV/0!
B32: ACAO | G32: =E32*F32 -> 0 | H32: =ROUNDDOWN(IF(OR(B32="ACAO",B32="DIR",B32="ETF"),G32*Configurações!$B$9,IF(B32="OPCAO",G32*Configurações!$B$23,0)),2) -> 0 | I32: =ROUNDDOWN(IF(OR(B32="ACAO",B32="ETF",B32="DIR"),G32*Configurações!$C$9,IF(B32="OPCAO",G32*Configurações!$C$23,0)),2) -> 0 | J32: =ROUNDDOWN(IF(OR(B32="ACAO",B32="ETF",B32="DIR"),G32*Configurações!$D$9,IF(B32="OPCAO",G32*Configurações!$D$23,0)),2) -> 0 | M32: =G32+J32+K32+N32+L32+I32+H32 -> 0 | N32: =K32*$N$5 -> 0 | P32: =IF(D:D=$Q$4,E32,0) -> 0 | Q32: =IF(D:D=$Q$4,G32,0) -> 0 | R32: =R31+P32 -> 0 | S32: =IF(P32<=0,S31,IF(P32>0,((T31+Q32)/R32))) -> #DIV/0! | T32: =IF(R32=0,0,R32*S32) -> 0 | U32: =IF(D:D=$Q$4,H32+I32+J32+K32+L32+N32,0) -> 0 | V32: =IF(P32>0,SUM(T32,$U$7:U32),IF(P32=0,V31,IF(P32<0,V31+(P32*W32)))) -> 0 | W32: =IF(P32<=0,W31,IF(P32>0,V32/R32)) -> #DIV/0!
B33: ACAO | G33: =E33*F33 -> 0 | H33: =ROUNDDOWN(IF(OR(B33="ACAO",B33="DIR",B33="ETF"),G33*Configurações!$B$9,IF(B33="OPCAO",G33*Configurações!$B$23,0)),2) -> 0 | I33: =ROUNDDOWN(IF(OR(B33="ACAO",B33="ETF",B33="DIR"),G33*Configurações!$C$9,IF(B33="OPCAO",G33*Configurações!$C$23,0)),2) -> 0 | J33: =ROUNDDOWN(IF(OR(B33="ACAO",B33="ETF",B33="DIR"),G33*Configurações!$D$9,IF(B33="OPCAO",G33*Configurações!$D$23,0)),2) -> 0 | M33: =G33+J33+K33+N33+L33+I33+H33 -> 0 | N33: =K33*$N$5 -> 0 | P33: =IF(D:D=$Q$4,E33,0) -> 0 | Q33: =IF(D:D=$Q$4,G33,0) -> 0 | R33: =R32+P33 -> 0 | S33: =IF(P33<=0,S32,IF(P33>0,((T32+Q33)/R33))) -> #DIV/0! | T33: =IF(R33=0,0,R33*S33) -> 0 | U33: =IF(D:D=$Q$4,H33+I33+J33+K33+L33+N33,0) -> 0 | V33: =IF(P33>0,SUM(T33,$U$7:U33),IF(P33=0,V32,IF(P33<0,V32+(P33*W33)))) -> 0 | W33: =IF(P33<=0,W32,IF(P33>0,V33/R33)) -> #DIV/0! | Y33: Resultado se acionado Stop | AA33: =IF(AA6="","-",(AA30-AA14)*AA8) -> - | AC33: CAMPO AUTOMÁTICO
B34: ACAO | G34: =E34*F34 -> 0 | H34: =ROUNDDOWN(IF(OR(B34="ACAO",B34="DIR",B34="ETF"),G34*Configurações!$B$9,IF(B34="OPCAO",G34*Configurações!$B$23,0)),2) -> 0 | I34: =ROUNDDOWN(IF(OR(B34="ACAO",B34="ETF",B34="DIR"),G34*Configurações!$C$9,IF(B34="OPCAO",G34*Configurações!$C$23,0)),2) -> 0 | J34: =ROUNDDOWN(IF(OR(B34="ACAO",B34="ETF",B34="DIR"),G34*Configurações!$D$9,IF(B34="OPCAO",G34*Configurações!$D$23,0)),2) -> 0 | M34: =G34+J34+K34+N34+L34+I34+H34 -> 0 | N34: =K34*$N$5 -> 0 | P34: =IF(D:D=$Q$4,E34,0) -> 0 | Q34: =IF(D:D=$Q$4,G34,0) -> 0 | R34: =R33+P34 -> 0 | S34: =IF(P34<=0,S33,IF(P34>0,((T33+Q34)/R34))) -> #DIV/0! | T34: =IF(R34=0,0,R34*S34) -> 0 | U34: =IF(D:D=$Q$4,H34+I34+J34+K34+L34+N34,0) -> 0 | V34: =IF(P34>0,SUM(T34,$U$7:U34),IF(P34=0,V33,IF(P34<0,V33+(P34*W34)))) -> 0 | W34: =IF(P34<=0,W33,IF(P34>0,V34/R34)) -> #DIV/0!
B35: ACAO | G35: =E35*F35 -> 0 | H35: =ROUNDDOWN(IF(OR(B35="ACAO",B35="DIR",B35="ETF"),G35*Configurações!$B$9,IF(B35="OPCAO",G35*Configurações!$B$23,0)),2) -> 0 | I35: =ROUNDDOWN(IF(OR(B35="ACAO",B35="ETF",B35="DIR"),G35*Configurações!$C$9,IF(B35="OPCAO",G35*Configurações!$C$23,0)),2) -> 0 | J35: =ROUNDDOWN(IF(OR(B35="ACAO",B35="ETF",B35="DIR"),G35*Configurações!$D$9,IF(B35="OPCAO",G35*Configurações!$D$23,0)),2) -> 0 | M35: =G35+J35+K35+N35+L35+I35+H35 -> 0 | N35: =K35*$N$5 -> 0 | P35: =IF(D:D=$Q$4,E35,0) -> 0 | Q35: =IF(D:D=$Q$4,G35,0) -> 0 | R35: =R34+P35 -> 0 | S35: =IF(P35<=0,S34,IF(P35>0,((T34+Q35)/R35))) -> #DIV/0! | T35: =IF(R35=0,0,R35*S35) -> 0 | U35: =IF(D:D=$Q$4,H35+I35+J35+K35+L35+N35,0) -> 0 | V35: =IF(P35>0,SUM(T35,$U$7:U35),IF(P35=0,V34,IF(P35<0,V34+(P35*W35)))) -> 0 | W35: =IF(P35<=0,W34,IF(P35>0,V35/R35)) -> #DIV/0!
B36: ACAO | G36: =E36*F36 -> 0 | H36: =ROUNDDOWN(IF(OR(B36="ACAO",B36="DIR",B36="ETF"),G36*Configurações!$B$9,IF(B36="OPCAO",G36*Configurações!$B$23,0)),2) -> 0 | I36: =ROUNDDOWN(IF(OR(B36="ACAO",B36="ETF",B36="DIR"),G36*Configurações!$C$9,IF(B36="OPCAO",G36*Configurações!$C$23,0)),2) -> 0 | J36: =ROUNDDOWN(IF(OR(B36="ACAO",B36="ETF",B36="DIR"),G36*Configurações!$D$9,IF(B36="OPCAO",G36*Configurações!$D$23,0)),2) -> 0 | M36: =G36+J36+K36+N36+L36+I36+H36 -> 0 | N36: =K36*$N$5 -> 0 | P36: =IF(D:D=$Q$4,E36,0) -> 0 | Q36: =IF(D:D=$Q$4,G36,0) -> 0 | R36: =R35+P36 -> 0 | S36: =IF(P36<=0,S35,IF(P36>0,((T35+Q36)/R36))) -> #DIV/0! | T36: =IF(R36=0,0,R36*S36) -> 0 | U36: =IF(D:D=$Q$4,H36+I36+J36+K36+L36+N36,0) -> 0 | V36: =IF(P36>0,SUM(T36,$U$7:U36),IF(P36=0,V35,IF(P36<0,V35+(P36*W36)))) -> 0 | W36: =IF(P36<=0,W35,IF(P36>0,V36/R36)) -> #DIV/0!
B37: ACAO | G37: =E37*F37 -> 0 | H37: =ROUNDDOWN(IF(OR(B37="ACAO",B37="DIR",B37="ETF"),G37*Configurações!$B$9,IF(B37="OPCAO",G37*Configurações!$B$23,0)),2) -> 0 | I37: =ROUNDDOWN(IF(OR(B37="ACAO",B37="ETF",B37="DIR"),G37*Configurações!$C$9,IF(B37="OPCAO",G37*Configurações!$C$23,0)),2) -> 0 | J37: =ROUNDDOWN(IF(OR(B37="ACAO",B37="ETF",B37="DIR"),G37*Configurações!$D$9,IF(B37="OPCAO",G37*Configurações!$D$23,0)),2) -> 0 | M37: =G37+J37+K37+N37+L37+I37+H37 -> 0 | N37: =K37*$N$5 -> 0 | P37: =IF(D:D=$Q$4,E37,0) -> 0 | Q37: =IF(D:D=$Q$4,G37,0) -> 0 | R37: =R36+P37 -> 0 | S37: =IF(P37<=0,S36,IF(P37>0,((T36+Q37)/R37))) -> #DIV/0! | T37: =IF(R37=0,0,R37*S37) -> 0 | U37: =IF(D:D=$Q$4,H37+I37+J37+K37+L37+N37,0) -> 0 | V37: =IF(P37>0,SUM(T37,$U$7:U37),IF(P37=0,V36,IF(P37<0,V36+(P37*W37)))) -> 0 | W37: =IF(P37<=0,W36,IF(P37>0,V37/R37)) -> #DIV/0!
B38: ACAO | G38: =E38*F38 -> 0 | H38: =ROUNDDOWN(IF(OR(B38="ACAO",B38="DIR",B38="ETF"),G38*Configurações!$B$9,IF(B38="OPCAO",G38*Configurações!$B$23,0)),2) -> 0 | I38: =ROUNDDOWN(IF(OR(B38="ACAO",B38="ETF",B38="DIR"),G38*Configurações!$C$9,IF(B38="OPCAO",G38*Configurações!$C$23,0)),2) -> 0 | J38: =ROUNDDOWN(IF(OR(B38="ACAO",B38="ETF",B38="DIR"),G38*Configurações!$D$9,IF(B38="OPCAO",G38*Configurações!$D$23,0)),2) -> 0 | M38: =G38+J38+K38+N38+L38+I38+H38 -> 0 | N38: =K38*$N$5 -> 0 | P38: =IF(D:D=$Q$4,E38,0) -> 0 | Q38: =IF(D:D=$Q$4,G38,0) -> 0 | R38: =R37+P38 -> 0 | S38: =IF(P38<=0,S37,IF(P38>0,((T37+Q38)/R38))) -> #DIV/0! | T38: =IF(R38=0,0,R38*S38) -> 0 | U38: =IF(D:D=$Q$4,H38+I38+J38+K38+L38+N38,0) -> 0 | V38: =IF(P38>0,SUM(T38,$U$7:U38),IF(P38=0,V37,IF(P38<0,V37+(P38*W38)))) -> 0 | W38: =IF(P38<=0,W37,IF(P38>0,V38/R38)) -> #DIV/0!
B39: ACAO | G39: =E39*F39 -> 0 | H39: =ROUNDDOWN(IF(OR(B39="ACAO",B39="DIR",B39="ETF"),G39*Configurações!$B$9,IF(B39="OPCAO",G39*Configurações!$B$23,0)),2) -> 0 | I39: =ROUNDDOWN(IF(OR(B39="ACAO",B39="ETF",B39="DIR"),G39*Configurações!$C$9,IF(B39="OPCAO",G39*Configurações!$C$23,0)),2) -> 0 | J39: =ROUNDDOWN(IF(OR(B39="ACAO",B39="ETF",B39="DIR"),G39*Configurações!$D$9,IF(B39="OPCAO",G39*Configurações!$D$23,0)),2) -> 0 | M39: =G39+J39+K39+N39+L39+I39+H39 -> 0 | N39: =K39*$N$5 -> 0 | P39: =IF(D:D=$Q$4,E39,0) -> 0 | Q39: =IF(D:D=$Q$4,G39,0) -> 0 | R39: =R38+P39 -> 0 | S39: =IF(P39<=0,S38,IF(P39>0,((T38+Q39)/R39))) -> #DIV/0! | T39: =IF(R39=0,0,R39*S39) -> 0 | U39: =IF(D:D=$Q$4,H39+I39+J39+K39+L39+N39,0) -> 0 | V39: =IF(P39>0,SUM(T39,$U$7:U39),IF(P39=0,V38,IF(P39<0,V38+(P39*W39)))) -> 0 | W39: =IF(P39<=0,W38,IF(P39>0,V39/R39)) -> #DIV/0!
B40: ACAO | G40: =E40*F40 -> 0 | H40: =ROUNDDOWN(IF(OR(B40="ACAO",B40="DIR",B40="ETF"),G40*Configurações!$B$9,IF(B40="OPCAO",G40*Configurações!$B$23,0)),2) -> 0 | I40: =ROUNDDOWN(IF(OR(B40="ACAO",B40="ETF",B40="DIR"),G40*Configurações!$C$9,IF(B40="OPCAO",G40*Configurações!$C$23,0)),2) -> 0 | J40: =ROUNDDOWN(IF(OR(B40="ACAO",B40="ETF",B40="DIR"),G40*Configurações!$D$9,IF(B40="OPCAO",G40*Configurações!$D$23,0)),2) -> 0 | M40: =G40+J40+K40+N40+L40+I40+H40 -> 0 | N40: =K40*$N$5 -> 0 | P40: =IF(D:D=$Q$4,E40,0) -> 0 | Q40: =IF(D:D=$Q$4,G40,0) -> 0 | R40: =R39+P40 -> 0 | S40: =IF(P40<=0,S39,IF(P40>0,((T39+Q40)/R40))) -> #DIV/0! | T40: =IF(R40=0,0,R40*S40) -> 0 | U40: =IF(D:D=$Q$4,H40+I40+J40+K40+L40+N40,0) -> 0 | V40: =IF(P40>0,SUM(T40,$U$7:U40),IF(P40=0,V39,IF(P40<0,V39+(P40*W40)))) -> 0 | W40: =IF(P40<=0,W39,IF(P40>0,V40/R40)) -> #DIV/0!
B41: ACAO | G41: =E41*F41 -> 0 | H41: =ROUNDDOWN(IF(OR(B41="ACAO",B41="DIR",B41="ETF"),G41*Configurações!$B$9,IF(B41="OPCAO",G41*Configurações!$B$23,0)),2) -> 0 | I41: =ROUNDDOWN(IF(OR(B41="ACAO",B41="ETF",B41="DIR"),G41*Configurações!$C$9,IF(B41="OPCAO",G41*Configurações!$C$23,0)),2) -> 0 | J41: =ROUNDDOWN(IF(OR(B41="ACAO",B41="ETF",B41="DIR"),G41*Configurações!$D$9,IF(B41="OPCAO",G41*Configurações!$D$23,0)),2) -> 0 | M41: =G41+J41+K41+N41+L41+I41+H41 -> 0 | N41: =K41*$N$5 -> 0 | P41: =IF(D:D=$Q$4,E41,0) -> 0 | Q41: =IF(D:D=$Q$4,G41,0) -> 0 | R41: =R40+P41 -> 0 | S41: =IF(P41<=0,S40,IF(P41>0,((T40+Q41)/R41))) -> #DIV/0! | T41: =IF(R41=0,0,R41*S41) -> 0 | U41: =IF(D:D=$Q$4,H41+I41+J41+K41+L41+N41,0) -> 0 | V41: =IF(P41>0,SUM(T41,$U$7:U41),IF(P41=0,V40,IF(P41<0,V40+(P41*W41)))) -> 0 | W41: =IF(P41<=0,W40,IF(P41>0,V41/R41)) -> #DIV/0!
B42: ACAO | G42: =E42*F42 -> 0 | H42: =ROUNDDOWN(IF(OR(B42="ACAO",B42="DIR",B42="ETF"),G42*Configurações!$B$9,IF(B42="OPCAO",G42*Configurações!$B$23,0)),2) -> 0 | I42: =ROUNDDOWN(IF(OR(B42="ACAO",B42="ETF",B42="DIR"),G42*Configurações!$C$9,IF(B42="OPCAO",G42*Configurações!$C$23,0)),2) -> 0 | J42: =ROUNDDOWN(IF(OR(B42="ACAO",B42="ETF",B42="DIR"),G42*Configurações!$D$9,IF(B42="OPCAO",G42*Configurações!$D$23,0)),2) -> 0 | M42: =G42+J42+K42+N42+L42+I42+H42 -> 0 | N42: =K42*$N$5 -> 0 | P42: =IF(D:D=$Q$4,E42,0) -> 0 | Q42: =IF(D:D=$Q$4,G42,0) -> 0 | R42: =R41+P42 -> 0 | S42: =IF(P42<=0,S41,IF(P42>0,((T41+Q42)/R42))) -> #DIV/0! | T42: =IF(R42=0,0,R42*S42) -> 0 | U42: =IF(D:D=$Q$4,H42+I42+J42+K42+L42+N42,0) -> 0 | V42: =IF(P42>0,SUM(T42,$U$7:U42),IF(P42=0,V41,IF(P42<0,V41+(P42*W42)))) -> 0 | W42: =IF(P42<=0,W41,IF(P42>0,V42/R42)) -> #DIV/0!
B43: ACAO | G43: =E43*F43 -> 0 | H43: =ROUNDDOWN(IF(OR(B43="ACAO",B43="DIR",B43="ETF"),G43*Configurações!$B$9,IF(B43="OPCAO",G43*Configurações!$B$23,0)),2) -> 0 | I43: =ROUNDDOWN(IF(OR(B43="ACAO",B43="ETF",B43="DIR"),G43*Configurações!$C$9,IF(B43="OPCAO",G43*Configurações!$C$23,0)),2) -> 0 | J43: =ROUNDDOWN(IF(OR(B43="ACAO",B43="ETF",B43="DIR"),G43*Configurações!$D$9,IF(B43="OPCAO",G43*Configurações!$D$23,0)),2) -> 0 | M43: =G43+J43+K43+N43+L43+I43+H43 -> 0 | N43: =K43*$N$5 -> 0 | P43: =IF(D:D=$Q$4,E43,0) -> 0 | Q43: =IF(D:D=$Q$4,G43,0) -> 0 | R43: =R42+P43 -> 0 | S43: =IF(P43<=0,S42,IF(P43>0,((T42+Q43)/R43))) -> #DIV/0! | T43: =IF(R43=0,0,R43*S43) -> 0 | U43: =IF(D:D=$Q$4,H43+I43+J43+K43+L43+N43,0) -> 0 | V43: =IF(P43>0,SUM(T43,$U$7:U43),IF(P43=0,V42,IF(P43<0,V42+(P43*W43)))) -> 0 | W43: =IF(P43<=0,W42,IF(P43>0,V43/R43)) -> #DIV/0!
B44: ACAO | G44: =E44*F44 -> 0 | H44: =ROUNDDOWN(IF(OR(B44="ACAO",B44="DIR",B44="ETF"),G44*Configurações!$B$9,IF(B44="OPCAO",G44*Configurações!$B$23,0)),2) -> 0 | I44: =ROUNDDOWN(IF(OR(B44="ACAO",B44="ETF",B44="DIR"),G44*Configurações!$C$9,IF(B44="OPCAO",G44*Configurações!$C$23,0)),2) -> 0 | J44: =ROUNDDOWN(IF(OR(B44="ACAO",B44="ETF",B44="DIR"),G44*Configurações!$D$9,IF(B44="OPCAO",G44*Configurações!$D$23,0)),2) -> 0 | M44: =G44+J44+K44+N44+L44+I44+H44 -> 0 | N44: =K44*$N$5 -> 0 | P44: =IF(D:D=$Q$4,E44,0) -> 0 | Q44: =IF(D:D=$Q$4,G44,0) -> 0 | R44: =R43+P44 -> 0 | S44: =IF(P44<=0,S43,IF(P44>0,((T43+Q44)/R44))) -> #DIV/0! | T44: =IF(R44=0,0,R44*S44) -> 0 | U44: =IF(D:D=$Q$4,H44+I44+J44+K44+L44+N44,0) -> 0 | V44: =IF(P44>0,SUM(T44,$U$7:U44),IF(P44=0,V43,IF(P44<0,V43+(P44*W44)))) -> 0 | W44: =IF(P44<=0,W43,IF(P44>0,V44/R44)) -> #DIV/0!
B45: ACAO | G45: =E45*F45 -> 0 | H45: =ROUNDDOWN(IF(OR(B45="ACAO",B45="DIR",B45="ETF"),G45*Configurações!$B$9,IF(B45="OPCAO",G45*Configurações!$B$23,0)),2) -> 0 | I45: =ROUNDDOWN(IF(OR(B45="ACAO",B45="ETF",B45="DIR"),G45*Configurações!$C$9,IF(B45="OPCAO",G45*Configurações!$C$23,0)),2) -> 0 | J45: =ROUNDDOWN(IF(OR(B45="ACAO",B45="ETF",B45="DIR"),G45*Configurações!$D$9,IF(B45="OPCAO",G45*Configurações!$D$23,0)),2) -> 0 | M45: =G45+J45+K45+N45+L45+I45+H45 -> 0 | N45: =K45*$N$5 -> 0 | P45: =IF(D:D=$Q$4,E45,0) -> 0 | Q45: =IF(D:D=$Q$4,G45,0) -> 0 | R45: =R44+P45 -> 0 | S45: =IF(P45<=0,S44,IF(P45>0,((T44+Q45)/R45))) -> #DIV/0! | T45: =IF(R45=0,0,R45*S45) -> 0 | U45: =IF(D:D=$Q$4,H45+I45+J45+K45+L45+N45,0) -> 0 | V45: =IF(P45>0,SUM(T45,$U$7:U45),IF(P45=0,V44,IF(P45<0,V44+(P45*W45)))) -> 0 | W45: =IF(P45<=0,W44,IF(P45>0,V45/R45)) -> #DIV/0!
... B81: ACAO | G81: =E81*F81 -> 0 | H81: =ROUNDDOWN(IF(OR(B81="ACAO",B81="DIR",B81="ETF"),G81*Configurações!$B$9,IF(B81="OPCAO",G81*Configurações!$B$23,0)),2) -> 0 | I81: =ROUNDDOWN(IF(OR(B81="ACAO",B81="ETF",B81="DIR"),G81*Configurações!$C$9,IF(B81="OPCAO",G81*Configurações!$C$23,0)),2) -> 0 | J81: =ROUNDDOWN(IF(OR(B81="ACAO",B81="ETF",B81="DIR"),G81*Configurações!$D$9,IF(B81="OPCAO",G81*Configurações!$D$23,0)),2) -> 0 | M81: =G81+J81+K81+N81+L81+I81+H81 -> 0 | N81: =K81*$N$5 -> 0 | P81: =IF(D:D=$Q$4,E81,0) -> 0 | Q81: =IF(D:D=$Q$4,G81,0) -> 0 | R81: =R80+P81 -> 0 | S81: =IF(P81<=0,S80,IF(P81>0,((T80+Q81)/R81))) -> #DIV/0! | T81: =IF(R81=0,0,R81*S81) -> 0 | U81: =IF(D:D=$Q$4,H81+I81+J81+K81+L81+N81,0) -> 0 | V81: =IF(P81>0,SUM(T81,$U$7:U81),IF(P81=0,V80,IF(P81<0,V80+(P81*W81)))) -> 0 | W81: =IF(P81<=0,W80,IF(P81>0,V81/R81)) -> #DIV/0!
B84: Quadro das Operações VENDA A DESCOBERTO (abertas) | N84: ISS | P84: ATIVO | Q84: =AA86 -> 0 | R84: CALCULADORA PREÇO MÉDIO | Y84: CÁLCULO DE PREÇO MÉDIO
B85: Tipo | C85: Data Venda | D85: Código Ativo | E85: Quantidade | F85: Preço Venda | G85: Movimento Venda | H85: Taxa Negociação | I85: Taxa Liquidação | J85: Taxa Registro | K85: Corretagens de Venda | L85: Outras despesas | M85: Total investido | N85: ='Operações Normais'!X7 -> 0.1068 | P85: Quantidade | Q85: Total | R85: Quantidade atual | S85: Preço médio atual | T85: Investimento atual | U85: Custos | V85: Investimento atual com custos embutidos | W85: Preço médio atual com custos
Y86: INSIRA O CÓDIGO DO ATIVO >
B87: ACAO | G87: =E87*F87 -> 0 | H87: =ROUNDDOWN(IF(OR(B87="ACAO",B87="DIR",B87="ETF"),G87*Configurações!$B$9,IF(B87="OPCAO",G87*Configurações!$B$23,0)),2) -> 0 | I87: =ROUNDDOWN(IF(OR(B87="ACAO",B87="ETF",B87="DIR"),G87*Configurações!$C$9,IF(B87="OPCAO",G87*Configurações!$C$23,0)),2) -> 0 | J87: =ROUNDDOWN(IF(OR(B87="ACAO",B87="ETF",B87="DIR"),G87*Configurações!$D$9,IF(B87="OPCAO",G87*Configurações!$D$23,0)),2) -> 0 | M87: =-G87+J87+K87+N87+L87+I87+H87 -> 0 | N87: =K87*$N$85 -> 0 | P87: =IF(D:D=$Q$84,E87,0) -> 0 | Q87: =IF(D:D=$Q$84,G87,0) -> 0 | R87: =P87 -> 0 | S87: =Q87/R87 -> #DIV/0! | T87: =IF(R87=0,0,R87*S87) -> 0 | U87: =IF(D:D=$Q$84,H87+I87+J87+K87+L87+N87,0) -> 0 | V87: =T87-U87 -> 0 | W87: =V87/R87 -> #DIV/0!
B88: ACAO | G88: =E88*F88 -> 0 | H88: =ROUNDDOWN(IF(OR(B88="ACAO",B88="DIR",B88="ETF"),G88*Configurações!$B$9,IF(B88="OPCAO",G88*Configurações!$B$23,0)),2) -> 0 | I88: =ROUNDDOWN(IF(OR(B88="ACAO",B88="ETF",B88="DIR"),G88*Configurações!$C$9,IF(B88="OPCAO",G88*Configurações!$C$23,0)),2) -> 0 | J88: =ROUNDDOWN(IF(OR(B88="ACAO",B88="ETF",B88="DIR"),G88*Configurações!$D$9,IF(B88="OPCAO",G88*Configurações!$D$23,0)),2) -> 0 | M88: =-G88+J88+K88+N88+L88+I88+H88 -> 0 | N88: =K88*$N$85 -> 0 | P88: =IF(D:D=$Q$84,E88,0) -> 0 | Q88: =IF(D:D=$Q$84,G88,0) -> 0 | R88: =R87+P88 -> 0 | S88: =IF(P88<=0,S87,IF(P88>0,((T87+Q88)/R88))) -> #DIV/0! | T88: =IF(R88=0,0,R88*S88) -> 0 | U88: =IF(D:D=$Q$84,H88+I88+J88+K88+L88+N88,0) -> 0 | V88: =IF(P88>0,T88-SUM($U$87:U88),IF(P88=0,V87,IF(P88<0,V87+(P88*W88)))) -> 0 | W88: =IF(P88<=0,W87,IF(P88>0,V88/R88)) -> #DIV/0! | Y88: Quantidade | AA88: =R161 -> 0 | AC88: CAMPO AUTOMÁTICO
B89: ACAO | G89: =E89*F89 -> 0 | H89: =ROUNDDOWN(IF(OR(B89="ACAO",B89="DIR",B89="ETF"),G89*Configurações!$B$9,IF(B89="OPCAO",G89*Configurações!$B$23,0)),2) -> 0 | I89: =ROUNDDOWN(IF(OR(B89="ACAO",B89="ETF",B89="DIR"),G89*Configurações!$C$9,IF(B89="OPCAO",G89*Configurações!$C$23,0)),2) -> 0 | J89: =ROUNDDOWN(IF(OR(B89="ACAO",B89="ETF",B89="DIR"),G89*Configurações!$D$9,IF(B89="OPCAO",G89*Configurações!$D$23,0)),2) -> 0 | M89: =-G89+J89+K89+N89+L89+I89+H89 -> 0 | N89: =K89*$N$85 -> 0 | P89: =IF(D:D=$Q$84,E89,0) -> 0 | Q89: =IF(D:D=$Q$84,G89,0) -> 0 | R89: =R88+P89 -> 0 | S89: =IF(P89<=0,S88,IF(P89>0,((T88+Q89)/R89))) -> #DIV/0! | T89: =IF(R89=0,0,R89*S89) -> 0 | U89: =IF(D:D=$Q$84,H89+I89+J89+K89+L89+N89,0) -> 0 | V89: =IF(P89>0,T89-SUM($U$87:U89),IF(P89=0,V88,IF(P89<0,V88+(P89*W89)))) -> 0 | W89: =IF(P89<=0,W88,IF(P89>0,V89/R89)) -> #DIV/0!
B90: ACAO | G90: =E90*F90 -> 0 | H90: =ROUNDDOWN(IF(OR(B90="ACAO",B90="DIR",B90="ETF"),G90*Configurações!$B$9,IF(B90="OPCAO",G90*Configurações!$B$23,0)),2) -> 0 | I90: =ROUNDDOWN(IF(OR(B90="ACAO",B90="ETF",B90="DIR"),G90*Configurações!$C$9,IF(B90="OPCAO",G90*Configurações!$C$23,0)),2) -> 0 | J90: =ROUNDDOWN(IF(OR(B90="ACAO",B90="ETF",B90="DIR"),G90*Configurações!$D$9,IF(B90="OPCAO",G90*Configurações!$D$23,0)),2) -> 0 | M90: =-G90+J90+K90+N90+L90+I90+H90 -> 0 | N90: =K90*$N$85 -> 0 | P90: =IF(D:D=$Q$84,E90,0) -> 0 | Q90: =IF(D:D=$Q$84,G90,0) -> 0 | R90: =R89+P90 -> 0 | S90: =IF(P90<=0,S89,IF(P90>0,(T89+Q90)/R90)) -> #DIV/0! | T90: =IF(R90=0,0,R90*S90) -> 0 | U90: =IF(D:D=$Q$84,H90+I90+J90+K90+L90+N90,0) -> 0 | V90: =IF(P90>0,T90-SUM($U$87:U90),IF(P90=0,V89,IF(P90<0,V89+(P90*W90)))) -> 0 | W90: =IF(P90<=0,W89,IF(P90>0,V90/R90)) -> #DIV/0!
B91: ACAO | G91: =E91*F91 -> 0 | H91: =ROUNDDOWN(IF(OR(B91="ACAO",B91="DIR",B91="ETF"),G91*Configurações!$B$9,IF(B91="OPCAO",G91*Configurações!$B$23,0)),2) -> 0 | I91: =ROUNDDOWN(IF(OR(B91="ACAO",B91="ETF",B91="DIR"),G91*Configurações!$C$9,IF(B91="OPCAO",G91*Configurações!$C$23,0)),2) -> 0 | J91: =ROUNDDOWN(IF(OR(B91="ACAO",B91="ETF",B91="DIR"),G91*Configurações!$D$9,IF(B91="OPCAO",G91*Configurações!$D$23,0)),2) -> 0 | M91: =-G91+J91+K91+N91+L91+I91+H91 -> 0 | N91: =K91*$N$85 -> 0 | P91: =IF(D:D=$Q$84,E91,0) -> 0 | Q91: =IF(D:D=$Q$84,G91,0) -> 0 | R91: =R90+P91 -> 0 | S91: =IF(P91<=0,S90,IF(P91>0,((T90+Q91)/R91))) -> #DIV/0! | T91: =IF(R91=0,0,R91*S91) -> 0 | U91: =IF(D:D=$Q$84,H91+I91+J91+K91+L91+N91,0) -> 0 | V91: =IF(P91>0,T91-SUM($U$87:U91),IF(P91=0,V90,IF(P91<0,V90+(P91*W91)))) -> 0 | W91: =IF(P91<=0,W90,IF(P91>0,V91/R91)) -> #DIV/0! | Y91: Preço médio sem custos (taxas) | AA91: =IF(AA86="","-",S161) -> - | AC91: CAMPO AUTOMÁTICO
B92: ACAO | G92: =E92*F92 -> 0 | H92: =ROUNDDOWN(IF(OR(B92="ACAO",B92="DIR",B92="ETF"),G92*Configurações!$B$9,IF(B92="OPCAO",G92*Configurações!$B$23,0)),2) -> 0 | I92: =ROUNDDOWN(IF(OR(B92="ACAO",B92="ETF",B92="DIR"),G92*Configurações!$C$9,IF(B92="OPCAO",G92*Configurações!$C$23,0)),2) -> 0 | J92: =ROUNDDOWN(IF(OR(B92="ACAO",B92="ETF",B92="DIR"),G92*Configurações!$D$9,IF(B92="OPCAO",G92*Configurações!$D$23,0)),2) -> 0 | M92: =-G92+J92+K92+N92+L92+I92+H92 -> 0 | N92: =K92*$N$85 -> 0 | P92: =IF(D:D=$Q$84,E92,0) -> 0 | Q92: =IF(D:D=$Q$84,G92,0) -> 0 | R92: =R91+P92 -> 0 | S92: =IF(P92<=0,S91,IF(P92>0,((T91+Q92)/R92))) -> #DIV/0! | T92: =IF(R92=0,0,R92*S92) -> 0 | U92: =IF(D:D=$Q$84,H92+I92+J92+K92+L92+N92,0) -> 0 | V92: =IF(P92>0,T92-SUM($U$87:U92),IF(P92=0,V91,IF(P92<0,V91+(P92*W92)))) -> 0 | W92: =IF(P92<=0,W91,IF(P92>0,V92/R92)) -> #DIV/0!
B93: ACAO | G93: =E93*F93 -> 0 | H93: =ROUNDDOWN(IF(OR(B93="ACAO",B93="DIR",B93="ETF"),G93*Configurações!$B$9,IF(B93="OPCAO",G93*Configurações!$B$23,0)),2) -> 0 | I93: =ROUNDDOWN(IF(OR(B93="ACAO",B93="ETF",B93="DIR"),G93*Configurações!$C$9,IF(B93="OPCAO",G93*Configurações!$C$23,0)),2) -> 0 | J93: =ROUNDDOWN(IF(OR(B93="ACAO",B93="ETF",B93="DIR"),G93*Configurações!$D$9,IF(B93="OPCAO",G93*Configurações!$D$23,0)),2) -> 0 | M93: =-G93+J93+K93+N93+L93+I93+H93 -> 0 | N93: =K93*$N$85 -> 0 | P93: =IF(D:D=$Q$84,E93,0) -> 0 | Q93: =IF(D:D=$Q$84,G93,0) -> 0 | R93: =R92+P93 -> 0 | S93: =IF(P93<=0,S92,IF(P93>0,((T92+Q93)/R93))) -> #DIV/0! | T93: =IF(R93=0,0,R93*S93) -> 0 | U93: =IF(D:D=$Q$84,H93+I93+J93+K93+L93+N93,0) -> 0 | V93: =IF(P93>0,T93-SUM($U$87:U93),IF(P93=0,V92,IF(P93<0,V92+(P93*W93)))) -> 0 | W93: =IF(P93<=0,W92,IF(P93>0,V93/R93)) -> #DIV/0!
B94: ACAO | G94: =E94*F94 -> 0 | H94: =ROUNDDOWN(IF(OR(B94="ACAO",B94="DIR",B94="ETF"),G94*Configurações!$B$9,IF(B94="OPCAO",G94*Configurações!$B$23,0)),2) -> 0 | I94: =ROUNDDOWN(IF(OR(B94="ACAO",B94="ETF",B94="DIR"),G94*Configurações!$C$9,IF(B94="OPCAO",G94*Configurações!$C$23,0)),2) -> 0 | J94: =ROUNDDOWN(IF(OR(B94="ACAO",B94="ETF",B94="DIR"),G94*Configurações!$D$9,IF(B94="OPCAO",G94*Configurações!$D$23,0)),2) -> 0 | M94: =-G94+J94+K94+N94+L94+I94+H94 -> 0 | N94: =K94*$N$85 -> 0 | P94: =IF(D:D=$Q$84,E94,0) -> 0 | Q94: =IF(D:D=$Q$84,G94,0) -> 0 | R94: =R93+P94 -> 0 | S94: =IF(P94<=0,S93,IF(P94>0,((T93+Q94)/R94))) -> #DIV/0! | T94: =IF(R94=0,0,R94*S94) -> 0 | U94: =IF(D:D=$Q$84,H94+I94+J94+K94+L94+N94,0) -> 0 | V94: =IF(P94>0,T94-SUM($U$87:U94),IF(P94=0,V93,IF(P94<0,V93+(P94*W94)))) -> 0 | W94: =IF(P94<=0,W93,IF(P94>0,V94/R94)) -> #DIV/0! | Y94: Preço médio com custos (taxas) | AA94: =IF(AA86="","-",W161) -> - | AC94: CAMPO AUTOMÁTICO
B95: ACAO | G95: =E95*F95 -> 0 | H95: =ROUNDDOWN(IF(OR(B95="ACAO",B95="DIR",B95="ETF"),G95*Configurações!$B$9,IF(B95="OPCAO",G95*Configurações!$B$23,0)),2) -> 0 | I95: =ROUNDDOWN(IF(OR(B95="ACAO",B95="ETF",B95="DIR"),G95*Configurações!$C$9,IF(B95="OPCAO",G95*Configurações!$C$23,0)),2) -> 0 | J95: =ROUNDDOWN(IF(OR(B95="ACAO",B95="ETF",B95="DIR"),G95*Configurações!$D$9,IF(B95="OPCAO",G95*Configurações!$D$23,0)),2) -> 0 | M95: =-G95+J95+K95+N95+L95+I95+H95 -> 0 | N95: =K95*$N$85 -> 0 | P95: =IF(D:D=$Q$84,E95,0) -> 0 | Q95: =IF(D:D=$Q$84,G95,0) -> 0 | R95: =R94+P95 -> 0 | S95: =IF(P95<=0,S94,IF(P95>0,((T94+Q95)/R95))) -> #DIV/0! | T95: =IF(R95=0,0,R95*S95) -> 0 | U95: =IF(D:D=$Q$84,H95+I95+J95+K95+L95+N95,0) -> 0 | V95: =IF(P95>0,T95-SUM($U$87:U95),IF(P95=0,V94,IF(P95<0,V94+(P95*W95)))) -> 0 | W95: =IF(P95<=0,W94,IF(P95>0,V95/R95)) -> #DIV/0!
B96: ACAO | G96: =E96*F96 -> 0 | H96: =ROUNDDOWN(IF(OR(B96="ACAO",B96="DIR",B96="ETF"),G96*Configurações!$B$9,IF(B96="OPCAO",G96*Configurações!$B$23,0)),2) -> 0 | I96: =ROUNDDOWN(IF(OR(B96="ACAO",B96="ETF",B96="DIR"),G96*Configurações!$C$9,IF(B96="OPCAO",G96*Configurações!$C$23,0)),2) -> 0 | J96: =ROUNDDOWN(IF(OR(B96="ACAO",B96="ETF",B96="DIR"),G96*Configurações!$D$9,IF(B96="OPCAO",G96*Configurações!$D$23,0)),2) -> 0 | M96: =-G96+J96+K96+N96+L96+I96+H96 -> 0 | N96: =K96*$N$85 -> 0 | P96: =IF(D:D=$Q$84,E96,0) -> 0 | Q96: =IF(D:D=$Q$84,G96,0) -> 0 | R96: =R95+P96 -> 0 | S96: =IF(P96<=0,S95,IF(P96>0,((T95+Q96)/R96))) -> #DIV/0! | T96: =IF(R96=0,0,R96*S96) -> 0 | U96: =IF(D:D=$Q$84,H96+I96+J96+K96+L96+N96,0) -> 0 | V96: =IF(P96>0,T96-SUM($U$87:U96),IF(P96=0,V95,IF(P96<0,V95+(P96*W96)))) -> 0 | W96: =IF(P96<=0,W95,IF(P96>0,V96/R96)) -> #DIV/0!
B97: ACAO | G97: =E97*F97 -> 0 | H97: =ROUNDDOWN(IF(OR(B97="ACAO",B97="DIR",B97="ETF"),G97*Configurações!$B$9,IF(B97="OPCAO",G97*Configurações!$B$23,0)),2) -> 0 | I97: =ROUNDDOWN(IF(OR(B97="ACAO",B97="ETF",B97="DIR"),G97*Configurações!$C$9,IF(B97="OPCAO",G97*Configurações!$C$23,0)),2) -> 0 | J97: =ROUNDDOWN(IF(OR(B97="ACAO",B97="ETF",B97="DIR"),G97*Configurações!$D$9,IF(B97="OPCAO",G97*Configurações!$D$23,0)),2) -> 0 | M97: =-G97+J97+K97+N97+L97+I97+H97 -> 0 | N97: =K97*$N$85 -> 0 | P97: =IF(D:D=$Q$84,E97,0) -> 0 | Q97: =IF(D:D=$Q$84,G97,0) -> 0 | R97: =R96+P97 -> 0 | S97: =IF(P97<=0,S96,IF(P97>0,((T96+Q97)/R97))) -> #DIV/0! | T97: =IF(R97=0,0,R97*S97) -> 0 | U97: =IF(D:D=$Q$84,H97+I97+J97+K97+L97+N97,0) -> 0 | V97: =IF(P97>0,T97-SUM($U$87:U97),IF(P97=0,V96,IF(P97<0,V96+(P97*W97)))) -> 0 | W97: =IF(P97<=0,W96,IF(P97>0,V97/R97)) -> #DIV/0!
B98: ACAO | G98: =E98*F98 -> 0 | H98: =ROUNDDOWN(IF(OR(B98="ACAO",B98="DIR",B98="ETF"),G98*Configurações!$B$9,IF(B98="OPCAO",G98*Configurações!$B$23,0)),2) -> 0 | I98: =ROUNDDOWN(IF(OR(B98="ACAO",B98="ETF",B98="DIR"),G98*Configurações!$C$9,IF(B98="OPCAO",G98*Configurações!$C$23,0)),2) -> 0 | J98: =ROUNDDOWN(IF(OR(B98="ACAO",B98="ETF",B98="DIR"),G98*Configurações!$D$9,IF(B98="OPCAO",G98*Configurações!$D$23,0)),2) -> 0 | M98: =-G98+J98+K98+N98+L98+I98+H98 -> 0 | N98: =K98*$N$85 -> 0 | P98: =IF(D:D=$Q$84,E98,0) -> 0 | Q98: =IF(D:D=$Q$84,G98,0) -> 0 | R98: =R97+P98 -> 0 | S98: =IF(P98<=0,S97,IF(P98>0,((T97+Q98)/R98))) -> #DIV/0! | T98: =IF(R98=0,0,R98*S98) -> 0 | U98: =IF(D:D=$Q$84,H98+I98+J98+K98+L98+N98,0) -> 0 | V98: =IF(P98>0,T98-SUM($U$87:U98),IF(P98=0,V97,IF(P98<0,V97+(P98*W98)))) -> 0 | W98: =IF(P98<=0,W97,IF(P98>0,V98/R98)) -> #DIV/0! | Y98: SIMULAÇÃO DE RESULTADO E STOP
B99: ACAO | G99: =E99*F99 -> 0 | H99: =ROUNDDOWN(IF(OR(B99="ACAO",B99="DIR",B99="ETF"),G99*Configurações!$B$9,IF(B99="OPCAO",G99*Configurações!$B$23,0)),2) -> 0 | I99: =ROUNDDOWN(IF(OR(B99="ACAO",B99="ETF",B99="DIR"),G99*Configurações!$C$9,IF(B99="OPCAO",G99*Configurações!$C$23,0)),2) -> 0 | J99: =ROUNDDOWN(IF(OR(B99="ACAO",B99="ETF",B99="DIR"),G99*Configurações!$D$9,IF(B99="OPCAO",G99*Configurações!$D$23,0)),2) -> 0 | M99: =-G99+J99+K99+N99+L99+I99+H99 -> 0 | N99: =K99*$N$85 -> 0 | P99: =IF(D:D=$Q$84,E99,0) -> 0 | Q99: =IF(D:D=$Q$84,G99,0) -> 0 | R99: =R98+P99 -> 0 | S99: =IF(P99<=0,S98,IF(P99>0,((T98+Q99)/R99))) -> #DIV/0! | T99: =IF(R99=0,0,R99*S99) -> 0 | U99: =IF(D:D=$Q$84,H99+I99+J99+K99+L99+N99,0) -> 0 | V99: =IF(P99>0,T99-SUM($U$87:U99),IF(P99=0,V98,IF(P99<0,V98+(P99*W99)))) -> 0 | W99: =IF(P99<=0,W98,IF(P99>0,V99/R99)) -> #DIV/0!
B100: ACAO | G100: =E100*F100 -> 0 | H100: =ROUNDDOWN(IF(OR(B100="ACAO",B100="DIR",B100="ETF"),G100*Configurações!$B$9,IF(B100="OPCAO",G100*Configurações!$B$23,0)),2) -> 0 | I100: =ROUNDDOWN(IF(OR(B100="ACAO",B100="ETF",B100="DIR"),G100*Configurações!$C$9,IF(B100="OPCAO",G100*Configurações!$C$23,0)),2) -> 0 | J100: =ROUNDDOWN(IF(OR(B100="ACAO",B100="ETF",B100="DIR"),G100*Configurações!$D$9,IF(B100="OPCAO",G100*Configurações!$D$23,0)),2) -> 0 | M100: =-G100+J100+K100+N100+L100+I100+H100 -> 0 | N100: =K100*$N$85 -> 0 | P100: =IF(D:D=$Q$84,E100,0) -> 0 | Q100: =IF(D:D=$Q$84,G100,0) -> 0 | R100: =R99+P100 -> 0 | S100: =IF(P100<=0,S99,IF(P100>0,((T99+Q100)/R100))) -> #DIV/0! | T100: =IF(R100=0,0,R100*S100) -> 0 | U100: =IF(D:D=$Q$84,H100+I100+J100+K100+L100+N100,0) -> 0 | V100: =IF(P100>0,T100-SUM($U$87:U100),IF(P100=0,V99,IF(P100<0,V99+(P100*W100)))) -> 0 | W100: =IF(P100<=0,W99,IF(P100>0,V100/R100)) -> #DIV/0!
B101: ACAO | G101: =E101*F101 -> 0 | H101: =ROUNDDOWN(IF(OR(B101="ACAO",B101="DIR",B101="ETF"),G101*Configurações!$B$9,IF(B101="OPCAO",G101*Configurações!$B$23,0)),2) -> 0 | I101: =ROUNDDOWN(IF(OR(B101="ACAO",B101="ETF",B101="DIR"),G101*Configurações!$C$9,IF(B101="OPCAO",G101*Configurações!$C$23,0)),2) -> 0 | J101: =ROUNDDOWN(IF(OR(B101="ACAO",B101="ETF",B101="DIR"),G101*Configurações!$D$9,IF(B101="OPCAO",G101*Configurações!$D$23,0)),2) -> 0 | M101: =-G101+J101+K101+N101+L101+I101+H101 -> 0 | N101: =K101*$N$85 -> 0 | P101: =IF(D:D=$Q$84,E101,0) -> 0 | Q101: =IF(D:D=$Q$84,G101,0) -> 0 | R101: =R100+P101 -> 0 | S101: =IF(P101<=0,S100,IF(P101>0,((T100+Q101)/R101))) -> #DIV/0! | T101: =IF(R101=0,0,R101*S101) -> 0 | U101: =IF(D:D=$Q$84,H101+I101+J101+K101+L101+N101,0) -> 0 | V101: =IF(P101>0,T101-SUM($U$87:U101),IF(P101=0,V100,IF(P101<0,V100+(P101*W101)))) -> 0 | W101: =IF(P101<=0,W100,IF(P101>0,V101/R101)) -> #DIV/0! | Y101: Cotação atual do ativo
B102: ACAO | G102: =E102*F102 -> 0 | H102: =ROUNDDOWN(IF(OR(B102="ACAO",B102="DIR",B102="ETF"),G102*Configurações!$B$9,IF(B102="OPCAO",G102*Configurações!$B$23,0)),2) -> 0 | I102: =ROUNDDOWN(IF(OR(B102="ACAO",B102="ETF",B102="DIR"),G102*Configurações!$C$9,IF(B102="OPCAO",G102*Configurações!$C$23,0)),2) -> 0 | J102: =ROUNDDOWN(IF(OR(B102="ACAO",B102="ETF",B102="DIR"),G102*Configurações!$D$9,IF(B102="OPCAO",G102*Configurações!$D$23,0)),2) -> 0 | M102: =-G102+J102+K102+N102+L102+I102+H102 -> 0 | N102: =K102*$N$85 -> 0 | P102: =IF(D:D=$Q$84,E102,0) -> 0 | Q102: =IF(D:D=$Q$84,G102,0) -> 0 | R102: =R101+P102 -> 0 | S102: =IF(P102<=0,S101,IF(P102>0,((T101+Q102)/R102))) -> #DIV/0! | T102: =IF(R102=0,0,R102*S102) -> 0 | U102: =IF(D:D=$Q$84,H102+I102+J102+K102+L102+N102,0) -> 0 | V102: =IF(P102>0,T102-SUM($U$87:U102),IF(P102=0,V101,IF(P102<0,V101+(P102*W102)))) -> 0 | W102: =IF(P102<=0,W101,IF(P102>0,V102/R102)) -> #DIV/0!
B103: ACAO | G103: =E103*F103 -> 0 | H103: =ROUNDDOWN(IF(OR(B103="ACAO",B103="DIR",B103="ETF"),G103*Configurações!$B$9,IF(B103="OPCAO",G103*Configurações!$B$23,0)),2) -> 0 | I103: =ROUNDDOWN(IF(OR(B103="ACAO",B103="ETF",B103="DIR"),G103*Configurações!$C$9,IF(B103="OPCAO",G103*Configurações!$C$23,0)),2) -> 0 | J103: =ROUNDDOWN(IF(OR(B103="ACAO",B103="ETF",B103="DIR"),G103*Configurações!$D$9,IF(B103="OPCAO",G103*Configurações!$D$23,0)),2) -> 0 | M103: =-G103+J103+K103+N103+L103+I103+H103 -> 0 | N103: =K103*$N$85 -> 0 | P103: =IF(D:D=$Q$84,E103,0) -> 0 | Q103: =IF(D:D=$Q$84,G103,0) -> 0 | R103: =R102+P103 -> 0 | S103: =IF(P103<=0,S102,IF(P103>0,((T102+Q103)/R103))) -> #DIV/0! | T103: =IF(R103=0,0,R103*S103) -> 0 | U103: =IF(D:D=$Q$84,H103+I103+J103+K103+L103+N103,0) -> 0 | V103: =IF(P103>0,T103-SUM($U$87:U103),IF(P103=0,V102,IF(P103<0,V102+(P103*W103)))) -> 0 | W103: =IF(P103<=0,W102,IF(P103>0,V103/R103)) -> #DIV/0!
B104: ACAO | G104: =E104*F104 -> 0 | H104: =ROUNDDOWN(IF(OR(B104="ACAO",B104="DIR",B104="ETF"),G104*Configurações!$B$9,IF(B104="OPCAO",G104*Configurações!$B$23,0)),2) -> 0 | I104: =ROUNDDOWN(IF(OR(B104="ACAO",B104="ETF",B104="DIR"),G104*Configurações!$C$9,IF(B104="OPCAO",G104*Configurações!$C$23,0)),2) -> 0 | J104: =ROUNDDOWN(IF(OR(B104="ACAO",B104="ETF",B104="DIR"),G104*Configurações!$D$9,IF(B104="OPCAO",G104*Configurações!$D$23,0)),2) -> 0 | M104: =-G104+J104+K104+N104+L104+I104+H104 -> 0 | N104: =K104*$N$85 -> 0 | P104: =IF(D:D=$Q$84,E104,0) -> 0 | Q104: =IF(D:D=$Q$84,G104,0) -> 0 | R104: =R103+P104 -> 0 | S104: =IF(P104<=0,S103,IF(P104>0,((T103+Q104)/R104))) -> #DIV/0! | T104: =IF(R104=0,0,R104*S104) -> 0 | U104: =IF(D:D=$Q$84,H104+I104+J104+K104+L104+N104,0) -> 0 | V104: =IF(P104>0,T104-SUM($U$87:U104),IF(P104=0,V103,IF(P104<0,V103+(P104*W104)))) -> 0 | W104: =IF(P104<=0,W103,IF(P104>0,V104/R104)) -> #DIV/0! | Y104: Resultado atual da operação ( R$ ) | AA104: =IF(AA86="","-",(AA94-AA101)*AA88) -> - | AC104: CAMPO AUTOMÁTICO
B105: ACAO | G105: =E105*F105 -> 0 | H105: =ROUNDDOWN(IF(OR(B105="ACAO",B105="DIR",B105="ETF"),G105*Configurações!$B$9,IF(B105="OPCAO",G105*Configurações!$B$23,0)),2) -> 0 | I105: =ROUNDDOWN(IF(OR(B105="ACAO",B105="ETF",B105="DIR"),G105*Configurações!$C$9,IF(B105="OPCAO",G105*Configurações!$C$23,0)),2) -> 0 | J105: =ROUNDDOWN(IF(OR(B105="ACAO",B105="ETF",B105="DIR"),G105*Configurações!$D$9,IF(B105="OPCAO",G105*Configurações!$D$23,0)),2) -> 0 | M105: =-G105+J105+K105+N105+L105+I105+H105 -> 0 | N105: =K105*$N$85 -> 0 | P105: =IF(D:D=$Q$84,E105,0) -> 0 | Q105: =IF(D:D=$Q$84,G105,0) -> 0 | R105: =R104+P105 -> 0 | S105: =IF(P105<=0,S104,IF(P105>0,((T104+Q105)/R105))) -> #DIV/0! | T105: =IF(R105=0,0,R105*S105) -> 0 | U105: =IF(D:D=$Q$84,H105+I105+J105+K105+L105+N105,0) -> 0 | V105: =IF(P105>0,T105-SUM($U$87:U105),IF(P105=0,V104,IF(P105<0,V104+(P105*W105)))) -> 0 | W105: =IF(P105<=0,W104,IF(P105>0,V105/R105)) -> #DIV/0!
B106: ACAO | G106: =E106*F106 -> 0 | H106: =ROUNDDOWN(IF(OR(B106="ACAO",B106="DIR",B106="ETF"),G106*Configurações!$B$9,IF(B106="OPCAO",G106*Configurações!$B$23,0)),2) -> 0 | I106: =ROUNDDOWN(IF(OR(B106="ACAO",B106="ETF",B106="DIR"),G106*Configurações!$C$9,IF(B106="OPCAO",G106*Configurações!$C$23,0)),2) -> 0 | J106: =ROUNDDOWN(IF(OR(B106="ACAO",B106="ETF",B106="DIR"),G106*Configurações!$D$9,IF(B106="OPCAO",G106*Configurações!$D$23,0)),2) -> 0 | M106: =-G106+J106+K106+N106+L106+I106+H106 -> 0 | N106: =K106*$N$85 -> 0 | P106: =IF(D:D=$Q$84,E106,0) -> 0 | Q106: =IF(D:D=$Q$84,G106,0) -> 0 | R106: =R105+P106 -> 0 | S106: =IF(P106<=0,S105,IF(P106>0,((T105+Q106)/R106))) -> #DIV/0! | T106: =IF(R106=0,0,R106*S106) -> 0 | U106: =IF(D:D=$Q$84,H106+I106+J106+K106+L106+N106,0) -> 0 | V106: =IF(P106>0,T106-SUM($U$87:U106),IF(P106=0,V105,IF(P106<0,V105+(P106*W106)))) -> 0 | W106: =IF(P106<=0,W105,IF(P106>0,V106/R106)) -> #DIV/0!
B107: ACAO | G107: =E107*F107 -> 0 | H107: =ROUNDDOWN(IF(OR(B107="ACAO",B107="DIR",B107="ETF"),G107*Configurações!$B$9,IF(B107="OPCAO",G107*Configurações!$B$23,0)),2) -> 0 | I107: =ROUNDDOWN(IF(OR(B107="ACAO",B107="ETF",B107="DIR"),G107*Configurações!$C$9,IF(B107="OPCAO",G107*Configurações!$C$23,0)),2) -> 0 | J107: =ROUNDDOWN(IF(OR(B107="ACAO",B107="ETF",B107="DIR"),G107*Configurações!$D$9,IF(B107="OPCAO",G107*Configurações!$D$23,0)),2) -> 0 | M107: =-G107+J107+K107+N107+L107+I107+H107 -> 0 | N107: =K107*$N$85 -> 0 | P107: =IF(D:D=$Q$84,E107,0) -> 0 | Q107: =IF(D:D=$Q$84,G107,0) -> 0 | R107: =R106+P107 -> 0 | S107: =IF(P107<=0,S106,IF(P107>0,((T106+Q107)/R107))) -> #DIV/0! | T107: =IF(R107=0,0,R107*S107) -> 0 | U107: =IF(D:D=$Q$84,H107+I107+J107+K107+L107+N107,0) -> 0 | V107: =IF(P107>0,T107-SUM($U$87:U107),IF(P107=0,V106,IF(P107<0,V106+(P107*W107)))) -> 0 | W107: =IF(P107<=0,W106,IF(P107>0,V107/R107)) -> #DIV/0! | Y107: Resultado atual da operação ( % ) | AA107: =IF(AA86="","-",(AA94-AA101)/AA101) -> - | AC107: CAMPO AUTOMÁTICO
B108: ACAO | G108: =E108*F108 -> 0 | H108: =ROUNDDOWN(IF(OR(B108="ACAO",B108="DIR",B108="ETF"),G108*Configurações!$B$9,IF(B108="OPCAO",G108*Configurações!$B$23,0)),2) -> 0 | I108: =ROUNDDOWN(IF(OR(B108="ACAO",B108="ETF",B108="DIR"),G108*Configurações!$C$9,IF(B108="OPCAO",G108*Configurações!$C$23,0)),2) -> 0 | J108: =ROUNDDOWN(IF(OR(B108="ACAO",B108="ETF",B108="DIR"),G108*Configurações!$D$9,IF(B108="OPCAO",G108*Configurações!$D$23,0)),2) -> 0 | M108: =-G108+J108+K108+N108+L108+I108+H108 -> 0 | N108: =K108*$N$85 -> 0 | P108: =IF(D:D=$Q$84,E108,0) -> 0 | Q108: =IF(D:D=$Q$84,G108,0) -> 0 | R108: =R107+P108 -> 0 | S108: =IF(P108<=0,S107,IF(P108>0,((T107+Q108)/R108))) -> #DIV/0! | T108: =IF(R108=0,0,R108*S108) -> 0 | U108: =IF(D:D=$Q$84,H108+I108+J108+K108+L108+N108,0) -> 0 | V108: =IF(P108>0,T108-SUM($U$87:U108),IF(P108=0,V107,IF(P108<0,V107+(P108*W108)))) -> 0 | W108: =IF(P108<=0,W107,IF(P108>0,V108/R108)) -> #DIV/0!
B109: ACAO | G109: =E109*F109 -> 0 | H109: =ROUNDDOWN(IF(OR(B109="ACAO",B109="DIR",B109="ETF"),G109*Configurações!$B$9,IF(B109="OPCAO",G109*Configurações!$B$23,0)),2) -> 0 | I109: =ROUNDDOWN(IF(OR(B109="ACAO",B109="ETF",B109="DIR"),G109*Configurações!$C$9,IF(B109="OPCAO",G109*Configurações!$C$23,0)),2) -> 0 | J109: =ROUNDDOWN(IF(OR(B109="ACAO",B109="ETF",B109="DIR"),G109*Configurações!$D$9,IF(B109="OPCAO",G109*Configurações!$D$23,0)),2) -> 0 | M109: =-G109+J109+K109+N109+L109+I109+H109 -> 0 | N109: =K109*$N$85 -> 0 | P109: =IF(D:D=$Q$84,E109,0) -> 0 | Q109: =IF(D:D=$Q$84,G109,0) -> 0 | R109: =R108+P109 -> 0 | S109: =IF(P109<=0,S108,IF(P109>0,((T108+Q109)/R109))) -> #DIV/0! | T109: =IF(R109=0,0,R109*S109) -> 0 | U109: =IF(D:D=$Q$84,H109+I109+J109+K109+L109+N109,0) -> 0 | V109: =IF(P109>0,T109-SUM($U$87:U109),IF(P109=0,V108,IF(P109<0,V108+(P109*W109)))) -> 0 | W109: =IF(P109<=0,W108,IF(P109>0,V109/R109)) -> #DIV/0!
B110: ACAO | G110: =E110*F110 -> 0 | H110: =ROUNDDOWN(IF(OR(B110="ACAO",B110="DIR",B110="ETF"),G110*Configurações!$B$9,IF(B110="OPCAO",G110*Configurações!$B$23,0)),2) -> 0 | I110: =ROUNDDOWN(IF(OR(B110="ACAO",B110="ETF",B110="DIR"),G110*Configurações!$C$9,IF(B110="OPCAO",G110*Configurações!$C$23,0)),2) -> 0 | J110: =ROUNDDOWN(IF(OR(B110="ACAO",B110="ETF",B110="DIR"),G110*Configurações!$D$9,IF(B110="OPCAO",G110*Configurações!$D$23,0)),2) -> 0 | M110: =-G110+J110+K110+N110+L110+I110+H110 -> 0 | N110: =K110*$N$85 -> 0 | P110: =IF(D:D=$Q$84,E110,0) -> 0 | Q110: =IF(D:D=$Q$84,G110,0) -> 0 | R110: =R109+P110 -> 0 | S110: =IF(P110<=0,S109,IF(P110>0,((T109+Q110)/R110))) -> #DIV/0! | T110: =IF(R110=0,0,R110*S110) -> 0 | U110: =IF(D:D=$Q$84,H110+I110+J110+K110+L110+N110,0) -> 0 | V110: =IF(P110>0,T110-SUM($U$87:U110),IF(P110=0,V109,IF(P110<0,V109+(P110*W110)))) -> 0 | W110: =IF(P110<=0,W109,IF(P110>0,V110/R110)) -> #DIV/0! | Y110: Stop
B111: ACAO | G111: =E111*F111 -> 0 | H111: =ROUNDDOWN(IF(OR(B111="ACAO",B111="DIR",B111="ETF"),G111*Configurações!$B$9,IF(B111="OPCAO",G111*Configurações!$B$23,0)),2) -> 0 | I111: =ROUNDDOWN(IF(OR(B111="ACAO",B111="ETF",B111="DIR"),G111*Configurações!$C$9,IF(B111="OPCAO",G111*Configurações!$C$23,0)),2) -> 0 | J111: =ROUNDDOWN(IF(OR(B111="ACAO",B111="ETF",B111="DIR"),G111*Configurações!$D$9,IF(B111="OPCAO",G111*Configurações!$D$23,0)),2) -> 0 | M111: =-G111+J111+K111+N111+L111+I111+H111 -> 0 | N111: =K111*$N$85 -> 0 | P111: =IF(D:D=$Q$84,E111,0) -> 0 | Q111: =IF(D:D=$Q$84,G111,0) -> 0 | R111: =R110+P111 -> 0 | S111: =IF(P111<=0,S110,IF(P111>0,((T110+Q111)/R111))) -> #DIV/0! | T111: =IF(R111=0,0,R111*S111) -> 0 | U111: =IF(D:D=$Q$84,H111+I111+J111+K111+L111+N111,0) -> 0 | V111: =IF(P111>0,T111-SUM($U$87:U111),IF(P111=0,V110,IF(P111<0,V110+(P111*W111)))) -> 0 | W111: =IF(P111<=0,W110,IF(P111>0,V111/R111)) -> #DIV/0!
B112: ACAO | G112: =E112*F112 -> 0 | H112: =ROUNDDOWN(IF(OR(B112="ACAO",B112="DIR",B112="ETF"),G112*Configurações!$B$9,IF(B112="OPCAO",G112*Configurações!$B$23,0)),2) -> 0 | I112: =ROUNDDOWN(IF(OR(B112="ACAO",B112="ETF",B112="DIR"),G112*Configurações!$C$9,IF(B112="OPCAO",G112*Configurações!$C$23,0)),2) -> 0 | J112: =ROUNDDOWN(IF(OR(B112="ACAO",B112="ETF",B112="DIR"),G112*Configurações!$D$9,IF(B112="OPCAO",G112*Configurações!$D$23,0)),2) -> 0 | M112: =-G112+J112+K112+N112+L112+I112+H112 -> 0 | N112: =K112*$N$85 -> 0 | P112: =IF(D:D=$Q$84,E112,0) -> 0 | Q112: =IF(D:D=$Q$84,G112,0) -> 0 | R112: =R111+P112 -> 0 | S112: =IF(P112<=0,S111,IF(P112>0,((T111+Q112)/R112))) -> #DIV/0! | T112: =IF(R112=0,0,R112*S112) -> 0 | U112: =IF(D:D=$Q$84,H112+I112+J112+K112+L112+N112,0) -> 0 | V112: =IF(P112>0,T112-SUM($U$87:U112),IF(P112=0,V111,IF(P112<0,V111+(P112*W112)))) -> 0 | W112: =IF(P112<=0,W111,IF(P112>0,V112/R112)) -> #DIV/0!
B113: ACAO | G113: =E113*F113 -> 0 | H113: =ROUNDDOWN(IF(OR(B113="ACAO",B113="DIR",B113="ETF"),G113*Configurações!$B$9,IF(B113="OPCAO",G113*Configurações!$B$23,0)),2) -> 0 | I113: =ROUNDDOWN(IF(OR(B113="ACAO",B113="ETF",B113="DIR"),G113*Configurações!$C$9,IF(B113="OPCAO",G113*Configurações!$C$23,0)),2) -> 0 | J113: =ROUNDDOWN(IF(OR(B113="ACAO",B113="ETF",B113="DIR"),G113*Configurações!$D$9,IF(B113="OPCAO",G113*Configurações!$D$23,0)),2) -> 0 | M113: =-G113+J113+K113+N113+L113+I113+H113 -> 0 | N113: =K113*$N$85 -> 0 | P113: =IF(D:D=$Q$84,E113,0) -> 0 | Q113: =IF(D:D=$Q$84,G113,0) -> 0 | R113: =R112+P113 -> 0 | S113: =IF(P113<=0,S112,IF(P113>0,((T112+Q113)/R113))) -> #DIV/0! | T113: =IF(R113=0,0,R113*S113) -> 0 | U113: =IF(D:D=$Q$84,H113+I113+J113+K113+L113+N113,0) -> 0 | V113: =IF(P113>0,T113-SUM($U$87:U113),IF(P113=0,V112,IF(P113<0,V112+(P113*W113)))) -> 0 | W113: =IF(P113<=0,W112,IF(P113>0,V113/R113)) -> #DIV/0! | Y113: Resultado se acionado Stop | AA113: =IF(AA86="","-",(AA94-AA110)*AA88) -> - | AC113: CAMPO AUTOMÁTICO
B114: ACAO | G114: =E114*F114 -> 0 | H114: =ROUNDDOWN(IF(OR(B114="ACAO",B114="DIR",B114="ETF"),G114*Configurações!$B$9,IF(B114="OPCAO",G114*Configurações!$B$23,0)),2) -> 0 | I114: =ROUNDDOWN(IF(OR(B114="ACAO",B114="ETF",B114="DIR"),G114*Configurações!$C$9,IF(B114="OPCAO",G114*Configurações!$C$23,0)),2) -> 0 | J114: =ROUNDDOWN(IF(OR(B114="ACAO",B114="ETF",B114="DIR"),G114*Configurações!$D$9,IF(B114="OPCAO",G114*Configurações!$D$23,0)),2) -> 0 | M114: =-G114+J114+K114+N114+L114+I114+H114 -> 0 | N114: =K114*$N$85 -> 0 | P114: =IF(D:D=$Q$84,E114,0) -> 0 | Q114: =IF(D:D=$Q$84,G114,0) -> 0 | R114: =R113+P114 -> 0 | S114: =IF(P114<=0,S113,IF(P114>0,((T113+Q114)/R114))) -> #DIV/0! | T114: =IF(R114=0,0,R114*S114) -> 0 | U114: =IF(D:D=$Q$84,H114+I114+J114+K114+L114+N114,0) -> 0 | V114: =IF(P114>0,T114-SUM($U$87:U114),IF(P114=0,V113,IF(P114<0,V113+(P114*W114)))) -> 0 | W114: =IF(P114<=0,W113,IF(P114>0,V114/R114)) -> #DIV/0!
B115: ACAO | G115: =E115*F115 -> 0 | H115: =ROUNDDOWN(IF(OR(B115="ACAO",B115="DIR",B115="ETF"),G115*Configurações!$B$9,IF(B115="OPCAO",G115*Configurações!$B$23,0)),2) -> 0 | I115: =ROUNDDOWN(IF(OR(B115="ACAO",B115="ETF",B115="DIR"),G115*Configurações!$C$9,IF(B115="OPCAO",G115*Configurações!$C$23,0)),2) -> 0 | J115: =ROUNDDOWN(IF(OR(B115="ACAO",B115="ETF",B115="DIR"),G115*Configurações!$D$9,IF(B115="OPCAO",G115*Configurações!$D$23,0)),2) -> 0 | M115: =-G115+J115+K115+N115+L115+I115+H115 -> 0 | N115: =K115*$N$85 -> 0 | P115: =IF(D:D=$Q$84,E115,0) -> 0 | Q115: =IF(D:D=$Q$84,G115,0) -> 0 | R115: =R114+P115 -> 0 | S115: =IF(P115<=0,S114,IF(P115>0,((T114+Q115)/R115))) -> #DIV/0! | T115: =IF(R115=0,0,R115*S115) -> 0 | U115: =IF(D:D=$Q$84,H115+I115+J115+K115+L115+N115,0) -> 0 | V115: =IF(P115>0,T115-SUM($U$87:U115),IF(P115=0,V114,IF(P115<0,V114+(P115*W115)))) -> 0 | W115: =IF(P115<=0,W114,IF(P115>0,V115/R115)) -> #DIV/0!
B116: ACAO | G116: =E116*F116 -> 0 | H116: =ROUNDDOWN(IF(OR(B116="ACAO",B116="DIR",B116="ETF"),G116*Configurações!$B$9,IF(B116="OPCAO",G116*Configurações!$B$23,0)),2) -> 0 | I116: =ROUNDDOWN(IF(OR(B116="ACAO",B116="ETF",B116="DIR"),G116*Configurações!$C$9,IF(B116="OPCAO",G116*Configurações!$C$23,0)),2) -> 0 | J116: =ROUNDDOWN(IF(OR(B116="ACAO",B116="ETF",B116="DIR"),G116*Configurações!$D$9,IF(B116="OPCAO",G116*Configurações!$D$23,0)),2) -> 0 | M116: =-G116+J116+K116+N116+L116+I116+H116 -> 0 | N116: =K116*$N$85 -> 0 | P116: =IF(D:D=$Q$84,E116,0) -> 0 | Q116: =IF(D:D=$Q$84,G116,0) -> 0 | R116: =R115+P116 -> 0 | S116: =IF(P116<=0,S115,IF(P116>0,((T115+Q116)/R116))) -> #DIV/0! | T116: =IF(R116=0,0,R116*S116) -> 0 | U116: =IF(D:D=$Q$84,H116+I116+J116+K116+L116+N116,0) -> 0 | V116: =IF(P116>0,T116-SUM($U$87:U116),IF(P116=0,V115,IF(P116<0,V115+(P116*W116)))) -> 0 | W116: =IF(P116<=0,W115,IF(P116>0,V116/R116)) -> #DIV/0!
B117: ACAO | G117: =E117*F117 -> 0 | H117: =ROUNDDOWN(IF(OR(B117="ACAO",B117="DIR",B117="ETF"),G117*Configurações!$B$9,IF(B117="OPCAO",G117*Configurações!$B$23,0)),2) -> 0 | I117: =ROUNDDOWN(IF(OR(B117="ACAO",B117="ETF",B117="DIR"),G117*Configurações!$C$9,IF(B117="OPCAO",G117*Configurações!$C$23,0)),2) -> 0 | J117: =ROUNDDOWN(IF(OR(B117="ACAO",B117="ETF",B117="DIR"),G117*Configurações!$D$9,IF(B117="OPCAO",G117*Configurações!$D$23,0)),2) -> 0 | M117: =-G117+J117+K117+N117+L117+I117+H117 -> 0 | N117: =K117*$N$85 -> 0 | P117: =IF(D:D=$Q$84,E117,0) -> 0 | Q117: =IF(D:D=$Q$84,G117,0) -> 0 | R117: =R116+P117 -> 0 | S117: =IF(P117<=0,S116,IF(P117>0,((T116+Q117)/R117))) -> #DIV/0! | T117: =IF(R117=0,0,R117*S117) -> 0 | U117: =IF(D:D=$Q$84,H117+I117+J117+K117+L117+N117,0) -> 0 | V117: =IF(P117>0,T117-SUM($U$87:U117),IF(P117=0,V116,IF(P117<0,V116+(P117*W117)))) -> 0 | W117: =IF(P117<=0,W116,IF(P117>0,V117/R117)) -> #DIV/0!
B118: ACAO | G118: =E118*F118 -> 0 | H118: =ROUNDDOWN(IF(OR(B118="ACAO",B118="DIR",B118="ETF"),G118*Configurações!$B$9,IF(B118="OPCAO",G118*Configurações!$B$23,0)),2) -> 0 | I118: =ROUNDDOWN(IF(OR(B118="ACAO",B118="ETF",B118="DIR"),G118*Configurações!$C$9,IF(B118="OPCAO",G118*Configurações!$C$23,0)),2) -> 0 | J118: =ROUNDDOWN(IF(OR(B118="ACAO",B118="ETF",B118="DIR"),G118*Configurações!$D$9,IF(B118="OPCAO",G118*Configurações!$D$23,0)),2) -> 0 | M118: =-G118+J118+K118+N118+L118+I118+H118 -> 0 | N118: =K118*$N$85 -> 0 | P118: =IF(D:D=$Q$84,E118,0) -> 0 | Q118: =IF(D:D=$Q$84,G118,0) -> 0 | R118: =R117+P118 -> 0 | S118: =IF(P118<=0,S117,IF(P118>0,((T117+Q118)/R118))) -> #DIV/0! | T118: =IF(R118=0,0,R118*S118) -> 0 | U118: =IF(D:D=$Q$84,H118+I118+J118+K118+L118+N118,0) -> 0 | V118: =IF(P118>0,T118-SUM($U$87:U118),IF(P118=0,V117,IF(P118<0,V117+(P118*W118)))) -> 0 | W118: =IF(P118<=0,W117,IF(P118>0,V118/R118)) -> #DIV/0!
B119: ACAO | G119: =E119*F119 -> 0 | H119: =ROUNDDOWN(IF(OR(B119="ACAO",B119="DIR",B119="ETF"),G119*Configurações!$B$9,IF(B119="OPCAO",G119*Configurações!$B$23,0)),2) -> 0 | I119: =ROUNDDOWN(IF(OR(B119="ACAO",B119="ETF",B119="DIR"),G119*Configurações!$C$9,IF(B119="OPCAO",G119*Configurações!$C$23,0)),2) -> 0 | J119: =ROUNDDOWN(IF(OR(B119="ACAO",B119="ETF",B119="DIR"),G119*Configurações!$D$9,IF(B119="OPCAO",G119*Configurações!$D$23,0)),2) -> 0 | M119: =-G119+J119+K119+N119+L119+I119+H119 -> 0 | N119: =K119*$N$85 -> 0 | P119: =IF(D:D=$Q$84,E119,0) -> 0 | Q119: =IF(D:D=$Q$84,G119,0) -> 0 | R119: =R118+P119 -> 0 | S119: =IF(P119<=0,S118,IF(P119>0,((T118+Q119)/R119))) -> #DIV/0! | T119: =IF(R119=0,0,R119*S119) -> 0 | U119: =IF(D:D=$Q$84,H119+I119+J119+K119+L119+N119,0) -> 0 | V119: =IF(P119>0,T119-SUM($U$87:U119),IF(P119=0,V118,IF(P119<0,V118+(P119*W119)))) -> 0 | W119: =IF(P119<=0,W118,IF(P119>0,V119/R119)) -> #DIV/0!
B120: ACAO | G120: =E120*F120 -> 0 | H120: =ROUNDDOWN(IF(OR(B120="ACAO",B120="DIR",B120="ETF"),G120*Configurações!$B$9,IF(B120="OPCAO",G120*Configurações!$B$23,0)),2) -> 0 | I120: =ROUNDDOWN(IF(OR(B120="ACAO",B120="ETF",B120="DIR"),G120*Configurações!$C$9,IF(B120="OPCAO",G120*Configurações!$C$23,0)),2) -> 0 | J120: =ROUNDDOWN(IF(OR(B120="ACAO",B120="ETF",B120="DIR"),G120*Configurações!$D$9,IF(B120="OPCAO",G120*Configurações!$D$23,0)),2) -> 0 | M120: =-G120+J120+K120+N120+L120+I120+H120 -> 0 | N120: =K120*$N$85 -> 0 | P120: =IF(D:D=$Q$84,E120,0) -> 0 | Q120: =IF(D:D=$Q$84,G120,0) -> 0 | R120: =R119+P120 -> 0 | S120: =IF(P120<=0,S119,IF(P120>0,((T119+Q120)/R120))) -> #DIV/0! | T120: =IF(R120=0,0,R120*S120) -> 0 | U120: =IF(D:D=$Q$84,H120+I120+J120+K120+L120+N120,0) -> 0 | V120: =IF(P120>0,T120-SUM($U$87:U120),IF(P120=0,V119,IF(P120<0,V119+(P120*W120)))) -> 0 | W120: =IF(P120<=0,W119,IF(P120>0,V120/R120)) -> #DIV/0!
B121: ACAO | G121: =E121*F121 -> 0 | H121: =ROUNDDOWN(IF(OR(B121="ACAO",B121="DIR",B121="ETF"),G121*Configurações!$B$9,IF(B121="OPCAO",G121*Configurações!$B$23,0)),2) -> 0 | I121: =ROUNDDOWN(IF(OR(B121="ACAO",B121="ETF",B121="DIR"),G121*Configurações!$C$9,IF(B121="OPCAO",G121*Configurações!$C$23,0)),2) -> 0 | J121: =ROUNDDOWN(IF(OR(B121="ACAO",B121="ETF",B121="DIR"),G121*Configurações!$D$9,IF(B121="OPCAO",G121*Configurações!$D$23,0)),2) -> 0 | M121: =-G121+J121+K121+N121+L121+I121+H121 -> 0 | N121: =K121*$N$85 -> 0 | P121: =IF(D:D=$Q$84,E121,0) -> 0 | Q121: =IF(D:D=$Q$84,G121,0) -> 0 | R121: =R120+P121 -> 0 | S121: =IF(P121<=0,S120,IF(P121>0,((T120+Q121)/R121))) -> #DIV/0! | T121: =IF(R121=0,0,R121*S121) -> 0 | U121: =IF(D:D=$Q$84,H121+I121+J121+K121+L121+N121,0) -> 0 | V121: =IF(P121>0,T121-SUM($U$87:U121),IF(P121=0,V120,IF(P121<0,V120+(P121*W121)))) -> 0 | W121: =IF(P121<=0,W120,IF(P121>0,V121/R121)) -> #DIV/0!
B122: ACAO | G122: =E122*F122 -> 0 | H122: =ROUNDDOWN(IF(OR(B122="ACAO",B122="DIR",B122="ETF"),G122*Configurações!$B$9,IF(B122="OPCAO",G122*Configurações!$B$23,0)),2) -> 0 | I122: =ROUNDDOWN(IF(OR(B122="ACAO",B122="ETF",B122="DIR"),G122*Configurações!$C$9,IF(B122="OPCAO",G122*Configurações!$C$23,0)),2) -> 0 | J122: =ROUNDDOWN(IF(OR(B122="ACAO",B122="ETF",B122="DIR"),G122*Configurações!$D$9,IF(B122="OPCAO",G122*Configurações!$D$23,0)),2) -> 0 | M122: =-G122+J122+K122+N122+L122+I122+H122 -> 0 | N122: =K122*$N$85 -> 0 | P122: =IF(D:D=$Q$84,E122,0) -> 0 | Q122: =IF(D:D=$Q$84,G122,0) -> 0 | R122: =R121+P122 -> 0 | S122: =IF(P122<=0,S121,IF(P122>0,((T121+Q122)/R122))) -> #DIV/0! | T122: =IF(R122=0,0,R122*S122) -> 0 | U122: =IF(D:D=$Q$84,H122+I122+J122+K122+L122+N122,0) -> 0 | V122: =IF(P122>0,T122-SUM($U$87:U122),IF(P122=0,V121,IF(P122<0,V121+(P122*W122)))) -> 0 | W122: =IF(P122<=0,W121,IF(P122>0,V122/R122)) -> #DIV/0!
B123: ACAO | G123: =E123*F123 -> 0 | H123: =ROUNDDOWN(IF(OR(B123="ACAO",B123="DIR",B123="ETF"),G123*Configurações!$B$9,IF(B123="OPCAO",G123*Configurações!$B$23,0)),2) -> 0 | I123: =ROUNDDOWN(IF(OR(B123="ACAO",B123="ETF",B123="DIR"),G123*Configurações!$C$9,IF(B123="OPCAO",G123*Configurações!$C$23,0)),2) -> 0 | J123: =ROUNDDOWN(IF(OR(B123="ACAO",B123="ETF",B123="DIR"),G123*Configurações!$D$9,IF(B123="OPCAO",G123*Configurações!$D$23,0)),2) -> 0 | M123: =-G123+J123+K123+N123+L123+I123+H123 -> 0 | N123: =K123*$N$85 -> 0 | P123: =IF(D:D=$Q$84,E123,0) -> 0 | Q123: =IF(D:D=$Q$84,G123,0) -> 0 | R123: =R122+P123 -> 0 | S123: =IF(P123<=0,S122,IF(P123>0,((T122+Q123)/R123))) -> #DIV/0! | T123: =IF(R123=0,0,R123*S123) -> 0 | U123: =IF(D:D=$Q$84,H123+I123+J123+K123+L123+N123,0) -> 0 | V123: =IF(P123>0,T123-SUM($U$87:U123),IF(P123=0,V122,IF(P123<0,V122+(P123*W123)))) -> 0 | W123: =IF(P123<=0,W122,IF(P123>0,V123/R123)) -> #DIV/0!
B124: ACAO | G124: =E124*F124 -> 0 | H124: =ROUNDDOWN(IF(OR(B124="ACAO",B124="DIR",B124="ETF"),G124*Configurações!$B$9,IF(B124="OPCAO",G124*Configurações!$B$23,0)),2) -> 0 | I124: =ROUNDDOWN(IF(OR(B124="ACAO",B124="ETF",B124="DIR"),G124*Configurações!$C$9,IF(B124="OPCAO",G124*Configurações!$C$23,0)),2) -> 0 | J124: =ROUNDDOWN(IF(OR(B124="ACAO",B124="ETF",B124="DIR"),G124*Configurações!$D$9,IF(B124="OPCAO",G124*Configurações!$D$23,0)),2) -> 0 | M124: =-G124+J124+K124+N124+L124+I124+H124 -> 0 | N124: =K124*$N$85 -> 0 | P124: =IF(D:D=$Q$84,E124,0) -> 0 | Q124: =IF(D:D=$Q$84,G124,0) -> 0 | R124: =R123+P124 -> 0 | S124: =IF(P124<=0,S123,IF(P124>0,((T123+Q124)/R124))) -> #DIV/0! | T124: =IF(R124=0,0,R124*S124) -> 0 | U124: =IF(D:D=$Q$84,H124+I124+J124+K124+L124+N124,0) -> 0 | V124: =IF(P124>0,T124-SUM($U$87:U124),IF(P124=0,V123,IF(P124<0,V123+(P124*W124)))) -> 0 | W124: =IF(P124<=0,W123,IF(P124>0,V124/R124)) -> #DIV/0!
B125: ACAO | G125: =E125*F125 -> 0 | H125: =ROUNDDOWN(IF(OR(B125="ACAO",B125="DIR",B125="ETF"),G125*Configurações!$B$9,IF(B125="OPCAO",G125*Configurações!$B$23,0)),2) -> 0 | I125: =ROUNDDOWN(IF(OR(B125="ACAO",B125="ETF",B125="DIR"),G125*Configurações!$C$9,IF(B125="OPCAO",G125*Configurações!$C$23,0)),2) -> 0 | J125: =ROUNDDOWN(IF(OR(B125="ACAO",B125="ETF",B125="DIR"),G125*Configurações!$D$9,IF(B125="OPCAO",G125*Configurações!$D$23,0)),2) -> 0 | M125: =-G125+J125+K125+N125+L125+I125+H125 -> 0 | N125: =K125*$N$85 -> 0 | P125: =IF(D:D=$Q$84,E125,0) -> 0 | Q125: =IF(D:D=$Q$84,G125,0) -> 0 | R125: =R124+P125 -> 0 | S125: =IF(P125<=0,S124,IF(P125>0,((T124+Q125)/R125))) -> #DIV/0! | T125: =IF(R125=0,0,R125*S125) -> 0 | U125: =IF(D:D=$Q$84,H125+I125+J125+K125+L125+N125,0) -> 0 | V125: =IF(P125>0,T125-SUM($U$87:U125),IF(P125=0,V124,IF(P125<0,V124+(P125*W125)))) -> 0 | W125: =IF(P125<=0,W124,IF(P125>0,V125/R125)) -> #DIV/0!
... B161: ACAO | G161: =E161*F161 -> 0 | H161: =ROUNDDOWN(IF(OR(B161="ACAO",B161="DIR",B161="ETF"),G161*Configurações!$B$9,IF(B161="OPCAO",G161*Configurações!$B$23,0)),2) -> 0 | I161: =ROUNDDOWN(IF(OR(B161="ACAO",B161="ETF",B161="DIR"),G161*Configurações!$C$9,IF(B161="OPCAO",G161*Configurações!$C$23,0)),2) -> 0 | J161: =ROUNDDOWN(IF(OR(B161="ACAO",B161="ETF",B161="DIR"),G161*Configurações!$D$9,IF(B161="OPCAO",G161*Configurações!$D$23,0)),2) -> 0 | M161: =-G161+J161+K161+N161+L161+I161+H161 -> 0 | N161: =K161*$N$85 -> 0 | P161: =IF(D:D=$Q$84,E161,0) -> 0 | Q161: =IF(D:D=$Q$84,G161,0) -> 0 | R161: =R160+P161 -> 0 | S161: =IF(P161<=0,S160,IF(P161>0,((T160+Q161)/R161))) -> #DIV/0! | T161: =IF(R161=0,0,R161*S161) -> 0 | U161: =IF(D:D=$Q$84,H161+I161+J161+K161+L161+N161,0) -> 0 | V161: =IF(P161>0,T161-SUM($U$87:U161),IF(P161=0,V160,IF(P161<0,V160+(P161*W161)))) -> 0 | W161: =IF(P161<=0,W160,IF(P161>0,V161/R161)) -> #DIV/0!
B167: ACAO
B168: OPCAO
B169: ETF
B170: DIR

Sheet Proventos
B2: RELAÇÃO DE PROVENTOS E APORTES MENSAIS
B4: Ganhos JSCP | D4: =SUMIF(C9:C46,"JSCP",J9:K46) -> 0 | F4: + | G4: Ganhos Dividendos | I4: =SUMIF(C9:C46,"DIVIDENDOS",J9:K46) -> 0 | K4: = | L4: =SUM(D4,I4) -> 0
B7: ATIVO | C7: TIPO DE PROVENTO | D7: DISCRIMINAÇÃO (Nome e CNPJ da Empresa Pagadora / Outras informações) | J7: Valor | L7: Data de Pagamento | P7: BONIFICAÇÃO
P8: JSCP
C9: DIVIDENDOS | P9: DIVIDENDOS
P10: OUTROS

Sheet Configurações
B2: CONFIGURAÇÕES - TAXAS
B3: * Atualize aqui, caso necessário, as taxas de negociação (emolumentos), liquidação e registro cobradas pela B3.
B5: MERCADO DE AÇÕES - OPERAÇÕES NORMAIS
B7: TX. DE NEGOCIAÇÃO | C7: TX. DE LIQUIDAÇÃO | D7: TX. DE REGISTRO
B9: 3.34e-05 | C9: 0.000275 | D9: 0
B12: MERCADO DE AÇÕES - OPERAÇÕES DAY TRADE
B14: TX. DE NEGOCIAÇÃO | C14: TX. DE LIQUIDAÇÃO | D14: TX. DE REGISTRO
B16: 3.34e-05 | C16: 0.0002 | D16: 0
B19: MERCADO DE OPÇÕES - OPERAÇÕES NORMAIS
B21: TX. DE NEGOCIAÇÃO | C21: TX. DE LIQUIDAÇÃO | D21: TX. DE REGISTRO
B23: 0.00037 | C23: 0.000275 | D23: 0.000695
B26: MERCADO DE OPÇÕES - OPERAÇÕES DAY TRADE
B28: TX. DE NEGOCIAÇÃO | C28: TX. DE LIQUIDAÇÃO | D28: TX. DE REGISTRO
B30: 0.00013 | C30: 0.00018 | D30: 0.00014
B33: EXERCÍCIO DE OPÇÕES (LANÇAMENTO COBERTO)
B35: TX. DE NEGOCIAÇÃO | C35: TX. DE LIQUIDAÇÃO | D35: TX. DE REGISTRO
B37: 4.115e-05 | C37: 0.0002 | D37: 0
B39: * Titular da opção é cobrado conforme tarifa de operações normais com ações.
B40: * Taxas aplicadas sobre o strike da opção
B42: Onde encontrar as taxas atualizadas?
B44: CLIQUE AQUI E CONFIRA NO SITE DA B3
