Workbook
Name Concluído: 'Atividades detalhadas'!$U$1:$U$3
Name listastatus: 'Atividades detalhadas'!$U$1:$U$4
Name Status: 'Atividades detalhadas'!$U$1:$U$3
Name Statusesocial: 'Atividades detalhadas'!$U$1:$U$3

Sheet Atividades detalhadas
B1: Trabalho de Implantação do eSocial - Cliente XYZ INDUST | U1: Concluído
A2: Faturamento em 2016 - R$ 281.920.188,35 | E2: =AVERAGE(K16,K38,K56,K78,K102,K120,K138,K152,K164,K178,K191,K203,K215,K226,K251,K265,K275,K293,K306,K319,K326,K335,K343,K350,K358,K365,K373,K395,K417,K442,K458,K472,K487,K504,K523,K533,K542,K569,K600,K616,K637,K653,K663,K678,K692,K719,K728) -> 0.51818734 | G2: Concluído | H2: Atualizado em: | K2: 43068 | U2: Em andamento
A3: 1 | B3: Qualificação Cadastral | E3: Prazo da Atividade | G3: Responsável | I3: Acompanhamento | U3: Atrasado
E4: Início | F4: Fim | G4: Contabilidade | H4: Cliente | I4: Status | J4: Data conclusão | K4: % Conclusão | U4: Não Iniciado
C5: 1.1 | D5: Gerar informações do sistema para envio a Qualificação Cadastral em Lote | E5: 42919 | F5: 43084 | G5: Equipe DP | I5: Não Iniciado | J5: 42930 | K5: 0
C6: 1.2 | D6: Importar para o Sistema o arquivo retorno | E6: 42919 | F6: 43084 | G6: Equipe DP | I6: Concluído | J6: 42933 | K6: 1
C7: 1.3 | D7: Analise dos ajustes à serem realizados | E7: 42919 | F7: 43084 | G7: Equipe DP | I7: Concluído | J7: 42937 | K7: 1
C8: 1.4 | D8: Encaminhar informações para ajuste necessários | E8: 42919 | F8: 43084 | G8: Equipe DP | I8: Concluído | J8: 42940 | K8: 1
C9: 1.5 | D9: Receber informações para ajuste dos dados do Colaborador | E9: 42919 | F9: 43084 | H9: RH - Cliente | I9: Concluído | J9: 42941 | K9: 1
C10: 1.6 | D10: Solicitar o Colaborador para realizar o ajuste nos orgãos Governamentais | E10: 42919 | F10: 43084 | H10: RH - Cliente | I10: Concluído | J10: 42944 | K10: 1
C11: 1.7 | D11: Devolver as informações dos Colaboradores ajustadas | E11: 42919 | F11: 43084 | H11: RH - Cliente | I11: Concluído | J11: 42951 | K11: 1
C12: 1.8 | D12: Receber informações para ajuste dos dados do Colaborador no sistema | E12: 42919 | F12: 43084 | G12: Equipe DP | I12: Concluído | J12: 42954 | K12: 1
C13: 1.9 | D13: Corrigir as informações no sistema | E13: 42919 | F13: 43084 | G13: Equipe DP | I13: Concluído | J13: 42962 | K13: 1
C14: 1.12 | D14: Retransmitir para o eSocial (Qualif.Cadastral) | E14: 42919 | F14: 43084 | G14: Equipe DP | I14: Concluído | J14: 42965 | K14: 1
C15: 1.13 | D15: Fazer qualificação cadastral para os admitidos desta data em diante | E15: 42979 | F15: 42979 | H15: RH - Cliente | I15: Concluído | J15: 42979 | K15: 1
H16: Percentual de conclusão desta etapa: | K16: =AVERAGE(K5:K15) -> 0.90909091
A18: 2 | B18: Saneamento da Base - Análise de Impacto (Robô) | E18: Prazo da Atividade | G18: Responsável | I18: Acompanhamento
E19: Início | F19: Fim | G19: Contabilidade | H19: Cliente | I19: Status | J19: Data conclusão | K19: % Conclusão
C20: 2.1 | D20: Instalação do "Robô" para realizar Análise de Impacto das informações do eSocial | E20: 42919 | F20: 43084 | G20: Equipe T.I. | I20: Concluído | J20: 42923 | K20: 1
C21: 2.2 | D21: Treinamento da ferramenta "Robô" para equipe do DP | E21: 42919 | F21: 43084 | G21: Equipe T.I. | I21: Concluído | J21: 42926 | K21: 1
C22: 2.3 | D22: Multiplicar Treinamento da Ferramenta "Robô" a toda equipe DP | E22: 42919 | F22: 43084 | G22: Gestor DP | I22: Concluído | J22: 42927 | K22: 1
C23: 2.4 | D23: Esclarecimento de dúvidas de utilização da ferramenta "Robo" para equipe DP | E23: 42919 | F23: 43084 | G23: Gestor DP | I23: Concluído | J23: 42930 | K23: 1
C24: 2.5 | D24: Analise dos dados básicos do Empregador no Sistema de Folha de pagamento | E24: 42919 | F24: 43084 | G24: Equipe DP | I24: Concluído | J24: 42934 | K24: 1
C25: 2.6 | D25: Corrigir as informações do Empregador (se necessário) | E25: 42919 | F25: 43084 | G25: Equipe DP | I25: Concluído | J25: 42937 | K25: 1
C26: 2.7 | D26: Analisar se o Sistema de folha está adptado para atender as exigências do eSocial | E26: 42919 | F26: 43084 | G26: Equipe DP | I26: Concluído | J26: 42948 | K26: 1
C27: 2.8 | D27: Verificar todas as rubricas pagas em folha de pagamento nos ultimos 24 meses | E27: 42919 | F27: 43084 | G27: Equipe DP | I27: Concluído | J27: 42972 | K27: 1
C28: 2.9 | D28: Entender a necessidade de cada rubrica paga em folha de pagamento | E28: 42919 | F28: 43084 | G28: Equipe DP | I28: Concluído | J28: 42978 | K28: 1
C29: 2.10 | D29: Verificar as incidências dos Eventos e ajustar (se for necessário) | E29: 42919 | F29: 43084 | G29: Equipe DP | I29: Concluído | J29: 42993 | K29: 1
C30: 2.11 | D30: Verificar todos os cargos se estão com os CBO corretos | E30: 42919 | F30: 43084 | G30: Equipe DP | I30: Concluído | J30: 42990 | K30: 1
C31: 2.12 | D31: Ajustar os cargos que estão com o CBO não correspondente ao cargo | E31: 42919 | F31: 43084 | G31: Equipe DP | I31: Concluído | J31: 42993 | K31: 1
... C37: 2.18 | D37: Analisar as tabelas de horários (Registro de Ponto) | E37: 42919 | F37: 43084 | G37: Equipe DP | I37: Concluído | J37: 42993 | K37: 1
H38: Percentual de conclusão desta etapa: | K38: =AVERAGE(K20:K37) -> 1
A40: 3 | B40: Readequação dos Processos Internos | E40: Prazo da Atividade | G40: Responsável | I40: Acompanhamento
E41: Início | F41: Fim | G41: Contabilidade | H41: Cliente | I41: Status | J41: Data conclusão | K41: % Conclusão
C42: 3.1 | D42: Analisar as Admissões se atendem as exigências do eSocial | E42: 42919 | F42: 43084 | G42: Equipe DP | I42: Concluído | J42: 43007 | K42: 1
C43: 3.2 | D43: Analisar se todas as admissões possuem exame admissional com data correta | E43: 42919 | F43: 43084 | G43: Equipe DP | I43: Concluído | J43: 43007 | K43: 1
C44: 3.3 | D44: Analisar o cadastro de todas as admissões no sistema, se estão corretos e completos | E44: 42919 | F44: 43084 | G44: Equipe DP | I44: Concluído | J44: 43007 | K44: 1
C45: 3.4 | D45: Analisar os contratos de Estagiários, se atendem as exigências do eSocial | E45: 42919 | F45: 43084 | G45: Equipe DP | I45: Concluído | J45: 42998 | K45: 1
C46: 3.5 | D46: Analisar a cota dos Menores Aprendizes | E46: 42919 | F46: 43084 | G46: Equipe DP | I46: Concluído | J46: 43000 | K46: 1
C47: 3.6 | D47: Analisar a cota das Pessoas com Deficiência | E47: 42919 | F47: 43084 | G47: Equipe DP | I47: Concluído | J47: 43000 | K47: 1
C48: 3.7 | D48: Mapear possíveis erros nas rotinas internas e corrigí-los (Auditoria) | E48: 42919 | F48: 43084 | G48: Gestor DP | I48: Em andamento | K48: 0.82
C49: 3.8 | D49: Ajustar Declaração de Encargos para fins Salario Familia e Imposto de renda | E49: 42919 | F49: 43084 | G49: Equipe DP | I49: Concluído | J49: 42926 | K49: 1
C50: 3.9 | D50: Adequar o período de desligamentos por iniciativa da empresa ao eSocial | E50: 42919 | F50: 43084 | H50: RH - Cliente | I50: Concluído | J50: 43010 | K50: 1
C51: 3.10 | D51: Analisar se todas as demissões possuem exame demissional no prazo | E51: 42919 | F51: 43084 | G51: Equipe DP | I51: Concluído | J51: 43035 | K51: 1
C52: 3.11 | D52: Analisar nas Contratações dos Estrangeiros se estão com a documentação exigida conforme legislação vigênte (Lei n° 6.815/80 - Estatuto do Estrangeiro) | E52: 42919 | F52: 43084 | G52: Equipe DP | I52: Concluído | J52: 43039 | K52: 1
C53: 3.12 | D53: Ajustar o procedimento de concessão de férias (aviso com 30 dias antes do inicio) | E53: 42919 | F53: 43084 | H53: RH - Cliente | I53: Concluído | J53: 43038 | K53: 1
C54: 3.13 | D54: Revisar o procedimento de afastamentos (Atestados, auxilio doença, cat) | E54: 42919 | F54: 43084 | H54: RH - Cliente | I54: Concluído | J54: 43045 | K54: 1
C55: 3.14 | D55: Revisar o procedimento de contratação de autônomos | E55: 42919 | F55: 43084 | H55: RH - Cliente | I55: Concluído | J55: 43049 | K55: 1
H56: Percentual de conclusão desta etapa: | K56: =AVERAGE(K42:K55) -> 0.98714286
A58: 4 | B58: Análise da tabela S1000 - Informações do Empregador/Contribuinte | E58: Prazo da Atividade | G58: Responsável | I58: Acompanhamento
E59: Início | F59: Fim | G59: Contabilidade | H59: Cliente | I59: Status | J59: Data conclusão | K59: % Conclusão
C60: 4.1 | D60: Validar Evento de informações do empregador | E60: 42919 | F60: 43084 | G60: Equipe DP | I60: Concluído | J60: 43060 | K60: 1
C61: 4.2 | D61: Validar Informações de Identificação do Evento | E61: 42919 | F61: 43084 | G61: Equipe DP | I61: Concluído | J61: 43060 | K61: 1
C62: 4.3 | D62: Validar Informações de identificação do empregador | E62: 42919 | F62: 43084 | G62: Equipe DP | I62: Concluído | J62: 43060 | K62: 1
C63: 4.4 | D63: Validar Inclusão de novas informações | E63: 42919 | F63: 43084 | G63: Equipe DP | I63: Concluído | J63: 43060 | K63: 1
C64: 4.5 | D64: Validar Período de validade das informações incluídas | E64: 42919 | F64: 43084 | G64: Equipe DP | I64: Concluído | J64: 43060 | K64: 1
C65: 4.6 | D65: Validar Informações Complementares - Empresas Isentas - Dados da Isenção | E65: 42919 | F65: 43084 | G65: Equipe DP | I65: Concluído | J65: 43060 | K65: 1
C66: 4.7 | D66: Validar Informações de contato | E66: 42919 | F66: 43084 | G66: Equipe DP | I66: Concluído | J66: 43060 | K66: 1
C67: 4.8 | D67: Validar Informações relativas a Órgãos Públicos | E67: 42919 | F67: 43084 | G67: Equipe DP | I67: Concluído | J67: 43060 | K67: 1
C68: 4.9 | D68: Validar Informações relativas a Ente Federativo Responsável - EFR | E68: 42919 | F68: 43084 | G68: Equipe DP | I68: Concluído | J68: 43060 | K68: 1
C69: 4.10 | D69: Validar Informações relativas ao ente federativo estadual, distrital ou municipal | E69: 42919 | F69: 43084 | G69: Equipe DP | I69: Concluído | J69: 43060 | K69: 1
C70: 4.11 | D70: Validar Informações exclusivas de organismos internacionais e outras instituições extraterritoriais | E70: 42919 | F70: 43084 | G70: Equipe DP | I70: Concluído | J70: 43060 | K70: 1
C71: 4.12 | D71: Validar Informações do desenvolvedor do Software | E71: 42919 | F71: 43084 | G71: Equipe DP | I71: Concluído | J71: 43060 | K71: 1
... C77: 4.18 | D77: Validar Período de validade das informações excluídas | E77: 42919 | F77: 43084 | G77: Equipe DP | I77: Concluído | J77: 43060 | K77: 1
H78: Percentual de conclusão desta etapa: | K78: =AVERAGE(K60:K77) -> 1
A80: 5 | B80: Análise da tabela S1005 - Tabela de Estabelecimentos, Obras ou Unidades de Órgãos Públicos | E80: Prazo da Atividade | G80: Responsável | I80: Acompanhamento
E81: Início | F81: Fim | G81: Contabilidade | H81: Cliente | I81: Status | J81: Data conclusão | K81: % Conclusão
C82: 5.1 | D82: Validar Evento Tabela de Estabelecimentos, Obras ou Órgãos Públicos | E82: 42919 | F82: 43084 | G82: Equipe DP | I82: Concluído | J82: 43063 | K82: 1
C83: 5.2 | D83: Validar Informações de Identificação do Evento | E83: 42919 | F83: 43084 | G83: Equipe DP | I83: Concluído | J83: 43063 | K83: 1
C84: 5.3 | D84: Validar Informações de identificação do empregador | E84: 42919 | F84: 43084 | G84: Equipe DP | I84: Concluído | J84: 43063 | K84: 1
C85: 5.4 | D85: Validar Informações do Estabelecimento ou obra | E85: 42919 | F85: 43084 | G85: Equipe DP | I85: Concluído | J85: 43063 | K85: 1
C86: 5.5 | D86: Validar Inclusão de novas informações | E86: 42919 | F86: 43084 | G86: Equipe DP | I86: Concluído | J86: 43063 | K86: 1
C87: 5.6 | D87: Validar Identificação do estabelecimento, obra ou órgão público e validade das informações | E87: 42919 | F87: 43084 | G87: Equipe DP | I87: Concluído | J87: 43063 | K87: 1
C88: 5.7 | D88: Validar Detalhamento das informações do estabelecimento, obra ou órgão público | E88: 42919 | F88: 43084 | G88: Equipe DP | I88: Concluído | J88: 43063 | K88: 1
C89: 5.8 | D89: Validar Informações de Apuração da alíquota Gilrat do Estabelecimento | E89: 42919 | F89: 43084 | G89: Equipe DP | I89: Concluído | J89: 43063 | K89: 1
C90: 5.9 | D90: Validar Processo administrativo/judicial relativo à alíquota RAT | E90: 42919 | F90: 43084 | G90: Equipe DP | I90: Concluído | J90: 43063 | K90: 1
C91: 5.10 | D91: Validar Processo administrativo/judicial relativo ao FAP | E91: 42919 | F91: 43084 | G91: Equipe DP | I91: Concluído | J91: 43063 | K91: 1
C92: 5.11 | D92: Validar Informações relativas ao CAEPF | E92: 42919 | F92: 43084 | G92: Equipe DP | I92: Concluído | J92: 43063 | K92: 1
C93: 5.12 | D93: Validar Indicativo de substituição da contribuição Patronal - Obra de Construção Civil | E93: 42919 | F93: 43084 | G93: Equipe DP | I93: Concluído | J93: 43063 | K93: 1
... C101: 5.20 | D101: Validar Exclusão das informações | E101: 42919 | F101: 43084 | G101: Equipe DP | I101: Concluído | J101: 43063 | K101: 1
H102: Percentual de conclusão desta etapa: | K102: =AVERAGE(K82:K101) -> 1
A104: 6 | B104: Análise da tabela S1010 - Tabela de Rúbricas | E104: Prazo da Atividade | G104: Responsável | I104: Acompanhamento
E105: Início | F105: Fim | G105: Contabilidade | H105: Cliente | I105: Status | J105: Data conclusão | K105: % Conclusão
C106: 6.1 | D106: Validar Evento Tabela de Rubricas | E106: 42919 | F106: 43084 | G106: Equipe DP | I106: Concluído | J106: 43066 | K106: 1
C107: 6.2 | D107: Validar Informações de Identificação do Evento | E107: 42919 | F107: 43084 | G107: Equipe DP | I107: Concluído | J107: 43066 | K107: 1
C108: 6.3 | D108: Validar Informações de identificação do empregador | E108: 42919 | F108: 43084 | G108: Equipe DP | I108: Concluído | J108: 43066 | K108: 1
C109: 6.4 | D109: Fazer a Co-relação das rubricas do sistema x eSocial conforme (Tabela 03) do eSocial | E109: 42919 | F109: 43084 | G109: Equipe DP | I109: Concluído | J109: 43066 | K109: 1
C110: 6.5 | D110: Validar os campos "Repercute" das rubricas do Sistema (Não é mais necessário) | E110: 42919 | F110: 43084 | G110: Equipe DP | I110: Concluído | J110: 43066 | K110: 1
C111: 6.6 | D111: Validar Informações de identificação da rubrica e validade das informações | E111: 42919 | F111: 43084 | G111: Equipe DP | I111: Concluído | J111: 43066 | K111: 1
C112: 6.7 | D112: Validar Identificação de Processo - Incidência de Contrib. Previdenciária | E112: 42919 | F112: 43084 | G112: Equipe DP | I112: Concluído | J112: 43066 | K112: 1
C113: 6.8 | D113: Validar Identificação de Processo - Incidência de IRRF | E113: 42919 | F113: 43084 | G113: Equipe DP | I113: Concluído | J113: 43066 | K113: 1
C114: 6.9 | D114: Validar Identificação de Processo - Incidência de FGTS | E114: 42919 | F114: 43084 | G114: Equipe DP | I114: Concluído | J114: 43066 | K114: 1
C115: 6.10 | D115: Validar Identificação de Processo - Incidência de Contrib. Sindical | E115: 42919 | F115: 43084 | G115: Equipe DP | I115: Concluído | J115: 43066 | K115: 1
C116: 6.11 | D116: Validar Alteração das informações das rubricas (Auditoria) | E116: 42919 | F116: 43084 | G116: Equipe DP | I116: Concluído | J116: 43066 | K116: 1
C117: 6.12 | D117: Validar Novo período de validade das informações | E117: 42919 | F117: 43084 | G117: Equipe DP | I117: Concluído | J117: 43066 | K117: 1
... C119: 6.14 | D119: Validar Identificação da rubrica que será excluída | E119: 42919 | F119: 43084 | G119: Equipe DP | I119: Concluído | J119: 43066 | K119: 1
H120: Percentual de conclusão desta etapa: | K120: =AVERAGE(K106:K119) -> 1
A122: 7 | B122: Análise da tabela S1020 - Lotações Tributárias | E122: Prazo da Atividade | G122: Responsável | I122: Acompanhamento
E123: Início | F123: Fim | G123: Contabilidade | H123: Cliente | I123: Status | J123: Data conclusão | K123: % Conclusão
C124: 7.1 | D124: Validar Evento Tabela de Lotações | E124: 42919 | F124: 43084 | G124: Equipe DP | I124: Em andamento | K124: 0.6
...

Sheet Resumo e Grafico
A3: ETAPAS DE IMPLANTAÇÃO DO e_SOCIAL | C3: % CONCLUSÃO XYZ INDUST S/A
A4: 1 | B4: Consciêntização Diretoria/Colab./Terceiros | C4: 1
A5: 2 | B5: Palestras com o Cliente sobre o eSocial | C5: 1
A6: 3 | B6: ='Atividades detalhadas'!B3 -> Qualificação Cadastral | C6: ='Atividades detalhadas'!K16 -> 0.90909091
A7: 4 | B7: ='Atividades detalhadas'!B18 -> Saneamento da Base - Análise de Impacto (Robô) | C7: ='Atividades detalhadas'!K38 -> 1
A8: 5 | B8: ='Atividades detalhadas'!B40 -> Readequação dos Processos Internos | C8: ='Atividades detalhadas'!K56 -> 0.98714286
A9: 6 | B9: Análise das Tabelas e Eventos | C9: =AVERAGE(C12:C55) -> 0.48769481
A10: 7 | B10: Entrega Oficial do eSocial | C10: =AVERAGE(C4:C8,C12:C55) -> 0.53785317
A12: 4 | B12: ='Atividades detalhadas'!B58 -> Análise da tabela S1000 - Informações do Empregador/Contribuinte | C12: ='Atividades detalhadas'!K78 -> 1
A13: 5 | B13: ='Atividades detalhadas'!B80 -> Análise da tabela S1005 - Tabela de Estabelecimentos, Obras ou Unidades de Órgãos Públicos | C13: ='Atividades detalhadas'!K102 -> 1
A14: 6 | B14: ='Atividades detalhadas'!B104 -> Análise da tabela S1010 - Tabela de Rúbricas | C14: ='Atividades detalhadas'!K120 -> 1
A15: 7 | B15: ='Atividades detalhadas'!B122 -> Análise da tabela S1020 - Lotações Tributárias | C15: ='Atividades detalhadas'!K138 -> 0.57857143
A16: 8 | B16: ='Atividades detalhadas'!B140 -> Análise da tabela S1030 - Tabela de Cargos/Empregos Públicos | C16: ='Atividades detalhadas'!K152 -> 0.9
A17: 9 | B17: ='Atividades detalhadas'!B154 -> Análise da tabela S1035 - Tabela de Carreiras Públicas | C17: ='Atividades detalhadas'!K164 -> 1
A18: 10 | B18: ='Atividades detalhadas'!B166 -> Análise da tabela S1040 - Tabela de Funções/Cargos em Comissão | C18: ='Atividades detalhadas'!K178 -> 1
A19: 11 | B19: ='Atividades detalhadas'!B180 -> Análise da tabela S1050 - Tabela de Horários/Turnos de Trabalho | C19: ='Atividades detalhadas'!K191 -> 1
A20: 12 | B20: ='Atividades detalhadas'!B193 -> Análise da tabela S1060 - Tabela de Ambientes de Trabalho | C20: ='Atividades detalhadas'!K203 -> 1
A21: 13 | B21: ='Atividades detalhadas'!B205 -> Análise da tabela S1070 - Tabela de Processos Administrativos/Judiciais | C21: ='Atividades detalhadas'!K215 -> 0
A22: 14 | B22: ='Atividades detalhadas'!B217 -> Análise da tabela S1080 - Tabela de Operadores Portuários | C22: ='Atividades detalhadas'!K226 -> 1
A23: 15 | B23: ='Atividades detalhadas'!B228 -> Análise da tabela S1200 - Remuneração de trabalhador vinculado ao Regime Geral de Previd. Social | C23: ='Atividades detalhadas'!K251 -> 1
A24: 16 | B24: ='Atividades detalhadas'!B253 -> Análise da tabela S1202 - Remuneração de servidor vinculado a Regime Próprio de Previd. Social | C24: ='Atividades detalhadas'!K265 -> 1
A25: 17 | B25: ='Atividades detalhadas'!B267 -> Análise da tabela S1207 - Benefícios previdenciários - RPPS | C25: ='Atividades detalhadas'!K275 -> 1
A26: 18 | B26: ='Atividades detalhadas'!B277 -> Análise da tabela S1210 - Pagamentos de Rendimentos do Trabalho | C26: ='Atividades detalhadas'!K293 -> 1
A27: 19 | B27: ='Atividades detalhadas'!B295 -> Análise da tabela S1250 - Aquisição de Produção Rural | C27: ='Atividades detalhadas'!K306 -> 1
A28: 20 | B28: ='Atividades detalhadas'!B308 -> Análise da tabela S1260 - Comercialização da Produção Rural Pessoa Física | C28: ='Atividades detalhadas'!K319 -> 1
A29: 21 | B29: ='Atividades detalhadas'!B321 -> Análise da tabela S1270 - Contratação de Trabalhadores Avulsos Não Portuários | C29: ='Atividades detalhadas'!K326 -> 1
A30: 22 | B30: ='Atividades detalhadas'!B328 -> Análise da tabela S1280 - Informações Complementares aos Eventos Periódicos | C30: ='Atividades detalhadas'!K335 -> 1
A31: 23 | B31: ='Atividades detalhadas'!B337 -> Análise da tabela S1295 - Solicitação de Totalização para Pagamento em Contingência | C31: ='Atividades detalhadas'!K343 -> 0
A32: 24 | B32: ='Atividades detalhadas'!B345 -> Análise da tabela S1298 - Reabertura dos Eventos Periódicos | C32: ='Atividades detalhadas'!K350 -> 0
A33: 25 | B33: ='Atividades detalhadas'!B352 -> Análise da tabela S1299 - Fechamento dos Eventos Periódicos | C33: ='Atividades detalhadas'!K358 -> 0
A34: 26 | B34: ='Atividades detalhadas'!B360 -> Análise da tabela S1300 - Contribuição Sindical Patronal | C34: ='Atividades detalhadas'!K365 -> 0
A35: 27 | B35: ='Atividades detalhadas'!B367 -> Análise da tabela S2190 - Admissão de Trabalhador - Registro Preliminar | C35: ='Atividades detalhadas'!K373 -> 1
A36: 28 | B36: ='Atividades detalhadas'!B375 -> Análise da tabela S2200 - Cadastramento Inicial do Vínculo e Admissão/Ingresso de Trabalhador | C36: ='Atividades detalhadas'!K395 -> 0.8
A37: 29 | B37: ='Atividades detalhadas'!B397 -> Análise da tabela S2205 - Alteração de Dados Cadastrais do Trabalhador | C37: ='Atividades detalhadas'!K417 -> 0
A38: 30 | B38: ='Atividades detalhadas'!B419 -> Análise da tabela S2206 - Alteração de Contrato de Trabalho | C38: ='Atividades detalhadas'!K442 -> 0
A39: 31 | B39: ='Atividades detalhadas'!B444 -> Análise da tabela S2210 - Comunicação de Acidente de Trabalho | C39: ='Atividades detalhadas'!K458 -> 0
A40: 32 | B40: ='Atividades detalhadas'!B460 -> Análise da tabela S2220 - Monitoramento da Saúde do Trabalhador (A partir de Julho/2017) | C40: ='Atividades detalhadas'!K472 -> 0
A41: 33 | B41: ='Atividades detalhadas'!B474 -> Análise da tabela S2230 - Afastamento Temporário | C41: ='Atividades detalhadas'!K487 -> 0
A42: 34 | B42: ='Atividades detalhadas'!B489 -> Análise da tabela S2240 - Condições Ambientais do Trabalho - Fatores de Risco (A partir de Julho/2017) | C42: ='Atividades detalhadas'!K504 -> 0
A43: 35 | B43: ='Atividades detalhadas'!B506 -> Análise da tabela S2241 - Insalubridade, Periculosidade e Aposentadoria Especial | C43: ='Atividades detalhadas'!K523 -> 0
A44: 36 | B44: ='Atividades detalhadas'!B525 -> Análise da tabela S2250 - Aviso Prévio | C44: ='Atividades detalhadas'!K533 -> 0.35
A45: 37 | B45: ='Atividades detalhadas'!B535 -> Análise da tabela S2298 - Reintegração | C45: ='Atividades detalhadas'!K542 -> 0
A46: 38 | B46: ='Atividades detalhadas'!B544 -> Análise da tabela S2299 - Desligamento | C46: ='Atividades detalhadas'!K569 -> 0
A47: 39 | B47: ='Atividades detalhadas'!B571 -> Análise da tabela S2300 - Trabalhador Sem Vínculo de Emprego/Estatutário - Início | C47: ='Atividades detalhadas'!K600 -> 0.83
A48: 40 | B48: ='Atividades detalhadas'!B602 -> Análise da tabela S2306 - Trabalhador Sem Vínculo de Emprego/Estatutário - Alteração | C48: ='Atividades detalhadas'!K616 -> 0
A49: 41 | B49: ='Atividades detalhadas'!B618 -> Análise da tabela S2399 - Trabalhador Sem Vínculo de Emprego/Estatutário - Término | C49: ='Atividades detalhadas'!K637 -> 0
A50: 42 | B50: ='Atividades detalhadas'!B639 -> Análise da tabela S2400 - Cadastro de Benefícios Previdenciários - RPPS | C50: ='Atividades detalhadas'!K653 -> 0
A51: 43 | B51: ='Atividades detalhadas'!B655 -> Análise da tabela S3000 - Exclusão de eventos | C51: ='Atividades detalhadas'!K663 -> 1
A52: 44 | B52: ='Atividades detalhadas'!B665 -> Análise da tabela S5001 - Informações das contribuições sociais por trabalhador | C52: ='Atividades detalhadas'!K678 -> 0
A53: 45 | B53: ='Atividades detalhadas'!B680 -> Análise da tabela S5002 - Imposto de Renda Retido na Fonte | C53: ='Atividades detalhadas'!K692 -> 0
A54: 46 | B54: ='Atividades detalhadas'!B694 -> Análise da tabela S5011 - Informações das contribuições sociais consolidadas por contribuinte | C54: ='Atividades detalhadas'!K719 -> 0
A55: 47 | B55: ='Atividades detalhadas'!B721 -> Análise da tabela S5012 - Informações do IRRF consolidadas por contribuinte | C55: ='Atividades detalhadas'!K728 -> 0
