Workbook

Sheet Indicadores_Ano
B2: Painel de Indicadores / Ano
B3: Indicador | D3: Status | E3: 2023 | F3: 2024 | G3: 2025 | H3: 2026 | I3: Resultados / Recomendações / Pontos problemáticos
B4: Satisfação dos Clientes | D4: Plan | E4: 0.7 | F4: 0.75 | G4: 0.8 | H4: 0.82
D5: Real | E5: 0.8 | F5: 0.8 | G5: 0.82 | H5: ='Satisf. dos Clientes'!B16 -> 0.88636364
B6: Reclamações de Clientes | D6: Plan | E6: 0 | F6: 0 | G6: 0 | H6: 0
D7: Real | E7: 0.03 | F7: 0.03 | G7: 0.03 | H7: ='Reclamações de Clientes'!B16 -> 0
B8: Capacitações Ministradas para os Colaboradores | D8: Plan | E8: 10 | F8: 11 | G8: 11 | H8: 11
D9: Real | E9: 10 | F9: 12 | G9: 14 | H9: ='Capac. Ministradas p. Colabor.'!B16 -> 9.8181818
B10: Acidentes com Colaboradores | D10: Plan | E10: 0 | F10: 0 | G10: 0 | H10: 0
D11: Real | E11: 0 | F11: 0 | G11: 0 | H11: ='Acid. com Colaboradores'!B16 -> 0.18181818
B12: Produtividade no Trabalho | D12: Plan | E12: 100000 | F12: 120000 | G12: 130000 | H12: 140000
D13: Real | E13: 120000 | F13: 130000 | G13: 150000 | H13: ='Prod. no Trabalho'!B16 -> 21818.182
B14: Margem de Lucro | D14: Plan | E14: 0.05 | F14: 0.05 | G14: 0.07 | H14: 0.07
D15: Real | E15: 0.06 | F15: 0.065 | G15: 0.07 | H15: ='Margem de Lucro'!B16 -> 0.091666667

Sheet Indicadores_Mês
B2: Painel de Indicadores / Mês
B3: Indicador | D3: Status | E3: JAN | F3: FEV | G3: MAR | H3: ABR | I3: MAI | J3: JUN | K3: JUL | L3: AGO | M3: SET | N3: OUT | O3: NOV | P3: DEZ | Q3: Resultados / Recomendações / Pontos problemáticos
B4: Satisfação dos Clientes | D4: Plan. | E4: 0.82 | F4: 0.82 | G4: 0.82 | H4: 0.82 | I4: 0.82 | J4: 0.82 | K4: 0.82 | L4: 0.82 | M4: 0.82 | N4: 0.82 | O4: 0.82 | P4: 0.82
D5: Real. | E5: ='Satisf. dos Clientes'!C16 -> 0.9 | F5: ='Satisf. dos Clientes'!D16 -> 0.875 | G5: ='Satisf. dos Clientes'!E16 | H5: ='Satisf. dos Clientes'!F16 | I5: ='Satisf. dos Clientes'!G16 | J5: ='Satisf. dos Clientes'!H16 | K5: ='Satisf. dos Clientes'!I16 | L5: ='Satisf. dos Clientes'!J16 | ... P5: ='Satisf. dos Clientes'!N16
B6: Reclamações de Clientes | D6: Plan. | E6: 0 | F6: 0 | G6: 0 | H6: 0 | I6: 0 | J6: 0 | K6: 0 | L6: 0 | M6: 0 | N6: 0 | O6: 0 | P6: 0
D7: Real. | E7: ='Reclamações de Clientes'!C16 -> 0 | F7: ='Reclamações de Clientes'!D16 -> 0 | G7: ='Reclamações de Clientes'!E16 | H7: ='Reclamações de Clientes'!F16 | I7: ='Reclamações de Clientes'!G16 | J7: ='Reclamações de Clientes'!H16 | K7: ='Reclamações de Clientes'!I16 | L7: ='Reclamações de Clientes'!J16 | ... P7: ='Reclamações de Clientes'!N16
B8: Capacitações Ministradas para os Colaboradores | D8: Plan. | E8: 0 | F8: 0 | G8: 0 | H8: 0 | I8: 0 | J8: 0 | K8: 0 | L8: 0 | M8: 0 | N8: 0 | O8: 0 | P8: 0
D9: Real. | E9: ='Capac. Ministradas p. Colabor.'!C16 -> 4.8 | F9: ='Capac. Ministradas p. Colabor.'!D16 -> 5 | G9: ='Capac. Ministradas p. Colabor.'!E16 | H9: ='Capac. Ministradas p. Colabor.'!F16 | I9: ='Capac. Ministradas p. Colabor.'!G16 | J9: ='Capac. Ministradas p. Colabor.'!H16 | K9: ='Capac. Ministradas p. Colabor.'!I16 | L9: ='Capac. Ministradas p. Colabor.'!J16 | ... P9: ='Capac. Ministradas p. Colabor.'!N16
B10: Acidentes com Colaboradores | D10: Plan. | E10: 0 | F10: 0 | G10: 0 | H10: 0 | I10: 0 | J10: 0 | K10: 0 | L10: 0 | M10: 0 | N10: 0 | O10: 0 | P10: 0
D11: Real. | E11: ='Acid. com Colaboradores'!C16 -> 0.2 | F11: ='Acid. com Colaboradores'!D16 -> 0 | G11: ='Acid. com Colaboradores'!E16 | H11: ='Acid. com Colaboradores'!F16 | I11: ='Acid. com Colaboradores'!G16 | J11: ='Acid. com Colaboradores'!H16 | K11: ='Acid. com Colaboradores'!I16 | L11: ='Acid. com Colaboradores'!J16 | ... P11: ='Acid. com Colaboradores'!N16
B12: Produtividade no Trabalho | D12: Plan. | E12: 10000 | F12: 10000 | G12: 10000 | H12: 10000 | I12: 10000 | J12: 10000 | K12: 10000 | L12: 10000 | M12: 10000 | N12: 10000 | O12: 10000 | P12: 10000
D13: Real. | E13: ='Prod. no Trabalho'!C16 -> 12000 | F13: ='Prod. no Trabalho'!D16 -> 10000 | G13: ='Prod. no Trabalho'!E16 | H13: ='Prod. no Trabalho'!F16 | I13: ='Prod. no Trabalho'!G16 | J13: ='Prod. no Trabalho'!H16 | K13: ='Prod. no Trabalho'!I16 | L13: ='Prod. no Trabalho'!J16 | ... P13: ='Prod. no Trabalho'!N16
B14: Margem de Lucro | D14: Plan. | E14: 0.07 | F14: 0.07 | G14: 0.07 | H14: 0.07 | I14: 0.07 | J14: 0.07 | K14: 0.07 | L14: 0.07 | M14: 0.07 | N14: 0.07 | O14: 0.07 | P14: 0.07
D15: Real. | E15: ='Margem de Lucro'!C16 -> 0.083333333 | F15: ='Margem de Lucro'!D16 -> 0.1 | G15: ='Margem de Lucro'!E16 | H15: ='Margem de Lucro'!F16 | I15: ='Margem de Lucro'!G16 | J15: ='Margem de Lucro'!H16 | K15: ='Margem de Lucro'!I16 | L15: ='Margem de Lucro'!J16 | ... P15: ='Margem de Lucro'!N16

Sheet Satisf. dos Clientes
A1: Sistemas de Indicadores de Desempenho
A2: Nome do Indicador: | B2: Satisfação de clientes
A3: Definição: | B3: Mede a satisfação dos clientes a partir dos resultados de pesquisas de satisfação
A4: Fórmula: | B4: ((somatório dos questionários respondidos como "Bom" e "Excelente") / (número total de questionários aplicados)) x 100
A5: Unidade: | B5: %
A6: Fonte de Dados: | B6: PREENCHER
A7: Frequência de Medição: | B7: PREENCHER
A8: Meta: | B8: PREENCHER
A9: Responsável: | B9: PREENCHER
A11: Apuração
A12: Empresa: | B12: Nome da empresa | L12: Ano: | M12: 2016
A13: Meses | B13: Acum. | C13: Jan | D13: Fev | E13: Mar | F13: Abr | G13: Mai | H13: Jun | I13: Jul | J13: Ago | K13: Set | L13: Out | M13: Nov | N13: Dez
A14: (somatório dos questionários respondidos como "Bom" e "Excelente") | B14: =SUM(C14:N14) -> 39 | C14: 18 | D14: 21
A15: (número total de questionários aplicados) | B15: =SUM(C15:N15) -> 44 | C15: 20 | D15: 24
A16: ((somatório dos questionários respondidos como "Bom" e "Excelente") / (número total de questionários aplicados)) x 100 | B16: =B14/B15 -> 0.88636364 | C16: =IF(C15="","",(C14/C15)) -> 0.9 | D16: =IF(D15="","",(D14/D15)) -> 0.875 | E16: =IF(E15="","",(E14/E15)) | F16: =IF(F15="","",(F14/F15)) | G16: =IF(G15="","",(G14/G15)) | H16: =IF(H15="","",(H14/H15)) | I16: =IF(I15="","",(I14/I15)) | J16: =IF(J15="","",(J14/J15)) | ... N16: =IF(N15="","",(N14/N15))

Sheet Reclamações de Clientes
A1: Sistemas de Indicadores de Desempenho
A2: Nome do Indicador: | B2: Reclamações de Clientes
A3: Definição: | B3: Mede a satisfação dos clientes a partir dos resultados de pesquisas de satisfação
A4: Fórmula: | B4: ((nº total de reclamações) / (total de entregas)) x 100
A5: Unidade: | B5: %
A6: Fonte de Dados: | B6: PREENCHER
A7: Frequência de Medição: | B7: PREENCHER
A8: Meta: | B8: PREENCHER
A9: Responsável: | B9: PREENCHER
A11: Apuração
A12: Empresa: | B12: Nome da empresa | L12: Ano: | M12: 2016
A13: Meses | B13: Acum. | C13: Jan | D13: Fev | E13: Mar | F13: Abr | G13: Mai | H13: Jun | I13: Jul | J13: Ago | K13: Set | L13: Out | M13: Nov | N13: Dez
A14: (nº total de reclamações) | B14: =SUM(C14:N14) -> 0 | C14: 0 | D14: 0
A15: (total de entregas) | B15: =SUM(C15:N15) -> 8 | C15: 6 | D15: 2
A16: ((nº total de reclamações) / (total de entregas)) x 100 | B16: =B14/B15 -> 0 | C16: =IF(C15="","",(C14/C15)) -> 0 | D16: =IF(D15="","",(D14/D15)) -> 0 | E16: =IF(E15="","",(E14/E15)) | F16: =IF(F15="","",(F14/F15)) | G16: =IF(G15="","",(G14/G15)) | H16: =IF(H15="","",(H14/H15)) | I16: =IF(I15="","",(I14/I15)) | J16: =IF(J15="","",(J14/J15)) | ... N16: =IF(N15="","",(N14/N15))

Sheet Capac. Ministradas p. Colabor.
A1: Sistemas de Indicadores de Desempenho
A2: Nome do Indicador: | B2: Capacitações ministradas para os colaboradores
A3: Definição: | B3: Mede a quantidade média de horas de capacitação aplicada por colaborador
A4: Fórmula: | B4: (somatório homens-hora de treinamentos realizados) / (nº de colaboradores ativos)
A5: Unidade: | B5: Horas
A6: Fonte de Dados: | B6: PREENCHER
A7: Frequência de Medição: | B7: PREENCHER
A8: Meta: | B8: PREENCHER
A9: Responsável: | B9: PREENCHER
A11: Apuração
A12: Empresa: | B12: Nome da empresa | L12: Ano: | M12: 2016
A13: Meses | B13: Acum. | C13: Jan | D13: Fev | E13: Mar | F13: Abr | G13: Mai | H13: Jun | I13: Jul | J13: Ago | K13: Set | L13: Out | M13: Nov | N13: Dez
A14: (somatório homens-hora de treinamentos realizados) | B14: =SUM(C14:N14) -> 54 | C14: 24 | D14: 30
A15: (nº de colaboradores ativos) | B15: =AVERAGE(C15:N15) -> 5.5 | C15: 5 | D15: 6
A16: (somatório homens-hora de treinamentos realizados) / (nº de colaboradores ativos) | B16: =B14/B15 -> 9.8181818 | C16: =IF(C15="","",(C14/C15)) -> 4.8 | D16: =IF(D15="","",(D14/D15)) -> 5 | E16: =IF(E15="","",(E14/E15)) | F16: =IF(F15="","",(F14/F15)) | G16: =IF(G15="","",(G14/G15)) | H16: =IF(H15="","",(H14/H15)) | I16: =IF(I15="","",(I14/I15)) | J16: =IF(J15="","",(J14/J15)) | ... N16: =IF(N15="","",(N14/N15))

Sheet Acid. com Colaboradores
A1: Sistemas de Indicadores de Desempenho
A2: Nome do Indicador: | B2: Acidentes com Colaboradores
A3: Definição: | B3: Corresponde à quantidade média de acidentes (com afastamento) por colaborador
A4: Fórmula: | B4: (nº total de acidentes (com afastamento)) / (nº de colaboradores ativos)
A5: Unidade: | B5: Acidentes
A6: Fonte de Dados: | B6: PREENCHER
A7: Frequência de Medição: | B7: PREENCHER
A8: Meta: | B8: PREENCHER
A9: Responsável: | B9: PREENCHER
A11: Apuração
A12: Empresa: | B12: Nome da empresa | L12: Ano: | M12: 2016
A13: Meses | B13: Acum. | C13: Jan | D13: Fev | E13: Mar | F13: Abr | G13: Mai | H13: Jun | I13: Jul | J13: Ago | K13: Set | L13: Out | M13: Nov | N13: Dez
A14: (nº total de acidentes (com afastamento)) | B14: =SUM(C14:N14) -> 1 | C14: 1 | D14: 0
A15: (nº de colaboradores ativos) | B15: =AVERAGE(C15:N15) -> 5.5 | C15: 5 | D15: 6
A16: (nº total de acidentes (com afastamento)) / (nº de colaboradores ativos) | B16: =B14/B15 -> 0.18181818 | C16: =IF(C15="","",(C14/C15)) -> 0.2 | D16: =IF(D15="","",(D14/D15)) -> 0 | E16: =IF(E15="","",(E14/E15)) | F16: =IF(F15="","",(F14/F15)) | G16: =IF(G15="","",(G14/G15)) | H16: =IF(H15="","",(H14/H15)) | I16: =IF(I15="","",(I14/I15)) | J16: =IF(J15="","",(J14/J15)) | ... N16: =IF(N15="","",(N14/N15))

Sheet Prod. no Trabalho
A1: Sistemas de Indicadores de Desempenho
A2: Nome do Indicador: | B2: Produtividade no Trabalho
A3: Definição: | B3: Corresponde à receita média gerada por colaborador da empresa
A4: Fórmula: | B4: (Receita) / (nº de colaboradores ativos)
A5: Unidade: | B5: R$
A6: Fonte de Dados: | B6: PREENCHER
A7: Frequência de Medição: | B7: PREENCHER
A8: Meta: | B8: PREENCHER
A9: Responsável: | B9: PREENCHER
A11: Apuração
A12: Empresa: | B12: Nome da empresa | L12: Ano: | M12: 2016
A13: Meses | B13: Acum. | C13: Jan | D13: Fev | E13: Mar | F13: Abr | G13: Mai | H13: Jun | I13: Jul | J13: Ago | K13: Set | L13: Out | M13: Nov | N13: Dez
A14: (Receita) | B14: =SUM(C14:N14) -> 120000 | C14: 60000 | D14: 60000
A15: (nº de colaboradores ativos) | B15: =AVERAGE(C15:N15) -> 5.5 | C15: 5 | D15: 6
A16: (Receita) / (nº de colaboradores ativos) | B16: =B14/B15 -> 21818.182 | C16: =IF(C15="","",(C14/C15)) -> 12000 | D16: =IF(D15="","",(D14/D15)) -> 10000 | E16: =IF(E15="","",(E14/E15)) | F16: =IF(F15="","",(F14/F15)) | G16: =IF(G15="","",(G14/G15)) | H16: =IF(H15="","",(H14/H15)) | I16: =IF(I15="","",(I14/I15)) | J16: =IF(J15="","",(J14/J15)) | ... N16: =IF(N15="","",(N14/N15))

Sheet Margem de Lucro
A1: Sistemas de Indicadores de Desempenho
A2: Nome do Indicador: | B2: Margem de Lucro
A3: Definição: | B3: Corresponde ao lucro aferido na operação após descontar os Custos e Despesas do negócio, da Receita Bruta apurada
A4: Fórmula: | B4: ((Receita) - (Custos + Despesas) / (Receita)) x 100
A5: Unidade: | B5: %
A6: Fonte de Dados: | B6: PREENCHER
A7: Frequência de Medição: | B7: PREENCHER
A8: Meta: | B8: PREENCHER
A9: Responsável: | B9: PREENCHER
A11: Apuração
A12: Empresa: | B12: Nome da empresa | L12: Ano: | M12: 2016
A13: Meses | B13: Acum. | C13: Jan | D13: Fev | E13: Mar | F13: Abr | G13: Mai | H13: Jun | I13: Jul | J13: Ago | K13: Set | L13: Out | M13: Nov | N13: Dez
A14: (Receita) - (Custos + Despesas) | B14: =SUM(C14:N14) -> 11000 | C14: 5000 | D14: 6000
A15: (Receita) | B15: =SUM(C15:N15) -> 120000 | C15: 60000 | D15: 60000
A16: ((Receita) - (Custos + Despesas) / (Receita)) x 100 | B16: =B14/B15 -> 0.091666667 | C16: =IF(C15="","",(C14/C15)) -> 0.083333333 | D16: =IF(D15="","",(D14/D15)) -> 0.1 | E16: =IF(E15="","",(E14/E15)) | F16: =IF(F15="","",(F14/F15)) | G16: =IF(G15="","",(G14/G15)) | H16: =IF(H15="","",(H14/H15)) | I16: =IF(I15="","",(I14/I15)) | J16: =IF(J15="","",(J14/J15)) | ... N16: =IF(N15="","",(N14/N15))
